{
  "type": "Feature",
  "properties": {
    "iso:country":"US",
    "sg:address":"600 Whitney Ranch Dr Ste D22",
    "sg:city":"Henderson",
    "sg:classifiers":[
        {
            "category":"Health Services",
            "subcategory":"Doctor",
            "type":"Services"
        }
    ],
    "sg:phone":"+1 702 456 2400",
    "sg:postcode":"89014",
    "sg:province":"NV",
    "sg:tags":[
        "medicine",
        "sport",
        "orthopedist"
    ],
    "wof:name":"Redfern Fred C MD",
    "wof:placetype":"venue"
},
  "geometry": {"coordinates":[-115.053001,36.064301],"type":"Point"}
}