{
  "type": "Feature",
  "properties": {
    "iso:country":"US",
    "sg:address":"2430 E Harmon Avenue",
    "sg:city":"Las Vegas",
    "sg:classifiers":[
        {
            "category":"Health Services",
            "subcategory":"Dentist",
            "type":"Services"
        }
    ],
    "sg:phone":"+1 702 733 0558",
    "sg:postcode":"89121",
    "sg:province":"NV",
    "wof:name":"Allen W Huang DMD Ms",
    "wof:placetype":"venue"
},
  "geometry": {"coordinates":[-115.11814200000001,36.107313],"type":"Point"}
}