{
  "type": "Feature",
  "properties": {
    "iso:country":"US",
    "sg:address":"3117 N Rainbow Boulevard",
    "sg:city":"Las Vegas",
    "sg:classifiers":[
        {
            "category":"Restaurant",
            "type":"Food & Drink"
        }
    ],
    "sg:phone":"+1 702 656 2919",
    "sg:postcode":"89108",
    "sg:province":"NV",
    "wof:name":"Port of Subs",
    "wof:placetype":"venue"
},
  "geometry": {"coordinates":[-115.242492,36.217019],"type":"Point"}
}