{
  "type": "Feature",
  "properties": {
    "iso:country":"US",
    "sg:address":"560 Idaho St",
    "sg:city":"Elko",
    "sg:classifiers":[
        {
            "category":"Food & Beverages",
            "subcategory":"Groceries & Convenience Stores",
            "type":"Retail Goods"
        }
    ],
    "sg:phone":"+1 775 738 3173",
    "sg:postcode":"89801",
    "sg:province":"NV",
    "sg:tags":[
        "grocer"
    ],
    "wof:name":"Roy's Inc",
    "wof:placetype":"venue"
},
  "geometry": {"coordinates":[-115.762604,40.832888],"type":"Point"}
}