{
  "type": "Feature",
  "properties": {
    "iso:country":"US",
    "sg:address":"5221 Meadow Rock Ave",
    "sg:city":"Las Vegas",
    "sg:classifiers":[
        {
            "category":"Home & Garden",
            "subcategory":"Carpets & Floor Coverings",
            "type":"Retail Goods"
        }
    ],
    "sg:phone":"+1 702 396 0566",
    "sg:postcode":"89130",
    "sg:province":"NV",
    "sg:tags":[
        "dealer",
        "rug"
    ],
    "wof:name":"Expert Flooring Solutions",
    "wof:placetype":"venue"
},
  "geometry": {"coordinates":[-115.213625,36.272893],"type":"Point"}
}