{
  "type": "Feature",
  "properties": {
    "iso:country":"US",
    "sg:address":"3416 Goni Rd",
    "sg:city":"Carson City",
    "sg:classifiers":[
        {
            "category":"Government",
            "subcategory":"Office",
            "type":"Public Place"
        }
    ],
    "sg:phone":"+1 775 687 4210",
    "sg:postcode":"89706",
    "sg:province":"NV",
    "sg:tags":[
        "state",
        "resource"
    ],
    "wof:name":"Aging Svc Div",
    "wof:placetype":"venue"
},
  "geometry": {"coordinates":[-119.747342,39.18965],"type":"Point"}
}