{
  "type": "Feature",
  "properties": {
    "iso:country":"US",
    "sg:address":"1882 Fairfield Ter",
    "sg:city":"Henderson",
    "sg:classifiers":[
        {
            "category":"Utilities",
            "subcategory":"Telephone",
            "type":"Services"
        }
    ],
    "sg:phone":"+1 702 436 5950",
    "sg:postcode":"89074",
    "sg:province":"NV",
    "sg:tags":[
        "communication",
        "computer"
    ],
    "wof:name":"Trimillenium Systems",
    "wof:placetype":"venue"
},
  "geometry": {"coordinates":[-115.06623500000001,36.041074],"type":"Point"}
}