{
  "type": "Feature",
  "properties": {
    "iso:country":"US",
    "sg:address":"1441 N Nellis Blvd",
    "sg:city":"Las Vegas",
    "sg:classifiers":[
        {
            "category":"Retail",
            "subcategory":"Storage",
            "type":"Services"
        }
    ],
    "sg:phone":"+1 702 438 4938",
    "sg:postcode":"89110",
    "sg:province":"NV",
    "sg:tags":[
        "self"
    ],
    "wof:name":"Nellis Mini Storage",
    "wof:placetype":"venue"
},
  "geometry": {"coordinates":[-115.06199599999999,36.185101],"type":"Point"}
}