{
  "type": "Feature",
  "properties": {
    "iso:country":"US",
    "sg:address":"6950 Via Olivero Avenue",
    "sg:city":"Las Vegas",
    "sg:classifiers":[
        {
            "category":"Real Estate",
            "subcategory":"Real Estate Services",
            "type":"Services"
        }
    ],
    "sg:phone":"+1 702 227 4777",
    "sg:postcode":"89117",
    "sg:province":"NV",
    "sg:tags":[
        "management",
        "property"
    ],
    "wof:name":"Continental Realty & Property Management",
    "wof:placetype":"venue"
},
  "geometry": {"coordinates":[-115.244176,36.146003],"type":"Point"}
}