{
  "type": "Feature",
  "properties": {
    "iso:country":"US",
    "sg:address":"2520 S Eastern Avenue",
    "sg:city":"Las Vegas",
    "sg:classifiers":[
        {
            "category":"Personal",
            "subcategory":"Beauty Salon",
            "type":"Services"
        }
    ],
    "sg:phone":"+1 702 457 4669",
    "sg:postcode":"89169",
    "sg:province":"NV",
    "sg:tags":[
        "hair"
    ],
    "wof:name":"Sinaloa Beauty Salon",
    "wof:placetype":"venue"
},
  "geometry": {"coordinates":[-115.123941,36.138491],"type":"Point"}
}