{
  "type": "Feature",
  "properties": {
    "iso:country":"US",
    "sg:address":"6587 S Las Vegas Blvd Ste 172",
    "sg:city":"Las Vegas",
    "sg:classifiers":[
        {
            "category":"Education",
            "subcategory":"Music School",
            "type":"Public Place"
        }
    ],
    "sg:phone":"+1 702 450 2260",
    "sg:postcode":"89119",
    "sg:province":"NV",
    "sg:tags":[
        "instrument",
        "teacher",
        "musical"
    ],
    "sg:website":"gc.guitarcenter.com/locations/st...",
    "wof:name":"Guitar Center",
    "wof:placetype":"venue"
},
  "geometry": {"coordinates":[-115.172237,36.068629],"type":"Point"}
}