{
  "type": "Feature",
  "properties": {
    "iso:country":"US",
    "sg:address":"3309 W Charleston Blvd",
    "sg:city":"Las Vegas",
    "sg:classifiers":[
        {
            "category":"Health Services",
            "subcategory":"Doctor",
            "type":"Services"
        }
    ],
    "sg:phone":"+1 702 838 0444",
    "sg:postcode":"89102",
    "sg:province":"NV",
    "sg:tags":[
        "physician",
        "surgeon",
        "cosmetic"
    ],
    "wof:name":"Vein Clinic of Las Vegas",
    "wof:placetype":"venue"
},
  "geometry": {"coordinates":[-115.18699599999999,36.158798],"type":"Point"}
}