{
  "type": "Feature",
  "properties": {
    "iso:country":"US",
    "sg:address":"3939 E Lake Mead Blvd",
    "sg:city":"Las Vegas",
    "sg:classifiers":[
        {
            "category":"Food & Beverages",
            "subcategory":"Bakery",
            "type":"Retail Goods"
        }
    ],
    "sg:phone":"+1 702 319 6688",
    "sg:postcode":"89115",
    "sg:province":"NV",
    "sg:tags":[
        "sandwich"
    ],
    "sg:website":"www.subway.com",
    "wof:name":"Subway",
    "wof:placetype":"venue"
},
  "geometry": {"coordinates":[-115.08899700000001,36.195801],"type":"Point"}
}