{
  "type": "Feature",
  "properties": {
    "iso:country":"US",
    "sg:address":"4921 W Sahara Ave",
    "sg:city":"Las Vegas",
    "sg:classifiers":[
        {
            "category":"Banks & Credit Unions",
            "subcategory":"Bank",
            "type":"Services"
        }
    ],
    "sg:phone":"+1 702 222 2274",
    "sg:postcode":"89146",
    "sg:province":"NV",
    "sg:tags":[
        "cashing",
        "check"
    ],
    "wof:name":"Rapid Cash",
    "wof:placetype":"venue"
},
  "geometry": {"coordinates":[-115.204507,36.144503],"type":"Point"}
}