{
  "type": "Feature",
  "properties": {
    "iso:country":"US",
    "sg:address":"734 E Sahara Ave",
    "sg:city":"Las Vegas",
    "sg:classifiers":[
        {
            "category":"Health Services",
            "subcategory":"Doctor",
            "type":"Services"
        }
    ],
    "sg:phone":"+1 702 650 3333",
    "sg:postcode":"89104",
    "sg:province":"NV",
    "sg:tags":[
        "dentist"
    ],
    "wof:name":"Community Family Dental",
    "wof:placetype":"venue"
},
  "geometry": {"coordinates":[-115.145371,36.144016],"type":"Point"}
}