{
  "type": "Feature",
  "properties": {
    "iso:country":"US",
    "sg:address":"407 N Curry St",
    "sg:city":"Carson City",
    "sg:classifiers":[
        {
            "category":"Bars & Pubs",
            "type":"Food & Drink"
        }
    ],
    "sg:phone":"+1 775 882 1816",
    "sg:postcode":"89703",
    "sg:province":"NV",
    "sg:tags":[
        "drinking",
        "nightlife"
    ],
    "wof:name":"Old Globe Saloon",
    "wof:placetype":"venue"
},
  "geometry": {"coordinates":[-119.76799800000001,39.1661],"type":"Point"}
}