{
  "type": "Feature",
  "properties": {
    "iso:country":"US",
    "sg:address":"4933 W Craig Rd",
    "sg:city":"Las Vegas",
    "sg:classifiers":[
        {
            "category":"Professional",
            "subcategory":"Advertising",
            "type":"Services"
        }
    ],
    "sg:phone":"+1 702 221 9060",
    "sg:postcode":"89130",
    "sg:province":"NV",
    "sg:tags":[
        "mailing",
        "list",
        "direct",
        "mail"
    ],
    "wof:name":"Prime Prospects Inc",
    "wof:placetype":"venue"
},
  "geometry": {"coordinates":[-115.209448,36.238702],"type":"Point"}
}