{
  "type": "Feature",
  "properties": {
    "iso:country":"US",
    "sg:address":"1500 Sheckler Cutoff",
    "sg:city":"Fallon",
    "sg:classifiers":[
        {
            "category":"Building & Trades",
            "subcategory":"Landscaping Services",
            "type":"Services"
        }
    ],
    "sg:phone":"+1 775 867 5538",
    "sg:postcode":"89406",
    "sg:province":"NV",
    "sg:tags":[
        "landscape",
        "contractor"
    ],
    "wof:name":"Kellie Dossey's Landscpg & Yd",
    "wof:placetype":"venue"
},
  "geometry": {"coordinates":[-118.875922,39.46478],"type":"Point"}
}