{
  "type": "Feature",
  "properties": {
    "iso:country":"US",
    "sg:address":"2774 San Lago Ct",
    "sg:city":"Las Vegas",
    "sg:classifiers":[
        {
            "category":"Wholesale",
            "subcategory":"Scrap",
            "type":"Manufacturing & Wholesale Goods"
        }
    ],
    "sg:phone":"+1 702 734 8883",
    "sg:postcode":"89121",
    "sg:province":"NV",
    "sg:tags":[
        "metal",
        "iron"
    ],
    "wof:name":"Sierra International Machinery",
    "wof:placetype":"venue"
},
  "geometry": {"coordinates":[-115.113923,36.126642],"type":"Point"}
}