{
  "type": "Feature",
  "properties": {
    "iso:country":"US",
    "sg:address":"290 S Maine St",
    "sg:city":"Fallon",
    "sg:classifiers":[
        {
            "category":"Shopping",
            "subcategory":"Department Store",
            "type":"Retail Goods"
        }
    ],
    "sg:phone":"+1 775 423 7132",
    "sg:postcode":"89406",
    "sg:province":"NV",
    "sg:tags":[
        "house",
        "mail"
    ],
    "wof:name":"JC Penney",
    "wof:placetype":"venue"
},
  "geometry": {"coordinates":[-118.77714,39.472146],"type":"Point"}
}