{
  "type": "Feature",
  "properties": {
    "iso:country":"US",
    "sg:address":"5301 Ocala Ln",
    "sg:city":"Las Vegas",
    "sg:classifiers":[
        {
            "category":"Retail",
            "subcategory":"Repair Shop",
            "type":"Services"
        }
    ],
    "sg:phone":"+1 702 458 2944",
    "sg:postcode":"89122",
    "sg:province":"NV",
    "sg:tags":[
        "equipment"
    ],
    "wof:name":"Desert Restaurant Equipment",
    "wof:placetype":"venue"
},
  "geometry": {"coordinates":[-115.058698,36.122694],"type":"Point"}
}