{
  "type": "Feature",
  "properties": {
    "iso:country":"US",
    "sg:address":"5205 Mill St",
    "sg:city":"Reno",
    "sg:classifiers":[
        {
            "category":"Utilities",
            "subcategory":"Telephone",
            "type":"Services"
        }
    ],
    "sg:phone":"+1 775 823 7500",
    "sg:postcode":"89502",
    "sg:province":"NV",
    "sg:tags":[
        "communications"
    ],
    "wof:name":"Excelcom Inc",
    "wof:placetype":"venue"
},
  "geometry": {"coordinates":[-119.751177,39.513956],"type":"Point"}
}