{
  "type": "Feature",
  "properties": {
    "iso:country":"US",
    "sg:address":"1215 Chapman Dr",
    "sg:city":"Las Vegas",
    "sg:classifiers":[
        {
            "category":"Arts & Performance",
            "subcategory":"Theater",
            "type":"Entertainment"
        }
    ],
    "sg:phone":"+1 702 385 1232",
    "sg:postcode":"89104",
    "sg:province":"NV",
    "sg:tags":[
        "group"
    ],
    "wof:name":"Cagey Concepts",
    "wof:placetype":"venue"
},
  "geometry": {"coordinates":[-115.131743,36.155862],"type":"Point"}
}