{
  "type": "Feature",
  "properties": {
    "iso:country":"US",
    "sg:address":"1800 Monterey Cypress Street",
    "sg:city":"Las Vegas",
    "sg:classifiers":[
        {
            "category":"Landmark",
            "subcategory":"Tourist Information",
            "type":"Public Place"
        }
    ],
    "sg:phone":"+1 702 360 7978",
    "sg:postcode":"89144",
    "sg:province":"NV",
    "sg:tags":[
        "tour"
    ],
    "wof:name":"Treasure Tours of Nevada",
    "wof:placetype":"venue"
},
  "geometry": {"coordinates":[-115.330754,36.191585],"type":"Point"}
}