{
  "type": "Feature",
  "properties": {
    "iso:country":"US",
    "sg:address":"503 Main St",
    "sg:city":"Gabbs",
    "sg:classifiers":[
        {
            "category":"Government",
            "subcategory":"Post Office",
            "type":"Public Place"
        }
    ],
    "sg:phone":"+1 775 000 1111",
    "sg:postcode":"89409",
    "sg:province":"NV",
    "wof:name":"US Post Office",
    "wof:placetype":"venue"
},
  "geometry": {"coordinates":[-117.92275100000001,38.870202],"type":"Point"}
}