{
  "type": "Feature",
  "properties": {
    "iso:country":"US",
    "sg:address":"5513 Escallonia St",
    "sg:city":"Las Vegas",
    "sg:classifiers":[
        {
            "category":"Professional",
            "subcategory":"Accounting & Tax Preparation",
            "type":"Services"
        }
    ],
    "sg:phone":"+1 702 658 1468",
    "sg:postcode":"89149",
    "sg:province":"NV",
    "sg:tags":[
        "bookkeeping",
        "general"
    ],
    "wof:name":"Reiff & Motto",
    "wof:placetype":"venue"
},
  "geometry": {"coordinates":[-115.27386300000001,36.261149],"type":"Point"}
}