{
  "type": "Feature",
  "properties": {
    "iso:country":"US",
    "sg:address":"304 Boulder Dr",
    "sg:city":"Carson City",
    "sg:classifiers":[
        {
            "category":"Shopping",
            "subcategory":"Gifts & Souvenirs",
            "type":"Retail Goods"
        }
    ],
    "sg:phone":"+1 775 883 6045",
    "sg:postcode":"89706",
    "sg:province":"NV",
    "sg:tags":[
        "direct",
        "merchandise"
    ],
    "wof:name":"C Joseph Gordon International",
    "wof:placetype":"venue"
},
  "geometry": {"coordinates":[-119.762445,39.192612],"type":"Point"}
}