{
  "type": "Feature",
  "properties": {
    "iso:country":"US",
    "sg:address":"6524 Hillside Brook Ave",
    "sg:city":"Las Vegas",
    "sg:classifiers":[
        {
            "category":"Professional",
            "subcategory":"Business Services",
            "type":"Services"
        }
    ],
    "sg:phone":"+1 702 644 4403",
    "sg:postcode":"89130",
    "sg:province":"NV",
    "wof:name":"Scott C Reversa",
    "wof:placetype":"venue"
},
  "geometry": {"coordinates":[-115.235869,36.248189],"type":"Point"}
}