{
  "type": "Feature",
  "properties": {
    "iso:country":"US",
    "sg:address":"9240 S Eastern Ave",
    "sg:city":"Las Vegas",
    "sg:classifiers":[
        {
            "category":"Restaurant",
            "type":"Food & Drink"
        }
    ],
    "sg:menulink":"http://www.allmenus.com/nv/las-vegas/224447-in--out-burger/menu/",
    "sg:postcode":"89123",
    "sg:province":"NV",
    "sg:tags":[
        "burger",
        "american"
    ],
    "wof:name":"In & Out Burger",
    "wof:placetype":"venue"
},
  "geometry": {"coordinates":[-115.117941,36.021453],"type":"Point"}
}