{
  "type": "Feature",
  "properties": {
    "iso:country":"US",
    "sg:address":"64 N Pearl St",
    "sg:city":"Las Vegas",
    "sg:classifiers":[
        {
            "category":"Social Services",
            "subcategory":"Adult Care",
            "type":"Services"
        }
    ],
    "sg:phone":"+1 702 437 8448",
    "sg:postcode":"89110",
    "sg:province":"NV",
    "sg:tags":[
        "residential"
    ],
    "wof:name":"Caring Hearts Care Home LLC",
    "wof:placetype":"venue"
},
  "geometry": {"coordinates":[-115.096958,36.161301],"type":"Point"}
}