{
  "type": "Feature",
  "properties": {
    "iso:country":"US",
    "sg:address":"9031 W Sahara Ave",
    "sg:city":"Las Vegas",
    "sg:classifiers":[
        {
            "category":"Food & Beverages",
            "subcategory":"Bakery",
            "type":"Retail Goods"
        }
    ],
    "sg:phone":"+1 702 476 1894",
    "sg:postcode":"89117",
    "sg:province":"NV",
    "sg:tags":[
        "sandwich"
    ],
    "sg:website":"www.subway.com",
    "wof:name":"Subway",
    "wof:placetype":"venue"
},
  "geometry": {"coordinates":[-115.294172,36.143731],"type":"Point"}
}