{
  "type": "Feature",
  "properties": {
    "iso:country":"US",
    "sg:address":"1958 E Charleston Boulevard",
    "sg:city":"Las Vegas",
    "sg:classifiers":[
        {
            "category":"Food & Beverages",
            "subcategory":"Groceries & Convenience Stores",
            "type":"Retail Goods"
        }
    ],
    "sg:phone":"+1 702 385 3835",
    "sg:postcode":"89104",
    "sg:province":"NV",
    "wof:name":"Savanh Market",
    "wof:placetype":"venue"
},
  "geometry": {"coordinates":[-115.121492,36.158744],"type":"Point"}
}