{
  "type": "Feature",
  "properties": {
    "iso:country":"US",
    "sg:address":"4525 S Sandhill Rd",
    "sg:city":"Las Vegas",
    "sg:classifiers":[
        {
            "category":"Professional",
            "subcategory":"Management & Consulting",
            "type":"Services"
        }
    ],
    "sg:phone":"+1 702 435 0387",
    "sg:postcode":"89121",
    "sg:province":"NV",
    "sg:tags":[
        "marketing",
        "program"
    ],
    "wof:name":"Best Rate Marketing",
    "wof:placetype":"venue"
},
  "geometry": {"coordinates":[-115.091927,36.106198],"type":"Point"}
}