{
  "type": "Feature",
  "properties": {
    "iso:country":"US",
    "sg:address":"5275 W 7th St",
    "sg:city":"Reno",
    "sg:classifiers":[
        {
            "category":"Arts & Performance",
            "subcategory":"Theater",
            "type":"Entertainment"
        }
    ],
    "sg:phone":"+1 775 747 0680",
    "sg:postcode":"89523",
    "sg:province":"NV",
    "sg:tags":[
        "theatrical",
        "manager",
        "producer"
    ],
    "wof:name":"Phil Entertainment",
    "wof:placetype":"venue"
},
  "geometry": {"coordinates":[-119.869519,39.538286],"type":"Point"}
}