{
  "type": "Feature",
  "properties": {
    "iso:country":"US",
    "sg:address":"3585 E Flamingo Road Suite 201",
    "sg:city":"Las Vegas",
    "sg:classifiers":[
        {
            "category":"Real Estate",
            "subcategory":"Real Estate Services",
            "type":"Services"
        }
    ],
    "sg:phone":"+1 702 215 5200",
    "sg:postcode":"89121",
    "sg:province":"NV",
    "sg:tags":[
        "management",
        "property"
    ],
    "wof:name":"Austin Property Management & Real Estate",
    "wof:placetype":"venue"
},
  "geometry": {"coordinates":[-115.096711,36.11517],"type":"Point"}
}