{
  "type": "Feature",
  "properties": {
    "iso:country":"US",
    "sg:address":"833 Nevada Hwy",
    "sg:city":"Boulder City",
    "sg:classifiers":[
        {
            "category":"Professional",
            "type":"Services"
        }
    ],
    "sg:phone":"+1 702 293 6685",
    "sg:postcode":"89005",
    "sg:province":"NV",
    "sg:tags":[
        "establishment"
    ],
    "wof:name":"Claremont Heights Corp",
    "wof:placetype":"venue"
},
  "geometry": {"coordinates":[-114.842152,35.973845],"type":"Point"}
}