{
  "type": "Feature",
  "properties": {
    "iso:country":"US",
    "sg:address":"280 S Water St",
    "sg:city":"Henderson",
    "sg:classifiers":[
        {
            "category":"Education",
            "subcategory":"Library",
            "type":"Public Place"
        }
    ],
    "sg:phone":"+1 702 565 8402",
    "sg:postcode":"89015",
    "sg:province":"NV",
    "sg:website":"www.hdpl.org",
    "wof:name":"Henderson Public Library",
    "wof:placetype":"venue"
},
  "geometry": {"coordinates":[-114.98188,36.031496],"type":"Point"}
}