{
  "type": "Feature",
  "properties": {
    "iso:country":"US",
    "sg:address":"1383 Bobby Way",
    "sg:city":"Fallon",
    "sg:classifiers":[
        {
            "category":"Manufacturing",
            "subcategory":"Glass & Minerals",
            "type":"Manufacturing & Wholesale Goods"
        }
    ],
    "sg:phone":"+1 775 423 5510",
    "sg:postcode":"89406",
    "sg:province":"NV",
    "sg:tags":[
        "product",
        "mfg"
    ],
    "wof:name":"Mark Glass",
    "wof:placetype":"venue"
},
  "geometry": {"coordinates":[-118.790076,39.501075],"type":"Point"}
}