{
  "type": "Feature",
  "properties": {
    "iso:country":"US",
    "sg:address":"6885 Coley Ave",
    "sg:city":"Las Vegas",
    "sg:classifiers":[
        {
            "category":"Real Estate",
            "subcategory":"Real Estate Services",
            "type":"Services"
        }
    ],
    "sg:phone":"+1 702 733 3910",
    "sg:postcode":"89146",
    "sg:province":"NV",
    "sg:tags":[
        "management",
        "property"
    ],
    "wof:name":"O'sullivan Realty",
    "wof:placetype":"venue"
},
  "geometry": {"coordinates":[-115.242512,36.134697],"type":"Point"}
}