{
  "type": "Feature",
  "properties": {
    "iso:country":"US",
    "sg:address":"123 Juanita Dr",
    "sg:city":"Incline Village",
    "sg:classifiers":[
        {
            "category":"Professional",
            "subcategory":"Management & Consulting",
            "type":"Services"
        }
    ],
    "sg:phone":"+1 775 831 3800",
    "sg:postcode":"89451",
    "sg:province":"NV",
    "sg:tags":[
        "consultant",
        "business"
    ],
    "wof:name":"Matrix Inc",
    "wof:placetype":"venue"
},
  "geometry": {"coordinates":[-119.953101,39.242233],"type":"Point"}
}