{
  "type": "Feature",
  "properties": {
    "iso:country":"US",
    "sg:address":"267 Spring Hills Ln",
    "sg:city":"Henderson",
    "sg:classifiers":[
        {
            "category":"Professional",
            "subcategory":"Computer Services",
            "type":"Services"
        }
    ],
    "sg:phone":"+1 702 454 0018",
    "sg:postcode":"89074",
    "sg:province":"NV",
    "sg:tags":[
        "prepackaged",
        "software"
    ],
    "wof:name":"Centerline Software Inc",
    "wof:placetype":"venue"
},
  "geometry": {"coordinates":[-115.077984,36.049775],"type":"Point"}
}