{
  "type": "Feature",
  "properties": {
    "iso:country":"US",
    "sg:address":"5115 Spring Mountain Road",
    "sg:city":"Las Vegas",
    "sg:classifiers":[
        {
            "category":"Bakery",
            "type":"Food & Drink"
        }
    ],
    "sg:phone":"+1 702 341 0168",
    "sg:postcode":"89146",
    "sg:province":"NV",
    "wof:name":"Provence Bakery",
    "wof:placetype":"venue"
},
  "geometry": {"coordinates":[-115.21117,36.126147],"type":"Point"}
}