{
  "type": "Feature",
  "properties": {
    "iso:country":"US",
    "sg:address":"5167 Losee Rd",
    "sg:city":"North Las Vegas",
    "sg:classifiers":[
        {
            "category":"Building & Trades",
            "subcategory":"Cleaning & Sanitation",
            "type":"Services"
        }
    ],
    "sg:phone":"+1 702 642 0070",
    "sg:postcode":"89031",
    "sg:province":"NV",
    "sg:tags":[
        "maintenance"
    ],
    "wof:name":"Lighthouse Model Maintena",
    "wof:placetype":"venue"
},
  "geometry": {"coordinates":[-115.117055,36.251665],"type":"Point"}
}