{
  "type": "Feature",
  "properties": {
    "iso:country":"US",
    "sg:address":"10797 Refectory Ave",
    "sg:city":"Las Vegas",
    "sg:classifiers":[
        {
            "category":"Building & Trades",
            "subcategory":"Construction",
            "type":"Services"
        }
    ],
    "sg:phone":"+1 702 341 5400",
    "sg:postcode":"89135",
    "sg:province":"NV",
    "sg:tags":[
        "interior",
        "design"
    ],
    "wof:name":"Sydney Designs",
    "wof:placetype":"venue"
},
  "geometry": {"coordinates":[-115.327637,36.130138],"type":"Point"}
}