{
  "type": "Feature",
  "properties": {
    "iso:country":"US",
    "sg:address":"1394 S Wells Ave",
    "sg:city":"Reno",
    "sg:classifiers":[
        {
            "category":"Shopping",
            "subcategory":"Clothing, Apparel, & Fashions",
            "type":"Retail Goods"
        }
    ],
    "sg:phone":"+1 775 786 5300",
    "sg:postcode":"89502",
    "sg:province":"NV",
    "wof:name":"Nimali Fashions",
    "wof:placetype":"venue"
},
  "geometry": {"coordinates":[-119.803072,39.511876],"type":"Point"}
}