{
  "type": "Feature",
  "properties": {
    "iso:country":"US",
    "sg:address":"27 Affonso Dr",
    "sg:city":"Mound House",
    "sg:classifiers":[
        {
            "category":"Manufacturing",
            "subcategory":"Metals",
            "type":"Manufacturing & Wholesale Goods"
        }
    ],
    "sg:phone":"+1 775 246 1934",
    "sg:postcode":"89706",
    "sg:province":"NV",
    "sg:tags":[
        "brass",
        "foundry",
        "bronze"
    ],
    "wof:name":"Tuscon Manufacturing",
    "wof:placetype":"venue"
},
  "geometry": {"coordinates":[-119.653092,39.221993],"type":"Point"}
}