{
  "type": "Feature",
  "properties": {
    "iso:country":"US",
    "sg:address":"5219 Masters Ave",
    "sg:city":"Las Vegas",
    "sg:classifiers":[
        {
            "category":"Building & Trades",
            "subcategory":"Construction",
            "type":"Services"
        }
    ],
    "sg:phone":"+1 702 204 3323",
    "sg:postcode":"89142",
    "sg:province":"NV",
    "sg:tags":[
        "general",
        "contractor"
    ],
    "wof:name":"American Venture Cnstr Group",
    "wof:placetype":"venue"
},
  "geometry": {"coordinates":[-115.0598,36.143021],"type":"Point"}
}