{
  "type": "Feature",
  "properties": {
    "iso:country":"US",
    "sg:address":"261 E Delamar Dr",
    "sg:city":"Henderson",
    "sg:classifiers":[
        {
            "category":"Building & Trades",
            "subcategory":"Construction",
            "type":"Services"
        }
    ],
    "sg:phone":"+1 619 562 2255",
    "sg:postcode":"89015",
    "sg:province":"NV",
    "sg:tags":[
        "company"
    ],
    "wof:name":"RD Engineering & Cnstr Inc",
    "wof:placetype":"venue"
},
  "geometry": {"coordinates":[-114.981544,36.016148],"type":"Point"}
}