{
  "type": "Feature",
  "properties": {
    "iso:country":"US",
    "sg:address":"620 Las Vegas Blvd N",
    "sg:city":"Las Vegas",
    "sg:classifiers":[
        {
            "category":"Organizations",
            "subcategory":"Community Association",
            "type":"Services"
        }
    ],
    "sg:phone":"+1 702 382 7364",
    "sg:postcode":"89101",
    "sg:province":"NV",
    "sg:tags":[
        "club"
    ],
    "wof:name":"Ukulele Lounge",
    "wof:placetype":"venue"
},
  "geometry": {"coordinates":[-115.13660299999999,36.175429],"type":"Point"}
}