{
  "type": "Feature",
  "properties": {
    "iso:country":"US",
    "sg:address":"2700 Chandler Ave",
    "sg:city":"Las Vegas",
    "sg:classifiers":[
        {
            "category":"Professional",
            "subcategory":"Management & Consulting",
            "type":"Services"
        }
    ],
    "sg:phone":"+1 702 795 0515",
    "sg:postcode":"89120",
    "sg:province":"NV",
    "sg:tags":[
        "control",
        "consultant",
        "quality"
    ],
    "wof:name":"ICF-Quality Assurance Lab",
    "wof:placetype":"venue"
},
  "geometry": {"coordinates":[-115.117136,36.074379],"type":"Point"}
}