{
  "type": "Feature",
  "properties": {
    "iso:country":"US",
    "sg:address":"4900 Buck Point Ct",
    "sg:city":"Reno",
    "sg:classifiers":[
        {
            "category":"Restaurant",
            "type":"Food & Drink"
        }
    ],
    "sg:phone":"+1 775 825 2520",
    "sg:postcode":"89509",
    "sg:province":"NV",
    "sg:tags":[
        "fast"
    ],
    "wof:name":"Szechuan Diner and Fast Food",
    "wof:placetype":"venue"
},
  "geometry": {"coordinates":[-119.834769,39.475373],"type":"Point"}
}