{
  "type": "Feature",
  "properties": {
    "iso:country":"US",
    "sg:address":"1008 Marsha Ln",
    "sg:city":"Gardnerville",
    "sg:classifiers":[
        {
            "category":"Building & Trades",
            "subcategory":"Construction",
            "type":"Services"
        }
    ],
    "sg:phone":"+1 775 691 5613",
    "sg:postcode":"89460",
    "sg:province":"NV",
    "sg:tags":[
        "home",
        "improvement"
    ],
    "wof:name":"Kyle's Home Maintenance",
    "wof:placetype":"venue"
},
  "geometry": {"coordinates":[-119.80635599999999,38.912194],"type":"Point"}
}