{
  "type": "Feature",
  "properties": {
    "iso:country":"US",
    "sg:address":"3456 E Brittlewood Ave",
    "sg:city":"Las Vegas",
    "sg:classifiers":[
        {
            "category":"Professional",
            "subcategory":"Management & Consulting",
            "type":"Services"
        }
    ],
    "sg:phone":"+1 702 735 7123",
    "sg:postcode":"89120",
    "sg:province":"NV",
    "sg:tags":[
        "counselor",
        "public",
        "relations"
    ],
    "wof:name":"Image Media",
    "wof:placetype":"venue"
},
  "geometry": {"coordinates":[-115.100009,36.091526],"type":"Point"}
}