{
  "type": "Feature",
  "properties": {
    "iso:country":"US",
    "sg:address":"12555 Broili Dr",
    "sg:city":"Reno",
    "sg:classifiers":[
        {
            "category":"Restaurant",
            "type":"Food & Drink"
        }
    ],
    "sg:phone":"+1 775 826 8508",
    "sg:postcode":"89511",
    "sg:province":"NV",
    "sg:tags":[
        "pizza"
    ],
    "wof:name":"New York Pizza Inc",
    "wof:placetype":"venue"
},
  "geometry": {"coordinates":[-119.776695,39.419429],"type":"Point"}
}