{
  "type": "Feature",
  "properties": {
    "iso:country":"US",
    "sg:address":"5105 Summit Ridge Ct",
    "sg:city":"Reno",
    "sg:classifiers":[
        {
            "category":"Food & Beverages",
            "subcategory":"Groceries & Convenience Stores",
            "type":"Retail Goods"
        }
    ],
    "sg:phone":"+1 775 787 3981",
    "sg:postcode":"89523",
    "sg:province":"NV",
    "sg:website":"www.jim4sparks.com",
    "wof:name":"7-Eleven",
    "wof:placetype":"venue"
},
  "geometry": {"coordinates":[-119.862467,39.520546],"type":"Point"}
}