{
  "type": "Feature",
  "properties": {
    "iso:country":"US",
    "sg:address":"2705 Hanging Rock Dr",
    "sg:city":"Las Vegas",
    "sg:classifiers":[
        {
            "category":"Real Estate",
            "subcategory":"Real Estate Agent",
            "type":"Services"
        }
    ],
    "sg:phone":"+1 702 258 7777",
    "sg:postcode":"89134",
    "sg:province":"NV",
    "wof:name":"Shaffer Rollin ER Rl Est Brkr",
    "wof:placetype":"venue"
},
  "geometry": {"coordinates":[-115.327958,36.20876],"type":"Point"}
}