{
  "type": "Feature",
  "properties": {
    "iso:country":"US",
    "sg:address":"1460 Eunice Way",
    "sg:city":"Washoe Valley",
    "sg:classifiers":[
        {
            "category":"Insurance",
            "subcategory":"Insurance Agent",
            "type":"Services"
        }
    ],
    "sg:phone":"+1 775 849 1994",
    "sg:postcode":"89704",
    "sg:province":"NV",
    "wof:name":"Mike Colson Insurance",
    "wof:placetype":"venue"
},
  "geometry": {"coordinates":[-119.78057800000001,39.312354],"type":"Point"}
}