{
  "type": "Feature",
  "properties": {
    "iso:country":"US",
    "sg:address":"1000 Duckhorn Ct",
    "sg:city":"Las Vegas",
    "sg:classifiers":[
        {
            "category":"Education",
            "subcategory":"Special Training",
            "type":"Public Place"
        }
    ],
    "sg:phone":"+1 702 233 6147",
    "sg:postcode":"89144",
    "sg:province":"NV",
    "wof:name":"Granados School of Languages",
    "wof:placetype":"venue"
},
  "geometry": {"coordinates":[-115.30735900000001,36.182179],"type":"Point"}
}