{
  "type": "Feature",
  "properties": {
    "iso:country":"US",
    "sg:address":"7322 Duck Springs Ct",
    "sg:city":"Las Vegas",
    "sg:classifiers":[
        {
            "category":"Restaurant",
            "type":"Food & Drink"
        }
    ],
    "sg:phone":"+1 702 877 2123",
    "sg:postcode":"89147",
    "sg:province":"NV",
    "wof:name":"Chinese Food Express",
    "wof:placetype":"venue"
},
  "geometry": {"coordinates":[-115.251558,36.122892],"type":"Point"}
}