{
  "type": "Feature",
  "properties": {
    "iso:country":"US",
    "sg:address":"5700 Spring Mountain Road",
    "sg:city":"Las Vegas",
    "sg:classifiers":[
        {
            "category":"Food & Beverages",
            "subcategory":"Groceries & Convenience Stores",
            "type":"Retail Goods"
        }
    ],
    "sg:phone":"+1 702 364 0633",
    "sg:postcode":"89146",
    "sg:province":"NV",
    "wof:name":"Sunfood Market",
    "wof:placetype":"venue"
},
  "geometry": {"coordinates":[-115.218515,36.125798],"type":"Point"}
}