{
  "type": "Feature",
  "properties": {
    "iso:country":"US",
    "sg:address":"1771 E Flamingo Rd",
    "sg:city":"Las Vegas",
    "sg:classifiers":[
        {
            "category":"Professional",
            "subcategory":"Lawyer & Legal Services",
            "type":"Services"
        }
    ],
    "sg:phone":"+1 702 731 2333",
    "sg:postcode":"89119",
    "sg:province":"NV",
    "wof:name":"Michaelson & Associates",
    "wof:placetype":"venue"
},
  "geometry": {"coordinates":[-115.130906,36.114523],"type":"Point"}
}