{
  "type": "Feature",
  "properties": {
    "iso:country":"US",
    "sg:address":"2575 Montessouri St",
    "sg:city":"Las Vegas",
    "sg:classifiers":[
        {
            "category":"Real Estate",
            "subcategory":"Architect",
            "type":"Services"
        }
    ],
    "sg:phone":"+1 702 388 9199",
    "sg:postcode":"89117",
    "sg:province":"NV",
    "sg:tags":[
        "illustrator",
        "architectural"
    ],
    "wof:name":"Neil Ponsky & Assoc",
    "wof:placetype":"venue"
},
  "geometry": {"coordinates":[-115.247474,36.143586],"type":"Point"}
}