{
  "type": "Feature",
  "properties": {
    "iso:country":"US",
    "sg:address":"8191 Palace Monaco Ave",
    "sg:city":"Las Vegas",
    "sg:classifiers":[
        {
            "category":"Autos & Motor Vehicles",
            "subcategory":"Auto Supplies",
            "type":"Retail Goods"
        }
    ],
    "sg:phone":"+1 702 491 2127",
    "sg:postcode":"89117",
    "sg:province":"NV",
    "wof:name":"3j Motors",
    "wof:placetype":"venue"
},
  "geometry": {"coordinates":[-115.267602,36.129746],"type":"Point"}
}