{
  "type": "Feature",
  "properties": {
    "iso:country":"US",
    "sg:address":"701 North Green Valley Parkway Suite 200",
    "sg:city":"Henderson",
    "sg:classifiers":[
        {
            "category":"Professional",
            "subcategory":"Computer Services",
            "type":"Services"
        }
    ],
    "sg:phone":"+1 773 842 7126",
    "sg:postcode":"80974",
    "sg:province":"NV",
    "sg:tags":[
        "investment-banking",
        "fundraising",
        "consulting",
        "ma",
        "mergers-and-acquisitions"
    ],
    "sg:website":"http://www.petskyprunier.com",
    "wof:name":"Petsky Prunier",
    "wof:placetype":"venue"
},
  "geometry": {"coordinates":[-115.085994,36.027565],"type":"Point"}
}