{
  "type": "Feature",
  "properties": {
    "iso:country":"US",
    "sg:address":"412 W John St",
    "sg:city":"Carson City",
    "sg:classifiers":[
        {
            "category":"Health Services",
            "subcategory":"Doctor",
            "type":"Services"
        }
    ],
    "sg:phone":"+1 877 817 1500",
    "sg:postcode":"89703",
    "sg:province":"NV",
    "sg:tags":[
        "ophthalmologist",
        "surgeon",
        "physician"
    ],
    "sg:website":"www.sierralaservision.com",
    "wof:name":"Sierra Nevada Laser Center",
    "wof:placetype":"venue"
},
  "geometry": {"coordinates":[-119.769997,39.171101],"type":"Point"}
}