{
  "type": "Feature",
  "properties": {
    "iso:country":"US",
    "sg:address":"1229 N Linn Ln",
    "sg:city":"Las Vegas",
    "sg:classifiers":[
        {
            "category":"Manufacturing",
            "subcategory":"Glass & Minerals",
            "type":"Manufacturing & Wholesale Goods"
        }
    ],
    "sg:phone":"+1 702 452 9942",
    "sg:postcode":"89110",
    "sg:province":"NV",
    "sg:tags":[
        "mfg"
    ],
    "wof:name":"Extreme Tanks",
    "wof:placetype":"venue"
},
  "geometry": {"coordinates":[-115.04846999999999,36.183203],"type":"Point"}
}