{
  "type": "Feature",
  "properties": {
    "iso:country":"US",
    "sg:address":"3841 Heron's Landing Dr",
    "sg:city":"Reno",
    "sg:classifiers":[
        {
            "category":"Building & Trades",
            "subcategory":"Plumbing",
            "type":"Services"
        }
    ],
    "sg:phone":"+1 775 853 3221",
    "sg:postcode":"89502",
    "sg:province":"NV",
    "sg:tags":[
        "plumbing",
        "contractor"
    ],
    "wof:name":"Price & Sons Plumbing",
    "wof:placetype":"venue"
},
  "geometry": {"coordinates":[-119.738647,39.483033],"type":"Point"}
}