{
  "type": "Feature",
  "properties": {
    "iso:country":"US",
    "sg:address":"1385 Cathy Ln",
    "sg:city":"Minden",
    "sg:classifiers":[
        {
            "category":"Manufacturing",
            "subcategory":"Building Materials",
            "type":"Manufacturing & Wholesale Goods"
        }
    ],
    "sg:phone":"+1 775 450 2542",
    "sg:postcode":"89423",
    "sg:province":"NV",
    "sg:tags":[
        "mfg"
    ],
    "wof:name":"Western Woodworking",
    "wof:placetype":"venue"
},
  "geometry": {"coordinates":[-119.734595,39.035713],"type":"Point"}
}