{
  "type": "Feature",
  "properties": {
    "iso:country":"US",
    "sg:address":"3130 S Rainbow Blvd",
    "sg:city":"Las Vegas",
    "sg:classifiers":[
        {
            "category":"Insurance",
            "subcategory":"Insurance Agent",
            "type":"Services"
        }
    ],
    "sg:phone":"+1 702 368 4217",
    "sg:postcode":"89146",
    "sg:province":"NV",
    "sg:website":"www.westernrisk.com",
    "wof:name":"Western Risk Insurance",
    "wof:placetype":"venue"
},
  "geometry": {"coordinates":[-115.24289,36.131863],"type":"Point"}
}