{
  "type": "Feature",
  "properties": {
    "iso:country":"US",
    "sg:address":"3600 S Highland Dr",
    "sg:city":"Las Vegas",
    "sg:classifiers":[
        {
            "category":"Home & Garden",
            "subcategory":"Building Materials",
            "type":"Retail Goods"
        },
        {
            "category":"Building & Trades",
            "subcategory":"Construction",
            "type":"Services"
        }
    ],
    "sg:phone":"+1 702 871 9797",
    "sg:postcode":"89103",
    "sg:province":"NV",
    "sg:tags":[
        "tile",
        "dealer"
    ],
    "wof:name":"Ceramic Outlet",
    "wof:placetype":"venue"
},
  "geometry": {"coordinates":[-115.1812,36.125098],"type":"Point"}
}