{
  "type": "Feature",
  "properties": {
    "iso:country":"US",
    "sg:address":"6767 W Tropicana Avenue Suite 102",
    "sg:city":"Las Vegas",
    "sg:classifiers":[
        {
            "category":"Communications",
            "subcategory":"Radio Station",
            "type":"Services"
        }
    ],
    "sg:phone":"+1 702 257 1035",
    "sg:postcode":"89103",
    "sg:province":"NV",
    "wof:name":"Kisf 103.5 Fm La Nueva",
    "wof:placetype":"venue"
},
  "geometry": {"coordinates":[-115.239703,36.09975],"type":"Point"}
}