{
  "type": "Feature",
  "properties": {
    "iso:country":"US",
    "sg:address":"4740 S Decatur Blvd",
    "sg:city":"Las Vegas",
    "sg:classifiers":[
        {
            "category":"Home & Garden",
            "subcategory":"Hardware",
            "type":"Retail Goods"
        }
    ],
    "sg:phone":"+1 702 889 9380",
    "sg:postcode":"89103",
    "sg:province":"NV",
    "sg:tags":[
        "equipment",
        "tool",
        "industrial",
        "used"
    ],
    "wof:name":"Harbor Freight Tools USA Inc",
    "wof:placetype":"venue"
},
  "geometry": {"coordinates":[-115.20790100000001,36.10526],"type":"Point"}
}