{
  "type": "Feature",
  "properties": {
    "iso:country":"US",
    "sg:address":"3111 N Rainbow Blvd",
    "sg:city":"Las Vegas",
    "sg:classifiers":[
        {
            "category":"Personal",
            "subcategory":"Beauty Salon",
            "type":"Services"
        }
    ],
    "sg:phone":"+1 702 655 8430",
    "sg:postcode":"89108",
    "sg:province":"NV",
    "sg:tags":[
        "manicuring"
    ],
    "wof:name":"Hanna-Banana Nail Care",
    "wof:placetype":"venue"
},
  "geometry": {"coordinates":[-115.242365,36.21658],"type":"Point"}
}