{
  "type": "Feature",
  "properties": {
    "iso:country":"US",
    "sg:address":"751 Summer Heights Ln",
    "sg:city":"Las Vegas",
    "sg:classifiers":[
        {
            "category":"Building & Trades",
            "subcategory":"Landscaping Services",
            "type":"Services"
        }
    ],
    "sg:phone":"+1 702 437 0891",
    "sg:postcode":"89110",
    "sg:province":"NV",
    "sg:tags":[
        "lawn",
        "maintenance",
        "grounds"
    ],
    "wof:name":"Maricela Alvarez Lawn Mntnc",
    "wof:placetype":"venue"
},
  "geometry": {"coordinates":[-115.047392,36.172701],"type":"Point"}
}