{
  "type": "Feature",
  "properties": {
    "iso:country":"US",
    "sg:address":"7835 S Rainbow Blvd",
    "sg:city":"Las Vegas",
    "sg:classifiers":[
        {
            "category":"Restaurant",
            "type":"Food & Drink"
        }
    ],
    "sg:phone":"+1 702 451 1942",
    "sg:postcode":"89139",
    "sg:province":"NV",
    "sg:tags":[
        "pizza"
    ],
    "sg:website":"www.foxspizzalasvegas.com",
    "wof:name":"Fox's Pizza Den",
    "wof:placetype":"venue"
},
  "geometry": {"coordinates":[-115.243351,36.04597],"type":"Point"}
}