{
  "type": "Feature",
  "properties": {
    "iso:country":"US",
    "sg:address":"2908 Lake East Dr",
    "sg:city":"Las Vegas",
    "sg:classifiers":[
        {
            "category":"Professional",
            "subcategory":"Advertising",
            "type":"Services"
        }
    ],
    "sg:phone":"+1 702 920 5210",
    "sg:postcode":"89117",
    "sg:province":"NV",
    "wof:name":"XTREMEDIVE.COM",
    "wof:placetype":"venue"
},
  "geometry": {"coordinates":[-115.282881,36.136073],"type":"Point"}
}