{
  "type": "Feature",
  "properties": {
    "iso:country":"US",
    "sg:address":"4432 el Carnal Way",
    "sg:city":"Las Vegas",
    "sg:classifiers":[
        {
            "category":"Retail",
            "subcategory":"Repair Shop",
            "type":"Services"
        },
        {
            "category":"Manufacturing",
            "subcategory":"Tools & Machinery",
            "type":"Manufacturing & Wholesale Goods"
        }
    ],
    "sg:phone":"+1 702 383 6900",
    "sg:postcode":"89121",
    "sg:province":"NV",
    "sg:tags":[
        "product",
        "upholsterer",
        "mfg"
    ],
    "wof:name":"Sew What Custom Canvas & Uphl",
    "wof:placetype":"venue"
},
  "geometry": {"coordinates":[-115.074879,36.106888],"type":"Point"}
}