{
  "type": "Feature",
  "properties": {
    "iso:country":"US",
    "sg:address":"7260 W Lake Mead Blvd Ste 5",
    "sg:city":"Las Vegas",
    "sg:classifiers":[
        {
            "category":"Health Services",
            "subcategory":"Dentist",
            "type":"Services"
        }
    ],
    "sg:phone":"+1 702 562 8852",
    "sg:postcode":"89128",
    "sg:province":"NV",
    "wof:name":"Acclaim Dental",
    "wof:placetype":"venue"
},
  "geometry": {"coordinates":[-115.250999,36.196098],"type":"Point"}
}