{
  "type": "Feature",
  "properties": {
    "iso:country":"US",
    "sg:address":"1324 Chichester Dr",
    "sg:city":"Gardnerville",
    "sg:classifiers":[
        {
            "category":"Professional",
            "subcategory":"Management & Consulting",
            "type":"Services"
        }
    ],
    "sg:phone":"+1 775 782 7284",
    "sg:postcode":"89410",
    "sg:province":"NV",
    "sg:tags":[
        "construction"
    ],
    "wof:name":"Chichester Estates Management",
    "wof:placetype":"venue"
},
  "geometry": {"coordinates":[-119.738749,38.942446],"type":"Point"}
}