{
  "type": "Feature",
  "properties": {
    "iso:country":"US",
    "sg:address":"1005 Carpenter Rd",
    "sg:city":"Lovelock",
    "sg:classifiers":[
        {
            "category":"Farming",
            "subcategory":"Farm & Veterinary Services",
            "type":"Manufacturing & Wholesale Goods"
        }
    ],
    "sg:phone":"+1 775 273 7001",
    "sg:postcode":"89419",
    "sg:province":"NV",
    "sg:tags":[
        "management"
    ],
    "wof:name":"Great Basin Farms",
    "wof:placetype":"venue"
},
  "geometry": {"coordinates":[-118.49557799999999,40.115056],"type":"Point"}
}