{
  "type": "Feature",
  "properties": {
    "iso:country":"US",
    "sg:address":"9732 State Rte 445",
    "sg:city":"Sparks",
    "sg:classifiers":[
        {
            "category":"Wholesale",
            "subcategory":"Stationery",
            "type":"Manufacturing & Wholesale Goods"
        }
    ],
    "sg:phone":"+1 775 626 5122",
    "sg:postcode":"89441",
    "sg:province":"NV",
    "sg:tags":[
        "supply"
    ],
    "wof:name":"Live Preserve & Remember",
    "wof:placetype":"venue"
},
  "geometry": {"coordinates":[-119.751149,39.561781],"type":"Point"}
}