{
  "type": "Feature",
  "properties": {
    "iso:country":"US",
    "sg:address":"900 W 1st St",
    "sg:city":"Reno",
    "sg:classifiers":[
        {
            "category":"Sports & Exercise",
            "subcategory":"Gym",
            "type":"Entertainment"
        }
    ],
    "sg:phone":"+1 775 323 2101",
    "sg:postcode":"89503",
    "sg:province":"NV",
    "sg:tags":[
        "fitness",
        "physical",
        "facility"
    ],
    "wof:name":"Fitness Evolution Inc",
    "wof:placetype":"venue"
},
  "geometry": {"coordinates":[-119.825313,39.523264],"type":"Point"}
}