{
  "type": "Feature",
  "properties": {
    "iso:country":"US",
    "sg:address":"Cosmopolitan Hotel and Casino 3708 Las Vegas Blvd S",
    "sg:city":"Las Vegas",
    "sg:classifiers":[
        {
            "category":"Restaurant",
            "type":"Food & Drink"
        }
    ],
    "sg:phone":"+1 877 551 7776",
    "sg:postcode":"89109",
    "sg:province":"NV",
    "sg:tags":[
        "mexican",
        "chinese"
    ],
    "sg:website":"www.cosmopolitanlasvegas.com",
    "wof:name":"China Poblano",
    "wof:placetype":"venue"
},
  "geometry": {"coordinates":[-115.175193,36.109629],"type":"Point"}
}