{
  "type": "Feature",
  "properties": {
    "iso:country":"US",
    "sg:address":"1845 N Rancho Dr",
    "sg:city":"Las Vegas",
    "sg:classifiers":[
        {
            "category":"Retail",
            "subcategory":"Auto Repair",
            "type":"Services"
        }
    ],
    "sg:phone":"+1 702 643 1001",
    "sg:postcode":"89106",
    "sg:province":"NV",
    "sg:tags":[
        "automotive"
    ],
    "wof:name":"D & K Radiator",
    "wof:placetype":"venue"
},
  "geometry": {"coordinates":[-115.190428,36.193202],"type":"Point"}
}