{
  "type": "Feature",
  "properties": {
    "iso:country":"US",
    "sg:address":"3799 Las Vegas Blvd S",
    "sg:city":"Las Vegas",
    "sg:classifiers":[
        {
            "category":"Bars & Pubs",
            "type":"Food & Drink"
        }
    ],
    "sg:menulink":"http://www.allmenus.com/nv/las-vegas/21850-wolfgang-puck-bar--grill-at-the-mgm-grand/menu/",
    "sg:phone":"+1 702 891 3000",
    "sg:postcode":"89109",
    "sg:province":"NV",
    "sg:tags":[
        "american"
    ],
    "wof:name":"Wolfgang Puck Bar & Grill At The MGM Grand",
    "wof:placetype":"venue"
},
  "geometry": {"coordinates":[-115.172111,36.101688],"type":"Point"}
}