{
  "type": "Feature",
  "properties": {
    "iso:country":"US",
    "sg:address":"7516 Maiden Run Ave",
    "sg:city":"Las Vegas",
    "sg:classifiers":[
        {
            "category":"Building & Trades",
            "subcategory":"Construction",
            "type":"Services"
        }
    ],
    "sg:phone":"+1 702 656 5995",
    "sg:postcode":"89130",
    "sg:province":"NV",
    "wof:name":"A K M Grading",
    "wof:placetype":"venue"
},
  "geometry": {"coordinates":[-115.258702,36.270675],"type":"Point"}
}