{
  "type": "Feature",
  "properties": {
    "iso:country":"US",
    "sg:address":"2105 Kirkland Ave",
    "sg:city":"Las Vegas",
    "sg:classifiers":[
        {
            "category":"Professional",
            "type":"Services"
        }
    ],
    "sg:phone":"+1 702 383 4028",
    "sg:postcode":"89102",
    "sg:province":"NV",
    "wof:name":"Sweet Desserts Inc",
    "wof:placetype":"venue"
},
  "geometry": {"coordinates":[-115.170293,36.149813],"type":"Point"}
}