{
  "type": "Feature",
  "properties": {
    "iso:country":"US",
    "sg:address":"2035 E Warm Springs Rd",
    "sg:city":"Las Vegas",
    "sg:classifiers":[
        {
            "category":"Professional",
            "subcategory":"Computer Services",
            "type":"Services"
        }
    ],
    "sg:phone":"+1 702 898 9078",
    "sg:postcode":"89119",
    "sg:province":"NV",
    "sg:tags":[
        "internet"
    ],
    "wof:name":"Utilitran America",
    "wof:placetype":"venue"
},
  "geometry": {"coordinates":[-115.124083,36.057298],"type":"Point"}
}