{
  "type": "Feature",
  "properties": {
    "iso:country":"US",
    "sg:address":"8275 S Eastern Ave",
    "sg:city":"Las Vegas",
    "sg:classifiers":[
        {
            "category":"Professional",
            "subcategory":"Lawyer & Legal Services",
            "type":"Services"
        }
    ],
    "sg:phone":"+1 702 990 8418",
    "sg:postcode":"89123",
    "sg:province":"NV",
    "wof:name":"Hays McConn Rice & Pickering",
    "wof:placetype":"venue"
},
  "geometry": {"coordinates":[-115.11839,36.039003],"type":"Point"}
}