{
  "type": "Feature",
  "properties": {
    "iso:country":"US",
    "sg:address":"5320 Procyon St",
    "sg:city":"Las Vegas",
    "sg:classifiers":[
        {
            "category":"Communications",
            "subcategory":"Film & Video Production",
            "type":"Services"
        }
    ],
    "sg:phone":"+1 702 597 1969",
    "sg:postcode":"89118",
    "sg:province":"NV",
    "sg:tags":[
        "taping"
    ],
    "sg:website":"www.centurylv.com",
    "wof:name":"CMX Century Productions",
    "wof:placetype":"venue"
},
  "geometry": {"coordinates":[-115.187614,36.092019],"type":"Point"}
}