{
  "type": "Feature",
  "properties": {
    "iso:country":"US",
    "sg:address":"857 Center St",
    "sg:city":"Henderson",
    "sg:classifiers":[
        {
            "category":"Professional",
            "subcategory":"Computer Services",
            "type":"Services"
        }
    ],
    "sg:phone":"+1 702 320 8760",
    "sg:postcode":"89015",
    "sg:province":"NV",
    "sg:tags":[
        "programing",
        "custom"
    ],
    "sg:website":"www.computertutor-online.com",
    "wof:name":"Computer Tutor",
    "wof:placetype":"venue"
},
  "geometry": {"coordinates":[-114.967275,36.044456],"type":"Point"}
}