{
  "type": "Feature",
  "properties": {
    "iso:country":"US",
    "sg:address":"3400 S Las Vegas Blvd Inside Mirage Hotel & Casino",
    "sg:city":"Las Vegas",
    "sg:classifiers":[
        {
            "category":"Shopping",
            "subcategory":"Jewelry",
            "type":"Retail Goods"
        }
    ],
    "sg:phone":"+1 702 791 7111",
    "sg:postcode":"89109",
    "sg:province":"NV",
    "sg:tags":[
        "watch"
    ],
    "sg:website":"www.mirage.com/shopping/shopping...",
    "wof:name":"The Watch Boutique",
    "wof:placetype":"venue"
},
  "geometry": {"coordinates":[-115.172361,36.120476],"type":"Point"}
}