{
  "type": "Feature",
  "properties": {
    "iso:country":"US",
    "sg:address":"936 E Overland St",
    "sg:city":"Carson City",
    "sg:classifiers":[
        {
            "category":"Building & Trades",
            "subcategory":"Construction",
            "type":"Services"
        }
    ],
    "sg:phone":"+1 775 883 8617",
    "sg:postcode":"89701",
    "sg:province":"NV",
    "sg:tags":[
        "contractor"
    ],
    "wof:name":"Jerome Joe Taylor Contractor",
    "wof:placetype":"venue"
},
  "geometry": {"coordinates":[-119.758548,39.126665],"type":"Point"}
}