{
  "type": "Feature",
  "properties": {
    "iso:country":"US",
    "sg:address":"2015 Helm Dr",
    "sg:city":"Las Vegas",
    "sg:classifiers":[
        {
            "category":"Building & Trades",
            "subcategory":"Construction",
            "type":"Services"
        }
    ],
    "sg:phone":"+1 702 737 7512",
    "sg:postcode":"89119",
    "sg:province":"NV",
    "sg:tags":[
        "marble",
        "contractor"
    ],
    "wof:name":"Las Vegas Marble & Granite",
    "wof:placetype":"venue"
},
  "geometry": {"coordinates":[-115.124401,36.067989],"type":"Point"}
}