{
  "type": "Feature",
  "properties": {
    "iso:country":"US",
    "sg:address":"1651 Palm St",
    "sg:city":"Las Vegas",
    "sg:classifiers":[
        {
            "category":"Bars & Pubs",
            "type":"Food & Drink"
        }
    ],
    "sg:phone":"+1 702 457 0010",
    "sg:postcode":"89104",
    "sg:province":"NV",
    "wof:name":"B T's Pub",
    "wof:placetype":"venue"
},
  "geometry": {"coordinates":[-115.101054,36.152014],"type":"Point"}
}