{
  "type": "Feature",
  "properties": {
    "iso:country":"US",
    "sg:address":"3120 Venture Dr",
    "sg:city":"Las Vegas",
    "sg:classifiers":[
        {
            "category":"Wholesale",
            "subcategory":"Motor Vehicles",
            "type":"Manufacturing & Wholesale Goods"
        }
    ],
    "sg:phone":"+1 702 312 6124",
    "sg:postcode":"89101",
    "sg:province":"NV",
    "sg:tags":[
        "manufacture",
        "suspension",
        "aftermarket",
        "system"
    ],
    "wof:name":"Amtech Corporation",
    "wof:placetype":"venue"
},
  "geometry": {"coordinates":[-115.103904,36.159976],"type":"Point"}
}