{
  "type": "Feature",
  "properties": {
    "iso:country":"US",
    "sg:address":"2100 S Casino Dr",
    "sg:city":"Laughlin",
    "sg:classifiers":[
        {
            "category":"Restaurant",
            "type":"Food & Drink"
        }
    ],
    "sg:menulink":"http://www.allmenus.com/nv/clark/133947-subway/menu/",
    "sg:phone":"+1 702 298 5609",
    "sg:postcode":"89029",
    "sg:province":"NV",
    "sg:tags":[
        "american",
        "sandwich"
    ],
    "wof:name":"Subway",
    "wof:placetype":"venue"
},
  "geometry": {"coordinates":[-114.573128,35.158421],"type":"Point"}
}