{
  "type": "Feature",
  "properties": {
    "iso:country":"US",
    "sg:address":"791 Marks St",
    "sg:city":"Henderson",
    "sg:classifiers":[
        {
            "category":"Autos & Motor Vehicles",
            "subcategory":"Auto Supplies",
            "type":"Retail Goods"
        },
        {
            "category":"Shopping",
            "type":"Retail Goods"
        }
    ],
    "sg:phone":"+1 702 352 2010",
    "sg:postcode":"89014",
    "sg:province":"NV",
    "sg:tags":[
        "tire"
    ],
    "sg:website":"www.costco.com/Warehouse/Warehou...",
    "wof:name":"Costco Warehouse",
    "wof:placetype":"venue"
},
  "geometry": {"coordinates":[-115.037166,36.06985],"type":"Point"}
}