{
  "type": "Feature",
  "properties": {
    "iso:country":"US",
    "sg:address":"3551 E Bonanza Road Suite 108",
    "sg:city":"Las Vegas",
    "sg:classifiers":[
        {
            "category":"Health Services",
            "subcategory":"Doctor",
            "type":"Services"
        },
        {
            "category":"Health Services",
            "subcategory":"Chiropractor",
            "type":"Services"
        }
    ],
    "sg:phone":"+1 702 437 0800",
    "sg:postcode":"89110",
    "sg:province":"NV",
    "wof:name":"Toranzo Eric DC",
    "wof:placetype":"venue"
},
  "geometry": {"coordinates":[-115.097367,36.173427],"type":"Point"}
}