{
  "type": "Feature",
  "properties": {
    "iso:country":"US",
    "sg:address":"566 River St",
    "sg:city":"Elko",
    "sg:classifiers":[
        {
            "category":"Personal",
            "subcategory":"Tattoo Parlor",
            "type":"Services"
        }
    ],
    "sg:phone":"+1 775 753 8287",
    "sg:postcode":"89801",
    "sg:province":"NV",
    "sg:tags":[
        "tattooing"
    ],
    "wof:name":"Mark Of Identity Tattooing",
    "wof:placetype":"venue"
},
  "geometry": {"coordinates":[-115.759339,40.831433],"type":"Point"}
}