{
  "type": "Feature",
  "properties": {
    "iso:country":"US",
    "sg:address":"140 Pacific Ave",
    "sg:city":"Winnemucca",
    "sg:classifiers":[
        {
            "category":"Wholesale",
            "subcategory":"Farm Supplies",
            "type":"Manufacturing & Wholesale Goods"
        }
    ],
    "sg:phone":"+1 775 623 2005",
    "sg:postcode":"89445",
    "sg:province":"NV",
    "sg:tags":[
        "fertilizer"
    ],
    "sg:website":"www.simplot.com",
    "wof:name":"Simplot Soilbuilders",
    "wof:placetype":"venue"
},
  "geometry": {"coordinates":[-117.73912799999999,40.978737],"type":"Point"}
}