{
  "type": "Feature",
  "properties": {
    "iso:country":"US",
    "sg:address":"275 Hill St",
    "sg:city":"Reno",
    "sg:classifiers":[
        {
            "category":"Professional",
            "subcategory":"Lawyer & Legal Services",
            "type":"Services"
        }
    ],
    "sg:phone":"+1 775 322 2332",
    "sg:postcode":"89501",
    "sg:province":"NV",
    "sg:tags":[
        "attorney"
    ],
    "wof:name":"Michael B Mc Donald",
    "wof:placetype":"venue"
},
  "geometry": {"coordinates":[-119.814355,39.522432],"type":"Point"}
}