{
  "type": "Feature",
  "properties": {
    "iso:country":"US",
    "sg:address":"3660 Cinder Lane",
    "sg:city":"Las Vegas",
    "sg:classifiers":[
        {
            "category":"Professional",
            "subcategory":"Art Services",
            "type":"Services"
        }
    ],
    "sg:phone":"+1 702 871 8300",
    "sg:postcode":"89103",
    "sg:province":"NV",
    "sg:tags":[
        "photographer"
    ],
    "sg:website":"www.cashmanphoto.com/",
    "wof:name":"Cashman Photo Enterprises",
    "wof:placetype":"venue"
},
  "geometry": {"coordinates":[-115.18245400000001,36.121957],"type":"Point"}
}