{
  "type": "Feature",
  "properties": {
    "iso:country":"US",
    "sg:address":"5025 S Eastern Avenue Suite 23",
    "sg:city":"Las Vegas",
    "sg:classifiers":[
        {
            "category":"Food & Beverages",
            "subcategory":"Liquor & Beverages",
            "type":"Retail Goods"
        },
        {
            "category":"Food & Beverages",
            "subcategory":"Meat & Fish",
            "type":"Retail Goods"
        }
    ],
    "sg:phone":"+1 702 736 7575",
    "sg:postcode":"89119",
    "sg:province":"NV",
    "sg:tags":[
        "shop",
        "beer",
        "spirit",
        "wine"
    ],
    "sg:website":"www.villagemeatandwine.com",
    "wof:name":"Village Meat & Wine",
    "wof:placetype":"venue"
},
  "geometry": {"coordinates":[-115.118887,36.097356],"type":"Point"}
}