{
  "type": "Feature",
  "properties": {
    "iso:country":"US",
    "sg:address":"2001 S Jones Blvd Ste D",
    "sg:city":"Las Vegas",
    "sg:classifiers":[
        {
            "category":"Real Estate",
            "subcategory":"Real Estate Services",
            "type":"Services"
        }
    ],
    "sg:phone":"+1 702 871 8280",
    "sg:postcode":"89146",
    "sg:province":"NV",
    "sg:tags":[
        "management",
        "property"
    ],
    "sg:website":"covenantmgmt.com/",
    "wof:name":"Covenant Management",
    "wof:placetype":"venue"
},
  "geometry": {"coordinates":[-115.226127,36.148751],"type":"Point"}
}