{
  "type": "Feature",
  "properties": {
    "iso:country":"US",
    "sg:address":"1289 Baring Blvd",
    "sg:city":"Sparks",
    "sg:classifiers":[
        {
            "category":"Manufacturing",
            "subcategory":"Retail Goods",
            "type":"Manufacturing & Wholesale Goods"
        }
    ],
    "sg:phone":"+1 775 356 5811",
    "sg:postcode":"89434",
    "sg:province":"NV",
    "sg:tags":[
        "lead",
        "mfg"
    ],
    "wof:name":"Potter L Playful L C",
    "wof:placetype":"venue"
},
  "geometry": {"coordinates":[-119.720564,39.556289],"type":"Point"}
}