{
  "type": "Feature",
  "properties": {
    "iso:country":"US",
    "sg:address":"4096 Kietzke Ln",
    "sg:city":"Reno",
    "sg:classifiers":[
        {
            "category":"Organizations",
            "subcategory":"Religious Organization",
            "type":"Services"
        }
    ],
    "sg:phone":"+1 775 829 8117",
    "sg:postcode":"89502",
    "sg:province":"NV",
    "sg:tags":[
        "church"
    ],
    "wof:name":"Christian Science Church",
    "wof:placetype":"venue"
},
  "geometry": {"coordinates":[-119.789348,39.484955],"type":"Point"}
}