{
  "type": "Feature",
  "properties": {
    "iso:country":"US",
    "sg:address":"18132 Wedge Pkwy",
    "sg:city":"Reno",
    "sg:classifiers":[
        {
            "category":"Restaurant",
            "type":"Food & Drink"
        }
    ],
    "sg:phone":"+1 775 853 1998",
    "sg:postcode":"89511",
    "sg:province":"NV",
    "wof:name":"Chinese Village",
    "wof:placetype":"venue"
},
  "geometry": {"coordinates":[-119.76708000000001,39.395674],"type":"Point"}
}