{
  "type": "Feature",
  "properties": {
    "iso:country":"US",
    "sg:address":"618 Idaho St",
    "sg:city":"Elko",
    "sg:classifiers":[
        {
            "category":"Social Services",
            "type":"Services"
        }
    ],
    "sg:phone":"+1 775 738 2299",
    "sg:postcode":"89801",
    "sg:province":"NV",
    "wof:name":"Canyon View Counseling Center",
    "wof:placetype":"venue"
},
  "geometry": {"coordinates":[-115.761396,40.833992],"type":"Point"}
}