{
  "type": "Feature",
  "properties": {
    "iso:country":"US",
    "sg:address":"3351 N Buffalo Drive",
    "sg:city":"Las Vegas",
    "sg:classifiers":[
        {
            "category":"Building & Trades",
            "subcategory":"Construction",
            "type":"Services"
        }
    ],
    "sg:phone":"+1 702 395 5329",
    "sg:postcode":"89129",
    "sg:province":"NV",
    "sg:tags":[
        "contractor"
    ],
    "wof:name":"Don Herman Construction",
    "wof:placetype":"venue"
},
  "geometry": {"coordinates":[-115.260722,36.220752],"type":"Point"}
}