{
  "type": "Feature",
  "properties": {
    "iso:country":"US",
    "sg:address":"6655 W Sahara Ave",
    "sg:city":"Las Vegas",
    "sg:classifiers":[
        {
            "category":"Health Services",
            "subcategory":"Doctor",
            "type":"Services"
        }
    ],
    "sg:phone":"+1 702 876 5800",
    "sg:postcode":"89146",
    "sg:province":"NV",
    "sg:tags":[
        "dentist"
    ],
    "wof:name":"Las Vegas Endodontics",
    "wof:placetype":"venue"
},
  "geometry": {"coordinates":[-115.237294,36.144008],"type":"Point"}
}