{
  "type": "Feature",
  "properties": {
    "iso:country":"US",
    "sg:address":"7795 W Sahara Ave Ste 101",
    "sg:city":"Las Vegas",
    "sg:classifiers":[
        {
            "category":"Banks & Credit Unions",
            "subcategory":"Bank",
            "type":"Services"
        },
        {
            "category":"Banks & Credit Unions",
            "subcategory":"Financial Services",
            "type":"Services"
        }
    ],
    "sg:phone":"+1 702 731 6300",
    "sg:postcode":"89117",
    "sg:province":"NV",
    "sg:tags":[
        "broker",
        "mortgage"
    ],
    "sg:website":"www.paramountbanknv.com",
    "wof:name":"Paramount Bank",
    "wof:placetype":"venue"
},
  "geometry": {"coordinates":[-115.260727,36.143436],"type":"Point"}
}