{
  "type": "Feature",
  "properties": {
    "iso:country":"US",
    "sg:address":"195 Main St",
    "sg:city":"Austin",
    "sg:classifiers":[
        {
            "category":"Manufacturing",
            "subcategory":"Lumber",
            "type":"Manufacturing & Wholesale Goods"
        }
    ],
    "sg:phone":"+1 775 964 1305",
    "sg:postcode":"89317",
    "sg:province":"NV",
    "sg:tags":[
        "forester"
    ],
    "wof:name":"Us DA Forestry Svc",
    "wof:placetype":"venue"
},
  "geometry": {"coordinates":[-115.007778,38.858047],"type":"Point"}
}