{
  "type": "Feature",
  "properties": {
    "iso:country":"US",
    "sg:address":"3074 S Cottage Ln",
    "sg:city":"Sparks",
    "sg:classifiers":[
        {
            "category":"Retail",
            "subcategory":"Animal Services",
            "type":"Services"
        }
    ],
    "sg:phone":"+1 775 626 3969",
    "sg:postcode":"89434",
    "sg:province":"NV",
    "sg:tags":[
        "pet",
        "boarding",
        "sitting"
    ],
    "wof:name":"Pamper Your Pets",
    "wof:placetype":"venue"
},
  "geometry": {"coordinates":[-119.706912,39.559899],"type":"Point"}
}