{
  "type": "Feature",
  "properties": {
    "iso:country":"US",
    "sg:address":"2250 E Tropicana Avenue",
    "sg:city":"Las Vegas",
    "sg:classifiers":[
        {
            "category":"Personal",
            "subcategory":"Nail Salon",
            "type":"Services"
        }
    ],
    "sg:phone":"+1 702 319 6616",
    "sg:postcode":"89119",
    "sg:province":"NV",
    "wof:name":"Nails by Lisa & Jenny",
    "wof:placetype":"venue"
},
  "geometry": {"coordinates":[-115.120596,36.100225],"type":"Point"}
}