{
  "type": "Feature",
  "properties": {
    "iso:country":"US",
    "sg:address":"500 E Windmill Ln Ste 165",
    "sg:city":"Las Vegas",
    "sg:classifiers":[
        {
            "category":"Restaurant",
            "type":"Food & Drink"
        }
    ],
    "sg:phone":"+1 702 823 2779",
    "sg:postcode":"89148",
    "sg:province":"NV",
    "sg:tags":[
        "sushi",
        "bar",
        "japanese"
    ],
    "sg:website":"mikosushilasvegas.com",
    "wof:name":"Miko's Izakaya",
    "wof:placetype":"venue"
},
  "geometry": {"coordinates":[-115.152127,36.042882],"type":"Point"}
}