{
  "type": "Feature",
  "properties": {
    "iso:country":"US",
    "sg:address":"5000 Meadowood Mall Cir",
    "sg:city":"Reno",
    "sg:classifiers":[
        {
            "category":"Restaurant",
            "type":"Food & Drink"
        }
    ],
    "sg:menulink":"http://www.allmenus.com/nv/reno-southeast/236289-surf-city-squeeze/menu/",
    "sg:phone":"+1 775 825 6200",
    "sg:postcode":"89502",
    "sg:province":"NV",
    "sg:tags":[
        "smoothy",
        "juice",
        "american"
    ],
    "wof:name":"Surf City Squeeze",
    "wof:placetype":"venue"
},
  "geometry": {"coordinates":[-119.785201,39.471498],"type":"Point"}
}