{
  "type": "Feature",
  "properties": {
    "iso:country":"US",
    "sg:address":"1300 W Sunset Rd",
    "sg:city":"Henderson",
    "sg:classifiers":[
        {
            "category":"Shopping",
            "subcategory":"Optician",
            "type":"Retail Goods"
        }
    ],
    "sg:phone":"+1 702 436 4042",
    "sg:postcode":"89014",
    "sg:province":"NV",
    "sg:tags":[
        "eyewear"
    ],
    "sg:website":"www2.sunglasshut.com",
    "wof:name":"Sunglass Hut International",
    "wof:placetype":"venue"
},
  "geometry": {"coordinates":[-115.040001,36.063801],"type":"Point"}
}