{
  "type": "Feature",
  "properties": {
    "iso:country":"US",
    "sg:address":"7775 Tamra Dr",
    "sg:city":"Reno",
    "sg:classifiers":[
        {
            "category":"Building & Trades",
            "subcategory":"Cleaning & Sanitation",
            "type":"Services"
        }
    ],
    "sg:phone":"+1 775 677 9077",
    "sg:postcode":"89506",
    "sg:province":"NV",
    "sg:tags":[
        "janitor"
    ],
    "wof:name":"Hanks Cleaning Svc",
    "wof:placetype":"venue"
},
  "geometry": {"coordinates":[-119.82915800000001,39.624335],"type":"Point"}
}