{
  "type": "Feature",
  "properties": {
    "iso:country":"US",
    "sg:address":"55 Megan Dr",
    "sg:city":"Henderson",
    "sg:classifiers":[
        {
            "category":"Autos & Motor Vehicles",
            "subcategory":"Auto Supplies",
            "type":"Retail Goods"
        }
    ],
    "sg:phone":"+1 702 361 1833",
    "sg:postcode":"89074",
    "sg:province":"NV",
    "wof:name":"John C Tsitouras",
    "wof:placetype":"venue"
},
  "geometry": {"coordinates":[-115.105571,36.030965],"type":"Point"}
}