{
  "type": "Feature",
  "properties": {
    "iso:country":"US",
    "sg:address":"4820 Stillwater Ave",
    "sg:city":"Las Vegas",
    "sg:classifiers":[
        {
            "category":"Building & Trades",
            "subcategory":"Construction",
            "type":"Services"
        },
        {
            "category":"Building & Trades",
            "subcategory":"Landscaping Services",
            "type":"Services"
        }
    ],
    "sg:phone":"+1 702 319 8990",
    "sg:postcode":"89110",
    "sg:province":"NV",
    "sg:tags":[
        "concrete",
        "contractor"
    ],
    "wof:name":"Royal Flush Concrete Inc",
    "wof:placetype":"venue"
},
  "geometry": {"coordinates":[-115.067514,36.182824],"type":"Point"}
}