{
  "type": "Feature",
  "properties": {
    "iso:country":"US",
    "sg:address":"1983 Whitney Mesa Dr",
    "sg:city":"Henderson",
    "sg:classifiers":[
        {
            "category":"Shopping",
            "subcategory":"Computers & Home Electronics",
            "type":"Retail Goods"
        }
    ],
    "sg:phone":"+1 702 269 7000",
    "sg:postcode":"89014",
    "sg:province":"NV",
    "wof:name":"Global Computer Service",
    "wof:placetype":"venue"
},
  "geometry": {"coordinates":[-115.072228,36.078113],"type":"Point"}
}