{
  "type": "Feature",
  "properties": {
    "iso:country":"US",
    "sg:address":"3162 Dove Run Creek Dr",
    "sg:city":"Las Vegas",
    "sg:classifiers":[
        {
            "category":"Freight",
            "type":"Transportation"
        }
    ],
    "sg:phone":"+1 702 227 6860",
    "sg:postcode":"89135",
    "sg:province":"NV",
    "sg:tags":[
        "operator",
        "local",
        "trucking"
    ],
    "wof:name":"Diablo Trucking Inc",
    "wof:placetype":"venue"
},
  "geometry": {"coordinates":[-115.341505,36.129573],"type":"Point"}
}