{
  "type": "Feature",
  "properties": {
    "iso:country":"US",
    "sg:address":"923 Tahoe Blvd",
    "sg:city":"Incline Village",
    "sg:classifiers":[
        {
            "category":"Health Services",
            "subcategory":"Chiropractor",
            "type":"Services"
        }
    ],
    "sg:phone":"+1 775 831 5544",
    "sg:postcode":"89451",
    "sg:province":"NV",
    "wof:name":"Incline Chiropractic",
    "wof:placetype":"venue"
},
  "geometry": {"coordinates":[-119.95089900000001,39.249541],"type":"Point"}
}