{
  "type": "Feature",
  "properties": {
    "iso:country":"US",
    "sg:address":"869 Caughlin Glen",
    "sg:city":"Reno",
    "sg:classifiers":[
        {
            "category":"Professional",
            "subcategory":"Management & Consulting",
            "type":"Services"
        }
    ],
    "sg:phone":"+1 775 323 1518",
    "sg:postcode":"89509",
    "sg:province":"NV",
    "sg:tags":[
        "consultant",
        "business"
    ],
    "wof:name":"Karen L Hruby",
    "wof:placetype":"venue"
},
  "geometry": {"coordinates":[-119.859574,39.501768],"type":"Point"}
}