{
  "type": "Feature",
  "properties": {
    "iso:country":"US",
    "sg:address":"4813 Intrepid Dr",
    "sg:city":"Las Vegas",
    "sg:classifiers":[
        {
            "category":"Building & Trades",
            "subcategory":"Cleaning & Sanitation",
            "type":"Services"
        }
    ],
    "sg:phone":"+1 702 286 0892",
    "sg:postcode":"89130",
    "sg:province":"NV",
    "sg:tags":[
        "maintenance"
    ],
    "wof:name":"L & J Janitorial",
    "wof:placetype":"venue"
},
  "geometry": {"coordinates":[-115.208571,36.254413],"type":"Point"}
}