{
  "type": "Feature",
  "properties": {
    "iso:country":"US",
    "sg:address":"6465 Rey del Sierra Ct",
    "sg:city":"Sparks",
    "sg:classifiers":[
        {
            "category":"Building & Trades",
            "subcategory":"Construction",
            "type":"Services"
        }
    ],
    "sg:phone":"+1 775 424 1402",
    "sg:postcode":"89436",
    "sg:province":"NV",
    "sg:tags":[
        "contractor"
    ],
    "wof:name":"Bill Dickson Construction Svc",
    "wof:placetype":"venue"
},
  "geometry": {"coordinates":[-119.679383,39.611476],"type":"Point"}
}