{
  "type": "Feature",
  "properties": {
    "iso:country":"US",
    "sg:address":"7665 Commercial Way",
    "sg:city":"Henderson",
    "sg:classifiers":[
        {
            "category":"Building & Trades",
            "subcategory":"Landscaping Services",
            "type":"Services"
        }
    ],
    "sg:phone":"+1 702 566 5469",
    "sg:postcode":"89011",
    "sg:province":"NV",
    "sg:tags":[
        "lawn",
        "maintenance",
        "grounds"
    ],
    "sg:website":"www.trugreen.com",
    "wof:name":"Tru Green Chem Lawn",
    "wof:placetype":"venue"
},
  "geometry": {"coordinates":[-115.02421699999999,36.055116],"type":"Point"}
}