{
  "type": "Feature",
  "properties": {
    "iso:country":"US",
    "sg:address":"2001 S Jones Blvd",
    "sg:city":"Las Vegas",
    "sg:classifiers":[
        {
            "category":"Real Estate",
            "subcategory":"Real Estate Agent",
            "type":"Services"
        }
    ],
    "sg:phone":"+1 702 648 5667",
    "sg:postcode":"89146",
    "sg:province":"NV",
    "sg:tags":[
        "appraisal"
    ],
    "wof:name":"Ias",
    "wof:placetype":"venue"
},
  "geometry": {"coordinates":[-115.225651,36.151054],"type":"Point"}
}