{
  "type": "Feature",
  "properties": {
    "iso:country":"US",
    "sg:address":"242 Lemmon Dr",
    "sg:city":"Reno",
    "sg:classifiers":[
        {
            "category":"Banks & Credit Unions",
            "subcategory":"Bank",
            "type":"Services"
        }
    ],
    "sg:phone":"+1 775 677 4486",
    "sg:postcode":"89506",
    "sg:province":"NV",
    "sg:tags":[
        "loan"
    ],
    "wof:name":"Paycheck Advance",
    "wof:placetype":"venue"
},
  "geometry": {"coordinates":[-119.849364,39.613148],"type":"Point"}
}