{
  "type": "Feature",
  "properties": {
    "iso:country":"US",
    "sg:address":"7854 White Fir St",
    "sg:city":"Reno",
    "sg:classifiers":[
        {
            "category":"Manufacturing",
            "subcategory":"Rubber & Plastics",
            "type":"Manufacturing & Wholesale Goods"
        }
    ],
    "sg:phone":"+1 775 747 7006",
    "sg:postcode":"89523",
    "sg:province":"NV",
    "sg:tags":[
        "steel",
        "mold",
        "parts",
        "component",
        "mfg"
    ],
    "sg:website":"www.messengermolding.com",
    "wof:name":"Messenger Molding",
    "wof:placetype":"venue"
},
  "geometry": {"coordinates":[-119.896119,39.507435],"type":"Point"}
}