{
  "type": "Feature",
  "properties": {
    "iso:country":"US",
    "sg:address":"1560 N Eastern Ave",
    "sg:city":"Las Vegas",
    "sg:classifiers":[
        {
            "category":"Restaurant",
            "type":"Food & Drink"
        }
    ],
    "sg:phone":"+1 702 383 2904",
    "sg:postcode":"89101",
    "sg:province":"NV",
    "sg:tags":[
        "eating"
    ],
    "wof:name":"Angelinas Baby Clothes",
    "wof:placetype":"venue"
},
  "geometry": {"coordinates":[-115.11602600000001,36.187383],"type":"Point"}
}