{
  "type": "Feature",
  "properties": {
    "iso:country":"US",
    "sg:address":"601 E Charleston Blvd",
    "sg:city":"Las Vegas",
    "sg:classifiers":[
        {
            "category":"Professional",
            "subcategory":"Accounting & Tax Preparation",
            "type":"Services"
        }
    ],
    "sg:phone":"+1 702 385 7080",
    "sg:postcode":"89104",
    "sg:province":"NV",
    "sg:tags":[
        "accountant"
    ],
    "wof:name":"Meservy Dennis K CPA",
    "wof:placetype":"venue"
},
  "geometry": {"coordinates":[-115.14525999999999,36.159057],"type":"Point"}
}