{
  "type": "Feature",
  "properties": {
    "iso:country":"US",
    "sg:address":"9017 S Pecos Rd",
    "sg:city":"Henderson",
    "sg:classifiers":[
        {
            "category":"Banks & Credit Unions",
            "subcategory":"Investment Brokerage",
            "type":"Services"
        }
    ],
    "sg:phone":"+1 702 476 2110",
    "sg:postcode":"89074",
    "sg:province":"NV",
    "sg:tags":[
        "investing"
    ],
    "wof:name":"Walker Asset Management Assets",
    "wof:placetype":"venue"
},
  "geometry": {"coordinates":[-115.1008,36.025596],"type":"Point"}
}