{
  "type": "Feature",
  "properties": {
    "iso:country":"US",
    "sg:address":"710 N Division St",
    "sg:city":"Carson City",
    "sg:classifiers":[
        {
            "category":"Health Services",
            "subcategory":"Dentist",
            "type":"Services"
        }
    ],
    "sg:phone":"+1 775 882 4242",
    "sg:postcode":"89703",
    "sg:province":"NV",
    "wof:name":"McElhany Susan DMD",
    "wof:placetype":"venue"
},
  "geometry": {"coordinates":[-119.768997,39.168301],"type":"Point"}
}