{
  "type": "Feature",
  "properties": {
    "iso:country":"US",
    "sg:address":"2593 Hummingbird Hill Ave",
    "sg:city":"Henderson",
    "sg:classifiers":[
        {
            "category":"Manufacturing",
            "subcategory":"Lumber",
            "type":"Manufacturing & Wholesale Goods"
        }
    ],
    "sg:phone":"+1 702 263 9928",
    "sg:postcode":"89074",
    "sg:province":"NV",
    "sg:tags":[
        "logging"
    ],
    "wof:name":"Parke Logging Inc",
    "wof:placetype":"venue"
},
  "geometry": {"coordinates":[-115.1142,36.03065],"type":"Point"}
}