{
  "type": "Feature",
  "properties": {
    "iso:country":"US",
    "sg:address":"345 E Prater Way",
    "sg:city":"Sparks",
    "sg:classifiers":[
        {
            "category":"Autos & Motor Vehicles",
            "subcategory":"Auto Supplies",
            "type":"Retail Goods"
        },
        {
            "category":"Wholesale",
            "subcategory":"Auto Parts",
            "type":"Manufacturing & Wholesale Goods"
        }
    ],
    "sg:phone":"+1 775 331 7550",
    "sg:postcode":"89431",
    "sg:province":"NV",
    "sg:tags":[
        "body",
        "automobile",
        "truck",
        "equipment",
        "accessory"
    ],
    "sg:website":"http://www.oreillyauto.com?utm_source=yellowpages&utm_medium=iyp&utm_campaign=2569",
    "wof:name":"Kragen O'Reilly Auto Parts",
    "wof:placetype":"venue"
},
  "geometry": {"coordinates":[-119.738714,39.541908],"type":"Point"}
}