{
  "type": "Feature",
  "properties": {
    "iso:country":"US",
    "sg:address":"2955 N Mccarran Blvd",
    "sg:city":"Sparks",
    "sg:classifiers":[
        {
            "category":"Restaurant",
            "type":"Food & Drink"
        }
    ],
    "sg:menulink":"http://www.allmenus.com/nv/sparks/162818-port-of-subs/menu/",
    "sg:phone":"+1 775 331 5555",
    "sg:postcode":"89431",
    "sg:province":"NV",
    "sg:tags":[
        "wrap",
        "american",
        "sandwich"
    ],
    "wof:name":"Port of Subs",
    "wof:placetype":"venue"
},
  "geometry": {"coordinates":[-119.755083,39.555272],"type":"Point"}
}