{
  "type": "Feature",
  "properties": {
    "iso:country":"US",
    "sg:address":"1855 Mc Cloud Ave",
    "sg:city":"Reno",
    "sg:classifiers":[
        {
            "category":"Retail",
            "subcategory":"Repair Shop",
            "type":"Services"
        }
    ],
    "sg:phone":"+1 775 322 9474",
    "sg:postcode":"89512",
    "sg:province":"NV",
    "sg:tags":[
        "upholsterer"
    ],
    "wof:name":"Atlas Custom Upholstery",
    "wof:placetype":"venue"
},
  "geometry": {"coordinates":[-119.79091099999999,39.547172],"type":"Point"}
}