{
  "type": "Feature",
  "properties": {
    "iso:country":"US",
    "sg:address":"490 Valley Rd",
    "sg:city":"Reno",
    "sg:classifiers":[
        {
            "category":"Freight",
            "type":"Transportation"
        },
        {
            "category":"Wholesale",
            "subcategory":"Scrap",
            "type":"Manufacturing & Wholesale Goods"
        }
    ],
    "sg:phone":"+1 775 331 2267",
    "sg:postcode":"89512",
    "sg:province":"NV",
    "sg:tags":[
        "solid",
        "waste",
        "center",
        "recycling",
        "collection"
    ],
    "sg:website":"www.swrsscrapmetal.com",
    "wof:name":"Solid Waste Reduction Services",
    "wof:placetype":"venue"
},
  "geometry": {"coordinates":[-119.807593,39.531278],"type":"Point"}
}