{
  "type": "Feature",
  "properties": {
    "iso:country":"US",
    "sg:address":"375 N Stephanie St",
    "sg:city":"Henderson",
    "sg:classifiers":[
        {
            "category":"Banks & Credit Unions",
            "subcategory":"Financial Services",
            "type":"Services"
        }
    ],
    "sg:phone":"+1 702 732 7777",
    "sg:postcode":"89014",
    "sg:province":"NV",
    "sg:tags":[
        "broker",
        "mortgage"
    ],
    "wof:name":"Nevada Mortgage",
    "wof:placetype":"venue"
},
  "geometry": {"coordinates":[-115.045998,36.054199],"type":"Point"}
}