{
  "type": "Feature",
  "properties": {
    "iso:country":"US",
    "sg:address":"5232 Shadow Valley St",
    "sg:city":"Las Vegas",
    "sg:classifiers":[
        {
            "category":"Ice Cream",
            "type":"Food & Drink"
        }
    ],
    "sg:menulink":"http://www.allmenus.com/nv/las-vegas/224870-dels-frozen-lemonade/menu/",
    "sg:postcode":"89148",
    "sg:province":"NV",
    "sg:tags":[
        "smoothy",
        "juice",
        "american"
    ],
    "wof:name":"Del's Frozen Lemonade",
    "wof:placetype":"venue"
},
  "geometry": {"coordinates":[-115.307761,36.093935],"type":"Point"}
}