{
  "type": "Feature",
  "properties": {
    "iso:country":"US",
    "sg:address":"6022 Smoke Ranch Rd",
    "sg:city":"Las Vegas",
    "sg:classifiers":[
        {
            "category":"Shopping",
            "subcategory":"Computers & Home Electronics",
            "type":"Retail Goods"
        }
    ],
    "sg:phone":"+1 702 638 2200",
    "sg:postcode":"89108",
    "sg:province":"NV",
    "sg:tags":[
        "software"
    ],
    "sg:website":"www.specsoft1.com",
    "wof:name":"Software Leader LLC",
    "wof:placetype":"venue"
},
  "geometry": {"coordinates":[-115.225085,36.203166],"type":"Point"}
}