{
  "type": "Feature",
  "properties": {
    "iso:country":"US",
    "sg:address":"3580 W Moberly Ave",
    "sg:city":"Las Vegas",
    "sg:classifiers":[
        {
            "category":"Real Estate",
            "subcategory":"Real Estate Agent",
            "type":"Services"
        }
    ],
    "sg:phone":"+1 702 433 9800",
    "sg:postcode":"89139",
    "sg:province":"NV",
    "wof:name":"Jack Diamond Real Estate",
    "wof:placetype":"venue"
},
  "geometry": {"coordinates":[-115.18608999999999,36.048158],"type":"Point"}
}