{
  "type": "Feature",
  "properties": {
    "iso:country":"US",
    "sg:address":"4921 W Sahara Ave",
    "sg:city":"Las Vegas",
    "sg:classifiers":[
        {
            "category":"Shopping",
            "subcategory":"Computers & Home Electronics",
            "type":"Retail Goods"
        }
    ],
    "sg:phone":"+1 702 944 6835",
    "sg:postcode":"89146",
    "sg:province":"NV",
    "wof:name":"Computer Attic Plus",
    "wof:placetype":"venue"
},
  "geometry": {"coordinates":[-115.204507,36.144503],"type":"Point"}
}