{
  "type": "Feature",
  "properties": {
    "iso:country":"US",
    "sg:address":"5833 Silver Heights St",
    "sg:city":"Las Vegas",
    "sg:classifiers":[
        {
            "category":"Building & Trades",
            "subcategory":"Construction",
            "type":"Services"
        }
    ],
    "sg:phone":"+1 702 286 6095",
    "sg:postcode":"89130",
    "sg:province":"NV",
    "sg:tags":[
        "contractor"
    ],
    "wof:name":"Solar Fx",
    "wof:placetype":"venue"
},
  "geometry": {"coordinates":[-115.253533,36.268885],"type":"Point"}
}