{
  "type": "Feature",
  "properties": {
    "iso:country":"US",
    "sg:address":"10312 Carolina Hills Ave",
    "sg:city":"Las Vegas",
    "sg:classifiers":[
        {
            "category":"Real Estate",
            "subcategory":"Real Estate Agent",
            "type":"Services"
        }
    ],
    "sg:phone":"+1 702 384 5210",
    "sg:postcode":"89144",
    "sg:province":"NV",
    "wof:name":"Keller Williams Realtors",
    "wof:placetype":"venue"
},
  "geometry": {"coordinates":[-115.323166,36.186242],"type":"Point"}
}