{
  "type": "Feature",
  "properties": {
    "iso:country":"US",
    "sg:address":"7175 W Lake Mead Blvd",
    "sg:city":"Las Vegas",
    "sg:classifiers":[
        {
            "category":"Restaurant",
            "type":"Food & Drink"
        }
    ],
    "sg:phone":"+1 702 459 7300",
    "sg:postcode":"89128",
    "sg:province":"NV",
    "sg:tags":[
        "japanese"
    ],
    "wof:name":"Yogis Teriyaki House",
    "wof:placetype":"venue"
},
  "geometry": {"coordinates":[-115.24925399999999,36.19585],"type":"Point"}
}