{
  "type": "Feature",
  "properties": {
    "iso:country":"US",
    "sg:address":"6530 N Buffalo Drive",
    "sg:city":"Las Vegas",
    "sg:classifiers":[
        {
            "category":"Restaurant",
            "type":"Food & Drink"
        }
    ],
    "sg:phone":"+1 702 658 9582",
    "sg:postcode":"89131",
    "sg:province":"NV",
    "sg:tags":[
        "pizza"
    ],
    "wof:name":"Foxes Pizza Den",
    "wof:placetype":"venue"
},
  "geometry": {"coordinates":[-115.233065,36.303196],"type":"Point"}
}