{
  "type": "Feature",
  "properties": {
    "iso:country":"US",
    "sg:address":"6220 Peggotty Ave",
    "sg:city":"Las Vegas",
    "sg:classifiers":[
        {
            "category":"Building & Trades",
            "subcategory":"Construction",
            "type":"Services"
        }
    ],
    "sg:phone":"+1 702 396 9318",
    "sg:postcode":"89130",
    "sg:province":"NV",
    "sg:tags":[
        "home",
        "builder"
    ],
    "wof:name":"Us Home Corp",
    "wof:placetype":"venue"
},
  "geometry": {"coordinates":[-115.23287999999999,36.274284],"type":"Point"}
}