{
  "type": "Feature",
  "properties": {
    "iso:country":"US",
    "sg:address":"4650 Grass Valley Rd",
    "sg:city":"Winnemucca",
    "sg:classifiers":[
        {
            "category":"Manufacturing",
            "subcategory":"Glass & Minerals",
            "type":"Manufacturing & Wholesale Goods"
        }
    ],
    "sg:phone":"+1 775 623 5577",
    "sg:postcode":"89445",
    "sg:province":"NV",
    "sg:tags":[
        "ready"
    ],
    "wof:name":"Kenner Concrete",
    "wof:placetype":"venue"
},
  "geometry": {"coordinates":[-117.744231,40.950057],"type":"Point"}
}