{
  "type": "Feature",
  "properties": {
    "iso:country":"US",
    "sg:address":"70 Linden St",
    "sg:city":"Reno",
    "sg:classifiers":[
        {
            "category":"Organizations",
            "subcategory":"Religious Organization",
            "type":"Services"
        }
    ],
    "sg:phone":"+1 775 828 5412",
    "sg:postcode":"89502",
    "sg:province":"NV",
    "sg:tags":[
        "church"
    ],
    "wof:name":"Assemblea Apostolica",
    "wof:placetype":"venue"
},
  "geometry": {"coordinates":[-119.797352,39.499893],"type":"Point"}
}