{
  "type": "Feature",
  "properties": {
    "iso:country":"US",
    "sg:address":"1548 E Charleston Blvd",
    "sg:city":"Las Vegas",
    "sg:classifiers":[
        {
            "category":"Organizations",
            "subcategory":"Community Association",
            "type":"Services"
        }
    ],
    "sg:phone":"+1 702 384 8387",
    "sg:postcode":"89104",
    "sg:province":"NV",
    "sg:tags":[
        "vintage",
        "used",
        "consignment"
    ],
    "wof:name":"Vietnam Veterans of America",
    "wof:placetype":"venue"
},
  "geometry": {"coordinates":[-115.13200399999999,36.158798],"type":"Point"}
}