{
  "type": "Feature",
  "properties": {
    "iso:country":"US",
    "sg:address":"2315 N Decatur Boulevard",
    "sg:city":"Las Vegas",
    "sg:classifiers":[
        {
            "category":"Retail",
            "subcategory":"Veterinary Services",
            "type":"Services"
        }
    ],
    "sg:phone":"+1 702 647 6234",
    "sg:postcode":"89108",
    "sg:province":"NV",
    "sg:tags":[
        "veterinarian"
    ],
    "wof:name":"Huff Gerald K DVM",
    "wof:placetype":"venue"
},
  "geometry": {"coordinates":[-115.205962,36.200936],"type":"Point"}
}