{
  "type": "Feature",
  "properties": {
    "iso:country":"US",
    "sg:address":"3065 Achilles Dr",
    "sg:city":"Reno",
    "sg:classifiers":[
        {
            "category":"Health Services",
            "subcategory":"Clinic",
            "type":"Services"
        }
    ],
    "sg:phone":"+1 775 324 7918",
    "sg:postcode":"89512",
    "sg:province":"NV",
    "sg:tags":[
        "home",
        "care"
    ],
    "wof:name":"Del's Loving Home Care",
    "wof:placetype":"venue"
},
  "geometry": {"coordinates":[-119.81283999999999,39.554208],"type":"Point"}
}