{
  "type": "Feature",
  "properties": {
    "iso:country":"US",
    "sg:address":"135 E 2nd St",
    "sg:city":"Battle Mountain",
    "sg:classifiers":[
        {
            "category":"Government",
            "subcategory":"Office",
            "type":"Public Place"
        }
    ],
    "sg:phone":"+1 775 635 5959",
    "sg:postcode":"89820",
    "sg:province":"NV",
    "sg:tags":[
        "family"
    ],
    "wof:name":"Lander County Wic Program",
    "wof:placetype":"venue"
},
  "geometry": {"coordinates":[-116.934275,40.640552],"type":"Point"}
}