{
  "type": "Feature",
  "properties": {
    "iso:country":"US",
    "sg:address":"5795 Tannerwood Dr",
    "sg:city":"Reno",
    "sg:classifiers":[
        {
            "category":"Professional",
            "subcategory":"Advertising",
            "type":"Services"
        }
    ],
    "sg:phone":"+1 775 849 9216",
    "sg:postcode":"89511",
    "sg:province":"NV",
    "sg:tags":[
        "counselor"
    ],
    "wof:name":"Davis Rounds Advertising",
    "wof:placetype":"venue"
},
  "geometry": {"coordinates":[-119.82455,39.372385],"type":"Point"}
}