{
  "type": "Feature",
  "properties": {
    "iso:country":"US",
    "sg:address":"490 N Lake St",
    "sg:city":"Reno",
    "sg:classifiers":[
        {
            "category":"Travel",
            "subcategory":"Hotels & Motels",
            "type":"Entertainment"
        }
    ],
    "sg:phone":"+1 775 786 5968",
    "sg:postcode":"89501",
    "sg:province":"NV",
    "wof:name":"Horseshoe Motel",
    "wof:placetype":"venue"
},
  "geometry": {"coordinates":[-119.812007,39.531686],"type":"Point"}
}