{
  "type": "Feature",
  "properties": {
    "iso:country":"US",
    "sg:address":"3687 Kings Row",
    "sg:city":"Reno",
    "sg:classifiers":[
        {
            "category":"Shopping",
            "subcategory":"Discount & Variety Stores",
            "type":"Retail Goods"
        }
    ],
    "sg:phone":"+1 775 746 4300",
    "sg:postcode":"89503",
    "sg:province":"NV",
    "wof:name":"Kalesa International & Variety",
    "wof:placetype":"venue"
},
  "geometry": {"coordinates":[-119.856692,39.542304],"type":"Point"}
}