{
  "type": "Feature",
  "properties": {
    "iso:country":"US",
    "sg:address":"4950 S Valley View Blvd",
    "sg:city":"Las Vegas",
    "sg:classifiers":[
        {
            "category":"Professional",
            "subcategory":"Engineering",
            "type":"Services"
        }
    ],
    "sg:phone":"+1 702 736 7677",
    "sg:postcode":"89118",
    "sg:province":"NV",
    "sg:tags":[
        "engineer"
    ],
    "wof:name":"Roush Industries",
    "wof:placetype":"venue"
},
  "geometry": {"coordinates":[-115.189751,36.099439],"type":"Point"}
}