{
  "type": "Feature",
  "properties": {
    "iso:country":"US",
    "sg:address":"1805 E Tropicana Avenue",
    "sg:city":"Las Vegas",
    "sg:classifiers":[
        {
            "category":"Food & Beverages",
            "subcategory":"Groceries & Convenience Stores",
            "type":"Retail Goods"
        }
    ],
    "sg:phone":"+1 702 736 1444",
    "sg:postcode":"89119",
    "sg:province":"NV",
    "sg:website":"www.7-eleven.com",
    "wof:name":"7-Eleven",
    "wof:placetype":"venue"
},
  "geometry": {"coordinates":[-115.12735000000001,36.100942],"type":"Point"}
}