{
  "type": "Feature",
  "properties": {
    "iso:country":"US",
    "sg:address":"1815 Westwind Rd",
    "sg:city":"Las Vegas",
    "sg:classifiers":[
        {
            "category":"Organizations",
            "subcategory":"Membership Organization",
            "type":"Services"
        }
    ],
    "sg:phone":"+1 702 870 3042",
    "sg:postcode":"89146",
    "sg:province":"NV",
    "wof:name":"National Society of Sons",
    "wof:placetype":"venue"
},
  "geometry": {"coordinates":[-115.219077,36.150049],"type":"Point"}
}