{
  "type": "Feature",
  "properties": {
    "iso:country":"US",
    "sg:address":"218 Incline Ct",
    "sg:city":"Incline Village",
    "sg:classifiers":[
        {
            "category":"Utilities",
            "subcategory":"Natural Gas",
            "type":"Services"
        }
    ],
    "sg:phone":"+1 775 831 7436",
    "sg:postcode":"89451",
    "sg:province":"NV",
    "sg:tags":[
        "company"
    ],
    "wof:name":"Southwest Gas Corp",
    "wof:placetype":"venue"
},
  "geometry": {"coordinates":[-119.950452,39.247946],"type":"Point"}
}