{
  "type": "Feature",
  "properties": {
    "iso:country":"US",
    "sg:address":"1021 Miradero Ln",
    "sg:city":"Las Vegas",
    "sg:classifiers":[
        {
            "category":"Organizations",
            "subcategory":"Religious Organization",
            "type":"Services"
        }
    ],
    "sg:phone":"+1 702 838 0051",
    "sg:postcode":"89134",
    "sg:province":"NV",
    "wof:name":"Santa Vida Ministries",
    "wof:placetype":"venue"
},
  "geometry": {"coordinates":[-115.29964200000001,36.183329],"type":"Point"}
}