{
  "type": "Feature",
  "properties": {
    "iso:country":"US",
    "sg:address":"61 W Mesquite Blvd",
    "sg:city":"Mesquite",
    "sg:classifiers":[
        {
            "category":"Utilities",
            "subcategory":"Telephone",
            "type":"Services"
        }
    ],
    "sg:phone":"+1 702 346 5211",
    "sg:postcode":"89027",
    "sg:province":"NV",
    "sg:tags":[
        "company"
    ],
    "sg:website":"www.rioaccess.net",
    "wof:name":"Rio Virgin Telephone Co",
    "wof:placetype":"venue"
},
  "geometry": {"coordinates":[-114.068907,36.804081],"type":"Point"}
}