{
  "type": "Feature",
  "properties": {
    "iso:country":"US",
    "sg:address":"1200 Mountain St",
    "sg:city":"Carson City",
    "sg:classifiers":[
        {
            "category":"Health Services",
            "subcategory":"Doctor",
            "type":"Services"
        }
    ],
    "sg:phone":"+1 775 885 2229",
    "sg:postcode":"89703",
    "sg:province":"NV",
    "wof:name":"Toth Joseph K MD",
    "wof:placetype":"venue"
},
  "geometry": {"coordinates":[-119.773003,39.170898],"type":"Point"}
}