{
  "type": "Feature",
  "properties": {
    "iso:country":"US",
    "sg:address":"3290 S Highland Dr",
    "sg:city":"Las Vegas",
    "sg:classifiers":[
        {
            "category":"Wholesale",
            "subcategory":"Furniture",
            "type":"Manufacturing & Wholesale Goods"
        }
    ],
    "sg:phone":"+1 702 737 2078",
    "sg:postcode":"89109",
    "sg:province":"NV",
    "sg:tags":[
        "retail",
        "used",
        "merchandise",
        "f"
    ],
    "wof:name":"Hotel Furniture Liquidators",
    "wof:placetype":"venue"
},
  "geometry": {"coordinates":[-115.177278,36.130791],"type":"Point"}
}