{
  "type": "Feature",
  "properties": {
    "iso:country":"US",
    "sg:address":"2580 Sorrel St",
    "sg:city":"Las Vegas",
    "sg:classifiers":[
        {
            "category":"Professional",
            "subcategory":"Accounting & Tax Preparation",
            "type":"Services"
        }
    ],
    "sg:phone":"+1 702 838 7298",
    "sg:postcode":"89146",
    "sg:province":"NV",
    "sg:tags":[
        "accountant"
    ],
    "wof:name":"Ira W Bradshaw CPA",
    "wof:placetype":"venue"
},
  "geometry": {"coordinates":[-115.23604,36.143742],"type":"Point"}
}