{
  "type": "Feature",
  "properties": {
    "iso:country":"US",
    "sg:address":"7781 W Tropical Parkway",
    "sg:city":"Las Vegas",
    "sg:classifiers":[
        {
            "category":"Home & Garden",
            "subcategory":"Household Appliances",
            "type":"Retail Goods"
        }
    ],
    "sg:phone":"+1 702 839 5417",
    "sg:postcode":"89149",
    "sg:province":"NV",
    "sg:website":"www.circuitcity.com",
    "wof:name":"Circuit City Appliance & Electronics",
    "wof:placetype":"venue"
},
  "geometry": {"coordinates":[-115.26559399999999,36.271038],"type":"Point"}
}