{
  "type": "Feature",
  "properties": {
    "iso:country":"US",
    "sg:address":"1263 S Stewart St",
    "sg:city":"Carson City",
    "sg:classifiers":[
        {
            "category":"Government",
            "subcategory":"Office",
            "type":"Public Place"
        }
    ],
    "sg:phone":"+1 775 888 7446",
    "sg:postcode":"89701",
    "sg:province":"NV",
    "sg:tags":[
        "department",
        "transportation",
        "for"
    ],
    "wof:name":"Research",
    "wof:placetype":"venue"
},
  "geometry": {"coordinates":[-119.76482,39.155393],"type":"Point"}
}