{
  "type": "Feature",
  "properties": {
    "iso:country":"US",
    "sg:address":"2755 Mountain City Hwy",
    "sg:city":"Elko",
    "sg:classifiers":[
        {
            "category":"Home & Garden",
            "subcategory":"Hardware",
            "type":"Retail Goods"
        },
        {
            "category":"Home & Garden",
            "subcategory":"Building Materials",
            "type":"Retail Goods"
        }
    ],
    "sg:phone":"+1 775 738 8454",
    "sg:postcode":"89801",
    "sg:province":"NV",
    "sg:tags":[
        "lumber"
    ],
    "wof:name":"Builders Mart Inc",
    "wof:placetype":"venue"
},
  "geometry": {"coordinates":[-115.793086,40.839012],"type":"Point"}
}