{
  "type": "Feature",
  "properties": {
    "iso:country":"US",
    "sg:address":"4090 S McCarran Blvd",
    "sg:city":"Reno",
    "sg:classifiers":[
        {
            "category":"Professional",
            "subcategory":"Advertising",
            "type":"Services"
        }
    ],
    "sg:phone":"+1 775 829 0652",
    "sg:postcode":"89502",
    "sg:province":"NV",
    "sg:tags":[
        "mailing",
        "shipping"
    ],
    "wof:name":"Mail Stop",
    "wof:placetype":"venue"
},
  "geometry": {"coordinates":[-119.763965,39.476788],"type":"Point"}
}