{
  "type": "Feature",
  "properties": {
    "iso:country":"US",
    "sg:address":"1147 Las Vegas Blvd S",
    "sg:city":"Las Vegas",
    "sg:classifiers":[
        {
            "category":"Animal Shelter",
            "type":"Public Place"
        }
    ],
    "sg:phone":"+1 702 727 3775",
    "sg:postcode":"89104",
    "sg:province":"NV",
    "sg:tags":[
        "adult"
    ],
    "wof:name":"Adult Superstore",
    "wof:placetype":"venue"
},
  "geometry": {"coordinates":[-115.148286,36.157395],"type":"Point"}
}