{
  "type": "Feature",
  "properties": {
    "iso:country":"US",
    "sg:address":"5860 S Pecos Rd",
    "sg:city":"Las Vegas",
    "sg:classifiers":[
        {
            "category":"Utilities",
            "subcategory":"Fuel Oil & Lpg",
            "type":"Services"
        }
    ],
    "sg:phone":"+1 702 592 4857",
    "sg:postcode":"89120",
    "sg:province":"NV",
    "sg:tags":[
        "dealer"
    ],
    "wof:name":"Northwind Firewood Tree S",
    "wof:placetype":"venue"
},
  "geometry": {"coordinates":[-115.10086800000001,36.084097],"type":"Point"}
}