{
  "type": "Feature",
  "properties": {
    "iso:country":"US",
    "sg:address":"210 Chiquis Ct",
    "sg:city":"Henderson",
    "sg:classifiers":[
        {
            "category":"Building & Trades",
            "subcategory":"Landscaping Services",
            "type":"Services"
        }
    ],
    "sg:phone":"+1 702 450 9321",
    "sg:postcode":"89074",
    "sg:province":"NV",
    "sg:tags":[
        "lawn",
        "maintenance",
        "grounds"
    ],
    "wof:name":"O'Hana Yard Svc & Gardening",
    "wof:placetype":"venue"
},
  "geometry": {"coordinates":[-115.06289599999999,36.043163],"type":"Point"}
}