{
  "type": "Feature",
  "properties": {
    "iso:country":"US",
    "sg:address":"460 Plumb Ln",
    "sg:city":"Reno",
    "sg:classifiers":[
        {
            "category":"Building & Trades",
            "subcategory":"Plumbing",
            "type":"Services"
        }
    ],
    "sg:phone":"+1 775 786 7586",
    "sg:postcode":"89502",
    "sg:province":"NV",
    "sg:tags":[
        "plumbing",
        "contractor"
    ],
    "wof:name":"A Plumberman",
    "wof:placetype":"venue"
},
  "geometry": {"coordinates":[-119.797124,39.505732],"type":"Point"}
}