{
  "type": "Feature",
  "properties": {
    "iso:country":"US",
    "sg:address":"6199 Valley Wood Dr",
    "sg:city":"Reno",
    "sg:classifiers":[
        {
            "category":"Building & Trades",
            "subcategory":"Construction",
            "type":"Services"
        }
    ],
    "sg:phone":"+1 775 747 7271",
    "sg:postcode":"89523",
    "sg:province":"NV",
    "sg:tags":[
        "engineering",
        "general"
    ],
    "wof:name":"Reno Tahoe Construction Inc",
    "wof:placetype":"venue"
},
  "geometry": {"coordinates":[-119.88506099999999,39.529754],"type":"Point"}
}