{
  "type": "Feature",
  "properties": {
    "iso:country":"US",
    "sg:address":"1521 Ruby Cliffs Ln",
    "sg:city":"Las Vegas",
    "sg:classifiers":[
        {
            "category":"Professional",
            "subcategory":"Management & Consulting",
            "type":"Services"
        }
    ],
    "sg:phone":"+1 702 228 3708",
    "sg:postcode":"89144",
    "sg:province":"NV",
    "wof:name":"C A & M Marketing",
    "wof:placetype":"venue"
},
  "geometry": {"coordinates":[-115.317547,36.188416],"type":"Point"}
}