{
  "type": "Feature",
  "properties": {
    "iso:country":"US",
    "sg:address":"2920 E Serene Ave",
    "sg:city":"Henderson",
    "sg:classifiers":[
        {
            "category":"Building & Trades",
            "subcategory":"Construction",
            "type":"Services"
        }
    ],
    "sg:phone":"+1 702 897 3865",
    "sg:postcode":"89074",
    "sg:province":"NV",
    "sg:tags":[
        "dry wall",
        "contractor"
    ],
    "wof:name":"Patch Co Inc",
    "wof:placetype":"venue"
},
  "geometry": {"coordinates":[-115.111797,36.020535],"type":"Point"}
}