{
  "type": "Feature",
  "properties": {
    "iso:country":"US",
    "sg:address":"1022 Silveranch Dr",
    "sg:city":"Gardnerville",
    "sg:classifiers":[
        {
            "category":"Shopping",
            "subcategory":"Florist",
            "type":"Retail Goods"
        }
    ],
    "sg:phone":"+1 775 265 0010",
    "sg:postcode":"89460",
    "sg:province":"NV",
    "wof:name":"Court House Of Flowers",
    "wof:placetype":"venue"
},
  "geometry": {"coordinates":[-119.74718900000001,38.911289],"type":"Point"}
}