{
  "type": "Feature",
  "properties": {
    "iso:country":"US",
    "sg:address":"4130 S Sandhill Rd Ste A15",
    "sg:city":"Las Vegas",
    "sg:classifiers":[
        {
            "category":"Manufacturing",
            "subcategory":"Leather Goods",
            "type":"Manufacturing & Wholesale Goods"
        }
    ],
    "sg:phone":"+1 702 221 4172",
    "sg:postcode":"89121",
    "sg:province":"NV",
    "sg:website":"www.tandyleatherfactory.com",
    "wof:name":"Tandy Leather Factory",
    "wof:placetype":"venue"
},
  "geometry": {"coordinates":[-115.091865,36.114288],"type":"Point"}
}