{
  "type": "Feature",
  "properties": {
    "iso:country":"US",
    "sg:address":"42 E Freeport Blvd",
    "sg:city":"Sparks",
    "sg:classifiers":[
        {
            "category":"Home & Garden",
            "subcategory":"Mobile Homes",
            "type":"Retail Goods"
        }
    ],
    "sg:phone":"+1 775 355 7592",
    "sg:postcode":"89431",
    "sg:province":"NV",
    "sg:tags":[
        "parts"
    ],
    "wof:name":"AAA Supply",
    "wof:placetype":"venue"
},
  "geometry": {"coordinates":[-119.741664,39.525632],"type":"Point"}
}