{
  "type": "Feature",
  "properties": {
    "iso:country":"US",
    "sg:address":"6125 Edna Ave",
    "sg:city":"Las Vegas",
    "sg:classifiers":[
        {
            "category":"Communications",
            "subcategory":"Film & Video Production",
            "type":"Services"
        }
    ],
    "sg:phone":"+1 702 388 8800",
    "sg:postcode":"89146",
    "sg:province":"NV",
    "sg:tags":[
        "tv"
    ],
    "wof:name":"Atlantic Syndication Network",
    "wof:placetype":"venue"
},
  "geometry": {"coordinates":[-115.226783,36.136611],"type":"Point"}
}