{
  "type": "Feature",
  "properties": {
    "iso:country":"US",
    "sg:address":"5022 Schumann Dr",
    "sg:city":"Las Vegas",
    "sg:classifiers":[
        {
            "category":"Wholesale",
            "subcategory":"Durable Goods & Equipment",
            "type":"Manufacturing & Wholesale Goods"
        }
    ],
    "sg:phone":"+1 702 368 4120",
    "sg:postcode":"89146",
    "sg:province":"NV",
    "sg:tags":[
        "importer"
    ],
    "wof:name":"Savedra Import Export",
    "wof:placetype":"venue"
},
  "geometry": {"coordinates":[-115.209224,36.132726],"type":"Point"}
}