{
  "type": "Feature",
  "properties": {
    "iso:country":"US",
    "sg:address":"11090 Boulder Glen Way",
    "sg:city":"Reno",
    "sg:classifiers":[
        {
            "category":"Professional",
            "subcategory":"Management & Consulting",
            "type":"Services"
        }
    ],
    "sg:phone":"+1 775 828 7323",
    "sg:postcode":"89511",
    "sg:province":"NV",
    "sg:tags":[
        "consultant",
        "business"
    ],
    "wof:name":"Jorge Barba",
    "wof:placetype":"venue"
},
  "geometry": {"coordinates":[-119.788035,39.425931],"type":"Point"}
}