{
  "type": "Feature",
  "properties": {
    "iso:country":"US",
    "sg:address":"3020 S Carson St",
    "sg:city":"Carson City",
    "sg:classifiers":[
        {
            "category":"Autos & Motor Vehicles",
            "subcategory":"Auto Supplies",
            "type":"Retail Goods"
        },
        {
            "category":"Wholesale",
            "subcategory":"Auto Parts",
            "type":"Manufacturing & Wholesale Goods"
        }
    ],
    "sg:phone":"+1 775 841 0161",
    "sg:postcode":"89701",
    "sg:province":"NV",
    "sg:tags":[
        "automotive",
        "tire",
        "repair"
    ],
    "sg:website":"www.lesschwab.com",
    "wof:name":"Les Schwab Tire Centers",
    "wof:placetype":"venue"
},
  "geometry": {"coordinates":[-119.768997,39.1399],"type":"Point"}
}