{
  "type": "Feature",
  "properties": {
    "iso:country":"US",
    "sg:address":"4691 S Valley View Blvd",
    "sg:city":"Las Vegas",
    "sg:classifiers":[
        {
            "category":"Manufacturing",
            "subcategory":"Motor Vehicles & Parts",
            "type":"Manufacturing & Wholesale Goods"
        }
    ],
    "sg:phone":"+1 702 597 5172",
    "sg:postcode":"89103",
    "sg:province":"NV",
    "sg:tags":[
        "trim",
        "auto",
        "mfg",
        "body",
        "supply"
    ],
    "wof:name":"Vegas Dash",
    "wof:placetype":"venue"
},
  "geometry": {"coordinates":[-115.189889,36.106417],"type":"Point"}
}