{
  "type": "Feature",
  "properties": {
    "iso:country":"US",
    "sg:address":"9408 Canyon Meadows Dr",
    "sg:city":"Reno",
    "sg:classifiers":[
        {
            "category":"Building & Trades",
            "subcategory":"Construction",
            "type":"Services"
        }
    ],
    "sg:phone":"+1 775 745 2884",
    "sg:postcode":"89506",
    "sg:province":"NV",
    "sg:tags":[
        "painter"
    ],
    "wof:name":"Anthony's Express Painting Co",
    "wof:placetype":"venue"
},
  "geometry": {"coordinates":[-119.8735,39.626503],"type":"Point"}
}