{
  "type": "Feature",
  "properties": {
    "iso:country":"US",
    "sg:address":"150 N Center St",
    "sg:city":"Reno",
    "sg:classifiers":[
        {
            "category":"Personal",
            "subcategory":"Adult",
            "type":"Services"
        }
    ],
    "sg:phone":"+1 775 323 1998",
    "sg:postcode":"89501",
    "sg:province":"NV",
    "sg:tags":[
        "escort"
    ],
    "wof:name":"Obsesion",
    "wof:placetype":"venue"
},
  "geometry": {"coordinates":[-119.811775,39.526704],"type":"Point"}
}