{
  "type": "Feature",
  "properties": {
    "iso:country":"US",
    "sg:address":"2952 Meade Ave",
    "sg:city":"Las Vegas",
    "sg:classifiers":[
        {
            "category":"Health Services",
            "subcategory":"Doctor",
            "type":"Services"
        }
    ],
    "sg:phone":"+1 702 384 1601",
    "sg:postcode":"89102",
    "sg:province":"NV",
    "sg:tags":[
        "physician",
        "surgeon"
    ],
    "wof:name":"Josephine M Daluga MD",
    "wof:placetype":"venue"
},
  "geometry": {"coordinates":[-115.180447,36.13634],"type":"Point"}
}