{
  "type": "Feature",
  "properties": {
    "iso:country":"US",
    "sg:address":"5680 Simmons St",
    "sg:city":"North Las Vegas",
    "sg:classifiers":[
        {
            "category":"Retail",
            "subcategory":"Auto Repair",
            "type":"Services"
        }
    ],
    "sg:phone":"+1 702 655 6911",
    "sg:postcode":"89031",
    "sg:province":"NV",
    "sg:website":"www.purrfectauto.com",
    "wof:name":"Purrfect Auto Service",
    "wof:placetype":"venue"
},
  "geometry": {"coordinates":[-115.179957,36.262893],"type":"Point"}
}