{
  "type": "Feature",
  "properties": {
    "iso:country":"US",
    "sg:address":"9215 Tisha Renee Ave",
    "sg:city":"Las Vegas",
    "sg:classifiers":[
        {
            "category":"Retail",
            "subcategory":"Auto Repair",
            "type":"Services"
        }
    ],
    "sg:phone":"+1 702 870 5901",
    "sg:postcode":"89147",
    "sg:province":"NV",
    "wof:name":"Expressway Texaco",
    "wof:placetype":"venue"
},
  "geometry": {"coordinates":[-115.29299899999999,36.120701],"type":"Point"}
}