{
  "type": "Feature",
  "properties": {
    "iso:country":"US",
    "sg:address":"10320 Juniper Creek Ln",
    "sg:city":"Las Vegas",
    "sg:classifiers":[
        {
            "category":"Professional",
            "type":"Services"
        }
    ],
    "sg:phone":"+1 702 227 9378",
    "sg:postcode":"89145",
    "sg:province":"NV",
    "sg:tags":[
        "establishment"
    ],
    "wof:name":"Extrim",
    "wof:placetype":"venue"
},
  "geometry": {"coordinates":[-115.32267899999999,36.161348],"type":"Point"}
}