{
  "type": "Feature",
  "properties": {
    "iso:country":"US",
    "sg:address":"963 W Moana Ln",
    "sg:city":"Reno",
    "sg:classifiers":[
        {
            "category":"Shopping",
            "subcategory":"Clothing, Apparel, & Fashions",
            "type":"Retail Goods"
        }
    ],
    "sg:phone":"+1 775 825 8404",
    "sg:postcode":"89509",
    "sg:province":"NV",
    "sg:tags":[
        "tailor"
    ],
    "wof:name":"PDQ Alterations",
    "wof:placetype":"venue"
},
  "geometry": {"coordinates":[-119.806718,39.491278],"type":"Point"}
}