{
  "type": "Feature",
  "properties": {
    "iso:country":"US",
    "sg:address":"654 J St",
    "sg:city":"Hawthorne",
    "sg:classifiers":[
        {
            "category":"Organizations",
            "subcategory":"Religious Organization",
            "type":"Services"
        }
    ],
    "sg:phone":"+1 775 945 5200",
    "sg:postcode":"89415",
    "sg:province":"NV",
    "sg:tags":[
        "church"
    ],
    "wof:name":"Jehovah's Witnesses",
    "wof:placetype":"venue"
},
  "geometry": {"coordinates":[-118.619775,38.526757],"type":"Point"}
}