{
  "type": "Feature",
  "properties": {
    "iso:country":"US",
    "sg:address":"9310 S Eastern Ave",
    "sg:city":"Las Vegas",
    "sg:classifiers":[
        {
            "category":"Health Services",
            "subcategory":"Health Practitioner",
            "type":"Services"
        }
    ],
    "sg:phone":"+1 702 616 9282",
    "sg:postcode":"89123",
    "sg:province":"NV",
    "sg:tags":[
        "nutritionist"
    ],
    "wof:name":"Musclemag International",
    "wof:placetype":"venue"
},
  "geometry": {"coordinates":[-115.118583,36.01887],"type":"Point"}
}