{
  "type": "Feature",
  "properties": {
    "iso:country":"US",
    "sg:address":"3807 E Climbing Fern Way",
    "sg:city":"Las Vegas",
    "sg:classifiers":[
        {
            "category":"Professional",
            "subcategory":"Computer Services",
            "type":"Services"
        }
    ],
    "sg:phone":"+1 702 644 8448",
    "sg:postcode":"89115",
    "sg:province":"NV",
    "wof:name":"Mobile Tech",
    "wof:placetype":"venue"
},
  "geometry": {"coordinates":[-115.091888,36.238353],"type":"Point"}
}