{
  "type": "Feature",
  "properties": {
    "iso:country":"US",
    "sg:address":"5969 Highland Spr",
    "sg:city":"Reno",
    "sg:classifiers":[
        {
            "category":"Building & Trades",
            "subcategory":"Construction",
            "type":"Services"
        }
    ],
    "sg:phone":"+1 775 857 2227",
    "sg:postcode":"89511",
    "sg:province":"NV",
    "sg:tags":[
        "masonry",
        "contractor"
    ],
    "wof:name":"Overland Construction Co",
    "wof:placetype":"venue"
},
  "geometry": {"coordinates":[-119.659569,39.360156],"type":"Point"}
}