{
  "type": "Feature",
  "properties": {
    "iso:country":"US",
    "sg:address":"805 Tillman Ln",
    "sg:city":"Gardnerville",
    "sg:classifiers":[
        {
            "category":"Food & Beverages",
            "subcategory":"Groceries & Convenience Stores",
            "type":"Retail Goods"
        }
    ],
    "sg:phone":"+1 775 265 2380",
    "sg:postcode":"89423",
    "sg:province":"NV",
    "wof:name":"7-Eleven",
    "wof:placetype":"venue"
},
  "geometry": {"coordinates":[-119.74204899999999,38.897147],"type":"Point"}
}