{
  "type": "Feature",
  "properties": {
    "iso:country":"US",
    "sg:address":"755 N Roop St",
    "sg:city":"Carson City",
    "sg:classifiers":[
        {
            "category":"Government",
            "subcategory":"Office",
            "type":"Public Place"
        }
    ],
    "sg:phone":"+1 775 684 7200",
    "sg:postcode":"89701",
    "sg:province":"NV",
    "sg:tags":[
        "state",
        "resource"
    ],
    "wof:name":"Human Resources-Welfare Div",
    "wof:placetype":"venue"
},
  "geometry": {"coordinates":[-119.761018,39.16811],"type":"Point"}
}