{
  "type": "Feature",
  "properties": {
    "iso:country":"US",
    "sg:address":"5576 W Rochelle Ave",
    "sg:city":"Las Vegas",
    "sg:classifiers":[
        {
            "category":"Shopping",
            "type":"Retail Goods"
        }
    ],
    "sg:phone":"+1 702 220 8678",
    "sg:postcode":"89103",
    "sg:province":"NV",
    "sg:tags":[
        "cosmetic",
        "perfume"
    ],
    "wof:name":"Perfume Aroma 3000",
    "wof:placetype":"venue"
},
  "geometry": {"coordinates":[-115.216564,36.111357],"type":"Point"}
}