{
  "type": "Feature",
  "properties": {
    "iso:country":"US",
    "sg:address":"35 N Edison Way",
    "sg:city":"Reno",
    "sg:classifiers":[
        {
            "category":"Building & Trades",
            "subcategory":"Cleaning & Sanitation",
            "type":"Services"
        }
    ],
    "sg:phone":"+1 775 856 2345",
    "sg:postcode":"89502",
    "sg:province":"NV",
    "sg:tags":[
        "house"
    ],
    "wof:name":"White Lotus Inc",
    "wof:placetype":"venue"
},
  "geometry": {"coordinates":[-119.752568,39.514999],"type":"Point"}
}