{
  "type": "Feature",
  "properties": {
    "iso:country":"US",
    "sg:address":"7465 W Sunset Road",
    "sg:city":"Las Vegas",
    "sg:classifiers":[
        {
            "category":"Shopping",
            "subcategory":"Computers & Home Electronics",
            "type":"Retail Goods"
        }
    ],
    "sg:phone":"+1 702 228 9004",
    "sg:postcode":"89113",
    "sg:province":"NV",
    "wof:name":"Sound Art Las Vegas",
    "wof:placetype":"venue"
},
  "geometry": {"coordinates":[-115.25416,36.070304],"type":"Point"}
}