{
  "type": "Feature",
  "properties": {
    "iso:country":"US",
    "sg:address":"401 Falcon Ln",
    "sg:city":"Las Vegas",
    "sg:classifiers":[
        {
            "category":"Arts & Performance",
            "subcategory":"Theater",
            "type":"Entertainment"
        }
    ],
    "sg:phone":"+1 702 870 9711",
    "sg:postcode":"89107",
    "sg:province":"NV",
    "sg:tags":[
        "group"
    ],
    "sg:website":"www.musicoftheharp.com",
    "wof:name":"Harp Music By Lisa Coffey",
    "wof:placetype":"venue"
},
  "geometry": {"coordinates":[-115.215399,36.167081],"type":"Point"}
}