{
  "type": "Feature",
  "properties": {
    "iso:country":"US",
    "sg:address":"2500 Valley Rd",
    "sg:city":"Reno",
    "sg:classifiers":[
        {
            "category":"Wholesale",
            "subcategory":"Construction Materials",
            "type":"Manufacturing & Wholesale Goods"
        }
    ],
    "sg:phone":"+1 775 324 9222",
    "sg:postcode":"89512",
    "sg:province":"NV",
    "sg:tags":[
        "granite"
    ],
    "wof:name":"Sunwood Ind",
    "wof:placetype":"venue"
},
  "geometry": {"coordinates":[-119.808103,39.550867],"type":"Point"}
}