{
  "type": "Feature",
  "properties": {
    "iso:country":"US",
    "sg:address":"1455 E Tropicana Ave",
    "sg:city":"Las Vegas",
    "sg:classifiers":[
        {
            "category":"Banks & Credit Unions",
            "subcategory":"Bank",
            "type":"Services"
        }
    ],
    "sg:phone":"+1 702 795 2227",
    "sg:postcode":"89119",
    "sg:province":"NV",
    "sg:tags":[
        "loan",
        "real estate"
    ],
    "wof:name":"Access Commercial Mortgage",
    "wof:placetype":"venue"
},
  "geometry": {"coordinates":[-115.13619300000001,36.100882],"type":"Point"}
}