{
  "type": "Feature",
  "properties": {
    "iso:country":"US",
    "sg:address":"777 E William St",
    "sg:city":"Carson City",
    "sg:classifiers":[
        {
            "category":"Social Services",
            "subcategory":"Job Training",
            "type":"Services"
        }
    ],
    "sg:phone":"+1 775 883 6257",
    "sg:postcode":"89701",
    "sg:province":"NV",
    "sg:tags":[
        "rehabilitation"
    ],
    "wof:name":"Wilcher Van Dyck & Assoc",
    "wof:placetype":"venue"
},
  "geometry": {"coordinates":[-119.762282,39.170311],"type":"Point"}
}