{
  "type": "Feature",
  "properties": {
    "iso:country":"US",
    "sg:address":"217 Kingsbury Grade Rd",
    "sg:city":"Stateline",
    "sg:classifiers":[
        {
            "category":"Food & Beverages",
            "subcategory":"Groceries & Convenience Stores",
            "type":"Retail Goods"
        }
    ],
    "sg:phone":"+1 775 588 3305",
    "sg:postcode":"89449",
    "sg:province":"NV",
    "wof:name":"Michelsen's Gas A Mart Inc",
    "wof:placetype":"venue"
},
  "geometry": {"coordinates":[-119.929808,38.968284],"type":"Point"}
}