{
  "type": "Feature",
  "properties": {
    "iso:country":"US",
    "sg:address":"380 N Maryland Pkwy",
    "sg:city":"Las Vegas",
    "sg:classifiers":[
        {
            "category":"Social Services",
            "type":"Services"
        }
    ],
    "sg:phone":"+1 702 382 0588",
    "sg:postcode":"89101",
    "sg:province":"NV",
    "sg:tags":[
        "organization",
        "welfare"
    ],
    "wof:name":"Hollyhock Adult Day Care Ctr",
    "wof:placetype":"venue"
},
  "geometry": {"coordinates":[-115.129867,36.170445],"type":"Point"}
}