{
  "type": "Feature",
  "properties": {
    "iso:country":"US",
    "sg:address":"10601 Amblewood Way",
    "sg:city":"Las Vegas",
    "sg:classifiers":[
        {
            "category":"Communications",
            "type":"Services"
        }
    ],
    "sg:phone":"+1 702 220 4914",
    "sg:postcode":"89144",
    "sg:province":"NV",
    "sg:tags":[
        "communication"
    ],
    "wof:name":"Rebel Communications LLC",
    "wof:placetype":"venue"
},
  "geometry": {"coordinates":[-115.326909,36.185677],"type":"Point"}
}