{
  "type": "Feature",
  "properties": {
    "iso:country":"US",
    "sg:address":"1800 Industrial Rd",
    "sg:city":"Las Vegas",
    "sg:classifiers":[
        {
            "category":"Health Services",
            "subcategory":"Clinic",
            "type":"Services"
        },
        {
            "category":"Social Services",
            "subcategory":"Job Training",
            "type":"Services"
        }
    ],
    "sg:phone":"+1 702 474 4104",
    "sg:postcode":"89102",
    "sg:province":"NV",
    "sg:tags":[
        "rehabilitation",
        "outpatient",
        "specialty"
    ],
    "wof:name":"New Life Medical Center",
    "wof:placetype":"venue"
},
  "geometry": {"coordinates":[-115.161729,36.148686],"type":"Point"}
}