{
  "type": "Feature",
  "properties": {
    "iso:country":"US",
    "sg:address":"3196 S Maryland Parkway",
    "sg:city":"Las Vegas",
    "sg:classifiers":[
        {
            "category":"Health Services",
            "subcategory":"Doctor",
            "type":"Services"
        }
    ],
    "sg:phone":"+1 702 791 0477",
    "sg:postcode":"89109",
    "sg:province":"NV",
    "wof:name":"Pediatric Gastroenterology & Nutrition Associates",
    "wof:placetype":"venue"
},
  "geometry": {"coordinates":[-115.13682799999999,36.133461],"type":"Point"}
}