{
  "type": "Feature",
  "properties": {
    "iso:country":"US",
    "sg:address":"6600 W Charleston Boulevard Suite 130",
    "sg:city":"Las Vegas",
    "sg:classifiers":[
        {
            "category":"Banks & Credit Unions",
            "subcategory":"Financial Services",
            "type":"Services"
        }
    ],
    "sg:phone":"+1 702 932 2840",
    "sg:postcode":"89146",
    "sg:province":"NV",
    "sg:tags":[
        "broker",
        "mortgage"
    ],
    "wof:name":"Hamilton Mortgage",
    "wof:placetype":"venue"
},
  "geometry": {"coordinates":[-115.239332,36.159242],"type":"Point"}
}