{
  "type": "Feature",
  "properties": {
    "iso:country":"US",
    "sg:address":"1807 Michael Dr",
    "sg:city":"Henderson",
    "sg:classifiers":[
        {
            "category":"Professional",
            "subcategory":"Testing Lab",
            "type":"Services"
        }
    ],
    "sg:phone":"+1 702 436 8036",
    "sg:postcode":"89048",
    "sg:province":"NV",
    "sg:tags":[
        "laboratory"
    ],
    "wof:name":"Valiente Calibration",
    "wof:placetype":"venue"
},
  "geometry": {"coordinates":[-116.084188,36.192954],"type":"Point"}
}