{
  "type": "Feature",
  "properties": {
    "iso:country":"US",
    "sg:address":"2775 Fremont Street Ofc",
    "sg:city":"Las Vegas",
    "sg:classifiers":[
        {
            "category":"Real Estate",
            "subcategory":"Real Estate Operator",
            "type":"Services"
        }
    ],
    "sg:phone":"+1 702 598 1718",
    "sg:postcode":"89104",
    "sg:province":"NV",
    "sg:tags":[
        "apartment"
    ],
    "sg:website":"www.somersetcommons.com",
    "wof:name":"Somerset Commons",
    "wof:placetype":"venue"
},
  "geometry": {"coordinates":[-115.112544,36.155683],"type":"Point"}
}