{
  "type": "Feature",
  "properties": {
    "iso:country":"US",
    "sg:address":"4140 Cannoli Cir",
    "sg:city":"Las Vegas",
    "sg:classifiers":[
        {
            "category":"Autos & Motor Vehicles",
            "subcategory":"Automobile Sales",
            "type":"Retail Goods"
        }
    ],
    "sg:phone":"+1 702 364 8049",
    "sg:postcode":"89103",
    "sg:province":"NV",
    "sg:tags":[
        "truck"
    ],
    "wof:name":"Valley Truck & Equipment",
    "wof:placetype":"venue"
},
  "geometry": {"coordinates":[-115.195602,36.103251],"type":"Point"}
}