{
  "type": "Feature",
  "properties": {
    "iso:country":"US",
    "sg:address":"325 Kenya Rd",
    "sg:city":"Las Vegas",
    "sg:classifiers":[
        {
            "category":"Health Services",
            "subcategory":"Nursing And Care Facility",
            "type":"Services"
        }
    ],
    "sg:phone":"+1 702 896 1934",
    "sg:postcode":"89123",
    "sg:province":"NV",
    "sg:tags":[
        "home",
        "rest"
    ],
    "wof:name":"Universal Home Care",
    "wof:placetype":"venue"
},
  "geometry": {"coordinates":[-115.157556,36.054999],"type":"Point"}
}