{
  "type": "Feature",
  "properties": {
    "iso:country":"US",
    "sg:address":"8490 S Eastern Ave",
    "sg:city":"Las Vegas",
    "sg:classifiers":[
        {
            "category":"Insurance",
            "subcategory":"Insurance Agent",
            "type":"Services"
        }
    ],
    "sg:phone":"+1 702 320 9226",
    "sg:postcode":"89123",
    "sg:province":"NV",
    "wof:name":"Insurance Depot",
    "wof:placetype":"venue"
},
  "geometry": {"coordinates":[-115.118246,36.036542],"type":"Point"}
}