{
  "type": "Feature",
  "properties": {
    "iso:country":"US",
    "sg:address":"432 S Boulder Hwy",
    "sg:city":"Henderson",
    "sg:classifiers":[
        {
            "category":"Retail",
            "subcategory":"Auto Repair",
            "type":"Services"
        },
        {
            "category":"Government",
            "subcategory":"Office",
            "type":"Public Place"
        }
    ],
    "sg:phone":"+1 702 564 5695",
    "sg:postcode":"89015",
    "sg:province":"NV",
    "sg:tags":[
        "smog",
        "check"
    ],
    "wof:name":"Boulder Basic Exxon Automotive",
    "wof:placetype":"venue"
},
  "geometry": {"coordinates":[-114.974728,36.033581],"type":"Point"}
}