{
  "type": "Feature",
  "properties": {
    "iso:country":"US",
    "sg:address":"4900 E Tropicana Ave",
    "sg:city":"Las Vegas",
    "sg:classifiers":[
        {
            "category":"Bars & Pubs",
            "type":"Food & Drink"
        }
    ],
    "sg:phone":"+1 702 454 0100",
    "sg:postcode":"89121",
    "sg:province":"NV",
    "sg:tags":[
        "lounge",
        "cocktail"
    ],
    "wof:name":"Trisha's Lounge",
    "wof:placetype":"venue"
},
  "geometry": {"coordinates":[-115.063931,36.100234],"type":"Point"}
}