{
  "type": "Feature",
  "properties": {
    "iso:country":"US",
    "sg:address":"3316 Hidden Ridge",
    "sg:city":"Las Vegas",
    "sg:classifiers":[
        {
            "category":"Shopping",
            "subcategory":"Gifts & Souvenirs",
            "type":"Retail Goods"
        }
    ],
    "sg:phone":"+1 702 243 0390",
    "sg:postcode":"89129",
    "sg:province":"NV",
    "sg:tags":[
        "basket",
        "parcel"
    ],
    "wof:name":"Gingerbread Haus",
    "wof:placetype":"venue"
},
  "geometry": {"coordinates":[-115.3036,36.221684],"type":"Point"}
}