{
  "type": "Feature",
  "properties": {
    "iso:country":"US",
    "sg:address":"610 Sheehan St",
    "sg:city":"Winnemucca",
    "sg:classifiers":[
        {
            "category":"Utilities",
            "subcategory":"Cable",
            "type":"Services"
        }
    ],
    "sg:phone":"+1 775 625 3239",
    "sg:postcode":"89445",
    "sg:province":"NV",
    "sg:tags":[
        "television"
    ],
    "wof:name":"Irv's Radio",
    "wof:placetype":"venue"
},
  "geometry": {"coordinates":[-117.738816,40.965588],"type":"Point"}
}