{
  "type": "Feature",
  "properties": {
    "iso:country":"US",
    "sg:address":"The Forum Shops 3500 Las Vegas Blvd S",
    "sg:city":"Las Vegas",
    "sg:classifiers":[
        {
            "category":"Shopping",
            "subcategory":"Clothing, Apparel, & Fashions",
            "type":"Retail Goods"
        }
    ],
    "sg:phone":"+1 702 735 9039",
    "sg:postcode":"89115",
    "sg:province":"NV",
    "sg:website":"www.christianaudigier.com",
    "wof:name":"Christian Audigier",
    "wof:placetype":"venue"
},
  "geometry": {"coordinates":[-115.17623399999999,36.119059],"type":"Point"}
}