{
  "type": "Feature",
  "properties": {
    "iso:country":"US",
    "sg:address":"1101 California Ave",
    "sg:city":"Reno",
    "sg:classifiers":[
        {
            "category":"Retail",
            "subcategory":"Auto Repair",
            "type":"Services"
        }
    ],
    "sg:phone":"+1 775 348 7508",
    "sg:postcode":"89509",
    "sg:province":"NV",
    "sg:tags":[
        "automobile",
        "lubrication"
    ],
    "wof:name":"Sierra Car Care",
    "wof:placetype":"venue"
},
  "geometry": {"coordinates":[-119.827413,39.51456],"type":"Point"}
}