{
  "type": "Feature",
  "properties": {
    "iso:country":"US",
    "sg:address":"8104 Sundown Vista Ave",
    "sg:city":"Las Vegas",
    "sg:classifiers":[
        {
            "category":"Professional",
            "subcategory":"Management & Consulting",
            "type":"Services"
        }
    ],
    "sg:phone":"+1 702 871 7825",
    "sg:postcode":"89147",
    "sg:province":"NV",
    "wof:name":"Asd Services Inc",
    "wof:placetype":"venue"
},
  "geometry": {"coordinates":[-115.268226,36.110345],"type":"Point"}
}