{
  "type": "Feature",
  "properties": {
    "iso:country":"US",
    "sg:address":"4710 W Dewey Dr",
    "sg:city":"Las Vegas",
    "sg:classifiers":[
        {
            "category":"Autos & Motor Vehicles",
            "subcategory":"Auto Supplies",
            "type":"Retail Goods"
        }
    ],
    "sg:phone":"+1 702 644 1170",
    "sg:postcode":"89118",
    "sg:province":"NV",
    "wof:name":"Guys Liners & Coatings",
    "wof:placetype":"venue"
},
  "geometry": {"coordinates":[-115.206487,36.088092],"type":"Point"}
}