{
  "type": "Feature",
  "properties": {
    "iso:country":"US",
    "sg:address":"2400 Western Ave",
    "sg:city":"Las Vegas",
    "sg:classifiers":[
        {
            "category":"Shopping",
            "subcategory":"Jewelry",
            "type":"Retail Goods"
        }
    ],
    "sg:phone":"+1 702 382 7411",
    "sg:postcode":"89102",
    "sg:province":"NV",
    "sg:tags":[
        "watch"
    ],
    "sg:website":"www.thejewelers.com",
    "wof:name":"The Jewelers",
    "wof:placetype":"venue"
},
  "geometry": {"coordinates":[-115.16700400000001,36.145513],"type":"Point"}
}