{
  "type": "Feature",
  "properties": {
    "iso:country":"US",
    "sg:address":"6480 W Flamingo Rd",
    "sg:city":"Las Vegas",
    "sg:classifiers":[
        {
            "category":"Professional",
            "subcategory":"Employment Agencies",
            "type":"Services"
        }
    ],
    "sg:phone":"+1 702 227 1573",
    "sg:postcode":"89103",
    "sg:province":"NV",
    "wof:name":"Las Vegas-Clark County Urban League",
    "wof:placetype":"venue"
},
  "geometry": {"coordinates":[-115.23358899999999,36.114756],"type":"Point"}
}