{
  "type": "Feature",
  "properties": {
    "iso:country":"US",
    "sg:address":"3528 S Maryland Pkwy",
    "sg:city":"Las Vegas",
    "sg:classifiers":[
        {
            "category":"Real Estate",
            "subcategory":"Real Estate Operator",
            "type":"Services"
        }
    ],
    "sg:phone":"+1 702 732 8949",
    "sg:postcode":"89109",
    "sg:province":"NV",
    "sg:tags":[
        "property",
        "commercial"
    ],
    "sg:website":"www.blvdmall.com",
    "wof:name":"Boulevard Mall",
    "wof:placetype":"venue"
},
  "geometry": {"coordinates":[-115.137074,36.126903],"type":"Point"}
}