{
  "type": "Feature",
  "properties": {
    "iso:country":"US",
    "sg:address":"1536 N 22nd St",
    "sg:city":"Las Vegas",
    "sg:classifiers":[
        {
            "category":"Real Estate",
            "subcategory":"Real Estate Operator",
            "type":"Services"
        }
    ],
    "sg:phone":"+1 702 649 1001",
    "sg:postcode":"89101",
    "sg:province":"NV",
    "sg:tags":[
        "building",
        "apartment"
    ],
    "wof:name":"Park North Apts",
    "wof:placetype":"venue"
},
  "geometry": {"coordinates":[-115.119427,36.187812],"type":"Point"}
}