{
  "type": "Feature",
  "properties": {
    "iso:country":"US",
    "sg:address":"8617 Raindrop Canyon Ave",
    "sg:city":"Las Vegas",
    "sg:classifiers":[
        {
            "category":"Organizations",
            "subcategory":"Non-profit Organization",
            "type":"Services"
        }
    ],
    "sg:phone":"+1 702 360 2033",
    "sg:postcode":"89129",
    "sg:province":"NV",
    "sg:tags":[
        "information",
        "treatment",
        "center",
        "smoker"
    ],
    "wof:name":"Stop Smoking Program",
    "wof:placetype":"venue"
},
  "geometry": {"coordinates":[-115.28014,36.226538],"type":"Point"}
}