{
  "type": "Feature",
  "properties": {
    "iso:country":"US",
    "sg:address":"3600 Las Vegas Blvd",
    "sg:city":"Las Vegas",
    "sg:classifiers":[
        {
            "category":"Shopping",
            "type":"Retail Goods"
        }
    ],
    "sg:phone":"+1 702 369 2944",
    "sg:postcode":"89109",
    "sg:province":"NV",
    "sg:website":"www.bottegaveneta.com",
    "wof:name":"Bottega Veneta",
    "wof:placetype":"venue"
},
  "geometry": {"coordinates":[-115.17299199999999,36.11394],"type":"Point"}
}