{
  "type": "Feature",
  "properties": {
    "iso:country":"US",
    "sg:address":"1428 Parkland Ave",
    "sg:city":"Carson City",
    "sg:classifiers":[
        {
            "category":"Building & Trades",
            "subcategory":"Construction",
            "type":"Services"
        }
    ],
    "sg:phone":"+1 775 885 9383",
    "sg:postcode":"89701",
    "sg:province":"NV",
    "sg:tags":[
        "excavation",
        "contractor"
    ],
    "wof:name":"Compaction Unlimited",
    "wof:placetype":"venue"
},
  "geometry": {"coordinates":[-119.755331,39.154032],"type":"Point"}
}