{
  "type": "Feature",
  "properties": {
    "iso:country":"US",
    "sg:address":"5861 W Craig Rd Ste 101",
    "sg:city":"Las Vegas",
    "sg:classifiers":[
        {
            "category":"Donuts",
            "subcategory":"None",
            "type":"Food & Drink"
        }
    ],
    "sg:phone":"+1 702 396 5031",
    "sg:postcode":"89130",
    "sg:province":"NV",
    "sg:website":"www.dunkindonuts.com",
    "wof:name":"Dunkin' Donuts",
    "wof:placetype":"venue"
},
  "geometry": {"coordinates":[-115.224341,36.238931],"type":"Point"}
}