{
  "type": "Feature",
  "properties": {
    "iso:country":"US",
    "sg:address":"3125 Cool Forest St",
    "sg:city":"Las Vegas",
    "sg:classifiers":[
        {
            "category":"Manufacturing",
            "subcategory":"Retail Goods",
            "type":"Manufacturing & Wholesale Goods"
        }
    ],
    "sg:phone":"+1 702 341 9098",
    "sg:postcode":"89117",
    "sg:province":"NV",
    "sg:tags":[
        "product",
        "mfg"
    ],
    "wof:name":"Martin Ellis Designs",
    "wof:placetype":"venue"
},
  "geometry": {"coordinates":[-115.268382,36.132359],"type":"Point"}
}