{
  "type": "Feature",
  "properties": {
    "iso:country":"US",
    "sg:address":"2420 E Desert Inn Rd",
    "sg:city":"Las Vegas",
    "sg:classifiers":[
        {
            "category":"Shopping",
            "subcategory":"Department Store",
            "type":"Retail Goods"
        }
    ],
    "sg:phone":"+1 702 733 9001",
    "sg:postcode":"89121",
    "sg:province":"NV",
    "wof:name":"Ross Dress For Less",
    "wof:placetype":"venue"
},
  "geometry": {"coordinates":[-115.117311,36.12988],"type":"Point"}
}