{
  "type": "Feature",
  "properties": {
    "iso:country":"US",
    "sg:address":"2450 Losee Road",
    "sg:city":"North Las Vegas",
    "sg:classifiers":[
        {
            "category":"Building & Trades",
            "subcategory":"Plumbing",
            "type":"Services"
        }
    ],
    "sg:phone":"+1 702 642 8400",
    "sg:postcode":"89030",
    "sg:province":"NV",
    "wof:name":"Aqua Plumbing 24 Hr Service & Repair",
    "wof:placetype":"venue"
},
  "geometry": {"coordinates":[-115.137059,36.204137],"type":"Point"}
}