{
  "type": "Feature",
  "properties": {
    "iso:country":"US",
    "sg:address":"6935 Aliante Pkwy Ste 104-300",
    "sg:city":"North Las Vegas",
    "sg:classifiers":[
        {
            "category":"Health Services",
            "subcategory":"Health Practitioner",
            "type":"Services"
        },
        {
            "category":"Social Services",
            "subcategory":"Retirement Home",
            "type":"Services"
        },
        {
            "category":"Community Center",
            "type":"Public Place"
        }
    ],
    "sg:phone":"+1 702 254 4663",
    "sg:postcode":"89084",
    "sg:province":"NV",
    "sg:tags":[
        "medical",
        "care"
    ],
    "sg:website":"www.homehelpers.cc/Default.aspx?...",
    "wof:name":"Home Helpers",
    "wof:placetype":"venue"
},
  "geometry": {"coordinates":[-115.17837299999999,36.293293],"type":"Point"}
}