{
  "type": "Feature",
  "properties": {
    "iso:country":"US",
    "sg:address":"5351 S Decatur Blvd Ste 200",
    "sg:city":"Las Vegas",
    "sg:classifiers":[
        {
            "category":"Professional",
            "subcategory":"Computer Services",
            "type":"Services"
        }
    ],
    "sg:phone":"+1 702 335 0000",
    "sg:postcode":"89118",
    "sg:province":"NV",
    "sg:tags":[
        "stereo",
        "installation"
    ],
    "sg:website":"www.702motoring.com",
    "wof:name":"702 Motoring",
    "wof:placetype":"venue"
},
  "geometry": {"coordinates":[-115.208068,36.092661],"type":"Point"}
}