{
  "type": "Feature",
  "properties": {
    "iso:country":"US",
    "sg:address":"5150 Mae Anne Ave",
    "sg:city":"Reno",
    "sg:classifiers":[
        {
            "category":"Shopping",
            "subcategory":"Department Store",
            "type":"Retail Goods"
        }
    ],
    "sg:phone":"+1 775 747 1178",
    "sg:postcode":"89523",
    "sg:province":"NV",
    "sg:tags":[
        "discount",
        "optical",
        "center",
        "pharmacy"
    ],
    "wof:name":"Shopko",
    "wof:placetype":"venue"
},
  "geometry": {"coordinates":[-119.86805699999999,39.533444],"type":"Point"}
}