{
  "type": "Feature",
  "properties": {
    "iso:country":"US",
    "sg:address":"1046 Bonita Ave",
    "sg:city":"Las Vegas",
    "sg:classifiers":[
        {
            "category":"Professional",
            "subcategory":"Business Services",
            "type":"Services"
        },
        {
            "category":"Wholesale",
            "subcategory":"Electrical",
            "type":"Manufacturing & Wholesale Goods"
        }
    ],
    "sg:phone":"+1 702 794 0690",
    "sg:postcode":"89104",
    "sg:province":"NV",
    "sg:tags":[
        "recording",
        "electronic",
        "studio"
    ],
    "wof:name":"Digital Media Co-Op",
    "wof:placetype":"venue"
},
  "geometry": {"coordinates":[-115.138414,36.148609],"type":"Point"}
}