{
  "type": "Feature",
  "properties": {
    "iso:country":"US",
    "sg:address":"2572 Idaho St",
    "sg:city":"Elko",
    "sg:classifiers":[
        {
            "category":"Utilities",
            "subcategory":"Mobile Phone",
            "type":"Services"
        }
    ],
    "sg:phone":"+1 775 738 7290",
    "sg:postcode":"89801",
    "sg:province":"NV",
    "sg:tags":[
        "telephone",
        "cellular"
    ],
    "wof:name":"Cellular One",
    "wof:placetype":"venue"
},
  "geometry": {"coordinates":[-115.74309599999999,40.853281],"type":"Point"}
}