{
  "type": "Feature",
  "properties": {
    "iso:country":"US",
    "sg:address":"908 Parkridge Pkwy",
    "sg:city":"Spring Creek",
    "sg:classifiers":[
        {
            "category":"Education",
            "subcategory":"Special Training",
            "type":"Public Place"
        }
    ],
    "sg:phone":"+1 775 777 7989",
    "sg:postcode":"89815",
    "sg:province":"NV",
    "wof:name":"Harmening & Assoc",
    "wof:placetype":"venue"
},
  "geometry": {"coordinates":[-115.538553,40.695093],"type":"Point"}
}