{
  "type": "Feature",
  "properties": {
    "iso:country":"US",
    "sg:address":"1076 River St",
    "sg:city":"Elko",
    "sg:classifiers":[
        {
            "category":"Home & Garden",
            "subcategory":"Building Materials",
            "type":"Retail Goods"
        }
    ],
    "sg:phone":"+1 775 738 7433",
    "sg:postcode":"89801",
    "sg:province":"NV",
    "sg:tags":[
        "installs",
        "garage",
        "opener",
        "door"
    ],
    "sg:website":"http://www.elkooverheaddoor.com",
    "wof:name":"Elko Overhead Door Co",
    "wof:placetype":"venue"
},
  "geometry": {"coordinates":[-115.754958,40.835134],"type":"Point"}
}