{
  "type": "Feature",
  "properties": {
    "iso:country":"US",
    "sg:address":"3111 S Valley View Blvd",
    "sg:city":"Las Vegas",
    "sg:classifiers":[
        {
            "category":"Wholesale",
            "subcategory":"Meat",
            "type":"Manufacturing & Wholesale Goods"
        }
    ],
    "sg:phone":"+1 702 248 1994",
    "sg:postcode":"89102",
    "sg:province":"NV",
    "wof:name":"Boar's Head Deli Provisions",
    "wof:placetype":"venue"
},
  "geometry": {"coordinates":[-115.19044,36.132927],"type":"Point"}
}