{
  "type": "Feature",
  "properties": {
    "iso:country":"US",
    "sg:address":"4305 E Sahara Ave",
    "sg:city":"Las Vegas",
    "sg:classifiers":[
        {
            "category":"Autos & Motor Vehicles",
            "subcategory":"Auto Supplies",
            "type":"Retail Goods"
        }
    ],
    "sg:phone":"+1 702 641 2591",
    "sg:postcode":"89104",
    "sg:province":"NV",
    "sg:tags":[
        "automobile",
        "parts"
    ],
    "wof:name":"Emotion Autowerks",
    "wof:placetype":"venue"
},
  "geometry": {"coordinates":[-115.07876400000001,36.144253],"type":"Point"}
}