{
  "type": "Feature",
  "properties": {
    "iso:country":"US",
    "sg:address":"2085 US Highway 50 E",
    "sg:city":"Carson City",
    "sg:classifiers":[
        {
            "category":"Professional",
            "subcategory":"Employment Agencies",
            "type":"Services"
        }
    ],
    "sg:phone":"+1 775 887 1800",
    "sg:postcode":"89701",
    "sg:province":"NV",
    "wof:name":"Westaff Inc",
    "wof:placetype":"venue"
},
  "geometry": {"coordinates":[-119.74299600000001,39.173801],"type":"Point"}
}