{
  "type": "Feature",
  "properties": {
    "iso:country":"US",
    "sg:address":"5250 E Stewart Ave",
    "sg:city":"Las Vegas",
    "sg:classifiers":[
        {
            "category":"Organizations",
            "subcategory":"Community Association",
            "type":"Services"
        }
    ],
    "sg:phone":"+1 702 358 5912",
    "sg:postcode":"89110",
    "sg:province":"NV",
    "sg:tags":[
        "support",
        "business"
    ],
    "wof:name":"Jose Samayoa Business Svc",
    "wof:placetype":"venue"
},
  "geometry": {"coordinates":[-115.05775,36.166774],"type":"Point"}
}