{
  "type": "Feature",
  "properties": {
    "iso:country":"US",
    "sg:address":"4953 Grey Mesa St",
    "sg:city":"Las Vegas",
    "sg:classifiers":[
        {
            "category":"Manufacturing",
            "subcategory":"Printing",
            "type":"Manufacturing & Wholesale Goods"
        }
    ],
    "sg:phone":"+1 702 871 8083",
    "sg:postcode":"89149",
    "sg:province":"NV",
    "sg:tags":[
        "directory",
        "publishing"
    ],
    "wof:name":"Perfect Wedding Guide",
    "wof:placetype":"venue"
},
  "geometry": {"coordinates":[-115.265805,36.250281],"type":"Point"}
}