{
  "type": "Feature",
  "properties": {
    "iso:country":"US",
    "sg:address":"847 Tanager St",
    "sg:city":"Incline Village",
    "sg:classifiers":[
        {
            "category":"Professional",
            "subcategory":"Art Services",
            "type":"Services"
        }
    ],
    "sg:phone":"+1 775 833 2066",
    "sg:postcode":"89451",
    "sg:province":"NV",
    "sg:tags":[
        "graphic",
        "designer"
    ],
    "wof:name":"About Face Graphics & Design",
    "wof:placetype":"venue"
},
  "geometry": {"coordinates":[-119.95613899999999,39.247362],"type":"Point"}
}