{
  "type": "Feature",
  "properties": {
    "iso:country":"US",
    "sg:address":"414 N McCarran Blvd",
    "sg:city":"Sparks",
    "sg:classifiers":[
        {
            "category":"Personal",
            "subcategory":"Beauty Salon",
            "type":"Services"
        }
    ],
    "sg:phone":"+1 775 331 1090",
    "sg:postcode":"89431",
    "sg:province":"NV",
    "sg:tags":[
        "shop"
    ],
    "wof:name":"Fancy Hair & Nails",
    "wof:placetype":"venue"
},
  "geometry": {"coordinates":[-119.734423,39.538904],"type":"Point"}
}