{
  "type": "Feature",
  "properties": {
    "iso:country":"US",
    "sg:address":"4445 Diamond Head Dr Ofc",
    "sg:city":"Las Vegas",
    "sg:classifiers":[
        {
            "category":"Real Estate",
            "subcategory":"Real Estate Operator",
            "type":"Services"
        }
    ],
    "sg:phone":"+1 702 459 6600",
    "sg:postcode":"89110",
    "sg:province":"NV",
    "sg:tags":[
        "apartment"
    ],
    "wof:name":"Desert Oasis Apartments",
    "wof:placetype":"venue"
},
  "geometry": {"coordinates":[-115.064003,36.174],"type":"Point"}
}