{
  "type": "Feature",
  "properties": {
    "iso:country":"US",
    "sg:address":"1901 Villanova Dr",
    "sg:city":"Reno",
    "sg:classifiers":[
        {
            "category":"Education",
            "subcategory":"School",
            "type":"Public Place"
        }
    ],
    "sg:phone":"+1 775 333 5180",
    "sg:postcode":"89502",
    "sg:province":"NV",
    "wof:name":"Roger Corbett Elementary Schl",
    "wof:placetype":"venue"
},
  "geometry": {"coordinates":[-119.782561,39.509429],"type":"Point"}
}