{
  "type": "Feature",
  "properties": {
    "iso:country":"US",
    "sg:address":"1914 E Sahara Avenue",
    "sg:city":"Las Vegas",
    "sg:classifiers":[
        {
            "category":"Retail",
            "subcategory":"Veterinary Services",
            "type":"Services"
        }
    ],
    "sg:phone":"+1 702 457 8043",
    "sg:postcode":"89104",
    "sg:province":"NV",
    "sg:tags":[
        "veterinarian"
    ],
    "wof:name":"Brinkmann Michael DVM Dacvo",
    "wof:placetype":"venue"
},
  "geometry": {"coordinates":[-115.122625,36.144314],"type":"Point"}
}