{
  "type": "Feature",
  "properties": {
    "iso:country":"US",
    "sg:address":"5052 S Jones Blvd",
    "sg:city":"Las Vegas",
    "sg:classifiers":[
        {
            "category":"Professional",
            "subcategory":"Accounting & Tax Preparation",
            "type":"Services"
        }
    ],
    "sg:phone":"+1 702 362 3123",
    "sg:postcode":"89118",
    "sg:province":"NV",
    "sg:tags":[
        "accountant"
    ],
    "sg:website":"www.rch-cpa.com",
    "wof:name":"STRATEGIC Wealth Advisors",
    "wof:placetype":"venue"
},
  "geometry": {"coordinates":[-115.224961,36.099081],"type":"Point"}
}