{
  "type": "Feature",
  "properties": {
    "iso:country":"US",
    "sg:address":"3050 E Desert Inn Rd Ste 123",
    "sg:city":"Las Vegas",
    "sg:classifiers":[
        {
            "category":"Shopping",
            "subcategory":"Pharmacy",
            "type":"Retail Goods"
        }
    ],
    "sg:phone":"+1 702 696 1527",
    "sg:postcode":"89121",
    "sg:province":"NV",
    "sg:tags":[
        "drugstore"
    ],
    "sg:website":"www.carenhome.com",
    "wof:name":"Care'n'home Inc",
    "wof:placetype":"venue"
},
  "geometry": {"coordinates":[-115.108355,36.129895],"type":"Point"}
}