{
  "type": "Feature",
  "properties": {
    "iso:country":"US",
    "sg:address":"5420 W Sahara Ave",
    "sg:city":"Las Vegas",
    "sg:classifiers":[
        {
            "category":"Professional",
            "subcategory":"Computer Services",
            "type":"Services"
        }
    ],
    "sg:phone":"+1 702 889 8333",
    "sg:postcode":"89146",
    "sg:province":"NV",
    "sg:tags":[
        "related"
    ],
    "wof:name":"Accent Networks",
    "wof:placetype":"venue"
},
  "geometry": {"coordinates":[-115.218733,36.14443],"type":"Point"}
}