{
  "type": "Feature",
  "properties": {
    "iso:country":"US",
    "sg:address":"5940 S Rainbow Boulevard",
    "sg:city":"Las Vegas",
    "sg:classifiers":[
        {
            "category":"Banks & Credit Unions",
            "subcategory":"Financial Services",
            "type":"Services"
        }
    ],
    "sg:phone":"+1 702 438 8300",
    "sg:postcode":"89118",
    "sg:province":"NV",
    "sg:tags":[
        "broker",
        "mortgage"
    ],
    "wof:name":"Milestone Mortgage",
    "wof:placetype":"venue"
},
  "geometry": {"coordinates":[-115.24270300000001,36.081483],"type":"Point"}
}