{
  "type": "Feature",
  "properties": {
    "iso:country":"US",
    "sg:address":"405 W 5th St",
    "sg:city":"Reno",
    "sg:classifiers":[
        {
            "category":"Shopping",
            "subcategory":"Used Merchandise",
            "type":"Retail Goods"
        }
    ],
    "sg:phone":"+1 775 323 2980",
    "sg:postcode":"89503",
    "sg:province":"NV",
    "sg:tags":[
        "shop",
        "consignment"
    ],
    "wof:name":"Nearly New Shoppe",
    "wof:placetype":"venue"
},
  "geometry": {"coordinates":[-119.821165,39.530076],"type":"Point"}
}