{
  "type": "Feature",
  "properties": {
    "iso:country":"US",
    "sg:address":"1800 Idlewild Dr",
    "sg:city":"Reno",
    "sg:classifiers":[
        {
            "category":"Real Estate",
            "subcategory":"Real Estate Operator",
            "type":"Services"
        }
    ],
    "sg:phone":"+1 775 322 6795",
    "sg:postcode":"89509",
    "sg:province":"NV",
    "sg:tags":[
        "apartment"
    ],
    "wof:name":"Idlewild Garden Apartments",
    "wof:placetype":"venue"
},
  "geometry": {"coordinates":[-119.831846,39.519726],"type":"Point"}
}