{
  "type": "Feature",
  "properties": {
    "iso:country":"US",
    "sg:address":"3377 Las Vegas Blvd S # 2195",
    "sg:city":"Las Vegas",
    "sg:classifiers":[
        {
            "category":"Shopping",
            "type":"Retail Goods"
        }
    ],
    "sg:phone":"+1 702 414 3799",
    "sg:postcode":"89109",
    "sg:province":"NV",
    "sg:website":"www.movadoboutique.com",
    "wof:name":"Movado Boutique",
    "wof:placetype":"venue"
},
  "geometry": {"coordinates":[-115.17123100000001,36.122341],"type":"Point"}
}