{
  "type": "Feature",
  "properties": {
    "iso:country":"US",
    "sg:address":"2375 E Prater Way",
    "sg:city":"Sparks",
    "sg:classifiers":[
        {
            "category":"Health Services",
            "subcategory":"Health Practitioner",
            "type":"Services"
        }
    ],
    "sg:phone":"+1 775 356 4404",
    "sg:postcode":"89434",
    "sg:province":"NV",
    "sg:tags":[
        "therapist",
        "physical"
    ],
    "wof:name":"Northern Nevada Rehabilitation",
    "wof:placetype":"venue"
},
  "geometry": {"coordinates":[-119.697425,39.542438],"type":"Point"}
}