{
  "type": "Feature",
  "properties": {
    "iso:country":"US",
    "sg:address":"3716 Lakeside Dr Ste 100",
    "sg:city":"Reno",
    "sg:classifiers":[
        {
            "category":"Insurance",
            "subcategory":"Hazard Insurance",
            "type":"Services"
        },
        {
            "category":"Insurance",
            "subcategory":"Insurance Agent",
            "type":"Services"
        },
        {
            "category":"Insurance",
            "subcategory":"Life Insurance",
            "type":"Services"
        },
        {
            "category":"Banks & Credit Unions",
            "subcategory":"Financial Services",
            "type":"Services"
        },
        {
            "category":"Insurance",
            "subcategory":"Health Insurance",
            "type":"Services"
        }
    ],
    "sg:phone":"+1 775 828 1216",
    "sg:postcode":"89509",
    "sg:province":"NV",
    "sg:tags":[
        "term",
        "sharing",
        "group",
        "profit",
        "long",
        "adjuster",
        "pension",
        "plan",
        "care"
    ],
    "sg:website":"http://www.healthbenefits.net",
    "wof:name":"Health Benefits Associates Inc",
    "wof:placetype":"venue"
},
  "geometry": {"coordinates":[-119.807907,39.4892],"type":"Point"}
}