{
  "type": "Feature",
  "properties": {
    "iso:country":"US",
    "sg:address":"209 S. Curry Street",
    "sg:city":"Carson City",
    "sg:classifiers":[
        {
            "category":"Personal",
            "subcategory":"Skin Care",
            "type":"Services"
        }
    ],
    "sg:phone":"+1 775 841 5969",
    "sg:postcode":"89703",
    "sg:province":"NV",
    "wof:name":"Mary's About Face & Body",
    "wof:placetype":"venue"
},
  "geometry": {"coordinates":[-119.767819,39.163167],"type":"Point"}
}