{
  "type": "Feature",
  "properties": {
    "iso:country":"US",
    "sg:address":"2220 E Bonanza Rd",
    "sg:city":"Las Vegas",
    "sg:classifiers":[
        {
            "category":"Personal",
            "subcategory":"Beauty Salon",
            "type":"Services"
        }
    ],
    "sg:phone":"+1 702 384 7454",
    "sg:postcode":"89101",
    "sg:province":"NV",
    "sg:tags":[
        "shop"
    ],
    "wof:name":"Pattys Beauty Salon Inc",
    "wof:placetype":"venue"
},
  "geometry": {"coordinates":[-115.119072,36.173889],"type":"Point"}
}