{
  "type": "Feature",
  "properties": {
    "iso:country":"US",
    "sg:address":"1030 W Sunset Rd",
    "sg:city":"Henderson",
    "sg:classifiers":[
        {
            "category":"Home & Garden",
            "subcategory":"Building Materials",
            "type":"Retail Goods"
        }
    ],
    "sg:phone":"+1 702 435 9200",
    "sg:postcode":"89014",
    "sg:province":"NV",
    "sg:tags":[
        "center"
    ],
    "sg:website":"www.homedepot.com",
    "wof:name":"Home Depot",
    "wof:placetype":"venue"
},
  "geometry": {"coordinates":[-115.036034,36.063848],"type":"Point"}
}