{
  "type": "Feature",
  "properties": {
    "iso:country":"US",
    "sg:address":"319 N Carson St",
    "sg:city":"Carson City",
    "sg:classifiers":[
        {
            "category":"Food & Beverages",
            "subcategory":"Specialty",
            "type":"Retail Goods"
        }
    ],
    "sg:phone":"+1 775 883 4004",
    "sg:postcode":"89701",
    "sg:province":"NV",
    "sg:tags":[
        "tea",
        "coffee"
    ],
    "wof:name":"Java Joe's",
    "wof:placetype":"venue"
},
  "geometry": {"coordinates":[-119.766998,39.165699],"type":"Point"}
}