{
  "type": "Feature",
  "properties": {
    "iso:country":"US",
    "sg:address":"3753 Howard Hughes Pkwy",
    "sg:city":"Las Vegas",
    "sg:classifiers":[
        {
            "category":"Banks & Credit Unions",
            "subcategory":"Bank",
            "type":"Services"
        }
    ],
    "sg:phone":"+1 702 784 7655",
    "sg:postcode":"89109",
    "sg:province":"NV",
    "sg:tags":[
        "mortgage",
        "loan",
        "broker",
        "real estate"
    ],
    "wof:name":"Pacific Coast Mortgage",
    "wof:placetype":"venue"
},
  "geometry": {"coordinates":[-115.15799699999999,36.120701],"type":"Point"}
}