{
  "type": "Feature",
  "properties": {
    "iso:country":"US",
    "sg:address":"1570 Rawhide Dr",
    "sg:city":"Henderson",
    "sg:classifiers":[
        {
            "category":"Building & Trades",
            "subcategory":"Cleaning & Sanitation",
            "type":"Services"
        }
    ],
    "sg:phone":"+1 702 565 0641",
    "sg:postcode":"89002",
    "sg:province":"NV",
    "sg:tags":[
        "maintenance"
    ],
    "wof:name":"C C Janitorial Inc",
    "wof:placetype":"venue"
},
  "geometry": {"coordinates":[-114.928398,36.003784],"type":"Point"}
}