{
  "type": "Feature",
  "properties": {
    "iso:country":"US",
    "sg:address":"3765 Losee Rd",
    "sg:city":"North Las Vegas",
    "sg:classifiers":[
        {
            "category":"Wholesale",
            "subcategory":"Auto Parts",
            "type":"Manufacturing & Wholesale Goods"
        }
    ],
    "sg:phone":"+1 702 657 9992",
    "sg:postcode":"89030",
    "sg:province":"NV",
    "sg:tags":[
        "equipment",
        "truck"
    ],
    "wof:name":"Lighthouse Inc",
    "wof:placetype":"venue"
},
  "geometry": {"coordinates":[-115.119342,36.228426],"type":"Point"}
}