{
  "type": "Feature",
  "properties": {
    "iso:country":"US",
    "sg:address":"414 Nevada Hwy",
    "sg:city":"Boulder City",
    "sg:classifiers":[
        {
            "category":"Insurance",
            "subcategory":"Insurance Agent",
            "type":"Services"
        }
    ],
    "sg:phone":"+1 702 293 7403",
    "sg:postcode":"89005",
    "sg:province":"NV",
    "wof:name":"American Family Insurance",
    "wof:placetype":"venue"
},
  "geometry": {"coordinates":[-114.836682,35.978947],"type":"Point"}
}