{
  "type": "Feature",
  "properties": {
    "iso:country":"US",
    "sg:address":"699 Long Valley Rd",
    "sg:city":"Gardnerville",
    "sg:classifiers":[
        {
            "category":"Education",
            "subcategory":"School",
            "type":"Public Place"
        }
    ],
    "sg:phone":"+1 775 265 2222",
    "sg:postcode":"89460",
    "sg:province":"NV",
    "wof:name":"Gene Scarselli Elementary Schl",
    "wof:placetype":"venue"
},
  "geometry": {"coordinates":[-119.72593,38.887083],"type":"Point"}
}