{
  "type": "Feature",
  "properties": {
    "iso:country":"US",
    "sg:address":"2910 S Highland Dr",
    "sg:city":"Las Vegas",
    "sg:classifiers":[
        {
            "category":"Wholesale",
            "subcategory":"Machinery & Supplies",
            "type":"Manufacturing & Wholesale Goods"
        },
        {
            "category":"Wholesale",
            "subcategory":"Electrical",
            "type":"Manufacturing & Wholesale Goods"
        }
    ],
    "sg:phone":"+1 702 369 5446",
    "sg:postcode":"89109",
    "sg:province":"NV",
    "sg:tags":[
        "control",
        "automatic"
    ],
    "wof:name":"Burke Engineering Co",
    "wof:placetype":"venue"
},
  "geometry": {"coordinates":[-115.172845,36.137509],"type":"Point"}
}