{
  "type": "Feature",
  "properties": {
    "iso:country":"US",
    "sg:address":"5115 Spring Mountain Rd",
    "sg:city":"Las Vegas",
    "sg:classifiers":[
        {
            "category":"Shopping",
            "subcategory":"Jewelry",
            "type":"Retail Goods"
        }
    ],
    "sg:phone":"+1 702 312 3279",
    "sg:postcode":"89146",
    "sg:province":"NV",
    "sg:tags":[
        "jeweler"
    ],
    "wof:name":"Hunq Thinh Jewelry",
    "wof:placetype":"venue"
},
  "geometry": {"coordinates":[-115.211353,36.12619],"type":"Point"}
}