{
  "type": "Feature",
  "properties": {
    "iso:country":"US",
    "sg:address":"4825 W Flamingo Rd Ste 8",
    "sg:city":"Las Vegas",
    "sg:classifiers":[
        {
            "category":"Personal",
            "subcategory":"Day Spa",
            "type":"Services"
        }
    ],
    "sg:phone":"+1 702 220 7706",
    "sg:postcode":"89103",
    "sg:province":"NV",
    "wof:name":"Spa by Dored G",
    "wof:placetype":"venue"
},
  "geometry": {"coordinates":[-115.206388,36.115386],"type":"Point"}
}