{
  "type": "Feature",
  "properties": {
    "iso:country":"US",
    "sg:address":"20 W Bridge St",
    "sg:city":"Yerington",
    "sg:classifiers":[
        {
            "category":"Restaurant",
            "type":"Food & Drink"
        }
    ],
    "sg:phone":"+1 775 463 9569",
    "sg:postcode":"89447",
    "sg:province":"NV",
    "wof:name":"El Alteno",
    "wof:placetype":"venue"
},
  "geometry": {"coordinates":[-119.164213,38.983035],"type":"Point"}
}