{
  "type": "Feature",
  "properties": {
    "iso:country":"US",
    "sg:address":"3230 S Buffalo Drive Suite 105",
    "sg:city":"Las Vegas",
    "sg:classifiers":[
        {
            "category":"Banks & Credit Unions",
            "subcategory":"Financial Services",
            "type":"Services"
        }
    ],
    "sg:phone":"+1 702 228 1857",
    "sg:postcode":"89117",
    "sg:province":"NV",
    "sg:tags":[
        "broker",
        "mortgage"
    ],
    "wof:name":"Milestone Residential Mortgage",
    "wof:placetype":"venue"
},
  "geometry": {"coordinates":[-115.260988,36.130418],"type":"Point"}
}