{
  "type": "Feature",
  "properties": {
    "iso:country":"US",
    "sg:address":"3048 Yankee Clipper Dr",
    "sg:city":"Las Vegas",
    "sg:classifiers":[
        {
            "category":"Professional",
            "subcategory":"Computer Services",
            "type":"Services"
        }
    ],
    "sg:phone":"+1 702 257 1527",
    "sg:postcode":"89117",
    "sg:province":"NV",
    "sg:tags":[
        "internet"
    ],
    "wof:name":"Las Vegas Jobs Com",
    "wof:placetype":"venue"
},
  "geometry": {"coordinates":[-115.283402,36.137989],"type":"Point"}
}