{
  "type": "Feature",
  "properties": {
    "iso:country":"US",
    "sg:address":"5887 W Agate Ave",
    "sg:city":"Las Vegas",
    "sg:classifiers":[
        {
            "category":"Wholesale",
            "subcategory":"Auto Parts",
            "type":"Manufacturing & Wholesale Goods"
        }
    ],
    "sg:phone":"+1 702 361 0207",
    "sg:postcode":"89139",
    "sg:province":"NV",
    "sg:tags":[
        "automotive",
        "tool"
    ],
    "wof:name":"Vegas Tools",
    "wof:placetype":"venue"
},
  "geometry": {"coordinates":[-115.219306,36.024149],"type":"Point"}
}