{
  "type": "Feature",
  "properties": {
    "iso:country":"US",
    "sg:address":"2075 S Rainbow Blvd",
    "sg:city":"Las Vegas",
    "sg:classifiers":[
        {
            "category":"Retail",
            "subcategory":"Auto Repair",
            "type":"Services"
        }
    ],
    "sg:phone":"+1 702 254 3891",
    "sg:postcode":"89146",
    "sg:province":"NV",
    "wof:name":"Imports and More...",
    "wof:placetype":"venue"
},
  "geometry": {"coordinates":[-115.243418,36.149059],"type":"Point"}
}