{
  "type": "Feature",
  "properties": {
    "iso:country":"US",
    "sg:address":"1740 Sunrise Pass Rd",
    "sg:city":"Minden",
    "sg:classifiers":[
        {
            "category":"Building & Trades",
            "subcategory":"Landscaping Services",
            "type":"Services"
        }
    ],
    "sg:phone":"+1 775 230 3591",
    "sg:postcode":"89423",
    "sg:province":"NV",
    "sg:tags":[
        "lawn",
        "maintenance",
        "grounds"
    ],
    "wof:name":"Ponds & Pathways Naturescape",
    "wof:placetype":"venue"
},
  "geometry": {"coordinates":[-119.69942,39.012263],"type":"Point"}
}