{
  "type": "Feature",
  "properties": {
    "iso:country":"US",
    "sg:address":"1900 E Desert Inn Road",
    "sg:city":"Las Vegas",
    "sg:classifiers":[
        {
            "category":"Health Services",
            "subcategory":"Chiropractor",
            "type":"Services"
        }
    ],
    "sg:phone":"+1 702 456 1200",
    "sg:postcode":"89169",
    "sg:province":"NV",
    "wof:name":"Lewis Scott D DC",
    "wof:placetype":"venue"
},
  "geometry": {"coordinates":[-115.12591,36.129985],"type":"Point"}
}