{
  "type": "Feature",
  "properties": {
    "iso:country":"US",
    "sg:address":"1503 N Tonopah Dr",
    "sg:city":"Las Vegas",
    "sg:classifiers":[
        {
            "category":"Organizations",
            "subcategory":"Religious Organization",
            "type":"Services"
        }
    ],
    "sg:phone":"+1 702 646 0738",
    "sg:postcode":"89106",
    "sg:province":"NV",
    "wof:name":"Revival Temple Church of God I",
    "wof:placetype":"venue"
},
  "geometry": {"coordinates":[-115.16990300000001,36.188293],"type":"Point"}
}