{
  "type": "Feature",
  "properties": {
    "iso:country":"US",
    "sg:address":"128 Shadow Ln",
    "sg:city":"Las Vegas",
    "sg:classifiers":[
        {
            "category":"Retail",
            "subcategory":"Repair Shop",
            "type":"Services"
        }
    ],
    "sg:phone":"+1 702 383 7008",
    "sg:postcode":"89106",
    "sg:province":"NV",
    "sg:tags":[
        "upholsterer"
    ],
    "wof:name":"Sanchez's Upholstery",
    "wof:placetype":"venue"
},
  "geometry": {"coordinates":[-115.165483,36.170971],"type":"Point"}
}