{
  "type": "Feature",
  "properties": {
    "iso:country":"US",
    "sg:address":"8161 Round Hills Cir",
    "sg:city":"Las Vegas",
    "sg:classifiers":[
        {
            "category":"Professional",
            "type":"Services"
        }
    ],
    "sg:phone":"+1 702 579 7727",
    "sg:postcode":"89113",
    "sg:province":"NV",
    "wof:name":"Gale Salerno RPR Ccr",
    "wof:placetype":"venue"
},
  "geometry": {"coordinates":[-115.269345,36.095425],"type":"Point"}
}