{
  "type": "Feature",
  "properties": {
    "iso:country":"US",
    "sg:address":"7251 W Lake Mead Blvd",
    "sg:city":"Las Vegas",
    "sg:classifiers":[
        {
            "category":"Banks & Credit Unions",
            "subcategory":"Bank",
            "type":"Services"
        }
    ],
    "sg:phone":"+1 702 562 4327",
    "sg:postcode":"89128",
    "sg:province":"NV",
    "wof:name":"Harris Bank Na the",
    "wof:placetype":"venue"
},
  "geometry": {"coordinates":[-115.250356,36.195862],"type":"Point"}
}