{
  "type": "Feature",
  "properties": {
    "iso:country":"US",
    "sg:address":"1849 Golden Shadow Dr",
    "sg:city":"Henderson",
    "sg:classifiers":[
        {
            "category":"Wholesale",
            "subcategory":"Machinery & Supplies",
            "type":"Manufacturing & Wholesale Goods"
        }
    ],
    "sg:phone":"+1 702 327 3555",
    "sg:postcode":"89002",
    "sg:province":"NV",
    "sg:tags":[
        "printer",
        "cartridge"
    ],
    "wof:name":"L & R Cartridges",
    "wof:placetype":"venue"
},
  "geometry": {"coordinates":[-115.09837,36.051404],"type":"Point"}
}