{
  "type": "Feature",
  "properties": {
    "iso:country":"US",
    "sg:address":"1351 W Sunset Rd",
    "sg:city":"Henderson",
    "sg:classifiers":[
        {
            "category":"Home & Garden",
            "subcategory":"Furniture",
            "type":"Retail Goods"
        }
    ],
    "sg:phone":"+1 702 456 9111",
    "sg:postcode":"89014",
    "sg:province":"NV",
    "sg:tags":[
        "mattress"
    ],
    "wof:name":"Mattress Pro Of Nevada",
    "wof:placetype":"venue"
},
  "geometry": {"coordinates":[-115.045115,36.063625],"type":"Point"}
}