{
  "type": "Feature",
  "properties": {
    "iso:country":"US",
    "sg:address":"6362 McLeod Drive",
    "sg:city":"Las Vegas",
    "sg:classifiers":[
        {
            "category":"Banks & Credit Unions",
            "subcategory":"Financial Services",
            "type":"Services"
        }
    ],
    "sg:phone":"+1 702 736 6446",
    "sg:postcode":"89120",
    "sg:province":"NV",
    "sg:tags":[
        "broker",
        "mortgage"
    ],
    "wof:name":"Rks Mortgage",
    "wof:placetype":"venue"
},
  "geometry": {"coordinates":[-115.111612,36.074442],"type":"Point"}
}