{
  "type": "Feature",
  "properties": {
    "iso:country":"US",
    "sg:address":"1255 Joy Lake Rd",
    "sg:city":"Reno",
    "sg:classifiers":[
        {
            "category":"Professional",
            "subcategory":"Engineering",
            "type":"Services"
        }
    ],
    "sg:phone":"+1 775 849 1955",
    "sg:postcode":"89511",
    "sg:province":"NV",
    "sg:tags":[
        "engineer"
    ],
    "wof:name":"Anderson & Assoc Engineering",
    "wof:placetype":"venue"
},
  "geometry": {"coordinates":[-119.844495,39.358438],"type":"Point"}
}