{
  "type": "Feature",
  "properties": {
    "iso:country":"US",
    "sg:address":"2113 Scarlet Rose Dr",
    "sg:city":"Las Vegas",
    "sg:classifiers":[
        {
            "category":"Banks & Credit Unions",
            "subcategory":"Investment Brokerage",
            "type":"Services"
        }
    ],
    "sg:phone":"+1 702 233 4721",
    "sg:postcode":"89134",
    "sg:province":"NV",
    "sg:tags":[
        "advisory"
    ],
    "wof:name":"Frank Bennett & Co",
    "wof:placetype":"venue"
},
  "geometry": {"coordinates":[-115.307976,36.196315],"type":"Point"}
}