{
  "type": "Feature",
  "properties": {
    "iso:country":"US",
    "sg:address":"8601 Scholar Lane",
    "sg:city":"Las Vegas",
    "sg:classifiers":[
        {
            "category":"Education",
            "subcategory":"Preschool",
            "type":"Public Place"
        },
        {
            "category":"Education",
            "subcategory":"School",
            "type":"Public Place"
        }
    ],
    "sg:phone":"+1 702 254 1610",
    "sg:postcode":"89128",
    "sg:province":"NV",
    "sg:tags":[
        "high",
        "middle",
        "elementary"
    ],
    "wof:name":"Meadows Beginning School",
    "wof:placetype":"venue"
},
  "geometry": {"coordinates":[-115.280515,36.196329],"type":"Point"}
}