{
  "type": "Feature",
  "properties": {
    "iso:country":"US",
    "sg:address":"2701 N Rainbow Blvd",
    "sg:city":"Las Vegas",
    "sg:classifiers":[
        {
            "category":"Real Estate",
            "subcategory":"Real Estate Operator",
            "type":"Services"
        }
    ],
    "sg:phone":"+1 702 658 0655",
    "sg:postcode":"89108",
    "sg:province":"NV",
    "sg:tags":[
        "building",
        "apartment"
    ],
    "wof:name":"Jik Properties Inc",
    "wof:placetype":"venue"
},
  "geometry": {"coordinates":[-115.242261,36.207017],"type":"Point"}
}