{
  "type": "Feature",
  "properties": {
    "iso:country":"US",
    "sg:address":"4255 W Viking Rd",
    "sg:city":"Las Vegas",
    "sg:classifiers":[
        {
            "category":"Professional",
            "subcategory":"Computer Services",
            "type":"Services"
        }
    ],
    "sg:phone":"+1 702 579 0137",
    "sg:postcode":"89103",
    "sg:province":"NV",
    "sg:tags":[
        "processing",
        "datum"
    ],
    "wof:name":"Bankcard Services",
    "wof:placetype":"venue"
},
  "geometry": {"coordinates":[-115.197453,36.118996],"type":"Point"}
}