{
  "type": "Feature",
  "properties": {
    "iso:country":"US",
    "sg:address":"1623 8th St",
    "sg:city":"Minden",
    "sg:classifiers":[
        {
            "category":"Manufacturing",
            "subcategory":"Printing",
            "type":"Manufacturing & Wholesale Goods"
        }
    ],
    "sg:phone":"+1 775 782 4520",
    "sg:postcode":"89423",
    "sg:province":"NV",
    "sg:tags":[
        "newspaper"
    ],
    "wof:name":"Sierra Scoop LLC",
    "wof:placetype":"venue"
},
  "geometry": {"coordinates":[-119.76491900000001,38.955208],"type":"Point"}
}