{
  "type": "Feature",
  "properties": {
    "iso:country":"US",
    "sg:address":"1731 Village Center Cir",
    "sg:city":"Las Vegas",
    "sg:classifiers":[
        {
            "category":"Real Estate",
            "subcategory":"Developer",
            "type":"Services"
        }
    ],
    "sg:phone":"+1 702 851 7200",
    "sg:postcode":"89134",
    "sg:province":"NV",
    "wof:name":"Venture Development Group",
    "wof:placetype":"venue"
},
  "geometry": {"coordinates":[-115.299387,36.190401],"type":"Point"}
}