{
  "type": "Feature",
  "properties": {
    "iso:country":"US",
    "sg:address":"3421 Happy Ln",
    "sg:city":"Las Vegas",
    "sg:classifiers":[
        {
            "category":"Building & Trades",
            "subcategory":"Landscaping Services",
            "type":"Services"
        }
    ],
    "sg:phone":"+1 702 433 0484",
    "sg:postcode":"89120",
    "sg:province":"NV",
    "sg:tags":[
        "landscape",
        "contractor"
    ],
    "wof:name":"Naridon Corporation",
    "wof:placetype":"venue"
},
  "geometry": {"coordinates":[-115.096745,36.069499],"type":"Point"}
}