{
  "type": "Feature",
  "properties": {
    "iso:country":"US",
    "sg:address":"2560 S Maryland Pkwy",
    "sg:city":"Las Vegas",
    "sg:classifiers":[
        {
            "category":"Insurance",
            "subcategory":"Hazard Insurance",
            "type":"Services"
        }
    ],
    "sg:phone":"+1 702 892 9908",
    "sg:postcode":"89109",
    "sg:province":"NV",
    "sg:tags":[
        "carrier"
    ],
    "wof:name":"Derrick Webb",
    "wof:placetype":"venue"
},
  "geometry": {"coordinates":[-115.136776,36.141836],"type":"Point"}
}