{
  "type": "Feature",
  "properties": {
    "iso:country":"US",
    "sg:address":"520 Mount Rose St",
    "sg:city":"Reno",
    "sg:classifiers":[
        {
            "category":"Professional",
            "subcategory":"Lawyer & Legal Services",
            "type":"Services"
        }
    ],
    "sg:phone":"+1 775 337 0773",
    "sg:postcode":"89509",
    "sg:province":"NV",
    "wof:name":"Carole M Pope",
    "wof:placetype":"venue"
},
  "geometry": {"coordinates":[-119.813546,39.509503],"type":"Point"}
}