{
  "type": "Feature",
  "properties": {
    "iso:country":"US",
    "sg:address":"1450 E Harmon Avenue Ofc",
    "sg:city":"Las Vegas",
    "sg:classifiers":[
        {
            "category":"Real Estate",
            "subcategory":"Real Estate Operator",
            "type":"Services"
        }
    ],
    "sg:phone":"+1 702 733 1907",
    "sg:postcode":"89119",
    "sg:province":"NV",
    "sg:tags":[
        "apartment"
    ],
    "wof:name":"Four Horizons Apartments",
    "wof:placetype":"venue"
},
  "geometry": {"coordinates":[-115.133978,36.107702],"type":"Point"}
}