{
  "type": "Feature",
  "properties": {
    "iso:country":"US",
    "sg:address":"5260 W 7th St",
    "sg:city":"Reno",
    "sg:classifiers":[
        {
            "category":"Retail",
            "subcategory":"Portrait Studio",
            "type":"Services"
        }
    ],
    "sg:phone":"+1 775 624 2000",
    "sg:postcode":"89523",
    "sg:province":"NV",
    "sg:tags":[
        "photographer"
    ],
    "wof:name":"Wal-Mart",
    "wof:placetype":"venue"
},
  "geometry": {"coordinates":[-119.86955500000001,39.538137],"type":"Point"}
}