{
  "type": "Feature",
  "properties": {
    "iso:country":"US",
    "sg:address":"8001 US Hwy 50",
    "sg:city":"Carson City",
    "sg:classifiers":[
        {
            "category":"Autos & Motor Vehicles",
            "subcategory":"Automobile Sales",
            "type":"Retail Goods"
        }
    ],
    "sg:phone":"+1 775 883 5500",
    "sg:postcode":"89701",
    "sg:province":"NV",
    "sg:tags":[
        "sport",
        "trailer",
        "utility"
    ],
    "wof:name":"Coy Truck Sales",
    "wof:placetype":"venue"
},
  "geometry": {"coordinates":[-119.68314100000001,39.208533],"type":"Point"}
}