{
  "type": "Feature",
  "properties": {
    "iso:country":"US",
    "sg:address":"4310 S. Cameron Street Suite 11",
    "sg:city":"Las Vegas",
    "sg:classifiers":[
        {
            "category":"Communications",
            "subcategory":"Newspaper",
            "type":"Services"
        }
    ],
    "sg:phone":"+1 702 385 2737",
    "sg:postcode":"89103",
    "sg:province":"NV",
    "sg:tags":[
        "print",
        "medium"
    ],
    "sg:website":"www.todayinlv.com",
    "wof:name":"Today In Las Vegas Magazine",
    "wof:placetype":"venue"
},
  "geometry": {"coordinates":[-115.204022,36.111617],"type":"Point"}
}