{
  "type": "Feature",
  "properties": {
    "iso:country":"US",
    "sg:address":"522 Clearbrook St",
    "sg:city":"Mesquite",
    "sg:classifiers":[
        {
            "category":"Autos & Motor Vehicles",
            "subcategory":"Recreational Vehicle Sales",
            "type":"Retail Goods"
        }
    ],
    "sg:phone":"+1 702 346 3565",
    "sg:postcode":"89027",
    "sg:province":"NV",
    "wof:name":"Eugene Sales",
    "wof:placetype":"venue"
},
  "geometry": {"coordinates":[-114.059016,36.820034],"type":"Point"}
}