{
  "type": "Feature",
  "properties": {
    "iso:country":"US",
    "sg:address":"7104 Dalegrove Dr",
    "sg:city":"Las Vegas",
    "sg:classifiers":[
        {
            "category":"Building & Trades",
            "subcategory":"Construction",
            "type":"Services"
        }
    ],
    "sg:phone":"+1 702 655 8735",
    "sg:postcode":"89129",
    "sg:province":"NV",
    "sg:tags":[
        "house"
    ],
    "wof:name":"Altered Shapes",
    "wof:placetype":"venue"
},
  "geometry": {"coordinates":[-115.251351,36.221435],"type":"Point"}
}