{
  "type": "Feature",
  "properties": {
    "iso:country":"US",
    "sg:address":"2400 Chatfield Dr",
    "sg:city":"Las Vegas",
    "sg:classifiers":[
        {
            "category":"Arts & Performance",
            "subcategory":"Theater",
            "type":"Entertainment"
        }
    ],
    "sg:phone":"+1 702 562 8899",
    "sg:postcode":"89128",
    "sg:province":"NV",
    "sg:tags":[
        "magician"
    ],
    "wof:name":"Awesome Entertainment",
    "wof:placetype":"venue"
},
  "geometry": {"coordinates":[-115.265467,36.203235],"type":"Point"}
}