{
  "type": "Feature",
  "properties": {
    "iso:country":"US",
    "sg:address":"2585 S Jones Blvd Ste 2F",
    "sg:city":"Las Vegas",
    "sg:classifiers":[
        {
            "category":"Banks & Credit Unions",
            "subcategory":"Financial Services",
            "type":"Services"
        }
    ],
    "sg:phone":"+1 702 650 7688",
    "sg:postcode":"89146",
    "sg:province":"NV",
    "sg:tags":[
        "broker",
        "mortgage"
    ],
    "wof:name":"Ampersand Mortgage",
    "wof:placetype":"venue"
},
  "geometry": {"coordinates":[-115.225715,36.142596],"type":"Point"}
}