{
  "type": "Feature",
  "properties": {
    "iso:country":"US",
    "sg:address":"2851 N Green Valley Parkway",
    "sg:city":"Henderson",
    "sg:classifiers":[
        {
            "category":"Shopping",
            "subcategory":"Pharmacy",
            "type":"Retail Goods"
        }
    ],
    "sg:phone":"+1 702 435 9849",
    "sg:postcode":"89014",
    "sg:province":"NV",
    "sg:tags":[
        "drugstore"
    ],
    "wof:name":"Albertsons Sav-On",
    "wof:placetype":"venue"
},
  "geometry": {"coordinates":[-115.082569,36.072882],"type":"Point"}
}