{
  "type": "Feature",
  "properties": {
    "iso:country":"US",
    "sg:address":"2758 N Green Valley Parkway",
    "sg:city":"Henderson",
    "sg:classifiers":[
        {
            "category":"Retail",
            "subcategory":"Veterinary Services",
            "type":"Services"
        }
    ],
    "sg:phone":"+1 702 454 4400",
    "sg:postcode":"89014",
    "sg:province":"NV",
    "sg:tags":[
        "veterinarian"
    ],
    "wof:name":"A Cat Hospital & Cat Motel",
    "wof:placetype":"venue"
},
  "geometry": {"coordinates":[-115.082134,36.070642],"type":"Point"}
}