{
  "type": "Feature",
  "properties": {
    "iso:country":"US",
    "sg:address":"3208 W Desert Inn Rd",
    "sg:city":"Las Vegas",
    "sg:classifiers":[
        {
            "category":"Wholesale",
            "subcategory":"Home Furnishings",
            "type":"Manufacturing & Wholesale Goods"
        }
    ],
    "sg:phone":"+1 702 876 5929",
    "sg:postcode":"89102",
    "sg:province":"NV",
    "sg:tags":[
        "closet",
        "accessory"
    ],
    "sg:website":"www.closetmasters.com",
    "wof:name":"Closet Masters LLC",
    "wof:placetype":"venue"
},
  "geometry": {"coordinates":[-115.18352400000001,36.130051],"type":"Point"}
}