{
  "type": "Feature",
  "properties": {
    "iso:country":"US",
    "sg:address":"10990 Lear Blvd",
    "sg:city":"Reno",
    "sg:classifiers":[
        {
            "category":"Professional",
            "type":"Services"
        }
    ],
    "sg:phone":"+1 775 677 1948",
    "sg:postcode":"89506",
    "sg:province":"NV",
    "sg:tags":[
        "transportation"
    ],
    "wof:name":"Its Logistics",
    "wof:placetype":"venue"
},
  "geometry": {"coordinates":[-119.863888,39.644128],"type":"Point"}
}