{
  "type": "Feature",
  "properties": {
    "iso:country":"US",
    "sg:address":"3220 N Leslie St",
    "sg:city":"Pahrump",
    "sg:classifiers":[
        {
            "category":"Professional",
            "subcategory":"Business Services",
            "type":"Services"
        }
    ],
    "sg:phone":"+1 775 537 6440",
    "sg:postcode":"89060",
    "sg:province":"NV",
    "wof:name":"Hampel Computer Sales",
    "wof:placetype":"venue"
},
  "geometry": {"coordinates":[-116.050588,36.268942],"type":"Point"}
}