{
  "type": "Feature",
  "properties": {
    "iso:country":"US",
    "sg:address":"2620 Regatta Dr Ste 102",
    "sg:city":"Las Vegas",
    "sg:classifiers":[
        {
            "category":"Real Estate",
            "subcategory":"Real Estate Services",
            "type":"Services"
        }
    ],
    "sg:phone":"+1 702 750 9725",
    "sg:postcode":"89128",
    "sg:province":"NV",
    "sg:tags":[
        "management",
        "property"
    ],
    "sg:website":"www.managevegas.com/",
    "wof:name":"Southwestern Management And Realty Team",
    "wof:placetype":"venue"
},
  "geometry": {"coordinates":[-115.26852700000001,36.207515],"type":"Point"}
}