{
  "type": "Feature",
  "properties": {
    "iso:country":"US",
    "sg:address":"12206 Carson Hwy",
    "sg:city":"Fallon",
    "sg:classifiers":[
        {
            "category":"Farming",
            "subcategory":"Fish & Marine Products",
            "type":"Manufacturing & Wholesale Goods"
        }
    ],
    "sg:phone":"+1 775 867 3143",
    "sg:postcode":"89406",
    "sg:province":"NV",
    "sg:tags":[
        "fisherman"
    ],
    "wof:name":"Murray Fish Co",
    "wof:placetype":"venue"
},
  "geometry": {"coordinates":[-118.998705,39.499301],"type":"Point"}
}