{
  "type": "Feature",
  "properties": {
    "iso:country":"US",
    "sg:address":"1114 Globe Mallow Ln",
    "sg:city":"Tonopah",
    "sg:classifiers":[
        {
            "category":"Government",
            "subcategory":"Office",
            "type":"Public Place"
        }
    ],
    "sg:phone":"+1 775 482 8181",
    "sg:postcode":"89049",
    "sg:province":"NV",
    "wof:name":"Nye County Planning & Building",
    "wof:placetype":"venue"
},
  "geometry": {"coordinates":[-117.251476,38.082968],"type":"Point"}
}