{
  "type": "Feature",
  "properties": {
    "iso:country":"US",
    "sg:address":"1800 US Highway 50 E Ste 13",
    "sg:city":"Carson City",
    "sg:classifiers":[
        {
            "category":"Food & Beverages",
            "subcategory":"Liquor & Beverages",
            "type":"Retail Goods"
        }
    ],
    "sg:phone":"+1 775 841 1669",
    "sg:postcode":"89701",
    "sg:province":"NV",
    "sg:tags":[
        "beer",
        "spirit",
        "wine"
    ],
    "wof:name":"Rand Avenue Convenience Store",
    "wof:placetype":"venue"
},
  "geometry": {"coordinates":[-119.748006,39.172931],"type":"Point"}
}