{
  "type": "Feature",
  "properties": {
    "iso:country":"US",
    "sg:address":"3457 Ringstar Road",
    "sg:city":"North Las Vegas",
    "sg:classifiers":[
        {
            "category":"Autos & Motor Vehicles",
            "subcategory":"Auto Supplies",
            "type":"Retail Goods"
        }
    ],
    "sg:phone":"+1 702 644 7702",
    "sg:postcode":"89030",
    "sg:province":"NV",
    "sg:tags":[
        "tire"
    ],
    "wof:name":"Grubs Tire Service",
    "wof:placetype":"venue"
},
  "geometry": {"coordinates":[-115.10305700000001,36.229411],"type":"Point"}
}