{
  "type": "Feature",
  "properties": {
    "iso:country":"US",
    "sg:address":"4225 Fidus",
    "sg:city":"Las Vegas",
    "sg:classifiers":[
        {
            "category":"Wholesale",
            "subcategory":"Photographic Equipment",
            "type":"Manufacturing & Wholesale Goods"
        }
    ],
    "sg:phone":"+1 702 651 9393",
    "sg:postcode":"89103",
    "sg:province":"NV",
    "sg:tags":[
        "motion",
        "picture",
        "film"
    ],
    "wof:name":"Maxxam Entertainment Inc",
    "wof:placetype":"venue"
},
  "geometry": {"coordinates":[-115.201189,36.112661],"type":"Point"}
}