{
  "type": "Feature",
  "properties": {
    "iso:country":"US",
    "sg:address":"600 Whitney Ranch Dr",
    "sg:city":"Henderson",
    "sg:classifiers":[
        {
            "category":"Health Services",
            "subcategory":"Doctor",
            "type":"Services"
        }
    ],
    "sg:phone":"+1 702 547 0088",
    "sg:postcode":"89014",
    "sg:province":"NV",
    "wof:name":"Adaoag Aaron MD",
    "wof:placetype":"venue"
},
  "geometry": {"coordinates":[-115.05237,36.06384],"type":"Point"}
}