{
  "type": "Feature",
  "properties": {
    "iso:country":"US",
    "sg:address":"7201 W Lake Mead Blvd",
    "sg:city":"Las Vegas",
    "sg:classifiers":[
        {
            "category":"Professional",
            "subcategory":"Lawyer & Legal Services",
            "type":"Services"
        }
    ],
    "sg:phone":"+1 702 233 9303",
    "sg:postcode":"89128",
    "sg:province":"NV",
    "sg:tags":[
        "attorney"
    ],
    "wof:name":"Kathryn Peck Law Office",
    "wof:placetype":"venue"
},
  "geometry": {"coordinates":[-115.24937799999999,36.195971],"type":"Point"}
}