{
  "type": "Feature",
  "properties": {
    "iso:country":"US",
    "sg:address":"1601 E Flamingo Rd Ste 20",
    "sg:city":"Las Vegas",
    "sg:classifiers":[
        {
            "category":"Real Estate",
            "subcategory":"Real Estate Services",
            "type":"Services"
        }
    ],
    "sg:phone":"+1 702 734 6100",
    "sg:postcode":"89119",
    "sg:province":"NV",
    "sg:tags":[
        "management",
        "property"
    ],
    "sg:website":"www.mcrelv.com",
    "wof:name":"Millennium Commercial Real Estate Services",
    "wof:placetype":"venue"
},
  "geometry": {"coordinates":[-115.130229,36.113634],"type":"Point"}
}