{
  "type": "Feature",
  "properties": {
    "iso:country":"US",
    "sg:address":"520 S 9th St",
    "sg:city":"Las Vegas",
    "sg:classifiers":[
        {
            "category":"Professional",
            "type":"Services"
        }
    ],
    "sg:phone":"+1 702 799 3140",
    "sg:postcode":"89101",
    "sg:province":"NV",
    "wof:name":"Cmm 1 LLC",
    "wof:placetype":"venue"
},
  "geometry": {"coordinates":[-115.139838,36.161738],"type":"Point"}
}