{
  "type": "Feature",
  "properties": {
    "iso:country":"US",
    "sg:address":"510 Marks Street",
    "sg:city":"Henderson",
    "sg:classifiers":[
        {
            "category":"Shopping",
            "subcategory":"Pets & Pet Supplies",
            "type":"Retail Goods"
        }
    ],
    "sg:phone":"+1 702 454 7387",
    "sg:postcode":"89014",
    "sg:province":"NV",
    "sg:tags":[
        "store"
    ],
    "wof:name":"Petland",
    "wof:placetype":"venue"
},
  "geometry": {"coordinates":[-115.036362,36.060327],"type":"Point"}
}