{
  "type": "Feature",
  "properties": {
    "iso:country":"US",
    "sg:address":"4425 E Sahara Ave",
    "sg:city":"Las Vegas",
    "sg:classifiers":[
        {
            "category":"Wholesale",
            "subcategory":"Machinery & Supplies",
            "type":"Manufacturing & Wholesale Goods"
        }
    ],
    "sg:phone":"+1 702 452 0666",
    "sg:postcode":"89104",
    "sg:province":"NV",
    "sg:tags":[
        "equipment",
        "material",
        "handling"
    ],
    "wof:name":"Mefpar",
    "wof:placetype":"venue"
},
  "geometry": {"coordinates":[-115.076987,36.144249],"type":"Point"}
}