{
  "type": "Feature",
  "properties": {
    "iso:country":"US",
    "sg:address":"5708 W Charleston Blvd",
    "sg:city":"Las Vegas",
    "sg:classifiers":[
        {
            "category":"Shopping",
            "type":"Retail Goods"
        }
    ],
    "sg:phone":"+1 702 877 1106",
    "sg:postcode":"89146",
    "sg:province":"NV",
    "sg:tags":[
        "stamp",
        "collector",
        "for"
    ],
    "wof:name":"Charleston Stamps",
    "wof:placetype":"venue"
},
  "geometry": {"coordinates":[-115.221105,36.159269],"type":"Point"}
}