{
  "type": "Feature",
  "properties": {
    "iso:country":"US",
    "sg:address":"4528 Amherst Ln",
    "sg:city":"Las Vegas",
    "sg:classifiers":[
        {
            "category":"Building & Trades",
            "subcategory":"Landscaping Services",
            "type":"Services"
        }
    ],
    "sg:phone":"+1 702 562 9021",
    "sg:postcode":"89107",
    "sg:province":"NV",
    "sg:tags":[
        "landscape",
        "contractor"
    ],
    "wof:name":"Swiftly Landscape",
    "wof:placetype":"venue"
},
  "geometry": {"coordinates":[-115.203968,36.169036],"type":"Point"}
}