{
  "type": "Feature",
  "properties": {
    "iso:country":"US",
    "sg:address":"2510 Tacchino St",
    "sg:city":"Reno",
    "sg:classifiers":[
        {
            "category":"Building & Trades",
            "subcategory":"Landscaping Services",
            "type":"Services"
        }
    ],
    "sg:phone":"+1 775 359 4412",
    "sg:postcode":"89512",
    "sg:province":"NV",
    "sg:tags":[
        "landscape",
        "contractor"
    ],
    "wof:name":"Peri Landscape Construction",
    "wof:placetype":"venue"
},
  "geometry": {"coordinates":[-119.782995,39.536668],"type":"Point"}
}