{
  "type": "Feature",
  "properties": {
    "iso:country":"US",
    "sg:address":"912 E Sahara Avenue",
    "sg:city":"Las Vegas",
    "sg:classifiers":[
        {
            "category":"Professional",
            "subcategory":"Lawyer & Legal Services",
            "type":"Services"
        }
    ],
    "sg:phone":"+1 702 477 7030",
    "sg:postcode":"89104",
    "sg:province":"NV",
    "wof:name":"Benson Lee & Associates Ltd",
    "wof:placetype":"venue"
},
  "geometry": {"coordinates":[-115.142298,36.144021],"type":"Point"}
}