{
  "type": "Feature",
  "properties": {
    "iso:country":"US",
    "sg:address":"21 E Mesquite Blvd",
    "sg:city":"Mesquite",
    "sg:classifiers":[
        {
            "category":"Insurance",
            "subcategory":"Insurance Agent",
            "type":"Services"
        }
    ],
    "sg:phone":"+1 702 346 5779",
    "sg:postcode":"89027",
    "sg:province":"NV",
    "wof:name":"Valley-Leavitt Insurance",
    "wof:placetype":"venue"
},
  "geometry": {"coordinates":[-114.066656,36.804102],"type":"Point"}
}