{
  "type": "Feature",
  "properties": {
    "iso:country":"US",
    "sg:address":"195 N Ada St",
    "sg:city":"Fallon",
    "sg:classifiers":[
        {
            "category":"Health Services",
            "subcategory":"Doctor",
            "type":"Services"
        }
    ],
    "sg:phone":"+1 775 423 4933",
    "sg:postcode":"89406",
    "sg:province":"NV",
    "sg:tags":[
        "clinic"
    ],
    "wof:name":"Diabetes Wellness",
    "wof:placetype":"venue"
},
  "geometry": {"coordinates":[-118.780309,39.476241],"type":"Point"}
}