{
  "type": "Feature",
  "properties": {
    "iso:country":"US",
    "sg:address":"548 N Nellis Blvd Ste E",
    "sg:city":"Las Vegas",
    "sg:classifiers":[
        {
            "category":"Health Services",
            "subcategory":"Health Practitioner",
            "type":"Services"
        }
    ],
    "sg:phone":"+1 702 538 8800",
    "sg:postcode":"89110",
    "sg:province":"NV",
    "sg:tags":[
        "acupuncture"
    ],
    "wof:name":"Sunny Hills Pain Clinic",
    "wof:placetype":"venue"
},
  "geometry": {"coordinates":[-115.06179899999999,36.169355],"type":"Point"}
}