{
  "type": "Feature",
  "properties": {
    "iso:country":"US",
    "sg:address":"3281 N Decatur Blvd",
    "sg:city":"Las Vegas",
    "sg:classifiers":[
        {
            "category":"Health Services",
            "subcategory":"Doctor",
            "type":"Services"
        }
    ],
    "sg:phone":"+1 702 395 8983",
    "sg:postcode":"89130",
    "sg:province":"NV",
    "sg:tags":[
        "physician",
        "surgeon"
    ],
    "wof:name":"Pediatric Acute Care",
    "wof:placetype":"venue"
},
  "geometry": {"coordinates":[-115.20739,36.217637],"type":"Point"}
}