{
  "type": "Feature",
  "properties": {
    "iso:country":"US",
    "sg:address":"1889 E Maule Ave",
    "sg:city":"Las Vegas",
    "sg:classifiers":[
        {
            "category":"Wholesale",
            "subcategory":"Medical Equipment & Supplies",
            "type":"Manufacturing & Wholesale Goods"
        }
    ],
    "sg:phone":"+1 702 795 0221",
    "sg:postcode":"89119",
    "sg:province":"NV",
    "sg:tags":[
        "hospital"
    ],
    "wof:name":"Mediq PRN",
    "wof:placetype":"venue"
},
  "geometry": {"coordinates":[-115.123815,36.064358],"type":"Point"}
}