{
  "type": "Feature",
  "properties": {
    "iso:country":"US",
    "sg:address":"3810 Flamingo Rd",
    "sg:city":"Pahrump",
    "sg:classifiers":[
        {
            "category":"Wholesale",
            "subcategory":"Construction Materials",
            "type":"Manufacturing & Wholesale Goods"
        }
    ],
    "sg:phone":"+1 775 727 6257",
    "sg:postcode":"89048",
    "sg:province":"NV",
    "sg:tags":[
        "concrete",
        "product"
    ],
    "wof:name":"JV-Industries",
    "wof:placetype":"venue"
},
  "geometry": {"coordinates":[-116.084441,36.190361],"type":"Point"}
}