{
  "type": "Feature",
  "properties": {
    "iso:country":"US",
    "sg:address":"2850 Rosanna St",
    "sg:city":"Las Vegas",
    "sg:classifiers":[
        {
            "category":"Professional",
            "subcategory":"Management & Consulting",
            "type":"Services"
        }
    ],
    "sg:phone":"+1 702 873 3189",
    "sg:postcode":"89117",
    "sg:province":"NV",
    "wof:name":"Max Rubin Enterprises",
    "wof:placetype":"venue"
},
  "geometry": {"coordinates":[-115.24509399999999,36.137699],"type":"Point"}
}