{
  "type": "Feature",
  "properties": {
    "iso:country":"US",
    "sg:address":"2670 Chandler Ave",
    "sg:city":"Las Vegas",
    "sg:classifiers":[
        {
            "category":"Communications",
            "subcategory":"Newspaper",
            "type":"Services"
        }
    ],
    "sg:phone":"+1 702 614 9001",
    "sg:postcode":"89120",
    "sg:province":"NV",
    "sg:tags":[
        "print",
        "medium"
    ],
    "wof:name":"Southern Nevada Family Magazine",
    "wof:placetype":"venue"
},
  "geometry": {"coordinates":[-115.113998,36.074001],"type":"Point"}
}