{
  "type": "Feature",
  "properties": {
    "iso:country":"US",
    "sg:address":"1275 S Lamb Blvd",
    "sg:city":"Las Vegas",
    "sg:classifiers":[
        {
            "category":"Fast Food",
            "type":"Food & Drink"
        }
    ],
    "sg:phone":"+1 702 453 6696",
    "sg:postcode":"89104",
    "sg:province":"NV",
    "wof:name":"Taco Bell",
    "wof:placetype":"venue"
},
  "geometry": {"coordinates":[-115.080782,36.157444],"type":"Point"}
}