{
  "type": "Feature",
  "properties": {
    "iso:country":"US",
    "sg:address":"6070 Boulder Hwy",
    "sg:city":"Las Vegas",
    "sg:classifiers":[
        {
            "category":"Retail",
            "subcategory":"Auto Rental",
            "type":"Services"
        }
    ],
    "sg:phone":"+1 702 456 6666",
    "sg:postcode":"89122",
    "sg:province":"NV",
    "sg:tags":[
        "recreational",
        "leasing",
        "vehicle"
    ],
    "wof:name":"Cruise America",
    "wof:placetype":"venue"
},
  "geometry": {"coordinates":[-115.040008,36.091139],"type":"Point"}
}