{
  "type": "Feature",
  "properties": {
    "iso:country":"US",
    "sg:address":"2660 S Maryland Pkwy",
    "sg:city":"Las Vegas",
    "sg:classifiers":[
        {
            "category":"Bars & Pubs",
            "subcategory":"Nightclub",
            "type":"Food & Drink"
        }
    ],
    "sg:phone":"+1 702 737 1966",
    "sg:postcode":"89109",
    "sg:province":"NV",
    "sg:tags":[
        "nightlife"
    ],
    "wof:name":"Office 7 Lounge",
    "wof:placetype":"venue"
},
  "geometry": {"coordinates":[-115.137001,36.141102],"type":"Point"}
}