{
  "type": "Feature",
  "properties": {
    "iso:country":"US",
    "sg:address":"8717 Pesaro Dr",
    "sg:city":"Las Vegas",
    "sg:classifiers":[
        {
            "category":"Professional",
            "type":"Services"
        }
    ],
    "sg:phone":"+1 702 240 6553",
    "sg:postcode":"89117",
    "sg:province":"NV",
    "wof:name":"KB Pool Service",
    "wof:placetype":"venue"
},
  "geometry": {"coordinates":[-115.285433,36.152688],"type":"Point"}
}