{
  "type": "Feature",
  "properties": {
    "iso:country":"US",
    "sg:address":"4205 W Tompkins Ave",
    "sg:city":"Las Vegas",
    "sg:classifiers":[
        {
            "category":"Building & Trades",
            "subcategory":"Construction",
            "type":"Services"
        }
    ],
    "sg:phone":"+1 702 639 9200",
    "sg:postcode":"89103",
    "sg:province":"NV",
    "sg:tags":[
        "concrete",
        "contractor"
    ],
    "wof:name":"Csi",
    "wof:placetype":"venue"
},
  "geometry": {"coordinates":[-115.197738,36.104618],"type":"Point"}
}