{
  "type": "Feature",
  "properties": {
    "iso:country":"US",
    "sg:address":"4300 N Pecos Rd Ste 32",
    "sg:city":"Las Vegas",
    "sg:classifiers":[
        {
            "category":"Building & Trades",
            "subcategory":"Plumbing",
            "type":"Services"
        }
    ],
    "sg:phone":"+1 702 643 7555",
    "sg:postcode":"89115",
    "sg:province":"NV",
    "wof:name":"Young Plumbing & Mechanical",
    "wof:placetype":"venue"
},
  "geometry": {"coordinates":[-115.066002,36.218102],"type":"Point"}
}