{
  "type": "Feature",
  "properties": {
    "iso:country":"US",
    "sg:address":"6432 Break Point Ave",
    "sg:city":"Las Vegas",
    "sg:classifiers":[
        {
            "category":"Professional",
            "subcategory":"Management & Consulting",
            "type":"Services"
        }
    ],
    "sg:phone":"+1 702 656 9184",
    "sg:postcode":"89130",
    "sg:province":"NV",
    "sg:tags":[
        "business"
    ],
    "wof:name":"Marcy Leggiere Consulting",
    "wof:placetype":"venue"
},
  "geometry": {"coordinates":[-115.235551,36.257365],"type":"Point"}
}