{
  "type": "Feature",
  "properties": {
    "iso:country":"US",
    "sg:address":"950 Pilot Rd",
    "sg:city":"Las Vegas",
    "sg:classifiers":[
        {
            "category":"Government",
            "subcategory":"Post Office",
            "type":"Public Place"
        }
    ],
    "sg:phone":"+1 702 000 1111",
    "sg:postcode":"89119",
    "sg:province":"NV",
    "wof:name":"US Post Office",
    "wof:placetype":"venue"
},
  "geometry": {"coordinates":[-115.146146,36.065887],"type":"Point"}
}