{
  "type": "Feature",
  "properties": {
    "iso:country":"US",
    "sg:address":"3948 Autumn St",
    "sg:city":"Las Vegas",
    "sg:classifiers":[
        {
            "category":"Retail",
            "subcategory":"Repair Shop",
            "type":"Services"
        }
    ],
    "sg:phone":"+1 702 374 8197",
    "sg:postcode":"89120",
    "sg:province":"NV",
    "sg:tags":[
        "related"
    ],
    "wof:name":"Dent Tech Inc",
    "wof:placetype":"venue"
},
  "geometry": {"coordinates":[-115.087788,36.099025],"type":"Point"}
}