{
  "type": "Feature",
  "properties": {
    "iso:country":"US",
    "sg:address":"230 S Maryland Pkwy",
    "sg:city":"Las Vegas",
    "sg:classifiers":[
        {
            "category":"Professional",
            "type":"Services"
        }
    ],
    "sg:phone":"+1 702 382 7001",
    "sg:postcode":"89101",
    "sg:province":"NV",
    "sg:tags":[
        "establishment"
    ],
    "wof:name":"John's Paving",
    "wof:placetype":"venue"
},
  "geometry": {"coordinates":[-115.13404300000001,36.163873],"type":"Point"}
}