{
  "type": "Feature",
  "properties": {
    "iso:country":"US",
    "sg:address":"Holiday Inn 1553 N. Boulder Highway",
    "sg:city":"Henderson",
    "sg:classifiers":[
        {
            "category":"Restaurant",
            "type":"Food & Drink"
        }
    ],
    "sg:phone":"+1 702 564 9200",
    "sg:postcode":"89011",
    "sg:province":"NV",
    "wof:name":"Kem's Restaurant",
    "wof:placetype":"venue"
},
  "geometry": {"coordinates":[-115.005211,36.059535],"type":"Point"}
}