{
  "type": "Feature",
  "properties": {
    "iso:country":"US",
    "sg:address":"6555 Arville St",
    "sg:city":"Las Vegas",
    "sg:classifiers":[
        {
            "category":"Real Estate",
            "subcategory":"Real Estate Operator",
            "type":"Services"
        }
    ],
    "sg:phone":"+1 702 616 3178",
    "sg:postcode":"89118",
    "sg:province":"NV",
    "sg:tags":[
        "building",
        "nonresidential"
    ],
    "wof:name":"Ddrm Properties LLC",
    "wof:placetype":"venue"
},
  "geometry": {"coordinates":[-115.199303,36.0709],"type":"Point"}
}