{
  "type": "Feature",
  "properties": {
    "iso:country":"US",
    "sg:address":"76 N Maine St",
    "sg:city":"Fallon",
    "sg:classifiers":[
        {
            "category":"Professional",
            "subcategory":"Research",
            "type":"Services"
        }
    ],
    "sg:phone":"+1 775 428 1225",
    "sg:postcode":"89406",
    "sg:province":"NV",
    "sg:tags":[
        "development",
        "laboratory"
    ],
    "wof:name":"International Capital & Metals",
    "wof:placetype":"venue"
},
  "geometry": {"coordinates":[-118.776916,39.47523],"type":"Point"}
}