{
  "type": "Feature",
  "properties": {
    "iso:country":"US",
    "sg:address":"3595 E Winner Dr",
    "sg:city":"Las Vegas",
    "sg:classifiers":[
        {
            "category":"Recreation",
            "type":"Entertainment"
        }
    ],
    "sg:phone":"+1 702 456 4653",
    "sg:postcode":"89120",
    "sg:province":"NV",
    "wof:name":"Grand Slam Golf Inc",
    "wof:placetype":"venue"
},
  "geometry": {"coordinates":[-115.095533,36.088084],"type":"Point"}
}