{
  "type": "Feature",
  "properties": {
    "iso:country":"US",
    "sg:address":"905 Linda Way",
    "sg:city":"Sparks",
    "sg:classifiers":[
        {
            "category":"Wholesale",
            "subcategory":"Construction Materials",
            "type":"Manufacturing & Wholesale Goods"
        }
    ],
    "sg:phone":"+1 775 355 0700",
    "sg:postcode":"89431",
    "sg:province":"NV",
    "sg:tags":[
        "glass"
    ],
    "wof:name":"Sierra Glass Distributors",
    "wof:placetype":"venue"
},
  "geometry": {"coordinates":[-119.74801100000001,39.521666],"type":"Point"}
}