{
  "type": "Feature",
  "properties": {
    "iso:country":"US",
    "sg:address":"375 N. Stephanie Street Suite 141",
    "sg:city":"Henderson",
    "sg:classifiers":[
        {
            "category":"Professional",
            "subcategory":"Computer Services",
            "type":"Services"
        }
    ],
    "sg:phone":"+1 702 446 8106",
    "sg:postcode":"89014-8909",
    "sg:province":"NV",
    "sg:tags":[
        "instructions",
        "manuals",
        "how-to",
        "needinstructions-com",
        "need-instructions-llc",
        "need-instructions",
        "diy",
        "do-it-your-self"
    ],
    "sg:website":"http://www.NeedInstructions.com",
    "wof:name":"NeedInstructions.com",
    "wof:placetype":"venue"
},
  "geometry": {"coordinates":[-115.04634,36.0551],"type":"Point"}
}