{
  "type": "Feature",
  "properties": {
    "iso:country":"US",
    "sg:address":"807 Larch Ct",
    "sg:city":"Las Vegas",
    "sg:classifiers":[
        {
            "category":"Professional",
            "subcategory":"Business Services",
            "type":"Services"
        }
    ],
    "sg:phone":"+1 702 363 0134",
    "sg:postcode":"89145",
    "sg:province":"NV",
    "sg:tags":[
        "broker",
        "merchandise"
    ],
    "wof:name":"Raaz Printing",
    "wof:placetype":"venue"
},
  "geometry": {"coordinates":[-115.252564,36.163108],"type":"Point"}
}