{
  "type": "Feature",
  "properties": {
    "iso:country":"US",
    "sg:address":"1853 Betsy Ross Dr",
    "sg:city":"Las Vegas",
    "sg:classifiers":[
        {
            "category":"Building & Trades",
            "subcategory":"Construction",
            "type":"Services"
        }
    ],
    "sg:phone":"+1 702 277 1914",
    "sg:postcode":"89108",
    "sg:province":"NV",
    "sg:tags":[
        "house",
        "nonresidential"
    ],
    "wof:name":"M C Nelson Construction Svcs",
    "wof:placetype":"venue"
},
  "geometry": {"coordinates":[-115.237338,36.193441],"type":"Point"}
}