{
  "type": "Feature",
  "properties": {
    "iso:country":"US",
    "sg:address":"7400 Las Vegas Blvd S",
    "sg:city":"Las Vegas",
    "sg:classifiers":[
        {
            "category":"Building & Trades",
            "subcategory":"Cleaning & Sanitation",
            "type":"Services"
        }
    ],
    "sg:phone":"+1 702 896 5200",
    "sg:postcode":"89123",
    "sg:province":"NV",
    "sg:tags":[
        "janitor"
    ],
    "wof:name":"Magic Brite Janitorial",
    "wof:placetype":"venue"
},
  "geometry": {"coordinates":[-115.172273,36.05511],"type":"Point"}
}