{
  "type": "Feature",
  "properties": {
    "iso:country":"US",
    "sg:address":"Royal Resort Hotel 99 Convention Center Dr",
    "sg:city":"Las Vegas",
    "sg:classifiers":[
        {
            "category":"Arts & Performance",
            "subcategory":"Arts Center",
            "type":"Entertainment"
        }
    ],
    "sg:phone":"+1 866 485 3638",
    "sg:postcode":"89109",
    "sg:province":"NV",
    "sg:tags":[
        "performing"
    ],
    "sg:website":"www.larrygjones.com",
    "wof:name":"Larry G Jones",
    "wof:placetype":"venue"
},
  "geometry": {"coordinates":[-115.163323,36.132306],"type":"Point"}
}