{
  "type": "Feature",
  "properties": {
    "iso:country":"US",
    "sg:address":"560 N Nellis Blvd",
    "sg:city":"Las Vegas",
    "sg:classifiers":[
        {
            "category":"Building & Trades",
            "subcategory":"Locksmith",
            "type":"Services"
        }
    ],
    "sg:phone":"+1 702 560 6010",
    "sg:postcode":"89110",
    "sg:province":"NV",
    "sg:tags":[
        "key"
    ],
    "wof:name":"0 007 Lock1 Service",
    "wof:placetype":"venue"
},
  "geometry": {"coordinates":[-115.06180000000001,36.16958],"type":"Point"}
}