{
  "type": "Feature",
  "properties": {
    "iso:country":"US",
    "sg:address":"961 Topsy Ln Ste 442",
    "sg:city":"Carson City",
    "sg:classifiers":[
        {
            "category":"Professional",
            "subcategory":"Lawyer & Legal Services",
            "type":"Services"
        }
    ],
    "sg:phone":"+1 775 267 3303",
    "sg:postcode":"89705",
    "sg:province":"NV",
    "sg:tags":[
        "notary"
    ],
    "wof:name":"Farmers Insurance and Financial Services-Tim Ghan Cpcu",
    "wof:placetype":"venue"
},
  "geometry": {"coordinates":[-119.776414,39.110253],"type":"Point"}
}