{
  "type": "Feature",
  "properties": {
    "iso:country":"US",
    "sg:address":"3025 E Russell Rd",
    "sg:city":"Las Vegas",
    "sg:classifiers":[
        {
            "category":"Health Services",
            "subcategory":"Nursing And Care Facility",
            "type":"Services"
        }
    ],
    "sg:phone":"+1 702 451 7896",
    "sg:postcode":"89120",
    "sg:province":"NV",
    "sg:tags":[
        "skilled"
    ],
    "wof:name":"Loyalton Of Las Vegas",
    "wof:placetype":"venue"
},
  "geometry": {"coordinates":[-115.10542599999999,36.086386],"type":"Point"}
}