{
  "type": "Feature",
  "properties": {
    "iso:country":"US",
    "sg:address":"5850 Sky Pointe Dr",
    "sg:city":"Las Vegas",
    "sg:classifiers":[
        {
            "category":"Wholesale",
            "subcategory":"Groceries",
            "type":"Manufacturing & Wholesale Goods"
        }
    ],
    "sg:phone":"+1 702 523 1256",
    "sg:postcode":"89130",
    "sg:province":"NV",
    "sg:tags":[
        "general"
    ],
    "wof:name":"Coliel Food Brokers",
    "wof:placetype":"venue"
},
  "geometry": {"coordinates":[-115.256218,36.266797],"type":"Point"}
}