{
  "type": "Feature",
  "properties": {
    "iso:country":"US",
    "sg:address":"6721 Scarborough Ave",
    "sg:city":"Las Vegas",
    "sg:classifiers":[
        {
            "category":"Building & Trades",
            "subcategory":"Construction",
            "type":"Services"
        }
    ],
    "sg:phone":"+1 702 456 7560",
    "sg:postcode":"89107",
    "sg:province":"NV",
    "sg:tags":[
        "handyman"
    ],
    "wof:name":"Your 24 Hour Handymen",
    "wof:placetype":"venue"
},
  "geometry": {"coordinates":[-115.243703,36.16685],"type":"Point"}
}