{
  "type": "Feature",
  "properties": {
    "iso:country":"US",
    "sg:address":"The Cts",
    "sg:city":"Las Vegas",
    "sg:classifiers":[
        {
            "category":"Building & Trades",
            "subcategory":"Construction",
            "type":"Services"
        }
    ],
    "sg:phone":"+1 702 257 1188",
    "sg:postcode":"89101",
    "sg:province":"NV",
    "sg:tags":[
        "contractor"
    ],
    "wof:name":"Astoria Homes",
    "wof:placetype":"venue"
},
  "geometry": {"coordinates":[-115.121005,36.171041],"type":"Point"}
}