{
  "type": "Feature",
  "properties": {
    "iso:country":"US",
    "sg:address":"1270 Berrum Ln",
    "sg:city":"Reno",
    "sg:classifiers":[
        {
            "category":"Retail",
            "subcategory":"Car Wash",
            "type":"Services"
        }
    ],
    "sg:phone":"+1 775 826 2076",
    "sg:postcode":"89509",
    "sg:province":"NV",
    "sg:tags":[
        "carwash",
        "automobile",
        "detail",
        "clean"
    ],
    "wof:name":"J & J Auto Detail",
    "wof:placetype":"venue"
},
  "geometry": {"coordinates":[-119.812092,39.493634],"type":"Point"}
}