{
  "type": "Feature",
  "properties": {
    "iso:country":"US",
    "sg:address":"1642 Sunrise View Dr",
    "sg:city":"Las Vegas",
    "sg:classifiers":[
        {
            "category":"Social Services",
            "subcategory":"Adult Care",
            "type":"Services"
        }
    ],
    "sg:phone":"+1 702 437 1473",
    "sg:postcode":"89156",
    "sg:province":"NV",
    "sg:tags":[
        "home",
        "residential"
    ],
    "wof:name":"Good Samaritan",
    "wof:placetype":"venue"
},
  "geometry": {"coordinates":[-115.042156,36.189364],"type":"Point"}
}