{
  "type": "Feature",
  "properties": {
    "iso:country":"US",
    "sg:address":"6436 Burgundy Way",
    "sg:city":"Las Vegas",
    "sg:classifiers":[
        {
            "category":"Professional",
            "subcategory":"Management & Consulting",
            "type":"Services"
        }
    ],
    "sg:phone":"+1 702 880 7878",
    "sg:postcode":"89107",
    "sg:province":"NV",
    "sg:tags":[
        "party",
        "planning"
    ],
    "wof:name":"Keg World",
    "wof:placetype":"venue"
},
  "geometry": {"coordinates":[-115.235315,36.165749],"type":"Point"}
}