{
  "type": "Feature",
  "properties": {
    "iso:country":"US",
    "sg:address":"2180 E Warm Springs Rd",
    "sg:city":"Las Vegas",
    "sg:classifiers":[
        {
            "category":"Real Estate",
            "subcategory":"Real Estate Operator",
            "type":"Services"
        }
    ],
    "sg:phone":"+1 866 642 9321",
    "sg:postcode":"89119",
    "sg:province":"NV",
    "sg:tags":[
        "apartment"
    ],
    "wof:name":"Camden Tiara",
    "wof:placetype":"venue"
},
  "geometry": {"coordinates":[-115.135809,36.057452],"type":"Point"}
}