{
  "type": "Feature",
  "properties": {
    "iso:country":"US",
    "sg:address":"5890 Ridge Ln",
    "sg:city":"Reno",
    "sg:classifiers":[
        {
            "category":"Retail",
            "subcategory":"Auto Repair",
            "type":"Services"
        }
    ],
    "sg:phone":"+1 775 741 2503",
    "sg:postcode":"89523",
    "sg:province":"NV",
    "sg:tags":[
        "automotive"
    ],
    "wof:name":"Mike Moble Mechanic",
    "wof:placetype":"venue"
},
  "geometry": {"coordinates":[-119.879777,39.53312],"type":"Point"}
}