{
  "type": "Feature",
  "properties": {
    "iso:country":"US",
    "sg:address":"4350 Arville St",
    "sg:city":"Las Vegas",
    "sg:classifiers":[
        {
            "category":"Wholesale",
            "subcategory":"Plants",
            "type":"Manufacturing & Wholesale Goods"
        }
    ],
    "sg:phone":"+1 702 876 6131",
    "sg:postcode":"89103",
    "sg:province":"NV",
    "sg:tags":[
        "stone",
        "cactus",
        "landscape",
        "supply"
    ],
    "wof:name":"Peacock Supply",
    "wof:placetype":"venue"
},
  "geometry": {"coordinates":[-115.199242,36.109107],"type":"Point"}
}