{
  "type": "Feature",
  "properties": {
    "iso:country":"US",
    "sg:address":"6334 W Sahara Ave",
    "sg:city":"Las Vegas",
    "sg:classifiers":[
        {
            "category":"Shopping",
            "subcategory":"Jewelry",
            "type":"Retail Goods"
        }
    ],
    "sg:phone":"+1 702 362 5625",
    "sg:postcode":"89146",
    "sg:province":"NV",
    "sg:tags":[
        "clocks"
    ],
    "wof:name":"Clock Gallery",
    "wof:placetype":"venue"
},
  "geometry": {"coordinates":[-115.230681,36.144192],"type":"Point"}
}