{
  "type": "Feature",
  "properties": {
    "iso:country":"US",
    "sg:address":"2764 Lake Sahara Drive",
    "sg:city":"Las Vegas",
    "sg:classifiers":[
        {
            "category":"Personal",
            "subcategory":"Beauty Salon",
            "type":"Services"
        },
        {
            "category":"Personal",
            "subcategory":"Day Spa",
            "type":"Services"
        }
    ],
    "sg:phone":"+1 702 242 4806",
    "sg:postcode":"89117",
    "sg:province":"NV",
    "sg:tags":[
        "hair"
    ],
    "sg:website":"www.azuresalonlv.com/",
    "wof:name":"Azure Salon & Spa",
    "wof:placetype":"venue"
},
  "geometry": {"coordinates":[-115.29068700000001,36.141286],"type":"Point"}
}