{
  "type": "Feature",
  "properties": {
    "iso:country":"US",
    "sg:address":"525 Waterwheel Falls Dr",
    "sg:city":"Henderson",
    "sg:classifiers":[
        {
            "category":"Real Estate",
            "subcategory":"Real Estate Agent",
            "type":"Services"
        }
    ],
    "sg:phone":"+1 702 281 5228",
    "sg:postcode":"89015",
    "sg:province":"NV",
    "sg:tags":[
        "inspection"
    ],
    "wof:name":"Preferred Property Inspection",
    "wof:placetype":"venue"
},
  "geometry": {"coordinates":[-115.00577,36.027726],"type":"Point"}
}