{
  "type": "Feature",
  "properties": {
    "iso:country":"US",
    "sg:address":"3960 Lilac Haze St",
    "sg:city":"Las Vegas",
    "sg:classifiers":[
        {
            "category":"Professional",
            "subcategory":"Business Services",
            "type":"Services"
        }
    ],
    "sg:phone":"+1 702 341 9811",
    "sg:postcode":"89147",
    "sg:province":"NV",
    "sg:tags":[
        "water",
        "treatment"
    ],
    "wof:name":"Superfoods Network",
    "wof:placetype":"venue"
},
  "geometry": {"coordinates":[-115.296342,36.118098],"type":"Point"}
}