{
  "type": "Feature",
  "properties": {
    "iso:country":"US",
    "sg:address":"571 Idaho St",
    "sg:city":"Elko",
    "sg:classifiers":[
        {
            "category":"Government",
            "subcategory":"Office",
            "type":"Public Place"
        },
        {
            "category":"Government",
            "subcategory":"Court House",
            "type":"Public Place"
        }
    ],
    "sg:phone":"+1 775 738 6526",
    "sg:postcode":"89801",
    "sg:province":"NV",
    "sg:tags":[
        "recorder",
        "municipality"
    ],
    "wof:name":"County of Elko",
    "wof:placetype":"venue"
},
  "geometry": {"coordinates":[-115.76278600000001,40.832909],"type":"Point"}
}