{
  "type": "Feature",
  "properties": {
    "iso:country":"US",
    "sg:address":"1350 Kelso Dunes Ave",
    "sg:city":"Henderson",
    "sg:classifiers":[
        {
            "category":"Real Estate",
            "subcategory":"Real Estate Operator",
            "type":"Services"
        }
    ],
    "sg:phone":"+1 702 568 5252",
    "sg:postcode":"89014",
    "sg:province":"NV",
    "sg:tags":[
        "apartment"
    ],
    "sg:website":"www.liveatalliance.com/adoberanc...",
    "wof:name":"Adobe Ranch Apartment Homes",
    "wof:placetype":"venue"
},
  "geometry": {"coordinates":[-115.044246,36.053836],"type":"Point"}
}