{
  "type": "Feature",
  "properties": {
    "iso:country":"US",
    "sg:address":"3823 Losee Rd",
    "sg:city":"North Las Vegas",
    "sg:classifiers":[
        {
            "category":"Building & Trades",
            "subcategory":"Plumbing",
            "type":"Services"
        }
    ],
    "sg:phone":"+1 702 642 1900",
    "sg:postcode":"89030",
    "sg:province":"NV",
    "sg:tags":[
        "contractor"
    ],
    "wof:name":"Majestic Plumbing Inc",
    "wof:placetype":"venue"
},
  "geometry": {"coordinates":[-115.119843,36.22758],"type":"Point"}
}