{
  "type": "Feature",
  "properties": {
    "iso:country":"US",
    "sg:address":"9383 Apache Spring",
    "sg:city":"Las Vegas",
    "sg:classifiers":[
        {
            "category":"Retail",
            "subcategory":"Laundry & Dry Cleaning",
            "type":"Services"
        }
    ],
    "sg:phone":"+1 702 362 6020",
    "sg:postcode":"89117",
    "sg:province":"NV",
    "sg:tags":[
        "cleaners",
        "rug",
        "carpet"
    ],
    "wof:name":"United Carpet Cleaning",
    "wof:placetype":"venue"
},
  "geometry": {"coordinates":[-115.295615,36.126545],"type":"Point"}
}