{
  "type": "Feature",
  "properties": {
    "iso:country":"US",
    "sg:address":"628 Village Blvd",
    "sg:city":"Incline Village",
    "sg:classifiers":[
        {
            "category":"Travel",
            "subcategory":"Travel Agent",
            "type":"Entertainment"
        }
    ],
    "sg:phone":"+1 775 831 5846",
    "sg:postcode":"89451",
    "sg:province":"NV",
    "sg:tags":[
        "agency",
        "bureau"
    ],
    "wof:name":"Incline Travel",
    "wof:placetype":"venue"
},
  "geometry": {"coordinates":[-119.947577,39.262458],"type":"Point"}
}