{
  "type": "Feature",
  "properties": {
    "iso:country":"US",
    "sg:address":"3062 Via del Corso",
    "sg:city":"Henderson",
    "sg:classifiers":[
        {
            "category":"Building & Trades",
            "subcategory":"Electrical",
            "type":"Services"
        }
    ],
    "sg:phone":"+1 702 876 6289",
    "sg:postcode":"89052",
    "sg:province":"NV",
    "sg:tags":[
        "special",
        "contractor"
    ],
    "wof:name":"VTAT Inc",
    "wof:placetype":"venue"
},
  "geometry": {"coordinates":[-115.120896,35.970142],"type":"Point"}
}