{
  "type": "Feature",
  "properties": {
    "iso:country":"US",
    "sg:address":"1407 Industrial Rd",
    "sg:city":"Las Vegas",
    "sg:classifiers":[
        {
            "category":"Wholesale",
            "subcategory":"Home Furnishings",
            "type":"Manufacturing & Wholesale Goods"
        }
    ],
    "sg:phone":"+1 702 383 8121",
    "sg:postcode":"89102",
    "sg:province":"NV",
    "sg:website":"www.milocorporation.com",
    "wof:name":"Milo Inc",
    "wof:placetype":"venue"
},
  "geometry": {"coordinates":[-115.158455,36.153806],"type":"Point"}
}