{
  "type": "Feature",
  "properties": {
    "iso:country":"US",
    "sg:address":"4387 W Sunset Rd",
    "sg:city":"Las Vegas",
    "sg:classifiers":[
        {
            "category":"Building & Trades",
            "subcategory":"Construction",
            "type":"Services"
        }
    ],
    "sg:phone":"+1 702 678 6787",
    "sg:postcode":"89118",
    "sg:province":"NV",
    "sg:tags":[
        "dry wall",
        "contractor"
    ],
    "wof:name":"Walldesign Inc",
    "wof:placetype":"venue"
},
  "geometry": {"coordinates":[-115.200743,36.071662],"type":"Point"}
}