{
  "type": "Feature",
  "properties": {
    "iso:country":"US",
    "sg:address":"42 S Water St",
    "sg:city":"Henderson",
    "sg:classifiers":[
        {
            "category":"Restaurant",
            "type":"Food & Drink"
        }
    ],
    "sg:phone":"+1 702 638 8200",
    "sg:postcode":"89015",
    "sg:province":"NV",
    "sg:tags":[
        "tea",
        "rooms"
    ],
    "wof:name":"Village Tea Shop",
    "wof:placetype":"venue"
},
  "geometry": {"coordinates":[-114.985722,36.035365],"type":"Point"}
}