{
  "type": "Feature",
  "properties": {
    "iso:country":"US",
    "sg:address":"85 Kirman Ave",
    "sg:city":"Reno",
    "sg:classifiers":[
        {
            "category":"Health Services",
            "subcategory":"Doctor",
            "type":"Services"
        }
    ],
    "sg:phone":"+1 775 329 0222",
    "sg:postcode":"89502",
    "sg:province":"NV",
    "wof:name":"Conrath Craig MD",
    "wof:placetype":"venue"
},
  "geometry": {"coordinates":[-119.798413,39.526196],"type":"Point"}
}