{
  "type": "Feature",
  "properties": {
    "iso:country":"US",
    "sg:address":"5317 S Eastern Ave",
    "sg:city":"Las Vegas",
    "sg:classifiers":[
        {
            "category":"Restaurant",
            "type":"Food & Drink"
        }
    ],
    "sg:phone":"+1 702 798 2898",
    "sg:postcode":"89119",
    "sg:province":"NV",
    "sg:tags":[
        "caterer"
    ],
    "wof:name":"Andes Corp",
    "wof:placetype":"venue"
},
  "geometry": {"coordinates":[-115.118916,36.090175],"type":"Point"}
}