{
  "type": "Feature",
  "properties": {
    "iso:country":"US",
    "sg:address":"4425 E Colton Ave",
    "sg:city":"Las Vegas",
    "sg:classifiers":[
        {
            "category":"Professional",
            "subcategory":"Management & Consulting",
            "type":"Services"
        }
    ],
    "sg:phone":"+1 702 643 2366",
    "sg:postcode":"89115",
    "sg:province":"NV",
    "sg:tags":[
        "construction"
    ],
    "wof:name":"Artic Pipe & Material",
    "wof:placetype":"venue"
},
  "geometry": {"coordinates":[-115.077296,36.221434],"type":"Point"}
}