{
  "type": "Feature",
  "properties": {
    "iso:country":"US",
    "sg:address":"395 W Minor St",
    "sg:city":"Winnemucca",
    "sg:classifiers":[
        {
            "category":"Health Services",
            "subcategory":"Doctor",
            "type":"Services"
        }
    ],
    "sg:phone":"+1 775 623 1228",
    "sg:postcode":"89445",
    "sg:province":"NV",
    "sg:tags":[
        "dentist"
    ],
    "wof:name":"Rick L Grant Inc",
    "wof:placetype":"venue"
},
  "geometry": {"coordinates":[-117.725339,40.963697],"type":"Point"}
}