{
  "type": "Feature",
  "properties": {
    "iso:country":"US",
    "sg:address":"1000 Mountain City Hwy",
    "sg:city":"Elko",
    "sg:classifiers":[
        {
            "category":"Retail",
            "subcategory":"Car Wash",
            "type":"Services"
        }
    ],
    "sg:phone":"+1 775 738 6738",
    "sg:postcode":"89801",
    "sg:province":"NV",
    "sg:tags":[
        "polishing",
        "washing"
    ],
    "wof:name":"K & L Car Wash",
    "wof:placetype":"venue"
},
  "geometry": {"coordinates":[-115.777644,40.828114],"type":"Point"}
}