{
  "type": "Feature",
  "properties": {
    "iso:country":"US",
    "sg:address":"9917 Shadowgate Ct",
    "sg:city":"Las Vegas",
    "sg:classifiers":[
        {
            "category":"Professional",
            "subcategory":"Management & Consulting",
            "type":"Services"
        }
    ],
    "sg:phone":"+1 702 515 6032",
    "sg:postcode":"89148",
    "sg:province":"NV",
    "sg:tags":[
        "marketing",
        "consultant"
    ],
    "wof:name":"Maximus Marketing",
    "wof:placetype":"venue"
},
  "geometry": {"coordinates":[-115.309458,36.097673],"type":"Point"}
}