{
  "type": "Feature",
  "properties": {
    "iso:country":"US",
    "sg:address":"89 N Nellis Blvd",
    "sg:city":"Las Vegas",
    "sg:classifiers":[
        {
            "category":"Shopping",
            "subcategory":"Shoes",
            "type":"Retail Goods"
        }
    ],
    "sg:phone":"+1 702 438 9928",
    "sg:postcode":"89110",
    "sg:province":"NV",
    "sg:tags":[
        "store"
    ],
    "sg:website":"www.payless.com",
    "wof:name":"Payless Shoesource",
    "wof:placetype":"venue"
},
  "geometry": {"coordinates":[-115.06199599999999,36.161499],"type":"Point"}
}