{
  "type": "Feature",
  "properties": {
    "iso:country":"US",
    "sg:address":"8160 S Eastern Ave",
    "sg:city":"Las Vegas",
    "sg:classifiers":[
        {
            "category":"Retail",
            "subcategory":"Laundry & Dry Cleaning",
            "type":"Services"
        }
    ],
    "sg:phone":"+1 702 269 9600",
    "sg:postcode":"89123",
    "sg:province":"NV",
    "wof:name":"Eldorado Cleaners",
    "wof:placetype":"venue"
},
  "geometry": {"coordinates":[-115.11823200000001,36.040619],"type":"Point"}
}