{
  "type": "Feature",
  "properties": {
    "iso:country":"US",
    "sg:address":"119 Bell St",
    "sg:city":"Reno",
    "sg:classifiers":[
        {
            "category":"Personal",
            "subcategory":"Massage",
            "type":"Services"
        },
        {
            "category":"Health Services",
            "subcategory":"Health Practitioner",
            "type":"Services"
        }
    ],
    "sg:phone":"+1 775 786 6515",
    "sg:postcode":"89503",
    "sg:province":"NV",
    "wof:name":"Alternative Health Massage",
    "wof:placetype":"venue"
},
  "geometry": {"coordinates":[-119.821129,39.525175],"type":"Point"}
}