{
  "type": "Feature",
  "properties": {
    "iso:country":"US",
    "sg:address":"846 Victorian Ave",
    "sg:city":"Sparks",
    "sg:classifiers":[
        {
            "category":"Professional",
            "subcategory":"Art Services",
            "type":"Services"
        }
    ],
    "sg:phone":"+1 775 626 4577",
    "sg:postcode":"89431",
    "sg:province":"NV",
    "sg:tags":[
        "graphic",
        "designer"
    ],
    "wof:name":"Fuze",
    "wof:placetype":"venue"
},
  "geometry": {"coordinates":[-119.753585,39.534941],"type":"Point"}
}