{
  "type": "Feature",
  "properties": {
    "iso:country":"US",
    "sg:address":"1960 Severn Dr",
    "sg:city":"Reno",
    "sg:classifiers":[
        {
            "category":"Building & Trades",
            "subcategory":"Electrical",
            "type":"Services"
        }
    ],
    "sg:phone":"+1 775 691 8477",
    "sg:postcode":"89503",
    "sg:province":"NV",
    "sg:tags":[
        "electric",
        "contractor"
    ],
    "wof:name":"Lance Electric",
    "wof:placetype":"venue"
},
  "geometry": {"coordinates":[-119.84426999999999,39.539521],"type":"Point"}
}