{
  "type": "Feature",
  "properties": {
    "iso:country":"US",
    "sg:address":"6661 Silverstream Avenue",
    "sg:city":"Las Vegas",
    "sg:classifiers":[
        {
            "category":"Real Estate",
            "subcategory":"Real Estate Operator",
            "type":"Services"
        }
    ],
    "sg:phone":"+1 702 877 0837",
    "sg:postcode":"89107",
    "sg:province":"NV",
    "sg:tags":[
        "apartment"
    ],
    "wof:name":"St Croix Apartments",
    "wof:placetype":"venue"
},
  "geometry": {"coordinates":[-115.240455,36.177599],"type":"Point"}
}