{
  "type": "Feature",
  "properties": {
    "iso:country":"US",
    "sg:address":"4890 W Tropicana Ave",
    "sg:city":"Las Vegas",
    "sg:classifiers":[
        {
            "category":"Food & Beverages",
            "subcategory":"Groceries & Convenience Stores",
            "type":"Retail Goods"
        }
    ],
    "sg:phone":"+1 702 871 5179",
    "sg:postcode":"89103",
    "sg:province":"NV",
    "wof:name":"7-Eleven",
    "wof:placetype":"venue"
},
  "geometry": {"coordinates":[-115.206879,36.10081],"type":"Point"}
}