{
  "type": "Feature",
  "properties": {
    "iso:country":"US",
    "sg:address":"3528 S Maryland Pkwy",
    "sg:city":"Las Vegas",
    "sg:classifiers":[
        {
            "category":"Sports & Exercise",
            "subcategory":"Bicycle Rental",
            "type":"Entertainment"
        }
    ],
    "sg:phone":"+1 702 369 9877",
    "sg:postcode":"89169",
    "sg:province":"NV",
    "sg:tags":[
        "wear"
    ],
    "sg:website":"www.lids.com",
    "wof:name":"Lids Corporation",
    "wof:placetype":"venue"
},
  "geometry": {"coordinates":[-115.136938,36.125661],"type":"Point"}
}