{
  "type": "Feature",
  "properties": {
    "iso:country":"US",
    "sg:address":"2885 S Decatur Blvd",
    "sg:city":"Las Vegas",
    "sg:classifiers":[
        {
            "category":"Restaurant",
            "type":"Food & Drink"
        }
    ],
    "sg:phone":"+1 702 873 3606",
    "sg:postcode":"89102",
    "sg:province":"NV",
    "wof:name":"Circle K Piccadilly Pizza",
    "wof:placetype":"venue"
},
  "geometry": {"coordinates":[-115.208107,36.140889],"type":"Point"}
}