{
  "type": "Feature",
  "properties": {
    "iso:country":"US",
    "sg:address":"74 N Pecos Rd",
    "sg:city":"Las Vegas",
    "sg:classifiers":[
        {
            "category":"Professional",
            "subcategory":"Accounting & Tax Preparation",
            "type":"Services"
        }
    ],
    "sg:phone":"+1 702 990 9991",
    "sg:postcode":"89101",
    "sg:province":"NV",
    "sg:tags":[
        "accountant"
    ],
    "wof:name":"Kristy Anaya CPA",
    "wof:placetype":"venue"
},
  "geometry": {"coordinates":[-115.101018,36.159029],"type":"Point"}
}