{
  "type": "Feature",
  "properties": {
    "iso:country":"US",
    "sg:address":"1033 S Rainbow Blvd",
    "sg:city":"Las Vegas",
    "sg:classifiers":[
        {
            "category":"Personal",
            "subcategory":"Tanning Parlor",
            "type":"Services"
        }
    ],
    "sg:phone":"+1 702 878 8267",
    "sg:postcode":"89145",
    "sg:province":"NV",
    "sg:tags":[
        "salon"
    ],
    "wof:name":"Totally Tan Inc",
    "wof:placetype":"venue"
},
  "geometry": {"coordinates":[-115.244332,36.165631],"type":"Point"}
}