{
  "type": "Feature",
  "properties": {
    "iso:country":"US",
    "sg:address":"2265 Village Walk Dr",
    "sg:city":"Henderson",
    "sg:classifiers":[
        {
            "category":"Home & Garden",
            "subcategory":"Home Furnishings",
            "type":"Retail Goods"
        },
        {
            "category":"Home & Garden",
            "subcategory":"Furniture",
            "type":"Retail Goods"
        }
    ],
    "sg:phone":"+1 702 270 3737",
    "sg:postcode":"89052",
    "sg:province":"NV",
    "sg:tags":[
        "decor",
        "kitchen",
        "store",
        "bath"
    ],
    "sg:website":"www.potterybarn.com",
    "wof:name":"Pottery Barn",
    "wof:placetype":"venue"
},
  "geometry": {"coordinates":[-115.084915,36.02179],"type":"Point"}
}