{
  "type": "Feature",
  "properties": {
    "iso:country":"US",
    "sg:address":"5380 S Valley View Blvd",
    "sg:city":"Las Vegas",
    "sg:classifiers":[
        {
            "category":"Manufacturing",
            "subcategory":"Building Materials",
            "type":"Manufacturing & Wholesale Goods"
        }
    ],
    "sg:phone":"+1 702 597 2230",
    "sg:postcode":"89118",
    "sg:province":"NV",
    "sg:website":"www.gmmonarchwest.com",
    "wof:name":"G M Monarch West",
    "wof:placetype":"venue"
},
  "geometry": {"coordinates":[-115.18977099999999,36.093277],"type":"Point"}
}