{
  "type": "Feature",
  "properties": {
    "iso:country":"US",
    "sg:address":"3545 Vista Blvd",
    "sg:city":"Sparks",
    "sg:classifiers":[
        {
            "category":"Building & Trades",
            "subcategory":"Plumbing",
            "type":"Services"
        }
    ],
    "sg:phone":"+1 775 626 6208",
    "sg:postcode":"89436",
    "sg:province":"NV",
    "sg:tags":[
        "m",
        "contractor"
    ],
    "wof:name":"Four Seasons Mechanical",
    "wof:placetype":"venue"
},
  "geometry": {"coordinates":[-119.70576699999999,39.564363],"type":"Point"}
}