{
  "type": "Feature",
  "properties": {
    "iso:country":"US",
    "sg:address":"3915 W Hacienda Ave",
    "sg:city":"Las Vegas",
    "sg:classifiers":[
        {
            "category":"Home & Garden",
            "subcategory":"Home Furnishings",
            "type":"Retail Goods"
        }
    ],
    "sg:phone":"+1 702 360 0951",
    "sg:postcode":"89118",
    "sg:province":"NV",
    "sg:tags":[
        "venetian",
        "blind"
    ],
    "wof:name":"P & J Custom Window Coverings",
    "wof:placetype":"venue"
},
  "geometry": {"coordinates":[-115.192689,36.093534],"type":"Point"}
}