{
  "type": "Feature",
  "properties": {
    "iso:country":"US",
    "sg:address":"3100 E Charleston Blvd",
    "sg:city":"Las Vegas",
    "sg:classifiers":[
        {
            "category":"Professional",
            "subcategory":"Management & Consulting",
            "type":"Services"
        }
    ],
    "sg:phone":"+1 702 207 2034",
    "sg:postcode":"89104",
    "sg:province":"NV",
    "sg:tags":[
        "business"
    ],
    "sg:website":"www.prattcommunications.com",
    "wof:name":"Pratt Communications",
    "wof:placetype":"venue"
},
  "geometry": {"coordinates":[-115.10350099999999,36.158836],"type":"Point"}
}