{
  "type": "Feature",
  "properties": {
    "iso:country":"US",
    "sg:address":"1795 Peavine Ct",
    "sg:city":"Reno",
    "sg:classifiers":[
        {
            "category":"Professional",
            "type":"Services"
        }
    ],
    "sg:phone":"+1 775 746 1783",
    "sg:postcode":"89503",
    "sg:province":"NV",
    "wof:name":"Manuel F Magallanes Services",
    "wof:placetype":"venue"
},
  "geometry": {"coordinates":[-119.842514,39.546942],"type":"Point"}
}