{
  "type": "Feature",
  "properties": {
    "iso:country":"US",
    "sg:address":"2500 N Tenaya Way",
    "sg:city":"Las Vegas",
    "sg:classifiers":[
        {
            "category":"Health Services",
            "subcategory":"Hospital",
            "type":"Services"
        }
    ],
    "sg:phone":"+1 702 562 2021",
    "sg:postcode":"89128",
    "sg:province":"NV",
    "sg:website":"www.healthsouth.com",
    "wof:name":"Healthsouth Hospital At Tenaya",
    "wof:placetype":"venue"
},
  "geometry": {"coordinates":[-115.25154999999999,36.205794],"type":"Point"}
}