{
  "type": "Feature",
  "properties": {
    "iso:country":"US",
    "sg:address":"3261 Fritz Ln",
    "sg:city":"Pahrump",
    "sg:classifiers":[
        {
            "category":"Banks & Credit Unions",
            "subcategory":"Bank",
            "type":"Services"
        }
    ],
    "sg:phone":"+1 775 727 7343",
    "sg:postcode":"89048",
    "sg:province":"NV",
    "sg:tags":[
        "mortgage"
    ],
    "wof:name":"Direct Equity",
    "wof:placetype":"venue"
},
  "geometry": {"coordinates":[-116.07122699999999,36.199058],"type":"Point"}
}