{
  "type": "Feature",
  "properties": {
    "iso:country":"US",
    "sg:address":"1 US Hwy 95 Alt",
    "sg:city":"Yerington",
    "sg:classifiers":[
        {
            "category":"Wholesale",
            "subcategory":"Stationery",
            "type":"Manufacturing & Wholesale Goods"
        }
    ],
    "sg:phone":"+1 775 463 3325",
    "sg:postcode":"89447",
    "sg:province":"NV",
    "sg:tags":[
        "packaging",
        "material"
    ],
    "wof:name":"GTG Packaging",
    "wof:placetype":"venue"
},
  "geometry": {"coordinates":[-119.16359300000001,38.993884],"type":"Point"}
}