{
  "type": "Feature",
  "properties": {
    "iso:country":"US",
    "sg:address":"4440 E Tropicana Ave",
    "sg:city":"Las Vegas",
    "sg:classifiers":[
        {
            "category":"Shopping",
            "type":"Retail Goods"
        }
    ],
    "sg:phone":"+1 702 436 0278",
    "sg:postcode":"89121",
    "sg:province":"NV",
    "sg:tags":[
        "art",
        "gallery",
        "dealer"
    ],
    "wof:name":"Art Man",
    "wof:placetype":"venue"
},
  "geometry": {"coordinates":[-115.077708,36.100358],"type":"Point"}
}