{
  "type": "Feature",
  "properties": {
    "iso:country":"US",
    "sg:address":"3420 Las Vegas Blvd N",
    "sg:city":"Las Vegas",
    "sg:classifiers":[
        {
            "category":"Retail",
            "subcategory":"Auto Repair",
            "type":"Services"
        }
    ],
    "sg:phone":"+1 702 644 3826",
    "sg:postcode":"89115",
    "sg:province":"NV",
    "sg:tags":[
        "repairing",
        "automobile"
    ],
    "wof:name":"Macmurray Muffler Shop",
    "wof:placetype":"venue"
},
  "geometry": {"coordinates":[-115.080709,36.225005],"type":"Point"}
}