{
  "type": "Feature",
  "properties": {
    "iso:country":"US",
    "sg:address":"953 E Sahara Ave",
    "sg:city":"Las Vegas",
    "sg:classifiers":[
        {
            "category":"Arts & Performance",
            "subcategory":"Dance",
            "type":"Entertainment"
        }
    ],
    "sg:postcode":"89109",
    "sg:province":"NV",
    "sg:tags":[
        "school"
    ],
    "wof:name":"Gina Kim Korean Dance Academy",
    "wof:placetype":"venue"
},
  "geometry": {"coordinates":[-115.142319,36.143247],"type":"Point"}
}