{
  "type": "Feature",
  "properties": {
    "iso:country":"US",
    "sg:address":"6605 Las Vegas Blvd S",
    "sg:city":"Las Vegas",
    "sg:classifiers":[
        {
            "category":"Shopping",
            "subcategory":"Mobile Phones",
            "type":"Retail Goods"
        }
    ],
    "sg:phone":"+1 702 896 0050",
    "sg:postcode":"89119",
    "sg:province":"NV",
    "wof:name":"Cell Planet",
    "wof:placetype":"venue"
},
  "geometry": {"coordinates":[-115.17263,36.069219],"type":"Point"}
}