{
  "type": "Feature",
  "properties": {
    "iso:country":"US",
    "sg:address":"225 W Williams Ave",
    "sg:city":"Fallon",
    "sg:classifiers":[
        {
            "category":"Autos & Motor Vehicles",
            "subcategory":"Automobile Sales",
            "type":"Retail Goods"
        }
    ],
    "sg:phone":"+1 775 423 8841",
    "sg:postcode":"89406",
    "sg:province":"NV",
    "sg:tags":[
        "car",
        "dealer"
    ],
    "wof:name":"E-Zee Auto Sales",
    "wof:placetype":"venue"
},
  "geometry": {"coordinates":[-118.780027,39.474729],"type":"Point"}
}