{
  "type": "Feature",
  "properties": {
    "iso:country":"US",
    "sg:address":"1555 Eli Dr",
    "sg:city":"Reno",
    "sg:classifiers":[
        {
            "category":"Building & Trades",
            "subcategory":"Landscaping Services",
            "type":"Services"
        }
    ],
    "sg:phone":"+1 775 851 2227",
    "sg:postcode":"89511",
    "sg:province":"NV",
    "wof:name":"Spanish Gardener",
    "wof:placetype":"venue"
},
  "geometry": {"coordinates":[-119.77968,39.436893],"type":"Point"}
}