{
  "type": "Feature",
  "properties": {
    "iso:country":"US",
    "sg:address":"5716 Pine Cone Pl",
    "sg:city":"Las Vegas",
    "sg:classifiers":[
        {
            "category":"Social Services",
            "subcategory":"Child Care",
            "type":"Services"
        }
    ],
    "sg:phone":"+1 702 646 8893",
    "sg:postcode":"89108",
    "sg:province":"NV",
    "wof:name":"Carrie Jones Family Day Care",
    "wof:placetype":"venue"
},
  "geometry": {"coordinates":[-115.218913,36.191375],"type":"Point"}
}