{
  "type": "Feature",
  "properties": {
    "iso:country":"US",
    "sg:address":"465 E Main St",
    "sg:city":"Fernley",
    "sg:classifiers":[
        {
            "category":"Home & Garden",
            "subcategory":"Hardware",
            "type":"Retail Goods"
        }
    ],
    "sg:phone":"+1 775 575 5599",
    "sg:postcode":"89408",
    "sg:province":"NV",
    "wof:name":"Wallace True Value Hardware",
    "wof:placetype":"venue"
},
  "geometry": {"coordinates":[-119.242071,39.607153],"type":"Point"}
}