{
  "type": "Feature",
  "properties": {
    "iso:country":"US",
    "sg:address":"500 Hillside Dr",
    "sg:city":"Mesquite",
    "sg:classifiers":[
        {
            "category":"Government",
            "subcategory":"Jail",
            "type":"Public Place"
        }
    ],
    "sg:phone":"+1 702 346 6925",
    "sg:postcode":"89027",
    "sg:province":"NV",
    "sg:tags":[
        "govt",
        "city",
        "institution"
    ],
    "wof:name":"Mesquite City Detention Ctr",
    "wof:placetype":"venue"
},
  "geometry": {"coordinates":[-114.057867,36.813127],"type":"Point"}
}