{
  "type": "Feature",
  "properties": {
    "iso:country":"US",
    "sg:address":"3850 E Flamingo Rd",
    "sg:city":"Las Vegas",
    "sg:classifiers":[
        {
            "category":"Shopping",
            "type":"Retail Goods"
        }
    ],
    "sg:phone":"+1 702 433 7351",
    "sg:postcode":"89121",
    "sg:province":"NV",
    "sg:tags":[
        "telephone",
        "cellular"
    ],
    "wof:name":"Cellular Plus",
    "wof:placetype":"venue"
},
  "geometry": {"coordinates":[-115.091283,36.115331],"type":"Point"}
}