{
  "type": "Feature",
  "properties": {
    "iso:country":"US",
    "sg:address":"2901 E Sahara Ave",
    "sg:city":"Las Vegas",
    "sg:classifiers":[
        {
            "category":"Professional",
            "type":"Services"
        }
    ],
    "sg:phone":"+1 702 457 0809",
    "sg:postcode":"89104",
    "sg:province":"NV",
    "wof:name":"US Armed Forces Reserve Ctr",
    "wof:placetype":"venue"
},
  "geometry": {"coordinates":[-115.112996,36.144255],"type":"Point"}
}