{
  "type": "Feature",
  "properties": {
    "iso:country":"US",
    "sg:address":"6747 Spencer St",
    "sg:city":"Las Vegas",
    "sg:classifiers":[
        {
            "category":"Wholesale",
            "subcategory":"Office Equipment",
            "type":"Manufacturing & Wholesale Goods"
        }
    ],
    "sg:phone":"+1 702 436 4434",
    "sg:postcode":"89119",
    "sg:province":"NV",
    "sg:tags":[
        "machine",
        "duplicating",
        "copying"
    ],
    "sg:website":"www.imagistics.com",
    "wof:name":"Mountain Business Products",
    "wof:placetype":"venue"
},
  "geometry": {"coordinates":[-115.12773799999999,36.067265],"type":"Point"}
}