{
  "type": "Feature",
  "properties": {
    "iso:country":"US",
    "sg:address":"3871 S. Valley View Blvd #7",
    "sg:city":"Las Vegas",
    "sg:classifiers":[
        {
            "category":"Personal",
            "subcategory":"Massage",
            "type":"Services"
        }
    ],
    "sg:phone":"+1 702 251 3888",
    "sg:postcode":"89103",
    "sg:province":"NV",
    "wof:name":"Water Cubes Reflexology",
    "wof:placetype":"venue"
},
  "geometry": {"coordinates":[-115.191306,36.119639],"type":"Point"}
}