{
  "type": "Feature",
  "properties": {
    "iso:country":"US",
    "sg:address":"160 E Gault Way",
    "sg:city":"Sparks",
    "sg:classifiers":[
        {
            "category":"Organizations",
            "subcategory":"Religious Organization",
            "type":"Services"
        }
    ],
    "sg:phone":"+1 775 356 0753",
    "sg:postcode":"89431",
    "sg:province":"NV",
    "sg:tags":[
        "church"
    ],
    "wof:name":"Living Ch Of Religious Science",
    "wof:placetype":"venue"
},
  "geometry": {"coordinates":[-119.738198,39.555897],"type":"Point"}
}