{
  "type": "Feature",
  "properties": {
    "iso:country":"US",
    "sg:address":"144 West St",
    "sg:city":"Reno",
    "sg:classifiers":[
        {
            "category":"Bars & Pubs",
            "type":"Food & Drink"
        }
    ],
    "sg:phone":"+1 775 324 1224",
    "sg:postcode":"89501",
    "sg:province":"NV",
    "sg:tags":[
        "lounge",
        "cocktail"
    ],
    "wof:name":"Green Room",
    "wof:placetype":"venue"
},
  "geometry": {"coordinates":[-119.815697,39.52588],"type":"Point"}
}