{
  "type": "Feature",
  "properties": {
    "iso:country":"US",
    "sg:address":"3141 Westwood Dr",
    "sg:city":"Las Vegas",
    "sg:classifiers":[
        {
            "category":"Building & Trades",
            "subcategory":"Plumbing",
            "type":"Services"
        }
    ],
    "sg:phone":"+1 702 876 7778",
    "sg:postcode":"89109",
    "sg:province":"NV",
    "sg:tags":[
        "contractor"
    ],
    "wof:name":"Quality Air Conditioning",
    "wof:placetype":"venue"
},
  "geometry": {"coordinates":[-115.176269,36.136093],"type":"Point"}
}