{
  "type": "Feature",
  "properties": {
    "iso:country":"US",
    "sg:address":"5491 Cow Town Ln",
    "sg:city":"Las Vegas",
    "sg:classifiers":[
        {
            "category":"Manufacturing",
            "subcategory":"Tools & Machinery",
            "type":"Manufacturing & Wholesale Goods"
        }
    ],
    "sg:phone":"+1 702 873 4306",
    "sg:postcode":"89118",
    "sg:province":"NV",
    "sg:tags":[
        "manufacture",
        "equipment",
        "electrical"
    ],
    "wof:name":"Video Walls USA Inc",
    "wof:placetype":"venue"
},
  "geometry": {"coordinates":[-115.223931,36.089849],"type":"Point"}
}