{
  "type": "Feature",
  "properties": {
    "iso:country":"US",
    "sg:address":"4800 Vegas Valley Dr",
    "sg:city":"Las Vegas",
    "sg:classifiers":[
        {
            "category":"Health Services",
            "subcategory":"Clinic",
            "type":"Services"
        }
    ],
    "sg:phone":"+1 702 812 4917",
    "sg:postcode":"89121",
    "sg:province":"NV",
    "wof:name":"Madge Cassel Reflexologist",
    "wof:placetype":"venue"
},
  "geometry": {"coordinates":[-115.06612,36.137048],"type":"Point"}
}