{
  "type": "Feature",
  "properties": {
    "iso:country":"US",
    "sg:address":"1545 S Wells Ave",
    "sg:city":"Reno",
    "sg:classifiers":[
        {
            "category":"Shopping",
            "subcategory":"Gifts & Souvenirs",
            "type":"Retail Goods"
        }
    ],
    "sg:phone":"+1 775 358 0577",
    "sg:postcode":"89502",
    "sg:province":"NV",
    "sg:tags":[
        "balloon",
        "artist"
    ],
    "wof:name":"Balloons & Toons",
    "wof:placetype":"venue"
},
  "geometry": {"coordinates":[-119.803135,39.510901],"type":"Point"}
}