{
  "type": "Feature",
  "properties": {
    "iso:country":"US",
    "sg:address":"1863 Helm Dr",
    "sg:city":"Las Vegas",
    "sg:classifiers":[
        {
            "category":"Professional",
            "subcategory":"Advertising",
            "type":"Services"
        }
    ],
    "sg:phone":"+1 702 873 4600",
    "sg:postcode":"89119",
    "sg:province":"NV",
    "sg:tags":[
        "outdoor"
    ],
    "sg:website":"www.lamar.com",
    "wof:name":"Lamar Advertising Co",
    "wof:placetype":"venue"
},
  "geometry": {"coordinates":[-115.126306,36.068022],"type":"Point"}
}