{
  "type": "Feature",
  "properties": {
    "iso:country":"US",
    "sg:address":"4124 Fairport",
    "sg:city":"North Las Vegas",
    "sg:classifiers":[
        {
            "category":"Shopping",
            "subcategory":"Stationery & Office Supplies",
            "type":"Retail Goods"
        }
    ],
    "sg:phone":"+1 702 647 6109",
    "sg:postcode":"89032",
    "sg:province":"NV",
    "sg:tags":[
        "album",
        "scrapbook"
    ],
    "wof:name":"Creative Memories",
    "wof:placetype":"venue"
},
  "geometry": {"coordinates":[-115.186252,36.234146],"type":"Point"}
}