{
  "type": "Feature",
  "properties": {
    "iso:country":"US",
    "sg:address":"131 Greenbriar Townhouse Way",
    "sg:city":"Las Vegas",
    "sg:classifiers":[
        {
            "category":"Home & Garden",
            "subcategory":"Home Furnishings",
            "type":"Retail Goods"
        }
    ],
    "sg:phone":"+1 702 367 1435",
    "sg:postcode":"89121",
    "sg:province":"NV",
    "sg:tags":[
        "curtain",
        "made",
        "drapery"
    ],
    "wof:name":"Designs By J",
    "wof:placetype":"venue"
},
  "geometry": {"coordinates":[-115.093014,36.133671],"type":"Point"}
}