{
  "type": "Feature",
  "properties": {
    "iso:country":"US",
    "sg:address":"7501 W Washington Ave",
    "sg:city":"Las Vegas",
    "sg:classifiers":[
        {
            "category":"Retail",
            "subcategory":"Auto Repair",
            "type":"Services"
        }
    ],
    "sg:phone":"+1 702 242 1018",
    "sg:postcode":"89128",
    "sg:province":"NV",
    "sg:tags":[
        "repairing",
        "automobile"
    ],
    "wof:name":"Purrfect Auto Svc",
    "wof:placetype":"venue"
},
  "geometry": {"coordinates":[-115.252607,36.181262],"type":"Point"}
}