{
  "type": "Feature",
  "properties": {
    "iso:country":"US",
    "sg:address":"208 W 4th St",
    "sg:city":"Reno",
    "sg:classifiers":[
        {
            "category":"Food & Beverages",
            "subcategory":"Liquor & Beverages",
            "type":"Retail Goods"
        }
    ],
    "sg:phone":"+1 775 329 4657",
    "sg:postcode":"89501",
    "sg:province":"NV",
    "wof:name":"Paradise Food & Liquor",
    "wof:placetype":"venue"
},
  "geometry": {"coordinates":[-119.818063,39.529107],"type":"Point"}
}