{
  "type": "Feature",
  "properties": {
    "iso:country":"US",
    "sg:address":"2500 N Buffalo Dr",
    "sg:city":"Las Vegas",
    "sg:classifiers":[
        {
            "category":"Real Estate",
            "subcategory":"Real Estate Agent",
            "type":"Services"
        }
    ],
    "sg:phone":"+1 702 838 2520",
    "sg:postcode":"89128",
    "sg:province":"NV",
    "wof:name":"Industrial Properties Dev",
    "wof:placetype":"venue"
},
  "geometry": {"coordinates":[-115.260653,36.204136],"type":"Point"}
}