{
  "type": "Feature",
  "properties": {
    "iso:country":"US",
    "sg:address":"4500 Arville St",
    "sg:city":"Las Vegas",
    "sg:classifiers":[
        {
            "category":"Retail",
            "subcategory":"Auto Repair",
            "type":"Services"
        }
    ],
    "sg:phone":"+1 702 269 9751",
    "sg:postcode":"89103",
    "sg:province":"NV",
    "sg:tags":[
        "body",
        "automobile",
        "painting"
    ],
    "wof:name":"Restoration Station",
    "wof:placetype":"venue"
},
  "geometry": {"coordinates":[-115.199241,36.104537],"type":"Point"}
}