{
  "type": "Feature",
  "properties": {
    "iso:country":"US",
    "sg:address":"10250 Ferret Cir",
    "sg:city":"Reno",
    "sg:classifiers":[
        {
            "category":"Restaurant",
            "type":"Food & Drink"
        }
    ],
    "sg:phone":"+1 775 345 6121",
    "sg:postcode":"89523",
    "sg:province":"NV",
    "sg:tags":[
        "eating"
    ],
    "wof:name":"Herb Elegant Catering Co",
    "wof:placetype":"venue"
},
  "geometry": {"coordinates":[-119.926446,39.519382],"type":"Point"}
}