{
  "type": "Feature",
  "properties": {
    "iso:country":"US",
    "sg:address":"3035 E Patrick Ln",
    "sg:city":"Las Vegas",
    "sg:classifiers":[
        {
            "category":"Building & Trades",
            "subcategory":"Construction",
            "type":"Services"
        }
    ],
    "sg:phone":"+1 702 243 2500",
    "sg:postcode":"89120",
    "sg:province":"NV",
    "sg:tags":[
        "asbestos",
        "removal"
    ],
    "wof:name":"Walker Specialty Construction",
    "wof:placetype":"venue"
},
  "geometry": {"coordinates":[-115.107902,36.078924],"type":"Point"}
}