{
  "type": "Feature",
  "properties": {
    "iso:country":"US",
    "sg:address":"1102 N Curry St",
    "sg:city":"Carson City",
    "sg:classifiers":[
        {
            "category":"Insurance",
            "subcategory":"Insurance Agent",
            "type":"Services"
        }
    ],
    "sg:phone":"+1 775 885 0100",
    "sg:postcode":"89703",
    "sg:province":"NV",
    "wof:name":"Allstate",
    "wof:placetype":"venue"
},
  "geometry": {"coordinates":[-119.767866,39.170465],"type":"Point"}
}