{
  "type": "Feature",
  "properties": {
    "iso:country":"US",
    "sg:address":"3504 Chevy Chase Ave",
    "sg:city":"Las Vegas",
    "sg:classifiers":[
        {
            "category":"Building & Trades",
            "subcategory":"Cleaning & Sanitation",
            "type":"Services"
        }
    ],
    "sg:phone":"+1 702 452 3303",
    "sg:postcode":"89110",
    "sg:province":"NV",
    "sg:tags":[
        "repair",
        "maintenance"
    ],
    "wof:name":"J J Rooter Service Inc",
    "wof:placetype":"venue"
},
  "geometry": {"coordinates":[-115.097537,36.183247],"type":"Point"}
}