{
  "type": "Feature",
  "properties": {
    "iso:country":"US",
    "sg:address":"5335 Snyder Ave",
    "sg:city":"Carson City",
    "sg:classifiers":[
        {
            "category":"Organizations",
            "subcategory":"Religious Organization",
            "type":"Services"
        }
    ],
    "sg:phone":"+1 775 882 1967",
    "sg:postcode":"89701",
    "sg:province":"NV",
    "sg:tags":[
        "catholic",
        "church"
    ],
    "wof:name":"Corpus Christi Catholic Church",
    "wof:placetype":"venue"
},
  "geometry": {"coordinates":[-119.75421900000001,39.116558],"type":"Point"}
}