{
  "type": "Feature",
  "properties": {
    "iso:country":"US",
    "sg:address":"11 Bullion Dr",
    "sg:city":"Carson City",
    "sg:classifiers":[
        {
            "category":"Manufacturing",
            "subcategory":"Electronics",
            "type":"Manufacturing & Wholesale Goods"
        }
    ],
    "sg:phone":"+1 775 885 7737",
    "sg:postcode":"89706",
    "sg:province":"NV",
    "sg:tags":[
        "rf",
        "amplifier",
        "sales"
    ],
    "wof:name":"IMT Rf Products",
    "wof:placetype":"venue"
},
  "geometry": {"coordinates":[-119.746271,39.177347],"type":"Point"}
}