{
  "type": "Feature",
  "properties": {
    "iso:country":"US",
    "sg:address":"6650 N Durango Dr",
    "sg:city":"Las Vegas",
    "sg:classifiers":[
        {
            "category":"Building & Trades",
            "subcategory":"Construction",
            "type":"Services"
        }
    ],
    "sg:phone":"+1 702 228 4866",
    "sg:postcode":"89149",
    "sg:province":"NV",
    "sg:tags":[
        "designer",
        "dealer",
        "pool",
        "swimming"
    ],
    "wof:name":"Mr Pool & Mrs Patio",
    "wof:placetype":"venue"
},
  "geometry": {"coordinates":[-115.278595,36.282765],"type":"Point"}
}