{
  "type": "Feature",
  "properties": {
    "iso:country":"US",
    "sg:address":"1960 E Maule Ave",
    "sg:city":"Las Vegas",
    "sg:classifiers":[
        {
            "category":"Professional",
            "type":"Services"
        }
    ],
    "sg:phone":"+1 702 798 4433",
    "sg:postcode":"89119",
    "sg:province":"NV",
    "wof:name":"Nevada Environmental Care Inc",
    "wof:placetype":"venue"
},
  "geometry": {"coordinates":[-115.124726,36.064518],"type":"Point"}
}