{
  "type": "Feature",
  "properties": {
    "iso:country":"US",
    "sg:address":"2650 16th St",
    "sg:city":"Sparks",
    "sg:classifiers":[
        {
            "category":"Real Estate",
            "subcategory":"Real Estate Operator",
            "type":"Services"
        }
    ],
    "sg:phone":"+1 775 331 7066",
    "sg:postcode":"89431",
    "sg:province":"NV",
    "sg:tags":[
        "apartment"
    ],
    "wof:name":"Bethel Plaza Apartments",
    "wof:placetype":"venue"
},
  "geometry": {"coordinates":[-119.763663,39.554504],"type":"Point"}
}