{
  "type": "Feature",
  "properties": {
    "iso:country":"US",
    "sg:address":"4760 W Sahara Ave",
    "sg:city":"Las Vegas",
    "sg:classifiers":[
        {
            "category":"Real Estate",
            "subcategory":"Developer",
            "type":"Services"
        }
    ],
    "sg:phone":"+1 702 258 4330",
    "sg:postcode":"89102",
    "sg:province":"NV",
    "sg:tags":[
        "building",
        "operator",
        "nonresidential"
    ],
    "wof:name":"Sahara Pavilion Management Off",
    "wof:placetype":"venue"
},
  "geometry": {"coordinates":[-115.20813800000001,36.144522],"type":"Point"}
}