{
  "type": "Feature",
  "properties": {
    "iso:country":"US",
    "sg:address":"730 S Rampart Blvd",
    "sg:city":"Las Vegas",
    "sg:classifiers":[
        {
            "category":"Food & Beverages",
            "subcategory":"Liquor & Beverages",
            "type":"Retail Goods"
        }
    ],
    "sg:phone":"+1 702 933 8740",
    "sg:postcode":"89145",
    "sg:province":"NV",
    "sg:tags":[
        "beer",
        "spirit",
        "wine"
    ],
    "sg:website":"www.totalwine.com",
    "wof:name":"Total Wine & More",
    "wof:placetype":"venue"
},
  "geometry": {"coordinates":[-115.291478,36.162448],"type":"Point"}
}