{
  "type": "Feature",
  "properties": {
    "iso:country":"US",
    "sg:address":"628 Las Vegas Blvd S",
    "sg:city":"Las Vegas",
    "sg:classifiers":[
        {
            "category":"Shopping",
            "subcategory":"Tobacco",
            "type":"Retail Goods"
        }
    ],
    "sg:phone":"+1 702 489 7581",
    "sg:postcode":"89101",
    "sg:province":"NV",
    "sg:tags":[
        "shop"
    ],
    "wof:name":"Weedz Alternatives",
    "wof:placetype":"venue"
},
  "geometry": {"coordinates":[-115.144867,36.163203],"type":"Point"}
}