{
  "type": "Feature",
  "properties": {
    "iso:country":"US",
    "sg:address":"1225 Dartmouth Ave",
    "sg:city":"Lovelock",
    "sg:classifiers":[
        {
            "category":"Freight",
            "type":"Transportation"
        }
    ],
    "sg:phone":"+1 775 273 9310",
    "sg:postcode":"89419",
    "sg:province":"NV",
    "sg:tags":[
        "broker"
    ],
    "wof:name":"Southern Transport Co",
    "wof:placetype":"venue"
},
  "geometry": {"coordinates":[-118.473913,40.183028],"type":"Point"}
}