{
  "type": "Feature",
  "properties": {
    "iso:country":"US",
    "sg:address":"3920 Ron Ct",
    "sg:city":"Las Vegas",
    "sg:classifiers":[
        {
            "category":"Health Services",
            "subcategory":"Doctor",
            "type":"Services"
        }
    ],
    "sg:phone":"+1 702 734 0071",
    "sg:postcode":"89115",
    "sg:province":"NV",
    "sg:tags":[
        "medical"
    ],
    "wof:name":"Ellis Bandt Birkin Kollins",
    "wof:placetype":"venue"
},
  "geometry": {"coordinates":[-115.08901,36.235641],"type":"Point"}
}