{
  "type": "Feature",
  "properties": {
    "iso:country":"US",
    "sg:address":"6039 Eldora Ave Ste E",
    "sg:city":"Las Vegas",
    "sg:classifiers":[
        {
            "category":"Health Services",
            "subcategory":"Doctor",
            "type":"Services"
        }
    ],
    "sg:phone":"+1 702 228 4900",
    "sg:postcode":"89146",
    "sg:province":"NV",
    "sg:tags":[
        "psychiatrist"
    ],
    "wof:name":"Eldora Medical Associates",
    "wof:placetype":"venue"
},
  "geometry": {"coordinates":[-115.224407,36.140361],"type":"Point"}
}