{
  "type": "Feature",
  "properties": {
    "iso:country":"US",
    "sg:address":"2201 S 17th St",
    "sg:city":"Las Vegas",
    "sg:classifiers":[
        {
            "category":"Professional",
            "subcategory":"Business Services",
            "type":"Services"
        }
    ],
    "sg:phone":"+1 702 735 4641",
    "sg:postcode":"89104",
    "sg:province":"NV",
    "wof:name":"Global Assoc of Nevada",
    "wof:placetype":"venue"
},
  "geometry": {"coordinates":[-115.128455,36.146915],"type":"Point"}
}