{
  "type": "Feature",
  "properties": {
    "iso:country":"US",
    "sg:address":"1810 S Christy Ln",
    "sg:city":"Las Vegas",
    "sg:classifiers":[
        {
            "category":"Building & Trades",
            "subcategory":"Cleaning & Sanitation",
            "type":"Services"
        }
    ],
    "sg:phone":"+1 702 451 0461",
    "sg:postcode":"89142",
    "sg:province":"NV",
    "sg:tags":[
        "janitor",
        "maintenance"
    ],
    "wof:name":"Quisqueya Cleaning Services",
    "wof:placetype":"venue"
},
  "geometry": {"coordinates":[-115.05372699999999,36.151932],"type":"Point"}
}