{
  "type": "Feature",
  "properties": {
    "iso:country":"US",
    "sg:address":"8520 W 4th St",
    "sg:city":"Reno",
    "sg:classifiers":[
        {
            "category":"Banks & Credit Unions",
            "subcategory":"Bank",
            "type":"Services"
        }
    ],
    "sg:phone":"+1 775 787 6500",
    "sg:postcode":"89523",
    "sg:province":"NV",
    "sg:tags":[
        "loan",
        "real estate"
    ],
    "wof:name":"Wise Financial Svc",
    "wof:placetype":"venue"
},
  "geometry": {"coordinates":[-119.897367,39.509232],"type":"Point"}
}