{
  "type": "Feature",
  "properties": {
    "iso:country":"US",
    "sg:address":"6330 W Charleston Blvd",
    "sg:city":"Las Vegas",
    "sg:classifiers":[
        {
            "category":"Shopping",
            "subcategory":"Clothing, Apparel, & Fashions",
            "type":"Retail Goods"
        }
    ],
    "sg:phone":"+1 702 259 3975",
    "sg:postcode":"89146",
    "sg:province":"NV",
    "sg:tags":[
        "accessory",
        "clothing",
        "women's"
    ],
    "sg:website":"www.rainbowshops.com",
    "wof:name":"Rainbow Apparel",
    "wof:placetype":"venue"
},
  "geometry": {"coordinates":[-115.231729,36.159403],"type":"Point"}
}