{
  "type": "Feature",
  "properties": {
    "iso:country":"US",
    "sg:address":"800 S Wells Ave",
    "sg:city":"Reno",
    "sg:classifiers":[
        {
            "category":"Food & Beverages",
            "subcategory":"Groceries & Convenience Stores",
            "type":"Retail Goods"
        }
    ],
    "sg:phone":"+1 775 322 6711",
    "sg:postcode":"89502",
    "sg:province":"NV",
    "wof:name":"7-Eleven",
    "wof:placetype":"venue"
},
  "geometry": {"coordinates":[-119.803172,39.517303],"type":"Point"}
}