{
  "type": "Feature",
  "properties": {
    "iso:country":"US",
    "sg:address":"5820 S Pecos Road Bldg A",
    "sg:city":"Las Vegas",
    "sg:classifiers":[
        {
            "category":"Building & Trades",
            "subcategory":"Construction",
            "type":"Services"
        }
    ],
    "sg:phone":"+1 702 262 9047",
    "sg:postcode":"89120",
    "sg:province":"NV",
    "sg:tags":[
        "contractor"
    ],
    "wof:name":"United States Government",
    "wof:placetype":"venue"
},
  "geometry": {"coordinates":[-115.101046,36.084094],"type":"Point"}
}