{
  "type": "Feature",
  "properties": {
    "iso:country":"US",
    "sg:address":"2381 E Windmill Ln",
    "sg:city":"Las Vegas",
    "sg:classifiers":[
        {
            "category":"Insurance",
            "subcategory":"Insurance Agent",
            "type":"Services"
        }
    ],
    "sg:phone":"+1 702 270 4500",
    "sg:postcode":"89123",
    "sg:province":"NV",
    "wof:name":"Mike Seifer and Associates",
    "wof:placetype":"venue"
},
  "geometry": {"coordinates":[-115.119021,36.042203],"type":"Point"}
}