{
  "type": "Feature",
  "properties": {
    "iso:country":"US",
    "sg:address":"1445 W Sunset Rd inside Borders Books & Music",
    "sg:city":"Henderson",
    "sg:classifiers":[
        {
            "category":"Coffee & Tea",
            "type":"Food & Drink"
        },
        {
            "category":"Internet Cafe",
            "subcategory":"None",
            "type":"Food & Drink"
        }
    ],
    "sg:phone":"+1 800 611 7793",
    "sg:postcode":"89014",
    "sg:province":"NV",
    "sg:website":"www.seattlesbest.com",
    "wof:name":"Seattle's Best Coffee",
    "wof:placetype":"venue"
},
  "geometry": {"coordinates":[-115.048574,36.062575],"type":"Point"}
}