{
  "type": "Feature",
  "properties": {
    "iso:country":"US",
    "sg:address":"1201 State Hwy 160",
    "sg:city":"Pahrump",
    "sg:classifiers":[
        {
            "category":"Health Services",
            "subcategory":"Clinic",
            "type":"Services"
        }
    ],
    "sg:phone":"+1 775 751 9991",
    "sg:postcode":"89048",
    "sg:province":"NV",
    "sg:tags":[
        "home"
    ],
    "sg:website":"www.visitingangels.com",
    "wof:name":"Visiting Angels-N Las Vegas",
    "wof:placetype":"venue"
},
  "geometry": {"coordinates":[-115.97599200000001,36.201649],"type":"Point"}
}