{
  "type": "Feature",
  "properties": {
    "iso:country":"US",
    "sg:address":"8685 W Sahara Avenue",
    "sg:city":"Las Vegas",
    "sg:classifiers":[
        {
            "category":"Health Services",
            "subcategory":"Doctor",
            "type":"Services"
        }
    ],
    "sg:phone":"+1 702 318 5222",
    "sg:postcode":"89117",
    "sg:province":"NV",
    "sg:tags":[
        "practice",
        "family"
    ],
    "wof:name":"Lakes Family Physicians",
    "wof:placetype":"venue"
},
  "geometry": {"coordinates":[-115.290687,36.141286],"type":"Point"}
}