{
  "type": "Feature",
  "properties": {
    "iso:country":"US",
    "sg:address":"1485 Rincon Dr",
    "sg:city":"Sparks",
    "sg:classifiers":[
        {
            "category":"Freight",
            "type":"Transportation"
        }
    ],
    "sg:phone":"+1 775 626 4868",
    "sg:postcode":"89436",
    "sg:province":"NV",
    "wof:name":"H&H Enterprises LLC",
    "wof:placetype":"venue"
},
  "geometry": {"coordinates":[-119.71965400000001,39.586375],"type":"Point"}
}