{
  "type": "Feature",
  "properties": {
    "iso:country":"US",
    "sg:address":"2656 Ridgewater Circle",
    "sg:city":"Henderson",
    "sg:classifiers":[
        {
            "category":"Personal",
            "type":"Services"
        }
    ],
    "sg:phone":"+1 702 480 1983",
    "sg:postcode":"89074",
    "sg:province":"NV",
    "sg:tags":[
        "home"
    ],
    "sg:website":"www.allstatewaterheaters.com",
    "wof:name":"Allstate Water Heaters Inc.",
    "wof:placetype":"venue"
},
  "geometry": {"coordinates":[-115.101669,36.047993],"type":"Point"}
}