{
  "type": "Feature",
  "properties": {
    "iso:country":"US",
    "sg:address":"2666 Harrigan Rd",
    "sg:city":"Fallon",
    "sg:phone":"+1 775 423 2141",
    "sg:postcode":"89406",
    "sg:province":"NV",
    "sg:tags":[
        "irrigation",
        "company"
    ],
    "sg:website":"www.tcid.org",
    "wof:name":"Truckee-Carson Irrigation",
    "wof:placetype":"venue"
},
  "geometry": {"coordinates":[-118.763025,39.452263],"type":"Point"}
}