{
  "type": "Feature",
  "properties": {
    "iso:country":"US",
    "sg:address":"500 Glendale Ave",
    "sg:city":"Sparks",
    "sg:classifiers":[
        {
            "category":"Wholesale",
            "subcategory":"Durable Goods & Equipment",
            "type":"Manufacturing & Wholesale Goods"
        }
    ],
    "sg:phone":"+1 775 358 6310",
    "sg:postcode":"89431",
    "sg:province":"NV",
    "sg:tags":[
        "laser"
    ],
    "wof:name":"Spectra Lasers LLC",
    "wof:placetype":"venue"
},
  "geometry": {"coordinates":[-119.752737,39.527437],"type":"Point"}
}