{
  "type": "Feature",
  "properties": {
    "iso:country":"US",
    "sg:address":"3691 Glen Echo Ct",
    "sg:city":"Reno",
    "sg:classifiers":[
        {
            "category":"Banks & Credit Unions",
            "subcategory":"Financial Services",
            "type":"Services"
        }
    ],
    "sg:phone":"+1 775 825 1755",
    "sg:postcode":"89509",
    "sg:province":"NV",
    "sg:tags":[
        "investor"
    ],
    "wof:name":"Oppio Investments LLC",
    "wof:placetype":"venue"
},
  "geometry": {"coordinates":[-119.849572,39.484045],"type":"Point"}
}