{
  "type": "Feature",
  "properties": {
    "iso:country":"US",
    "sg:address":"10300 W Charleston Boulevard Suite 13",
    "sg:city":"Las Vegas",
    "sg:classifiers":[
        {
            "category":"Banks & Credit Unions",
            "subcategory":"Bank",
            "type":"Services"
        }
    ],
    "sg:phone":"+1 702 363 8151",
    "sg:postcode":"89135",
    "sg:province":"NV",
    "wof:name":"State Farm Insurance",
    "wof:placetype":"venue"
},
  "geometry": {"coordinates":[-115.320681,36.158969],"type":"Point"}
}