{
  "type": "Feature",
  "properties": {
    "iso:country":"US",
    "sg:address":"2801 S Valley View Blvd",
    "sg:city":"Las Vegas",
    "sg:classifiers":[
        {
            "category":"Real Estate",
            "subcategory":"Real Estate Agent",
            "type":"Services"
        }
    ],
    "sg:phone":"+1 702 413 9603",
    "sg:postcode":"89102",
    "sg:province":"NV",
    "sg:tags":[
        "management"
    ],
    "wof:name":"Rent It Buy It Property Mgmt",
    "wof:placetype":"venue"
},
  "geometry": {"coordinates":[-115.19070600000001,36.140525],"type":"Point"}
}