{
  "type": "Feature",
  "properties": {
    "iso:country":"US",
    "sg:address":"1320 Aultman St",
    "sg:city":"Ely",
    "sg:classifiers":[
        {
            "category":"Banks & Credit Unions",
            "subcategory":"Investment Brokerage",
            "type":"Services"
        }
    ],
    "sg:phone":"+1 775 289 8519",
    "sg:postcode":"89301",
    "sg:province":"NV",
    "sg:tags":[
        "consultant",
        "financing"
    ],
    "wof:name":"RNDC",
    "wof:placetype":"venue"
},
  "geometry": {"coordinates":[-114.88365,39.249732],"type":"Point"}
}