{
  "type": "Feature",
  "properties": {
    "iso:country":"US",
    "sg:address":"3450 Tanto Cir",
    "sg:city":"Las Vegas",
    "sg:classifiers":[
        {
            "category":"Building & Trades",
            "subcategory":"Cleaning & Sanitation",
            "type":"Services"
        }
    ],
    "sg:phone":"+1 702 292 4335",
    "sg:postcode":"89121",
    "sg:province":"NV",
    "sg:tags":[
        "home"
    ],
    "wof:name":"ABC Real Complete Cleaning and Restoration Specialist Las Vegas",
    "wof:placetype":"venue"
},
  "geometry": {"coordinates":[-115.099019,36.110051],"type":"Point"}
}