{
  "type": "Feature",
  "properties": {
    "iso:country":"US",
    "sg:address":"2770 S Maryland Parkway",
    "sg:city":"Las Vegas",
    "sg:classifiers":[
        {
            "category":"Banks & Credit Unions",
            "subcategory":"Atm",
            "type":"Services"
        }
    ],
    "sg:phone":"+1 702 737 0569",
    "sg:postcode":"89109",
    "sg:province":"NV",
    "sg:tags":[
        "bankruptcy"
    ],
    "wof:name":"Lorendo Law Office",
    "wof:placetype":"venue"
},
  "geometry": {"coordinates":[-115.13685700000001,36.139463],"type":"Point"}
}