{
  "type": "Feature",
  "properties": {
    "iso:country":"US",
    "sg:address":"4175 Arville St",
    "sg:city":"Las Vegas",
    "sg:classifiers":[
        {
            "category":"Professional",
            "subcategory":"Management & Consulting",
            "type":"Services"
        }
    ],
    "sg:phone":"+1 702 372 8941",
    "sg:postcode":"89103",
    "sg:province":"NV",
    "wof:name":"Rox Management",
    "wof:placetype":"venue"
},
  "geometry": {"coordinates":[-115.199443,36.115047],"type":"Point"}
}