{
  "type": "Feature",
  "properties": {
    "iso:country":"US",
    "sg:address":"3305 Spring Mountain Rd",
    "sg:city":"Las Vegas",
    "sg:classifiers":[
        {
            "category":"Real Estate",
            "subcategory":"Real Estate Agent",
            "type":"Services"
        }
    ],
    "sg:phone":"+1 702 435 7265",
    "sg:postcode":"89102",
    "sg:province":"NV",
    "wof:name":"Warburg Capital",
    "wof:placetype":"venue"
},
  "geometry": {"coordinates":[-115.184418,36.126242],"type":"Point"}
}