{
  "type": "Feature",
  "properties": {
    "iso:country":"US",
    "sg:address":"1561 Jones St",
    "sg:city":"Minden",
    "sg:classifiers":[
        {
            "category":"Manufacturing",
            "subcategory":"Printing",
            "type":"Manufacturing & Wholesale Goods"
        }
    ],
    "sg:phone":"+1 775 267 3703",
    "sg:postcode":"89423",
    "sg:province":"NV",
    "sg:tags":[
        "publisher"
    ],
    "wof:name":"Pine Nut Press",
    "wof:placetype":"venue"
},
  "geometry": {"coordinates":[-119.718335,39.032054],"type":"Point"}
}