{
  "type": "Feature",
  "properties": {
    "iso:country":"US",
    "sg:address":"2293 Duneville St",
    "sg:city":"Las Vegas",
    "sg:classifiers":[
        {
            "category":"Banks & Credit Unions",
            "subcategory":"Investment Brokerage",
            "type":"Services"
        }
    ],
    "sg:phone":"+1 702 383 6767",
    "sg:postcode":"89146",
    "sg:province":"NV",
    "sg:tags":[
        "advisory"
    ],
    "wof:name":"Sager Holdings Inc",
    "wof:placetype":"venue"
},
  "geometry": {"coordinates":[-115.221155,36.147878],"type":"Point"}
}