{
  "type": "Feature",
  "properties": {
    "iso:country":"US",
    "sg:address":"1343 Dressen Ave",
    "sg:city":"Las Vegas",
    "sg:classifiers":[
        {
            "category":"Organizations",
            "subcategory":"Religious Organization",
            "type":"Services"
        }
    ],
    "sg:phone":"+1 702 270 7777",
    "sg:postcode":"89123",
    "sg:province":"NV",
    "sg:tags":[
        "church"
    ],
    "wof:name":"Oasis Christian Fellowship",
    "wof:placetype":"venue"
},
  "geometry": {"coordinates":[-115.134263,36.024533],"type":"Point"}
}