{
  "type": "Feature",
  "properties": {
    "iso:country":"US",
    "sg:address":"378 E Country Club Dr",
    "sg:city":"Henderson",
    "sg:classifiers":[
        {
            "category":"Government",
            "subcategory":"Office",
            "type":"Public Place"
        }
    ],
    "sg:phone":"+1 702 568 7749",
    "sg:postcode":"89015",
    "sg:province":"NV",
    "sg:tags":[
        "development"
    ],
    "wof:name":"Barron AK Co",
    "wof:placetype":"venue"
},
  "geometry": {"coordinates":[-114.982893,36.019781],"type":"Point"}
}