{
  "type": "Feature",
  "properties": {
    "iso:country":"US",
    "sg:address":"2585 S Jones Blvd",
    "sg:city":"Las Vegas",
    "sg:classifiers":[
        {
            "category":"Real Estate",
            "subcategory":"Real Estate Agent",
            "type":"Services"
        }
    ],
    "sg:phone":"+1 702 251 7790",
    "sg:postcode":"89146",
    "sg:province":"NV",
    "wof:name":"Homes For Less",
    "wof:placetype":"venue"
},
  "geometry": {"coordinates":[-115.225366,36.143968],"type":"Point"}
}