{
  "type": "Feature",
  "properties": {
    "iso:country":"US",
    "sg:address":"6017 Fawn Ave",
    "sg:city":"Las Vegas",
    "sg:classifiers":[
        {
            "category":"Recreation",
            "type":"Entertainment"
        }
    ],
    "sg:phone":"+1 702 878 4532",
    "sg:postcode":"89107",
    "sg:province":"NV",
    "wof:name":"Skalak Swim School",
    "wof:placetype":"venue"
},
  "geometry": {"coordinates":[-115.22144,36.177799],"type":"Point"}
}