{
  "type": "Feature",
  "properties": {
    "iso:country":"US",
    "sg:address":"1040 Victorian Ave",
    "sg:city":"Sparks",
    "sg:classifiers":[
        {
            "category":"Restaurant",
            "type":"Food & Drink"
        }
    ],
    "sg:menulink":"http://www.allmenus.com/nv/sparks/162817-port-of-subs/menu/",
    "sg:phone":"+1 775 358 4771",
    "sg:postcode":"89431",
    "sg:province":"NV",
    "sg:tags":[
        "wrap",
        "american",
        "sandwich"
    ],
    "wof:name":"Port of Subs",
    "wof:placetype":"venue"
},
  "geometry": {"coordinates":[-119.75642999999999,39.535215],"type":"Point"}
}