{
  "type": "Feature",
  "properties": {
    "iso:country":"US",
    "sg:address":"551 W Main St",
    "sg:city":"Elko",
    "sg:classifiers":[
        {
            "category":"Wholesale",
            "subcategory":"Machinery & Supplies",
            "type":"Manufacturing & Wholesale Goods"
        }
    ],
    "sg:phone":"+1 775 753 8088",
    "sg:postcode":"89801",
    "sg:province":"NV",
    "sg:tags":[
        "equipment",
        "pump",
        "industrial"
    ],
    "wof:name":"C H Spencer & Company",
    "wof:placetype":"venue"
},
  "geometry": {"coordinates":[-115.77094,40.826662],"type":"Point"}
}