{
  "type": "Feature",
  "properties": {
    "iso:country":"US",
    "sg:address":"1070 E Roland St",
    "sg:city":"Carson City",
    "sg:classifiers":[
        {
            "category":"Building & Trades",
            "subcategory":"Cleaning & Sanitation",
            "type":"Services"
        }
    ],
    "sg:phone":"+1 775 883 7308",
    "sg:postcode":"89701",
    "sg:province":"NV",
    "sg:tags":[
        "maintenance"
    ],
    "wof:name":"Silverstate Building Maint",
    "wof:placetype":"venue"
},
  "geometry": {"coordinates":[-119.757112,39.123044],"type":"Point"}
}