{
  "type": "Feature",
  "properties": {
    "iso:country":"US",
    "sg:address":"2475 Robb Dr",
    "sg:city":"Reno",
    "sg:classifiers":[
        {
            "category":"Real Estate",
            "subcategory":"Real Estate Operator",
            "type":"Services"
        }
    ],
    "sg:phone":"+1 775 348 2400",
    "sg:postcode":"89523",
    "sg:province":"NV",
    "sg:tags":[
        "apartment",
        "complex"
    ],
    "wof:name":"Manzanita Gate",
    "wof:placetype":"venue"
},
  "geometry": {"coordinates":[-119.89242,39.546257],"type":"Point"}
}