{
  "type": "Feature",
  "properties": {
    "iso:country":"US",
    "sg:address":"573 Dale Dr",
    "sg:city":"Incline Village",
    "sg:classifiers":[
        {
            "category":"Professional",
            "type":"Services"
        }
    ],
    "sg:phone":"+1 775 831 0755",
    "sg:postcode":"89451",
    "sg:province":"NV",
    "sg:tags":[
        "establishment"
    ],
    "wof:name":"Whytecliff Enterprises Inc",
    "wof:placetype":"venue"
},
  "geometry": {"coordinates":[-119.982097,39.254155],"type":"Point"}
}