{
  "type": "Feature",
  "properties": {
    "iso:country":"US",
    "sg:address":"3150 N Tenaya Way Ste 320",
    "sg:city":"Las Vegas",
    "sg:classifiers":[
        {
            "category":"Health Services",
            "subcategory":"Doctor",
            "type":"Services"
        }
    ],
    "sg:phone":"+1 702 731 8224",
    "sg:postcode":"89128",
    "sg:province":"NV",
    "sg:tags":[
        "cardiologist"
    ],
    "wof:name":"Cardiovascular Consultants of Nevada",
    "wof:placetype":"venue"
},
  "geometry": {"coordinates":[-115.264999,36.196301],"type":"Point"}
}