{
  "type": "Feature",
  "properties": {
    "iso:country":"US",
    "sg:address":"600 Florida St",
    "sg:city":"Pahrump",
    "sg:classifiers":[
        {
            "category":"Organizations",
            "subcategory":"Religious Organization",
            "type":"Services"
        }
    ],
    "sg:phone":"+1 775 727 4151",
    "sg:postcode":"89048",
    "sg:province":"NV",
    "sg:tags":[
        "church"
    ],
    "sg:website":"www.usacommunityuplink.com",
    "wof:name":"Church On A Mission",
    "wof:placetype":"venue"
},
  "geometry": {"coordinates":[-116.016353,36.190986],"type":"Point"}
}