{
  "type": "Feature",
  "properties": {
    "iso:country":"US",
    "sg:address":"1650 Foothill Dr",
    "sg:city":"Boulder City",
    "sg:classifiers":[
        {
            "category":"Manufacturing",
            "subcategory":"Glass & Minerals",
            "type":"Manufacturing & Wholesale Goods"
        }
    ],
    "sg:phone":"+1 702 293 5329",
    "sg:postcode":"89005",
    "sg:province":"NV",
    "sg:tags":[
        "fabricator",
        "fiber"
    ],
    "sg:website":"www.markvfiberglass.com",
    "wof:name":"Mark V Fiberglass",
    "wof:placetype":"venue"
},
  "geometry": {"coordinates":[-114.85762,35.971314],"type":"Point"}
}