{
  "type": "Feature",
  "properties": {
    "iso:country":"US",
    "sg:address":"321 S Frontage Rd",
    "sg:city":"Pahrump",
    "sg:classifiers":[
        {
            "category":"Shopping",
            "subcategory":"Computers & Home Electronics",
            "type":"Retail Goods"
        }
    ],
    "sg:phone":"+1 775 751 4882",
    "sg:postcode":"89048",
    "sg:province":"NV",
    "sg:tags":[
        "equipment",
        "satellite",
        "sales",
        "system"
    ],
    "wof:name":"Community Dish LLC",
    "wof:placetype":"venue"
},
  "geometry": {"coordinates":[-115.99443,36.22117],"type":"Point"}
}