{
  "type": "Feature",
  "properties": {
    "iso:country":"US",
    "sg:address":"902 Spencer St",
    "sg:city":"Carson City",
    "sg:classifiers":[
        {
            "category":"Building & Trades",
            "subcategory":"Electrical",
            "type":"Services"
        }
    ],
    "sg:phone":"+1 775 882 3165",
    "sg:postcode":"89703",
    "sg:province":"NV",
    "sg:tags":[
        "electric",
        "contractor"
    ],
    "wof:name":"Kilty Electric",
    "wof:placetype":"venue"
},
  "geometry": {"coordinates":[-119.787831,39.171165],"type":"Point"}
}