{
  "type": "Feature",
  "properties": {
    "iso:country":"US",
    "sg:address":"1601 N Main Street",
    "sg:city":"North Las Vegas",
    "sg:classifiers":[
        {
            "category":"Retail",
            "subcategory":"Auto Repair",
            "type":"Services"
        }
    ],
    "sg:phone":"+1 702 399 0981",
    "sg:postcode":"89030",
    "sg:province":"NV",
    "wof:name":"J & A International",
    "wof:placetype":"venue"
},
  "geometry": {"coordinates":[-115.135341,36.188708],"type":"Point"}
}