{
  "type": "Feature",
  "properties": {
    "iso:country":"US",
    "sg:address":"3501 S Rainbow Boulevard",
    "sg:city":"Las Vegas",
    "sg:classifiers":[
        {
            "category":"Restaurant",
            "type":"Food & Drink"
        }
    ],
    "sg:phone":"+1 702 220 3070",
    "sg:postcode":"89103",
    "sg:province":"NV",
    "sg:tags":[
        "traditional",
        "american"
    ],
    "sg:website":"www.applebees.com",
    "wof:name":"Applebee's Neighborhood Grill & Bar",
    "wof:placetype":"venue"
},
  "geometry": {"coordinates":[-115.244018,36.124774],"type":"Point"}
}