{
  "type": "Feature",
  "properties": {
    "iso:country":"US",
    "sg:address":"403 Idaho St",
    "sg:city":"Reno",
    "sg:classifiers":[
        {
            "category":"Autos & Motor Vehicles",
            "subcategory":"Auto Supplies",
            "type":"Retail Goods"
        }
    ],
    "sg:phone":"+1 800 852 0427",
    "sg:postcode":"89506",
    "sg:province":"NV",
    "sg:tags":[
        "automobile",
        "accessory"
    ],
    "wof:name":"Brite Stars Sales-Service",
    "wof:placetype":"venue"
},
  "geometry": {"coordinates":[-119.837788,39.685918],"type":"Point"}
}