{
  "type": "Feature",
  "properties": {
    "iso:country":"US",
    "sg:address":"714 N Nellis Boulevard",
    "sg:city":"Las Vegas",
    "sg:classifiers":[
        {
            "category":"Food & Beverages",
            "subcategory":"Liquor & Beverages",
            "type":"Retail Goods"
        }
    ],
    "sg:phone":"+1 702 453 8311",
    "sg:postcode":"89110",
    "sg:province":"NV",
    "sg:tags":[
        "beer",
        "spirit",
        "wine"
    ],
    "wof:name":"Las Palmas Liquors",
    "wof:placetype":"venue"
},
  "geometry": {"coordinates":[-115.062031,36.172432],"type":"Point"}
}