{
  "type": "Feature",
  "properties": {
    "iso:country":"US",
    "sg:address":"2580 Duneville St Ste 109",
    "sg:city":"Las Vegas",
    "sg:classifiers":[
        {
            "category":"Retail",
            "subcategory":"Auto Rental",
            "type":"Services"
        }
    ],
    "sg:phone":"+1 702 368 3772",
    "sg:postcode":"89146",
    "sg:province":"NV",
    "sg:tags":[
        "car"
    ],
    "wof:name":"Enterprise Rent-A-Car",
    "wof:placetype":"venue"
},
  "geometry": {"coordinates":[-115.221001,36.143002],"type":"Point"}
}