{
  "type": "Feature",
  "properties": {
    "iso:country":"US",
    "sg:address":"850 S Rock Blvd",
    "sg:city":"Sparks",
    "sg:classifiers":[
        {
            "category":"Wholesale",
            "subcategory":"Machinery & Supplies",
            "type":"Manufacturing & Wholesale Goods"
        }
    ],
    "sg:phone":"+1 775 331 4673",
    "sg:postcode":"89431",
    "sg:province":"NV",
    "sg:tags":[
        "equipment",
        "industrial"
    ],
    "wof:name":"Hose & Fittings Etc",
    "wof:placetype":"venue"
},
  "geometry": {"coordinates":[-119.766634,39.526767],"type":"Point"}
}