{
  "type": "Feature",
  "properties": {
    "iso:country":"US",
    "sg:address":"2924 Windstorm Ave",
    "sg:city":"Las Vegas",
    "sg:classifiers":[
        {
            "category":"Retail",
            "subcategory":"Car Wash",
            "type":"Services"
        }
    ],
    "sg:phone":"+1 702 860 4615",
    "sg:postcode":"89106",
    "sg:province":"NV",
    "sg:tags":[
        "automobile",
        "detail",
        "clean"
    ],
    "wof:name":"Bowlivian Mobile Detail",
    "wof:placetype":"venue"
},
  "geometry": {"coordinates":[-115.180724,36.191789],"type":"Point"}
}