{
  "type": "Feature",
  "properties": {
    "iso:country":"US",
    "sg:address":"1110 E Charleston Blvd",
    "sg:city":"Las Vegas",
    "sg:classifiers":[
        {
            "category":"Food & Beverages",
            "subcategory":"Groceries & Convenience Stores",
            "type":"Retail Goods"
        }
    ],
    "sg:phone":"+1 702 385 9275",
    "sg:postcode":"89104",
    "sg:province":"NV",
    "sg:tags":[
        "grocer"
    ],
    "wof:name":"Grocery Outlet",
    "wof:placetype":"venue"
},
  "geometry": {"coordinates":[-115.137051,36.158804],"type":"Point"}
}