{
  "type": "Feature",
  "properties": {
    "iso:country":"US",
    "sg:address":"5380 Cameron St",
    "sg:city":"Las Vegas",
    "sg:classifiers":[
        {
            "category":"Recreation",
            "type":"Entertainment"
        }
    ],
    "sg:phone":"+1 702 222 0911",
    "sg:postcode":"89118",
    "sg:province":"NV",
    "sg:tags":[
        "charter",
        "canoe"
    ],
    "sg:website":"www.bigbluepacific.com",
    "wof:name":"Big Blue Pacific Kayak Advntrs",
    "wof:placetype":"venue"
},
  "geometry": {"coordinates":[-115.20377999999999,36.092373],"type":"Point"}
}