{
  "type": "Feature",
  "properties": {
    "iso:country":"US",
    "sg:address":"421 Hill St",
    "sg:city":"Reno",
    "sg:classifiers":[
        {
            "category":"Health Services",
            "subcategory":"Health Practitioner",
            "type":"Services"
        }
    ],
    "sg:phone":"+1 775 348 1488",
    "sg:postcode":"89501",
    "sg:province":"NV",
    "wof:name":"Kim I Webster",
    "wof:placetype":"venue"
},
  "geometry": {"coordinates":[-119.813576,39.52032],"type":"Point"}
}