{
  "type": "Feature",
  "properties": {
    "iso:country":"US",
    "sg:address":"2100 E Lake Mead Blvd",
    "sg:city":"North Las Vegas",
    "sg:classifiers":[
        {
            "category":"Restaurant",
            "type":"Food & Drink"
        }
    ],
    "sg:phone":"+1 702 657 9008",
    "sg:postcode":"89030",
    "sg:province":"NV",
    "sg:tags":[
        "chinese"
    ],
    "wof:name":"M B China Restaurant",
    "wof:placetype":"venue"
},
  "geometry": {"coordinates":[-115.119003,36.1959],"type":"Point"}
}