{
  "type": "Feature",
  "properties": {
    "iso:country":"US",
    "sg:address":"3760 Tranquility Ridge Ct",
    "sg:city":"Las Vegas",
    "sg:classifiers":[
        {
            "category":"Shopping",
            "subcategory":"Clothing, Apparel, & Fashions",
            "type":"Retail Goods"
        }
    ],
    "sg:phone":"+1 702 870 3733",
    "sg:postcode":"89147",
    "sg:province":"NV",
    "sg:tags":[
        "fur",
        "business"
    ],
    "wof:name":"Shirley Clifton",
    "wof:placetype":"venue"
},
  "geometry": {"coordinates":[-115.306567,36.121228],"type":"Point"}
}