{
  "type": "Feature",
  "properties": {
    "iso:country":"US",
    "sg:address":"4465 W Hacienda Ave Ste 106",
    "sg:city":"Las Vegas",
    "sg:classifiers":[
        {
            "category":"Autos & Motor Vehicles",
            "subcategory":"Automobile Sales",
            "type":"Retail Goods"
        },
        {
            "category":"Taxi",
            "type":"Transportation"
        },
        {
            "category":"Airline",
            "type":"Transportation"
        },
        {
            "category":"Sports & Exercise",
            "subcategory":"Golf",
            "type":"Entertainment"
        }
    ],
    "sg:phone":"+1 702 248 2631",
    "sg:postcode":"89118",
    "sg:province":"NV",
    "sg:tags":[
        "shuttle",
        "airport",
        "limo"
    ],
    "sg:website":"www.lasvegastransportation.com",
    "wof:name":"Las Vegas Transportation Inc",
    "wof:placetype":"venue"
},
  "geometry": {"coordinates":[-115.20062,36.093107],"type":"Point"}
}