{
  "type": "Feature",
  "properties": {
    "iso:country":"US",
    "sg:address":"332 W Sherwood Dr",
    "sg:city":"Henderson",
    "sg:classifiers":[
        {
            "category":"Professional",
            "subcategory":"Business Services",
            "type":"Services"
        }
    ],
    "sg:phone":"+1 702 558 7202",
    "sg:postcode":"89015",
    "sg:province":"NV",
    "wof:name":"BRC Design",
    "wof:placetype":"venue"
},
  "geometry": {"coordinates":[-114.995227,36.024743],"type":"Point"}
}