{
  "type": "Feature",
  "properties": {
    "iso:country":"US",
    "sg:address":"6711 Rocking Horse Ave",
    "sg:city":"Las Vegas",
    "sg:classifiers":[
        {
            "category":"Banks & Credit Unions",
            "subcategory":"Financial Services",
            "type":"Services"
        }
    ],
    "sg:phone":"+1 702 645 6742",
    "sg:postcode":"89108",
    "sg:province":"NV",
    "sg:tags":[
        "company",
        "holding"
    ],
    "wof:name":"Honey Six Inc",
    "wof:placetype":"venue"
},
  "geometry": {"coordinates":[-115.24108699999999,36.222538],"type":"Point"}
}