{
  "type": "Feature",
  "properties": {
    "iso:country":"US",
    "sg:address":"2745 W Centennial Pkwy #130",
    "sg:city":"North Las Vegas",
    "sg:classifiers":[
        {
            "category":"Restaurant",
            "type":"Food & Drink"
        }
    ],
    "sg:phone":"+1 702 645 4967",
    "sg:postcode":"89084",
    "sg:province":"NV",
    "sg:tags":[
        "sushi",
        "bar"
    ],
    "wof:name":"Sushi Tachi",
    "wof:placetype":"venue"
},
  "geometry": {"coordinates":[-115.109066,36.276419],"type":"Point"}
}