{
  "type": "Feature",
  "properties": {
    "iso:country":"US",
    "sg:address":"6355 Silver Lake Rd",
    "sg:city":"Reno",
    "sg:classifiers":[
        {
            "category":"Professional",
            "subcategory":"Business Services",
            "type":"Services"
        }
    ],
    "sg:phone":"+1 775 691 7661",
    "sg:postcode":"89506",
    "sg:province":"NV",
    "sg:tags":[
        "organizing",
        "services-household"
    ],
    "wof:name":"Cal & Mazz Golf Management",
    "wof:placetype":"venue"
},
  "geometry": {"coordinates":[-119.88514000000001,39.624633],"type":"Point"}
}