{
  "type": "Feature",
  "properties": {
    "iso:country":"US",
    "sg:address":"712 E Musser St",
    "sg:city":"Carson City",
    "sg:classifiers":[
        {
            "category":"Professional",
            "subcategory":"Lawyer & Legal Services",
            "type":"Services"
        }
    ],
    "sg:phone":"+1 775 883 7000",
    "sg:postcode":"89701",
    "sg:province":"NV",
    "sg:tags":[
        "attorney"
    ],
    "wof:name":"Norman J Azevedo Attorney-Law",
    "wof:placetype":"venue"
},
  "geometry": {"coordinates":[-119.76120299999999,39.164625],"type":"Point"}
}