{
  "type": "Feature",
  "properties": {
    "iso:country":"US",
    "sg:address":"598 N Eastern Ave",
    "sg:city":"Las Vegas",
    "sg:classifiers":[
        {
            "category":"Autos & Motor Vehicles",
            "subcategory":"Fuel & Gas Station",
            "type":"Retail Goods"
        }
    ],
    "sg:phone":"+1 702 383 8459",
    "sg:postcode":"89101",
    "sg:province":"NV",
    "sg:tags":[
        "oil"
    ],
    "wof:name":"Chevron Terrible Herbst",
    "wof:placetype":"venue"
},
  "geometry": {"coordinates":[-115.116061,36.172691],"type":"Point"}
}