{
  "type": "Feature",
  "properties": {
    "iso:country":"US",
    "sg:address":"1705 Candace Ct",
    "sg:city":"Fernley",
    "sg:classifiers":[
        {
            "category":"Building & Trades",
            "subcategory":"Construction",
            "type":"Services"
        }
    ],
    "sg:phone":"+1 775 575 6798",
    "sg:postcode":"89408",
    "sg:province":"NV",
    "sg:tags":[
        "roofing",
        "siding",
        "contractor"
    ],
    "wof:name":"La Voie Roofing Inc",
    "wof:placetype":"venue"
},
  "geometry": {"coordinates":[-119.21306300000001,39.587642],"type":"Point"}
}