{
  "type": "Feature",
  "properties": {
    "iso:country":"US",
    "sg:address":"1111 Fremont St",
    "sg:city":"Las Vegas",
    "sg:classifiers":[
        {
            "category":"Travel",
            "subcategory":"Hotels & Motels",
            "type":"Entertainment"
        }
    ],
    "sg:phone":"+1 702 382 0306",
    "sg:postcode":"89101",
    "sg:province":"NV",
    "wof:name":"Lucky Motel",
    "wof:placetype":"venue"
},
  "geometry": {"coordinates":[-115.132728,36.165929],"type":"Point"}
}