{
  "type": "Feature",
  "properties": {
    "iso:country":"US",
    "sg:address":"32100 S Las Vegas Blvd",
    "sg:city":"Jean",
    "sg:classifiers":[
        {
            "category":"Shopping",
            "subcategory":"Clothing, Apparel, & Fashions",
            "type":"Retail Goods"
        }
    ],
    "sg:phone":"+1 702 874 1760",
    "sg:postcode":"89019",
    "sg:province":"NV",
    "sg:tags":[
        "item",
        "boutique"
    ],
    "wof:name":"Icing By Claire's",
    "wof:placetype":"venue"
},
  "geometry": {"coordinates":[-115.387756,35.611139],"type":"Point"}
}