{
  "type": "Feature",
  "properties": {
    "iso:country":"US",
    "sg:address":"891 De Marco Dr",
    "sg:city":"Henderson",
    "sg:classifiers":[
        {
            "category":"Restaurant",
            "type":"Food & Drink"
        }
    ],
    "sg:phone":"+1 702 565 7466",
    "sg:postcode":"89011",
    "sg:province":"NV",
    "sg:tags":[
        "italian"
    ],
    "wof:name":"Carmines Little Italy",
    "wof:placetype":"venue"
},
  "geometry": {"coordinates":[-114.955492,36.074046],"type":"Point"}
}