{
  "type": "Feature",
  "properties": {
    "iso:country":"US",
    "sg:address":"755 S Grand Central Parkway",
    "sg:city":"Las Vegas",
    "sg:classifiers":[
        {
            "category":"Restaurant",
            "type":"Food & Drink"
        }
    ],
    "sg:phone":"+1 702 385 5353",
    "sg:postcode":"89106",
    "sg:province":"NV",
    "wof:name":"Italia Express",
    "wof:placetype":"venue"
},
  "geometry": {"coordinates":[-115.157303,36.162804],"type":"Point"}
}