{
  "type": "Feature",
  "properties": {
    "iso:country":"US",
    "sg:address":"2250 Lincoln Rd",
    "sg:city":"Las Vegas",
    "sg:phone":"+1 702 453 2730",
    "sg:postcode":"89115",
    "sg:province":"NV",
    "sg:tags":[
        "real",
        "lessor",
        "farm",
        "corn",
        "soybean",
        "property"
    ],
    "wof:name":"Larry Eilers",
    "wof:placetype":"venue"
},
  "geometry": {"coordinates":[-115.084638,36.202167],"type":"Point"}
}