{
  "type": "Feature",
  "properties": {
    "iso:country":"US",
    "sg:address":"2201 Industrial Rd",
    "sg:city":"Las Vegas",
    "sg:classifiers":[
        {
            "category":"Manufacturing",
            "subcategory":"Apparel",
            "type":"Manufacturing & Wholesale Goods"
        }
    ],
    "sg:phone":"+1 702 384 8606",
    "sg:postcode":"89102",
    "sg:province":"NV",
    "sg:tags":[
        "awning",
        "canopy"
    ],
    "wof:name":"Don & Lee's Trim Shop",
    "wof:placetype":"venue"
},
  "geometry": {"coordinates":[-115.163909,36.145564],"type":"Point"}
}