{
  "type": "Feature",
  "properties": {
    "iso:country":"US",
    "sg:address":"3440 E Oreana Ave",
    "sg:city":"Las Vegas",
    "sg:classifiers":[
        {
            "category":"Real Estate",
            "subcategory":"Real Estate Agent",
            "type":"Services"
        }
    ],
    "sg:phone":"+1 702 456 7563",
    "sg:postcode":"89120",
    "sg:province":"NV",
    "wof:name":"Albert Cannata Company",
    "wof:placetype":"venue"
},
  "geometry": {"coordinates":[-115.099328,36.090614],"type":"Point"}
}