{
  "type": "Feature",
  "properties": {
    "iso:country":"US",
    "sg:address":"3663 E Sunset Rd Ste 401",
    "sg:city":"Las Vegas",
    "sg:classifiers":[
        {
            "category":"Health Services",
            "subcategory":"Dentist",
            "type":"Services"
        }
    ],
    "sg:phone":"+1 702 433 5583",
    "sg:postcode":"89120",
    "sg:province":"NV",
    "sg:tags":[
        "pediatric"
    ],
    "wof:name":"Sunset Pediatric Dentistry",
    "wof:placetype":"venue"
},
  "geometry": {"coordinates":[-115.094995,36.071108],"type":"Point"}
}