{
  "type": "Feature",
  "properties": {
    "iso:country":"US",
    "sg:address":"3585 Brown Ln",
    "sg:city":"Winnemucca",
    "sg:classifiers":[
        {
            "category":"Freight",
            "type":"Transportation"
        }
    ],
    "sg:phone":"+1 760 481 4318",
    "sg:postcode":"89445",
    "sg:province":"NV",
    "sg:tags":[
        "arrangement"
    ],
    "wof:name":"Belland Trucking",
    "wof:placetype":"venue"
},
  "geometry": {"coordinates":[-117.760714,40.910094],"type":"Point"}
}