{
  "type": "Feature",
  "properties": {
    "iso:country":"US",
    "sg:address":"6501 Brandywine Way",
    "sg:city":"Las Vegas",
    "sg:classifiers":[
        {
            "category":"Building & Trades",
            "subcategory":"Landscaping Services",
            "type":"Services"
        }
    ],
    "sg:phone":"+1 702 878 0534",
    "sg:postcode":"89107",
    "sg:province":"NV",
    "sg:tags":[
        "landscape"
    ],
    "wof:name":"Dallas E Lister",
    "wof:placetype":"venue"
},
  "geometry": {"coordinates":[-115.240029,36.165006],"type":"Point"}
}