{
  "type": "Feature",
  "properties": {
    "iso:country":"US",
    "sg:address":"282 S Decatur Blvd",
    "sg:city":"Las Vegas",
    "sg:classifiers":[
        {
            "category":"Banks & Credit Unions",
            "subcategory":"Bank",
            "type":"Services"
        }
    ],
    "sg:phone":"+1 702 259 5505",
    "sg:postcode":"89107",
    "sg:province":"NV",
    "sg:tags":[
        "depository",
        "banking"
    ],
    "wof:name":"Chek Line Inc",
    "wof:placetype":"venue"
},
  "geometry": {"coordinates":[-115.20605999999999,36.171409],"type":"Point"}
}