{
  "type": "Feature",
  "properties": {
    "iso:country":"US",
    "sg:address":"9420 W Sahara Ave",
    "sg:city":"Las Vegas",
    "sg:classifiers":[
        {
            "category":"Real Estate",
            "subcategory":"Real Estate Agent",
            "type":"Services"
        }
    ],
    "sg:phone":"+1 702 365 1500",
    "sg:postcode":"89117",
    "sg:province":"NV",
    "wof:name":"Allen & Shirley June",
    "wof:placetype":"venue"
},
  "geometry": {"coordinates":[-115.300631,36.144488],"type":"Point"}
}