{
  "type": "Feature",
  "properties": {
    "iso:country":"US",
    "sg:address":"3770 Howard Hughes Parkway",
    "sg:city":"Las Vegas",
    "sg:classifiers":[
        {
            "category":"Professional",
            "subcategory":"Lawyer & Legal Services",
            "type":"Services"
        }
    ],
    "sg:phone":"+1 702 369 2900",
    "sg:postcode":"89169",
    "sg:province":"NV",
    "wof:name":"Roberts Thomas L Atty",
    "wof:placetype":"venue"
},
  "geometry": {"coordinates":[-115.157774,36.120596],"type":"Point"}
}