{
  "type": "Feature",
  "properties": {
    "iso:country":"US",
    "sg:address":"3625 W Russell Road",
    "sg:city":"Las Vegas",
    "sg:classifiers":[
        {
            "category":"Banks & Credit Unions",
            "subcategory":"Bank",
            "type":"Services"
        }
    ],
    "sg:phone":"+1 702 740 5666",
    "sg:postcode":"89118",
    "sg:province":"NV",
    "sg:website":"www.colonialbank.com",
    "wof:name":"Colonial Bank",
    "wof:placetype":"venue"
},
  "geometry": {"coordinates":[-115.188062,36.086171],"type":"Point"}
}