{
  "type": "Feature",
  "properties": {
    "iso:country":"US",
    "sg:address":"2144 Volante Cir",
    "sg:city":"Henderson",
    "sg:classifiers":[
        {
            "category":"Real Estate",
            "subcategory":"Real Estate Agent",
            "type":"Services"
        }
    ],
    "sg:phone":"+1 702 407 1273",
    "sg:postcode":"89052",
    "sg:province":"NV",
    "wof:name":"Gunnette Properties",
    "wof:placetype":"venue"
},
  "geometry": {"coordinates":[-115.078515,35.975255],"type":"Point"}
}