{
  "type": "Feature",
  "properties": {
    "iso:country":"US",
    "sg:address":"3045 E Post Rd",
    "sg:city":"Las Vegas",
    "sg:classifiers":[
        {
            "category":"Wholesale",
            "subcategory":"Non-durable Goods",
            "type":"Manufacturing & Wholesale Goods"
        }
    ],
    "sg:phone":"+1 702 253 6373",
    "sg:postcode":"89120",
    "sg:province":"NV",
    "sg:tags":[
        "advertising",
        "specialty"
    ],
    "sg:website":"www.specprousa.com",
    "wof:name":"Specpro",
    "wof:placetype":"venue"
},
  "geometry": {"coordinates":[-115.10888,36.075201],"type":"Point"}
}