{
  "type": "Feature",
  "properties": {
    "iso:country":"US",
    "sg:address":"3700 S Paradise Rd",
    "sg:city":"Las Vegas",
    "sg:classifiers":[
        {
            "category":"Fast Food",
            "type":"Food & Drink"
        }
    ],
    "sg:phone":"+1 702 731 5756",
    "sg:postcode":"89169",
    "sg:province":"NV",
    "sg:website":"www.mcdonalds.com",
    "wof:name":"McDonald's",
    "wof:placetype":"venue"
},
  "geometry": {"coordinates":[-115.15486799999999,36.122023],"type":"Point"}
}