{
  "type": "Feature",
  "properties": {
    "iso:country":"US",
    "sg:address":"9080 Double Diamond Pkwy Suite A3",
    "sg:city":"Reno",
    "sg:classifiers":[
        {
            "category":"Professional",
            "subcategory":"Advertising",
            "type":"Services"
        },
        {
            "category":"Autos & Motor Vehicles",
            "subcategory":"Auto Supplies",
            "type":"Retail Goods"
        },
        {
            "category":"Wholesale",
            "subcategory":"Auto Parts",
            "type":"Manufacturing & Wholesale Goods"
        }
    ],
    "sg:phone":"+1 775 853 7671",
    "sg:postcode":"89521",
    "sg:province":"NV",
    "sg:tags":[
        "equipment",
        "automobile",
        "truck",
        "accessory"
    ],
    "sg:website":"http://www.jodog.com",
    "wof:name":"JoDog Sport Inc",
    "wof:placetype":"venue"
},
  "geometry": {"coordinates":[-119.74916,39.448563],"type":"Point"}
}