{
  "type": "Feature",
  "properties": {
    "iso:country":"US",
    "sg:address":"9330 W Sahara Ave",
    "sg:city":"Las Vegas",
    "sg:classifiers":[
        {
            "category":"Restaurant",
            "type":"Food & Drink"
        }
    ],
    "sg:phone":"+1 702 240 7466",
    "sg:postcode":"89117",
    "sg:province":"NV",
    "wof:name":"Frank Manhattan Restaurant",
    "wof:placetype":"venue"
},
  "geometry": {"coordinates":[-115.29833000000001,36.144492],"type":"Point"}
}