{
  "type": "Feature",
  "properties": {
    "iso:country":"US",
    "sg:address":"735 S Taylor St",
    "sg:city":"Fallon",
    "sg:classifiers":[
        {
            "category":"Retail",
            "subcategory":"Repair Shop",
            "type":"Services"
        }
    ],
    "sg:phone":"+1 775 423 7696",
    "sg:postcode":"89406",
    "sg:province":"NV",
    "sg:tags":[
        "lock",
        "locksmith"
    ],
    "wof:name":"S & S Sterling",
    "wof:placetype":"venue"
},
  "geometry": {"coordinates":[-118.781474,39.467381],"type":"Point"}
}