{
  "type": "Feature",
  "properties": {
    "iso:country":"US",
    "sg:address":"970 6th St",
    "sg:city":"Wells",
    "sg:classifiers":[
        {
            "category":"Retail",
            "subcategory":"Auto Repair",
            "type":"Services"
        }
    ],
    "sg:phone":"+1 775 752 3938",
    "sg:postcode":"89835",
    "sg:province":"NV",
    "sg:tags":[
        "truck"
    ],
    "wof:name":"Roadway Diesel",
    "wof:placetype":"venue"
},
  "geometry": {"coordinates":[-114.96001699999999,41.103266],"type":"Point"}
}