{
  "type": "Feature",
  "properties": {
    "iso:country":"US",
    "sg:address":"7636 Westcliff Dr",
    "sg:city":"Las Vegas",
    "sg:classifiers":[
        {
            "category":"Retail",
            "subcategory":"Laundry & Dry Cleaning",
            "type":"Services"
        }
    ],
    "sg:phone":"+1 702 360 6431",
    "sg:postcode":"89145",
    "sg:province":"NV",
    "sg:tags":[
        "cleaners"
    ],
    "wof:name":"Premier Property Solutions",
    "wof:placetype":"venue"
},
  "geometry": {"coordinates":[-115.261025,36.174074],"type":"Point"}
}