{
  "type": "Feature",
  "properties": {
    "iso:country":"US",
    "sg:address":"1580 Hawthorne Rd",
    "sg:city":"Reno",
    "sg:classifiers":[
        {
            "category":"Social Services",
            "subcategory":"Child Care",
            "type":"Services"
        }
    ],
    "sg:phone":"+1 775 827 3355",
    "sg:postcode":"89502",
    "sg:province":"NV",
    "wof:name":"Little Hearts Preschool",
    "wof:placetype":"venue"
},
  "geometry": {"coordinates":[-119.777924,39.482397],"type":"Point"}
}