{
  "type": "Feature",
  "properties": {
    "iso:country":"US",
    "sg:address":"3887 E Lake Mead Blvd",
    "sg:city":"Las Vegas",
    "sg:classifiers":[
        {
            "category":"Food & Beverages",
            "subcategory":"Groceries & Convenience Stores",
            "type":"Retail Goods"
        }
    ],
    "sg:phone":"+1 702 452 3939",
    "sg:postcode":"89115",
    "sg:province":"NV",
    "sg:tags":[
        "market"
    ],
    "wof:name":"Rainbow Market",
    "wof:placetype":"venue"
},
  "geometry": {"coordinates":[-115.089996,36.195801],"type":"Point"}
}