{
  "type": "Feature",
  "properties": {
    "iso:country":"US",
    "sg:address":"611 Kuenzli St",
    "sg:city":"Reno",
    "sg:classifiers":[
        {
            "category":"Wholesale",
            "subcategory":"Vending Machines",
            "type":"Manufacturing & Wholesale Goods"
        }
    ],
    "sg:phone":"+1 775 786 9179",
    "sg:postcode":"89502",
    "sg:province":"NV",
    "wof:name":"Starcade Amusement",
    "wof:placetype":"venue"
},
  "geometry": {"coordinates":[-119.80315400000001,39.52843],"type":"Point"}
}