{
  "type": "Feature",
  "properties": {
    "iso:country":"US",
    "sg:address":"5275 Ross Dr",
    "sg:city":"Reno",
    "sg:classifiers":[
        {
            "category":"Building & Trades",
            "subcategory":"Construction",
            "type":"Services"
        }
    ],
    "sg:phone":"+1 775 747 7277",
    "sg:postcode":"89519",
    "sg:province":"NV",
    "sg:tags":[
        "contractor"
    ],
    "wof:name":"Gill Construction Inc",
    "wof:placetype":"venue"
},
  "geometry": {"coordinates":[-119.87738899999999,39.501939],"type":"Point"}
}