{
  "type": "Feature",
  "properties": {
    "iso:country":"US",
    "sg:address":"155 N Edison Way",
    "sg:city":"Reno",
    "sg:classifiers":[
        {
            "category":"Manufacturing",
            "subcategory":"Building Materials",
            "type":"Manufacturing & Wholesale Goods"
        },
        {
            "category":"Building & Trades",
            "subcategory":"Construction",
            "type":"Services"
        }
    ],
    "sg:phone":"+1 775 856 1080",
    "sg:postcode":"89502",
    "sg:province":"NV",
    "sg:tags":[
        "mfg",
        "contractor",
        "wood",
        "carpentry",
        "cabinet",
        "maker",
        "kitchen"
    ],
    "wof:name":"Moyle Cabinet & Design",
    "wof:placetype":"venue"
},
  "geometry": {"coordinates":[-119.750177,39.515531],"type":"Point"}
}