{
  "type": "Feature",
  "properties": {
    "iso:country":"US",
    "sg:address":"1395 Greg St",
    "sg:city":"Sparks",
    "sg:classifiers":[
        {
            "category":"Health Services",
            "subcategory":"Clinic",
            "type":"Services"
        }
    ],
    "sg:phone":"+1 775 352 7742",
    "sg:postcode":"89431",
    "sg:province":"NV",
    "sg:tags":[
        "home"
    ],
    "sg:website":"www.apria.com",
    "wof:name":"Apria Healthcare",
    "wof:placetype":"venue"
},
  "geometry": {"coordinates":[-119.76235699999999,39.523319],"type":"Point"}
}