{
  "type": "Feature",
  "properties": {
    "iso:country":"US",
    "sg:address":"4530 Meadows Ln",
    "sg:city":"Las Vegas",
    "sg:classifiers":[
        {
            "category":"Shopping",
            "subcategory":"Used Merchandise",
            "type":"Retail Goods"
        }
    ],
    "sg:phone":"+1 702 646 5668",
    "sg:postcode":"89107",
    "sg:province":"NV",
    "sg:tags":[
        "shop",
        "thrift"
    ],
    "wof:name":"Faith Lutheran Thrift Store",
    "wof:placetype":"venue"
},
  "geometry": {"coordinates":[-115.194733,36.170222],"type":"Point"}
}