{
  "type": "Feature",
  "properties": {
    "iso:country":"US",
    "sg:address":"375 E Harmon Ave",
    "sg:city":"Las Vegas",
    "sg:classifiers":[
        {
            "category":"Retail",
            "subcategory":"Auto Rental",
            "type":"Services"
        }
    ],
    "sg:phone":"+1 702 734 3977",
    "sg:postcode":"89169",
    "sg:province":"NV",
    "sg:tags":[
        "car"
    ],
    "wof:name":"Enterprise Rent-A-Car",
    "wof:placetype":"venue"
},
  "geometry": {"coordinates":[-115.15614600000001,36.106258],"type":"Point"}
}