{
  "type": "Feature",
  "properties": {
    "iso:country":"US",
    "sg:address":"3140 Polaris Ave #41",
    "sg:city":"Las Vegas",
    "sg:classifiers":[
        {
            "category":"Personal",
            "type":"Services"
        }
    ],
    "sg:phone":"+1 702 435 6617",
    "sg:postcode":"89102",
    "sg:province":"NV",
    "sg:tags":[
        "home"
    ],
    "sg:website":"www.branche-enterprises.com",
    "wof:name":"Desert Cabinets",
    "wof:placetype":"venue"
},
  "geometry": {"coordinates":[-115.186761,36.132363],"type":"Point"}
}