{
  "type": "Feature",
  "properties": {
    "iso:country":"US",
    "sg:address":"691 Lamoille Hwy",
    "sg:city":"Lamoille",
    "sg:classifiers":[
        {
            "category":"Travel",
            "subcategory":"Hotels & Motels",
            "type":"Entertainment"
        }
    ],
    "sg:phone":"+1 775 753 8515",
    "sg:postcode":"89803",
    "sg:province":"NV",
    "wof:name":"Lamoille House",
    "wof:placetype":"venue"
},
  "geometry": {"coordinates":[-115.475646,40.728739],"type":"Point"}
}