{
  "type": "Feature",
  "properties": {
    "iso:country":"US",
    "sg:address":"651 N Rainbow Blvd Ste 110",
    "sg:city":"Las Vegas",
    "sg:classifiers":[
        {
            "category":"Coffee & Tea",
            "type":"Food & Drink"
        }
    ],
    "sg:phone":"+1 702 992 6277",
    "sg:postcode":"89107",
    "sg:province":"NV",
    "sg:website":"www.starbucks.com/",
    "wof:name":"Starbucks",
    "wof:placetype":"venue"
},
  "geometry": {"coordinates":[-115.242508,36.179404],"type":"Point"}
}