{
  "type": "Feature",
  "properties": {
    "iso:country":"US",
    "sg:address":"2206 S Rainbow Blvd",
    "sg:city":"Las Vegas",
    "sg:classifiers":[
        {
            "category":"Shopping",
            "subcategory":"Clothing, Apparel, & Fashions",
            "type":"Retail Goods"
        }
    ],
    "sg:phone":"+1 702 257 1115",
    "sg:postcode":"89146",
    "sg:province":"NV",
    "wof:name":"A Secret Closet",
    "wof:placetype":"venue"
},
  "geometry": {"coordinates":[-115.242977,36.147012],"type":"Point"}
}