{
  "type": "Feature",
  "properties": {
    "iso:country":"US",
    "sg:address":"1110 E Charleston Blvd",
    "sg:city":"Las Vegas",
    "sg:classifiers":[
        {
            "category":"Food & Beverages",
            "subcategory":"Groceries & Convenience Stores",
            "type":"Retail Goods"
        }
    ],
    "sg:phone":"+1 702 364 8600",
    "sg:postcode":"89104",
    "sg:province":"NV",
    "wof:name":"Los Compadres Meat Market",
    "wof:placetype":"venue"
},
  "geometry": {"coordinates":[-115.138222,36.158731],"type":"Point"}
}