{
  "type": "Feature",
  "properties": {
    "iso:country":"US",
    "sg:address":"7888 Tidal Pool Ct",
    "sg:city":"Las Vegas",
    "sg:classifiers":[
        {
            "category":"Building & Trades",
            "subcategory":"Cleaning & Sanitation",
            "type":"Services"
        }
    ],
    "sg:phone":"+1 702 227 9207",
    "sg:postcode":"89139",
    "sg:province":"NV",
    "sg:tags":[
        "maintenance"
    ],
    "wof:name":"His Way Janitorial Svc",
    "wof:placetype":"venue"
},
  "geometry": {"coordinates":[-115.23886299999999,36.046774],"type":"Point"}
}