{
  "type": "Feature",
  "properties": {
    "iso:country":"US",
    "sg:address":"4535 W Sahara Ave",
    "sg:city":"Las Vegas",
    "sg:classifiers":[
        {
            "category":"Professional",
            "subcategory":"Management & Consulting",
            "type":"Services"
        }
    ],
    "sg:phone":"+1 702 733 0063",
    "sg:postcode":"89102",
    "sg:province":"NV",
    "sg:tags":[
        "development",
        "workforce"
    ],
    "wof:name":"Atheneum Learning Systems Inc",
    "wof:placetype":"venue"
},
  "geometry": {"coordinates":[-115.200202,36.144404],"type":"Point"}
}