{
  "type": "Feature",
  "properties": {
    "iso:country":"US",
    "sg:address":"360 Freeport Blvd",
    "sg:city":"Sparks",
    "sg:classifiers":[
        {
            "category":"Building & Trades",
            "subcategory":"Construction",
            "type":"Services"
        }
    ],
    "sg:phone":"+1 775 826 5546",
    "sg:postcode":"89431",
    "sg:province":"NV",
    "sg:tags":[
        "downspouts",
        "gutter"
    ],
    "wof:name":"Advanced Seamless Rain Gutter",
    "wof:placetype":"venue"
},
  "geometry": {"coordinates":[-119.74476900000001,39.52565],"type":"Point"}
}