{
  "type": "Feature",
  "properties": {
    "iso:country":"US",
    "sg:address":"711 Smokey Mountain Ave",
    "sg:city":"Henderson",
    "sg:classifiers":[
        {
            "category":"Building & Trades",
            "subcategory":"Construction",
            "type":"Services"
        }
    ],
    "sg:phone":"+1 702 565 0874",
    "sg:postcode":"89012",
    "sg:province":"NV",
    "sg:tags":[
        "carpenter"
    ],
    "wof:name":"Howard Helderlein",
    "wof:placetype":"venue"
},
  "geometry": {"coordinates":[-115.01832,36.023167],"type":"Point"}
}