{
  "type": "Feature",
  "properties": {
    "iso:country":"US",
    "sg:address":"4041 Elkridge Dr",
    "sg:city":"Las Vegas",
    "sg:classifiers":[
        {
            "category":"Professional",
            "subcategory":"Business Services",
            "type":"Services"
        }
    ],
    "sg:phone":"+1 702 731 6617",
    "sg:postcode":"89129",
    "sg:province":"NV",
    "sg:tags":[
        "bus"
    ],
    "wof:name":"Market America",
    "wof:placetype":"venue"
},
  "geometry": {"coordinates":[-115.250099,36.23478],"type":"Point"}
}