{
  "type": "Feature",
  "properties": {
    "iso:country":"US",
    "sg:address":"1428 Tonopah St",
    "sg:city":"Reno",
    "sg:classifiers":[
        {
            "category":"Health Services",
            "subcategory":"Doctor",
            "type":"Services"
        }
    ],
    "sg:phone":"+1 775 329 4886",
    "sg:postcode":"89509",
    "sg:province":"NV",
    "sg:tags":[
        "dentist"
    ],
    "wof:name":"Earl Dental Svc",
    "wof:placetype":"venue"
},
  "geometry": {"coordinates":[-119.80671,39.509959],"type":"Point"}
}