{
  "type": "Feature",
  "properties": {
    "iso:country":"US",
    "sg:address":"2211 Las Vegas Boulevard S",
    "sg:city":"Las Vegas",
    "sg:classifiers":[
        {
            "category":"Travel",
            "subcategory":"Hotels & Motels",
            "type":"Entertainment"
        }
    ],
    "sg:phone":"+1 702 732 2468",
    "sg:postcode":"89104",
    "sg:province":"NV",
    "wof:name":"Holiday House Holiday Motel",
    "wof:placetype":"venue"
},
  "geometry": {"coordinates":[-115.15571,36.146092],"type":"Point"}
}