{
  "type": "Feature",
  "properties": {
    "iso:country":"US",
    "sg:address":"5333 Arville St",
    "sg:city":"Las Vegas",
    "sg:classifiers":[
        {
            "category":"Professional",
            "subcategory":"Engineering",
            "type":"Services"
        }
    ],
    "sg:phone":"+1 702 798 8545",
    "sg:postcode":"89118",
    "sg:province":"NV",
    "wof:name":"Cw Group",
    "wof:placetype":"venue"
},
  "geometry": {"coordinates":[-115.199266,36.091776],"type":"Point"}
}