{
  "type": "Feature",
  "properties": {
    "iso:country":"US",
    "sg:address":"300 E Charleston Blvd",
    "sg:city":"Las Vegas",
    "sg:classifiers":[
        {
            "category":"Professional",
            "subcategory":"Lawyer & Legal Services",
            "type":"Services"
        }
    ],
    "sg:phone":"+1 702 432 6446",
    "sg:postcode":"89104",
    "sg:province":"NV",
    "wof:name":"Fair Treatment For Immigrants",
    "wof:placetype":"venue"
},
  "geometry": {"coordinates":[-115.150375,36.158837],"type":"Point"}
}