{
  "type": "Feature",
  "properties": {
    "iso:country":"US",
    "sg:address":"5039 Philmar Ave",
    "sg:city":"Las Vegas",
    "sg:classifiers":[
        {
            "category":"Manufacturing",
            "subcategory":"Glass & Minerals",
            "type":"Manufacturing & Wholesale Goods"
        }
    ],
    "sg:phone":"+1 702 451 1036",
    "sg:postcode":"89120",
    "sg:province":"NV",
    "sg:tags":[
        "mfg"
    ],
    "wof:name":"Nevada Land & Development",
    "wof:placetype":"venue"
},
  "geometry": {"coordinates":[-115.077043,36.099307],"type":"Point"}
}