{
  "type": "Feature",
  "properties": {
    "iso:country":"US",
    "sg:address":"3415 W. Craig Rd Ste 202",
    "sg:city":"North Las Vegas",
    "sg:classifiers":[
        {
            "category":"Insurance",
            "subcategory":"Hazard Insurance",
            "type":"Services"
        }
    ],
    "sg:phone":"+1 702 647 8448",
    "sg:postcode":"89032",
    "sg:province":"NV",
    "wof:name":"US Auto Insurance Agency",
    "wof:placetype":"venue"
},
  "geometry": {"coordinates":[-115.186223,36.238939],"type":"Point"}
}