{
  "type": "Feature",
  "properties": {
    "iso:country":"US",
    "sg:address":"3500 Las Vegas Blvd S",
    "sg:city":"Las Vegas",
    "sg:classifiers":[
        {
            "category":"Restaurant",
            "type":"Food & Drink"
        }
    ],
    "sg:menulink":"http://www.allmenus.com/nv/las-vegas/267322-il-mulino---las-vegas/menu/",
    "sg:phone":"+1 702 492 6000",
    "sg:postcode":"89109",
    "sg:province":"NV",
    "sg:tags":[
        "italian"
    ],
    "wof:name":"Il Mulino - Las Vegas",
    "wof:placetype":"venue"
},
  "geometry": {"coordinates":[-115.17320599999999,36.117738],"type":"Point"}
}