{
  "type": "Feature",
  "properties": {
    "iso:country":"US",
    "sg:address":"6010 W Cheyenne Ave",
    "sg:city":"Las Vegas",
    "sg:classifiers":[
        {
            "category":"Food & Beverages",
            "subcategory":"Specialty",
            "type":"Retail Goods"
        }
    ],
    "sg:phone":"+1 702 395 0395",
    "sg:postcode":"89108",
    "sg:province":"NV",
    "sg:tags":[
        "water",
        "bulk",
        "company"
    ],
    "wof:name":"Cheyenne Jones Water Store",
    "wof:placetype":"venue"
},
  "geometry": {"coordinates":[-115.22769099999999,36.217071],"type":"Point"}
}