{
  "type": "Feature",
  "properties": {
    "iso:country":"US",
    "sg:address":"6301 Mountain Vista Ste 205",
    "sg:city":"Henderson",
    "sg:classifiers":[
        {
            "category":"Health Services",
            "subcategory":"Doctor",
            "type":"Services"
        }
    ],
    "sg:phone":"+1 702 614 5437",
    "sg:postcode":"89014",
    "sg:province":"NV",
    "sg:tags":[
        "pediatrician"
    ],
    "wof:name":"Foothills Pediatrics",
    "wof:placetype":"venue"
},
  "geometry": {"coordinates":[-115.073849,36.075016],"type":"Point"}
}