{
  "type": "Feature",
  "properties": {
    "iso:country":"US",
    "sg:address":"2920 E Serene Ave",
    "sg:city":"Henderson",
    "sg:classifiers":[
        {
            "category":"Professional",
            "subcategory":"Accounting & Tax Preparation",
            "type":"Services"
        }
    ],
    "sg:phone":"+1 702 897 1190",
    "sg:postcode":"89074",
    "sg:province":"NV",
    "sg:tags":[
        "accountant"
    ],
    "wof:name":"Allen R Anderson CPA",
    "wof:placetype":"venue"
},
  "geometry": {"coordinates":[-115.111797,36.020535],"type":"Point"}
}