{
  "type": "Feature",
  "properties": {
    "iso:country":"US",
    "sg:address":"2550 Duneville St",
    "sg:city":"Las Vegas",
    "sg:classifiers":[
        {
            "category":"Professional",
            "subcategory":"Management & Consulting",
            "type":"Services"
        }
    ],
    "sg:phone":"+1 702 252 4626",
    "sg:postcode":"89146",
    "sg:province":"NV",
    "sg:tags":[
        "consultant"
    ],
    "wof:name":"Sunrise Omni",
    "wof:placetype":"venue"
},
  "geometry": {"coordinates":[-115.2209,36.143412],"type":"Point"}
}