{
  "type": "Feature",
  "properties": {
    "iso:country":"US",
    "sg:address":"1001 S Rainbow Blvd",
    "sg:city":"Las Vegas",
    "sg:classifiers":[
        {
            "category":"Utilities",
            "subcategory":"Mobile Phone",
            "type":"Services"
        }
    ],
    "sg:phone":"+1 702 878 0787",
    "sg:postcode":"89145",
    "sg:province":"NV",
    "sg:tags":[
        "telephone",
        "cellular"
    ],
    "wof:name":"Chatter Box Wireless Inc",
    "wof:placetype":"venue"
},
  "geometry": {"coordinates":[-115.244316,36.165237],"type":"Point"}
}