{
  "type": "Feature",
  "properties": {
    "iso:country":"US",
    "sg:address":"4810 S Nellis Blvd",
    "sg:city":"Las Vegas",
    "sg:classifiers":[
        {
            "category":"Shopping",
            "subcategory":"Florist",
            "type":"Retail Goods"
        }
    ],
    "sg:phone":"+1 702 456 8088",
    "sg:postcode":"89121",
    "sg:province":"NV",
    "wof:name":"Hearts and Flowers Florist",
    "wof:placetype":"venue"
},
  "geometry": {"coordinates":[-115.063969,36.102195],"type":"Point"}
}