{
  "type": "Feature",
  "properties": {
    "iso:country":"US",
    "sg:address":"325 S 3rd St",
    "sg:city":"Las Vegas",
    "sg:classifiers":[
        {
            "category":"Professional",
            "subcategory":"Lawyer & Legal Services",
            "type":"Services"
        }
    ],
    "sg:phone":"+1 702 869 9623",
    "sg:postcode":"89101",
    "sg:province":"NV",
    "wof:name":"Brian Abbington",
    "wof:placetype":"venue"
},
  "geometry": {"coordinates":[-115.144981,36.166979],"type":"Point"}
}