{
  "type": "Feature",
  "properties": {
    "iso:country":"US",
    "sg:address":"1173 Pelican Lake Ln",
    "sg:city":"Las Vegas",
    "sg:classifiers":[
        {
            "category":"Shopping",
            "subcategory":"Computers & Home Electronics",
            "type":"Retail Goods"
        }
    ],
    "sg:phone":"+1 702 407 7146",
    "sg:postcode":"89123",
    "sg:province":"NV",
    "sg:tags":[
        "audio"
    ],
    "wof:name":"Exquisite Home Theater",
    "wof:placetype":"venue"
},
  "geometry": {"coordinates":[-115.138119,36.040672],"type":"Point"}
}