{
  "type": "Feature",
  "properties": {
    "iso:country":"US",
    "sg:address":"1405 Arville St",
    "sg:city":"Las Vegas",
    "sg:classifiers":[
        {
            "category":"Insurance",
            "subcategory":"Insurance Agent",
            "type":"Services"
        }
    ],
    "sg:phone":"+1 702 258 8283",
    "sg:postcode":"89102",
    "sg:province":"NV",
    "wof:name":"Medicare Supplemental Benefits",
    "wof:placetype":"venue"
},
  "geometry": {"coordinates":[-115.199684,36.158206],"type":"Point"}
}