{
  "type": "Feature",
  "properties": {
    "iso:country":"US",
    "sg:address":"5647 Hickam Ave",
    "sg:city":"Las Vegas",
    "sg:classifiers":[
        {
            "category":"Building & Trades",
            "subcategory":"Construction",
            "type":"Services"
        }
    ],
    "sg:phone":"+1 702 871 0324",
    "sg:postcode":"89130",
    "sg:province":"NV",
    "sg:tags":[
        "residential",
        "commercial"
    ],
    "wof:name":"Jaehn Construction West",
    "wof:placetype":"venue"
},
  "geometry": {"coordinates":[-115.219983,36.236006],"type":"Point"}
}