{
  "type": "Feature",
  "properties": {
    "iso:country":"US",
    "sg:address":"4141 Lake Tahoe Blvd",
    "sg:city":"South Lake Tahoe",
    "sg:classifiers":[
        {
            "category":"Travel",
            "subcategory":"Hotels & Motels",
            "type":"Entertainment"
        }
    ],
    "sg:phone":"+1 530 544 0269",
    "sg:postcode":"96150",
    "sg:province":"CA",
    "wof:name":"Ann's Motel",
    "wof:placetype":"venue"
},
  "geometry": {"coordinates":[-119.942314,38.958949],"type":"Point"}
}