{
  "type": "Feature",
  "properties": {
    "iso:country":"US",
    "sg:address":"994 Glendale Ave",
    "sg:city":"Sparks",
    "sg:classifiers":[
        {
            "category":"Wholesale",
            "subcategory":"Machinery & Supplies",
            "type":"Manufacturing & Wholesale Goods"
        }
    ],
    "sg:phone":"+1 775 355 9933",
    "sg:postcode":"89431",
    "sg:province":"NV",
    "sg:tags":[
        "janitor"
    ],
    "sg:website":"www.laketahoesupply.com",
    "wof:name":"Lake Tahoe Supply Co",
    "wof:placetype":"venue"
},
  "geometry": {"coordinates":[-119.755606,39.527739],"type":"Point"}
}