{
  "type": "Feature",
  "properties": {
    "iso:country":"US",
    "sg:address":"4347 W Charleston Blvd",
    "sg:city":"Las Vegas",
    "sg:classifiers":[
        {
            "category":"Bars & Pubs",
            "subcategory":"Lounge",
            "type":"Food & Drink"
        },
        {
            "category":"Bars & Pubs",
            "subcategory":"Gay Bar",
            "type":"Food & Drink"
        }
    ],
    "sg:phone":"+1 702 385 3539",
    "sg:postcode":"89102",
    "sg:province":"NV",
    "sg:website":"www.flexlasvegas.com",
    "wof:name":"Flex Lounge",
    "wof:placetype":"venue"
},
  "geometry": {"coordinates":[-115.198997,36.158901],"type":"Point"}
}