{
  "type": "Feature",
  "properties": {
    "iso:country":"US",
    "sg:address":"2207 Bellanca St",
    "sg:city":"Minden",
    "sg:classifiers":[
        {
            "category":"Autos & Motor Vehicles",
            "subcategory":"Automobile Sales",
            "type":"Retail Goods"
        }
    ],
    "sg:phone":"+1 775 782 4483",
    "sg:postcode":"89423",
    "sg:province":"NV",
    "wof:name":"Liberty Aircraft Sales",
    "wof:placetype":"venue"
},
  "geometry": {"coordinates":[-119.757496,38.99812],"type":"Point"}
}