{
  "type": "Feature",
  "properties": {
    "iso:country":"US",
    "sg:address":"201 Las Vegas Blvd S",
    "sg:city":"Las Vegas",
    "sg:classifiers":[
        {
            "category":"Professional",
            "subcategory":"Lawyer & Legal Services",
            "type":"Services"
        }
    ],
    "sg:phone":"+1 702 489 9800",
    "sg:postcode":"89101",
    "sg:province":"NV",
    "wof:name":"Law Office of Jonathan Schulman the",
    "wof:placetype":"venue"
},
  "geometry": {"coordinates":[-115.141207,36.167996],"type":"Point"}
}