{
  "type": "Feature",
  "properties": {
    "iso:country":"US",
    "sg:address":"4701 Cameron St",
    "sg:city":"Las Vegas",
    "sg:classifiers":[
        {
            "category":"Mining & Drilling",
            "type":"Manufacturing & Wholesale Goods"
        }
    ],
    "sg:phone":"+1 702 362 5266",
    "sg:postcode":"89103",
    "sg:province":"NV",
    "sg:tags":[
        "stone"
    ],
    "wof:name":"Stone Systems",
    "wof:placetype":"venue"
},
  "geometry": {"coordinates":[-115.203904,36.100892],"type":"Point"}
}