{
  "type": "Feature",
  "properties": {
    "iso:country":"US",
    "sg:address":"2215 Green Vista Dr",
    "sg:city":"Sparks",
    "sg:classifiers":[
        {
            "category":"Professional",
            "subcategory":"Accounting & Tax Preparation",
            "type":"Services"
        }
    ],
    "sg:phone":"+1 775 355 7388",
    "sg:postcode":"89431",
    "sg:province":"NV",
    "sg:tags":[
        "return",
        "filing"
    ],
    "wof:name":"General Business Svc",
    "wof:placetype":"venue"
},
  "geometry": {"coordinates":[-119.77466200000001,39.55837],"type":"Point"}
}