{
  "type": "Feature",
  "properties": {
    "iso:country":"US",
    "sg:address":"3355 E Tropicana Avenue",
    "sg:city":"Las Vegas",
    "sg:classifiers":[
        {
            "category":"Personal",
            "subcategory":"Nail Salon",
            "type":"Services"
        }
    ],
    "sg:phone":"+1 702 898 7002",
    "sg:postcode":"89121",
    "sg:province":"NV",
    "wof:name":"Nail Max",
    "wof:placetype":"venue"
},
  "geometry": {"coordinates":[-115.102793,36.099955],"type":"Point"}
}