{
  "type": "Feature",
  "properties": {
    "iso:country":"US",
    "sg:address":"7810 W Ann Rd",
    "sg:city":"Las Vegas",
    "sg:classifiers":[
        {
            "category":"Restaurant",
            "type":"Food & Drink"
        }
    ],
    "sg:menulink":"http://www.allmenus.com/nv/las-vegas/82842-villa-pizza/menu/",
    "sg:phone":"+1 702 656 9695",
    "sg:postcode":"89149",
    "sg:province":"NV",
    "sg:tags":[
        "american",
        "italian",
        "pizza"
    ],
    "wof:name":"Villa Pizza",
    "wof:placetype":"venue"
},
  "geometry": {"coordinates":[-115.266277,36.263817],"type":"Point"}
}