{
  "type": "Feature",
  "properties": {
    "iso:country":"US",
    "sg:address":"15 Julie Ct",
    "sg:city":"Winnemucca",
    "sg:classifiers":[
        {
            "category":"Shopping",
            "subcategory":"Gifts & Souvenirs",
            "type":"Retail Goods"
        }
    ],
    "sg:phone":"+1 775 625 2028",
    "sg:postcode":"89445",
    "sg:province":"NV",
    "wof:name":"Sports Cards Inc",
    "wof:placetype":"venue"
},
  "geometry": {"coordinates":[-117.718497,40.96956],"type":"Point"}
}