{
  "type": "Feature",
  "properties": {
    "iso:country":"US",
    "sg:address":"8421 Eddy Stone Ave",
    "sg:city":"Las Vegas",
    "sg:classifiers":[
        {
            "category":"Personal",
            "type":"Services"
        }
    ],
    "sg:phone":"+1 702 730 3058",
    "sg:postcode":"89117",
    "sg:province":"NV",
    "sg:tags":[
        "therapist",
        "massage"
    ],
    "wof:name":"Betty Ann Railey Massage",
    "wof:placetype":"venue"
},
  "geometry": {"coordinates":[-115.277163,36.154384],"type":"Point"}
}