{
  "type": "Feature",
  "properties": {
    "iso:country":"US",
    "sg:address":"2801 S Valley View Blvd",
    "sg:city":"Las Vegas",
    "sg:classifiers":[
        {
            "category":"Professional",
            "subcategory":"Computer Services",
            "type":"Services"
        }
    ],
    "sg:phone":"+1 702 364 1690",
    "sg:postcode":"89102",
    "sg:province":"NV",
    "sg:tags":[
        "agency",
        "advertising",
        "internet"
    ],
    "wof:name":"Emarketingmedia LLC",
    "wof:placetype":"venue"
},
  "geometry": {"coordinates":[-115.190706,36.140525],"type":"Point"}
}