{
  "type": "Feature",
  "properties": {
    "iso:country":"US",
    "sg:address":"6254 Peach Orchard Rd",
    "sg:city":"Las Vegas",
    "sg:classifiers":[
        {
            "category":"Building & Trades",
            "subcategory":"Construction",
            "type":"Services"
        }
    ],
    "sg:phone":"+1 702 431 5841",
    "sg:postcode":"89142",
    "sg:province":"NV",
    "wof:name":"Gng Steel",
    "wof:placetype":"venue"
},
  "geometry": {"coordinates":[-115.037243,36.146538],"type":"Point"}
}