{
  "type": "Feature",
  "properties": {
    "iso:country":"US",
    "sg:address":"2000 S Lamb Blvd",
    "sg:city":"Las Vegas",
    "sg:classifiers":[
        {
            "category":"Home & Garden",
            "subcategory":"Mobile Homes",
            "type":"Retail Goods"
        }
    ],
    "sg:phone":"+1 702 457 5000",
    "sg:postcode":"89104",
    "sg:province":"NV",
    "wof:name":"Desert Rose Mobile Home Park",
    "wof:placetype":"venue"
},
  "geometry": {"coordinates":[-115.083083,36.148444],"type":"Point"}
}