{
  "type": "Feature",
  "properties": {
    "iso:country":"US",
    "sg:address":"93 W Center St",
    "sg:city":"Fallon",
    "sg:classifiers":[
        {
            "category":"Organizations",
            "subcategory":"Community Association",
            "type":"Services"
        }
    ],
    "sg:phone":"+1 775 423 2239",
    "sg:postcode":"89406",
    "sg:province":"NV",
    "sg:tags":[
        "fraternal"
    ],
    "wof:name":"Elks Lodge",
    "wof:placetype":"venue"
},
  "geometry": {"coordinates":[-118.777261,39.472976],"type":"Point"}
}