{
  "type": "Feature",
  "properties": {
    "iso:country":"US",
    "sg:address":"7529 Sea Spray Ave",
    "sg:city":"Las Vegas",
    "sg:classifiers":[
        {
            "category":"Real Estate",
            "subcategory":"Architect",
            "type":"Services"
        }
    ],
    "sg:phone":"+1 702 304 1660",
    "sg:postcode":"89128",
    "sg:province":"NV",
    "wof:name":"Labar Architecture Inc",
    "wof:placetype":"venue"
},
  "geometry": {"coordinates":[-115.257714,36.191278],"type":"Point"}
}