{
  "type": "Feature",
  "properties": {
    "iso:country":"US",
    "sg:address":"3565 W Harmon Ave",
    "sg:city":"Las Vegas",
    "sg:classifiers":[
        {
            "category":"Retail",
            "subcategory":"Laundry & Dry Cleaning",
            "type":"Services"
        }
    ],
    "sg:phone":"+1 702 795 0524",
    "sg:postcode":"89103",
    "sg:province":"NV",
    "sg:tags":[
        "cleaners",
        "rug",
        "carpet"
    ],
    "wof:name":"MPI Of Nevada",
    "wof:placetype":"venue"
},
  "geometry": {"coordinates":[-115.186997,36.10812],"type":"Point"}
}