{
  "type": "Feature",
  "properties": {
    "iso:country":"US",
    "sg:address":"8216 Fritzen Ave",
    "sg:city":"Las Vegas",
    "sg:classifiers":[
        {
            "category":"Retail",
            "subcategory":"Portrait Studio",
            "type":"Services"
        }
    ],
    "sg:phone":"+1 702 480 8535",
    "sg:postcode":"89131",
    "sg:province":"NV",
    "sg:tags":[
        "photographer"
    ],
    "wof:name":"Generations Photography",
    "wof:placetype":"venue"
},
  "geometry": {"coordinates":[-115.277753,36.302401],"type":"Point"}
}