{
  "type": "Feature",
  "properties": {
    "iso:country":"US",
    "sg:address":"5375 Eugene Ave",
    "sg:city":"Las Vegas",
    "sg:classifiers":[
        {
            "category":"Organizations",
            "subcategory":"Community Association",
            "type":"Services"
        }
    ],
    "sg:phone":"+1 702 648 0640",
    "sg:postcode":"89108",
    "sg:province":"NV",
    "sg:tags":[
        "homeowner"
    ],
    "wof:name":"D & G Consulting Services",
    "wof:placetype":"venue"
},
  "geometry": {"coordinates":[-115.212258,36.199135],"type":"Point"}
}