{
  "type": "Feature",
  "properties": {
    "iso:country":"US",
    "sg:address":"3443 Hera",
    "sg:city":"Las Vegas",
    "sg:classifiers":[
        {
            "category":"Wholesale",
            "subcategory":"Groceries",
            "type":"Manufacturing & Wholesale Goods"
        }
    ],
    "sg:phone":"+1 702 259 2157",
    "sg:postcode":"89117",
    "sg:province":"NV",
    "sg:tags":[
        "confectionery"
    ],
    "wof:name":"Were Nuttss",
    "wof:placetype":"venue"
},
  "geometry": {"coordinates":[-115.28745,36.127365],"type":"Point"}
}