{
  "type": "Feature",
  "properties": {
    "iso:country":"US",
    "sg:address":"4914 Boulder Hwy",
    "sg:city":"Las Vegas",
    "sg:classifiers":[
        {
            "category":"Banks & Credit Unions",
            "subcategory":"Bank",
            "type":"Services"
        }
    ],
    "sg:phone":"+1 702 434 3718",
    "sg:postcode":"89121",
    "sg:province":"NV",
    "sg:tags":[
        "cashing",
        "check"
    ],
    "wof:name":"Cash Plus",
    "wof:placetype":"venue"
},
  "geometry": {"coordinates":[-115.069695,36.117508],"type":"Point"}
}