{
  "type": "Feature",
  "properties": {
    "iso:country":"US",
    "sg:address":"2001 Ramrod Ave",
    "sg:city":"Henderson",
    "sg:classifiers":[
        {
            "category":"Shopping",
            "subcategory":"Adult",
            "type":"Retail Goods"
        }
    ],
    "sg:phone":"+1 702 531 6555",
    "sg:postcode":"89014",
    "sg:province":"NV",
    "sg:tags":[
        "entertainment"
    ],
    "wof:name":"Escort Agency On Call 24 7",
    "wof:placetype":"venue"
},
  "geometry": {"coordinates":[-115.07332700000001,36.076173],"type":"Point"}
}