{
  "type": "Feature",
  "properties": {
    "iso:country":"US",
    "sg:address":"1651 N Rancho Dr",
    "sg:city":"Las Vegas",
    "sg:classifiers":[
        {
            "category":"Retail",
            "subcategory":"Veterinary Services",
            "type":"Services"
        }
    ],
    "sg:phone":"+1 702 648 0414",
    "sg:postcode":"89106",
    "sg:province":"NV",
    "sg:tags":[
        "boarding",
        "kennel"
    ],
    "wof:name":"Ark Animal Clinic",
    "wof:placetype":"venue"
},
  "geometry": {"coordinates":[-115.187475,36.189934],"type":"Point"}
}