{
  "type": "Feature",
  "properties": {
    "iso:country":"US",
    "sg:address":"307 W Winnie Ln",
    "sg:city":"Carson City",
    "sg:classifiers":[
        {
            "category":"Health Services",
            "subcategory":"Doctor",
            "type":"Services"
        }
    ],
    "sg:phone":"+1 775 885 2323",
    "sg:postcode":"89703",
    "sg:province":"NV",
    "sg:tags":[
        "dentist"
    ],
    "wof:name":"Carson City Family Dentistry",
    "wof:placetype":"venue"
},
  "geometry": {"coordinates":[-119.76934900000001,39.179119],"type":"Point"}
}