{
  "type": "Feature",
  "properties": {
    "iso:country":"US",
    "sg:address":"955 W Moana Ln",
    "sg:city":"Reno",
    "sg:classifiers":[
        {
            "category":"Professional",
            "subcategory":"Management & Consulting",
            "type":"Services"
        }
    ],
    "sg:phone":"+1 775 827 9595",
    "sg:postcode":"89509",
    "sg:province":"NV",
    "sg:tags":[
        "personnel",
        "consultant"
    ],
    "sg:website":"http://www.staffmark.com",
    "wof:name":"Staffmark",
    "wof:placetype":"venue"
},
  "geometry": {"coordinates":[-119.806814,39.491186],"type":"Point"}
}