{
  "type": "Feature",
  "properties": {
    "iso:country":"US",
    "sg:address":"7801 W Charleston Blvd",
    "sg:city":"Las Vegas",
    "sg:classifiers":[
        {
            "category":"Retail",
            "subcategory":"Auto Repair",
            "type":"Services"
        }
    ],
    "sg:phone":"+1 702 307 8650",
    "sg:postcode":"89117",
    "sg:province":"NV",
    "sg:tags":[
        "automobile",
        "inspection"
    ],
    "wof:name":"Smog Busters",
    "wof:placetype":"venue"
},
  "geometry": {"coordinates":[-115.262311,36.1591],"type":"Point"}
}