{
  "type": "Feature",
  "properties": {
    "iso:country":"US",
    "sg:address":"2841 W Craig Rd",
    "sg:city":"North Las Vegas",
    "sg:classifiers":[
        {
            "category":"Manufacturing",
            "subcategory":"Food",
            "type":"Manufacturing & Wholesale Goods"
        }
    ],
    "sg:phone":"+1 702 631 1945",
    "sg:postcode":"89032",
    "sg:province":"NV",
    "sg:tags":[
        "cottonseed",
        "mill",
        "oil",
        "product"
    ],
    "wof:name":"Goudy's II",
    "wof:placetype":"venue"
},
  "geometry": {"coordinates":[-115.178637,36.239355],"type":"Point"}
}