{
  "type": "Feature",
  "properties": {
    "iso:country":"US",
    "sg:address":"4555 E Charleston Blvd",
    "sg:city":"Las Vegas",
    "sg:classifiers":[
        {
            "category":"Restaurant",
            "type":"Food & Drink"
        }
    ],
    "sg:phone":"+1 702 641 6002",
    "sg:postcode":"89104",
    "sg:province":"NV",
    "sg:tags":[
        "out"
    ],
    "wof:name":"Taqueria Victor",
    "wof:placetype":"venue"
},
  "geometry": {"coordinates":[-115.079235,36.158885],"type":"Point"}
}