{
  "type": "Feature",
  "properties": {
    "iso:country":"US",
    "sg:address":"9101 Safeport Cove Ct",
    "sg:city":"Las Vegas",
    "sg:classifiers":[
        {
            "category":"Professional",
            "subcategory":"Art Services",
            "type":"Services"
        }
    ],
    "sg:phone":"+1 702 254 5923",
    "sg:postcode":"89117",
    "sg:province":"NV",
    "sg:tags":[
        "photography",
        "commercial"
    ],
    "wof:name":"Shooting Gallery",
    "wof:placetype":"venue"
},
  "geometry": {"coordinates":[-115.296561,36.136241],"type":"Point"}
}