{
  "type": "Feature",
  "properties": {
    "iso:country":"US",
    "sg:address":"6336 Clarice Ave",
    "sg:city":"Las Vegas",
    "sg:classifiers":[
        {
            "category":"Personal",
            "type":"Services"
        }
    ],
    "sg:phone":"+1 702 869 5042",
    "sg:postcode":"89107",
    "sg:province":"NV",
    "sg:tags":[
        "therapist",
        "massage"
    ],
    "wof:name":"Alissa Anderson Massage",
    "wof:placetype":"venue"
},
  "geometry": {"coordinates":[-115.22944,36.175779],"type":"Point"}
}