{
  "type": "Feature",
  "properties": {
    "iso:country":"US",
    "sg:address":"4155 W Russell Rd",
    "sg:city":"Las Vegas",
    "sg:classifiers":[
        {
            "category":"Wholesale",
            "subcategory":"Electrical",
            "type":"Manufacturing & Wholesale Goods"
        }
    ],
    "sg:phone":"+1 702 362 8203",
    "sg:postcode":"89118",
    "sg:province":"NV",
    "sg:tags":[
        "equipment",
        "electric",
        "supply"
    ],
    "sg:website":"www.g-m-i.net",
    "wof:name":"GROVE Madsen Industries",
    "wof:placetype":"venue"
},
  "geometry": {"coordinates":[-115.195773,36.086253],"type":"Point"}
}