{
  "type": "Feature",
  "properties": {
    "iso:country":"US",
    "sg:address":"832 S Boulder Hwy",
    "sg:city":"Henderson",
    "sg:classifiers":[
        {
            "category":"Restaurant",
            "type":"Food & Drink"
        }
    ],
    "sg:phone":"+1 702 558 3972",
    "sg:postcode":"89015",
    "sg:province":"NV",
    "sg:website":"www.portofsubs.com",
    "wof:name":"Port of Subs",
    "wof:placetype":"venue"
},
  "geometry": {"coordinates":[-114.966436,36.025794],"type":"Point"}
}