{
  "type": "Feature",
  "properties": {
    "iso:country":"US",
    "sg:address":"3716 E Russell Rd",
    "sg:city":"Las Vegas",
    "sg:classifiers":[
        {
            "category":"Health Services",
            "subcategory":"Health Practitioner",
            "type":"Services"
        }
    ],
    "sg:phone":"+1 702 434 0664",
    "sg:postcode":"89120",
    "sg:province":"NV",
    "sg:tags":[
        "counseling",
        "mental"
    ],
    "wof:name":"Neuropsychology Clinic",
    "wof:placetype":"venue"
},
  "geometry": {"coordinates":[-115.094002,36.0858],"type":"Point"}
}