{
  "type": "Feature",
  "properties": {
    "iso:country":"US",
    "sg:address":"4894 W Lone Mountain Rd",
    "sg:city":"Las Vegas",
    "sg:classifiers":[
        {
            "category":"Professional",
            "subcategory":"Advertising",
            "type":"Services"
        }
    ],
    "sg:phone":"+1 702 658 1847",
    "sg:postcode":"89130",
    "sg:province":"NV",
    "sg:tags":[
        "mailing",
        "shipping"
    ],
    "wof:name":"Post Express",
    "wof:placetype":"venue"
},
  "geometry": {"coordinates":[-115.209733,36.246687],"type":"Point"}
}