{
  "type": "Feature",
  "properties": {
    "iso:country":"US",
    "sg:address":"2901 Las Vegas Blvd S Riviera Hotel and Casino",
    "sg:city":"Las Vegas",
    "sg:classifiers":[
        {
            "category":"Arts & Performance",
            "subcategory":"Art Gallery",
            "type":"Entertainment"
        }
    ],
    "sg:postcode":"89109",
    "sg:province":"NV",
    "wof:name":"Crazy Girls Bronze Sculpture",
    "wof:placetype":"venue"
},
  "geometry": {"coordinates":[-115.162099,36.136251],"type":"Point"}
}