{
  "type": "Feature",
  "properties": {
    "iso:country":"US",
    "sg:address":"3325 Las Vegas Blvd S",
    "sg:city":"Las Vegas",
    "sg:classifiers":[
        {
            "category":"Restaurant",
            "type":"Food & Drink"
        },
        {
            "category":"Recreation",
            "subcategory":"Dance Hall",
            "type":"Entertainment"
        }
    ],
    "sg:phone":"+1 702 791 1800",
    "sg:postcode":"89109",
    "sg:province":"NV",
    "sg:tags":[
        "club",
        "italian"
    ],
    "sg:website":"www.lavolv.com",
    "wof:name":"LAVO Italian Restaurant & Nightclub",
    "wof:placetype":"venue"
},
  "geometry": {"coordinates":[-115.171026,36.122677],"type":"Point"}
}