{
  "type": "Feature",
  "properties": {
    "iso:country":"US",
    "sg:address":"6501 Vegas Dr",
    "sg:city":"Las Vegas",
    "sg:classifiers":[
        {
            "category":"Personal",
            "type":"Services"
        }
    ],
    "sg:phone":"+1 702 474 6748",
    "sg:postcode":"89108",
    "sg:province":"NV",
    "sg:tags":[
        "shopping"
    ],
    "wof:name":"I Shop 4U",
    "wof:placetype":"venue"
},
  "geometry": {"coordinates":[-115.235232,36.188481],"type":"Point"}
}