{
  "type": "Feature",
  "properties": {
    "iso:country":"US",
    "sg:address":"1350 W Horizon Ridge Pkwy",
    "sg:city":"Henderson",
    "sg:classifiers":[
        {
            "category":"Retail",
            "subcategory":"Repair Shop",
            "type":"Services"
        }
    ],
    "sg:phone":"+1 702 898 2310",
    "sg:postcode":"89012",
    "sg:province":"NV",
    "sg:tags":[
        "merchandise"
    ],
    "wof:name":"Framing 4-U",
    "wof:placetype":"venue"
},
  "geometry": {"coordinates":[-115.044446,36.021936],"type":"Point"}
}