{
  "type": "Feature",
  "properties": {
    "iso:country":"US",
    "sg:address":"1550 N Green Valley Pkwy #300",
    "sg:city":"Henderson",
    "sg:classifiers":[
        {
            "category":"Health Services",
            "subcategory":"Clinic",
            "type":"Services"
        },
        {
            "category":"Sports & Exercise",
            "subcategory":"Gym",
            "type":"Entertainment"
        }
    ],
    "sg:phone":"+1 702 202 1300",
    "sg:postcode":"89074",
    "sg:province":"NV",
    "sg:tags":[
        "trainer",
        "medical"
    ],
    "sg:website":"www.snapfitness.com",
    "wof:name":"Snap Fitness",
    "wof:placetype":"venue"
},
  "geometry": {"coordinates":[-115.084602,36.029581],"type":"Point"}
}