{
  "type": "Feature",
  "properties": {
    "iso:country":"US",
    "sg:address":"4916 Canadian Dr",
    "sg:city":"Las Vegas",
    "sg:classifiers":[
        {
            "category":"Arts & Performance",
            "subcategory":"Theater",
            "type":"Entertainment"
        }
    ],
    "sg:phone":"+1 702 655 5940",
    "sg:postcode":"89130",
    "sg:province":"NV",
    "sg:tags":[
        "live",
        "music"
    ],
    "wof:name":"Personal Pop",
    "wof:placetype":"venue"
},
  "geometry": {"coordinates":[-115.210404,36.250162],"type":"Point"}
}