{
  "type": "Feature",
  "properties": {
    "iso:country":"US",
    "sg:address":"353 Pilot Rd",
    "sg:city":"Las Vegas",
    "sg:classifiers":[
        {
            "category":"Building & Trades",
            "subcategory":"Construction",
            "type":"Services"
        }
    ],
    "sg:phone":"+1 702 270 6310",
    "sg:postcode":"89119",
    "sg:province":"NV",
    "sg:tags":[
        "contractor"
    ],
    "sg:website":"www.sunrisecarpentry.com",
    "wof:name":"Sunrise Carpentry Inc",
    "wof:placetype":"venue"
},
  "geometry": {"coordinates":[-115.156441,36.06774],"type":"Point"}
}