{
  "type": "Feature",
  "properties": {
    "iso:country":"US",
    "sg:address":"827 S Boulder Hwy",
    "sg:city":"Henderson",
    "sg:classifiers":[
        {
            "category":"Real Estate",
            "subcategory":"Real Estate Services",
            "type":"Services"
        }
    ],
    "sg:phone":"+1 702 566 8185",
    "sg:postcode":"89015",
    "sg:province":"NV",
    "sg:tags":[
        "management",
        "property"
    ],
    "sg:website":"www.knappsales.com",
    "wof:name":"Knapp Realty",
    "wof:placetype":"venue"
},
  "geometry": {"coordinates":[-114.967003,36.026299],"type":"Point"}
}