{
  "type": "Feature",
  "properties": {
    "iso:country":"US",
    "sg:address":"207 Kingsbury Grade Rd",
    "sg:city":"Stateline",
    "sg:classifiers":[
        {
            "category":"Personal",
            "type":"Services"
        }
    ],
    "sg:phone":"+1 775 588 6637",
    "sg:postcode":"89449",
    "sg:province":"CA",
    "sg:tags":[
        "consultant",
        "wedding"
    ],
    "wof:name":"Weddings With A View",
    "wof:placetype":"venue"
},
  "geometry": {"coordinates":[-119.92985,38.968283],"type":"Point"}
}