{
  "type": "Feature",
  "properties": {
    "iso:country":"US",
    "sg:address":"7380 S Eastern Ave",
    "sg:city":"Las Vegas",
    "sg:classifiers":[
        {
            "category":"Communications",
            "type":"Services"
        }
    ],
    "sg:phone":"+1 702 433 8324",
    "sg:postcode":"89119",
    "sg:province":"NV",
    "sg:tags":[
        "web",
        "design"
    ],
    "sg:website":"www.techservice2u.com/",
    "wof:name":"Tech Service 2U",
    "wof:placetype":"venue"
},
  "geometry": {"coordinates":[-115.118267,36.055682],"type":"Point"}
}