{
  "type": "Feature",
  "properties": {
    "iso:country":"US",
    "sg:address":"6557 Strawberry Cream Ct",
    "sg:city":"Las Vegas",
    "sg:classifiers":[
        {
            "category":"Health Services",
            "subcategory":"Doctor",
            "type":"Services"
        }
    ],
    "sg:phone":"+1 702 207 0313",
    "sg:postcode":"89142",
    "sg:province":"NV",
    "wof:name":"Ely Family Dental",
    "wof:placetype":"venue"
},
  "geometry": {"coordinates":[-115.030784,36.152023],"type":"Point"}
}