{
  "type": "Feature",
  "properties": {
    "iso:country":"US",
    "sg:address":"83 E Agate Ave",
    "sg:city":"Las Vegas",
    "sg:classifiers":[
        {
            "category":"Professional",
            "subcategory":"Management & Consulting",
            "type":"Services"
        }
    ],
    "sg:phone":"+1 702 740 4337",
    "sg:postcode":"89123",
    "sg:province":"NV",
    "sg:tags":[
        "consultant",
        "telecommunication"
    ],
    "wof:name":"Altair Communications",
    "wof:placetype":"venue"
},
  "geometry": {"coordinates":[-115.168995,36.024588],"type":"Point"}
}