{
  "type": "Feature",
  "properties": {
    "iso:country":"US",
    "sg:address":"1848 E Charleston Blvd",
    "sg:city":"Las Vegas",
    "sg:classifiers":[
        {
            "category":"Shopping",
            "type":"Retail Goods"
        }
    ],
    "sg:phone":"+1 702 368 0300",
    "sg:postcode":"89104",
    "sg:province":"NV",
    "sg:tags":[
        "cosmetic",
        "perfume"
    ],
    "wof:name":"Avon Products",
    "wof:placetype":"venue"
},
  "geometry": {"coordinates":[-115.12411400000001,36.15879],"type":"Point"}
}