{
  "type": "Feature",
  "properties": {
    "iso:country":"US",
    "sg:address":"2400 N Buffalo Dr Ste 145",
    "sg:city":"Las Vegas",
    "sg:classifiers":[
        {
            "category":"Restaurant",
            "type":"Food & Drink"
        }
    ],
    "sg:phone":"+1 702 541 6708",
    "sg:postcode":"89128",
    "sg:province":"NV",
    "sg:tags":[
        "traditional",
        "american",
        "brunch",
        "breakfast"
    ],
    "sg:website":"www.babycakescafelv.com",
    "wof:name":"Babycakes Cafe",
    "wof:placetype":"venue"
},
  "geometry": {"coordinates":[-115.259969,36.204023],"type":"Point"}
}