{
  "type": "Feature",
  "properties": {
    "iso:country":"US",
    "sg:address":"1845 Southview Dr",
    "sg:city":"Sparks",
    "sg:classifiers":[
        {
            "category":"Professional",
            "type":"Services"
        }
    ],
    "sg:phone":"+1 775 626 3454",
    "sg:postcode":"89436",
    "sg:province":"NV",
    "sg:tags":[
        "communications",
        "contracting"
    ],
    "wof:name":"FCC Communications Inc",
    "wof:placetype":"venue"
},
  "geometry": {"coordinates":[-119.707407,39.578932],"type":"Point"}
}