{
  "type": "Feature",
  "properties": {
    "iso:country":"US",
    "sg:address":"9295 Prototype Dr",
    "sg:city":"Reno",
    "sg:classifiers":[
        {
            "category":"Manufacturing",
            "subcategory":"Retail Goods",
            "type":"Manufacturing & Wholesale Goods"
        }
    ],
    "sg:phone":"+1 775 448 7777",
    "sg:postcode":"89521",
    "sg:province":"NV",
    "sg:tags":[
        "equipment",
        "gaming",
        "supply"
    ],
    "sg:website":"www.igt.com",
    "wof:name":"International Game Technology",
    "wof:placetype":"venue"
},
  "geometry": {"coordinates":[-119.761218,39.449492],"type":"Point"}
}