{
  "type": "Feature",
  "properties": {
    "iso:country":"US",
    "sg:address":"3113 Conners Dr",
    "sg:city":"Las Vegas",
    "sg:classifiers":[
        {
            "category":"Real Estate",
            "subcategory":"Real Estate Agent",
            "type":"Services"
        }
    ],
    "sg:phone":"+1 702 870 1964",
    "sg:postcode":"89107",
    "sg:province":"NV",
    "wof:name":"H & Gg PROPERTIES Co",
    "wof:placetype":"venue"
},
  "geometry": {"coordinates":[-115.18529700000001,36.169472],"type":"Point"}
}