{
  "type": "Feature",
  "properties": {
    "iso:country":"US",
    "sg:address":"1176 W Lake Mead Blvd",
    "sg:city":"Las Vegas",
    "sg:classifiers":[
        {
            "category":"Banks & Credit Unions",
            "subcategory":"Bank",
            "type":"Services"
        }
    ],
    "sg:phone":"+1 702 631 4390",
    "sg:postcode":"89106",
    "sg:province":"NV",
    "sg:tags":[
        "loan",
        "real estate"
    ],
    "wof:name":"Moving On Up Inc",
    "wof:placetype":"venue"
},
  "geometry": {"coordinates":[-115.157714,36.195768],"type":"Point"}
}