{
  "type": "Feature",
  "properties": {
    "iso:country":"US",
    "sg:address":"1838 Walker Ln",
    "sg:city":"Henderson",
    "sg:classifiers":[
        {
            "category":"Health Services",
            "subcategory":"Hospital",
            "type":"Services"
        }
    ],
    "sg:phone":"+1 702 898 3282",
    "sg:postcode":"89014",
    "sg:province":"NV",
    "sg:tags":[
        "medical",
        "center"
    ],
    "wof:name":"Pcca",
    "wof:placetype":"venue"
},
  "geometry": {"coordinates":[-115.06500200000001,36.057899],"type":"Point"}
}