{
  "type": "Feature",
  "properties": {
    "iso:country":"US",
    "sg:address":"955 W Craig Rd Ste 108",
    "sg:city":"North Las Vegas",
    "sg:classifiers":[
        {
            "category":"Banks & Credit Unions",
            "subcategory":"Financial Services",
            "type":"Services"
        }
    ],
    "sg:phone":"+1 702 647 4599",
    "sg:postcode":"89032",
    "sg:province":"NV",
    "sg:tags":[
        "broker",
        "mortgage"
    ],
    "sg:website":"www.loansfast.com",
    "wof:name":"American General Financial Services",
    "wof:placetype":"venue"
},
  "geometry": {"coordinates":[-115.154937,36.238368],"type":"Point"}
}