{
  "type": "Feature",
  "properties": {
    "iso:country":"US",
    "sg:address":"5130 Meadowood Mall Cir",
    "sg:city":"Reno",
    "sg:classifiers":[
        {
            "category":"Shopping",
            "subcategory":"Hobbies, Toys, & Games",
            "type":"Retail Goods"
        }
    ],
    "sg:phone":"+1 775 825 3023",
    "sg:postcode":"89502",
    "sg:province":"NV",
    "sg:website":"www.allaboardsk8andsno.net",
    "wof:name":"World Of Toys",
    "wof:placetype":"venue"
},
  "geometry": {"coordinates":[-119.781425,39.476381],"type":"Point"}
}