{
  "type": "Feature",
  "properties": {
    "iso:country":"US",
    "sg:address":"1460 Tree Line Dr",
    "sg:city":"Las Vegas",
    "sg:classifiers":[
        {
            "category":"Organizations",
            "subcategory":"Religious Organization",
            "type":"Services"
        }
    ],
    "sg:phone":"+1 702 432 3711",
    "sg:postcode":"89142",
    "sg:province":"NV",
    "sg:tags":[
        "church"
    ],
    "wof:name":"Orchard Baptist Church",
    "wof:placetype":"venue"
},
  "geometry": {"coordinates":[-115.038286,36.155244],"type":"Point"}
}