{
  "type": "Feature",
  "properties": {
    "iso:country":"US",
    "sg:address":"4315 Viento Way",
    "sg:city":"Reno",
    "sg:classifiers":[
        {
            "category":"Social Services",
            "type":"Services"
        }
    ],
    "sg:phone":"+1 775 787 2294",
    "sg:postcode":"89502",
    "sg:province":"NV",
    "sg:tags":[
        "counselor",
        "marriage",
        "family"
    ],
    "wof:name":"Marriage & Family Therapy",
    "wof:placetype":"venue"
},
  "geometry": {"coordinates":[-119.752365,39.487056],"type":"Point"}
}