{
  "type": "Feature",
  "properties": {
    "iso:country":"US",
    "sg:address":"3836 Losee Rd",
    "sg:city":"North Las Vegas",
    "sg:classifiers":[
        {
            "category":"Building & Trades",
            "subcategory":"Equipment Rental",
            "type":"Services"
        }
    ],
    "sg:phone":"+1 702 642 2250",
    "sg:postcode":"89030",
    "sg:province":"NV",
    "sg:tags":[
        "heavy",
        "construction"
    ],
    "wof:name":"R & T Enterprises",
    "wof:placetype":"venue"
},
  "geometry": {"coordinates":[-115.119834,36.2273],"type":"Point"}
}