{
  "type": "Feature",
  "properties": {
    "iso:country":"US",
    "sg:address":"4680 Polaris Ave",
    "sg:city":"Las Vegas",
    "sg:classifiers":[
        {
            "category":"Arts & Performance",
            "subcategory":"Art Gallery",
            "type":"Entertainment"
        }
    ],
    "sg:phone":"+1 702 792 9292",
    "sg:postcode":"89103",
    "sg:province":"NV",
    "wof:name":"Lassen International Inc",
    "wof:placetype":"venue"
},
  "geometry": {"coordinates":[-115.185288,36.104919],"type":"Point"}
}