{
  "type": "Feature",
  "properties": {
    "iso:country":"US",
    "sg:address":"1974 N Rainbow Blvd",
    "sg:city":"Las Vegas",
    "sg:classifiers":[
        {
            "category":"Restaurant",
            "type":"Food & Drink"
        }
    ],
    "sg:phone":"+1 702 638 2746",
    "sg:postcode":"89108",
    "sg:province":"NV",
    "sg:tags":[
        "thai"
    ],
    "sg:website":"www.pinkaowthai.com",
    "wof:name":"Pin-Kaow Thai Restaurant",
    "wof:placetype":"venue"
},
  "geometry": {"coordinates":[-115.241997,36.195],"type":"Point"}
}