{
  "type": "Feature",
  "properties": {
    "iso:country":"US",
    "sg:address":"205 E Warm Springs Rd",
    "sg:city":"Las Vegas",
    "sg:classifiers":[
        {
            "category":"Real Estate",
            "subcategory":"Real Estate Agent",
            "type":"Services"
        }
    ],
    "sg:phone":"+1 702 440 4636",
    "sg:postcode":"89119",
    "sg:province":"NV",
    "wof:name":"R B Realty",
    "wof:placetype":"venue"
},
  "geometry": {"coordinates":[-115.161188,36.05687],"type":"Point"}
}