{
  "type": "Feature",
  "properties": {
    "iso:country":"US",
    "sg:address":"3568 Losee Rd",
    "sg:city":"North Las Vegas",
    "sg:classifiers":[
        {
            "category":"Wholesale",
            "subcategory":"Construction Materials",
            "type":"Manufacturing & Wholesale Goods"
        }
    ],
    "sg:phone":"+1 702 222 0838",
    "sg:postcode":"89030",
    "sg:province":"NV",
    "sg:tags":[
        "lumber"
    ],
    "wof:name":"Johnson Manley Black LLC",
    "wof:placetype":"venue"
},
  "geometry": {"coordinates":[-115.117125,36.231203],"type":"Point"}
}