{
  "type": "Feature",
  "properties": {
    "iso:country":"US",
    "sg:address":"21 N Mojave Rd",
    "sg:city":"Las Vegas",
    "sg:classifiers":[
        {
            "category":"Arts & Performance",
            "subcategory":"Theater",
            "type":"Entertainment"
        }
    ],
    "sg:phone":"+1 702 437 1451",
    "sg:postcode":"89101",
    "sg:province":"NV",
    "sg:tags":[
        "dance",
        "company"
    ],
    "wof:name":"Rainbow Connextion",
    "wof:placetype":"venue"
},
  "geometry": {"coordinates":[-115.105457,36.160854],"type":"Point"}
}