{
  "type": "Feature",
  "properties": {
    "iso:country":"US",
    "sg:address":"2255 Larkin Cir",
    "sg:city":"Sparks",
    "sg:classifiers":[
        {
            "category":"Wholesale",
            "subcategory":"Groceries",
            "type":"Manufacturing & Wholesale Goods"
        }
    ],
    "sg:phone":"+1 775 358 8447",
    "sg:postcode":"89431",
    "sg:province":"NV",
    "sg:tags":[
        "general"
    ],
    "wof:name":"Sysco Transportation",
    "wof:placetype":"venue"
},
  "geometry": {"coordinates":[-119.701974,39.522977],"type":"Point"}
}