{
  "type": "Feature",
  "properties": {
    "iso:country":"US",
    "sg:address":"2301 Renaissance Dr",
    "sg:city":"Las Vegas",
    "sg:classifiers":[
        {
            "category":"Banks & Credit Unions",
            "subcategory":"Bank",
            "type":"Services"
        }
    ],
    "sg:phone":"+1 702 933 6568",
    "sg:postcode":"89119",
    "sg:province":"NV",
    "sg:website":"www.silverstatebank.com",
    "wof:name":"Silver State Bank",
    "wof:placetype":"venue"
},
  "geometry": {"coordinates":[-115.122498,36.103284],"type":"Point"}
}