{
  "type": "Feature",
  "properties": {
    "iso:country":"US",
    "sg:address":"631 N Stephanie St",
    "sg:city":"Henderson",
    "sg:classifiers":[
        {
            "category":"Wholesale",
            "subcategory":"Vending Machines",
            "type":"Manufacturing & Wholesale Goods"
        },
        {
            "category":"Social Services",
            "subcategory":"Job Training",
            "type":"Services"
        }
    ],
    "sg:phone":"+1 702 232 2544",
    "sg:postcode":"89014",
    "sg:province":"NV",
    "sg:tags":[
        "operator",
        "employment"
    ],
    "wof:name":"Principles International",
    "wof:placetype":"venue"
},
  "geometry": {"coordinates":[-115.046233,36.064622],"type":"Point"}
}