{
  "type": "Feature",
  "properties": {
    "iso:country":"US",
    "sg:address":"2421 E Stewart Ave",
    "sg:city":"Las Vegas",
    "sg:classifiers":[
        {
            "category":"Autos & Motor Vehicles",
            "subcategory":"Auto Supplies",
            "type":"Retail Goods"
        }
    ],
    "sg:phone":"+1 702 384 1902",
    "sg:postcode":"89101",
    "sg:province":"NV",
    "sg:tags":[
        "tire"
    ],
    "wof:name":"Sullins Tire & Svc",
    "wof:placetype":"venue"
},
  "geometry": {"coordinates":[-115.116059,36.166638],"type":"Point"}
}