{
  "type": "Feature",
  "properties": {
    "iso:country":"US",
    "sg:address":"1450 Hulda Way",
    "sg:city":"Sparks",
    "sg:classifiers":[
        {
            "category":"Wholesale",
            "subcategory":"Office Equipment",
            "type":"Manufacturing & Wholesale Goods"
        }
    ],
    "sg:phone":"+1 775 329 2870",
    "sg:postcode":"89431",
    "sg:province":"NV",
    "wof:name":"Nevada Office Machines Inc",
    "wof:placetype":"venue"
},
  "geometry": {"coordinates":[-119.710587,39.524062],"type":"Point"}
}