{
  "type": "Feature",
  "properties": {
    "iso:country":"US",
    "sg:address":"3960 Howard Hughes Pkwy",
    "sg:city":"Las Vegas",
    "sg:classifiers":[
        {
            "category":"Real Estate",
            "subcategory":"Real Estate Agent",
            "type":"Services"
        }
    ],
    "sg:phone":"+1 702 735 2009",
    "sg:postcode":"89169",
    "sg:province":"NV",
    "sg:website":"www.lvcolliers.com",
    "wof:name":"Colliers International",
    "wof:placetype":"venue"
},
  "geometry": {"coordinates":[-115.157749,36.11686],"type":"Point"}
}