{
  "type": "Feature",
  "properties": {
    "iso:country":"US",
    "sg:address":"1102 Sharp",
    "sg:city":"North Las Vegas",
    "sg:classifiers":[
        {
            "category":"Manufacturing",
            "subcategory":"Metals",
            "type":"Manufacturing & Wholesale Goods"
        }
    ],
    "sg:phone":"+1 702 642 1231",
    "sg:postcode":"89030",
    "sg:province":"NV",
    "sg:tags":[
        "ornamental",
        "structural",
        "work",
        "metalwork",
        "mfg"
    ],
    "wof:name":"Iron Specialists",
    "wof:placetype":"venue"
},
  "geometry": {"coordinates":[-115.127185,36.220179],"type":"Point"}
}