{
  "type": "Feature",
  "properties": {
    "iso:country":"US",
    "sg:address":"360 Max Ct",
    "sg:city":"Henderson",
    "sg:classifiers":[
        {
            "category":"Organizations",
            "subcategory":"Professional Association",
            "type":"Services"
        }
    ],
    "sg:phone":"+1 702 914 8711",
    "sg:postcode":"89015",
    "sg:province":"NV",
    "wof:name":"Mystic Bay Assn",
    "wof:placetype":"venue"
},
  "geometry": {"coordinates":[-115.005126,36.057052],"type":"Point"}
}