{
  "type": "Feature",
  "properties": {
    "iso:country":"US",
    "sg:address":"920 Valley Rd",
    "sg:city":"Reno",
    "sg:classifiers":[
        {
            "category":"Professional",
            "subcategory":"Research",
            "type":"Services"
        }
    ],
    "sg:phone":"+1 775 784 5329",
    "sg:postcode":"89512",
    "sg:province":"NV",
    "sg:tags":[
        "commercial",
        "physical"
    ],
    "wof:name":"Forestry Sciences Laboratory",
    "wof:placetype":"venue"
},
  "geometry": {"coordinates":[-119.807721,39.538767],"type":"Point"}
}