{
  "type": "Feature",
  "properties": {
    "iso:country":"US",
    "sg:address":"6295 Pride",
    "sg:city":"Las Vegas",
    "sg:classifiers":[
        {
            "category":"Organizations",
            "subcategory":"Membership Organization",
            "type":"Services"
        }
    ],
    "sg:phone":"+1 702 221 9234",
    "sg:postcode":"89103",
    "sg:province":"NV",
    "wof:name":"Traditions Homeowners Assn",
    "wof:placetype":"venue"
},
  "geometry": {"coordinates":[-115.22739300000001,36.118587],"type":"Point"}
}