{
  "type": "Feature",
  "properties": {
    "iso:country":"US",
    "sg:address":"8965 S. Eastern #260 Suite O",
    "sg:city":"Las Vegas",
    "sg:classifiers":[
        {
            "category":"Autos & Motor Vehicles",
            "subcategory":"Automobile Sales",
            "type":"Retail Goods"
        },
        {
            "category":"Banks & Credit Unions",
            "subcategory":"Financial Services",
            "type":"Services"
        }
    ],
    "sg:phone":"+1 702 478 2605",
    "sg:postcode":"89123",
    "sg:province":"NV",
    "sg:tags":[
        "car",
        "advising"
    ],
    "sg:website":"www.speedycarloans.com",
    "wof:name":"Speedy Car Loans",
    "wof:placetype":"venue"
},
  "geometry": {"coordinates":[-115.119719,36.026376],"type":"Point"}
}