{
  "type": "Feature",
  "properties": {
    "iso:country":"US",
    "sg:address":"3170 Polaris Ave Ste 31",
    "sg:city":"Las Vegas",
    "sg:classifiers":[
        {
            "category":"Education",
            "subcategory":"Music School",
            "type":"Public Place"
        },
        {
            "category":"Shopping",
            "subcategory":"Computers & Home Electronics",
            "type":"Retail Goods"
        }
    ],
    "sg:phone":"+1 702 492 6803",
    "sg:postcode":"89102",
    "sg:province":"NV",
    "sg:tags":[
        "instrument",
        "teacher",
        "musical"
    ],
    "sg:website":"www.musiciansadvocate.com",
    "wof:name":"Musician's Advocate Discount Pro Audio",
    "wof:placetype":"venue"
},
  "geometry": {"coordinates":[-115.185571,36.132524],"type":"Point"}
}