{
  "type": "Feature",
  "properties": {
    "iso:country":"US",
    "sg:address":"4175 S Riley St #200",
    "sg:city":"Las Vegas",
    "sg:classifiers":[
        {
            "category":"Insurance",
            "subcategory":"Hazard Insurance",
            "type":"Services"
        }
    ],
    "sg:phone":"+1 702 699 5569",
    "sg:postcode":"89147",
    "sg:province":"NV",
    "sg:website":"insuranceinlasvegasnv.com",
    "wof:name":"Absolute Insurance Service, Inc.",
    "wof:placetype":"venue"
},
  "geometry": {"coordinates":[-115.28415699999999,36.113574],"type":"Point"}
}