{
  "type": "Feature",
  "properties": {
    "iso:country":"US",
    "sg:address":"1200 S 4th St Ste 104",
    "sg:city":"Las Vegas",
    "sg:classifiers":[
        {
            "category":"Real Estate",
            "subcategory":"Real Estate Services",
            "type":"Services"
        }
    ],
    "sg:phone":"+1 702 306 3044",
    "sg:postcode":"89104",
    "sg:province":"NV",
    "sg:website":"www.trusteesaleclearinghouse.com",
    "wof:name":"Trustee Sale Clearing House",
    "wof:placetype":"venue"
},
  "geometry": {"coordinates":[-115.150242,36.157412],"type":"Point"}
}