{
  "type": "Feature",
  "properties": {
    "iso:country":"US",
    "sg:address":"3580 Polaris Avenue Suite 8",
    "sg:city":"Las Vegas",
    "sg:classifiers":[
        {
            "category":"Personal",
            "type":"Services"
        }
    ],
    "sg:phone":"+1 702 731 1880",
    "sg:postcode":"89103",
    "sg:province":"NV",
    "sg:tags":[
        "mover"
    ],
    "wof:name":"Precision Computer Rentals",
    "wof:placetype":"venue"
},
  "geometry": {"coordinates":[-115.185447,36.123673],"type":"Point"}
}