{
  "type": "Feature",
  "properties": {
    "iso:country":"US",
    "sg:address":"25 Brandermill Dr",
    "sg:city":"Henderson",
    "sg:classifiers":[
        {
            "category":"Education",
            "subcategory":"Special Training",
            "type":"Public Place"
        }
    ],
    "sg:phone":"+1 702 360 2904",
    "sg:postcode":"89052",
    "sg:province":"NV",
    "wof:name":"Alan Wal Performance Driving",
    "wof:placetype":"venue"
},
  "geometry": {"coordinates":[-115.08932900000001,35.966023],"type":"Point"}
}