{
  "type": "Feature",
  "properties": {
    "iso:country":"US",
    "sg:address":"7710 W Sahara Ave",
    "sg:city":"Las Vegas",
    "sg:classifiers":[
        {
            "category":"Health Services",
            "subcategory":"Doctor",
            "type":"Services"
        }
    ],
    "sg:phone":"+1 702 228 7941",
    "sg:postcode":"89117",
    "sg:province":"NV",
    "sg:tags":[
        "physician",
        "surgeon"
    ],
    "wof:name":"Kappellini Medical Inc",
    "wof:placetype":"venue"
},
  "geometry": {"coordinates":[-115.259745,36.143793],"type":"Point"}
}