{
  "type": "Feature",
  "properties": {
    "iso:country":"US",
    "sg:address":"3318 S Highland Dr",
    "sg:city":"Las Vegas",
    "sg:classifiers":[
        {
            "category":"Autos & Motor Vehicles",
            "subcategory":"Auto Supplies",
            "type":"Retail Goods"
        }
    ],
    "sg:phone":"+1 702 220 5262",
    "sg:postcode":"89109",
    "sg:province":"NV",
    "wof:name":"Maximum Performance Motorsport",
    "wof:placetype":"venue"
},
  "geometry": {"coordinates":[-115.177041,36.131073],"type":"Point"}
}