{
  "type": "Feature",
  "properties": {
    "iso:country":"US",
    "sg:address":"3770 Las Vegas Blvd S",
    "sg:city":"Las Vegas",
    "sg:classifiers":[
        {
            "category":"Restaurant",
            "type":"Food & Drink"
        }
    ],
    "sg:menulink":"http://www.allmenus.com/nv/las-vegas/9877-blackstones-steak-house/menu/",
    "sg:phone":"+1 800 311 8999",
    "sg:postcode":"89109",
    "sg:province":"NV",
    "sg:tags":[
        "american",
        "steakhouse"
    ],
    "wof:name":"Blackstone's Steak House",
    "wof:placetype":"venue"
},
  "geometry": {"coordinates":[-115.176457,36.104464],"type":"Point"}
}