{
  "type": "Feature",
  "properties": {
    "iso:country":"US",
    "sg:address":"1819 Hymer Ave",
    "sg:city":"Sparks",
    "sg:classifiers":[
        {
            "category":"Organizations",
            "subcategory":"Labor Organization",
            "type":"Services"
        }
    ],
    "sg:phone":"+1 775 359 4241",
    "sg:postcode":"89431",
    "sg:province":"NV",
    "wof:name":"Local 241",
    "wof:placetype":"venue"
},
  "geometry": {"coordinates":[-119.768133,39.53086],"type":"Point"}
}