{
  "type": "Feature",
  "properties": {
    "iso:country":"US",
    "sg:address":"10537 Galleon Peak Ln",
    "sg:city":"Las Vegas",
    "sg:classifiers":[
        {
            "category":"Professional",
            "subcategory":"Accounting & Tax Preparation",
            "type":"Services"
        }
    ],
    "sg:phone":"+1 702 880 9409",
    "sg:postcode":"89149",
    "sg:province":"NV",
    "sg:tags":[
        "accountant"
    ],
    "wof:name":"Best Doggone Bookkeeping Co LLC",
    "wof:placetype":"venue"
},
  "geometry": {"coordinates":[-115.324948,36.301393],"type":"Point"}
}