{
  "type": "Feature",
  "properties": {
    "iso:country":"US",
    "sg:address":"10250 Rarity Ave",
    "sg:city":"Las Vegas",
    "sg:classifiers":[
        {
            "category":"Building & Trades",
            "subcategory":"Construction",
            "type":"Services"
        }
    ],
    "sg:phone":"+1 702 645 4628",
    "sg:postcode":"89135",
    "sg:province":"NV",
    "sg:tags":[
        "house",
        "nonresidential"
    ],
    "wof:name":"Able Builders Inc",
    "wof:placetype":"venue"
},
  "geometry": {"coordinates":[-115.317595,36.136661],"type":"Point"}
}