{
  "type": "Feature",
  "properties": {
    "iso:country":"US",
    "sg:address":"4986 Ridgeview Dr",
    "sg:city":"Las Vegas",
    "sg:classifiers":[
        {
            "category":"Building & Trades",
            "subcategory":"Construction",
            "type":"Services"
        }
    ],
    "sg:phone":"+1 702 456 3895",
    "sg:postcode":"89120",
    "sg:province":"NV",
    "sg:tags":[
        "hanging",
        "contractor"
    ],
    "wof:name":"Valleywide Painting",
    "wof:placetype":"venue"
},
  "geometry": {"coordinates":[-115.092279,36.09795],"type":"Point"}
}