{
  "type": "Feature",
  "properties": {
    "iso:country":"US",
    "sg:address":"990 D St",
    "sg:city":"Las Vegas",
    "sg:classifiers":[
        {
            "category":"Social Services",
            "subcategory":"Child Care",
            "type":"Services"
        }
    ],
    "sg:phone":"+1 702 647 4907",
    "sg:postcode":"89106",
    "sg:province":"NV",
    "sg:tags":[
        "center",
        "day"
    ],
    "wof:name":"Variety Day Home",
    "wof:placetype":"venue"
},
  "geometry": {"coordinates":[-115.147003,36.181599],"type":"Point"}
}