{
  "type": "Feature",
  "properties": {
    "iso:country":"US",
    "sg:address":"3732 Lakeside Dr",
    "sg:city":"Reno",
    "sg:classifiers":[
        {
            "category":"Health Services",
            "subcategory":"Health Practitioner",
            "type":"Services"
        }
    ],
    "sg:phone":"+1 775 825 2588",
    "sg:postcode":"89509",
    "sg:province":"NV",
    "sg:tags":[
        "psychotherapist"
    ],
    "wof:name":"Mountain Quest Hypnotherapy",
    "wof:placetype":"venue"
},
  "geometry": {"coordinates":[-119.807835,39.48958],"type":"Point"}
}