{
  "type": "Feature",
  "properties": {
    "iso:country":"US",
    "sg:address":"450 W Silver St",
    "sg:city":"Elko",
    "sg:classifiers":[
        {
            "category":"Home & Garden",
            "subcategory":"Building Materials",
            "type":"Retail Goods"
        }
    ],
    "sg:phone":"+1 775 777 7587",
    "sg:postcode":"89801",
    "sg:province":"NV",
    "sg:tags":[
        "paint",
        "window",
        "covering"
    ],
    "wof:name":"Paints Plus",
    "wof:placetype":"venue"
},
  "geometry": {"coordinates":[-115.770746,40.825537],"type":"Point"}
}