{
  "type": "Feature",
  "properties": {
    "iso:country":"US",
    "sg:address":"P.O. Box 6000",
    "sg:city":"The Lakes",
    "sg:classifiers":[
        {
            "category":"Banks & Credit Unions",
            "subcategory":"Bank",
            "type":"Services"
        }
    ],
    "sg:phone":"+1 888 766 2484",
    "sg:postcode":"89163",
    "sg:province":"NV",
    "sg:website":"www.citicards.com",
    "wof:name":"Citibank/Choice",
    "wof:placetype":"venue"
},
  "geometry": {"coordinates":[-115.13639999999999,36.1753],"type":"Point"}
}