{
  "type": "Feature",
  "properties": {
    "iso:country":"US",
    "sg:address":"2270 Corporate Cir",
    "sg:city":"Henderson",
    "sg:classifiers":[
        {
            "category":"Professional",
            "subcategory":"Engineering",
            "type":"Services"
        }
    ],
    "sg:phone":"+1 702 263 7275",
    "sg:postcode":"89074",
    "sg:province":"NV",
    "sg:tags":[
        "engineer"
    ],
    "wof:name":"PBS & J",
    "wof:placetype":"venue"
},
  "geometry": {"coordinates":[-115.08991,36.026831],"type":"Point"}
}