{
  "type": "Feature",
  "properties": {
    "iso:country":"US",
    "sg:address":"3631 Seneca Ln",
    "sg:city":"Las Vegas",
    "sg:classifiers":[
        {
            "category":"Real Estate",
            "subcategory":"Real Estate Operator",
            "type":"Services"
        }
    ],
    "sg:phone":"+1 702 361 4942",
    "sg:postcode":"89169",
    "sg:province":"NV",
    "sg:tags":[
        "building",
        "nonresidential"
    ],
    "wof:name":"Shelbourne Properties Ltd",
    "wof:placetype":"venue"
},
  "geometry": {"coordinates":[-115.127952,36.123761],"type":"Point"}
}