{
  "type": "Feature",
  "properties": {
    "iso:country":"US",
    "sg:address":"55 S Valle Verde Dr",
    "sg:city":"Henderson",
    "sg:classifiers":[
        {
            "category":"Real Estate",
            "subcategory":"Real Estate Agent",
            "type":"Services"
        }
    ],
    "sg:phone":"+1 702 434 8885",
    "sg:postcode":"89012",
    "sg:province":"NV",
    "sg:website":"www.kbmorrisrealestate.com",
    "wof:name":"K B Morris Real Estate Inc",
    "wof:placetype":"venue"
},
  "geometry": {"coordinates":[-115.06233899999999,36.024124],"type":"Point"}
}