{
  "type": "Feature",
  "properties": {
    "iso:country":"US",
    "sg:address":"3600 N Buffalo Dr Ste 100",
    "sg:city":"Las Vegas",
    "sg:classifiers":[
        {
            "category":"Health Services",
            "subcategory":"Dentist",
            "type":"Services"
        }
    ],
    "sg:phone":"+1 702 405 6100",
    "sg:postcode":"89129",
    "sg:province":"NV",
    "wof:name":"Holland Jonathan D DDS",
    "wof:placetype":"venue"
},
  "geometry": {"coordinates":[-115.26029,36.225786],"type":"Point"}
}