{
  "type": "Feature",
  "properties": {
    "iso:country":"US",
    "sg:address":"3141 Fremont Street",
    "sg:city":"Las Vegas",
    "sg:classifiers":[
        {
            "category":"Retail",
            "subcategory":"Auto Repair",
            "type":"Services"
        }
    ],
    "sg:phone":"+1 702 212 0442",
    "sg:postcode":"89104",
    "sg:province":"NV",
    "wof:name":"Raul's Auto Shop",
    "wof:placetype":"venue"
},
  "geometry": {"coordinates":[-115.10422,36.14856],"type":"Point"}
}