{
  "type": "Feature",
  "properties": {
    "iso:country":"US",
    "sg:address":"7604 Charles Conrad Cir",
    "sg:city":"Las Vegas",
    "sg:classifiers":[
        {
            "category":"Professional",
            "subcategory":"Business Services",
            "type":"Services"
        }
    ],
    "sg:phone":"+1 702 240 2007",
    "sg:postcode":"89145",
    "sg:province":"NV",
    "sg:tags":[
        "planning",
        "sales"
    ],
    "wof:name":"Craig Hanson",
    "wof:placetype":"venue"
},
  "geometry": {"coordinates":[-115.260759,36.15969],"type":"Point"}
}