{
  "type": "Feature",
  "properties": {
    "iso:country":"US",
    "sg:address":"4444 Wellsboro St",
    "sg:city":"Las Vegas",
    "sg:classifiers":[
        {
            "category":"Professional",
            "subcategory":"Business Services",
            "type":"Services"
        }
    ],
    "sg:phone":"+1 702 248 3983",
    "sg:postcode":"89147",
    "sg:province":"NV",
    "sg:tags":[
        "interior",
        "consultant",
        "design",
        "decorator"
    ],
    "wof:name":"Jessy's Elegant Home Decor",
    "wof:placetype":"venue"
},
  "geometry": {"coordinates":[-115.26483,36.107938],"type":"Point"}
}