{
  "type": "Feature",
  "properties": {
    "iso:country":"US",
    "sg:address":"2310 E Serene Ave",
    "sg:city":"Las Vegas",
    "sg:classifiers":[
        {
            "category":"Banks & Credit Unions",
            "subcategory":"Bank",
            "type":"Services"
        }
    ],
    "sg:phone":"+1 702 897 1156",
    "sg:postcode":"89123",
    "sg:province":"NV",
    "wof:name":"1st National Bank of Nevada",
    "wof:placetype":"venue"
},
  "geometry": {"coordinates":[-115.120003,36.020401],"type":"Point"}
}