{
  "type": "Feature",
  "properties": {
    "iso:country":"US",
    "sg:address":"106 Walker Way",
    "sg:city":"Boulder City",
    "sg:classifiers":[
        {
            "category":"Building & Trades",
            "subcategory":"Plumbing",
            "type":"Services"
        }
    ],
    "sg:phone":"+1 702 293 0300",
    "sg:postcode":"89005",
    "sg:province":"NV",
    "sg:tags":[
        "plumbing",
        "contractor"
    ],
    "wof:name":"Angelone's Plumbing",
    "wof:placetype":"venue"
},
  "geometry": {"coordinates":[-114.845184,35.984527],"type":"Point"}
}