{
  "type": "Feature",
  "properties": {
    "iso:country":"US",
    "sg:address":"1613 Viewmont Ct",
    "sg:city":"Gardnerville",
    "sg:classifiers":[
        {
            "category":"Arts & Performance",
            "subcategory":"Theater",
            "type":"Entertainment"
        }
    ],
    "sg:phone":"+1 775 782 1016",
    "sg:postcode":"89410",
    "sg:province":"NV",
    "sg:tags":[
        "bureau"
    ],
    "wof:name":"Exotic Entertainment",
    "wof:placetype":"venue"
},
  "geometry": {"coordinates":[-119.715182,38.948786],"type":"Point"}
}