{
  "type": "Feature",
  "properties": {
    "iso:country":"US",
    "sg:address":"1800 Idaho St",
    "sg:city":"Elko",
    "sg:classifiers":[
        {
            "category":"Communications",
            "subcategory":"Radio Station",
            "type":"Services"
        }
    ],
    "sg:phone":"+1 775 738 1240",
    "sg:postcode":"89801",
    "sg:province":"NV",
    "sg:tags":[
        "company",
        "broadcasting"
    ],
    "sg:website":"www.elkoradio.com",
    "wof:name":"Elko Broadcasting",
    "wof:placetype":"venue"
},
  "geometry": {"coordinates":[-115.749509,40.845485],"type":"Point"}
}