{
  "type": "Feature",
  "properties": {
    "iso:country":"US",
    "sg:address":"3933 W Ali Baba Ln",
    "sg:city":"Las Vegas",
    "sg:classifiers":[
        {
            "category":"Freight",
            "type":"Transportation"
        }
    ],
    "sg:phone":"+1 702 649 8930",
    "sg:postcode":"89118",
    "sg:province":"NV",
    "sg:tags":[
        "operator",
        "mover",
        "trucking"
    ],
    "wof:name":"Aoki Noda Moving and Storage",
    "wof:placetype":"venue"
},
  "geometry": {"coordinates":[-115.191892,36.09535],"type":"Point"}
}