{
  "type": "Feature",
  "properties": {
    "iso:country":"US",
    "sg:address":"590 E Appion Way",
    "sg:city":"Carson City",
    "sg:classifiers":[
        {
            "category":"Wholesale",
            "subcategory":"Machinery & Supplies",
            "type":"Manufacturing & Wholesale Goods"
        }
    ],
    "sg:phone":"+1 775 882 9052",
    "sg:postcode":"89701",
    "sg:province":"NV",
    "sg:tags":[
        "pump"
    ],
    "wof:name":"W M Blain Well Drilling & Pump",
    "wof:placetype":"venue"
},
  "geometry": {"coordinates":[-119.761177,39.124783],"type":"Point"}
}