{
  "type": "Feature",
  "properties": {
    "iso:country":"US",
    "sg:address":"2550 Chandler Ave",
    "sg:city":"Las Vegas",
    "sg:classifiers":[
        {
            "category":"Professional",
            "subcategory":"Employment Agencies",
            "type":"Services"
        }
    ],
    "sg:phone":"+1 702 736 5830",
    "sg:postcode":"89120",
    "sg:province":"NV",
    "sg:tags":[
        "opportunity"
    ],
    "wof:name":"N V Placement Svc",
    "wof:placetype":"venue"
},
  "geometry": {"coordinates":[-115.114721,36.074127],"type":"Point"}
}