{
  "type": "Feature",
  "properties": {
    "iso:country":"US",
    "sg:address":"615 S 7th St",
    "sg:city":"Las Vegas",
    "sg:classifiers":[
        {
            "category":"Professional",
            "subcategory":"Accounting & Tax Preparation",
            "type":"Services"
        }
    ],
    "sg:phone":"+1 702 474 6250",
    "sg:postcode":"89101",
    "sg:province":"NV",
    "wof:name":"Constance M Lentz CPA Ltd",
    "wof:placetype":"venue"
},
  "geometry": {"coordinates":[-115.142808,36.161415],"type":"Point"}
}