{
  "type": "Feature",
  "properties": {
    "iso:country":"US",
    "sg:address":"1625 E Prater Way",
    "sg:city":"Sparks",
    "sg:classifiers":[
        {
            "category":"Insurance",
            "subcategory":"Health Insurance",
            "type":"Services"
        }
    ],
    "sg:phone":"+1 775 352 6900",
    "sg:postcode":"89434",
    "sg:province":"NV",
    "sg:tags":[
        "plan"
    ],
    "wof:name":"CDS Group Health",
    "wof:placetype":"venue"
},
  "geometry": {"coordinates":[-119.7114,39.541868],"type":"Point"}
}