{
  "type": "Feature",
  "properties": {
    "iso:country":"US",
    "sg:address":"5189 Meadowood Mall Cir",
    "sg:city":"Reno",
    "sg:classifiers":[
        {
            "category":"Shopping",
            "subcategory":"Optical Goods",
            "type":"Retail Goods"
        }
    ],
    "sg:phone":"+1 775 826 8778",
    "sg:postcode":"89502",
    "sg:province":"NV",
    "sg:tags":[
        "sun",
        "goggles",
        "sunglasses"
    ],
    "wof:name":"Sunglass Hut",
    "wof:placetype":"venue"
},
  "geometry": {"coordinates":[-119.78016,39.475186],"type":"Point"}
}