{
  "type": "Feature",
  "properties": {
    "iso:country":"US",
    "sg:address":"3720 W Oquendo Rd",
    "sg:city":"Las Vegas",
    "sg:classifiers":[
        {
            "category":"Manufacturing",
            "subcategory":"Electronics",
            "type":"Manufacturing & Wholesale Goods"
        }
    ],
    "sg:phone":"+1 702 630 1463",
    "sg:postcode":"89118",
    "sg:province":"NV",
    "sg:tags":[
        "aviation",
        "maintenance",
        "mfg"
    ],
    "wof:name":"Advanced Electronic Systems",
    "wof:placetype":"venue"
},
  "geometry": {"coordinates":[-115.188585,36.082723],"type":"Point"}
}