{
  "type": "Feature",
  "properties": {
    "iso:country":"US",
    "sg:address":"579 N Stephanie St",
    "sg:city":"Henderson",
    "sg:classifiers":[
        {
            "category":"Shopping",
            "subcategory":"Bicycles & Sporting Goods",
            "type":"Retail Goods"
        }
    ],
    "sg:phone":"+1 702 436 3089",
    "sg:postcode":"89014",
    "sg:province":"NV",
    "sg:tags":[
        "equipment",
        "golf",
        "supply"
    ],
    "sg:website":"www.copelandsports.com",
    "wof:name":"Copeland Sports",
    "wof:placetype":"venue"
},
  "geometry": {"coordinates":[-115.046292,36.056952],"type":"Point"}
}