{
  "type": "Feature",
  "properties": {
    "iso:country":"US",
    "sg:address":"689 Sierra Rose Dr",
    "sg:city":"Reno",
    "sg:classifiers":[
        {
            "category":"Banks & Credit Unions",
            "subcategory":"Investment Brokerage",
            "type":"Services"
        }
    ],
    "sg:phone":"+1 775 787 7888",
    "sg:postcode":"89511",
    "sg:province":"NV",
    "sg:tags":[
        "security"
    ],
    "wof:name":"Edward Jones Co",
    "wof:placetype":"venue"
},
  "geometry": {"coordinates":[-119.793773,39.473521],"type":"Point"}
}