{
  "type": "Feature",
  "properties": {
    "iso:country":"US",
    "sg:address":"265 E Warm Springs Rd",
    "sg:city":"Las Vegas",
    "sg:classifiers":[
        {
            "category":"Professional",
            "subcategory":"Accounting & Tax Preparation",
            "type":"Services"
        }
    ],
    "sg:phone":"+1 702 471 7223",
    "sg:postcode":"89119",
    "sg:province":"NV",
    "sg:tags":[
        "accountant"
    ],
    "sg:website":"www.llbcpa.com",
    "wof:name":"Larry L Bertsch, CPA & Associates",
    "wof:placetype":"venue"
},
  "geometry": {"coordinates":[-115.161381,36.056926],"type":"Point"}
}