{
  "type": "Feature",
  "properties": {
    "iso:country":"US",
    "sg:address":"1019 S Arlington Ave",
    "sg:city":"Reno",
    "sg:classifiers":[
        {
            "category":"Retail",
            "subcategory":"Laundry & Dry Cleaning",
            "type":"Services"
        }
    ],
    "sg:phone":"+1 775 284 6350",
    "sg:postcode":"89509",
    "sg:province":"NV",
    "wof:name":"Pressed 4 Time",
    "wof:placetype":"venue"
},
  "geometry": {"coordinates":[-119.81722000000001,39.513991],"type":"Point"}
}