{
  "type": "Feature",
  "properties": {
    "iso:country":"US",
    "sg:address":"493 Hot Springs Rd",
    "sg:city":"Carson City",
    "sg:classifiers":[
        {
            "category":"Real Estate",
            "subcategory":"Real Estate Operator",
            "type":"Services"
        }
    ],
    "sg:phone":"+1 775 882 7727",
    "sg:postcode":"89706",
    "sg:province":"NV",
    "sg:tags":[
        "mobile",
        "home",
        "site",
        "community"
    ],
    "wof:name":"Lone Mountain Mobile HM Cmnty",
    "wof:placetype":"venue"
},
  "geometry": {"coordinates":[-119.765328,39.182606],"type":"Point"}
}