{
  "type": "Feature",
  "properties": {
    "iso:country":"US",
    "sg:address":"8716 Canyon Ranch St",
    "sg:city":"Las Vegas",
    "sg:classifiers":[
        {
            "category":"Building & Trades",
            "subcategory":"Cleaning & Sanitation",
            "type":"Services"
        }
    ],
    "sg:phone":"+1 702 997 5945",
    "sg:postcode":"89131",
    "sg:province":"NV",
    "sg:tags":[
        "carpet"
    ],
    "sg:website":"www.allcleanlv.com",
    "wof:name":"All Clean Total Care",
    "wof:placetype":"venue"
},
  "geometry": {"coordinates":[-115.222362,36.319005],"type":"Point"}
}