{
  "type": "Feature",
  "properties": {
    "iso:country":"US",
    "sg:address":"755 Kuenzli St",
    "sg:city":"Reno",
    "sg:classifiers":[
        {
            "category":"Professional",
            "subcategory":"Business Services",
            "type":"Services"
        }
    ],
    "sg:phone":"+1 775 787 6112",
    "sg:postcode":"89502",
    "sg:province":"NV",
    "wof:name":"Humberto C Bravo",
    "wof:placetype":"venue"
},
  "geometry": {"coordinates":[-119.801624,39.52843],"type":"Point"}
}