{
  "type": "Feature",
  "properties": {
    "iso:country":"US",
    "sg:address":"6135 W Sahara Ave",
    "sg:city":"Las Vegas",
    "sg:classifiers":[
        {
            "category":"Professional",
            "subcategory":"Computer Services",
            "type":"Services"
        }
    ],
    "sg:phone":"+1 702 940 3200",
    "sg:postcode":"89146",
    "sg:province":"NV",
    "sg:tags":[
        "internet"
    ],
    "wof:name":"Net Tek",
    "wof:placetype":"venue"
},
  "geometry": {"coordinates":[-115.226715,36.144127],"type":"Point"}
}