{
  "type": "Feature",
  "properties": {
    "iso:country":"US",
    "sg:address":"5313 W Cheyenne Ave",
    "sg:city":"Las Vegas",
    "sg:classifiers":[
        {
            "category":"Professional",
            "subcategory":"Management & Consulting",
            "type":"Services"
        }
    ],
    "sg:phone":"+1 702 396 6040",
    "sg:postcode":"89108",
    "sg:province":"NV",
    "sg:tags":[
        "construction"
    ],
    "wof:name":"P B Construction Svc",
    "wof:placetype":"venue"
},
  "geometry": {"coordinates":[-115.216683,36.216909],"type":"Point"}
}