{
  "type": "Feature",
  "properties": {
    "iso:country":"US",
    "sg:address":"1740 Mountain City Hwy",
    "sg:city":"Elko",
    "sg:classifiers":[
        {
            "category":"Food & Beverages",
            "subcategory":"Groceries & Convenience Stores",
            "type":"Retail Goods"
        }
    ],
    "sg:phone":"+1 775 777 1333",
    "sg:postcode":"89801",
    "sg:province":"NV",
    "sg:tags":[
        "supermarket",
        "drug",
        "center"
    ],
    "wof:name":"Smiths",
    "wof:placetype":"venue"
},
  "geometry": {"coordinates":[-115.785623,40.832736],"type":"Point"}
}