{
  "type": "Feature",
  "properties": {
    "iso:country":"US",
    "sg:address":"40 N Valle Verde Dr",
    "sg:city":"Henderson",
    "sg:classifiers":[
        {
            "category":"Health Services",
            "subcategory":"Dentist",
            "type":"Services"
        }
    ],
    "sg:phone":"+1 702 648 0011",
    "sg:postcode":"89074",
    "sg:province":"NV",
    "wof:name":"Smilecity Henderson",
    "wof:placetype":"venue"
},
  "geometry": {"coordinates":[-115.062942,36.029739],"type":"Point"}
}