{
  "type": "Feature",
  "properties": {
    "iso:country":"US",
    "sg:address":"3915 W Hacienda Ave",
    "sg:city":"Las Vegas",
    "sg:classifiers":[
        {
            "category":"Freight",
            "type":"Transportation"
        }
    ],
    "sg:phone":"+1 702 262 6544",
    "sg:postcode":"89118",
    "sg:province":"NV",
    "sg:tags":[
        "hauler",
        "contract",
        "trucking"
    ],
    "wof:name":"Specialty Logistics",
    "wof:placetype":"venue"
},
  "geometry": {"coordinates":[-115.192689,36.093534],"type":"Point"}
}