{
  "type": "Feature",
  "properties": {
    "iso:country":"US",
    "sg:address":"2960 Westwood Dr",
    "sg:city":"Las Vegas",
    "sg:classifiers":[
        {
            "category":"Manufacturing",
            "subcategory":"Metals",
            "type":"Manufacturing & Wholesale Goods"
        }
    ],
    "sg:phone":"+1 702 650 9808",
    "sg:postcode":"89109",
    "sg:province":"NV",
    "sg:tags":[
        "coating",
        "powder"
    ],
    "wof:name":"Coatings Unlimited",
    "wof:placetype":"venue"
},
  "geometry": {"coordinates":[-115.17821600000001,36.132813],"type":"Point"}
}