{
  "type": "Feature",
  "properties": {
    "iso:country":"US",
    "sg:address":"7620 Las Vegas Blvd S",
    "sg:city":"Las Vegas",
    "sg:classifiers":[
        {
            "category":"Restaurant",
            "type":"Food & Drink"
        }
    ],
    "sg:menulink":"http://www.allmenus.com/nv/las-vegas/133893-subway/menu/",
    "sg:phone":"+1 702 263 4074",
    "sg:postcode":"89123",
    "sg:province":"NV",
    "sg:tags":[
        "american",
        "sandwich"
    ],
    "wof:name":"Subway",
    "wof:placetype":"venue"
},
  "geometry": {"coordinates":[-115.17220399999999,36.051183],"type":"Point"}
}