{
  "type": "Feature",
  "properties": {
    "iso:country":"US",
    "sg:address":"1532 H St",
    "sg:city":"Las Vegas",
    "sg:classifiers":[
        {
            "category":"Retail",
            "subcategory":"Laundry & Dry Cleaning",
            "type":"Services"
        }
    ],
    "sg:phone":"+1 702 648 2756",
    "sg:postcode":"89106",
    "sg:province":"NV",
    "wof:name":"Cantrell's Cleaners",
    "wof:placetype":"venue"
},
  "geometry": {"coordinates":[-115.152,36.188],"type":"Point"}
}