{
  "type": "Feature",
  "properties": {
    "iso:country":"US",
    "sg:address":"6194 W Flamingo Rd",
    "sg:city":"Las Vegas",
    "sg:classifiers":[
        {
            "category":"Retail",
            "subcategory":"Laundry & Dry Cleaning",
            "type":"Services"
        }
    ],
    "sg:phone":"+1 702 367 8383",
    "sg:postcode":"89103",
    "sg:province":"NV",
    "sg:tags":[
        "cleaner"
    ],
    "wof:name":"Al Phillips the Cleaner Inc",
    "wof:placetype":"venue"
},
  "geometry": {"coordinates":[-115.226997,36.1147],"type":"Point"}
}