{
  "type": "Feature",
  "properties": {
    "iso:country":"US",
    "sg:address":"9081 Baysinger Dr",
    "sg:city":"Las Vegas",
    "sg:classifiers":[
        {
            "category":"Building & Trades",
            "subcategory":"Construction",
            "type":"Services"
        }
    ],
    "sg:phone":"+1 702 242 1998",
    "sg:postcode":"89129",
    "sg:province":"NV",
    "sg:tags":[
        "house"
    ],
    "wof:name":"Southern California Constructi",
    "wof:placetype":"venue"
},
  "geometry": {"coordinates":[-115.294219,36.226521],"type":"Point"}
}