{
  "type": "Feature",
  "properties": {
    "iso:country":"US",
    "sg:address":"6433 Mecham Ave",
    "sg:city":"Las Vegas",
    "sg:classifiers":[
        {
            "category":"Professional",
            "subcategory":"Detective & Security Services",
            "type":"Services"
        }
    ],
    "sg:phone":"+1 702 258 1638",
    "sg:postcode":"89107",
    "sg:province":"NV",
    "sg:tags":[
        "guard",
        "patrol"
    ],
    "wof:name":"Tooth Imprint Id",
    "wof:placetype":"venue"
},
  "geometry": {"coordinates":[-115.236802,36.174383],"type":"Point"}
}