{
  "type": "Feature",
  "properties": {
    "iso:country":"US",
    "sg:address":"1420 Foster Dr",
    "sg:city":"Reno",
    "sg:classifiers":[
        {
            "category":"Building & Trades",
            "subcategory":"Construction",
            "type":"Services"
        }
    ],
    "sg:phone":"+1 775 322 5880",
    "sg:postcode":"89509",
    "sg:province":"NV",
    "wof:name":"Sanjo Construction Ltd",
    "wof:placetype":"venue"
},
  "geometry": {"coordinates":[-119.83949699999999,39.515756],"type":"Point"}
}