{
  "type": "Feature",
  "properties": {
    "iso:country":"US",
    "sg:address":"7816 Purple Mountain Ave",
    "sg:city":"Las Vegas",
    "sg:classifiers":[
        {
            "category":"Professional",
            "subcategory":"Computer Services",
            "type":"Services"
        }
    ],
    "sg:phone":"+1 702 327 3300",
    "sg:postcode":"89131",
    "sg:province":"NV",
    "sg:tags":[
        "related"
    ],
    "wof:name":"Tech & Beyond",
    "wof:placetype":"venue"
},
  "geometry": {"coordinates":[-115.266732,36.290567],"type":"Point"}
}