{
  "type": "Feature",
  "properties": {
    "iso:country":"US",
    "sg:address":"595 College D Ste D",
    "sg:city":"Henderson",
    "sg:classifiers":[
        {
            "category":"Personal",
            "subcategory":"Tanning Parlor",
            "type":"Services"
        }
    ],
    "sg:phone":"+1 702 566 6962",
    "sg:postcode":"89012",
    "sg:province":"NV",
    "sg:website":"www.tanfactoryonline.com",
    "wof:name":"Tan Factory",
    "wof:placetype":"venue"
},
  "geometry": {"coordinates":[-114.963499,36.013015],"type":"Point"}
}