{
  "type": "Feature",
  "properties": {
    "iso:country":"US",
    "sg:address":"2022 Waverly Cir",
    "sg:city":"Henderson",
    "sg:classifiers":[
        {
            "category":"Communications",
            "subcategory":"Film & Video Production",
            "type":"Services"
        }
    ],
    "sg:phone":"+1 702 435 5199",
    "sg:postcode":"89014",
    "sg:province":"NV",
    "sg:tags":[
        "taping"
    ],
    "sg:website":"www.dpvideo.com",
    "wof:name":"D P Video Productions",
    "wof:placetype":"venue"
},
  "geometry": {"coordinates":[-115.077983,36.052321],"type":"Point"}
}