{
  "type": "Feature",
  "properties": {
    "iso:country":"US",
    "sg:address":"615 Nugget Ave",
    "sg:city":"Sparks",
    "sg:classifiers":[
        {
            "category":"Freight",
            "type":"Transportation"
        }
    ],
    "sg:phone":"+1 775 355 8020",
    "sg:postcode":"89431",
    "sg:province":"NV",
    "sg:tags":[
        "trucking"
    ],
    "wof:name":"Interwest Delivery Svc",
    "wof:placetype":"venue"
},
  "geometry": {"coordinates":[-119.750832,39.533812],"type":"Point"}
}