{
  "type": "Feature",
  "properties": {
    "iso:country":"US",
    "sg:address":"3993 Howard Hughes Pkwy",
    "sg:city":"Las Vegas",
    "sg:classifiers":[
        {
            "category":"Professional",
            "subcategory":"Lawyer & Legal Services",
            "type":"Services"
        }
    ],
    "sg:phone":"+1 702 949 8200",
    "sg:postcode":"89169",
    "sg:province":"NV",
    "sg:tags":[
        "attorney"
    ],
    "sg:website":"www.lrlaw.com",
    "wof:name":"Lewis & Roca",
    "wof:placetype":"venue"
},
  "geometry": {"coordinates":[-115.157402,36.117459],"type":"Point"}
}