{
  "type": "Feature",
  "properties": {
    "iso:country":"US",
    "sg:address":"6651 Azure Dr",
    "sg:city":"Las Vegas",
    "sg:classifiers":[
        {
            "category":"Government",
            "subcategory":"Office",
            "type":"Public Place"
        }
    ],
    "sg:phone":"+1 702 395 7584",
    "sg:postcode":"89130",
    "sg:province":"NV",
    "sg:tags":[
        "state",
        "program",
        "health"
    ],
    "wof:name":"Clark County Health Dist Air",
    "wof:placetype":"venue"
},
  "geometry": {"coordinates":[-115.239807,36.272654],"type":"Point"}
}