{
  "type": "Feature",
  "properties": {
    "iso:country":"US",
    "sg:address":"105 E Harmon Ave",
    "sg:city":"Las Vegas",
    "sg:classifiers":[
        {
            "category":"Restaurant",
            "type":"Food & Drink"
        }
    ],
    "sg:phone":"+1 702 369 5639",
    "sg:postcode":"89109",
    "sg:province":"NV",
    "wof:name":"Joey Bistro & Bar",
    "wof:placetype":"venue"
},
  "geometry": {"coordinates":[-115.172387,36.10795],"type":"Point"}
}