{
  "type": "Feature",
  "properties": {
    "iso:country":"US",
    "sg:address":"592 California Ave Ste E",
    "sg:city":"Reno",
    "sg:classifiers":[
        {
            "category":"Building & Trades",
            "subcategory":"Construction",
            "type":"Services"
        },
        {
            "category":"Building & Trades",
            "subcategory":"Electrical",
            "type":"Services"
        }
    ],
    "sg:phone":"+1 775 324 4143",
    "sg:postcode":"89509",
    "sg:province":"NV",
    "sg:tags":[
        "repair",
        "industrial",
        "electrician",
        "electric",
        "contractors-commercial",
        "maintenance",
        "home"
    ],
    "wof:name":"Olectric Electrical Services",
    "wof:placetype":"venue"
},
  "geometry": {"coordinates":[-119.819887,39.520032],"type":"Point"}
}