{
  "type": "Feature",
  "properties": {
    "iso:country":"US",
    "sg:address":"6117 Burnt Hills Dr",
    "sg:city":"Las Vegas",
    "sg:classifiers":[
        {
            "category":"Health Services",
            "subcategory":"Optometrist",
            "type":"Services"
        }
    ],
    "sg:phone":"+1 702 242 4282",
    "sg:postcode":"89130",
    "sg:province":"NV",
    "wof:name":"Dr Stephen Myers Optometry",
    "wof:placetype":"venue"
},
  "geometry": {"coordinates":[-115.227636,36.243142],"type":"Point"}
}