{
  "type": "Feature",
  "properties": {
    "iso:country":"US",
    "sg:address":"24 State Rte 28",
    "sg:city":"Crystal Bay",
    "sg:classifiers":[
        {
            "category":"Travel",
            "subcategory":"Hotels & Motels",
            "type":"Entertainment"
        }
    ],
    "sg:phone":"+1 775 831 0287",
    "sg:postcode":"89402",
    "sg:province":"NV",
    "wof:name":"Crystal Bay Motel",
    "wof:placetype":"venue"
},
  "geometry": {"coordinates":[-120.005481,39.227472],"type":"Point"}
}