{
  "type": "Feature",
  "properties": {
    "iso:country":"US",
    "sg:address":"6130 W Flamingo Rd",
    "sg:city":"Las Vegas",
    "sg:classifiers":[
        {
            "category":"Wholesale",
            "subcategory":"Furniture",
            "type":"Manufacturing & Wholesale Goods"
        }
    ],
    "sg:phone":"+1 702 367 1508",
    "sg:postcode":"89103",
    "sg:province":"NV",
    "wof:name":"Mobay Distributors",
    "wof:placetype":"venue"
},
  "geometry": {"coordinates":[-115.228835,36.114588],"type":"Point"}
}