{
  "type": "Feature",
  "properties": {
    "iso:country":"US",
    "sg:address":"5755 Spring Mountain Rd",
    "sg:city":"Las Vegas",
    "sg:classifiers":[
        {
            "category":"Deli",
            "type":"Food & Drink"
        },
        {
            "category":"Restaurant",
            "type":"Food & Drink"
        }
    ],
    "sg:phone":"+1 702 871 5577",
    "sg:postcode":"89146",
    "sg:province":"NV",
    "sg:tags":[
        "italian"
    ],
    "sg:website":"www.romalv.com",
    "wof:name":"Roma Deli & Restaurant",
    "wof:placetype":"venue"
},
  "geometry": {"coordinates":[-115.219897,36.125166],"type":"Point"}
}