{
  "type": "Feature",
  "properties": {
    "iso:country":"US",
    "sg:address":"5060 N Tioga Way",
    "sg:city":"Las Vegas",
    "sg:classifiers":[
        {
            "category":"Recreation",
            "type":"Entertainment"
        }
    ],
    "sg:phone":"+1 702 647 1359",
    "sg:postcode":"89149",
    "sg:province":"NV",
    "sg:tags":[
        "club",
        "membership"
    ],
    "wof:name":"Nra Member Council Las Vegas",
    "wof:placetype":"venue"
},
  "geometry": {"coordinates":[-115.258056,36.252358],"type":"Point"}
}