{
  "type": "Feature",
  "properties": {
    "iso:country":"US",
    "sg:address":"1810 Lake Ave",
    "sg:city":"Silver Springs",
    "sg:classifiers":[
        {
            "category":"Professional",
            "type":"Services"
        }
    ],
    "sg:phone":"+1 775 577 3444",
    "sg:postcode":"89429",
    "sg:province":"NV",
    "sg:tags":[
        "establishment"
    ],
    "wof:name":"Unlimited Mud System",
    "wof:placetype":"venue"
},
  "geometry": {"coordinates":[-119.213277,39.404429],"type":"Point"}
}