{
  "type": "Feature",
  "properties": {
    "iso:country":"US",
    "sg:address":"2358 Pickwick Dr",
    "sg:city":"Henderson",
    "sg:classifiers":[
        {
            "category":"Professional",
            "subcategory":"Computer Services",
            "type":"Services"
        }
    ],
    "sg:phone":"+1 702 433 8021",
    "sg:postcode":"89014",
    "sg:province":"NV",
    "sg:tags":[
        "datum"
    ],
    "wof:name":"R C Web",
    "wof:placetype":"venue"
},
  "geometry": {"coordinates":[-115.082695,36.064585],"type":"Point"}
}