{
  "type": "Feature",
  "properties": {
    "iso:country":"US",
    "sg:address":"11416 S Eastern Ave",
    "sg:city":"Henderson",
    "sg:classifiers":[
        {
            "category":"Professional",
            "subcategory":"Business Services",
            "type":"Services"
        }
    ],
    "sg:phone":"+1 702 614 9338",
    "sg:postcode":"89052",
    "sg:province":"NV",
    "wof:name":"Interiors By Royce",
    "wof:placetype":"venue"
},
  "geometry": {"coordinates":[-115.100757,35.980598],"type":"Point"}
}