{
  "type": "Feature",
  "properties": {
    "iso:country":"US",
    "sg:address":"2075 Palm St Ste I",
    "sg:city":"Las Vegas",
    "sg:classifiers":[
        {
            "category":"Retail",
            "subcategory":"Auto Repair",
            "type":"Services"
        }
    ],
    "sg:phone":"+1 702 431 4909",
    "sg:postcode":"89104",
    "sg:province":"NV",
    "wof:name":"Ace Service",
    "wof:placetype":"venue"
},
  "geometry": {"coordinates":[-115.100998,36.148102],"type":"Point"}
}