{
  "type": "Feature",
  "properties": {
    "iso:country":"US",
    "sg:address":"200 N McCarran Blvd",
    "sg:city":"Sparks",
    "sg:classifiers":[
        {
            "category":"Recreation",
            "subcategory":"Arcade",
            "type":"Entertainment"
        }
    ],
    "sg:phone":"+1 775 359 0550",
    "sg:postcode":"89431",
    "sg:province":"NV",
    "sg:tags":[
        "casino"
    ],
    "wof:name":"Sierra Sid's Casino",
    "wof:placetype":"venue"
},
  "geometry": {"coordinates":[-119.737236,39.535188],"type":"Point"}
}