{
  "type": "Feature",
  "properties": {
    "iso:country":"US",
    "sg:address":"644 S Wells Ave",
    "sg:city":"Reno",
    "sg:classifiers":[
        {
            "category":"Real Estate",
            "subcategory":"Real Estate Agent",
            "type":"Services"
        }
    ],
    "sg:phone":"+1 775 323 0404",
    "sg:postcode":"89502",
    "sg:province":"NV",
    "sg:tags":[
        "property",
        "management",
        "rental",
        "broker"
    ],
    "wof:name":"Action Properties Inc.",
    "wof:placetype":"venue"
},
  "geometry": {"coordinates":[-119.803185,39.519811],"type":"Point"}
}