{
  "type": "Feature",
  "properties": {
    "iso:country":"US",
    "sg:address":"2575 Montessouri Street",
    "sg:city":"Las Vegas",
    "sg:classifiers":[
        {
            "category":"Building & Trades",
            "subcategory":"Construction",
            "type":"Services"
        }
    ],
    "sg:phone":"+1 702 363 8060",
    "sg:postcode":"89117",
    "sg:province":"NV",
    "sg:tags":[
        "contractor"
    ],
    "sg:website":"www.sunwestcustomhomes.com",
    "wof:name":"Sun West Custom Homes",
    "wof:placetype":"venue"
},
  "geometry": {"coordinates":[-115.247406,36.142561],"type":"Point"}
}