{
  "type": "Feature",
  "properties": {
    "iso:country":"US",
    "sg:address":"8245 Rodeo Dr",
    "sg:city":"Las Vegas",
    "sg:classifiers":[
        {
            "category":"Building & Trades",
            "subcategory":"Construction",
            "type":"Services"
        }
    ],
    "sg:phone":"+1 702 837 9682",
    "sg:postcode":"89123",
    "sg:province":"NV",
    "sg:tags":[
        "general",
        "contractor"
    ],
    "wof:name":"Flexon",
    "wof:placetype":"venue"
},
  "geometry": {"coordinates":[-115.122061,36.03932],"type":"Point"}
}