{
  "type": "Feature",
  "properties": {
    "iso:country":"US",
    "sg:address":"2545 S Bruce Street Suite 8",
    "sg:city":"Las Vegas",
    "sg:classifiers":[
        {
            "category":"Health Services",
            "subcategory":"Doctor",
            "type":"Services"
        }
    ],
    "sg:phone":"+1 702 733 0744",
    "sg:postcode":"89169",
    "sg:province":"NV",
    "wof:name":"Aci Pediatrics East",
    "wof:placetype":"venue"
},
  "geometry": {"coordinates":[-115.125434,36.143462],"type":"Point"}
}