{
  "type": "Feature",
  "properties": {
    "iso:country":"US",
    "sg:address":"711 S Carson St",
    "sg:city":"Carson City",
    "sg:classifiers":[
        {
            "category":"Shopping",
            "subcategory":"Stationery & Office Supplies",
            "type":"Retail Goods"
        }
    ],
    "sg:phone":"+1 877 263 6270",
    "sg:postcode":"89701",
    "sg:province":"NV",
    "sg:tags":[
        "reseller"
    ],
    "wof:name":"Promedia Marketing Inc",
    "wof:placetype":"venue"
},
  "geometry": {"coordinates":[-119.766931,39.159406],"type":"Point"}
}