{
  "type": "Feature",
  "properties": {
    "iso:country":"US",
    "sg:address":"3001 Westwind Rd",
    "sg:city":"Las Vegas",
    "sg:classifiers":[
        {
            "category":"Building & Trades",
            "subcategory":"Locksmith",
            "type":"Services"
        }
    ],
    "sg:phone":"+1 702 583 4287",
    "sg:postcode":"89146",
    "sg:province":"NV",
    "sg:tags":[
        "key"
    ],
    "wof:name":"Telcel Com",
    "wof:placetype":"venue"
},
  "geometry": {"coordinates":[-115.21879,36.135055],"type":"Point"}
}