{
  "type": "Feature",
  "properties": {
    "iso:country":"US",
    "sg:address":"5148 Future Dr",
    "sg:city":"Las Vegas",
    "sg:classifiers":[
        {
            "category":"Banks & Credit Unions",
            "subcategory":"Financial Services",
            "type":"Services"
        }
    ],
    "sg:phone":"+1 702 655 0843",
    "sg:postcode":"89130",
    "sg:province":"NV",
    "sg:tags":[
        "investor"
    ],
    "wof:name":"Stranahan Enterprises Inc",
    "wof:placetype":"venue"
},
  "geometry": {"coordinates":[-115.209439,36.252332],"type":"Point"}
}