{
  "type": "Feature",
  "properties": {
    "iso:country":"US",
    "sg:address":"705 S Grand Central Pkwy",
    "sg:city":"Las Vegas",
    "sg:classifiers":[
        {
            "category":"Shopping",
            "subcategory":"Books",
            "type":"Retail Goods"
        }
    ],
    "sg:phone":"+1 702 366 0649",
    "sg:postcode":"89106",
    "sg:province":"NV",
    "sg:tags":[
        "dealer"
    ],
    "wof:name":"Book Warehouse",
    "wof:placetype":"venue"
},
  "geometry": {"coordinates":[-115.155378,36.165635],"type":"Point"}
}