{
  "type": "Feature",
  "properties": {
    "iso:country":"US",
    "sg:address":"3240 Discovery Bay Ct",
    "sg:city":"Las Vegas",
    "sg:classifiers":[
        {
            "category":"Banks & Credit Unions",
            "subcategory":"Financial Services",
            "type":"Services"
        }
    ],
    "sg:phone":"+1 702 254 2291",
    "sg:postcode":"89117",
    "sg:province":"NV",
    "sg:tags":[
        "trust",
        "management"
    ],
    "wof:name":"Pat Bibby Corrado Trust",
    "wof:placetype":"venue"
},
  "geometry": {"coordinates":[-115.301284,36.132158],"type":"Point"}
}