{
  "type": "Feature",
  "properties": {
    "iso:country":"US",
    "sg:address":"1654 Parkchester Dr",
    "sg:city":"Las Vegas",
    "sg:classifiers":[
        {
            "category":"Retail",
            "subcategory":"Repair Shop",
            "type":"Services"
        }
    ],
    "sg:phone":"+1 702 631 5345",
    "sg:postcode":"89108",
    "sg:province":"NV",
    "sg:tags":[
        "electronic"
    ],
    "wof:name":"ETC",
    "wof:placetype":"venue"
},
  "geometry": {"coordinates":[-115.200136,36.188343],"type":"Point"}
}