{
  "type": "Feature",
  "properties": {
    "iso:country":"US",
    "sg:address":"3360 E Russell Rd",
    "sg:city":"Las Vegas",
    "sg:classifiers":[
        {
            "category":"Real Estate",
            "subcategory":"Real Estate Agent",
            "type":"Services"
        },
        {
            "category":"Insurance",
            "subcategory":"Insurance Agent",
            "type":"Services"
        }
    ],
    "sg:phone":"+1 702 338 1070",
    "sg:postcode":"89120",
    "sg:province":"NV",
    "wof:name":"Five Star Realty",
    "wof:placetype":"venue"
},
  "geometry": {"coordinates":[-115.101935,36.086439],"type":"Point"}
}