{
  "type": "Feature",
  "properties": {
    "iso:country":"US",
    "sg:address":"7240 Periwinkle Dr",
    "sg:city":"Las Vegas",
    "sg:classifiers":[
        {
            "category":"Building & Trades",
            "subcategory":"Cleaning & Sanitation",
            "type":"Services"
        }
    ],
    "sg:phone":"+1 702 369 6102",
    "sg:postcode":"89128",
    "sg:province":"NV",
    "sg:tags":[
        "house"
    ],
    "wof:name":"Rosalia's Cleaning Svc",
    "wof:placetype":"venue"
},
  "geometry": {"coordinates":[-115.249897,36.188284],"type":"Point"}
}