{
  "type": "Feature",
  "properties": {
    "iso:country":"US",
    "sg:address":"3680 S Maryland Pkwy",
    "sg:city":"Las Vegas",
    "sg:classifiers":[
        {
            "category":"Shopping",
            "type":"Retail Goods"
        },
        {
            "category":"Shopping",
            "subcategory":"Beauty & Cosmetics",
            "type":"Retail Goods"
        }
    ],
    "sg:phone":"+1 702 735 0290",
    "sg:postcode":"89169",
    "sg:province":"NV",
    "sg:tags":[
        "shop",
        "merchandise",
        "perfume"
    ],
    "sg:website":"www.bathandbodyworks.com",
    "wof:name":"Bath & Body Works Inc",
    "wof:placetype":"venue"
},
  "geometry": {"coordinates":[-115.137182,36.125302],"type":"Point"}
}