{
  "type": "Feature",
  "properties": {
    "iso:country":"US",
    "sg:address":"2202 W Charleston Blvd #10",
    "sg:city":"Las Vegas",
    "sg:classifiers":[
        {
            "category":"Health Services",
            "subcategory":"Dentist",
            "type":"Services"
        }
    ],
    "sg:phone":"+1 702 382 5678",
    "sg:postcode":"89102",
    "sg:province":"NV",
    "sg:website":"nevadadentalservices.com/",
    "wof:name":"Nevada Dental Services",
    "wof:placetype":"venue"
},
  "geometry": {"coordinates":[-115.17200099999999,36.159493],"type":"Point"}
}