{
  "type": "Feature",
  "properties": {
    "iso:country":"US",
    "sg:address":"2901 N Tenaya Way",
    "sg:city":"Las Vegas",
    "sg:classifiers":[
        {
            "category":"Health Services",
            "subcategory":"Chiropractor",
            "type":"Services"
        }
    ],
    "sg:phone":"+1 702 497 6506",
    "sg:postcode":"89128",
    "sg:province":"NV",
    "wof:name":"David Spendlove",
    "wof:placetype":"venue"
},
  "geometry": {"coordinates":[-115.24961,36.212648],"type":"Point"}
}