{
  "type": "Feature",
  "properties": {
    "iso:country":"US",
    "sg:address":"430 Jeanell Dr Ste C",
    "sg:city":"Carson City",
    "sg:classifiers":[
        {
            "category":"Social Services",
            "subcategory":"Child Care",
            "type":"Services"
        }
    ],
    "sg:phone":"+1 775 885 8588",
    "sg:postcode":"89703",
    "sg:province":"NV",
    "sg:tags":[
        "day"
    ],
    "wof:name":"Kidding Around",
    "wof:placetype":"venue"
},
  "geometry": {"coordinates":[-119.769718,39.180173],"type":"Point"}
}