{
  "type": "Feature",
  "properties": {
    "iso:country":"US",
    "sg:address":"1318 Patricia Dr",
    "sg:city":"Gardnerville",
    "sg:classifiers":[
        {
            "category":"Retail",
            "subcategory":"Repair Shop",
            "type":"Services"
        }
    ],
    "sg:phone":"+1 775 265 1587",
    "sg:postcode":"89460",
    "sg:province":"NV",
    "wof:name":"A Helping Hand",
    "wof:placetype":"venue"
},
  "geometry": {"coordinates":[-119.739733,38.887417],"type":"Point"}
}