{
  "type": "Feature",
  "properties": {
    "iso:country":"US",
    "sg:address":"4770 Blue Diamond Rd",
    "sg:city":"Las Vegas",
    "sg:classifiers":[
        {
            "category":"Shopping",
            "subcategory":"Tobacco",
            "type":"Retail Goods"
        }
    ],
    "sg:phone":"+1 702 269 6172",
    "sg:postcode":"89139",
    "sg:province":"NV",
    "sg:tags":[
        "shop"
    ],
    "wof:name":"Cigar Shop #3",
    "wof:placetype":"venue"
},
  "geometry": {"coordinates":[-115.20571700000001,36.033782],"type":"Point"}
}