{
  "type": "Feature",
  "properties": {
    "iso:country":"US",
    "sg:address":"8118 Warbonnet Way",
    "sg:city":"Las Vegas",
    "sg:classifiers":[
        {
            "category":"Building & Trades",
            "subcategory":"Construction",
            "type":"Services"
        }
    ],
    "sg:phone":"+1 702 270 9205",
    "sg:postcode":"89113",
    "sg:province":"NV",
    "sg:tags":[
        "contractor"
    ],
    "wof:name":"Richmond American Homes Sales Offices",
    "wof:placetype":"venue"
},
  "geometry": {"coordinates":[-115.265376,36.040612],"type":"Point"}
}