{
  "type": "Feature",
  "properties": {
    "iso:country":"US",
    "sg:address":"22 Sandwedge Dr",
    "sg:city":"Henderson",
    "sg:classifiers":[
        {
            "category":"Real Estate",
            "subcategory":"Real Estate Agent",
            "type":"Services"
        }
    ],
    "sg:phone":"+1 702 914 7765",
    "sg:postcode":"89074",
    "sg:province":"NV",
    "wof:name":"Durango Properties",
    "wof:placetype":"venue"
},
  "geometry": {"coordinates":[-115.06523,36.028566],"type":"Point"}
}