{
  "type": "Feature",
  "properties": {
    "iso:country":"US",
    "sg:address":"4225 Baker Ln",
    "sg:city":"Reno",
    "sg:classifiers":[
        {
            "category":"Building & Trades",
            "subcategory":"Construction",
            "type":"Services"
        }
    ],
    "sg:phone":"+1 775 746 3800",
    "sg:postcode":"89509",
    "sg:province":"NV",
    "sg:tags":[
        "water",
        "waste",
        "treatment",
        "infrastructure"
    ],
    "wof:name":"Western Water Development Co",
    "wof:placetype":"venue"
},
  "geometry": {"coordinates":[-119.798714,39.484786],"type":"Point"}
}