{
  "type": "Feature",
  "properties": {
    "iso:country":"US",
    "sg:address":"2281 Aultman St",
    "sg:city":"Ely",
    "sg:classifiers":[
        {
            "category":"Retail",
            "subcategory":"Auto Rental",
            "type":"Services"
        }
    ],
    "sg:phone":"+1 775 289 2277",
    "sg:postcode":"89301",
    "sg:province":"NV",
    "sg:tags":[
        "renting",
        "automobile"
    ],
    "wof:name":"Ely Rent A Car",
    "wof:placetype":"venue"
},
  "geometry": {"coordinates":[-114.876126,39.253021],"type":"Point"}
}