{
  "type": "Feature",
  "properties": {
    "iso:country":"US",
    "sg:address":"8316 Moapa Water St",
    "sg:city":"Las Vegas",
    "sg:classifiers":[
        {
            "category":"Shopping",
            "type":"Retail Goods"
        }
    ],
    "sg:phone":"+1 702 254 8112",
    "sg:postcode":"89131",
    "sg:province":"NV",
    "sg:tags":[
        "pet",
        "food",
        "supply"
    ],
    "wof:name":"Zpet Cafe",
    "wof:placetype":"venue"
},
  "geometry": {"coordinates":[-115.26978699999999,36.312713],"type":"Point"}
}