{
  "type": "Feature",
  "properties": {
    "iso:country":"US",
    "sg:address":"1941 State Hwy 160",
    "sg:city":"Pahrump",
    "sg:classifiers":[
        {
            "category":"Real Estate",
            "subcategory":"Real Estate Agent",
            "type":"Services"
        }
    ],
    "sg:phone":"+1 775 751 2253",
    "sg:postcode":"89048",
    "sg:province":"NV",
    "wof:name":"Available Properties Property",
    "wof:placetype":"venue"
},
  "geometry": {"coordinates":[-115.96539799999999,36.19129],"type":"Point"}
}