{
  "type": "Feature",
  "properties": {
    "iso:country":"US",
    "sg:address":"708 Overview Dr",
    "sg:city":"Las Vegas",
    "sg:classifiers":[
        {
            "category":"Building & Trades",
            "subcategory":"Cleaning & Sanitation",
            "type":"Services"
        }
    ],
    "sg:phone":"+1 702 657 8739",
    "sg:postcode":"89145",
    "sg:province":"NV",
    "sg:tags":[
        "janitor"
    ],
    "wof:name":"Super Cleaning Svc",
    "wof:placetype":"venue"
},
  "geometry": {"coordinates":[-115.278896,36.162578],"type":"Point"}
}