{
  "type": "Feature",
  "properties": {
    "iso:country":"US",
    "sg:address":"1700 E Desert Inn Rd Ste 307",
    "sg:city":"Las Vegas",
    "sg:classifiers":[
        {
            "category":"Community Center",
            "type":"Public Place"
        }
    ],
    "sg:phone":"+1 702 369 2880",
    "sg:postcode":"89169",
    "sg:province":"NV",
    "sg:tags":[
        "medical"
    ],
    "sg:website":"www.colonsos.com",
    "wof:name":"Colon Therapy of Las Vegas",
    "wof:placetype":"venue"
},
  "geometry": {"coordinates":[-115.129301,36.130195],"type":"Point"}
}