{
  "type": "Feature",
  "properties": {
    "iso:country":"US",
    "sg:address":"6340 E Crow Ct",
    "sg:city":"Sun Valley",
    "sg:classifiers":[
        {
            "category":"Personal",
            "subcategory":"Beauty Salon",
            "type":"Services"
        }
    ],
    "sg:phone":"+1 775 674 0517",
    "sg:postcode":"89433",
    "sg:province":"NV",
    "sg:tags":[
        "shop"
    ],
    "wof:name":"Bella Vita Salon",
    "wof:placetype":"venue"
},
  "geometry": {"coordinates":[-119.768296,39.607635],"type":"Point"}
}