{
  "type": "Feature",
  "properties": {
    "iso:country":"US",
    "sg:address":"440 E St",
    "sg:city":"Hawthorne",
    "sg:classifiers":[
        {
            "category":"Home & Garden",
            "subcategory":"Hardware",
            "type":"Retail Goods"
        }
    ],
    "sg:phone":"+1 775 945 2491",
    "sg:postcode":"89415",
    "sg:province":"NV",
    "wof:name":"Wagner's Ace Hardware",
    "wof:placetype":"venue"
},
  "geometry": {"coordinates":[-118.624687,38.523811],"type":"Point"}
}