{
  "type": "Feature",
  "properties": {
    "iso:country":"US",
    "sg:address":"3732 Justin Springs Cir",
    "sg:city":"Las Vegas",
    "sg:classifiers":[
        {
            "category":"Professional",
            "subcategory":"Lawyer & Legal Services",
            "type":"Services"
        }
    ],
    "sg:phone":"+1 702 736 5297",
    "sg:postcode":"89108",
    "sg:province":"NV",
    "sg:tags":[
        "attorney"
    ],
    "wof:name":"Maile L Esteban Law Office",
    "wof:placetype":"venue"
},
  "geometry": {"coordinates":[-115.22873,36.227878],"type":"Point"}
}