{
  "type": "Feature",
  "properties": {
    "iso:country":"US",
    "sg:address":"1505 Wigwam Pkwy. Suite 240",
    "sg:city":"Henderson",
    "sg:classifiers":[
        {
            "category":"Health Services",
            "subcategory":"Health Practitioner",
            "type":"Services"
        }
    ],
    "sg:phone":"+1 702 568 0195",
    "sg:postcode":"89074",
    "sg:province":"NV",
    "sg:tags":[
        "therapy",
        "physical"
    ],
    "sg:website":"www.mattsmithpt.com/home",
    "wof:name":"Matt Smith Physical Therapy",
    "wof:placetype":"venue"
},
  "geometry": {"coordinates":[-115.049831,36.033705],"type":"Point"}
}