{
  "type": "Feature",
  "properties": {
    "iso:country":"US",
    "sg:address":"2451 E Falcon St",
    "sg:city":"Pahrump",
    "sg:classifiers":[
        {
            "category":"Retail",
            "subcategory":"Laundry & Dry Cleaning",
            "type":"Services"
        }
    ],
    "sg:phone":"+1 775 727 5101",
    "sg:postcode":"89048",
    "sg:province":"NV",
    "sg:tags":[
        "cleaners",
        "rug",
        "carpet"
    ],
    "wof:name":"Spring Fresh Carpet & Uphlstry",
    "wof:placetype":"venue"
},
  "geometry": {"coordinates":[-115.969414,36.162865],"type":"Point"}
}