{
  "type": "Feature",
  "properties": {
    "iso:country":"US",
    "sg:address":"3375 S Decatur Blvd Ste 9",
    "sg:city":"Las Vegas",
    "sg:classifiers":[
        {
            "category":"Restaurant",
            "type":"Food & Drink"
        }
    ],
    "sg:phone":"+1 702 248 3020",
    "sg:postcode":"89103",
    "sg:province":"NV",
    "sg:tags":[
        "mexican"
    ],
    "wof:name":"La Choza de Don Huichito",
    "wof:placetype":"venue"
},
  "geometry": {"coordinates":[-115.221557,36.106994],"type":"Point"}
}