{
  "type": "Feature",
  "properties": {
    "iso:country":"US",
    "sg:address":"3325 Western Ave",
    "sg:city":"Las Vegas",
    "sg:classifiers":[
        {
            "category":"Wholesale",
            "subcategory":"Groceries",
            "type":"Manufacturing & Wholesale Goods"
        }
    ],
    "sg:phone":"+1 702 369 7447",
    "sg:postcode":"89109",
    "sg:province":"NV",
    "wof:name":"Italian Foods",
    "wof:placetype":"venue"
},
  "geometry": {"coordinates":[-115.178384,36.127868],"type":"Point"}
}