{
  "type": "Feature",
  "properties": {
    "iso:country":"US",
    "sg:address":"2900 Pinebough Ct",
    "sg:city":"Reno",
    "sg:classifiers":[
        {
            "category":"Professional",
            "type":"Services"
        }
    ],
    "sg:phone":"+1 775 825 5524",
    "sg:postcode":"89509",
    "sg:province":"NV",
    "wof:name":"Passey Bond Co Inc",
    "wof:placetype":"venue"
},
  "geometry": {"coordinates":[-119.834626,39.496731],"type":"Point"}
}