{
  "type": "Feature",
  "properties": {
    "iso:country":"US",
    "sg:address":"2926 E Nashua Pl",
    "sg:city":"Sparks",
    "sg:classifiers":[
        {
            "category":"Professional",
            "subcategory":"Business Services",
            "type":"Services"
        }
    ],
    "sg:phone":"+1 775 626 8190",
    "sg:postcode":"89436",
    "sg:province":"NV",
    "wof:name":"W & A Enterprises",
    "wof:placetype":"venue"
},
  "geometry": {"coordinates":[-119.68964,39.565741],"type":"Point"}
}