{
  "type": "Feature",
  "properties": {
    "iso:country":"US",
    "sg:address":"620 Arrayo Way",
    "sg:city":"Boulder City",
    "sg:classifiers":[
        {
            "category":"Freight",
            "type":"Transportation"
        }
    ],
    "sg:phone":"+1 702 293 2651",
    "sg:postcode":"89005",
    "sg:province":"NV",
    "sg:tags":[
        "general"
    ],
    "wof:name":"Foothill Storage",
    "wof:placetype":"venue"
},
  "geometry": {"coordinates":[-114.820397,35.976015],"type":"Point"}
}