{
  "type": "Feature",
  "properties": {
    "iso:country":"US",
    "sg:address":"2925 S Rainbow Blvd",
    "sg:city":"Las Vegas",
    "sg:classifiers":[
        {
            "category":"Banks & Credit Unions",
            "subcategory":"Bank",
            "type":"Services"
        }
    ],
    "sg:phone":"+1 702 952 7502",
    "sg:postcode":"89146",
    "sg:province":"NV",
    "wof:name":"First Security Bank of Nevada",
    "wof:placetype":"venue"
},
  "geometry": {"coordinates":[-115.24299600000001,36.1362],"type":"Point"}
}