{
  "type": "Feature",
  "properties": {
    "iso:country":"US",
    "sg:address":"9965 Prattville Ave",
    "sg:city":"Las Vegas",
    "sg:classifiers":[
        {
            "category":"Professional",
            "subcategory":"Accounting & Tax Preparation",
            "type":"Services"
        }
    ],
    "sg:phone":"+1 702 876 5504",
    "sg:postcode":"89148",
    "sg:province":"NV",
    "wof:name":"Bmt Enterprises",
    "wof:placetype":"venue"
},
  "geometry": {"coordinates":[-115.312371,36.081034],"type":"Point"}
}