{
  "type": "Feature",
  "properties": {
    "iso:country":"US",
    "sg:address":"560 E Williams Ave",
    "sg:city":"Fallon",
    "sg:classifiers":[
        {
            "category":"Shopping",
            "subcategory":"Pharmacy",
            "type":"Retail Goods"
        }
    ],
    "sg:phone":"+1 775 423 1130",
    "sg:postcode":"89406",
    "sg:province":"NV",
    "sg:tags":[
        "home",
        "medical",
        "drugstore",
        "equipment"
    ],
    "wof:name":"Fallon Family United Drug",
    "wof:placetype":"venue"
},
  "geometry": {"coordinates":[-118.769463,39.474775],"type":"Point"}
}