{
  "type": "Feature",
  "properties": {
    "iso:country":"US",
    "sg:address":"48 el Rio Ct",
    "sg:city":"Henderson",
    "sg:classifiers":[
        {
            "category":"Building & Trades",
            "subcategory":"Construction",
            "type":"Services"
        }
    ],
    "sg:phone":"+1 702 567 2659",
    "sg:postcode":"89012",
    "sg:province":"NV",
    "sg:tags":[
        "contractor"
    ],
    "wof:name":"Chantal A Beaumier",
    "wof:placetype":"venue"
},
  "geometry": {"coordinates":[-115.024576,36.0307],"type":"Point"}
}