{
  "type": "Feature",
  "properties": {
    "iso:country":"US",
    "sg:address":"4230 N Pecos Rd",
    "sg:city":"Las Vegas",
    "sg:classifiers":[
        {
            "category":"Building & Trades",
            "subcategory":"Construction",
            "type":"Services"
        }
    ],
    "sg:phone":"+1 702 437 3732",
    "sg:postcode":"89115",
    "sg:province":"NV",
    "sg:tags":[
        "builder",
        "patio",
        "deck"
    ],
    "wof:name":"Custom Creation In One Co",
    "wof:placetype":"venue"
},
  "geometry": {"coordinates":[-115.09764699999999,36.238518],"type":"Point"}
}