{
  "type": "Feature",
  "properties": {
    "iso:country":"US",
    "sg:address":"2491 E Tropicana Avenue",
    "sg:city":"Las Vegas",
    "sg:classifiers":[
        {
            "category":"Personal",
            "subcategory":"Barber",
            "type":"Services"
        }
    ],
    "sg:phone":"+1 702 898 0400",
    "sg:postcode":"89121",
    "sg:province":"NV",
    "wof:name":"Jesse's Barber Shop",
    "wof:placetype":"venue"
},
  "geometry": {"coordinates":[-115.116317,36.099882],"type":"Point"}
}