{
  "type": "Feature",
  "properties": {
    "iso:country":"US",
    "sg:address":"1300 W Sunset Rd Ste 2837",
    "sg:city":"Henderson",
    "sg:classifiers":[
        {
            "category":"Fast Food",
            "type":"Food & Drink"
        }
    ],
    "sg:phone":"+1 702 456 0968",
    "sg:postcode":"89014",
    "sg:province":"NV",
    "sg:website":"www.mcdonalds.com",
    "wof:name":"McDonald's Restaurants",
    "wof:placetype":"venue"
},
  "geometry": {"coordinates":[-115.040233,36.063823],"type":"Point"}
}