{
  "type": "Feature",
  "properties": {
    "iso:country":"US",
    "sg:address":"1139 Linn Lane",
    "sg:city":"Las Vegas",
    "sg:classifiers":[
        {
            "category":"Education",
            "subcategory":"School",
            "type":"Public Place"
        }
    ],
    "sg:phone":"+1 702 799 7200",
    "sg:postcode":"89110",
    "sg:province":"NV",
    "sg:website":"www.ccsd.net",
    "wof:name":"Clark County School District",
    "wof:placetype":"venue"
},
  "geometry": {"coordinates":[-115.048382,36.178412],"type":"Point"}
}