{
  "type": "Feature",
  "properties": {
    "iso:country":"US",
    "sg:address":"5315 Meadowood Mall Cir",
    "sg:city":"Reno",
    "sg:classifiers":[
        {
            "category":"Shopping",
            "type":"Retail Goods"
        }
    ],
    "sg:phone":"+1 775 829 1820",
    "sg:postcode":"89502",
    "sg:province":"NV",
    "sg:tags":[
        "merchandise"
    ],
    "wof:name":"Wicks & Sticks",
    "wof:placetype":"venue"
},
  "geometry": {"coordinates":[-119.782905,39.471599],"type":"Point"}
}