{
  "type": "Feature",
  "properties": {
    "iso:country":"US",
    "sg:address":"610 S 7th St",
    "sg:city":"Las Vegas",
    "sg:classifiers":[
        {
            "category":"Insurance",
            "subcategory":"Insurance Agent",
            "type":"Services"
        }
    ],
    "sg:phone":"+1 702 876 9318",
    "sg:postcode":"89101",
    "sg:province":"NV",
    "sg:tags":[
        "adjuster"
    ],
    "wof:name":"Triad Professional Adjusters",
    "wof:placetype":"venue"
},
  "geometry": {"coordinates":[-115.142966,36.16144],"type":"Point"}
}