{
  "type": "Feature",
  "properties": {
    "iso:country":"US",
    "sg:address":"4809 Kietzke Ln",
    "sg:city":"Reno",
    "sg:classifiers":[
        {
            "category":"Personal",
            "subcategory":"Beauty Salon",
            "type":"Services"
        }
    ],
    "sg:phone":"+1 775 827 2211",
    "sg:postcode":"89509",
    "sg:province":"NV",
    "sg:tags":[
        "shop"
    ],
    "wof:name":"Great Clips",
    "wof:placetype":"venue"
},
  "geometry": {"coordinates":[-119.791543,39.482344],"type":"Point"}
}