{
  "type": "Feature",
  "properties": {
    "iso:country":"US",
    "sg:address":"4321 W Flamingo Road",
    "sg:city":"Las Vegas",
    "sg:classifiers":[
        {
            "category":"Shopping",
            "subcategory":"Pawn Shop",
            "type":"Retail Goods"
        }
    ],
    "sg:phone":"+1 702 947 8833",
    "sg:postcode":"89103",
    "sg:province":"NV",
    "wof:name":"Stuff",
    "wof:placetype":"venue"
},
  "geometry": {"coordinates":[-115.19682899999999,36.115345],"type":"Point"}
}