{
  "type": "Feature",
  "properties": {
    "iso:country":"US",
    "sg:address":"18124 Wedge Pkwy",
    "sg:city":"Reno",
    "sg:classifiers":[
        {
            "category":"Travel",
            "subcategory":"Campground",
            "type":"Entertainment"
        }
    ],
    "sg:phone":"+1 775 852 8270",
    "sg:postcode":"89511",
    "sg:province":"NV",
    "sg:tags":[
        "trailer"
    ],
    "wof:name":"Klamath Ranch Resort",
    "wof:placetype":"venue"
},
  "geometry": {"coordinates":[-119.76707,39.395698],"type":"Point"}
}