{
  "type": "Feature",
  "properties": {
    "iso:country":"US",
    "sg:address":"925 Farm District Rd",
    "sg:city":"Fernley",
    "sg:classifiers":[
        {
            "category":"Shopping",
            "subcategory":"Clothing, Apparel, & Fashions",
            "type":"Retail Goods"
        }
    ],
    "sg:phone":"+1 775 835 0349",
    "sg:postcode":"89408",
    "sg:province":"NV",
    "sg:tags":[
        "western"
    ],
    "wof:name":"K W Western",
    "wof:placetype":"venue"
},
  "geometry": {"coordinates":[-119.226863,39.594594],"type":"Point"}
}