{
  "type": "Feature",
  "properties": {
    "iso:country":"US",
    "sg:address":"325 W Liberty St",
    "sg:city":"Reno",
    "sg:classifiers":[
        {
            "category":"Professional",
            "subcategory":"Lawyer & Legal Services",
            "type":"Services"
        }
    ],
    "sg:phone":"+1 775 324 5998",
    "sg:postcode":"89501",
    "sg:province":"NV",
    "sg:tags":[
        "attorney"
    ],
    "wof:name":"Michael Merchant",
    "wof:placetype":"venue"
},
  "geometry": {"coordinates":[-119.816429,39.520801],"type":"Point"}
}