{
  "type": "Feature",
  "properties": {
    "iso:country":"US",
    "sg:address":"9555 Las Vegas Blvd S",
    "sg:city":"Las Vegas",
    "sg:classifiers":[
        {
            "category":"Organizations",
            "subcategory":"Religious Organization",
            "type":"Services"
        }
    ],
    "sg:phone":"+1 702 260 7660",
    "sg:postcode":"89123",
    "sg:province":"NV",
    "sg:tags":[
        "church"
    ],
    "wof:name":"Beautiful Savior Lutheran Chr",
    "wof:placetype":"venue"
},
  "geometry": {"coordinates":[-115.172418,36.017109],"type":"Point"}
}