{
  "type": "Feature",
  "properties": {
    "iso:country":"US",
    "sg:address":"7845 Clearwood Ave",
    "sg:city":"Las Vegas",
    "sg:classifiers":[
        {
            "category":"Autos & Motor Vehicles",
            "subcategory":"Automobile Sales",
            "type":"Retail Goods"
        }
    ],
    "sg:phone":"+1 702 260 1406",
    "sg:postcode":"89123",
    "sg:province":"NV",
    "sg:tags":[
        "used"
    ],
    "wof:name":"Used Lighting Incorporated",
    "wof:placetype":"venue"
},
  "geometry": {"coordinates":[-115.127972,36.046424],"type":"Point"}
}