{
  "type": "Feature",
  "properties": {
    "iso:country":"US",
    "sg:address":"6360 McLeod Dr",
    "sg:city":"Las Vegas",
    "sg:classifiers":[
        {
            "category":"Wholesale",
            "subcategory":"Durable Goods & Equipment",
            "type":"Manufacturing & Wholesale Goods"
        }
    ],
    "sg:phone":"+1 702 798 5355",
    "sg:postcode":"89120",
    "sg:province":"NV",
    "sg:tags":[
        "gaming",
        "supply"
    ],
    "wof:name":"Spectronix",
    "wof:placetype":"venue"
},
  "geometry": {"coordinates":[-115.11270399999999,36.072588],"type":"Point"}
}