{
  "type": "Feature",
  "properties": {
    "iso:country":"US",
    "sg:address":"9326 W Sahara Avenue",
    "sg:city":"Las Vegas",
    "sg:classifiers":[
        {
            "category":"Personal",
            "subcategory":"Barber",
            "type":"Services"
        }
    ],
    "sg:phone":"+1 702 233 6594",
    "sg:postcode":"89117",
    "sg:province":"NV",
    "sg:website":"www.supercuts.com",
    "wof:name":"Supercuts",
    "wof:placetype":"venue"
},
  "geometry": {"coordinates":[-115.29826,36.144483],"type":"Point"}
}