{
  "type": "Feature",
  "properties": {
    "iso:country":"US",
    "sg:address":"6150 Eisner Dr",
    "sg:city":"Las Vegas",
    "sg:classifiers":[
        {
            "category":"Building & Trades",
            "subcategory":"Electrical",
            "type":"Services"
        }
    ],
    "sg:phone":"+1 702 395 7144",
    "sg:postcode":"89131",
    "sg:province":"NV",
    "sg:tags":[
        "electrical",
        "contractor"
    ],
    "wof:name":"C & M Electric Services Inc",
    "wof:placetype":"venue"
},
  "geometry": {"coordinates":[-115.225966,36.296007],"type":"Point"}
}