{
  "type": "Feature",
  "properties": {
    "iso:country":"US",
    "sg:address":"2055 Trento Ln",
    "sg:city":"Fallon",
    "sg:classifiers":[
        {
            "category":"Restaurant",
            "type":"Food & Drink"
        }
    ],
    "sg:phone":"+1 775 867 2031",
    "sg:postcode":"89406",
    "sg:province":"NV",
    "wof:name":"Billie Jo's Cafe",
    "wof:placetype":"venue"
},
  "geometry": {"coordinates":[-118.912613,39.508432],"type":"Point"}
}