{
  "type": "Feature",
  "properties": {
    "iso:country":"US",
    "sg:address":"7970 Teresita Ave",
    "sg:city":"Las Vegas",
    "sg:classifiers":[
        {
            "category":"Arts & Performance",
            "subcategory":"Theater",
            "type":"Entertainment"
        }
    ],
    "sg:phone":"+1 702 250 0461",
    "sg:postcode":"89147",
    "sg:province":"NV",
    "sg:tags":[
        "live",
        "music"
    ],
    "wof:name":"Sonic Image",
    "wof:placetype":"venue"
},
  "geometry": {"coordinates":[-115.264899,36.111841],"type":"Point"}
}