{
  "type": "Feature",
  "properties": {
    "iso:country":"US",
    "sg:address":"800 Tahoe Blvd",
    "sg:city":"Incline Village",
    "sg:classifiers":[
        {
            "category":"Shopping",
            "type":"Retail Goods"
        }
    ],
    "sg:phone":"+1 530 314 5034",
    "sg:postcode":"89451",
    "sg:province":"NV",
    "sg:tags":[
        "merchandise"
    ],
    "wof:name":"Cell N Game LLC",
    "wof:placetype":"venue"
},
  "geometry": {"coordinates":[-119.96139599999999,39.250322],"type":"Point"}
}