{
  "type": "Feature",
  "properties": {
    "iso:country":"US",
    "sg:address":"5203 Martingale Ave",
    "sg:city":"Las Vegas",
    "sg:classifiers":[
        {
            "category":"Shopping",
            "subcategory":"Clothing, Apparel, & Fashions",
            "type":"Retail Goods"
        }
    ],
    "sg:phone":"+1 702 444 1863",
    "sg:postcode":"89119",
    "sg:province":"NV",
    "sg:tags":[
        "tailor"
    ],
    "wof:name":"Creative Design",
    "wof:placetype":"venue"
},
  "geometry": {"coordinates":[-115.12258799999999,36.095039],"type":"Point"}
}