{
  "type": "Feature",
  "properties": {
    "iso:country":"US",
    "sg:address":"1254 Dove Tree Ct",
    "sg:city":"Henderson",
    "sg:classifiers":[
        {
            "category":"Professional",
            "subcategory":"Accounting & Tax Preparation",
            "type":"Services"
        }
    ],
    "sg:phone":"+1 702 639 1800",
    "sg:postcode":"89014",
    "sg:province":"NV",
    "sg:tags":[
        "accountant"
    ],
    "wof:name":"Dirk Carla CPA",
    "wof:placetype":"venue"
},
  "geometry": {"coordinates":[-115.038455,36.050304],"type":"Point"}
}