{
  "type": "Feature",
  "properties": {
    "iso:country":"US",
    "sg:address":"9950 W Cheyenne Avenue",
    "sg:city":"Las Vegas",
    "sg:classifiers":[
        {
            "category":"Professional",
            "subcategory":"Lawyer & Legal Services",
            "type":"Services"
        }
    ],
    "sg:phone":"+1 702 384 4012",
    "sg:postcode":"89129",
    "sg:province":"NV",
    "wof:name":"McKay Raymond E Atty",
    "wof:placetype":"venue"
},
  "geometry": {"coordinates":[-115.313985,36.218429],"type":"Point"}
}