{
  "type": "Feature",
  "properties": {
    "iso:country":"US",
    "sg:address":"3200 Las Vegas Fwy",
    "sg:city":"North Las Vegas",
    "sg:classifiers":[
        {
            "category":"Shopping",
            "type":"Retail Goods"
        }
    ],
    "sg:phone":"+1 702 657 8857",
    "sg:postcode":"89030",
    "sg:province":"NV",
    "sg:tags":[
        "awning",
        "canopy"
    ],
    "wof:name":"Metals USA",
    "wof:placetype":"venue"
},
  "geometry": {"coordinates":[-115.120255,36.22264],"type":"Point"}
}