{
  "type": "Feature",
  "properties": {
    "iso:country":"US",
    "sg:address":"3630 Black Forest Ln",
    "sg:city":"Sparks",
    "sg:classifiers":[
        {
            "category":"Banks & Credit Unions",
            "subcategory":"Financial Services",
            "type":"Services"
        }
    ],
    "sg:phone":"+1 775 626 2175",
    "sg:postcode":"89434",
    "sg:province":"NV",
    "sg:tags":[
        "investor"
    ],
    "wof:name":"Bogart Stevenson Investments",
    "wof:placetype":"venue"
},
  "geometry": {"coordinates":[-119.71410400000001,39.565796],"type":"Point"}
}