{
  "type": "Feature",
  "properties": {
    "iso:country":"US",
    "sg:address":"6020 W Craig Rd",
    "sg:city":"Las Vegas",
    "sg:classifiers":[
        {
            "category":"Restaurant",
            "type":"Food & Drink"
        }
    ],
    "sg:menulink":"http://www.allmenus.com/nv/las-vegas/122959-quiznos-sub/menu/",
    "sg:phone":"+1 702 395 2121",
    "sg:postcode":"89130",
    "sg:province":"NV",
    "sg:tags":[
        "wrap",
        "american",
        "sandwich"
    ],
    "wof:name":"Quiznos Sub",
    "wof:placetype":"venue"
},
  "geometry": {"coordinates":[-115.22685,36.239241],"type":"Point"}
}