{
  "type": "Feature",
  "properties": {
    "iso:country":"US",
    "sg:address":"311 S Valley View Blvd",
    "sg:city":"Las Vegas",
    "sg:classifiers":[
        {
            "category":"Building & Trades",
            "subcategory":"Construction",
            "type":"Services"
        }
    ],
    "sg:phone":"+1 702 247 9838",
    "sg:postcode":"89107",
    "sg:province":"NV",
    "sg:tags":[
        "dry",
        "hanging",
        "business",
        "contractor"
    ],
    "wof:name":"Premier Painting Inc",
    "wof:placetype":"venue"
},
  "geometry": {"coordinates":[-115.192498,36.166636],"type":"Point"}
}