{
  "type": "Feature",
  "properties": {
    "iso:country":"US",
    "sg:address":"3111 Blossom Glen Dr",
    "sg:city":"Henderson",
    "sg:classifiers":[
        {
            "category":"Home & Garden",
            "subcategory":"Home Furnishings",
            "type":"Retail Goods"
        }
    ],
    "sg:phone":"+1 702 735 2378",
    "sg:postcode":"89014",
    "sg:province":"NV",
    "wof:name":"Simply Best Blinds",
    "wof:placetype":"venue"
},
  "geometry": {"coordinates":[-115.08979600000001,36.061835],"type":"Point"}
}