{
  "type": "Feature",
  "properties": {
    "iso:country":"US",
    "sg:address":"41250 S Eastern Ave.",
    "sg:city":"Las Vegas",
    "sg:classifiers":[
        {
            "category":"Personal",
            "subcategory":"Nail Salon",
            "type":"Services"
        }
    ],
    "sg:phone":"+1 702 233 9829",
    "sg:postcode":"89121",
    "sg:province":"NV",
    "wof:name":"Pink Nail Salon",
    "wof:placetype":"venue"
},
  "geometry": {"coordinates":[-115.118828,36.099937],"type":"Point"}
}