{
  "type": "Feature",
  "properties": {
    "iso:country":"US",
    "sg:address":"9770 S Mccarran Blvd",
    "sg:city":"Reno",
    "sg:classifiers":[
        {
            "category":"Health Services",
            "subcategory":"Doctor",
            "type":"Services"
        },
        {
            "category":"Wholesale",
            "subcategory":"Medical Equipment & Supplies",
            "type":"Manufacturing & Wholesale Goods"
        },
        {
            "category":"Health Services",
            "subcategory":"Health Practitioner",
            "type":"Services"
        }
    ],
    "sg:phone":"+1 775 322 4589",
    "sg:postcode":"89523",
    "sg:province":"NV",
    "sg:tags":[
        "physician",
        "ear",
        "surgeons",
        "hearing",
        "otorhinolaryngology",
        "throat",
        "device",
        "nose",
        "assistive",
        "aid",
        "surgeon",
        "audiologists"
    ],
    "wof:name":"Nevada ENT & Hearing Associates",
    "wof:placetype":"venue"
},
  "geometry": {"coordinates":[-119.862261,39.52186],"type":"Point"}
}