{
  "type": "Feature",
  "properties": {
    "iso:country":"US",
    "sg:address":"4845 W Tropicana Ave",
    "sg:city":"Las Vegas",
    "sg:classifiers":[
        {
            "category":"Autos & Motor Vehicles",
            "subcategory":"Automobile Sales",
            "type":"Retail Goods"
        }
    ],
    "sg:phone":"+1 702 367 9600",
    "sg:postcode":"89103",
    "sg:province":"NV",
    "sg:tags":[
        "car",
        "used",
        "dealer"
    ],
    "sg:website":"www.thesupercarstore.com",
    "wof:name":"Carollo Falconi Super Car Str",
    "wof:placetype":"venue"
},
  "geometry": {"coordinates":[-115.207538,36.10096],"type":"Point"}
}