{
  "type": "Feature",
  "properties": {
    "iso:country":"US",
    "sg:address":"1555 E Flamingo Road",
    "sg:city":"Las Vegas",
    "sg:classifiers":[
        {
            "category":"Professional",
            "subcategory":"Employment Agencies",
            "type":"Services"
        }
    ],
    "sg:phone":"+1 702 951 0130",
    "sg:postcode":"89119",
    "sg:province":"NV",
    "wof:name":"Tnt Temporary & Staffing Services",
    "wof:placetype":"venue"
},
  "geometry": {"coordinates":[-115.131484,36.114504],"type":"Point"}
}