{
  "type": "Feature",
  "properties": {
    "iso:country":"US",
    "sg:address":"3381 S Jones Blvd",
    "sg:city":"Las Vegas",
    "sg:classifiers":[
        {
            "category":"Banks & Credit Unions",
            "subcategory":"Financial Services",
            "type":"Services"
        }
    ],
    "sg:phone":"+1 702 579 9989",
    "sg:postcode":"89146",
    "sg:province":"NV",
    "sg:tags":[
        "broker",
        "mortgage"
    ],
    "wof:name":"Fortune Mortgage Co",
    "wof:placetype":"venue"
},
  "geometry": {"coordinates":[-115.225151,36.127609],"type":"Point"}
}