{
  "type": "Feature",
  "properties": {
    "iso:country":"US",
    "sg:address":"5704 Losee Rd",
    "sg:city":"North Las Vegas",
    "sg:classifiers":[
        {
            "category":"Professional",
            "subcategory":"Advertising",
            "type":"Services"
        }
    ],
    "sg:phone":"+1 702 396 2123",
    "sg:postcode":"89030",
    "sg:province":"NV",
    "sg:website":"www.lasvegasyes.com",
    "wof:name":"LASVEGASYES.COM",
    "wof:placetype":"venue"
},
  "geometry": {"coordinates":[-115.116913,36.268907],"type":"Point"}
}