{
  "type": "Feature",
  "properties": {
    "iso:country":"US",
    "sg:address":"7944 March Brown Ave",
    "sg:city":"Las Vegas",
    "sg:classifiers":[
        {
            "category":"Manufacturing",
            "subcategory":"Retail Goods",
            "type":"Manufacturing & Wholesale Goods"
        }
    ],
    "sg:phone":"+1 702 219 4022",
    "sg:postcode":"89149",
    "sg:province":"NV",
    "sg:tags":[
        "product",
        "mfg"
    ],
    "wof:name":"Bradley Model Maintenance",
    "wof:placetype":"venue"
},
  "geometry": {"coordinates":[-115.265726,36.268426],"type":"Point"}
}