{
  "type": "Feature",
  "properties": {
    "iso:country":"US",
    "sg:address":"2785 E Desert Inn Rd",
    "sg:city":"Las Vegas",
    "sg:classifiers":[
        {
            "category":"Organizations",
            "subcategory":"Membership Organization",
            "type":"Services"
        },
        {
            "category":"Organizations",
            "subcategory":"Professional Association",
            "type":"Services"
        }
    ],
    "sg:phone":"+1 702 369 9995",
    "sg:postcode":"89121",
    "sg:province":"NV",
    "wof:name":"American Diabetes Association",
    "wof:placetype":"venue"
},
  "geometry": {"coordinates":[-115.111638,36.129709],"type":"Point"}
}