{
  "type": "Feature",
  "properties": {
    "iso:country":"US",
    "sg:address":"537 E Ogden Ave",
    "sg:city":"Las Vegas",
    "sg:classifiers":[
        {
            "category":"Building & Trades",
            "subcategory":"Plumbing",
            "type":"Services"
        }
    ],
    "sg:phone":"+1 702 383 9855",
    "sg:postcode":"89101",
    "sg:province":"NV",
    "wof:name":"Desert Plumbing & Hearing",
    "wof:placetype":"venue"
},
  "geometry": {"coordinates":[-115.13927099999999,36.170321],"type":"Point"}
}