{
  "type": "Feature",
  "properties": {
    "iso:country":"US",
    "sg:address":"3196 S Maryland Pkwy",
    "sg:city":"Las Vegas",
    "sg:classifiers":[
        {
            "category":"Health Services",
            "subcategory":"Doctor",
            "type":"Services"
        }
    ],
    "sg:phone":"+1 702 735 7272",
    "sg:postcode":"89109",
    "sg:province":"NV",
    "sg:tags":[
        "medical"
    ],
    "wof:name":"Neurosurgical Associates Nev",
    "wof:placetype":"venue"
},
  "geometry": {"coordinates":[-115.136792,36.131912],"type":"Point"}
}