{
  "type": "Feature",
  "properties": {
    "iso:country":"US",
    "sg:address":"1182 Little Sidnee Dr",
    "sg:city":"Las Vegas",
    "sg:classifiers":[
        {
            "category":"Wholesale",
            "subcategory":"Medical Equipment & Supplies",
            "type":"Manufacturing & Wholesale Goods"
        }
    ],
    "sg:phone":"+1 702 837 7953",
    "sg:postcode":"89123",
    "sg:province":"NV",
    "wof:name":"Asafo Global Enterprises Inc",
    "wof:placetype":"venue"
},
  "geometry": {"coordinates":[-115.136803,36.056983],"type":"Point"}
}