{
  "type": "Feature",
  "properties": {
    "iso:country":"US",
    "sg:address":"711 E Washington St",
    "sg:city":"Carson City",
    "sg:classifiers":[
        {
            "category":"Professional",
            "subcategory":"Lawyer & Legal Services",
            "type":"Services"
        }
    ],
    "sg:phone":"+1 775 885 8071",
    "sg:postcode":"89701",
    "sg:province":"NV",
    "wof:name":"Johnson Erik R Atty",
    "wof:placetype":"venue"
},
  "geometry": {"coordinates":[-119.762001,39.168499],"type":"Point"}
}