{
  "type": "Feature",
  "properties": {
    "iso:country":"US",
    "sg:address":"6600 Pearblossom Ln",
    "sg:city":"Las Vegas",
    "sg:classifiers":[
        {
            "category":"Building & Trades",
            "subcategory":"Landscaping Services",
            "type":"Services"
        }
    ],
    "sg:phone":"+1 702 645 2007",
    "sg:postcode":"89108",
    "sg:province":"NV",
    "sg:tags":[
        "gardening"
    ],
    "wof:name":"Good Earth Gardening",
    "wof:placetype":"venue"
},
  "geometry": {"coordinates":[-115.241603,36.239066],"type":"Point"}
}