{
  "type": "Feature",
  "properties": {
    "iso:country":"US",
    "sg:address":"1170 S Wells Ave",
    "sg:city":"Reno",
    "sg:classifiers":[
        {
            "category":"Food & Beverages",
            "subcategory":"Specialty",
            "type":"Retail Goods"
        }
    ],
    "sg:phone":"+1 775 786 8814",
    "sg:postcode":"89502",
    "sg:province":"NV",
    "sg:tags":[
        "health",
        "diet"
    ],
    "wof:name":"Truckee Meadows Herbs",
    "wof:placetype":"venue"
},
  "geometry": {"coordinates":[-119.80309099999999,39.514515],"type":"Point"}
}