{
  "type": "Feature",
  "properties": {
    "iso:country":"US",
    "sg:address":"6080 S Jones Blvd",
    "sg:city":"Las Vegas",
    "sg:classifiers":[
        {
            "category":"Organizations",
            "subcategory":"Religious Organization",
            "type":"Services"
        }
    ],
    "sg:phone":"+1 702 453 0033",
    "sg:postcode":"89118",
    "sg:province":"NV",
    "sg:tags":[
        "church"
    ],
    "wof:name":"St Paul Jung Ha Sang Korean",
    "wof:placetype":"venue"
},
  "geometry": {"coordinates":[-115.224802,36.079496],"type":"Point"}
}