{
  "type": "Feature",
  "properties": {
    "iso:country":"US",
    "sg:address":"4000 Vanessa Dr",
    "sg:city":"Las Vegas",
    "sg:classifiers":[
        {
            "category":"Professional",
            "type":"Services"
        }
    ],
    "sg:phone":"+1 702 871 5115",
    "sg:postcode":"89103",
    "sg:province":"NV",
    "sg:tags":[
        "establishment"
    ],
    "wof:name":"Hospitality International",
    "wof:placetype":"venue"
},
  "geometry": {"coordinates":[-115.19207400000001,36.125339],"type":"Point"}
}