{
  "type": "Feature",
  "properties": {
    "iso:country":"US",
    "sg:address":"2245 N Decatur Blvd Ste A",
    "sg:city":"Las Vegas",
    "sg:classifiers":[
        {
            "category":"Bars & Pubs",
            "subcategory":"Sports Bar",
            "type":"Food & Drink"
        }
    ],
    "sg:phone":"+1 702 648 8081",
    "sg:postcode":"89108",
    "sg:province":"NV",
    "wof:name":"Fast Break Lounge",
    "wof:placetype":"venue"
},
  "geometry": {"coordinates":[-115.206372,36.200069],"type":"Point"}
}