{
  "type": "Feature",
  "properties": {
    "iso:country":"US",
    "sg:address":"3250 E Sahara Ave",
    "sg:city":"Las Vegas",
    "sg:classifiers":[
        {
            "category":"Autos & Motor Vehicles",
            "subcategory":"Automobile Sales",
            "type":"Retail Goods"
        }
    ],
    "sg:phone":"+1 702 457 8061",
    "sg:postcode":"89104",
    "sg:province":"NV",
    "sg:tags":[
        "repair",
        "dealer",
        "car",
        "general"
    ],
    "sg:website":"www.unitednissanlv.com",
    "wof:name":"United Nissan Inc",
    "wof:placetype":"venue"
},
  "geometry": {"coordinates":[-115.104192,36.144456],"type":"Point"}
}