{
  "type": "Feature",
  "properties": {
    "iso:country":"US",
    "sg:address":"294 E Moana Ln",
    "sg:city":"Reno",
    "sg:classifiers":[
        {
            "category":"Banks & Credit Unions",
            "subcategory":"Bank",
            "type":"Services"
        }
    ],
    "sg:phone":"+1 775 829 9228",
    "sg:postcode":"89502",
    "sg:province":"NV",
    "sg:tags":[
        "loan",
        "real estate"
    ],
    "wof:name":"Oak Street Mortgage",
    "wof:placetype":"venue"
},
  "geometry": {"coordinates":[-119.792424,39.492589],"type":"Point"}
}