{
  "type": "Feature",
  "properties": {
    "iso:country":"US",
    "sg:address":"555 Reactor Way",
    "sg:city":"Reno",
    "sg:classifiers":[
        {
            "category":"Organizations",
            "subcategory":"Non-profit Organization",
            "type":"Services"
        },
        {
            "category":"Manufacturing",
            "subcategory":"Tools & Machinery",
            "type":"Manufacturing & Wholesale Goods"
        }
    ],
    "sg:phone":"+1 775 829 7400",
    "sg:postcode":"89502",
    "sg:province":"NV",
    "sg:tags":[
        "wood",
        "electrical",
        "mfg"
    ],
    "wof:name":"High Sierra Industries Inc",
    "wof:placetype":"venue"
},
  "geometry": {"coordinates":[-119.760421,39.505776],"type":"Point"}
}