{
  "type": "Feature",
  "properties": {
    "iso:country":"US",
    "sg:address":"3844 Meadows Ln",
    "sg:city":"Las Vegas",
    "sg:classifiers":[
        {
            "category":"Professional",
            "subcategory":"Management & Consulting",
            "type":"Services"
        }
    ],
    "sg:phone":"+1 702 953 2020",
    "sg:postcode":"89107",
    "sg:province":"NV",
    "sg:tags":[
        "business"
    ],
    "wof:name":"Comm 2020",
    "wof:placetype":"venue"
},
  "geometry": {"coordinates":[-115.20383200000001,36.170295],"type":"Point"}
}