{
  "type": "Feature",
  "properties": {
    "iso:country":"US",
    "sg:address":"2800 N Tenaya Way",
    "sg:city":"Las Vegas",
    "sg:classifiers":[
        {
            "category":"Health Services",
            "subcategory":"Doctor",
            "type":"Services"
        }
    ],
    "sg:phone":"+1 702 242 4616",
    "sg:postcode":"89128",
    "sg:province":"NV",
    "sg:tags":[
        "reconstructive",
        "surgery",
        "plastic"
    ],
    "wof:name":"Rifley William J III MD",
    "wof:placetype":"venue"
},
  "geometry": {"coordinates":[-115.249644,36.20871],"type":"Point"}
}