{
  "type": "Feature",
  "properties": {
    "iso:country":"US",
    "sg:address":"2306 State Hwy 208",
    "sg:city":"Smith",
    "sg:classifiers":[
        {
            "category":"Government",
            "subcategory":"Post Office",
            "type":"Public Place"
        }
    ],
    "sg:phone":"+1 775 465 2301",
    "sg:postcode":"89430",
    "sg:province":"NV",
    "wof:name":"US Post Office",
    "wof:placetype":"venue"
},
  "geometry": {"coordinates":[-119.344015,38.782441],"type":"Point"}
}