{
  "type": "Feature",
  "properties": {
    "iso:country":"US",
    "sg:address":"7920 W Tropical Pkwy",
    "sg:city":"Las Vegas",
    "sg:classifiers":[
        {
            "category":"Retail",
            "subcategory":"Laundry & Dry Cleaning",
            "type":"Services"
        }
    ],
    "sg:phone":"+1 702 839 1523",
    "sg:postcode":"89149",
    "sg:province":"NV",
    "sg:tags":[
        "cleaner"
    ],
    "wof:name":"Park Avenue Cleaners & Shoe Repair",
    "wof:placetype":"venue"
},
  "geometry": {"coordinates":[-115.26799800000001,36.270599],"type":"Point"}
}