{
  "type": "Feature",
  "properties": {
    "iso:country":"US",
    "sg:address":"4444 W Craig Rd",
    "sg:city":"North Las Vegas",
    "sg:classifiers":[
        {
            "category":"Shopping",
            "subcategory":"Computers & Home Electronics",
            "type":"Retail Goods"
        }
    ],
    "sg:phone":"+1 702 631 3709",
    "sg:postcode":"89032",
    "sg:province":"NV",
    "sg:tags":[
        "equipment",
        "satellite",
        "system"
    ],
    "wof:name":"Dishman",
    "wof:placetype":"venue"
},
  "geometry": {"coordinates":[-115.202034,36.239026],"type":"Point"}
}