{
  "type": "Feature",
  "properties": {
    "iso:country":"US",
    "sg:address":"507 Churchill St",
    "sg:city":"Fallon",
    "sg:classifiers":[
        {
            "category":"Organizations",
            "subcategory":"Religious Organization",
            "type":"Services"
        }
    ],
    "sg:phone":"+1 775 423 3551",
    "sg:postcode":"89406",
    "sg:province":"NV",
    "sg:tags":[
        "church"
    ],
    "wof:name":"Holy Trinity Episcopal Parish",
    "wof:placetype":"venue"
},
  "geometry": {"coordinates":[-118.775861,39.470231],"type":"Point"}
}