{
  "type": "Feature",
  "properties": {
    "iso:country":"US",
    "sg:address":"2855 S Nellis Blvd",
    "sg:city":"Las Vegas",
    "sg:classifiers":[
        {
            "category":"Shopping",
            "subcategory":"Pharmacy",
            "type":"Retail Goods"
        }
    ],
    "sg:phone":"+1 702 431 4194",
    "sg:postcode":"89121",
    "sg:province":"NV",
    "wof:name":"Sav-On 9042",
    "wof:placetype":"venue"
},
  "geometry": {"coordinates":[-115.065546,36.140241],"type":"Point"}
}