{
  "type": "Feature",
  "properties": {
    "iso:country":"US",
    "sg:address":"1180 E Desert Inn Rd",
    "sg:city":"Las Vegas",
    "sg:classifiers":[
        {
            "category":"Restaurant",
            "type":"Food & Drink"
        }
    ],
    "sg:menulink":"http://www.allmenus.com/nv/las-vegas/161096-carls-jr/menu/",
    "sg:phone":"+1 702 369 7061",
    "sg:postcode":"89109",
    "sg:province":"NV",
    "sg:tags":[
        "burger",
        "american"
    ],
    "wof:name":"Carl's Jr.",
    "wof:placetype":"venue"
},
  "geometry": {"coordinates":[-115.13733000000001,36.130118],"type":"Point"}
}