{
  "type": "Feature",
  "properties": {
    "iso:country":"US",
    "sg:address":"2700 Horseshoe Dr",
    "sg:city":"Las Vegas",
    "sg:classifiers":[
        {
            "category":"Professional",
            "subcategory":"Detective & Security Services",
            "type":"Services"
        }
    ],
    "sg:phone":"+1 702 433 6068",
    "sg:postcode":"89120",
    "sg:province":"NV",
    "sg:tags":[
        "investigator"
    ],
    "wof:name":"Infoserve",
    "wof:placetype":"venue"
},
  "geometry": {"coordinates":[-115.112448,36.087372],"type":"Point"}
}