{
  "type": "Feature",
  "properties": {
    "iso:country":"US",
    "sg:address":"2223 N Rampart Blvd",
    "sg:city":"Las Vegas",
    "sg:classifiers":[
        {
            "category":"Bagels",
            "subcategory":"None",
            "type":"Food & Drink"
        }
    ],
    "sg:phone":"+1 702 838 4991",
    "sg:postcode":"89128",
    "sg:province":"NV",
    "sg:website":"www.sterlingbagels.com/",
    "wof:name":"Sterling Bagels",
    "wof:placetype":"venue"
},
  "geometry": {"coordinates":[-115.281363,36.201018],"type":"Point"}
}