{
  "type": "Feature",
  "properties": {
    "iso:country":"US",
    "sg:address":"428 Proud Eagle Ln",
    "sg:city":"Las Vegas",
    "sg:classifiers":[
        {
            "category":"Professional",
            "subcategory":"Management & Consulting",
            "type":"Services"
        }
    ],
    "sg:phone":"+1 702 804 0257",
    "sg:postcode":"89144",
    "sg:province":"NV",
    "wof:name":"R Roger Romrell",
    "wof:placetype":"venue"
},
  "geometry": {"coordinates":[-115.305927,36.179166],"type":"Point"}
}