{
  "type": "Feature",
  "properties": {
    "iso:country":"US",
    "sg:address":"1275 Tacoma Way",
    "sg:city":"Reno",
    "sg:classifiers":[
        {
            "category":"Professional",
            "subcategory":"Art Services",
            "type":"Services"
        }
    ],
    "sg:phone":"+1 775 786 9489",
    "sg:postcode":"89509",
    "sg:province":"NV",
    "sg:tags":[
        "commercial",
        "design"
    ],
    "wof:name":"Ditto Design",
    "wof:placetype":"venue"
},
  "geometry": {"coordinates":[-119.83386400000001,39.508793],"type":"Point"}
}