{
  "type": "Feature",
  "properties": {
    "iso:country":"US",
    "sg:address":"2838 Marco St",
    "sg:city":"Las Vegas",
    "sg:classifiers":[
        {
            "category":"Building & Trades",
            "subcategory":"Pest Control",
            "type":"Services"
        }
    ],
    "sg:phone":"+1 702 649 0019",
    "sg:postcode":"89115",
    "sg:province":"NV",
    "sg:website":"www.preventivepestcontrol.com",
    "wof:name":"Preventive Pest Control",
    "wof:placetype":"venue"
},
  "geometry": {"coordinates":[-115.067799,36.21161],"type":"Point"}
}