{
  "type": "Feature",
  "properties": {
    "iso:country":"US",
    "sg:address":"7883 Fall Harvest Dr",
    "sg:city":"Las Vegas",
    "sg:classifiers":[
        {
            "category":"Building & Trades",
            "subcategory":"Construction",
            "type":"Services"
        }
    ],
    "sg:phone":"+1 702 873 6910",
    "sg:postcode":"89147",
    "sg:province":"NV",
    "sg:tags":[
        "contractor"
    ],
    "wof:name":"Windowear Window Treatment",
    "wof:placetype":"venue"
},
  "geometry": {"coordinates":[-115.263751,36.123357],"type":"Point"}
}