{
  "type": "Feature",
  "properties": {
    "iso:country":"US",
    "sg:address":"2260 Duneville St",
    "sg:city":"Las Vegas",
    "sg:classifiers":[
        {
            "category":"Professional",
            "subcategory":"Business Services",
            "type":"Services"
        }
    ],
    "sg:phone":"+1 702 368 4900",
    "sg:postcode":"89146",
    "sg:province":"NV",
    "sg:tags":[
        "environmental",
        "engineering"
    ],
    "wof:name":"Tesoros Corporation",
    "wof:placetype":"venue"
},
  "geometry": {"coordinates":[-115.220994,36.147578],"type":"Point"}
}