{
  "type": "Feature",
  "properties": {
    "iso:country":"US",
    "sg:address":"1731 Westwood Dr",
    "sg:city":"Minden",
    "sg:classifiers":[
        {
            "category":"Shopping",
            "subcategory":"Crafts & Fabrics",
            "type":"Retail Goods"
        }
    ],
    "sg:phone":"+1 775 782 6179",
    "sg:postcode":"89423",
    "sg:province":"NV",
    "sg:tags":[
        "material",
        "quilting",
        "supply"
    ],
    "wof:name":"TRS Designs",
    "wof:placetype":"venue"
},
  "geometry": {"coordinates":[-119.78634,38.960211],"type":"Point"}
}