{
  "type": "Feature",
  "properties": {
    "iso:country":"US",
    "sg:address":"26 W Horizon Ridge Parkway",
    "sg:city":"Henderson",
    "sg:classifiers":[
        {
            "category":"Restaurant",
            "type":"Food & Drink"
        }
    ],
    "sg:phone":"+1 702 382 9300",
    "sg:postcode":"89012",
    "sg:province":"NV",
    "wof:name":"Jack In the Box",
    "wof:placetype":"venue"
},
  "geometry": {"coordinates":[-114.992751,36.01191],"type":"Point"}
}