{
  "type": "Feature",
  "properties": {
    "iso:country":"US",
    "sg:address":"2246 Portabello Rd",
    "sg:city":"Las Vegas",
    "sg:classifiers":[
        {
            "category":"Professional",
            "type":"Services"
        }
    ],
    "sg:phone":"+1 702 433 0719",
    "sg:postcode":"89119",
    "sg:province":"NV",
    "sg:tags":[
        "product",
        "mfg",
        "cosmetic",
        "an",
        "hair",
        "cleaning"
    ],
    "wof:name":"Nevacal",
    "wof:placetype":"venue"
},
  "geometry": {"coordinates":[-115.122402,36.117065],"type":"Point"}
}