{
  "type": "Feature",
  "properties": {
    "iso:country":"US",
    "sg:address":"5420 Spring Mountain Rd",
    "sg:city":"Las Vegas",
    "sg:classifiers":[
        {
            "category":"Retail",
            "subcategory":"Auto Repair",
            "type":"Services"
        }
    ],
    "sg:phone":"+1 702 871 3350",
    "sg:postcode":"89146",
    "sg:province":"NV",
    "sg:tags":[
        "muffler",
        "exhaust",
        "system"
    ],
    "wof:name":"Midas Auto Svc Experts",
    "wof:placetype":"venue"
},
  "geometry": {"coordinates":[-115.213831,36.126082],"type":"Point"}
}