{
  "type": "Feature",
  "properties": {
    "iso:country":"US",
    "sg:address":"1104 James St",
    "sg:city":"Las Vegas",
    "sg:classifiers":[
        {
            "category":"Building & Trades",
            "subcategory":"Landscaping Services",
            "type":"Services"
        }
    ],
    "sg:phone":"+1 702 396 4303",
    "sg:postcode":"89101",
    "sg:province":"NV",
    "sg:tags":[
        "landscape",
        "contractor"
    ],
    "wof:name":"Tree Experts Of Las Vegas",
    "wof:placetype":"venue"
},
  "geometry": {"coordinates":[-115.106252,36.184661],"type":"Point"}
}