{
  "type": "Feature",
  "properties": {
    "iso:country":"US",
    "sg:address":"2470 N Decatur Blvd",
    "sg:city":"Las Vegas",
    "sg:classifiers":[
        {
            "category":"Airport",
            "type":"Transportation"
        }
    ],
    "sg:phone":"+1 702 647 2235",
    "sg:postcode":"89108",
    "sg:province":"NV",
    "sg:tags":[
        "aircraft",
        "maintenance"
    ],
    "wof:name":"Elite Aero",
    "wof:placetype":"venue"
},
  "geometry": {"coordinates":[-115.20568400000001,36.203626],"type":"Point"}
}