{
  "type": "Feature",
  "properties": {
    "iso:country":"US",
    "sg:address":"2801 Belmont Dr",
    "sg:city":"Henderson",
    "sg:classifiers":[
        {
            "category":"Wholesale",
            "subcategory":"Farm Supplies",
            "type":"Manufacturing & Wholesale Goods"
        }
    ],
    "sg:phone":"+1 702 897 1617",
    "sg:postcode":"89074",
    "sg:province":"NV",
    "sg:tags":[
        "fertilizer",
        "equipment",
        "plant"
    ],
    "wof:name":"Automated Fertilizing Systems",
    "wof:placetype":"venue"
},
  "geometry": {"coordinates":[-115.107436,36.019562],"type":"Point"}
}