{
  "type": "Feature",
  "properties": {
    "iso:country":"US",
    "sg:address":"830 Meadow Springs Dr",
    "sg:city":"Reno",
    "sg:classifiers":[
        {
            "category":"Education",
            "subcategory":"College",
            "type":"Public Place"
        }
    ],
    "sg:phone":"+1 775 784 6682",
    "sg:postcode":"89509",
    "sg:province":"NV",
    "wof:name":"Howard Rosenberg PC",
    "wof:placetype":"venue"
},
  "geometry": {"coordinates":[-119.806038,39.482163],"type":"Point"}
}