{
  "type": "Feature",
  "properties": {
    "iso:country":"US",
    "sg:address":"395 Freeport Blvd",
    "sg:city":"Sparks",
    "sg:classifiers":[
        {
            "category":"Professional",
            "subcategory":"Advertising",
            "type":"Services"
        }
    ],
    "sg:phone":"+1 775 358 7865",
    "sg:postcode":"89431",
    "sg:province":"NV",
    "wof:name":"Sticker Guy",
    "wof:placetype":"venue"
},
  "geometry": {"coordinates":[-119.744465,39.525505],"type":"Point"}
}