{
  "type": "Feature",
  "properties": {
    "iso:country":"US",
    "sg:address":"1280 E Silverado Ranch Blvd",
    "sg:city":"Las Vegas",
    "sg:classifiers":[
        {
            "category":"Autos & Motor Vehicles",
            "subcategory":"Auto Supplies",
            "type":"Retail Goods"
        },
        {
            "category":"Retail",
            "subcategory":"Auto Repair",
            "type":"Services"
        }
    ],
    "sg:phone":"+1 702 368 6900",
    "sg:postcode":"89183",
    "sg:province":"NV",
    "sg:tags":[
        "tire"
    ],
    "sg:website":"www.tireworkstcc.com",
    "wof:name":"Tire Works Total Car Care",
    "wof:placetype":"venue"
},
  "geometry": {"coordinates":[-115.135752,36.013363],"type":"Point"}
}