{
  "type": "Feature",
  "properties": {
    "iso:country":"US",
    "sg:address":"6255 S Mojave Rd",
    "sg:city":"Las Vegas",
    "sg:classifiers":[
        {
            "category":"Recreation",
            "subcategory":"Amusement Park",
            "type":"Entertainment"
        }
    ],
    "sg:phone":"+1 702 454 2399",
    "sg:postcode":"89120",
    "sg:province":"NV",
    "sg:tags":[
        "park"
    ],
    "wof:name":"Coney Island Emporium",
    "wof:placetype":"venue"
},
  "geometry": {"coordinates":[-115.105459,36.07574],"type":"Point"}
}