{
  "type": "Feature",
  "properties": {
    "iso:country":"US",
    "sg:address":"3050 Blue Spruce Rd",
    "sg:city":"Reno",
    "sg:classifiers":[
        {
            "category":"Professional",
            "subcategory":"Management & Consulting",
            "type":"Services"
        }
    ],
    "sg:phone":"+1 775 849 9101",
    "sg:postcode":"89511",
    "sg:province":"NV",
    "sg:tags":[
        "business"
    ],
    "wof:name":"Ybs Inc",
    "wof:placetype":"venue"
},
  "geometry": {"coordinates":[-119.85244,39.356479],"type":"Point"}
}