{
  "type": "Feature",
  "properties": {
    "iso:country":"US",
    "sg:address":"2291 S Fort Apache Rd",
    "sg:city":"Las Vegas",
    "sg:classifiers":[
        {
            "category":"Health Services",
            "subcategory":"Doctor",
            "type":"Services"
        }
    ],
    "sg:phone":"+1 702 732 8800",
    "sg:postcode":"89117",
    "sg:province":"NV",
    "sg:tags":[
        "dentist"
    ],
    "wof:name":"John Doung LTD",
    "wof:placetype":"venue"
},
  "geometry": {"coordinates":[-115.297021,36.148708],"type":"Point"}
}