{
  "type": "Feature",
  "properties": {
    "iso:country":"US",
    "sg:address":"3726 Funston Way",
    "sg:city":"Las Vegas",
    "sg:classifiers":[
        {
            "category":"Building & Trades",
            "subcategory":"Landscaping Services",
            "type":"Services"
        }
    ],
    "sg:phone":"+1 702 644 5263",
    "sg:postcode":"89129",
    "sg:province":"NV",
    "sg:tags":[
        "landscape",
        "contractor"
    ],
    "wof:name":"Bella Terra Inc",
    "wof:placetype":"venue"
},
  "geometry": {"coordinates":[-115.26917,36.227281],"type":"Point"}
}