{
  "type": "Feature",
  "properties": {
    "iso:country":"US",
    "sg:address":"2061 Losee Rd",
    "sg:city":"North Las Vegas",
    "sg:classifiers":[
        {
            "category":"Freight",
            "type":"Transportation"
        }
    ],
    "sg:phone":"+1 702 321 0953",
    "sg:postcode":"89030",
    "sg:province":"NV",
    "sg:tags":[
        "mover"
    ],
    "wof:name":"A-Able Move",
    "wof:placetype":"venue"
},
  "geometry": {"coordinates":[-115.141587,36.198142],"type":"Point"}
}