{
  "type": "Feature",
  "properties": {
    "iso:country":"US",
    "sg:address":"1401 Arville St Ste H",
    "sg:city":"Las Vegas",
    "sg:classifiers":[
        {
            "category":"Real Estate",
            "subcategory":"Real Estate Services",
            "type":"Services"
        }
    ],
    "sg:phone":"+1 702 386 9009",
    "sg:postcode":"89102",
    "sg:province":"NV",
    "wof:name":"Shaffer Realty Inc",
    "wof:placetype":"venue"
},
  "geometry": {"coordinates":[-115.199158,36.156159],"type":"Point"}
}