{
  "type": "Feature",
  "properties": {
    "iso:country":"US",
    "sg:address":"6055 E Lake Mead Boulevard",
    "sg:city":"Las Vegas",
    "sg:classifiers":[
        {
            "category":"Arena",
            "subcategory":"Sports Club",
            "type":"Entertainment"
        }
    ],
    "sg:phone":"+1 702 452 7100",
    "sg:postcode":"89156",
    "sg:province":"NV",
    "sg:tags":[
        "martial art"
    ],
    "wof:name":"Tiger Taekwon DO",
    "wof:placetype":"venue"
},
  "geometry": {"coordinates":[-115.040656,36.196045],"type":"Point"}
}