{
  "type": "Feature",
  "properties": {
    "iso:country":"US",
    "sg:address":"522 Bayberry Dr",
    "sg:city":"Las Vegas",
    "sg:classifiers":[
        {
            "category":"Food & Beverages",
            "subcategory":"Groceries & Convenience Stores",
            "type":"Retail Goods"
        }
    ],
    "sg:phone":"+1 702 431 5326",
    "sg:postcode":"89110",
    "sg:province":"NV",
    "sg:tags":[
        "grocer"
    ],
    "wof:name":"Rivas Produce",
    "wof:placetype":"venue"
},
  "geometry": {"coordinates":[-115.068457,36.172078],"type":"Point"}
}