{
  "type": "Feature",
  "properties": {
    "iso:country":"US",
    "sg:address":"5080 Bella Ct",
    "sg:city":"Reno",
    "sg:classifiers":[
        {
            "category":"Building & Trades",
            "subcategory":"Construction",
            "type":"Services"
        }
    ],
    "sg:phone":"+1 775 826 8285",
    "sg:postcode":"89509",
    "sg:province":"NV",
    "sg:tags":[
        "home",
        "builder"
    ],
    "wof:name":"Bel Sera",
    "wof:placetype":"venue"
},
  "geometry": {"coordinates":[-119.829688,39.476924],"type":"Point"}
}