{
  "type": "Feature",
  "properties": {
    "iso:country":"US",
    "sg:address":"5025 S Eastern Avenue",
    "sg:city":"Las Vegas",
    "sg:classifiers":[
        {
            "category":"Restaurant",
            "type":"Food & Drink"
        }
    ],
    "sg:phone":"+1 702 891 0119",
    "sg:postcode":"89119",
    "sg:province":"NV",
    "wof:name":"Putter's At Eastern",
    "wof:placetype":"venue"
},
  "geometry": {"coordinates":[-115.118887,36.097356],"type":"Point"}
}