{
  "type": "Feature",
  "properties": {
    "iso:country":"US",
    "sg:address":"7220 Brook Crest Ave",
    "sg:city":"Las Vegas",
    "sg:classifiers":[
        {
            "category":"Home & Garden",
            "subcategory":"Building Materials",
            "type":"Retail Goods"
        }
    ],
    "sg:phone":"+1 702 396 7135",
    "sg:postcode":"89131",
    "sg:province":"NV",
    "wof:name":"Visions Stained Glass",
    "wof:placetype":"venue"
},
  "geometry": {"coordinates":[-115.252081,36.294857],"type":"Point"}
}