{
  "type": "Feature",
  "properties": {
    "iso:country":"US",
    "sg:address":"4215 S Durango Dr",
    "sg:city":"Las Vegas",
    "sg:classifiers":[
        {
            "category":"Shopping",
            "subcategory":"Mobile Phones",
            "type":"Retail Goods"
        }
    ],
    "sg:phone":"+1 702 304 2355",
    "sg:postcode":"89147",
    "sg:province":"NV",
    "wof:name":"Cellsius",
    "wof:placetype":"venue"
},
  "geometry": {"coordinates":[-115.2792,36.112765],"type":"Point"}
}