{
  "type": "Feature",
  "properties": {
    "iso:country":"US",
    "sg:address":"335 Edison Way",
    "sg:city":"Reno",
    "sg:classifiers":[
        {
            "category":"Utilities",
            "subcategory":"Telephone",
            "type":"Services"
        }
    ],
    "sg:phone":"+1 775 284 9006",
    "sg:postcode":"89502",
    "sg:province":"NV",
    "sg:tags":[
        "provider"
    ],
    "wof:name":"R & N Cord Enterprises Inc",
    "wof:placetype":"venue"
},
  "geometry": {"coordinates":[-119.755239,39.507896],"type":"Point"}
}