{
  "type": "Feature",
  "properties": {
    "iso:country":"US",
    "sg:address":"355 Curnow Canyon Rd",
    "sg:city":"Reno",
    "sg:classifiers":[
        {
            "category":"Building & Trades",
            "subcategory":"Construction",
            "type":"Services"
        }
    ],
    "sg:phone":"+1 775 425 2757",
    "sg:postcode":"89510",
    "sg:province":"NV",
    "sg:tags":[
        "contractor"
    ],
    "wof:name":"Advanced Fencing LLC",
    "wof:placetype":"venue"
},
  "geometry": {"coordinates":[-119.651043,39.717354],"type":"Point"}
}