{
  "type": "Feature",
  "properties": {
    "iso:country":"US",
    "sg:address":"3973 S Mccarran Blvd",
    "sg:city":"Reno",
    "sg:classifiers":[
        {
            "category":"Professional",
            "subcategory":"Management & Consulting",
            "type":"Services"
        },
        {
            "category":"Professional",
            "subcategory":"Employment Agencies",
            "type":"Services"
        }
    ],
    "sg:phone":"+1 775 826 4442",
    "sg:postcode":"89502",
    "sg:province":"NV",
    "sg:tags":[
        "personnel",
        "consultant"
    ],
    "wof:name":"Express Employment Professionals",
    "wof:placetype":"venue"
},
  "geometry": {"coordinates":[-119.762715,39.476966],"type":"Point"}
}