{
  "type": "Feature",
  "properties": {
    "iso:country":"US",
    "sg:address":"1363 W Owens Ave",
    "sg:city":"Las Vegas",
    "sg:classifiers":[
        {
            "category":"Shopping",
            "subcategory":"Clothing, Apparel, & Fashions",
            "type":"Retail Goods"
        }
    ],
    "sg:phone":"+1 702 631 6130",
    "sg:postcode":"89106",
    "sg:province":"NV",
    "wof:name":"Lord & Wolfe Fashions",
    "wof:placetype":"venue"
},
  "geometry": {"coordinates":[-115.157739,36.188357],"type":"Point"}
}