{
  "type": "Feature",
  "properties": {
    "iso:country":"US",
    "sg:address":"1016 Robin St",
    "sg:city":"Las Vegas",
    "sg:classifiers":[
        {
            "category":"Building & Trades",
            "subcategory":"Cleaning & Sanitation",
            "type":"Services"
        }
    ],
    "sg:phone":"+1 702 339 8727",
    "sg:postcode":"89106",
    "sg:province":"NV",
    "sg:tags":[
        "maintenance"
    ],
    "wof:name":"Golden House Cleaning",
    "wof:placetype":"venue"
},
  "geometry": {"coordinates":[-115.174335,36.183792],"type":"Point"}
}