{
  "type": "Feature",
  "properties": {
    "iso:country":"US",
    "sg:address":"Planet Hollywood 3667 Las Vegas Blvd S",
    "sg:city":"Las Vegas",
    "sg:classifiers":[
        {
            "category":"Restaurant",
            "type":"Food & Drink"
        }
    ],
    "sg:phone":"+1 702 785 9005",
    "sg:postcode":"89109",
    "sg:province":"NV",
    "sg:tags":[
        "breakfast",
        "brunch",
        "buffet"
    ],
    "sg:website":"www.planethollywoodresort.com/di...",
    "wof:name":"The Spice Market Buffet",
    "wof:placetype":"venue"
},
  "geometry": {"coordinates":[-115.17282,36.11077],"type":"Point"}
}