{
  "type": "Feature",
  "properties": {
    "iso:country":"US",
    "sg:address":"6504 Smokey Pine Way",
    "sg:city":"Las Vegas",
    "sg:classifiers":[
        {
            "category":"Retail",
            "subcategory":"Animal Services",
            "type":"Services"
        }
    ],
    "sg:phone":"+1 702 384 3647",
    "sg:postcode":"89108",
    "sg:province":"NV",
    "sg:tags":[
        "training",
        "dog"
    ],
    "wof:name":"Diamond K-9 Training",
    "wof:placetype":"venue"
},
  "geometry": {"coordinates":[-115.23566,36.202978],"type":"Point"}
}