{
  "type": "Feature",
  "properties": {
    "iso:country":"US",
    "sg:address":"6000 S. Eastern Suite 9A",
    "sg:city":"Las Vegas",
    "sg:classifiers":[
        {
            "category":"Personal",
            "subcategory":"Adult",
            "type":"Services"
        }
    ],
    "sg:phone":"+1 702 795 2500",
    "sg:postcode":"89123",
    "sg:province":"NV",
    "sg:tags":[
        "midwife"
    ],
    "sg:website":"wellroundedmomma.com/Home_Page.html",
    "wof:name":"Well Rounded Momma",
    "wof:placetype":"venue"
},
  "geometry": {"coordinates":[-115.117561,36.080357],"type":"Point"}
}