{
  "type": "Feature",
  "properties": {
    "iso:country":"US",
    "sg:address":"4775 McLeod Dr",
    "sg:city":"Las Vegas",
    "sg:classifiers":[
        {
            "category":"Retail",
            "subcategory":"Event Space",
            "type":"Services"
        },
        {
            "category":"Park",
            "type":"Public Place"
        },
        {
            "category":"Recreation",
            "subcategory":"Playground",
            "type":"Entertainment"
        }
    ],
    "sg:phone":"+1 702 455 7513",
    "sg:postcode":"89121",
    "sg:province":"NV",
    "sg:tags":[
        "venue"
    ],
    "wof:name":"Paradise Park",
    "wof:placetype":"venue"
},
  "geometry": {"coordinates":[-115.109955,36.102287],"type":"Point"}
}