{
  "type": "Feature",
  "properties": {
    "iso:country":"US",
    "sg:address":"The Crystals 3780 S Las Vegas Blvd",
    "sg:city":"Las Vegas",
    "sg:classifiers":[
        {
            "category":"Shopping",
            "subcategory":"Clothing, Apparel, & Fashions",
            "type":"Retail Goods"
        }
    ],
    "sg:phone":"+1 702 262 9671",
    "sg:postcode":"89115",
    "sg:province":"NV",
    "sg:tags":[
        "clothing",
        "women's"
    ],
    "sg:website":"www.emiliopucci.com",
    "wof:name":"Emilio Pucci",
    "wof:placetype":"venue"
},
  "geometry": {"coordinates":[-115.173604,36.103523],"type":"Point"}
}