{
  "type": "Feature",
  "properties": {
    "iso:country":"US",
    "sg:address":"965 Parkview Dr",
    "sg:city":"Carson City",
    "sg:classifiers":[
        {
            "category":"Education",
            "subcategory":"School",
            "type":"Public Place"
        }
    ],
    "sg:phone":"+1 775 267 4528",
    "sg:postcode":"89705",
    "sg:province":"NV",
    "sg:tags":[
        "real estate"
    ],
    "wof:name":"Neibaur & Neibaur",
    "wof:placetype":"venue"
},
  "geometry": {"coordinates":[-119.771726,39.08913],"type":"Point"}
}