{
  "type": "Feature",
  "properties": {
    "iso:country":"US",
    "sg:address":"85 Washington St",
    "sg:city":"Reno",
    "sg:classifiers":[
        {
            "category":"Personal",
            "type":"Services"
        }
    ],
    "sg:phone":"+1 775 786 8100",
    "sg:postcode":"89503",
    "sg:province":"NV",
    "sg:tags":[
        "therapist",
        "massage"
    ],
    "wof:name":"VI Cardinalli",
    "wof:placetype":"venue"
},
  "geometry": {"coordinates":[-119.82186,39.522975],"type":"Point"}
}