{
  "type": "Feature",
  "properties": {
    "iso:country":"US",
    "sg:address":"2810 W Charleston Blvd",
    "sg:city":"Las Vegas",
    "sg:classifiers":[
        {
            "category":"Professional",
            "subcategory":"Business Services",
            "type":"Services"
        }
    ],
    "sg:phone":"+1 702 259 5500",
    "sg:postcode":"89102",
    "sg:province":"NV",
    "sg:tags":[
        "television",
        "co",
        "trade"
    ],
    "wof:name":"On-Line Cable Services Inc",
    "wof:placetype":"venue"
},
  "geometry": {"coordinates":[-115.183272,36.159028],"type":"Point"}
}