{
  "type": "Feature",
  "properties": {
    "iso:country":"US",
    "sg:address":"1022 Nevada Hwy",
    "sg:city":"Boulder City",
    "sg:classifiers":[
        {
            "category":"Professional",
            "subcategory":"Business Services",
            "type":"Services"
        }
    ],
    "sg:phone":"+1 702 293 7043",
    "sg:postcode":"89005",
    "sg:province":"NV",
    "sg:tags":[
        "packaging"
    ],
    "wof:name":"Postnet",
    "wof:placetype":"venue"
},
  "geometry": {"coordinates":[-114.844742,35.974663],"type":"Point"}
}