{
  "type": "Feature",
  "properties": {
    "iso:country":"US",
    "sg:address":"16560 Wedge Pkwy",
    "sg:city":"Reno",
    "sg:classifiers":[
        {
            "category":"Retail",
            "subcategory":"Veterinary Services",
            "type":"Services"
        }
    ],
    "sg:phone":"+1 775 853 8550",
    "sg:postcode":"89511",
    "sg:province":"NV",
    "sg:tags":[
        "clinic",
        "veterinarian",
        "hospital"
    ],
    "sg:website":"http://www.mountrosevets.com",
    "wof:name":"Mount Rose Animal Hospital",
    "wof:placetype":"venue"
},
  "geometry": {"coordinates":[-119.763329,39.400527],"type":"Point"}
}