{
  "type": "Feature",
  "properties": {
    "iso:country":"US",
    "sg:address":"9341 Dancing Daffodil Ave",
    "sg:city":"Las Vegas",
    "sg:classifiers":[
        {
            "category":"Building & Trades",
            "subcategory":"Plumbing",
            "type":"Services"
        }
    ],
    "sg:phone":"+1 702 243 4581",
    "sg:postcode":"89129",
    "sg:province":"NV",
    "sg:tags":[
        "fire",
        "design",
        "sprinkler",
        "system"
    ],
    "wof:name":"Fire Sprinkler Cad",
    "wof:placetype":"venue"
},
  "geometry": {"coordinates":[-115.299464,36.22486],"type":"Point"}
}