{
  "type": "Feature",
  "properties": {
    "iso:country":"US",
    "sg:address":"1705 Linn Ln",
    "sg:city":"Las Vegas",
    "sg:classifiers":[
        {
            "category":"Freight",
            "type":"Transportation"
        }
    ],
    "sg:phone":"+1 702 643 8389",
    "sg:postcode":"89156",
    "sg:province":"NV",
    "sg:tags":[
        "trucking"
    ],
    "wof:name":"Southwest Paving & Grading Inc",
    "wof:placetype":"venue"
},
  "geometry": {"coordinates":[-115.048336,36.189796],"type":"Point"}
}