{
  "type": "Feature",
  "properties": {
    "iso:country":"US",
    "sg:address":"1710 Mountain City Hwy",
    "sg:city":"Elko",
    "sg:classifiers":[
        {
            "category":"Autos & Motor Vehicles",
            "subcategory":"Auto Supplies",
            "type":"Retail Goods"
        },
        {
            "category":"Wholesale",
            "subcategory":"Auto Parts",
            "type":"Manufacturing & Wholesale Goods"
        }
    ],
    "sg:phone":"+1 775 777 3977",
    "sg:postcode":"89801",
    "sg:province":"NV",
    "sg:tags":[
        "body",
        "automobile",
        "truck",
        "equipment",
        "accessory"
    ],
    "sg:website":"http://www.oreillyauto.com?utm_source=yellowpages&utm_medium=iyp&utm_campaign=2804",
    "wof:name":"Checker O'Reilly Auto Parts",
    "wof:placetype":"venue"
},
  "geometry": {"coordinates":[-115.785776,40.832809],"type":"Point"}
}