{
  "type": "Feature",
  "properties": {
    "iso:country":"US",
    "sg:address":"3347 E Russell Rd",
    "sg:city":"Las Vegas",
    "sg:classifiers":[
        {
            "category":"Restaurant",
            "type":"Food & Drink"
        }
    ],
    "sg:phone":"+1 702 435 6873",
    "sg:postcode":"89120",
    "sg:province":"NV",
    "sg:tags":[
        "breakfast",
        "brunch"
    ],
    "wof:name":"Bagel Restaurant Cafe",
    "wof:placetype":"venue"
},
  "geometry": {"coordinates":[-115.102631,36.086163],"type":"Point"}
}