{
  "type": "Feature",
  "properties": {
    "iso:country":"US",
    "sg:address":"890 Fairbanks St",
    "sg:city":"Pahrump",
    "sg:classifiers":[
        {
            "category":"Building & Trades",
            "subcategory":"Plumbing",
            "type":"Services"
        }
    ],
    "sg:phone":"+1 775 727 7488",
    "sg:postcode":"89060",
    "sg:province":"NV",
    "sg:tags":[
        "conditioning",
        "air",
        "system",
        "contractor"
    ],
    "wof:name":"Pahrump Valley Air",
    "wof:placetype":"venue"
},
  "geometry": {"coordinates":[-116.02611899999999,36.224053],"type":"Point"}
}