{
  "type": "Feature",
  "properties": {
    "iso:country":"US",
    "sg:address":"1381 Romanesca Dr",
    "sg:city":"Henderson",
    "sg:classifiers":[
        {
            "category":"Wholesale",
            "subcategory":"Construction Materials",
            "type":"Manufacturing & Wholesale Goods"
        }
    ],
    "sg:phone":"+1 702 240 9836",
    "sg:postcode":"89052",
    "sg:province":"NV",
    "sg:tags":[
        "fence"
    ],
    "wof:name":"A Babyguard Of Nv LLC",
    "wof:placetype":"venue"
},
  "geometry": {"coordinates":[-115.081794,35.976491],"type":"Point"}
}