{
  "type": "Feature",
  "properties": {
    "iso:country":"US",
    "sg:address":"1105 Terminal Way",
    "sg:city":"Reno",
    "sg:classifiers":[
        {
            "category":"Professional",
            "subcategory":"Detective & Security Services",
            "type":"Services"
        }
    ],
    "sg:phone":"+1 775 322 7779",
    "sg:postcode":"89502",
    "sg:province":"NV",
    "sg:tags":[
        "car"
    ],
    "wof:name":"Analytical Polygraph Inc",
    "wof:placetype":"venue"
},
  "geometry": {"coordinates":[-119.77735,39.516148],"type":"Point"}
}