{
  "type": "Feature",
  "properties": {
    "iso:country":"US",
    "sg:address":"3375 Glen Ave",
    "sg:city":"Las Vegas",
    "sg:classifiers":[
        {
            "category":"Retail",
            "subcategory":"Auto Rental",
            "type":"Services"
        }
    ],
    "sg:phone":"+1 702 641 4839",
    "sg:postcode":"89121",
    "sg:province":"NV",
    "sg:tags":[
        "renting",
        "truck",
        "leasing"
    ],
    "wof:name":"U-Haul Co",
    "wof:placetype":"venue"
},
  "geometry": {"coordinates":[-115.102991,36.144594],"type":"Point"}
}