{
  "type": "Feature",
  "properties": {
    "iso:country":"US",
    "sg:address":"7662 W Lake Mead Blvd",
    "sg:city":"Las Vegas",
    "sg:classifiers":[
        {
            "category":"Restaurant",
            "type":"Food & Drink"
        }
    ],
    "sg:menulink":"http://www.allmenus.com/nv/las-vegas/196533-mcdonalds/menu/",
    "sg:postcode":"89128",
    "sg:province":"NV",
    "sg:tags":[
        "burger",
        "american"
    ],
    "wof:name":"McDonald's",
    "wof:placetype":"venue"
},
  "geometry": {"coordinates":[-115.26169400000001,36.196705],"type":"Point"}
}