{
  "type": "Feature",
  "properties": {
    "iso:country":"US",
    "sg:address":"711 Marks St",
    "sg:city":"Henderson",
    "sg:classifiers":[
        {
            "category":"Home & Garden",
            "subcategory":"Building Materials",
            "type":"Retail Goods"
        },
        {
            "category":"Building & Trades",
            "subcategory":"Construction",
            "type":"Services"
        }
    ],
    "sg:phone":"+1 702 365 7859",
    "sg:postcode":"89014",
    "sg:province":"NV",
    "sg:tags":[
        "tile",
        "dealer"
    ],
    "wof:name":"Tile Outlet",
    "wof:placetype":"venue"
},
  "geometry": {"coordinates":[-115.036369,36.067048],"type":"Point"}
}