{
  "type": "Feature",
  "properties": {
    "iso:country":"US",
    "sg:address":"10416 Timber Canyon Ave",
    "sg:city":"Las Vegas",
    "sg:classifiers":[
        {
            "category":"Retail",
            "subcategory":"Laundry & Dry Cleaning",
            "type":"Services"
        }
    ],
    "sg:phone":"+1 702 254 6387",
    "sg:postcode":"89129",
    "sg:province":"NV",
    "sg:tags":[
        "cleaners",
        "rug",
        "carpet"
    ],
    "wof:name":"All Pro Carpet Cleaning & Svc",
    "wof:placetype":"venue"
},
  "geometry": {"coordinates":[-115.322748,36.220479],"type":"Point"}
}