{
  "type": "Feature",
  "properties": {
    "iso:country":"US",
    "sg:address":"3250 W Idaho St",
    "sg:city":"Elko",
    "sg:classifiers":[
        {
            "category":"Professional",
            "subcategory":"Engineering",
            "type":"Services"
        }
    ],
    "sg:phone":"+1 775 738 1778",
    "sg:postcode":"89801",
    "sg:province":"NV",
    "wof:name":"Engineering Services LLC",
    "wof:placetype":"venue"
},
  "geometry": {"coordinates":[-115.80843400000001,40.816214],"type":"Point"}
}