{
  "type": "Feature",
  "properties": {
    "iso:country":"US",
    "sg:address":"45 Ryverson Ct",
    "sg:city":"Sparks",
    "sg:classifiers":[
        {
            "category":"Retail",
            "subcategory":"Repair Shop",
            "type":"Services"
        }
    ],
    "sg:phone":"+1 775 425 3333",
    "sg:postcode":"89441",
    "sg:province":"NV",
    "sg:tags":[
        "lock",
        "locksmith"
    ],
    "wof:name":"Pyramid Key Co",
    "wof:placetype":"venue"
},
  "geometry": {"coordinates":[-119.709356,39.646781],"type":"Point"}
}