{
  "type": "Feature",
  "properties": {
    "iso:country":"US",
    "sg:address":"333 N Rancho Dr",
    "sg:city":"Las Vegas",
    "sg:classifiers":[
        {
            "category":"Professional",
            "subcategory":"Lawyer & Legal Services",
            "type":"Services"
        }
    ],
    "sg:phone":"+1 702 631 0031",
    "sg:postcode":"89106",
    "sg:province":"NV",
    "sg:tags":[
        "attorney"
    ],
    "wof:name":"James J Ream Law Office",
    "wof:placetype":"venue"
},
  "geometry": {"coordinates":[-115.174905,36.176152],"type":"Point"}
}