{
  "type": "Feature",
  "properties": {
    "iso:country":"US",
    "sg:address":"7158 Sixshooter Dr",
    "sg:city":"Las Vegas",
    "sg:classifiers":[
        {
            "category":"Building & Trades",
            "subcategory":"Construction",
            "type":"Services"
        }
    ],
    "sg:phone":"+1 702 914 8780",
    "sg:postcode":"89119",
    "sg:province":"NV",
    "sg:tags":[
        "roofing"
    ],
    "wof:name":"Southwest Roofing",
    "wof:placetype":"venue"
},
  "geometry": {"coordinates":[-115.13292800000001,36.059816],"type":"Point"}
}