{
  "type": "Feature",
  "properties": {
    "iso:country":"US",
    "sg:address":"709 E Robinson St",
    "sg:city":"Carson City",
    "sg:classifiers":[
        {
            "category":"Organizations",
            "subcategory":"Labor Organization",
            "type":"Services"
        }
    ],
    "sg:phone":"+1 775 882 3910",
    "sg:postcode":"89701",
    "sg:province":"NV",
    "sg:website":"www.snea.org",
    "wof:name":"State Of Nevada Employees Assn",
    "wof:placetype":"venue"
},
  "geometry": {"coordinates":[-119.761155,39.167066],"type":"Point"}
}