{
  "type": "Feature",
  "properties": {
    "iso:country":"US",
    "sg:address":"8084 W Sahara Ave",
    "sg:city":"Las Vegas",
    "sg:classifiers":[
        {
            "category":"Health Services",
            "subcategory":"Chiropractor",
            "type":"Services"
        }
    ],
    "sg:phone":"+1 702 233 3366",
    "sg:postcode":"89117",
    "sg:province":"NV",
    "wof:name":"Maria A Giacalone",
    "wof:placetype":"venue"
},
  "geometry": {"coordinates":[-115.265994,36.143871],"type":"Point"}
}