{
  "type": "Feature",
  "properties": {
    "iso:country":"US",
    "sg:address":"527 Fairview Dr",
    "sg:city":"Carson City",
    "sg:classifiers":[
        {
            "category":"Home & Garden",
            "subcategory":"Household Appliances",
            "type":"Retail Goods"
        }
    ],
    "sg:phone":"+1 775 882 3551",
    "sg:postcode":"89701",
    "sg:province":"NV",
    "sg:tags":[
        "equipment",
        "fixture",
        "lighting"
    ],
    "wof:name":"Capital Wholesale Electric",
    "wof:placetype":"venue"
},
  "geometry": {"coordinates":[-119.76300000000001,39.150002],"type":"Point"}
}