{
  "type": "Feature",
  "properties": {
    "iso:country":"US",
    "sg:address":"5790 Wynn Road",
    "sg:city":"Las Vegas",
    "sg:classifiers":[
        {
            "category":"Building & Trades",
            "subcategory":"Construction",
            "type":"Services"
        }
    ],
    "sg:phone":"+1 702 895 7672",
    "sg:postcode":"89118",
    "sg:province":"NV",
    "sg:tags":[
        "contractor"
    ],
    "wof:name":"Las Vegas Underground Construction",
    "wof:placetype":"venue"
},
  "geometry": {"coordinates":[-115.19446600000001,36.084555],"type":"Point"}
}