{
  "type": "Feature",
  "properties": {
    "iso:country":"US",
    "sg:address":"5053 Mount Pleasant Ln",
    "sg:city":"Las Vegas",
    "sg:classifiers":[
        {
            "category":"Professional",
            "subcategory":"Business Services",
            "type":"Services"
        }
    ],
    "sg:phone":"+1 702 438 6744",
    "sg:postcode":"89113",
    "sg:province":"NV",
    "wof:name":"Clair Enterprises LLC",
    "wof:placetype":"venue"
},
  "geometry": {"coordinates":[-115.277614,36.097576],"type":"Point"}
}