{
  "type": "Feature",
  "properties": {
    "iso:country":"US",
    "sg:address":"2562 Silver State Pkwy",
    "sg:city":"Minden",
    "sg:classifiers":[
        {
            "category":"Wholesale",
            "subcategory":"Durable Goods & Equipment",
            "type":"Manufacturing & Wholesale Goods"
        }
    ],
    "sg:phone":"+1 775 267 5959",
    "sg:postcode":"89423",
    "sg:province":"NV",
    "sg:tags":[
        "laser"
    ],
    "sg:website":"www.intelite.com",
    "wof:name":"Intelite",
    "wof:placetype":"venue"
},
  "geometry": {"coordinates":[-119.75129099999999,39.024179],"type":"Point"}
}