{
  "type": "Feature",
  "properties": {
    "iso:country":"US",
    "sg:address":"4985 W Tropicana Ave",
    "sg:city":"Las Vegas",
    "sg:classifiers":[
        {
            "category":"Restaurant",
            "type":"Food & Drink"
        }
    ],
    "sg:menulink":"http://www.allmenus.com/nv/las-vegas/122975-quiznos-sub/menu/",
    "sg:phone":"+1 702 889 4441",
    "sg:postcode":"89103",
    "sg:province":"NV",
    "sg:tags":[
        "wrap",
        "american",
        "sandwich"
    ],
    "wof:name":"Quiznos Sub",
    "wof:placetype":"venue"
},
  "geometry": {"coordinates":[-115.20900899999999,36.100808],"type":"Point"}
}