{
  "type": "Feature",
  "properties": {
    "iso:country":"US",
    "sg:address":"1443 Romanesca Dr",
    "sg:city":"Henderson",
    "sg:classifiers":[
        {
            "category":"Building & Trades",
            "subcategory":"Construction",
            "type":"Services"
        }
    ],
    "sg:phone":"+1 702 492 9927",
    "sg:postcode":"89052",
    "sg:province":"NV",
    "sg:tags":[
        "house"
    ],
    "wof:name":"Ko Construction Inc",
    "wof:placetype":"venue"
},
  "geometry": {"coordinates":[-115.078357,35.974585],"type":"Point"}
}