{
  "type": "Feature",
  "properties": {
    "iso:country":"US",
    "sg:address":"9550 W Sahara Ave",
    "sg:city":"Las Vegas",
    "sg:classifiers":[
        {
            "category":"Wholesale",
            "subcategory":"Electrical",
            "type":"Manufacturing & Wholesale Goods"
        }
    ],
    "sg:phone":"+1 702 562 7589",
    "sg:postcode":"89117",
    "sg:province":"NV",
    "sg:tags":[
        "control",
        "security",
        "system"
    ],
    "wof:name":"St George Security & Alarms",
    "wof:placetype":"venue"
},
  "geometry": {"coordinates":[-115.3065,36.144481],"type":"Point"}
}