{
  "type": "Feature",
  "properties": {
    "iso:country":"US",
    "sg:address":"675 Fairview Dr Ste 231",
    "sg:city":"Carson City",
    "sg:classifiers":[
        {
            "category":"Shopping",
            "subcategory":"Jewelry",
            "type":"Retail Goods"
        }
    ],
    "sg:phone":"+1 775 884 2000",
    "sg:postcode":"89701",
    "sg:province":"NV",
    "wof:name":"Carson-Tahoe Jewelers",
    "wof:placetype":"venue"
},
  "geometry": {"coordinates":[-119.761753,39.149776],"type":"Point"}
}