{
  "type": "Feature",
  "properties": {
    "iso:country":"US",
    "sg:address":"4005 W Dewey Dr",
    "sg:city":"Las Vegas",
    "sg:classifiers":[
        {
            "category":"Retail",
            "subcategory":"Auto Repair",
            "type":"Services"
        }
    ],
    "sg:phone":"+1 702 952 0056",
    "sg:postcode":"89118",
    "sg:province":"NV",
    "wof:name":"First Mercedes Benz & Bmw Service",
    "wof:placetype":"venue"
},
  "geometry": {"coordinates":[-115.194,36.088001],"type":"Point"}
}