{
  "type": "Feature",
  "properties": {
    "iso:country":"US",
    "sg:address":"2470 E Tropicana Ave Ste B",
    "sg:city":"Las Vegas",
    "sg:classifiers":[
        {
            "category":"Shopping",
            "subcategory":"Mobile Phones",
            "type":"Retail Goods"
        }
    ],
    "sg:phone":"+1 702 450 3691",
    "sg:postcode":"89121",
    "sg:province":"NV",
    "sg:website":"www.cingular.com",
    "wof:name":"Cingular Wireless",
    "wof:placetype":"venue"
},
  "geometry": {"coordinates":[-115.117254,36.100146],"type":"Point"}
}