{
  "type": "Feature",
  "properties": {
    "iso:country":"US",
    "sg:address":"4535 W Russell Rd",
    "sg:city":"Las Vegas",
    "sg:classifiers":[
        {
            "category":"Freight",
            "type":"Transportation"
        }
    ],
    "sg:phone":"+1 702 642 1959",
    "sg:postcode":"89118",
    "sg:province":"NV",
    "sg:tags":[
        "operator",
        "hauling",
        "trucking"
    ],
    "wof:name":"M & B Transportation",
    "wof:placetype":"venue"
},
  "geometry": {"coordinates":[-115.203109,36.086265],"type":"Point"}
}