{
  "type": "Feature",
  "properties": {
    "iso:country":"US",
    "sg:address":"294 E Moana Ln Ste 1",
    "sg:city":"Reno",
    "sg:classifiers":[
        {
            "category":"Restaurant",
            "type":"Food & Drink"
        }
    ],
    "sg:menulink":"http://www.allmenus.com/nv/reno-southeast/283503-sushi-club/menu/",
    "sg:phone":"+1 775 828 7311",
    "sg:postcode":"89502",
    "sg:province":"NV",
    "sg:tags":[
        "sushi",
        "japanese",
        "asian"
    ],
    "wof:name":"Sushi Club",
    "wof:placetype":"venue"
},
  "geometry": {"coordinates":[-119.796277,39.491584],"type":"Point"}
}