{
  "type": "Feature",
  "properties": {
    "iso:country":"US",
    "sg:address":"71 N East St",
    "sg:city":"Fallon",
    "sg:classifiers":[
        {
            "category":"Retail",
            "subcategory":"Auto Repair",
            "type":"Services"
        }
    ],
    "sg:phone":"+1 775 423 6600",
    "sg:postcode":"89406",
    "sg:province":"NV",
    "sg:tags":[
        "general"
    ],
    "wof:name":"Mikes Auto Repair",
    "wof:placetype":"venue"
},
  "geometry": {"coordinates":[-118.772817,39.474946],"type":"Point"}
}