{
  "type": "Feature",
  "properties": {
    "iso:country":"US",
    "sg:address":"333 Glendale Ave",
    "sg:city":"Sparks",
    "sg:classifiers":[
        {
            "category":"Home & Garden",
            "subcategory":"Building Materials",
            "type":"Retail Goods"
        }
    ],
    "sg:phone":"+1 775 358 9900",
    "sg:postcode":"89431",
    "sg:province":"NV",
    "wof:name":"High Sierra Lumber",
    "wof:placetype":"venue"
},
  "geometry": {"coordinates":[-119.748334,39.527332],"type":"Point"}
}