{
  "type": "Feature",
  "properties": {
    "iso:country":"US",
    "sg:address":"2549 Thornview St",
    "sg:city":"Las Vegas",
    "sg:classifiers":[
        {
            "category":"Professional",
            "subcategory":"Computer Services",
            "type":"Services"
        }
    ],
    "sg:phone":"+1 702 636 7600",
    "sg:postcode":"89135",
    "sg:province":"NV",
    "sg:tags":[
        "marketing",
        "software"
    ],
    "wof:name":"MSP",
    "wof:placetype":"venue"
},
  "geometry": {"coordinates":[-115.329091,36.141535],"type":"Point"}
}