{
  "type": "Feature",
  "properties": {
    "iso:country":"US",
    "sg:address":"2214 Paradise Rd",
    "sg:city":"Las Vegas",
    "sg:classifiers":[
        {
            "category":"Shopping",
            "subcategory":"Gifts & Souvenirs",
            "type":"Retail Goods"
        }
    ],
    "sg:phone":"+1 702 893 6665",
    "sg:postcode":"89104",
    "sg:province":"NV",
    "sg:tags":[
        "collectible"
    ],
    "wof:name":"A Sarno's Sport Cards",
    "wof:placetype":"venue"
},
  "geometry": {"coordinates":[-115.153665,36.145757],"type":"Point"}
}