{
  "type": "Feature",
  "properties": {
    "iso:country":"US",
    "sg:address":"460 Emerson Way",
    "sg:city":"Sparks",
    "sg:classifiers":[
        {
            "category":"Professional",
            "subcategory":"Accounting & Tax Preparation",
            "type":"Services"
        }
    ],
    "sg:phone":"+1 775 828 1113",
    "sg:postcode":"89431",
    "sg:province":"NV",
    "sg:tags":[
        "bookkeeping",
        "general"
    ],
    "wof:name":"Affordable Business Svc",
    "wof:placetype":"venue"
},
  "geometry": {"coordinates":[-119.750463,39.558318],"type":"Point"}
}