{
  "type": "Feature",
  "properties": {
    "iso:country":"US",
    "sg:address":"2112 Bay Hill Dr",
    "sg:city":"Las Vegas",
    "sg:classifiers":[
        {
            "category":"Professional",
            "type":"Services"
        }
    ],
    "sg:phone":"+1 702 821 1062",
    "sg:postcode":"89117",
    "sg:province":"NV",
    "sg:tags":[
        "establishment"
    ],
    "wof:name":"Neil J Mullins Jr LTD",
    "wof:placetype":"venue"
},
  "geometry": {"coordinates":[-115.295485,36.149833],"type":"Point"}
}