{
  "type": "Feature",
  "properties": {
    "iso:country":"US",
    "sg:address":"3645 Las Vegas Blvd S",
    "sg:city":"Las Vegas",
    "sg:classifiers":[
        {
            "category":"Restaurant",
            "type":"Food & Drink"
        }
    ],
    "sg:phone":"+1 702 891 8626",
    "sg:postcode":"89109",
    "sg:province":"NV",
    "sg:tags":[
        "sushi",
        "bar",
        "japanese"
    ],
    "wof:name":"Ichiban Sushi",
    "wof:placetype":"venue"
},
  "geometry": {"coordinates":[-115.172997,36.111599],"type":"Point"}
}