{
  "type": "Feature",
  "properties": {
    "iso:country":"US",
    "sg:address":"3240 Arville St",
    "sg:city":"Las Vegas",
    "sg:classifiers":[
        {
            "category":"Retail",
            "subcategory":"Repair Shop",
            "type":"Services"
        }
    ],
    "sg:phone":"+1 702 880 7433",
    "sg:postcode":"89102",
    "sg:province":"NV",
    "sg:tags":[
        "scooter",
        "motorcycle",
        "motor"
    ],
    "wof:name":"West Side Cycles",
    "wof:placetype":"venue"
},
  "geometry": {"coordinates":[-115.199091,36.129999],"type":"Point"}
}