{
  "type": "Feature",
  "properties": {
    "iso:country":"US",
    "sg:address":"6280 S Valley View Boulevard",
    "sg:city":"Las Vegas",
    "sg:classifiers":[
        {
            "category":"Banks & Credit Unions",
            "subcategory":"Investment Brokerage",
            "type":"Services"
        }
    ],
    "sg:phone":"+1 702 452 4412",
    "sg:postcode":"89118",
    "sg:province":"NV",
    "sg:tags":[
        "investing"
    ],
    "wof:name":"Las Vegas Property Exchange",
    "wof:placetype":"venue"
},
  "geometry": {"coordinates":[-115.189945,36.075534],"type":"Point"}
}