{
  "type": "Feature",
  "properties": {
    "iso:country":"US",
    "sg:address":"770 E Warm Springs Rd",
    "sg:city":"Las Vegas",
    "sg:classifiers":[
        {
            "category":"Arts & Performance",
            "subcategory":"Theater",
            "type":"Entertainment"
        },
        {
            "category":"Professional",
            "subcategory":"Business Services",
            "type":"Services"
        }
    ],
    "sg:phone":"+1 702 260 8605",
    "sg:postcode":"89119",
    "sg:province":"NV",
    "sg:tags":[
        "tourism",
        "promoting",
        "ci",
        "organizing"
    ],
    "sg:website":"www.lasvegasevents.com",
    "wof:name":"Las Vegas Events Inc",
    "wof:placetype":"venue"
},
  "geometry": {"coordinates":[-115.146784,36.0572],"type":"Point"}
}