{
  "type": "Feature",
  "properties": {
    "iso:country":"US",
    "sg:address":"880 E Front St",
    "sg:city":"Fallon",
    "sg:classifiers":[
        {
            "category":"Wholesale",
            "subcategory":"Beer",
            "type":"Manufacturing & Wholesale Goods"
        }
    ],
    "sg:phone":"+1 775 423 3432",
    "sg:postcode":"89406",
    "sg:province":"NV",
    "sg:tags":[
        "water",
        "ale"
    ],
    "wof:name":"Valley Distributors Inc",
    "wof:placetype":"venue"
},
  "geometry": {"coordinates":[-118.765455,39.467536],"type":"Point"}
}