{
  "type": "Feature",
  "properties": {
    "iso:country":"US",
    "sg:address":"4440 E Tropicana Ave",
    "sg:city":"Las Vegas",
    "sg:classifiers":[
        {
            "category":"Shopping",
            "subcategory":"Clothing, Apparel, & Fashions",
            "type":"Retail Goods"
        }
    ],
    "sg:phone":"+1 702 433 9101",
    "sg:postcode":"89121",
    "sg:province":"NV",
    "sg:tags":[
        "furnishing"
    ],
    "wof:name":"Primero Choice",
    "wof:placetype":"venue"
},
  "geometry": {"coordinates":[-115.077708,36.100358],"type":"Point"}
}