{
  "type": "Feature",
  "properties": {
    "iso:country":"US",
    "sg:address":"8200 Bluff Creek Ave",
    "sg:city":"Las Vegas",
    "sg:classifiers":[
        {
            "category":"Building & Trades",
            "subcategory":"Landscaping Services",
            "type":"Services"
        }
    ],
    "sg:phone":"+1 702 396 7124",
    "sg:postcode":"89131",
    "sg:province":"NV",
    "sg:tags":[
        "lawn",
        "maintenance",
        "grounds"
    ],
    "wof:name":"Paloma Lawn Svc",
    "wof:placetype":"venue"
},
  "geometry": {"coordinates":[-115.275863,36.294819],"type":"Point"}
}