{
  "type": "Feature",
  "properties": {
    "iso:country":"US",
    "sg:address":"1200 S Rock Blvd",
    "sg:city":"Sparks",
    "sg:classifiers":[
        {
            "category":"Autos & Motor Vehicles",
            "subcategory":"Auto Supplies",
            "type":"Retail Goods"
        }
    ],
    "sg:phone":"+1 775 331 2271",
    "sg:postcode":"89431",
    "sg:province":"NV",
    "sg:tags":[
        "automobile",
        "stereo",
        "radio"
    ],
    "wof:name":"Dreamcar South",
    "wof:placetype":"venue"
},
  "geometry": {"coordinates":[-119.765456,39.521696],"type":"Point"}
}