{
  "type": "Feature",
  "properties": {
    "iso:country":"US",
    "sg:address":"4101 Caughlin Sq",
    "sg:city":"Reno",
    "sg:classifiers":[
        {
            "category":"Health Services",
            "subcategory":"Doctor",
            "type":"Services"
        }
    ],
    "sg:phone":"+1 775 827 5800",
    "sg:postcode":"89519",
    "sg:province":"NV",
    "sg:tags":[
        "physician",
        "surgeon"
    ],
    "wof:name":"Scott Boyden MD",
    "wof:placetype":"venue"
},
  "geometry": {"coordinates":[-119.853883,39.484277],"type":"Point"}
}