{
  "type": "Feature",
  "properties": {
    "iso:country":"US",
    "sg:address":"3058 E Sunset Rd",
    "sg:city":"Las Vegas",
    "sg:classifiers":[
        {
            "category":"Professional",
            "subcategory":"Business Services",
            "type":"Services"
        }
    ],
    "sg:phone":"+1 702 939 2712",
    "sg:postcode":"89120",
    "sg:province":"NV",
    "sg:tags":[
        "telemarketing"
    ],
    "sg:website":"www.spherion.com",
    "wof:name":"Interim CCS",
    "wof:placetype":"venue"
},
  "geometry": {"coordinates":[-115.10816699999999,36.071637],"type":"Point"}
}