{
  "type": "Feature",
  "properties": {
    "iso:country":"US",
    "sg:address":"9712 Blatimac Ave",
    "sg:city":"Las Vegas",
    "sg:classifiers":[
        {
            "category":"Insurance",
            "subcategory":"Insurance Agent",
            "type":"Services"
        }
    ],
    "sg:phone":"+1 702 360 6553",
    "sg:postcode":"89129",
    "sg:province":"NV",
    "wof:name":"Dewey Dwight Brown Insurance",
    "wof:placetype":"venue"
},
  "geometry": {"coordinates":[-115.308222,36.22191],"type":"Point"}
}