{
  "type": "Feature",
  "properties": {
    "iso:country":"US",
    "sg:address":"7452 Thornsby",
    "sg:city":"Las Vegas",
    "sg:classifiers":[
        {
            "category":"Retail",
            "subcategory":"Auto Repair",
            "type":"Services"
        }
    ],
    "sg:phone":"+1 702 220 4598",
    "sg:postcode":"89120",
    "sg:province":"NV",
    "sg:tags":[
        "repairing",
        "automobile"
    ],
    "wof:name":"Fix It Auto Repairs",
    "wof:placetype":"venue"
},
  "geometry": {"coordinates":[-115.103463,36.054132],"type":"Point"}
}