{
  "type": "Feature",
  "properties": {
    "iso:country":"US",
    "sg:address":"10013 Sail Landing Ct",
    "sg:city":"Las Vegas",
    "sg:classifiers":[
        {
            "category":"Professional",
            "type":"Services"
        }
    ],
    "sg:phone":"+1 702 224 0627",
    "sg:postcode":"89117",
    "sg:province":"NV",
    "wof:name":"Plantsrus",
    "wof:placetype":"venue"
},
  "geometry": {"coordinates":[-115.31463599999999,36.133783],"type":"Point"}
}