{
  "type": "Feature",
  "properties": {
    "iso:country":"US",
    "sg:address":"7501 W Lake Mead Blvd",
    "sg:city":"Las Vegas",
    "sg:classifiers":[
        {
            "category":"Health Services",
            "subcategory":"Doctor",
            "type":"Services"
        }
    ],
    "sg:phone":"+1 702 214 6343",
    "sg:postcode":"89128",
    "sg:province":"NV",
    "sg:tags":[
        "physician",
        "allergy"
    ],
    "wof:name":"Allergy Relief Specialists",
    "wof:placetype":"venue"
},
  "geometry": {"coordinates":[-115.254545,36.196014],"type":"Point"}
}