{
  "type": "Feature",
  "properties": {
    "iso:country":"US",
    "sg:address":"112 S Jones Boulevard",
    "sg:city":"Las Vegas",
    "sg:classifiers":[
        {
            "category":"Health Services",
            "subcategory":"Doctor",
            "type":"Services"
        },
        {
            "category":"Personal",
            "subcategory":"Day Spa",
            "type":"Services"
        }
    ],
    "sg:phone":"+1 702 838 4644",
    "sg:postcode":"89107",
    "sg:province":"NV",
    "sg:tags":[
        "dermatologist"
    ],
    "wof:name":"Advanced Skin & Laser Institute",
    "wof:placetype":"venue"
},
  "geometry": {"coordinates":[-115.22418,36.171935],"type":"Point"}
}