{
  "type": "Feature",
  "properties": {
    "iso:country":"US",
    "sg:address":"3093 S Valley View Blvd",
    "sg:city":"Las Vegas",
    "sg:classifiers":[
        {
            "category":"Retail",
            "subcategory":"Laundry & Dry Cleaning",
            "type":"Services"
        }
    ],
    "sg:phone":"+1 702 362 3677",
    "sg:postcode":"89102",
    "sg:province":"NV",
    "sg:website":"www.bigapplecleaners.com",
    "wof:name":"Big Apple Cleaners",
    "wof:placetype":"venue"
},
  "geometry": {"coordinates":[-115.190532,36.133969],"type":"Point"}
}