{
  "type": "Feature",
  "properties": {
    "iso:country":"US",
    "sg:address":"6975 Speedway Blvd",
    "sg:city":"Las Vegas",
    "sg:classifiers":[
        {
            "category":"Home & Garden",
            "subcategory":"Building Materials",
            "type":"Retail Goods"
        }
    ],
    "sg:phone":"+1 702 643 9494",
    "sg:postcode":"89115",
    "sg:province":"NV",
    "wof:name":"Champion Designs",
    "wof:placetype":"venue"
},
  "geometry": {"coordinates":[-115.020004,36.279195],"type":"Point"}
}