{
  "type": "Feature",
  "properties": {
    "iso:country":"US",
    "sg:address":"244 View Dr",
    "sg:city":"Las Vegas",
    "sg:classifiers":[
        {
            "category":"Building & Trades",
            "subcategory":"Landscaping Services",
            "type":"Services"
        }
    ],
    "sg:phone":"+1 702 657 8005",
    "sg:postcode":"89107",
    "sg:province":"NV",
    "sg:tags":[
        "landscape",
        "contractor"
    ],
    "wof:name":"Sun Valley Landscaping",
    "wof:placetype":"venue"
},
  "geometry": {"coordinates":[-115.219672,36.170675],"type":"Point"}
}