{
  "type": "Feature",
  "properties": {
    "iso:country":"US",
    "sg:address":"13900 Stead Blvd",
    "sg:city":"Reno",
    "sg:classifiers":[
        {
            "category":"Food & Beverages",
            "subcategory":"Groceries & Convenience Stores",
            "type":"Retail Goods"
        }
    ],
    "sg:phone":"+1 775 971 2781",
    "sg:postcode":"89506",
    "sg:province":"NV",
    "wof:name":"Winner's Corner Convenience",
    "wof:placetype":"venue"
},
  "geometry": {"coordinates":[-119.881664,39.642801],"type":"Point"}
}