{
  "type": "Feature",
  "properties": {
    "iso:country":"US",
    "sg:address":"520 Gentry Way",
    "sg:city":"Reno",
    "sg:classifiers":[
        {
            "category":"Real Estate",
            "subcategory":"Real Estate Operator",
            "type":"Services"
        }
    ],
    "sg:phone":"+1 775 825 0337",
    "sg:postcode":"89502",
    "sg:province":"NV",
    "sg:tags":[
        "mobile",
        "home",
        "community"
    ],
    "wof:name":"Bonanza Mobile Lodge",
    "wof:placetype":"venue"
},
  "geometry": {"coordinates":[-119.790467,39.494857],"type":"Point"}
}