{
  "type": "Feature",
  "properties": {
    "iso:country":"US",
    "sg:address":"7155 Bilpar Rd",
    "sg:city":"Las Vegas",
    "sg:classifiers":[
        {
            "category":"Building & Trades",
            "subcategory":"Construction",
            "type":"Services"
        }
    ],
    "sg:phone":"+1 702 645 5885",
    "sg:postcode":"89131",
    "sg:province":"NV",
    "sg:tags":[
        "heavy"
    ],
    "wof:name":"Osburn Construction",
    "wof:placetype":"venue"
},
  "geometry": {"coordinates":[-115.248408,36.277351],"type":"Point"}
}