{
  "type": "Feature",
  "properties": {
    "iso:country":"US",
    "sg:address":"1209 Aultman St",
    "sg:city":"Ely",
    "sg:classifiers":[
        {
            "category":"Retail",
            "subcategory":"Auto Repair",
            "type":"Services"
        }
    ],
    "sg:phone":"+1 775 289 4611",
    "sg:postcode":"89301",
    "sg:province":"NV",
    "sg:tags":[
        "repairing",
        "automobile",
        "radiator"
    ],
    "wof:name":"Birch Brothers Garage",
    "wof:placetype":"venue"
},
  "geometry": {"coordinates":[-114.885008,39.249105],"type":"Point"}
}