{
  "type": "Feature",
  "properties": {
    "iso:country":"US",
    "sg:address":"7340 Smoke Ranch Rd",
    "sg:city":"Las Vegas",
    "sg:classifiers":[
        {
            "category":"Home & Garden",
            "subcategory":"Furniture",
            "type":"Retail Goods"
        },
        {
            "category":"Wholesale",
            "subcategory":"Furniture",
            "type":"Manufacturing & Wholesale Goods"
        }
    ],
    "sg:phone":"+1 702 304 0909",
    "sg:postcode":"89128",
    "sg:province":"NV",
    "sg:tags":[
        "sales"
    ],
    "sg:website":"www.a-furnishings.com",
    "wof:name":"On The Web Marketing Group",
    "wof:placetype":"venue"
},
  "geometry": {"coordinates":[-115.25643599999999,36.203544],"type":"Point"}
}