{
  "type": "Feature",
  "properties": {
    "iso:country":"US",
    "sg:address":"2965 Vista Blvd",
    "sg:city":"Sparks",
    "sg:classifiers":[
        {
            "category":"Personal",
            "subcategory":"Beauty Salon",
            "type":"Services"
        }
    ],
    "sg:phone":"+1 775 626 5556",
    "sg:postcode":"89434",
    "sg:province":"NV",
    "wof:name":"Renee Cartinella",
    "wof:placetype":"venue"
},
  "geometry": {"coordinates":[-119.705646,39.557371],"type":"Point"}
}