{
  "type": "Feature",
  "properties": {
    "iso:country":"US",
    "sg:address":"1285 Financial Blvd",
    "sg:city":"Reno",
    "sg:classifiers":[
        {
            "category":"Shopping",
            "subcategory":"Computers & Home Electronics",
            "type":"Retail Goods"
        }
    ],
    "sg:phone":"+1 775 332 8800",
    "sg:postcode":"89502",
    "sg:province":"NV",
    "sg:tags":[
        "software"
    ],
    "sg:website":"www.qwikpayroll.com",
    "wof:name":"Intuit Payroll Svc",
    "wof:placetype":"venue"
},
  "geometry": {"coordinates":[-119.747911,39.509393],"type":"Point"}
}