{
  "type": "Feature",
  "properties": {
    "iso:country":"US",
    "sg:address":"731 Pilot Rd",
    "sg:city":"Las Vegas",
    "sg:classifiers":[
        {
            "category":"Manufacturing",
            "subcategory":"Electronics",
            "type":"Manufacturing & Wholesale Goods"
        }
    ],
    "sg:phone":"+1 702 897 9424",
    "sg:postcode":"89119",
    "sg:province":"NV",
    "sg:tags":[
        "communications",
        "security",
        "mfg",
        "electrical",
        "contractor"
    ],
    "wof:name":"Siemens Building Technologies",
    "wof:placetype":"venue"
},
  "geometry": {"coordinates":[-115.148798,36.06784],"type":"Point"}
}