{
  "type": "Feature",
  "properties": {
    "iso:country":"US",
    "sg:address":"7730 W Cheyenne Ave",
    "sg:city":"Las Vegas",
    "sg:classifiers":[
        {
            "category":"Health Services",
            "subcategory":"Health Practitioner",
            "type":"Services"
        }
    ],
    "sg:phone":"+1 702 655 8535",
    "sg:postcode":"89129",
    "sg:province":"NV",
    "sg:tags":[
        "therapist",
        "physical"
    ],
    "wof:name":"Sports",
    "wof:placetype":"venue"
},
  "geometry": {"coordinates":[-115.262407,36.218358],"type":"Point"}
}