{
  "type": "Feature",
  "properties": {
    "iso:country":"US",
    "sg:address":"1550 E College Pkwy",
    "sg:city":"Carson City",
    "sg:classifiers":[
        {
            "category":"Government",
            "subcategory":"Office",
            "type":"Public Place"
        }
    ],
    "sg:phone":"+1 775 687 4475",
    "sg:postcode":"89706",
    "sg:province":"NV",
    "sg:tags":[
        "state",
        "program"
    ],
    "wof:name":"Licensure & Certification Bur",
    "wof:placetype":"venue"
},
  "geometry": {"coordinates":[-119.748767,39.190098],"type":"Point"}
}