{
  "type": "Feature",
  "properties": {
    "iso:country":"US",
    "sg:address":"2200 Harvard Way",
    "sg:city":"Reno",
    "sg:classifiers":[
        {
            "category":"Health Services",
            "subcategory":"Optometrist",
            "type":"Services"
        }
    ],
    "sg:phone":"+1 775 827 3644",
    "sg:postcode":"89502",
    "sg:province":"NV",
    "wof:name":"Rick Winkelman Od",
    "wof:placetype":"venue"
},
  "geometry": {"coordinates":[-119.785793,39.501987],"type":"Point"}
}