{
  "type": "Feature",
  "properties": {
    "iso:country":"US",
    "sg:address":"3378 Kietzke Ln",
    "sg:city":"Reno",
    "sg:classifiers":[
        {
            "category":"Building & Trades",
            "subcategory":"Construction",
            "type":"Services"
        }
    ],
    "sg:phone":"+1 775 829 2411",
    "sg:postcode":"89502",
    "sg:province":"NV",
    "sg:tags":[
        "contractor"
    ],
    "wof:name":"Custom Dream Homes",
    "wof:placetype":"venue"
},
  "geometry": {"coordinates":[-119.789202,39.487004],"type":"Point"}
}