{
  "type": "Feature",
  "properties": {
    "iso:country":"US",
    "sg:address":"380 Freeport Blvd",
    "sg:city":"Sparks",
    "sg:classifiers":[
        {
            "category":"Retail",
            "subcategory":"Repair Shop",
            "type":"Services"
        }
    ],
    "sg:phone":"+1 775 355 1277",
    "sg:postcode":"89431",
    "sg:province":"NV",
    "sg:tags":[
        "related"
    ],
    "wof:name":"Affordable Vehicle Repair",
    "wof:placetype":"venue"
},
  "geometry": {"coordinates":[-119.744591,39.525653],"type":"Point"}
}