{
  "type": "Feature",
  "properties": {
    "iso:country":"US",
    "sg:address":"7180 Jackson Rd",
    "sg:city":"Winnemucca",
    "sg:classifiers":[
        {
            "category":"Shopping",
            "subcategory":"Bicycles & Sporting Goods",
            "type":"Retail Goods"
        }
    ],
    "sg:phone":"+1 775 623 3074",
    "sg:postcode":"89445",
    "sg:province":"NV",
    "wof:name":"Petes Shooting Supplies",
    "wof:placetype":"venue"
},
  "geometry": {"coordinates":[-117.76331,40.913945],"type":"Point"}
}