{
  "type": "Feature",
  "properties": {
    "iso:country":"US",
    "sg:address":"5828 Spring Mountain Rd",
    "sg:city":"Las Vegas",
    "sg:classifiers":[
        {
            "category":"Building & Trades",
            "subcategory":"Construction",
            "type":"Services"
        }
    ],
    "sg:phone":"+1 702 227 1211",
    "sg:postcode":"89146",
    "sg:province":"NV",
    "sg:tags":[
        "interior",
        "contractor",
        "floor",
        "designing",
        "covering"
    ],
    "wof:name":"Floorfax",
    "wof:placetype":"venue"
},
  "geometry": {"coordinates":[-115.222255,36.125648],"type":"Point"}
}