{
  "type": "Feature",
  "properties": {
    "iso:country":"US",
    "sg:address":"3270 E Tropicana Ave",
    "sg:city":"Las Vegas",
    "sg:classifiers":[
        {
            "category":"Bakery",
            "type":"Food & Drink"
        }
    ],
    "sg:phone":"+1 702 898 0311",
    "sg:postcode":"89121",
    "sg:province":"NV",
    "sg:website":"www.greatbunsbakery.net",
    "wof:name":"Great Buns Bakery",
    "wof:placetype":"venue"
},
  "geometry": {"coordinates":[-115.103996,36.099998],"type":"Point"}
}