{
  "type": "Feature",
  "properties": {
    "iso:country":"US",
    "sg:address":"1214 Johnson St",
    "sg:city":"Carson City",
    "sg:classifiers":[
        {
            "category":"Insurance",
            "subcategory":"Life Insurance",
            "type":"Services"
        }
    ],
    "sg:phone":"+1 775 884 0288",
    "sg:postcode":"89706",
    "sg:province":"NV",
    "sg:tags":[
        "carrier"
    ],
    "wof:name":"Benefit Source",
    "wof:placetype":"venue"
},
  "geometry": {"coordinates":[-119.764217,39.171212],"type":"Point"}
}