{
  "type": "Feature",
  "properties": {
    "iso:country":"US",
    "sg:address":"2054 Majestic Peak Dr",
    "sg:city":"Henderson",
    "sg:classifiers":[
        {
            "category":"Professional",
            "subcategory":"Business Services",
            "type":"Services"
        }
    ],
    "sg:phone":"+1 702 837 0354",
    "sg:postcode":"89074",
    "sg:province":"NV",
    "wof:name":"Navetta Bernard Designer",
    "wof:placetype":"venue"
},
  "geometry": {"coordinates":[-115.076669,36.028326],"type":"Point"}
}