{
  "type": "Feature",
  "properties": {
    "iso:country":"US",
    "sg:address":"1008 E 4th St",
    "sg:city":"Reno",
    "sg:classifiers":[
        {
            "category":"Building & Trades",
            "subcategory":"Construction",
            "type":"Services"
        },
        {
            "category":"Building & Trades",
            "subcategory":"Electrical",
            "type":"Services"
        },
        {
            "category":"Building & Trades",
            "subcategory":"Plumbing",
            "type":"Services"
        },
        {
            "category":"Home & Garden",
            "subcategory":"Building Materials",
            "type":"Retail Goods"
        },
        {
            "category":"Professional",
            "subcategory":"Engineering",
            "type":"Services"
        },
        {
            "category":"Building & Trades",
            "subcategory":"Cleaning & Sanitation",
            "type":"Services"
        }
    ],
    "sg:phone":"+1 775 322 9434",
    "sg:postcode":"89512",
    "sg:province":"NV",
    "sg:tags":[
        "plumber",
        "duct",
        "system",
        "specialty",
        "equipment",
        "furnaces-heating",
        "heating",
        "contractor",
        "air conditioning"
    ],
    "sg:website":"http://www.rhpinc.net",
    "wof:name":"RHP Mechanical",
    "wof:placetype":"venue"
},
  "geometry": {"coordinates":[-119.800504,39.532532],"type":"Point"}
}