{
  "type": "Feature",
  "properties": {
    "iso:country":"US",
    "sg:address":"3014 Playa del Rey St",
    "sg:city":"Las Vegas",
    "sg:classifiers":[
        {
            "category":"Wholesale",
            "subcategory":"Machinery & Supplies",
            "type":"Manufacturing & Wholesale Goods"
        }
    ],
    "sg:phone":"+1 702 791 5575",
    "sg:postcode":"89169",
    "sg:province":"NV",
    "sg:tags":[
        "equipment",
        "establishment"
    ],
    "wof:name":"Bravo & Sons Carpet Cleaning",
    "wof:placetype":"venue"
},
  "geometry": {"coordinates":[-115.128118,36.134641],"type":"Point"}
}