{
  "type": "Feature",
  "properties": {
    "iso:country":"US",
    "sg:address":"6280 S Valley View Blvd #100",
    "sg:city":"Las Vegas",
    "sg:classifiers":[
        {
            "category":"Restaurant",
            "type":"Food & Drink"
        }
    ],
    "sg:phone":"+1 702 476 5337",
    "sg:postcode":"89118",
    "sg:province":"NV",
    "sg:tags":[
        "new",
        "american"
    ],
    "sg:website":"www.sunsetgrilllv.com",
    "wof:name":"Sunset Grill",
    "wof:placetype":"venue"
},
  "geometry": {"coordinates":[-115.188947,36.077459],"type":"Point"}
}