{
  "type": "Feature",
  "properties": {
    "iso:country":"US",
    "sg:address":"7950 W Tropical Pkwy",
    "sg:city":"Las Vegas",
    "sg:classifiers":[
        {
            "category":"Shopping",
            "subcategory":"Stationery & Office Supplies",
            "type":"Retail Goods"
        }
    ],
    "sg:phone":"+1 702 658 0157",
    "sg:postcode":"89149",
    "sg:province":"NV",
    "sg:tags":[
        "album",
        "scrapbook"
    ],
    "wof:name":"Addicted To Scrap",
    "wof:placetype":"venue"
},
  "geometry": {"coordinates":[-115.26888,36.270546],"type":"Point"}
}