{
  "type": "Feature",
  "properties": {
    "iso:country":"US",
    "sg:address":"1200 W Warm Springs Rd",
    "sg:city":"Henderson",
    "sg:classifiers":[
        {
            "category":"Food & Beverages",
            "subcategory":"Groceries & Convenience Stores",
            "type":"Retail Goods"
        }
    ],
    "sg:phone":"+1 702 458 9101",
    "sg:postcode":"89014",
    "sg:province":"NV",
    "wof:name":"Rebel Oil Co",
    "wof:placetype":"venue"
},
  "geometry": {"coordinates":[-115.03746599999999,36.056276],"type":"Point"}
}