{
  "type": "Feature",
  "properties": {
    "iso:country":"US",
    "sg:address":"3430 E Tropicana Ave",
    "sg:city":"Las Vegas",
    "sg:classifiers":[
        {
            "category":"Food & Beverages",
            "subcategory":"Specialty",
            "type":"Retail Goods"
        }
    ],
    "sg:phone":"+1 702 547 5282",
    "sg:postcode":"89121",
    "sg:province":"NV",
    "sg:tags":[
        "tea",
        "coffee"
    ],
    "wof:name":"Java Beans",
    "wof:placetype":"venue"
},
  "geometry": {"coordinates":[-115.09968600000001,36.100127],"type":"Point"}
}