{
  "type": "Feature",
  "properties": {
    "iso:country":"US",
    "sg:address":"2554 Idaho St",
    "sg:city":"Elko",
    "sg:classifiers":[
        {
            "category":"Health Services",
            "subcategory":"Doctor",
            "type":"Services"
        }
    ],
    "sg:phone":"+1 775 738 1120",
    "sg:postcode":"89801",
    "sg:province":"NV",
    "sg:tags":[
        "dentist"
    ],
    "wof:name":"Quinn Dufurrena DDS",
    "wof:placetype":"venue"
},
  "geometry": {"coordinates":[-115.74303,40.853388],"type":"Point"}
}