{
  "type": "Feature",
  "properties": {
    "iso:country":"US",
    "sg:address":"651 N McCarran Blvd",
    "sg:city":"Sparks",
    "sg:classifiers":[
        {
            "category":"Retail",
            "subcategory":"Auto Repair",
            "type":"Services"
        }
    ],
    "sg:phone":"+1 775 358 7800",
    "sg:postcode":"89431",
    "sg:province":"NV",
    "sg:tags":[
        "repairing",
        "automobile"
    ],
    "wof:name":"Econo Lube N' Tune Shop",
    "wof:placetype":"venue"
},
  "geometry": {"coordinates":[-119.734013,39.539901],"type":"Point"}
}