{
  "type": "Feature",
  "properties": {
    "iso:country":"US",
    "sg:address":"2450 Lockheed Way",
    "sg:city":"Carson City",
    "sg:classifiers":[
        {
            "category":"Communications",
            "subcategory":"Radio Station",
            "type":"Services"
        }
    ],
    "sg:phone":"+1 775 885 2424",
    "sg:postcode":"89706",
    "sg:province":"NV",
    "sg:tags":[
        "broadcast"
    ],
    "wof:name":"F & M Mafco Inc",
    "wof:placetype":"venue"
},
  "geometry": {"coordinates":[-119.74206,39.197682],"type":"Point"}
}