{
  "type": "Feature",
  "properties": {
    "iso:country":"US",
    "sg:address":"10048 Twilight Point Ct",
    "sg:city":"Las Vegas",
    "sg:classifiers":[
        {
            "category":"Professional",
            "subcategory":"Business Services",
            "type":"Services"
        }
    ],
    "sg:phone":"+1 702 301 7881",
    "sg:postcode":"89148",
    "sg:province":"NV",
    "wof:name":"Redesigning Reality",
    "wof:placetype":"venue"
},
  "geometry": {"coordinates":[-115.311387,36.096025],"type":"Point"}
}