{
  "type": "Feature",
  "properties": {
    "iso:country":"US",
    "sg:address":"5011 Meadowood Mall Cir",
    "sg:city":"Reno",
    "sg:classifiers":[
        {
            "category":"Professional",
            "subcategory":"Lawyer & Legal Services",
            "type":"Services"
        }
    ],
    "sg:phone":"+1 775 827 8666",
    "sg:postcode":"89502",
    "sg:province":"NV",
    "sg:tags":[
        "attorney"
    ],
    "wof:name":"Beesley Bruce T",
    "wof:placetype":"venue"
},
  "geometry": {"coordinates":[-119.78519900000001,39.475981],"type":"Point"}
}