{
  "type": "Feature",
  "properties": {
    "iso:country":"US",
    "sg:address":"640 Eastgate Rd",
    "sg:city":"Henderson",
    "sg:classifiers":[
        {
            "category":"Retail",
            "subcategory":"Pet Boarding",
            "type":"Services"
        }
    ],
    "sg:phone":"+1 702 565 7297",
    "sg:postcode":"89011",
    "sg:province":"NV",
    "sg:tags":[
        "boarding/pet",
        "sitting"
    ],
    "sg:website":"www.pawsnclawslv.com",
    "wof:name":"Paws 'n Claws Pet Resort",
    "wof:placetype":"venue"
},
  "geometry": {"coordinates":[-115.019914,36.065113],"type":"Point"}
}