{
  "type": "Feature",
  "properties": {
    "iso:country":"US",
    "sg:address":"440 Spokane St",
    "sg:city":"Reno",
    "sg:classifiers":[
        {
            "category":"Shopping",
            "subcategory":"Crafts & Fabrics",
            "type":"Retail Goods"
        }
    ],
    "sg:phone":"+1 775 323 4777",
    "sg:postcode":"89512",
    "sg:province":"NV",
    "sg:tags":[
        "shop"
    ],
    "sg:website":"www.windymoonquilts.com",
    "wof:name":"Windy Moon Quilts",
    "wof:placetype":"venue"
},
  "geometry": {"coordinates":[-119.80054,39.534252],"type":"Point"}
}