{
  "type": "Feature",
  "properties": {
    "iso:country":"US",
    "sg:address":"755 E Flamingo Rd",
    "sg:city":"Las Vegas",
    "sg:classifiers":[
        {
            "category":"Professional",
            "subcategory":"Research",
            "type":"Services"
        }
    ],
    "sg:phone":"+1 702 862 5400",
    "sg:postcode":"89119",
    "sg:province":"NV",
    "sg:tags":[
        "environmental",
        "ecological"
    ],
    "sg:website":"www.dri.edu",
    "wof:name":"Desert Research Institute",
    "wof:placetype":"venue"
},
  "geometry": {"coordinates":[-115.149168,36.11467],"type":"Point"}
}