{
  "type": "Feature",
  "properties": {
    "iso:country":"US",
    "sg:address":"5128 W Charleston Blvd",
    "sg:city":"Las Vegas",
    "sg:classifiers":[
        {
            "category":"Insurance",
            "subcategory":"Hazard Insurance",
            "type":"Services"
        }
    ],
    "sg:phone":"+1 702 851 7777",
    "sg:postcode":"89146",
    "sg:province":"NV",
    "sg:website":"www.elementalins.com",
    "wof:name":"Elemental Insurance & Finance",
    "wof:placetype":"venue"
},
  "geometry": {"coordinates":[-115.211268,36.159167],"type":"Point"}
}