{
  "type": "Feature",
  "properties": {
    "iso:country":"US",
    "sg:address":"219 Rusty Plank Ave",
    "sg:city":"Las Vegas",
    "sg:classifiers":[
        {
            "category":"Personal",
            "subcategory":"Beauty Salon",
            "type":"Services"
        }
    ],
    "sg:phone":"+1 702 895 9945",
    "sg:postcode":"89148",
    "sg:province":"NV",
    "wof:name":"Auto Looks",
    "wof:placetype":"venue"
},
  "geometry": {"coordinates":[-115.293274,36.049234],"type":"Point"}
}