{
  "type": "Feature",
  "properties": {
    "iso:country":"US",
    "sg:address":"2730 Coventry Green Ave",
    "sg:city":"Henderson",
    "sg:classifiers":[
        {
            "category":"Professional",
            "type":"Services"
        }
    ],
    "sg:phone":"+1 702 897 1006",
    "sg:postcode":"89074",
    "sg:province":"NV",
    "wof:name":"Fancy Fun Spcial Events Design",
    "wof:placetype":"venue"
},
  "geometry": {"coordinates":[-115.108738,36.04189],"type":"Point"}
}