{
  "type": "Feature",
  "properties": {
    "iso:country":"US",
    "sg:address":"2250 E Flamingo Rd",
    "sg:city":"Las Vegas",
    "sg:classifiers":[
        {
            "category":"Health Services",
            "subcategory":"Hospital",
            "type":"Services"
        }
    ],
    "sg:phone":"+1 702 784 4300",
    "sg:postcode":"89119",
    "sg:province":"NV",
    "wof:name":"Kindred Hospital Las Vegas Flamingo",
    "wof:placetype":"venue"
},
  "geometry": {"coordinates":[-115.121002,36.114799],"type":"Point"}
}