{
  "type": "Feature",
  "properties": {
    "iso:country":"US",
    "sg:address":"220 Sunshine Ln",
    "sg:city":"Reno",
    "sg:classifiers":[
        {
            "category":"Retail",
            "subcategory":"Auto Repair",
            "type":"Services"
        }
    ],
    "sg:phone":"+1 775 322 6022",
    "sg:postcode":"89502",
    "sg:province":"NV",
    "sg:tags":[
        "shop"
    ],
    "wof:name":"A & L Automotive",
    "wof:placetype":"venue"
},
  "geometry": {"coordinates":[-119.787858,39.526115],"type":"Point"}
}