{
  "type": "Feature",
  "properties": {
    "iso:country":"US",
    "sg:address":"1 Broadway",
    "sg:city":"Alamo",
    "sg:classifiers":[
        {
            "category":"Banks & Credit Unions",
            "subcategory":"Bank",
            "type":"Services"
        }
    ],
    "sg:phone":"+1 775 725 3391",
    "sg:postcode":"89001",
    "sg:province":"NV",
    "wof:name":"Nevada Bank & Trust Co",
    "wof:placetype":"venue"
},
  "geometry": {"coordinates":[-115.165727,37.36418],"type":"Point"}
}