{
  "type": "Feature",
  "properties": {
    "iso:country":"US",
    "sg:address":"845 Railroad St",
    "sg:city":"Elko",
    "sg:classifiers":[
        {
            "category":"Health Services",
            "subcategory":"Doctor",
            "type":"Services"
        }
    ],
    "sg:phone":"+1 775 778 6762",
    "sg:postcode":"89801",
    "sg:province":"NV",
    "sg:tags":[
        "medical"
    ],
    "wof:name":"Sonja Brownlee MD Faap",
    "wof:placetype":"venue"
},
  "geometry": {"coordinates":[-115.75902499999999,40.834882],"type":"Point"}
}