{
  "type": "Feature",
  "properties": {
    "iso:country":"US",
    "sg:address":"61 Rainbow Cir",
    "sg:city":"West Wendover",
    "sg:classifiers":[
        {
            "category":"Home & Garden",
            "subcategory":"Mobile Homes",
            "type":"Retail Goods"
        }
    ],
    "sg:phone":"+1 775 478 5146",
    "sg:postcode":"89883",
    "sg:province":"NV",
    "wof:name":"Oasis Mobile Home Brokers",
    "wof:placetype":"venue"
},
  "geometry": {"coordinates":[-114.470505,41.031088],"type":"Point"}
}