{
  "type": "Feature",
  "properties": {
    "iso:country":"US",
    "sg:address":"862 W Bartlett Ave",
    "sg:city":"Las Vegas",
    "sg:classifiers":[
        {
            "category":"Building & Trades",
            "subcategory":"Construction",
            "type":"Services"
        }
    ],
    "sg:phone":"+1 702 249 0202",
    "sg:postcode":"89106",
    "sg:province":"NV",
    "sg:tags":[
        "handyman"
    ],
    "wof:name":"Best Choice Handyman Svc",
    "wof:placetype":"venue"
},
  "geometry": {"coordinates":[-115.152816,36.200343],"type":"Point"}
}