{
  "type": "Feature",
  "properties": {
    "iso:country":"US",
    "sg:address":"1603 Myles Way",
    "sg:city":"Carson City",
    "sg:classifiers":[
        {
            "category":"Banks & Credit Unions",
            "subcategory":"Financial Services",
            "type":"Services"
        }
    ],
    "sg:phone":"+1 775 841 2730",
    "sg:postcode":"89701",
    "sg:province":"NV",
    "sg:tags":[
        "investor"
    ],
    "wof:name":"Triple S Investments Inc",
    "wof:placetype":"venue"
},
  "geometry": {"coordinates":[-119.748445,39.141707],"type":"Point"}
}