{
  "type": "Feature",
  "properties": {
    "iso:country":"US",
    "sg:address":"1890 Pinto Cir",
    "sg:city":"Gardnerville",
    "sg:classifiers":[
        {
            "category":"Building & Trades",
            "subcategory":"Construction",
            "type":"Services"
        }
    ],
    "sg:phone":"+1 775 265 5754",
    "sg:postcode":"89410",
    "sg:province":"NV",
    "sg:tags":[
        "general",
        "contractor"
    ],
    "wof:name":"John Fent Construction",
    "wof:placetype":"venue"
},
  "geometry": {"coordinates":[-119.688894,38.895538],"type":"Point"}
}