{
  "type": "Feature",
  "properties": {
    "iso:country":"US",
    "sg:address":"8000 W Sahara Ave",
    "sg:city":"Las Vegas",
    "sg:classifiers":[
        {
            "category":"Coffee & Tea",
            "type":"Food & Drink"
        }
    ],
    "sg:menulink":"http://www.allmenus.com/nv/las-vegas/125379-starbucks-coffee/menu/",
    "sg:phone":"+1 702 838 3597",
    "sg:postcode":"89117",
    "sg:province":"NV",
    "sg:tags":[
        "american"
    ],
    "wof:name":"Starbucks Coffee",
    "wof:placetype":"venue"
},
  "geometry": {"coordinates":[-115.26602200000001,36.144235],"type":"Point"}
}