{
  "type": "Feature",
  "properties": {
    "iso:country":"US",
    "sg:address":"3315 W Craig Rd",
    "sg:city":"North Las Vegas",
    "sg:classifiers":[
        {
            "category":"Personal",
            "subcategory":"Beauty Salon",
            "type":"Services"
        }
    ],
    "sg:phone":"+1 702 638 1450",
    "sg:postcode":"89032",
    "sg:province":"NV",
    "wof:name":"Jasmines Beauty Supply",
    "wof:placetype":"venue"
},
  "geometry": {"coordinates":[-115.187556,36.239413],"type":"Point"}
}