{
  "type": "Feature",
  "properties": {
    "iso:country":"US",
    "sg:address":"2920 Florence Ave",
    "sg:city":"Las Vegas",
    "sg:classifiers":[
        {
            "category":"Building & Trades",
            "subcategory":"Construction",
            "type":"Services"
        }
    ],
    "sg:phone":"+1 702 895 9339",
    "sg:postcode":"89120",
    "sg:province":"NV",
    "sg:tags":[
        "contractor"
    ],
    "wof:name":"K & K Welding Service",
    "wof:placetype":"venue"
},
  "geometry": {"coordinates":[-115.110535,36.095917],"type":"Point"}
}