{
  "type": "Feature",
  "properties": {
    "iso:country":"US",
    "sg:address":"2500 Palomino Ln",
    "sg:city":"Las Vegas",
    "sg:classifiers":[
        {
            "category":"Building & Trades",
            "subcategory":"Landscaping Services",
            "type":"Services"
        }
    ],
    "sg:phone":"+1 702 258 0000",
    "sg:postcode":"89107",
    "sg:province":"NV",
    "sg:tags":[
        "landscape",
        "contractor"
    ],
    "wof:name":"Ray's Lawn & Sprinkler Svc",
    "wof:placetype":"venue"
},
  "geometry": {"coordinates":[-115.176091,36.162604],"type":"Point"}
}