{
  "type": "Feature",
  "properties": {
    "iso:country":"US",
    "sg:address":"3653 Evening Fog St",
    "sg:city":"Las Vegas",
    "sg:classifiers":[
        {
            "category":"Education",
            "subcategory":"Vocational School",
            "type":"Public Place"
        }
    ],
    "sg:phone":"+1 702 647 0001",
    "sg:postcode":"89129",
    "sg:province":"NV",
    "sg:tags":[
        "flight",
        "instruction",
        "rental",
        "plane"
    ],
    "wof:name":"Las Vegas Flying Club LLC",
    "wof:placetype":"venue"
},
  "geometry": {"coordinates":[-115.331527,36.226684],"type":"Point"}
}