{
  "type": "Feature",
  "properties": {
    "iso:country":"US",
    "sg:address":"4200 Kings Canyon Rd",
    "sg:city":"Carson City",
    "sg:classifiers":[
        {
            "category":"Professional",
            "subcategory":"Lawyer & Legal Services",
            "type":"Services"
        }
    ],
    "sg:phone":"+1 775 883 4404",
    "sg:postcode":"89703",
    "sg:province":"NV",
    "sg:tags":[
        "attorney"
    ],
    "wof:name":"Arthur J Bayer Jr PC",
    "wof:placetype":"venue"
},
  "geometry": {"coordinates":[-119.81226700000001,39.155088],"type":"Point"}
}