{
  "type": "Feature",
  "properties": {
    "iso:country":"US",
    "sg:address":"1414 S Maryland Pkwy",
    "sg:city":"Las Vegas",
    "sg:classifiers":[
        {
            "category":"Real Estate",
            "subcategory":"Real Estate Operator",
            "type":"Services"
        }
    ],
    "sg:phone":"+1 702 270 4106",
    "sg:postcode":"89104",
    "sg:province":"NV",
    "sg:tags":[
        "building",
        "nonresidential"
    ],
    "wof:name":"Gladiator Consulting",
    "wof:placetype":"venue"
},
  "geometry": {"coordinates":[-115.136989,36.155075],"type":"Point"}
}