{
  "type": "Feature",
  "properties": {
    "iso:country":"US",
    "sg:address":"499 Melrose Heights St",
    "sg:city":"Henderson",
    "sg:classifiers":[
        {
            "category":"Farming",
            "subcategory":"Livestock Farm",
            "type":"Manufacturing & Wholesale Goods"
        }
    ],
    "sg:phone":"+1 702 897 0449",
    "sg:postcode":"89052",
    "sg:province":"NV",
    "sg:tags":[
        "animal",
        "general"
    ],
    "wof:name":"Cholla Canyon Ranch",
    "wof:placetype":"venue"
},
  "geometry": {"coordinates":[-115.085325,36.010917],"type":"Point"}
}