{
  "type": "Feature",
  "properties": {
    "iso:country":"US",
    "sg:address":"1350 Rockafeller Dr",
    "sg:city":"Pahrump",
    "sg:classifiers":[
        {
            "category":"Retail",
            "subcategory":"Repair Shop",
            "type":"Services"
        }
    ],
    "sg:phone":"+1 775 537 6275",
    "sg:postcode":"89060",
    "sg:province":"NV",
    "sg:tags":[
        "appliance",
        "household",
        "electrical"
    ],
    "wof:name":"Marks Service Center",
    "wof:placetype":"venue"
},
  "geometry": {"coordinates":[-115.993828,36.239543],"type":"Point"}
}