{
  "type": "Feature",
  "properties": {
    "iso:country":"US",
    "sg:address":"1310 S Harmon Rd",
    "sg:city":"Fallon",
    "sg:classifiers":[
        {
            "category":"Professional",
            "subcategory":"Computer Services",
            "type":"Services"
        }
    ],
    "sg:phone":"+1 775 867 2676",
    "sg:postcode":"89406",
    "sg:province":"NV",
    "sg:tags":[
        "related"
    ],
    "wof:name":"Warburton Enterprises",
    "wof:placetype":"venue"
},
  "geometry": {"coordinates":[-118.687915,39.463437],"type":"Point"}
}