{
  "type": "Feature",
  "properties": {
    "iso:country":"US",
    "sg:address":"3035 Longley Ln",
    "sg:city":"Reno",
    "sg:classifiers":[
        {
            "category":"Government",
            "subcategory":"Office",
            "type":"Public Place"
        }
    ],
    "sg:phone":"+1 775 328 2144",
    "sg:postcode":"89502",
    "sg:province":"NV",
    "sg:tags":[
        "general"
    ],
    "wof:name":"Purchasing-Receiving",
    "wof:placetype":"venue"
},
  "geometry": {"coordinates":[-119.75493,39.494462],"type":"Point"}
}