{
  "type": "Feature",
  "properties": {
    "iso:country":"US",
    "sg:address":"1016 S 1st Street",
    "sg:city":"Las Vegas",
    "sg:classifiers":[
        {
            "category":"Shopping",
            "subcategory":"Books",
            "type":"Retail Goods"
        }
    ],
    "sg:phone":"+1 702 382 1076",
    "sg:postcode":"89101",
    "sg:province":"NV",
    "sg:tags":[
        "bookstore"
    ],
    "wof:name":"A-Action Adult Books & Videos",
    "wof:placetype":"venue"
},
  "geometry": {"coordinates":[-115.15274599999999,36.159906],"type":"Point"}
}