{
  "type": "Feature",
  "properties": {
    "iso:country":"US",
    "sg:address":"4620 S Valley View Blvd",
    "sg:city":"Las Vegas",
    "sg:classifiers":[
        {
            "category":"Professional",
            "subcategory":"Employment Agencies",
            "type":"Services"
        }
    ],
    "sg:phone":"+1 702 795 7767",
    "sg:postcode":"89103",
    "sg:province":"NV",
    "sg:tags":[
        "help",
        "contractor"
    ],
    "wof:name":"Staffing Resources",
    "wof:placetype":"venue"
},
  "geometry": {"coordinates":[-115.189752,36.105733],"type":"Point"}
}