{
  "type": "Feature",
  "properties": {
    "iso:country":"US",
    "sg:address":"602 Sandana Cir",
    "sg:city":"Las Vegas",
    "sg:classifiers":[
        {
            "category":"Professional",
            "subcategory":"Management & Consulting",
            "type":"Services"
        }
    ],
    "sg:phone":"+1 702 361 2802",
    "sg:postcode":"89123",
    "sg:province":"NV",
    "sg:tags":[
        "business"
    ],
    "wof:name":"Motovation Inc",
    "wof:placetype":"venue"
},
  "geometry": {"coordinates":[-115.150319,36.030561],"type":"Point"}
}