{
  "type": "Feature",
  "properties": {
    "iso:country":"US",
    "sg:address":"1528 US Highway 395 N",
    "sg:city":"Gardnerville",
    "sg:classifiers":[
        {
            "category":"Personal",
            "subcategory":"Beauty Salon",
            "type":"Services"
        }
    ],
    "sg:phone":"+1 775 783 4930",
    "sg:postcode":"89410",
    "sg:province":"NV",
    "wof:name":"Restoration Spa",
    "wof:placetype":"venue"
},
  "geometry": {"coordinates":[-119.55665,38.731896],"type":"Point"}
}