{
  "type": "Feature",
  "properties": {
    "iso:country":"US",
    "sg:address":"4929 Tindari St",
    "sg:city":"Las Vegas",
    "sg:classifiers":[
        {
            "category":"Retail",
            "subcategory":"Car Wash",
            "type":"Services"
        }
    ],
    "sg:phone":"+1 702 413 4425",
    "sg:postcode":"89130",
    "sg:province":"NV",
    "sg:tags":[
        "automobile",
        "detail",
        "clean"
    ],
    "wof:name":"L & L Auto Detailing",
    "wof:placetype":"venue"
},
  "geometry": {"coordinates":[-115.232282,36.25008],"type":"Point"}
}