{
  "type": "Feature",
  "properties": {
    "iso:country":"US",
    "sg:address":"9180 W Cheyenne Avenue",
    "sg:city":"Las Vegas",
    "sg:classifiers":[
        {
            "category":"Bars & Pubs",
            "type":"Food & Drink"
        }
    ],
    "sg:phone":"+1 702 562 0202",
    "sg:postcode":"89129",
    "sg:province":"NV",
    "wof:name":"Timbers IV Bar & Grill",
    "wof:placetype":"venue"
},
  "geometry": {"coordinates":[-115.295671,36.218747],"type":"Point"}
}