{
  "type": "Feature",
  "properties": {
    "iso:country":"US",
    "sg:address":"1478 4th St",
    "sg:city":"Minden",
    "sg:classifiers":[
        {
            "category":"Personal",
            "subcategory":"Beauty Salon",
            "type":"Services"
        }
    ],
    "sg:phone":"+1 775 782 6597",
    "sg:postcode":"89423",
    "sg:province":"NV",
    "sg:tags":[
        "shop"
    ],
    "wof:name":"Nails By Tiffany",
    "wof:placetype":"venue"
},
  "geometry": {"coordinates":[-119.764279,38.952455],"type":"Point"}
}