{
  "type": "Feature",
  "properties": {
    "iso:country":"US",
    "sg:address":"500 W College Pkwy",
    "sg:city":"Carson City",
    "sg:classifiers":[
        {
            "category":"Real Estate",
            "subcategory":"Real Estate Operator",
            "type":"Services"
        }
    ],
    "sg:phone":"+1 775 882 7555",
    "sg:postcode":"89706",
    "sg:province":"NV",
    "sg:tags":[
        "apartment"
    ],
    "wof:name":"Parkway Plaza Apartments",
    "wof:placetype":"venue"
},
  "geometry": {"coordinates":[-119.770513,39.190709],"type":"Point"}
}