{
  "type": "Feature",
  "properties": {
    "iso:country":"US",
    "sg:address":"3339 US Hwy 50",
    "sg:city":"Carson City",
    "sg:classifiers":[
        {
            "category":"Retail",
            "subcategory":"Auto Repair",
            "type":"Services"
        }
    ],
    "sg:phone":"+1 775 883 3339",
    "sg:postcode":"89701",
    "sg:province":"NV",
    "sg:tags":[
        "repairing",
        "automobile"
    ],
    "wof:name":"Carson Auto Works",
    "wof:placetype":"venue"
},
  "geometry": {"coordinates":[-119.769285,39.136255],"type":"Point"}
}