{
  "type": "Feature",
  "properties": {
    "iso:country":"US",
    "sg:address":"510 Plumb Ln",
    "sg:city":"Reno",
    "sg:classifiers":[
        {
            "category":"Insurance",
            "subcategory":"Insurance Agent",
            "type":"Services"
        }
    ],
    "sg:phone":"+1 775 882 3522",
    "sg:postcode":"89502",
    "sg:province":"NV",
    "sg:website":"www.aflac.com",
    "wof:name":"AFLAC",
    "wof:placetype":"venue"
},
  "geometry": {"coordinates":[-119.793854,39.505757],"type":"Point"}
}