{
  "type": "Feature",
  "properties": {
    "iso:country":"US",
    "sg:address":"5895 Duneville St",
    "sg:city":"Las Vegas",
    "sg:classifiers":[
        {
            "category":"Professional",
            "subcategory":"Management & Consulting",
            "type":"Services"
        }
    ],
    "sg:phone":"+1 702 873 1818",
    "sg:postcode":"89118",
    "sg:province":"NV",
    "sg:tags":[
        "publishing"
    ],
    "wof:name":"C S I Services Inc",
    "wof:placetype":"venue"
},
  "geometry": {"coordinates":[-115.220923,36.083734],"type":"Point"}
}