{
  "type": "Feature",
  "properties": {
    "iso:country":"US",
    "sg:address":"7790 W Sahara Avenue",
    "sg:city":"Las Vegas",
    "sg:classifiers":[
        {
            "category":"Food & Beverages",
            "subcategory":"Groceries & Convenience Stores",
            "type":"Retail Goods"
        }
    ],
    "sg:phone":"+1 702 360 5791",
    "sg:postcode":"89117",
    "sg:province":"NV",
    "wof:name":"Delek One Stop Lakes",
    "wof:placetype":"venue"
},
  "geometry": {"coordinates":[-115.260763,36.143869],"type":"Point"}
}