{
  "type": "Feature",
  "properties": {
    "iso:country":"US",
    "sg:address":"809 Pioche St",
    "sg:city":"Carson City",
    "sg:classifiers":[
        {
            "category":"Real Estate",
            "subcategory":"Architect",
            "type":"Services"
        }
    ],
    "sg:phone":"+1 775 841 0467",
    "sg:postcode":"89701",
    "sg:province":"NV",
    "sg:tags":[
        "architectural"
    ],
    "wof:name":"Custom Cuts Lawn & Ldscp Maint",
    "wof:placetype":"venue"
},
  "geometry": {"coordinates":[-119.758744,39.137426],"type":"Point"}
}