{
  "type": "Feature",
  "properties": {
    "iso:country":"US",
    "sg:address":"5453 Milkwood Ln",
    "sg:city":"Las Vegas",
    "sg:classifiers":[
        {
            "category":"Real Estate",
            "subcategory":"Real Estate Operator",
            "type":"Services"
        }
    ],
    "sg:phone":"+1 702 396 7370",
    "sg:postcode":"89149",
    "sg:province":"NV",
    "sg:tags":[
        "property",
        "lessor"
    ],
    "wof:name":"Executive Property Care",
    "wof:placetype":"venue"
},
  "geometry": {"coordinates":[-115.26597,36.260085],"type":"Point"}
}