{
  "type": "Feature",
  "properties": {
    "iso:country":"US",
    "sg:address":"4490 Bus Center Way",
    "sg:city":"Las Vegas",
    "sg:classifiers":[
        {
            "category":"Building & Trades",
            "subcategory":"Construction",
            "type":"Services"
        }
    ],
    "sg:phone":"+1 702 248 3800",
    "sg:postcode":"89118",
    "sg:province":"NV",
    "sg:tags":[
        "material",
        "contractor"
    ],
    "sg:website":"www.carrara.com",
    "wof:name":"Carrara Marble Co Of America",
    "wof:placetype":"venue"
},
  "geometry": {"coordinates":[-115.199381,36.091294],"type":"Point"}
}