{
  "type": "Feature",
  "properties": {
    "iso:country":"US",
    "sg:address":"3355 Spring Mountain Rd",
    "sg:city":"Las Vegas",
    "sg:classifiers":[
        {
            "category":"Banks & Credit Unions",
            "subcategory":"Financial Services",
            "type":"Services"
        }
    ],
    "sg:phone":"+1 702 319 8878",
    "sg:postcode":"89102",
    "sg:province":"NV",
    "sg:tags":[
        "broker",
        "mortgage"
    ],
    "wof:name":"Secured Home Loans",
    "wof:placetype":"venue"
},
  "geometry": {"coordinates":[-115.18499799999999,36.1264],"type":"Point"}
}