{
  "type": "Feature",
  "properties": {
    "iso:country":"US",
    "sg:address":"2575 S Maryland Pkwy",
    "sg:city":"Las Vegas",
    "sg:classifiers":[
        {
            "category":"Food & Beverages",
            "subcategory":"Groceries & Convenience Stores",
            "type":"Retail Goods"
        }
    ],
    "sg:phone":"+1 702 735 2135",
    "sg:postcode":"89109",
    "sg:province":"NV",
    "wof:name":"Albertsons Supermarkets",
    "wof:placetype":"venue"
},
  "geometry": {"coordinates":[-115.137001,36.143501],"type":"Point"}
}