{
  "type": "Feature",
  "properties": {
    "iso:country":"US",
    "sg:address":"1230 S Loop Rd",
    "sg:city":"Pahrump",
    "sg:classifiers":[
        {
            "category":"Building & Trades",
            "subcategory":"Construction",
            "type":"Services"
        }
    ],
    "sg:phone":"+1 775 751 9936",
    "sg:postcode":"89048",
    "sg:province":"NV",
    "sg:tags":[
        "contractor"
    ],
    "wof:name":"Twin Shores Development Inc",
    "wof:placetype":"venue"
},
  "geometry": {"coordinates":[-115.972319,36.201834],"type":"Point"}
}