{
  "type": "Feature",
  "properties": {
    "iso:country":"US",
    "sg:address":"1520 Marietta Way",
    "sg:city":"Sparks",
    "sg:classifiers":[
        {
            "category":"Shopping",
            "subcategory":"Luggage & Leather Goods",
            "type":"Retail Goods"
        }
    ],
    "sg:phone":"+1 775 356 5504",
    "sg:postcode":"89431",
    "sg:province":"NV",
    "wof:name":"H A Leather",
    "wof:placetype":"venue"
},
  "geometry": {"coordinates":[-119.75406599999999,39.520832],"type":"Point"}
}