{
  "type": "Feature",
  "properties": {
    "iso:country":"US",
    "sg:address":"2619 Sherwood St",
    "sg:city":"Las Vegas",
    "sg:classifiers":[
        {
            "category":"Health Services",
            "subcategory":"Clinic",
            "type":"Services"
        }
    ],
    "sg:phone":"+1 702 892 0030",
    "sg:postcode":"89109",
    "sg:province":"NV",
    "wof:name":"In Home Health Care",
    "wof:placetype":"venue"
},
  "geometry": {"coordinates":[-115.147246,36.14246],"type":"Point"}
}