{
  "type": "Feature",
  "properties": {
    "iso:country":"US",
    "sg:address":"1955 Pinion Rd",
    "sg:city":"Elko",
    "sg:classifiers":[
        {
            "category":"Retail",
            "subcategory":"Auto Repair",
            "type":"Services"
        }
    ],
    "sg:phone":"+1 775 738 4928",
    "sg:postcode":"89801",
    "sg:province":"NV",
    "sg:tags":[
        "automobile",
        "installation",
        "glass"
    ],
    "wof:name":"Elko Glass Svc",
    "wof:placetype":"venue"
},
  "geometry": {"coordinates":[-115.732709,40.83292],"type":"Point"}
}