{
  "type": "Feature",
  "properties": {
    "iso:country":"US",
    "sg:address":"3540 Boulder Hwy",
    "sg:city":"Las Vegas",
    "sg:classifiers":[
        {
            "category":"Autos & Motor Vehicles",
            "subcategory":"Auto Supplies",
            "type":"Retail Goods"
        },
        {
            "category":"Wholesale",
            "subcategory":"Auto Parts",
            "type":"Manufacturing & Wholesale Goods"
        }
    ],
    "sg:phone":"+1 702 431 8000",
    "sg:postcode":"89121",
    "sg:province":"NV",
    "sg:tags":[
        "automobile"
    ],
    "wof:name":"Meyers Western Auto Parts Inc",
    "wof:placetype":"venue"
},
  "geometry": {"coordinates":[-115.098985,36.143731],"type":"Point"}
}