{
  "type": "Feature",
  "properties": {
    "iso:country":"US",
    "sg:address":"8883 W Flamingo Rd",
    "sg:city":"Las Vegas",
    "sg:classifiers":[
        {
            "category":"Banks & Credit Unions",
            "subcategory":"Bank",
            "type":"Services"
        }
    ],
    "sg:phone":"+1 702 221 8316",
    "sg:postcode":"89147",
    "sg:province":"NV",
    "sg:tags":[
        "loan",
        "mortgage",
        "real estate"
    ],
    "wof:name":"Long Beach Mortgage Corp",
    "wof:placetype":"venue"
},
  "geometry": {"coordinates":[-115.287735,36.114831],"type":"Point"}
}