{
  "type": "Feature",
  "properties": {
    "iso:country":"US",
    "sg:address":"906 Carson Ave",
    "sg:city":"Las Vegas",
    "sg:classifiers":[
        {
            "category":"Manufacturing",
            "subcategory":"Printing",
            "type":"Manufacturing & Wholesale Goods"
        }
    ],
    "sg:phone":"+1 702 384 1745",
    "sg:postcode":"89101",
    "sg:province":"NV",
    "sg:tags":[
        "commercial",
        "printer",
        "lithographic"
    ],
    "wof:name":"Quali Print",
    "wof:placetype":"venue"
},
  "geometry": {"coordinates":[-115.135713,36.165721],"type":"Point"}
}