{
  "type": "Feature",
  "properties": {
    "iso:country":"US",
    "sg:address":"6126 W Charleston Blvd",
    "sg:city":"Las Vegas",
    "sg:classifiers":[
        {
            "category":"Professional",
            "subcategory":"Employment Agencies",
            "type":"Services"
        }
    ],
    "sg:phone":"+1 702 870 0399",
    "sg:postcode":"89146",
    "sg:province":"NV",
    "sg:tags":[
        "help",
        "contractor"
    ],
    "wof:name":"Labor Express Temporary Svc",
    "wof:placetype":"venue"
},
  "geometry": {"coordinates":[-115.224698,36.159265],"type":"Point"}
}