{
  "type": "Feature",
  "properties": {
    "iso:country":"US",
    "sg:address":"5000 W Oakey Blvd",
    "sg:city":"Las Vegas",
    "sg:classifiers":[
        {
            "category":"Home & Garden",
            "subcategory":"Building Materials",
            "type":"Retail Goods"
        }
    ],
    "sg:phone":"+1 702 480 6657",
    "sg:postcode":"89146",
    "sg:province":"NV",
    "sg:tags":[
        "screen",
        "window"
    ],
    "wof:name":"Aztec Screen & Door",
    "wof:placetype":"venue"
},
  "geometry": {"coordinates":[-115.210307,36.151768],"type":"Point"}
}