{
  "type": "Feature",
  "properties": {
    "iso:country":"US",
    "sg:address":"6655 W Sahara Ave",
    "sg:city":"Las Vegas",
    "sg:classifiers":[
        {
            "category":"Home & Garden",
            "subcategory":"Building Materials",
            "type":"Retail Goods"
        },
        {
            "category":"Wholesale",
            "subcategory":"Electrical",
            "type":"Manufacturing & Wholesale Goods"
        }
    ],
    "sg:phone":"+1 702 222 4038",
    "sg:postcode":"89146",
    "sg:province":"NV",
    "sg:tags":[
        "industrial",
        "parts",
        "supply"
    ],
    "wof:name":"In Tech Sales Corp",
    "wof:placetype":"venue"
},
  "geometry": {"coordinates":[-115.23729400000001,36.144008],"type":"Point"}
}