{
  "type": "Feature",
  "properties": {
    "iso:country":"US",
    "sg:address":"9560 W Sahara",
    "sg:city":"Las Vegas",
    "sg:classifiers":[
        {
            "category":"Restaurant",
            "type":"Food & Drink"
        }
    ],
    "sg:postcode":"89117",
    "sg:province":"NV",
    "sg:tags":[
        "spanish"
    ],
    "sg:website":"www.fireflylv.com",
    "wof:name":"Firefly Tapas Kitchen and Bar",
    "wof:placetype":"venue"
},
  "geometry": {"coordinates":[-115.30291,36.144938],"type":"Point"}
}