{
  "type": "Feature",
  "properties": {
    "iso:country":"US",
    "sg:address":"1250 N Eastern Ave",
    "sg:city":"Las Vegas",
    "sg:classifiers":[
        {
            "category":"Retail",
            "subcategory":"Auto Repair",
            "type":"Services"
        }
    ],
    "sg:phone":"+1 702 639 3991",
    "sg:postcode":"89101",
    "sg:province":"NV",
    "wof:name":"Lussin Auto Sales",
    "wof:placetype":"venue"
},
  "geometry": {"coordinates":[-115.115997,36.184101],"type":"Point"}
}