{
  "type": "Feature",
  "properties": {
    "iso:country":"US",
    "sg:address":"10040 W. Cheyenne Ave",
    "sg:city":"Las Vegas",
    "sg:classifiers":[
        {
            "category":"Restaurant",
            "type":"Food & Drink"
        }
    ],
    "sg:phone":"+1 702 228 8758",
    "sg:postcode":"89129",
    "sg:province":"NV",
    "sg:tags":[
        "sushi",
        "bar",
        "japanese"
    ],
    "sg:website":"www.tokyosushivegas.com/",
    "wof:name":"Tokyo Sushi House",
    "wof:placetype":"venue"
},
  "geometry": {"coordinates":[-115.314374,36.218781],"type":"Point"}
}