{
  "type": "Feature",
  "properties": {
    "iso:country":"US",
    "sg:address":"4523 Las Vegas Blvd",
    "sg:city":"Las Vegas",
    "sg:classifiers":[
        {
            "category":"Building & Trades",
            "subcategory":"Plumbing",
            "type":"Services"
        },
        {
            "category":"Building & Trades",
            "subcategory":"Construction",
            "type":"Services"
        }
    ],
    "sg:phone":"+1 702 834 8095",
    "sg:postcode":"89115",
    "sg:province":"NV",
    "sg:tags":[
        "air",
        "heating",
        "conditioning/hvac"
    ],
    "wof:name":"NOW! Plumbing and Heating",
    "wof:placetype":"venue"
},
  "geometry": {"coordinates":[-115.051431,36.242264],"type":"Point"}
}