{
  "type": "Feature",
  "properties": {
    "iso:country":"US",
    "sg:address":"4211 W Sahara Ave",
    "sg:city":"Las Vegas",
    "sg:classifiers":[
        {
            "category":"Arts & Performance",
            "subcategory":"Theater",
            "type":"Entertainment"
        }
    ],
    "sg:phone":"+1 702 222 0784",
    "sg:postcode":"89102",
    "sg:province":"NV",
    "sg:tags":[
        "musician"
    ],
    "wof:name":"El Peluche Musical",
    "wof:placetype":"venue"
},
  "geometry": {"coordinates":[-115.197731,36.144393],"type":"Point"}
}