{
  "type": "Feature",
  "properties": {
    "iso:country":"US",
    "sg:address":"1223 E Sahara Ave",
    "sg:city":"Las Vegas",
    "sg:classifiers":[
        {
            "category":"Restaurant",
            "type":"Food & Drink"
        }
    ],
    "sg:phone":"+1 702 696 1098",
    "sg:postcode":"89104",
    "sg:province":"NV",
    "sg:tags":[
        "eating"
    ],
    "wof:name":"Cheerful Restaurant",
    "wof:placetype":"venue"
},
  "geometry": {"coordinates":[-115.135279,36.144187],"type":"Point"}
}