{
  "type": "Feature",
  "properties": {
    "iso:country":"US",
    "sg:address":"1900 Western Ave",
    "sg:city":"Las Vegas",
    "sg:classifiers":[
        {
            "category":"Building & Trades",
            "subcategory":"Construction",
            "type":"Services"
        }
    ],
    "sg:phone":"+1 702 450 0707",
    "sg:postcode":"89102",
    "sg:province":"NV",
    "sg:tags":[
        "painter"
    ],
    "wof:name":"Alpha Omega Painting LLC",
    "wof:placetype":"venue"
},
  "geometry": {"coordinates":[-115.164262,36.149417],"type":"Point"}
}