{
  "type": "Feature",
  "properties": {
    "iso:country":"US",
    "sg:address":"8668 Spring Mountain Rd",
    "sg:city":"Las Vegas",
    "sg:classifiers":[
        {
            "category":"Banks & Credit Unions",
            "subcategory":"Bank",
            "type":"Services"
        }
    ],
    "sg:phone":"+1 702 942 2237",
    "sg:postcode":"89117",
    "sg:province":"NV",
    "sg:tags":[
        "loan",
        "real estate"
    ],
    "wof:name":"American Association-Federal",
    "wof:placetype":"venue"
},
  "geometry": {"coordinates":[-115.281067,36.125972],"type":"Point"}
}