{
  "type": "Feature",
  "properties": {
    "iso:country":"US",
    "sg:address":"3128 Las Vegas Boulevard S",
    "sg:city":"Las Vegas",
    "sg:classifiers":[
        {
            "category":"Travel",
            "subcategory":"Hotels & Motels",
            "type":"Entertainment"
        }
    ],
    "sg:phone":"+1 702 878 6711",
    "sg:postcode":"89109",
    "sg:province":"NV",
    "wof:name":"Trump Ruffin",
    "wof:placetype":"venue"
},
  "geometry": {"coordinates":[-115.16824800000001,36.126919],"type":"Point"}
}