{
  "type": "Feature",
  "properties": {
    "iso:country":"US",
    "sg:address":"Forum Shops at Caesars 3500 S Las Vegas Blvd",
    "sg:city":"Las Vegas",
    "sg:classifiers":[
        {
            "category":"Shopping",
            "subcategory":"Beauty & Cosmetics",
            "type":"Retail Goods"
        },
        {
            "category":"Personal",
            "subcategory":"Skin Care",
            "type":"Services"
        }
    ],
    "sg:phone":"+1 702 784 0025",
    "sg:postcode":"89109",
    "sg:province":"NV",
    "sg:tags":[
        "supply"
    ],
    "sg:website":"www.kiehls.com/_us/_en/catalog/f...",
    "wof:name":"Kiehl's",
    "wof:placetype":"venue"
},
  "geometry": {"coordinates":[-115.172913,36.117805],"type":"Point"}
}