{
  "type": "Feature",
  "properties": {
    "iso:country":"US",
    "sg:address":"8275 W Spring Mountain Rd",
    "sg:city":"Las Vegas",
    "sg:classifiers":[
        {
            "category":"Park",
            "type":"Public Place"
        },
        {
            "category":"Sports & Exercise",
            "subcategory":"Swimming Pool",
            "type":"Entertainment"
        }
    ],
    "sg:phone":"+1 702 455 7798",
    "sg:postcode":"89117",
    "sg:province":"NV",
    "sg:website":"www.accessclarkcounty.com/depts/...",
    "wof:name":"Desert Breeze Aquatic Facility",
    "wof:placetype":"venue"
},
  "geometry": {"coordinates":[-115.269971,36.125709],"type":"Point"}
}