{
  "type": "Feature",
  "properties": {
    "iso:country":"US",
    "sg:address":"7936 Lakepoint Cir",
    "sg:city":"Las Vegas",
    "sg:classifiers":[
        {
            "category":"Manufacturing",
            "subcategory":"Printing",
            "type":"Manufacturing & Wholesale Goods"
        }
    ],
    "sg:phone":"+1 702 889 3011",
    "sg:postcode":"89128",
    "sg:province":"NV",
    "sg:tags":[
        "printer"
    ],
    "wof:name":"EASY4COLOR.COM",
    "wof:placetype":"venue"
},
  "geometry": {"coordinates":[-115.267074,36.211282],"type":"Point"}
}