{
  "type": "Feature",
  "properties": {
    "iso:country":"US",
    "sg:address":"900 Karen Ave",
    "sg:city":"Las Vegas",
    "sg:classifiers":[
        {
            "category":"Professional",
            "subcategory":"Lawyer & Legal Services",
            "type":"Services"
        }
    ],
    "sg:phone":"+1 702 796 4300",
    "sg:postcode":"89109",
    "sg:province":"NV",
    "sg:tags":[
        "personal",
        "injury"
    ],
    "wof:name":"Law Office of Kenneth Sheehan",
    "wof:placetype":"venue"
},
  "geometry": {"coordinates":[-115.14299800000001,36.140499],"type":"Point"}
}