{
  "type": "Feature",
  "properties": {
    "iso:country":"US",
    "sg:address":"843 W Basin Ave",
    "sg:city":"Pahrump",
    "sg:classifiers":[
        {
            "category":"Shopping",
            "subcategory":"Bicycles & Sporting Goods",
            "type":"Retail Goods"
        }
    ],
    "sg:phone":"+1 775 727 5472",
    "sg:postcode":"89060",
    "sg:province":"NV",
    "sg:tags":[
        "saddlery",
        "harness"
    ],
    "wof:name":"Wehrlybird Leather",
    "wof:placetype":"venue"
},
  "geometry": {"coordinates":[-116.028139,36.219553],"type":"Point"}
}