{
  "type": "Feature",
  "properties": {
    "iso:country":"US",
    "sg:address":"4655 Quality",
    "sg:city":"Las Vegas",
    "sg:classifiers":[
        {
            "category":"Shopping",
            "subcategory":"Jewelry",
            "type":"Retail Goods"
        }
    ],
    "sg:phone":"+1 702 222 4374",
    "sg:postcode":"89103",
    "sg:province":"NV",
    "sg:tags":[
        "clocks"
    ],
    "wof:name":"Around The Clock",
    "wof:placetype":"venue"
},
  "geometry": {"coordinates":[-115.20608,36.105793],"type":"Point"}
}