{
  "type": "Feature",
  "properties": {
    "iso:country":"US",
    "sg:address":"3456 Las Vegas Fwy",
    "sg:city":"North Las Vegas",
    "sg:classifiers":[
        {
            "category":"Personal",
            "subcategory":"Beauty Salon",
            "type":"Services"
        }
    ],
    "sg:phone":"+1 702 399 3700",
    "sg:postcode":"89030",
    "sg:province":"NV",
    "sg:tags":[
        "shop"
    ],
    "wof:name":"Ebony & Ivory Beauty Salon",
    "wof:placetype":"venue"
},
  "geometry": {"coordinates":[-115.118651,36.224656],"type":"Point"}
}