{
  "type": "Feature",
  "properties": {
    "iso:country":"US",
    "sg:address":"2778 Newburgh Way",
    "sg:city":"Reno",
    "sg:classifiers":[
        {
            "category":"Building & Trades",
            "subcategory":"Construction",
            "type":"Services"
        }
    ],
    "sg:phone":"+1 775 787 2828",
    "sg:postcode":"89523",
    "sg:province":"NV",
    "sg:tags":[
        "plastering",
        "contractor"
    ],
    "wof:name":"Buus-Khan Plastering Co",
    "wof:placetype":"venue"
},
  "geometry": {"coordinates":[-119.876889,39.542191],"type":"Point"}
}