{
  "type": "Feature",
  "properties": {
    "iso:country":"US",
    "sg:address":"8620 Peace Way",
    "sg:city":"Las Vegas",
    "sg:classifiers":[
        {
            "category":"Real Estate",
            "subcategory":"Real Estate Operator",
            "type":"Services"
        }
    ],
    "sg:phone":"+1 702 367 0878",
    "sg:postcode":"89147",
    "sg:province":"NV",
    "sg:tags":[
        "building",
        "nonresidential"
    ],
    "wof:name":"Five Star Personal Shopping",
    "wof:placetype":"venue"
},
  "geometry": {"coordinates":[-115.28091999999999,36.107554],"type":"Point"}
}