{
  "type": "Feature",
  "properties": {
    "iso:country":"US",
    "sg:address":"535 Sierra Vista Drive",
    "sg:city":"Las Vegas",
    "sg:classifiers":[
        {
            "category":"Real Estate",
            "subcategory":"Real Estate Operator",
            "type":"Services"
        }
    ],
    "sg:phone":"+1 702 369 0789",
    "sg:postcode":"89169",
    "sg:province":"NV",
    "sg:tags":[
        "apartment"
    ],
    "wof:name":"Cordoba Arms Apts",
    "wof:placetype":"venue"
},
  "geometry": {"coordinates":[-115.150284,36.126856],"type":"Point"}
}