{
  "type": "Feature",
  "properties": {
    "iso:country":"US",
    "sg:address":"3765 Casa Colorado Ave",
    "sg:city":"Las Vegas",
    "sg:classifiers":[
        {
            "category":"Home & Garden",
            "subcategory":"Hardware",
            "type":"Retail Goods"
        }
    ],
    "sg:phone":"+1 702 683 7213",
    "sg:postcode":"89121",
    "sg:province":"NV",
    "wof:name":"Luvis Value Store",
    "wof:placetype":"venue"
},
  "geometry": {"coordinates":[-115.078014,36.121668],"type":"Point"}
}