{
  "type": "Feature",
  "properties": {
    "iso:country":"US",
    "sg:address":"1829 E Charleston Blvd",
    "sg:city":"Las Vegas",
    "sg:classifiers":[
        {
            "category":"Organizations",
            "subcategory":"Religious Organization",
            "type":"Services"
        }
    ],
    "sg:phone":"+1 702 444 0516",
    "sg:postcode":"89104",
    "sg:province":"NV",
    "sg:tags":[
        "church"
    ],
    "wof:name":"Iglesia De Dios Pentecostal",
    "wof:placetype":"venue"
},
  "geometry": {"coordinates":[-115.123851,36.15894],"type":"Point"}
}