{
  "type": "Feature",
  "properties": {
    "iso:country":"US",
    "sg:address":"5765 Holmby Ave",
    "sg:city":"Las Vegas",
    "sg:classifiers":[
        {
            "category":"Social Services",
            "subcategory":"Child Care",
            "type":"Services"
        }
    ],
    "sg:phone":"+1 702 870 8325",
    "sg:postcode":"89146",
    "sg:province":"NV",
    "sg:tags":[
        "day"
    ],
    "wof:name":"Halls Day Care Center",
    "wof:placetype":"venue"
},
  "geometry": {"coordinates":[-115.21995699999999,36.157334],"type":"Point"}
}