{
  "type": "Feature",
  "properties": {
    "iso:country":"US",
    "sg:address":"9737 Sierra Mesa Ave",
    "sg:city":"Las Vegas",
    "sg:classifiers":[
        {
            "category":"Social Services",
            "type":"Services"
        }
    ],
    "sg:phone":"+1 702 254 8884",
    "sg:postcode":"89117",
    "sg:province":"NV",
    "wof:name":"Crisis Communications Inc",
    "wof:placetype":"venue"
},
  "geometry": {"coordinates":[-115.307521,36.135291],"type":"Point"}
}