{
  "type": "Feature",
  "properties": {
    "iso:country":"US",
    "sg:address":"3377 Las Vegas Blvd S Ste 2125",
    "sg:city":"Las Vegas",
    "sg:classifiers":[
        {
            "category":"Shopping",
            "subcategory":"Jewelry",
            "type":"Retail Goods"
        }
    ],
    "sg:phone":"+1 702 734 1603",
    "sg:postcode":"89109",
    "sg:province":"NV",
    "wof:name":"Gioia",
    "wof:placetype":"venue"
},
  "geometry": {"coordinates":[-115.1714,36.12125],"type":"Point"}
}