{
  "type": "Feature",
  "properties": {
    "iso:country":"US",
    "sg:address":"7385 Prairie Falcon Rd",
    "sg:city":"Las Vegas",
    "sg:classifiers":[
        {
            "category":"Professional",
            "subcategory":"Computer Services",
            "type":"Services"
        }
    ],
    "sg:phone":"+1 702 856 3363",
    "sg:postcode":"89128",
    "sg:province":"NV",
    "sg:tags":[
        "consultant",
        "designer"
    ],
    "wof:name":"Com Global Information Tech",
    "wof:placetype":"venue"
},
  "geometry": {"coordinates":[-115.251748,36.206195],"type":"Point"}
}