{
  "type": "Feature",
  "properties": {
    "iso:country":"US",
    "sg:address":"2395 Roman Dr",
    "sg:city":"Sparks",
    "sg:classifiers":[
        {
            "category":"Autos & Motor Vehicles",
            "subcategory":"Auto Supplies",
            "type":"Retail Goods"
        }
    ],
    "sg:phone":"+1 775 323 1822",
    "sg:postcode":"89434",
    "sg:province":"NV",
    "sg:tags":[
        "accessories-wholesale",
        "automobile",
        "part",
        "parts",
        "manufacturer"
    ],
    "sg:website":"http://www.aboveboardmfg.com",
    "wof:name":"Dynapix Performance",
    "wof:placetype":"venue"
},
  "geometry": {"coordinates":[-119.70329700000001,39.552439],"type":"Point"}
}