{
  "type": "Feature",
  "properties": {
    "iso:country":"US",
    "sg:address":"5980 Spring Mountain Rd",
    "sg:city":"Las Vegas",
    "sg:classifiers":[
        {
            "category":"Retail",
            "subcategory":"Laundry & Dry Cleaning",
            "type":"Services"
        }
    ],
    "sg:phone":"+1 702 562 1940",
    "sg:postcode":"89146",
    "sg:province":"NV",
    "wof:name":"Rose's Shirts & Alterations",
    "wof:placetype":"venue"
},
  "geometry": {"coordinates":[-115.22317700000001,36.125654],"type":"Point"}
}