{
  "type": "Feature",
  "properties": {
    "iso:country":"US",
    "sg:address":"3504 S Maryland Pkwy",
    "sg:city":"Las Vegas",
    "sg:classifiers":[
        {
            "category":"Shopping",
            "subcategory":"Clothing, Apparel, & Fashions",
            "type":"Retail Goods"
        }
    ],
    "sg:phone":"+1 702 791 6865",
    "sg:postcode":"89109",
    "sg:province":"NV",
    "sg:tags":[
        "item",
        "boutique"
    ],
    "wof:name":"Claire's Boutique",
    "wof:placetype":"venue"
},
  "geometry": {"coordinates":[-115.137074,36.126903],"type":"Point"}
}