{
  "type": "Feature",
  "properties": {
    "iso:country":"US",
    "sg:address":"4130 Snowshoe Ln",
    "sg:city":"Reno",
    "sg:classifiers":[
        {
            "category":"Wholesale",
            "subcategory":"Vending Machines",
            "type":"Manufacturing & Wholesale Goods"
        }
    ],
    "sg:phone":"+1 775 827 6608",
    "sg:postcode":"89502",
    "sg:province":"NV",
    "wof:name":"Snack Queen",
    "wof:placetype":"venue"
},
  "geometry": {"coordinates":[-119.75399899999999,39.478409],"type":"Point"}
}