{
  "type": "Feature",
  "properties": {
    "iso:country":"US",
    "sg:address":"2363 5th St",
    "sg:city":"Elko",
    "sg:classifiers":[
        {
            "category":"Social Services",
            "type":"Services"
        }
    ],
    "sg:phone":"+1 775 738 1994",
    "sg:postcode":"89801",
    "sg:province":"NV",
    "wof:name":"Daniel J Tutty Lcsw Lacd",
    "wof:placetype":"venue"
},
  "geometry": {"coordinates":[-115.783008,40.846082],"type":"Point"}
}