{
  "type": "Feature",
  "properties": {
    "iso:country":"US",
    "sg:address":"1803 Western Ave",
    "sg:city":"Las Vegas",
    "sg:classifiers":[
        {
            "category":"Home & Garden",
            "subcategory":"Building Materials",
            "type":"Retail Goods"
        }
    ],
    "sg:phone":"+1 702 385 7199",
    "sg:postcode":"89102",
    "sg:province":"NV",
    "sg:tags":[
        "siding",
        "gutter",
        "rain"
    ],
    "sg:website":"www.americanbuilderslv.com",
    "wof:name":"American Builders",
    "wof:placetype":"venue"
},
  "geometry": {"coordinates":[-115.162176,36.152153],"type":"Point"}
}