{
  "type": "Feature",
  "properties": {
    "iso:country":"US",
    "sg:address":"2696 West Ann Road",
    "sg:city":"North Las Vegas",
    "sg:classifiers":[
        {
            "category":"Restaurant",
            "type":"Food & Drink"
        }
    ],
    "sg:phone":"+1 702 656 8823",
    "sg:postcode":"89031",
    "sg:province":"NV",
    "sg:tags":[
        "thai",
        "sushi",
        "bar",
        "chinese"
    ],
    "sg:website":"www.lvthaibasil.com",
    "wof:name":"Thai Basil",
    "wof:placetype":"venue"
},
  "geometry": {"coordinates":[-115.177666,36.261787],"type":"Point"}
}