{
  "type": "Feature",
  "properties": {
    "iso:country":"US",
    "sg:address":"7 Hematite Dr",
    "sg:city":"Carson City",
    "sg:classifiers":[
        {
            "category":"Personal",
            "type":"Services"
        }
    ],
    "sg:phone":"+1 775 246 3195",
    "sg:postcode":"89706",
    "sg:province":"NV",
    "wof:name":"Custom Handyman",
    "wof:placetype":"venue"
},
  "geometry": {"coordinates":[-119.676408,39.222011],"type":"Point"}
}