{
  "type": "Feature",
  "properties": {
    "iso:country":"US",
    "sg:address":"3312 Crystal Tower St",
    "sg:city":"Las Vegas",
    "sg:classifiers":[
        {
            "category":"Professional",
            "type":"Services"
        }
    ],
    "sg:phone":"+1 702 256 7946",
    "sg:postcode":"89129",
    "sg:province":"NV",
    "wof:name":"Better Pool LLC A",
    "wof:placetype":"venue"
},
  "geometry": {"coordinates":[-115.32006,36.222791],"type":"Point"}
}