{
  "type": "Feature",
  "properties": {
    "iso:country":"US",
    "sg:address":"3006 S Maryland Pkwy Ste 250",
    "sg:city":"Las Vegas",
    "sg:classifiers":[
        {
            "category":"Community Center",
            "type":"Public Place"
        }
    ],
    "sg:phone":"+1 702 731 8807",
    "sg:postcode":"89169",
    "sg:province":"NV",
    "sg:tags":[
        "medical"
    ],
    "wof:name":"The Breast Center",
    "wof:placetype":"venue"
},
  "geometry": {"coordinates":[-115.135677,36.135499],"type":"Point"}
}