{
  "type": "Feature",
  "properties": {
    "iso:country":"US",
    "sg:address":"800 Saylor Way",
    "sg:city":"Las Vegas",
    "sg:classifiers":[
        {
            "category":"Retail",
            "subcategory":"Portrait Studio",
            "type":"Services"
        }
    ],
    "sg:phone":"+1 702 870 7436",
    "sg:postcode":"89107",
    "sg:province":"NV",
    "sg:tags":[
        "photographer"
    ],
    "wof:name":"Substantial Stocking Shape",
    "wof:placetype":"venue"
},
  "geometry": {"coordinates":[-115.219878,36.180845],"type":"Point"}
}