{
  "type": "Feature",
  "properties": {
    "iso:country":"US",
    "sg:address":"2900 Clear Acre Ln",
    "sg:city":"Reno",
    "sg:classifiers":[
        {
            "category":"Insurance",
            "subcategory":"Insurance Agent",
            "type":"Services"
        },
        {
            "category":"Insurance",
            "subcategory":"Hazard Insurance",
            "type":"Services"
        },
        {
            "category":"Insurance",
            "subcategory":"Title Insurance",
            "type":"Services"
        },
        {
            "category":"Insurance",
            "subcategory":"Life Insurance",
            "type":"Services"
        }
    ],
    "sg:phone":"+1 775 324 4495",
    "sg:postcode":"89512",
    "sg:province":"NV",
    "sg:tags":[
        "business",
        "auto",
        "commercial",
        "homeowner",
        "motorcycle",
        "renter"
    ],
    "wof:name":"Allstate Insurance Company - Heidi Hamand",
    "wof:placetype":"venue"
},
  "geometry": {"coordinates":[-119.791548,39.557],"type":"Point"}
}