{
  "type": "Feature",
  "properties": {
    "iso:country":"US",
    "sg:address":"8375 W Flamingo Rd",
    "sg:city":"Las Vegas",
    "sg:classifiers":[
        {
            "category":"Professional",
            "subcategory":"Advertising",
            "type":"Services"
        }
    ],
    "sg:phone":"+1 702 251 3100",
    "sg:postcode":"89147",
    "sg:province":"NV",
    "sg:tags":[
        "counselor",
        "agency"
    ],
    "wof:name":"American Media Corporation",
    "wof:placetype":"venue"
},
  "geometry": {"coordinates":[-115.278007,36.114811],"type":"Point"}
}