{
  "type": "Feature",
  "properties": {
    "iso:country":"US",
    "sg:address":"2951 Siena Heights Dr",
    "sg:city":"Henderson",
    "sg:classifiers":[
        {
            "category":"Real Estate",
            "subcategory":"Real Estate Operator",
            "type":"Services"
        }
    ],
    "sg:phone":"+1 702 214 2600",
    "sg:postcode":"89052",
    "sg:province":"NV",
    "sg:tags":[
        "apartment"
    ],
    "wof:name":"Siena Villas",
    "wof:placetype":"venue"
},
  "geometry": {"coordinates":[-115.116044,36.00224],"type":"Point"}
}