{
  "type": "Feature",
  "properties": {
    "iso:country":"US",
    "sg:address":"2710 E Patrick Ln",
    "sg:city":"Las Vegas",
    "sg:classifiers":[
        {
            "category":"Building & Trades",
            "subcategory":"Electrical",
            "type":"Services"
        }
    ],
    "sg:phone":"+1 702 860 4510",
    "sg:postcode":"89120",
    "sg:province":"NV",
    "sg:tags":[
        "electric",
        "contractor"
    ],
    "wof:name":"Costas Electric",
    "wof:placetype":"venue"
},
  "geometry": {"coordinates":[-115.11313199999999,36.079016],"type":"Point"}
}