{
  "type": "Feature",
  "properties": {
    "iso:country":"US",
    "sg:address":"3220 US Hwy 50",
    "sg:city":"Carson City",
    "sg:classifiers":[
        {
            "category":"Restaurant",
            "type":"Food & Drink"
        }
    ],
    "sg:phone":"+1 775 884 9394",
    "sg:postcode":"89701",
    "sg:province":"NV",
    "wof:name":"El Aguila Real Mexican Rstrnt",
    "wof:placetype":"venue"
},
  "geometry": {"coordinates":[-119.769262,39.136883],"type":"Point"}
}