{
  "type": "Feature",
  "properties": {
    "iso:country":"US",
    "sg:address":"1716 Yellowwood Dr",
    "sg:city":"Las Vegas",
    "sg:classifiers":[
        {
            "category":"Shopping",
            "type":"Retail Goods"
        }
    ],
    "sg:phone":"+1 702 896 7148",
    "sg:postcode":"89123",
    "sg:province":"NV",
    "sg:tags":[
        "merchandise"
    ],
    "wof:name":"Pet Doors N More",
    "wof:placetype":"venue"
},
  "geometry": {"coordinates":[-115.13024,36.045927],"type":"Point"}
}