{
  "type": "Feature",
  "properties": {
    "iso:country":"US",
    "sg:address":"600 Jackson Ave",
    "sg:city":"Las Vegas",
    "sg:classifiers":[
        {
            "category":"Casinos & Gambling",
            "type":"Entertainment"
        }
    ],
    "sg:phone":"+1 702 647 3995",
    "sg:postcode":"89106",
    "sg:province":"NV",
    "wof:name":"New Town Tavern",
    "wof:placetype":"venue"
},
  "geometry": {"coordinates":[-115.150002,36.186001],"type":"Point"}
}