{
  "type": "Feature",
  "properties": {
    "iso:country":"US",
    "sg:address":"5562 Mountain Vista St",
    "sg:city":"Las Vegas",
    "sg:classifiers":[
        {
            "category":"Professional",
            "subcategory":"Business Services",
            "type":"Services"
        }
    ],
    "sg:phone":"+1 702 451 2741",
    "sg:postcode":"89120",
    "sg:province":"NV",
    "wof:name":"Patch Enterprises LLC",
    "wof:placetype":"venue"
},
  "geometry": {"coordinates":[-115.072984,36.085693],"type":"Point"}
}