{
  "type": "Feature",
  "properties": {
    "iso:country":"US",
    "sg:address":"8004 Dover Shores Ave",
    "sg:city":"Las Vegas",
    "sg:classifiers":[
        {
            "category":"Home & Garden",
            "subcategory":"Building Materials",
            "type":"Retail Goods"
        }
    ],
    "sg:phone":"+1 702 558 5000",
    "sg:postcode":"89128",
    "sg:province":"NV",
    "sg:tags":[
        "door"
    ],
    "wof:name":"D & G Garage Door Svc",
    "wof:placetype":"venue"
},
  "geometry": {"coordinates":[-115.268458,36.201937],"type":"Point"}
}