{
  "type": "Feature",
  "properties": {
    "iso:country":"US",
    "sg:address":"2421 E Gowan Rd",
    "sg:city":"North Las Vegas",
    "sg:classifiers":[
        {
            "category":"Building & Trades",
            "subcategory":"Plumbing",
            "type":"Services"
        }
    ],
    "sg:phone":"+1 702 873 2350",
    "sg:postcode":"89030",
    "sg:province":"NV",
    "sg:tags":[
        "air",
        "heating",
        "contractor",
        "system",
        "conditioning"
    ],
    "wof:name":"Duckett Air Conditioning  Inc",
    "wof:placetype":"venue"
},
  "geometry": {"coordinates":[-115.113007,36.224915],"type":"Point"}
}