{
  "type": "Feature",
  "properties": {
    "iso:country":"US",
    "sg:address":"1064 Sawmill Rd",
    "sg:city":"Incline Village",
    "sg:classifiers":[
        {
            "category":"Wholesale",
            "subcategory":"Chemicals & Plastics",
            "type":"Manufacturing & Wholesale Goods"
        }
    ],
    "sg:phone":"+1 415 221 5637",
    "sg:postcode":"89451",
    "sg:province":"NV",
    "sg:tags":[
        "industrial"
    ],
    "wof:name":"Pacific Chlorine Inc",
    "wof:placetype":"venue"
},
  "geometry": {"coordinates":[-119.93348899999999,39.242052],"type":"Point"}
}