{
  "type": "Feature",
  "properties": {
    "iso:country":"US",
    "sg:address":"250 Rhodes Rd",
    "sg:city":"Reno",
    "sg:classifiers":[
        {
            "category":"Building & Trades",
            "subcategory":"Landscaping Services",
            "type":"Services"
        }
    ],
    "sg:phone":"+1 775 849 8505",
    "sg:postcode":"89521",
    "sg:province":"NV",
    "wof:name":"Mountain Shadow Lawn",
    "wof:placetype":"venue"
},
  "geometry": {"coordinates":[-119.741904,39.375533],"type":"Point"}
}