{
  "type": "Feature",
  "properties": {
    "iso:country":"US",
    "sg:address":"2035 Dickerson Rd",
    "sg:city":"Reno",
    "sg:classifiers":[
        {
            "category":"Manufacturing",
            "subcategory":"Signs",
            "type":"Manufacturing & Wholesale Goods"
        }
    ],
    "sg:phone":"+1 775 786 1737",
    "sg:postcode":"89503",
    "sg:province":"NV",
    "sg:tags":[
        "specialty",
        "mfg"
    ],
    "wof:name":"Sign Shop The",
    "wof:placetype":"venue"
},
  "geometry": {"coordinates":[-119.83809599999999,39.522186],"type":"Point"}
}