{
  "type": "Feature",
  "properties": {
    "iso:country":"US",
    "sg:address":"330 Carousel Pkwy",
    "sg:city":"Henderson",
    "sg:classifiers":[
        {
            "category":"Real Estate",
            "subcategory":"Architect",
            "type":"Services"
        }
    ],
    "sg:phone":"+1 702 407 2479",
    "sg:postcode":"89014",
    "sg:province":"NV",
    "wof:name":"D R Horton Wow",
    "wof:placetype":"venue"
},
  "geometry": {"coordinates":[-115.032857,36.055019],"type":"Point"}
}