{
  "type": "Feature",
  "properties": {
    "iso:country":"US",
    "sg:address":"575 Forest St",
    "sg:city":"Reno",
    "sg:classifiers":[
        {
            "category":"Professional",
            "subcategory":"Lawyer & Legal Services",
            "type":"Services"
        }
    ],
    "sg:phone":"+1 775 329 5505",
    "sg:postcode":"89509",
    "sg:province":"NV",
    "sg:tags":[
        "attorney"
    ],
    "sg:website":"www.saint-aubin.org",
    "wof:name":"Robert F Saint-Aubin",
    "wof:placetype":"venue"
},
  "geometry": {"coordinates":[-119.811406,39.51987],"type":"Point"}
}