{
  "type": "Feature",
  "properties": {
    "iso:country":"US",
    "sg:address":"2437 Twin Flower Cir",
    "sg:city":"Las Vegas",
    "sg:classifiers":[
        {
            "category":"Professional",
            "subcategory":"Management & Consulting",
            "type":"Services"
        }
    ],
    "sg:phone":"+1 702 233 4088",
    "sg:postcode":"89134",
    "sg:province":"NV",
    "sg:tags":[
        "consultant",
        "broker"
    ],
    "wof:name":"College Line",
    "wof:placetype":"venue"
},
  "geometry": {"coordinates":[-115.297178,36.204881],"type":"Point"}
}