{
  "type": "Feature",
  "properties": {
    "iso:country":"US",
    "sg:address":"1606 Lynette Ln",
    "sg:city":"North Las Vegas",
    "sg:classifiers":[
        {
            "category":"Retail",
            "subcategory":"Portrait Studio",
            "type":"Services"
        }
    ],
    "sg:phone":"+1 702 636 2703",
    "sg:postcode":"89031",
    "sg:province":"NV",
    "sg:tags":[
        "photo"
    ],
    "wof:name":"All Occassions Photography",
    "wof:placetype":"venue"
},
  "geometry": {"coordinates":[-115.16558999999999,36.254889],"type":"Point"}
}