{
  "type": "Feature",
  "properties": {
    "iso:country":"US",
    "sg:address":"3681 E Mountcrest Dr",
    "sg:city":"Las Vegas",
    "sg:classifiers":[
        {
            "category":"Real Estate",
            "subcategory":"Real Estate Agent",
            "type":"Services"
        }
    ],
    "sg:phone":"+1 702 456 1432",
    "sg:postcode":"89121",
    "sg:province":"NV",
    "wof:name":"Jean Nikolich Co",
    "wof:placetype":"venue"
},
  "geometry": {"coordinates":[-115.094108,36.109169],"type":"Point"}
}