{
  "type": "Feature",
  "properties": {
    "iso:country":"US",
    "sg:address":"1930 Village Center Cir Ste 4",
    "sg:city":"Las Vegas",
    "sg:classifiers":[
        {
            "category":"Shopping",
            "subcategory":"Pets & Pet Supplies",
            "type":"Retail Goods"
        }
    ],
    "sg:phone":"+1 702 243 0004",
    "sg:postcode":"89134",
    "sg:province":"NV",
    "sg:tags":[
        "store"
    ],
    "sg:website":"www.scraps4pets.com",
    "wof:name":"Scraps 4 Pets",
    "wof:placetype":"venue"
},
  "geometry": {"coordinates":[-115.304053,36.192875],"type":"Point"}
}