{
  "type": "Feature",
  "properties": {
    "iso:country":"US",
    "sg:address":"5740 Arville St",
    "sg:city":"Las Vegas",
    "sg:classifiers":[
        {
            "category":"Manufacturing",
            "subcategory":"Building Materials",
            "type":"Manufacturing & Wholesale Goods"
        },
        {
            "category":"Home & Garden",
            "subcategory":"Furniture",
            "type":"Retail Goods"
        }
    ],
    "sg:phone":"+1 702 220 3728",
    "sg:postcode":"89118",
    "sg:province":"NV",
    "sg:tags":[
        "cabinet",
        "wood",
        "kitchen",
        "mfg"
    ],
    "wof:name":"Euro Kitchen Cabinets",
    "wof:placetype":"venue"
},
  "geometry": {"coordinates":[-115.199101,36.085239],"type":"Point"}
}