{
  "type": "Feature",
  "properties": {
    "iso:country":"US",
    "sg:address":"1903 Spode Ave",
    "sg:city":"Henderson",
    "sg:classifiers":[
        {
            "category":"Building & Trades",
            "subcategory":"Landscaping Services",
            "type":"Services"
        }
    ],
    "sg:phone":"+1 702 434 4100",
    "sg:postcode":"89014",
    "sg:province":"NV",
    "sg:tags":[
        "landscape"
    ],
    "wof:name":"Ainslies Evergreen Ldscp Maint",
    "wof:placetype":"venue"
},
  "geometry": {"coordinates":[-115.071095,36.056722],"type":"Point"}
}