{
  "type": "Feature",
  "properties": {
    "iso:country":"US",
    "sg:address":"1000 S Rainbow Blvd",
    "sg:city":"Las Vegas",
    "sg:classifiers":[
        {
            "category":"Health Services",
            "subcategory":"Doctor",
            "type":"Services"
        }
    ],
    "sg:phone":"+1 702 259 0088",
    "sg:postcode":"89145",
    "sg:province":"NV",
    "sg:tags":[
        "physician",
        "surgeon"
    ],
    "wof:name":"Summit Medical Group",
    "wof:placetype":"venue"
},
  "geometry": {"coordinates":[-115.244166,36.165245],"type":"Point"}
}