{
  "type": "Feature",
  "properties": {
    "iso:country":"US",
    "sg:address":"2003 E Charleston Boulevard",
    "sg:city":"Las Vegas",
    "sg:classifiers":[
        {
            "category":"Shopping",
            "subcategory":"Crafts & Fabrics",
            "type":"Retail Goods"
        }
    ],
    "sg:phone":"+1 702 382 5404",
    "sg:postcode":"89104",
    "sg:province":"NV",
    "sg:tags":[
        "art",
        "supply"
    ],
    "sg:website":"www.desertartsupplies.com",
    "wof:name":"Desert Art Supplies",
    "wof:placetype":"venue"
},
  "geometry": {"coordinates":[-115.121308,36.158962],"type":"Point"}
}