{
  "type": "Feature",
  "properties": {
    "iso:country":"US",
    "sg:address":"200 S 1st St",
    "sg:city":"Las Vegas",
    "sg:classifiers":[
        {
            "category":"Government",
            "subcategory":"Office",
            "type":"Public Place"
        }
    ],
    "sg:phone":"+1 702 455 4380",
    "sg:postcode":"89101",
    "sg:province":"NV",
    "wof:name":"Honorable Deborah J Lippis",
    "wof:placetype":"venue"
},
  "geometry": {"coordinates":[-115.146733,36.168874],"type":"Point"}
}