{
  "type": "Feature",
  "properties": {
    "iso:country":"US",
    "sg:address":"9500 W Maule Ave",
    "sg:city":"Las Vegas",
    "sg:classifiers":[
        {
            "category":"Real Estate",
            "subcategory":"Real Estate Operator",
            "type":"Services"
        }
    ],
    "sg:phone":"+1 702 740 5541",
    "sg:postcode":"89148",
    "sg:province":"NV",
    "sg:tags":[
        "apartment"
    ],
    "sg:website":"www.acernovillasapartments.com",
    "wof:name":"Acerno Villas",
    "wof:placetype":"venue"
},
  "geometry": {"coordinates":[-115.29991,36.063017],"type":"Point"}
}