{
  "type": "Feature",
  "properties": {
    "iso:country":"US",
    "sg:address":"9517 Tournament Canyon Dr",
    "sg:city":"Las Vegas",
    "sg:classifiers":[
        {
            "category":"Professional",
            "subcategory":"Management & Consulting",
            "type":"Services"
        }
    ],
    "sg:phone":"+1 702 360 1870",
    "sg:postcode":"89144",
    "sg:province":"NV",
    "sg:tags":[
        "consultant",
        "traffic"
    ],
    "wof:name":"Traffic Unlimited Ltd",
    "wof:placetype":"venue"
},
  "geometry": {"coordinates":[-115.303952,36.177724],"type":"Point"}
}