{
  "type": "Feature",
  "properties": {
    "iso:country":"US",
    "sg:address":"3016 Half Shell Way",
    "sg:city":"Las Vegas",
    "sg:classifiers":[
        {
            "category":"Building & Trades",
            "subcategory":"Electrical",
            "type":"Services"
        }
    ],
    "sg:phone":"+1 702 658 8507",
    "sg:postcode":"89128",
    "sg:province":"NV",
    "sg:tags":[
        "electric",
        "contractor"
    ],
    "wof:name":"Sparky Electric",
    "wof:placetype":"venue"
},
  "geometry": {"coordinates":[-115.275148,36.215618],"type":"Point"}
}