{
  "type": "Feature",
  "properties": {
    "iso:country":"US",
    "sg:address":"7005 Speedway Blvd",
    "sg:city":"Las Vegas",
    "sg:classifiers":[
        {
            "category":"Home & Garden",
            "subcategory":"Home Furnishings",
            "type":"Retail Goods"
        }
    ],
    "sg:phone":"+1 702 643 4860",
    "sg:postcode":"89115",
    "sg:province":"NV",
    "sg:tags":[
        "window",
        "covering"
    ],
    "wof:name":"Lindsco Inc",
    "wof:placetype":"venue"
},
  "geometry": {"coordinates":[-115.020056,36.279227],"type":"Point"}
}