{
  "type": "Feature",
  "properties": {
    "iso:country":"US",
    "sg:address":"4864 Cecile Ave",
    "sg:city":"Las Vegas",
    "sg:classifiers":[
        {
            "category":"Building & Trades",
            "subcategory":"Cleaning & Sanitation",
            "type":"Services"
        }
    ],
    "sg:phone":"+1 888 548 1722",
    "sg:postcode":"89115",
    "sg:province":"NV",
    "sg:tags":[
        "home"
    ],
    "sg:website":"homerestorationinlasvegas.info",
    "wof:name":"Rapid Response Restoration Inc -Water Damage Restoration Service",
    "wof:placetype":"venue"
},
  "geometry": {"coordinates":[-115.06749600000001,36.214975],"type":"Point"}
}