{
  "type": "Feature",
  "properties": {
    "iso:country":"US",
    "sg:address":"581 Green Acres Dr",
    "sg:city":"Gardnerville",
    "sg:classifiers":[
        {
            "category":"Shopping Center",
            "type":"Public Place"
        }
    ],
    "sg:phone":"+1 775 265 2436",
    "sg:postcode":"89460",
    "sg:province":"NV",
    "sg:tags":[
        "mall"
    ],
    "wof:name":"Transier Investments Inc",
    "wof:placetype":"venue"
},
  "geometry": {"coordinates":[-119.808621,38.881773],"type":"Point"}
}