{
  "type": "Feature",
  "properties": {
    "iso:country":"US",
    "sg:address":"795 Tillman Ln",
    "sg:city":"Gardnerville",
    "sg:classifiers":[
        {
            "category":"Restaurant",
            "type":"Food & Drink"
        }
    ],
    "sg:phone":"+1 775 265 1667",
    "sg:postcode":"89423",
    "sg:province":"NV",
    "sg:tags":[
        "shop",
        "coffee",
        "eating"
    ],
    "wof:name":"Northern Nevada Pony Espresso",
    "wof:placetype":"venue"
},
  "geometry": {"coordinates":[-119.74205,38.897441],"type":"Point"}
}