{
  "type": "Feature",
  "properties": {
    "iso:country":"US",
    "sg:address":"5051 Stewart Ave",
    "sg:city":"Las Vegas",
    "sg:classifiers":[
        {
            "category":"Health Services",
            "subcategory":"Health Practitioner",
            "type":"Services"
        }
    ],
    "sg:phone":"+1 702 309 1900",
    "sg:postcode":"89110",
    "sg:province":"NV",
    "sg:tags":[
        "therapy",
        "physical"
    ],
    "wof:name":"New Century Rehabilitation Ll",
    "wof:placetype":"venue"
},
  "geometry": {"coordinates":[-115.063215,36.166281],"type":"Point"}
}