{
  "type": "Feature",
  "properties": {
    "iso:country":"US",
    "sg:address":"1095 S Rock Blvd",
    "sg:city":"Reno",
    "sg:classifiers":[
        {
            "category":"Home & Garden",
            "subcategory":"Household Appliances",
            "type":"Retail Goods"
        },
        {
            "category":"Wholesale",
            "subcategory":"Construction Materials",
            "type":"Manufacturing & Wholesale Goods"
        },
        {
            "category":"Home & Garden",
            "subcategory":"Building Materials",
            "type":"Retail Goods"
        },
        {
            "category":"Wholesale",
            "subcategory":"Home Furnishings",
            "type":"Manufacturing & Wholesale Goods"
        }
    ],
    "sg:phone":"+1 775 688 5000",
    "sg:postcode":"89502",
    "sg:province":"NV",
    "sg:tags":[
        "bathroom",
        "supply",
        "fixture",
        "major",
        "cabinet",
        "part",
        "plumbing",
        "fixtures",
        "accessory",
        "supplies-wholesale",
        "manufacturer"
    ],
    "sg:website":"http://www-ferguson-com.netsolads.com/homeowner.shtml?_nsag=39485",
    "wof:name":"Ferguson Bath & Kitchen Gallery",
    "wof:placetype":"venue"
},
  "geometry": {"coordinates":[-119.754434,39.499977],"type":"Point"}
}