{
  "type": "Feature",
  "properties": {
    "iso:country":"US",
    "sg:address":"140 W 1st Ave",
    "sg:city":"Sun Valley",
    "sg:classifiers":[
        {
            "category":"Restaurant",
            "type":"Food & Drink"
        }
    ],
    "sg:menulink":"http://www.allmenus.com/nv/sun-valley/196573-mcdonalds/menu/",
    "sg:postcode":"89433",
    "sg:province":"NV",
    "sg:tags":[
        "burger",
        "american"
    ],
    "wof:name":"McDonald's",
    "wof:placetype":"venue"
},
  "geometry": {"coordinates":[-119.78092100000001,39.5779],"type":"Point"}
}