{
  "type": "Feature",
  "properties": {
    "iso:country":"US",
    "sg:address":"4025 Sunrise Ave",
    "sg:city":"Las Vegas",
    "sg:classifiers":[
        {
            "category":"Manufacturing",
            "subcategory":"Apparel",
            "type":"Manufacturing & Wholesale Goods"
        }
    ],
    "sg:phone":"+1 702 438 1188",
    "sg:postcode":"89110",
    "sg:province":"NV",
    "sg:tags":[
        "household",
        "furnishing",
        "mfg"
    ],
    "wof:name":"Traveling Quilter",
    "wof:placetype":"venue"
},
  "geometry": {"coordinates":[-115.087577,36.162601],"type":"Point"}
}