{
  "type": "Feature",
  "properties": {
    "iso:country":"US",
    "sg:address":"708 N Rainbow Blvd",
    "sg:city":"Las Vegas",
    "sg:classifiers":[
        {
            "category":"Insurance",
            "subcategory":"Insurance Agent",
            "type":"Services"
        }
    ],
    "sg:phone":"+1 702 870 2292",
    "sg:postcode":"89107",
    "sg:province":"NV",
    "wof:name":"Farmers Insurance Group",
    "wof:placetype":"venue"
},
  "geometry": {"coordinates":[-115.24222,36.1804],"type":"Point"}
}