{
  "type": "Feature",
  "properties": {
    "iso:country":"US",
    "sg:address":"171 N Gibson rd",
    "sg:city":"Henderson",
    "sg:classifiers":[
        {
            "category":"Restaurant",
            "type":"Food & Drink"
        }
    ],
    "sg:phone":"+1 702 233 3100",
    "sg:postcode":"89014",
    "sg:province":"NV",
    "sg:tags":[
        "middle",
        "eastern",
        "greek"
    ],
    "wof:name":"Manna Taste Of Mediterranean",
    "wof:placetype":"venue"
},
  "geometry": {"coordinates":[-115.029869,36.039432],"type":"Point"}
}