{
  "type": "Feature",
  "properties": {
    "iso:country":"US",
    "sg:address":"2055 S Rainbow Blvd",
    "sg:city":"Las Vegas",
    "sg:classifiers":[
        {
            "category":"Retail",
            "subcategory":"Auto Repair",
            "type":"Services"
        }
    ],
    "sg:phone":"+1 702 255 2996",
    "sg:postcode":"89146",
    "sg:province":"NV",
    "wof:name":"Purrfect Auto Service",
    "wof:placetype":"venue"
},
  "geometry": {"coordinates":[-115.242996,36.149601],"type":"Point"}
}