{
  "type": "Feature",
  "properties": {
    "iso:country":"US",
    "sg:address":"24 Main St",
    "sg:city":"Pioche",
    "sg:classifiers":[
        {
            "category":"Utilities",
            "subcategory":"Cable",
            "type":"Services"
        }
    ],
    "sg:phone":"+1 775 962 5111",
    "sg:postcode":"89043",
    "sg:province":"NV",
    "sg:tags":[
        "television"
    ],
    "wof:name":"Rainbow Cable",
    "wof:placetype":"venue"
},
  "geometry": {"coordinates":[-114.453991,37.927899],"type":"Point"}
}