{
  "type": "Feature",
  "properties": {
    "iso:country":"US",
    "sg:address":"295 Los Altos Pkwy Ste 101",
    "sg:city":"Sparks",
    "sg:classifiers":[
        {
            "category":"Bars & Pubs",
            "type":"Food & Drink"
        }
    ],
    "sg:menulink":"http://www.allmenus.com/nv/warm-springs-truckee-canyon/293393-l--l-hawaiian-barbecue/menu/",
    "sg:phone":"+1 775 829 9888",
    "sg:postcode":"89436",
    "sg:province":"NV",
    "sg:tags":[
        "barbecue"
    ],
    "wof:name":"L & L Hawaiian Barbecue",
    "wof:placetype":"venue"
},
  "geometry": {"coordinates":[-119.71427,39.586029],"type":"Point"}
}