{
  "type": "Feature",
  "properties": {
    "iso:country":"US",
    "sg:address":"131 Coney Island Dr",
    "sg:city":"Sparks",
    "sg:classifiers":[
        {
            "category":"Building & Trades",
            "subcategory":"Construction",
            "type":"Services"
        }
    ],
    "sg:phone":"+1 775 359 4300",
    "sg:postcode":"89431",
    "sg:province":"NV",
    "sg:tags":[
        "resurfacing",
        "laying",
        "refinishing",
        "floor"
    ],
    "wof:name":"Five Star Svc",
    "wof:placetype":"venue"
},
  "geometry": {"coordinates":[-119.742797,39.519545],"type":"Point"}
}