{
  "type": "Feature",
  "properties": {
    "iso:country":"US",
    "sg:address":"6335 Annie Oakley Dr Ofc",
    "sg:city":"Las Vegas",
    "sg:classifiers":[
        {
            "category":"Real Estate",
            "subcategory":"Real Estate Operator",
            "type":"Services"
        }
    ],
    "sg:phone":"+1 702 456 5757",
    "sg:postcode":"89120",
    "sg:province":"NV",
    "sg:tags":[
        "apartment"
    ],
    "wof:name":"Mesa Verde",
    "wof:placetype":"venue"
},
  "geometry": {"coordinates":[-115.086998,36.0741],"type":"Point"}
}