{
  "type": "Feature",
  "properties": {
    "iso:country":"US",
    "sg:address":"3909 Cool Meadows Dr",
    "sg:city":"Las Vegas",
    "sg:classifiers":[
        {
            "category":"Real Estate",
            "subcategory":"Real Estate Agent",
            "type":"Services"
        }
    ],
    "sg:phone":"+1 702 655 5529",
    "sg:postcode":"89129",
    "sg:province":"NV",
    "wof:name":"Liberty Realty",
    "wof:placetype":"venue"
},
  "geometry": {"coordinates":[-115.270899,36.231404],"type":"Point"}
}