{
  "type": "Feature",
  "properties": {
    "iso:country":"US",
    "sg:address":"1700 Pahrump Valley Blvd",
    "sg:city":"Pahrump",
    "sg:classifiers":[
        {
            "category":"Real Estate",
            "subcategory":"Real Estate Agent",
            "type":"Services"
        }
    ],
    "sg:phone":"+1 775 727 2332",
    "sg:postcode":"89048",
    "sg:province":"NV",
    "sg:website":"www.pahrumpaccessrealty.com",
    "wof:name":"Access Realty",
    "wof:placetype":"venue"
},
  "geometry": {"coordinates":[-115.988987,36.195426],"type":"Point"}
}