{
  "type": "Feature",
  "properties": {
    "iso:country":"US",
    "sg:address":"45 Desert Rose Ct",
    "sg:city":"Sparks",
    "sg:classifiers":[
        {
            "category":"Organizations",
            "subcategory":"Religious Organization",
            "type":"Services"
        }
    ],
    "sg:phone":"+1 775 425 2775",
    "sg:postcode":"89441",
    "sg:province":"NV",
    "sg:tags":[
        "church"
    ],
    "wof:name":"Spanish Springs Community Chr",
    "wof:placetype":"venue"
},
  "geometry": {"coordinates":[-119.767651,39.536607],"type":"Point"}
}