{
  "type": "Feature",
  "properties": {
    "iso:country":"US",
    "sg:address":"714 Spice Islands Dr",
    "sg:city":"Sparks",
    "sg:classifiers":[
        {
            "category":"Wholesale",
            "subcategory":"Electrical",
            "type":"Manufacturing & Wholesale Goods"
        }
    ],
    "sg:phone":"+1 775 331 3593",
    "sg:postcode":"89431",
    "sg:province":"NV",
    "sg:tags":[
        "control",
        "security",
        "system"
    ],
    "wof:name":"C S Security & Sound",
    "wof:placetype":"venue"
},
  "geometry": {"coordinates":[-119.736894,39.518134],"type":"Point"}
}