{
  "type": "Feature",
  "properties": {
    "iso:country":"US",
    "sg:address":"10504 Garden Light Dr",
    "sg:city":"Las Vegas",
    "sg:classifiers":[
        {
            "category":"Shopping",
            "subcategory":"Gifts & Souvenirs",
            "type":"Retail Goods"
        }
    ],
    "sg:phone":"+1 702 243 8313",
    "sg:postcode":"89135",
    "sg:province":"NV",
    "wof:name":"Albrecht Promotions",
    "wof:placetype":"venue"
},
  "geometry": {"coordinates":[-115.32160500000001,36.127594],"type":"Point"}
}