{
  "type": "Feature",
  "properties": {
    "iso:country":"US",
    "sg:address":"4949 E Monroe Ave",
    "sg:city":"Las Vegas",
    "sg:classifiers":[
        {
            "category":"Building & Trades",
            "subcategory":"Cleaning & Sanitation",
            "type":"Services"
        }
    ],
    "sg:phone":"+1 702 768 1181",
    "sg:postcode":"89110",
    "sg:province":"NV",
    "sg:tags":[
        "maintenance"
    ],
    "wof:name":"South West Janitorial Maint",
    "wof:placetype":"venue"
},
  "geometry": {"coordinates":[-115.065289,36.18492],"type":"Point"}
}