{
  "type": "Feature",
  "properties": {
    "iso:country":"US",
    "sg:address":"2775 Desert Marigold Ln",
    "sg:city":"Las Vegas",
    "sg:classifiers":[
        {
            "category":"Park",
            "type":"Public Place"
        }
    ],
    "sg:postcode":"89135",
    "sg:province":"NV",
    "wof:name":"Willows Paseo Park",
    "wof:placetype":"venue"
},
  "geometry": {"coordinates":[-115.320857,36.138568],"type":"Point"}
}