{
  "type": "Feature",
  "properties": {
    "iso:country":"US",
    "sg:address":"901 Arizona St",
    "sg:city":"Boulder City",
    "sg:classifiers":[
        {
            "category":"Organizations",
            "subcategory":"Membership Organization",
            "type":"Services"
        }
    ],
    "sg:phone":"+1 702 293 1809",
    "sg:postcode":"89005",
    "sg:province":"NV",
    "wof:name":"Masonic Temple Boulder Lodge",
    "wof:placetype":"venue"
},
  "geometry": {"coordinates":[-114.832774,35.978304],"type":"Point"}
}