{
  "type": "Feature",
  "properties": {
    "iso:country":"US",
    "sg:address":"850 Brass Ring",
    "sg:city":"Las Vegas",
    "sg:classifiers":[
        {
            "category":"Building & Trades",
            "subcategory":"Construction",
            "type":"Services"
        }
    ],
    "sg:phone":"+1 702 361 1517",
    "sg:postcode":"89123",
    "sg:province":"NV",
    "sg:tags":[
        "nonresidential"
    ],
    "wof:name":"Power Landscaping",
    "wof:placetype":"venue"
},
  "geometry": {"coordinates":[-115.14197,36.04391],"type":"Point"}
}