{
  "type": "Feature",
  "properties": {
    "iso:country":"US",
    "sg:address":"75 Pringle Way",
    "sg:city":"Reno",
    "sg:classifiers":[
        {
            "category":"Health Services",
            "subcategory":"Doctor",
            "type":"Services"
        }
    ],
    "sg:phone":"+1 775 786 4200",
    "sg:postcode":"89502",
    "sg:province":"NV",
    "sg:tags":[
        "medicine",
        "physician",
        "practice",
        "surgeons",
        "family"
    ],
    "wof:name":"Kevin A Linkus Md Facs Facc Fccp",
    "wof:placetype":"venue"
},
  "geometry": {"coordinates":[-119.793831,39.526348],"type":"Point"}
}