{
  "type": "Feature",
  "properties": {
    "iso:country":"US",
    "sg:address":"7575 west sunset road suite 130",
    "sg:city":"Las Vegas",
    "sg:classifiers":[
        {
            "category":"Shopping",
            "subcategory":"Bicycles & Sporting Goods",
            "type":"Retail Goods"
        }
    ],
    "sg:phone":"+1 702 257 7787",
    "sg:postcode":"89113",
    "sg:province":"NV",
    "sg:website":"www.ddisportsonline.com",
    "wof:name":"Ddi Sports",
    "wof:placetype":"venue"
},
  "geometry": {"coordinates":[-115.256709,36.068521],"type":"Point"}
}