{
  "type": "Feature",
  "properties": {
    "iso:country":"US",
    "sg:address":"2561 Windmill Parkway",
    "sg:city":"Henderson",
    "sg:classifiers":[
        {
            "category":"Restaurant",
            "type":"Food & Drink"
        },
        {
            "category":"Bars & Pubs",
            "subcategory":"Nightclub",
            "type":"Food & Drink"
        }
    ],
    "sg:phone":"+1 702 385 7568",
    "sg:postcode":"89074",
    "sg:province":"NV",
    "sg:tags":[
        "nightlife"
    ],
    "wof:name":"The Gin Mill",
    "wof:placetype":"venue"
},
  "geometry": {"coordinates":[-115.09835200000001,36.042151],"type":"Point"}
}