{
  "type": "Feature",
  "properties": {
    "iso:country":"US",
    "sg:address":"501 Parkson Rd",
    "sg:city":"Henderson",
    "sg:classifiers":[
        {
            "category":"Manufacturing",
            "subcategory":"Glass & Minerals",
            "type":"Manufacturing & Wholesale Goods"
        }
    ],
    "sg:phone":"+1 702 565 9751",
    "sg:postcode":"89011",
    "sg:province":"NV",
    "sg:tags":[
        "concrete",
        "mfg"
    ],
    "wof:name":"Rinker Materials West Llc",
    "wof:placetype":"venue"
},
  "geometry": {"coordinates":[-115.022388,36.063845],"type":"Point"}
}