{
  "type": "Feature",
  "properties": {
    "iso:country":"US",
    "sg:address":"1280 Plumb Ln",
    "sg:city":"Reno",
    "sg:classifiers":[
        {
            "category":"Manufacturing",
            "subcategory":"Signs",
            "type":"Manufacturing & Wholesale Goods"
        },
        {
            "category":"Professional",
            "subcategory":"Business Services",
            "type":"Services"
        }
    ],
    "sg:phone":"+1 775 827 8899",
    "sg:postcode":"89502",
    "sg:province":"NV",
    "sg:tags":[
        "body",
        "auto",
        "advertising",
        "se"
    ],
    "wof:name":"Fastsigns",
    "wof:placetype":"venue"
},
  "geometry": {"coordinates":[-119.782331,39.505808],"type":"Point"}
}