{
  "type": "Feature",
  "properties": {
    "iso:country":"US",
    "sg:address":"3900 N Rancho Dr",
    "sg:city":"Las Vegas",
    "sg:classifiers":[
        {
            "category":"Shopping",
            "subcategory":"Stationery & Office Supplies",
            "type":"Retail Goods"
        }
    ],
    "sg:phone":"+1 702 839 5366",
    "sg:postcode":"89130",
    "sg:province":"NV",
    "sg:tags":[
        "album",
        "scrapbook"
    ],
    "wof:name":"Scrapbook Superstore",
    "wof:placetype":"venue"
},
  "geometry": {"coordinates":[-115.22329,36.229295],"type":"Point"}
}