{
  "type": "Feature",
  "properties": {
    "iso:country":"US",
    "sg:address":"534 Feliz Contado Ct",
    "sg:city":"Henderson",
    "sg:classifiers":[
        {
            "category":"Travel",
            "subcategory":"Travel Agent",
            "type":"Entertainment"
        }
    ],
    "sg:phone":"+1 702 293 1033",
    "sg:postcode":"89015",
    "sg:province":"NV",
    "sg:tags":[
        "tours",
        "promoter"
    ],
    "wof:name":"Vegas Off Road",
    "wof:placetype":"venue"
},
  "geometry": {"coordinates":[-114.954637,36.023546],"type":"Point"}
}