{
  "type": "Feature",
  "properties": {
    "iso:country":"US",
    "sg:address":"3330 W Hacienda Avenue",
    "sg:city":"Las Vegas",
    "sg:classifiers":[
        {
            "category":"Food & Beverages",
            "subcategory":"Candy",
            "type":"Retail Goods"
        }
    ],
    "sg:phone":"+1 702 240 5082",
    "sg:postcode":"89118",
    "sg:province":"NV",
    "sg:tags":[
        "store"
    ],
    "wof:name":"Sin City Suckers",
    "wof:placetype":"venue"
},
  "geometry": {"coordinates":[-115.184736,36.093636],"type":"Point"}
}