{
  "type": "Feature",
  "properties": {
    "iso:country":"US",
    "sg:address":"500 Jackson Ave",
    "sg:city":"Las Vegas",
    "sg:classifiers":[
        {
            "category":"Organizations",
            "subcategory":"Religious Organization",
            "type":"Services"
        }
    ],
    "sg:phone":"+1 702 648 6700",
    "sg:postcode":"89106",
    "sg:province":"NV",
    "sg:tags":[
        "church"
    ],
    "wof:name":"True Vine Missionary Baptist",
    "wof:placetype":"venue"
},
  "geometry": {"coordinates":[-115.149627,36.185915],"type":"Point"}
}