{
  "type": "Feature",
  "properties": {
    "iso:country":"US",
    "sg:address":"1767 Bitterbrush Ct",
    "sg:city":"Gardnerville",
    "sg:classifiers":[
        {
            "category":"Real Estate",
            "subcategory":"Real Estate Agent",
            "type":"Services"
        }
    ],
    "sg:phone":"+1 775 783 8225",
    "sg:postcode":"89410",
    "sg:province":"NV",
    "sg:tags":[
        "management"
    ],
    "wof:name":"Sandberg Management Co",
    "wof:placetype":"venue"
},
  "geometry": {"coordinates":[-119.696112,38.941307],"type":"Point"}
}