{
  "type": "Feature",
  "properties": {
    "iso:country":"US",
    "sg:address":"4118 Lake Tahoe Blvd",
    "sg:city":"South Lake Tahoe",
    "sg:classifiers":[
        {
            "category":"Personal",
            "subcategory":"Beauty Salon",
            "type":"Services"
        }
    ],
    "sg:phone":"+1 530 541 3813",
    "sg:postcode":"96150",
    "sg:province":"CA",
    "sg:tags":[
        "spa",
        "day"
    ],
    "wof:name":"Body Essentials",
    "wof:placetype":"venue"
},
  "geometry": {"coordinates":[-119.942043,38.959082],"type":"Point"}
}