{
  "type": "Feature",
  "properties": {
    "iso:country":"US",
    "sg:address":"8610 S Eastern Ave",
    "sg:city":"Las Vegas",
    "sg:classifiers":[
        {
            "category":"Professional",
            "subcategory":"Accounting & Tax Preparation",
            "type":"Services"
        }
    ],
    "sg:phone":"+1 702 898 7120",
    "sg:postcode":"89123",
    "sg:province":"NV",
    "sg:tags":[
        "accountant"
    ],
    "wof:name":"Schultz William A CPA Ltd",
    "wof:placetype":"venue"
},
  "geometry": {"coordinates":[-115.119003,36.032799],"type":"Point"}
}