{
  "type": "Feature",
  "properties": {
    "iso:country":"US",
    "sg:address":"485 S Rock Blvd",
    "sg:city":"Reno",
    "sg:classifiers":[
        {
            "category":"Building & Trades",
            "subcategory":"Equipment Rental",
            "type":"Services"
        }
    ],
    "sg:phone":"+1 775 856 5804",
    "sg:postcode":"89502",
    "sg:province":"NV",
    "sg:tags":[
        "aircraft",
        "leasing",
        "charter"
    ],
    "wof:name":"American Medflight Inc",
    "wof:placetype":"venue"
},
  "geometry": {"coordinates":[-119.763814,39.506956],"type":"Point"}
}