{
  "type": "Feature",
  "properties": {
    "iso:country":"US",
    "sg:address":"10345 W Regena Ave",
    "sg:city":"Las Vegas",
    "sg:classifiers":[
        {
            "category":"Building & Trades",
            "subcategory":"Construction",
            "type":"Services"
        }
    ],
    "sg:phone":"+1 702 655 8780",
    "sg:postcode":"89149",
    "sg:province":"NV",
    "sg:tags":[
        "house",
        "general",
        "contractor"
    ],
    "wof:name":"Blaser Construction Inc",
    "wof:placetype":"venue"
},
  "geometry": {"coordinates":[-115.32269100000001,36.275363],"type":"Point"}
}