{
  "type": "Feature",
  "properties": {
    "iso:country":"US",
    "sg:address":"3650 S Decatur Blvd Ste 1",
    "sg:city":"Las Vegas",
    "sg:classifiers":[
        {
            "category":"Restaurant",
            "type":"Food & Drink"
        }
    ],
    "sg:phone":"+1 702 221 0766",
    "sg:postcode":"89103",
    "sg:province":"NV",
    "wof:name":"Saigon Fragrance Vietnamese Noodle House",
    "wof:placetype":"venue"
},
  "geometry": {"coordinates":[-115.216003,36.111301],"type":"Point"}
}