{
  "type": "Feature",
  "properties": {
    "iso:country":"US",
    "sg:address":"9340 W Flamingo Rd",
    "sg:city":"Las Vegas",
    "sg:classifiers":[
        {
            "category":"Restaurant",
            "type":"Food & Drink"
        }
    ],
    "sg:phone":"+1 702 243 0916",
    "sg:postcode":"89147",
    "sg:province":"NV",
    "wof:name":"KOBE Sushi Bar",
    "wof:placetype":"venue"
},
  "geometry": {"coordinates":[-115.293762,36.11499],"type":"Point"}
}