{
  "type": "Feature",
  "properties": {
    "iso:country":"US",
    "sg:address":"7604 Tiny Tortoise Street",
    "sg:city":"Las Vegas",
    "sg:classifiers":[
        {
            "category":"Retail",
            "subcategory":"Pet Boarding",
            "type":"Services"
        }
    ],
    "sg:phone":"+1 702 655 1619",
    "sg:postcode":"89149",
    "sg:province":"NV",
    "sg:tags":[
        "boarding/pet",
        "sitting"
    ],
    "wof:name":"Tlc Pet Sitting Service & More",
    "wof:placetype":"venue"
},
  "geometry": {"coordinates":[-115.306628,36.299893],"type":"Point"}
}