{
  "type": "Feature",
  "properties": {
    "iso:country":"US",
    "sg:address":"330 N Sandhill Blvd",
    "sg:city":"Mesquite",
    "sg:classifiers":[
        {
            "category":"Shopping",
            "type":"Retail Goods"
        }
    ],
    "sg:phone":"+1 702 346 4622",
    "sg:postcode":"89027",
    "sg:province":"NV",
    "sg:tags":[
        "hearing",
        "equipment",
        "supply",
        "impaired"
    ],
    "wof:name":"Audiology & Hearing Care",
    "wof:placetype":"venue"
},
  "geometry": {"coordinates":[-114.063996,36.809444],"type":"Point"}
}