{
  "type": "Feature",
  "properties": {
    "iso:country":"US",
    "sg:address":"10257 Strada Laterina Ct",
    "sg:city":"Las Vegas",
    "sg:classifiers":[
        {
            "category":"Wholesale",
            "subcategory":"Non-durable Goods",
            "type":"Manufacturing & Wholesale Goods"
        }
    ],
    "sg:phone":"+1 702 869 4151",
    "sg:postcode":"89135",
    "sg:province":"NV",
    "sg:tags":[
        "advertising"
    ],
    "wof:name":"Kennedy Advertising",
    "wof:placetype":"venue"
},
  "geometry": {"coordinates":[-115.316064,36.110108],"type":"Point"}
}