{
  "type": "Feature",
  "properties": {
    "iso:country":"US",
    "sg:address":"2470 E Flamingo Rd",
    "sg:city":"Las Vegas",
    "sg:classifiers":[
        {
            "category":"Health Services",
            "subcategory":"Doctor",
            "type":"Services"
        }
    ],
    "sg:phone":"+1 702 796 4278",
    "sg:postcode":"89121",
    "sg:province":"NV",
    "sg:tags":[
        "medical"
    ],
    "wof:name":"Mohamed Ahmed MD",
    "wof:placetype":"venue"
},
  "geometry": {"coordinates":[-115.117366,36.114816],"type":"Point"}
}