{
  "type": "Feature",
  "properties": {
    "iso:country":"US",
    "sg:address":"4555 Inland Ct",
    "sg:city":"Las Vegas",
    "sg:classifiers":[
        {
            "category":"Building & Trades",
            "subcategory":"Construction",
            "type":"Services"
        }
    ],
    "sg:phone":"+1 702 203 7831",
    "sg:postcode":"89147",
    "sg:province":"NV",
    "sg:tags":[
        "coping",
        "plastering",
        "tiling",
        "pool",
        "swimming"
    ],
    "wof:name":"Marine Tile & Coatings",
    "wof:placetype":"venue"
},
  "geometry": {"coordinates":[-115.243773,36.105538],"type":"Point"}
}