{
  "type": "Feature",
  "properties": {
    "iso:country":"US",
    "sg:address":"655 Country Club Dr",
    "sg:city":"Elko",
    "sg:classifiers":[
        {
            "category":"Recreation",
            "type":"Entertainment"
        }
    ],
    "sg:phone":"+1 775 777 0983",
    "sg:postcode":"89801",
    "sg:province":"NV",
    "sg:tags":[
        "concessionaire"
    ],
    "wof:name":"Fat Daddy's",
    "wof:placetype":"venue"
},
  "geometry": {"coordinates":[-115.75785399999999,40.842995],"type":"Point"}
}