{
  "type": "Feature",
  "properties": {
    "iso:country":"US",
    "sg:address":"997 Ridgeview Dr",
    "sg:city":"Carson City",
    "sg:classifiers":[
        {
            "category":"Personal",
            "subcategory":"Beauty Salon",
            "type":"Services"
        }
    ],
    "sg:phone":"+1 775 783 9113",
    "sg:postcode":"89705",
    "sg:province":"NV",
    "wof:name":"Short Cut",
    "wof:placetype":"venue"
},
  "geometry": {"coordinates":[-119.770022,39.093998],"type":"Point"}
}