{
  "type": "Feature",
  "properties": {
    "iso:country":"US",
    "sg:address":"1208 Chaparral Dr",
    "sg:city":"Mesquite",
    "sg:classifiers":[
        {
            "category":"Real Estate",
            "subcategory":"Developer",
            "type":"Services"
        }
    ],
    "sg:phone":"+1 702 346 8182",
    "sg:postcode":"89027",
    "sg:province":"NV",
    "wof:name":"Summerhills Townhomes",
    "wof:placetype":"venue"
},
  "geometry": {"coordinates":[-114.052437,36.828793],"type":"Point"}
}