{
  "type": "Feature",
  "properties": {
    "iso:country":"US",
    "sg:address":"2815 W Ford Ave",
    "sg:city":"Las Vegas",
    "sg:classifiers":[
        {
            "category":"Building & Trades",
            "subcategory":"Cleaning & Sanitation",
            "type":"Services"
        }
    ],
    "sg:phone":"+1 702 293 5500",
    "sg:postcode":"89123",
    "sg:province":"NV",
    "sg:tags":[
        "janitor"
    ],
    "wof:name":"Clark County Janitorial",
    "wof:placetype":"venue"
},
  "geometry": {"coordinates":[-115.177336,36.031806],"type":"Point"}
}