{
  "type": "Feature",
  "properties": {
    "iso:country":"US",
    "sg:address":"500 Hillside Dr",
    "sg:city":"Mesquite",
    "sg:classifiers":[
        {
            "category":"Government",
            "subcategory":"Office",
            "type":"Public Place"
        }
    ],
    "sg:phone":"+1 702 346 1867",
    "sg:postcode":"89027",
    "sg:province":"NV",
    "wof:name":"Clark County Marriage License",
    "wof:placetype":"venue"
},
  "geometry": {"coordinates":[-114.057867,36.813127],"type":"Point"}
}