{
  "type": "Feature",
  "properties": {
    "iso:country":"US",
    "sg:address":"5666 Roundrock Dr",
    "sg:city":"Las Vegas",
    "sg:classifiers":[
        {
            "category":"Building & Trades",
            "subcategory":"Landscaping Services",
            "type":"Services"
        }
    ],
    "sg:phone":"+1 702 263 2002",
    "sg:postcode":"89142",
    "sg:province":"NV",
    "sg:tags":[
        "tree"
    ],
    "wof:name":"Saunder's Palm & Tree Trimming",
    "wof:placetype":"venue"
},
  "geometry": {"coordinates":[-115.05175,36.143402],"type":"Point"}
}