{
  "type": "Feature",
  "properties": {
    "iso:country":"US",
    "sg:address":"384 S Reese St",
    "sg:city":"Battle Mountain",
    "sg:classifiers":[
        {
            "category":"Organizations",
            "subcategory":"Religious Organization",
            "type":"Services"
        }
    ],
    "sg:phone":"+1 775 635 3450",
    "sg:postcode":"89820",
    "sg:province":"NV",
    "sg:tags":[
        "church"
    ],
    "wof:name":"St John Bosco Catholic Church",
    "wof:placetype":"venue"
},
  "geometry": {"coordinates":[-116.936426,40.639364],"type":"Point"}
}