{
  "type": "Feature",
  "properties": {
    "iso:country":"US",
    "sg:address":"151 N Main St",
    "sg:city":"Silverpeak",
    "sg:classifiers":[
        {
            "category":"Government",
            "subcategory":"Post Office",
            "type":"Public Place"
        }
    ],
    "sg:phone":"+1 775 937 2366",
    "sg:postcode":"89001",
    "sg:province":"NV",
    "wof:name":"US Post Office",
    "wof:placetype":"venue"
},
  "geometry": {"coordinates":[-115.165812,37.364803],"type":"Point"}
}