{
  "type": "Feature",
  "properties": {
    "iso:country":"US",
    "sg:address":"1445 Kirston St",
    "sg:city":"Reno",
    "sg:classifiers":[
        {
            "category":"Shopping",
            "subcategory":"Bicycles & Sporting Goods",
            "type":"Retail Goods"
        }
    ],
    "sg:phone":"+1 775 787 7427",
    "sg:postcode":"89503",
    "sg:province":"NV",
    "wof:name":"Fishermans Friend",
    "wof:placetype":"venue"
},
  "geometry": {"coordinates":[-119.859346,39.539285],"type":"Point"}
}