{
  "type": "Feature",
  "properties": {
    "iso:country":"US",
    "sg:address":"5052 S Jones Blvd Ste 135",
    "sg:city":"Las Vegas",
    "sg:classifiers":[
        {
            "category":"Banks & Credit Unions",
            "subcategory":"Financial Services",
            "type":"Services"
        }
    ],
    "sg:phone":"+1 702 871 8600",
    "sg:postcode":"89118",
    "sg:province":"NV",
    "sg:tags":[
        "broker",
        "mortgage"
    ],
    "wof:name":"Golden Empire Mortgage",
    "wof:placetype":"venue"
},
  "geometry": {"coordinates":[-115.22443,36.09682],"type":"Point"}
}