{
  "type": "Feature",
  "properties": {
    "iso:country":"US",
    "sg:address":"4429 Kalamazoo St",
    "sg:city":"Las Vegas",
    "sg:classifiers":[
        {
            "category":"Shopping",
            "subcategory":"Clothing, Apparel, & Fashions",
            "type":"Retail Goods"
        }
    ],
    "sg:phone":"+1 702 253 9261",
    "sg:postcode":"89147",
    "sg:province":"NV",
    "wof:name":"Discount Custom Leather & AP",
    "wof:placetype":"venue"
},
  "geometry": {"coordinates":[-115.256393,36.10916],"type":"Point"}
}