{
  "type": "Feature",
  "properties": {
    "iso:country":"US",
    "sg:address":"2925 N Green Valley Pkwy",
    "sg:city":"Henderson",
    "sg:classifiers":[
        {
            "category":"Recreation",
            "type":"Entertainment"
        }
    ],
    "sg:phone":"+1 702 547 0200",
    "sg:postcode":"89014",
    "sg:province":"NV",
    "wof:name":"Par 2",
    "wof:placetype":"venue"
},
  "geometry": {"coordinates":[-115.0831,36.077819],"type":"Point"}
}