{
  "type": "Feature",
  "properties": {
    "iso:country":"US",
    "sg:address":"7350 Prairie Falcon Rd",
    "sg:city":"Las Vegas",
    "sg:classifiers":[
        {
            "category":"Recreation",
            "subcategory":"Amusement Park",
            "type":"Entertainment"
        },
        {
            "category":"Recreation",
            "subcategory":"Arcade",
            "type":"Entertainment"
        }
    ],
    "sg:phone":"+1 702 227 7223",
    "sg:postcode":"89128",
    "sg:province":"NV",
    "sg:website":"www.polepositionraceway.com/summ...",
    "wof:name":"Pole Position Raceway",
    "wof:placetype":"venue"
},
  "geometry": {"coordinates":[-115.253339,36.207274],"type":"Point"}
}