{
  "type": "Feature",
  "properties": {
    "iso:country":"US",
    "sg:address":"3700 S. Hualapai Way 203-204",
    "sg:city":"Las Vegas",
    "sg:classifiers":[
        {
            "category":"Sports & Exercise",
            "subcategory":"Gym",
            "type":"Entertainment"
        }
    ],
    "sg:phone":"+1 702 227 9642",
    "sg:postcode":"89147",
    "sg:province":"NV",
    "sg:tags":[
        "yoga"
    ],
    "sg:website":"www.bikramyogawestside.com/schedule",
    "wof:name":"Bikram Yoga Westside",
    "wof:placetype":"venue"
},
  "geometry": {"coordinates":[-115.314302,36.121809],"type":"Point"}
}