{
  "type": "Feature",
  "properties": {
    "iso:country":"US",
    "sg:address":"120 E Horizon Dr",
    "sg:city":"Henderson",
    "sg:classifiers":[
        {
            "category":"Shopping",
            "subcategory":"Gifts & Souvenirs",
            "type":"Retail Goods"
        }
    ],
    "sg:phone":"+1 702 568 9627",
    "sg:postcode":"89015",
    "sg:province":"NV",
    "sg:tags":[
        "shop"
    ],
    "wof:name":"Le Melange Gifts Collectibles",
    "wof:placetype":"venue"
},
  "geometry": {"coordinates":[-114.987002,36.012599],"type":"Point"}
}