{
  "type": "Feature",
  "properties": {
    "iso:country":"US",
    "sg:address":"3711 Heritage Ave",
    "sg:city":"Las Vegas",
    "sg:classifiers":[
        {
            "category":"Recreation",
            "type":"Entertainment"
        }
    ],
    "sg:phone":"+1 702 458 3273",
    "sg:postcode":"89121",
    "sg:province":"NV",
    "wof:name":"Sita Tiger Astrology",
    "wof:placetype":"venue"
},
  "geometry": {"coordinates":[-115.093672,36.120264],"type":"Point"}
}