{
  "type": "Feature",
  "properties": {
    "iso:country":"US",
    "sg:address":"6059 Thorne Bay Ct",
    "sg:city":"Las Vegas",
    "sg:classifiers":[
        {
            "category":"Personal",
            "type":"Services"
        }
    ],
    "sg:phone":"+1 702 437 7634",
    "sg:postcode":"89110",
    "sg:province":"NV",
    "wof:name":"R&B Handyman",
    "wof:placetype":"venue"
},
  "geometry": {"coordinates":[-115.039688,36.183299],"type":"Point"}
}