{
  "type": "Feature",
  "properties": {
    "iso:country":"US",
    "sg:address":"521 Hammill Ln",
    "sg:city":"Reno",
    "sg:classifiers":[
        {
            "category":"Organizations",
            "subcategory":"Political Organization",
            "type":"Services"
        }
    ],
    "sg:phone":"+1 775 827 9934",
    "sg:postcode":"89511",
    "sg:province":"NV",
    "wof:name":"Nevada Republican Party",
    "wof:placetype":"venue"
},
  "geometry": {"coordinates":[-119.792967,39.472115],"type":"Point"}
}