{
  "type": "Feature",
  "properties": {
    "iso:country":"US",
    "sg:address":"968 Armillaria St",
    "sg:city":"Henderson",
    "sg:classifiers":[
        {
            "category":"Building & Trades",
            "subcategory":"Construction",
            "type":"Services"
        }
    ],
    "sg:phone":"+1 702 871 9094",
    "sg:postcode":"89011",
    "sg:province":"NV",
    "sg:tags":[
        "contractor"
    ],
    "wof:name":"Perma-Glaze",
    "wof:placetype":"venue"
},
  "geometry": {"coordinates":[-114.946569,36.080127],"type":"Point"}
}