{
  "type": "Feature",
  "properties": {
    "iso:country":"US",
    "sg:address":"9415 W Tropicana Ave",
    "sg:city":"Las Vegas",
    "sg:classifiers":[
        {
            "category":"Restaurant",
            "type":"Food & Drink"
        }
    ],
    "sg:menulink":"http://www.allmenus.com/nv/las-vegas/196522-mcdonalds/menu/",
    "sg:postcode":"89147",
    "sg:province":"NV",
    "sg:tags":[
        "burger",
        "american"
    ],
    "wof:name":"McDonald's",
    "wof:placetype":"venue"
},
  "geometry": {"coordinates":[-115.297832,36.099535],"type":"Point"}
}