{
  "type": "Feature",
  "properties": {
    "iso:country":"US",
    "sg:address":"1000 N Martin L King Blvd",
    "sg:city":"Las Vegas",
    "sg:classifiers":[
        {
            "category":"Personal",
            "subcategory":"Barber",
            "type":"Services"
        }
    ],
    "sg:phone":"+1 702 648 9500",
    "sg:postcode":"89106",
    "sg:province":"NV",
    "wof:name":"Hair Unlimited",
    "wof:placetype":"venue"
},
  "geometry": {"coordinates":[-115.16100299999999,36.181801],"type":"Point"}
}