{
  "type": "Feature",
  "properties": {
    "iso:country":"US",
    "sg:address":"502 N Division St",
    "sg:city":"Carson City",
    "sg:classifiers":[
        {
            "category":"Banks & Credit Unions",
            "subcategory":"Financial Services",
            "type":"Services"
        }
    ],
    "sg:phone":"+1 775 886 0809",
    "sg:postcode":"89703",
    "sg:province":"NV",
    "sg:tags":[
        "investment",
        "closed"
    ],
    "wof:name":"National Harvest LLC",
    "wof:placetype":"venue"
},
  "geometry": {"coordinates":[-119.769574,39.166541],"type":"Point"}
}