{
  "type": "Feature",
  "properties": {
    "iso:country":"US",
    "sg:address":"2611 S Buffalo Dr",
    "sg:city":"Las Vegas",
    "sg:classifiers":[
        {
            "category":"Organizations",
            "subcategory":"Religious Organization",
            "type":"Services"
        }
    ],
    "sg:phone":"+1 702 365 9403",
    "sg:postcode":"89117",
    "sg:province":"NV",
    "sg:tags":[
        "church"
    ],
    "wof:name":"Nole Christian Ministries",
    "wof:placetype":"venue"
},
  "geometry": {"coordinates":[-115.261021,36.140232],"type":"Point"}
}