{
  "type": "Feature",
  "properties": {
    "iso:country":"US",
    "sg:address":"5459 Mexican Rose Ct",
    "sg:city":"Las Vegas",
    "sg:classifiers":[
        {
            "category":"Professional",
            "subcategory":"Business Services",
            "type":"Services"
        }
    ],
    "sg:phone":"+1 702 434 4319",
    "sg:postcode":"89120",
    "sg:province":"NV",
    "wof:name":"Simmons Design",
    "wof:placetype":"venue"
},
  "geometry": {"coordinates":[-115.089596,36.089735],"type":"Point"}
}