{
  "type": "Feature",
  "properties": {
    "iso:country":"US",
    "sg:address":"3584 W Plumb Ln",
    "sg:city":"Reno",
    "sg:classifiers":[
        {
            "category":"Real Estate",
            "subcategory":"Architect",
            "type":"Services"
        }
    ],
    "sg:phone":"+1 775 348 2063",
    "sg:postcode":"89509",
    "sg:province":"NV",
    "wof:name":"Archidea",
    "wof:placetype":"venue"
},
  "geometry": {"coordinates":[-119.856939,39.500717],"type":"Point"}
}