{
  "type": "Feature",
  "properties": {
    "iso:country":"US",
    "sg:address":"3070 S Nellis Blvd",
    "sg:city":"Las Vegas",
    "sg:classifiers":[
        {
            "category":"Building & Trades",
            "subcategory":"Construction",
            "type":"Services"
        }
    ],
    "sg:phone":"+1 702 457 1088",
    "sg:postcode":"89121",
    "sg:province":"NV",
    "sg:tags":[
        "painter"
    ],
    "wof:name":"K W Painting & Drywall",
    "wof:placetype":"venue"
},
  "geometry": {"coordinates":[-115.065372,36.134027],"type":"Point"}
}