{
  "type": "Feature",
  "properties": {
    "iso:country":"US",
    "sg:address":"1316 Kim Pl",
    "sg:city":"Minden",
    "sg:classifiers":[
        {
            "category":"Shopping",
            "type":"Retail Goods"
        }
    ],
    "sg:phone":"+1 775 885 7997",
    "sg:postcode":"89423",
    "sg:province":"NV",
    "sg:tags":[
        "typewriter"
    ],
    "wof:name":"Hamilton Business Machines",
    "wof:placetype":"venue"
},
  "geometry": {"coordinates":[-119.74114899999999,39.043157],"type":"Point"}
}