{
  "type": "Feature",
  "properties": {
    "iso:country":"US",
    "sg:address":"9010 W Sahara Ave",
    "sg:city":"Las Vegas",
    "sg:classifiers":[
        {
            "category":"Personal",
            "subcategory":"Beauty Salon",
            "type":"Services"
        }
    ],
    "sg:phone":"+1 702 255 7333",
    "sg:postcode":"89117",
    "sg:province":"NV",
    "sg:tags":[
        "shop"
    ],
    "wof:name":"Unique Hair",
    "wof:placetype":"venue"
},
  "geometry": {"coordinates":[-115.28962799999999,36.14422],"type":"Point"}
}