{
  "type": "Feature",
  "properties": {
    "iso:country":"US",
    "sg:address":"5420 Kietzke Ln",
    "sg:city":"Reno",
    "sg:classifiers":[
        {
            "category":"Health Services",
            "subcategory":"Doctor",
            "type":"Services"
        }
    ],
    "sg:phone":"+1 775 827 5511",
    "sg:postcode":"89511",
    "sg:province":"NV",
    "sg:tags":[
        "dentist"
    ],
    "sg:website":"http://www.renosleepdentistry.com",
    "wof:name":"Homanfar Ramin DDS",
    "wof:placetype":"venue"
},
  "geometry": {"coordinates":[-119.79093399999999,39.466263],"type":"Point"}
}