{
  "type": "Feature",
  "properties": {
    "iso:country":"US",
    "sg:address":"2570 E Tropicana Ave",
    "sg:city":"Las Vegas",
    "sg:classifiers":[
        {
            "category":"Personal",
            "type":"Services"
        }
    ],
    "sg:phone":"+1 702 876 6867",
    "sg:postcode":"89121",
    "sg:province":"NV",
    "sg:tags":[
        "therapist",
        "massage"
    ],
    "wof:name":"Massage Referral Svc",
    "wof:placetype":"venue"
},
  "geometry": {"coordinates":[-115.11669000000001,36.100019],"type":"Point"}
}