{
  "type": "Feature",
  "properties": {
    "iso:country":"US",
    "sg:address":"3581 Birtcher Dr",
    "sg:city":"Las Vegas",
    "sg:classifiers":[
        {
            "category":"Organizations",
            "subcategory":"Professional Association",
            "type":"Services"
        }
    ],
    "sg:phone":"+1 702 270 4195",
    "sg:postcode":"89118",
    "sg:province":"NV",
    "sg:tags":[
        "sales"
    ],
    "wof:name":"Progressive Wholesale",
    "wof:placetype":"venue"
},
  "geometry": {"coordinates":[-115.185784,36.076437],"type":"Point"}
}