{
  "type": "Feature",
  "properties": {
    "iso:country":"US",
    "sg:address":"7121 W Craig Rd",
    "sg:city":"Las Vegas",
    "sg:classifiers":[
        {
            "category":"Freight",
            "type":"Transportation"
        }
    ],
    "sg:phone":"+1 702 348 0761",
    "sg:postcode":"89129",
    "sg:province":"NV",
    "sg:tags":[
        "trucking"
    ],
    "wof:name":"XTC Trucking Inc",
    "wof:placetype":"venue"
},
  "geometry": {"coordinates":[-115.249581,36.2404],"type":"Point"}
}