{
  "type": "Feature",
  "properties": {
    "iso:country":"US",
    "sg:address":"1314 N Nellis Blvd Ste A",
    "sg:city":"Las Vegas",
    "sg:classifiers":[
        {
            "category":"Retail",
            "subcategory":"Auto Repair",
            "type":"Services"
        }
    ],
    "sg:phone":"+1 702 438 7100",
    "sg:postcode":"89110",
    "sg:province":"NV",
    "wof:name":"Brake Masters",
    "wof:placetype":"venue"
},
  "geometry": {"coordinates":[-115.061996,36.183601],"type":"Point"}
}