{
  "type": "Feature",
  "properties": {
    "iso:country":"US",
    "sg:address":"1300 N Boulder Hwy",
    "sg:city":"Henderson",
    "sg:classifiers":[
        {
            "category":"Autos & Motor Vehicles",
            "subcategory":"Automobile Sales",
            "type":"Retail Goods"
        }
    ],
    "sg:phone":"+1 702 568 5353",
    "sg:postcode":"89015",
    "sg:province":"NV",
    "sg:tags":[
        "automotive"
    ],
    "sg:website":"sunsetautolv.com",
    "wof:name":"Sunset Auto Imports",
    "wof:placetype":"venue"
},
  "geometry": {"coordinates":[-114.95552600000001,36.016198],"type":"Point"}
}