{
  "type": "Feature",
  "properties": {
    "iso:country":"US",
    "sg:address":"6465 Buckaroo Ave",
    "sg:city":"Las Vegas",
    "sg:classifiers":[
        {
            "category":"Travel",
            "subcategory":"Travel Agent",
            "type":"Entertainment"
        }
    ],
    "sg:phone":"+1 702 655 1401",
    "sg:postcode":"89108",
    "sg:province":"NV",
    "sg:tags":[
        "agency"
    ],
    "wof:name":"All Tour & Travel Co",
    "wof:placetype":"venue"
},
  "geometry": {"coordinates":[-115.23587,36.215069],"type":"Point"}
}