{
  "type": "Feature",
  "properties": {
    "iso:country":"US",
    "sg:address":"4510 Meadows Ln",
    "sg:city":"Las Vegas",
    "sg:classifiers":[
        {
            "category":"Shopping",
            "subcategory":"Department Store",
            "type":"Retail Goods"
        }
    ],
    "sg:phone":"+1 702 259 8639",
    "sg:postcode":"89107",
    "sg:province":"NV",
    "wof:name":"Fallas Paredes",
    "wof:placetype":"venue"
},
  "geometry": {"coordinates":[-115.19495,36.170222],"type":"Point"}
}