{
  "type": "Feature",
  "properties": {
    "iso:country":"US",
    "sg:address":"1270 Burnham Ave",
    "sg:city":"Las Vegas",
    "sg:classifiers":[
        {
            "category":"Professional",
            "subcategory":"Management & Consulting",
            "type":"Services"
        }
    ],
    "sg:phone":"+1 702 474 2929",
    "sg:postcode":"89104",
    "sg:province":"NV",
    "sg:tags":[
        "business"
    ],
    "wof:name":"Gary Sadow",
    "wof:placetype":"venue"
},
  "geometry": {"coordinates":[-115.12337599999999,36.155889],"type":"Point"}
}