{
  "type": "Feature",
  "properties": {
    "iso:country":"US",
    "sg:address":"1736 E Charleston Boulevard",
    "sg:city":"Las Vegas",
    "sg:classifiers":[
        {
            "category":"Professional",
            "subcategory":"Lawyer & Legal Services",
            "type":"Services"
        }
    ],
    "sg:phone":"+1 702 366 1606",
    "sg:postcode":"89104",
    "sg:province":"NV",
    "sg:tags":[
        "notary"
    ],
    "wof:name":"Plus Mail",
    "wof:placetype":"venue"
},
  "geometry": {"coordinates":[-115.12701300000001,36.158899],"type":"Point"}
}