{
  "type": "Feature",
  "properties": {
    "iso:country":"US",
    "sg:address":"72 W Horizon Ridge Pkwy",
    "sg:city":"Henderson",
    "sg:classifiers":[
        {
            "category":"Sports & Exercise",
            "subcategory":"Gym",
            "type":"Entertainment"
        }
    ],
    "sg:phone":"+1 702 202 1200",
    "sg:postcode":"89012",
    "sg:province":"NV",
    "sg:tags":[
        "pilate"
    ],
    "sg:website":"www.thepilatesplus.net",
    "wof:name":"Pilates+",
    "wof:placetype":"venue"
},
  "geometry": {"coordinates":[-114.992667,36.013035],"type":"Point"}
}