{
  "type": "Feature",
  "properties": {
    "iso:country":"US",
    "sg:address":"7594 Ancient Title Ct",
    "sg:city":"Las Vegas",
    "sg:classifiers":[
        {
            "category":"Insurance",
            "subcategory":"Hazard Insurance",
            "type":"Services"
        }
    ],
    "sg:phone":"+1 702 870 2245",
    "sg:postcode":"89113",
    "sg:province":"NV",
    "sg:tags":[
        "bond"
    ],
    "wof:name":"A Bailbond Co Inc",
    "wof:placetype":"venue"
},
  "geometry": {"coordinates":[-115.256965,36.08461],"type":"Point"}
}