{
  "type": "Feature",
  "properties": {
    "iso:country":"US",
    "sg:address":"445 E Windmill Ln",
    "sg:city":"Las Vegas",
    "sg:classifiers":[
        {
            "category":"Professional",
            "subcategory":"Accounting & Tax Preparation",
            "type":"Services"
        }
    ],
    "sg:phone":"+1 702 269 2455",
    "sg:postcode":"89123",
    "sg:province":"NV",
    "sg:tags":[
        "return",
        "filing"
    ],
    "wof:name":"H & R Block Tax Svc",
    "wof:placetype":"venue"
},
  "geometry": {"coordinates":[-115.150725,36.042391],"type":"Point"}
}