{
  "type": "Feature",
  "properties": {
    "iso:country":"US",
    "sg:address":"4561 E Bonanza Rd",
    "sg:city":"Las Vegas",
    "sg:classifiers":[
        {
            "category":"Retail",
            "subcategory":"Auto Repair",
            "type":"Services"
        }
    ],
    "sg:phone":"+1 702 333 1568",
    "sg:postcode":"89110",
    "sg:province":"NV",
    "wof:name":"California Auto Repair",
    "wof:placetype":"venue"
},
  "geometry": {"coordinates":[-115.07493700000001,36.173498],"type":"Point"}
}