{
  "type": "Feature",
  "properties": {
    "iso:country":"US",
    "sg:address":"3035 S Monte Cristo Way",
    "sg:city":"Las Vegas",
    "sg:classifiers":[
        {
            "category":"Professional",
            "subcategory":"Management & Consulting",
            "type":"Services"
        }
    ],
    "sg:phone":"+1 702 252 4783",
    "sg:postcode":"89117",
    "sg:province":"NV",
    "wof:name":"Services A Protocol V",
    "wof:placetype":"venue"
},
  "geometry": {"coordinates":[-115.254296,36.133553],"type":"Point"}
}