{
  "type": "Feature",
  "properties": {
    "iso:country":"US",
    "sg:address":"3770 Howard Hughes Pkwy",
    "sg:city":"Las Vegas",
    "sg:classifiers":[
        {
            "category":"Manufacturing",
            "subcategory":"Chemicals & Compounds",
            "type":"Manufacturing & Wholesale Goods"
        }
    ],
    "sg:phone":"+1 702 735 2200",
    "sg:postcode":"89169",
    "sg:province":"NV",
    "sg:tags":[
        "specialty",
        "mfg"
    ],
    "sg:website":"www.apfc.com",
    "wof:name":"American Pacific Corporation",
    "wof:placetype":"venue"
},
  "geometry": {"coordinates":[-115.157801,36.121146],"type":"Point"}
}