{
  "type": "Feature",
  "properties": {
    "iso:country":"US",
    "sg:address":"4520 S Pecos Rd",
    "sg:city":"Las Vegas",
    "sg:classifiers":[
        {
            "category":"Professional",
            "type":"Services"
        }
    ],
    "sg:phone":"+1 702 914 7441",
    "sg:postcode":"89121",
    "sg:province":"NV",
    "wof:name":"Eve Inc",
    "wof:placetype":"venue"
},
  "geometry": {"coordinates":[-115.100624,36.107356],"type":"Point"}
}