{
  "type": "Feature",
  "properties": {
    "iso:country":"US",
    "sg:address":"3160 S Valley View Blvd",
    "sg:city":"Las Vegas",
    "sg:classifiers":[
        {
            "category":"Social Services",
            "type":"Services"
        }
    ],
    "sg:phone":"+1 702 873 0403",
    "sg:postcode":"89102",
    "sg:province":"NV",
    "sg:tags":[
        "counselor",
        "marriage",
        "family"
    ],
    "wof:name":"Help Center",
    "wof:placetype":"venue"
},
  "geometry": {"coordinates":[-115.190231,36.131595],"type":"Point"}
}