{
  "type": "Feature",
  "properties": {
    "iso:country":"US",
    "sg:address":"10123 Sparrow Ridge Ave",
    "sg:city":"Las Vegas",
    "sg:classifiers":[
        {
            "category":"Professional",
            "subcategory":"Business Services",
            "type":"Services"
        }
    ],
    "sg:phone":"+1 702 255 3006",
    "sg:postcode":"89117",
    "sg:province":"NV",
    "sg:tags":[
        "broker",
        "merchandise"
    ],
    "wof:name":"F M Brokerage",
    "wof:placetype":"venue"
},
  "geometry": {"coordinates":[-115.31282899999999,36.128606],"type":"Point"}
}