{
  "type": "Feature",
  "properties": {
    "iso:country":"US",
    "sg:address":"504 Lob Wedge Ct",
    "sg:city":"Las Vegas",
    "sg:classifiers":[
        {
            "category":"Wholesale",
            "subcategory":"Drugs",
            "type":"Manufacturing & Wholesale Goods"
        }
    ],
    "sg:phone":"+1 702 255 6018",
    "sg:postcode":"89144",
    "sg:province":"NV",
    "sg:tags":[
        "pharmaceutical",
        "product"
    ],
    "wof:name":"Legend Pharmaceuticals",
    "wof:placetype":"venue"
},
  "geometry": {"coordinates":[-115.299953,36.178608],"type":"Point"}
}