{
  "type": "Feature",
  "properties": {
    "iso:country":"US",
    "sg:address":"2980 S Jones Blvd",
    "sg:city":"Las Vegas",
    "sg:classifiers":[
        {
            "category":"Banks & Credit Unions",
            "subcategory":"Bank",
            "type":"Services"
        }
    ],
    "sg:phone":"+1 702 307 2777",
    "sg:postcode":"89146",
    "sg:province":"NV",
    "sg:tags":[
        "loan",
        "real estate"
    ],
    "wof:name":"Summit Home Loans",
    "wof:placetype":"venue"
},
  "geometry": {"coordinates":[-115.225027,36.136336],"type":"Point"}
}