{
  "type": "Feature",
  "properties": {
    "iso:country":"US",
    "sg:address":"6145 Harrison Dr",
    "sg:city":"Las Vegas",
    "sg:classifiers":[
        {
            "category":"Home & Garden",
            "subcategory":"Carpets & Floor Coverings",
            "type":"Retail Goods"
        }
    ],
    "sg:phone":"+1 702 258 1505",
    "sg:postcode":"89120",
    "sg:province":"NV",
    "sg:tags":[
        "dealer",
        "rug"
    ],
    "wof:name":"Quality Flooring",
    "wof:placetype":"venue"
},
  "geometry": {"coordinates":[-115.112456,36.074827],"type":"Point"}
}