{
  "type": "Feature",
  "properties": {
    "iso:country":"US",
    "sg:address":"7575 S Rainbow Blvd Ste 104",
    "sg:city":"Las Vegas",
    "sg:classifiers":[
        {
            "category":"Restaurant",
            "type":"Food & Drink"
        }
    ],
    "sg:phone":"+1 702 270 8838",
    "sg:postcode":"89139",
    "sg:province":"NV",
    "sg:tags":[
        "pizza"
    ],
    "sg:website":"www.brothersitalianbistro.com/",
    "wof:name":"Brothers Italian Bistro",
    "wof:placetype":"venue"
},
  "geometry": {"coordinates":[-115.243898,36.050849],"type":"Point"}
}