{
  "type": "Feature",
  "properties": {
    "iso:country":"US",
    "sg:address":"3 Newlands Cir",
    "sg:city":"Reno",
    "sg:classifiers":[
        {
            "category":"Freight",
            "type":"Transportation"
        }
    ],
    "sg:phone":"+1 775 786 9256",
    "sg:postcode":"89509",
    "sg:province":"NV",
    "sg:tags":[
        "terminal",
        "truck",
        "facility"
    ],
    "wof:name":"Dawn Ligon",
    "wof:placetype":"venue"
},
  "geometry": {"coordinates":[-119.82404099999999,39.5181],"type":"Point"}
}