{
  "type": "Feature",
  "properties": {
    "iso:country":"US",
    "sg:address":"6400 S Eastern Avenue",
    "sg:city":"Las Vegas",
    "sg:classifiers":[
        {
            "category":"Shopping",
            "subcategory":"Florist",
            "type":"Retail Goods"
        }
    ],
    "sg:phone":"+1 702 739 9945",
    "sg:postcode":"89119",
    "sg:province":"NV",
    "wof:name":"A-Alessi's II East Coast Flowers & Gifts",
    "wof:placetype":"venue"
},
  "geometry": {"coordinates":[-115.118499,36.073831],"type":"Point"}
}