{
  "type": "Feature",
  "properties": {
    "iso:country":"US",
    "sg:address":"5740 S Eastern Ave",
    "sg:city":"Las Vegas",
    "sg:classifiers":[
        {
            "category":"Banks & Credit Unions",
            "subcategory":"Bank",
            "type":"Services"
        }
    ],
    "sg:phone":"+1 702 853 1900",
    "sg:postcode":"89119",
    "sg:province":"NV",
    "sg:tags":[
        "loan",
        "real estate"
    ],
    "sg:website":"www.acerefi.com",
    "wof:name":"Ace Mortgage Funding",
    "wof:placetype":"venue"
},
  "geometry": {"coordinates":[-115.118734,36.085051],"type":"Point"}
}