{
  "type": "Feature",
  "properties": {
    "iso:country":"US",
    "sg:address":"1175 Financial Blvd",
    "sg:city":"Reno",
    "sg:classifiers":[
        {
            "category":"Government",
            "subcategory":"Office",
            "type":"Public Place"
        }
    ],
    "sg:phone":"+1 775 784 5221",
    "sg:postcode":"89502",
    "sg:province":"NV",
    "sg:tags":[
        "federal",
        "human"
    ],
    "wof:name":"US Social Security Adm",
    "wof:placetype":"venue"
},
  "geometry": {"coordinates":[-119.74735699999999,39.510293],"type":"Point"}
}