{
  "type": "Feature",
  "properties": {
    "iso:country":"US",
    "sg:address":"514 Island Ave",
    "sg:city":"Reno",
    "sg:classifiers":[
        {
            "category":"Professional",
            "subcategory":"Management & Consulting",
            "type":"Services"
        }
    ],
    "sg:phone":"+1 775 333 6998",
    "sg:postcode":"89501",
    "sg:province":"NV",
    "sg:tags":[
        "facilitation",
        "training"
    ],
    "wof:name":"Sierra Circle Consulting",
    "wof:placetype":"venue"
},
  "geometry": {"coordinates":[-119.816529,39.523476],"type":"Point"}
}