{
  "type": "Feature",
  "properties": {
    "iso:country":"US",
    "sg:address":"411 10th St",
    "sg:city":"Elko",
    "sg:classifiers":[
        {
            "category":"Travel",
            "subcategory":"Hotels & Motels",
            "type":"Entertainment"
        }
    ],
    "sg:phone":"+1 775 738 8018",
    "sg:postcode":"89801",
    "sg:province":"NV",
    "wof:name":"Economy Inn",
    "wof:placetype":"venue"
},
  "geometry": {"coordinates":[-115.758943,40.836676],"type":"Point"}
}