{
  "type": "Feature",
  "properties": {
    "iso:country":"US",
    "sg:address":"500 E Prater Way",
    "sg:city":"Sparks",
    "sg:classifiers":[
        {
            "category":"Banks & Credit Unions",
            "subcategory":"Bank",
            "type":"Services"
        }
    ],
    "sg:phone":"+1 775 852 6611",
    "sg:postcode":"89431",
    "sg:province":"NV",
    "wof:name":"Nevada State Bank",
    "wof:placetype":"venue"
},
  "geometry": {"coordinates":[-119.73554900000001,39.541949],"type":"Point"}
}