{
  "type": "Feature",
  "properties": {
    "iso:country":"US",
    "sg:address":"1732 Maple Creek Ln",
    "sg:city":"Carson City",
    "sg:classifiers":[
        {
            "category":"Wholesale",
            "subcategory":"Machinery & Supplies",
            "type":"Manufacturing & Wholesale Goods"
        }
    ],
    "sg:phone":"+1 775 841 4831",
    "sg:postcode":"89701",
    "sg:province":"NV",
    "sg:tags":[
        "equipment",
        "establishment"
    ],
    "wof:name":"Sierra Vacuum Systems",
    "wof:placetype":"venue"
},
  "geometry": {"coordinates":[-119.749741,39.142195],"type":"Point"}
}