{
  "type": "Feature",
  "properties": {
    "iso:country":"US",
    "sg:address":"3255 S Eastern Ave",
    "sg:city":"Las Vegas",
    "sg:classifiers":[
        {
            "category":"Banks & Credit Unions",
            "subcategory":"Financial Services",
            "type":"Services"
        }
    ],
    "sg:phone":"+1 702 444 9111",
    "sg:postcode":"89169",
    "sg:province":"NV",
    "sg:website":"www.911bailbondslv.com",
    "wof:name":"911 Bail Bonds",
    "wof:placetype":"venue"
},
  "geometry": {"coordinates":[-115.118863,36.130583],"type":"Point"}
}