{
  "type": "Feature",
  "properties": {
    "iso:country":"US",
    "sg:address":"10155 W. Twain Ave. Suite #110",
    "sg:city":"Las Vegas",
    "sg:classifiers":[
        {
            "category":"Health Services",
            "subcategory":"Doctor",
            "type":"Services"
        }
    ],
    "sg:phone":"+1 702 243 2689",
    "sg:postcode":"89147",
    "sg:province":"NV",
    "sg:tags":[
        "practice",
        "family"
    ],
    "sg:website":"www.sparksfamilymedicine.com",
    "wof:name":"Amy R Sparks, MD.",
    "wof:placetype":"venue"
},
  "geometry": {"coordinates":[-115.313945,36.12255],"type":"Point"}
}