{
  "type": "Feature",
  "properties": {
    "iso:country":"US",
    "sg:address":"1343 E Silverado Ranch Boulevard",
    "sg:city":"Las Vegas",
    "sg:classifiers":[
        {
            "category":"Autos & Motor Vehicles",
            "subcategory":"Fuel & Gas Station",
            "type":"Retail Goods"
        },
        {
            "category":"Retail",
            "subcategory":"Car Wash",
            "type":"Services"
        }
    ],
    "sg:phone":"+1 702 270 6873",
    "sg:postcode":"89183",
    "sg:province":"NV",
    "wof:name":"Terrible Herbst",
    "wof:placetype":"venue"
},
  "geometry": {"coordinates":[-115.134816,36.013396],"type":"Point"}
}