{
  "type": "Feature",
  "properties": {
    "iso:country":"US",
    "sg:address":"5085 Dean Martin Dr",
    "sg:city":"Las Vegas",
    "sg:classifiers":[
        {
            "category":"Travel",
            "subcategory":"Hotels & Motels",
            "type":"Entertainment"
        }
    ],
    "sg:phone":"+1 702 739 6747",
    "sg:postcode":"89118",
    "sg:province":"NV",
    "sg:website":"www.motel6.com",
    "wof:name":"Motel 6 Inc",
    "wof:placetype":"venue"
},
  "geometry": {"coordinates":[-115.181914,36.097753],"type":"Point"}
}