{
  "type": "Feature",
  "properties": {
    "iso:country":"US",
    "sg:address":"947 S Rainbow Boulevard",
    "sg:city":"Las Vegas",
    "sg:classifiers":[
        {
            "category":"Cinema",
            "subcategory":"Movie Rental",
            "type":"Entertainment"
        }
    ],
    "sg:phone":"+1 702 258 9075",
    "sg:postcode":"89145",
    "sg:province":"NV",
    "sg:tags":[
        "game",
        "video"
    ],
    "sg:website":"www.gamestop.com",
    "wof:name":"Game Stop",
    "wof:placetype":"venue"
},
  "geometry": {"coordinates":[-115.243744,36.16058],"type":"Point"}
}