{
  "type": "Feature",
  "properties": {
    "iso:country":"US",
    "sg:address":"500 E Parr Blvd",
    "sg:city":"Reno",
    "sg:classifiers":[
        {
            "category":"Railroad",
            "type":"Transportation"
        }
    ],
    "sg:phone":"+1 775 323 4213",
    "sg:postcode":"89512",
    "sg:province":"NV",
    "sg:tags":[
        "operator",
        "line"
    ],
    "wof:name":"Union Pacific Railroad Company",
    "wof:placetype":"venue"
},
  "geometry": {"coordinates":[-119.81459599999999,39.570238],"type":"Point"}
}