{
  "type": "Feature",
  "properties": {
    "iso:country":"US",
    "sg:address":"2251 S Fort Apache Rd",
    "sg:city":"Las Vegas",
    "sg:classifiers":[
        {
            "category":"Banks & Credit Unions",
            "subcategory":"Bank",
            "type":"Services"
        }
    ],
    "sg:phone":"+1 702 341 6378",
    "sg:postcode":"89117",
    "sg:province":"NV",
    "sg:tags":[
        "financing"
    ],
    "wof:name":"Household International",
    "wof:placetype":"venue"
},
  "geometry": {"coordinates":[-115.29628,36.150032],"type":"Point"}
}