{
  "type": "Feature",
  "properties": {
    "iso:country":"US",
    "sg:address":"3450 E Russell Road",
    "sg:city":"Las Vegas",
    "sg:classifiers":[
        {
            "category":"Health Services",
            "subcategory":"Clinic",
            "type":"Services"
        }
    ],
    "sg:phone":"+1 702 214 4253",
    "sg:postcode":"89120",
    "sg:province":"NV",
    "sg:tags":[
        "counseling",
        "mental"
    ],
    "wof:name":"Maria G. Doncaster, PhD",
    "wof:placetype":"venue"
},
  "geometry": {"coordinates":[-115.099591,36.086723],"type":"Point"}
}