{
  "type": "Feature",
  "properties": {
    "iso:country":"US",
    "sg:address":"723 S Casino Center Blvd",
    "sg:city":"Las Vegas",
    "sg:classifiers":[
        {
            "category":"Freight",
            "type":"Transportation"
        }
    ],
    "sg:phone":"+1 702 269 4533",
    "sg:postcode":"89101",
    "sg:province":"NV",
    "wof:name":"Rks Transport Inc",
    "wof:placetype":"venue"
},
  "geometry": {"coordinates":[-115.149165,36.162784],"type":"Point"}
}