{
  "type": "Feature",
  "properties": {
    "iso:country":"US",
    "sg:address":"532 Faultless St",
    "sg:city":"Henderson",
    "sg:classifiers":[
        {
            "category":"Building & Trades",
            "subcategory":"Construction",
            "type":"Services"
        }
    ],
    "sg:phone":"+1 702 431 5578",
    "sg:postcode":"89015",
    "sg:province":"NV",
    "sg:tags":[
        "roofing",
        "contractor"
    ],
    "wof:name":"Harris Roofing",
    "wof:placetype":"venue"
},
  "geometry": {"coordinates":[-114.94155000000001,36.026054],"type":"Point"}
}