{
  "type": "Feature",
  "properties": {
    "iso:country":"US",
    "sg:address":"2060 E Serene Ave",
    "sg:city":"Las Vegas",
    "sg:classifiers":[
        {
            "category":"Restaurant",
            "type":"Food & Drink"
        }
    ],
    "sg:menulink":"http://www.allmenus.com/nv/las-vegas/164165-wienerschnitzel/menu/",
    "sg:phone":"+1 702 269 8082",
    "sg:postcode":"89123",
    "sg:province":"NV",
    "sg:tags":[
        "sandwich",
        "dog",
        "burger",
        "hot",
        "wrap",
        "american"
    ],
    "wof:name":"Wienerschnitzel",
    "wof:placetype":"venue"
},
  "geometry": {"coordinates":[-115.123598,36.020527],"type":"Point"}
}