{
  "type": "Feature",
  "properties": {
    "iso:country":"US",
    "sg:address":"5659 Duncan Dr",
    "sg:city":"Las Vegas",
    "sg:classifiers":[
        {
            "category":"Health Services",
            "subcategory":"Clinic",
            "type":"Services"
        }
    ],
    "sg:phone":"+1 702 645 8093",
    "sg:postcode":"89130",
    "sg:province":"NV",
    "wof:name":"Health Core LLC",
    "wof:placetype":"venue"
},
  "geometry": {"coordinates":[-115.218936,36.228871],"type":"Point"}
}