{
  "type": "Feature",
  "properties": {
    "iso:country":"US",
    "sg:address":"7435 S Eastern Ave",
    "sg:city":"Las Vegas",
    "sg:classifiers":[
        {
            "category":"Shopping",
            "subcategory":"Tobacco",
            "type":"Retail Goods"
        }
    ],
    "sg:phone":"+1 702 260 4354",
    "sg:postcode":"89123",
    "sg:province":"NV",
    "sg:tags":[
        "shop"
    ],
    "wof:name":"Saf Corporation",
    "wof:placetype":"venue"
},
  "geometry": {"coordinates":[-115.118369,36.05437],"type":"Point"}
}