{
  "type": "Feature",
  "properties": {
    "iso:country":"US",
    "sg:address":"The Resort at Summerlin 221 N. Rampart Blvd",
    "sg:city":"Las Vegas",
    "sg:classifiers":[
        {
            "category":"Restaurant",
            "type":"Food & Drink"
        }
    ],
    "sg:phone":"+1 702 869 5966",
    "sg:postcode":"89145",
    "sg:province":"NV",
    "sg:tags":[
        "traditional",
        "american"
    ],
    "sg:website":"www.jwlasvegasresort.com/restaur...",
    "wof:name":"Promenade Cafe",
    "wof:placetype":"venue"
},
  "geometry": {"coordinates":[-115.290595,36.175699],"type":"Point"}
}