{
  "type": "Feature",
  "properties": {
    "iso:country":"US",
    "sg:address":"47 S Spring Mountain Cir",
    "sg:city":"Sparks",
    "sg:classifiers":[
        {
            "category":"Shopping",
            "subcategory":"Bicycles & Sporting Goods",
            "type":"Retail Goods"
        }
    ],
    "sg:phone":"+1 775 425 2911",
    "sg:postcode":"89436",
    "sg:province":"NV",
    "wof:name":"L S & B Guns",
    "wof:placetype":"venue"
},
  "geometry": {"coordinates":[-119.72085300000001,39.629586],"type":"Point"}
}