{
  "type": "Feature",
  "properties": {
    "iso:country":"US",
    "sg:address":"1290 Kietzke Ln",
    "sg:city":"Reno",
    "sg:classifiers":[
        {
            "category":"Autos & Motor Vehicles",
            "subcategory":"Auto Supplies",
            "type":"Retail Goods"
        }
    ],
    "sg:phone":"+1 775 324 3111",
    "sg:postcode":"89502",
    "sg:province":"NV",
    "sg:tags":[
        "automotive",
        "tire"
    ],
    "sg:website":"www.lesschwab.com",
    "wof:name":"Les Schwab Tire Center",
    "wof:placetype":"venue"
},
  "geometry": {"coordinates":[-119.789169,39.512958],"type":"Point"}
}