{
  "type": "Feature",
  "properties": {
    "iso:country":"US",
    "sg:address":"4171 S Maryland Pkwy",
    "sg:city":"Las Vegas",
    "sg:classifiers":[
        {
            "category":"Shopping",
            "subcategory":"Florist",
            "type":"Retail Goods"
        }
    ],
    "sg:phone":"+1 702 740 4770",
    "sg:postcode":"89119",
    "sg:province":"NV",
    "sg:website":"www.englishgardenflorist.com/",
    "wof:name":"English Garden Florist",
    "wof:placetype":"venue"
},
  "geometry": {"coordinates":[-115.137729,36.113096],"type":"Point"}
}