{
  "type": "Feature",
  "properties": {
    "iso:country":"US",
    "sg:address":"222 N Sierra St",
    "sg:city":"Reno",
    "sg:classifiers":[
        {
            "category":"Travel",
            "subcategory":"Hotels & Motels",
            "type":"Entertainment"
        }
    ],
    "sg:phone":"+1 775 322 2178",
    "sg:postcode":"89501",
    "sg:province":"NV",
    "sg:website":"http://www.highdeserthosting.net",
    "wof:name":"Ace Motor Lodge",
    "wof:placetype":"venue"
},
  "geometry": {"coordinates":[-119.814837,39.527434],"type":"Point"}
}