{
  "type": "Feature",
  "properties": {
    "iso:country":"US",
    "sg:address":"5250 Neil Rd",
    "sg:city":"Reno",
    "sg:classifiers":[
        {
            "category":"Health Services",
            "subcategory":"Doctor",
            "type":"Services"
        }
    ],
    "sg:phone":"+1 775 823 1999",
    "sg:postcode":"89502",
    "sg:province":"NV",
    "sg:tags":[
        "physician",
        "surgeon"
    ],
    "sg:website":"www.renorad.com",
    "wof:name":"Reno Radiological Assoc",
    "wof:placetype":"venue"
},
  "geometry": {"coordinates":[-119.778557,39.474723],"type":"Point"}
}