{
  "type": "Feature",
  "properties": {
    "iso:country":"US",
    "sg:address":"3330 E Tropicana Avenue",
    "sg:city":"Las Vegas",
    "sg:classifiers":[
        {
            "category":"Banks & Credit Unions",
            "subcategory":"Financial Services",
            "type":"Services"
        }
    ],
    "sg:phone":"+1 702 547 0053",
    "sg:postcode":"89121",
    "sg:province":"NV",
    "sg:tags":[
        "broker",
        "mortgage"
    ],
    "wof:name":"Alvarez M",
    "wof:placetype":"venue"
},
  "geometry": {"coordinates":[-115.102572,36.10009],"type":"Point"}
}