{
  "type": "Feature",
  "properties": {
    "iso:country":"US",
    "sg:address":"1281 Terminal Way",
    "sg:city":"Reno",
    "sg:classifiers":[
        {
            "category":"Organizations",
            "subcategory":"Professional Association",
            "type":"Services"
        }
    ],
    "sg:phone":"+1 775 322 7064",
    "sg:postcode":"89502",
    "sg:province":"NV",
    "wof:name":"American Heart Assn",
    "wof:placetype":"venue"
},
  "geometry": {"coordinates":[-119.777517,39.51147],"type":"Point"}
}