{
  "type": "Feature",
  "properties": {
    "iso:country":"US",
    "sg:address":"3700 Crazy Horse Rd",
    "sg:city":"Reno",
    "sg:classifiers":[
        {
            "category":"Building & Trades",
            "subcategory":"Equipment Rental",
            "type":"Services"
        }
    ],
    "sg:phone":"+1 775 475 2602",
    "sg:postcode":"89510",
    "sg:province":"NV",
    "sg:tags":[
        "sales"
    ],
    "wof:name":"McKinnies Equipment Co",
    "wof:placetype":"venue"
},
  "geometry": {"coordinates":[-119.59397,39.734601],"type":"Point"}
}