{
  "type": "Feature",
  "properties": {
    "iso:country":"US",
    "sg:address":"9055 S Eastern Ave",
    "sg:city":"Las Vegas",
    "sg:classifiers":[
        {
            "category":"Restaurant",
            "type":"Food & Drink"
        }
    ],
    "sg:phone":"+1 702 458 4745",
    "sg:postcode":"89123",
    "sg:province":"NV",
    "wof:name":"American Grill",
    "wof:placetype":"venue"
},
  "geometry": {"coordinates":[-115.118557,36.026039],"type":"Point"}
}