{
  "type": "Feature",
  "properties": {
    "iso:country":"US",
    "sg:address":"855 Sparks Blvd",
    "sg:city":"Sparks",
    "sg:classifiers":[
        {
            "category":"Banks & Credit Unions",
            "subcategory":"Investment Brokerage",
            "type":"Services"
        },
        {
            "category":"Banks & Credit Unions",
            "subcategory":"Bank",
            "type":"Services"
        },
        {
            "category":"Banks & Credit Unions",
            "subcategory":"Financial Services",
            "type":"Services"
        }
    ],
    "sg:phone":"+1 775 685 2240",
    "sg:postcode":"89434",
    "sg:province":"NV",
    "sg:tags":[
        "saving",
        "commercial"
    ],
    "sg:website":"http://www.bankofthewest.com",
    "wof:name":"Bank Of The West",
    "wof:placetype":"venue"
},
  "geometry": {"coordinates":[-119.715408,39.5442],"type":"Point"}
}