{
  "type": "Feature",
  "properties": {
    "iso:country":"US",
    "sg:address":"7401 W Charleston Blvd",
    "sg:city":"Las Vegas",
    "sg:classifiers":[
        {
            "category":"Professional",
            "type":"Services"
        }
    ],
    "sg:phone":"+1 702 228 6102",
    "sg:postcode":"89117",
    "sg:province":"NV",
    "wof:name":"Nevada Sky Corporation",
    "wof:placetype":"venue"
},
  "geometry": {"coordinates":[-115.260368,36.159093],"type":"Point"}
}