{
  "type": "Feature",
  "properties": {
    "iso:country":"US",
    "sg:address":"5041 Ironhorse Ranch Ave",
    "sg:city":"Las Vegas",
    "sg:classifiers":[
        {
            "category":"Banks & Credit Unions",
            "subcategory":"Financial Services",
            "type":"Services"
        }
    ],
    "sg:phone":"+1 702 645 1503",
    "sg:postcode":"89131",
    "sg:province":"NV",
    "sg:tags":[
        "investment",
        "closed"
    ],
    "wof:name":"Betty Brossard",
    "wof:placetype":"venue"
},
  "geometry": {"coordinates":[-115.209756,36.315053],"type":"Point"}
}