{
  "type": "Feature",
  "properties": {
    "iso:country":"US",
    "sg:address":"69 Adams Waite Ln",
    "sg:city":"Bunkerville",
    "sg:classifiers":[
        {
            "category":"Building & Trades",
            "subcategory":"Plumbing",
            "type":"Services"
        }
    ],
    "sg:phone":"+1 702 346 4961",
    "sg:postcode":"89024",
    "sg:province":"NV",
    "sg:tags":[
        "conditioning",
        "air",
        "system",
        "contractor"
    ],
    "wof:name":"S E Mechanical",
    "wof:placetype":"venue"
},
  "geometry": {"coordinates":[-114.121009,36.772698],"type":"Point"}
}