{
  "type": "Feature",
  "properties": {
    "iso:country":"US",
    "sg:address":"6180 S Pearl St",
    "sg:city":"Las Vegas",
    "sg:classifiers":[
        {
            "category":"Freight",
            "type":"Transportation"
        }
    ],
    "sg:phone":"+1 702 851 7630",
    "sg:postcode":"89120",
    "sg:province":"NV",
    "sg:tags":[
        "mover"
    ],
    "wof:name":"Pyramid Logistics Svc Inc",
    "wof:placetype":"venue"
},
  "geometry": {"coordinates":[-115.096356,36.076653],"type":"Point"}
}