{
  "type": "Feature",
  "properties": {
    "iso:country":"US",
    "sg:address":"1299 N Mountain St",
    "sg:city":"Carson City",
    "sg:classifiers":[
        {
            "category":"Health Services",
            "subcategory":"Doctor",
            "type":"Services"
        }
    ],
    "sg:phone":"+1 775 883 1700",
    "sg:postcode":"89703",
    "sg:province":"NV",
    "sg:tags":[
        "surgery",
        "center",
        "out"
    ],
    "wof:name":"Casci",
    "wof:placetype":"venue"
},
  "geometry": {"coordinates":[-119.772873,39.171741],"type":"Point"}
}