{
  "type": "Feature",
  "properties": {
    "iso:country":"US",
    "sg:address":"7810 W Ann Rd",
    "sg:city":"Las Vegas",
    "sg:classifiers":[
        {
            "category":"Sports & Exercise",
            "subcategory":"Gym",
            "type":"Entertainment"
        }
    ],
    "sg:phone":"+1 702 255 0000",
    "sg:postcode":"89149",
    "sg:province":"NV",
    "sg:tags":[
        "fitness",
        "physical",
        "facility"
    ],
    "wof:name":"Pure Pilates",
    "wof:placetype":"venue"
},
  "geometry": {"coordinates":[-115.266917,36.263058],"type":"Point"}
}