{
  "type": "Feature",
  "properties": {
    "iso:country":"US",
    "sg:address":"3191 Green River Dr",
    "sg:city":"Reno",
    "sg:classifiers":[
        {
            "category":"Organizations",
            "subcategory":"Membership Organization",
            "type":"Services"
        }
    ],
    "sg:phone":"+1 775 787 7852",
    "sg:postcode":"89503",
    "sg:province":"NV",
    "wof:name":"American Therapeutic Assn",
    "wof:placetype":"venue"
},
  "geometry": {"coordinates":[-119.856369,39.54814],"type":"Point"}
}