{
  "type": "Feature",
  "properties": {
    "iso:country":"US",
    "sg:address":"3346 Smoke Tree Ln",
    "sg:city":"Las Vegas",
    "sg:classifiers":[
        {
            "category":"Building & Trades",
            "subcategory":"Plumbing",
            "type":"Services"
        }
    ],
    "sg:phone":"+1 702 454 6720",
    "sg:postcode":"89120",
    "sg:province":"NV",
    "sg:tags":[
        "plumbing",
        "contractor"
    ],
    "wof:name":"Chris Juelke Plumbing",
    "wof:placetype":"venue"
},
  "geometry": {"coordinates":[-115.102093,36.068034],"type":"Point"}
}