{
  "type": "Feature",
  "properties": {
    "iso:country":"US",
    "sg:address":"10161 Park Run Dr Ste 150",
    "sg:city":"Las Vegas",
    "sg:classifiers":[
        {
            "category":"Building & Trades",
            "subcategory":"Construction",
            "type":"Services"
        }
    ],
    "sg:phone":"+1 702 515 7492",
    "sg:postcode":"89145",
    "sg:province":"NV",
    "sg:tags":[
        "contractor"
    ],
    "wof:name":"Lewis Construction Inc",
    "wof:placetype":"venue"
},
  "geometry": {"coordinates":[-115.31666,36.161109],"type":"Point"}
}