{
  "type": "Feature",
  "properties": {
    "iso:country":"US",
    "sg:address":"2450 W Charleston Blvd",
    "sg:city":"Las Vegas",
    "sg:classifiers":[
        {
            "category":"Health Services",
            "subcategory":"Doctor",
            "type":"Services"
        }
    ],
    "sg:phone":"+1 702 259 5027",
    "sg:postcode":"89102",
    "sg:province":"NV",
    "sg:tags":[
        "physician",
        "surgeon"
    ],
    "wof:name":"Ebert Institute Of Cosmetic",
    "wof:placetype":"venue"
},
  "geometry": {"coordinates":[-115.174678,36.158978],"type":"Point"}
}