{
  "type": "Feature",
  "properties": {
    "iso:country":"US",
    "sg:address":"198 N Pecos Rd",
    "sg:city":"Henderson",
    "sg:classifiers":[
        {
            "category":"Food & Beverages",
            "subcategory":"Groceries & Convenience Stores",
            "type":"Retail Goods"
        }
    ],
    "sg:phone":"+1 702 433 4343",
    "sg:postcode":"89074",
    "sg:province":"NV",
    "wof:name":"Texaco",
    "wof:placetype":"venue"
},
  "geometry": {"coordinates":[-115.100266,36.042389],"type":"Point"}
}