{
  "type": "Feature",
  "properties": {
    "iso:country":"US",
    "sg:address":"1130 Amarillo Ave",
    "sg:city":"Pahrump",
    "sg:classifiers":[
        {
            "category":"Building & Trades",
            "subcategory":"Electrical",
            "type":"Services"
        }
    ],
    "sg:phone":"+1 775 727 8296",
    "sg:postcode":"89048",
    "sg:province":"NV",
    "sg:tags":[
        "electrical",
        "contractor"
    ],
    "wof:name":"D J Sign Big Horn Condo",
    "wof:placetype":"venue"
},
  "geometry": {"coordinates":[-116.019755,36.182156],"type":"Point"}
}