{
  "type": "Feature",
  "properties": {
    "iso:country":"US",
    "sg:address":"5 Castle Way",
    "sg:city":"Carson City",
    "sg:classifiers":[
        {
            "category":"Professional",
            "subcategory":"Advertising",
            "type":"Services"
        }
    ],
    "sg:phone":"+1 775 883 3538",
    "sg:postcode":"89706",
    "sg:province":"NV",
    "sg:tags":[
        "agency"
    ],
    "wof:name":"Alexander Hill & Associates",
    "wof:placetype":"venue"
},
  "geometry": {"coordinates":[-119.766781,39.191014],"type":"Point"}
}