{
  "type": "Feature",
  "properties": {
    "iso:country":"US",
    "sg:address":"7080 N. Durango Drive Suite 150",
    "sg:city":"Las Vegas",
    "sg:classifiers":[
        {
            "category":"Shopping",
            "subcategory":"Bridal",
            "type":"Retail Goods"
        }
    ],
    "sg:phone":"+1 702 456 3500",
    "sg:postcode":"89149",
    "sg:province":"NV",
    "sg:website":"www.blushbrideslv.com",
    "wof:name":"Blush Bridal Boutique",
    "wof:placetype":"venue"
},
  "geometry": {"coordinates":[-115.287747,36.289564],"type":"Point"}
}