{
  "type": "Feature",
  "properties": {
    "iso:country":"US",
    "sg:address":"410 O'Brian Way",
    "sg:city":"Sparks",
    "sg:classifiers":[
        {
            "category":"Building & Trades",
            "subcategory":"Construction",
            "type":"Services"
        }
    ],
    "sg:phone":"+1 775 827 4748",
    "sg:postcode":"89431",
    "sg:province":"NV",
    "sg:tags":[
        "home",
        "manufactured",
        "repair"
    ],
    "wof:name":"Mels Home Repair",
    "wof:placetype":"venue"
},
  "geometry": {"coordinates":[-119.08854599999999,38.997814],"type":"Point"}
}