{
  "type": "Feature",
  "properties": {
    "iso:country":"US",
    "sg:address":"7156 Cherrywood Forest Ln",
    "sg:city":"Las Vegas",
    "sg:classifiers":[
        {
            "category":"Personal",
            "type":"Services"
        }
    ],
    "sg:phone":"+1 702 452 1319",
    "sg:postcode":"89156",
    "sg:province":"NV",
    "wof:name":"Sights & Bytes",
    "wof:placetype":"venue"
},
  "geometry": {"coordinates":[-115.01616199999999,36.201808],"type":"Point"}
}