{
  "type": "Feature",
  "properties": {
    "iso:country":"US",
    "sg:address":"3327 Erva St",
    "sg:city":"Las Vegas",
    "sg:classifiers":[
        {
            "category":"Banks & Credit Unions",
            "subcategory":"Financial Services",
            "type":"Services"
        }
    ],
    "sg:phone":"+1 702 242 5859",
    "sg:postcode":"89117",
    "sg:province":"NV",
    "sg:tags":[
        "company",
        "holding"
    ],
    "wof:name":"Business Holdings Inc",
    "wof:placetype":"venue"
},
  "geometry": {"coordinates":[-115.292533,36.129618],"type":"Point"}
}