{
  "type": "Feature",
  "properties": {
    "iso:country":"US",
    "sg:address":"7501 Bridlehorne Ave",
    "sg:city":"Las Vegas",
    "sg:classifiers":[
        {
            "category":"Professional",
            "subcategory":"Business Services",
            "type":"Services"
        }
    ],
    "sg:phone":"+1 702 365 7857",
    "sg:postcode":"89131",
    "sg:province":"NV",
    "sg:tags":[
        "interior",
        "consultant",
        "design",
        "decorator"
    ],
    "wof:name":"Franchestas Interior Design",
    "wof:placetype":"venue"
},
  "geometry": {"coordinates":[-115.257503,36.294328],"type":"Point"}
}