{
  "type": "Feature",
  "properties": {
    "iso:country":"US",
    "sg:address":"4035 E Post Rd",
    "sg:city":"Las Vegas",
    "sg:classifiers":[
        {
            "category":"Wholesale",
            "subcategory":"Stationery",
            "type":"Manufacturing & Wholesale Goods"
        },
        {
            "category":"Manufacturing",
            "subcategory":"Printing",
            "type":"Manufacturing & Wholesale Goods"
        }
    ],
    "sg:phone":"+1 702 367 6888",
    "sg:postcode":"89120",
    "sg:province":"NV",
    "sg:tags":[
        "printer",
        "form",
        "business"
    ],
    "wof:name":"Nevada Form Specialists Inc",
    "wof:placetype":"venue"
},
  "geometry": {"coordinates":[-115.085407,36.074605],"type":"Point"}
}