{
  "type": "Feature",
  "properties": {
    "iso:country":"US",
    "sg:address":"71 Spectrum Blvd",
    "sg:city":"Las Vegas",
    "sg:classifiers":[
        {
            "category":"Real Estate",
            "subcategory":"Architect",
            "type":"Services"
        }
    ],
    "sg:phone":"+1 702 438 6900",
    "sg:postcode":"89101",
    "sg:province":"NV",
    "sg:tags":[
        "material",
        "architectural"
    ],
    "wof:name":"Hoseks Architectural Studio",
    "wof:placetype":"venue"
},
  "geometry": {"coordinates":[-115.102205,36.161397],"type":"Point"}
}