{
  "type": "Feature",
  "properties": {
    "iso:country":"US",
    "sg:address":"140 Culverwell St",
    "sg:city":"Caliente",
    "sg:classifiers":[
        {
            "category":"Organizations",
            "subcategory":"Religious Organization",
            "type":"Services"
        }
    ],
    "sg:phone":"+1 775 726 3665",
    "sg:postcode":"89008",
    "sg:province":"NV",
    "sg:tags":[
        "church"
    ],
    "wof:name":"Caliente Community Methodist",
    "wof:placetype":"venue"
},
  "geometry": {"coordinates":[-114.512263,37.616619],"type":"Point"}
}