{
  "type": "Feature",
  "properties": {
    "iso:country":"US",
    "sg:address":"3611 S Lindell Rd",
    "sg:city":"Las Vegas",
    "sg:classifiers":[
        {
            "category":"Utilities",
            "subcategory":"Telephone",
            "type":"Services"
        }
    ],
    "sg:phone":"+1 702 252 8845",
    "sg:postcode":"89103",
    "sg:province":"NV",
    "sg:tags":[
        "host",
        "internet"
    ],
    "wof:name":"Nevada Internet Services",
    "wof:placetype":"venue"
},
  "geometry": {"coordinates":[-115.216555,36.123691],"type":"Point"}
}