{
  "type": "Feature",
  "properties": {
    "iso:country":"US",
    "sg:address":"2700 Gallagher Ct",
    "sg:city":"Las Vegas",
    "sg:classifiers":[
        {
            "category":"Manufacturing",
            "subcategory":"Printing",
            "type":"Manufacturing & Wholesale Goods"
        }
    ],
    "sg:phone":"+1 702 319 4300",
    "sg:postcode":"89117",
    "sg:province":"NV",
    "sg:tags":[
        "multimedia"
    ],
    "wof:name":"And Media",
    "wof:placetype":"venue"
},
  "geometry": {"coordinates":[-115.311297,36.142587],"type":"Point"}
}