{
  "type": "Feature",
  "properties": {
    "iso:country":"US",
    "sg:address":"3261 Elliott Dr",
    "sg:city":"Reno",
    "sg:classifiers":[
        {
            "category":"Restaurant",
            "type":"Food & Drink"
        }
    ],
    "sg:phone":"+1 775 322 4439",
    "sg:postcode":"89512",
    "sg:province":"NV",
    "wof:name":"Mann's Restaurant",
    "wof:placetype":"venue"
},
  "geometry": {"coordinates":[-119.79200899999999,39.564646],"type":"Point"}
}