{
  "type": "Feature",
  "properties": {
    "iso:country":"US",
    "sg:address":"4437 W Charleston Blvd",
    "sg:city":"Las Vegas",
    "sg:classifiers":[
        {
            "category":"Restaurant",
            "type":"Food & Drink"
        }
    ],
    "sg:phone":"+1 702 258 5184",
    "sg:postcode":"89102",
    "sg:province":"NV",
    "sg:tags":[
        "device",
        "operator",
        "eating",
        "amusement"
    ],
    "wof:name":"Charlies Bar & Grill",
    "wof:placetype":"venue"
},
  "geometry": {"coordinates":[-115.200775,36.158975],"type":"Point"}
}