{
  "type": "Feature",
  "properties": {
    "iso:country":"US",
    "sg:address":"239 Plumb Ln",
    "sg:city":"Reno",
    "sg:classifiers":[
        {
            "category":"Shopping",
            "type":"Retail Goods"
        }
    ],
    "sg:phone":"+1 775 322 5779",
    "sg:postcode":"89502",
    "sg:province":"NV",
    "sg:tags":[
        "hawaiian"
    ],
    "wof:name":"Kona Girl",
    "wof:placetype":"venue"
},
  "geometry": {"coordinates":[-119.802644,39.505792],"type":"Point"}
}