{
  "type": "Feature",
  "properties": {
    "iso:country":"US",
    "sg:address":"2000 Scenic Sunrise Dr",
    "sg:city":"Las Vegas",
    "sg:classifiers":[
        {
            "category":"Shopping",
            "subcategory":"Computers & Home Electronics",
            "type":"Retail Goods"
        }
    ],
    "sg:phone":"+1 702 768 7726",
    "sg:postcode":"89117",
    "sg:province":"NV",
    "sg:tags":[
        "parts",
        "supply"
    ],
    "wof:name":"1clear PCS",
    "wof:placetype":"venue"
},
  "geometry": {"coordinates":[-115.303078,36.148572],"type":"Point"}
}