{
  "type": "Feature",
  "properties": {
    "iso:country":"US",
    "sg:address":"1821 Western Ave",
    "sg:city":"Las Vegas",
    "sg:classifiers":[
        {
            "category":"Insurance",
            "subcategory":"Insurance Agent",
            "type":"Services"
        }
    ],
    "sg:phone":"+1 702 212 4970",
    "sg:postcode":"89102",
    "sg:province":"NV",
    "wof:name":"American Auto Insurance",
    "wof:placetype":"venue"
},
  "geometry": {"coordinates":[-115.16213500000001,36.15223],"type":"Point"}
}