{
  "type": "Feature",
  "properties": {
    "iso:country":"US",
    "sg:address":"2208 E Charleston Blvd",
    "sg:city":"Las Vegas",
    "sg:classifiers":[
        {
            "category":"Shopping",
            "subcategory":"Books",
            "type":"Retail Goods"
        }
    ],
    "sg:phone":"+1 702 464 6414",
    "sg:postcode":"89104",
    "sg:province":"NV",
    "sg:tags":[
        "bookstore"
    ],
    "wof:name":"Vcv Libreria Cristiana",
    "wof:placetype":"venue"
},
  "geometry": {"coordinates":[-115.11764,36.158764],"type":"Point"}
}