{
  "type": "Feature",
  "properties": {
    "iso:country":"US",
    "sg:address":"3773 Baker Ln",
    "sg:city":"Reno",
    "sg:classifiers":[
        {
            "category":"Health Services",
            "subcategory":"Doctor",
            "type":"Services"
        }
    ],
    "sg:phone":"+1 775 825 1875",
    "sg:postcode":"89509",
    "sg:province":"NV",
    "wof:name":"Vowles Keith O DDS",
    "wof:placetype":"venue"
},
  "geometry": {"coordinates":[-119.798757,39.490008],"type":"Point"}
}