{
  "type": "Feature",
  "properties": {
    "iso:country":"US",
    "sg:address":"2725 Crystal Beach Dr",
    "sg:city":"Las Vegas",
    "sg:classifiers":[
        {
            "category":"Communications",
            "subcategory":"Newspaper",
            "type":"Services"
        }
    ],
    "sg:phone":"+1 702 382 1923",
    "sg:postcode":"89128",
    "sg:province":"NV",
    "sg:tags":[
        "print",
        "medium"
    ],
    "sg:website":"www.andersonpromotions.com",
    "wof:name":"Anderson Promotions",
    "wof:placetype":"venue"
},
  "geometry": {"coordinates":[-115.267998,36.209801],"type":"Point"}
}