{
  "type": "Feature",
  "properties": {
    "iso:country":"US",
    "sg:address":"833 Nevada Hwy",
    "sg:city":"Boulder City",
    "sg:classifiers":[
        {
            "category":"Retail",
            "subcategory":"Funeral Services",
            "type":"Services"
        }
    ],
    "sg:phone":"+1 702 294 3000",
    "sg:postcode":"89005",
    "sg:province":"NV",
    "sg:tags":[
        "director"
    ],
    "wof:name":"Boulder City Family Mortuary",
    "wof:placetype":"venue"
},
  "geometry": {"coordinates":[-114.842152,35.973845],"type":"Point"}
}