{
  "type": "Feature",
  "properties": {
    "iso:country":"US",
    "sg:address":"5825 Eldoro Ave",
    "sg:city":"Las Vegas",
    "sg:classifiers":[
        {
            "category":"Organizations",
            "subcategory":"Religious Organization",
            "type":"Services"
        }
    ],
    "sg:phone":"+1 702 871 1900",
    "sg:postcode":"89146",
    "sg:province":"NV",
    "sg:tags":[
        "church"
    ],
    "wof:name":"Iglesia Amigos De Israel",
    "wof:placetype":"venue"
},
  "geometry": {"coordinates":[-115.221215,36.140484],"type":"Point"}
}