{
  "type": "Feature",
  "properties": {
    "iso:country":"US",
    "sg:address":"2225 Green Vista Dr",
    "sg:city":"Sparks",
    "sg:classifiers":[
        {
            "category":"Banks & Credit Unions",
            "subcategory":"Bank",
            "type":"Services"
        }
    ],
    "sg:phone":"+1 775 673 7730",
    "sg:postcode":"89431",
    "sg:province":"NV",
    "sg:tags":[
        "loan",
        "real estate"
    ],
    "wof:name":"Platinum First Mortgage",
    "wof:placetype":"venue"
},
  "geometry": {"coordinates":[-119.774569,39.558607],"type":"Point"}
}