{
  "type": "Feature",
  "properties": {
    "iso:country":"US",
    "sg:address":"224 Vassar St",
    "sg:city":"Reno",
    "sg:classifiers":[
        {
            "category":"Shopping",
            "subcategory":"Jewelry",
            "type":"Retail Goods"
        },
        {
            "category":"Wholesale",
            "subcategory":"Jewelry",
            "type":"Manufacturing & Wholesale Goods"
        }
    ],
    "sg:phone":"+1 775 329 2728",
    "sg:postcode":"89502",
    "sg:province":"NV",
    "sg:tags":[
        "stone",
        "jeweler"
    ],
    "wof:name":"Lapis Bear Jewelry Inc",
    "wof:placetype":"venue"
},
  "geometry": {"coordinates":[-119.803479,39.512806],"type":"Point"}
}