{
  "type": "Feature",
  "properties": {
    "iso:country":"US",
    "sg:address":"1125 Terminal Way",
    "sg:city":"Reno",
    "sg:classifiers":[
        {
            "category":"Health Services",
            "subcategory":"Clinic",
            "type":"Services"
        }
    ],
    "sg:phone":"+1 775 329 6451",
    "sg:postcode":"89502",
    "sg:province":"NV",
    "sg:tags":[
        "banks",
        "blood",
        "center"
    ],
    "wof:name":"United Blood Svc",
    "wof:placetype":"venue"
},
  "geometry": {"coordinates":[-119.777349,39.516452],"type":"Point"}
}