{
  "type": "Feature",
  "properties": {
    "iso:country":"US",
    "sg:address":"145 N Humboldt St",
    "sg:city":"Battle Mountain",
    "sg:classifiers":[
        {
            "category":"Utilities",
            "subcategory":"Electric",
            "type":"Services"
        }
    ],
    "sg:phone":"+1 775 635 2476",
    "sg:postcode":"89820",
    "sg:province":"NV",
    "sg:tags":[
        "company"
    ],
    "wof:name":"Sierra Pacific Power Co",
    "wof:placetype":"venue"
},
  "geometry": {"coordinates":[-116.932936,40.644902],"type":"Point"}
}