{
  "type": "Feature",
  "properties": {
    "iso:country":"US",
    "sg:address":"2320 Tam Dr",
    "sg:city":"Las Vegas",
    "sg:classifiers":[
        {
            "category":"Real Estate",
            "subcategory":"Real Estate Operator",
            "type":"Services"
        }
    ],
    "sg:phone":"+1 702 643 0015",
    "sg:postcode":"89102",
    "sg:province":"NV",
    "sg:tags":[
        "apartment"
    ],
    "wof:name":"Toscana Apartments",
    "wof:placetype":"venue"
},
  "geometry": {"coordinates":[-115.162345,36.145741],"type":"Point"}
}