{
  "type": "Feature",
  "properties": {
    "iso:country":"US",
    "sg:address":"7945 W Sahara Ave",
    "sg:city":"Las Vegas",
    "sg:classifiers":[
        {
            "category":"Cinema",
            "subcategory":"Movie Rental",
            "type":"Entertainment"
        }
    ],
    "sg:phone":"+1 702 804 0079",
    "sg:postcode":"89117",
    "sg:province":"NV",
    "sg:tags":[
        "operates",
        "game",
        "video",
        "owns",
        "hollywood",
        "store"
    ],
    "wof:name":"Hollywood Video",
    "wof:placetype":"venue"
},
  "geometry": {"coordinates":[-115.26405099999999,36.143678],"type":"Point"}
}