{
  "type": "Feature",
  "properties": {
    "iso:country":"US",
    "sg:address":"14 Via de Luccia",
    "sg:city":"Henderson",
    "sg:classifiers":[
        {
            "category":"Retail",
            "subcategory":"Photofinishing",
            "type":"Services"
        }
    ],
    "sg:phone":"+1 702 260 8800",
    "sg:postcode":"89074",
    "sg:province":"NV",
    "sg:tags":[
        "photographic"
    ],
    "wof:name":"Golf Experience Photo",
    "wof:placetype":"venue"
},
  "geometry": {"coordinates":[-115.098794,36.027171],"type":"Point"}
}