{
  "type": "Feature",
  "properties": {
    "iso:country":"US",
    "sg:address":"3226 Spring Mountain Road",
    "sg:city":"Las Vegas",
    "sg:classifiers":[
        {
            "category":"Shopping",
            "subcategory":"Clothing, Apparel, & Fashions",
            "type":"Retail Goods"
        }
    ],
    "sg:phone":"+1 702 247 1101",
    "sg:postcode":"89102",
    "sg:province":"NV",
    "sg:tags":[
        "lingerie"
    ],
    "wof:name":"Spring Mountain Book & Video",
    "wof:placetype":"venue"
},
  "geometry": {"coordinates":[-115.18348,36.126493],"type":"Point"}
}