{
  "type": "Feature",
  "properties": {
    "iso:country":"US",
    "sg:address":"736 McCourry Blvd",
    "sg:city":"Incline Village",
    "sg:classifiers":[
        {
            "category":"Organizations",
            "subcategory":"Religious Organization",
            "type":"Services"
        }
    ],
    "sg:phone":"+1 775 831 0784",
    "sg:postcode":"89451",
    "sg:province":"NV",
    "sg:tags":[
        "church"
    ],
    "sg:website":"www.inclinechurch.org",
    "wof:name":"Village Presbyterian Church",
    "wof:placetype":"venue"
},
  "geometry": {"coordinates":[-119.964066,39.255353],"type":"Point"}
}