{
  "type": "Feature",
  "properties": {
    "iso:country":"US",
    "sg:address":"4187 E Sahara Ave",
    "sg:city":"Las Vegas",
    "sg:classifiers":[
        {
            "category":"Utilities",
            "subcategory":"Telephone",
            "type":"Services"
        }
    ],
    "sg:phone":"+1 702 641 0821",
    "sg:postcode":"89104",
    "sg:province":"NV",
    "sg:tags":[
        "communications"
    ],
    "wof:name":"MCI",
    "wof:placetype":"venue"
},
  "geometry": {"coordinates":[-115.086928,36.14426],"type":"Point"}
}