{
  "type": "Feature",
  "properties": {
    "iso:country":"US",
    "sg:address":"30 Brown Dr",
    "sg:city":"Carson City",
    "sg:classifiers":[
        {
            "category":"Wholesale",
            "subcategory":"Machinery & Supplies",
            "type":"Manufacturing & Wholesale Goods"
        },
        {
            "category":"Home & Garden",
            "subcategory":"Garden Supply",
            "type":"Retail Goods"
        }
    ],
    "sg:phone":"+1 775 246 9888",
    "sg:postcode":"89706",
    "sg:province":"NV",
    "sg:tags":[
        "landscaping",
        "equipment"
    ],
    "wof:name":"Chromascape Inc",
    "wof:placetype":"venue"
},
  "geometry": {"coordinates":[-119.658304,39.22503],"type":"Point"}
}