{
  "type": "Feature",
  "properties": {
    "iso:country":"US",
    "sg:address":"444 Kirman Ave",
    "sg:city":"Reno",
    "sg:classifiers":[
        {
            "category":"Building & Trades",
            "subcategory":"Cleaning & Sanitation",
            "type":"Services"
        }
    ],
    "sg:phone":"+1 775 322 3273",
    "sg:postcode":"89502",
    "sg:province":"NV",
    "sg:tags":[
        "janitor"
    ],
    "wof:name":"Edgil Cleaning Svc",
    "wof:placetype":"venue"
},
  "geometry": {"coordinates":[-119.798382,39.521746],"type":"Point"}
}