{
  "type": "Feature",
  "properties": {
    "iso:country":"US",
    "sg:address":"1720 Mountain City Hwy",
    "sg:city":"Elko",
    "sg:classifiers":[
        {
            "category":"Banks & Credit Unions",
            "subcategory":"Bank",
            "type":"Services"
        }
    ],
    "sg:phone":"+1 775 753 8585",
    "sg:postcode":"89801",
    "sg:province":"NV",
    "sg:tags":[
        "federal"
    ],
    "wof:name":"Operating Engineers Local Un 3",
    "wof:placetype":"venue"
},
  "geometry": {"coordinates":[-115.786333,40.833332],"type":"Point"}
}