{
  "type": "Feature",
  "properties": {
    "iso:country":"US",
    "sg:address":"5740 Arville St",
    "sg:city":"Las Vegas",
    "sg:classifiers":[
        {
            "category":"Real Estate",
            "subcategory":"Real Estate Agent",
            "type":"Services"
        }
    ],
    "sg:phone":"+1 702 362 6485",
    "sg:postcode":"89118",
    "sg:province":"NV",
    "wof:name":"Bedford Property Investors Inc",
    "wof:placetype":"venue"
},
  "geometry": {"coordinates":[-115.199101,36.085239],"type":"Point"}
}