{
  "type": "Feature",
  "properties": {
    "iso:country":"US",
    "sg:address":"4955 S Durango Drive",
    "sg:city":"Las Vegas",
    "sg:classifiers":[
        {
            "category":"Banks & Credit Unions",
            "subcategory":"Financial Services",
            "type":"Services"
        }
    ],
    "sg:phone":"+1 702 932 3101",
    "sg:postcode":"89113",
    "sg:province":"NV",
    "sg:tags":[
        "broker",
        "mortgage"
    ],
    "wof:name":"North Pacific Mortgage Company",
    "wof:placetype":"venue"
},
  "geometry": {"coordinates":[-115.279194,36.098928],"type":"Point"}
}