{
  "type": "Feature",
  "properties": {
    "iso:country":"US",
    "sg:address":"New York New York Hotel 3790 Las Vegas Blvd S",
    "sg:city":"Las Vegas",
    "sg:classifiers":[
        {
            "category":"Restaurant",
            "type":"Food & Drink"
        }
    ],
    "sg:phone":"+1 702 740 6300",
    "sg:postcode":"89109",
    "sg:province":"NV",
    "sg:tags":[
        "fusion",
        "asian"
    ],
    "sg:website":"www.nynyhotelcasino.com/restaura...",
    "wof:name":"Chin Chin Cafe",
    "wof:placetype":"venue"
},
  "geometry": {"coordinates":[-115.175122,36.102123],"type":"Point"}
}