{
  "type": "Feature",
  "properties": {
    "iso:country":"US",
    "sg:address":"400 E Stewart Ave",
    "sg:city":"Las Vegas",
    "sg:classifiers":[
        {
            "category":"Government",
            "subcategory":"Police Station",
            "type":"Public Place"
        }
    ],
    "sg:phone":"+1 702 229 3394",
    "sg:postcode":"89101",
    "sg:province":"NV",
    "sg:tags":[
        "department"
    ],
    "wof:name":"Police Dept-Media Relations",
    "wof:placetype":"venue"
},
  "geometry": {"coordinates":[-115.139141,36.171576],"type":"Point"}
}