{
  "type": "Feature",
  "properties": {
    "iso:country":"US",
    "sg:address":"325 S 3rd St",
    "sg:city":"Las Vegas",
    "sg:classifiers":[
        {
            "category":"Real Estate",
            "subcategory":"Real Estate Agent",
            "type":"Services"
        }
    ],
    "sg:phone":"+1 702 382 9663",
    "sg:postcode":"89101",
    "sg:province":"NV",
    "wof:name":"Woodland Properties",
    "wof:placetype":"venue"
},
  "geometry": {"coordinates":[-115.144981,36.166979],"type":"Point"}
}