{
  "type": "Feature",
  "properties": {
    "iso:country":"US",
    "sg:address":"2237 Oddie Blvd",
    "sg:city":"Sparks",
    "sg:classifiers":[
        {
            "category":"Food & Beverages",
            "subcategory":"Specialty",
            "type":"Retail Goods"
        }
    ],
    "sg:phone":"+1 775 356 8327",
    "sg:postcode":"89431",
    "sg:province":"NV",
    "sg:tags":[
        "herb"
    ],
    "wof:name":"A Z Enterprises",
    "wof:placetype":"venue"
},
  "geometry": {"coordinates":[-119.773218,39.545409],"type":"Point"}
}