{
  "type": "Feature",
  "properties": {
    "iso:country":"US",
    "sg:address":"5362 McLeod Drive",
    "sg:city":"Las Vegas",
    "sg:classifiers":[
        {
            "category":"Education",
            "subcategory":"School",
            "type":"Public Place"
        }
    ],
    "sg:phone":"+1 702 456 3850",
    "sg:postcode":"89120",
    "sg:province":"NV",
    "sg:tags":[
        "high",
        "middle",
        "elementary"
    ],
    "sg:website":"www.peson-lv.com",
    "wof:name":"Protocol Etiquette School of Nevada-Las Vegas",
    "wof:placetype":"venue"
},
  "geometry": {"coordinates":[-115.110022,36.092679],"type":"Point"}
}