{
  "type": "Feature",
  "properties": {
    "iso:country":"US",
    "sg:address":"4437 Sunrise Ave",
    "sg:city":"Las Vegas",
    "sg:classifiers":[
        {
            "category":"Professional",
            "subcategory":"Accounting & Tax Preparation",
            "type":"Services"
        }
    ],
    "sg:phone":"+1 702 453 2364",
    "sg:postcode":"89110",
    "sg:province":"NV",
    "sg:tags":[
        "return"
    ],
    "wof:name":"Gatdula Medita",
    "wof:placetype":"venue"
},
  "geometry": {"coordinates":[-115.077915,36.162789],"type":"Point"}
}