{
  "type": "Feature",
  "properties": {
    "iso:country":"US",
    "sg:address":"4404 Thicket Ave",
    "sg:city":"North Las Vegas",
    "sg:classifiers":[
        {
            "category":"Manufacturing",
            "subcategory":"Signs",
            "type":"Manufacturing & Wholesale Goods"
        }
    ],
    "sg:phone":"+1 702 649 9333",
    "sg:postcode":"89031",
    "sg:province":"NV",
    "sg:tags":[
        "specialty",
        "mfg"
    ],
    "wof:name":"Metro Signs",
    "wof:placetype":"venue"
},
  "geometry": {"coordinates":[-115.200213,36.240769],"type":"Point"}
}