{
  "type": "Feature",
  "properties": {
    "iso:country":"US",
    "sg:address":"975 Industrial Way",
    "sg:city":"Sparks",
    "sg:classifiers":[
        {
            "category":"Manufacturing",
            "subcategory":"Buildings",
            "type":"Manufacturing & Wholesale Goods"
        },
        {
            "category":"Building & Trades",
            "subcategory":"Plumbing",
            "type":"Services"
        },
        {
            "category":"Building & Trades",
            "subcategory":"Construction",
            "type":"Services"
        }
    ],
    "sg:phone":"+1 775 355 1017",
    "sg:postcode":"89431",
    "sg:province":"NV",
    "sg:tags":[
        "repair",
        "plumber",
        "industrial",
        "systems-repairing",
        "contractors-commercial",
        "builder",
        "specialty",
        "system",
        "equipment",
        "heating",
        "cleaning",
        "home",
        "plumbing-drain",
        "contractor",
        "air conditioning",
        "sewer"
    ],
    "sg:website":"http://www.gardnerplumbingheating.com",
    "wof:name":"Gardner Plumbing & Heating",
    "wof:placetype":"venue"
},
  "geometry": {"coordinates":[-119.758326,39.524952],"type":"Point"}
}