{
  "type": "Feature",
  "properties": {
    "iso:country":"US",
    "sg:address":"9620 W Russell Rd",
    "sg:city":"Las Vegas",
    "sg:classifiers":[
        {
            "category":"Real Estate",
            "subcategory":"Real Estate Operator",
            "type":"Services"
        }
    ],
    "sg:phone":"+1 702 933 5332",
    "sg:postcode":"89148",
    "sg:province":"NV",
    "sg:tags":[
        "building",
        "apartment"
    ],
    "sg:website":"www.thechapelhillapts.com",
    "wof:name":"Chapel Hill Apartments",
    "wof:placetype":"venue"
},
  "geometry": {"coordinates":[-115.302002,36.085098],"type":"Point"}
}