{
  "type": "Feature",
  "properties": {
    "iso:country":"US",
    "sg:address":"943 W Moana Ln",
    "sg:city":"Reno",
    "sg:classifiers":[
        {
            "category":"Personal",
            "subcategory":"Beauty Salon",
            "type":"Services"
        }
    ],
    "sg:phone":"+1 775 827 1702",
    "sg:postcode":"89509",
    "sg:province":"NV",
    "wof:name":"Hair Co",
    "wof:placetype":"venue"
},
  "geometry": {"coordinates":[-119.80709899999999,39.491276],"type":"Point"}
}