{
  "type": "Feature",
  "properties": {
    "iso:country":"US",
    "sg:address":"8005 Jo Marcy Dr",
    "sg:city":"Las Vegas",
    "sg:classifiers":[
        {
            "category":"Professional",
            "subcategory":"Management & Consulting",
            "type":"Services"
        }
    ],
    "sg:phone":"+1 702 256 9001",
    "sg:postcode":"89131",
    "sg:province":"NV",
    "sg:tags":[
        "business"
    ],
    "wof:name":"Collage Marketing Group",
    "wof:placetype":"venue"
},
  "geometry": {"coordinates":[-115.270308,36.303971],"type":"Point"}
}