{
  "type": "Feature",
  "properties": {
    "iso:country":"US",
    "sg:address":"4745 Longley Ln",
    "sg:city":"Reno",
    "sg:classifiers":[
        {
            "category":"Building & Trades",
            "subcategory":"Equipment Rental",
            "type":"Services"
        }
    ],
    "sg:phone":"+1 775 828 3900",
    "sg:postcode":"89502",
    "sg:province":"NV",
    "sg:tags":[
        "leasing",
        "furniture"
    ],
    "sg:website":"www.glbe.com",
    "wof:name":"Cort Furniture Rental",
    "wof:placetype":"venue"
},
  "geometry": {"coordinates":[-119.76313500000001,39.481267],"type":"Point"}
}