{
  "type": "Feature",
  "properties": {
    "iso:country":"US",
    "sg:address":"5151 Sigstrom Dr",
    "sg:city":"Carson City",
    "sg:classifiers":[
        {
            "category":"Manufacturing",
            "subcategory":"Metals",
            "type":"Manufacturing & Wholesale Goods"
        }
    ],
    "sg:phone":"+1 775 883 9212",
    "sg:postcode":"89706",
    "sg:province":"NV",
    "sg:tags":[
        "machine",
        "screw",
        "product"
    ],
    "wof:name":"Protomatics",
    "wof:placetype":"venue"
},
  "geometry": {"coordinates":[-119.735181,39.20603],"type":"Point"}
}