{
  "type": "Feature",
  "properties": {
    "iso:country":"US",
    "sg:address":"671 E Naples Dr",
    "sg:city":"Las Vegas",
    "sg:classifiers":[
        {
            "category":"Professional",
            "type":"Services"
        }
    ],
    "sg:phone":"+1 702 597 9888",
    "sg:postcode":"89119",
    "sg:province":"NV",
    "wof:name":"Air Pak General Services Inc",
    "wof:placetype":"venue"
},
  "geometry": {"coordinates":[-115.14798,36.105581],"type":"Point"}
}