{
  "type": "Feature",
  "properties": {
    "iso:country":"US",
    "sg:address":"817 W 2nd St",
    "sg:city":"Verdi",
    "sg:classifiers":[
        {
            "category":"Personal",
            "subcategory":"Beauty Salon",
            "type":"Services"
        }
    ],
    "sg:phone":"+1 775 345 1200",
    "sg:postcode":"89439",
    "sg:province":"NV",
    "wof:name":"Annie's Salon",
    "wof:placetype":"venue"
},
  "geometry": {"coordinates":[-119.986782,39.519183],"type":"Point"}
}