{
  "type": "Feature",
  "properties": {
    "iso:country":"US",
    "sg:address":"120 W 2nd St",
    "sg:city":"Carson City",
    "sg:classifiers":[
        {
            "category":"Government",
            "subcategory":"Office",
            "type":"Public Place"
        }
    ],
    "sg:phone":"+1 775 687 3840",
    "sg:postcode":"89703",
    "sg:province":"NV",
    "sg:tags":[
        "admin",
        "affairs",
        "state"
    ],
    "wof:name":"Veterans Service Office",
    "wof:placetype":"venue"
},
  "geometry": {"coordinates":[-119.76770999999999,39.16331],"type":"Point"}
}