{
  "type": "Feature",
  "properties": {
    "iso:country":"US",
    "sg:address":"2065 Meadow Ridge Dr",
    "sg:city":"Elko",
    "sg:classifiers":[
        {
            "category":"Farming",
            "subcategory":"Farm & Veterinary Services",
            "type":"Manufacturing & Wholesale Goods"
        }
    ],
    "sg:phone":"+1 775 758 5420",
    "sg:postcode":"89801",
    "sg:province":"NV",
    "sg:tags":[
        "crop",
        "harvesting"
    ],
    "wof:name":"Sam Lawson Trust",
    "wof:placetype":"venue"
},
  "geometry": {"coordinates":[-115.78408,40.84015],"type":"Point"}
}