{
  "type": "Feature",
  "properties": {
    "iso:country":"US",
    "sg:address":"1058 S Main St",
    "sg:city":"Las Vegas",
    "sg:classifiers":[
        {
            "category":"Building & Trades",
            "subcategory":"Plumbing",
            "type":"Services"
        },
        {
            "category":"Wholesale",
            "subcategory":"Electrical",
            "type":"Manufacturing & Wholesale Goods"
        }
    ],
    "sg:phone":"+1 702 384 2932",
    "sg:postcode":"89101",
    "sg:province":"NV",
    "sg:tags":[
        "fire",
        "installs",
        "alarm",
        "system",
        "sprinkler"
    ],
    "wof:name":"Ace Fire Systems Inc",
    "wof:placetype":"venue"
},
  "geometry": {"coordinates":[-115.153747,36.159682],"type":"Point"}
}