{
  "type": "Feature",
  "properties": {
    "iso:country":"US",
    "sg:address":"3230 E Flamingo Rd",
    "sg:city":"Las Vegas",
    "sg:classifiers":[
        {
            "category":"Shopping",
            "subcategory":"Books",
            "type":"Retail Goods"
        }
    ],
    "sg:phone":"+1 702 435 6463",
    "sg:postcode":"89121",
    "sg:province":"NV",
    "wof:name":"Mind Emporium",
    "wof:placetype":"venue"
},
  "geometry": {"coordinates":[-115.103851,36.115222],"type":"Point"}
}