{
  "type": "Feature",
  "properties": {
    "iso:country":"US",
    "sg:address":"3651 W Ali Baba Ln",
    "sg:city":"Las Vegas",
    "sg:classifiers":[
        {
            "category":"Building & Trades",
            "subcategory":"Electrical",
            "type":"Services"
        }
    ],
    "sg:phone":"+1 702 795 2010",
    "sg:postcode":"89118",
    "sg:province":"NV",
    "sg:tags":[
        "telecommunication",
        "contractor"
    ],
    "wof:name":"Steimel Communications Inc",
    "wof:placetype":"venue"
},
  "geometry": {"coordinates":[-115.18823,36.095364],"type":"Point"}
}