{
  "type": "Feature",
  "properties": {
    "iso:country":"US",
    "sg:address":"426 D Ave",
    "sg:city":"Gabbs",
    "sg:classifiers":[
        {
            "category":"Organizations",
            "subcategory":"Community Association",
            "type":"Services"
        }
    ],
    "sg:phone":"+1 775 285 4013",
    "sg:postcode":"89409",
    "sg:province":"NV",
    "sg:tags":[
        "club"
    ],
    "wof:name":"Veterans Of Foreign Wars",
    "wof:placetype":"venue"
},
  "geometry": {"coordinates":[-117.93033699999999,38.857712],"type":"Point"}
}