{
  "type": "Feature",
  "properties": {
    "iso:country":"US",
    "sg:address":"3832 Pamplona St",
    "sg:city":"Las Vegas",
    "sg:classifiers":[
        {
            "category":"Shopping",
            "subcategory":"Gifts & Souvenirs",
            "type":"Retail Goods"
        }
    ],
    "sg:phone":"+1 702 253 5111",
    "sg:postcode":"89103",
    "sg:province":"NV",
    "wof:name":"Little Cat Company Inc",
    "wof:placetype":"venue"
},
  "geometry": {"coordinates":[-115.239238,36.119191],"type":"Point"}
}