{
  "type": "Feature",
  "properties": {
    "iso:country":"US",
    "sg:address":"4205 W Tropicana Ave",
    "sg:city":"Las Vegas",
    "sg:classifiers":[
        {
            "category":"Freight",
            "type":"Transportation"
        }
    ],
    "sg:phone":"+1 702 242 9232",
    "sg:postcode":"89103",
    "sg:province":"NV",
    "sg:tags":[
        "operator",
        "trucking"
    ],
    "wof:name":"Gmk Auto Transport",
    "wof:placetype":"venue"
},
  "geometry": {"coordinates":[-115.197676,36.100966],"type":"Point"}
}