{
  "type": "Feature",
  "properties": {
    "iso:country":"US",
    "sg:address":"7879 Windward Rd",
    "sg:city":"Las Vegas",
    "sg:classifiers":[
        {
            "category":"Professional",
            "subcategory":"Management & Consulting",
            "type":"Services"
        }
    ],
    "sg:phone":"+1 702 367 8556",
    "sg:postcode":"89147",
    "sg:province":"NV",
    "sg:tags":[
        "business"
    ],
    "wof:name":"Consulmar & Assoc Intl",
    "wof:placetype":"venue"
},
  "geometry": {"coordinates":[-115.26337100000001,36.102395],"type":"Point"}
}