{
  "type": "Feature",
  "properties": {
    "iso:country":"US",
    "sg:address":"4545 Cameron St",
    "sg:city":"Las Vegas",
    "sg:classifiers":[
        {
            "category":"Professional",
            "subcategory":"Business Services",
            "type":"Services"
        }
    ],
    "sg:phone":"+1 702 367 1650",
    "sg:postcode":"89103",
    "sg:province":"NV",
    "sg:tags":[
        "convention",
        "meeting",
        "facility"
    ],
    "wof:name":"Expo Services",
    "wof:placetype":"venue"
},
  "geometry": {"coordinates":[-115.204036,36.106402],"type":"Point"}
}