{
  "type": "Feature",
  "properties": {
    "iso:country":"US",
    "sg:address":"2600 Clayton St",
    "sg:city":"North Las Vegas",
    "sg:classifiers":[
        {
            "category":"Organizations",
            "subcategory":"Religious Organization",
            "type":"Services"
        }
    ],
    "sg:phone":"+1 702 646 9075",
    "sg:postcode":"89032",
    "sg:province":"NV",
    "sg:tags":[
        "church"
    ],
    "wof:name":"Macedonia Baptist Church",
    "wof:placetype":"venue"
},
  "geometry": {"coordinates":[-115.16994099999999,36.207933],"type":"Point"}
}