{
  "type": "Feature",
  "properties": {
    "iso:country":"US",
    "sg:address":"8029 W Sahara Ave",
    "sg:city":"Las Vegas",
    "sg:classifiers":[
        {
            "category":"Education",
            "subcategory":"Special Training",
            "type":"Public Place"
        }
    ],
    "sg:phone":"+1 702 562 0800",
    "sg:postcode":"89117",
    "sg:province":"NV",
    "sg:tags":[
        "program"
    ],
    "wof:name":"OMI Assoc",
    "wof:placetype":"venue"
},
  "geometry": {"coordinates":[-115.266364,36.14373],"type":"Point"}
}