{
  "type": "Feature",
  "properties": {
    "iso:country":"US",
    "sg:address":"750 S Rampart Blvd",
    "sg:city":"Las Vegas",
    "sg:classifiers":[
        {
            "category":"Shopping",
            "subcategory":"Clothing, Apparel, & Fashions",
            "type":"Retail Goods"
        }
    ],
    "sg:phone":"+1 702 838 1811",
    "sg:postcode":"89145",
    "sg:province":"NV",
    "sg:tags":[
        "infant",
        "wear"
    ],
    "wof:name":"Bellini Baby To Teen",
    "wof:placetype":"venue"
},
  "geometry": {"coordinates":[-115.291403,36.162729],"type":"Point"}
}