{
  "type": "Feature",
  "properties": {
    "iso:country":"US",
    "sg:address":"1225 Eddy St",
    "sg:city":"Gardnerville",
    "sg:classifiers":[
        {
            "category":"Manufacturing",
            "subcategory":"Motor Vehicles & Parts",
            "type":"Manufacturing & Wholesale Goods"
        }
    ],
    "sg:phone":"+1 775 782 2110",
    "sg:postcode":"89410",
    "sg:province":"NV",
    "sg:tags":[
        "mfg"
    ],
    "wof:name":"Richard Kudrna",
    "wof:placetype":"venue"
},
  "geometry": {"coordinates":[-119.747965,38.940947],"type":"Point"}
}