{
  "type": "Feature",
  "properties": {
    "iso:country":"US",
    "sg:address":"1717 Afton Dr",
    "sg:city":"Las Vegas",
    "sg:classifiers":[
        {
            "category":"Professional",
            "subcategory":"Engineering",
            "type":"Services"
        }
    ],
    "sg:phone":"+1 702 242 5264",
    "sg:postcode":"89117",
    "sg:province":"NV",
    "sg:tags":[
        "engineer"
    ],
    "wof:name":"Big Rock Co Inc",
    "wof:placetype":"venue"
},
  "geometry": {"coordinates":[-115.271315,36.152111],"type":"Point"}
}