{
  "type": "Feature",
  "properties": {
    "iso:country":"US",
    "sg:address":"2129 Rainbow Falls Dr",
    "sg:city":"Las Vegas",
    "sg:classifiers":[
        {
            "category":"Professional",
            "subcategory":"Secretarial Services",
            "type":"Services"
        }
    ],
    "sg:phone":"+1 702 228 7871",
    "sg:postcode":"89134",
    "sg:province":"NV",
    "sg:tags":[
        "typing"
    ],
    "wof:name":"Legal Source 2000",
    "wof:placetype":"venue"
},
  "geometry": {"coordinates":[-115.28541300000001,36.200823],"type":"Point"}
}