{
  "type": "Feature",
  "properties": {
    "iso:country":"US",
    "sg:address":"5416 Rainbows End Dr",
    "sg:city":"Las Vegas",
    "sg:classifiers":[
        {
            "category":"Professional",
            "subcategory":"Computer Services",
            "type":"Services"
        }
    ],
    "sg:phone":"+1 702 655 5949",
    "sg:postcode":"89149",
    "sg:province":"NV",
    "sg:tags":[
        "design",
        "system"
    ],
    "wof:name":"Lonborg Design Services",
    "wof:placetype":"venue"
},
  "geometry": {"coordinates":[-115.276016,36.26173],"type":"Point"}
}