{
  "type": "Feature",
  "properties": {
    "iso:country":"US",
    "sg:address":"1911 N Main St",
    "sg:city":"Virginia City",
    "sg:classifiers":[
        {
            "category":"Manufacturing",
            "subcategory":"Printing",
            "type":"Manufacturing & Wholesale Goods"
        }
    ],
    "sg:phone":"+1 775 847 0222",
    "sg:postcode":"89440",
    "sg:province":"NV",
    "sg:tags":[
        "publisher",
        "guide"
    ],
    "wof:name":"Gold Hill Publishing Co",
    "wof:placetype":"venue"
},
  "geometry": {"coordinates":[-119.65697,39.293031],"type":"Point"}
}