{
  "type": "Feature",
  "properties": {
    "iso:country":"US",
    "sg:address":"6480 W Flamingo Rd",
    "sg:city":"Las Vegas",
    "sg:classifiers":[
        {
            "category":"Health Services",
            "subcategory":"Doctor",
            "type":"Services"
        }
    ],
    "sg:phone":"+1 702 220 3658",
    "sg:postcode":"89103",
    "sg:province":"NV",
    "sg:tags":[
        "medical"
    ],
    "wof:name":"Select Medical Corporation",
    "wof:placetype":"venue"
},
  "geometry": {"coordinates":[-115.229893,36.114593],"type":"Point"}
}