{
  "type": "Feature",
  "properties": {
    "iso:country":"US",
    "sg:address":"6655 W Sahara Ave",
    "sg:city":"Las Vegas",
    "sg:classifiers":[
        {
            "category":"Communications",
            "subcategory":"Radio Station",
            "type":"Services"
        }
    ],
    "sg:phone":"+1 702 796 1100",
    "sg:postcode":"89157",
    "sg:province":"NV",
    "sg:website":"www.jackbaby.com",
    "wof:name":"100.5 Jack FM",
    "wof:placetype":"venue"
},
  "geometry": {"coordinates":[-115.237678,36.144026],"type":"Point"}
}