{
  "type": "Feature",
  "properties": {
    "iso:country":"US",
    "sg:address":"3905 Carter Dr",
    "sg:city":"Wellington",
    "sg:classifiers":[
        {
            "category":"Retail",
            "subcategory":"Auto Repair",
            "type":"Services"
        }
    ],
    "sg:phone":"+1 775 266 9300",
    "sg:postcode":"89444",
    "sg:province":"NV",
    "sg:tags":[
        "repairing",
        "automobile"
    ],
    "wof:name":"TRE Garage",
    "wof:placetype":"venue"
},
  "geometry": {"coordinates":[-119.503723,38.732053],"type":"Point"}
}