{
  "type": "Feature",
  "properties": {
    "iso:country":"US",
    "sg:address":"1312 S 8th St",
    "sg:city":"Las Vegas",
    "sg:classifiers":[
        {
            "category":"Wholesale",
            "subcategory":"Non-durable Goods",
            "type":"Manufacturing & Wholesale Goods"
        }
    ],
    "sg:phone":"+1 702 385 5158",
    "sg:postcode":"89104",
    "sg:province":"NV",
    "sg:tags":[
        "candle"
    ],
    "wof:name":"Golden Starlight",
    "wof:placetype":"venue"
},
  "geometry": {"coordinates":[-115.143985,36.153883],"type":"Point"}
}