{
  "type": "Feature",
  "properties": {
    "iso:country":"US",
    "sg:address":"149 N Gibson Rd",
    "sg:city":"Henderson",
    "sg:classifiers":[
        {
            "category":"Recreation",
            "type":"Entertainment"
        }
    ],
    "sg:phone":"+1 702 567 6850",
    "sg:postcode":"89014",
    "sg:province":"NV",
    "sg:tags":[
        "paint",
        "ball",
        "sport"
    ],
    "wof:name":"Tektonx Paintball",
    "wof:placetype":"venue"
},
  "geometry": {"coordinates":[-115.02936099999999,36.038063],"type":"Point"}
}