{
  "type": "Feature",
  "properties": {
    "iso:country":"US",
    "sg:address":"2761 Emerson Ave",
    "sg:city":"Las Vegas",
    "sg:classifiers":[
        {
            "category":"Organizations",
            "subcategory":"Religious Organization",
            "type":"Services"
        }
    ],
    "sg:phone":"+1 702 313 5270",
    "sg:postcode":"89121",
    "sg:province":"NV",
    "wof:name":"Sanford Akelrod",
    "wof:placetype":"venue"
},
  "geometry": {"coordinates":[-115.118482,36.125969],"type":"Point"}
}