{
  "type": "Feature",
  "properties": {
    "iso:country":"US",
    "sg:address":"719 W 5th St",
    "sg:city":"Reno",
    "sg:classifiers":[
        {
            "category":"Food & Beverages",
            "subcategory":"Specialty",
            "type":"Retail Goods"
        }
    ],
    "sg:phone":"+1 775 323 1331",
    "sg:postcode":"89503",
    "sg:province":"NV",
    "sg:tags":[
        "health",
        "diet"
    ],
    "wof:name":"Burton's Wellness Ctr",
    "wof:placetype":"venue"
},
  "geometry": {"coordinates":[-119.825529,39.529261],"type":"Point"}
}