{
  "type": "Feature",
  "properties": {
    "iso:country":"US",
    "sg:address":"9635 Gateway Dr",
    "sg:city":"Reno",
    "sg:classifiers":[
        {
            "category":"Professional",
            "subcategory":"Art Services",
            "type":"Services"
        }
    ],
    "sg:phone":"+1 775 828 4700",
    "sg:postcode":"89521",
    "sg:province":"NV",
    "sg:tags":[
        "graphic",
        "design"
    ],
    "wof:name":"C L M Design",
    "wof:placetype":"venue"
},
  "geometry": {"coordinates":[-119.762453,39.442535],"type":"Point"}
}