{
  "type": "Feature",
  "properties": {
    "iso:country":"US",
    "sg:address":"505 Copper St",
    "sg:city":"Elko",
    "sg:classifiers":[
        {
            "category":"Personal",
            "subcategory":"Beauty Salon",
            "type":"Services"
        }
    ],
    "sg:phone":"+1 775 738 2827",
    "sg:postcode":"89801",
    "sg:province":"NV",
    "sg:tags":[
        "treatment",
        "skin"
    ],
    "wof:name":"Jafra Cosmetics",
    "wof:placetype":"venue"
},
  "geometry": {"coordinates":[-115.795007,40.846837],"type":"Point"}
}