{
  "type": "Feature",
  "properties": {
    "iso:country":"US",
    "sg:address":"3570 W Dewey Dr",
    "sg:city":"Las Vegas",
    "sg:classifiers":[
        {
            "category":"Manufacturing",
            "subcategory":"Glass & Minerals",
            "type":"Manufacturing & Wholesale Goods"
        },
        {
            "category":"Building & Trades",
            "subcategory":"Construction",
            "type":"Services"
        }
    ],
    "sg:phone":"+1 702 736 7675",
    "sg:postcode":"89118",
    "sg:province":"NV",
    "sg:tags":[
        "concrete",
        "sub",
        "contractor"
    ],
    "wof:name":"Extreme Concrete",
    "wof:placetype":"venue"
},
  "geometry": {"coordinates":[-115.187088,36.088149],"type":"Point"}
}