{
  "type": "Feature",
  "properties": {
    "iso:country":"US",
    "sg:address":"7141 S Eastern Ave",
    "sg:city":"Las Vegas",
    "sg:classifiers":[
        {
            "category":"Bars & Pubs",
            "type":"Food & Drink"
        }
    ],
    "sg:phone":"+1 702 260 8930",
    "sg:postcode":"89119",
    "sg:province":"NV",
    "wof:name":"Bounty Hunters",
    "wof:placetype":"venue"
},
  "geometry": {"coordinates":[-115.11845700000001,36.060096],"type":"Point"}
}