{
  "type": "Feature",
  "properties": {
    "iso:country":"US",
    "sg:address":"9640 W Tropicana Ave #101",
    "sg:city":"Las Vegas",
    "sg:classifiers":[
        {
            "category":"Restaurant",
            "type":"Food & Drink"
        }
    ],
    "sg:phone":"+1 702 489 2800",
    "sg:postcode":"89147",
    "sg:province":"NV",
    "sg:tags":[
        "barbeque"
    ],
    "sg:website":"www.buzzbbq.com",
    "wof:name":"Buzz BBQ",
    "wof:placetype":"venue"
},
  "geometry": {"coordinates":[-115.302403,36.10107],"type":"Point"}
}