{
  "type": "Feature",
  "properties": {
    "iso:country":"US",
    "sg:address":"4408 S Eastern Ave",
    "sg:city":"Las Vegas",
    "sg:classifiers":[
        {
            "category":"Health Services",
            "subcategory":"Doctor",
            "type":"Services"
        }
    ],
    "sg:phone":"+1 702 731 5700",
    "sg:postcode":"89119",
    "sg:province":"NV",
    "sg:tags":[
        "surgeon",
        "oral"
    ],
    "wof:name":"Bruno James DDS",
    "wof:placetype":"venue"
},
  "geometry": {"coordinates":[-115.11900300000001,36.108799],"type":"Point"}
}