{
  "type": "Feature",
  "properties": {
    "iso:country":"US",
    "sg:address":"4045 S Eastern Ave",
    "sg:city":"Las Vegas",
    "sg:classifiers":[
        {
            "category":"Professional",
            "subcategory":"Business Services",
            "type":"Services"
        },
        {
            "category":"Banks & Credit Unions",
            "subcategory":"Bank",
            "type":"Services"
        }
    ],
    "sg:phone":"+1 702 731 6665",
    "sg:postcode":"89119",
    "sg:province":"NV",
    "sg:tags":[
        "merchant",
        "account",
        "broker",
        "other",
        "plan",
        "card"
    ],
    "sg:website":"www.ezvisamc.com",
    "wof:name":"Merchant Credit Card Services",
    "wof:placetype":"venue"
},
  "geometry": {"coordinates":[-115.119159,36.117416],"type":"Point"}
}