{
  "type": "Feature",
  "properties": {
    "iso:country":"US",
    "sg:address":"2601 Enterprise Rd",
    "sg:city":"Reno",
    "sg:classifiers":[
        {
            "category":"Education",
            "subcategory":"College",
            "type":"Public Place"
        }
    ],
    "sg:phone":"+1 775 784 4036",
    "sg:postcode":"89512",
    "sg:province":"NV",
    "wof:name":"Board Of Regents",
    "wof:placetype":"venue"
},
  "geometry": {"coordinates":[-119.813175,39.550591],"type":"Point"}
}