{
  "type": "Feature",
  "properties": {
    "iso:country":"US",
    "sg:address":"777 E Harmon Avenue",
    "sg:city":"Las Vegas",
    "sg:classifiers":[
        {
            "category":"Real Estate",
            "subcategory":"Real Estate Operator",
            "type":"Services"
        }
    ],
    "sg:phone":"+1 702 737 8982",
    "sg:postcode":"89119",
    "sg:province":"NV",
    "sg:tags":[
        "apartment"
    ],
    "wof:name":"Rebel House Apts",
    "wof:placetype":"venue"
},
  "geometry": {"coordinates":[-115.148023,36.107847],"type":"Point"}
}