{
  "type": "Feature",
  "properties": {
    "iso:country":"US",
    "sg:address":"3340 N Rancho Dr",
    "sg:city":"Las Vegas",
    "sg:classifiers":[
        {
            "category":"Shopping",
            "type":"Retail Goods"
        }
    ],
    "sg:phone":"+1 702 396 9093",
    "sg:postcode":"89130",
    "sg:province":"NV",
    "sg:tags":[
        "merchandise"
    ],
    "wof:name":"Sensation Spas Of Nevada",
    "wof:placetype":"venue"
},
  "geometry": {"coordinates":[-115.21434499999999,36.219642],"type":"Point"}
}