{
  "type": "Feature",
  "properties": {
    "iso:country":"US",
    "sg:address":"4150 S Eastern Ave",
    "sg:city":"Las Vegas",
    "sg:classifiers":[
        {
            "category":"Organizations",
            "subcategory":"Religious Organization",
            "type":"Services"
        }
    ],
    "sg:phone":"+1 702 733 8323",
    "sg:postcode":"89119",
    "sg:province":"NV",
    "wof:name":"St Viator Catholic Church",
    "wof:placetype":"venue"
},
  "geometry": {"coordinates":[-115.11907600000001,36.113674],"type":"Point"}
}