{
  "type": "Feature",
  "properties": {
    "iso:country":"US",
    "sg:address":"4050 W Mesa Vista Ave",
    "sg:city":"Las Vegas",
    "sg:classifiers":[
        {
            "category":"Building & Trades",
            "subcategory":"Plumbing",
            "type":"Services"
        }
    ],
    "sg:phone":"+1 702 798 1234",
    "sg:postcode":"89118",
    "sg:province":"NV",
    "sg:tags":[
        "conditioning",
        "air",
        "system",
        "contractor"
    ],
    "wof:name":"NSI Supply",
    "wof:placetype":"venue"
},
  "geometry": {"coordinates":[-115.190617,36.091864],"type":"Point"}
}