{
  "type": "Feature",
  "properties": {
    "iso:country":"US",
    "sg:address":"298 S Decatur Blvd",
    "sg:city":"Las Vegas",
    "sg:classifiers":[
        {
            "category":"Professional",
            "subcategory":"Management & Consulting",
            "type":"Services"
        }
    ],
    "sg:phone":"+1 702 878 0507",
    "sg:postcode":"89107",
    "sg:province":"NV",
    "sg:tags":[
        "gaming",
        "consultant"
    ],
    "wof:name":"Terrible Herbst Inc",
    "wof:placetype":"venue"
},
  "geometry": {"coordinates":[-115.20598,36.171766],"type":"Point"}
}