{
  "type": "Feature",
  "properties": {
    "iso:country":"US",
    "sg:address":"3735 Spring Mountain Rd Ste 203",
    "sg:city":"Las Vegas",
    "sg:classifiers":[
        {
            "category":"Personal",
            "subcategory":"Massage",
            "type":"Services"
        }
    ],
    "sg:phone":"+1 702 273 8120",
    "sg:postcode":"89102",
    "sg:province":"NV",
    "wof:name":"Professional Foot Massage",
    "wof:placetype":"venue"
},
  "geometry": {"coordinates":[-115.189329,36.126512],"type":"Point"}
}