{
  "type": "Feature",
  "properties": {
    "iso:country":"US",
    "sg:address":"2110 N Lamb Blvd",
    "sg:city":"Las Vegas",
    "sg:classifiers":[
        {
            "category":"Organizations",
            "subcategory":"Religious Organization",
            "type":"Services"
        }
    ],
    "sg:phone":"+1 702 438 4888",
    "sg:postcode":"89115",
    "sg:province":"NV",
    "sg:tags":[
        "church"
    ],
    "wof:name":"Apostolic Assembly 2",
    "wof:placetype":"venue"
},
  "geometry": {"coordinates":[-115.080056,36.197251],"type":"Point"}
}