{
  "type": "Feature",
  "properties": {
    "iso:country":"US",
    "sg:address":"9430 del Webb Blvd",
    "sg:city":"Las Vegas",
    "sg:classifiers":[
        {
            "category":"Professional",
            "subcategory":"Management & Consulting",
            "type":"Services"
        }
    ],
    "sg:phone":"+1 702 254 6191",
    "sg:postcode":"89134",
    "sg:province":"NV",
    "sg:tags":[
        "international",
        "investment",
        "private",
        "sales"
    ],
    "wof:name":"Interchange Group",
    "wof:placetype":"venue"
},
  "geometry": {"coordinates":[-115.298535,36.210344],"type":"Point"}
}