{
  "type": "Feature",
  "properties": {
    "iso:country":"US",
    "sg:address":"1210 S Valley View Blvd",
    "sg:city":"Las Vegas",
    "sg:classifiers":[
        {
            "category":"Insurance",
            "subcategory":"Insurance Agent",
            "type":"Services"
        }
    ],
    "sg:phone":"+1 702 678 6868",
    "sg:postcode":"89102",
    "sg:province":"NV",
    "wof:name":"USA Risk Services",
    "wof:placetype":"venue"
},
  "geometry": {"coordinates":[-115.192472,36.158997],"type":"Point"}
}