{
  "type": "Feature",
  "properties": {
    "iso:country":"US",
    "sg:address":"5420 Leadville Ave",
    "sg:city":"Las Vegas",
    "sg:classifiers":[
        {
            "category":"Wholesale",
            "subcategory":"Chemicals & Plastics",
            "type":"Manufacturing & Wholesale Goods"
        }
    ],
    "sg:phone":"+1 323 851 1712",
    "sg:postcode":"89130",
    "sg:province":"NV",
    "sg:tags":[
        "alcohol",
        "ethyl"
    ],
    "wof:name":"Pluteus International Inc",
    "wof:placetype":"venue"
},
  "geometry": {"coordinates":[-115.21766700000001,36.271699],"type":"Point"}
}