{
  "type": "Feature",
  "properties": {
    "iso:country":"US",
    "sg:address":"1380 Di Blasi Dr",
    "sg:city":"Las Vegas",
    "sg:classifiers":[
        {
            "category":"Insurance",
            "subcategory":"Insurance Agent",
            "type":"Services"
        }
    ],
    "sg:phone":"+1 702 363 6322",
    "sg:postcode":"89119",
    "sg:province":"NV",
    "wof:name":"Katherine Lookingbill",
    "wof:placetype":"venue"
},
  "geometry": {"coordinates":[-115.13314699999999,36.089671],"type":"Point"}
}