{
  "type": "Feature",
  "properties": {
    "iso:country":"US",
    "sg:address":"3100 S Durango Dr Ste 108",
    "sg:city":"Las Vegas",
    "sg:classifiers":[
        {
            "category":"Professional",
            "subcategory":"Lawyer & Legal Services",
            "type":"Services"
        }
    ],
    "sg:phone":"+1 702 462 5600",
    "sg:postcode":"89117",
    "sg:province":"NV",
    "sg:website":"www.wadelawgroup.com",
    "wof:name":"Wade Law Group",
    "wof:placetype":"venue"
},
  "geometry": {"coordinates":[-115.278501,36.133454],"type":"Point"}
}