{
  "type": "Feature",
  "properties": {
    "iso:country":"US",
    "sg:address":"1301 S Virginia St",
    "sg:city":"Reno",
    "sg:classifiers":[
        {
            "category":"Farming",
            "subcategory":"Fish & Marine Products",
            "type":"Manufacturing & Wholesale Goods"
        },
        {
            "category":"Shopping",
            "subcategory":"Crafts & Fabrics",
            "type":"Retail Goods"
        },
        {
            "category":"Education",
            "subcategory":"School",
            "type":"Public Place"
        }
    ],
    "sg:phone":"+1 775 786 1128",
    "sg:postcode":"89502",
    "sg:province":"NV",
    "sg:tags":[
        "picture",
        "art",
        "framing",
        "supply"
    ],
    "sg:website":"http://www.nvfinearts.com",
    "wof:name":"Nevada Fine Arts",
    "wof:placetype":"venue"
},
  "geometry": {"coordinates":[-119.806099,39.511719],"type":"Point"}
}