{
  "type": "Feature",
  "properties": {
    "iso:country":"US",
    "sg:address":"5825 W Sahara Ave",
    "sg:city":"Las Vegas",
    "sg:classifiers":[
        {
            "category":"Shopping",
            "subcategory":"Catalog Store",
            "type":"Retail Goods"
        }
    ],
    "sg:phone":"+1 702 365 9610",
    "sg:postcode":"89146",
    "sg:province":"NV",
    "sg:tags":[
        "mail",
        "consulting",
        "management",
        "house"
    ],
    "wof:name":"First Liberty International",
    "wof:placetype":"venue"
},
  "geometry": {"coordinates":[-115.219824,36.144265],"type":"Point"}
}