{
  "type": "Feature",
  "properties": {
    "iso:country":"US",
    "sg:address":"639 Isbell Rd",
    "sg:city":"Reno",
    "sg:classifiers":[
        {
            "category":"Professional",
            "type":"Services"
        }
    ],
    "sg:phone":"+1 775 823 3096",
    "sg:postcode":"89509",
    "sg:province":"NV",
    "wof:name":"Uphl Inc",
    "wof:placetype":"venue"
},
  "geometry": {"coordinates":[-119.803787,39.492284],"type":"Point"}
}