{
  "type": "Feature",
  "properties": {
    "iso:country":"US",
    "sg:address":"1588 Watshemu Dr",
    "sg:city":"Gardnerville",
    "sg:classifiers":[
        {
            "category":"Government",
            "subcategory":"Office",
            "type":"Public Place"
        }
    ],
    "sg:phone":"+1 775 265 2410",
    "sg:postcode":"89460",
    "sg:province":"NV",
    "sg:tags":[
        "housing",
        "program"
    ],
    "wof:name":"Washoe Housing Authority",
    "wof:placetype":"venue"
},
  "geometry": {"coordinates":[-119.716665,38.900265],"type":"Point"}
}