{
  "type": "Feature",
  "properties": {
    "iso:country":"US",
    "sg:address":"Fashion Show Mall 3200 Las Vegas Blvd Suite 2090",
    "sg:city":"Las Vegas",
    "sg:classifiers":[
        {
            "category":"Shopping",
            "subcategory":"Clothing, Apparel, & Fashions",
            "type":"Retail Goods"
        }
    ],
    "sg:phone":"+1 702 737 1968",
    "sg:postcode":"89109",
    "sg:province":"NV",
    "wof:name":"Bally",
    "wof:placetype":"venue"
},
  "geometry": {"coordinates":[-115.171626,36.12809],"type":"Point"}
}