{
  "type": "Feature",
  "properties": {
    "iso:country":"US",
    "sg:address":"45 S Maine St",
    "sg:city":"Fallon",
    "sg:classifiers":[
        {
            "category":"Professional",
            "subcategory":"Computer Services",
            "type":"Services"
        }
    ],
    "sg:phone":"+1 775 423 8229",
    "sg:postcode":"89406",
    "sg:province":"NV",
    "sg:tags":[
        "repair"
    ],
    "sg:website":"www.cub.net",
    "wof:name":"Comp-U-Build Computers Inc",
    "wof:placetype":"venue"
},
  "geometry": {"coordinates":[-118.776945,39.47442],"type":"Point"}
}