{
  "type": "Feature",
  "properties": {
    "iso:country":"US",
    "sg:address":"5060 W Hacienda Avenue",
    "sg:city":"Las Vegas",
    "sg:classifiers":[
        {
            "category":"Real Estate",
            "subcategory":"Real Estate Operator",
            "type":"Services"
        }
    ],
    "sg:phone":"+1 702 307 5100",
    "sg:postcode":"89118",
    "sg:province":"NV",
    "sg:tags":[
        "apartment"
    ],
    "wof:name":"Conejo Villas",
    "wof:placetype":"venue"
},
  "geometry": {"coordinates":[-115.2099,36.093511],"type":"Point"}
}