{
  "type": "Feature",
  "properties": {
    "iso:country":"US",
    "sg:address":"92 W Mesquite Blvd",
    "sg:city":"Mesquite",
    "sg:classifiers":[
        {
            "category":"Travel",
            "subcategory":"Hotels & Motels",
            "type":"Entertainment"
        }
    ],
    "sg:phone":"+1 702 346 5756",
    "sg:postcode":"89027",
    "sg:province":"NV",
    "sg:tags":[
        "operation"
    ],
    "wof:name":"Desert Palms Motel",
    "wof:placetype":"venue"
},
  "geometry": {"coordinates":[-114.069536,36.803925],"type":"Point"}
}