{
  "type": "Feature",
  "properties": {
    "iso:country":"US",
    "sg:address":"4754 E Flamingo Rd",
    "sg:city":"Las Vegas",
    "sg:classifiers":[
        {
            "category":"Retail",
            "subcategory":"Repair Shop",
            "type":"Services"
        }
    ],
    "sg:phone":"+1 702 459 5614",
    "sg:postcode":"89121",
    "sg:province":"NV",
    "wof:name":"A Quality Repair",
    "wof:placetype":"venue"
},
  "geometry": {"coordinates":[-115.069959,36.115002],"type":"Point"}
}