{
  "type": "Feature",
  "properties": {
    "iso:country":"US",
    "sg:address":"6115 Grand Teton Dr",
    "sg:city":"Las Vegas",
    "sg:classifiers":[
        {
            "category":"Building & Trades",
            "subcategory":"Construction",
            "type":"Services"
        }
    ],
    "sg:phone":"+1 702 258 5958",
    "sg:postcode":"89131",
    "sg:province":"NV",
    "sg:tags":[
        "painter"
    ],
    "wof:name":"J Compton Painting & Paperhang",
    "wof:placetype":"venue"
},
  "geometry": {"coordinates":[-115.228302,36.304886],"type":"Point"}
}