{
  "type": "Feature",
  "properties": {
    "iso:country":"US",
    "sg:address":"2090 E Flamingo Rd Ste 200",
    "sg:city":"Las Vegas",
    "sg:classifiers":[
        {
            "category":"Health Services",
            "subcategory":"Optometrist",
            "type":"Services"
        }
    ],
    "sg:phone":"+1 702 733 9271",
    "sg:postcode":"89119",
    "sg:province":"NV",
    "wof:name":"Casey Paul MD",
    "wof:placetype":"venue"
},
  "geometry": {"coordinates":[-115.124059,36.115587],"type":"Point"}
}