{
  "type": "Feature",
  "properties": {
    "iso:country":"US",
    "sg:address":"1195 Corporate Blvd",
    "sg:city":"Reno",
    "sg:classifiers":[
        {
            "category":"Social Services",
            "subcategory":"Child Care",
            "type":"Services"
        }
    ],
    "sg:phone":"+1 775 857 1815",
    "sg:postcode":"89502",
    "sg:province":"NV",
    "wof:name":"Aces",
    "wof:placetype":"venue"
},
  "geometry": {"coordinates":[-119.749139,39.513136],"type":"Point"}
}