{
  "type": "Feature",
  "properties": {
    "iso:country":"US",
    "sg:address":"1905 View Dr",
    "sg:city":"Elko",
    "sg:classifiers":[
        {
            "category":"Shopping",
            "type":"Retail Goods"
        }
    ],
    "sg:phone":"+1 775 738 6307",
    "sg:postcode":"89801",
    "sg:province":"NV",
    "sg:tags":[
        "spa",
        "hot",
        "tub"
    ],
    "wof:name":"Tropical Waters Spa & Supplies",
    "wof:placetype":"venue"
},
  "geometry": {"coordinates":[-115.751717,40.847759],"type":"Point"}
}