{
  "type": "Feature",
  "properties": {
    "iso:country":"US",
    "sg:address":"9004 W Sahara Avenue",
    "sg:city":"Las Vegas",
    "sg:classifiers":[
        {
            "category":"Banks & Credit Unions",
            "subcategory":"Bank",
            "type":"Services"
        }
    ],
    "sg:phone":"+1 702 254 8090",
    "sg:postcode":"89117",
    "sg:province":"NV",
    "wof:name":"U S Bank",
    "wof:placetype":"venue"
},
  "geometry": {"coordinates":[-115.293136,36.144466],"type":"Point"}
}