{
  "type": "Feature",
  "properties": {
    "iso:country":"US",
    "sg:address":"3418 Odlum Pt Ln",
    "sg:city":"North Las Vegas",
    "sg:classifiers":[
        {
            "category":"Professional",
            "subcategory":"Business Services",
            "type":"Services"
        }
    ],
    "sg:phone":"+1 702 638 1332",
    "sg:postcode":"89032",
    "sg:province":"NV",
    "wof:name":"Action Pool & Lawn Service",
    "wof:placetype":"venue"
},
  "geometry": {"coordinates":[-115.18868500000001,36.235362],"type":"Point"}
}