{
  "type": "Feature",
  "properties": {
    "iso:country":"US",
    "sg:address":"1600 S Maryland Pkwy",
    "sg:city":"Las Vegas",
    "sg:classifiers":[
        {
            "category":"Real Estate",
            "subcategory":"Real Estate Agent",
            "type":"Services"
        }
    ],
    "sg:phone":"+1 702 877 3398",
    "sg:postcode":"89104",
    "sg:province":"NV",
    "wof:name":"Slatauski Realty",
    "wof:placetype":"venue"
},
  "geometry": {"coordinates":[-115.136989,36.155075],"type":"Point"}
}