{
  "type": "Feature",
  "properties": {
    "iso:country":"US",
    "sg:address":"10120 W Flamingo Road Suite 4",
    "sg:city":"Las Vegas",
    "sg:classifiers":[
        {
            "category":"Retail",
            "subcategory":"Laundry & Dry Cleaning",
            "type":"Services"
        }
    ],
    "sg:phone":"+1 702 898 6777",
    "sg:postcode":"89147",
    "sg:province":"NV",
    "wof:name":"Boston Cleaners",
    "wof:placetype":"venue"
},
  "geometry": {"coordinates":[-115.312914,36.115285],"type":"Point"}
}