{
  "type": "Feature",
  "properties": {
    "iso:country":"US",
    "sg:address":"3211 W Charleston Blvd",
    "sg:city":"Las Vegas",
    "sg:classifiers":[
        {
            "category":"Health Services",
            "subcategory":"Doctor",
            "type":"Services"
        }
    ],
    "sg:phone":"+1 702 822 2000",
    "sg:postcode":"89102",
    "sg:province":"NV",
    "sg:tags":[
        "physician",
        "surgeon"
    ],
    "wof:name":"Cancer & Blood Specialists",
    "wof:placetype":"venue"
},
  "geometry": {"coordinates":[-115.184839,36.158885],"type":"Point"}
}