{
  "type": "Feature",
  "properties": {
    "iso:country":"US",
    "sg:address":"4310 E Tropicana",
    "sg:city":"Las Vegas",
    "sg:classifiers":[
        {
            "category":"Restaurant",
            "type":"Food & Drink"
        }
    ],
    "sg:phone":"+1 702 307 4040",
    "sg:postcode":"89121",
    "sg:province":"NV",
    "wof:name":"Roma Pizza",
    "wof:placetype":"venue"
},
  "geometry": {"coordinates":[-115.079459,36.100801],"type":"Point"}
}