{
  "type": "Feature",
  "properties": {
    "iso:country":"US",
    "sg:address":"330 E Warm Springs Road",
    "sg:city":"Las Vegas",
    "sg:classifiers":[
        {
            "category":"Banks & Credit Unions",
            "subcategory":"Financial Services",
            "type":"Services"
        }
    ],
    "sg:phone":"+1 702 315 2116",
    "sg:postcode":"89119",
    "sg:province":"NV",
    "sg:tags":[
        "broker",
        "mortgage"
    ],
    "wof:name":"Coast Funding",
    "wof:placetype":"venue"
},
  "geometry": {"coordinates":[-115.158629,36.056813],"type":"Point"}
}