{
  "type": "Feature",
  "properties": {
    "iso:country":"US",
    "sg:address":"3312 Meade Ave",
    "sg:city":"Las Vegas",
    "sg:classifiers":[
        {
            "category":"Home & Garden",
            "subcategory":"Furniture",
            "type":"Retail Goods"
        }
    ],
    "sg:phone":"+1 702 220 5349",
    "sg:postcode":"89102",
    "sg:province":"NV",
    "wof:name":"People's Furniture",
    "wof:placetype":"venue"
},
  "geometry": {"coordinates":[-115.17907700000001,36.136313],"type":"Point"}
}