{
  "type": "Feature",
  "properties": {
    "iso:country":"US",
    "sg:address":"4009 Mountain Trek St",
    "sg:city":"Las Vegas",
    "sg:classifiers":[
        {
            "category":"Building & Trades",
            "subcategory":"Construction",
            "type":"Services"
        }
    ],
    "sg:phone":"+1 702 436 7946",
    "sg:postcode":"89129",
    "sg:province":"NV",
    "sg:tags":[
        "coping",
        "plastering",
        "tiling",
        "pool",
        "swimming"
    ],
    "wof:name":"Desert Palm Pool Svc",
    "wof:placetype":"venue"
},
  "geometry": {"coordinates":[-115.292478,36.234493],"type":"Point"}
}