{
  "type": "Feature",
  "properties": {
    "iso:country":"US",
    "sg:address":"Sunset Station Hotel & Casino 1301 W. Sunset Rd",
    "sg:city":"Henderson",
    "sg:classifiers":[
        {
            "category":"Restaurant",
            "type":"Food & Drink"
        }
    ],
    "sg:phone":"+1 888 786 7389",
    "sg:postcode":"89014",
    "sg:province":"NV",
    "sg:tags":[
        "buffet"
    ],
    "wof:name":"Feast Buffet",
    "wof:placetype":"venue"
},
  "geometry": {"coordinates":[-115.040623,36.063652],"type":"Point"}
}