{
  "type": "Feature",
  "properties": {
    "iso:country":"US",
    "sg:address":"590 Pyramid Way",
    "sg:city":"Sparks",
    "sg:classifiers":[
        {
            "category":"Organizations",
            "subcategory":"Religious Organization",
            "type":"Services"
        }
    ],
    "sg:phone":"+1 775 358 5977",
    "sg:postcode":"89431",
    "sg:province":"NV",
    "wof:name":"Immac Cnception Cathlic Church",
    "wof:placetype":"venue"
},
  "geometry": {"coordinates":[-119.752818,39.537933],"type":"Point"}
}