{
  "type": "Feature",
  "properties": {
    "iso:country":"US",
    "sg:address":"8400 Farm Rd Ste 140",
    "sg:city":"Las Vegas",
    "sg:classifiers":[
        {
            "category":"Arena",
            "subcategory":"Sports Club",
            "type":"Entertainment"
        }
    ],
    "sg:phone":"+1 702 399 0150",
    "sg:postcode":"89131",
    "sg:province":"NV",
    "sg:tags":[
        "martial art"
    ],
    "wof:name":"United Studios of Self Defense",
    "wof:placetype":"venue"
},
  "geometry": {"coordinates":[-115.278983,36.299529],"type":"Point"}
}