{
  "type": "Feature",
  "properties": {
    "iso:country":"US",
    "sg:address":"114 S Boulder Hwy",
    "sg:city":"Henderson",
    "sg:classifiers":[
        {
            "category":"Restaurant",
            "type":"Food & Drink"
        }
    ],
    "sg:menulink":"http://www.allmenus.com/nv/las-vegas/210377-kfc---kentucky-fried-chicken/menu/",
    "sg:phone":"+1 702 564 2704",
    "sg:postcode":"89015",
    "sg:province":"NV",
    "sg:tags":[
        "american",
        "chicken"
    ],
    "wof:name":"KFC - Kentucky Fried Chicken",
    "wof:placetype":"venue"
},
  "geometry": {"coordinates":[-114.98048900000001,36.039141],"type":"Point"}
}