{
  "type": "Feature",
  "properties": {
    "iso:country":"US",
    "sg:address":"3355 Las Vegas Blvd S",
    "sg:city":"Las Vegas",
    "sg:classifiers":[
        {
            "category":"Restaurant",
            "type":"Food & Drink"
        }
    ],
    "sg:phone":"+1 702 388 8338",
    "sg:postcode":"89109",
    "sg:province":"NV",
    "sg:website":"www.taorestaurant.com",
    "wof:name":"Tao Restaurant",
    "wof:placetype":"venue"
},
  "geometry": {"coordinates":[-115.172724,36.118406],"type":"Point"}
}