{
  "type": "Feature",
  "properties": {
    "iso:country":"US",
    "sg:address":"159 Shady Ln",
    "sg:city":"Stateline",
    "sg:classifiers":[
        {
            "category":"Health Services",
            "subcategory":"Medical Lab",
            "type":"Services"
        }
    ],
    "sg:phone":"+1 775 588 2266",
    "sg:postcode":"89449",
    "sg:province":"CA",
    "sg:tags":[
        "laboratory"
    ],
    "wof:name":"Stateline Dental Laboratory",
    "wof:placetype":"venue"
},
  "geometry": {"coordinates":[-119.931141,38.968334],"type":"Point"}
}