{
  "type": "Feature",
  "properties": {
    "iso:country":"US",
    "sg:address":"1705 Marietta Way",
    "sg:city":"Sparks",
    "sg:classifiers":[
        {
            "category":"Autos & Motor Vehicles",
            "subcategory":"Automobile Sales",
            "type":"Retail Goods"
        },
        {
            "category":"Wholesale",
            "subcategory":"Farm Supplies",
            "type":"Manufacturing & Wholesale Goods"
        },
        {
            "category":"Wholesale",
            "subcategory":"Scrap",
            "type":"Manufacturing & Wholesale Goods"
        },
        {
            "category":"Retail",
            "subcategory":"Auto Repair",
            "type":"Services"
        }
    ],
    "sg:phone":"+1 775 359 8484",
    "sg:postcode":"89431",
    "sg:province":"NV",
    "sg:tags":[
        "engines-rebuild",
        "cars-wholesale",
        "used",
        "wrecking",
        "exchange",
        "car",
        "transport",
        "dealers-used",
        "truck",
        "trailer",
        "new",
        "salvage",
        "tractor"
    ],
    "wof:name":"Nevada Auto Wreckers",
    "wof:placetype":"venue"
},
  "geometry": {"coordinates":[-119.75402099999999,39.519066],"type":"Point"}
}