{
  "type": "Feature",
  "properties": {
    "iso:country":"US",
    "sg:address":"8113 Sapphire Bay Cir",
    "sg:city":"Las Vegas",
    "sg:classifiers":[
        {
            "category":"Building & Trades",
            "subcategory":"Construction",
            "type":"Services"
        }
    ],
    "sg:phone":"+1 702 228 9910",
    "sg:postcode":"89128",
    "sg:province":"NV",
    "sg:tags":[
        "contractor"
    ],
    "wof:name":"Thomas Browne Ltd",
    "wof:placetype":"venue"
},
  "geometry": {"coordinates":[-115.270555,36.209968],"type":"Point"}
}