{
  "type": "Feature",
  "properties": {
    "iso:country":"US",
    "sg:address":"6198 W Flamingo Rd",
    "sg:city":"Las Vegas",
    "sg:classifiers":[
        {
            "category":"Fast Food",
            "type":"Food & Drink"
        }
    ],
    "sg:phone":"+1 702 362 0111",
    "sg:postcode":"89103",
    "sg:province":"NV",
    "sg:tags":[
        "burger"
    ],
    "sg:website":"www.wendys.com",
    "wof:name":"Wendy's Old Fashioned Hamburgers",
    "wof:placetype":"venue"
},
  "geometry": {"coordinates":[-115.226175,36.114892],"type":"Point"}
}