{
  "type": "Feature",
  "properties": {
    "iso:country":"US",
    "sg:address":"600 Fremont St",
    "sg:city":"Las Vegas",
    "sg:classifiers":[
        {
            "category":"Travel",
            "subcategory":"Hotels & Motels",
            "type":"Entertainment"
        }
    ],
    "sg:phone":"+1 702 385 5200",
    "sg:postcode":"89101",
    "sg:province":"NV",
    "wof:name":"Hotel El Cortez",
    "wof:placetype":"venue"
},
  "geometry": {"coordinates":[-115.139,36.168499],"type":"Point"}
}