{
  "type": "Feature",
  "properties": {
    "iso:country":"US",
    "sg:address":"3750 Arville St",
    "sg:city":"Las Vegas",
    "sg:classifiers":[
        {
            "category":"Autos & Motor Vehicles",
            "subcategory":"Automobile Sales",
            "type":"Retail Goods"
        }
    ],
    "sg:phone":"+1 702 556 1437",
    "sg:postcode":"89103",
    "sg:province":"NV",
    "sg:tags":[
        "limo"
    ],
    "sg:website":"www.lasvegasexecutivelimo.com",
    "wof:name":"Las Vegas Limousine Executive Sedan",
    "wof:placetype":"venue"
},
  "geometry": {"coordinates":[-115.198075,36.120848],"type":"Point"}
}