{
  "type": "Feature",
  "properties": {
    "iso:country":"US",
    "sg:address":"6355 Silver Lake Rd",
    "sg:city":"Reno",
    "sg:classifiers":[
        {
            "category":"Bars & Pubs",
            "type":"Food & Drink"
        }
    ],
    "sg:phone":"+1 775 972 7905",
    "sg:postcode":"89506",
    "sg:province":"NV",
    "sg:tags":[
        "lounge",
        "cocktail"
    ],
    "wof:name":"Hole In One Rstrnt & Lounge",
    "wof:placetype":"venue"
},
  "geometry": {"coordinates":[-119.885279,39.624711],"type":"Point"}
}