{
  "type": "Feature",
  "properties": {
    "iso:country":"US",
    "sg:address":"395 Westbrook Ln",
    "sg:city":"Reno",
    "sg:classifiers":[
        {
            "category":"Arts & Performance",
            "subcategory":"Theater",
            "type":"Entertainment"
        }
    ],
    "sg:phone":"+1 775 323 2242",
    "sg:postcode":"89506",
    "sg:province":"NV",
    "sg:tags":[
        "live",
        "music"
    ],
    "wof:name":"Boogieman",
    "wof:placetype":"venue"
},
  "geometry": {"coordinates":[-119.856534,39.611438],"type":"Point"}
}