{
  "type": "Feature",
  "properties": {
    "iso:country":"US",
    "sg:address":"5525 Meadowood Mall Cir",
    "sg:city":"Reno",
    "sg:classifiers":[
        {
            "category":"Shopping",
            "subcategory":"Photographic Equipment",
            "type":"Retail Goods"
        }
    ],
    "sg:phone":"+1 775 826 7756",
    "sg:postcode":"89502",
    "sg:province":"NV",
    "sg:tags":[
        "photofinishing",
        "supply"
    ],
    "wof:name":"Ritz Camera Centers Inc",
    "wof:placetype":"venue"
},
  "geometry": {"coordinates":[-119.779772,39.474685],"type":"Point"}
}