{
  "type": "Feature",
  "properties": {
    "iso:country":"US",
    "sg:address":"1590 E Sahara Ave",
    "sg:city":"Las Vegas",
    "sg:classifiers":[
        {
            "category":"Banks & Credit Unions",
            "subcategory":"Bank",
            "type":"Services"
        }
    ],
    "sg:phone":"+1 702 893 9800",
    "sg:postcode":"89104",
    "sg:province":"NV",
    "sg:tags":[
        "loan"
    ],
    "wof:name":"Auto Title Loan Store",
    "wof:placetype":"venue"
},
  "geometry": {"coordinates":[-115.12981,36.144407],"type":"Point"}
}