{
  "type": "Feature",
  "properties": {
    "iso:country":"US",
    "sg:address":"427 Artemus Ct",
    "sg:city":"Henderson",
    "sg:classifiers":[
        {
            "category":"Travel",
            "subcategory":"Travel Agent",
            "type":"Entertainment"
        }
    ],
    "sg:phone":"+1 702 407 6838",
    "sg:postcode":"89074",
    "sg:province":"NV",
    "sg:tags":[
        "agency"
    ],
    "wof:name":"Deltour Travel",
    "wof:placetype":"venue"
},
  "geometry": {"coordinates":[-115.11581,36.010931],"type":"Point"}
}