{
  "type": "Feature",
  "properties": {
    "iso:country":"US",
    "sg:address":"4055 N Cloud Nine Ln",
    "sg:city":"Las Vegas",
    "sg:classifiers":[
        {
            "category":"Health Services",
            "subcategory":"Nursing And Care Facility",
            "type":"Services"
        }
    ],
    "sg:phone":"+1 702 644 8270",
    "sg:postcode":"89115",
    "sg:province":"NV",
    "sg:tags":[
        "home",
        "skilled",
        "convalescent"
    ],
    "wof:name":"Becky's Home Care",
    "wof:placetype":"venue"
},
  "geometry": {"coordinates":[-115.093727,36.233257],"type":"Point"}
}