{
  "type": "Feature",
  "properties": {
    "iso:country":"US",
    "sg:address":"4240 W Flamingo Rd Ste 100",
    "sg:city":"Las Vegas",
    "sg:classifiers":[
        {
            "category":"Banks & Credit Unions",
            "subcategory":"Bank",
            "type":"Services"
        }
    ],
    "sg:phone":"+1 702 383 0009",
    "sg:postcode":"89103",
    "sg:province":"NV",
    "sg:website":"www.nsbank.com",
    "wof:name":"Nevada State Bank",
    "wof:placetype":"venue"
},
  "geometry": {"coordinates":[-115.196752,36.11603],"type":"Point"}
}