{
  "type": "Feature",
  "properties": {
    "iso:country":"US",
    "sg:address":"7210 Hurst Park Rd",
    "sg:city":"Reno",
    "sg:classifiers":[
        {
            "category":"Cinema",
            "subcategory":"Movie Rental",
            "type":"Entertainment"
        }
    ],
    "sg:phone":"+1 775 348 7600",
    "sg:postcode":"89502",
    "sg:province":"NV",
    "sg:tags":[
        "video",
        "tape"
    ],
    "wof:name":"Reno Video",
    "wof:placetype":"venue"
},
  "geometry": {"coordinates":[-119.71141900000001,39.491512],"type":"Point"}
}