{
  "type": "Feature",
  "properties": {
    "iso:country":"US",
    "sg:address":"1390 State Hwy 88",
    "sg:city":"Minden",
    "sg:classifiers":[
        {
            "category":"Retail",
            "subcategory":"Veterinary Services",
            "type":"Services"
        }
    ],
    "sg:phone":"+1 775 782 3664",
    "sg:postcode":"89423",
    "sg:province":"NV",
    "sg:tags":[
        "pet",
        "hospital",
        "for"
    ],
    "sg:website":"www.carsonvalleyvet.com",
    "wof:name":"Carson Valley Veterinary Hosp",
    "wof:placetype":"venue"
},
  "geometry": {"coordinates":[-119.779538,38.932404],"type":"Point"}
}