{
  "type": "Feature",
  "properties": {
    "iso:country":"US",
    "sg:address":"3826 Ponderosa Way",
    "sg:city":"Las Vegas",
    "sg:classifiers":[
        {
            "category":"Home & Garden",
            "subcategory":"Building Materials",
            "type":"Retail Goods"
        }
    ],
    "sg:phone":"+1 702 739 7055",
    "sg:postcode":"89118",
    "sg:province":"NV",
    "sg:tags":[
        "windows"
    ],
    "wof:name":"Window Depot Of Las Vegas",
    "wof:placetype":"venue"
},
  "geometry": {"coordinates":[-115.192461,36.080935],"type":"Point"}
}