{
  "type": "Feature",
  "properties": {
    "iso:country":"US",
    "sg:address":"956 Wigwam Pkwy",
    "sg:city":"Henderson",
    "sg:classifiers":[
        {
            "category":"Sports & Exercise",
            "subcategory":"Gym",
            "type":"Entertainment"
        }
    ],
    "sg:phone":"+1 702 564 2461",
    "sg:postcode":"89014",
    "sg:province":"NV",
    "sg:tags":[
        "trainer"
    ],
    "wof:name":"Sin City Crossfit",
    "wof:placetype":"venue"
},
  "geometry": {"coordinates":[-115.02645,36.034742],"type":"Point"}
}