{
  "type": "Feature",
  "properties": {
    "iso:country":"US",
    "sg:address":"2626 S Rainbow Blvd",
    "sg:city":"Las Vegas",
    "sg:classifiers":[
        {
            "category":"Health Services",
            "subcategory":"Podiatrist",
            "type":"Services"
        }
    ],
    "sg:phone":"+1 702 838 8558",
    "sg:postcode":"89146",
    "sg:province":"NV",
    "wof:name":"Todd J Zang DPM",
    "wof:placetype":"venue"
},
  "geometry": {"coordinates":[-115.242835,36.140972],"type":"Point"}
}