{
  "type": "Feature",
  "properties": {
    "iso:country":"US",
    "sg:address":"9516 W Flamingo Rd",
    "sg:city":"Las Vegas",
    "sg:classifiers":[
        {
            "category":"Food & Beverages",
            "subcategory":"Specialty",
            "type":"Retail Goods"
        },
        {
            "category":"Restaurant",
            "type":"Food & Drink"
        }
    ],
    "sg:phone":"+1 702 638 9500",
    "sg:postcode":"89147",
    "sg:province":"NV",
    "sg:tags":[
        "gluten-free",
        "pizza"
    ],
    "wof:name":"Sammy's Woodfired Pizza",
    "wof:placetype":"venue"
},
  "geometry": {"coordinates":[-115.300203,36.115168],"type":"Point"}
}