{
  "type": "Feature",
  "properties": {
    "iso:country":"US",
    "sg:address":"5828 Half Moon Way",
    "sg:city":"Las Vegas",
    "sg:classifiers":[
        {
            "category":"Building & Trades",
            "subcategory":"Construction",
            "type":"Services"
        }
    ],
    "sg:phone":"+1 702 658 7449",
    "sg:postcode":"89108",
    "sg:province":"NV",
    "sg:tags":[
        "house"
    ],
    "wof:name":"Chester Stites",
    "wof:placetype":"venue"
},
  "geometry": {"coordinates":[-115.222093,36.222993],"type":"Point"}
}