{
  "type": "Feature",
  "properties": {
    "iso:country":"US",
    "sg:address":"4405 Yorkwood Dr",
    "sg:city":"North Las Vegas",
    "sg:classifiers":[
        {
            "category":"Professional",
            "subcategory":"Computer Services",
            "type":"Services"
        }
    ],
    "sg:phone":"+1 702 645 6218",
    "sg:postcode":"89032",
    "sg:province":"NV",
    "sg:tags":[
        "design",
        "system"
    ],
    "wof:name":"Blue Systems Aplcat Web Design",
    "wof:placetype":"venue"
},
  "geometry": {"coordinates":[-115.199732,36.229333],"type":"Point"}
}