{
  "type": "Feature",
  "properties": {
    "iso:country":"US",
    "sg:address":"5546 Camino Al Norte",
    "sg:city":"North Las Vegas",
    "sg:classifiers":[
        {
            "category":"Professional",
            "subcategory":"Lawyer & Legal Services",
            "type":"Services"
        }
    ],
    "sg:phone":"+1 702 631 4623",
    "sg:postcode":"89031",
    "sg:province":"NV",
    "sg:tags":[
        "notary"
    ],
    "wof:name":"The Ups Store",
    "wof:placetype":"venue"
},
  "geometry": {"coordinates":[-115.15565700000001,36.260533],"type":"Point"}
}