{
  "type": "Feature",
  "properties": {
    "iso:country":"US",
    "sg:address":"4480 Paradise Rd",
    "sg:city":"Las Vegas",
    "sg:classifiers":[
        {
            "category":"Shopping",
            "subcategory":"Clothing, Apparel, & Fashions",
            "type":"Retail Goods"
        }
    ],
    "sg:phone":"+1 702 413 0480",
    "sg:postcode":"89169",
    "sg:province":"NV",
    "sg:tags":[
        "clothing",
        "women's"
    ],
    "sg:website":"www.vavoomlasvegas.com/",
    "wof:name":"Vavoom Girly Boutique",
    "wof:placetype":"venue"
},
  "geometry": {"coordinates":[-115.151273,36.108903],"type":"Point"}
}