{
  "type": "Feature",
  "properties": {
    "iso:country":"US",
    "sg:address":"688 Rising Brook Dr",
    "sg:city":"Henderson",
    "sg:classifiers":[
        {
            "category":"Personal",
            "subcategory":"Beauty Salon",
            "type":"Services"
        }
    ],
    "sg:phone":"+1 702 450 3688",
    "sg:postcode":"89011",
    "sg:province":"NV",
    "sg:tags":[
        "shop"
    ],
    "wof:name":"Allure Inc",
    "wof:placetype":"venue"
},
  "geometry": {"coordinates":[-115.016898,36.078343],"type":"Point"}
}