{
  "type": "Feature",
  "properties": {
    "iso:country":"US",
    "sg:address":"3415 E Russell Rd",
    "sg:city":"Las Vegas",
    "sg:classifiers":[
        {
            "category":"Restaurant",
            "type":"Food & Drink"
        }
    ],
    "sg:menulink":"http://www.allmenus.com/nv/las-vegas/208479-taco-bell/menu/",
    "sg:phone":"+1 702 436 0080",
    "sg:postcode":"89120",
    "sg:province":"NV",
    "sg:tags":[
        "mexican"
    ],
    "wof:name":"Taco Bell",
    "wof:placetype":"venue"
},
  "geometry": {"coordinates":[-115.100477,36.085942],"type":"Point"}
}