{
  "type": "Feature",
  "properties": {
    "iso:country":"US",
    "sg:address":"5875 S Rainbow Boulevard",
    "sg:city":"Las Vegas",
    "sg:classifiers":[
        {
            "category":"Personal",
            "subcategory":"Day Spa",
            "type":"Services"
        }
    ],
    "sg:phone":"+1 702 889 6292",
    "sg:postcode":"89118",
    "sg:province":"NV",
    "wof:name":"Maya Makeover",
    "wof:placetype":"venue"
},
  "geometry": {"coordinates":[-115.239413,36.081512],"type":"Point"}
}