{
  "type": "Feature",
  "properties": {
    "iso:country":"US",
    "sg:address":"2260 Reno Hwy",
    "sg:city":"Fallon",
    "sg:classifiers":[
        {
            "category":"Real Estate",
            "subcategory":"Real Estate Agent",
            "type":"Services"
        }
    ],
    "sg:phone":"+1 775 423 5557",
    "sg:postcode":"89406",
    "sg:province":"NV",
    "wof:name":"Venture Properties",
    "wof:placetype":"venue"
},
  "geometry": {"coordinates":[-118.80586099999999,39.47765],"type":"Point"}
}