{
  "type": "Feature",
  "properties": {
    "iso:country":"US",
    "sg:address":"2217 N Green Valley Pkwy",
    "sg:city":"Henderson",
    "sg:classifiers":[
        {
            "category":"Restaurant",
            "type":"Food & Drink"
        }
    ],
    "sg:menulink":"http://www.allmenus.com/nv/las-vegas/196458-mcdonalds/menu/",
    "sg:postcode":"89014",
    "sg:province":"NV",
    "sg:tags":[
        "burger",
        "american"
    ],
    "wof:name":"McDonald's",
    "wof:placetype":"venue"
},
  "geometry": {"coordinates":[-115.08286699999999,36.053234],"type":"Point"}
}