{
  "type": "Feature",
  "properties": {
    "iso:country":"US",
    "sg:address":"3553 S Valley View Blvd",
    "sg:city":"Las Vegas",
    "sg:classifiers":[
        {
            "category":"Health Services",
            "subcategory":"Health Practitioner",
            "type":"Services"
        }
    ],
    "sg:phone":"+1 702 768 8793",
    "sg:postcode":"89103",
    "sg:province":"NV",
    "sg:tags":[
        "acupuncture",
        "spa",
        "day"
    ],
    "wof:name":"Good Hand Acupressure & Massage Center",
    "wof:placetype":"venue"
},
  "geometry": {"coordinates":[-115.19021100000001,36.125801],"type":"Point"}
}