{
  "type": "Feature",
  "properties": {
    "iso:country":"US",
    "sg:address":"13987 S Virginia St",
    "sg:city":"Reno",
    "sg:classifiers":[
        {
            "category":"Coffee & Tea",
            "type":"Food & Drink"
        },
        {
            "category":"Cafe",
            "type":"Food & Drink"
        },
        {
            "category":"Bakery",
            "type":"Food & Drink"
        }
    ],
    "sg:menulink":"http://www.allmenus.com/nv/reno-southwest/234045-nestle-toll-house-cafe/menu/",
    "sg:phone":"+1 775 851 1771",
    "sg:postcode":"89511",
    "sg:province":"NV",
    "sg:tags":[
        "american",
        "pastry"
    ],
    "wof:name":"Nestle Toll House Cafe",
    "wof:placetype":"venue"
},
  "geometry": {"coordinates":[-119.75006500000001,39.408703],"type":"Point"}
}