{
  "type": "Feature",
  "properties": {
    "iso:country":"US",
    "sg:address":"5942 W Oquendo Rd",
    "sg:city":"Las Vegas",
    "sg:classifiers":[
        {
            "category":"Autos & Motor Vehicles",
            "subcategory":"Automobile Sales",
            "type":"Retail Goods"
        }
    ],
    "sg:phone":"+1 702 365 9055",
    "sg:postcode":"89118",
    "sg:province":"NV",
    "sg:tags":[
        "performance",
        "race",
        "dealer"
    ],
    "wof:name":"Fraley's Performance",
    "wof:placetype":"venue"
},
  "geometry": {"coordinates":[-115.222917,36.081879],"type":"Point"}
}