{
  "type": "Feature",
  "properties": {
    "iso:country":"US",
    "sg:address":"3285 Elk Clover St",
    "sg:city":"Las Vegas",
    "sg:classifiers":[
        {
            "category":"Travel",
            "subcategory":"Travel Agent",
            "type":"Entertainment"
        }
    ],
    "sg:phone":"+1 702 221 7245",
    "sg:postcode":"89135",
    "sg:province":"NV",
    "sg:tags":[
        "cruise"
    ],
    "wof:name":"Cruise One",
    "wof:placetype":"venue"
},
  "geometry": {"coordinates":[-115.340169,36.130987],"type":"Point"}
}