{
  "type": "Feature",
  "properties": {
    "iso:country":"US",
    "sg:address":"8565 W Sahara Ave",
    "sg:city":"Las Vegas",
    "sg:classifiers":[
        {
            "category":"Banks & Credit Unions",
            "subcategory":"Bank",
            "type":"Services"
        }
    ],
    "sg:phone":"+1 702 646 5435",
    "sg:postcode":"89117",
    "sg:province":"NV",
    "sg:tags":[
        "loan"
    ],
    "wof:name":"EMG Acquisition",
    "wof:placetype":"venue"
},
  "geometry": {"coordinates":[-115.275784,36.143954],"type":"Point"}
}