{
  "type": "Feature",
  "properties": {
    "iso:country":"US",
    "sg:address":"77 S Martin L King Boulevard",
    "sg:city":"Las Vegas",
    "sg:classifiers":[
        {
            "category":"Home & Garden",
            "subcategory":"Furniture",
            "type":"Retail Goods"
        }
    ],
    "sg:phone":"+1 702 382 9013",
    "sg:postcode":"89106",
    "sg:province":"NV",
    "sg:tags":[
        "store"
    ],
    "wof:name":"Furniture Gallery",
    "wof:placetype":"venue"
},
  "geometry": {"coordinates":[-115.16066,36.173889],"type":"Point"}
}