{
  "type": "Feature",
  "properties": {
    "iso:country":"US",
    "sg:address":"7225 Bermuda Road",
    "sg:city":"Las Vegas",
    "sg:classifiers":[
        {
            "category":"Real Estate",
            "subcategory":"Architect",
            "type":"Services"
        }
    ],
    "sg:phone":"+1 702 837 4221",
    "sg:postcode":"89119",
    "sg:province":"NV",
    "wof:name":"Baker Scott L Architect",
    "wof:placetype":"venue"
},
  "geometry": {"coordinates":[-115.15441,36.05854],"type":"Point"}
}