{
  "type": "Feature",
  "properties": {
    "iso:country":"US",
    "sg:address":"4121 W Sahara Ave",
    "sg:city":"Las Vegas",
    "sg:classifiers":[
        {
            "category":"Health Services",
            "subcategory":"Dentist",
            "type":"Services"
        }
    ],
    "sg:phone":"+1 702 876 4992",
    "sg:postcode":"89102",
    "sg:province":"NV",
    "wof:name":"West Sahara Dental Office",
    "wof:placetype":"venue"
},
  "geometry": {"coordinates":[-115.195999,36.144299],"type":"Point"}
}