{
  "type": "Feature",
  "properties": {
    "iso:country":"US",
    "sg:address":"1310 Hanson St",
    "sg:city":"Winnemucca",
    "sg:classifiers":[
        {
            "category":"Real Estate",
            "subcategory":"Real Estate Operator",
            "type":"Services"
        }
    ],
    "sg:phone":"+1 775 623 2116",
    "sg:postcode":"89445",
    "sg:province":"NV",
    "sg:tags":[
        "building",
        "apartment"
    ],
    "wof:name":"Willowbrook",
    "wof:placetype":"venue"
},
  "geometry": {"coordinates":[-117.727818,40.961862],"type":"Point"}
}