{
  "type": "Feature",
  "properties": {
    "iso:country":"US",
    "sg:address":"9590 Cordoba Blvd",
    "sg:city":"Sparks",
    "sg:classifiers":[
        {
            "category":"Home & Garden",
            "subcategory":"Building Materials",
            "type":"Retail Goods"
        },
        {
            "category":"Military Area",
            "subcategory":"Armory",
            "type":"Public Place"
        },
        {
            "category":"Building & Trades",
            "subcategory":"Construction",
            "type":"Services"
        }
    ],
    "sg:phone":"+1 775 331 1599",
    "sg:postcode":"89441",
    "sg:province":"NV",
    "sg:tags":[
        "repair",
        "fence",
        "builder",
        "contractor",
        "gazebo",
        "patio",
        "fence-sales"
    ],
    "sg:website":"http://www.hdfencing.com",
    "wof:name":"High Desert Fence Patio Covers",
    "wof:placetype":"venue"
},
  "geometry": {"coordinates":[-119.68727,39.653756],"type":"Point"}
}