{
  "type": "Feature",
  "properties": {
    "iso:country":"US",
    "sg:address":"2230 Corporate Cir Ste 250",
    "sg:city":"Henderson",
    "sg:classifiers":[
        {
            "category":"Real Estate",
            "subcategory":"Real Estate Agent",
            "type":"Services"
        }
    ],
    "sg:phone":"+1 702 348 8350",
    "sg:postcode":"89074",
    "sg:province":"NV",
    "wof:name":"Debra Pizzolato - Keller Williams Realty",
    "wof:placetype":"venue"
},
  "geometry": {"coordinates":[-115.08818100000001,36.027718],"type":"Point"}
}