{
  "type": "Feature",
  "properties": {
    "iso:country":"US",
    "sg:address":"4525 Polaris Ave",
    "sg:city":"Las Vegas",
    "sg:classifiers":[
        {
            "category":"Professional",
            "subcategory":"Accounting & Tax Preparation",
            "type":"Services"
        }
    ],
    "sg:phone":"+1 702 313 2283",
    "sg:postcode":"89103",
    "sg:province":"NV",
    "sg:tags":[
        "return"
    ],
    "wof:name":"Comprehensive Business Svcs",
    "wof:placetype":"venue"
},
  "geometry": {"coordinates":[-115.185591,36.10682],"type":"Point"}
}