{
  "type": "Feature",
  "properties": {
    "iso:country":"US",
    "sg:address":"4598 E Tropicana Ave",
    "sg:city":"Las Vegas",
    "sg:classifiers":[
        {
            "category":"Shopping",
            "subcategory":"Shoes",
            "type":"Retail Goods"
        }
    ],
    "sg:phone":"+1 702 458 5878",
    "sg:postcode":"89121",
    "sg:province":"NV",
    "wof:name":"Foot Locker",
    "wof:placetype":"venue"
},
  "geometry": {"coordinates":[-115.074348,36.100267],"type":"Point"}
}