{
  "type": "Feature",
  "properties": {
    "iso:country":"US",
    "sg:address":"475 Good Ave",
    "sg:city":"Battle Mountain",
    "sg:classifiers":[
        {
            "category":"Building & Trades",
            "subcategory":"Construction",
            "type":"Services"
        }
    ],
    "sg:phone":"+1 775 623 0474",
    "sg:postcode":"89820",
    "sg:province":"NV",
    "sg:tags":[
        "boring",
        "drilling",
        "contractor"
    ],
    "wof:name":"O'Keefe Drilling Co Inc",
    "wof:placetype":"venue"
},
  "geometry": {"coordinates":[-116.936219,40.635457],"type":"Point"}
}