{
  "type": "Feature",
  "properties": {
    "iso:country":"US",
    "sg:address":"1540 Mescalero Ave",
    "sg:city":"Reno",
    "sg:classifiers":[
        {
            "category":"Professional",
            "subcategory":"Management & Consulting",
            "type":"Services"
        }
    ],
    "sg:phone":"+1 775 232 3099",
    "sg:postcode":"89523",
    "sg:province":"NV",
    "sg:tags":[
        "business"
    ],
    "wof:name":"Center For Behavior Saftey",
    "wof:placetype":"venue"
},
  "geometry": {"coordinates":[-119.89675699999999,39.52613],"type":"Point"}
}