{
  "type": "Feature",
  "properties": {
    "iso:country":"US",
    "sg:address":"4850 W Flamingo Rd",
    "sg:city":"Las Vegas",
    "sg:classifiers":[
        {
            "category":"Personal",
            "subcategory":"Beauty Salon",
            "type":"Services"
        }
    ],
    "sg:phone":"+1 702 221 6033",
    "sg:postcode":"89103",
    "sg:province":"NV",
    "wof:name":"Great Clips",
    "wof:placetype":"venue"
},
  "geometry": {"coordinates":[-115.204806,36.115557],"type":"Point"}
}