{
  "type": "Feature",
  "properties": {
    "iso:country":"US",
    "sg:address":"6001 Talbot Ln",
    "sg:city":"Reno",
    "sg:classifiers":[
        {
            "category":"Professional",
            "type":"Services"
        }
    ],
    "sg:phone":"+1 775 829 2722",
    "sg:postcode":"89509",
    "sg:province":"NV",
    "sg:tags":[
        "establishment"
    ],
    "wof:name":"John Harrah Enterprises",
    "wof:placetype":"venue"
},
  "geometry": {"coordinates":[-119.800203,39.47286],"type":"Point"}
}