{
  "type": "Feature",
  "properties": {
    "iso:country":"US",
    "sg:address":"3908 el Cederal Ave",
    "sg:city":"Las Vegas",
    "sg:classifiers":[
        {
            "category":"Shopping",
            "type":"Retail Goods"
        }
    ],
    "sg:phone":"+1 702 731 9566",
    "sg:postcode":"89102",
    "sg:province":"NV",
    "sg:tags":[
        "awning",
        "canopy"
    ],
    "wof:name":"Jms Contractor",
    "wof:placetype":"venue"
},
  "geometry": {"coordinates":[-115.192792,36.150156],"type":"Point"}
}