{
  "type": "Feature",
  "properties": {
    "iso:country":"US",
    "sg:address":"6380 S Valley View Blvd",
    "sg:city":"Las Vegas",
    "sg:classifiers":[
        {
            "category":"Food & Beverages",
            "subcategory":"Bakery",
            "type":"Retail Goods"
        }
    ],
    "sg:phone":"+1 702 361 2047",
    "sg:postcode":"89118",
    "sg:province":"NV",
    "sg:tags":[
        "baker"
    ],
    "wof:name":"Nothing Bundt Cakes",
    "wof:placetype":"venue"
},
  "geometry": {"coordinates":[-115.189911,36.075064],"type":"Point"}
}