{
  "type": "Feature",
  "properties": {
    "iso:country":"US",
    "sg:address":"2585 Reno Hwy",
    "sg:city":"Fallon",
    "sg:classifiers":[
        {
            "category":"Retail",
            "subcategory":"Car Wash",
            "type":"Services"
        }
    ],
    "sg:phone":"+1 775 423 2256",
    "sg:postcode":"89406",
    "sg:province":"NV",
    "sg:tags":[
        "polishing",
        "washing"
    ],
    "wof:name":"Top Gun Car Wash",
    "wof:placetype":"venue"
},
  "geometry": {"coordinates":[-118.811571,39.478808],"type":"Point"}
}