{
  "type": "Feature",
  "properties": {
    "iso:country":"US",
    "sg:address":"3731 Winchester Ave",
    "sg:city":"Pahrump",
    "sg:classifiers":[
        {
            "category":"Building & Trades",
            "subcategory":"Landscaping Services",
            "type":"Services"
        }
    ],
    "sg:phone":"+1 775 751 9219",
    "sg:postcode":"89048",
    "sg:province":"NV",
    "sg:tags":[
        "lawn",
        "maintenance",
        "grounds"
    ],
    "wof:name":"Innovative Outdoor Solutions",
    "wof:placetype":"venue"
},
  "geometry": {"coordinates":[-116.04388,36.162908],"type":"Point"}
}