{
  "type": "Feature",
  "properties": {
    "iso:country":"US",
    "sg:address":"6510 N Buffalo Dr",
    "sg:city":"Las Vegas",
    "sg:classifiers":[
        {
            "category":"Utilities",
            "subcategory":"Mobile Phone",
            "type":"Services"
        }
    ],
    "sg:phone":"+1 702 395 2211",
    "sg:postcode":"89131",
    "sg:province":"NV",
    "sg:tags":[
        "telephone",
        "cellular"
    ],
    "wof:name":"Verizon Wireless",
    "wof:placetype":"venue"
},
  "geometry": {"coordinates":[-115.260429,36.284081],"type":"Point"}
}