{
  "type": "Feature",
  "properties": {
    "iso:country":"US",
    "sg:address":"1701 County Rd",
    "sg:city":"Minden",
    "sg:classifiers":[
        {
            "category":"Insurance",
            "subcategory":"Insurance Agent",
            "type":"Services"
        }
    ],
    "sg:phone":"+1 775 782 7107",
    "sg:postcode":"89423",
    "sg:province":"NV",
    "wof:name":"State Farm Insurance",
    "wof:placetype":"venue"
},
  "geometry": {"coordinates":[-119.771224,38.954475],"type":"Point"}
}