{
  "type": "Feature",
  "properties": {
    "iso:country":"US",
    "sg:address":"4023 W Oquendo Rd",
    "sg:city":"Las Vegas",
    "sg:classifiers":[
        {
            "category":"Manufacturing",
            "subcategory":"Tools & Machinery",
            "type":"Manufacturing & Wholesale Goods"
        }
    ],
    "sg:phone":"+1 702 860 6320",
    "sg:postcode":"89118",
    "sg:province":"NV",
    "sg:tags":[
        "machine",
        "shop"
    ],
    "wof:name":"Advanced Results Mach Tech Inc",
    "wof:placetype":"venue"
},
  "geometry": {"coordinates":[-115.192279,36.082607],"type":"Point"}
}