{
  "type": "Feature",
  "properties": {
    "iso:country":"US",
    "sg:address":"122 Industrial Park Rd",
    "sg:city":"Henderson",
    "sg:classifiers":[
        {
            "category":"Autos & Motor Vehicles",
            "subcategory":"Motorcycle Sales",
            "type":"Retail Goods"
        }
    ],
    "sg:phone":"+1 702 644 6686",
    "sg:postcode":"89015",
    "sg:province":"NV",
    "sg:tags":[
        "scooter"
    ],
    "wof:name":"R C Motorsports",
    "wof:placetype":"venue"
},
  "geometry": {"coordinates":[-115.003665,36.034257],"type":"Point"}
}