{
  "type": "Feature",
  "properties": {
    "iso:country":"US",
    "sg:address":"3485 W Harmon Ave",
    "sg:city":"Las Vegas",
    "sg:classifiers":[
        {
            "category":"Communications",
            "subcategory":"Film & Video Production",
            "type":"Services"
        }
    ],
    "sg:phone":"+1 702 341 9444",
    "sg:postcode":"89103",
    "sg:province":"NV",
    "sg:tags":[
        "motion",
        "taping"
    ],
    "sg:website":"www.mediaunderground.com",
    "wof:name":"Media Underground Inc",
    "wof:placetype":"venue"
},
  "geometry": {"coordinates":[-115.187622,36.10813],"type":"Point"}
}