{
  "type": "Feature",
  "properties": {
    "iso:country":"US",
    "sg:address":"Trump Hotel 2000 Fashion Show Dr",
    "sg:city":"Las Vegas",
    "sg:classifiers":[
        {
            "category":"Personal",
            "subcategory":"Day Spa",
            "type":"Services"
        }
    ],
    "sg:phone":"+1 702 476 8000",
    "sg:postcode":"89109",
    "sg:province":"NV",
    "sg:website":"www.trumplasvegashotel.com",
    "wof:name":"The Spa At Trump",
    "wof:placetype":"venue"
},
  "geometry": {"coordinates":[-115.173218,36.129088],"type":"Point"}
}