{
  "type": "Feature",
  "properties": {
    "iso:country":"US",
    "sg:address":"3237 Industrial Rd",
    "sg:city":"Las Vegas",
    "sg:classifiers":[
        {
            "category":"Personal",
            "type":"Services"
        }
    ],
    "sg:phone":"+1 702 734 8187",
    "sg:postcode":"89109",
    "sg:province":"NV",
    "sg:tags":[
        "piercing"
    ],
    "wof:name":"Dead President Tattoo",
    "wof:placetype":"venue"
},
  "geometry": {"coordinates":[-115.174004,36.1306],"type":"Point"}
}