{
  "type": "Feature",
  "properties": {
    "iso:country":"US",
    "sg:address":"4995 S Eastern Avenue",
    "sg:city":"Las Vegas",
    "sg:classifiers":[
        {
            "category":"Shopping",
            "subcategory":"Stationery & Office Supplies",
            "type":"Retail Goods"
        }
    ],
    "sg:phone":"+1 702 736 4411",
    "sg:postcode":"89119",
    "sg:province":"NV",
    "sg:tags":[
        "equipment"
    ],
    "sg:website":"www.officemax.com",
    "wof:name":"Officemax",
    "wof:placetype":"venue"
},
  "geometry": {"coordinates":[-115.118746,36.09822],"type":"Point"}
}