{
  "type": "Feature",
  "properties": {
    "iso:country":"US",
    "sg:address":"4859 E Newton Dr",
    "sg:city":"Las Vegas",
    "sg:classifiers":[
        {
            "category":"Retail",
            "subcategory":"Laundry & Dry Cleaning",
            "type":"Services"
        }
    ],
    "sg:phone":"+1 702 458 9555",
    "sg:postcode":"89121",
    "sg:province":"NV",
    "sg:tags":[
        "cleaners",
        "rug",
        "carpet"
    ],
    "wof:name":"A",
    "wof:placetype":"venue"
},
  "geometry": {"coordinates":[-115.06424199999999,36.103326],"type":"Point"}
}