{
  "type": "Feature",
  "properties": {
    "iso:country":"US",
    "sg:address":"9577 World Cup Dr",
    "sg:city":"Las Vegas",
    "sg:classifiers":[
        {
            "category":"Retail",
            "subcategory":"Laundry & Dry Cleaning",
            "type":"Services"
        }
    ],
    "sg:phone":"+1 702 242 0733",
    "sg:postcode":"89117",
    "sg:province":"NV",
    "wof:name":"Nikone Cleaning Service",
    "wof:placetype":"venue"
},
  "geometry": {"coordinates":[-115.304953,36.151994],"type":"Point"}
}