{
  "type": "Feature",
  "properties": {
    "iso:country":"US",
    "sg:address":"40 Lonepine Ct",
    "sg:city":"Reno",
    "sg:classifiers":[
        {
            "category":"Real Estate",
            "subcategory":"Architect",
            "type":"Services"
        }
    ],
    "sg:phone":"+1 775 746 0619",
    "sg:postcode":"89519",
    "sg:province":"NV",
    "wof:name":"Cox & Kromydas Architects",
    "wof:placetype":"venue"
},
  "geometry": {"coordinates":[-119.869159,39.484823],"type":"Point"}
}