{
  "type": "Feature",
  "properties": {
    "iso:country":"US",
    "sg:address":"425 Drumm Ln",
    "sg:city":"Fallon",
    "sg:classifiers":[
        {
            "category":"Retail",
            "subcategory":"Auto Repair",
            "type":"Services"
        }
    ],
    "sg:phone":"+1 775 423 2024",
    "sg:postcode":"89406",
    "sg:province":"NV",
    "sg:tags":[
        "machine",
        "shop",
        "general"
    ],
    "wof:name":"Landis Inc",
    "wof:placetype":"venue"
},
  "geometry": {"coordinates":[-118.774098,39.445805],"type":"Point"}
}