{
  "type": "Feature",
  "properties": {
    "iso:country":"US",
    "sg:address":"353 Amber Pine St",
    "sg:city":"Las Vegas",
    "sg:classifiers":[
        {
            "category":"Professional",
            "subcategory":"Advertising",
            "type":"Services"
        }
    ],
    "sg:phone":"+1 702 610 9503",
    "sg:postcode":"89144",
    "sg:province":"NV",
    "sg:tags":[
        "agency"
    ],
    "wof:name":"Marquis Advertising",
    "wof:placetype":"venue"
},
  "geometry": {"coordinates":[-115.326712,36.16961],"type":"Point"}
}