{
  "type": "Feature",
  "properties": {
    "iso:country":"US",
    "sg:address":"7935 Sugar Pine Way",
    "sg:city":"Reno",
    "sg:classifiers":[
        {
            "category":"Wholesale",
            "subcategory":"Groceries",
            "type":"Manufacturing & Wholesale Goods"
        }
    ],
    "sg:phone":"+1 775 787 3020",
    "sg:postcode":"89523",
    "sg:province":"NV",
    "wof:name":"C & M Food Distributing Inc",
    "wof:placetype":"venue"
},
  "geometry": {"coordinates":[-119.89711699999999,39.50437],"type":"Point"}
}