{
  "type": "Feature",
  "properties": {
    "iso:country":"US",
    "sg:address":"800 E College Pkwy",
    "sg:city":"Carson City",
    "sg:classifiers":[
        {
            "category":"Professional",
            "subcategory":"Engineering",
            "type":"Services"
        }
    ],
    "sg:phone":"+1 775 883 7077",
    "sg:postcode":"89706",
    "sg:province":"NV",
    "sg:tags":[
        "laboratory",
        "testing",
        "surveying"
    ],
    "wof:name":"Lumos & Associates Inc",
    "wof:placetype":"venue"
},
  "geometry": {"coordinates":[-119.759828,39.190749],"type":"Point"}
}