{
  "type": "Feature",
  "properties": {
    "iso:country":"US",
    "sg:address":"361 Lakeport Dr",
    "sg:city":"Spring Creek",
    "sg:classifiers":[
        {
            "category":"Building & Trades",
            "subcategory":"Construction",
            "type":"Services"
        }
    ],
    "sg:phone":"+1 775 753 6419",
    "sg:postcode":"89815",
    "sg:province":"NV",
    "sg:tags":[
        "contractor"
    ],
    "wof:name":"Larry Ortman Construction",
    "wof:placetype":"venue"
},
  "geometry": {"coordinates":[-115.601767,40.739468],"type":"Point"}
}