{
  "type": "Feature",
  "properties": {
    "iso:country":"US",
    "sg:address":"4955 S Durango Dr",
    "sg:city":"Las Vegas",
    "sg:classifiers":[
        {
            "category":"Professional",
            "subcategory":"Management & Consulting",
            "type":"Services"
        }
    ],
    "sg:phone":"+1 702 364 5757",
    "sg:postcode":"89113",
    "sg:province":"NV",
    "sg:tags":[
        "consultant"
    ],
    "wof:name":"L S Construction Consulting",
    "wof:placetype":"venue"
},
  "geometry": {"coordinates":[-115.279314,36.097362],"type":"Point"}
}