{
  "type": "Feature",
  "properties": {
    "iso:country":"US",
    "sg:address":"2505 Anthem Village Dr",
    "sg:city":"Henderson",
    "sg:classifiers":[
        {
            "category":"Professional",
            "subcategory":"Management & Consulting",
            "type":"Services"
        }
    ],
    "sg:phone":"+1 702 632 8758",
    "sg:postcode":"89052",
    "sg:province":"NV",
    "sg:tags":[
        "consultant",
        "safety"
    ],
    "sg:website":"www.ntsconsortium.com",
    "wof:name":"Nationwide Testing & Safety",
    "wof:placetype":"venue"
},
  "geometry": {"coordinates":[-115.097925,35.978499],"type":"Point"}
}