{
  "type": "Feature",
  "properties": {
    "iso:country":"US",
    "sg:address":"8084 W Sahara Ave",
    "sg:city":"Las Vegas",
    "sg:classifiers":[
        {
            "category":"Banks & Credit Unions",
            "subcategory":"Bank",
            "type":"Services"
        }
    ],
    "sg:phone":"+1 702 363 5115",
    "sg:postcode":"89117",
    "sg:province":"NV",
    "sg:tags":[
        "broker",
        "mortgage"
    ],
    "wof:name":"Advanced Northstar Lending Inc",
    "wof:placetype":"venue"
},
  "geometry": {"coordinates":[-115.265994,36.143871],"type":"Point"}
}