{
  "type": "Feature",
  "properties": {
    "iso:country":"US",
    "sg:address":"9705 Enniskeen Ave",
    "sg:city":"Las Vegas",
    "sg:classifiers":[
        {
            "category":"Home & Garden",
            "subcategory":"Building Materials",
            "type":"Retail Goods"
        }
    ],
    "sg:phone":"+1 702 498 5126",
    "sg:postcode":"89129",
    "sg:province":"NV",
    "sg:tags":[
        "door"
    ],
    "wof:name":"Ben Franklin Window & Door Co",
    "wof:placetype":"venue"
},
  "geometry": {"coordinates":[-115.306324,36.225516],"type":"Point"}
}