{
  "type": "Feature",
  "properties": {
    "iso:country":"US",
    "sg:address":"5301 Longley Ln",
    "sg:city":"Reno",
    "sg:classifiers":[
        {
            "category":"Professional",
            "subcategory":"Testing Lab",
            "type":"Services"
        }
    ],
    "sg:phone":"+1 775 827 2854",
    "sg:postcode":"89511",
    "sg:province":"NV",
    "sg:tags":[
        "inspection",
        "infrared"
    ],
    "wof:name":"Infrared Inc",
    "wof:placetype":"venue"
},
  "geometry": {"coordinates":[-119.76661199999999,39.471615],"type":"Point"}
}