{
  "type": "Feature",
  "properties": {
    "iso:country":"US",
    "sg:address":"6363 S Pecos Rd",
    "sg:city":"Las Vegas",
    "sg:classifiers":[
        {
            "category":"Shopping",
            "subcategory":"Mobile Phones",
            "type":"Retail Goods"
        }
    ],
    "sg:phone":"+1 702 364 0299",
    "sg:postcode":"89120",
    "sg:province":"NV",
    "wof:name":"Beepme Las Vegas Inc",
    "wof:placetype":"venue"
},
  "geometry": {"coordinates":[-115.100981,36.074027],"type":"Point"}
}