{
  "type": "Feature",
  "properties": {
    "iso:country":"US",
    "sg:address":"2585 S Jones Blvd",
    "sg:city":"Las Vegas",
    "sg:classifiers":[
        {
            "category":"Professional",
            "subcategory":"Advertising",
            "type":"Services"
        }
    ],
    "sg:phone":"+1 702 215 3533",
    "sg:postcode":"89146",
    "sg:province":"NV",
    "sg:tags":[
        "counselor"
    ],
    "wof:name":"American Business Solutions",
    "wof:placetype":"venue"
},
  "geometry": {"coordinates":[-115.225366,36.143968],"type":"Point"}
}