{
  "type": "Feature",
  "properties": {
    "iso:country":"US",
    "sg:address":"3213 E Warm Springs Road",
    "sg:city":"Las Vegas",
    "sg:classifiers":[
        {
            "category":"Banks & Credit Unions",
            "subcategory":"Bank",
            "type":"Services"
        }
    ],
    "sg:phone":"+1 702 798 5099",
    "sg:postcode":"89120",
    "sg:province":"NV",
    "wof:name":"Aztex Atm",
    "wof:placetype":"venue"
},
  "geometry": {"coordinates":[-115.104169,36.057023],"type":"Point"}
}