{
  "type": "Feature",
  "properties": {
    "iso:country":"US",
    "sg:address":"4041 Audrie St",
    "sg:city":"Las Vegas",
    "sg:classifiers":[
        {
            "category":"Restaurant",
            "type":"Food & Drink"
        }
    ],
    "sg:phone":"+1 702 732 1424",
    "sg:postcode":"89109",
    "sg:province":"NV",
    "sg:tags":[
        "italian"
    ],
    "sg:website":"www.battistaslasvegas.com/",
    "wof:name":"Battista's Hole In the Wall",
    "wof:placetype":"venue"
},
  "geometry": {"coordinates":[-115.16799899999999,36.116199],"type":"Point"}
}