{
  "type": "Feature",
  "properties": {
    "iso:country":"US",
    "sg:address":"9990 Double R Blvd",
    "sg:city":"Reno",
    "sg:classifiers":[
        {
            "category":"Banks & Credit Unions",
            "subcategory":"Bank",
            "type":"Services"
        }
    ],
    "sg:phone":"+1 775 853 8600",
    "sg:postcode":"89521",
    "sg:province":"NV",
    "sg:website":"www.nevadasecuritybank.com",
    "wof:name":"Nevada Security Bank",
    "wof:placetype":"venue"
},
  "geometry": {"coordinates":[-119.760567,39.444953],"type":"Point"}
}