{
  "type": "Feature",
  "properties": {
    "iso:country":"US",
    "sg:address":"331 S Water St",
    "sg:city":"Henderson",
    "sg:classifiers":[
        {
            "category":"Retail",
            "subcategory":"Animal Services",
            "type":"Services"
        }
    ],
    "sg:phone":"+1 702 566 4141",
    "sg:postcode":"89015",
    "sg:province":"NV",
    "sg:tags":[
        "pet",
        "grooming",
        "washing"
    ],
    "wof:name":"A Cute Grooming Shop",
    "wof:placetype":"venue"
},
  "geometry": {"coordinates":[-114.978571,36.028498],"type":"Point"}
}