{
  "type": "Feature",
  "properties": {
    "iso:country":"US",
    "sg:address":"7414 Randel Jean Way",
    "sg:city":"Las Vegas",
    "sg:classifiers":[
        {
            "category":"Professional",
            "subcategory":"Business Services",
            "type":"Services"
        }
    ],
    "sg:phone":"+1 702 365 0504",
    "sg:postcode":"89113",
    "sg:province":"NV",
    "sg:tags":[
        "pool",
        "swimming"
    ],
    "wof:name":"Sparkles Pool Cleaning",
    "wof:placetype":"venue"
},
  "geometry": {"coordinates":[-115.253096,36.087734],"type":"Point"}
}