{
  "type": "Feature",
  "properties": {
    "iso:country":"US",
    "sg:address":"1967 N Decatur Blvd",
    "sg:city":"Las Vegas",
    "sg:classifiers":[
        {
            "category":"Building & Trades",
            "subcategory":"Equipment Rental",
            "type":"Services"
        }
    ],
    "sg:phone":"+1 702 631 7346",
    "sg:postcode":"89108",
    "sg:province":"NV",
    "wof:name":"Rent-A-Center",
    "wof:placetype":"venue"
},
  "geometry": {"coordinates":[-115.206052,36.194569],"type":"Point"}
}