{
  "type": "Feature",
  "properties": {
    "iso:country":"US",
    "sg:address":"1080 Telegraph St",
    "sg:city":"Reno",
    "sg:classifiers":[
        {
            "category":"Freight",
            "type":"Transportation"
        }
    ],
    "sg:phone":"+1 775 329 2333",
    "sg:postcode":"89502",
    "sg:province":"NV",
    "sg:tags":[
        "commercial",
        "storage"
    ],
    "wof:name":"Mini Warehouse",
    "wof:placetype":"venue"
},
  "geometry": {"coordinates":[-119.773342,39.515552],"type":"Point"}
}