{
  "type": "Feature",
  "properties": {
    "iso:country":"US",
    "sg:address":"9947 Canyon Peak Dr",
    "sg:city":"Las Vegas",
    "sg:classifiers":[
        {
            "category":"Building & Trades",
            "subcategory":"Construction",
            "type":"Services"
        }
    ],
    "sg:phone":"+1 702 407 1850",
    "sg:postcode":"89147",
    "sg:province":"NV",
    "sg:tags":[
        "home",
        "improvement"
    ],
    "wof:name":"Nevada Home Maintenance",
    "wof:placetype":"venue"
},
  "geometry": {"coordinates":[-115.308898,36.102266],"type":"Point"}
}