{
  "type": "Feature",
  "properties": {
    "iso:country":"US",
    "sg:address":"45 W 2nd St",
    "sg:city":"Reno",
    "sg:classifiers":[
        {
            "category":"Bars & Pubs",
            "type":"Food & Drink"
        }
    ],
    "sg:phone":"+1 775 329 1952",
    "sg:postcode":"89501",
    "sg:province":"NV",
    "sg:tags":[
        "drinking"
    ],
    "wof:name":"Reno Live Nightclub Complex",
    "wof:placetype":"venue"
},
  "geometry": {"coordinates":[-119.81451800000001,39.526763],"type":"Point"}
}