{
  "type": "Feature",
  "properties": {
    "iso:country":"US",
    "sg:address":"2080 E Flamingo Rd",
    "sg:city":"Las Vegas",
    "sg:classifiers":[
        {
            "category":"Personal",
            "subcategory":"Beauty Salon",
            "type":"Services"
        }
    ],
    "sg:phone":"+1 702 735 5808",
    "sg:postcode":"89119",
    "sg:province":"NV",
    "sg:tags":[
        "shop"
    ],
    "wof:name":"Details",
    "wof:placetype":"venue"
},
  "geometry": {"coordinates":[-115.125918,36.114706],"type":"Point"}
}