{
  "type": "Feature",
  "properties": {
    "iso:country":"US",
    "sg:address":"2324 Angelfire",
    "sg:city":"Las Vegas",
    "sg:classifiers":[
        {
            "category":"Professional",
            "subcategory":"Business Services",
            "type":"Services"
        },
        {
            "category":"Professional",
            "subcategory":"Management & Consulting",
            "type":"Services"
        }
    ],
    "sg:phone":"+1 702 838 0257",
    "sg:postcode":"89128",
    "sg:province":"NV",
    "sg:tags":[
        "consultant",
        "safety"
    ],
    "wof:name":"Reaux & Associates LLC",
    "wof:placetype":"venue"
},
  "geometry": {"coordinates":[-115.27724499999999,36.202541],"type":"Point"}
}