{
  "type": "Feature",
  "properties": {
    "iso:country":"US",
    "sg:address":"7851 Vegas Dr",
    "sg:city":"Las Vegas",
    "sg:classifiers":[
        {
            "category":"Social Services",
            "subcategory":"Child Care",
            "type":"Services"
        },
        {
            "category":"Organizations",
            "subcategory":"Religious Organization",
            "type":"Services"
        }
    ],
    "sg:phone":"+1 702 360 3550",
    "sg:postcode":"89128",
    "sg:province":"NV",
    "sg:tags":[
        "day"
    ],
    "sg:website":"www.shadowhills.org",
    "wof:name":"Shadow Hills Baptist Child Care Center",
    "wof:placetype":"venue"
},
  "geometry": {"coordinates":[-115.26566699999999,36.188709],"type":"Point"}
}