{
  "type": "Feature",
  "properties": {
    "iso:country":"US",
    "sg:address":"441 W Plumb Ln",
    "sg:city":"Reno",
    "sg:classifiers":[
        {
            "category":"Autos & Motor Vehicles",
            "subcategory":"Boat Sales",
            "type":"Retail Goods"
        }
    ],
    "sg:phone":"+1 775 786 1717",
    "sg:postcode":"89509",
    "sg:province":"NV",
    "sg:tags":[
        "automobile"
    ],
    "wof:name":"Grand Touring Imports Inc",
    "wof:placetype":"venue"
},
  "geometry": {"coordinates":[-119.813359,39.505788],"type":"Point"}
}