{
  "type": "Feature",
  "properties": {
    "iso:country":"US",
    "sg:address":"1750 E Desert Inn Rd",
    "sg:city":"Las Vegas",
    "sg:classifiers":[
        {
            "category":"Health Services",
            "subcategory":"Doctor",
            "type":"Services"
        }
    ],
    "sg:phone":"+1 702 735 5477",
    "sg:postcode":"89109",
    "sg:province":"NV",
    "sg:tags":[
        "medicine",
        "internal"
    ],
    "wof:name":"Hypertensin & Renal Institute of Nevada",
    "wof:placetype":"venue"
},
  "geometry": {"coordinates":[-115.127998,36.129799],"type":"Point"}
}