{
  "type": "Feature",
  "properties": {
    "iso:country":"US",
    "sg:address":"75 E Horizon Ridge Pkwy Ste 120",
    "sg:city":"Henderson",
    "sg:classifiers":[
        {
            "category":"Restaurant",
            "type":"Food & Drink"
        }
    ],
    "sg:phone":"+1 702 386 8883",
    "sg:postcode":"89002",
    "sg:province":"NV",
    "sg:tags":[
        "chinese"
    ],
    "wof:name":"Grand China",
    "wof:placetype":"venue"
},
  "geometry": {"coordinates":[-114.991205,36.008538],"type":"Point"}
}