{
  "type": "Feature",
  "properties": {
    "iso:country":"US",
    "sg:address":"251 Jeanell Dr",
    "sg:city":"Carson City",
    "sg:classifiers":[
        {
            "category":"Professional",
            "type":"Services"
        }
    ],
    "sg:phone":"+1 775 884 6104",
    "sg:postcode":"89703",
    "sg:province":"NV",
    "sg:tags":[
        "establishment"
    ],
    "wof:name":"Roja Inc",
    "wof:placetype":"venue"
},
  "geometry": {"coordinates":[-119.768435,39.179967],"type":"Point"}
}