{
  "type": "Feature",
  "properties": {
    "iso:country":"US",
    "sg:address":"1325 Airmotive Way",
    "sg:city":"Reno",
    "sg:classifiers":[
        {
            "category":"Professional",
            "subcategory":"Advertising",
            "type":"Services"
        }
    ],
    "sg:phone":"+1 775 284 5020",
    "sg:postcode":"89502",
    "sg:province":"NV",
    "sg:tags":[
        "counselor"
    ],
    "wof:name":"Swanson Advertising Inc",
    "wof:placetype":"venue"
},
  "geometry": {"coordinates":[-119.778866,39.511019],"type":"Point"}
}