{
  "type": "Feature",
  "properties": {
    "iso:country":"US",
    "sg:address":"159 Glen Brier Dr",
    "sg:city":"Spring Creek",
    "sg:classifiers":[
        {
            "category":"Real Estate",
            "subcategory":"Real Estate Agent",
            "type":"Services"
        }
    ],
    "sg:phone":"+1 775 777 9330",
    "sg:postcode":"89815",
    "sg:province":"NV",
    "sg:website":"www.realtor.com",
    "wof:name":"Copeland Realty",
    "wof:placetype":"venue"
},
  "geometry": {"coordinates":[-115.606763,40.741986],"type":"Point"}
}