{
  "type": "Feature",
  "properties": {
    "iso:country":"US",
    "sg:address":"925 Felix Palm Ave",
    "sg:city":"North Las Vegas",
    "sg:classifiers":[
        {
            "category":"Organizations",
            "subcategory":"Religious Organization",
            "type":"Services"
        }
    ],
    "sg:phone":"+1 702 878 1006",
    "sg:postcode":"89032",
    "sg:province":"NV",
    "sg:tags":[
        "church"
    ],
    "wof:name":"Catholic Apostolic Church Int",
    "wof:placetype":"venue"
},
  "geometry": {"coordinates":[-115.155552,36.233809],"type":"Point"}
}