{
  "type": "Feature",
  "properties": {
    "iso:country":"US",
    "sg:address":"6185 S Pecos Rd",
    "sg:city":"Las Vegas",
    "sg:classifiers":[
        {
            "category":"Organizations",
            "subcategory":"Religious Organization",
            "type":"Services"
        }
    ],
    "sg:phone":"+1 702 263 1082",
    "sg:postcode":"89120",
    "sg:province":"NV",
    "wof:name":"Hosana Ministeries Intern",
    "wof:placetype":"venue"
},
  "geometry": {"coordinates":[-115.101009,36.078161],"type":"Point"}
}