{
  "type": "Feature",
  "properties": {
    "iso:country":"US",
    "sg:address":"7209 Raincloud Dr",
    "sg:city":"Las Vegas",
    "sg:classifiers":[
        {
            "category":"Building & Trades",
            "subcategory":"Construction",
            "type":"Services"
        }
    ],
    "sg:phone":"+1 702 364 4666",
    "sg:postcode":"89145",
    "sg:province":"NV",
    "sg:tags":[
        "marking",
        "maintenance",
        "parking"
    ],
    "wof:name":"Action Sweeping Svc Inc",
    "wof:placetype":"venue"
},
  "geometry": {"coordinates":[-115.253547,36.173426],"type":"Point"}
}