{
  "type": "Feature",
  "properties": {
    "iso:country":"US",
    "sg:address":"771 E Horizon Dr Ste 156",
    "sg:city":"Henderson",
    "sg:classifiers":[
        {
            "category":"Restaurant",
            "type":"Food & Drink"
        }
    ],
    "sg:phone":"+1 702 568 6262",
    "sg:postcode":"89015",
    "sg:province":"NV",
    "sg:tags":[
        "pizza"
    ],
    "sg:website":"www.papajohns.com",
    "wof:name":"Papa John's Pizza",
    "wof:placetype":"venue"
},
  "geometry": {"coordinates":[-114.960089,36.013221],"type":"Point"}
}