{
  "type": "Feature",
  "properties": {
    "iso:country":"US",
    "sg:address":"5299 Treasure Ave",
    "sg:city":"Las Vegas",
    "sg:classifiers":[
        {
            "category":"Professional",
            "type":"Services"
        }
    ],
    "sg:phone":"+1 702 278 0098",
    "sg:postcode":"89122",
    "sg:province":"NV",
    "wof:name":"Oil Filtration Svc",
    "wof:placetype":"venue"
},
  "geometry": {"coordinates":[-115.057476,36.114342],"type":"Point"}
}