{
  "type": "Feature",
  "properties": {
    "iso:country":"US",
    "sg:address":"4480 E Charleston Blvd",
    "sg:city":"Las Vegas",
    "sg:classifiers":[
        {
            "category":"Home & Garden",
            "subcategory":"Furniture",
            "type":"Retail Goods"
        }
    ],
    "sg:phone":"+1 702 453 5655",
    "sg:postcode":"89104",
    "sg:province":"NV",
    "sg:tags":[
        "store"
    ],
    "wof:name":"Hacienda Furniture",
    "wof:placetype":"venue"
},
  "geometry": {"coordinates":[-115.108002,36.1492],"type":"Point"}
}