{
  "type": "Feature",
  "properties": {
    "iso:country":"US",
    "sg:address":"6212 W Charleston Blvd Ste 100",
    "sg:city":"Las Vegas",
    "sg:classifiers":[
        {
            "category":"Health Services",
            "subcategory":"Chiropractor",
            "type":"Services"
        }
    ],
    "sg:phone":"+1 702 878 3191",
    "sg:postcode":"89146",
    "sg:province":"NV",
    "wof:name":"Hansen Chiropractic Ofc",
    "wof:placetype":"venue"
},
  "geometry": {"coordinates":[-115.227997,36.159302],"type":"Point"}
}