{
  "type": "Feature",
  "properties": {
    "iso:country":"US",
    "sg:address":"7041 English Mist Cir",
    "sg:city":"Las Vegas",
    "sg:classifiers":[
        {
            "category":"Professional",
            "subcategory":"Secretarial Services",
            "type":"Services"
        }
    ],
    "sg:phone":"+1 702 240 6834",
    "sg:postcode":"89128",
    "sg:province":"NV",
    "sg:tags":[
        "reporting"
    ],
    "wof:name":"Resume Builders",
    "wof:placetype":"venue"
},
  "geometry": {"coordinates":[-115.24772,36.188124],"type":"Point"}
}