{
  "type": "Feature",
  "properties": {
    "iso:country":"US",
    "sg:address":"6118 W Charleston Blvd",
    "sg:city":"Las Vegas",
    "sg:classifiers":[
        {
            "category":"Restaurant",
            "type":"Food & Drink"
        }
    ],
    "sg:phone":"+1 702 878 0008",
    "sg:postcode":"89146",
    "sg:province":"NV",
    "sg:tags":[
        "mexican"
    ],
    "wof:name":"Tacos El Compita",
    "wof:placetype":"venue"
},
  "geometry": {"coordinates":[-115.224998,36.159401],"type":"Point"}
}