{
  "type": "Feature",
  "properties": {
    "iso:country":"US",
    "sg:address":"261 Country Club Pl",
    "sg:city":"Spring Creek",
    "sg:classifiers":[
        {
            "category":"Manufacturing",
            "subcategory":"Retail Goods",
            "type":"Manufacturing & Wholesale Goods"
        }
    ],
    "sg:phone":"+1 775 934 5850",
    "sg:postcode":"89815",
    "sg:province":"NV",
    "sg:tags":[
        "product",
        "mfg"
    ],
    "wof:name":"Angelic Aromas By Robyn",
    "wof:placetype":"venue"
},
  "geometry": {"coordinates":[-115.596981,40.746041],"type":"Point"}
}