{
  "type": "Feature",
  "properties": {
    "iso:country":"US",
    "sg:address":"7995 W Sahara Avenue",
    "sg:city":"Las Vegas",
    "sg:classifiers":[
        {
            "category":"Shopping",
            "subcategory":"Jewelry",
            "type":"Retail Goods"
        }
    ],
    "sg:phone":"+1 702 259 8011",
    "sg:postcode":"89117",
    "sg:province":"NV",
    "wof:name":"Las Vegas Manufacturing Jewelers",
    "wof:placetype":"venue"
},
  "geometry": {"coordinates":[-115.265051,36.143638],"type":"Point"}
}