{
  "type": "Feature",
  "properties": {
    "iso:country":"US",
    "sg:address":"111 Washington St",
    "sg:city":"Reno",
    "sg:classifiers":[
        {
            "category":"Health Services",
            "subcategory":"Clinic",
            "type":"Services"
        }
    ],
    "sg:phone":"+1 775 322 8414",
    "sg:postcode":"89503",
    "sg:province":"NV",
    "sg:tags":[
        "home"
    ],
    "wof:name":"Lend A Hand Senior Svc",
    "wof:placetype":"venue"
},
  "geometry": {"coordinates":[-119.822461,39.52503],"type":"Point"}
}