{
  "type": "Feature",
  "properties": {
    "iso:country":"US",
    "sg:address":"1850 E Sahara Ave",
    "sg:city":"Las Vegas",
    "sg:classifiers":[
        {
            "category":"Professional",
            "subcategory":"Management & Consulting",
            "type":"Services"
        }
    ],
    "sg:phone":"+1 702 486 8255",
    "sg:postcode":"89104",
    "sg:province":"NV",
    "wof:name":"Office For Hospital Patients",
    "wof:placetype":"venue"
},
  "geometry": {"coordinates":[-115.12426499999999,36.144412],"type":"Point"}
}