{
  "type": "Feature",
  "properties": {
    "iso:country":"US",
    "sg:address":"255 Virgil Ct",
    "sg:city":"Sparks",
    "sg:classifiers":[
        {
            "category":"Retail",
            "subcategory":"Laundry & Dry Cleaning",
            "type":"Services"
        }
    ],
    "sg:phone":"+1 775 424 1934",
    "sg:postcode":"89441",
    "sg:province":"NV",
    "sg:tags":[
        "cleaners",
        "rug",
        "carpet"
    ],
    "wof:name":"Majestic Carpet Care",
    "wof:placetype":"venue"
},
  "geometry": {"coordinates":[-119.693442,39.639424],"type":"Point"}
}