{
  "type": "Feature",
  "properties": {
    "iso:country":"US",
    "sg:address":"1304 Las Vegas Blvd S",
    "sg:city":"Las Vegas",
    "sg:classifiers":[
        {
            "category":"Shopping",
            "subcategory":"Clothing, Apparel, & Fashions",
            "type":"Retail Goods"
        }
    ],
    "sg:phone":"+1 702 385 7777",
    "sg:postcode":"89104",
    "sg:province":"NV",
    "sg:tags":[
        "shop",
        "bridal"
    ],
    "wof:name":"A San Francisco Sally's Wddng",
    "wof:placetype":"venue"
},
  "geometry": {"coordinates":[-115.149046,36.156596],"type":"Point"}
}