{
  "type": "Feature",
  "properties": {
    "iso:country":"US",
    "sg:address":"1373 Goldenglow Rd",
    "sg:city":"Las Vegas",
    "sg:classifiers":[
        {
            "category":"Building & Trades",
            "subcategory":"Electrical",
            "type":"Services"
        }
    ],
    "sg:phone":"+1 702 631 0710",
    "sg:postcode":"89108",
    "sg:province":"NV",
    "sg:tags":[
        "electrical",
        "contractor"
    ],
    "wof:name":"McGowan Electric",
    "wof:placetype":"venue"
},
  "geometry": {"coordinates":[-115.235688,36.186193],"type":"Point"}
}