{
  "type": "Feature",
  "properties": {
    "iso:country":"US",
    "sg:address":"2800 Alta Dr",
    "sg:city":"Las Vegas",
    "sg:classifiers":[
        {
            "category":"Real Estate",
            "subcategory":"Real Estate Agent",
            "type":"Services"
        }
    ],
    "sg:phone":"+1 702 259 9990",
    "sg:postcode":"89107",
    "sg:province":"NV",
    "wof:name":"3 Brothers Realty",
    "wof:placetype":"venue"
},
  "geometry": {"coordinates":[-115.183431,36.166268],"type":"Point"}
}