{
  "type": "Feature",
  "properties": {
    "iso:country":"US",
    "sg:address":"Encore 3131 Las Vegas Blvd. S",
    "sg:city":"Las Vegas",
    "sg:classifiers":[
        {
            "category":"Shopping",
            "subcategory":"Shoes",
            "type":"Retail Goods"
        }
    ],
    "sg:postcode":"89109",
    "sg:province":"NV",
    "sg:tags":[
        "store"
    ],
    "sg:website":"www.encorelasvegas.com",
    "wof:name":"In Step",
    "wof:placetype":"venue"
},
  "geometry": {"coordinates":[-115.167505,36.127002],"type":"Point"}
}