{
  "type": "Feature",
  "properties": {
    "iso:country":"US",
    "sg:address":"10100 S Eastern Ave",
    "sg:city":"Henderson",
    "sg:classifiers":[
        {
            "category":"Food & Beverages",
            "subcategory":"Bakery",
            "type":"Retail Goods"
        }
    ],
    "sg:phone":"+1 702 407 5639",
    "sg:postcode":"89052",
    "sg:province":"NV",
    "sg:tags":[
        "bagel"
    ],
    "wof:name":"Brooklyn Bagle Deli",
    "wof:placetype":"venue"
},
  "geometry": {"coordinates":[-115.112538,36.005945],"type":"Point"}
}