{
  "type": "Feature",
  "properties": {
    "iso:country":"US",
    "sg:address":"4130 S Sandhill Rd Ste A05",
    "sg:city":"Las Vegas",
    "sg:classifiers":[
        {
            "category":"Personal",
            "subcategory":"Tattoo Parlor",
            "type":"Services"
        }
    ],
    "sg:phone":"+1 702 367 8282",
    "sg:postcode":"89121",
    "sg:province":"NV",
    "wof:name":"Dragon Tat2",
    "wof:placetype":"venue"
},
  "geometry": {"coordinates":[-115.091728,36.114063],"type":"Point"}
}