{
  "type": "Feature",
  "properties": {
    "iso:country":"US",
    "sg:address":"1313 S Eastern Ave",
    "sg:city":"Las Vegas",
    "sg:classifiers":[
        {
            "category":"Professional",
            "subcategory":"Art Services",
            "type":"Services"
        }
    ],
    "sg:phone":"+1 702 385 6005",
    "sg:postcode":"89104",
    "sg:province":"NV",
    "sg:tags":[
        "graphic",
        "designer"
    ],
    "wof:name":"Graphicka",
    "wof:placetype":"venue"
},
  "geometry": {"coordinates":[-115.118929,36.154076],"type":"Point"}
}