{
  "type": "Feature",
  "properties": {
    "iso:country":"US",
    "sg:address":"11745 Juniper St",
    "sg:city":"Reno",
    "sg:classifiers":[
        {
            "category":"Shopping",
            "type":"Retail Goods"
        }
    ],
    "sg:phone":"+1 775 972 7561",
    "sg:postcode":"89506",
    "sg:province":"NV",
    "sg:tags":[
        "merchandise"
    ],
    "wof:name":"Party Lite Candles",
    "wof:placetype":"venue"
},
  "geometry": {"coordinates":[-119.839755,39.691853],"type":"Point"}
}