{
  "type": "Feature",
  "properties": {
    "iso:country":"US",
    "sg:address":"3395 W Lake Mead Blvd",
    "sg:city":"North Las Vegas",
    "sg:classifiers":[
        {
            "category":"Autos & Motor Vehicles",
            "subcategory":"Motorcycle Sales",
            "type":"Retail Goods"
        }
    ],
    "sg:phone":"+1 702 889 1292",
    "sg:postcode":"89032",
    "sg:province":"NV",
    "wof:name":"Scooterx",
    "wof:placetype":"venue"
},
  "geometry": {"coordinates":[-115.184419,36.197461],"type":"Point"}
}