{
  "type": "Feature",
  "properties": {
    "iso:country":"US",
    "sg:address":"810 Holman Way",
    "sg:city":"Sparks",
    "sg:classifiers":[
        {
            "category":"Shopping",
            "subcategory":"Books",
            "type":"Retail Goods"
        }
    ],
    "sg:phone":"+1 775 359 7940",
    "sg:postcode":"89431",
    "sg:province":"NV",
    "sg:tags":[
        "bookstore",
        "religious",
        "dealer"
    ],
    "wof:name":"His Word Christian Book Store",
    "wof:placetype":"venue"
},
  "geometry": {"coordinates":[-119.755485,39.549678],"type":"Point"}
}