{
  "type": "Feature",
  "properties": {
    "iso:country":"US",
    "sg:address":"6541 Ruby Red Cir",
    "sg:city":"Las Vegas",
    "sg:classifiers":[
        {
            "category":"Shopping",
            "subcategory":"Computers & Home Electronics",
            "type":"Retail Goods"
        }
    ],
    "sg:phone":"+1 702 277 7764",
    "sg:postcode":"89108",
    "sg:province":"NV",
    "sg:tags":[
        "equipment",
        "dealer"
    ],
    "wof:name":"Web Direct Pros",
    "wof:placetype":"venue"
},
  "geometry": {"coordinates":[-115.23678,36.184266],"type":"Point"}
}