{
  "type": "Feature",
  "properties": {
    "iso:country":"US",
    "sg:address":"3535 W Sahara Ave",
    "sg:city":"Las Vegas",
    "sg:classifiers":[
        {
            "category":"Shopping",
            "subcategory":"Computers & Home Electronics",
            "type":"Retail Goods"
        }
    ],
    "sg:phone":"+1 702 253 5379",
    "sg:postcode":"89102",
    "sg:province":"NV",
    "sg:tags":[
        "equipment",
        "electronic",
        "supply"
    ],
    "wof:name":"Sony Electronics",
    "wof:placetype":"venue"
},
  "geometry": {"coordinates":[-115.18892,36.144325],"type":"Point"}
}