{
  "type": "Feature",
  "properties": {
    "iso:country":"US",
    "sg:address":"200 Convention Center Dr",
    "sg:city":"Las Vegas",
    "sg:classifiers":[
        {
            "category":"Recreation",
            "subcategory":"Amusement Park",
            "type":"Entertainment"
        },
        {
            "category":"Retail",
            "subcategory":"Event Space",
            "type":"Services"
        }
    ],
    "sg:phone":"+1 702 731 4768",
    "sg:postcode":"89109",
    "sg:province":"NV",
    "sg:tags":[
        "venue"
    ],
    "sg:website":"www.vegasindoorskydiving.com",
    "wof:name":"Vegas Indoor Skydiving",
    "wof:placetype":"venue"
},
  "geometry": {"coordinates":[-115.16100299999999,36.132401],"type":"Point"}
}