{
  "type": "Feature",
  "properties": {
    "iso:country":"US",
    "sg:address":"5709 Sliding Rock St",
    "sg:city":"Las Vegas",
    "sg:classifiers":[
        {
            "category":"Professional",
            "subcategory":"Business Services",
            "type":"Services"
        }
    ],
    "sg:phone":"+1 702 360 8430",
    "sg:postcode":"89149",
    "sg:province":"NV",
    "wof:name":"Superior Accident Reconstructn",
    "wof:placetype":"venue"
},
  "geometry": {"coordinates":[-115.27724499999999,36.265319],"type":"Point"}
}