{
  "type": "Feature",
  "properties": {
    "iso:country":"US",
    "sg:address":"451 S Decatur Blvd",
    "sg:city":"Las Vegas",
    "sg:classifiers":[
        {
            "category":"Shopping",
            "subcategory":"Pharmacy",
            "type":"Retail Goods"
        }
    ],
    "sg:phone":"+1 702 870 1626",
    "sg:postcode":"89107",
    "sg:province":"NV",
    "sg:tags":[
        "drugstore"
    ],
    "sg:website":"walgreens.com",
    "wof:name":"Walgreens",
    "wof:placetype":"venue"
},
  "geometry": {"coordinates":[-115.205381,36.16743],"type":"Point"}
}