{
  "type": "Feature",
  "properties": {
    "iso:country":"US",
    "sg:address":"3476 Executive Pointe Way",
    "sg:city":"Carson City",
    "sg:classifiers":[
        {
            "category":"Government",
            "subcategory":"Court House",
            "type":"Public Place"
        }
    ],
    "sg:phone":"+1 775 687 3223",
    "sg:postcode":"89706",
    "sg:province":"NV",
    "sg:tags":[
        "private",
        "board",
        "license",
        "investigator"
    ],
    "wof:name":"Private Invstigator License Bd",
    "wof:placetype":"venue"
},
  "geometry": {"coordinates":[-119.744263,39.190238],"type":"Point"}
}