{
  "type": "Feature",
  "properties": {
    "iso:country":"US",
    "sg:address":"4040 E Wyoming Ave",
    "sg:city":"Las Vegas",
    "sg:classifiers":[
        {
            "category":"Organizations",
            "subcategory":"Religious Organization",
            "type":"Services"
        }
    ],
    "sg:phone":"+1 702 641 6168",
    "sg:postcode":"89104",
    "sg:province":"NV",
    "sg:tags":[
        "church"
    ],
    "wof:name":"Church Of Jesus Christ Of Lds",
    "wof:placetype":"venue"
},
  "geometry": {"coordinates":[-115.08620999999999,36.151934],"type":"Point"}
}