{
  "type": "Feature",
  "properties": {
    "iso:country":"US",
    "sg:address":"2473 N Gateway Rd",
    "sg:city":"Las Vegas",
    "sg:classifiers":[
        {
            "category":"Retail",
            "subcategory":"Auto Repair",
            "type":"Services"
        }
    ],
    "sg:phone":"+1 702 453 3461",
    "sg:postcode":"89115",
    "sg:province":"NV",
    "sg:tags":[
        "general"
    ],
    "wof:name":"Stepans Auto Service",
    "wof:placetype":"venue"
},
  "geometry": {"coordinates":[-115.087078,36.205411],"type":"Point"}
}