{
  "type": "Feature",
  "properties": {
    "iso:country":"US",
    "sg:address":"3544 Sierra Patricia Cir",
    "sg:city":"Las Vegas",
    "sg:classifiers":[
        {
            "category":"Professional",
            "subcategory":"Management & Consulting",
            "type":"Services"
        }
    ],
    "sg:phone":"+1 702 433 9007",
    "sg:postcode":"89121",
    "sg:province":"NV",
    "sg:tags":[
        "sport"
    ],
    "wof:name":"Jealean",
    "wof:placetype":"venue"
},
  "geometry": {"coordinates":[-115.097568,36.102069],"type":"Point"}
}