{
  "type": "Feature",
  "properties": {
    "iso:country":"US",
    "sg:address":"7600 S Rainbow Blvd",
    "sg:city":"Las Vegas",
    "sg:classifiers":[
        {
            "category":"Real Estate",
            "subcategory":"Real Estate Operator",
            "type":"Services"
        }
    ],
    "sg:phone":"+1 702 616 1773",
    "sg:postcode":"89139",
    "sg:province":"NV",
    "sg:tags":[
        "apartment"
    ],
    "wof:name":"Cantera Coronado Ranch",
    "wof:placetype":"venue"
},
  "geometry": {"coordinates":[-115.241911,36.050241],"type":"Point"}
}