{
  "type": "Feature",
  "properties": {
    "iso:country":"US",
    "sg:address":"340 E Warm Springs Rd",
    "sg:city":"Las Vegas",
    "sg:classifiers":[
        {
            "category":"Manufacturing",
            "subcategory":"Printing",
            "type":"Manufacturing & Wholesale Goods"
        }
    ],
    "sg:phone":"+1 702 260 4100",
    "sg:postcode":"89119",
    "sg:province":"NV",
    "sg:tags":[
        "consulting",
        "publishing",
        "business"
    ],
    "wof:name":"Electro Chemical Technologies",
    "wof:placetype":"venue"
},
  "geometry": {"coordinates":[-115.156071,36.057035],"type":"Point"}
}