{
  "type": "Feature",
  "properties": {
    "iso:country":"US",
    "sg:address":"693 N Mccarran Blvd",
    "sg:city":"Sparks",
    "sg:classifiers":[
        {
            "category":"Restaurant",
            "type":"Food & Drink"
        }
    ],
    "sg:menulink":"http://www.allmenus.com/nv/sparks/89973-applebees/menu/",
    "sg:phone":"+1 775 358 5811",
    "sg:postcode":"89431",
    "sg:province":"NV",
    "sg:tags":[
        "burger",
        "american",
        "sandwich",
        "soup"
    ],
    "wof:name":"Applebee's",
    "wof:placetype":"venue"
},
  "geometry": {"coordinates":[-119.733813,39.540854],"type":"Point"}
}