{
  "type": "Feature",
  "properties": {
    "iso:country":"US",
    "sg:address":"3542 W Sirius Ave",
    "sg:city":"Las Vegas",
    "sg:classifiers":[
        {
            "category":"Wholesale",
            "subcategory":"Hardware",
            "type":"Manufacturing & Wholesale Goods"
        }
    ],
    "sg:phone":"+1 702 454 7994",
    "sg:postcode":"89102",
    "sg:province":"NV",
    "sg:tags":[
        "bar",
        "supply"
    ],
    "wof:name":"Western Bar & Restaurant Supl",
    "wof:placetype":"venue"
},
  "geometry": {"coordinates":[-115.188138,36.133801],"type":"Point"}
}