{
  "type": "Feature",
  "properties": {
    "iso:country":"US",
    "sg:address":"6075 Spencer St",
    "sg:city":"Las Vegas",
    "sg:classifiers":[
        {
            "category":"Airline",
            "type":"Transportation"
        }
    ],
    "sg:phone":"+1 702 798 0644",
    "sg:postcode":"89119",
    "sg:province":"NV",
    "sg:tags":[
        "department",
        "cargo",
        "company",
        "air"
    ],
    "sg:website":"www.americawest.com",
    "wof:name":"America West Airlines Inc",
    "wof:placetype":"venue"
},
  "geometry": {"coordinates":[-115.127894,36.082351],"type":"Point"}
}