{
  "type": "Feature",
  "properties": {
    "iso:country":"US",
    "sg:address":"9313 Jadecrest Dr",
    "sg:city":"Las Vegas",
    "sg:classifiers":[
        {
            "category":"Wholesale",
            "subcategory":"Hardware",
            "type":"Manufacturing & Wholesale Goods"
        }
    ],
    "sg:phone":"+1 702 480 1175",
    "sg:postcode":"89134",
    "sg:province":"NV",
    "sg:tags":[
        "purifying",
        "cleaning",
        "air"
    ],
    "wof:name":"Schaper Air",
    "wof:placetype":"venue"
},
  "geometry": {"coordinates":[-115.299761,36.19866],"type":"Point"}
}