{
  "type": "Feature",
  "properties": {
    "iso:country":"US",
    "sg:address":"600 W Bonanza Rd",
    "sg:city":"Las Vegas",
    "sg:classifiers":[
        {
            "category":"Retail",
            "subcategory":"Auto Repair",
            "type":"Services"
        }
    ],
    "sg:phone":"+1 702 384 5099",
    "sg:postcode":"89106",
    "sg:province":"NV",
    "sg:tags":[
        "transmission"
    ],
    "wof:name":"World Transmissions Remfr",
    "wof:placetype":"venue"
},
  "geometry": {"coordinates":[-115.150971,36.177194],"type":"Point"}
}