{
  "type": "Feature",
  "properties": {
    "iso:country":"US",
    "sg:address":"35 E Agate Ave",
    "sg:city":"Las Vegas",
    "sg:classifiers":[
        {
            "category":"Shopping",
            "subcategory":"Adult",
            "type":"Retail Goods"
        }
    ],
    "sg:phone":"+1 702 836 0833",
    "sg:postcode":"89123",
    "sg:province":"NV",
    "sg:tags":[
        "entertainment"
    ],
    "wof:name":"Krave Nightclub",
    "wof:placetype":"venue"
},
  "geometry": {"coordinates":[-115.17062300000001,36.024563],"type":"Point"}
}