{
  "type": "Feature",
  "properties": {
    "iso:country":"US",
    "sg:address":"505 Enchanted Lakes Dr",
    "sg:city":"Henderson",
    "sg:classifiers":[
        {
            "category":"Professional",
            "type":"Services"
        }
    ],
    "sg:phone":"+1 702 260 6897",
    "sg:postcode":"89052",
    "sg:province":"NV",
    "sg:tags":[
        "establishment"
    ],
    "wof:name":"Nicar Franchising Inc",
    "wof:placetype":"venue"
},
  "geometry": {"coordinates":[-115.098409,36.008473],"type":"Point"}
}