{
  "type": "Feature",
  "properties": {
    "iso:country":"US",
    "sg:address":"3960 Howard Hughes Pkwy",
    "sg:city":"Las Vegas",
    "sg:classifiers":[
        {
            "category":"Real Estate",
            "subcategory":"Real Estate Agent",
            "type":"Services"
        },
        {
            "category":"Banks & Credit Unions",
            "subcategory":"Financial Services",
            "type":"Services"
        }
    ],
    "sg:phone":"+1 702 990 3808",
    "sg:postcode":"89169",
    "sg:province":"NV",
    "sg:tags":[
        "investment"
    ],
    "wof:name":"Hottleggz Realty",
    "wof:placetype":"venue"
},
  "geometry": {"coordinates":[-115.157749,36.11686],"type":"Point"}
}