{
  "type": "Feature",
  "properties": {
    "iso:country":"US",
    "sg:address":"8170 S Eastern Ave",
    "sg:city":"Las Vegas",
    "sg:classifiers":[
        {
            "category":"Professional",
            "subcategory":"Business Services",
            "type":"Services"
        }
    ],
    "sg:phone":"+1 702 269 7001",
    "sg:postcode":"89123",
    "sg:province":"NV",
    "wof:name":"Gmj Interiors",
    "wof:placetype":"venue"
},
  "geometry": {"coordinates":[-115.118191,36.040773],"type":"Point"}
}