{
  "type": "Feature",
  "properties": {
    "iso:country":"US",
    "sg:address":"2301 Norway Maple St",
    "sg:city":"Las Vegas",
    "sg:classifiers":[
        {
            "category":"Building & Trades",
            "subcategory":"Construction",
            "type":"Services"
        }
    ],
    "sg:phone":"+1 702 360 6464",
    "sg:postcode":"89117",
    "sg:province":"NV",
    "sg:tags":[
        "home",
        "builder"
    ],
    "wof:name":"Plush Home",
    "wof:placetype":"venue"
},
  "geometry": {"coordinates":[-115.274812,36.1468],"type":"Point"}
}