{
  "type": "Feature",
  "properties": {
    "iso:country":"US",
    "sg:address":"5301 Longley Ln",
    "sg:city":"Reno",
    "sg:classifiers":[
        {
            "category":"Wholesale",
            "subcategory":"Office Equipment",
            "type":"Manufacturing & Wholesale Goods"
        },
        {
            "category":"Manufacturing",
            "subcategory":"Tools & Machinery",
            "type":"Manufacturing & Wholesale Goods"
        }
    ],
    "sg:phone":"+1 775 786 1584",
    "sg:postcode":"89511",
    "sg:province":"NV",
    "sg:tags":[
        "register",
        "mfg",
        "cash",
        "calculating",
        "supply"
    ],
    "wof:name":"Micros Systems Inc",
    "wof:placetype":"venue"
},
  "geometry": {"coordinates":[-119.76661199999999,39.471615],"type":"Point"}
}