{
  "type": "Feature",
  "properties": {
    "iso:country":"US",
    "sg:address":"2290 Corporate Cir",
    "sg:city":"Henderson",
    "sg:classifiers":[
        {
            "category":"Education",
            "subcategory":"Vocational School",
            "type":"Public Place"
        }
    ],
    "sg:phone":"+1 702 269 7600",
    "sg:postcode":"89074",
    "sg:province":"NV",
    "wof:name":"Computer-Ed Institute",
    "wof:placetype":"venue"
},
  "geometry": {"coordinates":[-115.089766,36.026119],"type":"Point"}
}