{
  "type": "Feature",
  "properties": {
    "iso:country":"US",
    "sg:address":"2245 N Decatur Boulevard",
    "sg:city":"Las Vegas",
    "sg:classifiers":[
        {
            "category":"Arena",
            "subcategory":"Sports Club",
            "type":"Entertainment"
        }
    ],
    "sg:phone":"+1 702 638 7228",
    "sg:postcode":"89108",
    "sg:province":"NV",
    "sg:tags":[
        "martial art"
    ],
    "wof:name":"Bob Chaney's Karate & Kick Boxing Studio",
    "wof:placetype":"venue"
},
  "geometry": {"coordinates":[-115.20615,36.199433],"type":"Point"}
}