{
  "type": "Feature",
  "properties": {
    "iso:country":"US",
    "sg:address":"805 Kietzke Ln",
    "sg:city":"Reno",
    "sg:classifiers":[
        {
            "category":"Restaurant",
            "type":"Food & Drink"
        }
    ],
    "sg:menulink":"http://www.allmenus.com/nv/reno-southeast/181845-wendys/menu/",
    "sg:phone":"+1 775 322 2247",
    "sg:postcode":"89502",
    "sg:province":"NV",
    "sg:tags":[
        "burger",
        "american",
        "soup"
    ],
    "wof:name":"Wendy's",
    "wof:placetype":"venue"
},
  "geometry": {"coordinates":[-119.789867,39.518621],"type":"Point"}
}