{
  "type": "Feature",
  "properties": {
    "iso:country":"US",
    "sg:address":"321 E Pecos Way",
    "sg:city":"Las Vegas",
    "sg:classifiers":[
        {
            "category":"Health Services",
            "subcategory":"Chiropractor",
            "type":"Services"
        }
    ],
    "sg:phone":"+1 702 263 4925",
    "sg:postcode":"89121",
    "sg:province":"NV",
    "wof:name":"Ken Bahoora DC",
    "wof:placetype":"venue"
},
  "geometry": {"coordinates":[-115.100716,36.134017],"type":"Point"}
}