{
  "type": "Feature",
  "properties": {
    "iso:country":"US",
    "sg:address":"2095 Village Center Cir",
    "sg:city":"Las Vegas",
    "sg:classifiers":[
        {
            "category":"Health Services",
            "subcategory":"Chiropractor",
            "type":"Services"
        }
    ],
    "sg:phone":"+1 702 363 2082",
    "sg:postcode":"89134",
    "sg:province":"NV",
    "sg:website":"www.drdonnawoo.com",
    "wof:name":"Woo Donna W DC Atc",
    "wof:placetype":"venue"
},
  "geometry": {"coordinates":[-115.304001,36.189999],"type":"Point"}
}