{
  "type": "Feature",
  "properties": {
    "iso:country":"US",
    "sg:address":"5590 Painted Mirage Rd",
    "sg:city":"Las Vegas",
    "sg:classifiers":[
        {
            "category":"Health Services",
            "subcategory":"Dentist",
            "type":"Services"
        }
    ],
    "sg:phone":"+1 702 658 8008",
    "sg:postcode":"89149",
    "sg:province":"NV",
    "sg:website":"www.michaelpwebbersondds.com",
    "wof:name":"Michael P Webberson DDS",
    "wof:placetype":"venue"
},
  "geometry": {"coordinates":[-115.256421,36.262762],"type":"Point"}
}