{
  "type": "Feature",
  "properties": {
    "iso:country":"US",
    "sg:address":"4003 Ventura Way",
    "sg:city":"Las Vegas",
    "sg:classifiers":[
        {
            "category":"Professional",
            "subcategory":"Computer Services",
            "type":"Services"
        }
    ],
    "sg:phone":"+1 702 898 4565",
    "sg:postcode":"89121",
    "sg:province":"NV",
    "sg:tags":[
        "website",
        "design"
    ],
    "wof:name":"Showcase Studios",
    "wof:placetype":"venue"
},
  "geometry": {"coordinates":[-115.085747,36.103792],"type":"Point"}
}