{
  "type": "Feature",
  "properties": {
    "iso:country":"US",
    "sg:address":"4300 Kay Pl",
    "sg:city":"Las Vegas",
    "sg:classifiers":[
        {
            "category":"Food & Beverages",
            "subcategory":"Specialty",
            "type":"Retail Goods"
        }
    ],
    "sg:phone":"+1 702 250 6408",
    "sg:postcode":"89107",
    "sg:province":"NV",
    "wof:name":"Herbal Star International",
    "wof:placetype":"venue"
},
  "geometry": {"coordinates":[-115.199875,36.165389],"type":"Point"}
}