{
  "type": "Feature",
  "properties": {
    "iso:country":"US",
    "sg:address":"514 S Martin L King Boulevard",
    "sg:city":"Las Vegas",
    "sg:classifiers":[
        {
            "category":"Personal",
            "subcategory":"Barber",
            "type":"Services"
        }
    ],
    "sg:phone":"+1 702 399 3233",
    "sg:postcode":"89106",
    "sg:province":"NV",
    "wof:name":"House of Fades",
    "wof:placetype":"venue"
},
  "geometry": {"coordinates":[-115.160951,36.165826],"type":"Point"}
}