{
  "type": "Feature",
  "properties": {
    "iso:country":"US",
    "sg:address":"595 Booth St",
    "sg:city":"Reno",
    "sg:classifiers":[
        {
            "category":"Banks & Credit Unions",
            "subcategory":"Bank",
            "type":"Services"
        }
    ],
    "sg:phone":"+1 775 688 4940",
    "sg:postcode":"89509",
    "sg:province":"NV",
    "sg:tags":[
        "federal",
        "savings",
        "institution"
    ],
    "wof:name":"Wells Fargo",
    "wof:placetype":"venue"
},
  "geometry": {"coordinates":[-119.826515,39.516409],"type":"Point"}
}