{
  "type": "Feature",
  "properties": {
    "iso:country":"US",
    "sg:address":"6650 Vegas Dr",
    "sg:city":"Las Vegas",
    "sg:classifiers":[
        {
            "category":"Fast Food",
            "type":"Food & Drink"
        },
        {
            "category":"Restaurant",
            "type":"Food & Drink"
        }
    ],
    "sg:phone":"+1 702 631 3600",
    "sg:postcode":"89108",
    "sg:province":"NV",
    "sg:tags":[
        "mexican"
    ],
    "wof:name":"Roberto's Taco Shop",
    "wof:placetype":"venue"
},
  "geometry": {"coordinates":[-115.239998,36.188599],"type":"Point"}
}