{
  "type": "Feature",
  "properties": {
    "iso:country":"US",
    "sg:address":"5310 W Flamingo Rd",
    "sg:city":"Las Vegas",
    "sg:classifiers":[
        {
            "category":"Building & Trades",
            "subcategory":"Plumbing",
            "type":"Services"
        }
    ],
    "sg:phone":"+1 702 368 7540",
    "sg:postcode":"89103",
    "sg:province":"NV",
    "sg:tags":[
        "plumbing",
        "contractor"
    ],
    "wof:name":"Halcyon Plumbing",
    "wof:placetype":"venue"
},
  "geometry": {"coordinates":[-115.213458,36.115241],"type":"Point"}
}