{
  "type": "Feature",
  "properties": {
    "iso:country":"US",
    "sg:address":"2494 Hopi Ct",
    "sg:city":"Reno",
    "sg:classifiers":[
        {
            "category":"Retail",
            "subcategory":"Repair Shop",
            "type":"Services"
        }
    ],
    "sg:phone":"+1 775 677 2125",
    "sg:postcode":"89506",
    "sg:province":"NV",
    "wof:name":"Anytime Lock & Key",
    "wof:placetype":"venue"
},
  "geometry": {"coordinates":[-119.864965,39.599675],"type":"Point"}
}