{
  "type": "Feature",
  "properties": {
    "iso:country":"US",
    "sg:address":"1520 State Hwy 372",
    "sg:city":"Pahrump",
    "sg:classifiers":[
        {
            "category":"Personal",
            "subcategory":"Beauty Salon",
            "type":"Services"
        }
    ],
    "sg:phone":"+1 775 751 7663",
    "sg:postcode":"89048",
    "sg:province":"NV",
    "wof:name":"Don Michael Salon",
    "wof:placetype":"venue"
},
  "geometry": {"coordinates":[-115.99109799999999,36.206498],"type":"Point"}
}