{
  "type": "Feature",
  "properties": {
    "iso:country":"US",
    "sg:address":"4490 Spring Mountain Rd",
    "sg:city":"Las Vegas",
    "sg:classifiers":[
        {
            "category":"Restaurant",
            "type":"Food & Drink"
        }
    ],
    "sg:phone":"+1 702 221 2271",
    "sg:postcode":"89102",
    "sg:province":"NV",
    "wof:name":"Green Room",
    "wof:placetype":"venue"
},
  "geometry": {"coordinates":[-115.199478,36.1264],"type":"Point"}
}