{
  "type": "Feature",
  "properties": {
    "iso:country":"US",
    "sg:address":"5725 Range Rd",
    "sg:city":"Las Vegas",
    "sg:classifiers":[
        {
            "category":"Manufacturing",
            "subcategory":"Food",
            "type":"Manufacturing & Wholesale Goods"
        }
    ],
    "sg:phone":"+1 702 651 0997",
    "sg:postcode":"89115",
    "sg:province":"NV",
    "sg:tags":[
        "repair",
        "mfg"
    ],
    "wof:name":"Baker Commodities Inc",
    "wof:placetype":"venue"
},
  "geometry": {"coordinates":[-115.054613,36.262129],"type":"Point"}
}