{
  "type": "Feature",
  "properties": {
    "iso:country":"US",
    "sg:address":"4130 S Sandhill Rd",
    "sg:city":"Las Vegas",
    "sg:classifiers":[
        {
            "category":"Restaurant",
            "type":"Food & Drink"
        }
    ],
    "sg:phone":"+1 702 436 4793",
    "sg:postcode":"89121",
    "sg:province":"NV",
    "wof:name":"My Pueblo Pizza",
    "wof:placetype":"venue"
},
  "geometry": {"coordinates":[-115.091813,36.113175],"type":"Point"}
}