{
  "type": "Feature",
  "properties": {
    "iso:country":"US",
    "sg:address":"54 S Wells Ave",
    "sg:city":"Reno",
    "sg:classifiers":[
        {
            "category":"Shopping",
            "type":"Retail Goods"
        }
    ],
    "sg:phone":"+1 775 324 0809",
    "sg:postcode":"89502",
    "sg:province":"NV",
    "sg:tags":[
        "telephone",
        "cellular"
    ],
    "wof:name":"Wireless & More",
    "wof:placetype":"venue"
},
  "geometry": {"coordinates":[-119.802923,39.525986],"type":"Point"}
}