{
  "type": "Feature",
  "properties": {
    "iso:country":"US",
    "sg:address":"4955 E Craig Rd #3",
    "sg:city":"Las Vegas",
    "sg:classifiers":[
        {
            "category":"Restaurant",
            "type":"Food & Drink"
        }
    ],
    "sg:phone":"+1 702 632 3046",
    "sg:postcode":"89115",
    "sg:province":"NV",
    "wof:name":"Comfort Zone Cafe",
    "wof:placetype":"venue"
},
  "geometry": {"coordinates":[-115.065393,36.24008],"type":"Point"}
}