{
  "type": "Feature",
  "properties": {
    "iso:country":"US",
    "sg:address":"1010 Russell Way",
    "sg:city":"Sparks",
    "sg:classifiers":[
        {
            "category":"Building & Trades",
            "subcategory":"Pest Control",
            "type":"Services"
        }
    ],
    "sg:phone":"+1 775 378 7174",
    "sg:postcode":"89431",
    "sg:province":"NV",
    "wof:name":"Archer Pest Management",
    "wof:placetype":"venue"
},
  "geometry": {"coordinates":[-119.756094,39.548141],"type":"Point"}
}