{
  "type": "Feature",
  "properties": {
    "iso:country":"US",
    "sg:address":"529 Moran St",
    "sg:city":"Reno",
    "sg:classifiers":[
        {
            "category":"Professional",
            "subcategory":"Accounting & Tax Preparation",
            "type":"Services"
        }
    ],
    "sg:phone":"+1 775 329 1502",
    "sg:postcode":"89502",
    "sg:province":"NV",
    "wof:name":"R B and Co",
    "wof:placetype":"venue"
},
  "geometry": {"coordinates":[-119.802135,39.521335],"type":"Point"}
}