{
  "type": "Feature",
  "properties": {
    "iso:country":"US",
    "sg:address":"4186 Walhaven Ct",
    "sg:city":"Las Vegas",
    "sg:classifiers":[
        {
            "category":"Personal",
            "type":"Services"
        }
    ],
    "sg:phone":"+1 702 871 9522",
    "sg:postcode":"89103",
    "sg:province":"NV",
    "wof:name":"Reflexology of Las Vegas",
    "wof:placetype":"venue"
},
  "geometry": {"coordinates":[-115.235292,36.112675],"type":"Point"}
}