{
  "type": "Feature",
  "properties": {
    "iso:country":"US",
    "sg:address":"2660 Idlewild Dr",
    "sg:city":"Reno",
    "sg:classifiers":[
        {
            "category":"Professional",
            "subcategory":"Business Services",
            "type":"Services"
        }
    ],
    "sg:phone":"+1 775 322 1593",
    "sg:postcode":"89509",
    "sg:province":"NV",
    "wof:name":"T & P Enterprises Inc",
    "wof:placetype":"venue"
},
  "geometry": {"coordinates":[-119.84225,39.517231],"type":"Point"}
}