{
  "type": "Feature",
  "properties": {
    "iso:country":"US",
    "sg:address":"8048 Earl Grey Ct",
    "sg:city":"Las Vegas",
    "sg:classifiers":[
        {
            "category":"Shopping",
            "subcategory":"Gifts & Souvenirs",
            "type":"Retail Goods"
        }
    ],
    "sg:phone":"+1 702 338 3163",
    "sg:postcode":"89117",
    "sg:province":"NV",
    "wof:name":"Lucky Star Oriental Gift",
    "wof:placetype":"venue"
},
  "geometry": {"coordinates":[-115.26668,36.131235],"type":"Point"}
}