{
  "type": "Feature",
  "properties": {
    "iso:country":"US",
    "sg:address":"5565 S Decatur Blvd",
    "sg:city":"Las Vegas",
    "sg:classifiers":[
        {
            "category":"Building & Trades",
            "subcategory":"Construction",
            "type":"Services"
        }
    ],
    "sg:phone":"+1 702 326 0600",
    "sg:postcode":"89118",
    "sg:province":"NV",
    "sg:tags":[
        "contractor"
    ],
    "wof:name":"New Century Lawns",
    "wof:placetype":"venue"
},
  "geometry": {"coordinates":[-115.207991,36.089153],"type":"Point"}
}