{
  "type": "Feature",
  "properties": {
    "iso:country":"US",
    "sg:address":"633 E St",
    "sg:city":"Hawthorne",
    "sg:classifiers":[
        {
            "category":"Bars & Pubs",
            "type":"Food & Drink"
        }
    ],
    "sg:phone":"+1 775 945 5752",
    "sg:postcode":"89415",
    "sg:province":"NV",
    "wof:name":"Sierra Station",
    "wof:placetype":"venue"
},
  "geometry": {"coordinates":[-118.624707,38.527088],"type":"Point"}
}