{
  "type": "Feature",
  "properties": {
    "iso:country":"US",
    "sg:address":"1002 N Rancho Dr",
    "sg:city":"Las Vegas",
    "sg:classifiers":[
        {
            "category":"Restaurant",
            "type":"Food & Drink"
        }
    ],
    "sg:phone":"+1 702 631 5944",
    "sg:postcode":"89106",
    "sg:province":"NV",
    "wof:name":"LA Choza",
    "wof:placetype":"venue"
},
  "geometry": {"coordinates":[-115.180224,36.182293],"type":"Point"}
}