{
  "type": "Feature",
  "properties": {
    "iso:country":"US",
    "sg:address":"2600 Hampton Rd",
    "sg:city":"Henderson",
    "sg:classifiers":[
        {
            "category":"Restaurant",
            "type":"Food & Drink"
        }
    ],
    "sg:phone":"+1 702 617 5780",
    "sg:postcode":"89052",
    "sg:province":"NV",
    "wof:name":"Buckman's",
    "wof:placetype":"venue"
},
  "geometry": {"coordinates":[-115.103753,35.954062],"type":"Point"}
}