{
  "type": "Feature",
  "properties": {
    "iso:country":"US",
    "sg:address":"4431 N Rancho Drive",
    "sg:city":"Las Vegas",
    "sg:classifiers":[
        {
            "category":"Autos & Motor Vehicles",
            "subcategory":"Auto Supplies",
            "type":"Retail Goods"
        }
    ],
    "sg:phone":"+1 702 645 5330",
    "sg:postcode":"89130",
    "sg:province":"NV",
    "sg:tags":[
        "tire"
    ],
    "sg:website":"www.discounttire.com/makeappt",
    "wof:name":"Discount Tire",
    "wof:placetype":"venue"
},
  "geometry": {"coordinates":[-115.234448,36.240687],"type":"Point"}
}