{
  "type": "Feature",
  "properties": {
    "iso:country":"US",
    "sg:address":"1414 Industrial Rd",
    "sg:city":"Las Vegas",
    "sg:classifiers":[
        {
            "category":"Building & Trades",
            "subcategory":"Construction",
            "type":"Services"
        }
    ],
    "sg:phone":"+1 702 656 2333",
    "sg:postcode":"89102",
    "sg:province":"NV",
    "sg:tags":[
        "pipe",
        "line",
        "contractor"
    ],
    "wof:name":"Vazzana Underground Constr",
    "wof:placetype":"venue"
},
  "geometry": {"coordinates":[-115.158278,36.153813],"type":"Point"}
}