{
  "type": "Feature",
  "properties": {
    "iso:country":"US",
    "sg:address":"8275 S Eastern Avenue",
    "sg:city":"Las Vegas",
    "sg:classifiers":[
        {
            "category":"Professional",
            "subcategory":"Accounting & Tax Preparation",
            "type":"Services"
        }
    ],
    "sg:phone":"+1 702 990 8804",
    "sg:postcode":"89123",
    "sg:province":"NV",
    "sg:tags":[
        "accountant"
    ],
    "wof:name":"Moore Robert A CPA",
    "wof:placetype":"venue"
},
  "geometry": {"coordinates":[-115.118233,36.039004],"type":"Point"}
}