{
  "type": "Feature",
  "properties": {
    "iso:country":"US",
    "sg:address":"112 Diamond Lady Ln",
    "sg:city":"Spring Creek",
    "sg:classifiers":[
        {
            "category":"Building & Trades",
            "subcategory":"Plumbing",
            "type":"Services"
        }
    ],
    "sg:phone":"+1 775 753 6323",
    "sg:postcode":"89815",
    "sg:province":"NV",
    "sg:tags":[
        "septic"
    ],
    "wof:name":"Cunningham Pumping Svc",
    "wof:placetype":"venue"
},
  "geometry": {"coordinates":[-115.52678,40.717143],"type":"Point"}
}