{
  "type": "Feature",
  "properties": {
    "iso:country":"US",
    "sg:address":"6605 Las Vegas Blvd S",
    "sg:city":"Las Vegas",
    "sg:classifiers":[
        {
            "category":"Shopping Center",
            "type":"Public Place"
        }
    ],
    "sg:phone":"+1 702 269 5001",
    "sg:postcode":"89119",
    "sg:province":"NV",
    "sg:website":"www.townsquarelasvegas.com",
    "wof:name":"Town Square Las Vegas",
    "wof:placetype":"venue"
},
  "geometry": {"coordinates":[-115.172236,36.068549],"type":"Point"}
}