{
  "type": "Feature",
  "properties": {
    "iso:country":"US",
    "sg:address":"925 W Broadway",
    "sg:city":"Lovelock",
    "sg:classifiers":[
        {
            "category":"Bars & Pubs",
            "type":"Food & Drink"
        }
    ],
    "sg:phone":"+1 775 273 7015",
    "sg:postcode":"89419",
    "sg:province":"NV",
    "wof:name":"Longhorn Saloon",
    "wof:placetype":"venue"
},
  "geometry": {"coordinates":[-118.474038,40.179099],"type":"Point"}
}