{
  "type": "Feature",
  "properties": {
    "iso:country":"US",
    "sg:address":"13924 Lear Blvd",
    "sg:city":"Reno",
    "sg:classifiers":[
        {
            "category":"Professional",
            "type":"Services"
        }
    ],
    "sg:phone":"+1 775 972 4193",
    "sg:postcode":"89506",
    "sg:province":"NV",
    "sg:tags":[
        "writer"
    ],
    "wof:name":"Www.Comedyghostwriters.Com",
    "wof:placetype":"venue"
},
  "geometry": {"coordinates":[-119.88107100000001,39.643972],"type":"Point"}
}