{
  "type": "Feature",
  "properties": {
    "iso:country":"US",
    "sg:address":"3015 S Jones Blvd",
    "sg:city":"Las Vegas",
    "sg:classifiers":[
        {
            "category":"Retail",
            "subcategory":"Auto Rental",
            "type":"Services"
        }
    ],
    "sg:phone":"+1 702 253 1856",
    "sg:postcode":"89146",
    "sg:province":"NV",
    "sg:tags":[
        "trailer",
        "utility"
    ],
    "wof:name":"West Sahara Mini Storage",
    "wof:placetype":"venue"
},
  "geometry": {"coordinates":[-115.225111,36.133163],"type":"Point"}
}