{
  "type": "Feature",
  "properties": {
    "iso:country":"US",
    "sg:address":"4001 S Decatur Blvd Ste 9",
    "sg:city":"Las Vegas",
    "sg:classifiers":[
        {
            "category":"Shopping",
            "subcategory":"Florist",
            "type":"Retail Goods"
        }
    ],
    "sg:phone":"+1 702 579 3984",
    "sg:postcode":"89103",
    "sg:province":"NV",
    "wof:name":"Foxtail Plant & Floral",
    "wof:placetype":"venue"
},
  "geometry": {"coordinates":[-115.20831,36.117086],"type":"Point"}
}