{
  "type": "Feature",
  "properties": {
    "iso:country":"US",
    "sg:address":"940 Cornell Ave",
    "sg:city":"Lovelock",
    "sg:classifiers":[
        {
            "category":"Shopping",
            "subcategory":"Gifts & Souvenirs",
            "type":"Retail Goods"
        }
    ],
    "sg:phone":"+1 775 273 0702",
    "sg:postcode":"89419",
    "sg:province":"NV",
    "sg:tags":[
        "shop"
    ],
    "wof:name":"Gift Box",
    "wof:placetype":"venue"
},
  "geometry": {"coordinates":[-118.474942,40.179736],"type":"Point"}
}