{
  "type": "Feature",
  "properties": {
    "iso:country":"US",
    "sg:address":"457 Court St",
    "sg:city":"Reno",
    "sg:classifiers":[
        {
            "category":"Social Services",
            "type":"Services"
        }
    ],
    "sg:phone":"+1 775 322 7717",
    "sg:postcode":"89501",
    "sg:province":"NV",
    "sg:tags":[
        "counselor",
        "marriage",
        "family"
    ],
    "wof:name":"Brie Arnette",
    "wof:placetype":"venue"
},
  "geometry": {"coordinates":[-119.81737699999999,39.522607],"type":"Point"}
}