{
  "type": "Feature",
  "properties": {
    "iso:country":"US",
    "sg:address":"601 S 10th St",
    "sg:city":"Las Vegas",
    "sg:classifiers":[
        {
            "category":"Banks & Credit Unions",
            "subcategory":"Bank",
            "type":"Services"
        }
    ],
    "sg:phone":"+1 702 362 2002",
    "sg:postcode":"89101",
    "sg:province":"NV",
    "sg:tags":[
        "financing"
    ],
    "wof:name":"Wind River Financial LLC",
    "wof:placetype":"venue"
},
  "geometry": {"coordinates":[-115.139537,36.159803],"type":"Point"}
}