{
  "type": "Feature",
  "properties": {
    "iso:country":"US",
    "sg:address":"9301 W Sahara Ave",
    "sg:city":"Las Vegas",
    "sg:classifiers":[
        {
            "category":"Restaurant",
            "type":"Food & Drink"
        }
    ],
    "sg:phone":"+1 702 233 9090",
    "sg:postcode":"89117",
    "sg:province":"NV",
    "wof:name":"Zambonies Pizza",
    "wof:placetype":"venue"
},
  "geometry": {"coordinates":[-115.29765,36.144419],"type":"Point"}
}