{
  "type": "Feature",
  "properties": {
    "iso:country":"US",
    "sg:address":"3211 Builders Ave",
    "sg:city":"Las Vegas",
    "sg:classifiers":[
        {
            "category":"Home & Garden",
            "subcategory":"Furniture",
            "type":"Retail Goods"
        }
    ],
    "sg:phone":"+1 702 457 6387",
    "sg:postcode":"89101",
    "sg:province":"NV",
    "sg:tags":[
        "sales"
    ],
    "sg:website":"www.ofusa.com",
    "wof:name":"Office Furniture USA",
    "wof:placetype":"venue"
},
  "geometry": {"coordinates":[-115.103081,36.160777],"type":"Point"}
}