{
  "type": "Feature",
  "properties": {
    "iso:country":"US",
    "sg:address":"1295 E Moana Ln",
    "sg:city":"Reno",
    "sg:classifiers":[
        {
            "category":"Personal",
            "subcategory":"Beauty Salon",
            "type":"Services"
        }
    ],
    "sg:phone":"+1 775 824 0100",
    "sg:postcode":"89502",
    "sg:province":"NV",
    "sg:tags":[
        "hair",
        "stylist"
    ],
    "wof:name":"Total Beauty Salon",
    "wof:placetype":"venue"
},
  "geometry": {"coordinates":[-119.780972,39.492962],"type":"Point"}
}