{
  "type": "Feature",
  "properties": {
    "iso:country":"US",
    "sg:address":"3704 E Owens Ave",
    "sg:city":"North Las Vegas",
    "sg:classifiers":[
        {
            "category":"Bars & Pubs",
            "type":"Food & Drink"
        }
    ],
    "sg:phone":"+1 702 399 4722",
    "sg:postcode":"89030",
    "sg:province":"NV",
    "sg:tags":[
        "saloon"
    ],
    "wof:name":"Pecos Saloon",
    "wof:placetype":"venue"
},
  "geometry": {"coordinates":[-115.093717,36.188325],"type":"Point"}
}