{
  "type": "Feature",
  "properties": {
    "iso:country":"US",
    "sg:address":"275 W Atlantic Avenue Apt A",
    "sg:city":"Henderson",
    "sg:classifiers":[
        {
            "category":"Real Estate",
            "subcategory":"Real Estate Operator",
            "type":"Services"
        }
    ],
    "sg:phone":"+1 702 565 7028",
    "sg:postcode":"89015",
    "sg:province":"NV",
    "sg:tags":[
        "apartment"
    ],
    "wof:name":"Apartments In Henderson",
    "wof:placetype":"venue"
},
  "geometry": {"coordinates":[-114.990605,36.033136],"type":"Point"}
}