{
  "type": "Feature",
  "properties": {
    "iso:country":"US",
    "sg:address":"220 Edison Way",
    "sg:city":"Reno",
    "sg:classifiers":[
        {
            "category":"Organizations",
            "subcategory":"Religious Organization",
            "type":"Services"
        }
    ],
    "sg:phone":"+1 775 856 1110",
    "sg:postcode":"89502",
    "sg:province":"NV",
    "sg:tags":[
        "church"
    ],
    "sg:website":"www.calvarychapelreno.org",
    "wof:name":"Calvary Chapel Of Reno Sparks",
    "wof:placetype":"venue"
},
  "geometry": {"coordinates":[-119.753901,39.510209],"type":"Point"}
}