{
  "type": "Feature",
  "properties": {
    "iso:country":"US",
    "sg:address":"1129 Hidden Mist St",
    "sg:city":"Henderson",
    "sg:classifiers":[
        {
            "category":"Professional",
            "subcategory":"Business Services",
            "type":"Services"
        }
    ],
    "sg:phone":"+1 702 269 7628",
    "sg:postcode":"89052",
    "sg:province":"NV",
    "wof:name":"Dahawks Enterprises Inc",
    "wof:placetype":"venue"
},
  "geometry": {"coordinates":[-115.094956,35.987946],"type":"Point"}
}