{
  "type": "Feature",
  "properties": {
    "iso:country":"US",
    "sg:address":"3612 Mount Vernon Ave",
    "sg:city":"Las Vegas",
    "sg:classifiers":[
        {
            "category":"Real Estate",
            "subcategory":"Real Estate Agent",
            "type":"Services"
        }
    ],
    "sg:phone":"+1 702 399 0051",
    "sg:postcode":"89121",
    "sg:province":"NV",
    "wof:name":"Appraisal Shoppe",
    "wof:placetype":"venue"
},
  "geometry": {"coordinates":[-115.094408,36.12204],"type":"Point"}
}