{
  "type": "Feature",
  "properties": {
    "iso:country":"US",
    "sg:address":"7 Scarlet Cir",
    "sg:city":"Carson City",
    "sg:classifiers":[
        {
            "category":"Building & Trades",
            "subcategory":"Construction",
            "type":"Services"
        }
    ],
    "sg:phone":"+1 775 883 6479",
    "sg:postcode":"89706",
    "sg:province":"NV",
    "sg:tags":[
        "concrete",
        "contractor"
    ],
    "wof:name":"Centerpoint",
    "wof:placetype":"venue"
},
  "geometry": {"coordinates":[-119.753006,39.203824],"type":"Point"}
}