{
  "type": "Feature",
  "properties": {
    "iso:country":"US",
    "sg:address":"1973 N Nellis Blvd",
    "sg:city":"Las Vegas",
    "sg:classifiers":[
        {
            "category":"Professional",
            "subcategory":"Advertising",
            "type":"Services"
        }
    ],
    "sg:phone":"+1 702 459 4995",
    "sg:postcode":"89115",
    "sg:province":"NV",
    "sg:tags":[
        "mailing",
        "shipping"
    ],
    "wof:name":"UPS Store",
    "wof:placetype":"venue"
},
  "geometry": {"coordinates":[-115.062134,36.196227],"type":"Point"}
}