{
  "type": "Feature",
  "properties": {
    "iso:country":"US",
    "sg:address":"4821 Spring Mountain Rd",
    "sg:city":"Las Vegas",
    "sg:classifiers":[
        {
            "category":"Professional",
            "type":"Services"
        }
    ],
    "sg:phone":"+1 702 248 9690",
    "sg:postcode":"89102",
    "sg:province":"NV",
    "sg:tags":[
        "establishment"
    ],
    "wof:name":"Desert Capital",
    "wof:placetype":"venue"
},
  "geometry": {"coordinates":[-115.206122,36.126203],"type":"Point"}
}