{
  "type": "Feature",
  "properties": {
    "iso:country":"US",
    "sg:address":"3365 E Flamingo Rd Ste 4",
    "sg:city":"Las Vegas",
    "sg:classifiers":[
        {
            "category":"Health Services",
            "subcategory":"Clinic",
            "type":"Services"
        }
    ],
    "sg:phone":"+1 702 451 5434",
    "sg:postcode":"89121",
    "sg:province":"NV",
    "sg:tags":[
        "medical"
    ],
    "sg:website":"arcpointus.com/las_vegas",
    "wof:name":"arcpoint",
    "wof:placetype":"venue"
},
  "geometry": {"coordinates":[-115.101506,36.114479],"type":"Point"}
}