{
  "type": "Feature",
  "properties": {
    "iso:country":"US",
    "sg:address":"8115 Mohawk Ln",
    "sg:city":"Reno",
    "sg:classifiers":[
        {
            "category":"Social Services",
            "subcategory":"Adult Care",
            "type":"Services"
        }
    ],
    "sg:phone":"+1 775 677 8115",
    "sg:postcode":"89506",
    "sg:province":"NV",
    "sg:tags":[
        "residential"
    ],
    "wof:name":"Cloyds Care Home",
    "wof:placetype":"venue"
},
  "geometry": {"coordinates":[-119.865875,39.604675],"type":"Point"}
}