{
  "type": "Feature",
  "properties": {
    "iso:country":"US",
    "sg:address":"2975 Talbot St",
    "sg:city":"Las Vegas",
    "sg:classifiers":[
        {
            "category":"Real Estate",
            "subcategory":"Real Estate Agent",
            "type":"Services"
        },
        {
            "category":"Professional",
            "subcategory":"Business Services",
            "type":"Services"
        }
    ],
    "sg:phone":"+1 702 732 2931",
    "sg:postcode":"89169",
    "sg:province":"NV",
    "sg:tags":[
        "inspection"
    ],
    "wof:name":"Rivera Inspection Service",
    "wof:placetype":"venue"
},
  "geometry": {"coordinates":[-115.126974,36.134543],"type":"Point"}
}