{
  "type": "Feature",
  "properties": {
    "iso:country":"US",
    "sg:address":"195 N Edison Way",
    "sg:city":"Reno",
    "sg:classifiers":[
        {
            "category":"Home & Garden",
            "subcategory":"Building Materials",
            "type":"Retail Goods"
        }
    ],
    "sg:phone":"+1 775 329 4224",
    "sg:postcode":"89502",
    "sg:province":"NV",
    "sg:tags":[
        "screen",
        "window"
    ],
    "wof:name":"Silver State Screening",
    "wof:placetype":"venue"
},
  "geometry": {"coordinates":[-119.752798,39.514336],"type":"Point"}
}