{
  "type": "Feature",
  "properties": {
    "iso:country":"US",
    "sg:address":"520 East St",
    "sg:city":"Pahrump",
    "sg:classifiers":[
        {
            "category":"Parking",
            "type":"Transportation"
        }
    ],
    "sg:phone":"+1 775 537 6304",
    "sg:postcode":"89048",
    "sg:province":"NV",
    "sg:tags":[
        "garage"
    ],
    "wof:name":"Central Parking System",
    "wof:placetype":"venue"
},
  "geometry": {"coordinates":[-115.991879,36.212071],"type":"Point"}
}