{
  "type": "Feature",
  "properties": {
    "iso:country":"US",
    "sg:address":"1509 S Eastern Ave",
    "sg:city":"Las Vegas",
    "sg:classifiers":[
        {
            "category":"Professional",
            "subcategory":"Lawyer & Legal Services",
            "type":"Services"
        }
    ],
    "sg:phone":"+1 702 382 2288",
    "sg:postcode":"89104",
    "sg:province":"NV",
    "sg:tags":[
        "attorney"
    ],
    "wof:name":"Lillian Sondgeroth",
    "wof:placetype":"venue"
},
  "geometry": {"coordinates":[-115.118837,36.151765],"type":"Point"}
}