{
  "type": "Feature",
  "properties": {
    "iso:country":"US",
    "sg:address":"4131 W Oquendo Rd",
    "sg:city":"Las Vegas",
    "sg:classifiers":[
        {
            "category":"Professional",
            "subcategory":"Business Services",
            "type":"Services"
        }
    ],
    "sg:phone":"+1 702 730 1900",
    "sg:postcode":"89118",
    "sg:province":"NV",
    "sg:tags":[
        "organizing"
    ],
    "wof:name":"Garagetek",
    "wof:placetype":"venue"
},
  "geometry": {"coordinates":[-115.190722,36.082605],"type":"Point"}
}