{
  "type": "Feature",
  "properties": {
    "iso:country":"US",
    "sg:address":"7881 W Tropical Parkway",
    "sg:city":"Las Vegas",
    "sg:classifiers":[
        {
            "category":"Home & Garden",
            "subcategory":"Hardware",
            "type":"Retail Goods"
        }
    ],
    "sg:phone":"+1 702 839 5100",
    "sg:postcode":"89149",
    "sg:province":"NV",
    "sg:tags":[
        "store"
    ],
    "wof:name":"The Home Depot",
    "wof:placetype":"venue"
},
  "geometry": {"coordinates":[-115.26687699999999,36.270858],"type":"Point"}
}