{
  "type": "Feature",
  "properties": {
    "iso:country":"US",
    "sg:address":"1425 W 4th St",
    "sg:city":"Reno",
    "sg:classifiers":[
        {
            "category":"Bars & Pubs",
            "type":"Food & Drink"
        }
    ],
    "sg:phone":"+1 775 322 4779",
    "sg:postcode":"89503",
    "sg:province":"NV",
    "wof:name":"Desert Sunset Bar",
    "wof:placetype":"venue"
},
  "geometry": {"coordinates":[-119.83202300000001,39.52529],"type":"Point"}
}