{
  "type": "Feature",
  "properties": {
    "iso:country":"US",
    "sg:address":"2880 E Flamingo Rd Ste D",
    "sg:city":"Las Vegas",
    "sg:classifiers":[
        {
            "category":"Professional",
            "subcategory":"Lawyer & Legal Services",
            "type":"Services"
        }
    ],
    "sg:phone":"+1 702 734 1600",
    "sg:postcode":"89121",
    "sg:province":"NV",
    "sg:tags":[
        "personal",
        "injury"
    ],
    "wof:name":"Stoebling David & Associates",
    "wof:placetype":"venue"
},
  "geometry": {"coordinates":[-115.110001,36.115101],"type":"Point"}
}