{
  "type": "Feature",
  "properties": {
    "iso:country":"US",
    "sg:address":"3655 Las Vegas Blvd S",
    "sg:city":"Las Vegas",
    "sg:classifiers":[
        {
            "category":"Shopping",
            "type":"Retail Goods"
        }
    ],
    "sg:phone":"+1 702 943 4366",
    "sg:postcode":"89109",
    "sg:province":"NV",
    "sg:tags":[
        "spa",
        "hot",
        "tub"
    ],
    "wof:name":"Mandara Spa",
    "wof:placetype":"venue"
},
  "geometry": {"coordinates":[-115.172771,36.114256],"type":"Point"}
}