{
  "type": "Feature",
  "properties": {
    "iso:country":"US",
    "sg:address":"983 Shadow Lane",
    "sg:city":"Carson City",
    "sg:classifiers":[
        {
            "category":"Home & Garden",
            "subcategory":"Home Furnishings",
            "type":"Retail Goods"
        }
    ],
    "sg:phone":"+1 775 220 3659",
    "sg:postcode":"89705",
    "sg:province":"NV",
    "sg:tags":[
        "decor"
    ],
    "sg:website":"www.clutterbugcottage.com",
    "wof:name":"Clutterbug Cottage",
    "wof:placetype":"venue"
},
  "geometry": {"coordinates":[-119.773179,39.091645],"type":"Point"}
}