{
  "type": "Feature",
  "properties": {
    "iso:country":"US",
    "sg:address":"7555 Silverkist Ct",
    "sg:city":"Reno",
    "sg:classifiers":[
        {
            "category":"Restaurant",
            "type":"Food & Drink"
        }
    ],
    "sg:phone":"+1 775 972 5533",
    "sg:postcode":"89506",
    "sg:province":"NV",
    "wof:name":"Cromwell Patron",
    "wof:placetype":"venue"
},
  "geometry": {"coordinates":[-119.89462899999999,39.635865],"type":"Point"}
}