{
  "type": "Feature",
  "properties": {
    "iso:country":"US",
    "sg:address":"4969 Energy Way",
    "sg:city":"Reno",
    "sg:classifiers":[
        {
            "category":"Manufacturing",
            "subcategory":"Paper Products",
            "type":"Manufacturing & Wholesale Goods"
        }
    ],
    "sg:phone":"+1 775 856 2444",
    "sg:postcode":"89502",
    "sg:province":"NV",
    "sg:tags":[
        "fiber"
    ],
    "wof:name":"U S Cotton LLC",
    "wof:placetype":"venue"
},
  "geometry": {"coordinates":[-119.75843399999999,39.505744],"type":"Point"}
}