{
  "type": "Feature",
  "properties": {
    "iso:country":"US",
    "sg:address":"2695 Mill St",
    "sg:city":"Reno",
    "sg:classifiers":[
        {
            "category":"Professional",
            "subcategory":"Advertising",
            "type":"Services"
        }
    ],
    "sg:phone":"+1 775 324 2525",
    "sg:postcode":"89502",
    "sg:province":"NV",
    "sg:tags":[
        "printing",
        "mailing"
    ],
    "wof:name":"Panda Inc",
    "wof:placetype":"venue"
},
  "geometry": {"coordinates":[-119.777766,39.517833],"type":"Point"}
}