{
  "type": "Feature",
  "properties": {
    "iso:country":"US",
    "sg:address":"4343 N Rancho Dr",
    "sg:city":"Las Vegas",
    "sg:classifiers":[
        {
            "category":"Building & Trades",
            "subcategory":"Landscaping Services",
            "type":"Services"
        }
    ],
    "sg:phone":"+1 702 255 4868",
    "sg:postcode":"89130",
    "sg:province":"NV",
    "sg:tags":[
        "landscape",
        "contractor"
    ],
    "wof:name":"TNT Landscape",
    "wof:placetype":"venue"
},
  "geometry": {"coordinates":[-115.227778,36.234194],"type":"Point"}
}