{
  "type": "Feature",
  "properties": {
    "iso:country":"US",
    "sg:address":"9513 Spanish Steps Ln",
    "sg:city":"Las Vegas",
    "sg:classifiers":[
        {
            "category":"Home & Garden",
            "subcategory":"Building Materials",
            "type":"Retail Goods"
        }
    ],
    "sg:phone":"+1 702 382 7528",
    "sg:postcode":"89117",
    "sg:province":"NV",
    "wof:name":"Builders Emporium",
    "wof:placetype":"venue"
},
  "geometry": {"coordinates":[-115.304157,36.155658],"type":"Point"}
}