{
  "type": "Feature",
  "properties": {
    "iso:country":"US",
    "sg:address":"165 W Liberty St",
    "sg:city":"Reno",
    "sg:classifiers":[
        {
            "category":"Professional",
            "subcategory":"Lawyer & Legal Services",
            "type":"Services"
        }
    ],
    "sg:phone":"+1 775 333 0300",
    "sg:postcode":"89501",
    "sg:province":"NV",
    "sg:tags":[
        "attorney"
    ],
    "wof:name":"Avansino Melarkey Knobel",
    "wof:placetype":"venue"
},
  "geometry": {"coordinates":[-119.813194,39.521565],"type":"Point"}
}