{
  "type": "Feature",
  "properties": {
    "iso:country":"US",
    "sg:address":"300 Brinkby Ave",
    "sg:city":"Reno",
    "sg:classifiers":[
        {
            "category":"Health Services",
            "subcategory":"Doctor",
            "type":"Services"
        }
    ],
    "sg:phone":"+1 775 829 9929",
    "sg:postcode":"89509",
    "sg:province":"NV",
    "wof:name":"Crowley Regina L DDS",
    "wof:placetype":"venue"
},
  "geometry": {"coordinates":[-119.800551,39.495279],"type":"Point"}
}