{
  "type": "Feature",
  "properties": {
    "iso:country":"US",
    "sg:address":"11251 S Eastern Ave",
    "sg:city":"Henderson",
    "sg:classifiers":[
        {
            "category":"Health Services",
            "subcategory":"Doctor",
            "type":"Services"
        }
    ],
    "sg:phone":"+1 702 254 1777",
    "sg:postcode":"89052",
    "sg:province":"NV",
    "sg:tags":[
        "physician",
        "surgeon"
    ],
    "wof:name":"Fertility Center Of Las Vegas",
    "wof:placetype":"venue"
},
  "geometry": {"coordinates":[-115.101052,35.986869],"type":"Point"}
}