{
  "type": "Feature",
  "properties": {
    "iso:country":"US",
    "sg:address":"2941 Via Meridiana",
    "sg:city":"Henderson",
    "sg:classifiers":[
        {
            "category":"Professional",
            "subcategory":"Management & Consulting",
            "type":"Services"
        }
    ],
    "sg:phone":"+1 702 407 7735",
    "sg:postcode":"89052",
    "sg:province":"NV",
    "sg:tags":[
        "consultant",
        "business"
    ],
    "wof:name":"Template Consulting Group LLC",
    "wof:placetype":"venue"
},
  "geometry": {"coordinates":[-115.115508,35.986988],"type":"Point"}
}