{
  "type": "Feature",
  "properties": {
    "iso:country":"US",
    "sg:address":"10120 S Eastern Ave",
    "sg:city":"Henderson",
    "sg:classifiers":[
        {
            "category":"Banks & Credit Unions",
            "subcategory":"Investment Brokerage",
            "type":"Services"
        }
    ],
    "sg:phone":"+1 702 897 9997",
    "sg:postcode":"89052",
    "sg:province":"NV",
    "sg:tags":[
        "advisory",
        "financial"
    ],
    "wof:name":"WPG Wealth Preservation Grp",
    "wof:placetype":"venue"
},
  "geometry": {"coordinates":[-115.112787,36.006213],"type":"Point"}
}