{
  "type": "Feature",
  "properties": {
    "iso:country":"US",
    "sg:address":"4830 W Lone Mountain Rd",
    "sg:city":"Las Vegas",
    "sg:classifiers":[
        {
            "category":"Health Services",
            "subcategory":"Doctor",
            "type":"Services"
        }
    ],
    "sg:phone":"+1 702 319 7333",
    "sg:postcode":"89130",
    "sg:province":"NV",
    "sg:tags":[
        "podiatrist"
    ],
    "wof:name":"Dunetz Wayne DPM",
    "wof:placetype":"venue"
},
  "geometry": {"coordinates":[-115.207961,36.24822],"type":"Point"}
}