{
  "type": "Feature",
  "properties": {
    "iso:country":"US",
    "sg:address":"6230 S Decatur Blvd Ste.120",
    "sg:city":"Las Vegas",
    "sg:classifiers":[
        {
            "category":"Banks & Credit Unions",
            "subcategory":"Financial Services",
            "type":"Services"
        }
    ],
    "sg:phone":"+1 702 888 5626",
    "sg:postcode":"89118",
    "sg:province":"NV",
    "sg:website":"www.OnlyMoneyLoans.com",
    "wof:name":"Only Money Loans",
    "wof:placetype":"venue"
},
  "geometry": {"coordinates":[-115.207136,36.076723],"type":"Point"}
}