{
  "type": "Feature",
  "properties": {
    "iso:country":"US",
    "sg:address":"2235 E Flamingo Rd",
    "sg:city":"Las Vegas",
    "sg:classifiers":[
        {
            "category":"Manufacturing",
            "subcategory":"Signs",
            "type":"Manufacturing & Wholesale Goods"
        }
    ],
    "sg:phone":"+1 702 558 2916",
    "sg:postcode":"89119",
    "sg:province":"NV",
    "sg:tags":[
        "printing",
        "commercial",
        "specialty",
        "mfg"
    ],
    "wof:name":"Get Noticed Advertising",
    "wof:placetype":"venue"
},
  "geometry": {"coordinates":[-115.123639,36.114574],"type":"Point"}
}