{
  "type": "Feature",
  "properties": {
    "iso:country":"US",
    "sg:address":"3535 Las Vegas Boulevard S",
    "sg:city":"Las Vegas",
    "sg:classifiers":[
        {
            "category":"Building & Trades",
            "subcategory":"Construction",
            "type":"Services"
        }
    ],
    "sg:phone":"+1 702 732 7102",
    "sg:postcode":"89109",
    "sg:province":"NV",
    "sg:tags":[
        "contractor"
    ],
    "wof:name":"Engelstad Construction Company",
    "wof:placetype":"venue"
},
  "geometry": {"coordinates":[-115.17259300000001,36.11748],"type":"Point"}
}