{
  "type": "Feature",
  "properties": {
    "iso:country":"US",
    "sg:address":"7010 W Russell Rd",
    "sg:city":"Las Vegas",
    "sg:classifiers":[
        {
            "category":"Retail",
            "subcategory":"Auto Repair",
            "type":"Services"
        }
    ],
    "sg:phone":"+1 702 309 6450",
    "sg:postcode":"89113",
    "sg:province":"NV",
    "sg:tags":[
        "automobile",
        "inspection"
    ],
    "wof:name":"Smog Busters",
    "wof:placetype":"venue"
},
  "geometry": {"coordinates":[-115.242929,36.0852],"type":"Point"}
}