{
  "type": "Feature",
  "properties": {
    "iso:country":"US",
    "sg:address":"2801 Kings Way",
    "sg:city":"Las Vegas",
    "sg:classifiers":[
        {
            "category":"Utilities",
            "subcategory":"Mobile Phone",
            "type":"Services"
        }
    ],
    "sg:phone":"+1 702 365 8551",
    "sg:postcode":"89102",
    "sg:province":"NV",
    "sg:tags":[
        "telephone",
        "cellular"
    ],
    "wof:name":"Juarez Cell",
    "wof:placetype":"venue"
},
  "geometry": {"coordinates":[-115.18082800000001,36.141781],"type":"Point"}
}