{
  "type": "Feature",
  "properties": {
    "iso:country":"US",
    "sg:address":"5630 S Hualapai Way",
    "sg:city":"Las Vegas",
    "sg:classifiers":[
        {
            "category":"Bars & Pubs",
            "subcategory":"Sports Bar",
            "type":"Food & Drink"
        },
        {
            "category":"Restaurant",
            "type":"Food & Drink"
        },
        {
            "category":"Bars & Pubs",
            "subcategory":"Dive Bar",
            "type":"Food & Drink"
        }
    ],
    "sg:phone":"+1 702 243 0237",
    "sg:postcode":"89148",
    "sg:province":"NV",
    "sg:tags":[
        "traditional",
        "american"
    ],
    "sg:website":"ptstaverns.com/",
    "wof:name":"Pt's Pub",
    "wof:placetype":"venue"
},
  "geometry": {"coordinates":[-115.31526100000001,36.086378],"type":"Point"}
}