{
  "type": "Feature",
  "properties": {
    "iso:country":"US",
    "sg:address":"6315 E Lake Mead Blvd",
    "sg:city":"Las Vegas",
    "sg:classifiers":[
        {
            "category":"Retail",
            "subcategory":"Car Wash",
            "type":"Services"
        }
    ],
    "sg:phone":"+1 702 438 8787",
    "sg:postcode":"89156",
    "sg:province":"NV",
    "sg:tags":[
        "polishing",
        "washing"
    ],
    "wof:name":"Lake Mead Rainbow Car Wash",
    "wof:placetype":"venue"
},
  "geometry": {"coordinates":[-115.034572,36.195814],"type":"Point"}
}