{
  "type": "Feature",
  "properties": {
    "iso:country":"US",
    "sg:address":"2215 Renaissance Dr",
    "sg:city":"Las Vegas",
    "sg:classifiers":[
        {
            "category":"Shopping",
            "subcategory":"Discount & Variety Stores",
            "type":"Retail Goods"
        }
    ],
    "sg:phone":"+1 702 967 2464",
    "sg:postcode":"89119",
    "sg:province":"NV",
    "sg:tags":[
        "merchandise",
        "general"
    ],
    "wof:name":"Aer Sales",
    "wof:placetype":"venue"
},
  "geometry": {"coordinates":[-115.122901,36.100789],"type":"Point"}
}