{
  "type": "Feature",
  "properties": {
    "iso:country":"US",
    "sg:address":"710 E Flamingo Rd",
    "sg:city":"Las Vegas",
    "sg:classifiers":[
        {
            "category":"Personal",
            "subcategory":"Beauty Salon",
            "type":"Services"
        }
    ],
    "sg:phone":"+1 702 731 6245",
    "sg:postcode":"89119",
    "sg:province":"NV",
    "sg:tags":[
        "nail",
        "manicuring"
    ],
    "sg:website":"www.apolishednailsalon.com",
    "wof:name":"Polished Nails",
    "wof:placetype":"venue"
},
  "geometry": {"coordinates":[-115.14814699999999,36.114835],"type":"Point"}
}