{
  "type": "Feature",
  "properties": {
    "iso:country":"US",
    "sg:address":"2097 Buckeye Reef St",
    "sg:city":"Henderson",
    "sg:classifiers":[
        {
            "category":"Shopping",
            "subcategory":"Clothing, Apparel, & Fashions",
            "type":"Retail Goods"
        }
    ],
    "sg:phone":"+1 702 568 9596",
    "sg:postcode":"89002",
    "sg:province":"NV",
    "wof:name":"Bloomin Marvelous Maternity",
    "wof:placetype":"venue"
},
  "geometry": {"coordinates":[-114.934674,36.005078],"type":"Point"}
}