{
  "type": "Feature",
  "properties": {
    "iso:country":"US",
    "sg:address":"5640 Meadowood Mall Cir",
    "sg:city":"Reno",
    "sg:classifiers":[
        {
            "category":"Restaurant",
            "type":"Food & Drink"
        }
    ],
    "sg:phone":"+1 775 825 8878",
    "sg:postcode":"89502",
    "sg:province":"NV",
    "wof:name":"Fusion Express",
    "wof:placetype":"venue"
},
  "geometry": {"coordinates":[-119.7795,39.473076],"type":"Point"}
}