{
  "type": "Feature",
  "properties": {
    "iso:country":"US",
    "sg:address":"3370 Lookout Pl",
    "sg:city":"Reno",
    "sg:classifiers":[
        {
            "category":"Home & Garden",
            "subcategory":"Household Appliances",
            "type":"Retail Goods"
        }
    ],
    "sg:phone":"+1 775 324 6161",
    "sg:postcode":"89503",
    "sg:province":"NV",
    "wof:name":"A 1 Affordable Svc Co",
    "wof:placetype":"venue"
},
  "geometry": {"coordinates":[-119.83238,39.557977],"type":"Point"}
}