{
  "type": "Feature",
  "properties": {
    "iso:country":"US",
    "sg:address":"6592 N Decatur Blvd # 110",
    "sg:city":"Las Vegas",
    "sg:classifiers":[
        {
            "category":"Shopping",
            "subcategory":"Jewelry",
            "type":"Retail Goods"
        }
    ],
    "sg:phone":"+1 702 735 2378",
    "sg:postcode":"89131",
    "sg:province":"NV",
    "wof:name":"Better Jewelers",
    "wof:placetype":"venue"
},
  "geometry": {"coordinates":[-115.206619,36.277061],"type":"Point"}
}