{
  "type": "Feature",
  "properties": {
    "iso:country":"US",
    "sg:address":"10047 Sparrow Ridge Ave",
    "sg:city":"Las Vegas",
    "sg:classifiers":[
        {
            "category":"Building & Trades",
            "subcategory":"Cleaning & Sanitation",
            "type":"Services"
        }
    ],
    "sg:phone":"+1 702 804 1176",
    "sg:postcode":"89117",
    "sg:province":"NV",
    "sg:tags":[
        "butler",
        "maid"
    ],
    "wof:name":"Heavenly Maid",
    "wof:placetype":"venue"
},
  "geometry": {"coordinates":[-115.310712,36.12861],"type":"Point"}
}