{
  "type": "Feature",
  "properties": {
    "iso:country":"US",
    "sg:address":"9809 W Flamingo Rd",
    "sg:city":"Las Vegas",
    "sg:classifiers":[
        {
            "category":"Restaurant",
            "type":"Food & Drink"
        }
    ],
    "sg:phone":"+1 702 227 7238",
    "sg:postcode":"89147",
    "sg:province":"NV",
    "sg:tags":[
        "mexican"
    ],
    "sg:website":"www.zabas.com",
    "wof:name":"Zaba's Mexican Grill",
    "wof:placetype":"venue"
},
  "geometry": {"coordinates":[-115.306487,36.115042],"type":"Point"}
}