{
  "type": "Feature",
  "properties": {
    "iso:country":"US",
    "sg:address":"4885 W Tropicana Ave",
    "sg:city":"Las Vegas",
    "sg:classifiers":[
        {
            "category":"Food & Beverages",
            "subcategory":"Groceries & Convenience Stores",
            "type":"Retail Goods"
        }
    ],
    "sg:phone":"+1 702 895 7770",
    "sg:postcode":"89103",
    "sg:province":"NV",
    "wof:name":"Tropical Stop",
    "wof:placetype":"venue"
},
  "geometry": {"coordinates":[-115.20700100000001,36.1008],"type":"Point"}
}