{
  "type": "Feature",
  "properties": {
    "iso:country":"US",
    "sg:address":"7400 Las Vegas Blvd S",
    "sg:city":"Las Vegas",
    "sg:classifiers":[
        {
            "category":"Shopping",
            "subcategory":"Clothing, Apparel, & Fashions",
            "type":"Retail Goods"
        }
    ],
    "sg:phone":"+1 702 270 8772",
    "sg:postcode":"89123",
    "sg:province":"NV",
    "sg:tags":[
        "merchandise"
    ],
    "wof:name":"Coastal Cotton Co",
    "wof:placetype":"venue"
},
  "geometry": {"coordinates":[-115.172273,36.05511],"type":"Point"}
}