{
  "type": "Feature",
  "properties": {
    "iso:country":"US",
    "sg:address":"12535 Creek Crest Dr",
    "sg:city":"Reno",
    "sg:classifiers":[
        {
            "category":"Building & Trades",
            "subcategory":"Landscaping Services",
            "type":"Services"
        }
    ],
    "sg:phone":"+1 775 851 0597",
    "sg:postcode":"89511",
    "sg:province":"NV",
    "sg:tags":[
        "lawn",
        "maintenance",
        "grounds"
    ],
    "wof:name":"Beadell Lawn & Yard Mntnc",
    "wof:placetype":"venue"
},
  "geometry": {"coordinates":[-119.769025,39.420118],"type":"Point"}
}