{
  "type": "Feature",
  "properties": {
    "iso:country":"US",
    "sg:address":"3690 Grant Dr",
    "sg:city":"Reno",
    "sg:classifiers":[
        {
            "category":"Health Services",
            "subcategory":"Clinic",
            "type":"Services"
        },
        {
            "category":"Health Services",
            "subcategory":"Health Practitioner",
            "type":"Services"
        }
    ],
    "sg:phone":"+1 775 322 1616",
    "sg:postcode":"89509",
    "sg:province":"NV",
    "sg:tags":[
        "hypnotherapy",
        "specialty",
        "outpatient"
    ],
    "wof:name":"Habit Control Institute",
    "wof:placetype":"venue"
},
  "geometry": {"coordinates":[-119.803019,39.488883],"type":"Point"}
}