{
  "type": "Feature",
  "properties": {
    "iso:country":"US",
    "sg:address":"2152 Reno Hwy",
    "sg:city":"Fallon",
    "sg:classifiers":[
        {
            "category":"Real Estate",
            "subcategory":"Real Estate Agent",
            "type":"Services"
        }
    ],
    "sg:phone":"+1 775 423 6999",
    "sg:postcode":"89406",
    "sg:province":"NV",
    "wof:name":"Century 21",
    "wof:placetype":"venue"
},
  "geometry": {"coordinates":[-118.803877,39.477139],"type":"Point"}
}