{
  "type": "Feature",
  "properties": {
    "iso:country":"US",
    "sg:address":"3980 Topaz Ranch Dr",
    "sg:city":"Wellington",
    "sg:classifiers":[
        {
            "category":"Building & Trades",
            "subcategory":"Construction",
            "type":"Services"
        }
    ],
    "sg:phone":"+1 775 266 3543",
    "sg:postcode":"89444",
    "sg:province":"NV",
    "sg:tags":[
        "carpentry",
        "contractor"
    ],
    "wof:name":"Buddy Little Framers",
    "wof:placetype":"venue"
},
  "geometry": {"coordinates":[-119.499673,38.743068],"type":"Point"}
}