{
  "type": "Feature",
  "properties": {
    "iso:country":"US",
    "sg:address":"1581 Cavalry St",
    "sg:city":"Pahrump",
    "sg:classifiers":[
        {
            "category":"Home & Garden",
            "subcategory":"Home Furnishings",
            "type":"Retail Goods"
        }
    ],
    "sg:phone":"+1 775 751 3200",
    "sg:postcode":"89048",
    "sg:province":"NV",
    "wof:name":"Pahrump Lighting",
    "wof:placetype":"venue"
},
  "geometry": {"coordinates":[-115.9834,36.171495],"type":"Point"}
}