{
  "type": "Feature",
  "properties": {
    "iso:country":"US",
    "sg:address":"3290 N Rancho Dr",
    "sg:city":"Las Vegas",
    "sg:classifiers":[
        {
            "category":"Retail",
            "subcategory":"Storage",
            "type":"Services"
        }
    ],
    "sg:phone":"+1 702 656 5000",
    "sg:postcode":"89130",
    "sg:province":"NV",
    "sg:tags":[
        "self"
    ],
    "wof:name":"Rancho Self Storage Llc",
    "wof:placetype":"venue"
},
  "geometry": {"coordinates":[-115.212997,36.2187],"type":"Point"}
}