{
  "type": "Feature",
  "properties": {
    "iso:country":"US",
    "sg:address":"225 W Moana Ln",
    "sg:city":"Reno",
    "sg:classifiers":[
        {
            "category":"Real Estate",
            "subcategory":"Real Estate Operator",
            "type":"Services"
        }
    ],
    "sg:phone":"+1 775 826 4414",
    "sg:postcode":"89509",
    "sg:province":"NV",
    "sg:tags":[
        "building",
        "apartment",
        "general"
    ],
    "wof:name":"Moana Mini Public Storage",
    "wof:placetype":"venue"
},
  "geometry": {"coordinates":[-119.798787,39.491292],"type":"Point"}
}