{
  "type": "Feature",
  "properties": {
    "iso:country":"US",
    "sg:address":"4601 Rising Cove St",
    "sg:city":"Las Vegas",
    "sg:classifiers":[
        {
            "category":"Professional",
            "subcategory":"Computer Services",
            "type":"Services"
        }
    ],
    "sg:phone":"+1 702 413 6600",
    "sg:postcode":"89129",
    "sg:province":"NV",
    "sg:tags":[
        "internet"
    ],
    "wof:name":"Web Coast Design LLC",
    "wof:placetype":"venue"
},
  "geometry": {"coordinates":[-115.32608500000001,36.244146],"type":"Point"}
}