{
  "type": "Feature",
  "properties": {
    "iso:country":"US",
    "sg:address":"3140 Research Way",
    "sg:city":"Carson City",
    "sg:classifiers":[
        {
            "category":"Professional",
            "subcategory":"Engineering",
            "type":"Services"
        }
    ],
    "sg:phone":"+1 775 884 3886",
    "sg:postcode":"89706",
    "sg:province":"NV",
    "sg:tags":[
        "engineer"
    ],
    "wof:name":"Kleinfelder",
    "wof:placetype":"venue"
},
  "geometry": {"coordinates":[-119.749163,39.187671],"type":"Point"}
}