{
  "type": "Feature",
  "properties": {
    "iso:country":"US",
    "sg:address":"5675 S Valley View Blvd",
    "sg:city":"Las Vegas",
    "sg:phone":"+1 702 798 3998",
    "sg:postcode":"89118",
    "sg:province":"NV",
    "sg:tags":[
        "repair",
        "s",
        "commercial"
    ],
    "wof:name":"Standard Rest Eqp Las Vegas",
    "wof:placetype":"venue"
},
  "geometry": {"coordinates":[-115.189933,36.087691],"type":"Point"}
}