{
  "type": "Feature",
  "properties": {
    "iso:country":"US",
    "sg:address":"429 Max Ct",
    "sg:city":"Henderson",
    "sg:classifiers":[
        {
            "category":"Arts & Performance",
            "subcategory":"Theater",
            "type":"Entertainment"
        }
    ],
    "sg:phone":"+1 702 791 0001",
    "sg:postcode":"89011",
    "sg:province":"NV",
    "sg:tags":[
        "entertainer"
    ],
    "wof:name":"Power Moves Entertainment",
    "wof:placetype":"venue"
},
  "geometry": {"coordinates":[-115.004893,36.057264],"type":"Point"}
}