{
  "type": "Feature",
  "properties": {
    "iso:country":"US",
    "sg:address":"Mandalay Bay Theatre 3950 Las Vegas Blvd S",
    "sg:city":"Las Vegas",
    "sg:classifiers":[
        {
            "category":"Arts & Performance",
            "subcategory":"Arts Center",
            "type":"Entertainment"
        }
    ],
    "sg:phone":"+1 877 632 7400",
    "sg:postcode":"89119",
    "sg:province":"NV",
    "sg:tags":[
        "performing"
    ],
    "sg:website":"lionking.com",
    "wof:name":"The Lion King",
    "wof:placetype":"venue"
},
  "geometry": {"coordinates":[-115.176692,36.090305],"type":"Point"}
}