{
  "type": "Feature",
  "properties": {
    "iso:country":"US",
    "sg:address":"335 Edison Way",
    "sg:city":"Reno",
    "sg:classifiers":[
        {
            "category":"Shopping",
            "subcategory":"Catalog Store",
            "type":"Retail Goods"
        }
    ],
    "sg:phone":"+1 775 825 8178",
    "sg:postcode":"89502",
    "sg:province":"NV",
    "sg:tags":[
        "apparel",
        "mail",
        "internet",
        "order",
        "intimate"
    ],
    "wof:name":"Henry & June",
    "wof:placetype":"venue"
},
  "geometry": {"coordinates":[-119.755239,39.507896],"type":"Point"}
}