{
  "type": "Feature",
  "properties": {
    "iso:country":"US",
    "sg:address":"3 Clear Crossing Trl",
    "sg:city":"Henderson",
    "sg:classifiers":[
        {
            "category":"Manufacturing",
            "subcategory":"Retail Goods",
            "type":"Manufacturing & Wholesale Goods"
        }
    ],
    "sg:phone":"+1 702 896 2970",
    "sg:postcode":"89052",
    "sg:province":"NV",
    "sg:tags":[
        "product",
        "mfg"
    ],
    "wof:name":"Jsr Design",
    "wof:placetype":"venue"
},
  "geometry": {"coordinates":[-115.08178599999999,35.968157],"type":"Point"}
}