{
  "type": "Feature",
  "properties": {
    "iso:country":"US",
    "sg:address":"5965 W Tropicana Ave Ste D",
    "sg:city":"Las Vegas",
    "sg:classifiers":[
        {
            "category":"Personal",
            "subcategory":"Nail Salon",
            "type":"Services"
        }
    ],
    "sg:phone":"+1 702 221 7005",
    "sg:postcode":"89103",
    "sg:province":"NV",
    "wof:name":"Nailpro",
    "wof:placetype":"venue"
},
  "geometry": {"coordinates":[-115.223,36.099899],"type":"Point"}
}