{
  "type": "Feature",
  "properties": {
    "iso:country":"US",
    "sg:address":"5670 S Pecos Rd",
    "sg:city":"Las Vegas",
    "sg:classifiers":[
        {
            "category":"Utilities",
            "subcategory":"Telephone",
            "type":"Services"
        }
    ],
    "sg:phone":"+1 702 951 6200",
    "sg:postcode":"89120",
    "sg:province":"NV",
    "sg:tags":[
        "telecommunication"
    ],
    "sg:website":"www.valuetel.net",
    "wof:name":"Value Tel Corp",
    "wof:placetype":"venue"
},
  "geometry": {"coordinates":[-115.1009,36.089412],"type":"Point"}
}