{
  "type": "Feature",
  "properties": {
    "iso:country":"US",
    "sg:address":"10713 Woodlore Pl",
    "sg:city":"Las Vegas",
    "sg:classifiers":[
        {
            "category":"Wholesale",
            "subcategory":"Hardware",
            "type":"Manufacturing & Wholesale Goods"
        }
    ],
    "sg:phone":"+1 702 341 7600",
    "sg:postcode":"89144",
    "sg:province":"NV",
    "sg:tags":[
        "air",
        "parts",
        "conditioning",
        "supply"
    ],
    "wof:name":"Flex Systems Inc",
    "wof:placetype":"venue"
},
  "geometry": {"coordinates":[-115.32933300000001,36.189703],"type":"Point"}
}