{
  "type": "Feature",
  "properties": {
    "iso:country":"US",
    "sg:address":"18124 Wedge Pkwy",
    "sg:city":"Reno",
    "sg:classifiers":[
        {
            "category":"Professional",
            "subcategory":"Advertising",
            "type":"Services"
        }
    ],
    "sg:phone":"+1 775 852 1010",
    "sg:postcode":"89511",
    "sg:province":"NV",
    "sg:tags":[
        "mailing",
        "shipping"
    ],
    "wof:name":"UPS Store",
    "wof:placetype":"venue"
},
  "geometry": {"coordinates":[-119.76707,39.395698],"type":"Point"}
}