{
  "type": "Feature",
  "properties": {
    "iso:country":"US",
    "sg:address":"81 N Daisetta St",
    "sg:city":"Las Vegas",
    "sg:classifiers":[
        {
            "category":"Shopping",
            "type":"Retail Goods"
        }
    ],
    "sg:phone":"+1 702 453 8385",
    "sg:postcode":"89110",
    "sg:province":"NV",
    "sg:tags":[
        "pet",
        "food",
        "supply"
    ],
    "wof:name":"Pet Pantry",
    "wof:placetype":"venue"
},
  "geometry": {"coordinates":[-115.083287,36.162278],"type":"Point"}
}