{
  "type": "Feature",
  "properties": {
    "iso:country":"US",
    "sg:address":"464 W Winnemucca Blvd",
    "sg:city":"Winnemucca",
    "sg:classifiers":[
        {
            "category":"Personal",
            "subcategory":"Beauty Salon",
            "type":"Services"
        }
    ],
    "sg:phone":"+1 775 623 2444",
    "sg:postcode":"89445",
    "sg:province":"NV",
    "sg:tags":[
        "shop"
    ],
    "wof:name":"Prime Cut",
    "wof:placetype":"venue"
},
  "geometry": {"coordinates":[-117.739013,40.970235],"type":"Point"}
}