{
  "type": "Feature",
  "properties": {
    "iso:country":"US",
    "sg:address":"2889 Northtowne Ln",
    "sg:city":"Reno",
    "sg:classifiers":[
        {
            "category":"Restaurant",
            "type":"Food & Drink"
        }
    ],
    "sg:menulink":"http://www.allmenus.com/nv/reno-north/181840-wendys/menu/",
    "sg:phone":"+1 775 358 0668",
    "sg:postcode":"89512",
    "sg:province":"NV",
    "sg:tags":[
        "burger",
        "american",
        "soup"
    ],
    "wof:name":"Wendy's",
    "wof:placetype":"venue"
},
  "geometry": {"coordinates":[-119.782055,39.55619],"type":"Point"}
}