{
  "type": "Feature",
  "properties": {
    "iso:country":"US",
    "sg:address":"6501 Vicuna Dr",
    "sg:city":"Las Vegas",
    "sg:classifiers":[
        {
            "category":"Professional",
            "subcategory":"Accounting & Tax Preparation",
            "type":"Services"
        }
    ],
    "sg:phone":"+1 702 220 4178",
    "sg:postcode":"89146",
    "sg:province":"NV",
    "sg:tags":[
        "return"
    ],
    "wof:name":"Msg Business Tax Service",
    "wof:placetype":"venue"
},
  "geometry": {"coordinates":[-115.23687,36.147049],"type":"Point"}
}