{
  "type": "Feature",
  "properties": {
    "iso:country":"US",
    "sg:address":"1500 Las Vegas Blvd N",
    "sg:city":"Las Vegas",
    "sg:classifiers":[
        {
            "category":"Real Estate",
            "subcategory":"Developer",
            "type":"Services"
        }
    ],
    "sg:phone":"+1 702 229 6246",
    "sg:postcode":"89101",
    "sg:province":"NV",
    "sg:tags":[
        "cemetery"
    ],
    "wof:name":"Woodlawn Cemetery",
    "wof:placetype":"venue"
},
  "geometry": {"coordinates":[-115.133956,36.187043],"type":"Point"}
}