{
  "type": "Feature",
  "properties": {
    "iso:country":"US",
    "sg:address":"10949 Lampione St",
    "sg:city":"Las Vegas",
    "sg:classifiers":[
        {
            "category":"Professional",
            "subcategory":"Business Services",
            "type":"Services"
        }
    ],
    "sg:phone":"+1 702 988 0137",
    "sg:postcode":"89141",
    "sg:province":"NV",
    "sg:tags":[
        "processing",
        "datum"
    ],
    "wof:name":"Greenback Solutions Inc",
    "wof:placetype":"venue"
},
  "geometry": {"coordinates":[-115.222745,35.990453],"type":"Point"}
}