{
  "type": "Feature",
  "properties": {
    "iso:country":"US",
    "sg:address":"10860 W Charleston Blvd",
    "sg:city":"Las Vegas",
    "sg:classifiers":[
        {
            "category":"Personal",
            "subcategory":"Hair Removal",
            "type":"Services"
        }
    ],
    "sg:phone":"+1 702 253 2769",
    "sg:postcode":"89135",
    "sg:province":"NV",
    "sg:website":"eyebrowsrus.com",
    "wof:name":"Eyebrows R Us",
    "wof:placetype":"venue"
},
  "geometry": {"coordinates":[-115.332713,36.159114],"type":"Point"}
}