{
  "type": "Feature",
  "properties": {
    "iso:country":"US",
    "sg:address":"953 E Sahara Ave",
    "sg:city":"Las Vegas",
    "sg:classifiers":[
        {
            "category":"Restaurant",
            "type":"Food & Drink"
        }
    ],
    "sg:phone":"+1 702 893 3389",
    "sg:postcode":"89104",
    "sg:province":"NV",
    "wof:name":"Korea Castle Restaurant",
    "wof:placetype":"venue"
},
  "geometry": {"coordinates":[-115.1447,36.143958],"type":"Point"}
}