{
  "type": "Feature",
  "properties": {
    "iso:country":"US",
    "sg:address":"2192 Last Chance Rd",
    "sg:city":"Elko",
    "sg:classifiers":[
        {
            "category":"Retail",
            "subcategory":"Auto Repair",
            "type":"Services"
        }
    ],
    "sg:phone":"+1 775 738 3924",
    "sg:postcode":"89801",
    "sg:province":"NV",
    "sg:tags":[
        "body"
    ],
    "wof:name":"Elko Body Shop Inc",
    "wof:placetype":"venue"
},
  "geometry": {"coordinates":[-115.736048,40.837491],"type":"Point"}
}