{
  "type": "Feature",
  "properties": {
    "iso:country":"US",
    "sg:address":"6501 W Charleston Blvd",
    "sg:city":"Las Vegas",
    "sg:classifiers":[
        {
            "category":"Home & Garden",
            "subcategory":"Carpets & Floor Coverings",
            "type":"Retail Goods"
        }
    ],
    "sg:phone":"+1 702 877 5969",
    "sg:postcode":"89146",
    "sg:province":"NV",
    "sg:tags":[
        "dealer",
        "rug"
    ],
    "wof:name":"Lindbergh Carpet Co",
    "wof:placetype":"venue"
},
  "geometry": {"coordinates":[-115.239244,36.159135],"type":"Point"}
}