{
  "type": "Feature",
  "properties": {
    "iso:country":"US",
    "sg:address":"2570 Marco St",
    "sg:city":"Las Vegas",
    "sg:classifiers":[
        {
            "category":"Building & Trades",
            "subcategory":"Construction",
            "type":"Services"
        }
    ],
    "sg:phone":"+1 702 644 5442",
    "sg:postcode":"89115",
    "sg:province":"NV",
    "sg:tags":[
        "stucco",
        "contractor"
    ],
    "wof:name":"R W Stucco",
    "wof:placetype":"venue"
},
  "geometry": {"coordinates":[-115.068826,36.203924],"type":"Point"}
}