{
  "type": "Feature",
  "properties": {
    "iso:country":"US",
    "sg:address":"4800 S Maryland Pkwy",
    "sg:city":"Las Vegas",
    "sg:classifiers":[
        {
            "category":"Professional",
            "type":"Services"
        }
    ],
    "sg:phone":"+1 702 646 7785",
    "sg:postcode":"89119",
    "sg:province":"NV",
    "sg:tags":[
        "establishment"
    ],
    "wof:name":"B & F Enterprises",
    "wof:placetype":"venue"
},
  "geometry": {"coordinates":[-115.136949,36.102842],"type":"Point"}
}