{
  "type": "Feature",
  "properties": {
    "iso:country":"US",
    "sg:address":"50 W Liberty St",
    "sg:city":"Reno",
    "sg:classifiers":[
        {
            "category":"Banks & Credit Unions",
            "subcategory":"Financial Services",
            "type":"Services"
        },
        {
            "category":"Professional",
            "subcategory":"Management & Consulting",
            "type":"Services"
        }
    ],
    "sg:phone":"+1 775 322 0626",
    "sg:postcode":"89501",
    "sg:province":"NV",
    "sg:tags":[
        "consultant",
        "energy",
        "conservation",
        "real estate",
        "investment"
    ],
    "wof:name":"Hidden Splendor Resources Inc",
    "wof:placetype":"venue"
},
  "geometry": {"coordinates":[-119.811942,39.521675],"type":"Point"}
}