{
  "type": "Feature",
  "properties": {
    "iso:country":"US",
    "sg:address":"312 W Mesquite Blvd",
    "sg:city":"Mesquite",
    "sg:classifiers":[
        {
            "category":"Personal",
            "subcategory":"Beauty Salon",
            "type":"Services"
        }
    ],
    "sg:phone":"+1 702 345 3285",
    "sg:postcode":"89027",
    "sg:province":"NV",
    "sg:tags":[
        "manicuring"
    ],
    "wof:name":"Star Nails",
    "wof:placetype":"venue"
},
  "geometry": {"coordinates":[-114.073576,36.803918],"type":"Point"}
}