{
  "type": "Feature",
  "properties": {
    "iso:country":"US",
    "sg:address":"8570 del Webb Blvd",
    "sg:city":"Las Vegas",
    "sg:classifiers":[
        {
            "category":"Retail",
            "subcategory":"Funeral Services",
            "type":"Services"
        }
    ],
    "sg:phone":"+1 702 474 6699",
    "sg:postcode":"89134",
    "sg:province":"NV",
    "sg:tags":[
        "crematory"
    ],
    "wof:name":"Neptune Society",
    "wof:placetype":"venue"
},
  "geometry": {"coordinates":[-115.280678,36.210273],"type":"Point"}
}