{
  "type": "Feature",
  "properties": {
    "iso:country":"US",
    "sg:address":"3201 W Sahara Avenue Suite B",
    "sg:city":"Las Vegas",
    "sg:classifiers":[
        {
            "category":"Personal",
            "subcategory":"Massage",
            "type":"Services"
        }
    ],
    "sg:phone":"+1 702 876 5484",
    "sg:postcode":"89102",
    "sg:province":"NV",
    "wof:name":"Asian Flower Massage",
    "wof:placetype":"venue"
},
  "geometry": {"coordinates":[-115.184605,36.144307],"type":"Point"}
}