{
  "type": "Feature",
  "properties": {
    "iso:country":"US",
    "sg:address":"190 E Mesquite Blvd",
    "sg:city":"Mesquite",
    "sg:classifiers":[
        {
            "category":"Sports & Exercise",
            "subcategory":"Gym",
            "type":"Entertainment"
        }
    ],
    "sg:phone":"+1 702 346 1266",
    "sg:postcode":"89027",
    "sg:province":"NV",
    "sg:tags":[
        "center",
        "club",
        "gymnasium",
        "health",
        "fitness",
        "studio"
    ],
    "wof:name":"Curves For Women",
    "wof:placetype":"venue"
},
  "geometry": {"coordinates":[-114.06479299999999,36.80397],"type":"Point"}
}