{
  "type": "Feature",
  "properties": {
    "iso:country":"US",
    "sg:address":"8530 W Sunset Rd # 350",
    "sg:city":"Las Vegas",
    "sg:classifiers":[
        {
            "category":"Health Services",
            "subcategory":"Doctor",
            "type":"Services"
        }
    ],
    "sg:phone":"+1 702 851 1065",
    "sg:postcode":"89113",
    "sg:province":"NV",
    "wof:name":"Chang Bess, DO",
    "wof:placetype":"venue"
},
  "geometry": {"coordinates":[-115.276065,36.070192],"type":"Point"}
}