{
  "type": "Feature",
  "properties": {
    "iso:country":"US",
    "sg:address":"2535 Appollo Way",
    "sg:city":"Reno",
    "sg:classifiers":[
        {
            "category":"Building & Trades",
            "subcategory":"Plumbing",
            "type":"Services"
        }
    ],
    "sg:phone":"+1 775 747 1958",
    "sg:postcode":"89503",
    "sg:province":"NV",
    "sg:tags":[
        "sheet",
        "work",
        "metal",
        "contractor"
    ],
    "wof:name":"Alpine Sheet Metal Co",
    "wof:placetype":"venue"
},
  "geometry": {"coordinates":[-119.847295,39.535415],"type":"Point"}
}