{
  "type": "Feature",
  "properties": {
    "iso:country":"US",
    "sg:address":"265 US Hwy 95 Alt",
    "sg:city":"Yerington",
    "sg:classifiers":[
        {
            "category":"Bars & Pubs",
            "type":"Food & Drink"
        }
    ],
    "sg:phone":"+1 775 463 9530",
    "sg:postcode":"89447",
    "sg:province":"NV",
    "wof:name":"Wabuska Bar",
    "wof:placetype":"venue"
},
  "geometry": {"coordinates":[-119.166433,38.993833],"type":"Point"}
}