{
  "type": "Feature",
  "properties": {
    "iso:country":"US",
    "sg:address":"1445 W. Sunset Rd #7",
    "sg:city":"Henderson",
    "sg:classifiers":[
        {
            "category":"Professional",
            "subcategory":"Printing & Photocopies",
            "type":"Services"
        }
    ],
    "sg:phone":"+1 702 638 8383",
    "sg:postcode":"89014",
    "sg:province":"NV",
    "sg:website":"www.henderson.intlminutepress.com",
    "wof:name":"International Minute Press",
    "wof:placetype":"venue"
},
  "geometry": {"coordinates":[-115.048574,36.062575],"type":"Point"}
}