{
  "type": "Feature",
  "properties": {
    "iso:country":"US",
    "sg:address":"1312 Driscoll",
    "sg:city":"Las Vegas",
    "sg:classifiers":[
        {
            "category":"Real Estate",
            "subcategory":"Real Estate Agent",
            "type":"Services"
        }
    ],
    "sg:phone":"+1 702 838 5100",
    "sg:postcode":"89128",
    "sg:province":"NV",
    "wof:name":"Realty Executives",
    "wof:placetype":"venue"
},
  "geometry": {"coordinates":[-115.263885,36.185446],"type":"Point"}
}