{
  "type": "Feature",
  "properties": {
    "iso:country":"US",
    "sg:address":"1951 Ramrod Ave",
    "sg:city":"Henderson",
    "sg:classifiers":[
        {
            "category":"Shopping",
            "type":"Retail Goods"
        }
    ],
    "sg:phone":"+1 702 992 9200",
    "sg:postcode":"89014",
    "sg:province":"NV",
    "sg:tags":[
        "merchandise"
    ],
    "wof:name":"All Star Pool Company Inc",
    "wof:placetype":"venue"
},
  "geometry": {"coordinates":[-115.077367,36.075883],"type":"Point"}
}