{
  "type": "Feature",
  "properties": {
    "iso:country":"US",
    "sg:address":"890 W Williams Ave",
    "sg:city":"Fallon",
    "sg:classifiers":[
        {
            "category":"Food & Beverages",
            "subcategory":"Groceries & Convenience Stores",
            "type":"Retail Goods"
        }
    ],
    "sg:phone":"+1 775 428 2330",
    "sg:postcode":"89406",
    "sg:province":"NV",
    "sg:tags":[
        "grocer"
    ],
    "sg:website":"www.safeway.com",
    "wof:name":"Safeway",
    "wof:placetype":"venue"
},
  "geometry": {"coordinates":[-118.787244,39.474864],"type":"Point"}
}