{
  "type": "Feature",
  "properties": {
    "iso:country":"US",
    "sg:address":"500 S Martin L King Boulevard",
    "sg:city":"Las Vegas",
    "sg:classifiers":[
        {
            "category":"Shopping",
            "subcategory":"Pharmacy",
            "type":"Retail Goods"
        }
    ],
    "sg:phone":"+1 702 678 6267",
    "sg:postcode":"89106",
    "sg:province":"NV",
    "sg:tags":[
        "drugstore"
    ],
    "sg:website":"www.emerald-medical.com",
    "wof:name":"Emerald Pharmacy & Medical Supply",
    "wof:placetype":"venue"
},
  "geometry": {"coordinates":[-115.160968,36.1662],"type":"Point"}
}