{
  "type": "Feature",
  "properties": {
    "iso:country":"US",
    "sg:address":"1140 Almond Tree Lane",
    "sg:city":"Las Vegas",
    "sg:classifiers":[
        {
            "category":"Health Services",
            "subcategory":"Health Practitioner",
            "type":"Services"
        }
    ],
    "sg:phone":"+1 702 735 4844",
    "sg:postcode":"89104",
    "sg:province":"NV",
    "sg:tags":[
        "therapy",
        "physical"
    ],
    "wof:name":"Nobis Don Mspt",
    "wof:placetype":"venue"
},
  "geometry": {"coordinates":[-115.138884,36.145384],"type":"Point"}
}