{
  "type": "Feature",
  "properties": {
    "iso:country":"US",
    "sg:address":"3675 W Teco Ave",
    "sg:city":"Las Vegas",
    "sg:classifiers":[
        {
            "category":"Building & Trades",
            "subcategory":"Construction",
            "type":"Services"
        }
    ],
    "sg:phone":"+1 702 873 6986",
    "sg:postcode":"89118",
    "sg:province":"NV",
    "sg:tags":[
        "designer"
    ],
    "wof:name":"Sunset Design Studio",
    "wof:placetype":"venue"
},
  "geometry": {"coordinates":[-115.18964200000001,36.073477],"type":"Point"}
}