{
  "type": "Feature",
  "properties": {
    "iso:country":"US",
    "sg:address":"3429 S Jones Blvd",
    "sg:city":"Las Vegas",
    "sg:classifiers":[
        {
            "category":"Restaurant",
            "type":"Food & Drink"
        }
    ],
    "sg:phone":"+1 702 873 9795",
    "sg:postcode":"89146",
    "sg:province":"NV",
    "sg:tags":[
        "eating"
    ],
    "wof:name":"Taco Bell",
    "wof:placetype":"venue"
},
  "geometry": {"coordinates":[-115.22500700000001,36.127821],"type":"Point"}
}