{
  "type": "Feature",
  "properties": {
    "iso:country":"US",
    "sg:address":"3050 Mill St",
    "sg:city":"Reno",
    "sg:classifiers":[
        {
            "category":"Manufacturing",
            "subcategory":"Signs",
            "type":"Manufacturing & Wholesale Goods"
        }
    ],
    "sg:phone":"+1 775 324 6337",
    "sg:postcode":"89502",
    "sg:province":"NV",
    "sg:tags":[
        "advertising",
        "specialty"
    ],
    "wof:name":"J C Graphicx",
    "wof:placetype":"venue"
},
  "geometry": {"coordinates":[-119.773709,39.517069],"type":"Point"}
}