{
  "type": "Feature",
  "properties": {
    "iso:country":"US",
    "sg:address":"10901 Salford Dr",
    "sg:city":"Las Vegas",
    "sg:classifiers":[
        {
            "category":"Professional",
            "subcategory":"Business Services",
            "type":"Services"
        }
    ],
    "sg:phone":"+1 702 254 1144",
    "sg:postcode":"89144",
    "sg:province":"NV",
    "wof:name":"B Design",
    "wof:placetype":"venue"
},
  "geometry": {"coordinates":[-115.334576,36.173576],"type":"Point"}
}