{
  "type": "Feature",
  "properties": {
    "iso:country":"US",
    "sg:address":"9925 S Eastern Ave",
    "sg:city":"Las Vegas",
    "sg:classifiers":[
        {
            "category":"Bars & Pubs",
            "type":"Food & Drink"
        },
        {
            "category":"Restaurant",
            "type":"Food & Drink"
        }
    ],
    "sg:postcode":"89183",
    "sg:province":"NV",
    "wof:name":"Nacho Daddy",
    "wof:placetype":"venue"
},
  "geometry": {"coordinates":[-115.117166,36.008986],"type":"Point"}
}