{
  "type": "Feature",
  "properties": {
    "iso:country":"US",
    "sg:address":"4824 Longley Ln",
    "sg:city":"Reno",
    "sg:classifiers":[
        {
            "category":"Professional",
            "subcategory":"Computer Services",
            "type":"Services"
        }
    ],
    "sg:phone":"+1 775 745 6164",
    "sg:postcode":"89502",
    "sg:province":"NV",
    "sg:tags":[
        "retail",
        "internet"
    ],
    "wof:name":"Cigar Five Packs",
    "wof:placetype":"venue"
},
  "geometry": {"coordinates":[-119.76225700000001,39.483329],"type":"Point"}
}