{
  "type": "Feature",
  "properties": {
    "iso:country":"US",
    "sg:address":"4790 W University Avenue",
    "sg:city":"Las Vegas",
    "sg:classifiers":[
        {
            "category":"Real Estate",
            "subcategory":"Architect",
            "type":"Services"
        }
    ],
    "sg:phone":"+1 702 869 3808",
    "sg:postcode":"89103",
    "sg:province":"NV",
    "wof:name":"Johnson Mark R Architects",
    "wof:placetype":"venue"
},
  "geometry": {"coordinates":[-115.20555899999999,36.110083],"type":"Point"}
}