{
  "type": "Feature",
  "properties": {
    "iso:country":"US",
    "sg:address":"5601 Echo Ave",
    "sg:city":"Reno",
    "sg:classifiers":[
        {
            "category":"Organizations",
            "subcategory":"Religious Organization",
            "type":"Services"
        }
    ],
    "sg:phone":"+1 775 972 3325",
    "sg:postcode":"89506",
    "sg:province":"NV",
    "sg:tags":[
        "church"
    ],
    "wof:name":"Covenant Outreach Church",
    "wof:placetype":"venue"
},
  "geometry": {"coordinates":[-119.887956,39.654672],"type":"Point"}
}