{
  "type": "Feature",
  "properties": {
    "iso:country":"US",
    "sg:address":"241 Engine House Cir",
    "sg:city":"Glenbrook",
    "sg:classifiers":[
        {
            "category":"Professional",
            "subcategory":"Lawyer & Legal Services",
            "type":"Services"
        }
    ],
    "sg:phone":"+1 775 749 5352",
    "sg:postcode":"89413",
    "sg:province":"NV",
    "wof:name":"George W Prutzman",
    "wof:placetype":"venue"
},
  "geometry": {"coordinates":[-119.937923,39.090517],"type":"Point"}
}