{
  "type": "Feature",
  "properties": {
    "iso:country":"US",
    "sg:address":"691 Marks St Ste B",
    "sg:city":"Henderson",
    "sg:classifiers":[
        {
            "category":"Home & Garden",
            "subcategory":"Furniture",
            "type":"Retail Goods"
        }
    ],
    "sg:phone":"+1 702 450 4203",
    "sg:postcode":"89014",
    "sg:province":"NV",
    "sg:tags":[
        "store"
    ],
    "wof:name":"Norwalk the Furniture Idea",
    "wof:placetype":"venue"
},
  "geometry": {"coordinates":[-115.036421,36.067719],"type":"Point"}
}