{
  "type": "Feature",
  "properties": {
    "iso:country":"US",
    "sg:address":"5108 Gentle River Ave",
    "sg:city":"Las Vegas",
    "sg:classifiers":[
        {
            "category":"Real Estate",
            "subcategory":"Developer",
            "type":"Services"
        }
    ],
    "sg:phone":"+1 702 395 0926",
    "sg:postcode":"89130",
    "sg:province":"NV",
    "sg:tags":[
        "cemetery"
    ],
    "wof:name":"Cemetery Consulting Service",
    "wof:placetype":"venue"
},
  "geometry": {"coordinates":[-115.215908,36.228713],"type":"Point"}
}