{
  "type": "Feature",
  "properties": {
    "iso:country":"US",
    "sg:address":"3280 E Tropicana Ave",
    "sg:city":"Las Vegas",
    "sg:classifiers":[
        {
            "category":"Shopping",
            "subcategory":"Department Store",
            "type":"Retail Goods"
        }
    ],
    "sg:phone":"+1 702 456 1208",
    "sg:postcode":"89121",
    "sg:province":"NV",
    "wof:name":"LVP Liquidation Depot",
    "wof:placetype":"venue"
},
  "geometry": {"coordinates":[-115.102676,36.100097],"type":"Point"}
}