{
  "type": "Feature",
  "properties": {
    "iso:country":"US",
    "sg:address":"1458 E Desert Inn Rd Apt 4",
    "sg:city":"Las Vegas",
    "sg:classifiers":[
        {
            "category":"Shopping",
            "subcategory":"Pets & Pet Supplies",
            "type":"Retail Goods"
        }
    ],
    "sg:phone":"+1 201 854 2511",
    "sg:postcode":"89109",
    "sg:province":"NV",
    "sg:tags":[
        "store"
    ],
    "wof:name":"Amazona Pet Shop",
    "wof:placetype":"venue"
},
  "geometry": {"coordinates":[-115.133003,36.129799],"type":"Point"}
}