{
  "type": "Feature",
  "properties": {
    "iso:country":"US",
    "sg:address":"3867 S Valley View Blvd",
    "sg:city":"Las Vegas",
    "sg:classifiers":[
        {
            "category":"Wholesale",
            "subcategory":"Fruits & Vegetables",
            "type":"Manufacturing & Wholesale Goods"
        }
    ],
    "sg:phone":"+1 702 871 7818",
    "sg:postcode":"89103",
    "sg:province":"NV",
    "sg:tags":[
        "veggie"
    ],
    "wof:name":"California Wholesale Produce",
    "wof:placetype":"venue"
},
  "geometry": {"coordinates":[-115.190002,36.119701],"type":"Point"}
}