{
  "type": "Feature",
  "properties": {
    "iso:country":"US",
    "sg:address":"714 S 1st St",
    "sg:city":"Las Vegas",
    "sg:classifiers":[
        {
            "category":"Manufacturing",
            "subcategory":"Metals",
            "type":"Manufacturing & Wholesale Goods"
        }
    ],
    "sg:phone":"+1 702 382 8244",
    "sg:postcode":"89101",
    "sg:province":"NV",
    "sg:tags":[
        "metalwork",
        "sheet",
        "mfg"
    ],
    "wof:name":"Nevada Precision Sheet Metal",
    "wof:placetype":"venue"
},
  "geometry": {"coordinates":[-115.15051800000001,36.163248],"type":"Point"}
}