{
  "type": "Feature",
  "properties": {
    "iso:country":"US",
    "sg:address":"841 E 2nd St",
    "sg:city":"Carson City",
    "sg:classifiers":[
        {
            "category":"Insurance",
            "subcategory":"Insurance Agent",
            "type":"Services"
        }
    ],
    "sg:phone":"+1 775 884 1021",
    "sg:postcode":"89701",
    "sg:province":"NV",
    "wof:name":"Farmers Insurance",
    "wof:placetype":"venue"
},
  "geometry": {"coordinates":[-119.760328,39.163142],"type":"Point"}
}