{
  "type": "Feature",
  "properties": {
    "iso:country":"US",
    "sg:address":"1296 Hazelwood St",
    "sg:city":"Boulder City",
    "sg:classifiers":[
        {
            "category":"Manufacturing",
            "subcategory":"Rubber & Plastics",
            "type":"Manufacturing & Wholesale Goods"
        }
    ],
    "sg:phone":"+1 702 293 9555",
    "sg:postcode":"89005",
    "sg:province":"NV",
    "wof:name":"KMB",
    "wof:placetype":"venue"
},
  "geometry": {"coordinates":[-114.861043,35.965759],"type":"Point"}
}