{
  "type": "Feature",
  "properties": {
    "iso:country":"US",
    "sg:address":"8565 W Sahara Avenue",
    "sg:city":"Las Vegas",
    "sg:classifiers":[
        {
            "category":"Shopping",
            "subcategory":"Pawn Shop",
            "type":"Retail Goods"
        },
        {
            "category":"Banks & Credit Unions",
            "subcategory":"Financial Services",
            "type":"Services"
        }
    ],
    "sg:phone":"+1 702 233 6449",
    "sg:postcode":"89117",
    "sg:province":"NV",
    "sg:tags":[
        "loan",
        "check",
        "cashing/pay-day"
    ],
    "sg:website":"www.loanexfastcash.com",
    "wof:name":"Loanex",
    "wof:placetype":"venue"
},
  "geometry": {"coordinates":[-115.277908,36.143926],"type":"Point"}
}