{
  "type": "Feature",
  "properties": {
    "iso:country":"US",
    "sg:address":"3433 Las Vegas Fwy",
    "sg:city":"North Las Vegas",
    "sg:classifiers":[
        {
            "category":"Building & Trades",
            "subcategory":"Construction",
            "type":"Services"
        }
    ],
    "sg:phone":"+1 702 399 2468",
    "sg:postcode":"89030",
    "sg:province":"NV",
    "sg:tags":[
        "flooring",
        "contractor"
    ],
    "wof:name":"Practical Flooring Inc",
    "wof:placetype":"venue"
},
  "geometry": {"coordinates":[-115.122896,36.219392],"type":"Point"}
}