{
  "type": "Feature",
  "properties": {
    "iso:country":"US",
    "sg:address":"1881 W Alexander Rd",
    "sg:city":"North Las Vegas",
    "sg:classifiers":[
        {
            "category":"Professional",
            "type":"Services"
        }
    ],
    "sg:phone":"+1 702 808 4711",
    "sg:postcode":"89032",
    "sg:province":"NV",
    "wof:name":"Terrys World of Products",
    "wof:placetype":"venue"
},
  "geometry": {"coordinates":[-115.170163,36.23189],"type":"Point"}
}