{
  "type": "Feature",
  "properties": {
    "iso:country":"US",
    "sg:address":"1166 Annie Ct",
    "sg:city":"Minden",
    "sg:classifiers":[
        {
            "category":"Restaurant",
            "type":"Food & Drink"
        }
    ],
    "sg:phone":"+1 775 267 5555",
    "sg:postcode":"89423",
    "sg:province":"NV",
    "wof:name":"Nik-N-Willies Pizza",
    "wof:placetype":"venue"
},
  "geometry": {"coordinates":[-119.75505,39.023266],"type":"Point"}
}