{
  "type": "Feature",
  "properties": {
    "iso:country":"US",
    "sg:address":"3009 Post Road Suite B",
    "sg:city":"Las Vegas",
    "sg:classifiers":[
        {
            "category":"Building & Trades",
            "subcategory":"Landscaping Services",
            "type":"Services"
        },
        {
            "category":"Retail",
            "subcategory":"Auto Repair",
            "type":"Services"
        }
    ],
    "sg:phone":"+1 702 415 6168",
    "sg:postcode":"89147",
    "sg:province":"NV",
    "sg:website":"mechandyman.com/",
    "wof:name":"Mechandyman",
    "wof:placetype":"venue"
},
  "geometry": {"coordinates":[-115.181472,36.074912],"type":"Point"}
}