{
  "type": "Feature",
  "properties": {
    "iso:country":"US",
    "sg:address":"8124 Maddingley Ave",
    "sg:city":"Las Vegas",
    "sg:classifiers":[
        {
            "category":"Professional",
            "type":"Services"
        }
    ],
    "sg:phone":"+1 702 256 0837",
    "sg:postcode":"89117",
    "sg:province":"NV",
    "sg:tags":[
        "establishment"
    ],
    "wof:name":"Quantum Equities",
    "wof:placetype":"venue"
},
  "geometry": {"coordinates":[-115.26814299999999,36.137979],"type":"Point"}
}