{
  "type": "Feature",
  "properties": {
    "iso:country":"US",
    "sg:address":"147 E Liberty St",
    "sg:city":"Reno",
    "sg:classifiers":[
        {
            "category":"Professional",
            "subcategory":"Lawyer & Legal Services",
            "type":"Services"
        }
    ],
    "sg:phone":"+1 775 324 0338",
    "sg:postcode":"89501",
    "sg:province":"NV",
    "sg:tags":[
        "attorney"
    ],
    "wof:name":"Daniel S Corder LTD",
    "wof:placetype":"venue"
},
  "geometry": {"coordinates":[-119.80913700000001,39.522493],"type":"Point"}
}