{
  "type": "Feature",
  "properties": {
    "iso:country":"US",
    "sg:address":"3715 W Flamingo Rd",
    "sg:city":"Las Vegas",
    "sg:classifiers":[
        {
            "category":"Restaurant",
            "type":"Food & Drink"
        }
    ],
    "sg:menulink":"http://www.allmenus.com/nv/las-vegas/165462-del-taco/menu/",
    "sg:phone":"+1 702 364 9520",
    "sg:postcode":"89103",
    "sg:province":"NV",
    "sg:tags":[
        "american",
        "mexican",
        "tex-mex"
    ],
    "wof:name":"Del Taco",
    "wof:placetype":"venue"
},
  "geometry": {"coordinates":[-115.188785,36.114988],"type":"Point"}
}