{
  "type": "Feature",
  "properties": {
    "iso:country":"US",
    "sg:address":"137 Montello Ave",
    "sg:city":"Las Vegas",
    "sg:classifiers":[
        {
            "category":"Building & Trades",
            "subcategory":"Plumbing",
            "type":"Services"
        }
    ],
    "sg:phone":"+1 702 438 7561",
    "sg:postcode":"89110",
    "sg:province":"NV",
    "sg:tags":[
        "contractor"
    ],
    "wof:name":"Prime Heating & AC",
    "wof:placetype":"venue"
},
  "geometry": {"coordinates":[-115.066363,36.162163],"type":"Point"}
}