{
  "type": "Feature",
  "properties": {
    "iso:country":"US",
    "sg:address":"8228 Sedona Sunrise Dr",
    "sg:city":"Las Vegas",
    "sg:classifiers":[
        {
            "category":"Shopping",
            "type":"Retail Goods"
        }
    ],
    "sg:phone":"+1 702 734 4299",
    "sg:postcode":"89128",
    "sg:province":"NV",
    "sg:tags":[
        "art",
        "gallery"
    ],
    "wof:name":"Carrara Galleries",
    "wof:placetype":"venue"
},
  "geometry": {"coordinates":[-115.276252,36.195946],"type":"Point"}
}