{
  "type": "Feature",
  "properties": {
    "iso:country":"US",
    "sg:address":"295 Holcomb Ave",
    "sg:city":"Reno",
    "sg:classifiers":[
        {
            "category":"Banks & Credit Unions",
            "subcategory":"Investment Brokerage",
            "type":"Services"
        }
    ],
    "sg:phone":"+1 775 324 7332",
    "sg:postcode":"89502",
    "sg:province":"NV",
    "sg:tags":[
        "consultant",
        "planning",
        "financial"
    ],
    "wof:name":"Isler Financial",
    "wof:placetype":"venue"
},
  "geometry": {"coordinates":[-119.806543,39.524607],"type":"Point"}
}