{
  "type": "Feature",
  "properties": {
    "iso:country":"US",
    "sg:address":"3085 E Russell Rd",
    "sg:city":"Las Vegas",
    "sg:classifiers":[
        {
            "category":"Professional",
            "subcategory":"Management & Consulting",
            "type":"Services"
        }
    ],
    "sg:phone":"+1 702 610 9720",
    "sg:postcode":"89120",
    "sg:province":"NV",
    "wof:name":"Corporate Planners of America",
    "wof:placetype":"venue"
},
  "geometry": {"coordinates":[-115.10564100000001,36.086313],"type":"Point"}
}