{
  "type": "Feature",
  "properties": {
    "iso:country":"US",
    "sg:address":"5642 S Eastern Ave Ste C",
    "sg:city":"Las Vegas",
    "sg:classifiers":[
        {
            "category":"Health Services",
            "subcategory":"Chiropractor",
            "type":"Services"
        }
    ],
    "sg:phone":"+1 702 385 3333",
    "sg:postcode":"89119",
    "sg:province":"NV",
    "wof:name":"First Choice Chiropractic",
    "wof:placetype":"venue"
},
  "geometry": {"coordinates":[-115.118591,36.08733],"type":"Point"}
}