{
  "type": "Feature",
  "properties": {
    "iso:country":"US",
    "sg:address":"115 Highland Dr",
    "sg:city":"Ely",
    "sg:classifiers":[
        {
            "category":"Real Estate",
            "subcategory":"Real Estate Operator",
            "type":"Services"
        }
    ],
    "sg:phone":"+1 775 289 4499",
    "sg:postcode":"89301",
    "sg:province":"NV",
    "sg:tags":[
        "apartment"
    ],
    "wof:name":"Highlands Apartments",
    "wof:placetype":"venue"
},
  "geometry": {"coordinates":[-114.866004,39.243245],"type":"Point"}
}