{
  "type": "Feature",
  "properties": {
    "iso:country":"US",
    "sg:address":"7741 N El Capitan Way",
    "sg:city":"Las Vegas",
    "sg:classifiers":[
        {
            "category":"Fast Food",
            "type":"Food & Drink"
        }
    ],
    "sg:postcode":"89149",
    "sg:province":"NV",
    "wof:name":"Jack in the Box",
    "wof:placetype":"venue"
},
  "geometry": {"coordinates":[-115.28811,36.271798],"type":"Point"}
}