{
  "type": "Feature",
  "properties": {
    "iso:country":"US",
    "sg:address":"3129 Ravenshoe Dr",
    "sg:city":"Las Vegas",
    "sg:classifiers":[
        {
            "category":"Professional",
            "type":"Services"
        }
    ],
    "sg:phone":"+1 702 341 0528",
    "sg:postcode":"89134",
    "sg:province":"NV",
    "wof:name":"Shaw Tax Svc",
    "wof:placetype":"venue"
},
  "geometry": {"coordinates":[-115.325372,36.216778],"type":"Point"}
}