{
  "type": "Feature",
  "properties": {
    "iso:country":"US",
    "sg:address":"926 Incline Way",
    "sg:city":"Incline Village",
    "sg:classifiers":[
        {
            "category":"Shopping",
            "subcategory":"Catalog Store",
            "type":"Retail Goods"
        },
        {
            "category":"Manufacturing",
            "subcategory":"Printing",
            "type":"Manufacturing & Wholesale Goods"
        }
    ],
    "sg:phone":"+1 775 832 5692",
    "sg:postcode":"89451",
    "sg:province":"NV",
    "sg:tags":[
        "publisher",
        "music",
        "sales",
        "internet"
    ],
    "wof:name":"Music Giants Inc",
    "wof:placetype":"venue"
},
  "geometry": {"coordinates":[-119.949108,39.248077],"type":"Point"}
}