{
  "type": "Feature",
  "properties": {
    "iso:country":"US",
    "sg:address":"8817 Cypresswood Ave",
    "sg:city":"Las Vegas",
    "sg:classifiers":[
        {
            "category":"Airline",
            "type":"Transportation"
        }
    ],
    "sg:phone":"+1 702 595 8226",
    "sg:postcode":"89134",
    "sg:province":"NV",
    "sg:tags":[
        "scheduled",
        "domestic",
        "freight",
        "sea",
        "air"
    ],
    "wof:name":"Indigo Group",
    "wof:placetype":"venue"
},
  "geometry": {"coordinates":[-115.286222,36.199535],"type":"Point"}
}