{
  "type": "Feature",
  "properties": {
    "iso:country":"US",
    "sg:address":"8530 W Sahara Ave",
    "sg:city":"Las Vegas",
    "sg:classifiers":[
        {
            "category":"Manufacturing",
            "subcategory":"Chemicals & Compounds",
            "type":"Manufacturing & Wholesale Goods"
        }
    ],
    "sg:phone":"+1 702 568 1255",
    "sg:postcode":"89117",
    "sg:province":"NV",
    "sg:tags":[
        "mfg"
    ],
    "wof:name":"Boyz N Hood",
    "wof:placetype":"venue"
},
  "geometry": {"coordinates":[-115.276437,36.144118],"type":"Point"}
}