{
  "type": "Feature",
  "properties": {
    "iso:country":"US",
    "sg:address":"3664 S Highland Dr",
    "sg:city":"Las Vegas",
    "sg:classifiers":[
        {
            "category":"Building & Trades",
            "subcategory":"Cleaning & Sanitation",
            "type":"Services"
        }
    ],
    "sg:phone":"+1 702 247 6118",
    "sg:postcode":"89103",
    "sg:province":"NV",
    "sg:tags":[
        "butler",
        "maid"
    ],
    "wof:name":"Andre's Home Svc",
    "wof:placetype":"venue"
},
  "geometry": {"coordinates":[-115.18353500000001,36.123413],"type":"Point"}
}