{
  "type": "Feature",
  "properties": {
    "iso:country":"US",
    "sg:address":"4186 Toronto Cir",
    "sg:city":"Las Vegas",
    "sg:classifiers":[
        {
            "category":"Home & Garden",
            "subcategory":"Garden Supply",
            "type":"Retail Goods"
        }
    ],
    "sg:phone":"+1 702 456 3468",
    "sg:postcode":"89121",
    "sg:province":"NV",
    "sg:tags":[
        "landscaping",
        "equipment"
    ],
    "wof:name":"Yang Landscaping Co",
    "wof:placetype":"venue"
},
  "geometry": {"coordinates":[-115.083722,36.105412],"type":"Point"}
}