{
  "type": "Feature",
  "properties": {
    "iso:country":"US",
    "sg:address":"1139 W Huffaker Ln",
    "sg:city":"Reno",
    "sg:classifiers":[
        {
            "category":"Sports & Exercise",
            "subcategory":"Gym",
            "type":"Entertainment"
        }
    ],
    "sg:phone":"+1 775 852 2031",
    "sg:postcode":"89511",
    "sg:province":"NV",
    "sg:tags":[
        "athletic",
        "club",
        "membership"
    ],
    "wof:name":"Reno Athletic Club",
    "wof:placetype":"venue"
},
  "geometry": {"coordinates":[-119.79054600000001,39.455008],"type":"Point"}
}