{
  "type": "Feature",
  "properties": {
    "iso:country":"US",
    "sg:address":"3244 S Carson St",
    "sg:city":"Carson City",
    "sg:classifiers":[
        {
            "category":"Autos & Motor Vehicles",
            "subcategory":"Auto Supplies",
            "type":"Retail Goods"
        }
    ],
    "sg:phone":"+1 775 885 8111",
    "sg:postcode":"89701",
    "sg:province":"NV",
    "wof:name":"Custom Truck Accessories",
    "wof:placetype":"venue"
},
  "geometry": {"coordinates":[-119.769242,39.13703],"type":"Point"}
}