{
  "type": "Feature",
  "properties": {
    "iso:country":"US",
    "sg:address":"1913 I St",
    "sg:city":"Sparks",
    "sg:classifiers":[
        {
            "category":"Manufacturing",
            "subcategory":"Jewelry",
            "type":"Manufacturing & Wholesale Goods"
        }
    ],
    "sg:phone":"+1 775 356 6100",
    "sg:postcode":"89431",
    "sg:province":"NV",
    "wof:name":"Hamilton Custom Cast",
    "wof:placetype":"venue"
},
  "geometry": {"coordinates":[-119.77022700000001,39.541512],"type":"Point"}
}