{
  "type": "Feature",
  "properties": {
    "iso:country":"US",
    "sg:address":"4045 Spencer St",
    "sg:city":"Las Vegas",
    "sg:classifiers":[
        {
            "category":"Health Services",
            "subcategory":"Health Practitioner",
            "type":"Services"
        }
    ],
    "sg:phone":"+1 702 212 9800",
    "sg:postcode":"89119",
    "sg:province":"NV",
    "sg:tags":[
        "psychologist"
    ],
    "wof:name":"Baumann & Assoc",
    "wof:placetype":"venue"
},
  "geometry": {"coordinates":[-115.127902,36.11734],"type":"Point"}
}