{
  "type": "Feature",
  "properties": {
    "iso:country":"US",
    "sg:address":"8449 W Lake Mead Blvd",
    "sg:city":"Las Vegas",
    "sg:classifiers":[
        {
            "category":"Personal",
            "subcategory":"Beauty Salon",
            "type":"Services"
        }
    ],
    "sg:phone":"+1 702 341 0700",
    "sg:postcode":"89128",
    "sg:province":"NV",
    "sg:tags":[
        "nail",
        "shop"
    ],
    "wof:name":"Venus Nails",
    "wof:placetype":"venue"
},
  "geometry": {"coordinates":[-115.279999,36.198101],"type":"Point"}
}