{
  "type": "Feature",
  "properties": {
    "iso:country":"US",
    "sg:address":"17 Affonso Dr",
    "sg:city":"Carson City",
    "sg:classifiers":[
        {
            "category":"Manufacturing",
            "subcategory":"Tools & Machinery",
            "type":"Manufacturing & Wholesale Goods"
        }
    ],
    "sg:phone":"+1 775 246 3031",
    "sg:postcode":"89706",
    "sg:province":"NV",
    "sg:tags":[
        "manufacture",
        "mixing",
        "metering",
        "dispensing",
        "equipment"
    ],
    "wof:name":"H & G Industries International",
    "wof:placetype":"venue"
},
  "geometry": {"coordinates":[-119.652792,39.219076],"type":"Point"}
}