{
  "type": "Feature",
  "properties": {
    "iso:country":"US",
    "sg:address":"7291 W Lake Mead Blvd",
    "sg:city":"Las Vegas",
    "sg:classifiers":[
        {
            "category":"Banks & Credit Unions",
            "subcategory":"Financial Services",
            "type":"Services"
        }
    ],
    "sg:phone":"+1 702 256 4555",
    "sg:postcode":"89128",
    "sg:province":"NV",
    "sg:website":"www.moneytreeinc.com",
    "wof:name":"Moneytree",
    "wof:placetype":"venue"
},
  "geometry": {"coordinates":[-115.250833,36.195698],"type":"Point"}
}