{
  "type": "Feature",
  "properties": {
    "iso:country":"US",
    "sg:address":"2753 S Highland Dr",
    "sg:city":"Las Vegas",
    "sg:classifiers":[
        {
            "category":"Professional",
            "subcategory":"Art Services",
            "type":"Services"
        }
    ],
    "sg:phone":"+1 702 882 3989",
    "sg:postcode":"89109",
    "sg:province":"NV",
    "sg:tags":[
        "photographer"
    ],
    "sg:website":"studio2753.com",
    "wof:name":"Studio 2753",
    "wof:placetype":"venue"
},
  "geometry": {"coordinates":[-115.171615,36.140734],"type":"Point"}
}