{
  "type": "Feature",
  "properties": {
    "iso:country":"US",
    "sg:address":"1969 Davina St",
    "sg:city":"Henderson",
    "sg:classifiers":[
        {
            "category":"Wholesale",
            "subcategory":"Machinery & Supplies",
            "type":"Manufacturing & Wholesale Goods"
        }
    ],
    "sg:phone":"+1 702 896 0669",
    "sg:postcode":"89074",
    "sg:province":"NV",
    "sg:tags":[
        "equipment",
        "industrial"
    ],
    "wof:name":"Mayfran International",
    "wof:placetype":"venue"
},
  "geometry": {"coordinates":[-115.075203,36.037655],"type":"Point"}
}