{
  "type": "Feature",
  "properties": {
    "iso:country":"US",
    "sg:address":"8105 Desert Jewel Cir",
    "sg:city":"Las Vegas",
    "sg:classifiers":[
        {
            "category":"Arts & Performance",
            "subcategory":"Theater",
            "type":"Entertainment"
        }
    ],
    "sg:phone":"+1 702 256 8876",
    "sg:postcode":"89128",
    "sg:province":"NV",
    "sg:tags":[
        "theatrical"
    ],
    "wof:name":"International Artists MGT",
    "wof:placetype":"venue"
},
  "geometry": {"coordinates":[-115.270797,36.210792],"type":"Point"}
}