{
  "type": "Feature",
  "properties": {
    "iso:country":"US",
    "sg:address":"101 N Mojave Rd",
    "sg:city":"Las Vegas",
    "sg:classifiers":[
        {
            "category":"Wholesale",
            "subcategory":"Construction Materials",
            "type":"Manufacturing & Wholesale Goods"
        }
    ],
    "sg:phone":"+1 702 604 2099",
    "sg:postcode":"89101",
    "sg:province":"NV",
    "wof:name":"Garrett Materials LLC",
    "wof:placetype":"venue"
},
  "geometry": {"coordinates":[-115.105545,36.161602],"type":"Point"}
}