{
  "type": "Feature",
  "properties": {
    "iso:country":"US",
    "sg:address":"Planet Hollywood Casino 3667 Las Vegas Blvd",
    "sg:city":"Las Vegas",
    "sg:classifiers":[
        {
            "category":"Shopping",
            "subcategory":"Adult",
            "type":"Retail Goods"
        }
    ],
    "sg:postcode":"89109",
    "sg:province":"NV",
    "sg:tags":[
        "entertainment"
    ],
    "wof:name":"Pleasure Pit",
    "wof:placetype":"venue"
},
  "geometry": {"coordinates":[-115.16814,36.109952],"type":"Point"}
}