{
  "type": "Feature",
  "properties": {
    "iso:country":"US",
    "sg:address":"2329 Little Bighorn Dr",
    "sg:city":"Henderson",
    "sg:classifiers":[
        {
            "category":"Banks & Credit Unions",
            "subcategory":"Investment Brokerage",
            "type":"Services"
        }
    ],
    "sg:phone":"+1 702 837 6914",
    "sg:postcode":"89052",
    "sg:province":"NV",
    "sg:tags":[
        "advisory",
        "financial"
    ],
    "wof:name":"John T Kuryla Financial Svc",
    "wof:placetype":"venue"
},
  "geometry": {"coordinates":[-115.112737,35.942512],"type":"Point"}
}