{
  "type": "Feature",
  "properties": {
    "iso:country":"US",
    "sg:address":"3061 S Maryland Pkwy",
    "sg:city":"Las Vegas",
    "sg:classifiers":[
        {
            "category":"Health Services",
            "subcategory":"Doctor",
            "type":"Services"
        }
    ],
    "sg:phone":"+1 702 731 0022",
    "sg:postcode":"89109",
    "sg:province":"NV",
    "sg:tags":[
        "cardiologist"
    ],
    "wof:name":"Cohler Larry F MD PHD Facs",
    "wof:placetype":"venue"
},
  "geometry": {"coordinates":[-115.137001,36.133801],"type":"Point"}
}