{
  "type": "Feature",
  "properties": {
    "iso:country":"US",
    "sg:address":"124 S 6th St",
    "sg:city":"Las Vegas",
    "sg:classifiers":[
        {
            "category":"Food & Beverages",
            "subcategory":"Groceries & Convenience Stores",
            "type":"Retail Goods"
        }
    ],
    "sg:phone":"+1 702 869 7952",
    "sg:postcode":"89101",
    "sg:province":"NV",
    "wof:name":"Sidewalk Market",
    "wof:placetype":"venue"
},
  "geometry": {"coordinates":[-115.140169,36.16791],"type":"Point"}
}