{
  "type": "Feature",
  "properties": {
    "iso:country":"US",
    "sg:address":"845 Nevada St",
    "sg:city":"Reno",
    "sg:classifiers":[
        {
            "category":"Real Estate",
            "subcategory":"Real Estate Operator",
            "type":"Services"
        }
    ],
    "sg:phone":"+1 775 322 0371",
    "sg:postcode":"89503",
    "sg:province":"NV",
    "sg:tags":[
        "apartment"
    ],
    "wof:name":"Berger Apartments",
    "wof:placetype":"venue"
},
  "geometry": {"coordinates":[-119.821488,39.534938],"type":"Point"}
}