{
  "type": "Feature",
  "properties": {
    "iso:country":"US",
    "sg:address":"8305 Rocky Meadow Cir",
    "sg:city":"Reno",
    "sg:classifiers":[
        {
            "category":"Retail",
            "subcategory":"Laundry & Dry Cleaning",
            "type":"Services"
        }
    ],
    "sg:phone":"+1 775 351 1002",
    "sg:postcode":"89511",
    "sg:province":"NV",
    "sg:tags":[
        "cleaners",
        "rug",
        "carpet"
    ],
    "wof:name":"National Carpet Care",
    "wof:placetype":"venue"
},
  "geometry": {"coordinates":[-119.77970999999999,39.449578],"type":"Point"}
}