{
  "type": "Feature",
  "properties": {
    "iso:country":"US",
    "sg:address":"Galleria Mall 1300 W Sunset Road # 1225",
    "sg:city":"Henderson",
    "sg:classifiers":[
        {
            "category":"Personal",
            "subcategory":"Hair Removal",
            "type":"Services"
        }
    ],
    "sg:phone":"+1 702 293 6363",
    "sg:postcode":"89014",
    "sg:province":"NV",
    "sg:website":"www.patelsthreading.net",
    "wof:name":"Patel's Threading & Henna Art",
    "wof:placetype":"venue"
},
  "geometry": {"coordinates":[-115.040233,36.063823],"type":"Point"}
}