{
  "type": "Feature",
  "properties": {
    "iso:country":"US",
    "sg:address":"4795 S Durango Dr",
    "sg:city":"Las Vegas",
    "sg:classifiers":[
        {
            "category":"Professional",
            "subcategory":"Lawyer & Legal Services",
            "type":"Services"
        }
    ],
    "sg:phone":"+1 702 877 1500",
    "sg:postcode":"89147",
    "sg:province":"NV",
    "sg:website":"www.glenlerner.com/",
    "wof:name":"Glen J Lerner & Associates",
    "wof:placetype":"venue"
},
  "geometry": {"coordinates":[-115.279674,36.102242],"type":"Point"}
}