{
  "type": "Feature",
  "properties": {
    "iso:country":"US",
    "sg:address":"5325 Louie Ln",
    "sg:city":"Reno",
    "sg:classifiers":[
        {
            "category":"Building & Trades",
            "subcategory":"Construction",
            "type":"Services"
        }
    ],
    "sg:phone":"+1 775 826 6220",
    "sg:postcode":"89511",
    "sg:province":"NV",
    "sg:tags":[
        "roofing",
        "contractor"
    ],
    "wof:name":"Dean & Dunn Roofing LLC",
    "wof:placetype":"venue"
},
  "geometry": {"coordinates":[-119.766974,39.474955],"type":"Point"}
}