{
  "type": "Feature",
  "properties": {
    "iso:country":"US",
    "sg:address":"202 Long Shadow Ter",
    "sg:city":"Henderson",
    "sg:classifiers":[
        {
            "category":"Building & Trades",
            "subcategory":"Cleaning & Sanitation",
            "type":"Services"
        }
    ],
    "sg:phone":"+1 702 558 4245",
    "sg:postcode":"89015",
    "sg:province":"NV",
    "sg:tags":[
        "maintenance"
    ],
    "wof:name":"Verns Cleaning Service",
    "wof:placetype":"venue"
},
  "geometry": {"coordinates":[-114.95291,36.047628],"type":"Point"}
}