{
  "type": "Feature",
  "properties": {
    "iso:country":"US",
    "sg:address":"7670 W Lake Mead Blvd",
    "sg:city":"Las Vegas",
    "sg:classifiers":[
        {
            "category":"Professional",
            "subcategory":"Lawyer & Legal Services",
            "type":"Services"
        }
    ],
    "sg:phone":"+1 702 967 2485",
    "sg:postcode":"89128",
    "sg:province":"NV",
    "wof:name":"Timothy S Menter",
    "wof:placetype":"venue"
},
  "geometry": {"coordinates":[-115.261869,36.196315],"type":"Point"}
}