{
  "type": "Feature",
  "properties": {
    "iso:country":"US",
    "sg:address":"110 W Laval Dr",
    "sg:city":"Henderson",
    "sg:classifiers":[
        {
            "category":"Professional",
            "subcategory":"Business Services",
            "type":"Services"
        }
    ],
    "sg:phone":"+1 702 566 4578",
    "sg:postcode":"89015",
    "sg:province":"NV",
    "wof:name":"W & W Enterprises",
    "wof:placetype":"venue"
},
  "geometry": {"coordinates":[-114.98978700000001,36.025341],"type":"Point"}
}