{
  "type": "Feature",
  "properties": {
    "iso:country":"US",
    "sg:address":"2253 S Rainbow Blvd",
    "sg:city":"Las Vegas",
    "sg:classifiers":[
        {
            "category":"Shopping",
            "subcategory":"Florist",
            "type":"Retail Goods"
        }
    ],
    "sg:phone":"+1 702 737 7077",
    "sg:postcode":"89146",
    "sg:province":"NV",
    "sg:tags":[
        "personal"
    ],
    "sg:website":"www.wesendemotions.com",
    "wof:name":"Tiger Lily Flower Shop The",
    "wof:placetype":"venue"
},
  "geometry": {"coordinates":[-115.243146,36.147436],"type":"Point"}
}