{
  "type": "Feature",
  "properties": {
    "iso:country":"US",
    "sg:address":"4255 Spring Mountain Rd",
    "sg:city":"Las Vegas",
    "sg:classifiers":[
        {
            "category":"Shopping",
            "subcategory":"Jewelry",
            "type":"Retail Goods"
        }
    ],
    "sg:phone":"+1 702 227 9198",
    "sg:postcode":"89102",
    "sg:province":"NV",
    "sg:tags":[
        "jade"
    ],
    "wof:name":"Jana's Jade Gallery",
    "wof:placetype":"venue"
},
  "geometry": {"coordinates":[-115.19906,36.126257],"type":"Point"}
}