{
  "type": "Feature",
  "properties": {
    "iso:country":"US",
    "sg:address":"3300 Las Vegas Blvd S",
    "sg:city":"Las Vegas",
    "sg:classifiers":[
        {
            "category":"Organizations",
            "subcategory":"Community Association",
            "type":"Services"
        }
    ],
    "sg:phone":"+1 702 894 7390",
    "sg:postcode":"89109",
    "sg:province":"NV",
    "sg:tags":[
        "bar"
    ],
    "wof:name":"Kahunaville of Las Vegas Inc",
    "wof:placetype":"venue"
},
  "geometry": {"coordinates":[-115.172937,36.116715],"type":"Point"}
}