{
  "type": "Feature",
  "properties": {
    "iso:country":"US",
    "sg:address":"208 Delamar St",
    "sg:city":"Las Vegas",
    "sg:classifiers":[
        {
            "category":"Organizations",
            "subcategory":"Community Association",
            "type":"Services"
        }
    ],
    "sg:phone":"+1 702 648 8945",
    "sg:postcode":"89107",
    "sg:province":"NV",
    "wof:name":"Society For Preservation of AR",
    "wof:placetype":"venue"
},
  "geometry": {"coordinates":[-115.177544,36.177223],"type":"Point"}
}