{
  "type": "Feature",
  "properties": {
    "iso:country":"US",
    "sg:address":"191 S Frontage Rd",
    "sg:city":"Pahrump",
    "sg:classifiers":[
        {
            "category":"Insurance",
            "subcategory":"Insurance Agent",
            "type":"Services"
        }
    ],
    "sg:phone":"+1 775 727 5700",
    "sg:postcode":"89048",
    "sg:province":"NV",
    "wof:name":"Pahrump Valley Insurance",
    "wof:placetype":"venue"
},
  "geometry": {"coordinates":[-115.994789,36.222338],"type":"Point"}
}