{
  "type": "Feature",
  "properties": {
    "iso:country":"US",
    "sg:address":"3225 S Rainbow Blvd",
    "sg:city":"Las Vegas",
    "sg:classifiers":[
        {
            "category":"Banks & Credit Unions",
            "subcategory":"Financial Services",
            "type":"Services"
        }
    ],
    "sg:phone":"+1 702 248 8800",
    "sg:postcode":"89146",
    "sg:province":"NV",
    "sg:tags":[
        "company",
        "holding"
    ],
    "wof:name":"Field Stone Investments",
    "wof:placetype":"venue"
},
  "geometry": {"coordinates":[-115.243053,36.12992],"type":"Point"}
}