{
  "type": "Feature",
  "properties": {
    "iso:country":"US",
    "sg:address":"775 W Craig Rd Ste 156",
    "sg:city":"North Las Vegas",
    "sg:classifiers":[
        {
            "category":"Shopping",
            "subcategory":"Beauty & Cosmetics",
            "type":"Retail Goods"
        }
    ],
    "sg:phone":"+1 702 258 2843",
    "sg:postcode":"89032",
    "sg:province":"NV",
    "sg:tags":[
        "supply"
    ],
    "wof:name":"Attitudes 2 Supply & Salon",
    "wof:placetype":"venue"
},
  "geometry": {"coordinates":[-115.15373099999999,36.239213],"type":"Point"}
}