{
  "type": "Feature",
  "properties": {
    "iso:country":"US",
    "sg:address":"526 S Tonopah Dr",
    "sg:city":"Las Vegas",
    "sg:classifiers":[
        {
            "category":"Health Services",
            "subcategory":"Doctor",
            "type":"Services"
        }
    ],
    "sg:phone":"+1 702 258 7788",
    "sg:postcode":"89106",
    "sg:province":"NV",
    "sg:tags":[
        "medical"
    ],
    "wof:name":"Nevada Surgical Group",
    "wof:placetype":"venue"
},
  "geometry": {"coordinates":[-115.17002100000001,36.164417],"type":"Point"}
}