{
  "type": "Feature",
  "properties": {
    "iso:country":"US",
    "sg:address":"85 E Agate Ave",
    "sg:city":"Las Vegas",
    "sg:classifiers":[
        {
            "category":"Building & Trades",
            "subcategory":"Plumbing",
            "type":"Services"
        }
    ],
    "sg:phone":"+1 702 263 0607",
    "sg:postcode":"89123",
    "sg:province":"NV",
    "sg:tags":[
        "conditioning",
        "air",
        "system",
        "contractor"
    ],
    "wof:name":"Interstate Plumbing & Air Cond",
    "wof:placetype":"venue"
},
  "geometry": {"coordinates":[-115.169061,36.024589],"type":"Point"}
}