{
  "type": "Feature",
  "properties": {
    "iso:country":"US",
    "sg:address":"8144 Guava Nectar Ave",
    "sg:city":"Las Vegas",
    "sg:classifiers":[
        {
            "category":"Real Estate",
            "subcategory":"Real Estate Agent",
            "type":"Services"
        }
    ],
    "sg:phone":"+1 702 395 0630",
    "sg:postcode":"89131",
    "sg:province":"NV",
    "wof:name":"LCR Appraisal",
    "wof:placetype":"venue"
},
  "geometry": {"coordinates":[-115.272807,36.29746],"type":"Point"}
}