{
  "type": "Feature",
  "properties": {
    "iso:country":"US",
    "sg:address":"320 S 1st St",
    "sg:city":"Las Vegas",
    "sg:classifiers":[
        {
            "category":"Social Services",
            "type":"Services"
        }
    ],
    "sg:phone":"+1 702 385 9895",
    "sg:postcode":"89101",
    "sg:province":"NV",
    "sg:tags":[
        "house",
        "run",
        "halfway"
    ],
    "wof:name":"Clark Center",
    "wof:placetype":"venue"
},
  "geometry": {"coordinates":[-115.147405,36.167971],"type":"Point"}
}