{
  "type": "Feature",
  "properties": {
    "iso:country":"US",
    "sg:address":"900 Doolittle Ave",
    "sg:city":"Las Vegas",
    "sg:classifiers":[
        {
            "category":"Real Estate",
            "subcategory":"Real Estate Operator",
            "type":"Services"
        }
    ],
    "sg:phone":"+1 702 631 4949",
    "sg:postcode":"89106",
    "sg:province":"NV",
    "sg:tags":[
        "building",
        "apartment"
    ],
    "wof:name":"Sunset Palms Apartments",
    "wof:placetype":"venue"
},
  "geometry": {"coordinates":[-115.153378,36.192113],"type":"Point"}
}