{
  "type": "Feature",
  "properties": {
    "iso:country":"US",
    "sg:address":"405 Lovitt Ln",
    "sg:city":"Reno",
    "sg:classifiers":[
        {
            "category":"Building & Trades",
            "subcategory":"Construction",
            "type":"Services"
        }
    ],
    "sg:phone":"+1 775 322 0346",
    "sg:postcode":"89506",
    "sg:province":"NV",
    "sg:tags":[
        "painter"
    ],
    "wof:name":"Olympus & Assoc",
    "wof:placetype":"venue"
},
  "geometry": {"coordinates":[-119.820019,39.571599],"type":"Point"}
}