{
  "type": "Feature",
  "properties": {
    "iso:country":"US",
    "sg:address":"2632 Las Vegas Blvd N",
    "sg:city":"North Las Vegas",
    "sg:classifiers":[
        {
            "category":"Retail",
            "subcategory":"Auto Repair",
            "type":"Services"
        }
    ],
    "sg:phone":"+1 702 399 6292",
    "sg:postcode":"89030",
    "sg:province":"NV",
    "wof:name":"Royalty Auto Services",
    "wof:placetype":"venue"
},
  "geometry": {"coordinates":[-115.110001,36.2075],"type":"Point"}
}