{
  "type": "Feature",
  "properties": {
    "iso:country":"US",
    "sg:address":"32 Stokes Dr",
    "sg:city":"Mound House",
    "sg:classifiers":[
        {
            "category":"Mining & Drilling",
            "type":"Manufacturing & Wholesale Goods"
        }
    ],
    "sg:phone":"+1 775 246 0296",
    "sg:postcode":"89706",
    "sg:province":"NV",
    "sg:tags":[
        "metal"
    ],
    "wof:name":"Boart Longyear Co",
    "wof:placetype":"venue"
},
  "geometry": {"coordinates":[-119.657332,39.228463],"type":"Point"}
}