{
  "type": "Feature",
  "properties": {
    "iso:country":"US",
    "sg:address":"1607 Greg St",
    "sg:city":"Sparks",
    "sg:classifiers":[
        {
            "category":"Professional",
            "type":"Services"
        }
    ],
    "sg:phone":"+1 775 358 3788",
    "sg:postcode":"89431",
    "sg:province":"NV",
    "sg:tags":[
        "establishment"
    ],
    "wof:name":"Sierra Healthsearch",
    "wof:placetype":"venue"
},
  "geometry": {"coordinates":[-119.76746900000001,39.523409],"type":"Point"}
}