{
  "type": "Feature",
  "properties": {
    "iso:country":"US",
    "sg:address":"4410 N Rancho Dr",
    "sg:city":"Las Vegas",
    "sg:classifiers":[
        {
            "category":"Building & Trades",
            "subcategory":"Construction",
            "type":"Services"
        }
    ],
    "sg:phone":"+1 702 645 5401",
    "sg:postcode":"89130",
    "sg:province":"NV",
    "sg:tags":[
        "house"
    ],
    "wof:name":"Nevada Delco Construction",
    "wof:placetype":"venue"
},
  "geometry": {"coordinates":[-115.234554,36.241808],"type":"Point"}
}