{
  "type": "Feature",
  "properties": {
    "iso:country":"US",
    "sg:address":"1860 Wendy Way",
    "sg:city":"Reno",
    "sg:classifiers":[
        {
            "category":"Professional",
            "subcategory":"Business Services",
            "type":"Services"
        }
    ],
    "sg:phone":"+1 775 828 9958",
    "sg:postcode":"89509",
    "sg:province":"NV",
    "wof:name":"Borhani March & Assoc",
    "wof:placetype":"venue"
},
  "geometry": {"coordinates":[-119.814092,39.485409],"type":"Point"}
}