{
  "type": "Feature",
  "properties": {
    "iso:country":"US",
    "sg:address":"4300 Las Vegas Blvd N",
    "sg:city":"Las Vegas",
    "sg:classifiers":[
        {
            "category":"Organizations",
            "subcategory":"Religious Organization",
            "type":"Services"
        }
    ],
    "sg:phone":"+1 702 644 1055",
    "sg:postcode":"89115",
    "sg:province":"NV",
    "sg:tags":[
        "church"
    ],
    "wof:name":"Nellis Baptist Church",
    "wof:placetype":"venue"
},
  "geometry": {"coordinates":[-115.059135,36.237198],"type":"Point"}
}