{
  "type": "Feature",
  "properties": {
    "iso:country":"US",
    "sg:address":"4590 Tosco Dr",
    "sg:city":"Reno",
    "sg:classifiers":[
        {
            "category":"Real Estate",
            "subcategory":"Developer",
            "type":"Services"
        },
        {
            "category":"Building & Trades",
            "subcategory":"Construction",
            "type":"Services"
        }
    ],
    "sg:phone":"+1 775 825 5275",
    "sg:postcode":"89509",
    "sg:province":"NV",
    "sg:tags":[
        "house"
    ],
    "wof:name":"Strada Fiorita",
    "wof:placetype":"venue"
},
  "geometry": {"coordinates":[-119.83862999999999,39.479212],"type":"Point"}
}