{
  "type": "Feature",
  "properties": {
    "iso:country":"US",
    "sg:address":"2250 S Carson St",
    "sg:city":"Carson City",
    "sg:classifiers":[
        {
            "category":"Retail",
            "subcategory":"Auto Repair",
            "type":"Services"
        }
    ],
    "sg:phone":"+1 775 882 2300",
    "sg:postcode":"89701",
    "sg:province":"NV",
    "sg:tags":[
        "repairing",
        "automobile"
    ],
    "wof:name":"Brake Team",
    "wof:placetype":"venue"
},
  "geometry": {"coordinates":[-119.767059,39.148707],"type":"Point"}
}