{
  "type": "Feature",
  "properties": {
    "iso:country":"US",
    "sg:address":"750 Freeport Blvd",
    "sg:city":"Sparks",
    "sg:classifiers":[
        {
            "category":"Wholesale",
            "subcategory":"Electrical",
            "type":"Manufacturing & Wholesale Goods"
        }
    ],
    "sg:phone":"+1 775 358 7272",
    "sg:postcode":"89431",
    "sg:province":"NV",
    "sg:tags":[
        "electronic"
    ],
    "wof:name":"Aamp of America",
    "wof:placetype":"venue"
},
  "geometry": {"coordinates":[-119.75338499999999,39.525552],"type":"Point"}
}