{
  "type": "Feature",
  "properties": {
    "iso:country":"US",
    "sg:address":"2121 N Jones Blvd",
    "sg:city":"Las Vegas",
    "sg:classifiers":[
        {
            "category":"Real Estate",
            "subcategory":"Real Estate Operator",
            "type":"Services"
        }
    ],
    "sg:phone":"+1 866 984 5428",
    "sg:postcode":"89108",
    "sg:province":"NV",
    "sg:tags":[
        "apartment"
    ],
    "sg:website":"apartments.camdenliving.com/las-...",
    "wof:name":"Camden Hills",
    "wof:placetype":"venue"
},
  "geometry": {"coordinates":[-115.222539,36.197891],"type":"Point"}
}