{
  "type": "Feature",
  "properties": {
    "iso:country":"US",
    "sg:address":"6947 Speedway Blvd",
    "sg:city":"Las Vegas",
    "sg:classifiers":[
        {
            "category":"Building & Trades",
            "subcategory":"Electrical",
            "type":"Services"
        }
    ],
    "sg:phone":"+1 702 597 9677",
    "sg:postcode":"89115",
    "sg:province":"NV",
    "sg:tags":[
        "electric",
        "contractor"
    ],
    "wof:name":"G & M Whitney Electric",
    "wof:placetype":"venue"
},
  "geometry": {"coordinates":[-115.019956,36.279165],"type":"Point"}
}