{
  "type": "Feature",
  "properties": {
    "iso:country":"US",
    "sg:address":"8628 Canyon View Dr",
    "sg:city":"Las Vegas",
    "sg:classifiers":[
        {
            "category":"Building & Trades",
            "subcategory":"Construction",
            "type":"Services"
        }
    ],
    "sg:phone":"+1 702 341 1606",
    "sg:postcode":"89117",
    "sg:province":"NV",
    "sg:tags":[
        "hanging",
        "contractor"
    ],
    "wof:name":"Prestige Painting Contractors",
    "wof:placetype":"venue"
},
  "geometry": {"coordinates":[-115.281764,36.149875],"type":"Point"}
}