{
  "type": "Feature",
  "properties": {
    "iso:country":"US",
    "sg:address":"10301 Jeffreys St",
    "sg:city":"Henderson",
    "sg:classifiers":[
        {
            "category":"Health Services",
            "subcategory":"Doctor",
            "type":"Services"
        }
    ],
    "sg:phone":"+1 702 939 9416",
    "sg:postcode":"89052",
    "sg:province":"NV",
    "sg:tags":[
        "physician",
        "surgeon"
    ],
    "wof:name":"Rehabilitation Specialists",
    "wof:placetype":"venue"
},
  "geometry": {"coordinates":[-115.119106,36.001208],"type":"Point"}
}