{
  "type": "Feature",
  "properties": {
    "iso:country":"US",
    "sg:address":"8555 W Sahara Ave",
    "sg:city":"Las Vegas",
    "sg:classifiers":[
        {
            "category":"Shopping",
            "type":"Retail Goods"
        }
    ],
    "sg:phone":"+1 702 233 3350",
    "sg:postcode":"89117",
    "sg:province":"NV",
    "sg:tags":[
        "telephone",
        "cellular"
    ],
    "wof:name":"Las Vegas Oil",
    "wof:placetype":"venue"
},
  "geometry": {"coordinates":[-115.276062,36.143958],"type":"Point"}
}