{
  "type": "Feature",
  "properties": {
    "iso:country":"US",
    "sg:address":"917 Tahoe Blvd",
    "sg:city":"Incline Village",
    "sg:classifiers":[
        {
            "category":"Professional",
            "subcategory":"Management & Consulting",
            "type":"Services"
        }
    ],
    "sg:phone":"+1 775 832 5533",
    "sg:postcode":"89451",
    "sg:province":"NV",
    "sg:tags":[
        "consultant",
        "business"
    ],
    "wof:name":"TGR LTD",
    "wof:placetype":"venue"
},
  "geometry": {"coordinates":[-119.950227,39.249503],"type":"Point"}
}