{
  "type": "Feature",
  "properties": {
    "iso:country":"US",
    "sg:address":"690 Booth St",
    "sg:city":"Reno",
    "sg:classifiers":[
        {
            "category":"Food & Beverages",
            "subcategory":"Groceries & Convenience Stores",
            "type":"Retail Goods"
        }
    ],
    "sg:phone":"+1 775 323 4711",
    "sg:postcode":"89509",
    "sg:province":"NV",
    "wof:name":"7-Eleven",
    "wof:placetype":"venue"
},
  "geometry": {"coordinates":[-119.826375,39.515885],"type":"Point"}
}