{
  "type": "Feature",
  "properties": {
    "iso:country":"US",
    "sg:address":"1841 Longmeadow St",
    "sg:city":"Henderson",
    "sg:classifiers":[
        {
            "category":"Shopping",
            "subcategory":"Computers & Home Electronics",
            "type":"Retail Goods"
        }
    ],
    "sg:phone":"+1 702 564 8155",
    "sg:postcode":"89002",
    "sg:province":"NV",
    "sg:tags":[
        "software"
    ],
    "wof:name":"Phoenix Computers",
    "wof:placetype":"venue"
},
  "geometry": {"coordinates":[-114.935693,36.010443],"type":"Point"}
}