{
  "type": "Feature",
  "properties": {
    "iso:country":"US",
    "sg:address":"1736 W Charleston Blvd",
    "sg:city":"Las Vegas",
    "sg:classifiers":[
        {
            "category":"Arena",
            "subcategory":"Sports Club",
            "type":"Entertainment"
        }
    ],
    "sg:phone":"+1 702 433 0111",
    "sg:postcode":"89102",
    "sg:province":"NV",
    "sg:tags":[
        "manager",
        "recruiter",
        "promoter"
    ],
    "sg:website":"www.csaprepstar.com",
    "wof:name":"Collegiate Sports-America Prep",
    "wof:placetype":"venue"
},
  "geometry": {"coordinates":[-115.162641,36.158947],"type":"Point"}
}