{
  "type": "Feature",
  "properties": {
    "iso:country":"US",
    "sg:address":"5740 S Eastern Ave Ste 121",
    "sg:city":"Las Vegas",
    "sg:classifiers":[
        {
            "category":"Real Estate",
            "subcategory":"Architect",
            "type":"Services"
        }
    ],
    "sg:phone":"+1 702 933 4000",
    "sg:postcode":"89119",
    "sg:province":"NV",
    "wof:name":"Frch Design Worldwide-Lv",
    "wof:placetype":"venue"
},
  "geometry": {"coordinates":[-115.118689,36.08536],"type":"Point"}
}