{
  "type": "Feature",
  "properties": {
    "iso:country":"US",
    "sg:address":"122 W 2nd St",
    "sg:city":"Reno",
    "sg:classifiers":[
        {
            "category":"Personal",
            "subcategory":"Beauty Salon",
            "type":"Services"
        }
    ],
    "sg:phone":"+1 775 657 8688",
    "sg:postcode":"89501",
    "sg:province":"NV",
    "wof:name":"Aprez Salon And Spa",
    "wof:placetype":"venue"
},
  "geometry": {"coordinates":[-119.81488400000001,39.526632],"type":"Point"}
}