{
  "type": "Feature",
  "properties": {
    "iso:country":"US",
    "sg:address":"1105 Holliston Cir",
    "sg:city":"Las Vegas",
    "sg:classifiers":[
        {
            "category":"Professional",
            "subcategory":"Management & Consulting",
            "type":"Services"
        }
    ],
    "sg:phone":"+1 702 636 0054",
    "sg:postcode":"89108",
    "sg:province":"NV",
    "sg:tags":[
        "environmental"
    ],
    "wof:name":"Environments West",
    "wof:placetype":"venue"
},
  "geometry": {"coordinates":[-115.231866,36.183018],"type":"Point"}
}