{
  "type": "Feature",
  "properties": {
    "iso:country":"US",
    "sg:address":"9405 S Eastern Ave",
    "sg:city":"Las Vegas",
    "sg:classifiers":[
        {
            "category":"Travel",
            "subcategory":"Travel Agent",
            "type":"Entertainment"
        }
    ],
    "sg:phone":"+1 702 270 3159",
    "sg:postcode":"89123",
    "sg:province":"NV",
    "sg:tags":[
        "agency",
        "bureau"
    ],
    "wof:name":"West Coast Intl",
    "wof:placetype":"venue"
},
  "geometry": {"coordinates":[-115.118742,36.018414],"type":"Point"}
}