{
  "type": "Feature",
  "properties": {
    "iso:country":"US",
    "sg:address":"2548 Sunrise Dr",
    "sg:city":"Elko",
    "sg:classifiers":[
        {
            "category":"Wholesale",
            "subcategory":"Office Equipment",
            "type":"Manufacturing & Wholesale Goods"
        }
    ],
    "sg:phone":"+1 775 738 4664",
    "sg:postcode":"89801",
    "sg:province":"NV",
    "wof:name":"Opi",
    "wof:placetype":"venue"
},
  "geometry": {"coordinates":[-115.739459,40.832939],"type":"Point"}
}