{
  "type": "Feature",
  "properties": {
    "iso:country":"US",
    "sg:address":"2545 Chandler Ave",
    "sg:city":"Las Vegas",
    "sg:classifiers":[
        {
            "category":"Home & Garden",
            "subcategory":"Building Materials",
            "type":"Retail Goods"
        }
    ],
    "sg:phone":"+1 702 897 1999",
    "sg:postcode":"89120",
    "sg:province":"NV",
    "sg:tags":[
        "glass",
        "window",
        "plate"
    ],
    "wof:name":"Glass Connection",
    "wof:placetype":"venue"
},
  "geometry": {"coordinates":[-115.11465,36.073974],"type":"Point"}
}