{
  "type": "Feature",
  "properties": {
    "iso:country":"US",
    "sg:address":"2101 S Jones Blvd",
    "sg:city":"Las Vegas",
    "sg:classifiers":[
        {
            "category":"Real Estate",
            "subcategory":"Architect",
            "type":"Services"
        }
    ],
    "sg:phone":"+1 702 834 6200",
    "sg:postcode":"89146",
    "sg:province":"NV",
    "sg:website":"www.philipchun.com",
    "wof:name":"Philip Chun",
    "wof:placetype":"venue"
},
  "geometry": {"coordinates":[-115.225628,36.148003],"type":"Point"}
}