{
  "type": "Feature",
  "properties": {
    "iso:country":"US",
    "sg:address":"1068 Nordyke Ave",
    "sg:city":"Henderson",
    "sg:classifiers":[
        {
            "category":"Professional",
            "subcategory":"Art Services",
            "type":"Services"
        }
    ],
    "sg:phone":"+1 702 433 6775",
    "sg:postcode":"89015",
    "sg:province":"NV",
    "sg:tags":[
        "photographer"
    ],
    "sg:website":"www.bellavitaphoto.com",
    "wof:name":"Bella Vita Photography",
    "wof:placetype":"venue"
},
  "geometry": {"coordinates":[-114.94628,36.015181],"type":"Point"}
}