{
  "type": "Feature",
  "properties": {
    "iso:country":"US",
    "sg:address":"4205 W Tompkins Ave",
    "sg:city":"Las Vegas",
    "sg:classifiers":[
        {
            "category":"Wholesale",
            "subcategory":"Hardware",
            "type":"Manufacturing & Wholesale Goods"
        }
    ],
    "sg:phone":"+1 702 222 0466",
    "sg:postcode":"89103",
    "sg:province":"NV",
    "sg:tags":[
        "fastener"
    ],
    "wof:name":"White Cap",
    "wof:placetype":"venue"
},
  "geometry": {"coordinates":[-115.197738,36.104618],"type":"Point"}
}