{
  "type": "Feature",
  "properties": {
    "iso:country":"US",
    "sg:address":"10120 S Eastern Ave Suite 200",
    "sg:city":"Henderson",
    "sg:classifiers":[
        {
            "category":"Professional",
            "subcategory":"Advertising",
            "type":"Services"
        }
    ],
    "sg:phone":"+1 888 548 6661",
    "sg:postcode":"89052",
    "sg:province":"NV",
    "sg:website":"http://sellsmartfast.com",
    "wof:name":"Sell Smart Fast",
    "wof:placetype":"venue"
},
  "geometry": {"coordinates":[-115.112787,36.006213],"type":"Point"}
}