{
  "type": "Feature",
  "properties": {
    "iso:country":"US",
    "sg:address":"1319 Nevada Hwy",
    "sg:city":"Boulder City",
    "sg:classifiers":[
        {
            "category":"Building & Trades",
            "subcategory":"Construction",
            "type":"Services"
        }
    ],
    "sg:phone":"+1 702 293 5650",
    "sg:postcode":"89005",
    "sg:province":"NV",
    "sg:tags":[
        "roofing",
        "contractor"
    ],
    "wof:name":"Black Canyon Roofing",
    "wof:placetype":"venue"
},
  "geometry": {"coordinates":[-114.850934,35.971087],"type":"Point"}
}