{
  "type": "Feature",
  "properties": {
    "iso:country":"US",
    "sg:address":"801 S Center St",
    "sg:city":"Reno",
    "sg:classifiers":[
        {
            "category":"Home & Garden",
            "subcategory":"Building Materials",
            "type":"Retail Goods"
        },
        {
            "category":"Home & Garden",
            "subcategory":"Carpets & Floor Coverings",
            "type":"Retail Goods"
        }
    ],
    "sg:phone":"+1 775 323 4977",
    "sg:postcode":"89501",
    "sg:province":"NV",
    "sg:tags":[
        "hardwood",
        "laying",
        "contractor"
    ],
    "wof:name":"Teak & Hardwood Floors",
    "wof:placetype":"venue"
},
  "geometry": {"coordinates":[-119.807227,39.51687],"type":"Point"}
}