{
  "type": "Feature",
  "properties": {
    "iso:country":"US",
    "sg:address":"2928 Belmont Dr",
    "sg:city":"Henderson",
    "sg:classifiers":[
        {
            "category":"Building & Trades",
            "subcategory":"Cleaning & Sanitation",
            "type":"Services"
        }
    ],
    "sg:phone":"+1 702 736 5746",
    "sg:postcode":"89074",
    "sg:province":"NV",
    "sg:tags":[
        "home"
    ],
    "wof:name":"Santa Fe Housecleaning Service",
    "wof:placetype":"venue"
},
  "geometry": {"coordinates":[-115.111,36.019699],"type":"Point"}
}