{
  "type": "Feature",
  "properties": {
    "iso:country":"US",
    "sg:address":"1486 Rock Island Ln",
    "sg:city":"Las Vegas",
    "sg:classifiers":[
        {
            "category":"Building & Trades",
            "subcategory":"Cleaning & Sanitation",
            "type":"Services"
        }
    ],
    "sg:phone":"+1 702 365 5770",
    "sg:postcode":"89110",
    "sg:province":"NV",
    "sg:tags":[
        "maintenance"
    ],
    "wof:name":"Grand View Window Service",
    "wof:placetype":"venue"
},
  "geometry": {"coordinates":[-115.04752,36.187656],"type":"Point"}
}