{
  "type": "Feature",
  "properties": {
    "iso:country":"US",
    "sg:address":"754 Mays Blvd",
    "sg:city":"Incline Village",
    "sg:classifiers":[
        {
            "category":"Insurance",
            "subcategory":"Insurance Agent",
            "type":"Services"
        }
    ],
    "sg:phone":"+1 775 831 3773",
    "sg:postcode":"89451",
    "sg:province":"NV",
    "wof:name":"Allstate Insurance",
    "wof:placetype":"venue"
},
  "geometry": {"coordinates":[-119.96249899999999,39.246936],"type":"Point"}
}