{
  "type": "Feature",
  "properties": {
    "iso:country":"US",
    "sg:address":"5423 Winston Dr",
    "sg:city":"Las Vegas",
    "sg:classifiers":[
        {
            "category":"Cinema",
            "subcategory":"Movie Rental",
            "type":"Entertainment"
        }
    ],
    "sg:phone":"+1 702 871 1371",
    "sg:postcode":"89103",
    "sg:province":"NV",
    "sg:tags":[
        "video",
        "tape"
    ],
    "wof:name":"Raimon Enterprises",
    "wof:placetype":"venue"
},
  "geometry": {"coordinates":[-115.213927,36.120302],"type":"Point"}
}