{
  "type": "Feature",
  "properties": {
    "iso:country":"US",
    "sg:address":"333 Flint St",
    "sg:city":"Reno",
    "sg:classifiers":[
        {
            "category":"Arts & Performance",
            "subcategory":"Theater",
            "type":"Entertainment"
        }
    ],
    "sg:phone":"+1 775 322 0606",
    "sg:postcode":"89501",
    "sg:province":"NV",
    "sg:tags":[
        "dance",
        "company"
    ],
    "wof:name":"Nevada Ballet Theatre",
    "wof:placetype":"venue"
},
  "geometry": {"coordinates":[-119.81525,39.521271],"type":"Point"}
}