{
  "type": "Feature",
  "properties": {
    "iso:country":"US",
    "sg:address":"909 W Long St",
    "sg:city":"Carson City",
    "sg:classifiers":[
        {
            "category":"Wholesale",
            "subcategory":"Machinery & Supplies",
            "type":"Manufacturing & Wholesale Goods"
        }
    ],
    "sg:phone":"+1 775 883 6108",
    "sg:postcode":"89703",
    "sg:province":"NV",
    "sg:tags":[
        "industrial"
    ],
    "wof:name":"Industrial Plastic Valves Inc",
    "wof:placetype":"venue"
},
  "geometry": {"coordinates":[-119.773939,39.174007],"type":"Point"}
}