{
  "type": "Feature",
  "properties": {
    "iso:country":"US",
    "sg:address":"620 Tahoe St",
    "sg:city":"Reno",
    "sg:classifiers":[
        {
            "category":"Real Estate",
            "subcategory":"Developer",
            "type":"Services"
        }
    ],
    "sg:phone":"+1 775 425 6465",
    "sg:postcode":"89509",
    "sg:province":"NV",
    "wof:name":"Murphy Homes",
    "wof:placetype":"venue"
},
  "geometry": {"coordinates":[-119.811065,39.518918],"type":"Point"}
}