{
  "type": "Feature",
  "properties": {
    "iso:country":"US",
    "sg:address":"5162 Winston St",
    "sg:city":"Las Vegas",
    "sg:classifiers":[
        {
            "category":"Retail",
            "subcategory":"Laundry & Dry Cleaning",
            "type":"Services"
        }
    ],
    "sg:phone":"+1 702 227 9404",
    "sg:postcode":"89103",
    "sg:province":"NV",
    "sg:tags":[
        "cleaners",
        "rug",
        "carpet"
    ],
    "wof:name":"Premier Carpet Cleaning",
    "wof:placetype":"venue"
},
  "geometry": {"coordinates":[-115.210717,36.120376],"type":"Point"}
}