{
  "type": "Feature",
  "properties": {
    "iso:country":"US",
    "sg:address":"8126 Villa del Viento Dr",
    "sg:city":"Las Vegas",
    "sg:classifiers":[
        {
            "category":"Shopping",
            "type":"Retail Goods"
        }
    ],
    "sg:phone":"+1 702 228 8707",
    "sg:postcode":"89131",
    "sg:province":"NV",
    "sg:tags":[
        "merchandise"
    ],
    "wof:name":"A1 Pet Waste Removal Service",
    "wof:placetype":"venue"
},
  "geometry": {"coordinates":[-115.262823,36.307692],"type":"Point"}
}