{
  "type": "Feature",
  "properties": {
    "iso:country":"US",
    "sg:address":"5380 S Rainbow Boulevard Suite 200",
    "sg:city":"Las Vegas",
    "sg:classifiers":[
        {
            "category":"Health Services",
            "subcategory":"Doctor",
            "type":"Services"
        }
    ],
    "sg:phone":"+1 702 382 6100",
    "sg:postcode":"89118",
    "sg:province":"NV",
    "sg:tags":[
        "practice",
        "family"
    ],
    "wof:name":"Valley Primary Care Center",
    "wof:placetype":"venue"
},
  "geometry": {"coordinates":[-115.242881,36.09099],"type":"Point"}
}