{
  "type": "Feature",
  "properties": {
    "iso:country":"US",
    "sg:address":"3400 Rand Ln",
    "sg:city":"Pahrump",
    "sg:classifiers":[
        {
            "category":"Building & Trades",
            "subcategory":"Construction",
            "type":"Services"
        }
    ],
    "sg:phone":"+1 775 751 0992",
    "sg:postcode":"89060",
    "sg:province":"NV",
    "sg:tags":[
        "utility",
        "contractor"
    ],
    "wof:name":"Utility Readers LTD",
    "wof:placetype":"venue"
},
  "geometry": {"coordinates":[-116.073338,36.236929],"type":"Point"}
}