{
  "type": "Feature",
  "properties": {
    "iso:country":"US",
    "sg:address":"2555 E Tropicana Ave",
    "sg:city":"Las Vegas",
    "sg:classifiers":[
        {
            "category":"Home & Garden",
            "subcategory":"Furniture",
            "type":"Retail Goods"
        }
    ],
    "sg:phone":"+1 702 451 4488",
    "sg:postcode":"89121",
    "sg:province":"NV",
    "sg:tags":[
        "specializing",
        "futon"
    ],
    "wof:name":"Futon Lifestyle Furniture",
    "wof:placetype":"venue"
},
  "geometry": {"coordinates":[-115.116495,36.09987],"type":"Point"}
}