{
  "type": "Feature",
  "properties": {
    "iso:country":"US",
    "sg:address":"1000 Irma Ln",
    "sg:city":"Gardnerville",
    "sg:classifiers":[
        {
            "category":"Building & Trades",
            "subcategory":"Construction",
            "type":"Services"
        }
    ],
    "sg:phone":"+1 775 265 8854",
    "sg:postcode":"89460",
    "sg:province":"NV",
    "sg:tags":[
        "house"
    ],
    "wof:name":"Plimpton Bros Construction",
    "wof:placetype":"venue"
},
  "geometry": {"coordinates":[-119.810378,38.912718],"type":"Point"}
}