{
  "type": "Feature",
  "properties": {
    "iso:country":"US",
    "sg:address":"3155 East Patrick Ln Suite 11",
    "sg:city":"Las Vegas",
    "sg:classifiers":[
        {
            "category":"Real Estate",
            "subcategory":"Real Estate Services",
            "type":"Services"
        }
    ],
    "sg:phone":"+1 702 416 0087",
    "sg:postcode":"89136",
    "sg:province":"NV",
    "wof:name":"United Patrick Enterprises, Inc.",
    "wof:placetype":"venue"
},
  "geometry": {"coordinates":[-115.106195,36.079011],"type":"Point"}
}