{
  "type": "Feature",
  "properties": {
    "iso:country":"US",
    "sg:address":"7636 Flourish Springs St",
    "sg:city":"Las Vegas",
    "sg:classifiers":[
        {
            "category":"Professional",
            "subcategory":"Art Services",
            "type":"Services"
        }
    ],
    "sg:phone":"+1 702 334 5993",
    "sg:postcode":"89131",
    "sg:province":"NV",
    "sg:tags":[
        "photographer"
    ],
    "wof:name":"Angela Quick Photography",
    "wof:placetype":"venue"
},
  "geometry": {"coordinates":[-115.2642,36.299126],"type":"Point"}
}