{
  "type": "Feature",
  "properties": {
    "iso:country":"US",
    "sg:address":"450 Marsh Ave",
    "sg:city":"Reno",
    "sg:classifiers":[
        {
            "category":"Utilities",
            "subcategory":"Telephone",
            "type":"Services"
        }
    ],
    "sg:phone":"+1 775 284 8324",
    "sg:postcode":"89509",
    "sg:province":"NV",
    "sg:tags":[
        "telecommunication"
    ],
    "sg:website":"www.renosupport.com",
    "wof:name":"Avery Communications",
    "wof:placetype":"venue"
},
  "geometry": {"coordinates":[-119.816991,39.518943],"type":"Point"}
}