{
  "type": "Feature",
  "properties": {
    "iso:country":"US",
    "sg:address":"7370 Dean Martin Dr Ste 405",
    "sg:city":"Las Vegas",
    "sg:classifiers":[
        {
            "category":"Shopping",
            "subcategory":"Stationery & Office Supplies",
            "type":"Retail Goods"
        }
    ],
    "sg:phone":"+1 702 369 9401",
    "sg:postcode":"89139",
    "sg:province":"NV",
    "sg:tags":[
        "equipment"
    ],
    "sg:website":"www.lasvegasofficefurniture.net",
    "wof:name":"Las Vegas Office Furniture",
    "wof:placetype":"venue"
},
  "geometry": {"coordinates":[-115.183538,36.055694],"type":"Point"}
}