{
  "type": "Feature",
  "properties": {
    "iso:country":"US",
    "sg:address":"430 E Silverado Ranch Blvd Ste 100",
    "sg:city":"Las Vegas",
    "sg:classifiers":[
        {
            "category":"Restaurant",
            "type":"Food & Drink"
        }
    ],
    "sg:phone":"+1 702 796 9800",
    "sg:postcode":"89123",
    "sg:province":"NV",
    "sg:tags":[
        "mexican"
    ],
    "sg:website":"www.elpicante.net/",
    "wof:name":"El Picante",
    "wof:placetype":"venue"
},
  "geometry": {"coordinates":[-115.153844,36.014585],"type":"Point"}
}