{
  "type": "Feature",
  "properties": {
    "iso:country":"US",
    "sg:address":"1001 N Mountain St",
    "sg:city":"Carson City",
    "sg:classifiers":[
        {
            "category":"Health Services",
            "subcategory":"Doctor",
            "type":"Services"
        }
    ],
    "sg:phone":"+1 775 885 9400",
    "sg:postcode":"89703",
    "sg:province":"NV",
    "sg:tags":[
        "physician",
        "surgeon"
    ],
    "wof:name":"John P Lagios MD",
    "wof:placetype":"venue"
},
  "geometry": {"coordinates":[-119.772881,39.170006],"type":"Point"}
}