{
  "type": "Feature",
  "properties": {
    "iso:country":"US",
    "sg:address":"3732 Lakeside Dr",
    "sg:city":"Reno",
    "sg:classifiers":[
        {
            "category":"Banks & Credit Unions",
            "subcategory":"Investment Brokerage",
            "type":"Services"
        }
    ],
    "sg:phone":"+1 775 324 7878",
    "sg:postcode":"89509",
    "sg:province":"NV",
    "sg:tags":[
        "consultant",
        "planning",
        "financial"
    ],
    "wof:name":"Richter Financial",
    "wof:placetype":"venue"
},
  "geometry": {"coordinates":[-119.807835,39.48958],"type":"Point"}
}