{
  "type": "Feature",
  "properties": {
    "iso:country":"US",
    "sg:address":"9650 Gateway Dr",
    "sg:city":"Reno",
    "sg:classifiers":[
        {
            "category":"Professional",
            "subcategory":"Computer Services",
            "type":"Services"
        }
    ],
    "sg:phone":"+1 775 853 9784",
    "sg:postcode":"89521",
    "sg:province":"NV",
    "sg:tags":[
        "prepackaged",
        "software"
    ],
    "wof:name":"Marin Research Inc",
    "wof:placetype":"venue"
},
  "geometry": {"coordinates":[-119.76222,39.442132],"type":"Point"}
}