{
  "type": "Feature",
  "properties": {
    "iso:country":"US",
    "sg:address":"900 Mallory Way",
    "sg:city":"Carson City",
    "sg:classifiers":[
        {
            "category":"Building & Trades",
            "subcategory":"Construction",
            "type":"Services"
        }
    ],
    "sg:phone":"+1 775 841 3330",
    "sg:postcode":"89701",
    "sg:province":"NV",
    "sg:tags":[
        "masonry",
        "contractor"
    ],
    "wof:name":"M Squared Masonry Inc",
    "wof:placetype":"venue"
},
  "geometry": {"coordinates":[-119.7602,39.150876],"type":"Point"}
}