{
  "type": "Feature",
  "properties": {
    "iso:country":"US",
    "sg:address":"500 S Las Vegas Blvd",
    "sg:city":"Las Vegas",
    "sg:classifiers":[
        {
            "category":"Building & Trades",
            "subcategory":"Cleaning & Sanitation",
            "type":"Services"
        }
    ],
    "sg:phone":"+1 702 920 0827",
    "sg:postcode":"89101",
    "sg:province":"NV",
    "sg:tags":[
        "carpet"
    ],
    "wof:name":"Superb Carpet Cleaning",
    "wof:placetype":"venue"
},
  "geometry": {"coordinates":[-115.13749,36.174047],"type":"Point"}
}