{
  "type": "Feature",
  "properties": {
    "iso:country":"US",
    "sg:address":"3349 Meade Ave",
    "sg:city":"Las Vegas",
    "sg:classifiers":[
        {
            "category":"Retail",
            "subcategory":"Auto Repair",
            "type":"Services"
        }
    ],
    "sg:phone":"+1 702 876 1299",
    "sg:postcode":"89102",
    "sg:province":"NV",
    "sg:tags":[
        "repairing",
        "automobile",
        "automotive"
    ],
    "wof:name":"George's Alignment & Brake Service",
    "wof:placetype":"venue"
},
  "geometry": {"coordinates":[-115.18499799999999,36.1362],"type":"Point"}
}