{
  "type": "Feature",
  "properties": {
    "iso:country":"US",
    "sg:address":"5515 Camino Al Norte",
    "sg:city":"North Las Vegas",
    "sg:classifiers":[
        {
            "category":"Health Services",
            "subcategory":"Dentist",
            "type":"Services"
        }
    ],
    "sg:phone":"+1 702 633 6332",
    "sg:postcode":"89031",
    "sg:province":"NV",
    "wof:name":"Desert Palms Dental",
    "wof:placetype":"venue"
},
  "geometry": {"coordinates":[-115.155215,36.260162],"type":"Point"}
}