{
  "type": "Feature",
  "properties": {
    "iso:country":"US",
    "sg:address":"1964 Sycamore Trl",
    "sg:city":"Las Vegas",
    "sg:classifiers":[
        {
            "category":"Building & Trades",
            "subcategory":"Construction",
            "type":"Services"
        }
    ],
    "sg:phone":"+1 702 647 0864",
    "sg:postcode":"89108",
    "sg:province":"NV",
    "sg:tags":[
        "tile",
        "dealer"
    ],
    "wof:name":"Champion Tile & Marble",
    "wof:placetype":"venue"
},
  "geometry": {"coordinates":[-115.19401,36.195567],"type":"Point"}
}