{
  "type": "Feature",
  "properties": {
    "iso:country":"US",
    "sg:address":"1275 Kleppe Ln",
    "sg:city":"Sparks",
    "sg:classifiers":[
        {
            "category":"Wholesale",
            "subcategory":"Office Equipment",
            "type":"Manufacturing & Wholesale Goods"
        },
        {
            "category":"Professional",
            "subcategory":"Printing & Photocopies",
            "type":"Services"
        },
        {
            "category":"Shopping",
            "subcategory":"Computers & Home Electronics",
            "type":"Retail Goods"
        }
    ],
    "sg:phone":"+1 775 356 8890",
    "sg:postcode":"89431",
    "sg:province":"NV",
    "sg:tags":[
        "scanning",
        "printer",
        "plotting",
        "supply"
    ],
    "wof:name":"Printech",
    "wof:placetype":"venue"
},
  "geometry": {"coordinates":[-119.72234,39.523253],"type":"Point"}
}