{
  "type": "Feature",
  "properties": {
    "iso:country":"US",
    "sg:address":"900 S Murphy St",
    "sg:city":"Pahrump",
    "sg:classifiers":[
        {
            "category":"Wholesale",
            "subcategory":"Machinery & Supplies",
            "type":"Manufacturing & Wholesale Goods"
        }
    ],
    "sg:phone":"+1 775 727 0182",
    "sg:postcode":"89048",
    "sg:province":"NV",
    "sg:tags":[
        "equipment",
        "laundry"
    ],
    "wof:name":"Thermotek Industries",
    "wof:placetype":"venue"
},
  "geometry": {"coordinates":[-116.076435,36.211],"type":"Point"}
}