{
  "type": "Feature",
  "properties": {
    "iso:country":"US",
    "sg:address":"101 Conestoga Dr",
    "sg:city":"Carson City",
    "sg:classifiers":[
        {
            "category":"Building & Trades",
            "subcategory":"Landscaping Services",
            "type":"Services"
        }
    ],
    "sg:phone":"+1 775 841 9303",
    "sg:postcode":"89706",
    "sg:province":"NV",
    "sg:tags":[
        "landscape"
    ],
    "wof:name":"High Valley Landscaping",
    "wof:placetype":"venue"
},
  "geometry": {"coordinates":[-119.778032,39.204296],"type":"Point"}
}