{
  "type": "Feature",
  "properties": {
    "iso:country":"US",
    "sg:address":"84 John Stuart Mill St",
    "sg:city":"Henderson",
    "sg:classifiers":[
        {
            "category":"Professional",
            "subcategory":"Business Services",
            "type":"Services"
        }
    ],
    "sg:phone":"+1 702 558 4272",
    "sg:postcode":"89002",
    "sg:province":"NV",
    "wof:name":"Accurate Medical Trans Service",
    "wof:placetype":"venue"
},
  "geometry": {"coordinates":[-114.996596,36.004339],"type":"Point"}
}