{
  "type": "Feature",
  "properties": {
    "iso:country":"US",
    "sg:address":"2300 Dickerson Rd",
    "sg:city":"Reno",
    "sg:classifiers":[
        {
            "category":"Organizations",
            "subcategory":"Professional Association",
            "type":"Services"
        }
    ],
    "sg:phone":"+1 775 322 0558",
    "sg:postcode":"89503",
    "sg:province":"NV",
    "wof:name":"Volunteers For Outdoor Nevada",
    "wof:placetype":"venue"
},
  "geometry": {"coordinates":[-119.835193,39.523351],"type":"Point"}
}