{
  "type": "Feature",
  "properties": {
    "iso:country":"US",
    "sg:address":"4320 Sierra Madre Dr",
    "sg:city":"Reno",
    "sg:classifiers":[
        {
            "category":"Food & Beverages",
            "subcategory":"Specialty",
            "type":"Retail Goods"
        }
    ],
    "sg:phone":"+1 775 770 2299",
    "sg:postcode":"89502",
    "sg:province":"NV",
    "sg:tags":[
        "health",
        "diet"
    ],
    "wof:name":"Herbalife Distributor",
    "wof:placetype":"venue"
},
  "geometry": {"coordinates":[-119.74981099999999,39.47687],"type":"Point"}
}