{
  "type": "Feature",
  "properties": {
    "iso:country":"US",
    "sg:address":"409 East Silverado Ranch",
    "sg:city":"Las Vegas",
    "sg:classifiers":[
        {
            "category":"Donuts",
            "subcategory":"None",
            "type":"Food & Drink"
        }
    ],
    "sg:phone":"+1 702 616 0085",
    "sg:postcode":"89123",
    "sg:province":"NV",
    "sg:website":"www.dunkindonuts.com",
    "wof:name":"Dunkin Donuts",
    "wof:placetype":"venue"
},
  "geometry": {"coordinates":[-115.15431100000001,36.013266],"type":"Point"}
}