{
  "type": "Feature",
  "properties": {
    "iso:country":"US",
    "sg:address":"4200 Boulder Hwy",
    "sg:city":"Las Vegas",
    "sg:classifiers":[
        {
            "category":"Bars & Pubs",
            "type":"Food & Drink"
        }
    ],
    "sg:phone":"+1 702 458 3184",
    "sg:postcode":"89121",
    "sg:province":"NV",
    "wof:name":"Dew Drop Inn",
    "wof:placetype":"venue"
},
  "geometry": {"coordinates":[-115.082938,36.129164],"type":"Point"}
}