{
  "type": "Feature",
  "properties": {
    "iso:country":"US",
    "sg:address":"6741 W Alexander Rd",
    "sg:city":"Las Vegas",
    "sg:classifiers":[
        {
            "category":"Organizations",
            "subcategory":"Religious Organization",
            "type":"Services"
        }
    ],
    "sg:phone":"+1 702 649 7150",
    "sg:postcode":"89108",
    "sg:province":"NV",
    "sg:tags":[
        "church"
    ],
    "wof:name":"Present Truth Seventh Day",
    "wof:placetype":"venue"
},
  "geometry": {"coordinates":[-115.243199,36.232961],"type":"Point"}
}