{
  "type": "Feature",
  "properties": {
    "iso:country":"US",
    "sg:address":"1271 Moon Ridge Cir",
    "sg:city":"Reno",
    "sg:classifiers":[
        {
            "category":"Arts & Performance",
            "subcategory":"Theater",
            "type":"Entertainment"
        }
    ],
    "sg:phone":"+1 775 827 5056",
    "sg:postcode":"89523",
    "sg:province":"NV",
    "sg:tags":[
        "group"
    ],
    "wof:name":"Fun Characters & Woody Clown",
    "wof:placetype":"venue"
},
  "geometry": {"coordinates":[-119.89062,39.52284],"type":"Point"}
}