{
  "type": "Feature",
  "properties": {
    "iso:country":"US",
    "sg:address":"4985 S Fort Apache Rd",
    "sg:city":"Las Vegas",
    "sg:classifiers":[
        {
            "category":"Shopping",
            "subcategory":"Bicycles & Sporting Goods",
            "type":"Retail Goods"
        }
    ],
    "sg:phone":"+1 702 453 7271",
    "sg:postcode":"89148",
    "sg:province":"NV",
    "sg:tags":[
        "equipment",
        "golf",
        "supply"
    ],
    "wof:name":"Golf Monster",
    "wof:placetype":"venue"
},
  "geometry": {"coordinates":[-115.297391,36.097513],"type":"Point"}
}