{
  "type": "Feature",
  "properties": {
    "iso:country":"US",
    "sg:address":"911 N Buffalo Dr",
    "sg:city":"Las Vegas",
    "sg:classifiers":[
        {
            "category":"Personal",
            "type":"Services"
        }
    ],
    "sg:phone":"+1 702 254 6747",
    "sg:postcode":"89128",
    "sg:province":"NV",
    "sg:tags":[
        "therapist",
        "massage"
    ],
    "wof:name":"Touch-Life Massage & Wllnss",
    "wof:placetype":"venue"
},
  "geometry": {"coordinates":[-115.260057,36.183068],"type":"Point"}
}