{
  "type": "Feature",
  "properties": {
    "iso:country":"US",
    "sg:address":"9037 W Sahara Ave",
    "sg:city":"Las Vegas",
    "sg:classifiers":[
        {
            "category":"Building & Trades",
            "subcategory":"Construction",
            "type":"Services"
        }
    ],
    "sg:phone":"+1 702 363 2235",
    "sg:postcode":"89117",
    "sg:province":"NV",
    "sg:tags":[
        "masonry",
        "contractor"
    ],
    "wof:name":"E & F Cannon Masonry",
    "wof:placetype":"venue"
},
  "geometry": {"coordinates":[-115.288895,36.144055],"type":"Point"}
}