{
  "type": "Feature",
  "properties": {
    "iso:country":"US",
    "sg:address":"209 N Pecos Rd",
    "sg:city":"Henderson",
    "sg:classifiers":[
        {
            "category":"Restaurant",
            "type":"Food & Drink"
        }
    ],
    "sg:menulink":"http://www.allmenus.com/nv/las-vegas/169728-burger-king/menu/",
    "sg:phone":"+1 702 361 8723",
    "sg:postcode":"89074",
    "sg:province":"NV",
    "sg:tags":[
        "burger",
        "american"
    ],
    "wof:name":"Burger King",
    "wof:placetype":"venue"
},
  "geometry": {"coordinates":[-115.100961,36.043349],"type":"Point"}
}