{
  "type": "Feature",
  "properties": {
    "iso:country":"US",
    "sg:address":"931 American Pacific Dr",
    "sg:city":"Henderson",
    "sg:classifiers":[
        {
            "category":"Restaurant",
            "type":"Food & Drink"
        }
    ],
    "sg:phone":"+1 702 568 7374",
    "sg:postcode":"89014",
    "sg:province":"NV",
    "sg:tags":[
        "eating"
    ],
    "wof:name":"What A Sub",
    "wof:placetype":"venue"
},
  "geometry": {"coordinates":[-115.025873,36.041904],"type":"Point"}
}