{
  "type": "Feature",
  "properties": {
    "iso:country":"US",
    "sg:address":"6360 Simmons St",
    "sg:city":"North Las Vegas",
    "sg:classifiers":[
        {
            "category":"Coffee & Tea",
            "type":"Food & Drink"
        }
    ],
    "sg:menulink":"http://www.allmenus.com/nv/las-vegas/125403-starbucks-coffee/menu/",
    "sg:phone":"+1 702 658 8939",
    "sg:postcode":"89031",
    "sg:province":"NV",
    "sg:tags":[
        "american"
    ],
    "wof:name":"Starbucks Coffee",
    "wof:placetype":"venue"
},
  "geometry": {"coordinates":[-115.17978100000001,36.275706],"type":"Point"}
}