{
  "type": "Feature",
  "properties": {
    "iso:country":"US",
    "sg:address":"2025 Sweeney Ave",
    "sg:city":"Las Vegas",
    "sg:classifiers":[
        {
            "category":"Building & Trades",
            "subcategory":"Cleaning & Sanitation",
            "type":"Services"
        }
    ],
    "sg:phone":"+1 702 510 8267",
    "sg:postcode":"89104",
    "sg:province":"NV",
    "sg:tags":[
        "janitor"
    ],
    "wof:name":"Gaby's Cleaning",
    "wof:placetype":"venue"
},
  "geometry": {"coordinates":[-115.119421,36.153855],"type":"Point"}
}