{
  "type": "Feature",
  "properties": {
    "iso:country":"US",
    "sg:address":"10241 Juniper Creek Ln",
    "sg:city":"Las Vegas",
    "sg:classifiers":[
        {
            "category":"Health Services",
            "subcategory":"Clinic",
            "type":"Services"
        }
    ],
    "sg:phone":"+1 702 894 4454",
    "sg:postcode":"89145",
    "sg:province":"NV",
    "sg:tags":[
        "organization",
        "medical",
        "surgical"
    ],
    "wof:name":"Professional Medical Svc",
    "wof:placetype":"venue"
},
  "geometry": {"coordinates":[-115.320417,36.161601],"type":"Point"}
}