{
  "type": "Feature",
  "properties": {
    "iso:country":"US",
    "sg:address":"1600 S Boulder Hwy",
    "sg:city":"Henderson",
    "sg:classifiers":[
        {
            "category":"Autos & Motor Vehicles",
            "subcategory":"Recreational Vehicle Sales",
            "type":"Retail Goods"
        }
    ],
    "sg:phone":"+1 702 565 6525",
    "sg:postcode":"89015",
    "sg:province":"NV",
    "sg:tags":[
        "repair",
        "general"
    ],
    "wof:name":"Camping World",
    "wof:placetype":"venue"
},
  "geometry": {"coordinates":[-114.962267,36.021982],"type":"Point"}
}