{
  "type": "Feature",
  "properties": {
    "iso:country":"US",
    "sg:address":"5800 W Charleston Blvd",
    "sg:city":"Las Vegas",
    "sg:classifiers":[
        {
            "category":"Shopping",
            "subcategory":"Gifts & Souvenirs",
            "type":"Retail Goods"
        }
    ],
    "sg:phone":"+1 702 259 0422",
    "sg:postcode":"89146",
    "sg:province":"NV",
    "wof:name":"Southwest Stamps Collectibles",
    "wof:placetype":"venue"
},
  "geometry": {"coordinates":[-115.223943,36.159197],"type":"Point"}
}