{
  "type": "Feature",
  "properties": {
    "iso:country":"US",
    "sg:address":"3183 E Warm Springs Rd",
    "sg:city":"Las Vegas",
    "sg:classifiers":[
        {
            "category":"Communications",
            "type":"Services"
        }
    ],
    "sg:phone":"+1 702 933 5322",
    "sg:postcode":"89120",
    "sg:province":"NV",
    "wof:name":"Demac Communications Inc",
    "wof:placetype":"venue"
},
  "geometry": {"coordinates":[-115.10075399999999,36.056963],"type":"Point"}
}