{
  "type": "Feature",
  "properties": {
    "iso:country":"US",
    "sg:address":"538 Greenbrae Dr",
    "sg:city":"Sparks",
    "sg:classifiers":[
        {
            "category":"Professional",
            "subcategory":"Business Services",
            "type":"Services"
        },
        {
            "category":"Home & Garden",
            "subcategory":"Furniture",
            "type":"Retail Goods"
        }
    ],
    "sg:phone":"+1 775 359 4444",
    "sg:postcode":"89431",
    "sg:province":"NV",
    "wof:name":"Bazaar Enterprises",
    "wof:placetype":"venue"
},
  "geometry": {"coordinates":[-119.751731,39.54751],"type":"Point"}
}