{
  "type": "Feature",
  "properties": {
    "iso:country":"US",
    "sg:address":"1623 N Main St",
    "sg:city":"North Las Vegas",
    "sg:classifiers":[
        {
            "category":"Retail",
            "subcategory":"Auto Repair",
            "type":"Services"
        }
    ],
    "sg:phone":"+1 702 642 4868",
    "sg:postcode":"89030",
    "sg:province":"NV",
    "sg:tags":[
        "general"
    ],
    "wof:name":"V Three Corp",
    "wof:placetype":"venue"
},
  "geometry": {"coordinates":[-115.134034,36.190321],"type":"Point"}
}