{
  "type": "Feature",
  "properties": {
    "iso:country":"US",
    "sg:address":"2035 W Charleston Blvd",
    "sg:city":"Las Vegas",
    "sg:classifiers":[
        {
            "category":"Health Services",
            "subcategory":"Nursing And Care Facility",
            "type":"Services"
        }
    ],
    "sg:phone":"+1 702 386 7980",
    "sg:postcode":"89102",
    "sg:province":"NV",
    "sg:tags":[
        "convalescent",
        "hospital",
        "skilled",
        "specialty",
        "home"
    ],
    "wof:name":"Emmanuel Health Care Center",
    "wof:placetype":"venue"
},
  "geometry": {"coordinates":[-115.1695,36.15882],"type":"Point"}
}