{
  "type": "Feature",
  "properties": {
    "iso:country":"US",
    "sg:address":"2424 Oddie Blvd",
    "sg:city":"Reno",
    "sg:classifiers":[
        {
            "category":"Shopping",
            "type":"Retail Goods"
        }
    ],
    "sg:phone":"+1 775 358 5999",
    "sg:postcode":"89512",
    "sg:province":"NV",
    "sg:tags":[
        "factory",
        "outlet"
    ],
    "wof:name":"99 Cents Emporium",
    "wof:placetype":"venue"
},
  "geometry": {"coordinates":[-119.78349,39.545513],"type":"Point"}
}