{
  "type": "Feature",
  "properties": {
    "iso:country":"US",
    "sg:address":"894 Arrowhead Dr",
    "sg:city":"Gardnerville",
    "sg:classifiers":[
        {
            "category":"Manufacturing",
            "subcategory":"Signs",
            "type":"Manufacturing & Wholesale Goods"
        },
        {
            "category":"Professional",
            "subcategory":"Business Services",
            "type":"Services"
        }
    ],
    "sg:phone":"+1 775 265 7881",
    "sg:postcode":"89460",
    "sg:province":"NV",
    "sg:tags":[
        "lettering",
        "painting"
    ],
    "wof:name":"Arrow Head Signs",
    "wof:placetype":"venue"
},
  "geometry": {"coordinates":[-119.740055,38.903063],"type":"Point"}
}