{
  "type": "Feature",
  "properties": {
    "iso:country":"US",
    "sg:address":"3321 N Buffalo Dr",
    "sg:city":"Las Vegas",
    "sg:classifiers":[
        {
            "category":"Professional",
            "subcategory":"Engineering",
            "type":"Services"
        }
    ],
    "sg:phone":"+1 702 877 1300",
    "sg:postcode":"89129",
    "sg:province":"NV",
    "sg:tags":[
        "engineer"
    ],
    "wof:name":"Alpha Engineering Co",
    "wof:placetype":"venue"
},
  "geometry": {"coordinates":[-115.260491,36.221958],"type":"Point"}
}