{
  "type": "Feature",
  "properties": {
    "iso:country":"US",
    "sg:address":"5320 Cross Creek Ln",
    "sg:city":"Reno",
    "sg:classifiers":[
        {
            "category":"Professional",
            "type":"Services"
        }
    ],
    "sg:phone":"+1 775 849 2779",
    "sg:postcode":"89511",
    "sg:province":"NV",
    "wof:name":"Lewis B Gustafson",
    "wof:placetype":"venue"
},
  "geometry": {"coordinates":[-119.812527,39.364404],"type":"Point"}
}