{
  "type": "Feature",
  "properties": {
    "iso:country":"US",
    "sg:address":"2548 Terrytown Ave",
    "sg:city":"Henderson",
    "sg:classifiers":[
        {
            "category":"Real Estate",
            "subcategory":"Real Estate Agent",
            "type":"Services"
        }
    ],
    "sg:phone":"+1 702 269 3104",
    "sg:postcode":"89052",
    "sg:province":"NV",
    "wof:name":"Carl Johnson",
    "wof:placetype":"venue"
},
  "geometry": {"coordinates":[-115.09825499999999,35.97295],"type":"Point"}
}