{
  "type": "Feature",
  "properties": {
    "iso:country":"US",
    "sg:address":"3140 Polaris Ave",
    "sg:city":"Las Vegas",
    "sg:classifiers":[
        {
            "category":"Building & Trades",
            "subcategory":"Landscaping Services",
            "type":"Services"
        }
    ],
    "sg:phone":"+1 702 592 3647",
    "sg:postcode":"89102",
    "sg:province":"NV",
    "wof:name":"Brick Scapes Inc",
    "wof:placetype":"venue"
},
  "geometry": {"coordinates":[-115.18561099999999,36.130788],"type":"Point"}
}