{
  "type": "Feature",
  "properties": {
    "iso:country":"US",
    "sg:address":"1700 County Rd",
    "sg:city":"Minden",
    "sg:classifiers":[
        {
            "category":"Building & Trades",
            "subcategory":"Construction",
            "type":"Services"
        }
    ],
    "sg:phone":"+1 775 783 1883",
    "sg:postcode":"89423",
    "sg:province":"NV",
    "sg:tags":[
        "builder",
        "operative"
    ],
    "wof:name":"Sierra Asssted Lving Fundation",
    "wof:placetype":"venue"
},
  "geometry": {"coordinates":[-119.77406,38.95541],"type":"Point"}
}