{
  "type": "Feature",
  "properties": {
    "iso:country":"US",
    "sg:address":"3421 E Tropicana Ave",
    "sg:city":"Las Vegas",
    "sg:classifiers":[
        {
            "category":"Shopping",
            "subcategory":"Pets & Pet Supplies",
            "type":"Retail Goods"
        }
    ],
    "sg:phone":"+1 702 454 9777",
    "sg:postcode":"89121",
    "sg:province":"NV",
    "sg:tags":[
        "store"
    ],
    "wof:name":"Dorian's Cutting Edge",
    "wof:placetype":"venue"
},
  "geometry": {"coordinates":[-115.100998,36.099998],"type":"Point"}
}