{
  "type": "Feature",
  "properties": {
    "iso:country":"US",
    "sg:address":"3441 W Sahara Avenue",
    "sg:city":"Las Vegas",
    "sg:classifiers":[
        {
            "category":"Health Services",
            "subcategory":"Chiropractor",
            "type":"Services"
        }
    ],
    "sg:phone":"+1 702 220 9191",
    "sg:postcode":"89102",
    "sg:province":"NV",
    "wof:name":"Chong Jason DC",
    "wof:placetype":"venue"
},
  "geometry": {"coordinates":[-115.187467,36.144305],"type":"Point"}
}