{
  "type": "Feature",
  "properties": {
    "iso:country":"US",
    "sg:address":"2605 Sherwood St",
    "sg:city":"Las Vegas",
    "sg:classifiers":[
        {
            "category":"Real Estate",
            "subcategory":"Real Estate Operator",
            "type":"Services"
        }
    ],
    "sg:phone":"+1 702 737 4526",
    "sg:postcode":"89109",
    "sg:province":"NV",
    "sg:tags":[
        "apartment"
    ],
    "wof:name":"Classic Systems Inc",
    "wof:placetype":"venue"
},
  "geometry": {"coordinates":[-115.14723600000001,36.142214],"type":"Point"}
}