{
  "type": "Feature",
  "properties": {
    "iso:country":"US",
    "sg:address":"1167 Annie Ct",
    "sg:city":"Minden",
    "sg:classifiers":[
        {
            "category":"Professional",
            "subcategory":"Engineering",
            "type":"Services"
        }
    ],
    "sg:phone":"+1 775 267 0566",
    "sg:postcode":"89423",
    "sg:province":"NV",
    "sg:tags":[
        "engineer"
    ],
    "wof:name":"Geocon Consultants Inc",
    "wof:placetype":"venue"
},
  "geometry": {"coordinates":[-119.755056,39.023416],"type":"Point"}
}