{
  "type": "Feature",
  "properties": {
    "iso:country":"US",
    "sg:address":"777 N Rainbow Blvd",
    "sg:city":"Las Vegas",
    "sg:classifiers":[
        {
            "category":"Education",
            "subcategory":"Special Training",
            "type":"Public Place"
        }
    ],
    "sg:phone":"+1 702 461 7013",
    "sg:postcode":"89107",
    "sg:province":"NV",
    "sg:tags":[
        "instruction",
        "music"
    ],
    "wof:name":"Creative Hearts Music Instrctn",
    "wof:placetype":"venue"
},
  "geometry": {"coordinates":[-115.242369,36.17986],"type":"Point"}
}