{
  "type": "Feature",
  "properties": {
    "iso:country":"US",
    "sg:address":"3311 Meade Ave",
    "sg:city":"Las Vegas",
    "sg:classifiers":[
        {
            "category":"Professional",
            "subcategory":"Advertising",
            "type":"Services"
        }
    ],
    "sg:phone":"+1 702 889 2793",
    "sg:postcode":"89102",
    "sg:province":"NV",
    "sg:tags":[
        "designer",
        "display",
        "producer"
    ],
    "wof:name":"Design Factory",
    "wof:placetype":"venue"
},
  "geometry": {"coordinates":[-115.184816,36.136255],"type":"Point"}
}