{
  "type": "Feature",
  "properties": {
    "iso:country":"US",
    "sg:address":"4735 Faircenter",
    "sg:city":"Las Vegas",
    "sg:classifiers":[
        {
            "category":"Retail",
            "subcategory":"Veterinary Services",
            "type":"Services"
        }
    ],
    "sg:phone":"+1 702 648 2737",
    "sg:postcode":"89102",
    "sg:province":"NV",
    "sg:tags":[
        "veterinarian"
    ],
    "wof:name":"Jyl Rubin DVM",
    "wof:placetype":"venue"
},
  "geometry": {"coordinates":[-115.201459,36.158256],"type":"Point"}
}