{
  "type": "Feature",
  "properties": {
    "iso:country":"US",
    "sg:address":"515 S 3rd St",
    "sg:city":"Las Vegas",
    "sg:classifiers":[
        {
            "category":"Professional",
            "subcategory":"Lawyer & Legal Services",
            "type":"Services"
        }
    ],
    "sg:phone":"+1 702 477 0750",
    "sg:postcode":"89101",
    "sg:province":"NV",
    "wof:name":"Stuhff Michael Atty",
    "wof:placetype":"venue"
},
  "geometry": {"coordinates":[-115.146004,36.1651],"type":"Point"}
}