{
  "type": "Feature",
  "properties": {
    "iso:country":"US",
    "sg:address":"1188 California Ave",
    "sg:city":"Reno",
    "sg:classifiers":[
        {
            "category":"Professional",
            "subcategory":"Lawyer & Legal Services",
            "type":"Services"
        }
    ],
    "sg:phone":"+1 775 324 6257",
    "sg:postcode":"89509",
    "sg:province":"NV",
    "sg:tags":[
        "attorney",
        "law",
        "duo",
        "violence",
        "domestic",
        "drug",
        "charge",
        "criminal",
        "dwi"
    ],
    "wof:name":"Oakes John & Justin Attorneys At Law",
    "wof:placetype":"venue"
},
  "geometry": {"coordinates":[-119.828754,39.513689],"type":"Point"}
}