{
  "type": "Feature",
  "properties": {
    "iso:country":"US",
    "sg:address":"1555 Livermore Ln",
    "sg:city":"Carson City",
    "sg:classifiers":[
        {
            "category":"Park",
            "type":"Public Place"
        }
    ],
    "sg:postcode":"89701",
    "sg:province":"NV",
    "sg:website":"www.carson-city.nv.us/Index.aspx...",
    "wof:name":"Edmonds Sports Park",
    "wof:placetype":"venue"
},
  "geometry": {"coordinates":[-119.750371,39.121123],"type":"Point"}
}