{
  "type": "Feature",
  "properties": {
    "iso:country":"US",
    "sg:address":"242 Sunpac Ave",
    "sg:city":"Henderson",
    "sg:classifiers":[
        {
            "category":"Professional",
            "subcategory":"Business Services",
            "type":"Services"
        }
    ],
    "sg:phone":"+1 702 566 3091",
    "sg:postcode":"89011",
    "sg:province":"NV",
    "sg:tags":[
        "painter",
        "sign"
    ],
    "wof:name":"Sign Innovations",
    "wof:placetype":"venue"
},
  "geometry": {"coordinates":[-114.995556,36.069283],"type":"Point"}
}