{
  "type": "Feature",
  "properties": {
    "iso:country":"US",
    "sg:address":"5196 el Castano Ave",
    "sg:city":"Las Vegas",
    "sg:classifiers":[
        {
            "category":"Education",
            "subcategory":"Special Training",
            "type":"Public Place"
        }
    ],
    "sg:phone":"+1 702 290 3892",
    "sg:postcode":"89108",
    "sg:province":"NV",
    "sg:tags":[
        "aircraft",
        "school"
    ],
    "wof:name":"Maioli Flight Training",
    "wof:placetype":"venue"
},
  "geometry": {"coordinates":[-115.211259,36.206963],"type":"Point"}
}