{
  "type": "Feature",
  "properties": {
    "iso:country":"US",
    "sg:address":"2450 Chandler Ave",
    "sg:city":"Las Vegas",
    "sg:classifiers":[
        {
            "category":"Professional",
            "subcategory":"Accounting & Tax Preparation",
            "type":"Services"
        }
    ],
    "sg:phone":"+1 702 740 4610",
    "sg:postcode":"89120",
    "sg:province":"NV",
    "sg:tags":[
        "accountant"
    ],
    "wof:name":"David C Andrews LTD",
    "wof:placetype":"venue"
},
  "geometry": {"coordinates":[-115.11321,36.0739],"type":"Point"}
}