{
  "type": "Feature",
  "properties": {
    "iso:country":"US",
    "sg:address":"338 Ryland St",
    "sg:city":"Reno",
    "sg:classifiers":[
        {
            "category":"Professional",
            "subcategory":"Computer Services",
            "type":"Services"
        }
    ],
    "sg:phone":"+1 775 323 7242",
    "sg:postcode":"89501",
    "sg:province":"NV",
    "sg:tags":[
        "consultant"
    ],
    "wof:name":"Building Solutions LLC",
    "wof:placetype":"venue"
},
  "geometry": {"coordinates":[-119.80685,39.523697],"type":"Point"}
}