{
  "type": "Feature",
  "properties": {
    "iso:country":"US",
    "sg:address":"2912 S Highland Dr",
    "sg:city":"Las Vegas",
    "sg:classifiers":[
        {
            "category":"Manufacturing",
            "subcategory":"Furniture",
            "type":"Manufacturing & Wholesale Goods"
        }
    ],
    "sg:phone":"+1 702 633 7777",
    "sg:postcode":"89109",
    "sg:province":"NV",
    "wof:name":"Milano Design LLC",
    "wof:placetype":"venue"
},
  "geometry": {"coordinates":[-115.172794,36.137605],"type":"Point"}
}