{
  "type": "Feature",
  "properties": {
    "iso:country":"US",
    "sg:address":"7541 Lake Mead Blvd",
    "sg:city":"Las Vegas",
    "sg:classifiers":[
        {
            "category":"Fast Food",
            "type":"Food & Drink"
        }
    ],
    "sg:phone":"+1 702 982 2700",
    "sg:postcode":"89128",
    "sg:province":"NV",
    "sg:website":"www.evos.com",
    "wof:name":"Evos",
    "wof:placetype":"venue"
},
  "geometry": {"coordinates":[-115.258027,36.196035],"type":"Point"}
}