{
  "type": "Feature",
  "properties": {
    "iso:country":"US",
    "sg:address":"2317 Santa Rita Dr",
    "sg:city":"Las Vegas",
    "sg:classifiers":[
        {
            "category":"Farming",
            "subcategory":"Farm & Veterinary Services",
            "type":"Manufacturing & Wholesale Goods"
        }
    ],
    "sg:phone":"+1 702 791 3530",
    "sg:postcode":"89104",
    "sg:province":"NV",
    "sg:tags":[
        "labor",
        "contractor"
    ],
    "wof:name":"AA Plaster Corp",
    "wof:placetype":"venue"
},
  "geometry": {"coordinates":[-115.151706,36.143749],"type":"Point"}
}