{
  "type": "Feature",
  "properties": {
    "iso:country":"US",
    "sg:address":"4750 hwy 50 east Suite 2",
    "sg:city":"Carson City",
    "sg:classifiers":[
        {
            "category":"Arts & Performance",
            "subcategory":"Arts Center",
            "type":"Entertainment"
        },
        {
            "category":"Personal",
            "subcategory":"Tattoo Parlor",
            "type":"Services"
        }
    ],
    "sg:phone":"+1 775 883 8282",
    "sg:postcode":"89701",
    "sg:province":"NV",
    "sg:website":"www.therubylantern.com",
    "wof:name":"The Ruby Lantern",
    "wof:placetype":"venue"
},
  "geometry": {"coordinates":[-119.713996,39.18514],"type":"Point"}
}