{
  "type": "Feature",
  "properties": {
    "iso:country":"US",
    "sg:address":"3104 E Bonanza Rd",
    "sg:city":"Las Vegas",
    "sg:classifiers":[
        {
            "category":"Building & Trades",
            "subcategory":"Construction",
            "type":"Services"
        }
    ],
    "sg:phone":"+1 702 229 6331",
    "sg:postcode":"89101",
    "sg:province":"NV",
    "sg:tags":[
        "marking",
        "street",
        "sign"
    ],
    "wof:name":"Traffid/Electrical Field Ops",
    "wof:placetype":"venue"
},
  "geometry": {"coordinates":[-115.098271,36.173413],"type":"Point"}
}