{
  "type": "Feature",
  "properties": {
    "iso:country":"US",
    "sg:address":"10116 US Hwy 50",
    "sg:city":"Mound House",
    "sg:classifiers":[
        {
            "category":"Shopping",
            "subcategory":"Gifts & Souvenirs",
            "type":"Retail Goods"
        }
    ],
    "sg:phone":"+1 775 246 5752",
    "sg:postcode":"89702",
    "sg:province":"NV",
    "sg:tags":[
        "shop"
    ],
    "wof:name":"G K & Treasures",
    "wof:placetype":"venue"
},
  "geometry": {"coordinates":[-119.65266800000001,39.218904],"type":"Point"}
}