{
  "type": "Feature",
  "properties": {
    "iso:country":"US",
    "sg:address":"4255 E Charleston Blvd",
    "sg:city":"Las Vegas",
    "sg:classifiers":[
        {
            "category":"Personal",
            "subcategory":"Barber",
            "type":"Services"
        },
        {
            "category":"Education",
            "subcategory":"Vocational School",
            "type":"Public Place"
        }
    ],
    "sg:phone":"+1 702 641 7411",
    "sg:postcode":"89104",
    "sg:province":"NV",
    "sg:tags":[
        "cosmetology"
    ],
    "wof:name":"Supercuts",
    "wof:placetype":"venue"
},
  "geometry": {"coordinates":[-115.083,36.158798],"type":"Point"}
}