{
  "type": "Feature",
  "properties": {
    "iso:country":"US",
    "sg:address":"195 E Tropicana Ave",
    "sg:city":"Las Vegas",
    "sg:classifiers":[
        {
            "category":"Building & Trades",
            "subcategory":"Construction",
            "type":"Services"
        }
    ],
    "sg:phone":"+1 702 739 1400",
    "sg:postcode":"89109",
    "sg:province":"NV",
    "sg:tags":[
        "home",
        "builder"
    ],
    "wof:name":"D R Horton Inc",
    "wof:placetype":"venue"
},
  "geometry": {"coordinates":[-115.166356,36.100808],"type":"Point"}
}