{
  "type": "Feature",
  "properties": {
    "iso:country":"US",
    "sg:address":"9767 Gentle Spirit Drive",
    "sg:city":"Las Vegas",
    "sg:classifiers":[
        {
            "category":"Professional",
            "subcategory":"Accounting & Tax Preparation",
            "type":"Services"
        }
    ],
    "sg:phone":"+1 702 405 9912",
    "sg:postcode":"89148",
    "sg:province":"NV",
    "sg:tags":[
        "accountant"
    ],
    "sg:website":"www.profitandlasvegas.com/",
    "wof:name":"Profit and Las Vegas Bookkeeping, LLC",
    "wof:placetype":"venue"
},
  "geometry": {"coordinates":[-115.30574300000001,36.079914],"type":"Point"}
}