{
  "type": "Feature",
  "properties": {
    "iso:country":"US",
    "sg:address":"323 West St",
    "sg:city":"Reno",
    "sg:classifiers":[
        {
            "category":"Retail",
            "subcategory":"Repair Shop",
            "type":"Services"
        },
        {
            "category":"Shopping",
            "subcategory":"Computers & Home Electronics",
            "type":"Retail Goods"
        },
        {
            "category":"Manufacturing",
            "subcategory":"Motor Vehicles & Parts",
            "type":"Manufacturing & Wholesale Goods"
        },
        {
            "category":"Wholesale",
            "subcategory":"Office Equipment",
            "type":"Manufacturing & Wholesale Goods"
        },
        {
            "category":"Professional",
            "subcategory":"Computer Services",
            "type":"Services"
        },
        {
            "category":"Wholesale",
            "subcategory":"Computers",
            "type":"Manufacturing & Wholesale Goods"
        }
    ],
    "sg:phone":"+1 775 322 4559",
    "sg:postcode":"89501",
    "sg:province":"NV",
    "sg:tags":[
        "scanning",
        "fax",
        "network",
        "supply",
        "repair-business",
        "system",
        "machine",
        "hardware",
        "design",
        "equipment-service",
        "plotting",
        "typewriter"
    ],
    "sg:website":"http://www.since1928.com",
    "wof:name":"Harry's Business Machines Inc",
    "wof:placetype":"venue"
},
  "geometry": {"coordinates":[-119.816525,39.528404],"type":"Point"}
}