{
  "type": "Feature",
  "properties": {
    "iso:country":"US",
    "sg:address":"2421 Tech Center Ct",
    "sg:city":"Las Vegas",
    "sg:classifiers":[
        {
            "category":"Professional",
            "subcategory":"Business Services",
            "type":"Services"
        }
    ],
    "sg:phone":"+1 702 656 1979",
    "sg:postcode":"89128",
    "sg:province":"NV",
    "sg:tags":[
        "drafting"
    ],
    "wof:name":"J P Drafting",
    "wof:placetype":"venue"
},
  "geometry": {"coordinates":[-115.253745,36.20409],"type":"Point"}
}