{
  "type": "Feature",
  "properties": {
    "iso:country":"US",
    "sg:address":"2634 Calypso",
    "sg:city":"Las Vegas",
    "sg:classifiers":[
        {
            "category":"Real Estate",
            "subcategory":"Real Estate Agent",
            "type":"Services"
        }
    ],
    "sg:phone":"+1 702 274 0947",
    "sg:postcode":"89121",
    "sg:province":"NV",
    "sg:tags":[
        "inspection"
    ],
    "wof:name":"Key Home Inspections",
    "wof:placetype":"venue"
},
  "geometry": {"coordinates":[-115.113573,36.128374],"type":"Point"}
}