{
  "type": "Feature",
  "properties": {
    "iso:country":"US",
    "sg:address":"7575 W Washington Ave",
    "sg:city":"Las Vegas",
    "sg:classifiers":[
        {
            "category":"Building & Trades",
            "subcategory":"Construction",
            "type":"Services"
        }
    ],
    "sg:phone":"+1 702 460 3989",
    "sg:postcode":"89128",
    "sg:province":"NV",
    "sg:tags":[
        "house"
    ],
    "wof:name":"Home Krafters Remodeling",
    "wof:placetype":"venue"
},
  "geometry": {"coordinates":[-115.253827,36.181271],"type":"Point"}
}