{
  "type": "Feature",
  "properties": {
    "iso:country":"US",
    "sg:address":"2104 Greenbrae Dr",
    "sg:city":"Sparks",
    "sg:classifiers":[
        {
            "category":"Cinema",
            "subcategory":"Movie Rental",
            "type":"Entertainment"
        }
    ],
    "sg:phone":"+1 775 356 6655",
    "sg:postcode":"89431",
    "sg:province":"NV",
    "sg:tags":[
        "video",
        "tape"
    ],
    "wof:name":"Mr Video",
    "wof:placetype":"venue"
},
  "geometry": {"coordinates":[-119.77595599999999,39.547614],"type":"Point"}
}