{
  "type": "Feature",
  "properties": {
    "iso:country":"US",
    "sg:address":"1200 S Rock Blvd #2",
    "sg:city":"Sparks",
    "sg:classifiers":[
        {
            "category":"Retail",
            "subcategory":"Auto Repair",
            "type":"Services"
        }
    ],
    "sg:phone":"+1 775 856 1820",
    "sg:postcode":"89431",
    "sg:province":"NV",
    "sg:tags":[
        "body",
        "painting",
        "repairing",
        "automobile"
    ],
    "sg:website":"http://www.stevescollisioncenter.com",
    "wof:name":"Steve's Collision Center",
    "wof:placetype":"venue"
},
  "geometry": {"coordinates":[-119.766747,39.523472],"type":"Point"}
}