{
  "type": "Feature",
  "properties": {
    "iso:country":"US",
    "sg:address":"940 Southwood Blvd",
    "sg:city":"Incline Village",
    "sg:classifiers":[
        {
            "category":"Real Estate",
            "subcategory":"Real Estate Agent",
            "type":"Services"
        }
    ],
    "sg:phone":"+1 775 831 4646",
    "sg:postcode":"89451",
    "sg:province":"NV",
    "wof:name":"Davisson Odonnell Tahoe RE",
    "wof:placetype":"venue"
},
  "geometry": {"coordinates":[-119.947411,39.247658],"type":"Point"}
}