{
  "type": "Feature",
  "properties": {
    "iso:country":"US",
    "sg:address":"2300 W Sahara Ave",
    "sg:city":"Las Vegas",
    "sg:classifiers":[
        {
            "category":"Professional",
            "subcategory":"Credit Reporting & Collection",
            "type":"Services"
        }
    ],
    "sg:phone":"+1 702 362 0312",
    "sg:postcode":"89102",
    "sg:province":"NV",
    "sg:tags":[
        "agency"
    ],
    "wof:name":"Experian",
    "wof:placetype":"venue"
},
  "geometry": {"coordinates":[-115.177576,36.144338],"type":"Point"}
}