{
  "type": "Feature",
  "properties": {
    "iso:country":"US",
    "sg:address":"9130 West Russell Rd # 330",
    "sg:city":"Las Vegas",
    "sg:classifiers":[
        {
            "category":"Retail",
            "subcategory":"Event Space",
            "type":"Services"
        }
    ],
    "sg:phone":"+1 702 307 4959",
    "sg:postcode":"89148",
    "sg:province":"NV",
    "sg:tags":[
        "venue"
    ],
    "wof:name":"View 215",
    "wof:placetype":"venue"
},
  "geometry": {"coordinates":[-115.29123,36.085197],"type":"Point"}
}