{
  "type": "Feature",
  "properties": {
    "iso:country":"US",
    "sg:address":"10921 Mount Royal Ave",
    "sg:city":"Las Vegas",
    "sg:classifiers":[
        {
            "category":"Organizations",
            "subcategory":"Community Association",
            "type":"Services"
        }
    ],
    "sg:phone":"+1 702 617 1237",
    "sg:postcode":"89144",
    "sg:province":"NV",
    "wof:name":"Lodge Inc",
    "wof:placetype":"venue"
},
  "geometry": {"coordinates":[-115.3344,36.174864],"type":"Point"}
}