{
  "type": "Feature",
  "properties": {
    "iso:country":"US",
    "sg:address":"5685 S Eastern Ave",
    "sg:city":"Las Vegas",
    "sg:classifiers":[
        {
            "category":"Food & Beverages",
            "subcategory":"Groceries & Convenience Stores",
            "type":"Retail Goods"
        }
    ],
    "sg:phone":"+1 702 739 8651",
    "sg:postcode":"89119",
    "sg:province":"NV",
    "sg:tags":[
        "station",
        "gasoline"
    ],
    "wof:name":"Circle K",
    "wof:placetype":"venue"
},
  "geometry": {"coordinates":[-115.1189,36.089661],"type":"Point"}
}