{
  "type": "Feature",
  "properties": {
    "iso:country":"US",
    "sg:address":"2350 Oddie Blvd",
    "sg:city":"Sparks",
    "sg:classifiers":[
        {
            "category":"Shopping",
            "subcategory":"Discount & Variety Stores",
            "type":"Retail Goods"
        }
    ],
    "sg:phone":"+1 775 359 4244",
    "sg:postcode":"89431",
    "sg:province":"NV",
    "wof:name":"Savers",
    "wof:placetype":"venue"
},
  "geometry": {"coordinates":[-119.776715,39.545551],"type":"Point"}
}