{
  "type": "Feature",
  "properties": {
    "iso:country":"US",
    "sg:address":"6305 Sapphire Blue Court",
    "sg:city":"Las Vegas",
    "sg:classifiers":[
        {
            "category":"Shopping",
            "subcategory":"Stationery & Office Supplies",
            "type":"Retail Goods"
        }
    ],
    "sg:phone":"+1 702 838 5878",
    "sg:postcode":"89108",
    "sg:province":"NV",
    "sg:tags":[
        "equipment"
    ],
    "wof:name":"Indof",
    "wof:placetype":"venue"
},
  "geometry": {"coordinates":[-115.228797,36.187489],"type":"Point"}
}