{
  "type": "Feature",
  "properties": {
    "iso:country":"US",
    "sg:address":"58 N Ronald Ln",
    "sg:city":"Las Vegas",
    "sg:classifiers":[
        {
            "category":"Building & Trades",
            "subcategory":"Construction",
            "type":"Services"
        }
    ],
    "sg:phone":"+1 702 248 4033",
    "sg:postcode":"89110",
    "sg:province":"NV",
    "sg:tags":[
        "concrete",
        "contractor"
    ],
    "wof:name":"El Salvador Concrete",
    "wof:placetype":"venue"
},
  "geometry": {"coordinates":[-115.086292,36.159661],"type":"Point"}
}