{
  "type": "Feature",
  "properties": {
    "iso:country":"US",
    "sg:address":"4010 W Ali Baba Ln",
    "sg:city":"Las Vegas",
    "sg:classifiers":[
        {
            "category":"Manufacturing",
            "subcategory":"Printing",
            "type":"Manufacturing & Wholesale Goods"
        }
    ],
    "sg:phone":"+1 702 269 4545",
    "sg:postcode":"89118",
    "sg:province":"NV",
    "sg:tags":[
        "multimedia"
    ],
    "sg:website":"www.3vmedia.com",
    "wof:name":"3 V Media",
    "wof:placetype":"venue"
},
  "geometry": {"coordinates":[-115.19145,36.095503],"type":"Point"}
}