{
  "type": "Feature",
  "properties": {
    "iso:country":"US",
    "sg:address":"2320 Woodcrest Ln",
    "sg:city":"Carson City",
    "sg:classifiers":[
        {
            "category":"Government",
            "subcategory":"Police Station",
            "type":"Public Place"
        }
    ],
    "sg:phone":"+1 775 885 9111",
    "sg:postcode":"89701",
    "sg:province":"NV",
    "sg:tags":[
        "federal"
    ],
    "wof:name":"Senator Richard H Bryan",
    "wof:placetype":"venue"
},
  "geometry": {"coordinates":[-119.754852,39.14571],"type":"Point"}
}