{
  "type": "Feature",
  "properties": {
    "iso:country":"US",
    "sg:address":"6521 Homestead Rd",
    "sg:city":"Pahrump",
    "sg:classifiers":[
        {
            "category":"Building & Trades",
            "subcategory":"Construction",
            "type":"Services"
        }
    ],
    "sg:phone":"+1 775 727 0391",
    "sg:postcode":"89048",
    "sg:province":"NV",
    "sg:tags":[
        "contractor"
    ],
    "wof:name":"Dbe Excavating",
    "wof:placetype":"venue"
},
  "geometry": {"coordinates":[-115.95768,36.127186],"type":"Point"}
}