{
  "type": "Feature",
  "properties": {
    "iso:country":"US",
    "sg:address":"1608 Cedar Dr",
    "sg:city":"Boulder City",
    "sg:classifiers":[
        {
            "category":"Retail",
            "subcategory":"Photofinishing",
            "type":"Services"
        }
    ],
    "sg:phone":"+1 702 293 1160",
    "sg:postcode":"89005",
    "sg:province":"NV",
    "sg:tags":[
        "laboratory"
    ],
    "wof:name":"DCI Photography",
    "wof:placetype":"venue"
},
  "geometry": {"coordinates":[-114.854958,35.968693],"type":"Point"}
}