{
  "type": "Feature",
  "properties": {
    "iso:country":"US",
    "sg:address":"10101 Double R Blvd",
    "sg:city":"Reno",
    "sg:phone":"+1 775 982 7000",
    "sg:postcode":"89521",
    "sg:province":"NV",
    "sg:website":"http://www.renown.org",
    "wof:name":"Renown South Meadows Medical Center",
    "wof:placetype":"venue"
},
  "geometry": {"coordinates":[-119.757367,39.434172],"type":"Point"}
}