{
  "type": "Feature",
  "properties": {
    "iso:country":"US",
    "sg:address":"1500 Marietta Way",
    "sg:city":"Sparks",
    "sg:classifiers":[
        {
            "category":"Retail",
            "subcategory":"Auto Repair",
            "type":"Services"
        }
    ],
    "sg:phone":"+1 775 358 5900",
    "sg:postcode":"89431",
    "sg:province":"NV",
    "sg:tags":[
        "body"
    ],
    "wof:name":"Benjamins Auto Body",
    "wof:placetype":"venue"
},
  "geometry": {"coordinates":[-119.753992,39.520565],"type":"Point"}
}