{
  "type": "Feature",
  "properties": {
    "iso:country":"US",
    "sg:address":"4660 Lakeside Dr",
    "sg:city":"Reno",
    "sg:classifiers":[
        {
            "category":"Professional",
            "subcategory":"Accounting & Tax Preparation",
            "type":"Services"
        }
    ],
    "sg:phone":"+1 775 824 4585",
    "sg:postcode":"89509",
    "sg:province":"NV",
    "sg:tags":[
        "billing"
    ],
    "wof:name":"Coding Connection",
    "wof:placetype":"venue"
},
  "geometry": {"coordinates":[-119.80787,39.481119],"type":"Point"}
}