{
  "type": "Feature",
  "properties": {
    "iso:country":"US",
    "sg:address":"7721 Partridge Ave",
    "sg:city":"Las Vegas",
    "sg:classifiers":[
        {
            "category":"Building & Trades",
            "subcategory":"Construction",
            "type":"Services"
        }
    ],
    "sg:phone":"+1 702 363 2839",
    "sg:postcode":"89145",
    "sg:province":"NV",
    "sg:tags":[
        "contractor"
    ],
    "wof:name":"Klimes Equipment Repair",
    "wof:placetype":"venue"
},
  "geometry": {"coordinates":[-115.263613,36.163848],"type":"Point"}
}