{
  "type": "Feature",
  "properties": {
    "iso:country":"US",
    "sg:address":"3656 Pecos-Mcleod Connect",
    "sg:city":"Las Vegas",
    "sg:classifiers":[
        {
            "category":"Restaurant",
            "type":"Food & Drink"
        }
    ],
    "sg:phone":"+1 702 696 1231",
    "sg:postcode":"89121",
    "sg:province":"NV",
    "sg:tags":[
        "banquet",
        "rooms"
    ],
    "wof:name":"El Caribe Banquets",
    "wof:placetype":"venue"
},
  "geometry": {"coordinates":[-115.10813,36.1248],"type":"Point"}
}