{
  "type": "Feature",
  "properties": {
    "iso:country":"US",
    "sg:address":"4001 S Decatur Boulevard Suite 37",
    "sg:city":"Las Vegas",
    "sg:classifiers":[
        {
            "category":"Professional",
            "subcategory":"Lawyer & Legal Services",
            "type":"Services"
        }
    ],
    "sg:phone":"+1 702 871 9080",
    "sg:postcode":"89103",
    "sg:province":"NV",
    "sg:tags":[
        "notary"
    ],
    "wof:name":"The Ups Store",
    "wof:placetype":"venue"
},
  "geometry": {"coordinates":[-115.20831099999999,36.117086],"type":"Point"}
}