{
  "type": "Feature",
  "properties": {
    "iso:country":"US",
    "sg:address":"3250 N Tenaya Way Ste 107",
    "sg:city":"Las Vegas",
    "sg:classifiers":[
        {
            "category":"Cinema",
            "subcategory":"Movie Rental",
            "type":"Entertainment"
        }
    ],
    "sg:phone":"+1 702 655 1921",
    "sg:postcode":"89129",
    "sg:province":"NV",
    "sg:tags":[
        "game",
        "video"
    ],
    "sg:website":"www.gamerepair.com",
    "wof:name":"Game Repair",
    "wof:placetype":"venue"
},
  "geometry": {"coordinates":[-115.250999,36.2192],"type":"Point"}
}