{
  "type": "Feature",
  "properties": {
    "iso:country":"US",
    "sg:address":"10091 Vicki Ann Rd",
    "sg:city":"Pahrump",
    "sg:classifiers":[
        {
            "category":"Manufacturing",
            "subcategory":"Wood Products",
            "type":"Manufacturing & Wholesale Goods"
        }
    ],
    "sg:phone":"+1 775 751 8851",
    "sg:postcode":"89048",
    "sg:province":"NV",
    "sg:tags":[
        "mfg"
    ],
    "wof:name":"Denas Delights",
    "wof:placetype":"venue"
},
  "geometry": {"coordinates":[-115.974902,36.070506],"type":"Point"}
}