{
  "type": "Feature",
  "properties": {
    "iso:country":"US",
    "sg:address":"1805 N Carson St",
    "sg:city":"Carson City",
    "sg:classifiers":[
        {
            "category":"Professional",
            "subcategory":"Computer Services",
            "type":"Services"
        }
    ],
    "sg:phone":"+1 775 772 9895",
    "sg:postcode":"89701",
    "sg:province":"NV",
    "sg:tags":[
        "record",
        "management",
        "electronic",
        "system"
    ],
    "wof:name":"N V X Incorporated",
    "wof:placetype":"venue"
},
  "geometry": {"coordinates":[-119.766823,39.175645],"type":"Point"}
}