{
  "type": "Feature",
  "properties": {
    "iso:country":"US",
    "sg:address":"1325 Airmotive Way",
    "sg:city":"Reno",
    "sg:classifiers":[
        {
            "category":"Real Estate",
            "subcategory":"Real Estate Operator",
            "type":"Services"
        }
    ],
    "sg:phone":"+1 775 786 7001",
    "sg:postcode":"89502",
    "sg:province":"NV",
    "sg:tags":[
        "mobile",
        "residential",
        "builder",
        "home"
    ],
    "wof:name":"Lakeside Village",
    "wof:placetype":"venue"
},
  "geometry": {"coordinates":[-119.778866,39.511019],"type":"Point"}
}