{
  "type": "Feature",
  "properties": {
    "iso:country":"US",
    "sg:address":"8993 W Flamingo Rd",
    "sg:city":"Las Vegas",
    "sg:classifiers":[
        {
            "category":"Health Services",
            "subcategory":"Dentist",
            "type":"Services"
        }
    ],
    "sg:phone":"+1 702 438 0007",
    "sg:postcode":"89147",
    "sg:province":"NV",
    "wof:name":"Joe Brandon H DDS Ms",
    "wof:placetype":"venue"
},
  "geometry": {"coordinates":[-115.28782099999999,36.114732],"type":"Point"}
}