{
  "type": "Feature",
  "properties": {
    "iso:country":"US",
    "sg:address":"4808 Quinlan Ave",
    "sg:city":"Las Vegas",
    "sg:classifiers":[
        {
            "category":"Personal",
            "type":"Services"
        }
    ],
    "sg:phone":"+1 702 250 7501",
    "sg:postcode":"89130",
    "sg:province":"NV",
    "sg:tags":[
        "therapist",
        "massage"
    ],
    "wof:name":"Sandra L Jernagin Massage",
    "wof:placetype":"venue"
},
  "geometry": {"coordinates":[-115.209565,36.231453],"type":"Point"}
}