{
  "type": "Feature",
  "properties": {
    "iso:country":"US",
    "sg:address":"6696 Coronado Palms Ave",
    "sg:city":"Las Vegas",
    "sg:classifiers":[
        {
            "category":"Real Estate",
            "subcategory":"Real Estate Agent",
            "type":"Services"
        }
    ],
    "sg:phone":"+1 702 407 2355",
    "sg:postcode":"89139",
    "sg:province":"NV",
    "wof:name":"Pinnacle Sales Office",
    "wof:placetype":"venue"
},
  "geometry": {"coordinates":[-115.238626,36.049395],"type":"Point"}
}