{
  "type": "Feature",
  "properties": {
    "iso:country":"US",
    "sg:address":"4621 Goni Rd",
    "sg:city":"Carson City",
    "sg:classifiers":[
        {
            "category":"Manufacturing",
            "subcategory":"Rubber & Plastics",
            "type":"Manufacturing & Wholesale Goods"
        }
    ],
    "sg:phone":"+1 775 885 9298",
    "sg:postcode":"89706",
    "sg:province":"NV",
    "sg:tags":[
        "mfg",
        "mold",
        "molding"
    ],
    "wof:name":"Mattox Machine Shop",
    "wof:placetype":"venue"
},
  "geometry": {"coordinates":[-119.747138,39.200956],"type":"Point"}
}