{
  "type": "Feature",
  "properties": {
    "iso:country":"US",
    "sg:address":"1526 Pittman Ave",
    "sg:city":"Sparks",
    "sg:phone":"+1 775 356 8505",
    "sg:postcode":"89431",
    "sg:province":"NV",
    "sg:tags":[
        "equipment",
        "durable",
        "good",
        "commercial"
    ],
    "wof:name":"Ace Coin Machines",
    "wof:placetype":"venue"
},
  "geometry": {"coordinates":[-119.764352,39.529607],"type":"Point"}
}