{
  "type": "Feature",
  "properties": {
    "iso:country":"US",
    "sg:address":"220 E Warm Springs Rd",
    "sg:city":"Las Vegas",
    "sg:classifiers":[
        {
            "category":"Professional",
            "type":"Services"
        },
        {
            "category":"Restaurant",
            "type":"Food & Drink"
        }
    ],
    "sg:phone":"+1 702 577 2270",
    "sg:postcode":"89119",
    "sg:province":"NV",
    "sg:tags":[
        "pizza",
        "caterer"
    ],
    "sg:website":"www.nobleromans220.com",
    "wof:name":"Noble Roman's",
    "wof:placetype":"venue"
},
  "geometry": {"coordinates":[-115.163151,36.057056],"type":"Point"}
}