{
  "type": "Feature",
  "properties": {
    "iso:country":"US",
    "sg:address":"9490 Bermuda Rd",
    "sg:city":"Las Vegas",
    "sg:classifiers":[
        {
            "category":"Building & Trades",
            "subcategory":"Cleaning & Sanitation",
            "type":"Services"
        }
    ],
    "sg:phone":"+1 702 307 1778",
    "sg:postcode":"89123",
    "sg:province":"NV",
    "sg:tags":[
        "janitor"
    ],
    "wof:name":"Strip & Seal",
    "wof:placetype":"venue"
},
  "geometry": {"coordinates":[-115.154506,36.020348],"type":"Point"}
}