{
  "type": "Feature",
  "properties": {
    "iso:country":"US",
    "sg:address":"2285 Harvard Way",
    "sg:city":"Reno",
    "sg:classifiers":[
        {
            "category":"Retail",
            "subcategory":"Auto Repair",
            "type":"Services"
        }
    ],
    "sg:phone":"+1 775 324 1157",
    "sg:postcode":"89502",
    "sg:province":"NV",
    "sg:tags":[
        "repairing",
        "automobile"
    ],
    "wof:name":"B & K Quality Auto & Truck",
    "wof:placetype":"venue"
},
  "geometry": {"coordinates":[-119.785866,39.501759],"type":"Point"}
}