{
  "type": "Feature",
  "properties": {
    "iso:country":"US",
    "sg:address":"1471 N Jones Blvd",
    "sg:city":"Las Vegas",
    "sg:classifiers":[
        {
            "category":"Health Services",
            "subcategory":"Dentist",
            "type":"Services"
        }
    ],
    "sg:phone":"+1 702 851 6722",
    "sg:postcode":"89108",
    "sg:province":"NV",
    "wof:name":"Todays Dental",
    "wof:placetype":"venue"
},
  "geometry": {"coordinates":[-115.224249,36.187608],"type":"Point"}
}