{
  "type": "Feature",
  "properties": {
    "iso:country":"US",
    "sg:address":"1236 Blankenship Ave",
    "sg:city":"Las Vegas",
    "sg:classifiers":[
        {
            "category":"Restaurant",
            "type":"Food & Drink"
        }
    ],
    "sg:phone":"+1 702 453 2314",
    "sg:postcode":"89106",
    "sg:province":"NV",
    "sg:tags":[
        "eating"
    ],
    "wof:name":"Tildas Catering",
    "wof:placetype":"venue"
},
  "geometry": {"coordinates":[-115.157179,36.201275],"type":"Point"}
}