{
  "type": "Feature",
  "properties": {
    "iso:country":"US",
    "sg:address":"3763 Honey Ridge Ct",
    "sg:city":"Las Vegas",
    "sg:classifiers":[
        {
            "category":"Home & Garden",
            "subcategory":"Building Materials",
            "type":"Retail Goods"
        }
    ],
    "sg:phone":"+1 702 247 8882",
    "sg:postcode":"89135",
    "sg:province":"NV",
    "sg:tags":[
        "wallpaper",
        "accessory"
    ],
    "wof:name":"Wallpaper Elegance",
    "wof:placetype":"venue"
},
  "geometry": {"coordinates":[-115.33269199999999,36.120466],"type":"Point"}
}