{
  "type": "Feature",
  "properties": {
    "iso:country":"US",
    "sg:address":"7720 W Sahara Ave",
    "sg:city":"Las Vegas",
    "sg:classifiers":[
        {
            "category":"Personal",
            "type":"Services"
        }
    ],
    "sg:phone":"+1 702 296 6647",
    "sg:postcode":"89117",
    "sg:province":"NV",
    "sg:tags":[
        "therapist",
        "massage"
    ],
    "wof:name":"Samantha A Cirulli Massage",
    "wof:placetype":"venue"
},
  "geometry": {"coordinates":[-115.259576,36.143795],"type":"Point"}
}