{
  "type": "Feature",
  "properties": {
    "iso:country":"US",
    "sg:address":"1300 Mound House St",
    "sg:city":"Las Vegas",
    "sg:classifiers":[
        {
            "category":"Professional",
            "subcategory":"Management & Consulting",
            "type":"Services"
        }
    ],
    "sg:phone":"+1 702 531 6020",
    "sg:postcode":"89110",
    "sg:province":"NV",
    "sg:tags":[
        "fuel"
    ],
    "wof:name":"District 4 Manager",
    "wof:placetype":"venue"
},
  "geometry": {"coordinates":[-115.02912000000001,36.18293],"type":"Point"}
}