{
  "type": "Feature",
  "properties": {
    "iso:country":"US",
    "sg:address":"870 Deming Way",
    "sg:city":"Sparks",
    "sg:classifiers":[
        {
            "category":"Building & Trades",
            "subcategory":"Construction",
            "type":"Services"
        }
    ],
    "sg:phone":"+1 775 331 9099",
    "sg:postcode":"89431",
    "sg:province":"NV",
    "sg:tags":[
        "contractor"
    ],
    "wof:name":"Energetic Painting & Drywall",
    "wof:placetype":"venue"
},
  "geometry": {"coordinates":[-119.72205700000001,39.524772],"type":"Point"}
}