{
  "type": "Feature",
  "properties": {
    "iso:country":"US",
    "sg:address":"1480 Charleston Park Ave",
    "sg:city":"Pahrump",
    "sg:classifiers":[
        {
            "category":"Restaurant",
            "type":"Food & Drink"
        }
    ],
    "sg:phone":"+1 775 751 0700",
    "sg:postcode":"89048",
    "sg:province":"NV",
    "wof:name":"Charleston Pizza Factory",
    "wof:placetype":"venue"
},
  "geometry": {"coordinates":[-116.039863,36.20494],"type":"Point"}
}