{
  "type": "Feature",
  "properties": {
    "iso:country":"US",
    "sg:address":"2321 Hassett Ave",
    "sg:city":"Las Vegas",
    "sg:classifiers":[
        {
            "category":"Shopping",
            "subcategory":"Clothing, Apparel, & Fashions",
            "type":"Retail Goods"
        }
    ],
    "sg:phone":"+1 702 457 7747",
    "sg:postcode":"89104",
    "sg:province":"NV",
    "sg:tags":[
        "robe"
    ],
    "wof:name":"For Heaven's Sake",
    "wof:placetype":"venue"
},
  "geometry": {"coordinates":[-115.111468,36.150444],"type":"Point"}
}