{
  "type": "Feature",
  "properties": {
    "iso:country":"US",
    "sg:address":"2300 Paseo Verde Pkwy Green Valley Ranch Resort",
    "sg:city":"Henderson",
    "sg:classifiers":[
        {
            "category":"Juice Bar",
            "subcategory":"None",
            "type":"Food & Drink"
        },
        {
            "category":"Food & Beverages",
            "subcategory":"Bakery",
            "type":"Retail Goods"
        }
    ],
    "sg:phone":"+1 702 822 1931",
    "sg:postcode":"89052",
    "sg:province":"NV",
    "sg:tags":[
        "smoothy",
        "sandwich"
    ],
    "wof:name":"Tropical Smoothie Cafe",
    "wof:placetype":"venue"
},
  "geometry": {"coordinates":[-115.089995,36.020557],"type":"Point"}
}