{
  "type": "Feature",
  "properties": {
    "iso:country":"US",
    "sg:address":"8095 S Rainbow Blvd",
    "sg:city":"Las Vegas",
    "sg:classifiers":[
        {
            "category":"Autos & Motor Vehicles",
            "subcategory":"Fuel & Gas Station",
            "type":"Retail Goods"
        }
    ],
    "sg:phone":"+1 702 589 2840",
    "sg:postcode":"89139",
    "sg:province":"NV",
    "wof:name":"Choice",
    "wof:placetype":"venue"
},
  "geometry": {"coordinates":[-115.243617,36.041264],"type":"Point"}
}