{
  "type": "Feature",
  "properties": {
    "iso:country":"US",
    "sg:address":"Miracle Mile Shops 3667 Las Vegas Blvd S",
    "sg:city":"Las Vegas",
    "sg:classifiers":[
        {
            "category":"Arts & Performance",
            "subcategory":"Art Gallery",
            "type":"Entertainment"
        }
    ],
    "sg:phone":"+1 702 691 2506",
    "sg:postcode":"89136",
    "sg:province":"NV",
    "sg:website":"www.metmuseum.org/store",
    "wof:name":"The Metropolitan Museum of Art Store",
    "wof:placetype":"venue"
},
  "geometry": {"coordinates":[-115.17282,36.11077],"type":"Point"}
}