{
  "type": "Feature",
  "properties": {
    "iso:country":"US",
    "sg:address":"4350 Arville Street Suite 15",
    "sg:city":"Las Vegas",
    "sg:classifiers":[
        {
            "category":"Shopping",
            "subcategory":"Clothing, Apparel, & Fashions",
            "type":"Retail Goods"
        }
    ],
    "sg:phone":"+1 702 362 3096",
    "sg:postcode":"89103",
    "sg:province":"NV",
    "sg:tags":[
        "costume"
    ],
    "wof:name":"Imagination Costume",
    "wof:placetype":"venue"
},
  "geometry": {"coordinates":[-115.199304,36.110917],"type":"Point"}
}