{
  "type": "Feature",
  "properties": {
    "iso:country":"US",
    "sg:address":"1488 US Highway 395 N",
    "sg:city":"Gardnerville",
    "sg:classifiers":[
        {
            "category":"Restaurant",
            "type":"Food & Drink"
        }
    ],
    "sg:phone":"+1 775 782 4897",
    "sg:postcode":"89410",
    "sg:province":"NV",
    "sg:tags":[
        "italian"
    ],
    "wof:name":"Two Guys From Italy",
    "wof:placetype":"venue"
},
  "geometry": {"coordinates":[-119.557917,38.734203],"type":"Point"}
}