{
  "type": "Feature",
  "properties": {
    "iso:country":"US",
    "sg:address":"3111 W Tropicana Ave",
    "sg:city":"Las Vegas",
    "sg:classifiers":[
        {
            "category":"Restaurant",
            "type":"Food & Drink"
        }
    ],
    "sg:phone":"+1 702 736 3488",
    "sg:postcode":"89103",
    "sg:province":"NV",
    "sg:tags":[
        "eating"
    ],
    "wof:name":"IHOP",
    "wof:placetype":"venue"
},
  "geometry": {"coordinates":[-115.180325,36.100775],"type":"Point"}
}