{
  "type": "Feature",
  "properties": {
    "iso:country":"US",
    "sg:address":"5525 Wynn Rd",
    "sg:city":"Las Vegas",
    "sg:phone":"+1 702 364 2000",
    "sg:postcode":"89118",
    "sg:province":"NV",
    "sg:tags":[
        "equipment"
    ],
    "wof:name":"A & H Restaurant and Bar Sup",
    "wof:placetype":"venue"
},
  "geometry": {"coordinates":[-115.194587,36.088591],"type":"Point"}
}