{
  "type": "Feature",
  "properties": {
    "iso:country":"US",
    "sg:address":"2968 Juniper Hills Blvd",
    "sg:city":"Las Vegas",
    "sg:classifiers":[
        {
            "category":"Professional",
            "subcategory":"Management & Consulting",
            "type":"Services"
        }
    ],
    "sg:phone":"+1 702 285 7328",
    "sg:postcode":"89142",
    "sg:province":"NV",
    "sg:tags":[
        "support"
    ],
    "wof:name":"Diaz Orlean",
    "wof:placetype":"venue"
},
  "geometry": {"coordinates":[-115.060657,36.138614],"type":"Point"}
}