{
  "type": "Feature",
  "properties": {
    "iso:country":"US",
    "sg:address":"2620 White Pine Dr",
    "sg:city":"Henderson",
    "sg:classifiers":[
        {
            "category":"Professional",
            "subcategory":"Management & Consulting",
            "type":"Services"
        }
    ],
    "sg:phone":"+1 702 837 1215",
    "sg:postcode":"89074",
    "sg:province":"NV",
    "sg:tags":[
        "business"
    ],
    "wof:name":"Water Creations LTD",
    "wof:placetype":"venue"
},
  "geometry": {"coordinates":[-115.103182,36.05178],"type":"Point"}
}