{
  "type": "Feature",
  "properties": {
    "iso:country":"US",
    "sg:address":"5520 Desert Valley Dr",
    "sg:city":"Las Vegas",
    "sg:classifiers":[
        {
            "category":"Personal",
            "type":"Services"
        }
    ],
    "sg:phone":"+1 702 395 4308",
    "sg:postcode":"89149",
    "sg:province":"NV",
    "sg:tags":[
        "consultant",
        "wedding"
    ],
    "wof:name":"Gisela's Weddings Las Vegas",
    "wof:placetype":"venue"
},
  "geometry": {"coordinates":[-115.268309,36.26229],"type":"Point"}
}