{
  "type": "Feature",
  "properties": {
    "iso:country":"US",
    "sg:address":"2161 Pyramid Way",
    "sg:city":"Sparks",
    "sg:classifiers":[
        {
            "category":"Organizations",
            "subcategory":"Religious Organization",
            "type":"Services"
        }
    ],
    "sg:phone":"+1 775 331 4415",
    "sg:postcode":"89431",
    "sg:province":"NV",
    "wof:name":"Mountainview Fellowship",
    "wof:placetype":"venue"
},
  "geometry": {"coordinates":[-119.75269299999999,39.549429],"type":"Point"}
}