{
  "type": "Feature",
  "properties": {
    "iso:country":"US",
    "sg:address":"4840 Spring Mountain Road",
    "sg:city":"Las Vegas",
    "sg:classifiers":[
        {
            "category":"Health Services",
            "subcategory":"Dentist",
            "type":"Services"
        }
    ],
    "sg:phone":"+1 702 256 2111",
    "sg:postcode":"89102",
    "sg:province":"NV",
    "wof:name":"Nguyn Tam P Dentist",
    "wof:placetype":"venue"
},
  "geometry": {"coordinates":[-115.206647,36.126317],"type":"Point"}
}