{
  "type": "Feature",
  "properties": {
    "iso:country":"US",
    "sg:address":"73 US Hwy 95 Alt",
    "sg:city":"Yerington",
    "sg:classifiers":[
        {
            "category":"Farming",
            "subcategory":"Livestock Farm",
            "type":"Manufacturing & Wholesale Goods"
        }
    ],
    "sg:phone":"+1 775 463 2508",
    "sg:postcode":"89447",
    "sg:province":"NV",
    "sg:tags":[
        "beef",
        "cash",
        "crop",
        "field",
        "grain",
        "cattle",
        "feedlot"
    ],
    "wof:name":"Tom Connolly",
    "wof:placetype":"venue"
},
  "geometry": {"coordinates":[-119.16396899999999,38.993814],"type":"Point"}
}