{
  "type": "Feature",
  "properties": {
    "iso:country":"US",
    "sg:address":"3000 E Oquendo Rd",
    "sg:city":"Las Vegas",
    "sg:classifiers":[
        {
            "category":"Real Estate",
            "subcategory":"Real Estate Agent",
            "type":"Services"
        }
    ],
    "sg:phone":"+1 702 456 3194",
    "sg:postcode":"89120",
    "sg:province":"NV",
    "sg:tags":[
        "management"
    ],
    "wof:name":"Terra West Property Management",
    "wof:placetype":"venue"
},
  "geometry": {"coordinates":[-115.108164,36.082707],"type":"Point"}
}