{
  "type": "Feature",
  "properties": {
    "iso:country":"US",
    "sg:address":"4151 E Saint Louis Ave",
    "sg:city":"Las Vegas",
    "sg:classifiers":[
        {
            "category":"Health Services",
            "subcategory":"Hospital",
            "type":"Services"
        }
    ],
    "sg:phone":"+1 702 457 4961",
    "sg:postcode":"89104",
    "sg:province":"NV",
    "sg:tags":[
        "mental"
    ],
    "wof:name":"St Francis Group Home 2",
    "wof:placetype":"venue"
},
  "geometry": {"coordinates":[-115.084678,36.149041],"type":"Point"}
}