{
  "type": "Feature",
  "properties": {
    "iso:country":"US",
    "sg:address":"2605 S Decatur Blvd # 101",
    "sg:city":"Las Vegas",
    "sg:classifiers":[
        {
            "category":"Restaurant",
            "type":"Food & Drink"
        }
    ],
    "sg:phone":"+1 702 222 9557",
    "sg:postcode":"89102",
    "sg:province":"NV",
    "sg:tags":[
        "mexican"
    ],
    "sg:website":"www.lasgorditasrestaurant.com",
    "wof:name":"Las Gorditas",
    "wof:placetype":"venue"
},
  "geometry": {"coordinates":[-115.209177,36.143005],"type":"Point"}
}