{
  "type": "Feature",
  "properties": {
    "iso:country":"US",
    "sg:address":"7110 S Durango Drive",
    "sg:city":"Las Vegas",
    "sg:classifiers":[
        {
            "category":"Food & Beverages",
            "subcategory":"Groceries & Convenience Stores",
            "type":"Retail Goods"
        }
    ],
    "sg:phone":"+1 702 869 5505",
    "sg:postcode":"89113",
    "sg:province":"NV",
    "wof:name":"Fills",
    "wof:placetype":"venue"
},
  "geometry": {"coordinates":[-115.279173,36.058856],"type":"Point"}
}