{
  "type": "Feature",
  "properties": {
    "iso:country":"US",
    "sg:address":"2090 W College Pkwy",
    "sg:city":"Carson City",
    "sg:classifiers":[
        {
            "category":"Professional",
            "subcategory":"Lawyer & Legal Services",
            "type":"Services"
        }
    ],
    "sg:phone":"+1 775 884 0250",
    "sg:postcode":"89703",
    "sg:province":"NV",
    "wof:name":"Gabriel Michael Lynn",
    "wof:placetype":"venue"
},
  "geometry": {"coordinates":[-119.787193,39.186537],"type":"Point"}
}