{
  "type": "Feature",
  "properties": {
    "iso:country":"US",
    "sg:address":"2100 Fremont St",
    "sg:city":"Las Vegas",
    "sg:classifiers":[
        {
            "category":"Restaurant",
            "type":"Food & Drink"
        }
    ],
    "sg:phone":"+1 702 385 6444",
    "sg:postcode":"89101",
    "sg:province":"NV",
    "wof:name":"Ciscos Supper Club Inc",
    "wof:placetype":"venue"
},
  "geometry": {"coordinates":[-115.118464,36.15969],"type":"Point"}
}