{
  "type": "Feature",
  "properties": {
    "iso:country":"US",
    "sg:address":"10040 W Cheyenne Ave",
    "sg:city":"Las Vegas",
    "sg:classifiers":[
        {
            "category":"Food & Beverages",
            "subcategory":"Bakery",
            "type":"Retail Goods"
        }
    ],
    "sg:phone":"+1 702 579 9800",
    "sg:postcode":"89129",
    "sg:province":"NV",
    "sg:tags":[
        "sandwich"
    ],
    "sg:website":"www.slimssubshop.com",
    "wof:name":"Slims Sub Shop",
    "wof:placetype":"venue"
},
  "geometry": {"coordinates":[-115.314701,36.218517],"type":"Point"}
}