{
  "type": "Feature",
  "properties": {
    "iso:country":"US",
    "sg:address":"18 Kit Kat Dr",
    "sg:city":"Carson City",
    "sg:classifiers":[
        {
            "category":"Wholesale",
            "subcategory":"Sporting Goods",
            "type":"Manufacturing & Wholesale Goods"
        },
        {
            "category":"Shopping",
            "subcategory":"Bicycles & Sporting Goods",
            "type":"Retail Goods"
        }
    ],
    "sg:phone":"+1 775 246 3633",
    "sg:postcode":"89706",
    "sg:province":"NV",
    "sg:tags":[
        "equipment",
        "archery",
        "supply"
    ],
    "wof:name":"Meigs' Archery",
    "wof:placetype":"venue"
},
  "geometry": {"coordinates":[-119.6635,39.211812],"type":"Point"}
}