{
  "type": "Feature",
  "properties": {
    "iso:country":"US",
    "sg:address":"2882 Meade Avenue Suite 101",
    "sg:city":"Las Vegas",
    "sg:classifiers":[
        {
            "category":"Building & Trades",
            "subcategory":"Construction",
            "type":"Services"
        }
    ],
    "sg:phone":"+1 702 876 8511",
    "sg:postcode":"89102",
    "sg:province":"NV",
    "sg:tags":[
        "contractor"
    ],
    "wof:name":"K A S Construction & Development",
    "wof:placetype":"venue"
},
  "geometry": {"coordinates":[-115.179633,36.136288],"type":"Point"}
}