{
  "type": "Feature",
  "properties": {
    "iso:country":"US",
    "sg:address":"3104 Blue Monaco St",
    "sg:city":"Las Vegas",
    "sg:classifiers":[
        {
            "category":"Shopping",
            "subcategory":"Gifts & Souvenirs",
            "type":"Retail Goods"
        }
    ],
    "sg:phone":"+1 702 363 5077",
    "sg:postcode":"89117",
    "sg:province":"NV",
    "wof:name":"Bassket Hound",
    "wof:placetype":"venue"
},
  "geometry": {"coordinates":[-115.262599,36.133021],"type":"Point"}
}