{
  "type": "Feature",
  "properties": {
    "iso:country":"US",
    "sg:address":"5801 Sheep Dr",
    "sg:city":"Carson City",
    "sg:classifiers":[
        {
            "category":"Home & Garden",
            "subcategory":"Household Appliances",
            "type":"Retail Goods"
        }
    ],
    "sg:phone":"+1 775 887 9000",
    "sg:postcode":"89701",
    "sg:province":"NV",
    "sg:tags":[
        "cleaners",
        "vacuum"
    ],
    "wof:name":"Silver City Kirby",
    "wof:placetype":"venue"
},
  "geometry": {"coordinates":[-119.698472,39.188556],"type":"Point"}
}