{
  "type": "Feature",
  "properties": {
    "iso:country":"US",
    "sg:address":"1595 E Camero Ave",
    "sg:city":"Las Vegas",
    "sg:classifiers":[
        {
            "category":"Building & Trades",
            "subcategory":"Plumbing",
            "type":"Services"
        }
    ],
    "sg:phone":"+1 702 361 5421",
    "sg:postcode":"89123",
    "sg:province":"NV",
    "sg:tags":[
        "tank",
        "septic"
    ],
    "wof:name":"Valley Excavating",
    "wof:placetype":"venue"
},
  "geometry": {"coordinates":[-115.127831,36.036914],"type":"Point"}
}