{
  "type": "Feature",
  "properties": {
    "iso:country":"US",
    "sg:address":"510 Melarkey St",
    "sg:city":"Winnemucca",
    "sg:classifiers":[
        {
            "category":"Professional",
            "subcategory":"Employment Agencies",
            "type":"Services"
        }
    ],
    "sg:phone":"+1 775 623 6700",
    "sg:postcode":"89445",
    "sg:province":"NV",
    "sg:tags":[
        "help",
        "contractor"
    ],
    "wof:name":"Manpower Temporary Svc",
    "wof:placetype":"venue"
},
  "geometry": {"coordinates":[-117.73367500000001,40.971286],"type":"Point"}
}