{
  "type": "Feature",
  "properties": {
    "iso:country":"US",
    "sg:address":"3111 S Valley View Blvd",
    "sg:city":"Las Vegas",
    "sg:classifiers":[
        {
            "category":"Arts & Performance",
            "subcategory":"Art Gallery",
            "type":"Entertainment"
        }
    ],
    "sg:phone":"+1 702 222 1946",
    "sg:postcode":"89102",
    "sg:province":"NV",
    "wof:name":"Westside Art & Frame Inc",
    "wof:placetype":"venue"
},
  "geometry": {"coordinates":[-115.190002,36.133598],"type":"Point"}
}