{
  "type": "Feature",
  "properties": {
    "iso:country":"US",
    "sg:address":"7480 W Sahara Avenue",
    "sg:city":"Las Vegas",
    "sg:classifiers":[
        {
            "category":"Health Services",
            "subcategory":"Dentist",
            "type":"Services"
        }
    ],
    "sg:phone":"+1 702 562 2033",
    "sg:postcode":"89117",
    "sg:province":"NV",
    "sg:website":"www.scottmillerdds.com",
    "wof:name":"Miller Scott L DDS",
    "wof:placetype":"venue"
},
  "geometry": {"coordinates":[-115.255107,36.144042],"type":"Point"}
}