{
  "type": "Feature",
  "properties": {
    "iso:country":"US",
    "sg:address":"126 Mount Rose St",
    "sg:city":"Reno",
    "sg:classifiers":[
        {
            "category":"Building & Trades",
            "subcategory":"Construction",
            "type":"Services"
        }
    ],
    "sg:phone":"+1 775 348 4877",
    "sg:postcode":"89509",
    "sg:province":"NV",
    "sg:tags":[
        "sun",
        "solarium",
        "rooms",
        "builder"
    ],
    "wof:name":"Four Seasons Design & Rmdlng",
    "wof:placetype":"venue"
},
  "geometry": {"coordinates":[-119.807023,39.509612],"type":"Point"}
}