{
  "type": "Feature",
  "properties": {
    "iso:country":"US",
    "sg:address":"3100 Elkhorn Road",
    "sg:city":"North Las Vegas",
    "sg:classifiers":[
        {
            "category":"Sports & Exercise",
            "subcategory":"Golf",
            "type":"Entertainment"
        }
    ],
    "sg:phone":"+1 702 399 4888",
    "sg:postcode":"89084",
    "sg:province":"NV",
    "sg:website":"www.aliantegolf.com",
    "wof:name":"Aliante Golf Club",
    "wof:placetype":"venue"
},
  "geometry": {"coordinates":[-115.178068,36.294771],"type":"Point"}
}