{
  "type": "Feature",
  "properties": {
    "iso:country":"US",
    "sg:address":"202 S Nevada St",
    "sg:city":"Yerington",
    "sg:classifiers":[
        {
            "category":"Professional",
            "subcategory":"Management & Consulting",
            "type":"Services"
        }
    ],
    "sg:phone":"+1 775 463 5538",
    "sg:postcode":"89447",
    "sg:province":"NV",
    "sg:tags":[
        "machine",
        "energy",
        "saving"
    ],
    "wof:name":"Invention Innovations",
    "wof:placetype":"venue"
},
  "geometry": {"coordinates":[-119.161452,38.984283],"type":"Point"}
}