{
  "type": "Feature",
  "properties": {
    "iso:country":"US",
    "sg:address":"827 S Boulder Hwy",
    "sg:city":"Henderson",
    "sg:classifiers":[
        {
            "category":"Autos & Motor Vehicles",
            "subcategory":"Auto Supplies",
            "type":"Retail Goods"
        }
    ],
    "sg:phone":"+1 702 565 8735",
    "sg:postcode":"89015",
    "sg:province":"NV",
    "sg:tags":[
        "automobile",
        "parts"
    ],
    "wof:name":"NAPA Auto Parts Stores",
    "wof:placetype":"venue"
},
  "geometry": {"coordinates":[-114.973128,36.031773],"type":"Point"}
}