{
  "type": "Feature",
  "properties": {
    "iso:country":"US",
    "sg:address":"4255 Channel 10 Drive Ofc",
    "sg:city":"Las Vegas",
    "sg:classifiers":[
        {
            "category":"Real Estate",
            "subcategory":"Real Estate Operator",
            "type":"Services"
        }
    ],
    "sg:phone":"+1 702 735 9173",
    "sg:postcode":"89119",
    "sg:province":"NV",
    "sg:tags":[
        "apartment"
    ],
    "wof:name":"Villa Del Sol Apartments",
    "wof:placetype":"venue"
},
  "geometry": {"coordinates":[-115.121418,36.11179],"type":"Point"}
}