{
  "type": "Feature",
  "properties": {
    "iso:country":"US",
    "sg:address":"7924 Howard Dade Ave",
    "sg:city":"Las Vegas",
    "sg:classifiers":[
        {
            "category":"Professional",
            "subcategory":"Management & Consulting",
            "type":"Services"
        }
    ],
    "sg:phone":"+1 702 616 1691",
    "sg:postcode":"89129",
    "sg:province":"NV",
    "sg:tags":[
        "business"
    ],
    "wof:name":"Golden Hour Consulting",
    "wof:placetype":"venue"
},
  "geometry": {"coordinates":[-115.266948,36.230296],"type":"Point"}
}