{
  "type": "Feature",
  "properties": {
    "iso:country":"US",
    "sg:address":"1798 Shadow Park Dr",
    "sg:city":"Reno",
    "sg:classifiers":[
        {
            "category":"Building & Trades",
            "subcategory":"Plumbing",
            "type":"Services"
        }
    ],
    "sg:phone":"+1 775 747 2400",
    "sg:postcode":"89523",
    "sg:province":"NV",
    "sg:tags":[
        "product",
        "management",
        "energy",
        "system"
    ],
    "wof:name":"Bighorn Energy Svc",
    "wof:placetype":"venue"
},
  "geometry": {"coordinates":[-119.876389,39.530594],"type":"Point"}
}