{
  "type": "Feature",
  "properties": {
    "iso:country":"US",
    "sg:address":"2113 Alta Dr",
    "sg:city":"Las Vegas",
    "sg:classifiers":[
        {
            "category":"Food & Beverages",
            "subcategory":"Specialty",
            "type":"Retail Goods"
        },
        {
            "category":"Wholesale",
            "subcategory":"Drugs",
            "type":"Manufacturing & Wholesale Goods"
        }
    ],
    "sg:phone":"+1 702 382 5895",
    "sg:postcode":"89106",
    "sg:province":"NV",
    "sg:tags":[
        "vitamin"
    ],
    "wof:name":"Intraglobal Nutritional Prod",
    "wof:placetype":"venue"
},
  "geometry": {"coordinates":[-115.170606,36.166232],"type":"Point"}
}