{
  "type": "Feature",
  "properties": {
    "iso:country":"US",
    "sg:address":"11 W McArthur Ave",
    "sg:city":"Winnemucca",
    "sg:classifiers":[
        {
            "category":"Organizations",
            "subcategory":"Religious Organization",
            "type":"Services"
        }
    ],
    "sg:phone":"+1 775 623 4508",
    "sg:postcode":"89445",
    "sg:province":"NV",
    "sg:tags":[
        "church"
    ],
    "wof:name":"Winnemucca First LDS Ward",
    "wof:placetype":"venue"
},
  "geometry": {"coordinates":[-117.719964,40.966393],"type":"Point"}
}