{
  "type": "Feature",
  "properties": {
    "iso:country":"US",
    "sg:address":"1512 US Hwy 395 N",
    "sg:city":"Gardnerville",
    "sg:classifiers":[
        {
            "category":"Real Estate",
            "subcategory":"Real Estate Agent",
            "type":"Services"
        }
    ],
    "sg:phone":"+1 775 783 4007",
    "sg:postcode":"89410",
    "sg:province":"NV",
    "wof:name":"Silvera Commercial Real Estate",
    "wof:placetype":"venue"
},
  "geometry": {"coordinates":[-119.760469,38.950759],"type":"Point"}
}