{
  "type": "Feature",
  "properties": {
    "iso:country":"US",
    "sg:address":"4804 S Nellis Blvd",
    "sg:city":"Las Vegas",
    "sg:classifiers":[
        {
            "category":"Retail",
            "subcategory":"Repair Shop",
            "type":"Services"
        },
        {
            "category":"Home & Garden",
            "subcategory":"Garden Supply",
            "type":"Retail Goods"
        }
    ],
    "sg:phone":"+1 702 456 5866",
    "sg:postcode":"89121",
    "sg:province":"NV",
    "sg:tags":[
        "lawn",
        "mower",
        "mfg"
    ],
    "wof:name":"Lawn Mower Shop The",
    "wof:placetype":"venue"
},
  "geometry": {"coordinates":[-115.063964,36.10212],"type":"Point"}
}