{
  "type": "Feature",
  "properties": {
    "iso:country":"US",
    "sg:address":"1744 Forrest Way",
    "sg:city":"Carson City",
    "sg:classifiers":[
        {
            "category":"Professional",
            "subcategory":"Business Services",
            "type":"Services"
        }
    ],
    "sg:phone":"+1 775 884 1010",
    "sg:postcode":"89706",
    "sg:province":"NV",
    "wof:name":"Metal Solutions",
    "wof:placetype":"venue"
},
  "geometry": {"coordinates":[-119.750061,39.203647],"type":"Point"}
}