{
  "type": "Feature",
  "properties": {
    "iso:country":"US",
    "sg:address":"414 Poplar Dr",
    "sg:city":"Elko",
    "sg:classifiers":[
        {
            "category":"Arts & Performance",
            "subcategory":"Theater",
            "type":"Entertainment"
        }
    ],
    "sg:phone":"+1 775 777 1004",
    "sg:postcode":"89801",
    "sg:province":"NV",
    "sg:tags":[
        "karaoke"
    ],
    "wof:name":"Canyon Air Karaoke",
    "wof:placetype":"venue"
},
  "geometry": {"coordinates":[-115.792034,40.844486],"type":"Point"}
}