{
  "type": "Feature",
  "properties": {
    "iso:country":"US",
    "sg:address":"1389 Galleria Drive Suite 100",
    "sg:city":"Henderson",
    "sg:classifiers":[
        {
            "category":"Real Estate",
            "subcategory":"Real Estate Services",
            "type":"Services"
        }
    ],
    "sg:phone":"+1 702 795 4500",
    "sg:postcode":"89014",
    "sg:province":"NV",
    "sg:website":"www.realtyex.com",
    "wof:name":"Realty Executives of Nevada",
    "wof:placetype":"venue"
},
  "geometry": {"coordinates":[-115.044578,36.070869],"type":"Point"}
}