{
  "type": "Feature",
  "properties": {
    "iso:country":"US",
    "sg:address":"4070 Silvestri Ln",
    "sg:city":"Las Vegas",
    "sg:classifiers":[
        {
            "category":"Building & Trades",
            "subcategory":"Landscaping Services",
            "type":"Services"
        }
    ],
    "sg:phone":"+1 702 456 9702",
    "sg:postcode":"89120",
    "sg:province":"NV",
    "sg:tags":[
        "tree"
    ],
    "wof:name":"A American Tree Svc",
    "wof:placetype":"venue"
},
  "geometry": {"coordinates":[-115.086105,36.076628],"type":"Point"}
}