{
  "type": "Feature",
  "properties": {
    "iso:country":"US",
    "sg:address":"3601 E Wyoming Ave",
    "sg:city":"Las Vegas",
    "sg:classifiers":[
        {
            "category":"Organizations",
            "subcategory":"Religious Organization",
            "type":"Services"
        }
    ],
    "sg:phone":"+1 702 432 6614",
    "sg:postcode":"89104",
    "sg:province":"NV",
    "sg:tags":[
        "church"
    ],
    "wof:name":"Perfection In Christ Ministry",
    "wof:placetype":"venue"
},
  "geometry": {"coordinates":[-115.096133,36.151717],"type":"Point"}
}