{
  "type": "Feature",
  "properties": {
    "iso:country":"US",
    "sg:address":"1947 Cedar Hill Ct",
    "sg:city":"Henderson",
    "sg:classifiers":[
        {
            "category":"Real Estate",
            "subcategory":"Real Estate Operator",
            "type":"Services"
        }
    ],
    "sg:phone":"+1 702 386 3999",
    "sg:postcode":"89012",
    "sg:province":"NV",
    "sg:tags":[
        "landholding"
    ],
    "wof:name":"Alran Land Company",
    "wof:placetype":"venue"
},
  "geometry": {"coordinates":[-115.072204,36.02264],"type":"Point"}
}