{
  "type": "Feature",
  "properties": {
    "iso:country":"US",
    "sg:address":"2571 Anthem Village Dr",
    "sg:city":"Henderson",
    "sg:classifiers":[
        {
            "category":"Banks & Credit Unions",
            "subcategory":"Bank",
            "type":"Services"
        }
    ],
    "sg:phone":"+1 702 891 8880",
    "sg:postcode":"89052",
    "sg:province":"NV",
    "sg:tags":[
        "loan",
        "real estate"
    ],
    "wof:name":"Savings Mortgage Inc",
    "wof:placetype":"venue"
},
  "geometry": {"coordinates":[-115.0996,35.980109],"type":"Point"}
}