{
  "type": "Feature",
  "properties": {
    "iso:country":"US",
    "sg:address":"409 Glen Haven Dr",
    "sg:city":"Spring Creek",
    "sg:classifiers":[
        {
            "category":"Building & Trades",
            "subcategory":"Electrical",
            "type":"Services"
        }
    ],
    "sg:phone":"+1 775 753 8205",
    "sg:postcode":"89815",
    "sg:province":"NV",
    "sg:tags":[
        "electrical",
        "contractor"
    ],
    "wof:name":"Morgan Mj Electric",
    "wof:placetype":"venue"
},
  "geometry": {"coordinates":[-115.58325600000001,40.734367],"type":"Point"}
}