{
  "type": "Feature",
  "properties": {
    "iso:country":"US",
    "sg:address":"621 Mall Ring Cir",
    "sg:city":"Henderson",
    "sg:classifiers":[
        {
            "category":"Home & Garden",
            "subcategory":"Furniture",
            "type":"Retail Goods"
        }
    ],
    "sg:phone":"+1 702 450 3781",
    "sg:postcode":"89014",
    "sg:province":"NV",
    "sg:tags":[
        "store"
    ],
    "sg:website":"www.lanehomefurnishings.com",
    "wof:name":"Lane Home Furnishings",
    "wof:placetype":"venue"
},
  "geometry": {"coordinates":[-115.04069,36.064733],"type":"Point"}
}