{
  "type": "Feature",
  "properties": {
    "iso:country":"US",
    "sg:address":"3450 S Hualapai Way",
    "sg:city":"Las Vegas",
    "sg:classifiers":[
        {
            "category":"Health Services",
            "subcategory":"Doctor",
            "type":"Services"
        }
    ],
    "sg:phone":"+1 702 871 2578",
    "sg:postcode":"89117",
    "sg:province":"NV",
    "sg:tags":[
        "dentist"
    ],
    "sg:website":"www.willowspringslv.com/",
    "wof:name":"Willow Springs Dental",
    "wof:placetype":"venue"
},
  "geometry": {"coordinates":[-115.315006,36.128024],"type":"Point"}
}