{
  "type": "Feature",
  "properties": {
    "iso:country":"US",
    "sg:address":"300 S 4th Street",
    "sg:city":"Las Vegas",
    "sg:classifiers":[
        {
            "category":"Professional",
            "subcategory":"Lawyer & Legal Services",
            "type":"Services"
        }
    ],
    "sg:phone":"+1 702 474 9400",
    "sg:postcode":"89101",
    "sg:province":"NV",
    "wof:name":"Cowley Amanda J",
    "wof:placetype":"venue"
},
  "geometry": {"coordinates":[-115.143309,36.167529],"type":"Point"}
}