{
  "type": "Feature",
  "properties": {
    "iso:country":"US",
    "sg:address":"888 W 2nd St",
    "sg:city":"Reno",
    "sg:classifiers":[
        {
            "category":"Real Estate",
            "subcategory":"Real Estate Agent",
            "type":"Services"
        }
    ],
    "sg:phone":"+1 775 324 5788",
    "sg:postcode":"89503",
    "sg:province":"NV",
    "wof:name":"Home Revolution",
    "wof:placetype":"venue"
},
  "geometry": {"coordinates":[-119.823707,39.524894],"type":"Point"}
}