{
  "type": "Feature",
  "properties": {
    "iso:country":"US",
    "sg:address":"3175 Lindell Rd",
    "sg:city":"Las Vegas",
    "sg:classifiers":[
        {
            "category":"Professional",
            "subcategory":"Business Services",
            "type":"Services"
        }
    ],
    "sg:phone":"+1 702 455 4383",
    "sg:postcode":"89146",
    "sg:province":"NV",
    "wof:name":"National Arbitration Assn",
    "wof:placetype":"venue"
},
  "geometry": {"coordinates":[-115.216596,36.130931],"type":"Point"}
}