{
  "type": "Feature",
  "properties": {
    "iso:country":"US",
    "sg:address":"2000 Marsh Ave",
    "sg:city":"Reno",
    "sg:classifiers":[
        {
            "category":"Shopping",
            "subcategory":"Gifts & Souvenirs",
            "type":"Retail Goods"
        }
    ],
    "sg:phone":"+1 775 828 1891",
    "sg:postcode":"89509",
    "sg:province":"NV",
    "wof:name":"Executive Gift Source",
    "wof:placetype":"venue"
},
  "geometry": {"coordinates":[-119.828789,39.503546],"type":"Point"}
}