{
  "type": "Feature",
  "properties": {
    "iso:country":"US",
    "sg:address":"1501 S Main St",
    "sg:city":"Las Vegas",
    "sg:classifiers":[
        {
            "category":"Retail",
            "subcategory":"Auto Repair",
            "type":"Services"
        }
    ],
    "sg:phone":"+1 702 384 7426",
    "sg:postcode":"89104",
    "sg:province":"NV",
    "sg:tags":[
        "transmission"
    ],
    "wof:name":"B & M Transmission Co",
    "wof:placetype":"venue"
},
  "geometry": {"coordinates":[-115.15405199999999,36.152169],"type":"Point"}
}