{
  "type": "Feature",
  "properties": {
    "iso:country":"US",
    "sg:address":"9665 Odda Way",
    "sg:city":"Las Vegas",
    "sg:classifiers":[
        {
            "category":"Banks & Credit Unions",
            "subcategory":"Bank",
            "type":"Services"
        }
    ],
    "sg:phone":"+1 702 256 3469",
    "sg:postcode":"89117",
    "sg:province":"NV",
    "sg:tags":[
        "mortgage"
    ],
    "wof:name":"Locke Mortgage Services",
    "wof:placetype":"venue"
},
  "geometry": {"coordinates":[-115.307434,36.145036],"type":"Point"}
}