{
  "type": "Feature",
  "properties": {
    "iso:country":"US",
    "sg:address":"5200 US Hwy 50",
    "sg:city":"Carson City",
    "sg:classifiers":[
        {
            "category":"Food & Beverages",
            "subcategory":"Specialty",
            "type":"Retail Goods"
        },
        {
            "category":"Wholesale",
            "subcategory":"Groceries",
            "type":"Manufacturing & Wholesale Goods"
        }
    ],
    "sg:phone":"+1 775 882 2020",
    "sg:postcode":"89701",
    "sg:province":"NV",
    "sg:tags":[
        "tea",
        "coffee"
    ],
    "wof:name":"Boyd Coffee Company",
    "wof:placetype":"venue"
},
  "geometry": {"coordinates":[-119.708854,39.186725],"type":"Point"}
}