{
  "type": "Feature",
  "properties": {
    "iso:country":"US",
    "sg:address":"5385 W Sahara Ave",
    "sg:city":"Las Vegas",
    "sg:classifiers":[
        {
            "category":"Autos & Motor Vehicles",
            "subcategory":"Automobile Sales",
            "type":"Retail Goods"
        },
        {
            "category":"Autos & Motor Vehicles",
            "subcategory":"Auto Supplies",
            "type":"Retail Goods"
        }
    ],
    "sg:phone":"+1 702 495 2100",
    "sg:postcode":"89146",
    "sg:province":"NV",
    "sg:tags":[
        "car",
        "part"
    ],
    "sg:website":"www.subaruoflasvegas.com/",
    "wof:name":"Subaru of Las Vegas",
    "wof:placetype":"venue"
},
  "geometry": {"coordinates":[-115.215662,36.144289],"type":"Point"}
}