{
  "type": "Feature",
  "properties": {
    "iso:country":"US",
    "sg:address":"1815 E Lake Mead Blvd Ste 203",
    "sg:city":"North Las Vegas",
    "sg:classifiers":[
        {
            "category":"Personal",
            "subcategory":"Hair Removal",
            "type":"Services"
        }
    ],
    "sg:phone":"+1 702 997 8513",
    "sg:postcode":"89030",
    "sg:province":"NV",
    "wof:name":"Pannu Amarjit K MD",
    "wof:placetype":"venue"
},
  "geometry": {"coordinates":[-115.12134500000001,36.19555],"type":"Point"}
}