{
  "type": "Feature",
  "properties": {
    "iso:country":"US",
    "sg:address":"8905 Players Club Dr",
    "sg:city":"Las Vegas",
    "sg:classifiers":[
        {
            "category":"Shopping",
            "subcategory":"Used Merchandise",
            "type":"Retail Goods"
        }
    ],
    "sg:phone":"+1 702 228 3762",
    "sg:postcode":"89134",
    "sg:province":"NV",
    "sg:tags":[
        "furniture"
    ],
    "wof:name":"Paris Market Place",
    "wof:placetype":"venue"
},
  "geometry": {"coordinates":[-115.289928,36.180132],"type":"Point"}
}