{
  "type": "Feature",
  "properties": {
    "iso:country":"US",
    "sg:address":"1129 Hunter Lake Dr",
    "sg:city":"Reno",
    "sg:classifiers":[
        {
            "category":"Shopping",
            "subcategory":"Computers & Home Electronics",
            "type":"Retail Goods"
        }
    ],
    "sg:phone":"+1 775 323 8332",
    "sg:postcode":"89509",
    "sg:province":"NV",
    "sg:tags":[
        "television",
        "radio"
    ],
    "wof:name":"Lang Electronics",
    "wof:placetype":"venue"
},
  "geometry": {"coordinates":[-119.83586099999999,39.509324],"type":"Point"}
}