{
  "type": "Feature",
  "properties": {
    "iso:country":"US",
    "sg:address":"4800 Vegas Valley Dr",
    "sg:city":"Las Vegas",
    "sg:classifiers":[
        {
            "category":"Real Estate",
            "subcategory":"Real Estate Operator",
            "type":"Services"
        }
    ],
    "sg:phone":"+1 702 431 1623",
    "sg:postcode":"89121",
    "sg:province":"NV",
    "sg:tags":[
        "mobile",
        "home",
        "site"
    ],
    "wof:name":"Casa Del Sol Mobile Home Cmnty",
    "wof:placetype":"venue"
},
  "geometry": {"coordinates":[-115.06612,36.137048],"type":"Point"}
}