{
  "type": "Feature",
  "properties": {
    "iso:country":"US",
    "sg:address":"1450 W Horizon Ridge Pkwy",
    "sg:city":"Henderson",
    "sg:classifiers":[
        {
            "category":"Personal",
            "subcategory":"Beauty Salon",
            "type":"Services"
        }
    ],
    "sg:phone":"+1 702 617 6100",
    "sg:postcode":"89012",
    "sg:province":"NV",
    "sg:tags":[
        "shop"
    ],
    "wof:name":"Destination Island Salon Spa",
    "wof:placetype":"venue"
},
  "geometry": {"coordinates":[-115.050308,36.020755],"type":"Point"}
}