{
  "type": "Feature",
  "properties": {
    "iso:country":"US",
    "sg:address":"732 S 6th St Ste 201",
    "sg:city":"Las Vegas",
    "sg:classifiers":[
        {
            "category":"Professional",
            "subcategory":"Lawyer & Legal Services",
            "type":"Services"
        }
    ],
    "sg:phone":"+1 702 386 1756",
    "sg:postcode":"89101",
    "sg:province":"NV",
    "wof:name":"Law Offices of Clyde Dewitt",
    "wof:placetype":"venue"
},
  "geometry": {"coordinates":[-115.144364,36.161427],"type":"Point"}
}