{
  "type": "Feature",
  "properties": {
    "iso:country":"US",
    "sg:address":"1220 N Nellis Blvd",
    "sg:city":"Las Vegas",
    "sg:classifiers":[
        {
            "category":"Health Services",
            "subcategory":"Podiatrist",
            "type":"Services"
        }
    ],
    "sg:phone":"+1 702 878 5252",
    "sg:postcode":"89110",
    "sg:province":"NV",
    "wof:name":"Southern Nevada Foot & Ankle",
    "wof:placetype":"venue"
},
  "geometry": {"coordinates":[-115.062099,36.183071],"type":"Point"}
}