{
  "type": "Feature",
  "properties": {
    "iso:country":"US",
    "sg:address":"The Palazzo 3325 S Las Vegas Blvd",
    "sg:city":"Las Vegas",
    "sg:classifiers":[
        {
            "category":"Shopping",
            "subcategory":"Clothing, Apparel, & Fashions",
            "type":"Retail Goods"
        },
        {
            "category":"Shopping",
            "subcategory":"Shoes",
            "type":"Retail Goods"
        }
    ],
    "sg:postcode":"89109",
    "sg:province":"NV",
    "sg:tags":[
        "clothing",
        "store",
        "women's"
    ],
    "sg:website":"www.chloe.com",
    "wof:name":"Chloe",
    "wof:placetype":"venue"
},
  "geometry": {"coordinates":[-115.170463,36.123552],"type":"Point"}
}