{
  "type": "Feature",
  "properties": {
    "iso:country":"US",
    "sg:address":"7095 S Durango Dr",
    "sg:city":"Las Vegas",
    "sg:classifiers":[
        {
            "category":"Food & Beverages",
            "subcategory":"Groceries & Convenience Stores",
            "type":"Retail Goods"
        }
    ],
    "sg:phone":"+1 702 212 7095",
    "sg:postcode":"89113",
    "sg:province":"NV",
    "wof:name":"Guru Express Markets",
    "wof:placetype":"venue"
},
  "geometry": {"coordinates":[-115.279171,36.059157],"type":"Point"}
}