{
  "type": "Feature",
  "properties": {
    "iso:country":"US",
    "sg:address":"111 S Frontage Rd",
    "sg:city":"Pahrump",
    "sg:classifiers":[
        {
            "category":"Professional",
            "subcategory":"Business Services",
            "type":"Services"
        }
    ],
    "sg:phone":"+1 775 537 2400",
    "sg:postcode":"89048",
    "sg:province":"NV",
    "wof:name":"Business & Home Svc",
    "wof:placetype":"venue"
},
  "geometry": {"coordinates":[-115.995028,36.22306],"type":"Point"}
}