{
  "type": "Feature",
  "properties": {
    "iso:country":"US",
    "sg:address":"99 Convention Center Drive",
    "sg:city":"Las Vegas",
    "sg:classifiers":[
        {
            "category":"Professional",
            "type":"Services"
        },
        {
            "category":"Restaurant",
            "type":"Food & Drink"
        }
    ],
    "sg:phone":"+1 702 369 4179",
    "sg:postcode":"89109",
    "sg:province":"NV",
    "sg:tags":[
        "italian",
        "caterer"
    ],
    "wof:name":"Cosmo's Cafe-Ristorante",
    "wof:placetype":"venue"
},
  "geometry": {"coordinates":[-115.162824,36.132459],"type":"Point"}
}