{
  "type": "Feature",
  "properties": {
    "iso:country":"US",
    "sg:address":"2909 Jeffery Pines St",
    "sg:city":"Las Vegas",
    "sg:classifiers":[
        {
            "category":"Retail",
            "subcategory":"Laundry & Dry Cleaning",
            "type":"Services"
        }
    ],
    "sg:phone":"+1 702 460 4981",
    "sg:postcode":"89108",
    "sg:province":"NV",
    "wof:name":"Unlimited Carpet Cleaning",
    "wof:placetype":"venue"
},
  "geometry": {"coordinates":[-115.215356,36.210984],"type":"Point"}
}