{
  "type": "Feature",
  "properties": {
    "iso:country":"US",
    "sg:address":"5419 W Tropicana Ave",
    "sg:city":"Las Vegas",
    "sg:classifiers":[
        {
            "category":"Shopping",
            "subcategory":"Gifts & Souvenirs",
            "type":"Retail Goods"
        }
    ],
    "sg:phone":"+1 702 365 6847",
    "sg:postcode":"89103",
    "sg:province":"NV",
    "wof:name":"Facesn Cups",
    "wof:placetype":"venue"
},
  "geometry": {"coordinates":[-115.213435,36.100501],"type":"Point"}
}