{
  "type": "Feature",
  "properties": {
    "iso:country":"US",
    "sg:address":"2251 S Jones Blvd",
    "sg:city":"Las Vegas",
    "sg:classifiers":[
        {
            "category":"Health Services",
            "subcategory":"Clinic",
            "type":"Services"
        }
    ],
    "sg:phone":"+1 702 365 6060",
    "sg:postcode":"89146",
    "sg:province":"NV",
    "wof:name":"Acentra",
    "wof:placetype":"venue"
},
  "geometry": {"coordinates":[-115.225382,36.144672],"type":"Point"}
}