{
  "type": "Feature",
  "properties": {
    "iso:country":"US",
    "sg:address":"10600 Haileville Dr",
    "sg:city":"Las Vegas",
    "sg:classifiers":[
        {
            "category":"Real Estate",
            "subcategory":"Real Estate Agent",
            "type":"Services"
        }
    ],
    "sg:phone":"+1 702 645 7466",
    "sg:postcode":"89129",
    "sg:province":"NV",
    "wof:name":"Concordia Homes",
    "wof:placetype":"venue"
},
  "geometry": {"coordinates":[-115.328525,36.239678],"type":"Point"}
}