{
  "type": "Feature",
  "properties": {
    "iso:country":"US",
    "sg:address":"505 E Windmill Ln",
    "sg:city":"Las Vegas",
    "sg:classifiers":[
        {
            "category":"Personal",
            "subcategory":"Tanning Parlor",
            "type":"Services"
        }
    ],
    "sg:phone":"+1 702 914 8266",
    "sg:postcode":"89123",
    "sg:province":"NV",
    "wof:name":"Golden Effects Tanning Salon",
    "wof:placetype":"venue"
},
  "geometry": {"coordinates":[-115.152,36.042301],"type":"Point"}
}