{
  "type": "Feature",
  "properties": {
    "iso:country":"US",
    "sg:address":"4630 E Lake Mead Blvd",
    "sg:city":"Las Vegas",
    "sg:classifiers":[
        {
            "category":"Autos & Motor Vehicles",
            "subcategory":"Automobile Sales",
            "type":"Retail Goods"
        }
    ],
    "sg:phone":"+1 702 678 5131",
    "sg:postcode":"89115",
    "sg:province":"NV",
    "sg:tags":[
        "used"
    ],
    "wof:name":"Main Street Auto Sales",
    "wof:placetype":"venue"
},
  "geometry": {"coordinates":[-115.073335,36.1959],"type":"Point"}
}