{
  "type": "Feature",
  "properties": {
    "iso:country":"US",
    "sg:address":"2702 E Valley Rd",
    "sg:city":"Minden",
    "sg:classifiers":[
        {
            "category":"Social Services",
            "subcategory":"Adult Care",
            "type":"Services"
        }
    ],
    "sg:phone":"+1 775 267 2509",
    "sg:postcode":"89423",
    "sg:province":"NV",
    "sg:tags":[
        "home"
    ],
    "wof:name":"Rite Of Passage",
    "wof:placetype":"venue"
},
  "geometry": {"coordinates":[-119.714767,39.037458],"type":"Point"}
}