{
  "type": "Feature",
  "properties": {
    "iso:country":"US",
    "sg:address":"481 Frisco Dr",
    "sg:city":"Spring Creek",
    "sg:classifiers":[
        {
            "category":"Building & Trades",
            "subcategory":"Electrical",
            "type":"Services"
        }
    ],
    "sg:phone":"+1 775 738 9865",
    "sg:postcode":"89815",
    "sg:province":"NV",
    "sg:tags":[
        "electrical",
        "contractor"
    ],
    "wof:name":"Bruning Electric",
    "wof:placetype":"venue"
},
  "geometry": {"coordinates":[-115.581626,40.729699],"type":"Point"}
}