{
  "type": "Feature",
  "properties": {
    "iso:country":"US",
    "sg:address":"4599 Carriage Ln",
    "sg:city":"Las Vegas",
    "sg:classifiers":[
        {
            "category":"Retail",
            "subcategory":"Laundry & Dry Cleaning",
            "type":"Services"
        }
    ],
    "sg:phone":"+1 702 795 4609",
    "sg:postcode":"89119",
    "sg:province":"NV",
    "wof:name":"Julie R Morrison Custom Sewing",
    "wof:placetype":"venue"
},
  "geometry": {"coordinates":[-115.127328,36.105791],"type":"Point"}
}