{
  "type": "Feature",
  "properties": {
    "iso:country":"US",
    "sg:address":"3864 Comb Ct",
    "sg:city":"Las Vegas",
    "sg:classifiers":[
        {
            "category":"Shopping",
            "subcategory":"Computers & Home Electronics",
            "type":"Retail Goods"
        }
    ],
    "sg:phone":"+1 702 256 6470",
    "sg:postcode":"89104",
    "sg:province":"NV",
    "wof:name":"Dvd Hiway",
    "wof:placetype":"venue"
},
  "geometry": {"coordinates":[-115.08887199999999,36.153453],"type":"Point"}
}