{
  "type": "Feature",
  "properties": {
    "iso:country":"US",
    "sg:address":"1468 E Charleston Boulevard",
    "sg:city":"Las Vegas",
    "sg:classifiers":[
        {
            "category":"Food & Beverages",
            "subcategory":"Groceries & Convenience Stores",
            "type":"Retail Goods"
        }
    ],
    "sg:phone":"+1 702 384 5369",
    "sg:postcode":"89104",
    "sg:province":"NV",
    "sg:website":"www.7-eleven.com",
    "wof:name":"7-Eleven",
    "wof:placetype":"venue"
},
  "geometry": {"coordinates":[-115.13290499999999,36.158802],"type":"Point"}
}