{
  "type": "Feature",
  "properties": {
    "iso:country":"US",
    "sg:address":"1130 Sidehill Way",
    "sg:city":"Las Vegas",
    "sg:classifiers":[
        {
            "category":"Social Services",
            "subcategory":"Adult Care",
            "type":"Services"
        }
    ],
    "sg:phone":"+1 702 459 6670",
    "sg:postcode":"89110",
    "sg:province":"NV",
    "sg:tags":[
        "home",
        "residential"
    ],
    "wof:name":"S K Brown Inc",
    "wof:placetype":"venue"
},
  "geometry": {"coordinates":[-115.024714,36.178232],"type":"Point"}
}