{
  "type": "Feature",
  "properties": {
    "iso:country":"US",
    "sg:address":"1668 Spice Wood Cir",
    "sg:city":"Reno",
    "sg:phone":"+1 775 217 6295",
    "sg:postcode":"89523",
    "sg:province":"NV",
    "wof:name":"Cma Enterprises",
    "wof:placetype":"venue"
},
  "geometry": {"coordinates":[-119.911242,39.531201],"type":"Point"}
}