{
  "type": "Feature",
  "properties": {
    "iso:country":"US",
    "sg:address":"800 W Bonanza Road",
    "sg:city":"Las Vegas",
    "sg:classifiers":[
        {
            "category":"Social Services",
            "subcategory":"Child Care",
            "type":"Services"
        }
    ],
    "sg:phone":"+1 702 646 2062",
    "sg:postcode":"89106",
    "sg:province":"NV",
    "sg:tags":[
        "day"
    ],
    "wof:name":"Eob Community Action Partnership",
    "wof:placetype":"venue"
},
  "geometry": {"coordinates":[-115.15203,36.177288],"type":"Point"}
}