{
  "type": "Feature",
  "properties": {
    "iso:country":"US",
    "sg:address":"1707 W Charleston Boulevard",
    "sg:city":"Las Vegas",
    "sg:classifiers":[
        {
            "category":"Health Services",
            "subcategory":"Doctor",
            "type":"Services"
        }
    ],
    "sg:phone":"+1 702 671 5060",
    "sg:postcode":"89102",
    "sg:province":"NV",
    "sg:tags":[
        "medicine",
        "internal"
    ],
    "wof:name":"Nasiak Michael MD",
    "wof:placetype":"venue"
},
  "geometry": {"coordinates":[-115.164202,36.158784],"type":"Point"}
}