{
  "type": "Feature",
  "properties": {
    "iso:country":"US",
    "sg:address":"111 N Lake St",
    "sg:city":"Reno",
    "sg:classifiers":[
        {
            "category":"Travel",
            "subcategory":"Hotels & Motels",
            "type":"Entertainment"
        }
    ],
    "sg:phone":"+1 775 786 3170",
    "sg:postcode":"89501",
    "sg:province":"NV",
    "wof:name":"Oxford Motel",
    "wof:placetype":"venue"
},
  "geometry": {"coordinates":[-119.810712,39.527315],"type":"Point"}
}