{
  "type": "Feature",
  "properties": {
    "iso:country":"US",
    "sg:address":"953 E Sahara Ave",
    "sg:city":"Las Vegas",
    "sg:classifiers":[
        {
            "category":"Retail",
            "subcategory":"Repair Shop",
            "type":"Services"
        }
    ],
    "sg:phone":"+1 702 650 4440",
    "sg:postcode":"89104",
    "sg:province":"NV",
    "wof:name":"Desert Arms Gunsmith Shop",
    "wof:placetype":"venue"
},
  "geometry": {"coordinates":[-115.1447,36.143958],"type":"Point"}
}