{
  "type": "Feature",
  "properties": {
    "iso:country":"US",
    "sg:address":"345 Copeland Ct",
    "sg:city":"North Las Vegas",
    "sg:classifiers":[
        {
            "category":"Building & Trades",
            "subcategory":"Cleaning & Sanitation",
            "type":"Services"
        }
    ],
    "sg:phone":"+1 702 641 6834",
    "sg:postcode":"89032",
    "sg:province":"NV",
    "sg:tags":[
        "janitor"
    ],
    "wof:name":"L A Janitorial Cleaning Svc",
    "wof:placetype":"venue"
},
  "geometry": {"coordinates":[-115.146063,36.234593],"type":"Point"}
}