{
  "type": "Feature",
  "properties": {
    "iso:country":"US",
    "sg:address":"1410 Greg St",
    "sg:city":"Sparks",
    "sg:classifiers":[
        {
            "category":"Professional",
            "type":"Services"
        }
    ],
    "sg:phone":"+1 775 685 5600",
    "sg:postcode":"89431",
    "sg:province":"NV",
    "sg:tags":[
        "establishment"
    ],
    "wof:name":"Bally Systems",
    "wof:placetype":"venue"
},
  "geometry": {"coordinates":[-119.762676,39.523476],"type":"Point"}
}