{
  "type": "Feature",
  "properties": {
    "iso:country":"US",
    "sg:address":"9090 Alta Dr",
    "sg:city":"Las Vegas",
    "sg:classifiers":[
        {
            "category":"Arts & Performance",
            "subcategory":"Arts Center",
            "type":"Entertainment"
        },
        {
            "category":"Arts & Performance",
            "subcategory":"Music",
            "type":"Entertainment"
        }
    ],
    "sg:phone":"+1 702 731 2470",
    "sg:postcode":"89144",
    "sg:province":"NV",
    "sg:tags":[
        "performing",
        "venue"
    ],
    "sg:website":"www.loveshackbooking.com/",
    "wof:name":"Loveshack",
    "wof:placetype":"venue"
},
  "geometry": {"coordinates":[-115.29473299999999,36.168264],"type":"Point"}
}