{
  "type": "Feature",
  "properties": {
    "iso:country":"US",
    "sg:address":"4750 W Sahara Ave",
    "sg:city":"Las Vegas",
    "sg:classifiers":[
        {
            "category":"Restaurant",
            "type":"Food & Drink"
        }
    ],
    "sg:phone":"+1 702 870 0860",
    "sg:postcode":"89102",
    "sg:province":"NV",
    "sg:tags":[
        "eating"
    ],
    "wof:name":"Habibs Persian Cuisine",
    "wof:placetype":"venue"
},
  "geometry": {"coordinates":[-115.20813800000001,36.144522],"type":"Point"}
}