{
  "type": "Feature",
  "properties": {
    "iso:country":"US",
    "sg:address":"630 Pyramid Way",
    "sg:city":"Sparks",
    "sg:classifiers":[
        {
            "category":"Health Services",
            "subcategory":"Doctor",
            "type":"Services"
        }
    ],
    "sg:phone":"+1 775 356 8252",
    "sg:postcode":"89431",
    "sg:province":"NV",
    "wof:name":"Jose Talancon DDS",
    "wof:placetype":"venue"
},
  "geometry": {"coordinates":[-119.752794,39.539526],"type":"Point"}
}