{
  "type": "Feature",
  "properties": {
    "iso:country":"US",
    "sg:address":"7413 W Russell Rd",
    "sg:city":"Las Vegas",
    "sg:classifiers":[
        {
            "category":"Professional",
            "subcategory":"Accounting & Tax Preparation",
            "type":"Services"
        }
    ],
    "sg:phone":"+1 702 301 5794",
    "sg:postcode":"89113",
    "sg:province":"NV",
    "wof:name":"Quality Bookkeeping Services",
    "wof:placetype":"venue"
},
  "geometry": {"coordinates":[-115.252784,36.08511],"type":"Point"}
}