{
  "type": "Feature",
  "properties": {
    "iso:country":"US",
    "sg:address":"5625 S Grand Canyon Dr",
    "sg:city":"Las Vegas",
    "sg:classifiers":[
        {
            "category":"Shopping",
            "subcategory":"Pets & Pet Supplies",
            "type":"Retail Goods"
        },
        {
            "category":"Retail",
            "subcategory":"Veterinary Services",
            "type":"Services"
        },
        {
            "category":"Retail",
            "subcategory":"Pet Boarding",
            "type":"Services"
        }
    ],
    "sg:phone":"+1 702 258 0006",
    "sg:postcode":"89148",
    "sg:province":"NV",
    "sg:tags":[
        "veterinarian",
        "boarding/pet",
        "groomers",
        "sitting"
    ],
    "sg:website":"www.sienaanimalhospital.com/",
    "wof:name":"Siena Animal Hospital",
    "wof:placetype":"venue"
},
  "geometry": {"coordinates":[-115.307146,36.087196],"type":"Point"}
}