{
  "type": "Feature",
  "properties": {
    "iso:country":"US",
    "sg:address":"4071 Great Plains Way",
    "sg:city":"Las Vegas",
    "sg:classifiers":[
        {
            "category":"Professional",
            "subcategory":"Computer Services",
            "type":"Services"
        }
    ],
    "sg:phone":"+1 702 436 0686",
    "sg:postcode":"89121",
    "sg:province":"NV",
    "sg:tags":[
        "datum",
        "commercial",
        "desi"
    ],
    "sg:website":"www.poizenideas.com",
    "wof:name":"Poizen Ideas",
    "wof:placetype":"venue"
},
  "geometry": {"coordinates":[-115.07963,36.115987],"type":"Point"}
}