{
  "type": "Feature",
  "properties": {
    "iso:country":"US",
    "sg:address":"1195 Mayflower Dr",
    "sg:city":"Reno",
    "sg:classifiers":[
        {
            "category":"Professional",
            "subcategory":"Computer Services",
            "type":"Services"
        }
    ],
    "sg:phone":"+1 775 348 0984",
    "sg:postcode":"89509",
    "sg:province":"NV",
    "sg:tags":[
        "consulting",
        "technology"
    ],
    "wof:name":"Managed Networks Inc",
    "wof:placetype":"venue"
},
  "geometry": {"coordinates":[-119.854241,39.507975],"type":"Point"}
}