{
  "type": "Feature",
  "properties": {
    "iso:country":"US",
    "sg:address":"3154 Lapis Beach Drive",
    "sg:city":"Las Vegas",
    "sg:classifiers":[
        {
            "category":"Professional",
            "subcategory":"Art Services",
            "type":"Services"
        }
    ],
    "sg:phone":"+1 702 526 6696",
    "sg:postcode":"89117",
    "sg:province":"NV",
    "sg:tags":[
        "photographer"
    ],
    "wof:name":"Garden Song Studios Photography",
    "wof:placetype":"venue"
},
  "geometry": {"coordinates":[-115.269372,36.132001],"type":"Point"}
}