{
  "type": "Feature",
  "properties": {
    "iso:country":"US",
    "sg:address":"1090 E Desert Inn Rd Ste 200",
    "sg:city":"Las Vegas",
    "sg:classifiers":[
        {
            "category":"Health Services",
            "subcategory":"Doctor",
            "type":"Services"
        }
    ],
    "sg:phone":"+1 702 732 1493",
    "sg:postcode":"89109",
    "sg:province":"NV",
    "wof:name":"Bernstein Jonathan MD",
    "wof:placetype":"venue"
},
  "geometry": {"coordinates":[-115.139883,36.129892],"type":"Point"}
}