{
  "type": "Feature",
  "properties": {
    "iso:country":"US",
    "sg:address":"312 Gondola Way",
    "sg:city":"Henderson",
    "sg:classifiers":[
        {
            "category":"Manufacturing",
            "subcategory":"Toys & Sporting Goods",
            "type":"Manufacturing & Wholesale Goods"
        }
    ],
    "sg:phone":"+1 702 353 7773",
    "sg:postcode":"89074",
    "sg:province":"NV",
    "sg:tags":[
        "mfg"
    ],
    "wof:name":"Dwi Enterprises",
    "wof:placetype":"venue"
},
  "geometry": {"coordinates":[-115.08423999999999,36.051199],"type":"Point"}
}