{
  "type": "Feature",
  "properties": {
    "iso:country":"US",
    "sg:address":"1000 Ironwood Dr",
    "sg:city":"Las Vegas",
    "sg:classifiers":[
        {
            "category":"Professional",
            "subcategory":"Computer Services",
            "type":"Services"
        }
    ],
    "sg:phone":"+1 702 646 4165",
    "sg:postcode":"89108",
    "sg:province":"NV",
    "sg:tags":[
        "datum"
    ],
    "wof:name":"Synergy Unlimited Inc",
    "wof:placetype":"venue"
},
  "geometry": {"coordinates":[-115.192859,36.18231],"type":"Point"}
}