{
  "type": "Feature",
  "properties": {
    "iso:country":"US",
    "sg:address":"2065 Pabco Road",
    "sg:city":"Henderson",
    "sg:classifiers":[
        {
            "category":"Building & Trades",
            "subcategory":"Construction",
            "type":"Services"
        }
    ],
    "sg:phone":"+1 702 567 3007",
    "sg:postcode":"89011",
    "sg:province":"NV",
    "sg:tags":[
        "contractor"
    ],
    "wof:name":"Crux Subsurface",
    "wof:placetype":"venue"
},
  "geometry": {"coordinates":[-114.993668,36.070303],"type":"Point"}
}