{
  "type": "Feature",
  "properties": {
    "iso:country":"US",
    "sg:address":"7590 Colbert Dr",
    "sg:city":"Reno",
    "sg:classifiers":[
        {
            "category":"Autos & Motor Vehicles",
            "subcategory":"Fuel & Gas Station",
            "type":"Retail Goods"
        }
    ],
    "sg:phone":"+1 775 851 2009",
    "sg:postcode":"89511",
    "sg:province":"NV",
    "sg:tags":[
        "oil"
    ],
    "wof:name":"RAINBOW Market",
    "wof:placetype":"venue"
},
  "geometry": {"coordinates":[-119.774604,39.458762],"type":"Point"}
}