{
  "type": "Feature",
  "properties": {
    "iso:country":"US",
    "sg:address":"4855 W Winnemucca Blvd",
    "sg:city":"Winnemucca",
    "sg:classifiers":[
        {
            "category":"Freight",
            "type":"Transportation"
        }
    ],
    "sg:phone":"+1 775 623 2877",
    "sg:postcode":"89445",
    "sg:province":"NV",
    "sg:tags":[
        "trucking"
    ],
    "wof:name":"Motor Cargo",
    "wof:placetype":"venue"
},
  "geometry": {"coordinates":[-117.787773,40.935464],"type":"Point"}
}