{
  "type": "Feature",
  "properties": {
    "iso:country":"US",
    "sg:address":"160 E Grove St",
    "sg:city":"Reno",
    "sg:classifiers":[
        {
            "category":"Wholesale",
            "subcategory":"Groceries",
            "type":"Manufacturing & Wholesale Goods"
        }
    ],
    "sg:phone":"+1 775 825 6060",
    "sg:postcode":"89502",
    "sg:province":"NV",
    "sg:tags":[
        "confectionery"
    ],
    "wof:name":"Sweet Tooth Cafe",
    "wof:placetype":"venue"
},
  "geometry": {"coordinates":[-119.796337,39.50084],"type":"Point"}
}