{
  "type": "Feature",
  "properties": {
    "iso:country":"US",
    "sg:address":"1020 E Desert Inn Road",
    "sg:city":"Las Vegas",
    "sg:classifiers":[
        {
            "category":"Retail",
            "subcategory":"Auto Rental",
            "type":"Services"
        }
    ],
    "sg:phone":"+1 702 891 0807",
    "sg:postcode":"89109",
    "sg:province":"NV",
    "sg:tags":[
        "car"
    ],
    "wof:name":"A & Y Enterprises",
    "wof:placetype":"venue"
},
  "geometry": {"coordinates":[-115.140963,36.129784],"type":"Point"}
}