{
  "type": "Feature",
  "properties": {
    "iso:country":"US",
    "sg:address":"115 E Tropicana Ave",
    "sg:city":"Las Vegas",
    "sg:classifiers":[
        {
            "category":"Personal",
            "subcategory":"Psychics & Astrologers",
            "type":"Services"
        }
    ],
    "sg:postcode":"89109",
    "sg:province":"NV",
    "sg:website":"www.garyspivey.com",
    "wof:name":"Gary Spivey Psychic",
    "wof:placetype":"venue"
},
  "geometry": {"coordinates":[-115.167512,36.099814],"type":"Point"}
}