{
  "type": "Feature",
  "properties": {
    "iso:country":"US",
    "sg:address":"1900 S Rainbow Blvd",
    "sg:city":"Las Vegas",
    "sg:classifiers":[
        {
            "category":"Shopping",
            "type":"Retail Goods"
        }
    ],
    "sg:phone":"+1 702 362 4003",
    "sg:postcode":"89146",
    "sg:province":"NV",
    "sg:tags":[
        "house",
        "construction",
        "merchandise"
    ],
    "wof:name":"Superior Spa Services",
    "wof:placetype":"venue"
},
  "geometry": {"coordinates":[-115.243107,36.147869],"type":"Point"}
}