{
  "type": "Feature",
  "properties": {
    "iso:country":"US",
    "sg:address":"855 E Greg St",
    "sg:city":"Sparks",
    "sg:classifiers":[
        {
            "category":"Manufacturing",
            "subcategory":"Food",
            "type":"Manufacturing & Wholesale Goods"
        }
    ],
    "sg:phone":"+1 775 359 8661",
    "sg:postcode":"89431",
    "sg:province":"NV",
    "sg:tags":[
        "product",
        "mfg"
    ],
    "wof:name":"Rainbo Baking Company",
    "wof:placetype":"venue"
},
  "geometry": {"coordinates":[-119.726641,39.521296],"type":"Point"}
}