{
  "type": "Feature",
  "properties": {
    "iso:country":"US",
    "sg:address":"1601 E Katie Ave",
    "sg:city":"Las Vegas",
    "sg:classifiers":[
        {
            "category":"Professional",
            "type":"Services"
        }
    ],
    "sg:phone":"+1 702 215 4988",
    "sg:postcode":"89119",
    "sg:province":"NV",
    "wof:name":"Filipinas Paralegal Services",
    "wof:placetype":"venue"
},
  "geometry": {"coordinates":[-115.129299,36.120217],"type":"Point"}
}