{
  "type": "Feature",
  "properties": {
    "iso:country":"US",
    "sg:address":"1022 Mosskag Ct",
    "sg:city":"North Las Vegas",
    "sg:classifiers":[
        {
            "category":"Shopping",
            "subcategory":"Beauty & Cosmetics",
            "type":"Retail Goods"
        }
    ],
    "sg:phone":"+1 702 699 7390",
    "sg:postcode":"89032",
    "sg:province":"NV",
    "sg:tags":[
        "supply"
    ],
    "wof:name":"Avon Beauty Center",
    "wof:placetype":"venue"
},
  "geometry": {"coordinates":[-115.15602,36.228898],"type":"Point"}
}