{
  "type": "Feature",
  "properties": {
    "iso:country":"US",
    "sg:address":"2533 N Carson St",
    "sg:city":"Carson City",
    "sg:classifiers":[
        {
            "category":"Banks & Credit Unions",
            "subcategory":"Investment Brokerage",
            "type":"Services"
        }
    ],
    "sg:phone":"+1 775 841 7319",
    "sg:postcode":"89706",
    "sg:province":"NV",
    "sg:tags":[
        "investing"
    ],
    "wof:name":"Smoo Investments Inc",
    "wof:placetype":"venue"
},
  "geometry": {"coordinates":[-119.768997,39.183201],"type":"Point"}
}