{
  "type": "Feature",
  "properties": {
    "iso:country":"US",
    "sg:address":"8940 W Tropicana Ave",
    "sg:city":"Las Vegas",
    "sg:classifiers":[
        {
            "category":"Health Services",
            "subcategory":"Doctor",
            "type":"Services"
        }
    ],
    "sg:phone":"+1 702 365 6637",
    "sg:postcode":"89147",
    "sg:province":"NV",
    "sg:tags":[
        "clinic",
        "dentist"
    ],
    "wof:name":"Waldren Family Dentistry",
    "wof:placetype":"venue"
},
  "geometry": {"coordinates":[-115.306889,36.10003],"type":"Point"}
}