{
  "type": "Feature",
  "properties": {
    "iso:country":"US",
    "sg:address":"165 Lovett Rd",
    "sg:city":"Henderson",
    "sg:classifiers":[
        {
            "category":"Travel",
            "subcategory":"Travel Agent",
            "type":"Entertainment"
        }
    ],
    "sg:phone":"+1 702 568 0444",
    "sg:postcode":"89015",
    "sg:province":"NV",
    "sg:tags":[
        "agency",
        "bureau"
    ],
    "wof:name":"Uniglobe Logistics",
    "wof:placetype":"venue"
},
  "geometry": {"coordinates":[-114.951292,36.035315],"type":"Point"}
}