{
  "type": "Feature",
  "properties": {
    "iso:country":"US",
    "sg:address":"4495 W Hacienda Ave",
    "sg:city":"Las Vegas",
    "sg:classifiers":[
        {
            "category":"Professional",
            "subcategory":"Engineering",
            "type":"Services"
        }
    ],
    "sg:phone":"+1 702 367 9007",
    "sg:postcode":"89118",
    "sg:province":"NV",
    "sg:tags":[
        "engineer"
    ],
    "wof:name":"Intrepid Engineering",
    "wof:placetype":"venue"
},
  "geometry": {"coordinates":[-115.199317,36.093548],"type":"Point"}
}