{
  "type": "Feature",
  "properties": {
    "iso:country":"US",
    "sg:address":"6265 Industrial Rd",
    "sg:city":"Las Vegas",
    "sg:classifiers":[
        {
            "category":"Airline",
            "type":"Transportation"
        }
    ],
    "sg:phone":"+1 702 361 0676",
    "sg:postcode":"89118",
    "sg:province":"NV",
    "sg:tags":[
        "scheduled",
        "air"
    ],
    "wof:name":"Forrest Hummer Tours",
    "wof:placetype":"venue"
},
  "geometry": {"coordinates":[-115.181363,36.07756],"type":"Point"}
}