{
  "type": "Feature",
  "properties": {
    "iso:country":"US",
    "sg:address":"7910 S Rainbow Blvd Ste 100",
    "sg:city":"Las Vegas",
    "sg:classifiers":[
        {
            "category":"Health Services",
            "subcategory":"Dentist",
            "type":"Services"
        }
    ],
    "sg:phone":"+1 702 656 7846",
    "sg:postcode":"89139",
    "sg:province":"NV",
    "sg:tags":[
        "orthodontist"
    ],
    "wof:name":"MAI Orthodontics",
    "wof:placetype":"venue"
},
  "geometry": {"coordinates":[-115.243028,36.044535],"type":"Point"}
}