{
  "type": "Feature",
  "properties": {
    "iso:country":"US",
    "sg:address":"1711 Mapleleaf St",
    "sg:city":"Las Vegas",
    "sg:classifiers":[
        {
            "category":"Real Estate",
            "subcategory":"Real Estate Services",
            "type":"Services"
        }
    ],
    "sg:phone":"+1 702 501 6363",
    "sg:postcode":"89142",
    "sg:province":"NV",
    "sg:tags":[
        "home",
        "inspector"
    ],
    "sg:website":"www.affordablehomeinspectionlv.com",
    "wof:name":"Affordable Home Inspection",
    "wof:placetype":"venue"
},
  "geometry": {"coordinates":[-115.04655200000001,36.152806],"type":"Point"}
}