{
  "type": "Feature",
  "properties": {
    "iso:country":"US",
    "sg:address":"7925 Purple Mountain Ave",
    "sg:city":"Las Vegas",
    "sg:classifiers":[
        {
            "category":"Building & Trades",
            "subcategory":"Landscaping Services",
            "type":"Services"
        }
    ],
    "sg:phone":"+1 702 515 7514",
    "sg:postcode":"89131",
    "sg:province":"NV",
    "sg:tags":[
        "landscape",
        "contractor"
    ],
    "wof:name":"South West Lawn Shaping",
    "wof:placetype":"venue"
},
  "geometry": {"coordinates":[-115.268669,36.29042],"type":"Point"}
}