{
  "type": "Feature",
  "properties": {
    "iso:country":"US",
    "sg:address":"1105 S Rock Blvd",
    "sg:city":"Sparks",
    "sg:classifiers":[
        {
            "category":"Health Services",
            "subcategory":"Chiropractor",
            "type":"Services"
        }
    ],
    "sg:phone":"+1 775 358 2225",
    "sg:postcode":"89431",
    "sg:province":"NV",
    "wof:name":"Grensted Chiropractic",
    "wof:placetype":"venue"
},
  "geometry": {"coordinates":[-119.766828,39.525149],"type":"Point"}
}