{
  "type": "Feature",
  "properties": {
    "iso:country":"US",
    "sg:address":"700 S 3rd St",
    "sg:city":"Las Vegas",
    "sg:classifiers":[
        {
            "category":"Professional",
            "subcategory":"Lawyer & Legal Services",
            "type":"Services"
        }
    ],
    "sg:phone":"+1 702 384 7494",
    "sg:postcode":"89101",
    "sg:province":"NV",
    "wof:name":"Kelleher & Kelleher LLC",
    "wof:placetype":"venue"
},
  "geometry": {"coordinates":[-115.148272,36.162064],"type":"Point"}
}