{
  "type": "Feature",
  "properties": {
    "iso:country":"US",
    "sg:address":"700 S 7th St",
    "sg:city":"Las Vegas",
    "sg:classifiers":[
        {
            "category":"Professional",
            "subcategory":"Lawyer & Legal Services",
            "type":"Services"
        }
    ],
    "sg:phone":"+1 702 382 5222",
    "sg:postcode":"89101",
    "sg:province":"NV",
    "wof:name":"O'brien John D A Professional Corp",
    "wof:placetype":"venue"
},
  "geometry": {"coordinates":[-115.14299800000001,36.161098],"type":"Point"}
}