{
  "type": "Feature",
  "properties": {
    "iso:country":"US",
    "sg:address":"2775 Mayberry Dr",
    "sg:city":"Reno",
    "sg:classifiers":[
        {
            "category":"Professional",
            "subcategory":"Management & Consulting",
            "type":"Services"
        }
    ],
    "sg:phone":"+1 775 322 3282",
    "sg:postcode":"89509",
    "sg:province":"NV",
    "sg:tags":[
        "fuel"
    ],
    "wof:name":"Outcomes Management Systems",
    "wof:placetype":"venue"
},
  "geometry": {"coordinates":[-119.84810400000001,39.505892],"type":"Point"}
}