{
  "type": "Feature",
  "properties": {
    "iso:country":"US",
    "sg:address":"3869 Spring Mountain Road",
    "sg:city":"Las Vegas",
    "sg:classifiers":[
        {
            "category":"Personal",
            "subcategory":"Barber",
            "type":"Services"
        }
    ],
    "sg:phone":"+1 702 431 3420",
    "sg:postcode":"89102",
    "sg:province":"NV",
    "wof:name":"Gerardo's Classic Barber Shop",
    "wof:placetype":"venue"
},
  "geometry": {"coordinates":[-115.191346,36.126404],"type":"Point"}
}