{
  "type": "Feature",
  "properties": {
    "iso:country":"US",
    "sg:address":"1475 Terminal Way",
    "sg:city":"Reno",
    "sg:classifiers":[
        {
            "category":"Personal",
            "type":"Services"
        }
    ],
    "sg:phone":"+1 775 825 1655",
    "sg:postcode":"89502",
    "sg:province":"NV",
    "wof:name":"Cyndis Five Star Massage Thera",
    "wof:placetype":"venue"
},
  "geometry": {"coordinates":[-119.77754299999999,39.511086],"type":"Point"}
}