{
  "type": "Feature",
  "properties": {
    "iso:country":"US",
    "sg:address":"3110 Ponderosa Way Ste A",
    "sg:city":"Las Vegas",
    "sg:classifiers":[
        {
            "category":"Shopping",
            "subcategory":"Hobbies, Toys, & Games",
            "type":"Retail Goods"
        }
    ],
    "sg:phone":"+1 702 736 6664",
    "sg:postcode":"89118",
    "sg:province":"NV",
    "sg:tags":[
        "toy",
        "store"
    ],
    "sg:website":"www.playgroundwarehouse.com",
    "wof:name":"Playground Warehouse",
    "wof:placetype":"venue"
},
  "geometry": {"coordinates":[-115.182286,36.080897],"type":"Point"}
}