{
  "type": "Feature",
  "properties": {
    "iso:country":"US",
    "sg:address":"5213 Losee Rd",
    "sg:city":"North Las Vegas",
    "sg:classifiers":[
        {
            "category":"Shopping",
            "type":"Retail Goods"
        }
    ],
    "sg:phone":"+1 702 255 6279",
    "sg:postcode":"89031",
    "sg:province":"NV",
    "sg:tags":[
        "cosmetic",
        "perfume"
    ],
    "wof:name":"Kimberly Bullock",
    "wof:placetype":"venue"
},
  "geometry": {"coordinates":[-115.116969,36.250642],"type":"Point"}
}