{
  "type": "Feature",
  "properties": {
    "iso:country":"US",
    "sg:address":"4350 S Arville St",
    "sg:city":"Las Vegas",
    "sg:classifiers":[
        {
            "category":"Manufacturing",
            "subcategory":"Building Materials",
            "type":"Manufacturing & Wholesale Goods"
        },
        {
            "category":"Home & Garden",
            "subcategory":"Home Furnishings",
            "type":"Retail Goods"
        }
    ],
    "sg:phone":"+1 702 597 0333",
    "sg:postcode":"89103",
    "sg:province":"NV",
    "sg:tags":[
        "blind",
        "shutter",
        "mfg",
        "composite",
        "poly",
        "custom",
        "venetian",
        "wood",
        "fabricates"
    ],
    "wof:name":"Allbrite Shutters",
    "wof:placetype":"venue"
},
  "geometry": {"coordinates":[-115.199242,36.109107],"type":"Point"}
}