{
  "type": "Feature",
  "properties": {
    "iso:country":"US",
    "sg:address":"115 S Deer Run Rd",
    "sg:city":"Carson City",
    "sg:classifiers":[
        {
            "category":"Shopping",
            "subcategory":"Shoes",
            "type":"Retail Goods"
        }
    ],
    "sg:phone":"+1 775 882 4982",
    "sg:postcode":"89701",
    "sg:province":"NV",
    "wof:name":"Footsteps Inc",
    "wof:placetype":"venue"
},
  "geometry": {"coordinates":[-119.700418,39.163207],"type":"Point"}
}