{
  "type": "Feature",
  "properties": {
    "iso:country":"US",
    "sg:address":"418 Mineral Ln",
    "sg:city":"Hawthorne",
    "sg:classifiers":[
        {
            "category":"Government",
            "subcategory":"Fire Station",
            "type":"Public Place"
        }
    ],
    "sg:phone":"+1 775 945 2497",
    "sg:postcode":"89433",
    "sg:province":"NV",
    "sg:tags":[
        "department"
    ],
    "wof:name":"Hawthorne Fire Dept",
    "wof:placetype":"venue"
},
  "geometry": {"coordinates":[-119.78916700000001,39.601719],"type":"Point"}
}