{
  "type": "Feature",
  "properties": {
    "iso:country":"US",
    "sg:address":"761 S Rainbow Blvd",
    "sg:city":"Las Vegas",
    "sg:classifiers":[
        {
            "category":"Health Services",
            "subcategory":"Medical Lab",
            "type":"Services"
        }
    ],
    "sg:phone":"+1 702 733 7866",
    "sg:postcode":"89145",
    "sg:province":"NV",
    "sg:tags":[
        "laboratory"
    ],
    "wof:name":"Quest Diagnostics Inc",
    "wof:placetype":"venue"
},
  "geometry": {"coordinates":[-115.244011,36.162301],"type":"Point"}
}