{
  "type": "Feature",
  "properties": {
    "iso:country":"US",
    "sg:address":"4800 Alpine Pl Ste 11",
    "sg:city":"Las Vegas",
    "sg:classifiers":[
        {
            "category":"Health Services",
            "subcategory":"Hospital",
            "type":"Services"
        }
    ],
    "sg:phone":"+1 800 827 1000",
    "sg:postcode":"89107",
    "sg:province":"NV",
    "wof:name":"V A Benefits Office",
    "wof:placetype":"venue"
},
  "geometry": {"coordinates":[-115.206475,36.160291],"type":"Point"}
}