{
  "type": "Feature",
  "properties": {
    "iso:country":"US",
    "sg:address":"14315 Riata Cir",
    "sg:city":"Reno",
    "sg:classifiers":[
        {
            "category":"Social Services",
            "subcategory":"Adult Care",
            "type":"Services"
        }
    ],
    "sg:phone":"+1 775 851 4185",
    "sg:postcode":"89521",
    "sg:province":"NV",
    "sg:tags":[
        "home",
        "residential"
    ],
    "wof:name":"Summerdale Homes At Riata LLC",
    "wof:placetype":"venue"
},
  "geometry": {"coordinates":[-119.728612,39.39919],"type":"Point"}
}