{
  "type": "Feature",
  "properties": {
    "iso:country":"US",
    "sg:address":"2475 S Jones Boulevard",
    "sg:city":"Las Vegas",
    "sg:classifiers":[
        {
            "category":"Personal",
            "subcategory":"Nail Salon",
            "type":"Services"
        }
    ],
    "sg:phone":"+1 702 873 2378",
    "sg:postcode":"89146",
    "sg:province":"NV",
    "wof:name":"Beauty & the Best",
    "wof:placetype":"venue"
},
  "geometry": {"coordinates":[-115.22531499999999,36.143375],"type":"Point"}
}