{
  "type": "Feature",
  "properties": {
    "iso:country":"US",
    "sg:address":"3389 US Highway 50 E",
    "sg:city":"Carson City",
    "sg:classifiers":[
        {
            "category":"Autos & Motor Vehicles",
            "subcategory":"Fuel & Gas Station",
            "type":"Retail Goods"
        },
        {
            "category":"Food & Beverages",
            "subcategory":"Groceries & Convenience Stores",
            "type":"Retail Goods"
        }
    ],
    "sg:phone":"+1 775 883 4097",
    "sg:postcode":"89701",
    "sg:province":"NV",
    "wof:name":"Country Store",
    "wof:placetype":"venue"
},
  "geometry": {"coordinates":[-119.730003,39.178001],"type":"Point"}
}