{
  "type": "Feature",
  "properties": {
    "iso:country":"US",
    "sg:address":"6570 W Flamingo Rd",
    "sg:city":"Las Vegas",
    "sg:classifiers":[
        {
            "category":"Real Estate",
            "subcategory":"Real Estate Operator",
            "type":"Services"
        }
    ],
    "sg:phone":"+1 702 873 5209",
    "sg:postcode":"89103",
    "sg:province":"NV",
    "sg:tags":[
        "apartment"
    ],
    "wof:name":"Tango Apartments",
    "wof:placetype":"venue"
},
  "geometry": {"coordinates":[-115.235001,36.114601],"type":"Point"}
}