{
  "type": "Feature",
  "properties": {
    "iso:country":"US",
    "sg:address":"218 Tacoma Ave",
    "sg:city":"Carson City",
    "sg:classifiers":[
        {
            "category":"Organizations",
            "subcategory":"Community Association",
            "type":"Services"
        }
    ],
    "sg:phone":"+1 775 841 7347",
    "sg:postcode":"89703",
    "sg:province":"NV",
    "wof:name":"Kiwanis Club of Carson City",
    "wof:placetype":"venue"
},
  "geometry": {"coordinates":[-119.778572,39.163725],"type":"Point"}
}