{
  "type": "Feature",
  "properties": {
    "iso:country":"US",
    "sg:address":"7091 W Craig Rd Ste 104",
    "sg:city":"Las Vegas",
    "sg:classifiers":[
        {
            "category":"Shopping",
            "subcategory":"Baby Store",
            "type":"Retail Goods"
        }
    ],
    "sg:phone":"+1 702 932 3700",
    "sg:postcode":"89129",
    "sg:province":"NV",
    "sg:tags":[
        "gear",
        "furniture"
    ],
    "sg:website":"www.usababylv.com",
    "wof:name":"USA Baby Child Space",
    "wof:placetype":"venue"
},
  "geometry": {"coordinates":[-115.249691,36.240392],"type":"Point"}
}