{
  "type": "Feature",
  "properties": {
    "iso:country":"US",
    "sg:address":"10463 Luna Magico Ave",
    "sg:city":"Las Vegas",
    "sg:classifiers":[
        {
            "category":"Professional",
            "subcategory":"Art Services",
            "type":"Services"
        }
    ],
    "sg:phone":"+1 702 228 8195",
    "sg:postcode":"89135",
    "sg:province":"NV",
    "sg:tags":[
        "photographer"
    ],
    "wof:name":"Lennox Mc Lendon Photography",
    "wof:placetype":"venue"
},
  "geometry": {"coordinates":[-115.32186299999999,36.105868],"type":"Point"}
}