{
  "type": "Feature",
  "properties": {
    "iso:country":"US",
    "sg:address":"1610 Red Rock Dr",
    "sg:city":"Pahrump",
    "sg:classifiers":[
        {
            "category":"Professional",
            "subcategory":"Engineering",
            "type":"Services"
        }
    ],
    "sg:phone":"+1 775 727 5421",
    "sg:postcode":"89048",
    "sg:province":"NV",
    "sg:tags":[
        "engineer"
    ],
    "wof:name":"CRT Engineering Svc",
    "wof:placetype":"venue"
},
  "geometry": {"coordinates":[-116.026614,36.200487],"type":"Point"}
}