{
  "type": "Feature",
  "properties": {
    "iso:country":"US",
    "sg:address":"890 S Maine St",
    "sg:city":"Fallon",
    "sg:classifiers":[
        {
            "category":"Retail",
            "subcategory":"Auto Repair",
            "type":"Services"
        }
    ],
    "sg:phone":"+1 775 423 6306",
    "sg:postcode":"89406",
    "sg:province":"NV",
    "sg:tags":[
        "supply",
        "general"
    ],
    "wof:name":"Leos Ind V W Parts & Repr",
    "wof:placetype":"venue"
},
  "geometry": {"coordinates":[-118.77724000000001,39.466928],"type":"Point"}
}