{
  "type": "Feature",
  "properties": {
    "iso:country":"US",
    "sg:address":"601 Bridger Avenue",
    "sg:city":"Las Vegas",
    "sg:classifiers":[
        {
            "category":"Professional",
            "subcategory":"Lawyer & Legal Services",
            "type":"Services"
        }
    ],
    "sg:phone":"+1 702 382 5111",
    "sg:postcode":"89101",
    "sg:province":"NV",
    "sg:tags":[
        "divorce",
        "law",
        "family"
    ],
    "wof:name":"Rivers David J Atty",
    "wof:placetype":"venue"
},
  "geometry": {"coordinates":[-115.140598,36.166368],"type":"Point"}
}