{
  "type": "Feature",
  "properties": {
    "iso:country":"US",
    "sg:address":"4620 Meadows Ln",
    "sg:city":"Las Vegas",
    "sg:classifiers":[
        {
            "category":"Shopping",
            "subcategory":"Shoes",
            "type":"Retail Goods"
        }
    ],
    "sg:phone":"+1 702 870 9613",
    "sg:postcode":"89107",
    "sg:province":"NV",
    "wof:name":"Payless Shoesource",
    "wof:placetype":"venue"
},
  "geometry": {"coordinates":[-115.19375599999999,36.170219],"type":"Point"}
}