{
  "type": "Feature",
  "properties": {
    "iso:country":"US",
    "sg:address":"550 Yellow Pine Rd",
    "sg:city":"Reno",
    "sg:classifiers":[
        {
            "category":"Professional",
            "subcategory":"Management & Consulting",
            "type":"Services"
        }
    ],
    "sg:phone":"+1 775 849 1253",
    "sg:postcode":"89511",
    "sg:province":"NV",
    "wof:name":"Massingill Inc",
    "wof:placetype":"venue"
},
  "geometry": {"coordinates":[-119.843399,39.353728],"type":"Point"}
}