{
  "type": "Feature",
  "properties": {
    "iso:country":"US",
    "sg:address":"3665 S Fort Apache Road",
    "sg:city":"Las Vegas",
    "sg:classifiers":[
        {
            "category":"Health Services",
            "subcategory":"Optometrist",
            "type":"Services"
        }
    ],
    "sg:phone":"+1 702 207 2222",
    "sg:postcode":"89147",
    "sg:province":"NV",
    "wof:name":"Steed Cory OD",
    "wof:placetype":"venue"
},
  "geometry": {"coordinates":[-115.297005,36.123113],"type":"Point"}
}