{
  "type": "Feature",
  "properties": {
    "iso:country":"US",
    "sg:address":"10153 Prestancia Ave",
    "sg:city":"Las Vegas",
    "sg:classifiers":[
        {
            "category":"Professional",
            "subcategory":"Business Services",
            "type":"Services"
        }
    ],
    "sg:phone":"+1 702 233 6141",
    "sg:postcode":"89144",
    "sg:province":"NV",
    "wof:name":"Shirley Wickson Interiors",
    "wof:placetype":"venue"
},
  "geometry": {"coordinates":[-115.31802,36.176336],"type":"Point"}
}