{
  "type": "Feature",
  "properties": {
    "iso:country":"US",
    "sg:address":"3061 Westwood Dr",
    "sg:city":"Las Vegas",
    "sg:classifiers":[
        {
            "category":"Professional",
            "subcategory":"Lawyer & Legal Services",
            "type":"Services"
        }
    ],
    "sg:phone":"+1 702 733 3044",
    "sg:postcode":"89109",
    "sg:province":"NV",
    "wof:name":"George A Cromer Prof Corp",
    "wof:placetype":"venue"
},
  "geometry": {"coordinates":[-115.177414,36.134666],"type":"Point"}
}