{
  "type": "Feature",
  "properties": {
    "iso:country":"US",
    "sg:address":"557 E Sahara Ave Ste 111",
    "sg:city":"Las Vegas",
    "sg:classifiers":[
        {
            "category":"Food & Beverages",
            "subcategory":"Groceries & Convenience Stores",
            "type":"Retail Goods"
        }
    ],
    "sg:phone":"+1 702 892 8249",
    "sg:postcode":"89104",
    "sg:province":"NV",
    "wof:name":"Kwiky Mini Mart 4",
    "wof:placetype":"venue"
},
  "geometry": {"coordinates":[-115.148003,36.143799],"type":"Point"}
}