{
  "type": "Feature",
  "properties": {
    "iso:country":"US",
    "sg:address":"3817 Heron's Landing Dr",
    "sg:city":"Reno",
    "sg:classifiers":[
        {
            "category":"Communications",
            "subcategory":"Film & Video Production",
            "type":"Services"
        }
    ],
    "sg:phone":"+1 775 379 3985",
    "sg:postcode":"89502",
    "sg:province":"NV",
    "sg:tags":[
        "motion",
        "picture",
        "distribution"
    ],
    "wof:name":"Valley Wide Landscape",
    "wof:placetype":"venue"
},
  "geometry": {"coordinates":[-119.73842999999999,39.483184],"type":"Point"}
}