{
  "type": "Feature",
  "properties": {
    "iso:country":"US",
    "sg:address":"5062 Lunetto Ave",
    "sg:city":"Las Vegas",
    "sg:classifiers":[
        {
            "category":"Building & Trades",
            "subcategory":"Equipment Rental",
            "type":"Services"
        }
    ],
    "sg:phone":"+1 702 641 6555",
    "sg:postcode":"89141",
    "sg:province":"NV",
    "wof:name":"F C Sound",
    "wof:placetype":"venue"
},
  "geometry": {"coordinates":[-115.209361,35.989616],"type":"Point"}
}