{
  "type": "Feature",
  "properties": {
    "iso:country":"US",
    "sg:address":"134 Emden Dr",
    "sg:city":"Henderson",
    "sg:classifiers":[
        {
            "category":"Cinema",
            "subcategory":"Movie Rental",
            "type":"Entertainment"
        }
    ],
    "sg:phone":"+1 702 567 1891",
    "sg:postcode":"89015",
    "sg:province":"NV",
    "sg:tags":[
        "equipment",
        "camera",
        "system"
    ],
    "wof:name":"Totally Hidden Video",
    "wof:placetype":"venue"
},
  "geometry": {"coordinates":[-114.958133,36.044274],"type":"Point"}
}