{
  "type": "Feature",
  "properties": {
    "iso:country":"US",
    "sg:address":"333 Marsh Ave",
    "sg:city":"Reno",
    "sg:classifiers":[
        {
            "category":"Professional",
            "subcategory":"Lawyer & Legal Services",
            "type":"Services"
        }
    ],
    "sg:phone":"+1 775 348 2666",
    "sg:postcode":"89509",
    "sg:province":"NV",
    "wof:name":"John F Kirsch",
    "wof:placetype":"venue"
},
  "geometry": {"coordinates":[-119.81446800000001,39.519119],"type":"Point"}
}