{
  "type": "Feature",
  "properties": {
    "iso:country":"US",
    "sg:address":"1804 W Bonanza Rd",
    "sg:city":"Las Vegas",
    "sg:classifiers":[
        {
            "category":"Real Estate",
            "subcategory":"Real Estate Operator",
            "type":"Services"
        }
    ],
    "sg:phone":"+1 702 735 8702",
    "sg:postcode":"89106",
    "sg:province":"NV",
    "sg:tags":[
        "apartment"
    ],
    "wof:name":"Rancho Arms Apartments",
    "wof:placetype":"venue"
},
  "geometry": {"coordinates":[-115.164432,36.177208],"type":"Point"}
}