{
  "type": "Feature",
  "properties": {
    "iso:country":"US",
    "sg:address":"223 Hallett Cove Ct",
    "sg:city":"Boulder City",
    "sg:classifiers":[
        {
            "category":"Building & Trades",
            "subcategory":"Construction",
            "type":"Services"
        }
    ],
    "sg:phone":"+1 702 293 6003",
    "sg:postcode":"89005",
    "sg:province":"NV",
    "sg:tags":[
        "contractor"
    ],
    "wof:name":"Thomas Homes Inc",
    "wof:placetype":"venue"
},
  "geometry": {"coordinates":[-114.822565,35.990212],"type":"Point"}
}