{
  "type": "Feature",
  "properties": {
    "iso:country":"US",
    "sg:address":"1100 Plumb Ln",
    "sg:city":"Reno",
    "sg:classifiers":[
        {
            "category":"Personal",
            "subcategory":"Piercing",
            "type":"Services"
        }
    ],
    "sg:phone":"+1 775 829 7766",
    "sg:postcode":"89502",
    "sg:province":"NV",
    "sg:tags":[
        "body"
    ],
    "wof:name":"Piercing USA",
    "wof:placetype":"venue"
},
  "geometry": {"coordinates":[-119.780845,39.505872],"type":"Point"}
}