{
  "type": "Feature",
  "properties": {
    "iso:country":"US",
    "sg:address":"1528 Lady Bryan Ln",
    "sg:city":"Las Vegas",
    "sg:classifiers":[
        {
            "category":"Shopping",
            "subcategory":"Gifts & Souvenirs",
            "type":"Retail Goods"
        }
    ],
    "sg:phone":"+1 702 531 2739",
    "sg:postcode":"89110",
    "sg:province":"NV",
    "sg:tags":[
        "shop"
    ],
    "wof:name":"Fine Things",
    "wof:placetype":"venue"
},
  "geometry": {"coordinates":[-115.045235,36.18661],"type":"Point"}
}