{
  "type": "Feature",
  "properties": {
    "iso:country":"US",
    "sg:address":"299 Plumb Ln",
    "sg:city":"Reno",
    "sg:classifiers":[
        {
            "category":"Shopping",
            "type":"Retail Goods"
        }
    ],
    "sg:phone":"+1 775 826 6912",
    "sg:postcode":"89502",
    "sg:province":"NV",
    "sg:tags":[
        "telephone",
        "cellular"
    ],
    "wof:name":"Radio Shack",
    "wof:placetype":"venue"
},
  "geometry": {"coordinates":[-119.803214,39.505741],"type":"Point"}
}