{
  "type": "Feature",
  "properties": {
    "iso:country":"US",
    "sg:address":"4545 E Tropicana Ave",
    "sg:city":"Las Vegas",
    "sg:classifiers":[
        {
            "category":"Professional",
            "subcategory":"Accounting & Tax Preparation",
            "type":"Services"
        }
    ],
    "sg:phone":"+1 702 458 3939",
    "sg:postcode":"89121",
    "sg:province":"NV",
    "sg:tags":[
        "return",
        "filing"
    ],
    "wof:name":"Servitax Inc",
    "wof:placetype":"venue"
},
  "geometry": {"coordinates":[-115.074643,36.100195],"type":"Point"}
}