{
  "type": "Feature",
  "properties": {
    "iso:country":"US",
    "sg:address":"4338 Village Spring St",
    "sg:city":"Las Vegas",
    "sg:classifiers":[
        {
            "category":"Wholesale",
            "subcategory":"Groceries",
            "type":"Manufacturing & Wholesale Goods"
        }
    ],
    "sg:phone":"+1 702 876 9439",
    "sg:postcode":"89147",
    "sg:province":"NV",
    "sg:tags":[
        "food",
        "broker"
    ],
    "wof:name":"Imp Fine Foods",
    "wof:placetype":"venue"
},
  "geometry": {"coordinates":[-115.292689,36.110486],"type":"Point"}
}