{
  "type": "Feature",
  "properties": {
    "iso:country":"US",
    "sg:address":"2300 N Rainbow Blvd Unit 114",
    "sg:city":"Las Vegas",
    "sg:classifiers":[
        {
            "category":"Shopping",
            "subcategory":"Books",
            "type":"Retail Goods"
        }
    ],
    "sg:phone":"+1 702 648 8355",
    "sg:postcode":"89108",
    "sg:province":"NV",
    "sg:tags":[
        "bookstore"
    ],
    "sg:website":"www.familychristian.com",
    "wof:name":"Family Christian Stores",
    "wof:placetype":"venue"
},
  "geometry": {"coordinates":[-115.241997,36.202202],"type":"Point"}
}