{
  "type": "Feature",
  "properties": {
    "iso:country":"US",
    "sg:address":"170 N Boulder Hwy",
    "sg:city":"Henderson",
    "sg:classifiers":[
        {
            "category":"Shopping",
            "subcategory":"Tobacco",
            "type":"Retail Goods"
        }
    ],
    "sg:phone":"+1 702 558 5056",
    "sg:postcode":"89015",
    "sg:province":"NV",
    "sg:tags":[
        "shop"
    ],
    "wof:name":"Lake Mead Smoke & Gifts",
    "wof:placetype":"venue"
},
  "geometry": {"coordinates":[-114.98331,36.041269],"type":"Point"}
}