{
  "type": "Feature",
  "properties": {
    "iso:country":"US",
    "sg:address":"2770 S Maryland Pkwy",
    "sg:city":"Las Vegas",
    "sg:classifiers":[
        {
            "category":"Health Services",
            "subcategory":"Clinic",
            "type":"Services"
        }
    ],
    "sg:phone":"+1 702 734 2318",
    "sg:postcode":"89109",
    "sg:province":"NV",
    "sg:tags":[
        "home"
    ],
    "wof:name":"Angels Home Care Inc",
    "wof:placetype":"venue"
},
  "geometry": {"coordinates":[-115.1368,36.137848],"type":"Point"}
}