{
  "type": "Feature",
  "properties": {
    "iso:country":"US",
    "sg:address":"6337 Mount Rainier Ave",
    "sg:city":"Las Vegas",
    "sg:classifiers":[
        {
            "category":"Building & Trades",
            "subcategory":"Equipment Rental",
            "type":"Services"
        }
    ],
    "sg:phone":"+1 702 437 7441",
    "sg:postcode":"89156",
    "sg:province":"NV",
    "sg:tags":[
        "company",
        "vending"
    ],
    "wof:name":"A & B Vending",
    "wof:placetype":"venue"
},
  "geometry": {"coordinates":[-115.034809,36.199585],"type":"Point"}
}