{
  "type": "Feature",
  "properties": {
    "iso:country":"US",
    "sg:address":"6124 W Cheyenne Avenue",
    "sg:city":"Las Vegas",
    "sg:classifiers":[
        {
            "category":"Retail",
            "subcategory":"Veterinary Services",
            "type":"Services"
        }
    ],
    "sg:phone":"+1 702 645 7999",
    "sg:postcode":"89108",
    "sg:province":"NV",
    "sg:tags":[
        "veterinarian"
    ],
    "wof:name":"Schrader Kathryn DVM",
    "wof:placetype":"venue"
},
  "geometry": {"coordinates":[-115.227945,36.217119],"type":"Point"}
}