{
  "type": "Feature",
  "properties": {
    "iso:country":"US",
    "sg:address":"380 Courtland Ln",
    "sg:city":"Gardnerville",
    "sg:classifiers":[
        {
            "category":"Professional",
            "subcategory":"Management & Consulting",
            "type":"Services"
        }
    ],
    "sg:phone":"+1 775 265 4082",
    "sg:postcode":"89410",
    "sg:province":"NV",
    "sg:tags":[
        "consultant"
    ],
    "wof:name":"Renewable Energy Proj Designs",
    "wof:placetype":"venue"
},
  "geometry": {"coordinates":[-119.660023,38.864278],"type":"Point"}
}