{
  "type": "Feature",
  "properties": {
    "iso:country":"US",
    "sg:address":"5625 Leggett Rd",
    "sg:city":"Las Vegas",
    "sg:classifiers":[
        {
            "category":"Freight",
            "type":"Transportation"
        }
    ],
    "sg:phone":"+1 702 364 2100",
    "sg:postcode":"89149",
    "sg:province":"NV",
    "sg:tags":[
        "commercial",
        "storage"
    ],
    "wof:name":"Storage One",
    "wof:placetype":"venue"
},
  "geometry": {"coordinates":[-115.26738,36.263933],"type":"Point"}
}