{
  "type": "Feature",
  "properties": {
    "iso:country":"US",
    "sg:address":"4972 S Maryland Pkwy",
    "sg:city":"Las Vegas",
    "sg:classifiers":[
        {
            "category":"Professional",
            "type":"Services"
        }
    ],
    "sg:phone":"+1 702 736 4469",
    "sg:postcode":"89119",
    "sg:province":"NV",
    "sg:tags":[
        "establishment"
    ],
    "wof:name":"J Mode",
    "wof:placetype":"venue"
},
  "geometry": {"coordinates":[-115.136822,36.100876],"type":"Point"}
}