{
  "type": "Feature",
  "properties": {
    "iso:country":"US",
    "sg:address":"4510 W Diablo Dr Ste A102",
    "sg:city":"Las Vegas",
    "sg:classifiers":[
        {
            "category":"Autos & Motor Vehicles",
            "subcategory":"Auto Supplies",
            "type":"Retail Goods"
        }
    ],
    "sg:phone":"+1 702 335 5972",
    "sg:postcode":"89118",
    "sg:province":"NV",
    "sg:tags":[
        "glass"
    ],
    "sg:website":"www.eco-tint.com/",
    "wof:name":"Eco-Tint Window Tinting Las Vegas",
    "wof:placetype":"venue"
},
  "geometry": {"coordinates":[-115.202195,36.089991],"type":"Point"}
}