{
  "type": "Feature",
  "properties": {
    "iso:country":"US",
    "sg:address":"800 Viento del Montagna Ave",
    "sg:city":"Henderson",
    "sg:classifiers":[
        {
            "category":"Wholesale",
            "subcategory":"Non-durable Goods",
            "type":"Manufacturing & Wholesale Goods"
        }
    ],
    "sg:phone":"+1 702 341 6099",
    "sg:postcode":"89012",
    "sg:province":"NV",
    "wof:name":"Baskets OPlenty",
    "wof:placetype":"venue"
},
  "geometry": {"coordinates":[-115.021397,36.032015],"type":"Point"}
}