{
  "type": "Feature",
  "properties": {
    "iso:country":"US",
    "sg:address":"710 E Flamingo Ste 6",
    "sg:city":"Las Vegas",
    "sg:classifiers":[
        {
            "category":"Restaurant",
            "type":"Food & Drink"
        }
    ],
    "sg:phone":"+1 702 796 7333",
    "sg:postcode":"89119",
    "sg:province":"NV",
    "sg:tags":[
        "italian",
        "pizza"
    ],
    "wof:name":"Verona Pizza",
    "wof:placetype":"venue"
},
  "geometry": {"coordinates":[-115.146163,36.114774],"type":"Point"}
}