{
  "type": "Feature",
  "properties": {
    "iso:country":"US",
    "sg:address":"2001 S Jones Blvd",
    "sg:city":"Las Vegas",
    "sg:classifiers":[
        {
            "category":"Real Estate",
            "subcategory":"Developer",
            "type":"Services"
        }
    ],
    "sg:phone":"+1 702 365 8588",
    "sg:postcode":"89146",
    "sg:province":"NV",
    "sg:tags":[
        "development"
    ],
    "wof:name":"Pageantry Xix/E P LLC",
    "wof:placetype":"venue"
},
  "geometry": {"coordinates":[-115.225651,36.151054],"type":"Point"}
}