{
  "type": "Feature",
  "properties": {
    "iso:country":"US",
    "sg:address":"2510 Wigwam Pkwy",
    "sg:city":"Henderson",
    "sg:classifiers":[
        {
            "category":"Professional",
            "subcategory":"Lawyer & Legal Services",
            "type":"Services"
        }
    ],
    "sg:phone":"+1 702 407 7777",
    "sg:postcode":"89074",
    "sg:province":"NV",
    "wof:name":"Edward M Georgen PC",
    "wof:placetype":"venue"
},
  "geometry": {"coordinates":[-115.097743,36.034669],"type":"Point"}
}