{
  "type": "Feature",
  "properties": {
    "iso:country":"US",
    "sg:address":"3111 S Valley View Blvd",
    "sg:city":"Las Vegas",
    "sg:classifiers":[
        {
            "category":"Food & Beverages",
            "subcategory":"Specialty",
            "type":"Retail Goods"
        }
    ],
    "sg:phone":"+1 702 862 4372",
    "sg:postcode":"89102",
    "sg:province":"NV",
    "sg:tags":[
        "herb"
    ],
    "wof:name":"Herbal Works",
    "wof:placetype":"venue"
},
  "geometry": {"coordinates":[-115.19044,36.132927],"type":"Point"}
}