{
  "type": "Feature",
  "properties": {
    "iso:country":"US",
    "sg:address":"8390 S Rainbow Blvd",
    "sg:city":"Las Vegas",
    "sg:classifiers":[
        {
            "category":"Fast Food",
            "type":"Food & Drink"
        }
    ],
    "sg:phone":"+1 702 220 3912",
    "sg:postcode":"89139",
    "sg:province":"NV",
    "sg:tags":[
        "burger"
    ],
    "sg:website":"cheeburger.com/",
    "wof:name":"Cheeburger Cheeburger",
    "wof:placetype":"venue"
},
  "geometry": {"coordinates":[-115.243422,36.035964],"type":"Point"}
}