{
  "type": "Feature",
  "properties": {
    "iso:country":"US",
    "sg:address":"1401 N Decatur Blvd",
    "sg:city":"Las Vegas",
    "sg:classifiers":[
        {
            "category":"Shopping",
            "subcategory":"Beauty & Cosmetics",
            "type":"Retail Goods"
        }
    ],
    "sg:phone":"+1 702 648 5162",
    "sg:postcode":"89108",
    "sg:province":"NV",
    "sg:tags":[
        "supply"
    ],
    "sg:website":"www.bswsuperstores.com/gnuboard4/",
    "wof:name":"Beauty Supply Warehouse",
    "wof:placetype":"venue"
},
  "geometry": {"coordinates":[-115.206001,36.1861],"type":"Point"}
}