{
  "type": "Feature",
  "properties": {
    "iso:country":"US",
    "sg:address":"5289 Mineral Lake Dr",
    "sg:city":"Las Vegas",
    "sg:classifiers":[
        {
            "category":"Professional",
            "subcategory":"Management & Consulting",
            "type":"Services"
        }
    ],
    "sg:phone":"+1 702 401 8808",
    "sg:postcode":"89122",
    "sg:province":"NV",
    "sg:tags":[
        "teaching"
    ],
    "wof:name":"D & S Consulting",
    "wof:placetype":"venue"
},
  "geometry": {"coordinates":[-115.029046,36.093597],"type":"Point"}
}