{
  "type": "Feature",
  "properties": {
    "iso:country":"US",
    "sg:address":"6450 Stewart Avenue",
    "sg:city":"Las Vegas",
    "sg:classifiers":[
        {
            "category":"Organizations",
            "subcategory":"Non-profit Organization",
            "type":"Services"
        }
    ],
    "sg:phone":"+1 702 387 1010",
    "sg:postcode":"89110",
    "sg:province":"NV",
    "sg:tags":[
        "service/non-profit",
        "community"
    ],
    "sg:website":"www.10000kids.com",
    "wof:name":"10000 Kids",
    "wof:placetype":"venue"
},
  "geometry": {"coordinates":[-115.032435,36.166674],"type":"Point"}
}