{
  "type": "Feature",
  "properties": {
    "iso:country":"US",
    "sg:address":"5621 Ave Silla",
    "sg:city":"Las Vegas",
    "sg:classifiers":[
        {
            "category":"Building & Trades",
            "subcategory":"Landscaping Services",
            "type":"Services"
        }
    ],
    "sg:phone":"+1 702 497 9746",
    "sg:postcode":"89108",
    "sg:province":"NV",
    "sg:tags":[
        "landscape",
        "contractor"
    ],
    "wof:name":"Elite Landscape Inc",
    "wof:placetype":"venue"
},
  "geometry": {"coordinates":[-115.222228,36.210584],"type":"Point"}
}