{
  "type": "Feature",
  "properties": {
    "iso:country":"US",
    "sg:address":"4500 E Bonanza Road",
    "sg:city":"Las Vegas",
    "sg:classifiers":[
        {
            "category":"Health Services",
            "subcategory":"Chiropractor",
            "type":"Services"
        }
    ],
    "sg:phone":"+1 702 388 0599",
    "sg:postcode":"89110",
    "sg:province":"NV",
    "wof:name":"Northeastern Bonanza Lamb Chiropractic Center",
    "wof:placetype":"venue"
},
  "geometry": {"coordinates":[-115.078063,36.173557],"type":"Point"}
}