{
  "type": "Feature",
  "properties": {
    "iso:country":"US",
    "sg:address":"90 W 4th St",
    "sg:city":"Winnemucca",
    "sg:classifiers":[
        {
            "category":"Government",
            "subcategory":"Office",
            "type":"Public Place"
        }
    ],
    "sg:phone":"+1 775 623 6339",
    "sg:postcode":"89445",
    "sg:province":"NV",
    "sg:tags":[
        "village"
    ],
    "sg:website":"www.winnemuccacity.org",
    "wof:name":"Winnemucca Business License",
    "wof:placetype":"venue"
},
  "geometry": {"coordinates":[-117.734608,40.972249],"type":"Point"}
}