{
  "type": "Feature",
  "properties": {
    "iso:country":"US",
    "sg:address":"3204 Crescent Run Ct",
    "sg:city":"Las Vegas",
    "sg:classifiers":[
        {
            "category":"Building & Trades",
            "subcategory":"Cleaning & Sanitation",
            "type":"Services"
        }
    ],
    "sg:phone":"+1 702 360 3040",
    "sg:postcode":"89117",
    "sg:province":"NV",
    "sg:tags":[
        "window",
        "maintenance"
    ],
    "wof:name":"Jay's Window & Carpet Cleaning",
    "wof:placetype":"venue"
},
  "geometry": {"coordinates":[-115.299663,36.132861],"type":"Point"}
}