{
  "type": "Feature",
  "properties": {
    "iso:country":"US",
    "sg:address":"4855 Vegas Valley Dr Ofc",
    "sg:city":"Las Vegas",
    "sg:classifiers":[
        {
            "category":"Real Estate",
            "subcategory":"Real Estate Operator",
            "type":"Services"
        }
    ],
    "sg:phone":"+1 702 454 4979",
    "sg:postcode":"89121",
    "sg:province":"NV",
    "sg:tags":[
        "apartment"
    ],
    "sg:website":"www.sunridgeapartmenthomes.com",
    "wof:name":"Sunridge Apartment Homes",
    "wof:placetype":"venue"
},
  "geometry": {"coordinates":[-115.068001,36.136902],"type":"Point"}
}