{
  "type": "Feature",
  "properties": {
    "iso:country":"US",
    "sg:address":"3068 E Sunset Rd",
    "sg:city":"Las Vegas",
    "sg:classifiers":[
        {
            "category":"Professional",
            "subcategory":"Employment Agencies",
            "type":"Services"
        }
    ],
    "sg:phone":"+1 702 893 2626",
    "sg:postcode":"89120",
    "sg:province":"NV",
    "sg:tags":[
        "help",
        "supply"
    ],
    "wof:name":"Manpower",
    "wof:placetype":"venue"
},
  "geometry": {"coordinates":[-115.10841600000001,36.071635],"type":"Point"}
}