{
  "type": "Feature",
  "properties": {
    "iso:country":"US",
    "sg:address":"3000 W Ann Rd # 102-125",
    "sg:city":"North Las Vegas",
    "sg:classifiers":[
        {
            "category":"Personal",
            "type":"Services"
        }
    ],
    "sg:phone":"+1 702 688 8282",
    "sg:postcode":"89031",
    "sg:province":"NV",
    "sg:tags":[
        "home"
    ],
    "sg:website":"www.allthesecables.com",
    "wof:name":"All These Cables",
    "wof:placetype":"venue"
},
  "geometry": {"coordinates":[-115.180419,36.26314],"type":"Point"}
}