{
  "type": "Feature",
  "properties": {
    "iso:country":"US",
    "sg:address":"2955 N McCarran Blvd",
    "sg:city":"Sparks",
    "sg:classifiers":[
        {
            "category":"Professional",
            "subcategory":"Accounting & Tax Preparation",
            "type":"Services"
        }
    ],
    "sg:phone":"+1 775 356 1663",
    "sg:postcode":"89431",
    "sg:province":"NV",
    "sg:tags":[
        "return",
        "filing"
    ],
    "wof:name":"Jackson Hewitt Tax Svc",
    "wof:placetype":"venue"
},
  "geometry": {"coordinates":[-119.754701,39.556353],"type":"Point"}
}