{
  "type": "Feature",
  "properties": {
    "iso:country":"US",
    "sg:address":"4496 S Pecos Rd",
    "sg:city":"Las Vegas",
    "sg:classifiers":[
        {
            "category":"Health Services",
            "subcategory":"Doctor",
            "type":"Services"
        }
    ],
    "sg:phone":"+1 702 655 1216",
    "sg:postcode":"89121",
    "sg:province":"NV",
    "sg:tags":[
        "medical"
    ],
    "wof:name":"Veterinary Neurological Center",
    "wof:placetype":"venue"
},
  "geometry": {"coordinates":[-115.100655,36.109369],"type":"Point"}
}