{
  "type": "Feature",
  "properties": {
    "iso:country":"US",
    "sg:address":"5740 S Eastern Avenue",
    "sg:city":"Las Vegas",
    "sg:classifiers":[
        {
            "category":"Real Estate",
            "subcategory":"Architect",
            "type":"Services"
        }
    ],
    "sg:phone":"+1 702 853 0220",
    "sg:postcode":"89119",
    "sg:province":"NV",
    "wof:name":"The McIntosh Group",
    "wof:placetype":"venue"
},
  "geometry": {"coordinates":[-115.11874,36.085419],"type":"Point"}
}