{
  "type": "Feature",
  "properties": {
    "iso:country":"US",
    "sg:address":"2550 Hitchcock St",
    "sg:city":"Henderson",
    "sg:classifiers":[
        {
            "category":"Professional",
            "subcategory":"Computer Services",
            "type":"Services"
        }
    ],
    "sg:phone":"+1 702 492 6863",
    "sg:postcode":"89052",
    "sg:province":"NV",
    "sg:tags":[
        "system",
        "integration"
    ],
    "wof:name":"Globespanvirata Inc",
    "wof:placetype":"venue"
},
  "geometry": {"coordinates":[-115.095602,35.996713],"type":"Point"}
}