{
  "type": "Feature",
  "properties": {
    "iso:country":"US",
    "sg:address":"13911 Cadet Rd",
    "sg:city":"Fallon",
    "sg:classifiers":[
        {
            "category":"Food & Beverages",
            "subcategory":"Meat & Fish",
            "type":"Retail Goods"
        }
    ],
    "sg:phone":"+1 775 867 3489",
    "sg:postcode":"89406",
    "sg:province":"NV",
    "wof:name":"Lahontan Valley Meats",
    "wof:placetype":"venue"
},
  "geometry": {"coordinates":[-119.023732,39.483929],"type":"Point"}
}