{
  "type": "Feature",
  "properties": {
    "iso:country":"US",
    "sg:address":"974 Tillman Ln",
    "sg:city":"Gardnerville",
    "sg:classifiers":[
        {
            "category":"Place Of Worship",
            "subcategory":"Church",
            "type":"Public Place"
        },
        {
            "category":"Place Of Worship",
            "type":"Public Place"
        },
        {
            "category":"Organizations",
            "subcategory":"Religious Organization",
            "type":"Services"
        }
    ],
    "sg:phone":"+1 775 265 3544",
    "sg:postcode":"89460",
    "sg:province":"NV",
    "sg:tags":[
        "god",
        "god-independent",
        "churches-assemblies"
    ],
    "wof:name":"Dayspring Christian Assembly",
    "wof:placetype":"venue"
},
  "geometry": {"coordinates":[-119.742104,38.90889],"type":"Point"}
}