{
  "type": "Feature",
  "properties": {
    "iso:country":"US",
    "sg:address":"3360 N Pioneer Way",
    "sg:city":"Las Vegas",
    "sg:classifiers":[
        {
            "category":"Food & Beverages",
            "subcategory":"Specialty",
            "type":"Retail Goods"
        }
    ],
    "sg:phone":"+1 702 645 4574",
    "sg:postcode":"89129",
    "sg:province":"NV",
    "wof:name":"Bodi Power Surge Inc",
    "wof:placetype":"venue"
},
  "geometry": {"coordinates":[-115.255865,36.22191],"type":"Point"}
}