{
  "type": "Feature",
  "properties": {
    "iso:country":"US",
    "sg:address":"4990 W Craig Rd",
    "sg:city":"Las Vegas",
    "sg:classifiers":[
        {
            "category":"Retail",
            "subcategory":"Animal Services",
            "type":"Services"
        }
    ],
    "sg:phone":"+1 702 382 7297",
    "sg:postcode":"89130",
    "sg:province":"NV",
    "sg:tags":[
        "pet",
        "grooming",
        "washing"
    ],
    "wof:name":"Paws Fins & Feathers",
    "wof:placetype":"venue"
},
  "geometry": {"coordinates":[-115.208794,36.238845],"type":"Point"}
}