{
  "type": "Feature",
  "properties": {
    "iso:country":"US",
    "sg:address":"219 Redfield Pkwy",
    "sg:city":"Reno",
    "sg:classifiers":[
        {
            "category":"Professional",
            "subcategory":"Research",
            "type":"Services"
        }
    ],
    "sg:phone":"+1 775 828 0999",
    "sg:postcode":"89509",
    "sg:province":"NV",
    "sg:tags":[
        "environmental",
        "ecological"
    ],
    "wof:name":"Essex Environmental Inc",
    "wof:placetype":"venue"
},
  "geometry": {"coordinates":[-119.79830699999999,39.482909],"type":"Point"}
}