{
  "type": "Feature",
  "properties": {
    "iso:country":"US",
    "sg:address":"2056 Majestic Peak Dr",
    "sg:city":"Henderson",
    "sg:classifiers":[
        {
            "category":"Banks & Credit Unions",
            "subcategory":"Financial Services",
            "type":"Services"
        }
    ],
    "sg:phone":"+1 702 897 2272",
    "sg:postcode":"89074",
    "sg:province":"NV",
    "sg:tags":[
        "trust",
        "management"
    ],
    "wof:name":"Ovian Family Trust",
    "wof:placetype":"venue"
},
  "geometry": {"coordinates":[-115.076536,36.028317],"type":"Point"}
}