{
  "type": "Feature",
  "properties": {
    "iso:country":"US",
    "sg:address":"2233 Hondo Ln",
    "sg:city":"Elko",
    "sg:classifiers":[
        {
            "category":"Banks & Credit Unions",
            "subcategory":"Financial Services",
            "type":"Services"
        }
    ],
    "sg:phone":"+1 775 738 2070",
    "sg:postcode":"89801",
    "sg:province":"NV",
    "sg:tags":[
        "trust",
        "management"
    ],
    "wof:name":"Rein Munster Trust",
    "wof:placetype":"venue"
},
  "geometry": {"coordinates":[-115.81030800000001,40.827945],"type":"Point"}
}