{
  "type": "Feature",
  "properties": {
    "iso:country":"US",
    "sg:address":"505 Bonneville Ave",
    "sg:city":"Las Vegas",
    "sg:classifiers":[
        {
            "category":"Insurance",
            "subcategory":"Hazard Insurance",
            "type":"Services"
        },
        {
            "category":"Professional",
            "subcategory":"Business Services",
            "type":"Services"
        }
    ],
    "sg:phone":"+1 702 386 9116",
    "sg:postcode":"89101",
    "sg:province":"NV",
    "sg:tags":[
        "bond"
    ],
    "wof:name":"Rescue Bail Bonds Inc",
    "wof:placetype":"venue"
},
  "geometry": {"coordinates":[-115.143328,36.163015],"type":"Point"}
}