{
  "type": "Feature",
  "properties": {
    "iso:country":"US",
    "sg:address":"8578 W Lake Mead Blvd",
    "sg:city":"Las Vegas",
    "sg:classifiers":[
        {
            "category":"Retail",
            "subcategory":"Laundry & Dry Cleaning",
            "type":"Services"
        }
    ],
    "sg:phone":"+1 702 228 5843",
    "sg:postcode":"89128",
    "sg:province":"NV",
    "sg:tags":[
        "cleaner"
    ],
    "sg:website":"www.alphillips-thecleaner.com",
    "wof:name":"Al Phillips the Cleaner Inc",
    "wof:placetype":"venue"
},
  "geometry": {"coordinates":[-115.281998,36.1996],"type":"Point"}
}