{
  "type": "Feature",
  "properties": {
    "iso:country":"US",
    "sg:address":"1097 Broadmoor Ave",
    "sg:city":"Las Vegas",
    "sg:classifiers":[
        {
            "category":"Professional",
            "subcategory":"Management & Consulting",
            "type":"Services"
        }
    ],
    "sg:phone":"+1 702 732 3230",
    "sg:postcode":"89109",
    "sg:province":"NV",
    "wof:name":"Valtec Capital Corp",
    "wof:placetype":"venue"
},
  "geometry": {"coordinates":[-115.139669,36.132061],"type":"Point"}
}