{
  "type": "Feature",
  "properties": {
    "iso:country":"US",
    "sg:address":"885 US Hwy 50",
    "sg:city":"Zephyr Cove",
    "sg:classifiers":[
        {
            "category":"Social Services",
            "subcategory":"Adult Care",
            "type":"Services"
        }
    ],
    "sg:phone":"+1 775 588 5140",
    "sg:postcode":"89448",
    "sg:province":"NV",
    "sg:tags":[
        "organization",
        "senior",
        "citizen"
    ],
    "wof:name":"Tahoe Douglas Senior Ctr",
    "wof:placetype":"venue"
},
  "geometry": {"coordinates":[-119.947076,39.017526],"type":"Point"}
}