{
  "type": "Feature",
  "properties": {
    "iso:country":"US",
    "sg:address":"250 S Maine St",
    "sg:city":"Fallon",
    "sg:classifiers":[
        {
            "category":"Food & Beverages",
            "subcategory":"Meat & Fish",
            "type":"Retail Goods"
        }
    ],
    "sg:phone":"+1 775 423 2241",
    "sg:postcode":"89406",
    "sg:province":"NV",
    "wof:name":"Hecks Market",
    "wof:placetype":"venue"
},
  "geometry": {"coordinates":[-118.77713900000001,39.472548],"type":"Point"}
}