{
  "type": "Feature",
  "properties": {
    "iso:country":"US",
    "sg:address":"727 Riverside Dr",
    "sg:city":"Reno",
    "sg:classifiers":[
        {
            "category":"Social Services",
            "subcategory":"Adult Care",
            "type":"Services"
        }
    ],
    "sg:phone":"+1 775 322 6749",
    "sg:postcode":"89503",
    "sg:province":"NV",
    "sg:tags":[
        "home",
        "residential"
    ],
    "wof:name":"Riverhaven Residential Care",
    "wof:placetype":"venue"
},
  "geometry": {"coordinates":[-119.822135,39.521681],"type":"Point"}
}