{
  "type": "Feature",
  "properties": {
    "iso:country":"US",
    "sg:address":"8660 Corrigan Way",
    "sg:city":"Reno",
    "sg:classifiers":[
        {
            "category":"Professional",
            "subcategory":"Advertising",
            "type":"Services"
        }
    ],
    "sg:phone":"+1 775 544 8456",
    "sg:postcode":"89506",
    "sg:province":"NV",
    "sg:tags":[
        "agency"
    ],
    "wof:name":"Savings Four U",
    "wof:placetype":"venue"
},
  "geometry": {"coordinates":[-119.901149,39.631717],"type":"Point"}
}