{
  "type": "Feature",
  "properties": {
    "iso:country":"US",
    "sg:address":"5933 W. Tropicana Ave",
    "sg:city":"Las Vegas",
    "sg:classifiers":[
        {
            "category":"Autos & Motor Vehicles",
            "subcategory":"Auto Supplies",
            "type":"Retail Goods"
        }
    ],
    "sg:phone":"+1 702 368 2121",
    "sg:postcode":"89103",
    "sg:province":"NV",
    "sg:tags":[
        "glass"
    ],
    "wof:name":"Silver State Window Tinting",
    "wof:placetype":"venue"
},
  "geometry": {"coordinates":[-115.22231600000001,36.099628],"type":"Point"}
}