{
  "type": "Feature",
  "properties": {
    "iso:country":"US",
    "sg:address":"106 Main St",
    "sg:city":"Beatty",
    "sg:classifiers":[
        {
            "category":"Bars & Pubs",
            "type":"Food & Drink"
        }
    ],
    "sg:phone":"+1 775 553 2266",
    "sg:postcode":"89003",
    "sg:province":"NV",
    "sg:tags":[
        "lounge",
        "cocktail"
    ],
    "wof:name":"Sour Dough Saloon",
    "wof:placetype":"venue"
},
  "geometry": {"coordinates":[-116.758529,36.909196],"type":"Point"}
}