{
  "type": "Feature",
  "properties": {
    "iso:country":"US",
    "sg:address":"4950 S Fort Apache Road",
    "sg:city":"Las Vegas",
    "sg:classifiers":[
        {
            "category":"Shopping",
            "subcategory":"Department Store",
            "type":"Retail Goods"
        }
    ],
    "sg:phone":"+1 702 220 3087",
    "sg:postcode":"89148",
    "sg:province":"NV",
    "wof:name":"Pier 1 Imports #1386",
    "wof:placetype":"venue"
},
  "geometry": {"coordinates":[-115.297371,36.099321],"type":"Point"}
}