{
  "type": "Feature",
  "properties": {
    "iso:country":"US",
    "sg:address":"1440 Haskell St",
    "sg:city":"Reno",
    "sg:classifiers":[
        {
            "category":"Professional",
            "subcategory":"Lawyer & Legal Services",
            "type":"Services"
        }
    ],
    "sg:phone":"+1 775 337 0300",
    "sg:postcode":"89509",
    "sg:province":"NV",
    "sg:tags":[
        "attorney",
        "death",
        "personal",
        "worker",
        "compensation",
        "wrongful",
        "benefit",
        "employee",
        "injury",
        "law"
    ],
    "sg:website":"http://www.sigurdsonlaw.com",
    "wof:name":"Sigurdson, Kathleen Attorney At Law",
    "wof:placetype":"venue"
},
  "geometry": {"coordinates":[-119.808055,39.510226],"type":"Point"}
}