{
  "type": "Feature",
  "properties": {
    "iso:country":"US",
    "sg:address":"3516 Las Vegas Fwy",
    "sg:city":"North Las Vegas",
    "sg:classifiers":[
        {
            "category":"Shopping",
            "subcategory":"Gifts & Souvenirs",
            "type":"Retail Goods"
        }
    ],
    "sg:phone":"+1 702 399 8719",
    "sg:postcode":"89030",
    "sg:province":"NV",
    "sg:tags":[
        "party",
        "supply"
    ],
    "wof:name":"Rainbow Party Supply",
    "wof:placetype":"venue"
},
  "geometry": {"coordinates":[-115.119295,36.223709],"type":"Point"}
}