{
  "type": "Feature",
  "properties": {
    "iso:country":"US",
    "sg:address":"5032 Spencer St",
    "sg:city":"Las Vegas",
    "sg:classifiers":[
        {
            "category":"Utilities",
            "subcategory":"Telephone",
            "type":"Services"
        }
    ],
    "sg:phone":"+1 702 596 7985",
    "sg:postcode":"89119",
    "sg:province":"NV",
    "sg:tags":[
        "communications"
    ],
    "wof:name":"Jaquith Worldwide",
    "wof:placetype":"venue"
},
  "geometry": {"coordinates":[-115.12786,36.099708],"type":"Point"}
}