{
  "type": "Feature",
  "properties": {
    "iso:country":"US",
    "sg:address":"110 US Hwy 50",
    "sg:city":"Stateline",
    "sg:classifiers":[
        {
            "category":"Banks & Credit Unions",
            "subcategory":"Bank",
            "type":"Services"
        }
    ],
    "sg:phone":"+1 775 588 6652",
    "sg:postcode":"89448",
    "sg:province":"CA",
    "sg:website":"www.wellsfargo.com",
    "wof:name":"Wells Fargo Bank",
    "wof:placetype":"venue"
},
  "geometry": {"coordinates":[-119.93584199999999,38.968513],"type":"Point"}
}