{
  "type": "Feature",
  "properties": {
    "iso:country":"US",
    "sg:address":"1639 W Warm Springs Road",
    "sg:city":"Henderson",
    "sg:classifiers":[
        {
            "category":"Restaurant",
            "type":"Food & Drink"
        }
    ],
    "sg:phone":"+1 702 451 6777",
    "sg:postcode":"89014",
    "sg:province":"NV",
    "sg:tags":[
        "middle",
        "eastern"
    ],
    "wof:name":"King Kabob",
    "wof:placetype":"venue"
},
  "geometry": {"coordinates":[-115.055216,36.056047],"type":"Point"}
}