{
  "type": "Feature",
  "properties": {
    "iso:country":"US",
    "sg:address":"3571 E Sunset Rd",
    "sg:city":"Las Vegas",
    "sg:classifiers":[
        {
            "category":"Real Estate",
            "subcategory":"Real Estate Services",
            "type":"Services"
        }
    ],
    "sg:phone":"+1 702 458 9333",
    "sg:postcode":"89120",
    "sg:province":"NV",
    "sg:tags":[
        "company",
        "title"
    ],
    "wof:name":"Southwest Title",
    "wof:placetype":"venue"
},
  "geometry": {"coordinates":[-115.10020900000001,36.071476],"type":"Point"}
}