{
  "type": "Feature",
  "properties": {
    "iso:country":"US",
    "sg:address":"711 Mall Ring Cir",
    "sg:city":"Henderson",
    "sg:classifiers":[
        {
            "category":"Professional",
            "subcategory":"Lawyer & Legal Services",
            "type":"Services"
        }
    ],
    "sg:phone":"+1 702 434 8282",
    "sg:postcode":"89014",
    "sg:province":"NV",
    "wof:name":"Nettles Law Offices of Brian D Ltd",
    "wof:placetype":"venue"
},
  "geometry": {"coordinates":[-115.045108,36.069101],"type":"Point"}
}