{
  "type": "Feature",
  "properties": {
    "iso:country":"US",
    "sg:address":"2800 N Tenaya Way Suite 102",
    "sg:city":"Las Vegas",
    "sg:classifiers":[
        {
            "category":"Health Services",
            "subcategory":"Optometrist",
            "type":"Services"
        }
    ],
    "sg:phone":"+1 702 384 2020",
    "sg:postcode":"89128",
    "sg:province":"NV",
    "wof:name":"Eye Clinic of Las Vegas",
    "wof:placetype":"venue"
},
  "geometry": {"coordinates":[-115.249425,36.210849],"type":"Point"}
}