{
  "type": "Feature",
  "properties": {
    "iso:country":"US",
    "sg:address":"1502 N Carson St",
    "sg:city":"Carson City",
    "sg:classifiers":[
        {
            "category":"Personal",
            "subcategory":"Beauty Salon",
            "type":"Services"
        }
    ],
    "sg:phone":"+1 775 882 9484",
    "sg:postcode":"89701",
    "sg:province":"NV",
    "wof:name":"Hair It Is Styling Salon",
    "wof:placetype":"venue"
},
  "geometry": {"coordinates":[-119.766997,39.173429],"type":"Point"}
}