{
  "type": "Feature",
  "properties": {
    "iso:country":"US",
    "sg:address":"4301 E Charleston Boulevard",
    "sg:city":"Las Vegas",
    "sg:classifiers":[
        {
            "category":"Shopping",
            "subcategory":"Shoes",
            "type":"Retail Goods"
        }
    ],
    "sg:phone":"+1 702 453 0055",
    "sg:postcode":"89104",
    "sg:province":"NV",
    "sg:tags":[
        "store"
    ],
    "sg:website":"www.footlocker.com",
    "wof:name":"Foot Locker Stores",
    "wof:placetype":"venue"
},
  "geometry": {"coordinates":[-115.080157,36.158862],"type":"Point"}
}