{
  "type": "Feature",
  "properties": {
    "iso:country":"US",
    "sg:address":"2660 S Rainbow Blvd",
    "sg:city":"Las Vegas",
    "sg:classifiers":[
        {
            "category":"Banks & Credit Unions",
            "subcategory":"Bank",
            "type":"Services"
        }
    ],
    "sg:phone":"+1 702 248 0102",
    "sg:postcode":"89146",
    "sg:province":"NV",
    "sg:tags":[
        "mortgage"
    ],
    "wof:name":"Pacific American Mortgage",
    "wof:placetype":"venue"
},
  "geometry": {"coordinates":[-115.242834,36.14161],"type":"Point"}
}