{
  "type": "Feature",
  "properties": {
    "iso:country":"US",
    "sg:address":"5052 S Jones Blvd",
    "sg:city":"Las Vegas",
    "sg:classifiers":[
        {
            "category":"Health Services",
            "subcategory":"Doctor",
            "type":"Services"
        }
    ],
    "sg:phone":"+1 702 222 1856",
    "sg:postcode":"89118",
    "sg:province":"NV",
    "sg:tags":[
        "physician",
        "surgeon"
    ],
    "wof:name":"Sleep Telemedicine Svc",
    "wof:placetype":"venue"
},
  "geometry": {"coordinates":[-115.224961,36.099081],"type":"Point"}
}