{
  "type": "Feature",
  "properties": {
    "iso:country":"US",
    "sg:address":"7100 N Durango Dr",
    "sg:city":"Las Vegas",
    "sg:classifiers":[
        {
            "category":"Banks & Credit Unions",
            "subcategory":"Bank",
            "type":"Services"
        }
    ],
    "sg:phone":"+1 702 515 8560",
    "sg:postcode":"89149",
    "sg:province":"NV",
    "sg:website":"www.wellsfargo.com",
    "wof:name":"Wells Fargo",
    "wof:placetype":"venue"
},
  "geometry": {"coordinates":[-115.287334,36.290319],"type":"Point"}
}