{
  "type": "Feature",
  "properties": {
    "iso:country":"US",
    "sg:address":"4515 S Durango Dr",
    "sg:city":"Las Vegas",
    "sg:classifiers":[
        {
            "category":"Manufacturing",
            "subcategory":"Chemicals & Compounds",
            "type":"Manufacturing & Wholesale Goods"
        }
    ],
    "sg:phone":"+1 702 221 5690",
    "sg:postcode":"89147",
    "sg:province":"NV",
    "sg:tags":[
        "mfg",
        "printing",
        "ink"
    ],
    "wof:name":"Quality Ink Corp",
    "wof:placetype":"venue"
},
  "geometry": {"coordinates":[-115.279233,36.105473],"type":"Point"}
}