{
  "type": "Feature",
  "properties": {
    "iso:country":"US",
    "sg:address":"800 S 7th St",
    "sg:city":"Las Vegas",
    "sg:classifiers":[
        {
            "category":"Professional",
            "subcategory":"Lawyer & Legal Services",
            "type":"Services"
        }
    ],
    "sg:phone":"+1 702 382 2990",
    "sg:postcode":"89101",
    "sg:province":"NV",
    "sg:tags":[
        "attorney"
    ],
    "wof:name":"Michael J Amador & Assoc",
    "wof:placetype":"venue"
},
  "geometry": {"coordinates":[-115.14456,36.158833],"type":"Point"}
}