{
  "type": "Feature",
  "properties": {
    "iso:country":"US",
    "sg:address":"277 Merrick Way",
    "sg:city":"Henderson",
    "sg:classifiers":[
        {
            "category":"Wholesale",
            "subcategory":"Machinery & Supplies",
            "type":"Manufacturing & Wholesale Goods"
        }
    ],
    "sg:phone":"+1 702 456 6950",
    "sg:postcode":"89014",
    "sg:province":"NV",
    "sg:tags":[
        "pump"
    ],
    "wof:name":"Cortech Engineering",
    "wof:placetype":"venue"
},
  "geometry": {"coordinates":[-115.058182,36.047747],"type":"Point"}
}