{
  "type": "Feature",
  "properties": {
    "iso:country":"US",
    "sg:address":"860 E Sahara Ave",
    "sg:city":"Las Vegas",
    "sg:classifiers":[
        {
            "category":"Organizations",
            "subcategory":"Non-profit Organization",
            "type":"Services"
        }
    ],
    "sg:phone":"+1 702 294 2273",
    "sg:postcode":"89104",
    "sg:province":"NV",
    "sg:tags":[
        "alternative",
        "abortion"
    ],
    "sg:website":"www.awomanscare.org",
    "wof:name":"Ist Choice Pregnancy Svc",
    "wof:placetype":"venue"
},
  "geometry": {"coordinates":[-115.143979,36.144036],"type":"Point"}
}