{
  "type": "Feature",
  "properties": {
    "iso:country":"US",
    "sg:address":"2291 N Green Valley Parkway",
    "sg:city":"Henderson",
    "sg:classifiers":[
        {
            "category":"Shopping",
            "subcategory":"Florist",
            "type":"Retail Goods"
        }
    ],
    "sg:phone":"+1 702 433 4009",
    "sg:postcode":"89014",
    "sg:province":"NV",
    "sg:website":"www.tgiflowers.com",
    "wof:name":"Tgi Flowers",
    "wof:placetype":"venue"
},
  "geometry": {"coordinates":[-115.084517,36.056746],"type":"Point"}
}