{
  "type": "Feature",
  "properties": {
    "iso:country":"US",
    "sg:address":"143 Keystone Ave",
    "sg:city":"Reno",
    "sg:classifiers":[
        {
            "category":"Real Estate",
            "subcategory":"Real Estate Agent",
            "type":"Services"
        }
    ],
    "sg:phone":"+1 775 688 3211",
    "sg:postcode":"89503",
    "sg:province":"NV",
    "sg:website":"www.gatewayproperties.com",
    "wof:name":"Gateway Properties",
    "wof:placetype":"venue"
},
  "geometry": {"coordinates":[-119.82566,39.523976],"type":"Point"}
}