{
  "type": "Feature",
  "properties": {
    "iso:country":"US",
    "sg:address":"4616 W Sahara Ave",
    "sg:city":"Las Vegas",
    "sg:classifiers":[
        {
            "category":"Professional",
            "subcategory":"Business Services",
            "type":"Services"
        }
    ],
    "sg:phone":"+1 702 878 8999",
    "sg:postcode":"89102",
    "sg:province":"NV",
    "sg:tags":[
        "box",
        "mail",
        "rental"
    ],
    "wof:name":"UPS Stores The",
    "wof:placetype":"venue"
},
  "geometry": {"coordinates":[-115.203723,36.144573],"type":"Point"}
}