{
  "type": "Feature",
  "properties": {
    "iso:country":"US",
    "sg:address":"8116 Las Vegas Blvd S",
    "sg:city":"Las Vegas",
    "sg:classifiers":[
        {
            "category":"Professional",
            "subcategory":"Management & Consulting",
            "type":"Services"
        }
    ],
    "sg:phone":"+1 702 361 8398",
    "sg:postcode":"89123",
    "sg:province":"NV",
    "sg:tags":[
        "construction"
    ],
    "wof:name":"Massengale Construction",
    "wof:placetype":"venue"
},
  "geometry": {"coordinates":[-115.17234000000001,36.038838],"type":"Point"}
}