{
  "type": "Feature",
  "properties": {
    "iso:country":"US",
    "sg:address":"3305 Spring Mountain Road",
    "sg:city":"Las Vegas",
    "sg:classifiers":[
        {
            "category":"Banks & Credit Unions",
            "subcategory":"Financial Services",
            "type":"Services"
        }
    ],
    "sg:phone":"+1 702 413 9613",
    "sg:postcode":"89102",
    "sg:province":"NV",
    "sg:tags":[
        "broker",
        "mortgage"
    ],
    "wof:name":"24-7 Realty",
    "wof:placetype":"venue"
},
  "geometry": {"coordinates":[-115.184421,36.126249],"type":"Point"}
}