{
  "type": "Feature",
  "properties": {
    "iso:country":"US",
    "sg:address":"1294 Winter Solstice Ave",
    "sg:city":"Henderson",
    "sg:classifiers":[
        {
            "category":"Shopping",
            "type":"Retail Goods"
        }
    ],
    "sg:phone":"+1 702 436 7337",
    "sg:postcode":"89014",
    "sg:province":"NV",
    "sg:tags":[
        "merchandise"
    ],
    "wof:name":"Pro Services",
    "wof:placetype":"venue"
},
  "geometry": {"coordinates":[-115.04329199999999,36.049424],"type":"Point"}
}