{
  "type": "Feature",
  "properties": {
    "iso:country":"US",
    "sg:address":"4550 E Nye Ln",
    "sg:city":"Carson City",
    "sg:classifiers":[
        {
            "category":"Building & Trades",
            "subcategory":"Electrical",
            "type":"Services"
        }
    ],
    "sg:phone":"+1 775 882 0690",
    "sg:postcode":"89706",
    "sg:province":"NV",
    "sg:tags":[
        "electrical",
        "contractor"
    ],
    "wof:name":"Comstock Electrical",
    "wof:placetype":"venue"
},
  "geometry": {"coordinates":[-119.716068,39.186388],"type":"Point"}
}