{
  "type": "Feature",
  "properties": {
    "iso:country":"US",
    "sg:address":"3186 S Maryland Parkway",
    "sg:city":"Las Vegas",
    "sg:classifiers":[
        {
            "category":"Health Services",
            "subcategory":"Doctor",
            "type":"Services"
        }
    ],
    "sg:phone":"+1 702 731 8080",
    "sg:postcode":"89109",
    "sg:province":"NV",
    "wof:name":"Troyer Gary MD",
    "wof:placetype":"venue"
},
  "geometry": {"coordinates":[-115.136978,36.134095],"type":"Point"}
}