{
  "type": "Feature",
  "properties": {
    "iso:country":"US",
    "sg:address":"885 Apache Ln",
    "sg:city":"Las Vegas",
    "sg:classifiers":[
        {
            "category":"Local Transit",
            "type":"Transportation"
        }
    ],
    "sg:phone":"+1 702 644 2418",
    "sg:postcode":"89110",
    "sg:province":"NV",
    "wof:name":"T R Forrest Trucking",
    "wof:placetype":"venue"
},
  "geometry": {"coordinates":[-115.054618,36.176211],"type":"Point"}
}