{
  "type": "Feature",
  "properties": {
    "iso:country":"US",
    "sg:address":"5850 Sky Pointe Drive Ofc",
    "sg:city":"Las Vegas",
    "sg:classifiers":[
        {
            "category":"Real Estate",
            "subcategory":"Real Estate Operator",
            "type":"Services"
        }
    ],
    "sg:phone":"+1 702 655 0026",
    "sg:postcode":"89130",
    "sg:province":"NV",
    "sg:tags":[
        "apartment"
    ],
    "wof:name":"Eagle Crest Apartments",
    "wof:placetype":"venue"
},
  "geometry": {"coordinates":[-115.256472,36.266961],"type":"Point"}
}