{
  "type": "Feature",
  "properties": {
    "iso:country":"US",
    "sg:address":"125 Las Vegas Blvd S",
    "sg:city":"Las Vegas",
    "sg:classifiers":[
        {
            "category":"Recreation",
            "type":"Entertainment"
        }
    ],
    "sg:phone":"+1 702 221 2782",
    "sg:postcode":"89101",
    "sg:province":"NV",
    "sg:tags":[
        "aquarium"
    ],
    "wof:name":"Infinity Aquarium Design",
    "wof:placetype":"venue"
},
  "geometry": {"coordinates":[-115.141176,36.16833],"type":"Point"}
}