{
  "type": "Feature",
  "properties": {
    "iso:country":"US",
    "sg:address":"1518 Shady Rest Dr",
    "sg:city":"Henderson",
    "sg:classifiers":[
        {
            "category":"Professional",
            "subcategory":"Computer Services",
            "type":"Services"
        }
    ],
    "sg:phone":"+1 702 242 3490",
    "sg:postcode":"89014",
    "sg:province":"NV",
    "sg:tags":[
        "related"
    ],
    "wof:name":"Newcanvas Inc",
    "wof:placetype":"venue"
},
  "geometry": {"coordinates":[-115.053015,36.072048],"type":"Point"}
}