{
  "type": "Feature",
  "properties": {
    "iso:country":"US",
    "sg:address":"2615 E. Tropicana Ave.",
    "sg:city":"Las Vegas",
    "sg:classifiers":[
        {
            "category":"Banks & Credit Unions",
            "subcategory":"Financial Services",
            "type":"Services"
        }
    ],
    "sg:phone":"+1 702 898 3300",
    "sg:postcode":"89121",
    "sg:province":"NV",
    "sg:website":"www.moneytreeinc.com",
    "wof:name":"Moneytree",
    "wof:placetype":"venue"
},
  "geometry": {"coordinates":[-115.114148,36.099622],"type":"Point"}
}