{
  "type": "Feature",
  "properties": {
    "iso:country":"US",
    "sg:address":"2226 Paradise Rd",
    "sg:city":"Las Vegas",
    "sg:classifiers":[
        {
            "category":"Restaurant",
            "type":"Food & Drink"
        }
    ],
    "sg:phone":"+1 702 457 7874",
    "sg:postcode":"89104",
    "sg:province":"NV",
    "wof:name":"M & M Trading",
    "wof:placetype":"venue"
},
  "geometry": {"coordinates":[-115.153623,36.145838],"type":"Point"}
}