{
  "type": "Feature",
  "properties": {
    "iso:country":"US",
    "sg:address":"4950 W Craig Rd",
    "sg:city":"Las Vegas",
    "sg:classifiers":[
        {
            "category":"Professional",
            "subcategory":"Advertising",
            "type":"Services"
        }
    ],
    "sg:phone":"+1 702 396 9200",
    "sg:postcode":"89130",
    "sg:province":"NV",
    "sg:tags":[
        "mailing",
        "shipping"
    ],
    "wof:name":"Postnet",
    "wof:placetype":"venue"
},
  "geometry": {"coordinates":[-115.209244,36.23885],"type":"Point"}
}