{
  "type": "Feature",
  "properties": {
    "iso:country":"US",
    "sg:address":"1520 Red Rock St",
    "sg:city":"Las Vegas",
    "sg:classifiers":[
        {
            "category":"Building & Trades",
            "subcategory":"Cleaning & Sanitation",
            "type":"Services"
        }
    ],
    "sg:phone":"+1 702 880 1299",
    "sg:postcode":"89146",
    "sg:province":"NV",
    "sg:tags":[
        "maintenance"
    ],
    "wof:name":"Chiquita Janitorial Maint",
    "wof:placetype":"venue"
},
  "geometry": {"coordinates":[-115.22338499999999,36.154132],"type":"Point"}
}