{
  "type": "Feature",
  "properties": {
    "iso:country":"US",
    "sg:address":"455 California Ave",
    "sg:city":"Reno",
    "sg:classifiers":[
        {
            "category":"Insurance",
            "subcategory":"Insurance Agent",
            "type":"Services"
        }
    ],
    "sg:phone":"+1 775 323 3665",
    "sg:postcode":"89509",
    "sg:province":"NV",
    "sg:website":"www.ssibl.com",
    "wof:name":"Silver Sage Consulting",
    "wof:placetype":"venue"
},
  "geometry": {"coordinates":[-119.817122,39.520136],"type":"Point"}
}