{
  "type": "Feature",
  "properties": {
    "iso:country":"US",
    "sg:address":"1055 S Wells Ave",
    "sg:city":"Reno",
    "sg:classifiers":[
        {
            "category":"Health Services",
            "subcategory":"Doctor",
            "type":"Services"
        }
    ],
    "sg:phone":"+1 775 348 3860",
    "sg:postcode":"89502",
    "sg:province":"NV",
    "sg:tags":[
        "medical"
    ],
    "wof:name":"Paul E Dieringer MD",
    "wof:placetype":"venue"
},
  "geometry": {"coordinates":[-119.803242,39.515048],"type":"Point"}
}