{
  "type": "Feature",
  "properties": {
    "iso:country":"US",
    "sg:address":"3511 Buena Vista Dr",
    "sg:city":"Las Vegas",
    "sg:classifiers":[
        {
            "category":"Professional",
            "subcategory":"Accounting & Tax Preparation",
            "type":"Services"
        }
    ],
    "sg:phone":"+1 702 386 9318",
    "sg:postcode":"89121",
    "sg:province":"NV",
    "sg:tags":[
        "return"
    ],
    "wof:name":"Tax Solutions",
    "wof:placetype":"venue"
},
  "geometry": {"coordinates":[-115.118167,36.125234],"type":"Point"}
}