{
  "type": "Feature",
  "properties": {
    "iso:country":"US",
    "sg:address":"2228 Ramsgate Dr",
    "sg:city":"Henderson",
    "sg:classifiers":[
        {
            "category":"Professional",
            "subcategory":"Management & Consulting",
            "type":"Services"
        }
    ],
    "sg:phone":"+1 702 719 8251",
    "sg:postcode":"89074",
    "sg:province":"NV",
    "sg:tags":[
        "control",
        "builder"
    ],
    "wof:name":"C 2 LLC",
    "wof:placetype":"venue"
},
  "geometry": {"coordinates":[-115.090212,36.030923],"type":"Point"}
}