{
  "type": "Feature",
  "properties": {
    "iso:country":"US",
    "sg:address":"1620 Van Petten St",
    "sg:city":"Reno",
    "sg:classifiers":[
        {
            "category":"Building & Trades",
            "subcategory":"Landscaping Services",
            "type":"Services"
        },
        {
            "category":"Home & Garden",
            "subcategory":"Garden Supply",
            "type":"Retail Goods"
        }
    ],
    "sg:phone":"+1 775 745 3162",
    "sg:postcode":"89503",
    "sg:province":"NV",
    "sg:tags":[
        "horticulture",
        "product",
        "stump",
        "tree",
        "grinding",
        "removal",
        "arborist"
    ],
    "sg:website":"http://Treemasterservice.com",
    "wof:name":"Tree Master",
    "wof:placetype":"venue"
},
  "geometry": {"coordinates":[-119.842361,39.538514],"type":"Point"}
}