{
  "type": "Feature",
  "properties": {
    "iso:country":"US",
    "sg:address":"1310 Nevada Hwy",
    "sg:city":"Boulder City",
    "sg:classifiers":[
        {
            "category":"Personal",
            "subcategory":"Tanning Parlor",
            "type":"Services"
        }
    ],
    "sg:phone":"+1 702 294 6039",
    "sg:postcode":"89005",
    "sg:province":"NV",
    "sg:tags":[
        "salon"
    ],
    "wof:name":"Paradise Tans",
    "wof:placetype":"venue"
},
  "geometry": {"coordinates":[-114.850762,35.971307],"type":"Point"}
}