{
  "type": "Feature",
  "properties": {
    "iso:country":"US",
    "sg:address":"2750 Marion Dr",
    "sg:city":"Las Vegas",
    "sg:classifiers":[
        {
            "category":"Insurance",
            "subcategory":"Hazard Insurance",
            "type":"Services"
        }
    ],
    "sg:phone":"+1 702 641 2245",
    "sg:postcode":"89115",
    "sg:province":"NV",
    "sg:tags":[
        "bond"
    ],
    "wof:name":"A-Aalto Bail Bonds",
    "wof:placetype":"venue"
},
  "geometry": {"coordinates":[-115.071066,36.209826],"type":"Point"}
}