{
  "type": "Feature",
  "properties": {
    "iso:country":"US",
    "sg:address":"6440 Sky Pointe Dr",
    "sg:city":"Las Vegas",
    "sg:classifiers":[
        {
            "category":"Building & Trades",
            "subcategory":"Equipment Rental",
            "type":"Services"
        }
    ],
    "sg:phone":"+1 702 313 5867",
    "sg:postcode":"89131",
    "sg:province":"NV",
    "wof:name":"ABC Jump",
    "wof:placetype":"venue"
},
  "geometry": {"coordinates":[-115.263306,36.278962],"type":"Point"}
}