{
  "type": "Feature",
  "properties": {
    "iso:country":"US",
    "sg:address":"129 W Idaho St",
    "sg:city":"Elko",
    "sg:classifiers":[
        {
            "category":"Travel",
            "subcategory":"Hotels & Motels",
            "type":"Entertainment"
        }
    ],
    "sg:phone":"+1 775 738 8471",
    "sg:postcode":"89801",
    "sg:province":"NV",
    "wof:name":"Stampede Motel",
    "wof:placetype":"venue"
},
  "geometry": {"coordinates":[-115.767011,40.829212],"type":"Point"}
}