{
  "type": "Feature",
  "properties": {
    "iso:country":"US",
    "sg:address":"3110 S Durango Dr Ste 205",
    "sg:city":"Las Vegas",
    "sg:classifiers":[
        {
            "category":"Banks & Credit Unions",
            "subcategory":"Financial Services",
            "type":"Services"
        }
    ],
    "sg:phone":"+1 702 441 0770",
    "sg:postcode":"89117",
    "sg:province":"NV",
    "sg:tags":[
        "advising"
    ],
    "sg:website":"CreditGuardNevada.com",
    "wof:name":"Credit Guard, Inc.",
    "wof:placetype":"venue"
},
  "geometry": {"coordinates":[-115.278118,36.132703],"type":"Point"}
}