{
  "type": "Feature",
  "properties": {
    "iso:country":"US",
    "sg:address":"2131 Industrial Rd",
    "sg:city":"Las Vegas",
    "sg:classifiers":[
        {
            "category":"Professional",
            "subcategory":"Art Services",
            "type":"Services"
        }
    ],
    "sg:phone":"+1 702 384 7844",
    "sg:postcode":"89102",
    "sg:province":"NV",
    "sg:tags":[
        "photographer",
        "photography",
        "commercial"
    ],
    "wof:name":"Jerry Metellus Photography",
    "wof:placetype":"venue"
},
  "geometry": {"coordinates":[-115.164362,36.144795],"type":"Point"}
}