{
  "type": "Feature",
  "properties": {
    "iso:country":"US",
    "sg:address":"831 Highland Dr",
    "sg:city":"Elko",
    "sg:classifiers":[
        {
            "category":"Wholesale",
            "subcategory":"Machinery & Supplies",
            "type":"Manufacturing & Wholesale Goods"
        },
        {
            "category":"Retail",
            "subcategory":"Car Wash",
            "type":"Services"
        }
    ],
    "sg:phone":"+1 775 738 7040",
    "sg:postcode":"89801",
    "sg:province":"NV",
    "sg:tags":[
        "carwash"
    ],
    "wof:name":"Buggy Bath Car Wash The",
    "wof:placetype":"venue"
},
  "geometry": {"coordinates":[-115.775175,40.82918],"type":"Point"}
}