{
  "type": "Feature",
  "properties": {
    "iso:country":"US",
    "sg:address":"4581 W Flamingo Road",
    "sg:city":"Las Vegas",
    "sg:classifiers":[
        {
            "category":"Shopping",
            "subcategory":"Shoes",
            "type":"Retail Goods"
        }
    ],
    "sg:phone":"+1 702 227 4581",
    "sg:postcode":"89103",
    "sg:province":"NV",
    "sg:tags":[
        "store"
    ],
    "wof:name":"Bouncz Shoez Z-Coil",
    "wof:placetype":"venue"
},
  "geometry": {"coordinates":[-115.20365099999999,36.115322],"type":"Point"}
}