{
  "type": "Feature",
  "properties": {
    "iso:country":"US",
    "sg:address":"2660 S Maryland Pkwy Ste 24",
    "sg:city":"Las Vegas",
    "sg:classifiers":[
        {
            "category":"Bars & Pubs",
            "subcategory":"Nightclub",
            "type":"Food & Drink"
        }
    ],
    "sg:phone":"+1 702 737 3406",
    "sg:postcode":"89109",
    "sg:province":"NV",
    "sg:tags":[
        "nightlife"
    ],
    "wof:name":"Island Grill",
    "wof:placetype":"venue"
},
  "geometry": {"coordinates":[-115.136634,36.141224],"type":"Point"}
}