{
  "type": "Feature",
  "properties": {
    "iso:country":"US",
    "sg:address":"6625 S Valley View Blvd",
    "sg:city":"Las Vegas",
    "sg:classifiers":[
        {
            "category":"Professional",
            "subcategory":"Computer Services",
            "type":"Services"
        }
    ],
    "sg:phone":"+1 702 889 8333",
    "sg:postcode":"89118",
    "sg:province":"NV",
    "sg:tags":[
        "repair"
    ],
    "wof:name":"Accent Networks",
    "wof:placetype":"venue"
},
  "geometry": {"coordinates":[-115.19010400000001,36.069542],"type":"Point"}
}