{
  "type": "Feature",
  "properties": {
    "iso:country":"US",
    "sg:address":"556 Vine St",
    "sg:city":"Reno",
    "sg:classifiers":[
        {
            "category":"Professional",
            "subcategory":"Lawyer & Legal Services",
            "type":"Services"
        }
    ],
    "sg:phone":"+1 775 323 2000",
    "sg:postcode":"89503",
    "sg:province":"NV",
    "sg:tags":[
        "attorney"
    ],
    "wof:name":"Bonnie G Mahan LTD",
    "wof:placetype":"venue"
},
  "geometry": {"coordinates":[-119.826244,39.530771],"type":"Point"}
}