{
  "type": "Feature",
  "properties": {
    "iso:country":"US",
    "sg:address":"50 S Arrowhead Ln",
    "sg:city":"Mesquite",
    "sg:classifiers":[
        {
            "category":"Banks & Credit Unions",
            "subcategory":"Bank",
            "type":"Services"
        }
    ],
    "sg:phone":"+1 702 345 7510",
    "sg:postcode":"89027",
    "sg:province":"NV",
    "sg:tags":[
        "loan"
    ],
    "wof:name":"Courtesy Loans Inc",
    "wof:placetype":"venue"
},
  "geometry": {"coordinates":[-114.075421,36.803303],"type":"Point"}
}