{
  "type": "Feature",
  "properties": {
    "iso:country":"US",
    "sg:address":"43 Fairway Dr",
    "sg:city":"Yerington",
    "sg:classifiers":[
        {
            "category":"Real Estate",
            "subcategory":"Real Estate Agent",
            "type":"Services"
        }
    ],
    "sg:phone":"+1 775 463 2612",
    "sg:postcode":"89447",
    "sg:province":"NV",
    "wof:name":"Senior Citizens Lyon County",
    "wof:placetype":"venue"
},
  "geometry": {"coordinates":[-119.169507,38.968209],"type":"Point"}
}