{
  "type": "Feature",
  "properties": {
    "iso:country":"US",
    "sg:address":"4300 Meadows Lane Suite 10",
    "sg:city":"Las Vegas",
    "sg:classifiers":[
        {
            "category":"Shopping",
            "subcategory":"Mobile Phones",
            "type":"Retail Goods"
        }
    ],
    "sg:phone":"+1 702 878 0378",
    "sg:postcode":"89107",
    "sg:province":"NV",
    "wof:name":"Diamond Wireless",
    "wof:placetype":"venue"
},
  "geometry": {"coordinates":[-115.198629,36.170203],"type":"Point"}
}