{
  "type": "Feature",
  "properties": {
    "iso:country":"US",
    "sg:address":"2021 W Charleston Boulevard",
    "sg:city":"Las Vegas",
    "sg:classifiers":[
        {
            "category":"Shopping",
            "subcategory":"Florist",
            "type":"Retail Goods"
        }
    ],
    "sg:phone":"+1 702 384 1121",
    "sg:postcode":"89102",
    "sg:province":"NV",
    "sg:website":"www.dibellaflowers.com",
    "wof:name":"Dibella Flowers & Gifts",
    "wof:placetype":"venue"
},
  "geometry": {"coordinates":[-115.168999,36.158798],"type":"Point"}
}