{
  "type": "Feature",
  "properties": {
    "iso:country":"US",
    "sg:address":"10407 Abisso Dr",
    "sg:city":"Las Vegas",
    "sg:classifiers":[
        {
            "category":"Real Estate",
            "subcategory":"Real Estate Agent",
            "type":"Services"
        }
    ],
    "sg:phone":"+1 702 892 0356",
    "sg:postcode":"89135",
    "sg:province":"NV",
    "sg:tags":[
        "appraiser"
    ],
    "wof:name":"Atkins Appraisals",
    "wof:placetype":"venue"
},
  "geometry": {"coordinates":[-115.320602,36.100303],"type":"Point"}
}