{
  "type": "Feature",
  "properties": {
    "iso:country":"US",
    "sg:address":"17790 W Aspen Cir",
    "sg:city":"Reno",
    "sg:classifiers":[
        {
            "category":"Manufacturing",
            "subcategory":"Leather Goods",
            "type":"Manufacturing & Wholesale Goods"
        }
    ],
    "sg:phone":"+1 775 972 4004",
    "sg:postcode":"89508",
    "sg:province":"NV",
    "sg:tags":[
        "repair",
        "make",
        "tack",
        "horse"
    ],
    "wof:name":"Customs Saddlery Plus",
    "wof:placetype":"venue"
},
  "geometry": {"coordinates":[-119.990585,39.672996],"type":"Point"}
}