{
  "type": "Feature",
  "properties": {
    "iso:country":"US",
    "sg:address":"6000 S Eastern Ave",
    "sg:city":"Las Vegas",
    "sg:classifiers":[
        {
            "category":"Retail",
            "subcategory":"Laundry & Dry Cleaning",
            "type":"Services"
        }
    ],
    "sg:phone":"+1 702 896 3934",
    "sg:postcode":"89119",
    "sg:province":"NV",
    "sg:tags":[
        "cleaners",
        "rug",
        "carpet"
    ],
    "wof:name":"Mad Bob's",
    "wof:placetype":"venue"
},
  "geometry": {"coordinates":[-115.118706,36.081757],"type":"Point"}
}