{
  "type": "Feature",
  "properties": {
    "iso:country":"US",
    "sg:address":"7920 Tropical Pkwy Ste 170",
    "sg:city":"Las Vegas",
    "sg:classifiers":[
        {
            "category":"Restaurant",
            "type":"Food & Drink"
        }
    ],
    "sg:phone":"+1 702 396 0070",
    "sg:postcode":"89149",
    "sg:province":"NV",
    "sg:tags":[
        "greek"
    ],
    "sg:website":"www.marketgrillecafe.com",
    "wof:name":"Market Grille Cafe",
    "wof:placetype":"venue"
},
  "geometry": {"coordinates":[-115.267616,36.270902],"type":"Point"}
}