{
  "type": "Feature",
  "properties": {
    "iso:country":"US",
    "sg:address":"6255 Sharlands Ave",
    "sg:city":"Reno",
    "sg:classifiers":[
        {
            "category":"Restaurant",
            "type":"Food & Drink"
        }
    ],
    "sg:menulink":"http://www.allmenus.com/nv/reno-north/87908-zpizza/menu/",
    "sg:phone":"+1 775 787 9999",
    "sg:postcode":"89523",
    "sg:province":"NV",
    "sg:tags":[
        "american",
        "pizza"
    ],
    "wof:name":"Zpizza",
    "wof:placetype":"venue"
},
  "geometry": {"coordinates":[-119.887306,39.518737],"type":"Point"}
}