{
  "type": "Feature",
  "properties": {
    "iso:country":"US",
    "sg:address":"3326 Valley Ln",
    "sg:city":"Las Vegas",
    "sg:classifiers":[
        {
            "category":"Health Services",
            "subcategory":"Medical Lab",
            "type":"Services"
        }
    ],
    "sg:phone":"+1 702 227 0507",
    "sg:postcode":"89106",
    "sg:province":"NV",
    "sg:tags":[
        "laboratory",
        "dental"
    ],
    "wof:name":"Aztech Dental Lab",
    "wof:placetype":"venue"
},
  "geometry": {"coordinates":[-115.183779,36.193361],"type":"Point"}
}