{
  "type": "Feature",
  "properties": {
    "iso:country":"US",
    "sg:address":"3475 Las Vegas Blvd S",
    "sg:city":"Las Vegas",
    "sg:classifiers":[
        {
            "category":"Shopping",
            "subcategory":"Gifts & Souvenirs",
            "type":"Retail Goods"
        }
    ],
    "sg:phone":"+1 702 735 4977",
    "sg:postcode":"89109",
    "sg:province":"NV",
    "wof:name":"Maui Magnets",
    "wof:placetype":"venue"
},
  "geometry": {"coordinates":[-115.17154,36.12201],"type":"Point"}
}