{
  "type": "Feature",
  "properties": {
    "iso:country":"US",
    "sg:address":"3000 Paradise Rd",
    "sg:city":"Las Vegas",
    "sg:classifiers":[
        {
            "category":"Restaurant",
            "type":"Food & Drink"
        }
    ],
    "sg:phone":"+1 702 732 5755",
    "sg:postcode":"89109",
    "sg:province":"NV",
    "sg:tags":[
        "chinese"
    ],
    "wof:name":"Garden of the Dragon",
    "wof:placetype":"venue"
},
  "geometry": {"coordinates":[-115.151887,36.135782],"type":"Point"}
}