{
  "type": "Feature",
  "properties": {
    "iso:country":"US",
    "sg:address":"7441 W Lake Mead Blvd",
    "sg:city":"Las Vegas",
    "sg:classifiers":[
        {
            "category":"Retail",
            "subcategory":"Auto Rental",
            "type":"Services"
        }
    ],
    "sg:phone":"+1 702 254 0770",
    "sg:postcode":"89128",
    "sg:province":"NV",
    "sg:tags":[
        "recreational",
        "leasing",
        "vehicle"
    ],
    "sg:website":"www.rvn4fun.com",
    "wof:name":"RVN 4 Fun",
    "wof:placetype":"venue"
},
  "geometry": {"coordinates":[-115.256102,36.196033],"type":"Point"}
}