{
  "type": "Feature",
  "properties": {
    "iso:country":"US",
    "sg:address":"595 W Lake Mead Pkwy",
    "sg:city":"Henderson",
    "sg:classifiers":[
        {
            "category":"Health Services",
            "subcategory":"Doctor",
            "type":"Services"
        }
    ],
    "sg:phone":"+1 702 566 5500",
    "sg:postcode":"89015",
    "sg:province":"NV",
    "sg:tags":[
        "practice",
        "family"
    ],
    "wof:name":"Sampang Virginia MD",
    "wof:placetype":"venue"
},
  "geometry": {"coordinates":[-115.000072,36.035099],"type":"Point"}
}