{
  "type": "Feature",
  "properties": {
    "iso:country":"US",
    "sg:address":"2372 Pickwick Dr",
    "sg:city":"Henderson",
    "sg:classifiers":[
        {
            "category":"Professional",
            "subcategory":"Business Services",
            "type":"Services"
        }
    ],
    "sg:phone":"+1 702 454 1020",
    "sg:postcode":"89014",
    "sg:province":"NV",
    "sg:tags":[
        "interior",
        "consultant",
        "design",
        "decorator"
    ],
    "wof:name":"Slatoff & Assoc",
    "wof:placetype":"venue"
},
  "geometry": {"coordinates":[-115.082611,36.064756],"type":"Point"}
}