{
  "type": "Feature",
  "properties": {
    "iso:country":"US",
    "sg:address":"2914 Vegas Valley Dr",
    "sg:city":"Las Vegas",
    "sg:classifiers":[
        {
            "category":"Social Services",
            "subcategory":"Child Care",
            "type":"Services"
        }
    ],
    "sg:phone":"+1 702 457 5520",
    "sg:postcode":"89121",
    "sg:province":"NV",
    "sg:tags":[
        "day"
    ],
    "wof:name":"Reinharts Day Care Center",
    "wof:placetype":"venue"
},
  "geometry": {"coordinates":[-115.112797,36.137114],"type":"Point"}
}