{
  "type": "Feature",
  "properties": {
    "iso:country":"US",
    "sg:address":"417 Copper Valley Ct",
    "sg:city":"Las Vegas",
    "sg:classifiers":[
        {
            "category":"Professional",
            "subcategory":"Business Services",
            "type":"Services"
        }
    ],
    "sg:phone":"+1 702 248 1800",
    "sg:postcode":"89144",
    "sg:province":"NV",
    "wof:name":"Pipe Line Entertainment",
    "wof:placetype":"venue"
},
  "geometry": {"coordinates":[-115.32986,36.17863],"type":"Point"}
}