{
  "type": "Feature",
  "properties": {
    "iso:country":"US",
    "sg:address":"1055 Glendale Ave",
    "sg:city":"Sparks",
    "sg:classifiers":[
        {
            "category":"Building & Trades",
            "subcategory":"Landscaping Services",
            "type":"Services"
        }
    ],
    "sg:phone":"+1 775 355 0305",
    "sg:postcode":"89431",
    "sg:province":"NV",
    "sg:tags":[
        "material"
    ],
    "wof:name":"Empire Hardscape Supply",
    "wof:placetype":"venue"
},
  "geometry": {"coordinates":[-119.75500599999999,39.52752],"type":"Point"}
}