{
  "type": "Feature",
  "properties": {
    "iso:country":"US",
    "sg:address":"5225 S Valley View Blvd",
    "sg:city":"Las Vegas",
    "sg:classifiers":[
        {
            "category":"Wholesale",
            "subcategory":"Construction Materials",
            "type":"Manufacturing & Wholesale Goods"
        },
        {
            "category":"Building & Trades",
            "subcategory":"Construction",
            "type":"Services"
        }
    ],
    "sg:phone":"+1 702 798 5911",
    "sg:postcode":"89118",
    "sg:province":"NV",
    "sg:tags":[
        "garage",
        "cabinet",
        "retail",
        "maker",
        "mfg"
    ],
    "wof:name":"Nevada Garage Cabinets Inc",
    "wof:placetype":"venue"
},
  "geometry": {"coordinates":[-115.189914,36.094057],"type":"Point"}
}