{
  "type": "Feature",
  "properties": {
    "iso:country":"US",
    "sg:address":"9850 Granite Reef Ave",
    "sg:city":"Las Vegas",
    "sg:classifiers":[
        {
            "category":"Shopping",
            "type":"Retail Goods"
        }
    ],
    "sg:phone":"+1 702 254 4367",
    "sg:postcode":"89147",
    "sg:province":"NV",
    "sg:tags":[
        "electronics",
        "merchandise"
    ],
    "sg:website":"www.sounddistributors.com",
    "wof:name":"Sound Distributors",
    "wof:placetype":"venue"
},
  "geometry": {"coordinates":[-115.306999,36.1194],"type":"Point"}
}