{
  "type": "Feature",
  "properties": {
    "iso:country":"US",
    "sg:address":"900 N Roop St",
    "sg:city":"Carson City",
    "sg:classifiers":[
        {
            "category":"Education",
            "subcategory":"Library",
            "type":"Public Place"
        }
    ],
    "sg:phone":"+1 775 887 2244",
    "sg:postcode":"89701",
    "sg:province":"NV",
    "sg:website":"www.clan.lib.nv.us",
    "wof:name":"Carson City Public Library",
    "wof:placetype":"venue"
},
  "geometry": {"coordinates":[-119.76107,39.168957],"type":"Point"}
}