{
  "type": "Feature",
  "properties": {
    "iso:country":"US",
    "sg:address":"32100 Las Vegas Blvd S",
    "sg:city":"Jean",
    "sg:classifiers":[
        {
            "category":"Restaurant",
            "type":"Food & Drink"
        }
    ],
    "sg:menulink":"http://www.allmenus.com/nv/clark/240369-panda-express/menu/",
    "sg:phone":"+1 702 874 2268",
    "sg:postcode":"89019",
    "sg:province":"NV",
    "sg:tags":[
        "asian",
        "chinese"
    ],
    "wof:name":"Panda Express",
    "wof:placetype":"venue"
},
  "geometry": {"coordinates":[-115.38618200000001,35.60969],"type":"Point"}
}