{
  "type": "Feature",
  "properties": {
    "iso:country":"US",
    "sg:address":"2710 Wind Feather Trl",
    "sg:city":"Reno",
    "sg:classifiers":[
        {
            "category":"Mining & Drilling",
            "type":"Manufacturing & Wholesale Goods"
        }
    ],
    "sg:phone":"+1 775 852 5587",
    "sg:postcode":"89511",
    "sg:province":"NV",
    "sg:tags":[
        "oil",
        "gas",
        "producer"
    ],
    "wof:name":"Baldwin Exploration",
    "wof:placetype":"venue"
},
  "geometry": {"coordinates":[-119.805072,39.409734],"type":"Point"}
}