{
  "type": "Feature",
  "properties": {
    "iso:country":"US",
    "sg:address":"7924 March Brown Ave",
    "sg:city":"Las Vegas",
    "sg:classifiers":[
        {
            "category":"Professional",
            "subcategory":"Business Services",
            "type":"Services"
        }
    ],
    "sg:phone":"+1 702 633 4162",
    "sg:postcode":"89149",
    "sg:province":"NV",
    "wof:name":"Structure Exhibit & Event Mgmt",
    "wof:placetype":"venue"
},
  "geometry": {"coordinates":[-115.266248,36.268501],"type":"Point"}
}