{
  "type": "Feature",
  "properties": {
    "iso:country":"US",
    "sg:address":"55 E Grove St",
    "sg:city":"Reno",
    "sg:classifiers":[
        {
            "category":"Professional",
            "subcategory":"Business Services",
            "type":"Services"
        }
    ],
    "sg:phone":"+1 775 828 4225",
    "sg:postcode":"89502",
    "sg:province":"NV",
    "sg:tags":[
        "liquidator"
    ],
    "wof:name":"You'Ll Go Bananas",
    "wof:placetype":"venue"
},
  "geometry": {"coordinates":[-119.799483,39.501021],"type":"Point"}
}