{
  "type": "Feature",
  "properties": {
    "iso:country":"US",
    "sg:address":"3250 Sun Cloud Ct",
    "sg:city":"Reno",
    "sg:classifiers":[
        {
            "category":"Building & Trades",
            "subcategory":"Construction",
            "type":"Services"
        }
    ],
    "sg:phone":"+1 775 972 7231",
    "sg:postcode":"89506",
    "sg:province":"NV",
    "sg:tags":[
        "general",
        "commercial",
        "contractor"
    ],
    "wof:name":"Green Builders Inc",
    "wof:placetype":"venue"
},
  "geometry": {"coordinates":[-119.82005599999999,39.60974],"type":"Point"}
}