{
  "type": "Feature",
  "properties": {
    "iso:country":"US",
    "sg:address":"1605 Hinckley Ave",
    "sg:city":"Logandale",
    "sg:classifiers":[
        {
            "category":"Organizations",
            "subcategory":"Religious Organization",
            "type":"Services"
        }
    ],
    "sg:phone":"+1 702 398 3302",
    "sg:postcode":"89021",
    "sg:province":"NV",
    "sg:tags":[
        "church"
    ],
    "wof:name":"Church Of Jesus Christ Of Lds",
    "wof:placetype":"venue"
},
  "geometry": {"coordinates":[-114.47599700000001,36.587938],"type":"Point"}
}