{
  "type": "Feature",
  "properties": {
    "iso:country":"US",
    "sg:address":"8363 W Sunset Road Suite 340",
    "sg:city":"Las Vegas",
    "sg:classifiers":[
        {
            "category":"Professional",
            "subcategory":"Lawyer & Legal Services",
            "type":"Services"
        }
    ],
    "sg:phone":"+1 702 838 8500",
    "sg:postcode":"89113",
    "sg:province":"NV",
    "sg:tags":[
        "personal",
        "injury"
    ],
    "wof:name":"White Meany & Wetherrall Llp",
    "wof:placetype":"venue"
},
  "geometry": {"coordinates":[-115.273878,36.070322],"type":"Point"}
}