{
  "type": "Feature",
  "properties": {
    "iso:country":"US",
    "sg:address":"3680 S. Maryland Pkwy",
    "sg:city":"Las Vegas",
    "sg:classifiers":[
        {
            "category":"Shopping",
            "subcategory":"Clothing, Apparel, & Fashions",
            "type":"Retail Goods"
        }
    ],
    "sg:phone":"+1 702 693 4999",
    "sg:postcode":"89109",
    "sg:province":"NV",
    "sg:tags":[
        "clothing",
        "women's"
    ],
    "sg:website":"www.forever21.com",
    "wof:name":"Forever 21",
    "wof:placetype":"venue"
},
  "geometry": {"coordinates":[-115.137254,36.12257],"type":"Point"}
}