{
  "type": "Feature",
  "properties": {
    "iso:country":"US",
    "sg:address":"2538 Anthem Village Dr",
    "sg:city":"Henderson",
    "sg:classifiers":[
        {
            "category":"Health Services",
            "subcategory":"Doctor",
            "type":"Services"
        }
    ],
    "sg:phone":"+1 702 897 5560",
    "sg:postcode":"89052",
    "sg:province":"NV",
    "sg:tags":[
        "dentist"
    ],
    "wof:name":"Southwest Dental & Dentures",
    "wof:placetype":"venue"
},
  "geometry": {"coordinates":[-115.098416,35.979643],"type":"Point"}
}