{
  "type": "Feature",
  "properties": {
    "iso:country":"US",
    "sg:address":"7441 W Lake Mead Blvd",
    "sg:city":"Las Vegas",
    "sg:classifiers":[
        {
            "category":"Building & Trades",
            "subcategory":"Construction",
            "type":"Services"
        }
    ],
    "sg:phone":"+1 702 341 9677",
    "sg:postcode":"89128",
    "sg:province":"NV",
    "sg:tags":[
        "contractor"
    ],
    "wof:name":"Glassy Business Window Tinting",
    "wof:placetype":"venue"
},
  "geometry": {"coordinates":[-115.256102,36.196033],"type":"Point"}
}