{
  "type": "Feature",
  "properties": {
    "iso:country":"US",
    "sg:address":"851 E Fifth St",
    "sg:city":"Carson City",
    "sg:classifiers":[
        {
            "category":"Professional",
            "subcategory":"Lawyer & Legal Services",
            "type":"Services"
        }
    ],
    "sg:phone":"+1 775 882 5545",
    "sg:postcode":"89701",
    "sg:province":"NV",
    "wof:name":"Wilson Steven A",
    "wof:placetype":"venue"
},
  "geometry": {"coordinates":[-119.761002,39.1614],"type":"Point"}
}