{
  "type": "Feature",
  "properties": {
    "iso:country":"US",
    "sg:address":"8480 Farm Rd",
    "sg:city":"Las Vegas",
    "sg:classifiers":[
        {
            "category":"Restaurant",
            "type":"Food & Drink"
        }
    ],
    "sg:phone":"+1 702 839 0359",
    "sg:postcode":"89131",
    "sg:province":"NV",
    "wof:name":"Mc Donald's",
    "wof:placetype":"venue"
},
  "geometry": {"coordinates":[-115.27914199999999,36.299237],"type":"Point"}
}