{
  "type": "Feature",
  "properties": {
    "iso:country":"US",
    "sg:address":"5410 Regal Peak Dr",
    "sg:city":"Las Vegas",
    "sg:classifiers":[
        {
            "category":"Professional",
            "subcategory":"Secretarial Services",
            "type":"Services"
        }
    ],
    "sg:phone":"+1 702 363 0234",
    "sg:postcode":"89118",
    "sg:province":"NV",
    "sg:tags":[
        "reporting",
        "business"
    ],
    "wof:name":"Access One Grant Writing",
    "wof:placetype":"venue"
},
  "geometry": {"coordinates":[-115.23548,36.09016],"type":"Point"}
}