{
  "type": "Feature",
  "properties": {
    "iso:country":"US",
    "sg:address":"888 del Sol Dr",
    "sg:city":"Boulder City",
    "sg:classifiers":[
        {
            "category":"Real Estate",
            "subcategory":"Real Estate Operator",
            "type":"Services"
        }
    ],
    "sg:phone":"+1 702 293 2206",
    "sg:postcode":"89005",
    "sg:province":"NV",
    "sg:tags":[
        "apartment"
    ],
    "wof:name":"M & M Apartments",
    "wof:placetype":"venue"
},
  "geometry": {"coordinates":[-114.84448999999999,35.970026],"type":"Point"}
}