{
  "type": "Feature",
  "properties": {
    "iso:country":"US",
    "sg:address":"76 Mountain Ln",
    "sg:city":"Yerington",
    "sg:classifiers":[
        {
            "category":"Real Estate",
            "subcategory":"Real Estate Agent",
            "type":"Services"
        }
    ],
    "sg:phone":"+1 775 463 3072",
    "sg:postcode":"89447",
    "sg:province":"NV",
    "wof:name":"Specialized RE Projects",
    "wof:placetype":"venue"
},
  "geometry": {"coordinates":[-119.061758,39.00721],"type":"Point"}
}