{
  "type": "Feature",
  "properties": {
    "iso:country":"US",
    "sg:address":"4831 S Torrey Pines Dr",
    "sg:city":"Las Vegas",
    "sg:classifiers":[
        {
            "category":"Home & Garden",
            "subcategory":"Furniture",
            "type":"Retail Goods"
        }
    ],
    "sg:phone":"+1 702 251 4694",
    "sg:postcode":"89103",
    "sg:province":"NV",
    "wof:name":"Systems Seating & Solutions",
    "wof:placetype":"venue"
},
  "geometry": {"coordinates":[-115.23409700000001,36.100588],"type":"Point"}
}