{
  "type": "Feature",
  "properties": {
    "iso:country":"US",
    "sg:address":"228 Barite St",
    "sg:city":"Elko",
    "sg:classifiers":[
        {
            "category":"Retail",
            "subcategory":"Laundry & Dry Cleaning",
            "type":"Services"
        }
    ],
    "sg:phone":"+1 775 777 1079",
    "sg:postcode":"89801",
    "sg:province":"NV",
    "wof:name":"B Z Carpet Cleaning",
    "wof:placetype":"venue"
},
  "geometry": {"coordinates":[-115.788916,40.846504],"type":"Point"}
}