{
  "type": "Feature",
  "properties": {
    "iso:country":"US",
    "sg:address":"1380 Greg St",
    "sg:city":"Sparks",
    "sg:classifiers":[
        {
            "category":"Banks & Credit Unions",
            "subcategory":"Bank",
            "type":"Services"
        }
    ],
    "sg:phone":"+1 775 331 3777",
    "sg:postcode":"89431",
    "sg:province":"NV",
    "sg:tags":[
        "mortgage"
    ],
    "wof:name":"River City Mortgage",
    "wof:placetype":"venue"
},
  "geometry": {"coordinates":[-119.761818,39.523463],"type":"Point"}
}