{
  "type": "Feature",
  "properties": {
    "iso:country":"US",
    "sg:address":"4830 Heron Rd",
    "sg:city":"Carson City",
    "sg:classifiers":[
        {
            "category":"Bars & Pubs",
            "type":"Food & Drink"
        }
    ],
    "sg:phone":"+1 775 885 7583",
    "sg:postcode":"89701",
    "sg:province":"NV",
    "sg:tags":[
        "drinking",
        "eating"
    ],
    "wof:name":"For The Good Times",
    "wof:placetype":"venue"
},
  "geometry": {"coordinates":[-119.713071,39.160463],"type":"Point"}
}