{
  "type": "Feature",
  "properties": {
    "iso:country":"US",
    "sg:address":"7936 W Sahara Ave",
    "sg:city":"Las Vegas",
    "sg:classifiers":[
        {
            "category":"Professional",
            "subcategory":"Research",
            "type":"Services"
        }
    ],
    "sg:phone":"+1 702 853 1300",
    "sg:postcode":"89117",
    "sg:province":"NV",
    "sg:tags":[
        "market",
        "analysis"
    ],
    "wof:name":"Strategic Surveys Inc",
    "wof:placetype":"venue"
},
  "geometry": {"coordinates":[-115.264565,36.143842],"type":"Point"}
}