{
  "type": "Feature",
  "properties": {
    "iso:country":"US",
    "sg:address":"698 W 4th St",
    "sg:city":"Winnemucca",
    "sg:classifiers":[
        {
            "category":"Building & Trades",
            "subcategory":"Cleaning & Sanitation",
            "type":"Services"
        }
    ],
    "sg:phone":"+1 775 623 2863",
    "sg:postcode":"89445",
    "sg:province":"NV",
    "sg:tags":[
        "janitor"
    ],
    "wof:name":"Quality Janitorial",
    "wof:placetype":"venue"
},
  "geometry": {"coordinates":[-117.740051,40.967692],"type":"Point"}
}