{
  "type": "Feature",
  "properties": {
    "iso:country":"US",
    "sg:address":"5508 Crimson Ridge Dr",
    "sg:city":"Las Vegas",
    "sg:classifiers":[
        {
            "category":"Arts & Performance",
            "subcategory":"Theater",
            "type":"Entertainment"
        }
    ],
    "sg:phone":"+1 702 592 2664",
    "sg:postcode":"89130",
    "sg:province":"NV",
    "sg:tags":[
        "entertainer"
    ],
    "wof:name":"Just Between Us",
    "wof:placetype":"venue"
},
  "geometry": {"coordinates":[-115.217697,36.245308],"type":"Point"}
}