{
  "type": "Feature",
  "properties": {
    "iso:country":"US",
    "sg:address":"6526 Larchwood Ln",
    "sg:city":"Las Vegas",
    "sg:classifiers":[
        {
            "category":"Insurance",
            "subcategory":"Hazard Insurance",
            "type":"Services"
        }
    ],
    "sg:phone":"+1 702 248 6384",
    "sg:postcode":"89103",
    "sg:province":"NV",
    "sg:tags":[
        "carrier",
        "surety"
    ],
    "wof:name":"Agency In Shawa Insurance",
    "wof:placetype":"venue"
},
  "geometry": {"coordinates":[-115.235482,36.125203],"type":"Point"}
}