{
  "type": "Feature",
  "properties": {
    "iso:country":"US",
    "sg:address":"900 N Green Valley Pkwy",
    "sg:city":"Henderson",
    "sg:classifiers":[
        {
            "category":"Banks & Credit Unions",
            "subcategory":"Bank",
            "type":"Services"
        }
    ],
    "sg:phone":"+1 702 952 7530",
    "sg:postcode":"89074",
    "sg:province":"NV",
    "wof:name":"Wells Fargo Bank Nevada Na",
    "wof:placetype":"venue"
},
  "geometry": {"coordinates":[-115.085999,36.027802],"type":"Point"}
}