{
  "type": "Feature",
  "properties": {
    "iso:country":"US",
    "sg:address":"3000 W Ann Road",
    "sg:city":"North Las Vegas",
    "sg:classifiers":[
        {
            "category":"Personal",
            "subcategory":"Nail Salon",
            "type":"Services"
        }
    ],
    "sg:phone":"+1 702 656 6555",
    "sg:postcode":"89031",
    "sg:province":"NV",
    "wof:name":"Slick Nails",
    "wof:placetype":"venue"
},
  "geometry": {"coordinates":[-115.181624,36.261674],"type":"Point"}
}