{
  "type": "Feature",
  "properties": {
    "iso:country":"US",
    "sg:address":"401 Leighann Rd",
    "sg:city":"Henderson",
    "sg:classifiers":[
        {
            "category":"Building & Trades",
            "subcategory":"Construction",
            "type":"Services"
        }
    ],
    "sg:phone":"+1 702 564 2486",
    "sg:postcode":"89015",
    "sg:province":"NV",
    "sg:tags":[
        "contractor"
    ],
    "wof:name":"Ruby Masonry",
    "wof:placetype":"venue"
},
  "geometry": {"coordinates":[-114.999369,36.025696],"type":"Point"}
}