{
  "type": "Feature",
  "properties": {
    "iso:country":"US",
    "sg:address":"859 Northside Dr",
    "sg:city":"Elko",
    "sg:classifiers":[
        {
            "category":"Building & Trades",
            "subcategory":"Electrical",
            "type":"Services"
        }
    ],
    "sg:phone":"+1 775 738 5228",
    "sg:postcode":"89801",
    "sg:province":"NV",
    "sg:tags":[
        "electrical",
        "refrigeration",
        "contractor"
    ],
    "wof:name":"Control-Tech Rfrgn & Elc Co",
    "wof:placetype":"venue"
},
  "geometry": {"coordinates":[-115.778855,40.835018],"type":"Point"}
}