{
  "type": "Feature",
  "properties": {
    "iso:country":"US",
    "sg:address":"730 W 4th St",
    "sg:city":"Reno",
    "sg:classifiers":[
        {
            "category":"Autos & Motor Vehicles",
            "subcategory":"Auto Supplies",
            "type":"Retail Goods"
        }
    ],
    "sg:phone":"+1 775 329 1106",
    "sg:postcode":"89503",
    "sg:province":"NV",
    "wof:name":"Rays Tire Exchange Inc",
    "wof:placetype":"venue"
},
  "geometry": {"coordinates":[-119.82485800000001,39.527819],"type":"Point"}
}