{
  "type": "Feature",
  "properties": {
    "iso:country":"US",
    "sg:address":"200 N Royal Ascot Dr",
    "sg:city":"Las Vegas",
    "sg:classifiers":[
        {
            "category":"Manufacturing",
            "subcategory":"Electronics",
            "type":"Manufacturing & Wholesale Goods"
        }
    ],
    "sg:phone":"+1 702 804 7850",
    "sg:postcode":"89144",
    "sg:province":"NV",
    "sg:tags":[
        "mfg"
    ],
    "wof:name":"Horizon Dynamics Corp",
    "wof:placetype":"venue"
},
  "geometry": {"coordinates":[-115.31860399999999,36.174779],"type":"Point"}
}