{
  "type": "Feature",
  "properties": {
    "iso:country":"US",
    "sg:address":"214 Red Horizon Ter",
    "sg:city":"Henderson",
    "sg:classifiers":[
        {
            "category":"Professional",
            "subcategory":"Business Services",
            "type":"Services"
        }
    ],
    "sg:phone":"+1 702 568 0591",
    "sg:postcode":"89015",
    "sg:province":"NV",
    "wof:name":"Henderson Pool Service",
    "wof:placetype":"venue"
},
  "geometry": {"coordinates":[-114.950367,36.045879],"type":"Point"}
}