{
  "type": "Feature",
  "properties": {
    "iso:country":"US",
    "sg:address":"25 Heppner Dr",
    "sg:city":"Carson City",
    "sg:classifiers":[
        {
            "category":"Recreation",
            "type":"Entertainment"
        }
    ],
    "sg:phone":"+1 775 771 4175",
    "sg:postcode":"89706",
    "sg:province":"NV",
    "sg:tags":[
        "repair"
    ],
    "wof:name":"Highland Balloon Repair",
    "wof:placetype":"venue"
},
  "geometry": {"coordinates":[-119.654978,39.227967],"type":"Point"}
}