{
  "type": "Feature",
  "properties": {
    "iso:country":"US",
    "sg:address":"1005 Greg St",
    "sg:city":"Sparks",
    "sg:classifiers":[
        {
            "category":"Wholesale",
            "subcategory":"Electrical",
            "type":"Manufacturing & Wholesale Goods"
        }
    ],
    "sg:phone":"+1 775 358 1150",
    "sg:postcode":"89431",
    "sg:province":"NV",
    "sg:tags":[
        "appliance"
    ],
    "wof:name":"GE",
    "wof:placetype":"venue"
},
  "geometry": {"coordinates":[-119.756758,39.522625],"type":"Point"}
}