{
  "type": "Feature",
  "properties": {
    "iso:country":"US",
    "sg:address":"1039 Aspen Valley Ave",
    "sg:city":"Las Vegas",
    "sg:classifiers":[
        {
            "category":"Professional",
            "subcategory":"Business Services",
            "type":"Services"
        }
    ],
    "sg:phone":"+1 702 357 9266",
    "sg:postcode":"89123",
    "sg:province":"NV",
    "sg:tags":[
        "law",
        "paralegal",
        "family"
    ],
    "wof:name":"A Paralegal Solution",
    "wof:placetype":"venue"
},
  "geometry": {"coordinates":[-115.139677,36.021714],"type":"Point"}
}