{
  "type": "Feature",
  "properties": {
    "iso:country":"US",
    "sg:address":"1501 E Calvada Blvd",
    "sg:city":"Pahrump",
    "sg:classifiers":[
        {
            "category":"Government",
            "subcategory":"Office",
            "type":"Public Place"
        }
    ],
    "sg:phone":"+1 775 727 6060",
    "sg:postcode":"89048",
    "sg:province":"NV",
    "sg:tags":[
        "medical",
        "center"
    ],
    "wof:name":"Pahrump Medical Center",
    "wof:placetype":"venue"
},
  "geometry": {"coordinates":[-115.992797,36.19198],"type":"Point"}
}