{
  "type": "Feature",
  "properties": {
    "iso:country":"US",
    "sg:address":"5000 West Charleston Boulevard",
    "sg:city":"Las Vegas",
    "sg:classifiers":[
        {
            "category":"Building & Trades",
            "subcategory":"Plumbing",
            "type":"Services"
        },
        {
            "category":"Building & Trades",
            "subcategory":"Construction",
            "type":"Services"
        }
    ],
    "sg:phone":"+1 702 228 2332",
    "sg:postcode":"89138",
    "sg:province":"NV",
    "sg:tags":[
        "contractor"
    ],
    "sg:website":"www.myvegashandyman.com",
    "wof:name":"My Vegas Handyman",
    "wof:placetype":"venue"
},
  "geometry": {"coordinates":[-115.208669,36.159583],"type":"Point"}
}