{
  "type": "Feature",
  "properties": {
    "iso:country":"US",
    "sg:address":"4700 W Rochelle Ave",
    "sg:city":"Las Vegas",
    "sg:classifiers":[
        {
            "category":"Professional",
            "type":"Services"
        }
    ],
    "sg:phone":"+1 702 222 9544",
    "sg:postcode":"89103",
    "sg:province":"NV",
    "sg:tags":[
        "editorial"
    ],
    "wof:name":"Perfectedit",
    "wof:placetype":"venue"
},
  "geometry": {"coordinates":[-115.20679,36.111861],"type":"Point"}
}