{
  "type": "Feature",
  "properties": {
    "iso:country":"US",
    "sg:address":"8615 W Flamingo Road",
    "sg:city":"Las Vegas",
    "sg:classifiers":[
        {
            "category":"Autos & Motor Vehicles",
            "subcategory":"Fuel & Gas Station",
            "type":"Retail Goods"
        }
    ],
    "sg:phone":"+1 702 367 3933",
    "sg:postcode":"89147",
    "sg:province":"NV",
    "wof:name":"Flamingo Stop",
    "wof:placetype":"venue"
},
  "geometry": {"coordinates":[-115.279738,36.114746],"type":"Point"}
}