{
  "type": "Feature",
  "properties": {
    "iso:country":"US",
    "sg:address":"1325 Arizona St",
    "sg:city":"Boulder City",
    "sg:classifiers":[
        {
            "category":"Real Estate",
            "subcategory":"Real Estate Agent",
            "type":"Services"
        }
    ],
    "sg:phone":"+1 702 293 6014",
    "sg:postcode":"89005",
    "sg:province":"NV",
    "wof:name":"Hyde & Assoc Licensed Real Est",
    "wof:placetype":"venue"
},
  "geometry": {"coordinates":[-114.83656,35.978031],"type":"Point"}
}