{
  "type": "Feature",
  "properties": {
    "iso:country":"US",
    "sg:address":"7501 W Lake Mead Boulevard Suite 100",
    "sg:city":"Las Vegas",
    "sg:classifiers":[
        {
            "category":"Restaurant",
            "type":"Food & Drink"
        }
    ],
    "sg:phone":"+1 702 838 4100",
    "sg:postcode":"89128",
    "sg:province":"NV",
    "sg:tags":[
        "mexican"
    ],
    "sg:website":"www.bajafresh.com",
    "wof:name":"Baja Fresh Mexican Grill",
    "wof:placetype":"venue"
},
  "geometry": {"coordinates":[-115.25694,36.196034],"type":"Point"}
}