{
  "type": "Feature",
  "properties": {
    "iso:country":"US",
    "sg:address":"350 Greg St",
    "sg:city":"Sparks",
    "sg:classifiers":[
        {
            "category":"Home & Garden",
            "subcategory":"Building Materials",
            "type":"Retail Goods"
        }
    ],
    "sg:phone":"+1 775 356 1523",
    "sg:postcode":"89431",
    "sg:province":"NV",
    "sg:tags":[
        "glass",
        "window",
        "plate"
    ],
    "wof:name":"J & L Windows Inc",
    "wof:placetype":"venue"
},
  "geometry": {"coordinates":[-119.745454,39.521758],"type":"Point"}
}