{
  "type": "Feature",
  "properties": {
    "iso:country":"US",
    "sg:address":"1310 S Casino Center Blvd",
    "sg:city":"Las Vegas",
    "sg:classifiers":[
        {
            "category":"Professional",
            "subcategory":"Business Services",
            "type":"Services"
        }
    ],
    "sg:phone":"+1 702 384 4202",
    "sg:postcode":"89104",
    "sg:province":"NV",
    "sg:tags":[
        "drafting"
    ],
    "sg:website":"www.houseplans.com",
    "wof:name":"House Plan Studio",
    "wof:placetype":"venue"
},
  "geometry": {"coordinates":[-115.152632,36.154877],"type":"Point"}
}