{
  "type": "Feature",
  "properties": {
    "iso:country":"US",
    "sg:address":"1400 Baring Blvd",
    "sg:city":"Sparks",
    "sg:classifiers":[
        {
            "category":"Recreation",
            "type":"Entertainment"
        }
    ],
    "sg:phone":"+1 775 353 2385",
    "sg:postcode":"89434",
    "sg:province":"NV",
    "sg:tags":[
        "hall",
        "auditorium"
    ],
    "wof:name":"Sparks Alf Sorensen Comm Ctr",
    "wof:placetype":"venue"
},
  "geometry": {"coordinates":[-119.715919,39.556437],"type":"Point"}
}