{
  "type": "Feature",
  "properties": {
    "iso:country":"US",
    "sg:address":"500 W Owens Avenue",
    "sg:city":"Las Vegas",
    "sg:classifiers":[
        {
            "category":"Real Estate",
            "subcategory":"Real Estate Operator",
            "type":"Services"
        }
    ],
    "sg:phone":"+1 702 399 1424",
    "sg:postcode":"89106",
    "sg:province":"NV",
    "sg:tags":[
        "apartment"
    ],
    "wof:name":"Ruby Duncan Manor",
    "wof:placetype":"venue"
},
  "geometry": {"coordinates":[-115.14836200000001,36.188487],"type":"Point"}
}