{
  "type": "Feature",
  "properties": {
    "iso:country":"US",
    "sg:address":"2295 Kietzke Ln",
    "sg:city":"Reno",
    "sg:classifiers":[
        {
            "category":"Shopping",
            "subcategory":"Florist",
            "type":"Retail Goods"
        }
    ],
    "sg:phone":"+1 775 825 7272",
    "sg:postcode":"89502",
    "sg:province":"NV",
    "wof:name":"Floral Expressions",
    "wof:placetype":"venue"
},
  "geometry": {"coordinates":[-119.789177,39.502797],"type":"Point"}
}