{
  "type": "Feature",
  "properties": {
    "iso:country":"US",
    "sg:address":"3611 Lindell Rd",
    "sg:city":"Las Vegas",
    "sg:classifiers":[
        {
            "category":"Health Services",
            "subcategory":"Clinic",
            "type":"Services"
        }
    ],
    "sg:phone":"+1 702 367 0393",
    "sg:postcode":"89103",
    "sg:province":"NV",
    "sg:tags":[
        "counseling",
        "mental"
    ],
    "wof:name":"Agape Counseling Associates",
    "wof:placetype":"venue"
},
  "geometry": {"coordinates":[-115.216003,36.123901],"type":"Point"}
}