{
  "type": "Feature",
  "properties": {
    "iso:country":"US",
    "sg:address":"3180 W Sahara Ave",
    "sg:city":"Las Vegas",
    "sg:classifiers":[
        {
            "category":"Health Services",
            "subcategory":"Clinic",
            "type":"Services"
        }
    ],
    "sg:phone":"+1 702 252 8707",
    "sg:postcode":"89102",
    "sg:province":"NV",
    "sg:tags":[
        "p",
        "hospital",
        "specialty",
        "outpatient"
    ],
    "wof:name":"Jack Dymond Assoc Ladc-CRC",
    "wof:placetype":"venue"
},
  "geometry": {"coordinates":[-115.18344399999999,36.144442],"type":"Point"}
}