{
  "type": "Feature",
  "properties": {
    "iso:country":"US",
    "sg:address":"1350 Van Ness Ave",
    "sg:city":"Reno",
    "sg:classifiers":[
        {
            "category":"Banks & Credit Unions",
            "subcategory":"Financial Services",
            "type":"Services"
        }
    ],
    "sg:phone":"+1 775 747 4367",
    "sg:postcode":"89503",
    "sg:province":"NV",
    "sg:tags":[
        "investor"
    ],
    "wof:name":"Jxlc LLC",
    "wof:placetype":"venue"
},
  "geometry": {"coordinates":[-119.84128200000001,39.54233],"type":"Point"}
}