{
  "type": "Feature",
  "properties": {
    "iso:country":"US",
    "sg:address":"1406 Jobs Peak Dr",
    "sg:city":"Gardnerville",
    "sg:classifiers":[
        {
            "category":"Shopping",
            "subcategory":"Clothing, Apparel, & Fashions",
            "type":"Retail Goods"
        }
    ],
    "sg:phone":"+1 775 265 4594",
    "sg:postcode":"89460",
    "sg:province":"NV",
    "sg:tags":[
        "dancing",
        "supply"
    ],
    "wof:name":"Dancewear Etc",
    "wof:placetype":"venue"
},
  "geometry": {"coordinates":[-119.735657,38.905893],"type":"Point"}
}