{
  "type": "Feature",
  "properties": {
    "iso:country":"US",
    "sg:address":"6700 Via Austi Parkway",
    "sg:city":"Las Vegas",
    "sg:classifiers":[
        {
            "category":"Shopping",
            "subcategory":"Tobacco",
            "type":"Retail Goods"
        }
    ],
    "sg:phone":"+1 702 740 5802",
    "sg:postcode":"89119",
    "sg:province":"NV",
    "sg:tags":[
        "shop"
    ],
    "wof:name":"Partagas Cigar Factory",
    "wof:placetype":"venue"
},
  "geometry": {"coordinates":[-115.16225900000001,36.068602],"type":"Point"}
}