{
  "type": "Feature",
  "properties": {
    "iso:country":"US",
    "sg:address":"5489 Royal Vista Ln",
    "sg:city":"Las Vegas",
    "sg:classifiers":[
        {
            "category":"Professional",
            "subcategory":"Management & Consulting",
            "type":"Services"
        }
    ],
    "sg:phone":"+1 702 656 1582",
    "sg:postcode":"89149",
    "sg:province":"NV",
    "sg:tags":[
        "business"
    ],
    "wof:name":"Never Give Up",
    "wof:placetype":"venue"
},
  "geometry": {"coordinates":[-115.264357,36.261331],"type":"Point"}
}