{
  "type": "Feature",
  "properties": {
    "iso:country":"US",
    "sg:address":"723 Descartes Ave",
    "sg:city":"Henderson",
    "sg:classifiers":[
        {
            "category":"Building & Trades",
            "subcategory":"Construction",
            "type":"Services"
        }
    ],
    "sg:phone":"+1 702 566 7464",
    "sg:postcode":"89002",
    "sg:province":"NV",
    "sg:tags":[
        "house"
    ],
    "wof:name":"Kelsey Const Co",
    "wof:placetype":"venue"
},
  "geometry": {"coordinates":[-114.990314,36.002956],"type":"Point"}
}