{
  "type": "Feature",
  "properties": {
    "iso:country":"US",
    "sg:address":"3805 Cool Meadows Dr",
    "sg:city":"Las Vegas",
    "sg:classifiers":[
        {
            "category":"Building & Trades",
            "subcategory":"Pest Control",
            "type":"Services"
        }
    ],
    "sg:phone":"+1 702 258 4011",
    "sg:postcode":"89129",
    "sg:province":"NV",
    "wof:name":"A Reliable Pest Control",
    "wof:placetype":"venue"
},
  "geometry": {"coordinates":[-115.270584,36.232108],"type":"Point"}
}