{
  "type": "Feature",
  "properties": {
    "iso:country":"US",
    "sg:address":"6065 Polaris Ave",
    "sg:city":"Las Vegas",
    "sg:classifiers":[
        {
            "category":"Personal",
            "type":"Services"
        },
        {
            "category":"Retail",
            "subcategory":"Storage",
            "type":"Services"
        }
    ],
    "sg:phone":"+1 702 798 2925",
    "sg:postcode":"89118",
    "sg:province":"NV",
    "sg:tags":[
        "mover",
        "self"
    ],
    "wof:name":"Bekins Agent",
    "wof:placetype":"venue"
},
  "geometry": {"coordinates":[-115.185997,36.079399],"type":"Point"}
}