{
  "type": "Feature",
  "properties": {
    "iso:country":"US",
    "sg:address":"10110 W Charleston Blvd",
    "sg:city":"Las Vegas",
    "sg:classifiers":[
        {
            "category":"Real Estate",
            "subcategory":"Architect",
            "type":"Services"
        }
    ],
    "sg:phone":"+1 702 932 3705",
    "sg:postcode":"89135",
    "sg:province":"NV",
    "wof:name":"Cuningham Group",
    "wof:placetype":"venue"
},
  "geometry": {"coordinates":[-115.316286,36.159218],"type":"Point"}
}