{
  "type": "Feature",
  "properties": {
    "iso:country":"US",
    "sg:address":"5495 Cactus Thorn Ave",
    "sg:city":"Las Vegas",
    "sg:classifiers":[
        {
            "category":"Real Estate",
            "subcategory":"Real Estate Operator",
            "type":"Services"
        }
    ],
    "sg:phone":"+1 702 889 0372",
    "sg:postcode":"89118",
    "sg:province":"NV",
    "sg:tags":[
        "apartment"
    ],
    "wof:name":"Lindell Court Apt",
    "wof:placetype":"venue"
},
  "geometry": {"coordinates":[-115.216003,36.0909],"type":"Point"}
}