{
  "type": "Feature",
  "properties": {
    "iso:country":"US",
    "sg:address":"215 Denver Way",
    "sg:city":"Henderson",
    "sg:classifiers":[
        {
            "category":"Professional",
            "subcategory":"Business Services",
            "type":"Services"
        }
    ],
    "sg:phone":"+1 702 567 1677",
    "sg:postcode":"89015",
    "sg:province":"NV",
    "wof:name":"Anitas Botanical Paradise",
    "wof:placetype":"venue"
},
  "geometry": {"coordinates":[-114.999026,36.03039],"type":"Point"}
}