{
  "type": "Feature",
  "properties": {
    "iso:country":"US",
    "sg:address":"6000 S Eastern Ave",
    "sg:city":"Las Vegas",
    "sg:classifiers":[
        {
            "category":"Professional",
            "subcategory":"Testing Lab",
            "type":"Services"
        }
    ],
    "sg:phone":"+1 702 383 1199",
    "sg:postcode":"89119",
    "sg:province":"NV",
    "sg:tags":[
        "laboratory"
    ],
    "wof:name":"Atlas Consultants Inc",
    "wof:placetype":"venue"
},
  "geometry": {"coordinates":[-115.118706,36.081757],"type":"Point"}
}