{
  "type": "Feature",
  "properties": {
    "iso:country":"US",
    "sg:address":"1780 S Rainbow Blvd",
    "sg:city":"Las Vegas",
    "sg:classifiers":[
        {
            "category":"Food & Beverages",
            "subcategory":"Liquor & Beverages",
            "type":"Retail Goods"
        }
    ],
    "sg:phone":"+1 702 870 6300",
    "sg:postcode":"89146",
    "sg:province":"NV",
    "sg:tags":[
        "beer",
        "spirit",
        "wine"
    ],
    "wof:name":"Lee's Discount Liquor",
    "wof:placetype":"venue"
},
  "geometry": {"coordinates":[-115.242996,36.151901],"type":"Point"}
}