{
  "type": "Feature",
  "properties": {
    "iso:country":"US",
    "sg:address":"3006 S Maryland Parkway",
    "sg:city":"Las Vegas",
    "sg:classifiers":[
        {
            "category":"Health Services",
            "subcategory":"Doctor",
            "type":"Services"
        }
    ],
    "sg:phone":"+1 702 732 1290",
    "sg:postcode":"89109",
    "sg:province":"NV",
    "sg:tags":[
        "cardiologist"
    ],
    "sg:website":"www.childrensheartcenter.com",
    "wof:name":"Acherman Ruben J MD",
    "wof:placetype":"venue"
},
  "geometry": {"coordinates":[-115.136842,36.1358],"type":"Point"}
}