{
  "type": "Feature",
  "properties": {
    "iso:country":"US",
    "sg:address":"3980 E Sunset Road",
    "sg:city":"Las Vegas",
    "sg:classifiers":[
        {
            "category":"Shopping",
            "subcategory":"Mobile Phones",
            "type":"Retail Goods"
        }
    ],
    "sg:phone":"+1 702 898 7203",
    "sg:postcode":"89120",
    "sg:province":"NV",
    "wof:name":"Verizon Wireless",
    "wof:placetype":"venue"
},
  "geometry": {"coordinates":[-115.087588,36.071179],"type":"Point"}
}