{
  "type": "Feature",
  "properties": {
    "iso:country":"US",
    "sg:address":"5795 S Sandhill Road",
    "sg:city":"Las Vegas",
    "sg:classifiers":[
        {
            "category":"Professional",
            "subcategory":"Accounting & Tax Preparation",
            "type":"Services"
        }
    ],
    "sg:phone":"+1 702 736 4641",
    "sg:postcode":"89120",
    "sg:province":"NV",
    "sg:tags":[
        "accountant"
    ],
    "wof:name":"Benjamin W CPA",
    "wof:placetype":"venue"
},
  "geometry": {"coordinates":[-115.091324,36.083997],"type":"Point"}
}