{
  "type": "Feature",
  "properties": {
    "iso:country":"US",
    "sg:address":"308 Redondo St",
    "sg:city":"Henderson",
    "sg:classifiers":[
        {
            "category":"Professional",
            "type":"Services"
        }
    ],
    "sg:phone":"+1 702 220 7166",
    "sg:postcode":"89014",
    "sg:province":"NV",
    "wof:name":"Sandwiched Inn",
    "wof:placetype":"venue"
},
  "geometry": {"coordinates":[-115.063591,36.05184],"type":"Point"}
}