{
  "type": "Feature",
  "properties": {
    "iso:country":"US",
    "sg:address":"1080 Standard St",
    "sg:city":"Reno",
    "sg:classifiers":[
        {
            "category":"Freight",
            "type":"Transportation"
        }
    ],
    "sg:phone":"+1 775 329 2561",
    "sg:postcode":"89506",
    "sg:province":"NV",
    "sg:tags":[
        "company",
        "moving"
    ],
    "wof:name":"Mayflower Moving Agency",
    "wof:placetype":"venue"
},
  "geometry": {"coordinates":[-119.820457,39.589796],"type":"Point"}
}