{
  "type": "Feature",
  "properties": {
    "iso:country":"US",
    "sg:address":"1214 Victorian Ave",
    "sg:city":"Sparks",
    "sg:classifiers":[
        {
            "category":"Shopping",
            "subcategory":"Tobacco",
            "type":"Retail Goods"
        }
    ],
    "sg:phone":"+1 775 331 1466",
    "sg:postcode":"89431",
    "sg:province":"NV",
    "sg:tags":[
        "product"
    ],
    "wof:name":"Smoke Mart",
    "wof:placetype":"venue"
},
  "geometry": {"coordinates":[-119.758155,39.534906],"type":"Point"}
}