{
  "type": "Feature",
  "properties": {
    "iso:country":"US",
    "sg:address":"380 Edison Way",
    "sg:city":"Reno",
    "sg:classifiers":[
        {
            "category":"Education",
            "subcategory":"School",
            "type":"Public Place"
        }
    ],
    "sg:phone":"+1 775 353 5533",
    "sg:postcode":"89502",
    "sg:province":"NV",
    "wof:name":"Education Collaborative",
    "wof:placetype":"venue"
},
  "geometry": {"coordinates":[-119.754695,39.508855],"type":"Point"}
}