{
  "type": "Feature",
  "properties": {
    "iso:country":"US",
    "sg:address":"1916 S Eastern Ave",
    "sg:city":"Las Vegas",
    "sg:classifiers":[
        {
            "category":"Insurance",
            "subcategory":"Insurance Agent",
            "type":"Services"
        }
    ],
    "sg:phone":"+1 702 641 1000",
    "sg:postcode":"89104",
    "sg:province":"NV",
    "wof:name":"Ashe Insurance",
    "wof:placetype":"venue"
},
  "geometry": {"coordinates":[-115.118724,36.148318],"type":"Point"}
}