{
  "type": "Feature",
  "properties": {
    "iso:country":"US",
    "sg:address":"5001 E. Bonanza #106",
    "sg:city":"Las Vegas",
    "sg:classifiers":[
        {
            "category":"Retail",
            "subcategory":"Laundry & Dry Cleaning",
            "type":"Services"
        }
    ],
    "sg:phone":"+1 702 452 6060",
    "sg:postcode":"89110",
    "sg:province":"NV",
    "sg:website":"sunrisecleaners-lv.com/",
    "wof:name":"Sunrise Cleaners",
    "wof:placetype":"venue"
},
  "geometry": {"coordinates":[-115.064534,36.172991],"type":"Point"}
}