{
  "type": "Feature",
  "properties": {
    "iso:country":"US",
    "sg:address":"3700 E Desert Inn Rd #1",
    "sg:city":"Las Vegas",
    "sg:classifiers":[
        {
            "category":"Restaurant",
            "type":"Food & Drink"
        }
    ],
    "sg:phone":"+1 702 451 6656",
    "sg:postcode":"89121",
    "sg:province":"NV",
    "sg:tags":[
        "chinese"
    ],
    "wof:name":"Wo Fat",
    "wof:placetype":"venue"
},
  "geometry": {"coordinates":[-115.093591,36.130011],"type":"Point"}
}