{
  "type": "Feature",
  "properties": {
    "iso:country":"US",
    "sg:address":"3001 Cortez St",
    "sg:city":"Carson City",
    "sg:classifiers":[
        {
            "category":"Manufacturing",
            "subcategory":"Toys & Sporting Goods",
            "type":"Manufacturing & Wholesale Goods"
        }
    ],
    "sg:phone":"+1 775 882 8378",
    "sg:postcode":"89701",
    "sg:province":"NV",
    "sg:tags":[
        "decoration",
        "home",
        "mfg",
        "doll"
    ],
    "wof:name":"Makins Place",
    "wof:placetype":"venue"
},
  "geometry": {"coordinates":[-119.754982,39.14067],"type":"Point"}
}