{
  "type": "Feature",
  "properties": {
    "iso:country":"US",
    "sg:address":"1733 Hymer Ave",
    "sg:city":"Sparks",
    "sg:classifiers":[
        {
            "category":"Building & Trades",
            "subcategory":"Construction",
            "type":"Services"
        }
    ],
    "sg:phone":"+1 775 331 5585",
    "sg:postcode":"89431",
    "sg:province":"NV",
    "sg:tags":[
        "contractor"
    ],
    "wof:name":"Biale Construction LLC",
    "wof:placetype":"venue"
},
  "geometry": {"coordinates":[-119.767353,39.530768],"type":"Point"}
}