{
  "type": "Feature",
  "properties": {
    "iso:country":"US",
    "sg:address":"6589 Beach Plum Way",
    "sg:city":"Las Vegas",
    "sg:classifiers":[
        {
            "category":"Shopping",
            "subcategory":"Clothing, Apparel, & Fashions",
            "type":"Retail Goods"
        }
    ],
    "sg:phone":"+1 702 271 4141",
    "sg:postcode":"89156",
    "sg:province":"NV",
    "sg:tags":[
        "t"
    ],
    "wof:name":"Sierra Silk Screen",
    "wof:placetype":"venue"
},
  "geometry": {"coordinates":[-115.029129,36.200077],"type":"Point"}
}