{
  "type": "Feature",
  "properties": {
    "iso:country":"US",
    "sg:address":"4001 S Decatur Blvd",
    "sg:city":"Las Vegas",
    "sg:classifiers":[
        {
            "category":"Banks & Credit Unions",
            "subcategory":"Bank",
            "type":"Services"
        }
    ],
    "sg:phone":"+1 702 257 7092",
    "sg:postcode":"89103",
    "sg:province":"NV",
    "sg:tags":[
        "state"
    ],
    "wof:name":"Nevada State Bank",
    "wof:placetype":"venue"
},
  "geometry": {"coordinates":[-115.208131,36.116246],"type":"Point"}
}