{
  "type": "Feature",
  "properties": {
    "iso:country":"US",
    "sg:address":"10010 San Gervasio Ave",
    "sg:city":"Las Vegas",
    "sg:classifiers":[
        {
            "category":"Shopping",
            "subcategory":"Computers & Home Electronics",
            "type":"Retail Goods"
        }
    ],
    "sg:phone":"+1 702 838 7996",
    "sg:postcode":"89147",
    "sg:province":"NV",
    "sg:tags":[
        "equipment",
        "dealer"
    ],
    "wof:name":"Gama International",
    "wof:placetype":"venue"
},
  "geometry": {"coordinates":[-115.311181,36.105247],"type":"Point"}
}