{
  "type": "Feature",
  "properties": {
    "iso:country":"US",
    "sg:address":"5850 Polaris Ave",
    "sg:city":"Las Vegas",
    "sg:classifiers":[
        {
            "category":"Real Estate",
            "subcategory":"Architect",
            "type":"Services"
        }
    ],
    "sg:phone":"+1 702 435 4448",
    "sg:postcode":"89118",
    "sg:province":"NV",
    "sg:website":"www.pgal.com",
    "wof:name":"PGAL",
    "wof:placetype":"venue"
},
  "geometry": {"coordinates":[-115.185525,36.081663],"type":"Point"}
}