{
  "type": "Feature",
  "properties": {
    "iso:country":"US",
    "sg:address":"8120 Heavenly Star Cir",
    "sg:city":"Las Vegas",
    "sg:classifiers":[
        {
            "category":"Shopping",
            "subcategory":"Jewelry",
            "type":"Retail Goods"
        }
    ],
    "sg:phone":"+1 702 453 4071",
    "sg:postcode":"89128",
    "sg:province":"NV",
    "wof:name":"Nevada Jewelry Design",
    "wof:placetype":"venue"
},
  "geometry": {"coordinates":[-115.272479,36.185471],"type":"Point"}
}