{
  "type": "Feature",
  "properties": {
    "iso:country":"US",
    "sg:address":"3663 Las Vegas Blvd S",
    "sg:city":"Las Vegas",
    "sg:classifiers":[
        {
            "category":"Shopping",
            "subcategory":"Clothing, Apparel, & Fashions",
            "type":"Retail Goods"
        }
    ],
    "sg:phone":"+1 702 369 1195",
    "sg:postcode":"89109",
    "sg:province":"NV",
    "sg:tags":[
        "clothing",
        "women's"
    ],
    "sg:website":"www.hm.com",
    "wof:name":"H&M",
    "wof:placetype":"venue"
},
  "geometry": {"coordinates":[-115.172825,36.110983],"type":"Point"}
}