{
  "type": "Feature",
  "properties": {
    "iso:country":"US",
    "sg:address":"124 Wonder St",
    "sg:city":"Reno",
    "sg:phone":"+1 775 324 1864",
    "sg:postcode":"89502",
    "sg:province":"NV",
    "wof:name":"Silver Peak Restaurant & Brewery",
    "wof:placetype":"venue"
},
  "geometry": {"coordinates":[-119.80615,39.514056],"type":"Point"}
}