{
  "type": "Feature",
  "properties": {
    "iso:country":"US",
    "sg:address":"555 Double Eagle Ct",
    "sg:city":"Reno",
    "sg:classifiers":[
        {
            "category":"Government",
            "subcategory":"Office",
            "type":"Public Place"
        }
    ],
    "sg:phone":"+1 775 850 1440",
    "sg:postcode":"89521",
    "sg:province":"NV",
    "sg:tags":[
        "agency",
        "pharmacy",
        "state",
        "licensing",
        "inspection",
        "board"
    ],
    "wof:name":"Nevada State Board Of Pharmacy",
    "wof:placetype":"venue"
},
  "geometry": {"coordinates":[-119.762789,39.441895],"type":"Point"}
}