{
  "type": "Feature",
  "properties": {
    "iso:country":"US",
    "sg:address":"150 S Bridge St",
    "sg:city":"Winnemucca",
    "sg:classifiers":[
        {
            "category":"Recreation",
            "type":"Entertainment"
        }
    ],
    "sg:phone":"+1 775 625 4111",
    "sg:postcode":"89445",
    "sg:province":"NV",
    "sg:tags":[
        "slot",
        "car",
        "race",
        "course"
    ],
    "wof:name":"Wild Side Slot Car Racing",
    "wof:placetype":"venue"
},
  "geometry": {"coordinates":[-117.73646,40.974623],"type":"Point"}
}