{
  "type": "Feature",
  "properties": {
    "iso:country":"US",
    "sg:address":"620 N McCarran Blvd",
    "sg:city":"Sparks",
    "sg:classifiers":[
        {
            "category":"Food & Beverages",
            "subcategory":"Groceries & Convenience Stores",
            "type":"Retail Goods"
        }
    ],
    "sg:phone":"+1 775 358 6660",
    "sg:postcode":"89431",
    "sg:province":"NV",
    "sg:tags":[
        "supermarket"
    ],
    "wof:name":"Safeway",
    "wof:placetype":"venue"
},
  "geometry": {"coordinates":[-119.733722,39.540312],"type":"Point"}
}