{
  "type": "Feature",
  "properties": {
    "iso:country":"US",
    "sg:address":"2000 E Charleston Boulevard",
    "sg:city":"Las Vegas",
    "sg:classifiers":[
        {
            "category":"Restaurant",
            "type":"Food & Drink"
        }
    ],
    "sg:phone":"+1 702 388 0078",
    "sg:postcode":"89104",
    "sg:province":"NV",
    "wof:name":"Chinatown Cuisine",
    "wof:placetype":"venue"
},
  "geometry": {"coordinates":[-115.121162,36.15874],"type":"Point"}
}