{
  "type": "Feature",
  "properties": {
    "iso:country":"US",
    "sg:address":"10 Red Rock Rd",
    "sg:city":"Mound House",
    "sg:classifiers":[
        {
            "category":"Building & Trades",
            "subcategory":"Construction",
            "type":"Services"
        }
    ],
    "sg:phone":"+1 775 246 3626",
    "sg:postcode":"89706",
    "sg:province":"NV",
    "sg:tags":[
        "contractor"
    ],
    "wof:name":"Denton Cabinet Company Inc",
    "wof:placetype":"venue"
},
  "geometry": {"coordinates":[-119.676003,39.212502],"type":"Point"}
}