{
  "type": "Feature",
  "properties": {
    "iso:country":"US",
    "sg:address":"2503 E 2nd St",
    "sg:city":"Reno",
    "sg:classifiers":[
        {
            "category":"Government",
            "subcategory":"Office",
            "type":"Public Place"
        }
    ],
    "sg:phone":"+1 775 786 3860",
    "sg:postcode":"89502",
    "sg:province":"NV",
    "wof:name":"Reno-Sparks Bldg & Grounds",
    "wof:placetype":"venue"
},
  "geometry": {"coordinates":[-119.781434,39.527518],"type":"Point"}
}