{
  "type": "Feature",
  "properties": {
    "iso:country":"US",
    "sg:address":"1225 N Eastern Ave",
    "sg:city":"Las Vegas",
    "sg:classifiers":[
        {
            "category":"Autos & Motor Vehicles",
            "subcategory":"Auto Supplies",
            "type":"Retail Goods"
        }
    ],
    "sg:phone":"+1 702 633 5945",
    "sg:postcode":"89101",
    "sg:province":"NV",
    "sg:tags":[
        "automobile",
        "parts"
    ],
    "sg:website":"www.cskauto.com",
    "wof:name":"Checker Auto Parts",
    "wof:placetype":"venue"
},
  "geometry": {"coordinates":[-115.116153,36.184576],"type":"Point"}
}