{
  "type": "Feature",
  "properties": {
    "iso:country":"US",
    "sg:address":"924 Incline Way",
    "sg:city":"Incline Village",
    "sg:classifiers":[
        {
            "category":"Insurance",
            "subcategory":"Insurance Agent",
            "type":"Services"
        }
    ],
    "sg:phone":"+1 775 833 4577",
    "sg:postcode":"89451",
    "sg:province":"NV",
    "wof:name":"Athletically Inclined Ins",
    "wof:placetype":"venue"
},
  "geometry": {"coordinates":[-119.948579,39.247851],"type":"Point"}
}