{
  "type": "Feature",
  "properties": {
    "iso:country":"US",
    "sg:address":"2002 E Webb Ave",
    "sg:city":"North Las Vegas",
    "sg:classifiers":[
        {
            "category":"Building & Trades",
            "subcategory":"Landscaping Services",
            "type":"Services"
        }
    ],
    "sg:phone":"+1 702 399 5623",
    "sg:postcode":"89030",
    "sg:province":"NV",
    "wof:name":"Jose Rivas Lawn Maintenance",
    "wof:placetype":"venue"
},
  "geometry": {"coordinates":[-115.118374,36.189335],"type":"Point"}
}