{
  "type": "Feature",
  "properties": {
    "iso:country":"US",
    "sg:address":"2832 Edge Rock Cir",
    "sg:city":"Las Vegas",
    "sg:classifiers":[
        {
            "category":"Retail",
            "subcategory":"Laundry & Dry Cleaning",
            "type":"Services"
        }
    ],
    "sg:phone":"+1 702 233 8909",
    "sg:postcode":"89117",
    "sg:province":"NV",
    "sg:tags":[
        "cleaners",
        "rug",
        "carpet"
    ],
    "wof:name":"Unique Carpet Svc",
    "wof:placetype":"venue"
},
  "geometry": {"coordinates":[-115.3137,36.139719],"type":"Point"}
}