{
  "type": "Feature",
  "properties": {
    "iso:country":"US",
    "sg:address":"2300 S Jones Blvd",
    "sg:city":"Las Vegas",
    "sg:classifiers":[
        {
            "category":"Professional",
            "subcategory":"Accounting & Tax Preparation",
            "type":"Services"
        }
    ],
    "sg:phone":"+1 702 873 8340",
    "sg:postcode":"89146",
    "sg:province":"NV",
    "sg:tags":[
        "return",
        "filing"
    ],
    "wof:name":"Bert Purdy & Associates",
    "wof:placetype":"venue"
},
  "geometry": {"coordinates":[-115.225251,36.145113],"type":"Point"}
}