{
  "type": "Feature",
  "properties": {
    "iso:country":"US",
    "sg:address":"1885 S Arlington Ave",
    "sg:city":"Reno",
    "sg:classifiers":[
        {
            "category":"Professional",
            "subcategory":"Accounting & Tax Preparation",
            "type":"Services"
        }
    ],
    "sg:phone":"+1 775 323 7122",
    "sg:postcode":"89509",
    "sg:province":"NV",
    "sg:tags":[
        "firm"
    ],
    "wof:name":"Bartig Basler & Ray",
    "wof:placetype":"venue"
},
  "geometry": {"coordinates":[-119.817238,39.506236],"type":"Point"}
}