{
  "type": "Feature",
  "properties": {
    "iso:country":"US",
    "sg:address":"3950 Koval Lane",
    "sg:city":"Las Vegas",
    "sg:classifiers":[
        {
            "category":"Travel",
            "subcategory":"Hotels & Motels",
            "type":"Entertainment"
        }
    ],
    "sg:phone":"+1 702 731 6100",
    "sg:postcode":"89109",
    "sg:province":"NV",
    "sg:website":"www.summerbayresort.com/vegas.html",
    "wof:name":"Summer Bay Resorts Las Vegas Desert Club",
    "wof:placetype":"venue"
},
  "geometry": {"coordinates":[-115.161483,36.117707],"type":"Point"}
}