{
  "type": "Feature",
  "properties": {
    "iso:country":"US",
    "sg:address":"2640 E Sunset Rd",
    "sg:city":"Las Vegas",
    "sg:classifiers":[
        {
            "category":"Bars & Pubs",
            "subcategory":"Sports Bar",
            "type":"Food & Drink"
        },
        {
            "category":"Restaurant",
            "type":"Food & Drink"
        }
    ],
    "sg:phone":"+1 702 312 3500",
    "sg:postcode":"89120",
    "sg:province":"NV",
    "sg:tags":[
        "pizza"
    ],
    "wof:name":"Nikki Lee's Sports Pub & Grill",
    "wof:placetype":"venue"
},
  "geometry": {"coordinates":[-115.113998,36.071499],"type":"Point"}
}