{
  "type": "Feature",
  "properties": {
    "iso:country":"US",
    "sg:address":"245 Freeport Blvd",
    "sg:city":"Sparks",
    "sg:classifiers":[
        {
            "category":"Freight",
            "type":"Transportation"
        }
    ],
    "sg:phone":"+1 775 356 2053",
    "sg:postcode":"89431",
    "sg:province":"NV",
    "sg:tags":[
        "operator",
        "local",
        "trucking"
    ],
    "wof:name":"LDS",
    "wof:placetype":"venue"
},
  "geometry": {"coordinates":[-119.745787,39.525486],"type":"Point"}
}