{
  "type": "Feature",
  "properties": {
    "iso:country":"US",
    "sg:address":"1063 Spoonbill Dr",
    "sg:city":"Sparks",
    "sg:classifiers":[
        {
            "category":"Shopping",
            "subcategory":"Gifts & Souvenirs",
            "type":"Retail Goods"
        }
    ],
    "sg:phone":"+1 775 425 5867",
    "sg:postcode":"89441",
    "sg:province":"NV",
    "sg:tags":[
        "party",
        "supply"
    ],
    "wof:name":"Bouncing Around",
    "wof:placetype":"venue"
},
  "geometry": {"coordinates":[-119.724191,39.656292],"type":"Point"}
}