{
  "type": "Feature",
  "properties": {
    "iso:country":"US",
    "sg:address":"1590 4th St",
    "sg:city":"Minden",
    "sg:classifiers":[
        {
            "category":"Professional",
            "subcategory":"Lawyer & Legal Services",
            "type":"Services"
        }
    ],
    "sg:phone":"+1 775 782 7171",
    "sg:postcode":"89423",
    "sg:province":"NV",
    "sg:tags":[
        "attorney"
    ],
    "sg:website":"www.brooke-shaw.com",
    "wof:name":"Brooke Shaw Zumpft",
    "wof:placetype":"venue"
},
  "geometry": {"coordinates":[-119.763557,38.953487],"type":"Point"}
}