{
  "type": "Feature",
  "properties": {
    "iso:country":"US",
    "sg:address":"948 Incline Way",
    "sg:city":"Incline Village",
    "sg:classifiers":[
        {
            "category":"Building & Trades",
            "subcategory":"Landscaping Services",
            "type":"Services"
        }
    ],
    "sg:phone":"+1 775 832 1189",
    "sg:postcode":"89451",
    "sg:province":"NV",
    "sg:tags":[
        "landscape"
    ],
    "wof:name":"Grounds Department",
    "wof:placetype":"venue"
},
  "geometry": {"coordinates":[-119.947146,39.245903],"type":"Point"}
}