{
  "type": "Feature",
  "properties": {
    "iso:country":"US",
    "sg:address":"454 Washington St",
    "sg:city":"Reno",
    "sg:classifiers":[
        {
            "category":"Shopping",
            "subcategory":"Gifts & Souvenirs",
            "type":"Retail Goods"
        }
    ],
    "sg:phone":"+1 775 324 4540",
    "sg:postcode":"89503",
    "sg:province":"NV",
    "sg:tags":[
        "collectible"
    ],
    "wof:name":"Antique Rocker",
    "wof:placetype":"venue"
},
  "geometry": {"coordinates":[-119.823549,39.528776],"type":"Point"}
}