{
  "type": "Feature",
  "properties": {
    "iso:country":"US",
    "sg:address":"218 Vassar St",
    "sg:city":"Reno",
    "sg:classifiers":[
        {
            "category":"Shopping",
            "subcategory":"Clothing, Apparel, & Fashions",
            "type":"Retail Goods"
        }
    ],
    "sg:phone":"+1 775 324 2787",
    "sg:postcode":"89502",
    "sg:province":"NV",
    "sg:tags":[
        "ethnic"
    ],
    "sg:website":"www.artdogsandgrace.com",
    "wof:name":"Art Dogs & Grace",
    "wof:placetype":"venue"
},
  "geometry": {"coordinates":[-119.8034,39.512806],"type":"Point"}
}