{
  "type": "Feature",
  "properties": {
    "iso:country":"US",
    "sg:address":"1454 E Charleston Blvd",
    "sg:city":"Las Vegas",
    "sg:classifiers":[
        {
            "category":"Wholesale",
            "subcategory":"Jewelry",
            "type":"Manufacturing & Wholesale Goods"
        }
    ],
    "sg:phone":"+1 702 641 0195",
    "sg:postcode":"89104",
    "sg:province":"NV",
    "sg:tags":[
        "stone"
    ],
    "wof:name":"M M Jewelryland",
    "wof:placetype":"venue"
},
  "geometry": {"coordinates":[-115.133366,36.158808],"type":"Point"}
}