{
  "type": "Feature",
  "properties": {
    "iso:country":"US",
    "sg:address":"2725 S Jones Blvd Ste 110",
    "sg:city":"Las Vegas",
    "sg:classifiers":[
        {
            "category":"Professional",
            "subcategory":"Accounting & Tax Preparation",
            "type":"Services"
        }
    ],
    "sg:phone":"+1 702 364 0400",
    "sg:postcode":"89146",
    "sg:province":"NV",
    "sg:tags":[
        "accountant"
    ],
    "wof:name":"Joseph Ellsworth & Wolters Cpas",
    "wof:placetype":"venue"
},
  "geometry": {"coordinates":[-115.224998,36.139999],"type":"Point"}
}