{
  "type": "Feature",
  "properties": {
    "iso:country":"US",
    "sg:address":"3720 Las Vegas Blvd S.",
    "sg:city":"Las Vegas",
    "sg:classifiers":[
        {
            "category":"Shopping",
            "subcategory":"Clothing, Apparel, & Fashions",
            "type":"Retail Goods"
        }
    ],
    "sg:postcode":"89109",
    "sg:province":"NV",
    "sg:tags":[
        "men's",
        "clothing",
        "accessory",
        "women's"
    ],
    "sg:website":"www.crystalsatcitycenter.com/ret...",
    "wof:name":"Fendi",
    "wof:placetype":"venue"
},
  "geometry": {"coordinates":[-115.173172,36.107934],"type":"Point"}
}