{
  "type": "Feature",
  "properties": {
    "iso:country":"US",
    "sg:address":"948 Incline Way",
    "sg:city":"Incline Village",
    "sg:classifiers":[
        {
            "category":"Social Services",
            "type":"Services"
        }
    ],
    "sg:phone":"+1 775 298 0026",
    "sg:postcode":"89451",
    "sg:province":"NV",
    "sg:tags":[
        "information",
        "planning",
        "center",
        "family"
    ],
    "wof:name":"Planned Parenthood",
    "wof:placetype":"venue"
},
  "geometry": {"coordinates":[-119.947146,39.245903],"type":"Point"}
}