{
  "type": "Feature",
  "properties": {
    "iso:country":"US",
    "sg:address":"827 Spring Valley Pkwy",
    "sg:city":"Spring Creek",
    "sg:classifiers":[
        {
            "category":"Professional",
            "subcategory":"Management & Consulting",
            "type":"Services"
        }
    ],
    "sg:phone":"+1 775 777 9754",
    "sg:postcode":"89815",
    "sg:province":"NV",
    "wof:name":"Alberts Weber Stephanie",
    "wof:placetype":"venue"
},
  "geometry": {"coordinates":[-115.653812,40.812757],"type":"Point"}
}