{
  "type": "Feature",
  "properties": {
    "iso:country":"US",
    "sg:address":"810 Wild Hawk Dr",
    "sg:city":"Sparks",
    "sg:classifiers":[
        {
            "category":"Building & Trades",
            "subcategory":"Landscaping Services",
            "type":"Services"
        }
    ],
    "sg:phone":"+1 775 425 5666",
    "sg:postcode":"89436",
    "sg:province":"NV",
    "sg:tags":[
        "landscape",
        "contractor"
    ],
    "wof:name":"Mario's Landscape & Design",
    "wof:placetype":"venue"
},
  "geometry": {"coordinates":[-119.729536,39.633628],"type":"Point"}
}