{
  "type": "Feature",
  "properties": {
    "iso:country":"US",
    "sg:address":"8159 Owl Clan Ct",
    "sg:city":"Las Vegas",
    "sg:classifiers":[
        {
            "category":"Banks & Credit Unions",
            "subcategory":"Bank",
            "type":"Services"
        }
    ],
    "sg:phone":"+1 702 214 8618",
    "sg:postcode":"89131",
    "sg:province":"NV",
    "sg:tags":[
        "mortgage"
    ],
    "wof:name":"Mortgage Loan Specialist",
    "wof:placetype":"venue"
},
  "geometry": {"coordinates":[-115.273281,36.31213],"type":"Point"}
}