{
  "type": "Feature",
  "properties": {
    "iso:country":"US",
    "sg:address":"400 S 4th St",
    "sg:city":"Las Vegas",
    "sg:classifiers":[
        {
            "category":"Utilities",
            "subcategory":"Telephone",
            "type":"Services"
        }
    ],
    "sg:phone":"+1 702 967 9364",
    "sg:postcode":"89101",
    "sg:province":"NV",
    "sg:tags":[
        "to",
        "internet",
        "provides",
        "convention"
    ],
    "wof:name":"Priority Networks",
    "wof:placetype":"venue"
},
  "geometry": {"coordinates":[-115.144846,36.165076],"type":"Point"}
}