{
  "type": "Feature",
  "properties": {
    "iso:country":"US",
    "sg:address":"1020 N McCarran Blvd",
    "sg:city":"Reno",
    "sg:classifiers":[
        {
            "category":"Freight",
            "type":"Transportation"
        }
    ],
    "sg:phone":"+1 775 324 1888",
    "sg:postcode":"89512",
    "sg:province":"NV",
    "sg:tags":[
        "general"
    ],
    "wof:name":"Storamerica",
    "wof:placetype":"venue"
},
  "geometry": {"coordinates":[-119.830475,39.550878],"type":"Point"}
}