{
  "type": "Feature",
  "properties": {
    "iso:country":"US",
    "sg:address":"1524 Old US Hwy 395 S",
    "sg:city":"Gardnerville",
    "sg:classifiers":[
        {
            "category":"Shopping",
            "subcategory":"Clothing, Apparel, & Fashions",
            "type":"Retail Goods"
        }
    ],
    "sg:phone":"+1 775 783 1948",
    "sg:postcode":"89410",
    "sg:province":"NV",
    "sg:tags":[
        "shop",
        "bridal"
    ],
    "wof:name":"Countryside Bridal Boutique",
    "wof:placetype":"venue"
},
  "geometry": {"coordinates":[-119.553707,38.731209],"type":"Point"}
}