{
  "type": "Feature",
  "properties": {
    "iso:country":"US",
    "sg:address":"203 Oleander Pl",
    "sg:city":"Henderson",
    "sg:classifiers":[
        {
            "category":"Building & Trades",
            "subcategory":"Cleaning & Sanitation",
            "type":"Services"
        }
    ],
    "sg:phone":"+1 702 558 7882",
    "sg:postcode":"89015",
    "sg:province":"NV",
    "sg:tags":[
        "maintenance"
    ],
    "wof:name":"White Glove Cleaning",
    "wof:placetype":"venue"
},
  "geometry": {"coordinates":[-114.955576,36.046172],"type":"Point"}
}