{
  "type": "Feature",
  "properties": {
    "iso:country":"US",
    "sg:address":"4215 Las Vegas Blvd N",
    "sg:city":"Las Vegas",
    "sg:classifiers":[
        {
            "category":"Restaurant",
            "type":"Food & Drink"
        }
    ],
    "sg:phone":"+1 702 643 0200",
    "sg:postcode":"89115",
    "sg:province":"NV",
    "wof:name":"Mc Donald's",
    "wof:placetype":"venue"
},
  "geometry": {"coordinates":[-115.057396,36.238652],"type":"Point"}
}