{
  "type": "Feature",
  "properties": {
    "iso:country":"US",
    "sg:address":"2780 Las Vegas Blvd S",
    "sg:city":"Las Vegas",
    "sg:classifiers":[
        {
            "category":"Travel",
            "subcategory":"Hotels & Motels",
            "type":"Entertainment"
        }
    ],
    "sg:phone":"+1 702 733 1481",
    "sg:postcode":"89109",
    "sg:province":"NV",
    "wof:name":"Hilton Grand Vacations Club",
    "wof:placetype":"venue"
},
  "geometry": {"coordinates":[-115.159176,36.141695],"type":"Point"}
}