{
  "type": "Feature",
  "properties": {
    "iso:country":"US",
    "sg:address":"7377 S Jones Blvd Ste 108",
    "sg:city":"Las Vegas",
    "sg:classifiers":[
        {
            "category":"Personal",
            "subcategory":"Tanning Parlor",
            "type":"Services"
        }
    ],
    "sg:phone":"+1 702 221 8267",
    "sg:postcode":"89139",
    "sg:province":"NV",
    "wof:name":"Rio Tan",
    "wof:placetype":"venue"
},
  "geometry": {"coordinates":[-115.225192,36.05507],"type":"Point"}
}