{
  "type": "Feature",
  "properties": {
    "iso:country":"US",
    "sg:address":"4763 Procyon St",
    "sg:city":"Las Vegas",
    "sg:classifiers":[
        {
            "category":"Building & Trades",
            "subcategory":"Landscaping Services",
            "type":"Services"
        }
    ],
    "sg:phone":"+1 702 363 7665",
    "sg:postcode":"89103",
    "sg:province":"NV",
    "sg:tags":[
        "waterfall"
    ],
    "wof:name":"Hawaiian Pools & Waterscapes",
    "wof:placetype":"venue"
},
  "geometry": {"coordinates":[-115.187786,36.101783],"type":"Point"}
}