{
  "type": "Feature",
  "properties": {
    "iso:country":"US",
    "sg:address":"2412 S 15th St",
    "sg:city":"Las Vegas",
    "sg:classifiers":[
        {
            "category":"Building & Trades",
            "subcategory":"Construction",
            "type":"Services"
        }
    ],
    "sg:phone":"+1 702 435 7017",
    "sg:postcode":"89104",
    "sg:province":"NV",
    "sg:tags":[
        "resurfacing",
        "laying",
        "refinishing",
        "floor"
    ],
    "wof:name":"Robert Clark Flooring LLC",
    "wof:placetype":"venue"
},
  "geometry": {"coordinates":[-115.132894,36.14581],"type":"Point"}
}