{
  "type": "Feature",
  "properties": {
    "iso:country":"US",
    "sg:address":"3396 Lakeside Ct",
    "sg:city":"Reno",
    "sg:classifiers":[
        {
            "category":"Insurance",
            "subcategory":"Insurance Agent",
            "type":"Services"
        }
    ],
    "sg:phone":"+1 775 823 4636",
    "sg:postcode":"89509",
    "sg:province":"NV",
    "wof:name":"Sierra Meadows Insurance Inc",
    "wof:placetype":"venue"
},
  "geometry": {"coordinates":[-119.807283,39.493004],"type":"Point"}
}