{
  "type": "Feature",
  "properties": {
    "iso:country":"US",
    "sg:address":"5350 Capital Ct",
    "sg:city":"Reno",
    "sg:classifiers":[
        {
            "category":"Building & Trades",
            "subcategory":"Construction",
            "type":"Services"
        }
    ],
    "sg:phone":"+1 775 857 6615",
    "sg:postcode":"89502",
    "sg:province":"NV",
    "sg:tags":[
        "home",
        "builder"
    ],
    "wof:name":"R A Wheeler Construction Co",
    "wof:placetype":"venue"
},
  "geometry": {"coordinates":[-119.75286199999999,39.502903],"type":"Point"}
}