{
  "type": "Feature",
  "properties": {
    "iso:country":"US",
    "sg:address":"375 N Stephanie St Ste 1411",
    "sg:city":"Henderson",
    "sg:classifiers":[
        {
            "category":"Communications",
            "subcategory":"Newspaper",
            "type":"Services"
        },
        {
            "category":"Communications",
            "type":"Services"
        }
    ],
    "sg:phone":"+1 702 516 2882",
    "sg:postcode":"89014",
    "sg:province":"NV",
    "sg:tags":[
        "web",
        "design",
        "advertising"
    ],
    "wof:name":"Jedi Web Services",
    "wof:placetype":"venue"
},
  "geometry": {"coordinates":[-115.047923,36.054373],"type":"Point"}
}