{
  "type": "Feature",
  "properties": {
    "iso:country":"US",
    "sg:address":"3450 Boulder Hwy",
    "sg:city":"Las Vegas",
    "sg:classifiers":[
        {
            "category":"Retail",
            "subcategory":"Auto Repair",
            "type":"Services"
        }
    ],
    "sg:phone":"+1 702 457 7681",
    "sg:postcode":"89121",
    "sg:province":"NV",
    "sg:tags":[
        "repairing",
        "automobile"
    ],
    "wof:name":"Econo Lube N' Tune",
    "wof:placetype":"venue"
},
  "geometry": {"coordinates":[-115.097639,36.142255],"type":"Point"}
}