{
  "type": "Feature",
  "properties": {
    "iso:country":"US",
    "sg:address":"1515 E Tropicana Ave Ste 375",
    "sg:city":"Las Vegas",
    "sg:classifiers":[
        {
            "category":"Building & Trades",
            "subcategory":"Construction",
            "type":"Services"
        }
    ],
    "sg:phone":"+1 702 739 8010",
    "sg:postcode":"89119",
    "sg:province":"NV",
    "sg:tags":[
        "contractor"
    ],
    "wof:name":"Advance Construction Technology",
    "wof:placetype":"venue"
},
  "geometry": {"coordinates":[-115.132226,36.100753],"type":"Point"}
}