{
  "type": "Feature",
  "properties": {
    "iso:country":"US",
    "sg:address":"2261 S Rainbow Blvd",
    "sg:city":"Las Vegas",
    "sg:classifiers":[
        {
            "category":"Health Services",
            "subcategory":"Optometrist",
            "type":"Services"
        },
        {
            "category":"Shopping",
            "subcategory":"Optician",
            "type":"Retail Goods"
        }
    ],
    "sg:phone":"+1 702 254 0332",
    "sg:postcode":"89146",
    "sg:province":"NV",
    "sg:tags":[
        "eyewear"
    ],
    "sg:website":"www.eyesandopticslv.com",
    "wof:name":"Eyes & Optics",
    "wof:placetype":"venue"
},
  "geometry": {"coordinates":[-115.243146,36.146386],"type":"Point"}
}