{
  "type": "Feature",
  "properties": {
    "iso:country":"US",
    "sg:address":"2105 Westlund Dr",
    "sg:city":"Las Vegas",
    "sg:classifiers":[
        {
            "category":"Real Estate",
            "subcategory":"Real Estate Agent",
            "type":"Services"
        }
    ],
    "sg:phone":"+1 702 248 0011",
    "sg:postcode":"89102",
    "sg:province":"NV",
    "wof:name":"Heritage Group 1 Inc",
    "wof:placetype":"venue"
},
  "geometry": {"coordinates":[-115.173698,36.147624],"type":"Point"}
}