{
  "type": "Feature",
  "properties": {
    "iso:country":"US",
    "sg:address":"2649 Rungsted St",
    "sg:city":"Las Vegas",
    "sg:classifiers":[
        {
            "category":"Professional",
            "subcategory":"Management & Consulting",
            "type":"Services"
        }
    ],
    "sg:phone":"+1 702 431 2672",
    "sg:postcode":"89142",
    "sg:province":"NV",
    "sg:tags":[
        "business"
    ],
    "wof:name":"Online Exchange Consultants",
    "wof:placetype":"venue"
},
  "geometry": {"coordinates":[-115.060362,36.140409],"type":"Point"}
}