{
  "type": "Feature",
  "properties": {
    "iso:country":"US",
    "sg:address":"301 S Martin L King Blvd",
    "sg:city":"Las Vegas",
    "sg:classifiers":[
        {
            "category":"Home & Garden",
            "subcategory":"Furniture",
            "type":"Retail Goods"
        }
    ],
    "sg:phone":"+1 702 384 5870",
    "sg:postcode":"89106",
    "sg:province":"NV",
    "sg:tags":[
        "store"
    ],
    "wof:name":"Trs Inc",
    "wof:placetype":"venue"
},
  "geometry": {"coordinates":[-115.160608,36.169837],"type":"Point"}
}