{
  "type": "Feature",
  "properties": {
    "iso:country":"US",
    "sg:address":"345 Cheney St",
    "sg:city":"Reno",
    "sg:classifiers":[
        {
            "category":"Social Services",
            "type":"Services"
        }
    ],
    "sg:phone":"+1 775 323 1330",
    "sg:postcode":"89502",
    "sg:province":"NV",
    "wof:name":"Lemus Frank D Sr MA EDS Mft",
    "wof:placetype":"venue"
},
  "geometry": {"coordinates":[-119.80374,39.51837],"type":"Point"}
}