{
  "type": "Feature",
  "properties": {
    "iso:country":"US",
    "sg:address":"4424 Fernbrook Rd",
    "sg:city":"Las Vegas",
    "sg:classifiers":[
        {
            "category":"Building & Trades",
            "subcategory":"Landscaping Services",
            "type":"Services"
        }
    ],
    "sg:phone":"+1 702 364 5518",
    "sg:postcode":"89103",
    "sg:province":"NV",
    "sg:tags":[
        "landscape"
    ],
    "wof:name":"Curb Appeal",
    "wof:placetype":"venue"
},
  "geometry": {"coordinates":[-115.238648,36.10939],"type":"Point"}
}