{
  "type": "Feature",
  "properties": {
    "iso:country":"US",
    "sg:address":"3100 Dickerson Rd",
    "sg:city":"Reno",
    "sg:classifiers":[
        {
            "category":"Government",
            "subcategory":"Office",
            "type":"Public Place"
        }
    ],
    "sg:phone":"+1 775 334 3808",
    "sg:postcode":"89503",
    "sg:province":"NV",
    "sg:tags":[
        "village"
    ],
    "wof:name":"Oxbow Nature Study Area",
    "wof:placetype":"venue"
},
  "geometry": {"coordinates":[-119.844111,39.519838],"type":"Point"}
}