{
  "type": "Feature",
  "properties": {
    "iso:country":"US",
    "sg:address":"121 Los Altos Pkwy # 107",
    "sg:city":"Sparks",
    "sg:phone":"+1 775 354 2772",
    "sg:postcode":"89436",
    "sg:province":"NV",
    "wof:name":"Genghis Grill",
    "wof:placetype":"venue"
},
  "geometry": {"coordinates":[-119.74096299999999,39.583167],"type":"Point"}
}