{
  "type": "Feature",
  "properties": {
    "iso:country":"US",
    "sg:address":"8620 W Tropicana Avenue",
    "sg:city":"Las Vegas",
    "sg:classifiers":[
        {
            "category":"Banks & Credit Unions",
            "subcategory":"Bank",
            "type":"Services"
        }
    ],
    "sg:phone":"+1 702 252 8777",
    "sg:postcode":"89147",
    "sg:province":"NV",
    "sg:website":"www.tcbanknv.com",
    "wof:name":"Town & Country Bank",
    "wof:placetype":"venue"
},
  "geometry": {"coordinates":[-115.281181,36.100048],"type":"Point"}
}