{
  "type": "Feature",
  "properties": {
    "iso:country":"US",
    "sg:address":"330 S 3rd St",
    "sg:city":"Las Vegas",
    "sg:classifiers":[
        {
            "category":"Professional",
            "subcategory":"Lawyer & Legal Services",
            "type":"Services"
        }
    ],
    "sg:phone":"+1 702 388 8182",
    "sg:postcode":"89101",
    "sg:province":"NV",
    "wof:name":"Gonzales Xavier",
    "wof:placetype":"venue"
},
  "geometry": {"coordinates":[-115.144997,36.1675],"type":"Point"}
}