{
  "type": "Feature",
  "properties": {
    "iso:country":"US",
    "sg:address":"9620 Flying Eagle Ln",
    "sg:city":"Las Vegas",
    "sg:classifiers":[
        {
            "category":"Professional",
            "subcategory":"Management & Consulting",
            "type":"Services"
        }
    ],
    "sg:phone":"+1 702 896 1499",
    "sg:postcode":"89123",
    "sg:province":"NV",
    "sg:tags":[
        "consultant",
        "broker"
    ],
    "wof:name":"PMCS",
    "wof:placetype":"venue"
},
  "geometry": {"coordinates":[-115.166471,36.015319],"type":"Point"}
}