{
  "type": "Feature",
  "properties": {
    "iso:country":"US",
    "sg:address":"1945 Village Center Cir",
    "sg:city":"Las Vegas",
    "sg:classifiers":[
        {
            "category":"Health Services",
            "subcategory":"Doctor",
            "type":"Services"
        }
    ],
    "sg:phone":"+1 702 364 5100",
    "sg:postcode":"89134",
    "sg:province":"NV",
    "sg:tags":[
        "dentist",
        "orthodontist"
    ],
    "sg:website":"www.thalgott.com",
    "wof:name":"Summerlin Orthodontics",
    "wof:placetype":"venue"
},
  "geometry": {"coordinates":[-115.304002,36.192548],"type":"Point"}
}