{
  "type": "Feature",
  "properties": {
    "iso:country":"US",
    "sg:address":"819 S 4th St",
    "sg:city":"Las Vegas",
    "sg:classifiers":[
        {
            "category":"Building & Trades",
            "subcategory":"Construction",
            "type":"Services"
        }
    ],
    "sg:phone":"+1 702 383 7023",
    "sg:postcode":"89101",
    "sg:province":"NV",
    "sg:tags":[
        "contractor"
    ],
    "wof:name":"Breslin Builders",
    "wof:placetype":"venue"
},
  "geometry": {"coordinates":[-115.147696,36.16059],"type":"Point"}
}