{
  "type": "Feature",
  "properties": {
    "iso:country":"US",
    "sg:address":"1669 W. Horizon Ridge Pkwy",
    "sg:city":"Henderson",
    "sg:classifiers":[
        {
            "category":"Real Estate",
            "subcategory":"Real Estate Services",
            "type":"Services"
        }
    ],
    "sg:phone":"+1 702 510 9625",
    "sg:postcode":"89012",
    "sg:province":"NV",
    "sg:website":"www.lvshortsales.com",
    "wof:name":"i Realty",
    "wof:placetype":"venue"
},
  "geometry": {"coordinates":[-115.059436,36.013655],"type":"Point"}
}