{
  "type": "Feature",
  "properties": {
    "iso:country":"US",
    "sg:address":"1733 Stocker St",
    "sg:city":"North Las Vegas",
    "sg:classifiers":[
        {
            "category":"Shopping",
            "type":"Retail Goods"
        }
    ],
    "sg:phone":"+1 702 649 1407",
    "sg:postcode":"89030",
    "sg:province":"NV",
    "sg:tags":[
        "pet",
        "food",
        "supply"
    ],
    "wof:name":"Mastercraft Woodworks",
    "wof:placetype":"venue"
},
  "geometry": {"coordinates":[-115.139867,36.19203],"type":"Point"}
}