{
  "type": "Feature",
  "properties": {
    "iso:country":"US",
    "sg:address":"1331 S Rainbow Blvd Ste 200B",
    "sg:city":"Las Vegas",
    "sg:classifiers":[
        {
            "category":"Health Services",
            "subcategory":"Doctor",
            "type":"Services"
        }
    ],
    "sg:phone":"+1 702 255 2868",
    "sg:postcode":"89146",
    "sg:province":"NV",
    "sg:tags":[
        "obstetrician",
        "gynecologist"
    ],
    "wof:name":"Glassman Kramer & Scarff",
    "wof:placetype":"venue"
},
  "geometry": {"coordinates":[-115.244003,36.1563],"type":"Point"}
}