{
  "type": "Feature",
  "properties": {
    "iso:country":"US",
    "sg:address":"15 Carrington Way",
    "sg:city":"Reno",
    "sg:classifiers":[
        {
            "category":"Recreation",
            "type":"Entertainment"
        }
    ],
    "sg:phone":"+1 775 972 1009",
    "sg:postcode":"89506",
    "sg:province":"NV",
    "wof:name":"Netkarts Racing",
    "wof:placetype":"venue"
},
  "geometry": {"coordinates":[-119.838962,39.593144],"type":"Point"}
}