{
  "type": "Feature",
  "properties": {
    "iso:country":"US",
    "sg:address":"444 Riverside Rd",
    "sg:city":"Mesquite",
    "sg:classifiers":[
        {
            "category":"Real Estate",
            "subcategory":"Developer",
            "type":"Services"
        }
    ],
    "sg:phone":"+1 702 346 8406",
    "sg:postcode":"89027",
    "sg:province":"NV",
    "wof:name":"Touchtone Development",
    "wof:placetype":"venue"
},
  "geometry": {"coordinates":[-114.093424,36.795579],"type":"Point"}
}