{
  "type": "Feature",
  "properties": {
    "iso:country":"US",
    "sg:address":"30 B St",
    "sg:city":"Virginia City",
    "sg:classifiers":[
        {
            "category":"Restaurant",
            "type":"Food & Drink"
        }
    ],
    "sg:phone":"+1 775 847 9288",
    "sg:postcode":"89440",
    "sg:province":"NV",
    "sg:tags":[
        "eating"
    ],
    "wof:name":"Mandarin Garden Chinese Rest",
    "wof:placetype":"venue"
},
  "geometry": {"coordinates":[-119.649606,39.312247],"type":"Point"}
}