{
  "type": "Feature",
  "properties": {
    "iso:country":"US",
    "sg:address":"740 N Eastern Ave",
    "sg:city":"Las Vegas",
    "sg:classifiers":[
        {
            "category":"Real Estate",
            "subcategory":"Real Estate Operator",
            "type":"Services"
        }
    ],
    "sg:phone":"+1 702 732 1664",
    "sg:postcode":"89101",
    "sg:province":"NV",
    "sg:tags":[
        "property",
        "lessor"
    ],
    "wof:name":"Kdox",
    "wof:placetype":"venue"
},
  "geometry": {"coordinates":[-115.11605299999999,36.177515],"type":"Point"}
}