{
  "type": "Feature",
  "properties": {
    "iso:country":"US",
    "sg:address":"275 Mesa Blvd",
    "sg:city":"Mesquite",
    "sg:classifiers":[
        {
            "category":"Shopping",
            "subcategory":"Gifts & Souvenirs",
            "type":"Retail Goods"
        }
    ],
    "sg:phone":"+1 702 346 3838",
    "sg:postcode":"89027",
    "sg:province":"NV",
    "sg:tags":[
        "shop"
    ],
    "wof:name":"Gifts Galore and Liquor Store",
    "wof:placetype":"venue"
},
  "geometry": {"coordinates":[-114.064404,36.815723],"type":"Point"}
}