{
  "type": "Feature",
  "properties": {
    "iso:country":"US",
    "sg:address":"1010 12th St",
    "sg:city":"Sparks",
    "sg:classifiers":[
        {
            "category":"Manufacturing",
            "subcategory":"Toys & Sporting Goods",
            "type":"Manufacturing & Wholesale Goods"
        }
    ],
    "sg:phone":"+1 775 786 4775",
    "sg:postcode":"89431",
    "sg:province":"NV",
    "sg:tags":[
        "mfg"
    ],
    "wof:name":"Eibert Enterprises",
    "wof:placetype":"venue"
},
  "geometry": {"coordinates":[-119.757965,39.543555],"type":"Point"}
}