{
  "type": "Feature",
  "properties": {
    "iso:country":"US",
    "sg:address":"3095 E Patrick Ln",
    "sg:city":"Las Vegas",
    "sg:classifiers":[
        {
            "category":"Utilities",
            "subcategory":"Refuse",
            "type":"Services"
        }
    ],
    "sg:phone":"+1 702 898 3400",
    "sg:postcode":"89120",
    "sg:province":"NV",
    "sg:tags":[
        "crime",
        "trauma",
        "up",
        "clean",
        "scene"
    ],
    "sg:website":"www.anniethemaid.com",
    "wof:name":"Abatement Technology Masters",
    "wof:placetype":"venue"
},
  "geometry": {"coordinates":[-115.109274,36.078909],"type":"Point"}
}