{
  "type": "Feature",
  "properties": {
    "iso:country":"US",
    "sg:address":"3226 Kemp St",
    "sg:city":"North Las Vegas",
    "sg:classifiers":[
        {
            "category":"Social Services",
            "subcategory":"Adult Care",
            "type":"Services"
        }
    ],
    "sg:phone":"+1 702 636 1087",
    "sg:postcode":"89032",
    "sg:province":"NV",
    "sg:tags":[
        "home",
        "residential"
    ],
    "wof:name":"R J Assisted Living Ctr",
    "wof:placetype":"venue"
},
  "geometry": {"coordinates":[-115.17668,36.218999],"type":"Point"}
}