{
  "type": "Feature",
  "properties": {
    "iso:country":"US",
    "sg:address":"6705 Squaw Mountain Dr",
    "sg:city":"Las Vegas",
    "sg:classifiers":[
        {
            "category":"Professional",
            "subcategory":"Computer Services",
            "type":"Services"
        }
    ],
    "sg:phone":"+1 702 395 2127",
    "sg:postcode":"89130",
    "sg:province":"NV",
    "sg:tags":[
        "datum"
    ],
    "wof:name":"Catspaw Enterprises",
    "wof:placetype":"venue"
},
  "geometry": {"coordinates":[-115.245625,36.255406],"type":"Point"}
}