{
  "type": "Feature",
  "properties": {
    "iso:country":"US",
    "sg:address":"1667 Shadow Wood Ct",
    "sg:city":"Reno",
    "sg:classifiers":[
        {
            "category":"Professional",
            "subcategory":"Engineering",
            "type":"Services"
        }
    ],
    "sg:phone":"+1 775 787 8815",
    "sg:postcode":"89523",
    "sg:province":"NV",
    "wof:name":"Advanced Engineering Services",
    "wof:placetype":"venue"
},
  "geometry": {"coordinates":[-119.891852,39.528238],"type":"Point"}
}