{
  "type": "Feature",
  "properties": {
    "iso:country":"US",
    "sg:address":"3474 Forest View Ct",
    "sg:city":"Reno",
    "sg:classifiers":[
        {
            "category":"Professional",
            "subcategory":"Employment Agencies",
            "type":"Services"
        }
    ],
    "sg:phone":"+1 775 852 2062",
    "sg:postcode":"89511",
    "sg:province":"NV",
    "sg:tags":[
        "help",
        "supply"
    ],
    "wof:name":"Techquest Staffing LLC",
    "wof:placetype":"venue"
},
  "geometry": {"coordinates":[-119.818045,39.417031],"type":"Point"}
}