{
  "type": "Feature",
  "properties": {
    "iso:country":"US",
    "sg:address":"1652 Wedekind Rd",
    "sg:city":"Reno",
    "sg:classifiers":[
        {
            "category":"Real Estate",
            "subcategory":"Real Estate Operator",
            "type":"Services"
        }
    ],
    "sg:phone":"+1 775 322 1040",
    "sg:postcode":"89512",
    "sg:province":"NV",
    "sg:tags":[
        "building",
        "nonresidential"
    ],
    "wof:name":"Centennial Park Annex",
    "wof:placetype":"venue"
},
  "geometry": {"coordinates":[-119.802028,39.546417],"type":"Point"}
}