{
  "type": "Feature",
  "properties": {
    "iso:country":"US",
    "sg:address":"534 Lander St",
    "sg:city":"Reno",
    "sg:classifiers":[
        {
            "category":"Real Estate",
            "subcategory":"Architect",
            "type":"Services"
        }
    ],
    "sg:phone":"+1 775 329 7624",
    "sg:postcode":"89509",
    "sg:province":"NV",
    "sg:tags":[
        "engineering",
        "architectural"
    ],
    "wof:name":"Barada Fuetsch Architects AIA",
    "wof:placetype":"venue"
},
  "geometry": {"coordinates":[-119.815293,39.519397],"type":"Point"}
}