{
  "type": "Feature",
  "properties": {
    "iso:country":"US",
    "sg:address":"350 Hunter Lake Dr",
    "sg:city":"Reno",
    "sg:classifiers":[
        {
            "category":"Education",
            "subcategory":"School",
            "type":"Public Place"
        }
    ],
    "sg:phone":"+1 775 333 5358",
    "sg:postcode":"89509",
    "sg:province":"NV",
    "wof:name":"Washoe County School District",
    "wof:placetype":"venue"
},
  "geometry": {"coordinates":[-119.835718,39.517279],"type":"Point"}
}