{
  "type": "Feature",
  "properties": {
    "iso:country":"US",
    "sg:address":"5055 Sun Valley Blvd",
    "sg:city":"Sun Valley",
    "sg:classifiers":[
        {
            "category":"Professional",
            "subcategory":"Accounting & Tax Preparation",
            "type":"Services"
        }
    ],
    "sg:phone":"+1 775 284 3250",
    "sg:postcode":"89433",
    "sg:province":"NV",
    "sg:tags":[
        "return",
        "filing"
    ],
    "wof:name":"H & R Block Tax Svc",
    "wof:placetype":"venue"
},
  "geometry": {"coordinates":[-119.78102,39.574884],"type":"Point"}
}