{
  "type": "Feature",
  "properties": {
    "iso:country":"US",
    "sg:address":"4635 W Flamingo Rd",
    "sg:city":"Las Vegas",
    "sg:classifiers":[
        {
            "category":"Shopping",
            "subcategory":"Jewelry",
            "type":"Retail Goods"
        },
        {
            "category":"Shopping",
            "subcategory":"Pawn Shop",
            "type":"Retail Goods"
        }
    ],
    "sg:phone":"+1 702 252 7296",
    "sg:postcode":"89103",
    "sg:province":"NV",
    "sg:website":"www.superpawn.com",
    "wof:name":"Superpawn",
    "wof:placetype":"venue"
},
  "geometry": {"coordinates":[-115.204364,36.115282],"type":"Point"}
}