{
  "type": "Feature",
  "properties": {
    "iso:country":"US",
    "sg:address":"19 Pangloss St",
    "sg:city":"Henderson",
    "sg:classifiers":[
        {
            "category":"Home & Garden",
            "subcategory":"Home Furnishings",
            "type":"Retail Goods"
        }
    ],
    "sg:phone":"+1 702 567 6839",
    "sg:postcode":"89002",
    "sg:province":"NV",
    "wof:name":"Jackies Drapes & More",
    "wof:placetype":"venue"
},
  "geometry": {"coordinates":[-114.99011299999999,35.998562],"type":"Point"}
}