{
  "type": "Feature",
  "properties": {
    "iso:country":"US",
    "sg:address":"4515 W Sahara Ave",
    "sg:city":"Las Vegas",
    "sg:classifiers":[
        {
            "category":"Real Estate",
            "subcategory":"Real Estate Agent",
            "type":"Services"
        }
    ],
    "sg:phone":"+1 702 315 6100",
    "sg:postcode":"89102",
    "sg:province":"NV",
    "sg:website":"www.casalasvegas.com",
    "wof:name":"Century 21",
    "wof:placetype":"venue"
},
  "geometry": {"coordinates":[-115.200701,36.144406],"type":"Point"}
}