{
  "type": "Feature",
  "properties": {
    "iso:country":"US",
    "sg:address":"924 Elliot Park Ave",
    "sg:city":"North Las Vegas",
    "sg:classifiers":[
        {
            "category":"Professional",
            "subcategory":"Management & Consulting",
            "type":"Services"
        }
    ],
    "sg:phone":"+1 702 633 4159",
    "sg:postcode":"89032",
    "sg:province":"NV",
    "wof:name":"Modern Transport Inc",
    "wof:placetype":"venue"
},
  "geometry": {"coordinates":[-115.154394,36.232456],"type":"Point"}
}