{
  "type": "Feature",
  "properties": {
    "iso:country":"US",
    "sg:address":"50 Emery St",
    "sg:city":"Pahrump",
    "sg:classifiers":[
        {
            "category":"Health Services",
            "subcategory":"Doctor",
            "type":"Services"
        }
    ],
    "sg:phone":"+1 775 727 9600",
    "sg:postcode":"89048",
    "sg:province":"NV",
    "sg:tags":[
        "physician",
        "surgeon"
    ],
    "wof:name":"Pahrump Dermatology",
    "wof:placetype":"venue"
},
  "geometry": {"coordinates":[-115.992238,36.218544],"type":"Point"}
}