{
  "type": "Feature",
  "properties": {
    "iso:country":"US",
    "sg:address":"640 Kuenzli St",
    "sg:city":"Reno",
    "sg:classifiers":[
        {
            "category":"Food & Beverages",
            "subcategory":"Groceries & Convenience Stores",
            "type":"Retail Goods"
        }
    ],
    "sg:phone":"+1 775 337 2972",
    "sg:postcode":"89502",
    "sg:province":"NV",
    "sg:tags":[
        "grocer"
    ],
    "wof:name":"B & B Food & Liquor",
    "wof:placetype":"venue"
},
  "geometry": {"coordinates":[-119.803448,39.528278],"type":"Point"}
}