{
  "type": "Feature",
  "properties": {
    "iso:country":"US",
    "sg:address":"6545 Alta Dr",
    "sg:city":"Las Vegas",
    "sg:classifiers":[
        {
            "category":"Professional",
            "subcategory":"Accounting & Tax Preparation",
            "type":"Services"
        }
    ],
    "sg:phone":"+1 702 386 6862",
    "sg:postcode":"89107",
    "sg:province":"NV",
    "sg:tags":[
        "billing"
    ],
    "wof:name":"Nevada Medical Billing",
    "wof:placetype":"venue"
},
  "geometry": {"coordinates":[-115.23985,36.166344],"type":"Point"}
}