{
  "type": "Feature",
  "properties": {
    "iso:country":"US",
    "sg:address":"7220 S Paradise Rd",
    "sg:city":"Las Vegas",
    "sg:classifiers":[
        {
            "category":"Place Of Worship",
            "subcategory":"Church",
            "type":"Public Place"
        }
    ],
    "sg:phone":"+1 702 326 1642",
    "sg:postcode":"89119",
    "sg:province":"NV",
    "sg:website":"www.thestream.us/",
    "wof:name":"The Stream",
    "wof:placetype":"venue"
},
  "geometry": {"coordinates":[-115.140593,36.058596],"type":"Point"}
}