{
  "type": "Feature",
  "properties": {
    "iso:country":"US",
    "sg:address":"7400 Bisonwood Ave",
    "sg:city":"Las Vegas",
    "sg:classifiers":[
        {
            "category":"Arts & Performance",
            "subcategory":"Theater",
            "type":"Entertainment"
        }
    ],
    "sg:phone":"+1 702 639 6550",
    "sg:postcode":"89131",
    "sg:province":"NV",
    "sg:tags":[
        "bureau"
    ],
    "sg:website":"www.classique-productions.com",
    "wof:name":"Classique Productions",
    "wof:placetype":"venue"
},
  "geometry": {"coordinates":[-115.259345,36.292121],"type":"Point"}
}