{
  "type": "Feature",
  "properties": {
    "iso:country":"US",
    "sg:address":"7035 Durango St",
    "sg:city":"Las Vegas",
    "sg:classifiers":[
        {
            "category":"Food & Beverages",
            "subcategory":"Bakery",
            "type":"Retail Goods"
        }
    ],
    "sg:phone":"+1 702 435 7316",
    "sg:postcode":"89101",
    "sg:province":"NV",
    "sg:tags":[
        "sandwich"
    ],
    "wof:name":"Arby's Roast Beef Sandwich Restaurants",
    "wof:placetype":"venue"
},
  "geometry": {"coordinates":[-115.27948,36.060226],"type":"Point"}
}