{
  "type": "Feature",
  "properties": {
    "iso:country":"US",
    "sg:address":"1117 Desert Ln",
    "sg:city":"Las Vegas",
    "sg:classifiers":[
        {
            "category":"Arts & Performance",
            "subcategory":"Theater",
            "type":"Entertainment"
        }
    ],
    "sg:phone":"+1 702 759 9734",
    "sg:postcode":"89102",
    "sg:province":"NV",
    "sg:tags":[
        "management"
    ],
    "wof:name":"Starmakers USA",
    "wof:placetype":"venue"
},
  "geometry": {"coordinates":[-115.161727,36.157209],"type":"Point"}
}