{
  "type": "Feature",
  "properties": {
    "iso:country":"US",
    "sg:address":"890 Marita Ct",
    "sg:city":"Boulder City",
    "sg:classifiers":[
        {
            "category":"Travel",
            "subcategory":"Travel Agent",
            "type":"Entertainment"
        }
    ],
    "sg:phone":"+1 702 293 3807",
    "sg:postcode":"89005",
    "sg:province":"NV",
    "sg:tags":[
        "agency"
    ],
    "wof:name":"Boulder City Travel",
    "wof:placetype":"venue"
},
  "geometry": {"coordinates":[-114.839535,35.965319],"type":"Point"}
}