{
  "type": "Feature",
  "properties": {
    "iso:country":"US",
    "sg:address":"2290 E Flamingo Rd",
    "sg:city":"Las Vegas",
    "sg:classifiers":[
        {
            "category":"Communications",
            "subcategory":"Film & Video Production",
            "type":"Services"
        }
    ],
    "sg:phone":"+1 702 731 9447",
    "sg:postcode":"89119",
    "sg:province":"NV",
    "sg:tags":[
        "editing",
        "tape"
    ],
    "wof:name":"U-Edit Complete Video Svc",
    "wof:placetype":"venue"
},
  "geometry": {"coordinates":[-115.119775,36.114752],"type":"Point"}
}