{
  "type": "Feature",
  "properties": {
    "iso:country":"US",
    "sg:address":"777 W Lake Mead Pkwy",
    "sg:city":"Henderson",
    "sg:classifiers":[
        {
            "category":"Restaurant",
            "type":"Food & Drink"
        }
    ],
    "sg:phone":"+1 702 558 7000",
    "sg:postcode":"89015",
    "sg:province":"NV",
    "sg:tags":[
        "mexican",
        "seafood",
        "steakhouse"
    ],
    "sg:website":"www.gardunosrestaurants.com",
    "wof:name":"Garduno's Margarita Factory",
    "wof:placetype":"venue"
},
  "geometry": {"coordinates":[-115.006861,36.034385],"type":"Point"}
}