{
  "type": "Feature",
  "properties": {
    "iso:country":"US",
    "sg:address":"410 S 16th St",
    "sg:city":"Las Vegas",
    "sg:classifiers":[
        {
            "category":"Wholesale",
            "subcategory":"Durable Goods & Equipment",
            "type":"Manufacturing & Wholesale Goods"
        }
    ],
    "sg:phone":"+1 702 379 0147",
    "sg:postcode":"89101",
    "sg:province":"NV",
    "sg:tags":[
        "importer"
    ],
    "wof:name":"Caravan Imports Co",
    "wof:placetype":"venue"
},
  "geometry": {"coordinates":[-115.131391,36.158907],"type":"Point"}
}