{
  "type": "Feature",
  "properties": {
    "iso:country":"US",
    "sg:address":"1732 Lantana Dr",
    "sg:city":"Minden",
    "sg:classifiers":[
        {
            "category":"Professional",
            "subcategory":"Business Services",
            "type":"Services"
        }
    ],
    "sg:phone":"+1 510 461 2803",
    "sg:postcode":"89423",
    "sg:province":"NV",
    "wof:name":"Kbh Enterprises",
    "wof:placetype":"venue"
},
  "geometry": {"coordinates":[-119.76916,38.964335],"type":"Point"}
}