{
  "type": "Feature",
  "properties": {
    "iso:country":"US",
    "sg:address":"2180 E Warm Springs Rd",
    "sg:city":"Las Vegas",
    "sg:classifiers":[
        {
            "category":"Professional",
            "subcategory":"Engineering",
            "type":"Services"
        }
    ],
    "sg:phone":"+1 702 301 6555",
    "sg:postcode":"89119",
    "sg:province":"NV",
    "sg:tags":[
        "engineer"
    ],
    "wof:name":"International Consulting Engnr",
    "wof:placetype":"venue"
},
  "geometry": {"coordinates":[-115.11947,36.05704],"type":"Point"}
}