{
  "type": "Feature",
  "properties": {
    "iso:country":"US",
    "sg:address":"4650 Wedekind Rd",
    "sg:city":"Sparks",
    "sg:classifiers":[
        {
            "category":"Health Services",
            "subcategory":"Doctor",
            "type":"Services"
        }
    ],
    "sg:phone":"+1 775 356 8254",
    "sg:postcode":"89431",
    "sg:province":"NV",
    "sg:tags":[
        "dentist"
    ],
    "wof:name":"Webber R Dean DDS Inc",
    "wof:placetype":"venue"
},
  "geometry": {"coordinates":[-119.75965,39.558477],"type":"Point"}
}