{
  "type": "Feature",
  "properties": {
    "iso:country":"US",
    "sg:address":"4430 Fairview Rd",
    "sg:city":"Reno",
    "sg:classifiers":[
        {
            "category":"Social Services",
            "type":"Services"
        }
    ],
    "sg:phone":"+1 775 853 8592",
    "sg:postcode":"89511",
    "sg:province":"NV",
    "sg:tags":[
        "counseling",
        "genetic"
    ],
    "wof:name":"Northern Nevada Genetic Cnslng",
    "wof:placetype":"venue"
},
  "geometry": {"coordinates":[-119.805634,39.436004],"type":"Point"}
}