{
  "type": "Feature",
  "properties": {
    "iso:country":"US",
    "sg:address":"178 S Maine St",
    "sg:city":"Fallon",
    "sg:classifiers":[
        {
            "category":"Professional",
            "subcategory":"Engineering",
            "type":"Services"
        }
    ],
    "sg:phone":"+1 775 423 2188",
    "sg:postcode":"89406",
    "sg:province":"NV",
    "sg:tags":[
        "engineer"
    ],
    "sg:website":"www.lumosengineering.com",
    "wof:name":"Lumos & Assoc Inc",
    "wof:placetype":"venue"
},
  "geometry": {"coordinates":[-118.77713300000001,39.473232],"type":"Point"}
}