{
  "type": "Feature",
  "properties": {
    "iso:country":"US",
    "sg:address":"3709 Edison Ave",
    "sg:city":"Las Vegas",
    "sg:classifiers":[
        {
            "category":"Professional",
            "subcategory":"Computer Services",
            "type":"Services"
        }
    ],
    "sg:phone":"+1 702 456 4757",
    "sg:postcode":"89121",
    "sg:province":"NV",
    "sg:tags":[
        "datum"
    ],
    "wof:name":"E Z Designers",
    "wof:placetype":"venue"
},
  "geometry": {"coordinates":[-115.09437200000001,36.125527],"type":"Point"}
}