{
  "type": "Feature",
  "properties": {
    "iso:country":"US",
    "sg:address":"66 E Basic Rd",
    "sg:city":"Henderson",
    "sg:classifiers":[
        {
            "category":"Retail",
            "subcategory":"Auto Repair",
            "type":"Services"
        }
    ],
    "sg:phone":"+1 702 564 5613",
    "sg:postcode":"89015",
    "sg:province":"NV",
    "sg:tags":[
        "repairing",
        "automobile"
    ],
    "wof:name":"Duaine's Automotive",
    "wof:placetype":"venue"
},
  "geometry": {"coordinates":[-114.974998,36.032501],"type":"Point"}
}