{
  "type": "Feature",
  "properties": {
    "iso:country":"US",
    "sg:address":"1140 Autumn Hills Rd",
    "sg:city":"Gardnerville",
    "sg:classifiers":[
        {
            "category":"Retail",
            "subcategory":"Veterinary Services",
            "type":"Services"
        }
    ],
    "sg:phone":"+1 775 887 3668",
    "sg:postcode":"89460",
    "sg:province":"NV",
    "sg:tags":[
        "veterinarian"
    ],
    "wof:name":"High Siearra Equine",
    "wof:placetype":"venue"
},
  "geometry": {"coordinates":[-119.843898,38.920456],"type":"Point"}
}