{
  "type": "Feature",
  "properties": {
    "iso:country":"US",
    "sg:address":"2161 Fountain Springs Dr",
    "sg:city":"Henderson",
    "sg:classifiers":[
        {
            "category":"Professional",
            "subcategory":"Management & Consulting",
            "type":"Services"
        }
    ],
    "sg:phone":"+1 702 897 3027",
    "sg:postcode":"89074",
    "sg:province":"NV",
    "wof:name":"Broddarp of Nevada Inc",
    "wof:placetype":"venue"
},
  "geometry": {"coordinates":[-115.082864,36.02728],"type":"Point"}
}