{
  "type": "Feature",
  "properties": {
    "iso:country":"US",
    "sg:address":"1995 Tampa St",
    "sg:city":"Reno",
    "sg:classifiers":[
        {
            "category":"Building & Trades",
            "subcategory":"Construction",
            "type":"Services"
        }
    ],
    "sg:phone":"+1 775 329 2427",
    "sg:postcode":"89512",
    "sg:province":"NV",
    "sg:tags":[
        "maker",
        "cabinet"
    ],
    "wof:name":"Damm's Custom Cabinet Shop",
    "wof:placetype":"venue"
},
  "geometry": {"coordinates":[-119.802808,39.549731],"type":"Point"}
}