{
  "type": "Feature",
  "properties": {
    "iso:country":"US",
    "sg:address":"4055 S Maryland Pkwy",
    "sg:city":"Las Vegas",
    "sg:classifiers":[
        {
            "category":"Banks & Credit Unions",
            "subcategory":"Bank",
            "type":"Services"
        },
        {
            "category":"Banks & Credit Unions",
            "subcategory":"Financial Services",
            "type":"Services"
        }
    ],
    "sg:phone":"+1 702 650 0256",
    "sg:postcode":"89119",
    "sg:province":"NV",
    "sg:tags":[
        "broker",
        "mortgage"
    ],
    "sg:website":"www.wamu.com",
    "wof:name":"Washington Mutual",
    "wof:placetype":"venue"
},
  "geometry": {"coordinates":[-115.137854,36.116077],"type":"Point"}
}