{
  "type": "Feature",
  "properties": {
    "iso:country":"US",
    "sg:address":"615 S 7th St",
    "sg:city":"Las Vegas",
    "sg:classifiers":[
        {
            "category":"Professional",
            "subcategory":"Lawyer & Legal Services",
            "type":"Services"
        }
    ],
    "sg:phone":"+1 702 477 0443",
    "sg:postcode":"89101",
    "sg:province":"NV",
    "wof:name":"Lutfy E Leland",
    "wof:placetype":"venue"
},
  "geometry": {"coordinates":[-115.142186,36.161776],"type":"Point"}
}