{
  "type": "Feature",
  "properties": {
    "iso:country":"US",
    "sg:address":"1001 Dumont Blvd",
    "sg:city":"Las Vegas",
    "sg:classifiers":[
        {
            "category":"Real Estate",
            "subcategory":"Real Estate Operator",
            "type":"Services"
        }
    ],
    "sg:phone":"+1 702 735 4725",
    "sg:postcode":"89169",
    "sg:province":"NV",
    "sg:tags":[
        "apartment"
    ],
    "wof:name":"Rainwalk Apartments",
    "wof:placetype":"venue"
},
  "geometry": {"coordinates":[-115.138552,36.125303],"type":"Point"}
}