{
  "type": "Feature",
  "properties": {
    "iso:country":"US",
    "sg:address":"3250 S Fort Apache Rd",
    "sg:city":"Las Vegas",
    "sg:classifiers":[
        {
            "category":"Social Services",
            "subcategory":"Adult Care",
            "type":"Services"
        }
    ],
    "sg:phone":"+1 702 256 6500",
    "sg:postcode":"89117",
    "sg:province":"NV",
    "sg:tags":[
        "residential"
    ],
    "wof:name":"Sunlake Terrace",
    "wof:placetype":"venue"
},
  "geometry": {"coordinates":[-115.297032,36.131697],"type":"Point"}
}