{
  "type": "Feature",
  "properties": {
    "iso:country":"US",
    "sg:address":"5980 W Cougar Ave",
    "sg:city":"Las Vegas",
    "sg:classifiers":[
        {
            "category":"Building & Trades",
            "subcategory":"Construction",
            "type":"Services"
        }
    ],
    "sg:phone":"+1 702 651 8100",
    "sg:postcode":"89139",
    "sg:province":"NV",
    "sg:tags":[
        "contractor"
    ],
    "sg:website":"www.terracontracting.com",
    "wof:name":"Terra Contracting Inc",
    "wof:placetype":"venue"
},
  "geometry": {"coordinates":[-115.22402,36.03365],"type":"Point"}
}