{
  "type": "Feature",
  "properties": {
    "iso:country":"US",
    "sg:address":"1108 Shirleyann Ln",
    "sg:city":"Las Vegas",
    "sg:classifiers":[
        {
            "category":"Personal",
            "type":"Services"
        }
    ],
    "sg:phone":"+1 702 614 9547",
    "sg:postcode":"89128",
    "sg:province":"NV",
    "sg:tags":[
        "therapist",
        "massage"
    ],
    "wof:name":"Body Mechanix",
    "wof:placetype":"venue"
},
  "geometry": {"coordinates":[-115.270546,36.184928],"type":"Point"}
}