{
  "type": "Feature",
  "properties": {
    "iso:country":"US",
    "sg:address":"115 W Moana Ln",
    "sg:city":"Reno",
    "sg:classifiers":[
        {
            "category":"Home & Garden",
            "subcategory":"Furniture",
            "type":"Retail Goods"
        },
        {
            "category":"Home & Garden",
            "subcategory":"Carpets & Floor Coverings",
            "type":"Retail Goods"
        }
    ],
    "sg:phone":"+1 775 825 5988",
    "sg:postcode":"89509",
    "sg:province":"NV",
    "sg:tags":[
        "store",
        "mattress"
    ],
    "wof:name":"Furniture Superstore",
    "wof:placetype":"venue"
},
  "geometry": {"coordinates":[-119.797961,39.491355],"type":"Point"}
}