{
  "type": "Feature",
  "properties": {
    "iso:country":"US",
    "sg:address":"1625 8th St",
    "sg:city":"Minden",
    "sg:classifiers":[
        {
            "category":"Government",
            "subcategory":"Office",
            "type":"Public Place"
        }
    ],
    "sg:phone":"+1 775 782 9961",
    "sg:postcode":"89423",
    "sg:province":"NV",
    "wof:name":"Honorable David Gamble",
    "wof:placetype":"venue"
},
  "geometry": {"coordinates":[-119.76494,38.955302],"type":"Point"}
}