{
  "type": "Feature",
  "properties": {
    "iso:country":"US",
    "sg:address":"2909 W Charleston Blvd",
    "sg:city":"Las Vegas",
    "sg:classifiers":[
        {
            "category":"Building & Trades",
            "subcategory":"Construction",
            "type":"Services"
        }
    ],
    "sg:phone":"+1 702 304 4457",
    "sg:postcode":"89102",
    "sg:province":"NV",
    "sg:tags":[
        "comm"
    ],
    "wof:name":"Hi-Con Inc",
    "wof:placetype":"venue"
},
  "geometry": {"coordinates":[-115.181824,36.158862],"type":"Point"}
}