{
  "type": "Feature",
  "properties": {
    "iso:country":"US",
    "sg:address":"6636 Ironbound Bay Ave",
    "sg:city":"Las Vegas",
    "sg:classifiers":[
        {
            "category":"Real Estate",
            "subcategory":"Real Estate Agent",
            "type":"Services"
        }
    ],
    "sg:phone":"+1 702 233 2348",
    "sg:postcode":"89139",
    "sg:province":"NV",
    "wof:name":"Sapphire Realty",
    "wof:placetype":"venue"
},
  "geometry": {"coordinates":[-115.238082,36.043741],"type":"Point"}
}