{
  "type": "Feature",
  "properties": {
    "iso:country":"US",
    "sg:address":"8447 W Lake Mead Boulevard",
    "sg:city":"Las Vegas",
    "sg:classifiers":[
        {
            "category":"Shopping",
            "subcategory":"Optician",
            "type":"Retail Goods"
        }
    ],
    "sg:phone":"+1 702 228 1333",
    "sg:postcode":"89128",
    "sg:province":"NV",
    "sg:tags":[
        "eyewear"
    ],
    "wof:name":"Nu Vision Sport Optics",
    "wof:placetype":"venue"
},
  "geometry": {"coordinates":[-115.279746,36.198034],"type":"Point"}
}