{
  "type": "Feature",
  "properties": {
    "iso:country":"US",
    "sg:address":"458 Niles Way",
    "sg:city":"Reno",
    "sg:classifiers":[
        {
            "category":"Retail",
            "subcategory":"Laundry & Dry Cleaning",
            "type":"Services"
        }
    ],
    "sg:phone":"+1 775 287 7195",
    "sg:postcode":"89506",
    "sg:province":"NV",
    "sg:tags":[
        "cleaners",
        "rug",
        "carpet"
    ],
    "wof:name":"Best Steam Clean Carpet Clng",
    "wof:placetype":"venue"
},
  "geometry": {"coordinates":[-119.842473,39.645641],"type":"Point"}
}