{
  "type": "Feature",
  "properties": {
    "iso:country":"US",
    "sg:address":"180 Cassia Way",
    "sg:city":"Henderson",
    "sg:classifiers":[
        {
            "category":"Insurance",
            "subcategory":"Title Insurance",
            "type":"Services"
        },
        {
            "category":"Real Estate",
            "subcategory":"Real Estate Services",
            "type":"Services"
        }
    ],
    "sg:phone":"+1 702 568 7464",
    "sg:postcode":"89014",
    "sg:province":"NV",
    "sg:tags":[
        "company",
        "carrier",
        "abstract"
    ],
    "wof:name":"First American Title Insur Co",
    "wof:placetype":"venue"
},
  "geometry": {"coordinates":[-115.02674399999999,36.039537],"type":"Point"}
}