{
  "type": "Feature",
  "properties": {
    "iso:country":"US",
    "sg:address":"2407 Miki Ct",
    "sg:city":"Henderson",
    "sg:classifiers":[
        {
            "category":"Shopping",
            "subcategory":"Discount & Variety Stores",
            "type":"Retail Goods"
        }
    ],
    "sg:phone":"+1 702 596 2269",
    "sg:postcode":"89052",
    "sg:province":"NV",
    "sg:tags":[
        "merchandise",
        "general"
    ],
    "wof:name":"JMS Wholesale Enterprises",
    "wof:placetype":"venue"
},
  "geometry": {"coordinates":[-115.094395,35.997746],"type":"Point"}
}