{
  "type": "Feature",
  "properties": {
    "iso:country":"US",
    "sg:address":"2659 Fuller Ave",
    "sg:city":"Minden",
    "sg:classifiers":[
        {
            "category":"Autos & Motor Vehicles",
            "subcategory":"Recreational Vehicle Sales",
            "type":"Retail Goods"
        }
    ],
    "sg:phone":"+1 775 267 4566",
    "sg:postcode":"89423",
    "sg:province":"NV",
    "wof:name":"Rv Options",
    "wof:placetype":"venue"
},
  "geometry": {"coordinates":[-119.723882,39.027067],"type":"Point"}
}