{
  "type": "Feature",
  "properties": {
    "iso:country":"US",
    "sg:address":"1901 Kransten Dr",
    "sg:city":"Henderson",
    "sg:classifiers":[
        {
            "category":"Building & Trades",
            "subcategory":"Plumbing",
            "type":"Services"
        }
    ],
    "sg:phone":"+1 702 278 4747",
    "sg:postcode":"89074",
    "sg:province":"NV",
    "sg:tags":[
        "mechanical",
        "contractor"
    ],
    "wof:name":"Performance Mechanical Inc",
    "wof:placetype":"venue"
},
  "geometry": {"coordinates":[-115.070454,36.047204],"type":"Point"}
}