{
  "type": "Feature",
  "properties": {
    "iso:country":"US",
    "sg:address":"2200 E Serene Avenue #3306",
    "sg:city":"Las Vegas",
    "sg:classifiers":[
        {
            "category":"Home & Garden",
            "subcategory":"Building Materials",
            "type":"Retail Goods"
        }
    ],
    "sg:phone":"+1 702 837 4300",
    "sg:postcode":"89123",
    "sg:province":"NV",
    "sg:tags":[
        "supply"
    ],
    "wof:name":"The Home Depot #3306",
    "wof:placetype":"venue"
},
  "geometry": {"coordinates":[-115.124187,36.02144],"type":"Point"}
}