{
  "type": "Feature",
  "properties": {
    "iso:country":"US",
    "sg:address":"2215 Thomas W Ryan Blvd",
    "sg:city":"Las Vegas",
    "sg:classifiers":[
        {
            "category":"Restaurant",
            "type":"Food & Drink"
        }
    ],
    "sg:phone":"+1 702 240 1331",
    "sg:postcode":"89134",
    "sg:province":"NV",
    "sg:tags":[
        "banquet",
        "rooms"
    ],
    "wof:name":"Banquet Facilities Caterers",
    "wof:placetype":"venue"
},
  "geometry": {"coordinates":[-115.332725,36.204338],"type":"Point"}
}