{
  "type": "Feature",
  "properties": {
    "iso:country":"US",
    "sg:address":"9529 Summer Rain Dr",
    "sg:city":"Las Vegas",
    "sg:classifiers":[
        {
            "category":"Professional",
            "type":"Services"
        }
    ],
    "sg:phone":"+1 702 228 0029",
    "sg:postcode":"89134",
    "sg:province":"NV",
    "wof:name":"Think Young Forever Inc",
    "wof:placetype":"venue"
},
  "geometry": {"coordinates":[-115.303565,36.200476],"type":"Point"}
}