{
  "type": "Feature",
  "properties": {
    "iso:country":"US",
    "sg:address":"3325 Retail Dr Ste 110",
    "sg:city":"Carson City",
    "sg:classifiers":[
        {
            "category":"Restaurant",
            "type":"Food & Drink"
        }
    ],
    "sg:phone":"+1 775 884 8080",
    "sg:postcode":"89706",
    "sg:province":"NV",
    "sg:tags":[
        "pizza"
    ],
    "wof:name":"Round Table Pizza",
    "wof:placetype":"venue"
},
  "geometry": {"coordinates":[-119.75796,39.189443],"type":"Point"}
}