{
  "type": "Feature",
  "properties": {
    "iso:country":"US",
    "sg:address":"8450 Westcliff Dr",
    "sg:city":"Las Vegas",
    "sg:classifiers":[
        {
            "category":"Bars & Pubs",
            "type":"Food & Drink"
        }
    ],
    "sg:phone":"+1 702 360 4040",
    "sg:postcode":"89145",
    "sg:province":"NV",
    "wof:name":"Bounty Hunter",
    "wof:placetype":"venue"
},
  "geometry": {"coordinates":[-115.276838,36.173836],"type":"Point"}
}