{
  "type": "Feature",
  "properties": {
    "iso:country":"US",
    "sg:address":"9595 S Eastern Ave",
    "sg:city":"Las Vegas",
    "sg:classifiers":[
        {
            "category":"Restaurant",
            "type":"Food & Drink"
        }
    ],
    "sg:phone":"+1 702 953 2500",
    "sg:postcode":"89123",
    "sg:province":"NV",
    "sg:tags":[
        "mexican"
    ],
    "sg:website":"www.caferio.com",
    "wof:name":"Cafe Rio",
    "wof:placetype":"venue"
},
  "geometry": {"coordinates":[-115.11875499999999,36.014215],"type":"Point"}
}