{
  "type": "Feature",
  "properties": {
    "iso:country":"US",
    "sg:address":"5185 S Eastern Ave",
    "sg:city":"Las Vegas",
    "sg:classifiers":[
        {
            "category":"Building & Trades",
            "subcategory":"Construction",
            "type":"Services"
        }
    ],
    "sg:phone":"+1 702 456 2184",
    "sg:postcode":"89119",
    "sg:province":"NV",
    "sg:tags":[
        "roof",
        "structure"
    ],
    "wof:name":"Trutrus",
    "wof:placetype":"venue"
},
  "geometry": {"coordinates":[-115.118988,36.09553],"type":"Point"}
}