{
  "type": "Feature",
  "properties": {
    "iso:country":"US",
    "sg:address":"2880 Las Vegas Blvd S",
    "sg:city":"Las Vegas",
    "sg:classifiers":[
        {
            "category":"Shopping",
            "subcategory":"Shoes",
            "type":"Retail Goods"
        }
    ],
    "sg:phone":"+1 702 697 5990",
    "sg:postcode":"89109",
    "sg:province":"NV",
    "sg:tags":[
        "store"
    ],
    "wof:name":"The Right Shoes",
    "wof:placetype":"venue"
},
  "geometry": {"coordinates":[-115.162356,36.136401],"type":"Point"}
}