{
  "type": "Feature",
  "properties": {
    "iso:country":"US",
    "sg:address":"7 Commerce Center Dr",
    "sg:city":"Henderson",
    "sg:classifiers":[
        {
            "category":"Home & Garden",
            "subcategory":"Building Materials",
            "type":"Retail Goods"
        }
    ],
    "sg:phone":"+1 702 253 2700",
    "sg:postcode":"89014",
    "sg:province":"NV",
    "sg:tags":[
        "lumber"
    ],
    "wof:name":"Southern Nevada Lumber LLC",
    "wof:placetype":"venue"
},
  "geometry": {"coordinates":[-115.06885699999999,36.073314],"type":"Point"}
}