{
  "type": "Feature",
  "properties": {
    "iso:country":"US",
    "sg:address":"2533 N Carson St",
    "sg:city":"Carson City",
    "sg:classifiers":[
        {
            "category":"Professional",
            "subcategory":"Management & Consulting",
            "type":"Services"
        }
    ],
    "sg:phone":"+1 775 841 9143",
    "sg:postcode":"89706",
    "sg:province":"NV",
    "sg:tags":[
        "consultant",
        "business"
    ],
    "wof:name":"Cloud Nine Limited",
    "wof:placetype":"venue"
},
  "geometry": {"coordinates":[-119.76863899999999,39.183487],"type":"Point"}
}