{
  "type": "Feature",
  "properties": {
    "iso:country":"US",
    "sg:address":"3100 Mill St",
    "sg:city":"Reno",
    "sg:classifiers":[
        {
            "category":"Professional",
            "subcategory":"Computer Services",
            "type":"Services"
        }
    ],
    "sg:phone":"+1 775 284 8085",
    "sg:postcode":"89502",
    "sg:province":"NV",
    "sg:tags":[
        "development",
        "web"
    ],
    "wof:name":"Icart Solutions Inc",
    "wof:placetype":"venue"
},
  "geometry": {"coordinates":[-119.774223,39.517031],"type":"Point"}
}