{
  "type": "Feature",
  "properties": {
    "iso:country":"US",
    "sg:address":"6409 Rosemount Ave",
    "sg:city":"Las Vegas",
    "sg:classifiers":[
        {
            "category":"Building & Trades",
            "subcategory":"Cleaning & Sanitation",
            "type":"Services"
        }
    ],
    "sg:phone":"+1 702 438 6025",
    "sg:postcode":"89156",
    "sg:province":"NV",
    "sg:tags":[
        "janitor"
    ],
    "wof:name":"Partners In Grime Cleaning Co",
    "wof:placetype":"venue"
},
  "geometry": {"coordinates":[-115.033025,36.199761],"type":"Point"}
}