{
  "type": "Feature",
  "properties": {
    "iso:country":"US",
    "sg:address":"6363 S Pecos Rd",
    "sg:city":"Las Vegas",
    "sg:classifiers":[
        {
            "category":"Travel",
            "subcategory":"Travel Agent",
            "type":"Entertainment"
        }
    ],
    "sg:phone":"+1 702 798 3777",
    "sg:postcode":"89120",
    "sg:province":"NV",
    "sg:tags":[
        "tours",
        "promoter"
    ],
    "sg:website":"www.histours.com",
    "wof:name":"His Tours",
    "wof:placetype":"venue"
},
  "geometry": {"coordinates":[-115.100916,36.072467],"type":"Point"}
}