{
  "type": "Feature",
  "properties": {
    "iso:country":"US",
    "sg:address":"914 Columbia Ct",
    "sg:city":"Gardnerville",
    "sg:classifiers":[
        {
            "category":"Shopping",
            "subcategory":"Catalog Store",
            "type":"Retail Goods"
        }
    ],
    "sg:phone":"+1 775 450 6439",
    "sg:postcode":"89460",
    "sg:province":"NV",
    "sg:tags":[
        "house",
        "mail"
    ],
    "wof:name":"Rayjin Goods",
    "wof:placetype":"venue"
},
  "geometry": {"coordinates":[-119.748162,38.904399],"type":"Point"}
}