{
  "type": "Feature",
  "properties": {
    "iso:country":"US",
    "sg:address":"1451 Di Blasi Dr",
    "sg:city":"Las Vegas",
    "sg:classifiers":[
        {
            "category":"Shopping",
            "type":"Retail Goods"
        }
    ],
    "sg:phone":"+1 702 822 1550",
    "sg:postcode":"89119",
    "sg:province":"NV",
    "sg:tags":[
        "art",
        "gallery",
        "dealer"
    ],
    "wof:name":"My Brother's Art Co",
    "wof:placetype":"venue"
},
  "geometry": {"coordinates":[-115.133782,36.089529],"type":"Point"}
}