{
  "type": "Feature",
  "properties": {
    "iso:country":"US",
    "sg:address":"110 Country Club Dr",
    "sg:city":"Incline Village",
    "sg:classifiers":[
        {
            "category":"Professional",
            "type":"Services"
        }
    ],
    "sg:phone":"+1 775 832 8277",
    "sg:postcode":"89451",
    "sg:province":"NV",
    "sg:tags":[
        "establishment"
    ],
    "wof:name":"South Shore Capital",
    "wof:placetype":"venue"
},
  "geometry": {"coordinates":[-119.943068,39.23925],"type":"Point"}
}