{
  "type": "Feature",
  "properties": {
    "iso:country":"US",
    "sg:address":"329 Court St",
    "sg:city":"Elko",
    "sg:classifiers":[
        {
            "category":"Professional",
            "subcategory":"Art Services",
            "type":"Services"
        }
    ],
    "sg:phone":"+1 775 777 3129",
    "sg:postcode":"89801",
    "sg:province":"NV",
    "sg:tags":[
        "artist"
    ],
    "wof:name":"Axess Graphx",
    "wof:placetype":"venue"
},
  "geometry": {"coordinates":[-115.765149,40.832239],"type":"Point"}
}