{
  "type": "Feature",
  "properties": {
    "iso:country":"US",
    "sg:address":"10120 W Flamingo Rd Ste 4-192",
    "sg:city":"Las Vegas",
    "sg:classifiers":[
        {
            "category":"Communications",
            "subcategory":"Film & Video Production",
            "type":"Services"
        },
        {
            "category":"Communications",
            "subcategory":"Newspaper",
            "type":"Services"
        }
    ],
    "sg:phone":"+1 702 479 5215",
    "sg:postcode":"89147",
    "sg:province":"NV",
    "sg:tags":[
        "video/film",
        "advertising"
    ],
    "sg:website":"www.video-dean.com",
    "wof:name":"Video Dean",
    "wof:placetype":"venue"
},
  "geometry": {"coordinates":[-115.313369,36.115327],"type":"Point"}
}