{
  "type": "Feature",
  "properties": {
    "iso:country":"US",
    "sg:address":"3420 Kindred Ave",
    "sg:city":"Reno",
    "sg:classifiers":[
        {
            "category":"Real Estate",
            "subcategory":"Real Estate Operator",
            "type":"Services"
        }
    ],
    "sg:phone":"+1 775 827 2900",
    "sg:postcode":"89502",
    "sg:province":"NV",
    "sg:tags":[
        "building",
        "apartment"
    ],
    "wof:name":"Moana Apartments",
    "wof:placetype":"venue"
},
  "geometry": {"coordinates":[-119.783694,39.49084],"type":"Point"}
}