{
  "type": "Feature",
  "properties": {
    "iso:country":"US",
    "sg:address":"572 Gentry Way",
    "sg:city":"Reno",
    "sg:classifiers":[
        {
            "category":"Retail",
            "subcategory":"Auto Repair",
            "type":"Services"
        }
    ],
    "sg:phone":"+1 775 825 8033",
    "sg:postcode":"89502",
    "sg:province":"NV",
    "sg:tags":[
        "transmission",
        "general"
    ],
    "wof:name":"Bear Repair",
    "wof:placetype":"venue"
},
  "geometry": {"coordinates":[-119.78961099999999,39.494863],"type":"Point"}
}