{
  "type": "Feature",
  "properties": {
    "iso:country":"US",
    "sg:address":"1000 S Rainbow Blvd",
    "sg:city":"Las Vegas",
    "sg:classifiers":[
        {
            "category":"Health Services",
            "subcategory":"Medical Lab",
            "type":"Services"
        }
    ],
    "sg:phone":"+1 702 338 1995",
    "sg:postcode":"89145",
    "sg:province":"NV",
    "sg:tags":[
        "laboratory",
        "dental"
    ],
    "wof:name":"Bite Rite Dental Lab",
    "wof:placetype":"venue"
},
  "geometry": {"coordinates":[-115.244166,36.165245],"type":"Point"}
}