{
  "type": "Feature",
  "properties": {
    "iso:country":"US",
    "sg:address":"501 Nevada Hwy",
    "sg:city":"Boulder City",
    "sg:classifiers":[
        {
            "category":"Shopping",
            "subcategory":"Clothing, Apparel, & Fashions",
            "type":"Retail Goods"
        }
    ],
    "sg:phone":"+1 702 293 9600",
    "sg:postcode":"89005",
    "sg:province":"NV",
    "wof:name":"Desert Spice",
    "wof:placetype":"venue"
},
  "geometry": {"coordinates":[-114.837744,35.977643],"type":"Point"}
}