{
  "type": "Feature",
  "properties": {
    "iso:country":"US",
    "sg:address":"Owens & Nellia",
    "sg:city":"Las Vegas",
    "sg:classifiers":[
        {
            "category":"Social Services",
            "subcategory":"Child Care",
            "type":"Services"
        },
        {
            "category":"Education",
            "subcategory":"Preschool",
            "type":"Public Place"
        },
        {
            "category":"Education",
            "subcategory":"School",
            "type":"Public Place"
        }
    ],
    "sg:phone":"+1 702 450 8751",
    "sg:postcode":"89101",
    "sg:province":"NV",
    "sg:tags":[
        "elementary",
        "day"
    ],
    "sg:website":"splearningcenters.com",
    "wof:name":"Sweet Pea Learning Centers",
    "wof:placetype":"venue"
},
  "geometry": {"coordinates":[-115.062102,36.188756],"type":"Point"}
}