{
  "type": "Feature",
  "properties": {
    "iso:country":"US",
    "sg:address":"1333 N Buffalo, Ste 270",
    "sg:city":"Las Vegas",
    "sg:classifiers":[
        {
            "category":"Real Estate",
            "subcategory":"Real Estate Agent",
            "type":"Services"
        }
    ],
    "sg:phone":"+1 702 461 7211",
    "sg:postcode":"89128",
    "sg:province":"NV",
    "sg:website":"www.findlvhomes.com/",
    "wof:name":"Steve Bougon",
    "wof:placetype":"venue"
},
  "geometry": {"coordinates":[-115.259827,36.185383],"type":"Point"}
}