{
  "type": "Feature",
  "properties": {
    "iso:country":"US",
    "sg:address":"2970 Galit Ave",
    "sg:city":"Las Vegas",
    "sg:classifiers":[
        {
            "category":"Professional",
            "subcategory":"Business Services",
            "type":"Services"
        }
    ],
    "sg:phone":"+1 702 521 3113",
    "sg:postcode":"89121",
    "sg:province":"NV",
    "wof:name":"Pinkkitty Design",
    "wof:placetype":"venue"
},
  "geometry": {"coordinates":[-115.111104,36.125695],"type":"Point"}
}