{
  "type": "Feature",
  "properties": {
    "iso:country":"US",
    "sg:address":"McCarran International Airport Concourse D",
    "sg:city":"Las Vegas",
    "sg:classifiers":[
        {
            "category":"Bars & Pubs",
            "subcategory":"Lounge",
            "type":"Food & Drink"
        }
    ],
    "sg:phone":"+1 702 322 0832",
    "sg:postcode":"89119",
    "sg:province":"NV",
    "sg:website":"www.continental.com/web/en-US/co...",
    "wof:name":"Presidents Club",
    "wof:placetype":"venue"
},
  "geometry": {"coordinates":[-115.150194,36.085384],"type":"Point"}
}