{
  "type": "Feature",
  "properties": {
    "iso:country":"US",
    "sg:address":"8528 Vivid Violet Ave",
    "sg:city":"Las Vegas",
    "sg:classifiers":[
        {
            "category":"Shopping",
            "subcategory":"Computers & Home Electronics",
            "type":"Retail Goods"
        }
    ],
    "sg:phone":"+1 702 645 5078",
    "sg:postcode":"89143",
    "sg:province":"NV",
    "wof:name":"O P C International Inc",
    "wof:placetype":"venue"
},
  "geometry": {"coordinates":[-115.282628,36.311671],"type":"Point"}
}