{
  "type": "Feature",
  "properties": {
    "iso:country":"US",
    "sg:address":"3734 Las Vegas Blvd S",
    "sg:city":"Las Vegas",
    "sg:classifiers":[
        {
            "category":"Shopping",
            "subcategory":"Gifts & Souvenirs",
            "type":"Retail Goods"
        }
    ],
    "sg:phone":"+1 702 597 3008",
    "sg:postcode":"89109",
    "sg:province":"NV",
    "sg:tags":[
        "basket",
        "parcel"
    ],
    "wof:name":"Viva Vegas Gifts II",
    "wof:placetype":"venue"
},
  "geometry": {"coordinates":[-115.173053,36.104883],"type":"Point"}
}