{
  "type": "Feature",
  "properties": {
    "iso:country":"US",
    "sg:address":"791 Tillman Ln",
    "sg:city":"Gardnerville",
    "sg:classifiers":[
        {
            "category":"Personal",
            "subcategory":"Beauty Salon",
            "type":"Services"
        }
    ],
    "sg:phone":"+1 775 265 2029",
    "sg:postcode":"89460",
    "sg:province":"NV",
    "wof:name":"Spellbound Salon",
    "wof:placetype":"venue"
},
  "geometry": {"coordinates":[-119.742081,38.895599],"type":"Point"}
}