{
  "type": "Feature",
  "properties": {
    "iso:country":"US",
    "sg:address":"4940 Ampere Dr",
    "sg:city":"Reno",
    "sg:classifiers":[
        {
            "category":"Professional",
            "subcategory":"Detective & Security Services",
            "type":"Services"
        }
    ],
    "sg:phone":"+1 775 857 6808",
    "sg:postcode":"89502",
    "sg:province":"NV",
    "sg:tags":[
        "car",
        "armored"
    ],
    "wof:name":"Loomis Fargo Co",
    "wof:placetype":"venue"
},
  "geometry": {"coordinates":[-119.755505,39.509662],"type":"Point"}
}