{
  "type": "Feature",
  "properties": {
    "iso:country":"US",
    "sg:address":"10700 Stead Blvd",
    "sg:city":"Reno",
    "sg:classifiers":[
        {
            "category":"Real Estate",
            "subcategory":"Real Estate Operator",
            "type":"Services"
        }
    ],
    "sg:phone":"+1 775 972 7184",
    "sg:postcode":"89506",
    "sg:province":"NV",
    "sg:tags":[
        "mobile",
        "home",
        "park",
        "community"
    ],
    "wof:name":"Sierra Shadows Mobile Hm Cmnty",
    "wof:placetype":"venue"
},
  "geometry": {"coordinates":[-119.882068,39.626554],"type":"Point"}
}