{
  "type": "Feature",
  "properties": {
    "iso:country":"US",
    "sg:address":"204 S Decatur Blvd",
    "sg:city":"Las Vegas",
    "sg:classifiers":[
        {
            "category":"Home & Garden",
            "subcategory":"Home Furnishings",
            "type":"Retail Goods"
        }
    ],
    "sg:phone":"+1 702 870 7330",
    "sg:postcode":"89107",
    "sg:province":"NV",
    "sg:tags":[
        "linen",
        "bedding"
    ],
    "wof:name":"Strouds Linen Warehouse",
    "wof:placetype":"venue"
},
  "geometry": {"coordinates":[-115.206053,36.17186],"type":"Point"}
}