{
  "type": "Feature",
  "properties": {
    "iso:country":"US",
    "sg:address":"209 N Stephanie St",
    "sg:city":"Henderson",
    "sg:classifiers":[
        {
            "category":"Restaurant",
            "type":"Food & Drink"
        }
    ],
    "sg:phone":"+1 702 451 3030",
    "sg:postcode":"89074",
    "sg:province":"NV",
    "wof:name":"Domino's Pizza",
    "wof:placetype":"venue"
},
  "geometry": {"coordinates":[-115.04677700000001,36.042262],"type":"Point"}
}