{
  "type": "Feature",
  "properties": {
    "iso:country":"US",
    "sg:address":"3190 W Sahara Ave",
    "sg:city":"Las Vegas",
    "sg:classifiers":[
        {
            "category":"Bars & Pubs",
            "type":"Food & Drink"
        }
    ],
    "sg:phone":"+1 702 253 6013",
    "sg:postcode":"89102",
    "sg:province":"NV",
    "sg:tags":[
        "drinking"
    ],
    "wof:name":"Hurricane Harrys",
    "wof:placetype":"venue"
},
  "geometry": {"coordinates":[-115.183349,36.144442],"type":"Point"}
}