{
  "type": "Feature",
  "properties": {
    "iso:country":"US",
    "sg:address":"99 Willow Dove Ave",
    "sg:city":"Las Vegas",
    "sg:classifiers":[
        {
            "category":"Arts & Performance",
            "subcategory":"Music",
            "type":"Entertainment"
        }
    ],
    "sg:phone":"+1 702 530 6191",
    "sg:postcode":"89123",
    "sg:province":"NV",
    "sg:tags":[
        "dj"
    ],
    "sg:website":"elev8djs.com",
    "wof:name":"Elev8 Entertainment",
    "wof:placetype":"venue"
},
  "geometry": {"coordinates":[-115.167942,36.016641],"type":"Point"}
}