{
  "type": "Feature",
  "properties": {
    "iso:country":"US",
    "sg:address":"903 W 4th St",
    "sg:city":"Reno",
    "sg:classifiers":[
        {
            "category":"Shopping",
            "subcategory":"Used Merchandise",
            "type":"Retail Goods"
        }
    ],
    "sg:phone":"+1 775 324 7776",
    "sg:postcode":"89503",
    "sg:province":"NV",
    "sg:tags":[
        "shop",
        "thrift"
    ],
    "wof:name":"SPCA Of Northern Nevada",
    "wof:placetype":"venue"
},
  "geometry": {"coordinates":[-119.830917,39.525558],"type":"Point"}
}