{
  "type": "Feature",
  "properties": {
    "iso:country":"US",
    "sg:address":"2881 Bus Park Ct",
    "sg:city":"Las Vegas",
    "sg:classifiers":[
        {
            "category":"Banks & Credit Unions",
            "subcategory":"Bank",
            "type":"Services"
        }
    ],
    "sg:phone":"+1 702 719 5363",
    "sg:postcode":"89128",
    "sg:province":"NV",
    "sg:tags":[
        "loan",
        "real estate"
    ],
    "wof:name":"Silverstate Mortgage",
    "wof:placetype":"venue"
},
  "geometry": {"coordinates":[-115.25006399999999,36.213072],"type":"Point"}
}