{
  "type": "Feature",
  "properties": {
    "iso:country":"US",
    "sg:address":"63 E Basic Rd",
    "sg:city":"Henderson",
    "sg:classifiers":[
        {
            "category":"Shopping",
            "type":"Retail Goods"
        }
    ],
    "sg:phone":"+1 702 558 0232",
    "sg:postcode":"89015",
    "sg:province":"NV",
    "sg:tags":[
        "merchandise"
    ],
    "wof:name":"Scott Enterprises",
    "wof:placetype":"venue"
},
  "geometry": {"coordinates":[-114.976778,36.031811],"type":"Point"}
}