{
  "type": "Feature",
  "properties": {
    "iso:country":"US",
    "sg:address":"1013 Montpeliar St",
    "sg:city":"Las Vegas",
    "sg:classifiers":[
        {
            "category":"Museum",
            "type":"Entertainment"
        }
    ],
    "sg:phone":"+1 702 699 7007",
    "sg:postcode":"89110",
    "sg:province":"NV",
    "sg:tags":[
        "gallery"
    ],
    "wof:name":"Iris Fine Art",
    "wof:placetype":"venue"
},
  "geometry": {"coordinates":[-115.096516,36.183109],"type":"Point"}
}