{
  "type": "Feature",
  "properties": {
    "iso:country":"US",
    "sg:address":"3781 Mill St",
    "sg:city":"Reno",
    "sg:classifiers":[
        {
            "category":"Wholesale",
            "subcategory":"Construction Materials",
            "type":"Manufacturing & Wholesale Goods"
        }
    ],
    "sg:phone":"+1 775 322 0989",
    "sg:postcode":"89502",
    "sg:province":"NV",
    "sg:tags":[
        "plastering"
    ],
    "wof:name":"Garcias Equipment",
    "wof:placetype":"venue"
},
  "geometry": {"coordinates":[-119.762231,39.516227],"type":"Point"}
}