{
  "type": "Feature",
  "properties": {
    "iso:country":"US",
    "sg:address":"4308 Koval Ln",
    "sg:city":"Las Vegas",
    "sg:classifiers":[
        {
            "category":"Real Estate",
            "subcategory":"Real Estate Operator",
            "type":"Services"
        }
    ],
    "sg:phone":"+1 702 733 8888",
    "sg:postcode":"89109",
    "sg:province":"NV",
    "sg:tags":[
        "building",
        "apartment"
    ],
    "wof:name":"Grand Plaza Apts",
    "wof:placetype":"venue"
},
  "geometry": {"coordinates":[-115.163881,36.109116],"type":"Point"}
}