{
  "type": "Feature",
  "properties": {
    "iso:country":"US",
    "sg:address":"256 Kingsbury Grade Rd",
    "sg:city":"Stateline",
    "sg:classifiers":[
        {
            "category":"Professional",
            "subcategory":"Accounting & Tax Preparation",
            "type":"Services"
        }
    ],
    "sg:phone":"+1 775 588 1535",
    "sg:postcode":"89449",
    "sg:province":"NV",
    "sg:tags":[
        "bookkeeping",
        "general"
    ],
    "wof:name":"Accurate Tax Plus",
    "wof:placetype":"venue"
},
  "geometry": {"coordinates":[-119.929547,38.968288],"type":"Point"}
}