{
  "type": "Feature",
  "properties": {
    "iso:country":"US",
    "sg:address":"3206 Myles Dr",
    "sg:city":"Sparks",
    "sg:classifiers":[
        {
            "category":"Food & Beverages",
            "subcategory":"Specialty",
            "type":"Retail Goods"
        }
    ],
    "sg:phone":"+1 775 626 8226",
    "sg:postcode":"89434",
    "sg:province":"NV",
    "wof:name":"Nowakowski Marketing",
    "wof:placetype":"venue"
},
  "geometry": {"coordinates":[-119.707385,39.561264],"type":"Point"}
}