{
  "type": "Feature",
  "properties": {
    "iso:country":"US",
    "sg:address":"2075 Palm St",
    "sg:city":"Las Vegas",
    "sg:classifiers":[
        {
            "category":"Real Estate",
            "subcategory":"Real Estate Agent",
            "type":"Services"
        }
    ],
    "sg:phone":"+1 702 457 6044",
    "sg:postcode":"89104",
    "sg:province":"NV",
    "sg:tags":[
        "management"
    ],
    "wof:name":"Luther Kutcher Holding",
    "wof:placetype":"venue"
},
  "geometry": {"coordinates":[-115.100943,36.146244],"type":"Point"}
}