{
  "type": "Feature",
  "properties": {
    "iso:country":"US",
    "sg:address":"4718 Ponderosa Dr",
    "sg:city":"Carson City",
    "sg:classifiers":[
        {
            "category":"Organizations",
            "subcategory":"Professional Association",
            "type":"Services"
        }
    ],
    "sg:phone":"+1 775 882 4686",
    "sg:postcode":"89701",
    "sg:province":"NV",
    "wof:name":"Western States Sheriffs Assn",
    "wof:placetype":"venue"
},
  "geometry": {"coordinates":[-119.758944,39.124531],"type":"Point"}
}