{
  "type": "Feature",
  "properties": {
    "iso:country":"US",
    "sg:address":"653 N Town Center Dr",
    "sg:city":"Las Vegas",
    "sg:classifiers":[
        {
            "category":"Health Services",
            "subcategory":"Optometrist",
            "type":"Services"
        },
        {
            "category":"Health Services",
            "subcategory":"Doctor",
            "type":"Services"
        },
        {
            "category":"Personal",
            "subcategory":"Day Spa",
            "type":"Services"
        }
    ],
    "sg:phone":"+1 702 796 7546",
    "sg:postcode":"89144",
    "sg:province":"NV",
    "sg:tags":[
        "dermatologist"
    ],
    "wof:name":"Fong Andrea OD",
    "wof:placetype":"venue"
},
  "geometry": {"coordinates":[-115.316979,36.179149],"type":"Point"}
}