{
  "type": "Feature",
  "properties": {
    "iso:country":"US",
    "sg:address":"Gold Coast Hotel and Casino 4000 W Flamingo Rd",
    "sg:city":"Las Vegas",
    "sg:classifiers":[
        {
            "category":"Restaurant",
            "type":"Food & Drink"
        }
    ],
    "sg:phone":"+1 800 331 5334",
    "sg:postcode":"89103",
    "sg:province":"NV",
    "sg:tags":[
        "traditional",
        "american"
    ],
    "sg:website":"www.goldcoastcasino.com",
    "wof:name":"Cortez Room",
    "wof:placetype":"venue"
},
  "geometry": {"coordinates":[-115.19244500000001,36.115649],"type":"Point"}
}