{
  "type": "Feature",
  "properties": {
    "iso:country":"US",
    "sg:address":"999 Marietta Way",
    "sg:city":"Sparks",
    "sg:classifiers":[
        {
            "category":"Manufacturing",
            "subcategory":"Glass & Minerals",
            "type":"Manufacturing & Wholesale Goods"
        }
    ],
    "sg:phone":"+1 775 358 4430",
    "sg:postcode":"89431",
    "sg:province":"NV",
    "sg:tags":[
        "concrete",
        "brick",
        "prod",
        "block"
    ],
    "sg:website":"www.rinker.com",
    "wof:name":"Rinker Materials Hydro Conduit",
    "wof:placetype":"venue"
},
  "geometry": {"coordinates":[-119.753906,39.522217],"type":"Point"}
}