{
  "type": "Feature",
  "properties": {
    "iso:country":"US",
    "sg:address":"4965 W Tropicana Ave",
    "sg:city":"Las Vegas",
    "sg:classifiers":[
        {
            "category":"Personal",
            "subcategory":"Beauty Salon",
            "type":"Services"
        }
    ],
    "sg:phone":"+1 702 364 8100",
    "sg:postcode":"89103",
    "sg:province":"NV",
    "wof:name":"Soda",
    "wof:placetype":"venue"
},
  "geometry": {"coordinates":[-115.21158,36.10061],"type":"Point"}
}