{
  "type": "Feature",
  "properties": {
    "iso:country":"US",
    "sg:address":"3179 W Post Rd",
    "sg:city":"Las Vegas",
    "sg:classifiers":[
        {
            "category":"Manufacturing",
            "subcategory":"Printing",
            "type":"Manufacturing & Wholesale Goods"
        }
    ],
    "sg:phone":"+1 702 896 4454",
    "sg:postcode":"89118",
    "sg:province":"NV",
    "sg:tags":[
        "commercial"
    ],
    "sg:website":"www.imagelinegraphics.com",
    "wof:name":"Image Line Graphics",
    "wof:placetype":"venue"
},
  "geometry": {"coordinates":[-115.182135,36.07486],"type":"Point"}
}