{
  "type": "Feature",
  "properties": {
    "iso:country":"US",
    "sg:address":"701 N 20th Street",
    "sg:city":"Las Vegas",
    "sg:classifiers":[
        {
            "category":"Education",
            "subcategory":"School",
            "type":"Public Place"
        }
    ],
    "sg:phone":"+1 702 799 7896",
    "sg:postcode":"89101",
    "sg:province":"NV",
    "sg:tags":[
        "high",
        "middle",
        "elementary"
    ],
    "wof:name":"Schools Clark County Public",
    "wof:placetype":"venue"
},
  "geometry": {"coordinates":[-115.121438,36.175508],"type":"Point"}
}