{
  "type": "Feature",
  "properties": {
    "iso:country":"US",
    "sg:address":"1719 Industrial Rd",
    "sg:city":"Las Vegas",
    "sg:classifiers":[
        {
            "category":"Banks & Credit Unions",
            "subcategory":"Bank",
            "type":"Services"
        }
    ],
    "sg:phone":"+1 702 386 2700",
    "sg:postcode":"89102",
    "sg:province":"NV",
    "sg:tags":[
        "personal",
        "used",
        "institution",
        "merchandise"
    ],
    "wof:name":"Advance Auto Title Loan",
    "wof:placetype":"venue"
},
  "geometry": {"coordinates":[-115.16065500000001,36.150485],"type":"Point"}
}