{
  "type": "Feature",
  "properties": {
    "iso:country":"US",
    "sg:address":"5479 Birchbrook Ct",
    "sg:city":"Las Vegas",
    "sg:classifiers":[
        {
            "category":"Professional",
            "subcategory":"Management & Consulting",
            "type":"Services"
        }
    ],
    "sg:phone":"+1 702 436 0976",
    "sg:postcode":"89120",
    "sg:province":"NV",
    "sg:tags":[
        "business"
    ],
    "wof:name":"Fma Consulting",
    "wof:placetype":"venue"
},
  "geometry": {"coordinates":[-115.104392,36.090127],"type":"Point"}
}