{
  "type": "Feature",
  "properties": {
    "iso:country":"US",
    "sg:address":"100 W Liberty St",
    "sg:city":"Reno",
    "sg:classifiers":[
        {
            "category":"Real Estate",
            "subcategory":"Real Estate Agent",
            "type":"Services"
        }
    ],
    "sg:phone":"+1 775 329 4000",
    "sg:postcode":"89501",
    "sg:province":"NV",
    "wof:name":"Nai Hale Day Gallagher Co",
    "wof:placetype":"venue"
},
  "geometry": {"coordinates":[-119.813885,39.521288],"type":"Point"}
}