{
  "type": "Feature",
  "properties": {
    "iso:country":"US",
    "sg:address":"6180 Ingleston Dr",
    "sg:city":"Sparks",
    "sg:classifiers":[
        {
            "category":"Professional",
            "type":"Services"
        }
    ],
    "sg:phone":"+1 775 626 3560",
    "sg:postcode":"89436",
    "sg:province":"NV",
    "sg:tags":[
        "establishment"
    ],
    "wof:name":"Lakemont",
    "wof:placetype":"venue"
},
  "geometry": {"coordinates":[-119.694143,39.604852],"type":"Point"}
}