{
  "type": "Feature",
  "properties": {
    "iso:country":"US",
    "sg:address":"4729 S Carson St",
    "sg:city":"Carson City",
    "sg:classifiers":[
        {
            "category":"Real Estate",
            "subcategory":"Real Estate Operator",
            "type":"Services"
        }
    ],
    "sg:phone":"+1 775 884 0606",
    "sg:postcode":"89701",
    "sg:province":"NV",
    "sg:tags":[
        "apartment"
    ],
    "wof:name":"Mountain View Village",
    "wof:placetype":"venue"
},
  "geometry": {"coordinates":[-119.771004,39.123798],"type":"Point"}
}