{
  "type": "Feature",
  "properties": {
    "iso:country":"US",
    "sg:address":"8704 W Charleston Boulevard",
    "sg:city":"Las Vegas",
    "sg:classifiers":[
        {
            "category":"Home & Garden",
            "subcategory":"Furniture",
            "type":"Retail Goods"
        }
    ],
    "sg:phone":"+1 702 649 9800",
    "sg:postcode":"89117",
    "sg:province":"NV",
    "sg:tags":[
        "store"
    ],
    "wof:name":"Quixote Design Center",
    "wof:placetype":"venue"
},
  "geometry": {"coordinates":[-115.284967,36.159217],"type":"Point"}
}