{
  "type": "Feature",
  "properties": {
    "iso:country":"US",
    "sg:address":"680 Cedar St",
    "sg:city":"Elko",
    "sg:classifiers":[
        {
            "category":"Retail",
            "subcategory":"Repair Shop",
            "type":"Services"
        }
    ],
    "sg:phone":"+1 775 738 3367",
    "sg:postcode":"89801",
    "sg:province":"NV",
    "sg:tags":[
        "hardware",
        "motorcycle",
        "supply"
    ],
    "wof:name":"U-Haul",
    "wof:placetype":"venue"
},
  "geometry": {"coordinates":[-115.76585799999999,40.836242],"type":"Point"}
}