{
  "type": "Feature",
  "properties": {
    "iso:country":"US",
    "sg:address":"2305 Last Chance Rd",
    "sg:city":"Elko",
    "sg:classifiers":[
        {
            "category":"Mining & Drilling",
            "type":"Manufacturing & Wholesale Goods"
        }
    ],
    "sg:phone":"+1 775 738 8848",
    "sg:postcode":"89803",
    "sg:province":"NV",
    "sg:tags":[
        "metal"
    ],
    "wof:name":"Rimrock Drilling Inc",
    "wof:placetype":"venue"
},
  "geometry": {"coordinates":[-115.733977,40.839929],"type":"Point"}
}