{
  "type": "Feature",
  "properties": {
    "iso:country":"US",
    "sg:address":"2300 W Sahara Ave Ste 800",
    "sg:city":"Las Vegas",
    "sg:classifiers":[
        {
            "category":"Professional",
            "subcategory":"Computer Services",
            "type":"Services"
        }
    ],
    "sg:phone":"+1 702 949 9450",
    "sg:postcode":"89102",
    "sg:province":"NV",
    "sg:tags":[
        "repair"
    ],
    "sg:website":"datarecoverylasvegas.com",
    "wof:name":"ADR Data Recovery - Las Vegas",
    "wof:placetype":"venue"
},
  "geometry": {"coordinates":[-115.174256,36.14539],"type":"Point"}
}