{
  "type": "Feature",
  "properties": {
    "iso:country":"US",
    "sg:address":"3176 Cardinal Ln",
    "sg:city":"Las Vegas",
    "sg:classifiers":[
        {
            "category":"Professional",
            "type":"Services"
        }
    ],
    "sg:phone":"+1 702 433 8666",
    "sg:postcode":"89121",
    "sg:province":"NV",
    "wof:name":"Kevin McDaniel",
    "wof:placetype":"venue"
},
  "geometry": {"coordinates":[-115.106507,36.109892],"type":"Point"}
}