{
  "type": "Feature",
  "properties": {
    "iso:country":"US",
    "sg:address":"1 Plum Hollow Dr",
    "sg:city":"Henderson",
    "sg:classifiers":[
        {
            "category":"Banks & Credit Unions",
            "subcategory":"Investment Brokerage",
            "type":"Services"
        }
    ],
    "sg:phone":"+1 702 837 3498",
    "sg:postcode":"89052",
    "sg:province":"NV",
    "sg:tags":[
        "advisory",
        "research"
    ],
    "wof:name":"Korns Associates",
    "wof:placetype":"venue"
},
  "geometry": {"coordinates":[-115.09089,35.973887],"type":"Point"}
}