{
  "type": "Feature",
  "properties": {
    "iso:country":"US",
    "sg:address":"1601 Lakeside Dr",
    "sg:city":"Reno",
    "sg:classifiers":[
        {
            "category":"Health Services",
            "subcategory":"Dentist",
            "type":"Services"
        }
    ],
    "sg:phone":"+1 775 322 8610",
    "sg:postcode":"89509",
    "sg:province":"NV",
    "sg:tags":[
        "implant",
        "dentistry",
        "dentists-implantology"
    ],
    "sg:website":"http://gamboadds.com",
    "wof:name":"Gamboa Rafael M DDS",
    "wof:placetype":"venue"
},
  "geometry": {"coordinates":[-119.807316,39.508669],"type":"Point"}
}