{
  "type": "Feature",
  "properties": {
    "iso:country":"US",
    "sg:address":"995 Campton St",
    "sg:city":"Ely",
    "sg:classifiers":[
        {
            "category":"Local Transit",
            "type":"Transportation"
        }
    ],
    "sg:phone":"+1 775 289 6511",
    "sg:postcode":"89301",
    "sg:province":"NV",
    "sg:tags":[
        "ambulance"
    ],
    "wof:name":"White Pine County Ambulance",
    "wof:placetype":"venue"
},
  "geometry": {"coordinates":[-114.88864700000001,39.247396],"type":"Point"}
}