{
  "type": "Feature",
  "properties": {
    "iso:country":"US",
    "sg:address":"7993 Sky Birch Ct",
    "sg:city":"Las Vegas",
    "sg:classifiers":[
        {
            "category":"Professional",
            "subcategory":"Computer Services",
            "type":"Services"
        }
    ],
    "sg:phone":"+1 702 248 8951",
    "sg:postcode":"89147",
    "sg:province":"NV",
    "wof:name":"Computer PMS",
    "wof:placetype":"venue"
},
  "geometry": {"coordinates":[-115.26369,36.120041],"type":"Point"}
}