{
  "type": "Feature",
  "properties": {
    "iso:country":"US",
    "sg:address":"1001 Pyramid Way",
    "sg:city":"Sparks",
    "sg:classifiers":[
        {
            "category":"Banks & Credit Unions",
            "subcategory":"Investment Brokerage",
            "type":"Services"
        }
    ],
    "sg:phone":"+1 775 331 4331",
    "sg:postcode":"89431",
    "sg:province":"NV",
    "sg:tags":[
        "consultant",
        "planning",
        "financial"
    ],
    "wof:name":"Ibi Global",
    "wof:placetype":"venue"
},
  "geometry": {"coordinates":[-119.752673,39.543852],"type":"Point"}
}