{
  "type": "Feature",
  "properties": {
    "iso:country":"US",
    "sg:address":"2854 Geary Pl",
    "sg:city":"Las Vegas",
    "sg:classifiers":[
        {
            "category":"Sports & Exercise",
            "subcategory":"Golf",
            "type":"Entertainment"
        }
    ],
    "sg:phone":"+1 702 732 4289",
    "sg:postcode":"89109",
    "sg:province":"NV",
    "wof:name":"Las Vegas Country Club Master Association Inc",
    "wof:placetype":"venue"
},
  "geometry": {"coordinates":[-115.147891,36.138004],"type":"Point"}
}