{
  "type": "Feature",
  "properties": {
    "iso:country":"US",
    "sg:address":"7361 Hawk Shadow Ave",
    "sg:city":"Las Vegas",
    "sg:classifiers":[
        {
            "category":"Restaurant",
            "type":"Food & Drink"
        }
    ],
    "sg:phone":"+1 702 366 0222",
    "sg:postcode":"89113",
    "sg:province":"NV",
    "sg:tags":[
        "eating"
    ],
    "wof:name":"India Oven",
    "wof:placetype":"venue"
},
  "geometry": {"coordinates":[-115.252297,36.081819],"type":"Point"}
}