{
  "type": "Feature",
  "properties": {
    "iso:country":"US",
    "sg:address":"3704 Snorkel Cir",
    "sg:city":"Las Vegas",
    "sg:classifiers":[
        {
            "category":"Professional",
            "subcategory":"Business Services",
            "type":"Services"
        }
    ],
    "sg:phone":"+1 702 240 7964",
    "sg:postcode":"89108",
    "sg:province":"NV",
    "sg:tags":[
        "information",
        "referral"
    ],
    "wof:name":"CRR Creative Concepts",
    "wof:placetype":"venue"
},
  "geometry": {"coordinates":[-115.222781,36.227678],"type":"Point"}
}