{
  "type": "Feature",
  "properties": {
    "iso:country":"US",
    "sg:address":"1100 Terminal Way",
    "sg:city":"Reno",
    "sg:classifiers":[
        {
            "category":"Shopping",
            "subcategory":"Used Merchandise",
            "type":"Retail Goods"
        }
    ],
    "sg:phone":"+1 775 324 2228",
    "sg:postcode":"89502",
    "sg:province":"NV",
    "sg:tags":[
        "furniture"
    ],
    "wof:name":"Carl's Office Furniture",
    "wof:placetype":"venue"
},
  "geometry": {"coordinates":[-119.7775,39.516087],"type":"Point"}
}