{
  "type": "Feature",
  "properties": {
    "iso:country":"US",
    "sg:address":"9350 W Sahara Ave",
    "sg:city":"Las Vegas",
    "sg:classifiers":[
        {
            "category":"Ice Cream",
            "type":"Food & Drink"
        }
    ],
    "sg:menulink":"http://www.allmenus.com/nv/las-vegas/184173-cold-stone-creamery/menu/",
    "sg:phone":"+1 702 804 6180",
    "sg:postcode":"89117",
    "sg:province":"NV",
    "sg:tags":[
        "smoothy",
        "juice",
        "american"
    ],
    "wof:name":"Cold Stone Creamery",
    "wof:placetype":"venue"
},
  "geometry": {"coordinates":[-115.299824,36.146289],"type":"Point"}
}