{
  "type": "Feature",
  "properties": {
    "iso:country":"US",
    "sg:address":"3110 Polaris Ave",
    "sg:city":"Las Vegas",
    "sg:classifiers":[
        {
            "category":"Building & Trades",
            "subcategory":"Construction",
            "type":"Services"
        }
    ],
    "sg:phone":"+1 702 873 7677",
    "sg:postcode":"89102",
    "sg:province":"NV",
    "sg:tags":[
        "hanging",
        "contractor"
    ],
    "wof:name":"Ace Painting Inc",
    "wof:placetype":"venue"
},
  "geometry": {"coordinates":[-115.185593,36.130251],"type":"Point"}
}