{
  "type": "Feature",
  "properties": {
    "iso:country":"US",
    "sg:address":"840 E 5th St",
    "sg:city":"Reno",
    "sg:classifiers":[
        {
            "category":"Retail",
            "subcategory":"Animal Services",
            "type":"Services"
        }
    ],
    "sg:phone":"+1 775 324 7773",
    "sg:postcode":"89512",
    "sg:province":"NV",
    "sg:tags":[
        "shop",
        "shelter",
        "thrift"
    ],
    "sg:website":"http://www.spcanevada.org",
    "wof:name":"SPCA Of Northern Nevada",
    "wof:placetype":"venue"
},
  "geometry": {"coordinates":[-119.802716,39.533439],"type":"Point"}
}