{
  "type": "Feature",
  "properties": {
    "iso:country":"US",
    "sg:address":"311 S Roop St",
    "sg:city":"Carson City",
    "sg:classifiers":[
        {
            "category":"Bus Charters",
            "type":"Transportation"
        }
    ],
    "sg:phone":"+1 775 333 6955",
    "sg:postcode":"89701",
    "sg:province":"NV",
    "wof:name":"No Stress Express",
    "wof:placetype":"venue"
},
  "geometry": {"coordinates":[-119.76113100000001,39.163219],"type":"Point"}
}