{
  "type": "Feature",
  "properties": {
    "iso:country":"US",
    "sg:address":"1188 California Ave",
    "sg:city":"Reno",
    "sg:classifiers":[
        {
            "category":"Restaurant",
            "type":"Food & Drink"
        }
    ],
    "sg:phone":"+1 775 786 4843",
    "sg:postcode":"89509",
    "sg:province":"NV",
    "wof:name":"Burger King",
    "wof:placetype":"venue"
},
  "geometry": {"coordinates":[-119.825562,39.515898],"type":"Point"}
}