{
  "type": "Feature",
  "properties": {
    "iso:country":"US",
    "sg:address":"62 W Mesquite Blvd",
    "sg:city":"Mesquite",
    "sg:classifiers":[
        {
            "category":"Home & Garden",
            "subcategory":"Furniture",
            "type":"Retail Goods"
        }
    ],
    "sg:phone":"+1 702 346 3454",
    "sg:postcode":"89027",
    "sg:province":"NV",
    "wof:name":"Mesquite Furniture",
    "wof:placetype":"venue"
},
  "geometry": {"coordinates":[-114.068922,36.803931],"type":"Point"}
}