{
  "type": "Feature",
  "properties": {
    "iso:country":"US",
    "sg:address":"4501 Paradise Rd",
    "sg:city":"Las Vegas",
    "sg:classifiers":[
        {
            "category":"Food & Beverages",
            "subcategory":"Groceries & Convenience Stores",
            "type":"Retail Goods"
        }
    ],
    "sg:phone":"+1 702 735 1736",
    "sg:postcode":"89169",
    "sg:province":"NV",
    "wof:name":"St Tropez Convenience Mart",
    "wof:placetype":"venue"
},
  "geometry": {"coordinates":[-115.152576,36.107363],"type":"Point"}
}