{
  "type": "Feature",
  "properties": {
    "iso:country":"US",
    "sg:address":"5595 Simmons St Ste 3",
    "sg:city":"North Las Vegas",
    "sg:classifiers":[
        {
            "category":"Ice Cream",
            "type":"Food & Drink"
        }
    ],
    "sg:phone":"+1 702 791 0042",
    "sg:postcode":"89032",
    "sg:province":"NV",
    "sg:tags":[
        "frozen",
        "yogurt"
    ],
    "sg:website":"www.ritters.com",
    "wof:name":"Ritter's Frozen Custard",
    "wof:placetype":"venue"
},
  "geometry": {"coordinates":[-115.180053,36.260747],"type":"Point"}
}