{
  "type": "Feature",
  "properties": {
    "iso:country":"US",
    "sg:address":"4288 Cicada Way",
    "sg:city":"Las Vegas",
    "sg:classifiers":[
        {
            "category":"Building & Trades",
            "subcategory":"Cleaning & Sanitation",
            "type":"Services"
        }
    ],
    "sg:phone":"+1 702 798 0795",
    "sg:postcode":"89121",
    "sg:province":"NV",
    "sg:tags":[
        "maintenance"
    ],
    "wof:name":"Joe A Rios",
    "wof:placetype":"venue"
},
  "geometry": {"coordinates":[-115.080214,36.119445],"type":"Point"}
}