{
  "type": "Feature",
  "properties": {
    "iso:country":"US",
    "sg:address":"2050 Robb Dr",
    "sg:city":"Reno",
    "sg:classifiers":[
        {
            "category":"Organizations",
            "subcategory":"Religious Organization",
            "type":"Services"
        }
    ],
    "sg:phone":"+1 775 747 6613",
    "sg:postcode":"89523",
    "sg:province":"NV",
    "sg:tags":[
        "church"
    ],
    "wof:name":"Church Of Jesus Christ Of Lds",
    "wof:placetype":"venue"
},
  "geometry": {"coordinates":[-119.881793,39.53471],"type":"Point"}
}