{
  "type": "Feature",
  "properties": {
    "iso:country":"US",
    "sg:address":"3000 Paradise Rd",
    "sg:city":"Las Vegas",
    "sg:classifiers":[
        {
            "category":"Shopping",
            "subcategory":"Jewelry",
            "type":"Retail Goods"
        }
    ],
    "sg:phone":"+1 702 892 9288",
    "sg:postcode":"89109",
    "sg:province":"NV",
    "wof:name":"Landau Custom Jeweller",
    "wof:placetype":"venue"
},
  "geometry": {"coordinates":[-115.15471100000001,36.139679],"type":"Point"}
}