{
  "type": "Feature",
  "properties": {
    "iso:country":"US",
    "sg:address":"3500 Las Vegas Boulevard",
    "sg:city":"Las Vegas",
    "sg:classifiers":[
        {
            "category":"Shopping",
            "subcategory":"Jewelry",
            "type":"Retail Goods"
        }
    ],
    "sg:phone":"+1 702 862 4440",
    "sg:postcode":"89101",
    "sg:province":"NV",
    "sg:tags":[
        "watch"
    ],
    "wof:name":"Chopard Boutique",
    "wof:placetype":"venue"
},
  "geometry": {"coordinates":[-115.121005,36.171041],"type":"Point"}
}