{
  "type": "Feature",
  "properties": {
    "iso:country":"US",
    "sg:address":"5417 Evergreen Ave",
    "sg:city":"Las Vegas",
    "sg:classifiers":[
        {
            "category":"Professional",
            "subcategory":"Business Services",
            "type":"Services"
        }
    ],
    "sg:phone":"+1 702 838 1558",
    "sg:postcode":"89107",
    "sg:province":"NV",
    "wof:name":"Mobile Adventures Ltd",
    "wof:placetype":"venue"
},
  "geometry": {"coordinates":[-115.213402,36.163105],"type":"Point"}
}