{
  "type": "Feature",
  "properties": {
    "iso:country":"US",
    "sg:address":"2008 Victorian Ave",
    "sg:city":"Sparks",
    "sg:classifiers":[
        {
            "category":"Autos & Motor Vehicles",
            "subcategory":"Motorcycle Sales",
            "type":"Retail Goods"
        }
    ],
    "sg:phone":"+1 775 331 3022",
    "sg:postcode":"89431",
    "sg:province":"NV",
    "sg:tags":[
        "scooter"
    ],
    "wof:name":"Cycle Center",
    "wof:placetype":"venue"
},
  "geometry": {"coordinates":[-119.771231,39.535341],"type":"Point"}
}