{
  "type": "Feature",
  "properties": {
    "iso:country":"US",
    "sg:address":"880 E Plumb Ln",
    "sg:city":"Reno",
    "sg:classifiers":[
        {
            "category":"Restaurant",
            "type":"Food & Drink"
        }
    ],
    "sg:phone":"+1 775 829 8866",
    "sg:postcode":"89502",
    "sg:province":"NV",
    "sg:tags":[
        "buffet",
        "asian",
        "chinese",
        "pan"
    ],
    "wof:name":"Great Wall Chinese Buffet",
    "wof:placetype":"venue"
},
  "geometry": {"coordinates":[-119.786199,39.505877],"type":"Point"}
}