{
  "type": "Feature",
  "properties": {
    "iso:country":"US",
    "sg:address":"3515 N Bruce St",
    "sg:city":"North Las Vegas",
    "sg:classifiers":[
        {
            "category":"Building & Trades",
            "subcategory":"Equipment Rental",
            "type":"Services"
        }
    ],
    "sg:phone":"+1 702 639 6006",
    "sg:postcode":"89030",
    "sg:province":"NV",
    "wof:name":"Nes Trench Shoring",
    "wof:placetype":"venue"
},
  "geometry": {"coordinates":[-115.125285,36.223818],"type":"Point"}
}