{
  "type": "Feature",
  "properties": {
    "iso:country":"US",
    "sg:address":"4455 Paradise Road",
    "sg:city":"Las Vegas",
    "sg:classifiers":[
        {
            "category":"Shopping",
            "subcategory":"Jewelry",
            "type":"Retail Goods"
        }
    ],
    "sg:phone":"+1 702 693 4445",
    "sg:postcode":"89169",
    "sg:province":"NV",
    "wof:name":"Rocks the Jewelers",
    "wof:placetype":"venue"
},
  "geometry": {"coordinates":[-115.152559,36.1098],"type":"Point"}
}