{
  "type": "Feature",
  "properties": {
    "iso:country":"US",
    "sg:address":"1123 Cascade Dr",
    "sg:city":"Carson City",
    "sg:classifiers":[
        {
            "category":"Food & Beverages",
            "subcategory":"Specialty",
            "type":"Retail Goods"
        }
    ],
    "sg:phone":"+1 775 841 1112",
    "sg:postcode":"89701",
    "sg:province":"NV",
    "wof:name":"Body Wise International Inc",
    "wof:placetype":"venue"
},
  "geometry": {"coordinates":[-119.729877,39.170204],"type":"Point"}
}