{
  "type": "Feature",
  "properties": {
    "iso:country":"US",
    "sg:address":"320 Cabrillo Ln",
    "sg:city":"Reno",
    "sg:classifiers":[
        {
            "category":"Banks & Credit Unions",
            "subcategory":"Investment Brokerage",
            "type":"Services"
        }
    ],
    "sg:phone":"+1 775 425 1511",
    "sg:postcode":"89510",
    "sg:province":"NV",
    "sg:tags":[
        "retirement",
        "planning"
    ],
    "wof:name":"Iper Financial Intersecurities",
    "wof:placetype":"venue"
},
  "geometry": {"coordinates":[-119.694391,39.719519],"type":"Point"}
}