{
  "type": "Feature",
  "properties": {
    "iso:country":"US",
    "sg:address":"2240 Corporate Cir",
    "sg:city":"Henderson",
    "sg:classifiers":[
        {
            "category":"Utilities",
            "subcategory":"Telephone",
            "type":"Services"
        }
    ],
    "sg:phone":"+1 702 990 1000",
    "sg:postcode":"89074",
    "sg:province":"NV",
    "sg:tags":[
        "company"
    ],
    "sg:website":"www.xo.com",
    "wof:name":"X O Communications Inc",
    "wof:placetype":"venue"
},
  "geometry": {"coordinates":[-115.088885,36.02761],"type":"Point"}
}