{
  "type": "Feature",
  "properties": {
    "iso:country":"US",
    "sg:address":"7400 Las Vegas Blvd S Ste 121",
    "sg:city":"Las Vegas",
    "sg:classifiers":[
        {
            "category":"Shopping",
            "subcategory":"Bicycles & Sporting Goods",
            "type":"Retail Goods"
        }
    ],
    "sg:phone":"+1 702 260 8002",
    "sg:postcode":"89123",
    "sg:province":"NV",
    "wof:name":"Field of Dreams",
    "wof:placetype":"venue"
},
  "geometry": {"coordinates":[-115.172023,36.055081],"type":"Point"}
}