{
  "type": "Feature",
  "properties": {
    "iso:country":"US",
    "sg:address":"3655 S Durango Dr",
    "sg:city":"Las Vegas",
    "sg:classifiers":[
        {
            "category":"Personal",
            "subcategory":"Beauty Salon",
            "type":"Services"
        }
    ],
    "sg:phone":"+1 702 257 7000",
    "sg:postcode":"89147",
    "sg:province":"NV",
    "sg:tags":[
        "spa"
    ],
    "wof:name":"Destination Spa Salons",
    "wof:placetype":"venue"
},
  "geometry": {"coordinates":[-115.279613,36.12321],"type":"Point"}
}