{
  "type": "Feature",
  "properties": {
    "iso:country":"US",
    "sg:address":"1311 W Craig Rd",
    "sg:city":"North Las Vegas",
    "sg:classifiers":[
        {
            "category":"Restaurant",
            "type":"Food & Drink"
        }
    ],
    "sg:phone":"+1 702 399 5405",
    "sg:postcode":"89032",
    "sg:province":"NV",
    "wof:name":"Viva El Taco",
    "wof:placetype":"venue"
},
  "geometry": {"coordinates":[-115.156992,36.239317],"type":"Point"}
}