{
  "type": "Feature",
  "properties": {
    "iso:country":"US",
    "sg:address":"311 North Carson Street",
    "sg:city":"Carson City",
    "sg:classifiers":[
        {
            "category":"Bars & Pubs",
            "subcategory":"Lounge",
            "type":"Food & Drink"
        }
    ],
    "sg:phone":"+1 775 461 0466",
    "sg:postcode":"89701",
    "sg:province":"NV",
    "wof:name":"Jimmy G's Cigar Bar",
    "wof:placetype":"venue"
},
  "geometry": {"coordinates":[-119.76686599999999,39.165572],"type":"Point"}
}