{
  "type": "Feature",
  "properties": {
    "iso:country":"US",
    "sg:address":"1900 E Prater Way",
    "sg:city":"Sparks",
    "sg:classifiers":[
        {
            "category":"Health Services",
            "subcategory":"Clinic",
            "type":"Services"
        }
    ],
    "sg:phone":"+1 775 359 7810",
    "sg:postcode":"89434",
    "sg:province":"NV",
    "sg:tags":[
        "home"
    ],
    "wof:name":"Senior Helpers",
    "wof:placetype":"venue"
},
  "geometry": {"coordinates":[-119.711139,39.54194],"type":"Point"}
}