{
  "type": "Feature",
  "properties": {
    "iso:country":"US",
    "sg:address":"6208 Espinosa Ave",
    "sg:city":"Las Vegas",
    "sg:classifiers":[
        {
            "category":"Building & Trades",
            "subcategory":"Landscaping Services",
            "type":"Services"
        }
    ],
    "sg:phone":"+1 702 822 6239",
    "sg:postcode":"89108",
    "sg:province":"NV",
    "sg:tags":[
        "landscape"
    ],
    "wof:name":"Green Angel Landscape & Maint",
    "wof:placetype":"venue"
},
  "geometry": {"coordinates":[-115.23035400000001,36.198389],"type":"Point"}
}