{
  "type": "Feature",
  "properties": {
    "iso:country":"US",
    "sg:address":"3211 N Tenaya Way",
    "sg:city":"Las Vegas",
    "sg:classifiers":[
        {
            "category":"Professional",
            "subcategory":"Business Services",
            "type":"Services"
        }
    ],
    "sg:phone":"+1 702 839 4359",
    "sg:postcode":"89129",
    "sg:province":"NV",
    "sg:tags":[
        "box",
        "mail",
        "center"
    ],
    "wof:name":"Mail & Beyond",
    "wof:placetype":"venue"
},
  "geometry": {"coordinates":[-115.251455,36.219865],"type":"Point"}
}