{
  "type": "Feature",
  "properties": {
    "iso:country":"US",
    "sg:address":"7190 W Smoke Ranch Rd Ste 110",
    "sg:city":"Las Vegas",
    "sg:classifiers":[
        {
            "category":"Health Services",
            "subcategory":"Doctor",
            "type":"Services"
        },
        {
            "category":"Health Services",
            "subcategory":"Clinic",
            "type":"Services"
        }
    ],
    "sg:phone":"+1 702 987 1555",
    "sg:postcode":"89128",
    "sg:province":"NV",
    "sg:tags":[
        "loss",
        "medical",
        "weight",
        "spa"
    ],
    "sg:website":"www.angielorenzo.com",
    "wof:name":"Modern Medical & Wellness",
    "wof:placetype":"venue"
},
  "geometry": {"coordinates":[-115.258163,36.203504],"type":"Point"}
}