{
  "type": "Feature",
  "properties": {
    "iso:country":"US",
    "sg:address":"3979 Coolcrest Ct",
    "sg:city":"Las Vegas",
    "sg:classifiers":[
        {
            "category":"Professional",
            "subcategory":"Business Services",
            "type":"Services"
        }
    ],
    "sg:phone":"+1 702 655 7052",
    "sg:postcode":"89103",
    "sg:province":"NV",
    "sg:tags":[
        "inspection"
    ],
    "wof:name":"Consulting Services",
    "wof:placetype":"venue"
},
  "geometry": {"coordinates":[-115.218909,36.117017],"type":"Point"}
}