{
  "type": "Feature",
  "properties": {
    "iso:country":"US",
    "sg:address":"8122 Dancing Ave",
    "sg:city":"Las Vegas",
    "sg:classifiers":[
        {
            "category":"Banks & Credit Unions",
            "subcategory":"Financial Services",
            "type":"Services"
        }
    ],
    "sg:phone":"+1 702 538 9700",
    "sg:postcode":"89131",
    "sg:province":"NV",
    "sg:tags":[
        "broker",
        "mortgage"
    ],
    "wof:name":"T & L Homes and Loans",
    "wof:placetype":"venue"
},
  "geometry": {"coordinates":[-115.270202,36.329259],"type":"Point"}
}