{
  "type": "Feature",
  "properties": {
    "iso:country":"US",
    "sg:address":"2580 Wrondel Way",
    "sg:city":"Reno",
    "sg:classifiers":[
        {
            "category":"Place Of Worship",
            "subcategory":"Church",
            "type":"Public Place"
        },
        {
            "category":"Place Of Worship",
            "type":"Public Place"
        }
    ],
    "sg:phone":"+1 775 284 3256",
    "sg:postcode":"89502",
    "sg:province":"NV",
    "sg:tags":[
        "churches-christian"
    ],
    "wof:name":"Iglesia Christian El Verbo De Dios",
    "wof:placetype":"venue"
},
  "geometry": {"coordinates":[-119.796288,39.499939],"type":"Point"}
}