{
  "type": "Feature",
  "properties": {
    "iso:country":"US",
    "sg:address":"5088 San Anselmo St",
    "sg:city":"Las Vegas",
    "sg:classifiers":[
        {
            "category":"Wholesale",
            "subcategory":"Farm Supplies",
            "type":"Manufacturing & Wholesale Goods"
        }
    ],
    "sg:phone":"+1 702 451 4308",
    "sg:postcode":"89120",
    "sg:province":"NV",
    "sg:tags":[
        "operator",
        "local",
        "trucking"
    ],
    "wof:name":"Lynn Cowley & Sons Trucking",
    "wof:placetype":"venue"
},
  "geometry": {"coordinates":[-115.06713499999999,36.096032],"type":"Point"}
}