{
  "type": "Feature",
  "properties": {
    "iso:country":"US",
    "sg:address":"873 N Eastern Ave",
    "sg:city":"Las Vegas",
    "sg:classifiers":[
        {
            "category":"Professional",
            "subcategory":"Lawyer & Legal Services",
            "type":"Services"
        }
    ],
    "sg:phone":"+1 702 642 3113",
    "sg:postcode":"89101",
    "sg:province":"NV",
    "wof:name":"Bohn Michael F Law Offices",
    "wof:placetype":"venue"
},
  "geometry": {"coordinates":[-115.116133,36.180862],"type":"Point"}
}