{
  "type": "Feature",
  "properties": {
    "iso:country":"US",
    "sg:address":"12 W Mesquite Blvd",
    "sg:city":"Mesquite",
    "sg:classifiers":[
        {
            "category":"Professional",
            "subcategory":"Management & Consulting",
            "type":"Services"
        }
    ],
    "sg:phone":"+1 702 346 8987",
    "sg:postcode":"89027",
    "sg:province":"NV",
    "sg:tags":[
        "consultant",
        "broker"
    ],
    "wof:name":"Milby & Oliver Inc",
    "wof:placetype":"venue"
},
  "geometry": {"coordinates":[-114.068164,36.80394],"type":"Point"}
}