{
  "type": "Feature",
  "properties": {
    "iso:country":"US",
    "sg:address":"111 Country Club Dr",
    "sg:city":"Incline Village",
    "sg:classifiers":[
        {
            "category":"Communications",
            "subcategory":"Film & Video Production",
            "type":"Services"
        }
    ],
    "sg:phone":"+1 775 832 7756",
    "sg:postcode":"89451",
    "sg:province":"NV",
    "sg:tags":[
        "audio"
    ],
    "wof:name":"Presentation Svc",
    "wof:placetype":"venue"
},
  "geometry": {"coordinates":[-119.942783,39.2395],"type":"Point"}
}