{
  "type": "Feature",
  "properties": {
    "iso:country":"US",
    "sg:address":"4105 S Eastern Avenue",
    "sg:city":"Las Vegas",
    "sg:classifiers":[
        {
            "category":"Fast Food",
            "type":"Food & Drink"
        }
    ],
    "sg:phone":"+1 702 893 6622",
    "sg:postcode":"89119",
    "sg:province":"NV",
    "sg:website":"www.mcdonalds.com",
    "wof:name":"McDonalds Restaurant",
    "wof:placetype":"venue"
},
  "geometry": {"coordinates":[-115.119103,36.114023],"type":"Point"}
}