{
  "type": "Feature",
  "properties": {
    "iso:country":"US",
    "sg:address":"3156 E Russell Rd",
    "sg:city":"Las Vegas",
    "sg:classifiers":[
        {
            "category":"Professional",
            "subcategory":"Employment Agencies",
            "type":"Services"
        }
    ],
    "sg:phone":"+1 702 435 3650",
    "sg:postcode":"89120",
    "sg:province":"NV",
    "wof:name":"Executec Search Agency Inc",
    "wof:placetype":"venue"
},
  "geometry": {"coordinates":[-115.108778,36.086497],"type":"Point"}
}