{
  "type": "Feature",
  "properties": {
    "iso:country":"US",
    "sg:address":"8837 Sunset Breeze Dr",
    "sg:city":"Reno",
    "sg:classifiers":[
        {
            "category":"Transit Center",
            "subcategory":"Freight",
            "type":"Transportation"
        },
        {
            "category":"Freight",
            "type":"Transportation"
        }
    ],
    "sg:phone":"+1 775 762 6771",
    "sg:postcode":"89506",
    "sg:province":"NV",
    "sg:tags":[
        "local",
        "trucking-motor",
        "trucking"
    ],
    "wof:name":"Delo Trucking",
    "wof:placetype":"venue"
},
  "geometry": {"coordinates":[-119.896108,39.634361],"type":"Point"}
}