{
  "type": "Feature",
  "properties": {
    "iso:country":"US",
    "sg:address":"4325 Industrial Rd",
    "sg:city":"Las Vegas",
    "sg:classifiers":[
        {
            "category":"Shopping",
            "type":"Retail Goods"
        }
    ],
    "sg:phone":"+1 702 765 6565",
    "sg:postcode":"89103",
    "sg:province":"NV",
    "sg:tags":[
        "merchandise"
    ],
    "wof:name":"My Art Online Co 2",
    "wof:placetype":"venue"
},
  "geometry": {"coordinates":[-115.181288,36.109898],"type":"Point"}
}