{
  "type": "Feature",
  "properties": {
    "iso:country":"US",
    "sg:address":"6092 Walnut Creek Rd",
    "sg:city":"Reno",
    "sg:classifiers":[
        {
            "category":"Manufacturing",
            "subcategory":"Printing",
            "type":"Manufacturing & Wholesale Goods"
        }
    ],
    "sg:phone":"+1 775 746 1311",
    "sg:postcode":"89523",
    "sg:province":"NV",
    "sg:tags":[
        "publisher"
    ],
    "wof:name":"Cko Inc",
    "wof:placetype":"venue"
},
  "geometry": {"coordinates":[-119.883835,39.519304],"type":"Point"}
}