{
  "type": "Feature",
  "properties": {
    "iso:country":"US",
    "sg:address":"1409 E Lake Mead Boulevard",
    "sg:city":"North Las Vegas",
    "sg:classifiers":[
        {
            "category":"Health Services",
            "subcategory":"Doctor",
            "type":"Services"
        }
    ],
    "sg:phone":"+1 702 657 5775",
    "sg:postcode":"89030",
    "sg:province":"NV",
    "wof:name":"Futoran Robert J MD",
    "wof:placetype":"venue"
},
  "geometry": {"coordinates":[-115.122405,36.195794],"type":"Point"}
}