{
  "type": "Feature",
  "properties": {
    "iso:country":"US",
    "sg:address":"8072 W Sahara Ave Ste B",
    "sg:city":"Las Vegas",
    "sg:classifiers":[
        {
            "category":"Health Services",
            "subcategory":"Dentist",
            "type":"Services"
        }
    ],
    "sg:phone":"+1 702 363 0757",
    "sg:postcode":"89117",
    "sg:province":"NV",
    "wof:name":"Adams Richard K DDS",
    "wof:placetype":"venue"
},
  "geometry": {"coordinates":[-115.26738899999999,36.143936],"type":"Point"}
}