{
  "type": "Feature",
  "properties": {
    "iso:country":"US",
    "sg:address":"1575 Delucchi Ln",
    "sg:city":"Reno",
    "sg:classifiers":[
        {
            "category":"Banks & Credit Unions",
            "subcategory":"Investment Brokerage",
            "type":"Services"
        }
    ],
    "sg:phone":"+1 775 829 6911",
    "sg:postcode":"89502",
    "sg:province":"NV",
    "sg:tags":[
        "security"
    ],
    "wof:name":"Linsco/Private Ledger Corp",
    "wof:placetype":"venue"
},
  "geometry": {"coordinates":[-119.777446,39.469649],"type":"Point"}
}