{
  "type": "Feature",
  "properties": {
    "iso:country":"US",
    "sg:address":"7171 W Craig Road",
    "sg:city":"Las Vegas",
    "sg:classifiers":[
        {
            "category":"Retail",
            "subcategory":"Laundry & Dry Cleaning",
            "type":"Services"
        }
    ],
    "sg:phone":"+1 702 656 6406",
    "sg:postcode":"89129",
    "sg:province":"NV",
    "wof:name":"Won Cleaners",
    "wof:placetype":"venue"
},
  "geometry": {"coordinates":[-115.251475,36.240439],"type":"Point"}
}