{
  "type": "Feature",
  "properties": {
    "iso:country":"US",
    "sg:address":"3151 N Rainbow Blvd",
    "sg:city":"Las Vegas",
    "sg:classifiers":[
        {
            "category":"Building & Trades",
            "subcategory":"Construction",
            "type":"Services"
        }
    ],
    "sg:phone":"+1 702 395 8380",
    "sg:postcode":"89108",
    "sg:province":"NV",
    "sg:tags":[
        "coping",
        "plastering",
        "tiling",
        "pool",
        "swimming"
    ],
    "wof:name":"Judy's Pool Svc",
    "wof:placetype":"venue"
},
  "geometry": {"coordinates":[-115.242363,36.216042],"type":"Point"}
}