{
  "type": "Feature",
  "properties": {
    "iso:country":"US",
    "sg:address":"5260 Idaho St",
    "sg:city":"Elko",
    "sg:classifiers":[
        {
            "category":"Personal",
            "subcategory":"Beauty Salon",
            "type":"Services"
        }
    ],
    "sg:phone":"+1 775 738 7775",
    "sg:postcode":"89801",
    "sg:province":"NV",
    "sg:tags":[
        "shop"
    ],
    "wof:name":"Fantastic Sams",
    "wof:placetype":"venue"
},
  "geometry": {"coordinates":[-115.722408,40.874008],"type":"Point"}
}