{
  "type": "Feature",
  "properties": {
    "iso:country":"US",
    "sg:address":"4299 E Sunset Road",
    "sg:city":"Henderson",
    "sg:classifiers":[
        {
            "category":"Banks & Credit Unions",
            "subcategory":"Bank",
            "type":"Services"
        }
    ],
    "sg:phone":"+1 702 435 9902",
    "sg:postcode":"89014",
    "sg:province":"NV",
    "sg:website":"www.colonialbank.com",
    "wof:name":"Colonial Bank",
    "wof:placetype":"venue"
},
  "geometry": {"coordinates":[-115.08112,36.070906],"type":"Point"}
}