{
  "type": "Feature",
  "properties": {
    "iso:country":"US",
    "sg:address":"5264 Sacha Way",
    "sg:city":"Las Vegas",
    "sg:classifiers":[
        {
            "category":"Professional",
            "subcategory":"Business Services",
            "type":"Services"
        }
    ],
    "sg:phone":"+1 702 248 6625",
    "sg:postcode":"89118",
    "sg:province":"NV",
    "wof:name":"Svanchara Enterprises",
    "wof:placetype":"venue"
},
  "geometry": {"coordinates":[-115.219172,36.09342],"type":"Point"}
}