{
  "type": "Feature",
  "properties": {
    "iso:country":"US",
    "sg:address":"2756 N Green Valley Pkwy",
    "sg:city":"Henderson",
    "sg:classifiers":[
        {
            "category":"Professional",
            "subcategory":"Management & Consulting",
            "type":"Services"
        }
    ],
    "sg:phone":"+1 702 456 6701",
    "sg:postcode":"89014",
    "sg:province":"NV",
    "sg:tags":[
        "consultant",
        "e",
        "sales",
        "store"
    ],
    "wof:name":"International Aero Space Pdts",
    "wof:placetype":"venue"
},
  "geometry": {"coordinates":[-115.08233,36.068872],"type":"Point"}
}