{
  "type": "Feature",
  "properties": {
    "iso:country":"US",
    "sg:address":"113 Corbett St",
    "sg:city":"Carson City",
    "sg:classifiers":[
        {
            "category":"Retail",
            "subcategory":"Animal Services",
            "type":"Services"
        }
    ],
    "sg:phone":"+1 775 883 9729",
    "sg:postcode":"89706",
    "sg:province":"NV",
    "wof:name":"Dog Grooming By Nancy Hahn",
    "wof:placetype":"venue"
},
  "geometry": {"coordinates":[-119.765531,39.171903],"type":"Point"}
}