{
  "type": "Feature",
  "properties": {
    "iso:country":"US",
    "sg:address":"505 E Oakey Blvd",
    "sg:city":"Las Vegas",
    "sg:classifiers":[
        {
            "category":"Restaurant",
            "type":"Food & Drink"
        }
    ],
    "sg:phone":"+1 702 384 6452",
    "sg:postcode":"89104",
    "sg:province":"NV",
    "sg:tags":[
        "frozen",
        "yogurt",
        "parlor",
        "ice",
        "cream"
    ],
    "sg:website":"www.luvitfrozencustard.com",
    "wof:name":"Luv-It Frozen Custard",
    "wof:placetype":"venue"
},
  "geometry": {"coordinates":[-115.15118200000001,36.151552],"type":"Point"}
}