{
  "type": "Feature",
  "properties": {
    "iso:country":"US",
    "sg:address":"341 N Buffalo Dr",
    "sg:city":"Las Vegas",
    "sg:classifiers":[
        {
            "category":"Personal",
            "subcategory":"Hair Removal",
            "type":"Services"
        }
    ],
    "sg:phone":"+1 702 804 0166",
    "sg:postcode":"89145",
    "sg:province":"NV",
    "sg:tags":[
        "removing"
    ],
    "wof:name":"Renu Laser Cosmetics",
    "wof:placetype":"venue"
},
  "geometry": {"coordinates":[-115.259836,36.177634],"type":"Point"}
}