{
  "type": "Feature",
  "properties": {
    "iso:country":"US",
    "sg:address":"6383 Casey Rd",
    "sg:city":"Fallon",
    "sg:classifiers":[
        {
            "category":"Manufacturing",
            "subcategory":"Lumber",
            "type":"Manufacturing & Wholesale Goods"
        }
    ],
    "sg:phone":"+1 775 867 2804",
    "sg:postcode":"89406",
    "sg:province":"NV",
    "sg:tags":[
        "hardwood",
        "mill"
    ],
    "wof:name":"Jkcrafts",
    "wof:placetype":"venue"
},
  "geometry": {"coordinates":[-118.88258500000001,39.480875],"type":"Point"}
}