{
  "type": "Feature",
  "properties": {
    "iso:country":"US",
    "sg:address":"3720 E Tropicana Avenue",
    "sg:city":"Las Vegas",
    "sg:classifiers":[
        {
            "category":"Social Services",
            "subcategory":"Child Care",
            "type":"Services"
        },
        {
            "category":"Education",
            "subcategory":"Preschool",
            "type":"Public Place"
        },
        {
            "category":"Education",
            "subcategory":"School",
            "type":"Public Place"
        }
    ],
    "sg:phone":"+1 702 458 2243",
    "sg:postcode":"89121",
    "sg:province":"NV",
    "sg:tags":[
        "elementary",
        "day"
    ],
    "sg:website":"www.communitylutheran.com",
    "wof:name":"Hill & Dale Child Development Center",
    "wof:placetype":"venue"
},
  "geometry": {"coordinates":[-115.093542,36.100103],"type":"Point"}
}