{
  "type": "Feature",
  "properties": {
    "iso:country":"US",
    "sg:address":"1778 Autumn Rust Dr",
    "sg:city":"Las Vegas",
    "sg:classifiers":[
        {
            "category":"Professional",
            "subcategory":"Business Services",
            "type":"Services"
        }
    ],
    "sg:phone":"+1 702 361 0490",
    "sg:postcode":"89119",
    "sg:province":"NV",
    "wof:name":"Waigo Enterprises Inc",
    "wof:placetype":"venue"
},
  "geometry": {"coordinates":[-115.127754,36.063314],"type":"Point"}
}