{
  "type": "Feature",
  "properties": {
    "iso:country":"US",
    "sg:address":"4740 S Valley View Blvd",
    "sg:city":"Las Vegas",
    "sg:classifiers":[
        {
            "category":"Professional",
            "subcategory":"Advertising",
            "type":"Services"
        }
    ],
    "sg:phone":"+1 702 320 1955",
    "sg:postcode":"89103",
    "sg:province":"NV",
    "wof:name":"Fastlane Advertising LLC",
    "wof:placetype":"venue"
},
  "geometry": {"coordinates":[-115.189752,36.101642],"type":"Point"}
}