{
  "type": "Feature",
  "properties": {
    "iso:country":"US",
    "sg:address":"2951 N Deer Run Rd",
    "sg:city":"Carson City",
    "sg:classifiers":[
        {
            "category":"Retail",
            "subcategory":"Auto Repair",
            "type":"Services"
        }
    ],
    "sg:phone":"+1 775 841 2828",
    "sg:postcode":"89701",
    "sg:province":"NV",
    "sg:tags":[
        "repairing",
        "automobile"
    ],
    "wof:name":"Nevada Auto Repair",
    "wof:placetype":"venue"
},
  "geometry": {"coordinates":[-119.70066300000001,39.18507],"type":"Point"}
}