{
  "type": "Feature",
  "properties": {
    "iso:country":"US",
    "sg:address":"681 S Highway 160",
    "sg:city":"Pahrump",
    "sg:classifiers":[
        {
            "category":"Restaurant",
            "type":"Food & Drink"
        },
        {
            "category":"Ice Cream",
            "type":"Food & Drink"
        }
    ],
    "sg:menulink":"http://www.allmenus.com/nv/pahrump/167901-dairy-queen/menu/",
    "sg:phone":"+1 775 751 8410",
    "sg:postcode":"89048",
    "sg:province":"NV",
    "sg:tags":[
        "burger",
        "american",
        "ice",
        "cream"
    ],
    "wof:name":"Dairy Queen",
    "wof:placetype":"venue"
},
  "geometry": {"coordinates":[-115.984872,36.209239],"type":"Point"}
}