{
  "type": "Feature",
  "properties": {
    "iso:country":"US",
    "sg:address":"2500 W Oakey Blvd",
    "sg:city":"Las Vegas",
    "sg:classifiers":[
        {
            "category":"Professional",
            "type":"Services"
        }
    ],
    "sg:phone":"+1 702 878 7110",
    "sg:postcode":"89102",
    "sg:province":"NV",
    "sg:tags":[
        "writer"
    ],
    "wof:name":"Kalnasy Kenneth Anette Lawson",
    "wof:placetype":"venue"
},
  "geometry": {"coordinates":[-115.175872,36.151681],"type":"Point"}
}