{
  "type": "Feature",
  "properties": {
    "iso:country":"US",
    "sg:address":"4180 S Sandhill Rd",
    "sg:city":"Las Vegas",
    "sg:classifiers":[
        {
            "category":"Organizations",
            "subcategory":"Religious Organization",
            "type":"Services"
        }
    ],
    "sg:phone":"+1 702 731 4766",
    "sg:postcode":"89121",
    "sg:province":"NV",
    "sg:tags":[
        "church"
    ],
    "wof:name":"Sunrise Mountain Ministries",
    "wof:placetype":"venue"
},
  "geometry": {"coordinates":[-115.091869,36.114718],"type":"Point"}
}