{
  "type": "Feature",
  "properties": {
    "iso:country":"US",
    "sg:address":"7841 Dappled Light Ave",
    "sg:city":"Las Vegas",
    "sg:classifiers":[
        {
            "category":"Professional",
            "subcategory":"Art Services",
            "type":"Services"
        }
    ],
    "sg:phone":"+1 702 812 8880",
    "sg:postcode":"89131",
    "sg:province":"NV",
    "sg:tags":[
        "photographer"
    ],
    "sg:website":"www.jianphoto.com/",
    "wof:name":"Joshua Ian - Las Vegas Wedding Photography by Design",
    "wof:placetype":"venue"
},
  "geometry": {"coordinates":[-115.266359,36.300436],"type":"Point"}
}