{
  "type": "Feature",
  "properties": {
    "iso:country":"US",
    "sg:address":"9999 W Katie Ave Ofc",
    "sg:city":"Las Vegas",
    "sg:classifiers":[
        {
            "category":"Real Estate",
            "subcategory":"Real Estate Operator",
            "type":"Services"
        }
    ],
    "sg:phone":"+1 702 307 9999",
    "sg:postcode":"89147",
    "sg:province":"NV",
    "sg:tags":[
        "apartment"
    ],
    "wof:name":"Resort At the Lakes the",
    "wof:placetype":"venue"
},
  "geometry": {"coordinates":[-115.309998,36.120701],"type":"Point"}
}