{
  "type": "Feature",
  "properties": {
    "iso:country":"US",
    "sg:address":"4531 W Sahara Ave",
    "sg:city":"Las Vegas",
    "sg:classifiers":[
        {
            "category":"Recreation",
            "type":"Entertainment"
        }
    ],
    "sg:phone":"+1 702 444 1437",
    "sg:postcode":"89102",
    "sg:province":"NV",
    "sg:tags":[
        "martial",
        "arts",
        "instruction"
    ],
    "wof:name":"White Tiger Red Dragon Kempo",
    "wof:placetype":"venue"
},
  "geometry": {"coordinates":[-115.200249,36.144405],"type":"Point"}
}