{
  "type": "Feature",
  "properties": {
    "iso:country":"US",
    "sg:address":"6251 Brynhurst Dr",
    "sg:city":"Las Vegas",
    "sg:classifiers":[
        {
            "category":"Wholesale",
            "subcategory":"Machinery & Supplies",
            "type":"Manufacturing & Wholesale Goods"
        }
    ],
    "sg:phone":"+1 702 459 4590",
    "sg:postcode":"89156",
    "sg:province":"NV",
    "sg:tags":[
        "equipment",
        "transportation"
    ],
    "wof:name":"Waitman Helicopters Inc",
    "wof:placetype":"venue"
},
  "geometry": {"coordinates":[-115.035689,36.18963],"type":"Point"}
}