{
  "type": "Feature",
  "properties": {
    "iso:country":"US",
    "sg:address":"501 Casazza Dr",
    "sg:city":"Reno",
    "sg:classifiers":[
        {
            "category":"Health Services",
            "subcategory":"Clinic",
            "type":"Services"
        }
    ],
    "sg:phone":"+1 775 324 5004",
    "sg:postcode":"89502",
    "sg:province":"NV",
    "wof:name":"Spiritual Element",
    "wof:placetype":"venue"
},
  "geometry": {"coordinates":[-119.798198,39.507459],"type":"Point"}
}