{
  "type": "Feature",
  "properties": {
    "iso:country":"US",
    "sg:address":"1750 E Russell Rd",
    "sg:city":"Las Vegas",
    "sg:classifiers":[
        {
            "category":"Banks & Credit Unions",
            "subcategory":"Bank",
            "type":"Services"
        }
    ],
    "sg:phone":"+1 702 740 4003",
    "sg:postcode":"89119",
    "sg:province":"NV",
    "sg:tags":[
        "cashing",
        "check"
    ],
    "wof:name":"Mazzz Dinero Rapido",
    "wof:placetype":"venue"
},
  "geometry": {"coordinates":[-115.129527,36.086481],"type":"Point"}
}