{
  "type": "Feature",
  "properties": {
    "iso:country":"US",
    "sg:address":"6225 S Valley View Blvd",
    "sg:city":"Las Vegas",
    "sg:classifiers":[
        {
            "category":"Wholesale",
            "subcategory":"Hardware",
            "type":"Manufacturing & Wholesale Goods"
        }
    ],
    "sg:phone":"+1 702 269 7493",
    "sg:postcode":"89118",
    "sg:province":"NV",
    "sg:tags":[
        "plumbing",
        "fixture",
        "supply"
    ],
    "wof:name":"Solomon Sales",
    "wof:placetype":"venue"
},
  "geometry": {"coordinates":[-115.190028,36.077246],"type":"Point"}
}