{
  "type": "Feature",
  "properties": {
    "iso:country":"US",
    "sg:address":"4283 Muirwood Ct",
    "sg:city":"Reno",
    "sg:classifiers":[
        {
            "category":"Banks & Credit Unions",
            "subcategory":"Financial Services",
            "type":"Services"
        }
    ],
    "sg:phone":"+1 775 827 1897",
    "sg:postcode":"89509",
    "sg:province":"NV",
    "sg:tags":[
        "trust",
        "management"
    ],
    "wof:name":"King Family Charitable Trust",
    "wof:placetype":"venue"
},
  "geometry": {"coordinates":[-119.8234,39.484005],"type":"Point"}
}