{
  "type": "Feature",
  "properties": {
    "iso:country":"US",
    "sg:address":"10255 Coyote Creek Dr",
    "sg:city":"Reno",
    "sg:classifiers":[
        {
            "category":"Professional",
            "subcategory":"Management & Consulting",
            "type":"Services"
        }
    ],
    "sg:phone":"+1 775 852 7074",
    "sg:postcode":"89521",
    "sg:province":"NV",
    "sg:tags":[
        "business"
    ],
    "wof:name":"Project Directors Inc",
    "wof:placetype":"venue"
},
  "geometry": {"coordinates":[-119.741805,39.433938],"type":"Point"}
}