{
  "type": "Feature",
  "properties": {
    "iso:country":"US",
    "sg:address":"3663 Las Vegas Blvd S Ste 382",
    "sg:city":"Las Vegas",
    "sg:classifiers":[
        {
            "category":"Arts & Performance",
            "subcategory":"Art Gallery",
            "type":"Entertainment"
        }
    ],
    "sg:phone":"+1 702 792 6005",
    "sg:postcode":"89109",
    "sg:province":"NV",
    "wof:name":"Painted With Oil",
    "wof:placetype":"venue"
},
  "geometry": {"coordinates":[-115.170501,36.108768],"type":"Point"}
}