{
  "type": "Feature",
  "properties": {
    "iso:country":"US",
    "sg:address":"75 E Moana Ln",
    "sg:city":"Reno",
    "sg:classifiers":[
        {
            "category":"Home & Garden",
            "subcategory":"Furniture",
            "type":"Retail Goods"
        }
    ],
    "sg:phone":"+1 775 826 4800",
    "sg:postcode":"89502",
    "sg:province":"NV",
    "sg:tags":[
        "outdoor",
        "patio",
        "store"
    ],
    "sg:website":"http://www.californiabackyard.com",
    "wof:name":"Nevada Backyard",
    "wof:placetype":"venue"
},
  "geometry": {"coordinates":[-119.796219,39.491566],"type":"Point"}
}