{
  "type": "Feature",
  "properties": {
    "iso:country":"US",
    "sg:address":"3025 Fremont St",
    "sg:city":"Las Vegas",
    "sg:classifiers":[
        {
            "category":"Autos & Motor Vehicles",
            "subcategory":"Recreational Vehicle Sales",
            "type":"Retail Goods"
        }
    ],
    "sg:phone":"+1 702 457 9334",
    "sg:postcode":"89104",
    "sg:province":"NV",
    "sg:tags":[
        "boat"
    ],
    "wof:name":"Beachcomber Trailers",
    "wof:placetype":"venue"
},
  "geometry": {"coordinates":[-115.10579300000001,36.149668],"type":"Point"}
}