{
  "type": "Feature",
  "properties": {
    "iso:country":"US",
    "sg:address":"3801 Sequoia Ave",
    "sg:city":"Las Vegas",
    "sg:classifiers":[
        {
            "category":"Building & Trades",
            "subcategory":"Cleaning & Sanitation",
            "type":"Services"
        }
    ],
    "sg:phone":"+1 702 452 4297",
    "sg:postcode":"89110",
    "sg:province":"NV",
    "sg:tags":[
        "maintenance"
    ],
    "wof:name":"SM House Cleaning",
    "wof:placetype":"venue"
},
  "geometry": {"coordinates":[-115.093712,36.184919],"type":"Point"}
}