{
  "type": "Feature",
  "properties": {
    "iso:country":"US",
    "sg:address":"6895 E Lake Mead Blvd Ste A3",
    "sg:city":"Las Vegas",
    "sg:classifiers":[
        {
            "category":"Restaurant",
            "type":"Food & Drink"
        }
    ],
    "sg:phone":"+1 702 437 2288",
    "sg:postcode":"89156",
    "sg:province":"NV",
    "sg:tags":[
        "chinese"
    ],
    "sg:website":"www.mandarinexpressnv.com",
    "wof:name":"Mandarin Express",
    "wof:placetype":"venue"
},
  "geometry": {"coordinates":[-115.025484,36.194185],"type":"Point"}
}