{
  "type": "Feature",
  "properties": {
    "iso:country":"US",
    "sg:address":"570 W Cheyenne Avenue Suite 60",
    "sg:city":"North Las Vegas",
    "sg:classifiers":[
        {
            "category":"Building & Trades",
            "subcategory":"Plumbing",
            "type":"Services"
        }
    ],
    "sg:phone":"+1 702 649 8787",
    "sg:postcode":"89030",
    "sg:province":"NV",
    "wof:name":"P-C Plumbing",
    "wof:placetype":"venue"
},
  "geometry": {"coordinates":[-115.14789,36.21785],"type":"Point"}
}