{
  "type": "Feature",
  "properties": {
    "iso:country":"US",
    "sg:address":"509 Fremont St",
    "sg:city":"Las Vegas",
    "sg:classifiers":[
        {
            "category":"Personal",
            "subcategory":"Tattoo Parlor",
            "type":"Services"
        }
    ],
    "sg:phone":"+1 702 384 7379",
    "sg:postcode":"89101",
    "sg:province":"NV",
    "wof:name":"Las Vegas Tattoo & Souvenirs",
    "wof:placetype":"venue"
},
  "geometry": {"coordinates":[-115.140558,36.169036],"type":"Point"}
}