{
  "type": "Feature",
  "properties": {
    "iso:country":"US",
    "sg:address":"4550 W Oakey Blvd",
    "sg:city":"Las Vegas",
    "sg:classifiers":[
        {
            "category":"Banks & Credit Unions",
            "subcategory":"Financial Services",
            "type":"Services"
        }
    ],
    "sg:phone":"+1 702 220 4479",
    "sg:postcode":"89102",
    "sg:province":"NV",
    "sg:tags":[
        "broker",
        "mortgage"
    ],
    "wof:name":"Wilrock Mortgage",
    "wof:placetype":"venue"
},
  "geometry": {"coordinates":[-115.203625,36.152216],"type":"Point"}
}