{
  "type": "Feature",
  "properties": {
    "iso:country":"US",
    "sg:address":"2801 W Charleston Blvd Ste 201",
    "sg:city":"Las Vegas",
    "sg:classifiers":[
        {
            "category":"Community Center",
            "type":"Public Place"
        }
    ],
    "sg:phone":"+1 888 840 8688",
    "sg:postcode":"89102",
    "sg:province":"NV",
    "sg:tags":[
        "medical"
    ],
    "sg:website":"www.nonprofitstdtesting.org",
    "wof:name":"Las Vegas HIV/STD Testing",
    "wof:placetype":"venue"
},
  "geometry": {"coordinates":[-115.179282,36.158571],"type":"Point"}
}