{
  "type": "Feature",
  "properties": {
    "iso:country":"US",
    "sg:address":"3905 W Diablo Dr",
    "sg:city":"Las Vegas",
    "sg:classifiers":[
        {
            "category":"Building & Trades",
            "subcategory":"Construction",
            "type":"Services"
        }
    ],
    "sg:phone":"+1 702 739 6649",
    "sg:postcode":"89118",
    "sg:province":"NV",
    "sg:tags":[
        "roofing",
        "contractor"
    ],
    "sg:website":"www.wsp.com",
    "wof:name":"Western Single Ply",
    "wof:placetype":"venue"
},
  "geometry": {"coordinates":[-115.193361,36.089901],"type":"Point"}
}