{
  "type": "Feature",
  "properties": {
    "iso:country":"US",
    "sg:address":"7500 W Lake Mead Blvd Ste 2",
    "sg:city":"Las Vegas",
    "sg:classifiers":[
        {
            "category":"Ice Cream",
            "type":"Food & Drink"
        }
    ],
    "sg:phone":"+1 702 834 8200",
    "sg:postcode":"89128",
    "sg:province":"NV",
    "sg:tags":[
        "frozen",
        "yogurt"
    ],
    "sg:website":"www.menchies.com",
    "wof:name":"Menchie's Frozen Yogurt",
    "wof:placetype":"venue"
},
  "geometry": {"coordinates":[-115.25779900000001,36.19724],"type":"Point"}
}