{
  "type": "Feature",
  "properties": {
    "iso:country":"US",
    "sg:address":"1420 S Wells Ave",
    "sg:city":"Reno",
    "sg:classifiers":[
        {
            "category":"Restaurant",
            "type":"Food & Drink"
        }
    ],
    "sg:phone":"+1 775 786 8500",
    "sg:postcode":"89502",
    "sg:province":"NV",
    "sg:tags":[
        "eating"
    ],
    "wof:name":"Eatos Burritos",
    "wof:placetype":"venue"
},
  "geometry": {"coordinates":[-119.803062,39.511055],"type":"Point"}
}