{
  "type": "Feature",
  "properties": {
    "iso:country":"US",
    "sg:address":"1891 Bova Matrina Ct",
    "sg:city":"Las Vegas",
    "sg:classifiers":[
        {
            "category":"Shopping",
            "type":"Retail Goods"
        }
    ],
    "sg:phone":"+1 702 614 3970",
    "sg:postcode":"89123",
    "sg:province":"NV",
    "sg:tags":[
        "merchandise"
    ],
    "wof:name":"Lsc Consulting",
    "wof:placetype":"venue"
},
  "geometry": {"coordinates":[-115.125468,36.019295],"type":"Point"}
}