{
  "type": "Feature",
  "properties": {
    "iso:country":"US",
    "sg:address":"9816 Double Rock Dr",
    "sg:city":"Las Vegas",
    "sg:classifiers":[
        {
            "category":"Building & Trades",
            "subcategory":"Cleaning & Sanitation",
            "type":"Services"
        }
    ],
    "sg:phone":"+1 702 360 2946",
    "sg:postcode":"89134",
    "sg:province":"NV",
    "sg:tags":[
        "janitor"
    ],
    "wof:name":"Cleaner Than Clean Janitorial",
    "wof:placetype":"venue"
},
  "geometry": {"coordinates":[-115.311051,36.191237],"type":"Point"}
}