{
  "type": "Feature",
  "properties": {
    "iso:country":"US",
    "sg:address":"2225 Village Walk Drive",
    "sg:city":"Henderson",
    "sg:classifiers":[
        {
            "category":"Shopping",
            "subcategory":"Discount & Variety Stores",
            "type":"Retail Goods"
        }
    ],
    "sg:phone":"+1 702 492 7629",
    "sg:postcode":"89052",
    "sg:province":"NV",
    "sg:tags":[
        "outlet"
    ],
    "sg:website":"www.josbank.com",
    "wof:name":"Jos A Bank Clothiers",
    "wof:placetype":"venue"
},
  "geometry": {"coordinates":[-115.085055,36.021803],"type":"Point"}
}