{
  "type": "Feature",
  "properties": {
    "iso:country":"US",
    "sg:address":"3800 Euclid St",
    "sg:city":"Las Vegas",
    "sg:classifiers":[
        {
            "category":"Shopping",
            "subcategory":"Gifts & Souvenirs",
            "type":"Retail Goods"
        }
    ],
    "sg:phone":"+1 702 739 1973",
    "sg:postcode":"89121",
    "sg:province":"NV",
    "wof:name":"Images Of Nevada",
    "wof:placetype":"venue"
},
  "geometry": {"coordinates":[-115.116731,36.119952],"type":"Point"}
}