{
  "type": "Feature",
  "properties": {
    "iso:country":"US",
    "sg:address":"6853 Spencer St",
    "sg:city":"Las Vegas",
    "sg:classifiers":[
        {
            "category":"Building & Trades",
            "subcategory":"Equipment Rental",
            "type":"Services"
        },
        {
            "category":"Wholesale",
            "subcategory":"Electrical",
            "type":"Manufacturing & Wholesale Goods"
        }
    ],
    "sg:phone":"+1 702 459 1700",
    "sg:postcode":"89119",
    "sg:province":"NV",
    "sg:tags":[
        "testing",
        "electronic"
    ],
    "sg:website":"www.emt1.com",
    "wof:name":"Equipment Management Technolgy",
    "wof:placetype":"venue"
},
  "geometry": {"coordinates":[-115.127742,36.065455],"type":"Point"}
}