{
  "type": "Feature",
  "properties": {
    "iso:country":"US",
    "sg:address":"3555 Las Vegas Blvd S",
    "sg:city":"Las Vegas",
    "sg:classifiers":[
        {
            "category":"Personal",
            "subcategory":"Beauty Salon",
            "type":"Services"
        }
    ],
    "sg:phone":"+1 702 737 1456",
    "sg:postcode":"89109",
    "sg:province":"NV",
    "sg:tags":[
        "shop"
    ],
    "wof:name":"Alexandra Beauty Salon",
    "wof:placetype":"venue"
},
  "geometry": {"coordinates":[-115.170142,36.124232],"type":"Point"}
}