{
  "type": "Feature",
  "properties": {
    "iso:country":"US",
    "sg:address":"909 Shifting Sands Dr",
    "sg:city":"Las Vegas",
    "sg:classifiers":[
        {
            "category":"Arts & Performance",
            "subcategory":"Theater",
            "type":"Entertainment"
        }
    ],
    "sg:phone":"+1 702 870 6919",
    "sg:postcode":"89108",
    "sg:province":"NV",
    "sg:tags":[
        "live",
        "music"
    ],
    "wof:name":"Jovans DJ",
    "wof:placetype":"venue"
},
  "geometry": {"coordinates":[-115.22490000000001,36.180818],"type":"Point"}
}