{
  "type": "Feature",
  "properties": {
    "iso:country":"US",
    "sg:address":"5021 N Rainbow Blvd",
    "sg:city":"Las Vegas",
    "sg:classifiers":[
        {
            "category":"Bars & Pubs",
            "type":"Food & Drink"
        },
        {
            "category":"Restaurant",
            "type":"Food & Drink"
        }
    ],
    "sg:phone":"+1 702 655 5939",
    "sg:postcode":"89130",
    "sg:province":"NV",
    "sg:tags":[
        "traditional",
        "american"
    ],
    "wof:name":"Santa Fe Mining Company",
    "wof:placetype":"venue"
},
  "geometry": {"coordinates":[-115.24326000000001,36.252655],"type":"Point"}
}