{
  "type": "Feature",
  "properties": {
    "iso:country":"US",
    "sg:address":"599 East William",
    "sg:city":"Carson City",
    "sg:classifiers":[
        {
            "category":"Food & Beverages",
            "subcategory":"Groceries & Convenience Stores",
            "type":"Retail Goods"
        }
    ],
    "sg:postcode":"89701",
    "sg:province":"NV",
    "sg:website":"www.smithsfoodanddrug.com",
    "wof:name":"Smiths Food",
    "wof:placetype":"venue"
},
  "geometry": {"coordinates":[-119.762726,39.169394],"type":"Point"}
}