{
  "type": "Feature",
  "properties": {
    "iso:country":"US",
    "sg:address":"3240 E Desert Inn Rd",
    "sg:city":"Las Vegas",
    "sg:classifiers":[
        {
            "category":"Banks & Credit Unions",
            "subcategory":"Bank",
            "type":"Services"
        }
    ],
    "sg:phone":"+1 702 267 9240",
    "sg:postcode":"89121",
    "sg:province":"NV",
    "sg:tags":[
        "loan"
    ],
    "wof:name":"Loan Max",
    "wof:placetype":"venue"
},
  "geometry": {"coordinates":[-115.10169399999999,36.129772],"type":"Point"}
}