{
  "type": "Feature",
  "properties": {
    "iso:country":"US",
    "sg:address":"5725 S Valley View Blvd",
    "sg:city":"Las Vegas",
    "sg:classifiers":[
        {
            "category":"Building & Trades",
            "subcategory":"Electrical",
            "type":"Services"
        }
    ],
    "sg:phone":"+1 702 262 9400",
    "sg:postcode":"89118",
    "sg:province":"NV",
    "sg:tags":[
        "electrician"
    ],
    "wof:name":"Gifford Electric Technology",
    "wof:placetype":"venue"
},
  "geometry": {"coordinates":[-115.19000200000001,36.085899],"type":"Point"}
}