{
  "type": "Feature",
  "properties": {
    "iso:country":"US",
    "sg:address":"810 Dusan Way",
    "sg:city":"Las Vegas",
    "sg:classifiers":[
        {
            "category":"Building & Trades",
            "subcategory":"Construction",
            "type":"Services"
        }
    ],
    "sg:phone":"+1 702 564 7387",
    "sg:postcode":"89101",
    "sg:province":"NV",
    "sg:tags":[
        "contractor"
    ],
    "wof:name":"Mmrp Llc",
    "wof:placetype":"venue"
},
  "geometry": {"coordinates":[-114.95739,36.081919],"type":"Point"}
}