{
  "type": "Feature",
  "properties": {
    "iso:country":"US",
    "sg:address":"55 E Winnie Ln",
    "sg:city":"Carson City",
    "sg:classifiers":[
        {
            "category":"Recreation",
            "type":"Entertainment"
        }
    ],
    "sg:phone":"+1 775 882 5997",
    "sg:postcode":"89706",
    "sg:province":"NV",
    "sg:tags":[
        "drinking"
    ],
    "wof:name":"Cue-Phoria Billiards",
    "wof:placetype":"venue"
},
  "geometry": {"coordinates":[-119.765369,39.179101],"type":"Point"}
}