{
  "type": "Feature",
  "properties": {
    "iso:country":"US",
    "sg:address":"511 Dutchman Ave",
    "sg:city":"Henderson",
    "sg:classifiers":[
        {
            "category":"Retail",
            "subcategory":"Animal Services",
            "type":"Services"
        }
    ],
    "sg:phone":"+1 702 565 7682",
    "sg:postcode":"89011",
    "sg:province":"NV",
    "wof:name":"Personal Touch",
    "wof:placetype":"venue"
},
  "geometry": {"coordinates":[-114.996735,36.064992],"type":"Point"}
}