{
  "type": "Feature",
  "properties": {
    "iso:country":"US",
    "sg:address":"Koontz Ln and Center Dr",
    "sg:city":"Carson City",
    "sg:classifiers":[
        {
            "category":"Park",
            "type":"Public Place"
        }
    ],
    "sg:postcode":"89701",
    "sg:province":"NV",
    "sg:website":"www.carson-city.nv.us/Index.aspx...",
    "wof:name":"Mayor's Park",
    "wof:placetype":"venue"
},
  "geometry": {"coordinates":[-119.761224,39.133839],"type":"Point"}
}