{
  "type": "Feature",
  "properties": {
    "iso:country":"US",
    "sg:address":"4625 Mountaingate Dr",
    "sg:city":"Reno",
    "sg:classifiers":[
        {
            "category":"Banks & Credit Unions",
            "subcategory":"Investment Brokerage",
            "type":"Services"
        }
    ],
    "sg:phone":"+1 775 746 3940",
    "sg:postcode":"89519",
    "sg:province":"NV",
    "sg:tags":[
        "management"
    ],
    "wof:name":"Rice Family Investments",
    "wof:placetype":"venue"
},
  "geometry": {"coordinates":[-119.888606,39.501321],"type":"Point"}
}