{
  "type": "Feature",
  "properties": {
    "iso:country":"US",
    "sg:address":"2675 Windmill Pkwy",
    "sg:city":"Henderson",
    "sg:classifiers":[
        {
            "category":"Professional",
            "subcategory":"Management & Consulting",
            "type":"Services"
        }
    ],
    "sg:phone":"+1 702 270 2815",
    "sg:postcode":"89074",
    "sg:province":"NV",
    "sg:tags":[
        "business"
    ],
    "wof:name":"Minger Group",
    "wof:placetype":"venue"
},
  "geometry": {"coordinates":[-115.100965,36.042308],"type":"Point"}
}