{
  "type": "Feature",
  "properties": {
    "iso:country":"US",
    "sg:address":"518 Mountain City Hwy",
    "sg:city":"Elko",
    "sg:classifiers":[
        {
            "category":"Building & Trades",
            "subcategory":"Construction",
            "type":"Services"
        }
    ],
    "sg:phone":"+1 775 778 0303",
    "sg:postcode":"89801",
    "sg:province":"NV",
    "sg:tags":[
        "excavation",
        "reclamation",
        "contractor"
    ],
    "wof:name":"Walsh Reclamation Inc",
    "wof:placetype":"venue"
},
  "geometry": {"coordinates":[-115.771334,40.825385],"type":"Point"}
}