{
  "type": "Feature",
  "properties": {
    "iso:country":"US",
    "sg:address":"3855 S Valley View Blvd",
    "sg:city":"Las Vegas",
    "sg:classifiers":[
        {
            "category":"Shopping",
            "subcategory":"Clothing, Apparel, & Fashions",
            "type":"Retail Goods"
        }
    ],
    "sg:phone":"+1 702 222 0464",
    "sg:postcode":"89103",
    "sg:province":"NV",
    "sg:tags":[
        "clothing",
        "women's"
    ],
    "wof:name":"Miss Nikky Inc",
    "wof:placetype":"venue"
},
  "geometry": {"coordinates":[-115.19028900000001,36.121359],"type":"Point"}
}