{
  "type": "Feature",
  "properties": {
    "iso:country":"US",
    "sg:address":"572 Reactor Way",
    "sg:city":"Reno",
    "sg:classifiers":[
        {
            "category":"Manufacturing",
            "subcategory":"Food",
            "type":"Manufacturing & Wholesale Goods"
        }
    ],
    "sg:phone":"+1 775 856 3350",
    "sg:postcode":"89502",
    "sg:province":"NV",
    "sg:tags":[
        "product",
        "manufacturer"
    ],
    "sg:website":"www.mrs-aulds.com",
    "wof:name":"Mrs Auld's Gourmet Foods Inc",
    "wof:placetype":"venue"
},
  "geometry": {"coordinates":[-119.760982,39.503034],"type":"Point"}
}