{
  "type": "Feature",
  "properties": {
    "iso:country":"US",
    "sg:address":"7881 W Charleston Blvd",
    "sg:city":"Las Vegas",
    "sg:classifiers":[
        {
            "category":"Professional",
            "subcategory":"Business Services",
            "type":"Services"
        }
    ],
    "sg:phone":"+1 702 951 5333",
    "sg:postcode":"89117",
    "sg:province":"NV",
    "wof:name":"Bill Legere Commercial RE",
    "wof:placetype":"venue"
},
  "geometry": {"coordinates":[-115.2618,36.159019],"type":"Point"}
}