{
  "type": "Feature",
  "properties": {
    "iso:country":"US",
    "sg:address":"10529 Haileville Dr",
    "sg:city":"Las Vegas",
    "sg:classifiers":[
        {
            "category":"Manufacturing",
            "subcategory":"Chemicals & Compounds",
            "type":"Manufacturing & Wholesale Goods"
        }
    ],
    "sg:phone":"+1 702 360 5450",
    "sg:postcode":"89129",
    "sg:province":"NV",
    "sg:tags":[
        "mfg"
    ],
    "wof:name":"Turtle Mountain Supply Company",
    "wof:placetype":"venue"
},
  "geometry": {"coordinates":[-115.32741,36.239975],"type":"Point"}
}