{
  "type": "Feature",
  "properties": {
    "iso:country":"US",
    "sg:address":"1734 Blanchard Dr",
    "sg:city":"Henderson",
    "sg:classifiers":[
        {
            "category":"Building & Trades",
            "subcategory":"Landscaping Services",
            "type":"Services"
        }
    ],
    "sg:phone":"+1 702 433 5296",
    "sg:postcode":"89074",
    "sg:province":"NV",
    "sg:tags":[
        "landscape",
        "contractor"
    ],
    "wof:name":"A Ledstrom Brothers Landscpg",
    "wof:placetype":"venue"
},
  "geometry": {"coordinates":[-115.062462,36.035977],"type":"Point"}
}