{
  "type": "Feature",
  "properties": {
    "iso:country":"US",
    "sg:address":"1326 Fraya Dr",
    "sg:city":"Las Vegas",
    "sg:classifiers":[
        {
            "category":"Building & Trades",
            "subcategory":"Construction",
            "type":"Services"
        }
    ],
    "sg:phone":"+1 702 262 6080",
    "sg:postcode":"89119",
    "sg:province":"NV",
    "sg:tags":[
        "house"
    ],
    "wof:name":"Pinia Shy",
    "wof:placetype":"venue"
},
  "geometry": {"coordinates":[-115.135796,36.089243],"type":"Point"}
}