{
  "type": "Feature",
  "properties": {
    "iso:country":"US",
    "sg:address":"350 S Center St",
    "sg:city":"Reno",
    "sg:classifiers":[
        {
            "category":"Real Estate",
            "subcategory":"Real Estate Operator",
            "type":"Services"
        }
    ],
    "sg:phone":"+1 775 333 1181",
    "sg:postcode":"89501",
    "sg:province":"NV",
    "sg:tags":[
        "suite",
        "executive"
    ],
    "wof:name":"Worldwide Capital Managmeent",
    "wof:placetype":"venue"
},
  "geometry": {"coordinates":[-119.809924,39.522574],"type":"Point"}
}