{
  "type": "Feature",
  "properties": {
    "iso:country":"US",
    "sg:address":"4850 S Valley View Blvd",
    "sg:city":"Las Vegas",
    "sg:classifiers":[
        {
            "category":"Freight",
            "type":"Transportation"
        }
    ],
    "sg:phone":"+1 702 736 7663",
    "sg:postcode":"89103",
    "sg:province":"NV",
    "sg:tags":[
        "commercial",
        "storage"
    ],
    "wof:name":"A Low Cost Self Storage",
    "wof:placetype":"venue"
},
  "geometry": {"coordinates":[-115.18976499999999,36.103678],"type":"Point"}
}