{
  "type": "Feature",
  "properties": {
    "iso:country":"US",
    "sg:address":"3948 Pamplona St",
    "sg:city":"Las Vegas",
    "sg:classifiers":[
        {
            "category":"Retail",
            "subcategory":"Animal Services",
            "type":"Services"
        }
    ],
    "sg:phone":"+1 702 434 6590",
    "sg:postcode":"89103",
    "sg:province":"NV",
    "wof:name":"Civilized Dog",
    "wof:placetype":"venue"
},
  "geometry": {"coordinates":[-115.23922,36.116802],"type":"Point"}
}