{
  "type": "Feature",
  "properties": {
    "iso:country":"US",
    "sg:address":"877 Scarlet Ave",
    "sg:city":"Henderson",
    "sg:classifiers":[
        {
            "category":"Building & Trades",
            "subcategory":"Construction",
            "type":"Services"
        }
    ],
    "sg:phone":"+1 702 558 5472",
    "sg:postcode":"89002",
    "sg:province":"NV",
    "sg:tags":[
        "carport"
    ],
    "wof:name":"Advantage Awning Co",
    "wof:placetype":"venue"
},
  "geometry": {"coordinates":[-114.962342,36.0047],"type":"Point"}
}