{
  "type": "Feature",
  "properties": {
    "iso:country":"US",
    "sg:address":"4870 Carson Ln",
    "sg:city":"Reno",
    "sg:classifiers":[
        {
            "category":"Mining & Drilling",
            "type":"Manufacturing & Wholesale Goods"
        }
    ],
    "sg:phone":"+1 775 348 2079",
    "sg:postcode":"89506",
    "sg:province":"NV",
    "sg:tags":[
        "company"
    ],
    "wof:name":"Andresen Exploration Drilling",
    "wof:placetype":"venue"
},
  "geometry": {"coordinates":[-119.821444,39.572336],"type":"Point"}
}