{
  "type": "Feature",
  "properties": {
    "iso:country":"US",
    "sg:address":"3301 Spring Mountain Rd",
    "sg:city":"Las Vegas",
    "sg:classifiers":[
        {
            "category":"Wholesale",
            "subcategory":"Apparel",
            "type":"Manufacturing & Wholesale Goods"
        }
    ],
    "sg:phone":"+1 702 871 9077",
    "sg:postcode":"89102",
    "sg:province":"NV",
    "sg:tags":[
        "clothing"
    ],
    "wof:name":"Kristen & Friends",
    "wof:placetype":"venue"
},
  "geometry": {"coordinates":[-115.184457,36.126243],"type":"Point"}
}