{
  "type": "Feature",
  "properties": {
    "iso:country":"US",
    "sg:address":"2675 E Flamingo Rd Ste 3",
    "sg:city":"Las Vegas",
    "sg:classifiers":[
        {
            "category":"Health Services",
            "subcategory":"Dentist",
            "type":"Services"
        }
    ],
    "sg:phone":"+1 702 731 2757",
    "sg:postcode":"89121",
    "sg:province":"NV",
    "wof:name":"Oehler Daniel J DMD",
    "wof:placetype":"venue"
},
  "geometry": {"coordinates":[-115.113468,36.114774],"type":"Point"}
}