{
  "type": "Feature",
  "properties": {
    "iso:country":"US",
    "sg:address":"3395 S Jones Blvd",
    "sg:city":"Las Vegas",
    "sg:classifiers":[
        {
            "category":"Retail",
            "subcategory":"Animal Services",
            "type":"Services"
        }
    ],
    "sg:phone":"+1 702 321 7197",
    "sg:postcode":"89146",
    "sg:province":"NV",
    "sg:tags":[
        "pet"
    ],
    "wof:name":"Walks & Wags Pet Sitting",
    "wof:placetype":"venue"
},
  "geometry": {"coordinates":[-115.225004,36.12719],"type":"Point"}
}