{
  "type": "Feature",
  "properties": {
    "iso:country":"US",
    "sg:address":"105 Mount Rose St",
    "sg:city":"Reno",
    "sg:classifiers":[
        {
            "category":"Retail",
            "subcategory":"Auto Repair",
            "type":"Services"
        }
    ],
    "sg:phone":"+1 775 846 1788",
    "sg:postcode":"89509",
    "sg:province":"NV",
    "sg:tags":[
        "body",
        "automobile",
        "painting",
        "repairing"
    ],
    "wof:name":"Life's Touch Therapeutic Body Works",
    "wof:placetype":"venue"
},
  "geometry": {"coordinates":[-119.806875,39.509697],"type":"Point"}
}