{
  "type": "Feature",
  "properties": {
    "iso:country":"US",
    "sg:address":"3420 Rosalinda Dr",
    "sg:city":"Reno",
    "sg:classifiers":[
        {
            "category":"Wholesale",
            "subcategory":"Durable Goods & Equipment",
            "type":"Manufacturing & Wholesale Goods"
        }
    ],
    "sg:phone":"+1 775 746 8798",
    "sg:postcode":"89503",
    "sg:province":"NV",
    "sg:tags":[
        "importer"
    ],
    "sg:website":"www.sunspan.com",
    "wof:name":"Sunspan Corp",
    "wof:placetype":"venue"
},
  "geometry": {"coordinates":[-119.855726,39.543845],"type":"Point"}
}