{
  "type": "Feature",
  "properties": {
    "iso:country":"US",
    "sg:address":"101 S Rainbow Boulevard",
    "sg:city":"Las Vegas",
    "sg:classifiers":[
        {
            "category":"Banks & Credit Unions",
            "subcategory":"Financial Services",
            "type":"Services"
        }
    ],
    "sg:phone":"+1 702 313 2001",
    "sg:postcode":"89145",
    "sg:province":"NV",
    "sg:tags":[
        "broker",
        "mortgage"
    ],
    "wof:name":"Allied Home Mortgage Capital Corporation",
    "wof:placetype":"venue"
},
  "geometry": {"coordinates":[-115.24423400000001,36.173786],"type":"Point"}
}