{
  "type": "Feature",
  "properties": {
    "iso:country":"US",
    "sg:address":"6451 Brandywine Way",
    "sg:city":"Las Vegas",
    "sg:classifiers":[
        {
            "category":"Education",
            "subcategory":"School",
            "type":"Public Place"
        }
    ],
    "sg:phone":"+1 702 799 4233",
    "sg:postcode":"89107",
    "sg:province":"NV",
    "sg:tags":[
        "high",
        "middle",
        "elementary"
    ],
    "wof:name":"Schools Clark County Public",
    "wof:placetype":"venue"
},
  "geometry": {"coordinates":[-115.235533,36.164892],"type":"Point"}
}