{
  "type": "Feature",
  "properties": {
    "iso:country":"US",
    "sg:address":"216 N Arlington Ave",
    "sg:city":"Reno",
    "sg:classifiers":[
        {
            "category":"Personal",
            "subcategory":"Beauty Salon",
            "type":"Services"
        }
    ],
    "sg:phone":"+1 775 324 2255",
    "sg:postcode":"89501",
    "sg:province":"NV",
    "wof:name":"Hair Jazz & Nail Co",
    "wof:placetype":"venue"
},
  "geometry": {"coordinates":[-119.817297,39.526657],"type":"Point"}
}