{
  "type": "Feature",
  "properties": {
    "iso:country":"US",
    "sg:address":"98 E Lake Mead Pkwy Ste 104",
    "sg:city":"Henderson",
    "sg:classifiers":[
        {
            "category":"Health Services",
            "subcategory":"Optometrist",
            "type":"Services"
        }
    ],
    "sg:phone":"+1 702 240 2010",
    "sg:postcode":"89015",
    "sg:province":"NV",
    "wof:name":"Avista Eye Center",
    "wof:placetype":"venue"
},
  "geometry": {"coordinates":[-114.983299,36.038896],"type":"Point"}
}