{
  "type": "Feature",
  "properties": {
    "iso:country":"US",
    "sg:address":"455 E Silverado Ranch Blvd",
    "sg:city":"Las Vegas",
    "sg:classifiers":[
        {
            "category":"Restaurant",
            "type":"Food & Drink"
        }
    ],
    "sg:phone":"+1 702 396 9946",
    "sg:postcode":"89183",
    "sg:province":"NV",
    "sg:tags":[
        "eating"
    ],
    "sg:website":"www.jackinthebox.com",
    "wof:name":"Jack In The Box",
    "wof:placetype":"venue"
},
  "geometry": {"coordinates":[-115.14890800000001,36.013239],"type":"Point"}
}