{
  "type": "Feature",
  "properties": {
    "iso:country":"US",
    "sg:address":"3748 Lakeside Dr",
    "sg:city":"Reno",
    "sg:classifiers":[
        {
            "category":"Banks & Credit Unions",
            "subcategory":"Bank",
            "type":"Services"
        }
    ],
    "sg:phone":"+1 775 826 1700",
    "sg:postcode":"89509",
    "sg:province":"NV",
    "sg:tags":[
        "loan",
        "real estate"
    ],
    "wof:name":"National City Mortgage",
    "wof:placetype":"venue"
},
  "geometry": {"coordinates":[-119.807908,39.489819],"type":"Point"}
}