{
  "type": "Feature",
  "properties": {
    "iso:country":"US",
    "sg:address":"2050 Brierley Way",
    "sg:city":"Sparks",
    "sg:classifiers":[
        {
            "category":"Wholesale",
            "subcategory":"Electrical",
            "type":"Manufacturing & Wholesale Goods"
        }
    ],
    "sg:phone":"+1 775 331 4151",
    "sg:postcode":"89434",
    "sg:province":"NV",
    "sg:tags":[
        "generator"
    ],
    "wof:name":"Nevada Energy Systems Inc",
    "wof:placetype":"venue"
},
  "geometry": {"coordinates":[-119.701883,39.528131],"type":"Point"}
}