{
  "type": "Feature",
  "properties": {
    "iso:country":"US",
    "sg:address":"1539 US Hwy 395 N",
    "sg:city":"Gardnerville",
    "sg:classifiers":[
        {
            "category":"Autos & Motor Vehicles",
            "subcategory":"Motorcycle Sales",
            "type":"Retail Goods"
        }
    ],
    "sg:phone":"+1 775 782 2110",
    "sg:postcode":"89423",
    "sg:province":"NV",
    "sg:tags":[
        "scooter"
    ],
    "wof:name":"Bad Bonz Motor Sports Co",
    "wof:placetype":"venue"
},
  "geometry": {"coordinates":[-119.761956,38.952624],"type":"Point"}
}