{
  "type": "Feature",
  "properties": {
    "iso:country":"US",
    "sg:address":"2211 W Williams Ave",
    "sg:city":"Fallon",
    "sg:classifiers":[
        {
            "category":"Banks & Credit Unions",
            "subcategory":"Bank",
            "type":"Services"
        }
    ],
    "sg:phone":"+1 775 423 6541",
    "sg:postcode":"89406",
    "sg:province":"NV",
    "wof:name":"Wells Fargo Bank",
    "wof:placetype":"venue"
},
  "geometry": {"coordinates":[-118.80274,39.476691],"type":"Point"}
}