{
  "type": "Feature",
  "properties": {
    "iso:country":"US",
    "sg:address":"2253 Oddie Blvd",
    "sg:city":"Sparks",
    "sg:classifiers":[
        {
            "category":"Fast Food",
            "type":"Food & Drink"
        },
        {
            "category":"Restaurant",
            "type":"Food & Drink"
        },
        {
            "category":"Retail",
            "subcategory":"Event Space",
            "type":"Services"
        }
    ],
    "sg:phone":"+1 775 358 8228",
    "sg:postcode":"89431",
    "sg:province":"NV",
    "sg:tags":[
        "chinese",
        "facility",
        "hall",
        "take",
        "reception",
        "banquet",
        "pan",
        "asian"
    ],
    "wof:name":"Egg Roll King Two",
    "wof:placetype":"venue"
},
  "geometry": {"coordinates":[-119.77493,39.54549],"type":"Point"}
}