{
  "type": "Feature",
  "properties": {
    "iso:country":"US",
    "sg:address":"10880 S Eastern Ave",
    "sg:city":"Henderson",
    "sg:classifiers":[
        {
            "category":"Shopping",
            "type":"Retail Goods"
        }
    ],
    "sg:phone":"+1 702 897 0096",
    "sg:postcode":"89052",
    "sg:province":"NV",
    "sg:tags":[
        "picture",
        "frame"
    ],
    "wof:name":"Fastframe",
    "wof:placetype":"venue"
},
  "geometry": {"coordinates":[-115.10107000000001,35.995922],"type":"Point"}
}