{
  "type": "Feature",
  "properties": {
    "iso:country":"US",
    "sg:address":"1700 W Horizon Ridge Pkwy",
    "sg:city":"Henderson",
    "sg:classifiers":[
        {
            "category":"Professional",
            "subcategory":"Advertising",
            "type":"Services"
        }
    ],
    "sg:phone":"+1 702 837 8996",
    "sg:postcode":"89012",
    "sg:province":"NV",
    "sg:tags":[
        "counselor"
    ],
    "wof:name":"Imagine Marketing",
    "wof:placetype":"venue"
},
  "geometry": {"coordinates":[-115.061614,36.012046],"type":"Point"}
}