{
  "type": "Feature",
  "properties": {
    "iso:country":"US",
    "sg:address":"349 W 4th St",
    "sg:city":"Winnemucca",
    "sg:classifiers":[
        {
            "category":"Real Estate",
            "subcategory":"Real Estate Agent",
            "type":"Services"
        }
    ],
    "sg:phone":"+1 775 623 1134",
    "sg:postcode":"89445",
    "sg:province":"NV",
    "wof:name":"Century 21",
    "wof:placetype":"venue"
},
  "geometry": {"coordinates":[-117.736963,40.970296],"type":"Point"}
}