{
  "type": "Feature",
  "properties": {
    "iso:country":"US",
    "sg:address":"384 Rushing Creek Ct",
    "sg:city":"Henderson",
    "sg:classifiers":[
        {
            "category":"Real Estate",
            "subcategory":"Real Estate Agent",
            "type":"Services"
        }
    ],
    "sg:phone":"+1 702 435 6799",
    "sg:postcode":"89014",
    "sg:province":"NV",
    "wof:name":"Value Plus Realty Consultants",
    "wof:placetype":"venue"
},
  "geometry": {"coordinates":[-115.072701,36.054758],"type":"Point"}
}