{
  "type": "Feature",
  "properties": {
    "iso:country":"US",
    "sg:address":"1495 Ridgeview Dr",
    "sg:city":"Reno",
    "sg:classifiers":[
        {
            "category":"Professional",
            "subcategory":"Accounting & Tax Preparation",
            "type":"Services"
        }
    ],
    "sg:phone":"+1 775 824 3777",
    "sg:postcode":"89519",
    "sg:province":"NV",
    "sg:tags":[
        "payroll"
    ],
    "wof:name":"Maritech",
    "wof:placetype":"venue"
},
  "geometry": {"coordinates":[-119.81050999999999,39.471205],"type":"Point"}
}