{
  "type": "Feature",
  "properties": {
    "iso:country":"US",
    "sg:address":"4770 Convair Dr",
    "sg:city":"Carson City",
    "sg:classifiers":[
        {
            "category":"Wholesale",
            "subcategory":"Construction Materials",
            "type":"Manufacturing & Wholesale Goods"
        },
        {
            "category":"Manufacturing",
            "subcategory":"Wood Products",
            "type":"Manufacturing & Wholesale Goods"
        }
    ],
    "sg:phone":"+1 775 841 3390",
    "sg:postcode":"89706",
    "sg:province":"NV",
    "sg:tags":[
        "pallet",
        "skid",
        "mfg"
    ],
    "wof:name":"Atlas Pallet Co",
    "wof:placetype":"venue"
},
  "geometry": {"coordinates":[-119.738047,39.201122],"type":"Point"}
}