{
  "type": "Feature",
  "properties": {
    "iso:country":"US",
    "sg:address":"404 N McCarran Blvd",
    "sg:city":"Sparks",
    "sg:classifiers":[
        {
            "category":"Bars & Pubs",
            "type":"Food & Drink"
        }
    ],
    "sg:phone":"+1 775 355 8391",
    "sg:postcode":"89431",
    "sg:province":"NV",
    "sg:tags":[
        "lounge",
        "cocktail"
    ],
    "wof:name":"Outer Limits",
    "wof:placetype":"venue"
},
  "geometry": {"coordinates":[-119.734331,39.539045],"type":"Point"}
}