{
  "type": "Feature",
  "properties": {
    "iso:country":"US",
    "sg:address":"555 W Silver St",
    "sg:city":"Elko",
    "sg:classifiers":[
        {
            "category":"Real Estate",
            "subcategory":"Real Estate Operator",
            "type":"Services"
        }
    ],
    "sg:phone":"+1 775 738 4967",
    "sg:postcode":"89801",
    "sg:province":"NV",
    "sg:tags":[
        "building",
        "parks"
    ],
    "wof:name":"A & L Office Complex",
    "wof:placetype":"venue"
},
  "geometry": {"coordinates":[-115.771642,40.825209],"type":"Point"}
}