{
  "type": "Feature",
  "properties": {
    "iso:country":"US",
    "sg:address":"6103 Sundown Crest St",
    "sg:city":"Las Vegas",
    "sg:classifiers":[
        {
            "category":"Professional",
            "subcategory":"Business Services",
            "type":"Services"
        }
    ],
    "sg:phone":"+1 702 870 1006",
    "sg:postcode":"89113",
    "sg:province":"NV",
    "sg:tags":[
        "interior",
        "consultant",
        "design",
        "decorator"
    ],
    "wof:name":"G L Designs",
    "wof:placetype":"venue"
},
  "geometry": {"coordinates":[-115.253484,36.075441],"type":"Point"}
}