{
  "type": "Feature",
  "properties": {
    "iso:country":"US",
    "sg:address":"1229 W Owens Ave",
    "sg:city":"Las Vegas",
    "sg:classifiers":[
        {
            "category":"Organizations",
            "subcategory":"Religious Organization",
            "type":"Services"
        }
    ],
    "sg:phone":"+1 702 648 5665",
    "sg:postcode":"89106",
    "sg:province":"NV",
    "sg:tags":[
        "church"
    ],
    "wof:name":"New Bethany Family Worship",
    "wof:placetype":"venue"
},
  "geometry": {"coordinates":[-115.156762,36.188342],"type":"Point"}
}