{
  "type": "Feature",
  "properties": {
    "iso:country":"US",
    "sg:address":"195 N Edison Way",
    "sg:city":"Reno",
    "sg:classifiers":[
        {
            "category":"Building & Trades",
            "subcategory":"Cleaning & Sanitation",
            "type":"Services"
        }
    ],
    "sg:phone":"+1 775 856 1444",
    "sg:postcode":"89502",
    "sg:province":"NV",
    "sg:tags":[
        "janitor"
    ],
    "wof:name":"PHD Janitorial",
    "wof:placetype":"venue"
},
  "geometry": {"coordinates":[-119.752798,39.514336],"type":"Point"}
}