{
  "type": "Feature",
  "properties": {
    "iso:country":"US",
    "sg:address":"3932 E Wyoming Ave",
    "sg:city":"Las Vegas",
    "sg:classifiers":[
        {
            "category":"Shopping",
            "subcategory":"Jewelry",
            "type":"Retail Goods"
        }
    ],
    "sg:phone":"+1 702 399 4141",
    "sg:postcode":"89104",
    "sg:province":"NV",
    "sg:tags":[
        "jeweler"
    ],
    "wof:name":"Chucks Jewelry",
    "wof:placetype":"venue"
},
  "geometry": {"coordinates":[-115.088718,36.151913],"type":"Point"}
}