{
  "type": "Feature",
  "properties": {
    "iso:country":"US",
    "sg:address":"1650 Greg St",
    "sg:city":"Sparks",
    "sg:classifiers":[
        {
            "category":"Home & Garden",
            "subcategory":"Building Materials",
            "type":"Retail Goods"
        }
    ],
    "sg:phone":"+1 775 331 3110",
    "sg:postcode":"89431",
    "sg:province":"NV",
    "sg:tags":[
        "glass",
        "window",
        "plate"
    ],
    "wof:name":"Fast Glass Inc",
    "wof:placetype":"venue"
},
  "geometry": {"coordinates":[-119.768583,39.523535],"type":"Point"}
}