{
  "type": "Feature",
  "properties": {
    "iso:country":"US",
    "sg:address":"1560 N Eastern Ave",
    "sg:city":"Las Vegas",
    "sg:classifiers":[
        {
            "category":"Shopping",
            "subcategory":"Gifts & Souvenirs",
            "type":"Retail Goods"
        }
    ],
    "sg:phone":"+1 702 399 0700",
    "sg:postcode":"89101",
    "sg:province":"NV",
    "sg:tags":[
        "shop"
    ],
    "wof:name":"Elia's Home Decoration",
    "wof:placetype":"venue"
},
  "geometry": {"coordinates":[-115.116026,36.187383],"type":"Point"}
}