{
  "type": "Feature",
  "properties": {
    "iso:country":"US",
    "sg:address":"4600 W Tropicana Ave",
    "sg:city":"Las Vegas",
    "sg:classifiers":[
        {
            "category":"Autos & Motor Vehicles",
            "subcategory":"Automobile Sales",
            "type":"Retail Goods"
        }
    ],
    "sg:phone":"+1 702 566 5006",
    "sg:postcode":"89103",
    "sg:province":"NV",
    "sg:tags":[
        "classic"
    ],
    "wof:name":"Classic Auto Sales",
    "wof:placetype":"venue"
},
  "geometry": {"coordinates":[-115.206631,36.100887],"type":"Point"}
}