{
  "type": "Feature",
  "properties": {
    "iso:country":"US",
    "sg:address":"1420 S Rainbow Boulevard",
    "sg:city":"Las Vegas",
    "sg:classifiers":[
        {
            "category":"Professional",
            "subcategory":"Computer Services",
            "type":"Services"
        }
    ],
    "sg:phone":"+1 702 880 1201",
    "sg:postcode":"89146",
    "sg:province":"NV",
    "sg:tags":[
        "stereo",
        "installation"
    ],
    "wof:name":"Audio Express Home of the One Dollar Install",
    "wof:placetype":"venue"
},
  "geometry": {"coordinates":[-115.24344,36.155033],"type":"Point"}
}