{
  "type": "Feature",
  "properties": {
    "iso:country":"US",
    "sg:address":"300 W Saint Louis Ave",
    "sg:city":"Las Vegas",
    "sg:classifiers":[
        {
            "category":"Autos & Motor Vehicles",
            "subcategory":"Automobile Sales",
            "type":"Retail Goods"
        }
    ],
    "sg:phone":"+1 702 221 5555",
    "sg:postcode":"89102",
    "sg:province":"NV",
    "sg:tags":[
        "limo"
    ],
    "sg:website":"www.blslimo.com",
    "wof:name":"Bls Limousine Service of Las Vegas",
    "wof:placetype":"venue"
},
  "geometry": {"coordinates":[-115.161003,36.148499],"type":"Point"}
}