{
  "type": "Feature",
  "properties": {
    "iso:country":"US",
    "sg:address":"2881 S Valley View Blvd",
    "sg:city":"Las Vegas",
    "sg:classifiers":[
        {
            "category":"Professional",
            "subcategory":"Computer Services",
            "type":"Services"
        }
    ],
    "sg:phone":"+1 702 547 4638",
    "sg:postcode":"89102",
    "sg:province":"NV",
    "sg:tags":[
        "internet"
    ],
    "sg:website":"www.inetgateways.com",
    "wof:name":"INETGATEWAYS.COM",
    "wof:placetype":"venue"
},
  "geometry": {"coordinates":[-115.190599,36.1375],"type":"Point"}
}