{
  "type": "Feature",
  "properties": {
    "iso:country":"US",
    "sg:address":"3355 Las Vegas Boulevard S",
    "sg:city":"Las Vegas",
    "sg:classifiers":[
        {
            "category":"Shopping",
            "subcategory":"Optician",
            "type":"Retail Goods"
        }
    ],
    "sg:phone":"+1 702 733 2121",
    "sg:postcode":"89109",
    "sg:province":"NV",
    "sg:tags":[
        "eyewear"
    ],
    "sg:website":"loholdings.com/",
    "wof:name":"Dolce",
    "wof:placetype":"venue"
},
  "geometry": {"coordinates":[-115.171046,36.122457],"type":"Point"}
}