{
  "type": "Feature",
  "properties": {
    "iso:country":"US",
    "sg:address":"320 S Crestline Dr",
    "sg:city":"Las Vegas",
    "sg:classifiers":[
        {
            "category":"Social Services",
            "subcategory":"Child Care",
            "type":"Services"
        }
    ],
    "sg:phone":"+1 702 878 6022",
    "sg:postcode":"89107",
    "sg:province":"NV",
    "sg:tags":[
        "day"
    ],
    "wof:name":"Jones Day Care Center",
    "wof:placetype":"venue"
},
  "geometry": {"coordinates":[-115.232114,36.16874],"type":"Point"}
}