{
  "type": "Feature",
  "properties": {
    "iso:country":"US",
    "sg:address":"885 E Musser St",
    "sg:city":"Carson City",
    "sg:classifiers":[
        {
            "category":"Professional",
            "subcategory":"Lawyer & Legal Services",
            "type":"Services"
        },
        {
            "category":"Government",
            "subcategory":"Court House",
            "type":"Public Place"
        }
    ],
    "sg:phone":"+1 775 887 2098",
    "sg:postcode":"89701",
    "sg:province":"NV",
    "sg:tags":[
        "city",
        "counsel"
    ],
    "wof:name":"Carson City District Attorney",
    "wof:placetype":"venue"
},
  "geometry": {"coordinates":[-119.76073,39.164475],"type":"Point"}
}