{
  "type": "Feature",
  "properties": {
    "iso:country":"US",
    "sg:address":"815 S Main St",
    "sg:city":"Las Vegas",
    "sg:classifiers":[
        {
            "category":"Insurance",
            "subcategory":"Hazard Insurance",
            "type":"Services"
        }
    ],
    "sg:phone":"+1 702 384 9939",
    "sg:postcode":"89101",
    "sg:province":"NV",
    "sg:tags":[
        "bond"
    ],
    "wof:name":"Godfather's Bail Bonds",
    "wof:placetype":"venue"
},
  "geometry": {"coordinates":[-115.151798,36.162298],"type":"Point"}
}