{
  "type": "Feature",
  "properties": {
    "iso:country":"US",
    "sg:address":"2120 Jadeleaf Ct",
    "sg:city":"Las Vegas",
    "sg:classifiers":[
        {
            "category":"Professional",
            "subcategory":"Business Services",
            "type":"Services"
        }
    ],
    "sg:phone":"+1 702 838 3310",
    "sg:postcode":"89134",
    "sg:province":"NV",
    "wof:name":"Roth Enterprises Inc",
    "wof:placetype":"venue"
},
  "geometry": {"coordinates":[-115.299097,36.200183],"type":"Point"}
}