{
  "type": "Feature",
  "properties": {
    "iso:country":"US",
    "sg:address":"1140 E Desert Inn Road",
    "sg:city":"Las Vegas",
    "sg:classifiers":[
        {
            "category":"Banks & Credit Unions",
            "subcategory":"Bank",
            "type":"Services"
        },
        {
            "category":"Banks & Credit Unions",
            "subcategory":"Financial Services",
            "type":"Services"
        }
    ],
    "sg:phone":"+1 702 654 4780",
    "sg:postcode":"89109",
    "sg:province":"NV",
    "sg:tags":[
        "broker",
        "mortgage"
    ],
    "sg:website":"www.bankofamerica.com",
    "wof:name":"Bank of America",
    "wof:placetype":"venue"
},
  "geometry": {"coordinates":[-115.138823,36.129647],"type":"Point"}
}