{
  "type": "Feature",
  "properties": {
    "iso:country":"US",
    "sg:address":"240 E Horizon Dr",
    "sg:city":"Henderson",
    "sg:classifiers":[
        {
            "category":"Building & Trades",
            "subcategory":"Construction",
            "type":"Services"
        }
    ],
    "sg:phone":"+1 702 564 8484",
    "sg:postcode":"89015",
    "sg:province":"NV",
    "sg:website":"www.blanchardhoffman.com",
    "wof:name":"B & H Construction",
    "wof:placetype":"venue"
},
  "geometry": {"coordinates":[-114.984047,36.01262],"type":"Point"}
}