{
  "type": "Feature",
  "properties": {
    "iso:country":"US",
    "sg:address":"3320 Las Vegas Fwy",
    "sg:city":"North Las Vegas",
    "sg:classifiers":[
        {
            "category":"Wholesale",
            "subcategory":"Meat",
            "type":"Manufacturing & Wholesale Goods"
        }
    ],
    "sg:phone":"+1 702 399 1151",
    "sg:postcode":"89030",
    "sg:province":"NV",
    "wof:name":"LA Herradero Meat Market",
    "wof:placetype":"venue"
},
  "geometry": {"coordinates":[-115.121884,36.220054],"type":"Point"}
}