{
  "type": "Feature",
  "properties": {
    "iso:country":"US",
    "sg:address":"450 E 6th St",
    "sg:city":"Reno",
    "sg:classifiers":[
        {
            "category":"Building & Trades",
            "subcategory":"Electrical",
            "type":"Services"
        }
    ],
    "sg:phone":"+1 775 742 6544",
    "sg:postcode":"89512",
    "sg:province":"NV",
    "sg:tags":[
        "electrical",
        "contractor"
    ],
    "wof:name":"Deck Lightingcom",
    "wof:placetype":"venue"
},
  "geometry": {"coordinates":[-119.808384,39.53362],"type":"Point"}
}