{
  "type": "Feature",
  "properties": {
    "iso:country":"US",
    "sg:address":"1430 Greg St",
    "sg:city":"Sparks",
    "sg:classifiers":[
        {
            "category":"Manufacturing",
            "subcategory":"Tools & Machinery",
            "type":"Manufacturing & Wholesale Goods"
        }
    ],
    "sg:phone":"+1 775 355 3244",
    "sg:postcode":"89431",
    "sg:province":"NV",
    "sg:tags":[
        "machine",
        "shop"
    ],
    "wof:name":"Solid Solutions Design & Mach",
    "wof:placetype":"venue"
},
  "geometry": {"coordinates":[-119.763079,39.523484],"type":"Point"}
}