{
  "type": "Feature",
  "properties": {
    "iso:country":"US",
    "sg:address":"209 Plumb Ln",
    "sg:city":"Reno",
    "sg:classifiers":[
        {
            "category":"Professional",
            "type":"Services"
        }
    ],
    "sg:phone":"+1 775 322 5587",
    "sg:postcode":"89502",
    "sg:province":"NV",
    "wof:name":"Rebecca J Riersgard",
    "wof:placetype":"venue"
},
  "geometry": {"coordinates":[-119.802393,39.50578],"type":"Point"}
}