{
  "type": "Feature",
  "properties": {
    "iso:country":"US",
    "sg:address":"4785 Koval Ln",
    "sg:city":"Las Vegas",
    "sg:classifiers":[
        {
            "category":"Professional",
            "subcategory":"Management & Consulting",
            "type":"Services"
        }
    ],
    "sg:phone":"+1 702 736 1765",
    "sg:postcode":"89109",
    "sg:province":"NV",
    "sg:tags":[
        "construction"
    ],
    "wof:name":"Forest City Coml Cnstr Co",
    "wof:placetype":"venue"
},
  "geometry": {"coordinates":[-115.16394,36.102394],"type":"Point"}
}