{
  "type": "Feature",
  "properties": {
    "iso:country":"US",
    "sg:address":"3385 Norman Dr",
    "sg:city":"Reno",
    "sg:classifiers":[
        {
            "category":"Manufacturing",
            "subcategory":"Metals",
            "type":"Manufacturing & Wholesale Goods"
        }
    ],
    "sg:phone":"+1 775 322 9560",
    "sg:postcode":"89509",
    "sg:province":"NV",
    "sg:tags":[
        "development",
        "technology"
    ],
    "wof:name":"Mine Inc",
    "wof:placetype":"venue"
},
  "geometry": {"coordinates":[-119.841594,39.488216],"type":"Point"}
}