{
  "type": "Feature",
  "properties": {
    "iso:country":"US",
    "sg:address":"1721 N Decatur Boulevard",
    "sg:city":"Las Vegas",
    "sg:classifiers":[
        {
            "category":"Autos & Motor Vehicles",
            "subcategory":"Auto Supplies",
            "type":"Retail Goods"
        }
    ],
    "sg:phone":"+1 702 319 5263",
    "sg:postcode":"89108",
    "sg:province":"NV",
    "sg:tags":[
        "glass"
    ],
    "wof:name":"Auto Glass Centers",
    "wof:placetype":"venue"
},
  "geometry": {"coordinates":[-115.206369,36.189542],"type":"Point"}
}