{
  "type": "Feature",
  "properties": {
    "iso:country":"US",
    "sg:address":"1100 Kietzke Ln",
    "sg:city":"Reno",
    "sg:classifiers":[
        {
            "category":"Insurance",
            "subcategory":"Insurance Agent",
            "type":"Services"
        }
    ],
    "sg:phone":"+1 775 324 3553",
    "sg:postcode":"89502",
    "sg:province":"NV",
    "sg:tags":[
        "adjuster"
    ],
    "wof:name":"Cunningham Claims Services",
    "wof:placetype":"venue"
},
  "geometry": {"coordinates":[-119.789146,39.515491],"type":"Point"}
}