{
  "type": "Feature",
  "properties": {
    "iso:country":"US",
    "sg:address":"5415 W Harmon Ave",
    "sg:city":"Las Vegas",
    "sg:classifiers":[
        {
            "category":"Cinema",
            "subcategory":"Movie Rental",
            "type":"Entertainment"
        }
    ],
    "sg:phone":"+1 702 220 4563",
    "sg:postcode":"89103",
    "sg:province":"NV",
    "sg:tags":[
        "video",
        "tape"
    ],
    "wof:name":"Foto Video Estudio",
    "wof:placetype":"venue"
},
  "geometry": {"coordinates":[-115.21511099999999,36.107671],"type":"Point"}
}