{
  "type": "Feature",
  "properties": {
    "iso:country":"US",
    "sg:address":"310 Oakmont Dr",
    "sg:city":"Spring Creek",
    "sg:classifiers":[
        {
            "category":"Banks & Credit Unions",
            "subcategory":"Financial Services",
            "type":"Services"
        }
    ],
    "sg:phone":"+1 775 753 5015",
    "sg:postcode":"89815",
    "sg:province":"NV",
    "sg:tags":[
        "investor"
    ],
    "wof:name":"Gerald Lynch",
    "wof:placetype":"venue"
},
  "geometry": {"coordinates":[-115.592357,40.70713],"type":"Point"}
}