{
  "type": "Feature",
  "properties": {
    "iso:country":"US",
    "sg:address":"963 Topsy Lane",
    "sg:city":"Carson City",
    "sg:classifiers":[
        {
            "category":"Restaurant",
            "type":"Food & Drink"
        }
    ],
    "sg:phone":"+1 775 267 1400",
    "sg:postcode":"89705",
    "sg:province":"NV",
    "sg:tags":[
        "mexican"
    ],
    "wof:name":"La Salsa Grill",
    "wof:placetype":"venue"
},
  "geometry": {"coordinates":[-119.775438,39.108639],"type":"Point"}
}