{
  "type": "Feature",
  "properties": {
    "iso:country":"US",
    "sg:address":"4095 N Carson St",
    "sg:city":"Carson City",
    "sg:classifiers":[
        {
            "category":"Health Services",
            "subcategory":"Doctor",
            "type":"Services"
        }
    ],
    "sg:phone":"+1 775 885 9911",
    "sg:postcode":"89706",
    "sg:province":"NV",
    "wof:name":"Matuszewski T K MD",
    "wof:placetype":"venue"
},
  "geometry": {"coordinates":[-119.776001,39.196098],"type":"Point"}
}