{
  "type": "Feature",
  "properties": {
    "iso:country":"US",
    "sg:address":"5486 Boulder Hwy",
    "sg:city":"Las Vegas",
    "sg:classifiers":[
        {
            "category":"Restaurant",
            "type":"Food & Drink"
        }
    ],
    "sg:menulink":"http://www.allmenus.com/nv/las-vegas/64809-papa-johns-pizza/menu/",
    "sg:phone":"+1 702 386 7272",
    "sg:postcode":"89122",
    "sg:province":"NV",
    "sg:tags":[
        "american",
        "pizza"
    ],
    "wof:name":"Papa John's Pizza",
    "wof:placetype":"venue"
},
  "geometry": {"coordinates":[-115.053217,36.102686],"type":"Point"}
}