{
  "type": "Feature",
  "properties": {
    "iso:country":"US",
    "sg:address":"3975 S Durango Drive Suite 104",
    "sg:city":"Las Vegas",
    "sg:classifiers":[
        {
            "category":"Retail",
            "subcategory":"Funeral Services",
            "type":"Services"
        }
    ],
    "sg:phone":"+1 702 485 6500",
    "sg:postcode":"89147",
    "sg:province":"NV",
    "sg:tags":[
        "cemetery"
    ],
    "sg:website":"www.kraftsussman.com",
    "wof:name":"Kraft-Sussman Funeral Services",
    "wof:placetype":"venue"
},
  "geometry": {"coordinates":[-115.279649,36.118133],"type":"Point"}
}