{
  "type": "Feature",
  "properties": {
    "iso:country":"US",
    "sg:address":"5870 S Eastern Ave",
    "sg:city":"Las Vegas",
    "sg:classifiers":[
        {
            "category":"Professional",
            "subcategory":"Advertising",
            "type":"Services"
        }
    ],
    "sg:phone":"+1 702 000 1111",
    "sg:postcode":"89119",
    "sg:province":"NV",
    "sg:tags":[
        "mailing",
        "shipping"
    ],
    "wof:name":"Fed Ex World Service Ctr",
    "wof:placetype":"venue"
},
  "geometry": {"coordinates":[-115.118717,36.083774],"type":"Point"}
}