{
  "type": "Feature",
  "properties": {
    "iso:country":"US",
    "sg:address":"25 W Army St",
    "sg:city":"Henderson",
    "sg:classifiers":[
        {
            "category":"Shopping",
            "subcategory":"Tobacco",
            "type":"Retail Goods"
        }
    ],
    "sg:phone":"+1 702 568 8988",
    "sg:postcode":"89015",
    "sg:province":"NV",
    "sg:tags":[
        "shop"
    ],
    "wof:name":"Smoke Shop",
    "wof:placetype":"venue"
},
  "geometry": {"coordinates":[-114.98400100000001,36.032299],"type":"Point"}
}