{
  "type": "Feature",
  "properties": {
    "iso:country":"US",
    "sg:address":"4900 Losee Rd",
    "sg:city":"North Las Vegas",
    "sg:classifiers":[
        {
            "category":"Freight",
            "type":"Transportation"
        }
    ],
    "sg:phone":"+1 702 643 1133",
    "sg:postcode":"89030",
    "sg:province":"NV",
    "sg:tags":[
        "broker"
    ],
    "wof:name":"N Y K Logistics (eta) Inc",
    "wof:placetype":"venue"
},
  "geometry": {"coordinates":[-115.116969,36.250642],"type":"Point"}
}