{
  "type": "Feature",
  "properties": {
    "iso:country":"US",
    "sg:address":"2815 W Ford Ave",
    "sg:city":"Las Vegas",
    "sg:classifiers":[
        {
            "category":"Personal",
            "type":"Services"
        }
    ],
    "sg:phone":"+1 702 400 3436",
    "sg:postcode":"89123",
    "sg:province":"NV",
    "wof:name":"Handyman Green Mtc",
    "wof:placetype":"venue"
},
  "geometry": {"coordinates":[-115.177336,36.031806],"type":"Point"}
}