{
  "type": "Feature",
  "properties": {
    "iso:country":"US",
    "sg:address":"507 N Carson St",
    "sg:city":"Carson City",
    "sg:classifiers":[
        {
            "category":"Recreation",
            "subcategory":"Arcade",
            "type":"Entertainment"
        }
    ],
    "sg:phone":"+1 775 882 1626",
    "sg:postcode":"89701",
    "sg:province":"NV",
    "sg:tags":[
        "casino",
        "restaurant"
    ],
    "wof:name":"Carson City Nugget",
    "wof:placetype":"venue"
},
  "geometry": {"coordinates":[-119.766998,39.166698],"type":"Point"}
}