{
  "type": "Feature",
  "properties": {
    "iso:country":"US",
    "sg:address":"2575 S Cimarron Rd",
    "sg:city":"Las Vegas",
    "sg:classifiers":[
        {
            "category":"Professional",
            "subcategory":"Accounting & Tax Preparation",
            "type":"Services"
        }
    ],
    "sg:phone":"+1 702 562 0314",
    "sg:postcode":"89117",
    "sg:province":"NV",
    "sg:tags":[
        "return",
        "filing"
    ],
    "wof:name":"Tax Check USA",
    "wof:placetype":"venue"
},
  "geometry": {"coordinates":[-115.270047,36.141797],"type":"Point"}
}