{
  "type": "Feature",
  "properties": {
    "iso:country":"US",
    "sg:address":"1249 Baring Blvd",
    "sg:city":"Sparks",
    "sg:classifiers":[
        {
            "category":"Professional",
            "subcategory":"Business Services",
            "type":"Services"
        }
    ],
    "sg:phone":"+1 775 358 2500",
    "sg:postcode":"89434",
    "sg:province":"NV",
    "sg:tags":[
        "water",
        "treatment"
    ],
    "wof:name":"Water Mart",
    "wof:placetype":"venue"
},
  "geometry": {"coordinates":[-119.719623,39.556288],"type":"Point"}
}