{
  "type": "Feature",
  "properties": {
    "iso:country":"US",
    "sg:address":"3944 Dream St",
    "sg:city":"Las Vegas",
    "sg:classifiers":[
        {
            "category":"Professional",
            "subcategory":"Computer Services",
            "type":"Services"
        }
    ],
    "sg:phone":"+1 702 233 8188",
    "sg:postcode":"89108",
    "sg:province":"NV",
    "sg:tags":[
        "prepackaged",
        "software",
        "custom"
    ],
    "wof:name":"McFerrins Thinktank Inc",
    "wof:placetype":"venue"
},
  "geometry": {"coordinates":[-115.238948,36.232268],"type":"Point"}
}