{
  "type": "Feature",
  "properties": {
    "iso:country":"US",
    "sg:address":"4062 Paramount St",
    "sg:city":"Las Vegas",
    "sg:classifiers":[
        {
            "category":"Freight",
            "type":"Transportation"
        }
    ],
    "sg:phone":"+1 702 644 4932",
    "sg:postcode":"89115",
    "sg:province":"NV",
    "sg:tags":[
        "trucking"
    ],
    "wof:name":"Jose L Espinosa Delivery",
    "wof:placetype":"venue"
},
  "geometry": {"coordinates":[-115.0729,36.235168],"type":"Point"}
}