{
  "type": "Feature",
  "properties": {
    "iso:country":"US",
    "sg:address":"200 Evans Ave",
    "sg:city":"Reno",
    "sg:classifiers":[
        {
            "category":"Government",
            "subcategory":"Fire Station",
            "type":"Public Place"
        }
    ],
    "sg:phone":"+1 775 334 2300",
    "sg:postcode":"89501",
    "sg:province":"NV",
    "sg:tags":[
        "department"
    ],
    "sg:website":"www.cityofreno.com",
    "wof:name":"Reno Fire Dept",
    "wof:placetype":"venue"
},
  "geometry": {"coordinates":[-119.809617,39.528512],"type":"Point"}
}