{
  "type": "Feature",
  "properties": {
    "iso:country":"US",
    "sg:address":"8275 S Eastern Ave",
    "sg:city":"Las Vegas",
    "sg:classifiers":[
        {
            "category":"Real Estate",
            "subcategory":"Real Estate Services",
            "type":"Services"
        }
    ],
    "sg:phone":"+1 702 990 8404",
    "sg:postcode":"89123",
    "sg:province":"NV",
    "sg:tags":[
        "management",
        "property"
    ],
    "wof:name":"Wilcox Development",
    "wof:placetype":"venue"
},
  "geometry": {"coordinates":[-115.117996,36.039101],"type":"Point"}
}