{
  "type": "Feature",
  "properties": {
    "iso:country":"US",
    "sg:address":"7950 W Tropical Pkwy",
    "sg:city":"Las Vegas",
    "sg:classifiers":[
        {
            "category":"Shopping",
            "subcategory":"Shoes",
            "type":"Retail Goods"
        }
    ],
    "sg:phone":"+1 702 645 1482",
    "sg:postcode":"89149",
    "sg:province":"NV",
    "sg:tags":[
        "store"
    ],
    "wof:name":"Payless Shoes",
    "wof:placetype":"venue"
},
  "geometry": {"coordinates":[-115.268997,36.270401],"type":"Point"}
}