{
  "type": "Feature",
  "properties": {
    "iso:country":"US",
    "sg:address":"1651 N Virginia St",
    "sg:city":"Reno",
    "sg:classifiers":[
        {
            "category":"Travel",
            "subcategory":"Hotels & Motels",
            "type":"Entertainment"
        }
    ],
    "sg:phone":"+1 775 329 3464",
    "sg:postcode":"89503",
    "sg:province":"NV",
    "sg:website":"http://www.super8.com",
    "wof:name":"Super 8 Motel",
    "wof:placetype":"venue"
},
  "geometry": {"coordinates":[-119.82102,39.547556],"type":"Point"}
}