{
  "type": "Feature",
  "properties": {
    "iso:country":"US",
    "sg:address":"510 Plumb Ln",
    "sg:city":"Reno",
    "sg:classifiers":[
        {
            "category":"Professional",
            "subcategory":"Business Services",
            "type":"Services"
        }
    ],
    "sg:phone":"+1 775 829 0333",
    "sg:postcode":"89502",
    "sg:province":"NV",
    "sg:tags":[
        "real estate"
    ],
    "wof:name":"Susan L Matteoni",
    "wof:placetype":"venue"
},
  "geometry": {"coordinates":[-119.793854,39.505757],"type":"Point"}
}