{
  "type": "Feature",
  "properties": {
    "iso:country":"US",
    "sg:address":"260 N Gibson Rd.",
    "sg:city":"Henderson",
    "sg:classifiers":[
        {
            "category":"Autos & Motor Vehicles",
            "subcategory":"Automobile Sales",
            "type":"Retail Goods"
        }
    ],
    "sg:phone":"+1 800 716 6136",
    "sg:postcode":"89014",
    "sg:province":"NV",
    "sg:tags":[
        "car"
    ],
    "sg:website":"www.courtesyimports.com",
    "wof:name":"Courtesy Imports",
    "wof:placetype":"venue"
},
  "geometry": {"coordinates":[-115.02811,36.047173],"type":"Point"}
}