{
  "type": "Feature",
  "properties": {
    "iso:country":"US",
    "sg:address":"2915 Evening Rock St",
    "sg:city":"Las Vegas",
    "sg:classifiers":[
        {
            "category":"Professional",
            "subcategory":"Business Services",
            "type":"Services"
        }
    ],
    "sg:phone":"+1 702 240 3246",
    "sg:postcode":"89135",
    "sg:province":"NV",
    "sg:tags":[
        "appraiser"
    ],
    "wof:name":"James & Assoc",
    "wof:placetype":"venue"
},
  "geometry": {"coordinates":[-115.345399,36.139792],"type":"Point"}
}