{
  "type": "Feature",
  "properties": {
    "iso:country":"US",
    "sg:address":"8345 Herschell Rd",
    "sg:city":"Winnemucca",
    "sg:classifiers":[
        {
            "category":"Restaurant",
            "type":"Food & Drink"
        }
    ],
    "sg:phone":"+1 775 625 1663",
    "sg:postcode":"89445",
    "sg:province":"NV",
    "sg:tags":[
        "caterer"
    ],
    "wof:name":"Shascade Custom B-B-Q & Catrg",
    "wof:placetype":"venue"
},
  "geometry": {"coordinates":[-117.858472,40.8905],"type":"Point"}
}