{
  "type": "Feature",
  "properties": {
    "iso:country":"US",
    "sg:address":"4829 Plata del Sol Dr",
    "sg:city":"Las Vegas",
    "sg:classifiers":[
        {
            "category":"Restaurant",
            "type":"Food & Drink"
        }
    ],
    "sg:phone":"+1 702 435 6597",
    "sg:postcode":"89121",
    "sg:province":"NV",
    "sg:tags":[
        "caterer"
    ],
    "wof:name":"Have Cooker Will Traver",
    "wof:placetype":"venue"
},
  "geometry": {"coordinates":[-115.067499,36.110783],"type":"Point"}
}