{
  "type": "Feature",
  "properties": {
    "iso:country":"US",
    "sg:address":"655 N Town Center Drive",
    "sg:city":"Las Vegas",
    "sg:classifiers":[
        {
            "category":"Health Services",
            "subcategory":"Doctor",
            "type":"Services"
        }
    ],
    "sg:phone":"+1 702 233 2200",
    "sg:postcode":"89144",
    "sg:province":"NV",
    "sg:website":"www.cccnevada.com",
    "wof:name":"Comprehensive Cancer Centers of Nevada",
    "wof:placetype":"venue"
},
  "geometry": {"coordinates":[-115.31725900000001,36.178969],"type":"Point"}
}