{
  "type": "Feature",
  "properties": {
    "iso:country":"US",
    "sg:address":"6732 W Cheyenne Ave",
    "sg:city":"Las Vegas",
    "sg:classifiers":[
        {
            "category":"Restaurant",
            "type":"Food & Drink"
        }
    ],
    "sg:phone":"+1 702 658 0900",
    "sg:postcode":"89108",
    "sg:province":"NV",
    "wof:name":"Wendy's",
    "wof:placetype":"venue"
},
  "geometry": {"coordinates":[-115.24164500000001,36.218222],"type":"Point"}
}