{
  "type": "Feature",
  "properties": {
    "iso:country":"US",
    "sg:address":"4599 Longley Ln",
    "sg:city":"Reno",
    "sg:classifiers":[
        {
            "category":"Professional",
            "subcategory":"Engineering",
            "type":"Services"
        }
    ],
    "sg:phone":"+1 775 828 4889",
    "sg:postcode":"89502",
    "sg:province":"NV",
    "sg:tags":[
        "engineer"
    ],
    "sg:website":"www.msa-reno.com",
    "wof:name":"MSA Engineering",
    "wof:placetype":"venue"
},
  "geometry": {"coordinates":[-119.759434,39.488439],"type":"Point"}
}