{
  "type": "Feature",
  "properties": {
    "iso:country":"US",
    "sg:address":"98 S Carson St",
    "sg:city":"Fallon",
    "sg:classifiers":[
        {
            "category":"Manufacturing",
            "subcategory":"Printing",
            "type":"Manufacturing & Wholesale Goods"
        }
    ],
    "sg:phone":"+1 775 423 6696",
    "sg:postcode":"89406",
    "sg:province":"NV",
    "sg:tags":[
        "commercial"
    ],
    "wof:name":"Lahonton Printing",
    "wof:placetype":"venue"
},
  "geometry": {"coordinates":[-118.77821299999999,39.47391],"type":"Point"}
}