{
  "type": "Feature",
  "properties": {
    "iso:country":"US",
    "sg:address":"6356 Maratea Avenue",
    "sg:city":"Las Vegas",
    "sg:classifiers":[
        {
            "category":"Building & Trades",
            "subcategory":"Pest Control",
            "type":"Services"
        }
    ],
    "sg:phone":"+1 702 639 9611",
    "sg:postcode":"89130",
    "sg:province":"NV",
    "sg:website":"www.toplinepest.com",
    "wof:name":"Topline Pest Eliminators",
    "wof:placetype":"venue"
},
  "geometry": {"coordinates":[-115.232269,36.249099],"type":"Point"}
}