{
  "type": "Feature",
  "properties": {
    "iso:country":"US",
    "sg:address":"300 S 4th St",
    "sg:city":"Las Vegas",
    "sg:classifiers":[
        {
            "category":"Banks & Credit Unions",
            "subcategory":"Financial Services",
            "type":"Services"
        }
    ],
    "sg:phone":"+1 702 598 3738",
    "sg:postcode":"89101",
    "sg:province":"NV",
    "sg:tags":[
        "company",
        "holding"
    ],
    "wof:name":"Baker Refractories",
    "wof:placetype":"venue"
},
  "geometry": {"coordinates":[-115.144082,36.166237],"type":"Point"}
}