{
  "type": "Feature",
  "properties": {
    "iso:country":"US",
    "sg:address":"323 N Stewart St",
    "sg:city":"Carson City",
    "sg:classifiers":[
        {
            "category":"Travel",
            "subcategory":"Hotels & Motels",
            "type":"Entertainment"
        }
    ],
    "sg:phone":"+1 775 883 6607",
    "sg:postcode":"89701",
    "sg:province":"NV",
    "wof:name":"Stewart Street Inn",
    "wof:placetype":"venue"
},
  "geometry": {"coordinates":[-119.764,39.165199],"type":"Point"}
}