{
  "type": "Feature",
  "properties": {
    "iso:country":"US",
    "sg:address":"3030 S Highland Dr",
    "sg:city":"Las Vegas",
    "sg:classifiers":[
        {
            "category":"Education",
            "subcategory":"Vocational School",
            "type":"Public Place"
        }
    ],
    "sg:phone":"+1 702 733 3030",
    "sg:postcode":"89109",
    "sg:province":"NV",
    "wof:name":"Las Vegas Gaming & Tech School",
    "wof:placetype":"venue"
},
  "geometry": {"coordinates":[-115.176486,36.13193],"type":"Point"}
}