{
  "type": "Feature",
  "properties": {
    "iso:country":"US",
    "sg:address":"2730 Lima Ln",
    "sg:city":"Fallon",
    "sg:classifiers":[
        {
            "category":"Health Services",
            "subcategory":"Health Practitioner",
            "type":"Services"
        }
    ],
    "sg:phone":"+1 775 423 8116",
    "sg:postcode":"89406",
    "sg:province":"NV",
    "wof:name":"Massage Works",
    "wof:placetype":"venue"
},
  "geometry": {"coordinates":[-118.83805,39.449463],"type":"Point"}
}