{
  "type": "Feature",
  "properties": {
    "iso:country":"US",
    "sg:address":"2955 Industrial Rd",
    "sg:city":"Las Vegas",
    "sg:classifiers":[
        {
            "category":"Arts & Performance",
            "subcategory":"Theater",
            "type":"Entertainment"
        }
    ],
    "sg:phone":"+1 702 796 7960",
    "sg:postcode":"89109",
    "sg:province":"NV",
    "sg:tags":[
        "entertainer"
    ],
    "wof:name":"Las Vegas Elite Entertainers",
    "wof:placetype":"venue"
},
  "geometry": {"coordinates":[-115.165026,36.14379],"type":"Point"}
}