{
  "type": "Feature",
  "properties": {
    "iso:country":"US",
    "sg:address":"4047 Waterhole Cir",
    "sg:city":"Reno",
    "sg:classifiers":[
        {
            "category":"Professional",
            "subcategory":"Management & Consulting",
            "type":"Services"
        }
    ],
    "sg:phone":"+1 775 747 4469",
    "sg:postcode":"89509",
    "sg:province":"NV",
    "sg:tags":[
        "business"
    ],
    "wof:name":"Dominique River Consulting",
    "wof:placetype":"venue"
},
  "geometry": {"coordinates":[-119.87540799999999,39.492023],"type":"Point"}
}