{
  "type": "Feature",
  "properties": {
    "iso:country":"US",
    "sg:address":"4540 Arville St",
    "sg:city":"Las Vegas",
    "sg:phone":"+1 702 221 0500",
    "sg:postcode":"89103",
    "sg:province":"NV",
    "sg:tags":[
        "shelving"
    ],
    "wof:name":"3 Day Shelves",
    "wof:placetype":"venue"
},
  "geometry": {"coordinates":[-115.199179,36.105276],"type":"Point"}
}