{
  "type": "Feature",
  "properties": {
    "iso:country":"US",
    "sg:address":"3510 Barron Way",
    "sg:city":"Reno",
    "sg:classifiers":[
        {
            "category":"Building & Trades",
            "subcategory":"Plumbing",
            "type":"Services"
        }
    ],
    "sg:phone":"+1 775 857 2857",
    "sg:postcode":"89511",
    "sg:province":"NV",
    "sg:tags":[
        "plumbing",
        "contractor"
    ],
    "sg:website":"www.85pauls.com",
    "wof:name":"Paul's Plumbing & Heating Inc",
    "wof:placetype":"venue"
},
  "geometry": {"coordinates":[-119.769228,39.472487],"type":"Point"}
}