{
  "type": "Feature",
  "properties": {
    "iso:country":"US",
    "sg:address":"2169 Gabriel Dr",
    "sg:city":"Las Vegas",
    "sg:classifiers":[
        {
            "category":"Travel",
            "subcategory":"Campground",
            "type":"Entertainment"
        }
    ],
    "sg:phone":"+1 702 212 5437",
    "sg:postcode":"89119",
    "sg:province":"NV",
    "sg:tags":[
        "camp"
    ],
    "wof:name":"Camp Las Vegas",
    "wof:placetype":"venue"
},
  "geometry": {"coordinates":[-115.121375,36.10569],"type":"Point"}
}