{
  "type": "Feature",
  "properties": {
    "iso:country":"US",
    "sg:address":"3675 Pecos-Mcleod Connect",
    "sg:city":"Las Vegas",
    "sg:classifiers":[
        {
            "category":"Professional",
            "subcategory":"Accounting & Tax Preparation",
            "type":"Services"
        }
    ],
    "sg:phone":"+1 702 792 0500",
    "sg:postcode":"89121",
    "sg:province":"NV",
    "sg:tags":[
        "return"
    ],
    "wof:name":"Affordable Bookkeeping Inc",
    "wof:placetype":"venue"
},
  "geometry": {"coordinates":[-115.108469,36.124936],"type":"Point"}
}