{
  "type": "Feature",
  "properties": {
    "iso:country":"US",
    "sg:address":"3790 Redwood St",
    "sg:city":"Las Vegas",
    "sg:classifiers":[
        {
            "category":"Social Services",
            "subcategory":"Child Care",
            "type":"Services"
        }
    ],
    "sg:phone":"+1 702 362 9255",
    "sg:postcode":"89103",
    "sg:province":"NV",
    "wof:name":"My Little Schoolhouse",
    "wof:placetype":"venue"
},
  "geometry": {"coordinates":[-115.238361,36.120713],"type":"Point"}
}