{
  "type": "Feature",
  "properties": {
    "iso:country":"US",
    "sg:address":"815 S Rainbow Blvd",
    "sg:city":"Las Vegas",
    "sg:classifiers":[
        {
            "category":"Professional",
            "subcategory":"Business Services",
            "type":"Services"
        }
    ],
    "sg:phone":"+1 702 870 7890",
    "sg:postcode":"89145",
    "sg:province":"NV",
    "wof:name":"Sylvan Pools Supply Center Inc",
    "wof:placetype":"venue"
},
  "geometry": {"coordinates":[-115.244102,36.16296],"type":"Point"}
}