{
  "type": "Feature",
  "properties": {
    "iso:country":"US",
    "sg:address":"10908 Napa Ridge Dr",
    "sg:city":"Las Vegas",
    "sg:classifiers":[
        {
            "category":"Building & Trades",
            "subcategory":"Landscaping Services",
            "type":"Services"
        }
    ],
    "sg:phone":"+1 702 376 8906",
    "sg:postcode":"89144",
    "sg:province":"NV",
    "sg:tags":[
        "lawn",
        "maintenance",
        "grounds"
    ],
    "wof:name":"J Lawn Maintenance Svc",
    "wof:placetype":"venue"
},
  "geometry": {"coordinates":[-115.334086,36.177327],"type":"Point"}
}