{
  "type": "Feature",
  "properties": {
    "iso:country":"US",
    "sg:address":"1572 E College Pkwy",
    "sg:city":"Carson City",
    "sg:classifiers":[
        {
            "category":"Professional",
            "subcategory":"Engineering",
            "type":"Services"
        }
    ],
    "sg:phone":"+1 775 888 9992",
    "sg:postcode":"89706",
    "sg:province":"NV",
    "wof:name":"Mactec Engrg & Consulting",
    "wof:placetype":"venue"
},
  "geometry": {"coordinates":[-119.749024,39.190097],"type":"Point"}
}