{
  "type": "Feature",
  "properties": {
    "iso:country":"US",
    "sg:address":"2880 W Sahara Ave",
    "sg:city":"Las Vegas",
    "sg:classifiers":[
        {
            "category":"Wholesale",
            "subcategory":"Stationery",
            "type":"Manufacturing & Wholesale Goods"
        }
    ],
    "sg:phone":"+1 702 220 6245",
    "sg:postcode":"89102",
    "sg:province":"NV",
    "sg:tags":[
        "corporation",
        "supply"
    ],
    "wof:name":"Forward Nevada",
    "wof:placetype":"venue"
},
  "geometry": {"coordinates":[-115.179658,36.144422],"type":"Point"}
}