{
  "type": "Feature",
  "properties": {
    "iso:country":"US",
    "sg:address":"3339 Las Vegas Blvd S",
    "sg:city":"Las Vegas",
    "sg:classifiers":[
        {
            "category":"Restaurant",
            "type":"Food & Drink"
        }
    ],
    "sg:phone":"+1 702 792 9099",
    "sg:postcode":"89109",
    "sg:province":"NV",
    "sg:tags":[
        "bar"
    ],
    "wof:name":"Rosewood Grille",
    "wof:placetype":"venue"
},
  "geometry": {"coordinates":[-115.17276099999999,36.117907],"type":"Point"}
}