{
  "type": "Feature",
  "properties": {
    "iso:country":"US",
    "sg:address":"6349 Springwood Dr",
    "sg:city":"Reno",
    "sg:classifiers":[
        {
            "category":"Retail",
            "subcategory":"Auto Repair",
            "type":"Services"
        }
    ],
    "sg:phone":"+1 775 742 2086",
    "sg:postcode":"89523",
    "sg:province":"NV",
    "sg:tags":[
        "body",
        "automobile",
        "painting"
    ],
    "wof:name":"BBK Vehicle Inspection Inc",
    "wof:placetype":"venue"
},
  "geometry": {"coordinates":[-119.888392,39.534528],"type":"Point"}
}