{
  "type": "Feature",
  "properties": {
    "iso:country":"US",
    "sg:address":"240 W Center St",
    "sg:city":"Fallon",
    "sg:classifiers":[
        {
            "category":"Retail",
            "subcategory":"Repair Shop",
            "type":"Services"
        }
    ],
    "sg:phone":"+1 775 423 0327",
    "sg:postcode":"89406",
    "sg:province":"NV",
    "sg:tags":[
        "television",
        "radio"
    ],
    "wof:name":"Hariom TV Ctr",
    "wof:placetype":"venue"
},
  "geometry": {"coordinates":[-118.779833,39.473123],"type":"Point"}
}