{
  "type": "Feature",
  "properties": {
    "iso:country":"US",
    "sg:address":"6650 Spencer St",
    "sg:city":"Las Vegas",
    "sg:classifiers":[
        {
            "category":"Wholesale",
            "subcategory":"Durable Goods & Equipment",
            "type":"Manufacturing & Wholesale Goods"
        }
    ],
    "sg:phone":"+1 702 320 2192",
    "sg:postcode":"89119",
    "sg:province":"NV",
    "sg:tags":[
        "disc"
    ],
    "wof:name":"Image Entertainment Inc",
    "wof:placetype":"venue"
},
  "geometry": {"coordinates":[-115.127627,36.069258],"type":"Point"}
}