{
  "type": "Feature",
  "properties": {
    "iso:country":"US",
    "sg:address":"6775 Speedway Blvd",
    "sg:city":"Las Vegas",
    "sg:classifiers":[
        {
            "category":"Home & Garden",
            "subcategory":"Furniture",
            "type":"Retail Goods"
        }
    ],
    "sg:phone":"+1 702 643 1810",
    "sg:postcode":"89115",
    "sg:province":"NV",
    "sg:tags":[
        "hospitality",
        "fixture"
    ],
    "wof:name":"Andrewsville Hospitality Furn",
    "wof:placetype":"venue"
},
  "geometry": {"coordinates":[-115.019659,36.278981],"type":"Point"}
}