{
  "type": "Feature",
  "properties": {
    "iso:country":"US",
    "sg:address":"458 W Winnemucca Blvd",
    "sg:city":"Winnemucca",
    "sg:classifiers":[
        {
            "category":"Banks & Credit Unions",
            "subcategory":"Bank",
            "type":"Services"
        }
    ],
    "sg:phone":"+1 775 625 2333",
    "sg:postcode":"89445",
    "sg:province":"NV",
    "sg:tags":[
        "depository",
        "banking"
    ],
    "wof:name":"Check Fora Check",
    "wof:placetype":"venue"
},
  "geometry": {"coordinates":[-117.73897100000001,40.97028],"type":"Point"}
}