{
  "type": "Feature",
  "properties": {
    "iso:country":"US",
    "sg:address":"640 McKnight Street Apt C238",
    "sg:city":"Las Vegas",
    "sg:classifiers":[
        {
            "category":"Real Estate",
            "subcategory":"Real Estate Operator",
            "type":"Services"
        }
    ],
    "sg:phone":"+1 702 387 1700",
    "sg:postcode":"89101",
    "sg:province":"NV",
    "sg:tags":[
        "apartment"
    ],
    "wof:name":"Help Las Vegas Vets Apartments",
    "wof:placetype":"venue"
},
  "geometry": {"coordinates":[-115.112242,36.174714],"type":"Point"}
}