{
  "type": "Feature",
  "properties": {
    "iso:country":"US",
    "sg:address":"4701 N Torrey Pines Dr",
    "sg:city":"Las Vegas",
    "sg:classifiers":[
        {
            "category":"Manufacturing",
            "subcategory":"Lumber",
            "type":"Manufacturing & Wholesale Goods"
        }
    ],
    "sg:phone":"+1 702 515 5400",
    "sg:postcode":"89130",
    "sg:province":"NV",
    "sg:tags":[
        "government"
    ],
    "wof:name":"US Forestry Dept",
    "wof:placetype":"venue"
},
  "geometry": {"coordinates":[-115.233868,36.247113],"type":"Point"}
}