{
  "type": "Feature",
  "properties": {
    "iso:country":"US",
    "sg:address":"4760 S Pecos Rd",
    "sg:city":"Las Vegas",
    "sg:classifiers":[
        {
            "category":"Personal",
            "type":"Services"
        }
    ],
    "sg:phone":"+1 702 456 1501",
    "sg:postcode":"89121",
    "sg:province":"NV",
    "sg:tags":[
        "therapist",
        "massage"
    ],
    "wof:name":"Studio 4 Massage",
    "wof:placetype":"venue"
},
  "geometry": {"coordinates":[-115.100941,36.100566],"type":"Point"}
}