{
  "type": "Feature",
  "properties": {
    "iso:country":"US",
    "sg:address":"3663 Las Vegas Blvd S",
    "sg:city":"Las Vegas",
    "sg:classifiers":[
        {
            "category":"Restaurant",
            "type":"Food & Drink"
        }
    ],
    "sg:phone":"+1 702 731 1755",
    "sg:postcode":"89109",
    "sg:province":"NV",
    "sg:tags":[
        "italian"
    ],
    "wof:name":"Lombardis",
    "wof:placetype":"venue"
},
  "geometry": {"coordinates":[-115.172838,36.114701],"type":"Point"}
}