{
  "type": "Feature",
  "properties": {
    "iso:country":"US",
    "sg:address":"2005 Sierra Highlands Dr",
    "sg:city":"Reno",
    "sg:classifiers":[
        {
            "category":"Restaurant",
            "type":"Food & Drink"
        }
    ],
    "sg:menulink":"http://www.allmenus.com/nv/reno-north/283506-pizza-plus/menu/",
    "sg:phone":"+1 775 473 8730",
    "sg:postcode":"89523",
    "sg:province":"NV",
    "sg:tags":[
        "american",
        "pizza"
    ],
    "wof:name":"Pizza Plus",
    "wof:placetype":"venue"
},
  "geometry": {"coordinates":[-119.86871600000001,39.533609],"type":"Point"}
}