{
  "type": "Feature",
  "properties": {
    "iso:country":"US",
    "sg:address":"4440 E Tropicana Ave",
    "sg:city":"Las Vegas",
    "sg:classifiers":[
        {
            "category":"Wholesale",
            "subcategory":"Machinery & Supplies",
            "type":"Manufacturing & Wholesale Goods"
        }
    ],
    "sg:phone":"+1 702 433 4226",
    "sg:postcode":"89121",
    "sg:province":"NV",
    "sg:tags":[
        "salon",
        "beauty"
    ],
    "wof:name":"Olga's Beauty Supply",
    "wof:placetype":"venue"
},
  "geometry": {"coordinates":[-115.077708,36.100358],"type":"Point"}
}