{
  "type": "Feature",
  "properties": {
    "iso:country":"US",
    "sg:address":"2770 S Maryland Pkwy",
    "sg:city":"Las Vegas",
    "sg:classifiers":[
        {
            "category":"Professional",
            "subcategory":"Detective & Security Services",
            "type":"Services"
        }
    ],
    "sg:phone":"+1 702 734 5076",
    "sg:postcode":"89109",
    "sg:province":"NV",
    "sg:tags":[
        "car",
        "guard",
        "patrol"
    ],
    "wof:name":"Securitas Security Svc USA Inc",
    "wof:placetype":"venue"
},
  "geometry": {"coordinates":[-115.13679999999999,36.137848],"type":"Point"}
}