{
  "type": "Feature",
  "properties": {
    "iso:country":"US",
    "sg:address":"129 S Water St",
    "sg:city":"Henderson",
    "sg:classifiers":[
        {
            "category":"Utilities",
            "subcategory":"Telephone",
            "type":"Services"
        }
    ],
    "sg:phone":"+1 702 399 3100",
    "sg:postcode":"89015",
    "sg:province":"NV",
    "sg:tags":[
        "communication",
        "datum"
    ],
    "wof:name":"Wireless Works",
    "wof:placetype":"venue"
},
  "geometry": {"coordinates":[-114.983283,36.032971],"type":"Point"}
}