{
  "type": "Feature",
  "properties": {
    "iso:country":"US",
    "sg:address":"1300 Cashman Dr",
    "sg:city":"Las Vegas",
    "sg:classifiers":[
        {
            "category":"Professional",
            "subcategory":"Business Services",
            "type":"Services"
        }
    ],
    "sg:phone":"+1 702 822 6244",
    "sg:postcode":"89102",
    "sg:province":"NV",
    "wof:name":"Burress Cy",
    "wof:placetype":"venue"
},
  "geometry": {"coordinates":[-115.186253,36.154218],"type":"Point"}
}