{
  "type": "Feature",
  "properties": {
    "iso:country":"US",
    "sg:address":"4858 Willow Glen Dr",
    "sg:city":"Las Vegas",
    "sg:classifiers":[
        {
            "category":"Professional",
            "subcategory":"Management & Consulting",
            "type":"Services"
        }
    ],
    "sg:phone":"+1 702 876 2378",
    "sg:postcode":"89147",
    "sg:province":"NV",
    "sg:tags":[
        "consultant",
        "telecommunication"
    ],
    "wof:name":"Best Line Inc",
    "wof:placetype":"venue"
},
  "geometry": {"coordinates":[-115.277287,36.101395],"type":"Point"}
}