{
  "type": "Feature",
  "properties": {
    "iso:country":"US",
    "sg:address":"5230 W Patrick Ln Ste 120",
    "sg:city":"Las Vegas",
    "sg:classifiers":[
        {
            "category":"Real Estate",
            "subcategory":"Real Estate Services",
            "type":"Services"
        }
    ],
    "sg:phone":"+1 702 791 1970",
    "sg:postcode":"89118",
    "sg:province":"NV",
    "wof:name":"Rise Realty",
    "wof:placetype":"venue"
},
  "geometry": {"coordinates":[-115.212669,36.078932],"type":"Point"}
}