{
  "type": "Feature",
  "properties": {
    "iso:country":"US",
    "sg:address":"5961 Los Altos Pkwy",
    "sg:city":"Sparks",
    "sg:classifiers":[
        {
            "category":"Health Services",
            "subcategory":"Optometrist",
            "type":"Services"
        }
    ],
    "sg:phone":"+1 775 359 2020",
    "sg:postcode":"89436",
    "sg:province":"NV",
    "wof:name":"Pritchett Eye Care Assoc",
    "wof:placetype":"venue"
},
  "geometry": {"coordinates":[-119.70528899999999,39.5645],"type":"Point"}
}