{
  "type": "Feature",
  "properties": {
    "iso:country":"US",
    "sg:address":"5400 Meadowood Mall Cir",
    "sg:city":"Reno",
    "sg:classifiers":[
        {
            "category":"Shopping",
            "subcategory":"Optical Goods",
            "type":"Retail Goods"
        }
    ],
    "sg:phone":"+1 775 829 6254",
    "sg:postcode":"89502",
    "sg:province":"NV",
    "wof:name":"Sears Optical",
    "wof:placetype":"venue"
},
  "geometry": {"coordinates":[-119.783603,39.471453],"type":"Point"}
}