{
  "type": "Feature",
  "properties": {
    "iso:country":"US",
    "sg:address":"154 N Boulder Hwy",
    "sg:city":"Henderson",
    "sg:classifiers":[
        {
            "category":"Shopping",
            "subcategory":"Pharmacy",
            "type":"Retail Goods"
        }
    ],
    "sg:phone":"+1 702 564 5211",
    "sg:postcode":"89015",
    "sg:province":"NV",
    "sg:tags":[
        "drug",
        "store"
    ],
    "wof:name":"Sav-On 9081",
    "wof:placetype":"venue"
},
  "geometry": {"coordinates":[-114.984086,36.041479],"type":"Point"}
}