{
  "type": "Feature",
  "properties": {
    "iso:country":"US",
    "sg:address":"4455 E Tropicana Ave",
    "sg:city":"Las Vegas",
    "sg:classifiers":[
        {
            "category":"Food & Beverages",
            "subcategory":"Bakery",
            "type":"Retail Goods"
        },
        {
            "category":"Restaurant",
            "type":"Food & Drink"
        }
    ],
    "sg:phone":"+1 702 456 9998",
    "sg:postcode":"89121",
    "sg:province":"NV",
    "wof:name":"Josie's Bakery",
    "wof:placetype":"venue"
},
  "geometry": {"coordinates":[-115.076168,36.100208],"type":"Point"}
}