{
  "type": "Feature",
  "properties": {
    "iso:country":"US",
    "sg:address":"616 H St",
    "sg:city":"Las Vegas",
    "sg:classifiers":[
        {
            "category":"Professional",
            "type":"Services"
        }
    ],
    "sg:phone":"+1 702 242 1222",
    "sg:postcode":"89106",
    "sg:province":"NV",
    "sg:tags":[
        "caterer"
    ],
    "wof:name":"Abdullah Cafe & Catering",
    "wof:placetype":"venue"
},
  "geometry": {"coordinates":[-115.15165399999999,36.17776],"type":"Point"}
}