{
  "type": "Feature",
  "properties": {
    "iso:country":"US",
    "sg:address":"3132 Meade Ave",
    "sg:city":"Las Vegas",
    "sg:classifiers":[
        {
            "category":"Personal",
            "type":"Services"
        }
    ],
    "sg:phone":"+1 702 362 0397",
    "sg:postcode":"89102",
    "sg:province":"NV",
    "sg:tags":[
        "towing"
    ],
    "sg:website":"www.dndtowinginc.com",
    "wof:name":"D & D Towing Inc",
    "wof:placetype":"venue"
},
  "geometry": {"coordinates":[-115.182999,36.136398],"type":"Point"}
}