{
  "type": "Feature",
  "properties": {
    "iso:country":"US",
    "sg:address":"1331 W Craig Rd",
    "sg:city":"North Las Vegas",
    "sg:classifiers":[
        {
            "category":"Donuts",
            "subcategory":"None",
            "type":"Food & Drink"
        }
    ],
    "sg:phone":"+1 702 657 2527",
    "sg:postcode":"89032",
    "sg:province":"NV",
    "wof:name":"Krispy Kreme Doughnuts",
    "wof:placetype":"venue"
},
  "geometry": {"coordinates":[-115.161003,36.239201],"type":"Point"}
}