{
  "type": "Feature",
  "properties": {
    "iso:country":"US",
    "sg:address":"1280 Icehouse Ave",
    "sg:city":"Sparks",
    "sg:classifiers":[
        {
            "category":"Wholesale",
            "subcategory":"Machinery & Supplies",
            "type":"Manufacturing & Wholesale Goods"
        }
    ],
    "sg:phone":"+1 775 359 1570",
    "sg:postcode":"89431",
    "sg:province":"NV",
    "sg:tags":[
        "beauty"
    ],
    "wof:name":"Alberto-Culver Company",
    "wof:placetype":"venue"
},
  "geometry": {"coordinates":[-119.757003,39.529931],"type":"Point"}
}