{
  "type": "Feature",
  "properties": {
    "iso:country":"US",
    "sg:address":"790 Eagle Mountain Dr",
    "sg:city":"Las Vegas",
    "sg:classifiers":[
        {
            "category":"Professional",
            "subcategory":"Management & Consulting",
            "type":"Services"
        }
    ],
    "sg:phone":"+1 702 914 5723",
    "sg:postcode":"89123",
    "sg:province":"NV",
    "sg:tags":[
        "consultant",
        "medical",
        "legal"
    ],
    "wof:name":"KLM Medical Legal Conslnts",
    "wof:placetype":"venue"
},
  "geometry": {"coordinates":[-115.145731,36.052103],"type":"Point"}
}