{
  "type": "Feature",
  "properties": {
    "iso:country":"US",
    "sg:address":"51 E Grove St",
    "sg:city":"Reno",
    "sg:classifiers":[
        {
            "category":"Shopping",
            "subcategory":"Used Merchandise",
            "type":"Retail Goods"
        }
    ],
    "sg:phone":"+1 775 828 0770",
    "sg:postcode":"89502",
    "sg:province":"NV",
    "sg:website":"www.metropawn.com",
    "wof:name":"Metropawn",
    "wof:placetype":"venue"
},
  "geometry": {"coordinates":[-119.799449,39.501021],"type":"Point"}
}