{
  "type": "Feature",
  "properties": {
    "iso:country":"US",
    "sg:address":"1905 N Green Valley Pkwy",
    "sg:city":"Henderson",
    "sg:classifiers":[
        {
            "category":"Shopping",
            "subcategory":"Books",
            "type":"Retail Goods"
        }
    ],
    "sg:phone":"+1 702 896 6676",
    "sg:postcode":"89074",
    "sg:province":"NV",
    "sg:tags":[
        "dealer"
    ],
    "sg:website":"www.deseretbook.com",
    "wof:name":"Deseret Book",
    "wof:placetype":"venue"
},
  "geometry": {"coordinates":[-115.08233,36.042984],"type":"Point"}
}