{
  "type": "Feature",
  "properties": {
    "iso:country":"US",
    "sg:address":"7935 Badura Ave",
    "sg:city":"Las Vegas",
    "sg:classifiers":[
        {
            "category":"Real Estate",
            "subcategory":"Real Estate Services",
            "type":"Services"
        }
    ],
    "sg:phone":"+1 702 451 0479",
    "sg:postcode":"89113",
    "sg:province":"NV",
    "sg:tags":[
        "management",
        "property"
    ],
    "wof:name":"Pier Construction and Development",
    "wof:placetype":"venue"
},
  "geometry": {"coordinates":[-115.26341499999999,36.060965],"type":"Point"}
}