{
  "type": "Feature",
  "properties": {
    "iso:country":"US",
    "sg:address":"3235 Rutledge",
    "sg:city":"Las Vegas",
    "sg:classifiers":[
        {
            "category":"Banks & Credit Unions",
            "subcategory":"Investment Brokerage",
            "type":"Services"
        }
    ],
    "sg:phone":"+1 702 837 4907",
    "sg:postcode":"89120",
    "sg:province":"NV",
    "sg:tags":[
        "advisory",
        "financial"
    ],
    "wof:name":"United Bank Card",
    "wof:placetype":"venue"
},
  "geometry": {"coordinates":[-115.104112,36.054643],"type":"Point"}
}