{
  "type": "Feature",
  "properties": {
    "iso:country":"US",
    "sg:address":"932 Coatbridge St",
    "sg:city":"Las Vegas",
    "sg:classifiers":[
        {
            "category":"Shopping",
            "subcategory":"Discount & Variety Stores",
            "type":"Retail Goods"
        }
    ],
    "sg:phone":"+1 702 243 5134",
    "sg:postcode":"89145",
    "sg:province":"NV",
    "sg:tags":[
        "merchandise",
        "general"
    ],
    "wof:name":"Re' Products",
    "wof:placetype":"venue"
},
  "geometry": {"coordinates":[-115.294365,36.162087],"type":"Point"}
}