{
  "type": "Feature",
  "properties": {
    "iso:country":"US",
    "sg:address":"594 N Stephanie St",
    "sg:city":"Henderson",
    "sg:classifiers":[
        {
            "category":"Retail",
            "subcategory":"Laundry & Dry Cleaning",
            "type":"Services"
        }
    ],
    "sg:phone":"+1 702 252 7587",
    "sg:postcode":"89014",
    "sg:province":"NV",
    "sg:tags":[
        "cleaners"
    ],
    "wof:name":"A Plus Cleaners",
    "wof:placetype":"venue"
},
  "geometry": {"coordinates":[-115.046148,36.056344],"type":"Point"}
}