{
  "type": "Feature",
  "properties": {
    "iso:country":"US",
    "sg:address":"3054 S Valley View Blvd",
    "sg:city":"Las Vegas",
    "sg:classifiers":[
        {
            "category":"Professional",
            "subcategory":"Accounting & Tax Preparation",
            "type":"Services"
        }
    ],
    "sg:phone":"+1 702 873 0006",
    "sg:postcode":"89102",
    "sg:province":"NV",
    "sg:tags":[
        "return"
    ],
    "wof:name":"Ingles",
    "wof:placetype":"venue"
},
  "geometry": {"coordinates":[-115.190325,36.134633],"type":"Point"}
}