{
  "type": "Feature",
  "properties": {
    "iso:country":"US",
    "sg:address":"841 Palo Verde Dr",
    "sg:city":"Henderson",
    "sg:classifiers":[
        {
            "category":"Recreation",
            "type":"Entertainment"
        }
    ],
    "sg:phone":"+1 702 564 9828",
    "sg:postcode":"89015",
    "sg:province":"NV",
    "wof:name":"Schwartz Lisa Fields",
    "wof:placetype":"venue"
},
  "geometry": {"coordinates":[-114.963256,36.04176],"type":"Point"}
}