{
  "type": "Feature",
  "properties": {
    "iso:country":"US",
    "sg:address":"1324 Disc Dr",
    "sg:city":"Sparks",
    "sg:classifiers":[
        {
            "category":"Real Estate",
            "subcategory":"Real Estate Agent",
            "type":"Services"
        }
    ],
    "sg:phone":"+1 775 685 2323",
    "sg:postcode":"89436",
    "sg:province":"NV",
    "sg:website":"www.prunevada.com",
    "wof:name":"Prudential Nevada Realty",
    "wof:placetype":"venue"
},
  "geometry": {"coordinates":[-119.72163500000001,39.576672],"type":"Point"}
}