{
  "type": "Feature",
  "properties": {
    "iso:country":"US",
    "sg:address":"3965 S Durango Dr",
    "sg:city":"Las Vegas",
    "sg:classifiers":[
        {
            "category":"Banks & Credit Unions",
            "subcategory":"Bank",
            "type":"Services"
        }
    ],
    "sg:phone":"+1 702 360 9587",
    "sg:postcode":"89147",
    "sg:province":"NV",
    "wof:name":"Bank West Business Park",
    "wof:placetype":"venue"
},
  "geometry": {"coordinates":[-115.279059,36.120232],"type":"Point"}
}