{
  "type": "Feature",
  "properties": {
    "iso:country":"US",
    "sg:address":"1575 E Commercial Row",
    "sg:city":"Reno",
    "sg:classifiers":[
        {
            "category":"Wholesale",
            "subcategory":"Petroleum",
            "type":"Manufacturing & Wholesale Goods"
        }
    ],
    "sg:phone":"+1 775 323 1885",
    "sg:postcode":"89512",
    "sg:province":"NV",
    "sg:tags":[
        "bulk",
        "station",
        "gasoline"
    ],
    "wof:name":"Unocal Corporation",
    "wof:placetype":"venue"
},
  "geometry": {"coordinates":[-119.79219,39.532063],"type":"Point"}
}