{
  "type": "Feature",
  "properties": {
    "iso:country":"US",
    "sg:address":"3816 Las Vegas Fwy",
    "sg:city":"North Las Vegas",
    "sg:classifiers":[
        {
            "category":"Professional",
            "type":"Services"
        }
    ],
    "sg:phone":"+1 702 651 0920",
    "sg:postcode":"89030",
    "sg:province":"NV",
    "sg:tags":[
        "establishment"
    ],
    "wof:name":"American Help Foundation",
    "wof:placetype":"venue"
},
  "geometry": {"coordinates":[-115.109865,36.233449],"type":"Point"}
}