{
  "type": "Feature",
  "properties": {
    "iso:country":"US",
    "sg:address":"10290 Dupage Ave",
    "sg:city":"Las Vegas",
    "sg:classifiers":[
        {
            "category":"Professional",
            "type":"Services"
        }
    ],
    "sg:phone":"+1 702 804 6153",
    "sg:postcode":"89135",
    "sg:province":"NV",
    "sg:tags":[
        "establishment"
    ],
    "wof:name":"Berman Logistics",
    "wof:placetype":"venue"
},
  "geometry": {"coordinates":[-115.318003,36.135403],"type":"Point"}
}