{
  "type": "Feature",
  "properties": {
    "iso:country":"US",
    "sg:address":"9436 W Lake Mead Blvd",
    "sg:city":"Las Vegas",
    "sg:classifiers":[
        {
            "category":"Professional",
            "subcategory":"Management & Consulting",
            "type":"Services"
        }
    ],
    "sg:phone":"+1 702 251 4236",
    "sg:postcode":"89134",
    "sg:province":"NV",
    "sg:tags":[
        "construction"
    ],
    "wof:name":"Construction Defect Mitigators",
    "wof:placetype":"venue"
},
  "geometry": {"coordinates":[-115.302459,36.206339],"type":"Point"}
}