{
  "type": "Feature",
  "properties": {
    "iso:country":"US",
    "sg:address":"1340 W Newlands Dr",
    "sg:city":"Fernley",
    "sg:classifiers":[
        {
            "category":"Food & Beverages",
            "subcategory":"Groceries & Convenience Stores",
            "type":"Retail Goods"
        }
    ],
    "sg:phone":"+1 775 575 3565",
    "sg:postcode":"89408",
    "sg:province":"NV",
    "wof:name":"Perry Properties",
    "wof:placetype":"venue"
},
  "geometry": {"coordinates":[-119.220551,39.610066],"type":"Point"}
}