{
  "type": "Feature",
  "properties": {
    "iso:country":"US",
    "sg:address":"4521 S Madreperla St",
    "sg:city":"Las Vegas",
    "sg:classifiers":[
        {
            "category":"Retail",
            "subcategory":"Self-service Laundry",
            "type":"Services"
        }
    ],
    "sg:phone":"+1 702 644 1811",
    "sg:postcode":"89121",
    "sg:province":"NV",
    "sg:tags":[
        "coin"
    ],
    "wof:name":"Thunder Suds Lundromat Dry Clr",
    "wof:placetype":"venue"
},
  "geometry": {"coordinates":[-115.116224,36.106153],"type":"Point"}
}