{
  "type": "Feature",
  "properties": {
    "iso:country":"US",
    "sg:address":"4815 W Russell Road",
    "sg:city":"Las Vegas",
    "sg:classifiers":[
        {
            "category":"Shopping",
            "subcategory":"Mobile Phones",
            "type":"Retail Goods"
        }
    ],
    "sg:phone":"+1 702 212 7903",
    "sg:postcode":"89118",
    "sg:province":"NV",
    "wof:name":"Used 2-Way Wireless",
    "wof:placetype":"venue"
},
  "geometry": {"coordinates":[-115.20607099999999,36.086295],"type":"Point"}
}