{
  "type": "Feature",
  "properties": {
    "iso:country":"US",
    "sg:address":"701 Aspen Peak Loop",
    "sg:city":"Henderson",
    "sg:classifiers":[
        {
            "category":"Real Estate",
            "subcategory":"Real Estate Operator",
            "type":"Services"
        }
    ],
    "sg:phone":"+1 702 433 2900",
    "sg:postcode":"89011",
    "sg:province":"NV",
    "sg:tags":[
        "apartment"
    ],
    "wof:name":"South Valley Ranch Apartments",
    "wof:placetype":"venue"
},
  "geometry": {"coordinates":[-115.014036,36.074255],"type":"Point"}
}