{
  "type": "Feature",
  "properties": {
    "iso:country":"US",
    "sg:address":"1280 Bon Rea Way",
    "sg:city":"Reno",
    "sg:classifiers":[
        {
            "category":"Building & Trades",
            "subcategory":"Construction",
            "type":"Services"
        }
    ],
    "sg:phone":"+1 775 786 7925",
    "sg:postcode":"89503",
    "sg:province":"NV",
    "sg:tags":[
        "house"
    ],
    "wof:name":"Leslie H Holst",
    "wof:placetype":"venue"
},
  "geometry": {"coordinates":[-119.824678,39.540353],"type":"Point"}
}