{
  "type": "Feature",
  "properties": {
    "iso:country":"US",
    "sg:address":"1188 High School St",
    "sg:city":"Gardnerville",
    "sg:classifiers":[
        {
            "category":"Arts & Performance",
            "subcategory":"Theater",
            "type":"Entertainment"
        }
    ],
    "sg:phone":"+1 775 782 9768",
    "sg:postcode":"89410",
    "sg:province":"NV",
    "sg:tags":[
        "entertainer",
        "family"
    ],
    "wof:name":"Comstock Cowboys",
    "wof:placetype":"venue"
},
  "geometry": {"coordinates":[-119.750791,38.943689],"type":"Point"}
}