{
  "type": "Feature",
  "properties": {
    "iso:country":"US",
    "sg:address":"2975 E Sahara Ave",
    "sg:city":"Las Vegas",
    "sg:classifiers":[
        {
            "category":"Shopping",
            "subcategory":"Discount & Variety Stores",
            "type":"Retail Goods"
        }
    ],
    "sg:postcode":"89121",
    "sg:province":"NV",
    "wof:name":"K-Mart",
    "wof:placetype":"venue"
},
  "geometry": {"coordinates":[-115.11121300000001,36.143147],"type":"Point"}
}