{
  "type": "Feature",
  "properties": {
    "iso:country":"US",
    "sg:address":"916 S Valley View Blvd",
    "sg:city":"Las Vegas",
    "sg:classifiers":[
        {
            "category":"Professional",
            "subcategory":"Accounting & Tax Preparation",
            "type":"Services"
        }
    ],
    "sg:phone":"+1 702 360 5555",
    "sg:postcode":"89107",
    "sg:province":"NV",
    "sg:tags":[
        "return",
        "filing"
    ],
    "wof:name":"R B & Co",
    "wof:placetype":"venue"
},
  "geometry": {"coordinates":[-115.192596,36.161826],"type":"Point"}
}