{
  "type": "Feature",
  "properties": {
    "iso:country":"US",
    "sg:address":"3675 Pecos-Mcleod Connect",
    "sg:city":"Las Vegas",
    "sg:classifiers":[
        {
            "category":"Social Services",
            "type":"Services"
        }
    ],
    "sg:phone":"+1 702 893 2390",
    "sg:postcode":"89121",
    "sg:province":"NV",
    "wof:name":"Nadine Cracraft Mft",
    "wof:placetype":"venue"
},
  "geometry": {"coordinates":[-115.108469,36.124936],"type":"Point"}
}