{
  "type": "Feature",
  "properties": {
    "iso:country":"US",
    "sg:address":"6565 Spencer St",
    "sg:city":"Las Vegas",
    "sg:phone":"+1 702 270 8885",
    "sg:postcode":"89119",
    "sg:province":"NV",
    "sg:tags":[
        "distributor",
        "oil",
        "marketer"
    ],
    "wof:name":"Energyquest International",
    "wof:placetype":"venue"
},
  "geometry": {"coordinates":[-115.12782300000001,36.071248],"type":"Point"}
}