{
  "type": "Feature",
  "properties": {
    "iso:country":"US",
    "sg:address":"2900 Vassar St",
    "sg:city":"Reno",
    "sg:classifiers":[
        {
            "category":"Building & Trades",
            "subcategory":"Construction",
            "type":"Services"
        }
    ],
    "sg:phone":"+1 775 786 1950",
    "sg:postcode":"89502",
    "sg:province":"NV",
    "sg:tags":[
        "resurfacing",
        "laying",
        "refinishing",
        "floor"
    ],
    "wof:name":"Spangler Floor Coverings",
    "wof:placetype":"venue"
},
  "geometry": {"coordinates":[-119.7747,39.512982],"type":"Point"}
}