{
  "type": "Feature",
  "properties": {
    "iso:country":"US",
    "sg:address":"1616 E Lake Mead Boulevard",
    "sg:city":"North Las Vegas",
    "sg:classifiers":[
        {
            "category":"Restaurant",
            "type":"Food & Drink"
        }
    ],
    "sg:phone":"+1 702 649 6915",
    "sg:postcode":"89030",
    "sg:province":"NV",
    "sg:website":"www.wendys.com",
    "wof:name":"Wendy's Old Fashioned Hamburgers",
    "wof:placetype":"venue"
},
  "geometry": {"coordinates":[-115.12191,36.195773],"type":"Point"}
}