{
  "type": "Feature",
  "properties": {
    "iso:country":"US",
    "sg:address":"197 N Pecos Road",
    "sg:city":"Henderson",
    "sg:classifiers":[
        {
            "category":"Retail",
            "subcategory":"Laundry & Dry Cleaning",
            "type":"Services"
        }
    ],
    "sg:phone":"+1 702 361 1065",
    "sg:postcode":"89074",
    "sg:province":"NV",
    "wof:name":"Al Phillips the Cleaner",
    "wof:placetype":"venue"
},
  "geometry": {"coordinates":[-115.100472,36.041186],"type":"Point"}
}