{
  "type": "Feature",
  "properties": {
    "iso:country":"US",
    "sg:address":"1381 W Sunset Rd",
    "sg:city":"Henderson",
    "sg:classifiers":[
        {
            "category":"Personal",
            "subcategory":"Beauty Salon",
            "type":"Services"
        }
    ],
    "sg:phone":"+1 702 580 5559",
    "sg:postcode":"89014",
    "sg:province":"NV",
    "sg:tags":[
        "hair"
    ],
    "sg:website":"hairextensionsvegas.com",
    "wof:name":"Great Lengths Hair Extensions",
    "wof:placetype":"venue"
},
  "geometry": {"coordinates":[-115.045103,36.063497],"type":"Point"}
}