{
  "type": "Feature",
  "properties": {
    "iso:country":"US",
    "sg:address":"350 Salomon Cir",
    "sg:city":"Sparks",
    "sg:classifiers":[
        {
            "category":"Manufacturing",
            "subcategory":"Tools & Machinery",
            "type":"Manufacturing & Wholesale Goods"
        }
    ],
    "sg:phone":"+1 775 356 2796",
    "sg:postcode":"89434",
    "sg:province":"NV",
    "sg:tags":[
        "equipment",
        "pump",
        "mfg"
    ],
    "sg:website":"www.ebaracryo.com",
    "wof:name":"Ebara International Corp",
    "wof:placetype":"venue"
},
  "geometry": {"coordinates":[-119.700986,39.532317],"type":"Point"}
}