{
  "type": "Feature",
  "properties": {
    "iso:country":"US",
    "sg:address":"2850 Plumas St",
    "sg:city":"Reno",
    "sg:classifiers":[
        {
            "category":"Real Estate",
            "subcategory":"Real Estate Operator",
            "type":"Services"
        }
    ],
    "sg:phone":"+1 775 826 8218",
    "sg:postcode":"89509",
    "sg:province":"NV",
    "sg:tags":[
        "building",
        "property",
        "apartment",
        "lessor"
    ],
    "wof:name":"Plumas Garden Apartments",
    "wof:placetype":"venue"
},
  "geometry": {"coordinates":[-119.812496,39.495919],"type":"Point"}
}