{
  "type": "Feature",
  "properties": {
    "iso:country":"US",
    "sg:address":"1522 5th St",
    "sg:city":"Boulder City",
    "sg:classifiers":[
        {
            "category":"Professional",
            "subcategory":"Testing Lab",
            "type":"Services"
        }
    ],
    "sg:phone":"+1 702 293 5709",
    "sg:postcode":"89005",
    "sg:province":"NV",
    "sg:tags":[
        "laboratory"
    ],
    "wof:name":"Pelle Environmental Services",
    "wof:placetype":"venue"
},
  "geometry": {"coordinates":[-114.839453,35.973775],"type":"Point"}
}