{
  "type": "Feature",
  "properties": {
    "iso:country":"US",
    "sg:address":"1700 Western Ave Ste A",
    "sg:city":"Las Vegas",
    "sg:classifiers":[
        {
            "category":"Personal",
            "subcategory":"Nail Salon",
            "type":"Services"
        }
    ],
    "sg:phone":"+1 702 444 9688",
    "sg:postcode":"89102",
    "sg:province":"NV",
    "wof:name":"Mo' Nae Nail Spa",
    "wof:placetype":"venue"
},
  "geometry": {"coordinates":[-115.162923,36.151404],"type":"Point"}
}