{
  "type": "Feature",
  "properties": {
    "iso:country":"US",
    "sg:address":"1 Aultman St",
    "sg:city":"Ely",
    "sg:classifiers":[
        {
            "category":"Professional",
            "subcategory":"Accounting & Tax Preparation",
            "type":"Services"
        }
    ],
    "sg:phone":"+1 775 289 2774",
    "sg:postcode":"89301",
    "sg:province":"NV",
    "sg:tags":[
        "return",
        "filing"
    ],
    "wof:name":"Elite Tax Svc",
    "wof:placetype":"venue"
},
  "geometry": {"coordinates":[-114.897794,39.247312],"type":"Point"}
}