{
  "type": "Feature",
  "properties": {
    "iso:country":"US",
    "sg:address":"491 Blakeland Dr",
    "sg:city":"Spring Creek",
    "sg:classifiers":[
        {
            "category":"Personal",
            "subcategory":"Beauty Salon",
            "type":"Services"
        }
    ],
    "sg:phone":"+1 775 753 9386",
    "sg:postcode":"89815",
    "sg:province":"NV",
    "wof:name":"Wenderella's",
    "wof:placetype":"venue"
},
  "geometry": {"coordinates":[-115.604016,40.729519],"type":"Point"}
}