{
  "type": "Feature",
  "properties": {
    "iso:country":"US",
    "sg:address":"5160 S Eastern Ave",
    "sg:city":"Las Vegas",
    "sg:classifiers":[
        {
            "category":"Professional",
            "subcategory":"Engineering",
            "type":"Services"
        }
    ],
    "sg:phone":"+1 702 739 7211",
    "sg:postcode":"89119",
    "sg:province":"NV",
    "sg:tags":[
        "engineer"
    ],
    "wof:name":"EMS Engineering",
    "wof:placetype":"venue"
},
  "geometry": {"coordinates":[-115.118831,36.095114],"type":"Point"}
}