{
  "type": "Feature",
  "properties": {
    "iso:country":"US",
    "sg:address":"3900 Las Vegas Blvd S",
    "sg:city":"Las Vegas",
    "sg:classifiers":[
        {
            "category":"Ice Cream",
            "type":"Food & Drink"
        }
    ],
    "sg:phone":"+1 702 597 5330",
    "sg:postcode":"89119",
    "sg:province":"NV",
    "sg:tags":[
        "frozen",
        "yogurt"
    ],
    "wof:name":"Pyramid Ice Cream Inc",
    "wof:placetype":"venue"
},
  "geometry": {"coordinates":[-115.172997,36.095402],"type":"Point"}
}