{
  "type": "Feature",
  "properties": {
    "iso:country":"US",
    "sg:address":"2235 E Cheyenne Ave",
    "sg:city":"North Las Vegas",
    "sg:classifiers":[
        {
            "category":"Shopping",
            "subcategory":"Music",
            "type":"Retail Goods"
        }
    ],
    "sg:phone":"+1 702 657 0090",
    "sg:postcode":"89030",
    "sg:province":"NV",
    "sg:tags":[
        "dvd's"
    ],
    "wof:name":"Disco El Huarachazo",
    "wof:placetype":"venue"
},
  "geometry": {"coordinates":[-115.117099,36.217554],"type":"Point"}
}