{
  "type": "Feature",
  "properties": {
    "iso:country":"US",
    "sg:address":"143 S Maine St",
    "sg:city":"Fallon",
    "sg:classifiers":[
        {
            "category":"Bars & Pubs",
            "type":"Food & Drink"
        }
    ],
    "sg:phone":"+1 775 423 1787",
    "sg:postcode":"89406",
    "sg:province":"NV",
    "wof:name":"Frog Daddy Sportsbar",
    "wof:placetype":"venue"
},
  "geometry": {"coordinates":[-118.776978,39.473553],"type":"Point"}
}