{
  "type": "Feature",
  "properties": {
    "iso:country":"US",
    "sg:address":"1075 Taylor Pl",
    "sg:city":"Fallon",
    "sg:classifiers":[
        {
            "category":"Wholesale",
            "subcategory":"Vending Machines",
            "type":"Manufacturing & Wholesale Goods"
        }
    ],
    "sg:phone":"+1 775 423 5000",
    "sg:postcode":"89406",
    "sg:province":"NV",
    "wof:name":"Pepsi-Cola Co",
    "wof:placetype":"venue"
},
  "geometry": {"coordinates":[-118.805059,39.472767],"type":"Point"}
}