{
  "type": "Feature",
  "properties": {
    "iso:country":"US",
    "sg:address":"417 W Plumb Ln",
    "sg:city":"Reno",
    "sg:classifiers":[
        {
            "category":"Real Estate",
            "subcategory":"Real Estate Operator",
            "type":"Services"
        }
    ],
    "sg:phone":"+1 775 851 7668",
    "sg:postcode":"89509",
    "sg:province":"NV",
    "sg:tags":[
        "building",
        "nonresidential"
    ],
    "wof:name":"Preston Properties Inc",
    "wof:placetype":"venue"
},
  "geometry": {"coordinates":[-119.810951,39.505796],"type":"Point"}
}