{
  "type": "Feature",
  "properties": {
    "iso:country":"US",
    "sg:address":"2680 W Lake Ridge Shores",
    "sg:city":"Reno",
    "sg:classifiers":[
        {
            "category":"Wholesale",
            "subcategory":"Computers",
            "type":"Manufacturing & Wholesale Goods"
        }
    ],
    "sg:phone":"+1 775 852 1178",
    "sg:postcode":"89509",
    "sg:province":"NV",
    "wof:name":"PC Wholesalers",
    "wof:placetype":"venue"
},
  "geometry": {"coordinates":[-119.824883,39.476177],"type":"Point"}
}