{
  "type": "Feature",
  "properties": {
    "iso:country":"US",
    "sg:address":"7000 Leon Ave",
    "sg:city":"Las Vegas",
    "sg:classifiers":[
        {
            "category":"Shopping",
            "subcategory":"Computers & Home Electronics",
            "type":"Retail Goods"
        }
    ],
    "sg:phone":"+1 702 655 8176",
    "sg:postcode":"89131",
    "sg:province":"NV",
    "sg:tags":[
        "software"
    ],
    "wof:name":"Dollars & Cents LLC",
    "wof:placetype":"venue"
},
  "geometry": {"coordinates":[-115.219852,36.288838],"type":"Point"}
}