{
  "type": "Feature",
  "properties": {
    "iso:country":"US",
    "sg:address":"2385 E Prater Way",
    "sg:city":"Sparks",
    "sg:classifiers":[
        {
            "category":"Health Services",
            "subcategory":"Doctor",
            "type":"Services"
        }
    ],
    "sg:phone":"+1 775 331 6400",
    "sg:postcode":"89434",
    "sg:province":"NV",
    "sg:tags":[
        "physician",
        "surgeon"
    ],
    "wof:name":"Triangle Family Medicine",
    "wof:placetype":"venue"
},
  "geometry": {"coordinates":[-119.697536,39.542429],"type":"Point"}
}