{
  "type": "Feature",
  "properties": {
    "iso:country":"US",
    "sg:address":"450 S Buffalo Dr",
    "sg:city":"Las Vegas",
    "sg:classifiers":[
        {
            "category":"Insurance",
            "subcategory":"Insurance Agent",
            "type":"Services"
        }
    ],
    "sg:phone":"+1 702 562 0125",
    "sg:postcode":"89145",
    "sg:province":"NV",
    "wof:name":"Allstate",
    "wof:placetype":"venue"
},
  "geometry": {"coordinates":[-115.259865,36.167236],"type":"Point"}
}