{
  "type": "Feature",
  "properties": {
    "iso:country":"US",
    "sg:address":"3590 Hemlock Way",
    "sg:city":"Reno",
    "sg:classifiers":[
        {
            "category":"Professional",
            "subcategory":"Computer Services",
            "type":"Services"
        }
    ],
    "sg:phone":"+1 775 827 2708",
    "sg:postcode":"89509",
    "sg:province":"NV",
    "sg:tags":[
        "related"
    ],
    "wof:name":"Fritz Roske",
    "wof:placetype":"venue"
},
  "geometry": {"coordinates":[-119.84618500000001,39.482338],"type":"Point"}
}