{
  "type": "Feature",
  "properties": {
    "iso:country":"US",
    "sg:address":"8170 W Sahara Ave Ste 202",
    "sg:city":"Las Vegas",
    "sg:classifiers":[
        {
            "category":"Professional",
            "subcategory":"Accounting & Tax Preparation",
            "type":"Services"
        }
    ],
    "sg:phone":"+1 702 362 1345",
    "sg:postcode":"89117",
    "sg:province":"NV",
    "sg:tags":[
        "accountant"
    ],
    "wof:name":"Nancy A Romanowski CPA",
    "wof:placetype":"venue"
},
  "geometry": {"coordinates":[-115.269997,36.143902],"type":"Point"}
}