{
  "type": "Feature",
  "properties": {
    "iso:country":"US",
    "sg:address":"1907 Western Ave",
    "sg:city":"Las Vegas",
    "sg:classifiers":[
        {
            "category":"Wholesale",
            "subcategory":"Groceries",
            "type":"Manufacturing & Wholesale Goods"
        }
    ],
    "sg:phone":"+1 702 384 3803",
    "sg:postcode":"89102",
    "sg:province":"NV",
    "sg:tags":[
        "baker"
    ],
    "wof:name":"Chef's Delite Bakery",
    "wof:placetype":"venue"
},
  "geometry": {"coordinates":[-115.164525,36.148599],"type":"Point"}
}