{
  "type": "Feature",
  "properties": {
    "iso:country":"US",
    "sg:address":"2650 S Decatur Blvd",
    "sg:city":"Las Vegas",
    "sg:classifiers":[
        {
            "category":"Shopping",
            "type":"Retail Goods"
        }
    ],
    "sg:phone":"+1 702 253 5505",
    "sg:postcode":"89102",
    "sg:province":"NV",
    "sg:tags":[
        "cosmetic",
        "perfume"
    ],
    "wof:name":"Brother's Beauty Supply",
    "wof:placetype":"venue"
},
  "geometry": {"coordinates":[-115.208051,36.143633],"type":"Point"}
}