{
  "type": "Feature",
  "properties": {
    "iso:country":"US",
    "sg:address":"1700 N Buffalo Drive",
    "sg:city":"Las Vegas",
    "sg:classifiers":[
        {
            "category":"Health Services",
            "subcategory":"Optometrist",
            "type":"Services"
        }
    ],
    "sg:phone":"+1 702 643 2020",
    "sg:postcode":"89128",
    "sg:province":"NV",
    "wof:name":"Ohriner Harvey OD Ltd",
    "wof:placetype":"venue"
},
  "geometry": {"coordinates":[-115.259991,36.189909],"type":"Point"}
}