{
  "type": "Feature",
  "properties": {
    "iso:country":"US",
    "sg:address":"6711 Las Vegas Blvd S",
    "sg:city":"Las Vegas",
    "sg:classifiers":[
        {
            "category":"Travel",
            "subcategory":"Hotels & Motels",
            "type":"Entertainment"
        }
    ],
    "sg:phone":"+1 702 361 2111",
    "sg:postcode":"89119",
    "sg:province":"NV",
    "wof:name":"Vacation Village",
    "wof:placetype":"venue"
},
  "geometry": {"coordinates":[-115.1723,36.067715],"type":"Point"}
}