{
  "type": "Feature",
  "properties": {
    "iso:country":"US",
    "sg:address":"4700 Losee Rd",
    "sg:city":"North Las Vegas",
    "sg:classifiers":[
        {
            "category":"Manufacturing",
            "subcategory":"Rubber & Plastics",
            "type":"Manufacturing & Wholesale Goods"
        }
    ],
    "sg:phone":"+1 702 643 2644",
    "sg:postcode":"89030",
    "sg:province":"NV",
    "sg:tags":[
        "blow",
        "product",
        "rotational",
        "molded",
        "mfg",
        "finished"
    ],
    "wof:name":"Rotocast",
    "wof:placetype":"venue"
},
  "geometry": {"coordinates":[-115.116771,36.243616],"type":"Point"}
}