{
  "type": "Feature",
  "properties": {
    "iso:country":"US",
    "sg:address":"1381 W Sunset Rd",
    "sg:city":"Las Vegas",
    "sg:classifiers":[
        {
            "category":"Restaurant",
            "type":"Food & Drink"
        }
    ],
    "sg:phone":"+1 702 454 5656",
    "sg:postcode":"89119",
    "sg:province":"NV",
    "wof:name":"Jersey Mike's Submarines",
    "wof:placetype":"venue"
},
  "geometry": {"coordinates":[-115.17579,36.070994],"type":"Point"}
}