{
  "type": "Feature",
  "properties": {
    "iso:country":"US",
    "sg:address":"4665 Alder Dr",
    "sg:city":"Reno",
    "sg:classifiers":[
        {
            "category":"Building & Trades",
            "subcategory":"Construction",
            "type":"Services"
        }
    ],
    "sg:phone":"+1 775 329 3939",
    "sg:postcode":"89502",
    "sg:province":"NV",
    "sg:tags":[
        "floor",
        "laying",
        "contractor"
    ],
    "wof:name":"Reno Hardwood Flooring",
    "wof:placetype":"venue"
},
  "geometry": {"coordinates":[-119.775577,39.481158],"type":"Point"}
}