{
  "type": "Feature",
  "properties": {
    "iso:country":"US",
    "sg:address":"919 Shriver Blvd",
    "sg:city":"Sparks",
    "sg:classifiers":[
        {
            "category":"Home & Garden",
            "subcategory":"Building Materials",
            "type":"Retail Goods"
        }
    ],
    "sg:phone":"+1 775 856 5404",
    "sg:postcode":"89431",
    "sg:province":"NV",
    "sg:tags":[
        "door"
    ],
    "wof:name":"Sierra Automatic Garage Doors",
    "wof:placetype":"venue"
},
  "geometry": {"coordinates":[-119.745645,39.543652],"type":"Point"}
}