{
  "type": "Feature",
  "properties": {
    "iso:country":"US",
    "sg:address":"4555 Procyon St",
    "sg:city":"Las Vegas",
    "sg:classifiers":[
        {
            "category":"Manufacturing",
            "subcategory":"Furniture",
            "type":"Manufacturing & Wholesale Goods"
        }
    ],
    "sg:phone":"+1 702 796 7272",
    "sg:postcode":"89103",
    "sg:province":"NV",
    "sg:tags":[
        "mfg",
        "wood",
        "furn"
    ],
    "sg:website":"www.pacific-showcase.com",
    "wof:name":"Pacific Showcase",
    "wof:placetype":"venue"
},
  "geometry": {"coordinates":[-115.187772,36.104997],"type":"Point"}
}