{
  "type": "Feature",
  "properties": {
    "iso:country":"US",
    "sg:address":"3555 Indian Ln",
    "sg:city":"Reno",
    "sg:classifiers":[
        {
            "category":"Building & Trades",
            "subcategory":"Construction",
            "type":"Services"
        }
    ],
    "sg:phone":"+1 775 786 3550",
    "sg:postcode":"89506",
    "sg:province":"NV",
    "sg:tags":[
        "roofing",
        "contractor"
    ],
    "wof:name":"G M Flynn",
    "wof:placetype":"venue"
},
  "geometry": {"coordinates":[-119.811163,39.614706],"type":"Point"}
}