{
  "type": "Feature",
  "properties": {
    "iso:country":"US",
    "sg:address":"2015 S Hualapai Way",
    "sg:city":"Las Vegas",
    "sg:classifiers":[
        {
            "category":"Education",
            "subcategory":"School",
            "type":"Public Place"
        }
    ],
    "sg:phone":"+1 702 804 4400",
    "sg:postcode":"89117",
    "sg:province":"NV",
    "sg:tags":[
        "elementary"
    ],
    "sg:website":"www.faithlutheranlv.org",
    "wof:name":"Faith Lutheran Jr-Sr High School",
    "wof:placetype":"venue"
},
  "geometry": {"coordinates":[-115.31500200000001,36.1488],"type":"Point"}
}