{
  "type": "Feature",
  "properties": {
    "iso:country":"US",
    "sg:address":"400 Key West Ct",
    "sg:city":"Boulder City",
    "sg:classifiers":[
        {
            "category":"Wholesale",
            "subcategory":"Durable Goods & Equipment",
            "type":"Manufacturing & Wholesale Goods"
        }
    ],
    "sg:phone":"+1 702 294 3159",
    "sg:postcode":"89005",
    "sg:province":"NV",
    "sg:tags":[
        "laser"
    ],
    "sg:website":"www.divprod.com",
    "wof:name":"Nevada Products",
    "wof:placetype":"venue"
},
  "geometry": {"coordinates":[-114.833207,35.995381],"type":"Point"}
}