{
  "type": "Feature",
  "properties": {
    "iso:country":"US",
    "sg:address":"6336 Pedro Pl",
    "sg:city":"Las Vegas",
    "sg:classifiers":[
        {
            "category":"Professional",
            "subcategory":"Accounting & Tax Preparation",
            "type":"Services"
        }
    ],
    "sg:phone":"+1 702 645 5206",
    "sg:postcode":"89108",
    "sg:province":"NV",
    "sg:tags":[
        "medical",
        "billing"
    ],
    "wof:name":"Medical Billing Specialists",
    "wof:placetype":"venue"
},
  "geometry": {"coordinates":[-115.232218,36.205332],"type":"Point"}
}