{
  "type": "Feature",
  "properties": {
    "iso:country":"US",
    "sg:address":"485 E Main St",
    "sg:city":"Fernley",
    "sg:classifiers":[
        {
            "category":"Organizations",
            "subcategory":"Religious Organization",
            "type":"Services"
        }
    ],
    "sg:phone":"+1 775 575 4565",
    "sg:postcode":"89408",
    "sg:province":"NV",
    "wof:name":"First Baptist Church",
    "wof:placetype":"venue"
},
  "geometry": {"coordinates":[-119.240847,39.606847],"type":"Point"}
}