{
  "type": "Feature",
  "properties": {
    "iso:country":"US",
    "sg:address":"9000 S Eastern Ave",
    "sg:city":"Las Vegas",
    "sg:classifiers":[
        {
            "category":"Home & Garden",
            "subcategory":"Home Furnishings",
            "type":"Retail Goods"
        }
    ],
    "sg:phone":"+1 702 270 0727",
    "sg:postcode":"89123",
    "sg:province":"NV",
    "sg:tags":[
        "window",
        "covering"
    ],
    "wof:name":"Malibu Window Coverings",
    "wof:placetype":"venue"
},
  "geometry": {"coordinates":[-115.118387,36.027026],"type":"Point"}
}