{
  "type": "Feature",
  "properties": {
    "iso:country":"US",
    "sg:address":"1243 E Sahara Ave",
    "sg:city":"Las Vegas",
    "sg:classifiers":[
        {
            "category":"Restaurant",
            "type":"Food & Drink"
        }
    ],
    "sg:phone":"+1 702 369 1556",
    "sg:postcode":"89104",
    "sg:province":"NV",
    "wof:name":"Euro Place Ristorante",
    "wof:placetype":"venue"
},
  "geometry": {"coordinates":[-115.13571399999999,36.144183],"type":"Point"}
}