{
  "type": "Feature",
  "properties": {
    "iso:country":"US",
    "sg:address":"1301 N Rainbow Blvd",
    "sg:city":"Las Vegas",
    "sg:classifiers":[
        {
            "category":"Real Estate",
            "subcategory":"Real Estate Agent",
            "type":"Services"
        }
    ],
    "sg:phone":"+1 702 312 7775",
    "sg:postcode":"89108",
    "sg:province":"NV",
    "wof:name":"Thoroughbred Group",
    "wof:placetype":"venue"
},
  "geometry": {"coordinates":[-115.242351,36.185507],"type":"Point"}
}