{
  "type": "Feature",
  "properties": {
    "iso:country":"US",
    "sg:address":"3645 W Oquendo Rd",
    "sg:city":"Las Vegas",
    "sg:classifiers":[
        {
            "category":"Manufacturing",
            "subcategory":"Metals",
            "type":"Manufacturing & Wholesale Goods"
        }
    ],
    "sg:phone":"+1 702 222 0415",
    "sg:postcode":"89118",
    "sg:province":"NV",
    "sg:tags":[
        "mfg",
        "commercial",
        "representative",
        "municipal",
        "mechanical"
    ],
    "wof:name":"Engineered Eqp & Systems Co",
    "wof:placetype":"venue"
},
  "geometry": {"coordinates":[-115.189438,36.082595],"type":"Point"}
}