{
  "type": "Feature",
  "properties": {
    "iso:country":"US",
    "sg:address":"1280 Terminal Way",
    "sg:city":"Reno",
    "sg:classifiers":[
        {
            "category":"Shopping",
            "type":"Retail Goods"
        }
    ],
    "sg:phone":"+1 775 746 5184",
    "sg:postcode":"89502",
    "sg:province":"NV",
    "sg:tags":[
        "art",
        "gallery",
        "dealer"
    ],
    "wof:name":"Oasis Art",
    "wof:placetype":"venue"
},
  "geometry": {"coordinates":[-119.777367,39.51147],"type":"Point"}
}