{
  "type": "Feature",
  "properties": {
    "iso:country":"US",
    "sg:address":"3377 Las Vegas Blvd S 2275",
    "sg:city":"Las Vegas",
    "sg:classifiers":[
        {
            "category":"Arts & Performance",
            "subcategory":"Art Gallery",
            "type":"Entertainment"
        }
    ],
    "sg:phone":"+1 702 866 6813",
    "sg:postcode":"89109",
    "sg:province":"NV",
    "sg:website":"www.jackgallery.com",
    "wof:name":"Jack Gallery",
    "wof:placetype":"venue"
},
  "geometry": {"coordinates":[-115.17135,36.121244],"type":"Point"}
}