{
  "type": "Feature",
  "properties": {
    "iso:country":"US",
    "sg:address":"2058 Rawhide Village Ct",
    "sg:city":"Henderson",
    "sg:classifiers":[
        {
            "category":"Real Estate",
            "subcategory":"Architect",
            "type":"Services"
        }
    ],
    "sg:phone":"+1 702 617 4707",
    "sg:postcode":"89012",
    "sg:province":"NV",
    "sg:tags":[
        "architectural"
    ],
    "wof:name":"Spirit Consulting",
    "wof:placetype":"venue"
},
  "geometry": {"coordinates":[-115.072656,36.019593],"type":"Point"}
}