{
  "type": "Feature",
  "properties": {
    "iso:country":"US",
    "sg:address":"909 Walnut Dr",
    "sg:city":"Boulder City",
    "sg:classifiers":[
        {
            "category":"Autos & Motor Vehicles",
            "subcategory":"Boat Sales",
            "type":"Retail Goods"
        }
    ],
    "sg:phone":"+1 702 293 6773",
    "sg:postcode":"89005",
    "sg:province":"NV",
    "sg:tags":[
        "equipment",
        "marine",
        "supply"
    ],
    "wof:name":"Skull Marine Performance Engns",
    "wof:placetype":"venue"
},
  "geometry": {"coordinates":[-114.846367,35.968464],"type":"Point"}
}