{
  "type": "Feature",
  "properties": {
    "iso:country":"US",
    "sg:address":"770 E Warm Springs Road",
    "sg:city":"Las Vegas",
    "sg:classifiers":[
        {
            "category":"Health Services",
            "subcategory":"Dentist",
            "type":"Services"
        }
    ],
    "sg:phone":"+1 702 837 8977",
    "sg:postcode":"89119",
    "sg:province":"NV",
    "sg:website":"www.flexyoursmile.com",
    "wof:name":"Advanced Center For Implant and Cosmetic Dentistry",
    "wof:placetype":"venue"
},
  "geometry": {"coordinates":[-115.145911,36.057187],"type":"Point"}
}