{
  "type": "Feature",
  "properties": {
    "iso:country":"US",
    "sg:address":"418 Flint St",
    "sg:city":"Reno",
    "sg:classifiers":[
        {
            "category":"Professional",
            "subcategory":"Research",
            "type":"Services"
        }
    ],
    "sg:phone":"+1 775 323 0373",
    "sg:postcode":"89501",
    "sg:province":"NV",
    "sg:tags":[
        "foundation",
        "philanthropic"
    ],
    "wof:name":"E L Cord Foundation",
    "wof:placetype":"venue"
},
  "geometry": {"coordinates":[-119.814733,39.520277],"type":"Point"}
}