{
  "type": "Feature",
  "properties": {
    "iso:country":"US",
    "sg:address":"971 Topsy Ln #332",
    "sg:city":"Carson City",
    "sg:classifiers":[
        {
            "category":"Home & Garden",
            "subcategory":"Carpets & Floor Coverings",
            "type":"Retail Goods"
        }
    ],
    "sg:phone":"+1 775 267 0434",
    "sg:postcode":"89711",
    "sg:province":"NV",
    "sg:tags":[
        "mattress"
    ],
    "sg:website":"www.mattressdiscounters.com",
    "wof:name":"Mattress Discounters",
    "wof:placetype":"venue"
},
  "geometry": {"coordinates":[-119.77117,39.110351],"type":"Point"}
}