{
  "type": "Feature",
  "properties": {
    "iso:country":"US",
    "sg:address":"282 E Lake Mead Pkwy",
    "sg:city":"Henderson",
    "sg:classifiers":[
        {
            "category":"Health Services",
            "subcategory":"Doctor",
            "type":"Services"
        }
    ],
    "sg:phone":"+1 702 567 9002",
    "sg:postcode":"89015",
    "sg:province":"NV",
    "sg:tags":[
        "practice",
        "family"
    ],
    "wof:name":"Henderson Family Medical",
    "wof:placetype":"venue"
},
  "geometry": {"coordinates":[-114.977018,36.043256],"type":"Point"}
}