{
  "type": "Feature",
  "properties": {
    "iso:country":"US",
    "sg:address":"1875 E Sahara Ave",
    "sg:city":"Las Vegas",
    "sg:classifiers":[
        {
            "category":"Social Services",
            "type":"Services"
        }
    ],
    "sg:phone":"+1 702 894 5200",
    "sg:postcode":"89104",
    "sg:province":"NV",
    "sg:tags":[
        "organization",
        "welfare"
    ],
    "wof:name":"A Advantage Auto Donor",
    "wof:placetype":"venue"
},
  "geometry": {"coordinates":[-115.124724,36.144418],"type":"Point"}
}