{
  "type": "Feature",
  "properties": {
    "iso:country":"US",
    "sg:address":"9230 Azure Dr",
    "sg:city":"Las Vegas",
    "sg:classifiers":[
        {
            "category":"Social Services",
            "subcategory":"Child Care",
            "type":"Services"
        }
    ],
    "sg:phone":"+1 702 876 8124",
    "sg:postcode":"89149",
    "sg:province":"NV",
    "sg:tags":[
        "day"
    ],
    "wof:name":"Centennial Child Care",
    "wof:placetype":"venue"
},
  "geometry": {"coordinates":[-115.297304,36.273687],"type":"Point"}
}