{
  "type": "Feature",
  "properties": {
    "iso:country":"US",
    "sg:address":"1350 Davidson Way",
    "sg:city":"Reno",
    "sg:classifiers":[
        {
            "category":"Professional",
            "subcategory":"Research",
            "type":"Services"
        }
    ],
    "sg:phone":"+1 775 323 1972",
    "sg:postcode":"89509",
    "sg:province":"NV",
    "sg:tags":[
        "consulting",
        "commercial",
        "business",
        "physical"
    ],
    "wof:name":"ISEE Electronics",
    "wof:placetype":"venue"
},
  "geometry": {"coordinates":[-119.83871600000001,39.507208],"type":"Point"}
}