{
  "type": "Feature",
  "properties": {
    "iso:country":"US",
    "sg:address":"1005 Terminal Way",
    "sg:city":"Reno",
    "sg:classifiers":[
        {
            "category":"Professional",
            "subcategory":"Lawyer & Legal Services",
            "type":"Services"
        }
    ],
    "sg:phone":"+1 775 324 7676",
    "sg:postcode":"89502",
    "sg:province":"NV",
    "sg:tags":[
        "company",
        "incorporating"
    ],
    "sg:website":"www.nevcorp.com",
    "wof:name":"Corporate Office Svc",
    "wof:placetype":"venue"
},
  "geometry": {"coordinates":[-119.777355,39.514625],"type":"Point"}
}