{
  "type": "Feature",
  "properties": {
    "iso:country":"US",
    "sg:address":"684 Fernwood Lane",
    "sg:city":"Las Vegas",
    "sg:classifiers":[
        {
            "category":"Education",
            "subcategory":"School",
            "type":"Public Place"
        }
    ],
    "sg:phone":"+1 702 650 3600",
    "sg:postcode":"89169",
    "sg:province":"NV",
    "wof:name":"Academy For Career Enhancement",
    "wof:placetype":"venue"
},
  "geometry": {"coordinates":[-115.148731,36.125401],"type":"Point"}
}