{
  "type": "Feature",
  "properties": {
    "iso:country":"US",
    "sg:address":"820 Rancho Ln",
    "sg:city":"Las Vegas",
    "sg:classifiers":[
        {
            "category":"Personal",
            "type":"Services"
        }
    ],
    "sg:phone":"+1 702 321 4034",
    "sg:postcode":"89106",
    "sg:province":"NV",
    "sg:tags":[
        "therapist",
        "massage"
    ],
    "wof:name":"A Touch Pro-Eduardo Rochin",
    "wof:placetype":"venue"
},
  "geometry": {"coordinates":[-115.171649,36.160514],"type":"Point"}
}