{
  "type": "Feature",
  "properties": {
    "iso:country":"US",
    "sg:address":"1770 US Hwy 395 N",
    "sg:city":"Minden",
    "sg:classifiers":[
        {
            "category":"Home & Garden",
            "subcategory":"Household Appliances",
            "type":"Retail Goods"
        }
    ],
    "sg:phone":"+1 775 782 5099",
    "sg:postcode":"89423",
    "sg:province":"NV",
    "wof:name":"Marty's Appliance",
    "wof:placetype":"venue"
},
  "geometry": {"coordinates":[-119.779158,38.969171],"type":"Point"}
}