{
  "type": "Feature",
  "properties": {
    "iso:country":"US",
    "sg:address":"2024 Trailside Village Ave",
    "sg:city":"Henderson",
    "sg:classifiers":[
        {
            "category":"Building & Trades",
            "subcategory":"Pest Control",
            "type":"Services"
        }
    ],
    "sg:phone":"+1 702 434 6547",
    "sg:postcode":"89012",
    "sg:province":"NV",
    "sg:tags":[
        "mothproofing"
    ],
    "wof:name":"City Wide Services",
    "wof:placetype":"venue"
},
  "geometry": {"coordinates":[-115.07495299999999,36.01901],"type":"Point"}
}