{
  "type": "Feature",
  "properties": {
    "iso:country":"US",
    "sg:address":"1321 W Craig Rd",
    "sg:city":"Las Vegas",
    "sg:classifiers":[
        {
            "category":"Shopping",
            "subcategory":"Pets & Pet Supplies",
            "type":"Retail Goods"
        }
    ],
    "sg:phone":"+1 702 938 5880",
    "sg:postcode":"89132",
    "sg:province":"NV",
    "sg:tags":[
        "training"
    ],
    "wof:name":"Petsmart",
    "wof:placetype":"venue"
},
  "geometry": {"coordinates":[-115.146004,36.0998],"type":"Point"}
}