{
  "type": "Feature",
  "properties": {
    "iso:country":"US",
    "sg:address":"8732 Big Sagebrush Avenue",
    "sg:city":"Las Vegas",
    "sg:classifiers":[
        {
            "category":"Building & Trades",
            "subcategory":"Construction",
            "type":"Services"
        }
    ],
    "sg:phone":"+1 702 363 0482",
    "sg:postcode":"89117",
    "sg:province":"NV",
    "sg:tags":[
        "contractor"
    ],
    "sg:website":"www.kbhome.com",
    "wof:name":"Kb Home Sales Offices",
    "wof:placetype":"venue"
},
  "geometry": {"coordinates":[-115.285279,36.127291],"type":"Point"}
}