{
  "type": "Feature",
  "properties": {
    "iso:country":"US",
    "sg:address":"6375 S Pecos Rd",
    "sg:city":"Las Vegas",
    "sg:classifiers":[
        {
            "category":"Professional",
            "subcategory":"Lawyer & Legal Services",
            "type":"Services"
        }
    ],
    "sg:phone":"+1 702 898 9540",
    "sg:postcode":"89120",
    "sg:province":"NV",
    "sg:tags":[
        "attorney"
    ],
    "sg:website":"www.jeglaw.com",
    "wof:name":"Joh Eric Garde Law Office",
    "wof:placetype":"venue"
},
  "geometry": {"coordinates":[-115.10091799999999,36.072687],"type":"Point"}
}