{
  "type": "Feature",
  "properties": {
    "iso:country":"US",
    "sg:address":"4600 Vegas Dr Ofc",
    "sg:city":"Las Vegas",
    "sg:classifiers":[
        {
            "category":"Real Estate",
            "subcategory":"Real Estate Operator",
            "type":"Services"
        }
    ],
    "sg:phone":"+1 702 648 1157",
    "sg:postcode":"89108",
    "sg:province":"NV",
    "sg:tags":[
        "apartment"
    ],
    "wof:name":"Spring Woods Apartments",
    "wof:placetype":"venue"
},
  "geometry": {"coordinates":[-115.228996,36.209301],"type":"Point"}
}