{
  "type": "Feature",
  "properties": {
    "iso:country":"US",
    "sg:address":"4363 Spencer St",
    "sg:city":"Las Vegas",
    "sg:classifiers":[
        {
            "category":"Manufacturing",
            "subcategory":"Printing",
            "type":"Manufacturing & Wholesale Goods"
        }
    ],
    "sg:phone":"+1 702 459 5441",
    "sg:postcode":"89119",
    "sg:province":"NV",
    "sg:tags":[
        "multimedia"
    ],
    "wof:name":"Worldwide Media",
    "wof:placetype":"venue"
},
  "geometry": {"coordinates":[-115.128433,36.110402],"type":"Point"}
}