{
  "type": "Feature",
  "properties": {
    "iso:country":"US",
    "sg:address":"5085 S McCarran Blvd",
    "sg:city":"Reno",
    "sg:classifiers":[
        {
            "category":"Restaurant",
            "type":"Food & Drink"
        }
    ],
    "sg:phone":"+1 775 825 2552",
    "sg:postcode":"89502",
    "sg:province":"NV",
    "sg:tags":[
        "eating"
    ],
    "wof:name":"Woo Chong",
    "wof:placetype":"venue"
},
  "geometry": {"coordinates":[-119.782846,39.477002],"type":"Point"}
}