{
  "type": "Feature",
  "properties": {
    "iso:country":"US",
    "sg:address":"4752 Lomas Santa Fe St",
    "sg:city":"Las Vegas",
    "sg:classifiers":[
        {
            "category":"Professional",
            "subcategory":"Management & Consulting",
            "type":"Services"
        }
    ],
    "sg:phone":"+1 702 497 0777",
    "sg:postcode":"89147",
    "sg:province":"NV",
    "wof:name":"IMC Consulting Inc",
    "wof:placetype":"venue"
},
  "geometry": {"coordinates":[-115.284077,36.102266],"type":"Point"}
}