{
  "type": "Feature",
  "properties": {
    "iso:country":"US",
    "sg:address":"1720 Rockcrest Dr",
    "sg:city":"Las Vegas",
    "sg:classifiers":[
        {
            "category":"Shopping",
            "subcategory":"Gifts & Souvenirs",
            "type":"Retail Goods"
        }
    ],
    "sg:phone":"+1 702 648 2149",
    "sg:postcode":"89108",
    "sg:province":"NV",
    "sg:tags":[
        "basket",
        "parcel"
    ],
    "wof:name":"A Time To Remember",
    "wof:placetype":"venue"
},
  "geometry": {"coordinates":[-115.229665,36.190164],"type":"Point"}
}