{
  "type": "Feature",
  "properties": {
    "iso:country":"US",
    "sg:address":"136 Ridge St",
    "sg:city":"Reno",
    "sg:classifiers":[
        {
            "category":"Professional",
            "subcategory":"Lawyer & Legal Services",
            "type":"Services"
        }
    ],
    "sg:phone":"+1 775 786 3750",
    "sg:postcode":"89501",
    "sg:province":"NV",
    "sg:tags":[
        "attorney"
    ],
    "wof:name":"Peter C Neumann",
    "wof:placetype":"venue"
},
  "geometry": {"coordinates":[-119.813773,39.52216],"type":"Point"}
}