{
  "type": "Feature",
  "properties": {
    "iso:country":"US",
    "sg:address":"1340 Finale Ln",
    "sg:city":"Las Vegas",
    "sg:classifiers":[
        {
            "category":"Restaurant",
            "type":"Food & Drink"
        }
    ],
    "sg:phone":"+1 702 944 7243",
    "sg:postcode":"89119",
    "sg:province":"NV",
    "sg:tags":[
        "eating"
    ],
    "wof:name":"Wild Sage Cafe",
    "wof:placetype":"venue"
},
  "geometry": {"coordinates":[-115.134711,36.064285],"type":"Point"}
}