{
  "type": "Feature",
  "properties": {
    "iso:country":"US",
    "sg:address":"3380 W Hacienda Ave",
    "sg:city":"Las Vegas",
    "sg:classifiers":[
        {
            "category":"Building & Trades",
            "subcategory":"Construction",
            "type":"Services"
        }
    ],
    "sg:phone":"+1 702 451 3415",
    "sg:postcode":"89118",
    "sg:province":"NV",
    "sg:tags":[
        "general",
        "home",
        "remodeling",
        "comm",
        "contractor"
    ],
    "wof:name":"Lewton Construction",
    "wof:placetype":"venue"
},
  "geometry": {"coordinates":[-115.18454800000001,36.093667],"type":"Point"}
}