{
  "type": "Feature",
  "properties": {
    "iso:country":"US",
    "sg:address":"7416 N Rowdy St",
    "sg:city":"Las Vegas",
    "sg:classifiers":[
        {
            "category":"Professional",
            "subcategory":"Computer Services",
            "type":"Services"
        }
    ],
    "sg:phone":"+1 702 644 5554",
    "sg:postcode":"89131",
    "sg:province":"NV",
    "sg:tags":[
        "repair"
    ],
    "wof:name":"Vegastech",
    "wof:placetype":"venue"
},
  "geometry": {"coordinates":[-115.269481,36.295855],"type":"Point"}
}