{
  "type": "Feature",
  "properties": {
    "iso:country":"US",
    "sg:address":"3365 E Flamingo Road",
    "sg:city":"Las Vegas",
    "sg:classifiers":[
        {
            "category":"Banks & Credit Unions",
            "subcategory":"Financial Services",
            "type":"Services"
        }
    ],
    "sg:phone":"+1 702 932 5400",
    "sg:postcode":"89121",
    "sg:province":"NV",
    "sg:tags":[
        "broker",
        "mortgage"
    ],
    "wof:name":"Gateway Funding Diversified Mortgage",
    "wof:placetype":"venue"
},
  "geometry": {"coordinates":[-115.10146,36.115106],"type":"Point"}
}