{
  "type": "Feature",
  "properties": {
    "iso:country":"US",
    "sg:address":"1013 Seabury Hill",
    "sg:city":"Las Vegas",
    "sg:classifiers":[
        {
            "category":"Retail",
            "subcategory":"Repair Shop",
            "type":"Services"
        }
    ],
    "sg:phone":"+1 702 242 3273",
    "sg:postcode":"89128",
    "sg:province":"NV",
    "wof:name":"Onity Inc",
    "wof:placetype":"venue"
},
  "geometry": {"coordinates":[-115.27432899999999,36.181964],"type":"Point"}
}