{
  "type": "Feature",
  "properties": {
    "iso:country":"US",
    "sg:address":"1386 Astral Ct",
    "sg:city":"Sparks",
    "sg:classifiers":[
        {
            "category":"Retail",
            "subcategory":"Repair Shop",
            "type":"Services"
        }
    ],
    "sg:phone":"+1 775 626 0992",
    "sg:postcode":"89436",
    "sg:province":"NV",
    "wof:name":"White Lightning",
    "wof:placetype":"venue"
},
  "geometry": {"coordinates":[-119.71790300000001,39.56802],"type":"Point"}
}