{
  "type": "Feature",
  "properties": {
    "iso:country":"US",
    "sg:address":"6780 N Durango Dr",
    "sg:city":"Las Vegas",
    "sg:classifiers":[
        {
            "category":"Restaurant",
            "type":"Food & Drink"
        }
    ],
    "sg:menulink":"http://www.allmenus.com/nv/las-vegas/169736-burger-king/menu/",
    "sg:phone":"+1 702 458 1835",
    "sg:postcode":"89149",
    "sg:province":"NV",
    "sg:tags":[
        "burger",
        "american"
    ],
    "wof:name":"Burger King",
    "wof:placetype":"venue"
},
  "geometry": {"coordinates":[-115.287651,36.284192],"type":"Point"}
}