{
  "type": "Feature",
  "properties": {
    "iso:country":"US",
    "sg:address":"3315 E Russell Rd",
    "sg:city":"Las Vegas",
    "sg:classifiers":[
        {
            "category":"Professional",
            "subcategory":"Business Services",
            "type":"Services"
        }
    ],
    "sg:phone":"+1 702 616 1174",
    "sg:postcode":"89120",
    "sg:province":"NV",
    "sg:tags":[
        "convention",
        "meeting",
        "facility"
    ],
    "wof:name":"Upstage Events",
    "wof:placetype":"venue"
},
  "geometry": {"coordinates":[-115.098138,36.086066],"type":"Point"}
}