{
  "type": "Feature",
  "properties": {
    "iso:country":"US",
    "sg:address":"220 Maple Dr",
    "sg:city":"Lovelock",
    "sg:classifiers":[
        {
            "category":"Organizations",
            "subcategory":"Religious Organization",
            "type":"Services"
        }
    ],
    "sg:phone":"+1 775 273 7380",
    "sg:postcode":"89419",
    "sg:province":"NV",
    "sg:tags":[
        "church"
    ],
    "wof:name":"LDS Church-Bishop's Office",
    "wof:placetype":"venue"
},
  "geometry": {"coordinates":[-118.485085,40.170448],"type":"Point"}
}