{
  "type": "Feature",
  "properties": {
    "iso:country":"US",
    "sg:address":"2006 Sierra Vista Dr",
    "sg:city":"Tonopah",
    "sg:classifiers":[
        {
            "category":"Building & Trades",
            "subcategory":"Cleaning & Sanitation",
            "type":"Services"
        }
    ],
    "sg:phone":"+1 775 482 5766",
    "sg:postcode":"89049",
    "sg:province":"NV",
    "sg:tags":[
        "professional"
    ],
    "wof:name":"Mc Janitorial Service",
    "wof:placetype":"venue"
},
  "geometry": {"coordinates":[-117.24230900000001,38.090296],"type":"Point"}
}