{
  "type": "Feature",
  "properties": {
    "iso:country":"US",
    "sg:address":"2028 Venus St",
    "sg:city":"North Las Vegas",
    "sg:classifiers":[
        {
            "category":"Professional",
            "subcategory":"Management & Consulting",
            "type":"Services"
        }
    ],
    "sg:phone":"+1 702 399 5022",
    "sg:postcode":"89030",
    "sg:province":"NV",
    "sg:tags":[
        "fuel"
    ],
    "wof:name":"Centurion Management Svc",
    "wof:placetype":"venue"
},
  "geometry": {"coordinates":[-115.1191,36.22046],"type":"Point"}
}