{
  "type": "Feature",
  "properties": {
    "iso:country":"US",
    "sg:address":"4375 Las Vegas Blvd N",
    "sg:city":"Las Vegas",
    "sg:classifiers":[
        {
            "category":"Freight",
            "type":"Transportation"
        }
    ],
    "sg:phone":"+1 702 651 1006",
    "sg:postcode":"89115",
    "sg:province":"NV",
    "sg:tags":[
        "general"
    ],
    "wof:name":"Mobile Storage Group",
    "wof:placetype":"venue"
},
  "geometry": {"coordinates":[-115.061862,36.236179],"type":"Point"}
}