{
  "type": "Feature",
  "properties": {
    "iso:country":"US",
    "sg:address":"2915 W Charleston Blvd",
    "sg:city":"Las Vegas",
    "sg:classifiers":[
        {
            "category":"Professional",
            "type":"Services"
        }
    ],
    "sg:phone":"+1 702 383 6476",
    "sg:postcode":"89102",
    "sg:province":"NV",
    "sg:tags":[
        "establishment"
    ],
    "wof:name":"Sulick & Assoc",
    "wof:placetype":"venue"
},
  "geometry": {"coordinates":[-115.181751,36.158862],"type":"Point"}
}