{
  "type": "Feature",
  "properties": {
    "iso:country":"US",
    "sg:address":"2061 Rock Springs Drive",
    "sg:city":"Las Vegas",
    "sg:classifiers":[
        {
            "category":"Autos & Motor Vehicles",
            "subcategory":"Auto Supplies",
            "type":"Retail Goods"
        }
    ],
    "sg:phone":"+1 702 360 9800",
    "sg:postcode":"89128",
    "sg:province":"NV",
    "sg:tags":[
        "tire"
    ],
    "wof:name":"Big O Tires and Service Centers",
    "wof:placetype":"venue"
},
  "geometry": {"coordinates":[-115.247176,36.196962],"type":"Point"}
}