{
  "type": "Feature",
  "properties": {
    "iso:country":"US",
    "sg:address":"2180 Hearts Club Dr",
    "sg:city":"Henderson",
    "sg:classifiers":[
        {
            "category":"Professional",
            "subcategory":"Employment Agencies",
            "type":"Services"
        }
    ],
    "sg:phone":"+1 702 914 6880",
    "sg:postcode":"89074",
    "sg:province":"NV",
    "sg:tags":[
        "help",
        "supply"
    ],
    "wof:name":"Jfb Enterprises",
    "wof:placetype":"venue"
},
  "geometry": {"coordinates":[-115.083255,36.033683],"type":"Point"}
}