{
  "type": "Feature",
  "properties": {
    "iso:country":"US",
    "sg:address":"4580 S Eastern Ave",
    "sg:city":"Las Vegas",
    "sg:classifiers":[
        {
            "category":"Health Services",
            "subcategory":"Doctor",
            "type":"Services"
        }
    ],
    "sg:phone":"+1 702 317 6464",
    "sg:postcode":"89119",
    "sg:province":"NV",
    "sg:tags":[
        "physician",
        "surgeon"
    ],
    "wof:name":"St Mary's Heart Ctr",
    "wof:placetype":"venue"
},
  "geometry": {"coordinates":[-115.118987,36.107005],"type":"Point"}
}