{
  "type": "Feature",
  "properties": {
    "iso:country":"US",
    "sg:address":"8116 Mount Harris Ct",
    "sg:city":"Las Vegas",
    "sg:classifiers":[
        {
            "category":"Shopping",
            "subcategory":"Hobbies, Toys, & Games",
            "type":"Retail Goods"
        }
    ],
    "sg:phone":"+1 702 363 7621",
    "sg:postcode":"89145",
    "sg:province":"NV",
    "wof:name":"G and N Toys",
    "wof:placetype":"venue"
},
  "geometry": {"coordinates":[-115.26974300000001,36.165368],"type":"Point"}
}