{
  "type": "Feature",
  "properties": {
    "iso:country":"US",
    "sg:address":"9100 W Flamingo Rd",
    "sg:city":"Las Vegas",
    "sg:classifiers":[
        {
            "category":"Real Estate",
            "subcategory":"Real Estate Operator",
            "type":"Services"
        }
    ],
    "sg:phone":"+1 702 320 4444",
    "sg:postcode":"89147",
    "sg:province":"NV",
    "sg:tags":[
        "apartment"
    ],
    "sg:website":"www.liveatalliance.com/Broadston...",
    "wof:name":"Broadstone Flamingo West",
    "wof:placetype":"venue"
},
  "geometry": {"coordinates":[-115.29133299999999,36.11587],"type":"Point"}
}