{
  "type": "Feature",
  "properties": {
    "iso:country":"US",
    "sg:address":"820 Oriole Way",
    "sg:city":"Incline Village",
    "sg:classifiers":[
        {
            "category":"Professional",
            "subcategory":"Business Services",
            "type":"Services"
        }
    ],
    "sg:phone":"+1 775 831 3946",
    "sg:postcode":"89451",
    "sg:province":"NV",
    "wof:name":"Tia Rancourt",
    "wof:placetype":"venue"
},
  "geometry": {"coordinates":[-119.960904,39.249168],"type":"Point"}
}