{
  "type": "Feature",
  "properties": {
    "iso:country":"US",
    "sg:address":"845 E 2nd St",
    "sg:city":"Reno",
    "sg:classifiers":[
        {
            "category":"Wholesale",
            "subcategory":"Medical Equipment & Supplies",
            "type":"Manufacturing & Wholesale Goods"
        }
    ],
    "sg:phone":"+1 775 786 3080",
    "sg:postcode":"89502",
    "sg:province":"NV",
    "sg:tags":[
        "physician",
        "surgeon"
    ],
    "wof:name":"Northwestern Bone & Tissue",
    "wof:placetype":"venue"
},
  "geometry": {"coordinates":[-119.799139,39.527436],"type":"Point"}
}