{
  "type": "Feature",
  "properties": {
    "iso:country":"US",
    "sg:address":"700 E Sahara Ave",
    "sg:city":"Las Vegas",
    "sg:classifiers":[
        {
            "category":"Wholesale",
            "subcategory":"Jewelry",
            "type":"Manufacturing & Wholesale Goods"
        }
    ],
    "sg:phone":"+1 702 796 1665",
    "sg:postcode":"89104",
    "sg:province":"NV",
    "sg:tags":[
        "stone",
        "jeweler"
    ],
    "wof:name":"Pacific Rim Enterprises",
    "wof:placetype":"venue"
},
  "geometry": {"coordinates":[-115.1447,36.143958],"type":"Point"}
}