{
  "type": "Feature",
  "properties": {
    "iso:country":"US",
    "sg:address":"1421 Flint Ridge Ave",
    "sg:city":"Las Vegas",
    "sg:classifiers":[
        {
            "category":"Real Estate",
            "subcategory":"Real Estate Agent",
            "type":"Services"
        }
    ],
    "sg:phone":"+1 702 896 0419",
    "sg:postcode":"89123",
    "sg:province":"NV",
    "wof:name":"Altishin Inc",
    "wof:placetype":"venue"
},
  "geometry": {"coordinates":[-115.13225,36.054132],"type":"Point"}
}