{
  "type": "Feature",
  "properties": {
    "iso:country":"US",
    "sg:address":"2598 Ivoryhill St",
    "sg:city":"Las Vegas",
    "sg:classifiers":[
        {
            "category":"Shopping",
            "subcategory":"Catalog Store",
            "type":"Retail Goods"
        }
    ],
    "sg:phone":"+1 702 547 4438",
    "sg:postcode":"89135",
    "sg:province":"NV",
    "sg:tags":[
        "mail",
        "order"
    ],
    "wof:name":"Willows Gifts",
    "wof:placetype":"venue"
},
  "geometry": {"coordinates":[-115.331,36.143585],"type":"Point"}
}