{
  "type": "Feature",
  "properties": {
    "iso:country":"US",
    "sg:address":"408 Upland Boulevard",
    "sg:city":"Las Vegas",
    "sg:classifiers":[
        {
            "category":"Education",
            "subcategory":"School",
            "type":"Public Place"
        }
    ],
    "sg:phone":"+1 702 799 4223",
    "sg:postcode":"89107",
    "sg:province":"NV",
    "wof:name":"Clark County School District",
    "wof:placetype":"venue"
},
  "geometry": {"coordinates":[-115.21814999999999,36.167572],"type":"Point"}
}