{
  "type": "Feature",
  "properties": {
    "iso:country":"US",
    "sg:address":"5948 Crumbling Ridge St",
    "sg:city":"Henderson",
    "sg:classifiers":[
        {
            "category":"Personal",
            "subcategory":"Beauty Salon",
            "type":"Services"
        }
    ],
    "sg:phone":"+1 702 362 2664",
    "sg:postcode":"89011",
    "sg:province":"NV",
    "sg:tags":[
        "shop"
    ],
    "wof:name":"Hair Design By Cookie LLC",
    "wof:placetype":"venue"
},
  "geometry": {"coordinates":[-115.036859,36.080626],"type":"Point"}
}