{
  "type": "Feature",
  "properties": {
    "iso:country":"US",
    "sg:address":"29 N Nellis Blvd",
    "sg:city":"Las Vegas",
    "sg:classifiers":[
        {
            "category":"Professional",
            "subcategory":"Accounting & Tax Preparation",
            "type":"Services"
        }
    ],
    "sg:phone":"+1 702 452 3151",
    "sg:postcode":"89110",
    "sg:province":"NV",
    "sg:tags":[
        "return"
    ],
    "wof:name":"H & R Block",
    "wof:placetype":"venue"
},
  "geometry": {"coordinates":[-115.062332,36.159557],"type":"Point"}
}