{
  "type": "Feature",
  "properties": {
    "iso:country":"US",
    "sg:address":"1931 Turtlerock St",
    "sg:city":"Las Vegas",
    "sg:classifiers":[
        {
            "category":"Wholesale",
            "subcategory":"Non-durable Goods",
            "type":"Manufacturing & Wholesale Goods"
        }
    ],
    "sg:phone":"+1 702 809 2989",
    "sg:postcode":"89142",
    "sg:province":"NV",
    "wof:name":"Pattycakes Unlimited",
    "wof:placetype":"venue"
},
  "geometry": {"coordinates":[-115.044614,36.150461],"type":"Point"}
}