{
  "type": "Feature",
  "properties": {
    "iso:country":"US",
    "sg:address":"8961 Manhattan Rd",
    "sg:city":"Henderson",
    "sg:classifiers":[
        {
            "category":"Building & Trades",
            "subcategory":"Construction",
            "type":"Services"
        }
    ],
    "sg:phone":"+1 702 294 0036",
    "sg:postcode":"89014",
    "sg:province":"NV",
    "sg:tags":[
        "home",
        "builder"
    ],
    "wof:name":"Concordia Homes Of Nevada",
    "wof:placetype":"venue"
},
  "geometry": {"coordinates":[-115.10283099999999,36.027155],"type":"Point"}
}