{
  "type": "Feature",
  "properties": {
    "iso:country":"US",
    "sg:address":"1430 E Charleston Blvd",
    "sg:city":"Las Vegas",
    "sg:classifiers":[
        {
            "category":"Restaurant",
            "type":"Food & Drink"
        }
    ],
    "sg:phone":"+1 702 383 4929",
    "sg:postcode":"89104",
    "sg:province":"NV",
    "wof:name":"Joy's Pastry Shoppe",
    "wof:placetype":"venue"
},
  "geometry": {"coordinates":[-115.133624,36.158918],"type":"Point"}
}