{
  "type": "Feature",
  "properties": {
    "iso:country":"US",
    "sg:address":"1928 Western Ave",
    "sg:city":"Las Vegas",
    "sg:classifiers":[
        {
            "category":"Arts & Performance",
            "subcategory":"Theater",
            "type":"Entertainment"
        }
    ],
    "sg:phone":"+1 702 940 1100",
    "sg:postcode":"89102",
    "sg:province":"NV",
    "sg:tags":[
        "bureau"
    ],
    "wof:name":"Hard Bodies Entertainment",
    "wof:placetype":"venue"
},
  "geometry": {"coordinates":[-115.164126,36.149673],"type":"Point"}
}