{
  "type": "Feature",
  "properties": {
    "iso:country":"US",
    "sg:address":"Canyon Club At Four Queens Hotel & Casino 202 Fremont St",
    "sg:city":"Las Vegas",
    "sg:classifiers":[
        {
            "category":"Arts & Performance",
            "subcategory":"Arts Center",
            "type":"Entertainment"
        }
    ],
    "sg:phone":"+1 702 220 5426",
    "sg:postcode":"89101",
    "sg:province":"NV",
    "sg:tags":[
        "performing"
    ],
    "wof:name":"Harmik as Tom Jones",
    "wof:placetype":"venue"
},
  "geometry": {"coordinates":[-115.144028,36.170712],"type":"Point"}
}