{
  "type": "Feature",
  "properties": {
    "iso:country":"US",
    "sg:address":"3209 Las Vegas Blvd N",
    "sg:city":"Las Vegas",
    "sg:classifiers":[
        {
            "category":"Shopping",
            "subcategory":"Optician",
            "type":"Retail Goods"
        }
    ],
    "sg:phone":"+1 702 733 9331",
    "sg:postcode":"89115",
    "sg:province":"NV",
    "sg:tags":[
        "eyewear"
    ],
    "wof:name":"Sunglass Hut International-Watch Station",
    "wof:placetype":"venue"
},
  "geometry": {"coordinates":[-115.095705,36.216442],"type":"Point"}
}