{
  "type": "Feature",
  "properties": {
    "iso:country":"US",
    "sg:address":"564 Aultman St",
    "sg:city":"Ely",
    "sg:classifiers":[
        {
            "category":"Personal",
            "subcategory":"Beauty Salon",
            "type":"Services"
        }
    ],
    "sg:phone":"+1 775 289 6700",
    "sg:postcode":"89301",
    "sg:province":"NV",
    "wof:name":"Illusions Stylin' Salon",
    "wof:placetype":"venue"
},
  "geometry": {"coordinates":[-114.892408,39.248176],"type":"Point"}
}