{
  "type": "Feature",
  "properties": {
    "iso:country":"US",
    "sg:address":"6785 S. Eastern Ave Suite 5",
    "sg:city":"Las Vegas",
    "sg:classifiers":[
        {
            "category":"Health Services",
            "subcategory":"Clinic",
            "type":"Services"
        }
    ],
    "sg:phone":"+1 702 407 0281",
    "sg:postcode":"89120",
    "sg:province":"NV",
    "sg:tags":[
        "cannabis"
    ],
    "wof:name":"Green Life",
    "wof:placetype":"venue"
},
  "geometry": {"coordinates":[-115.118628,36.068954],"type":"Point"}
}