{
  "type": "Feature",
  "properties": {
    "iso:country":"US",
    "sg:address":"4870 W Flamingo Rd",
    "sg:city":"Las Vegas",
    "sg:classifiers":[
        {
            "category":"Fast Food",
            "type":"Food & Drink"
        }
    ],
    "sg:phone":"+1 702 871 0503",
    "sg:postcode":"89103",
    "sg:province":"NV",
    "sg:website":"www.tacobell.com",
    "wof:name":"Taco Bell",
    "wof:placetype":"venue"
},
  "geometry": {"coordinates":[-115.207249,36.11585],"type":"Point"}
}