{
  "type": "Feature",
  "properties": {
    "iso:country":"US",
    "sg:address":"10108 Desert Wind Dr",
    "sg:city":"Las Vegas",
    "sg:classifiers":[
        {
            "category":"Professional",
            "type":"Services"
        }
    ],
    "sg:phone":"+1 702 869 0585",
    "sg:postcode":"89144",
    "sg:province":"NV",
    "sg:tags":[
        "terminal",
        "provider",
        "public",
        "internet"
    ],
    "wof:name":"Terminal Online LLC",
    "wof:placetype":"venue"
},
  "geometry": {"coordinates":[-115.317211,36.186942],"type":"Point"}
}