{
  "type": "Feature",
  "properties": {
    "iso:country":"US",
    "sg:address":"1800 US Highway 50 E",
    "sg:city":"Carson City",
    "sg:classifiers":[
        {
            "category":"Insurance",
            "subcategory":"Health Insurance",
            "type":"Services"
        }
    ],
    "sg:phone":"+1 775 882 6700",
    "sg:postcode":"89701",
    "sg:province":"NV",
    "sg:tags":[
        "market"
    ],
    "wof:name":"Vitamin Villa",
    "wof:placetype":"venue"
},
  "geometry": {"coordinates":[-119.747002,39.172901],"type":"Point"}
}