{
  "type": "Feature",
  "properties": {
    "iso:country":"US",
    "sg:address":"2522 E Lake Mead Blvd",
    "sg:city":"North Las Vegas",
    "sg:classifiers":[
        {
            "category":"Health Services",
            "subcategory":"Chiropractor",
            "type":"Services"
        }
    ],
    "sg:phone":"+1 702 642 9672",
    "sg:postcode":"89030",
    "sg:province":"NV",
    "wof:name":"Best Care Chiropractic",
    "wof:placetype":"venue"
},
  "geometry": {"coordinates":[-115.114998,36.195702],"type":"Point"}
}