{
  "type": "Feature",
  "properties": {
    "iso:country":"US",
    "sg:address":"25 N Mojave Rd",
    "sg:city":"Las Vegas",
    "sg:classifiers":[
        {
            "category":"Retail",
            "subcategory":"Auto Repair",
            "type":"Services"
        }
    ],
    "sg:phone":"+1 702 212 3225",
    "sg:postcode":"89101",
    "sg:province":"NV",
    "sg:tags":[
        "repairing",
        "automobile"
    ],
    "wof:name":"F & A Auto Repair",
    "wof:placetype":"venue"
},
  "geometry": {"coordinates":[-115.106003,36.160301],"type":"Point"}
}