{
  "type": "Feature",
  "properties": {
    "iso:country":"US",
    "sg:address":"4435 Las Vegas Blvd N",
    "sg:city":"Las Vegas",
    "sg:classifiers":[
        {
            "category":"Retail",
            "subcategory":"Auto Rental",
            "type":"Services"
        }
    ],
    "sg:phone":"+1 702 643 3605",
    "sg:postcode":"89115",
    "sg:province":"NV",
    "sg:tags":[
        "renting",
        "automobile"
    ],
    "wof:name":"Enterprise Rent-A-Car",
    "wof:placetype":"venue"
},
  "geometry": {"coordinates":[-115.05247799999999,36.241668],"type":"Point"}
}