{
  "type": "Feature",
  "properties": {
    "iso:country":"US",
    "sg:address":"3347 E Russell Rd",
    "sg:city":"Las Vegas",
    "sg:classifiers":[
        {
            "category":"Restaurant",
            "type":"Food & Drink"
        }
    ],
    "sg:menulink":"http://www.allmenus.com/nv/las-vegas/236464-tropical-smoothie/menu/",
    "sg:phone":"+1 702 547 1931",
    "sg:postcode":"89120",
    "sg:province":"NV",
    "sg:tags":[
        "smoothy",
        "juice",
        "american"
    ],
    "wof:name":"Tropical Smoothie",
    "wof:placetype":"venue"
},
  "geometry": {"coordinates":[-115.101933,36.08591],"type":"Point"}
}