{
  "type": "Feature",
  "properties": {
    "iso:country":"US",
    "sg:address":"3130 S Rainbow Blvd",
    "sg:city":"Las Vegas",
    "sg:classifiers":[
        {
            "category":"Professional",
            "subcategory":"Accounting & Tax Preparation",
            "type":"Services"
        }
    ],
    "sg:phone":"+1 702 877 6035",
    "sg:postcode":"89146",
    "sg:province":"NV",
    "wof:name":"Mark W Sewald CPA",
    "wof:placetype":"venue"
},
  "geometry": {"coordinates":[-115.24289,36.131863],"type":"Point"}
}