{
  "type": "Feature",
  "properties": {
    "iso:country":"US",
    "sg:address":"Nellis AFB 5941 Fitzgerald Blvd",
    "sg:city":"Las Vegas",
    "sg:postcode":"89191",
    "sg:province":"NV",
    "wof:name":"Rickenbackers Cafe",
    "wof:placetype":"venue"
},
  "geometry": {"coordinates":[-115.043172,36.242398],"type":"Point"}
}