{
  "type": "Feature",
  "properties": {
    "iso:country":"US",
    "sg:address":"5081 S McCarran Blvd",
    "sg:city":"Reno",
    "sg:classifiers":[
        {
            "category":"Insurance",
            "subcategory":"Insurance Agent",
            "type":"Services"
        }
    ],
    "sg:phone":"+1 775 827 1000",
    "sg:postcode":"89502",
    "sg:province":"NV",
    "sg:website":"www.libertymutual.com",
    "wof:name":"Liberty Mutual Insurance",
    "wof:placetype":"venue"
},
  "geometry": {"coordinates":[-119.78276099999999,39.477001],"type":"Point"}
}