{
  "type": "Feature",
  "properties": {
    "iso:country":"US",
    "sg:address":"85 Chinchilla Ln",
    "sg:city":"Reno",
    "sg:classifiers":[
        {
            "category":"Professional",
            "subcategory":"Secretarial Services",
            "type":"Services"
        }
    ],
    "sg:phone":"+1 775 852 7957",
    "sg:postcode":"89511",
    "sg:province":"NV",
    "sg:tags":[
        "reporting"
    ],
    "wof:name":"Absolute Business Services",
    "wof:placetype":"venue"
},
  "geometry": {"coordinates":[-119.787518,39.410274],"type":"Point"}
}