{
  "type": "Feature",
  "properties": {
    "iso:country":"US",
    "sg:address":"929 N Pecos Rd",
    "sg:city":"Las Vegas",
    "sg:classifiers":[
        {
            "category":"Professional",
            "subcategory":"Accounting & Tax Preparation",
            "type":"Services"
        }
    ],
    "sg:phone":"+1 702 320 6645",
    "sg:postcode":"89101",
    "sg:province":"NV",
    "sg:tags":[
        "return",
        "filing"
    ],
    "wof:name":"J K Jordan Tax Svc",
    "wof:placetype":"venue"
},
  "geometry": {"coordinates":[-115.09836199999999,36.182992],"type":"Point"}
}