{
  "type": "Feature",
  "properties": {
    "iso:country":"US",
    "sg:address":"131 S Maine St",
    "sg:city":"Fallon",
    "sg:classifiers":[
        {
            "category":"Shopping",
            "type":"Retail Goods"
        }
    ],
    "sg:phone":"+1 775 423 6242",
    "sg:postcode":"89406",
    "sg:province":"NV",
    "sg:tags":[
        "monument"
    ],
    "wof:name":"Etched In Stone",
    "wof:placetype":"venue"
},
  "geometry": {"coordinates":[-118.776976,39.473661],"type":"Point"}
}