{
  "type": "Feature",
  "properties": {
    "iso:country":"US",
    "sg:address":"Annex at Las Vegas Factory Outlets 7400 Las Vegas Blvd S, Ste A-1",
    "sg:city":"Las Vegas",
    "sg:classifiers":[
        {
            "category":"Shopping",
            "subcategory":"Clothing, Apparel, & Fashions",
            "type":"Retail Goods"
        },
        {
            "category":"Shopping",
            "subcategory":"Hobbies, Toys, & Games",
            "type":"Retail Goods"
        }
    ],
    "sg:phone":"+1 702 260 8144",
    "sg:postcode":"89123",
    "sg:province":"NV",
    "sg:tags":[
        "toy",
        "men's",
        "women's",
        "children's",
        "clothing",
        "store"
    ],
    "wof:name":"Disney's Character Warehouse Outlet Store",
    "wof:placetype":"venue"
},
  "geometry": {"coordinates":[-115.17220500000001,36.055083],"type":"Point"}
}