{
  "type": "Feature",
  "properties": {
    "iso:country":"US",
    "sg:address":"1664 US Hwy 395 N",
    "sg:city":"Minden",
    "sg:classifiers":[
        {
            "category":"Banks & Credit Unions",
            "subcategory":"Bank",
            "type":"Services"
        }
    ],
    "sg:phone":"+1 775 782 3814",
    "sg:postcode":"89423",
    "sg:province":"NV",
    "sg:tags":[
        "broker",
        "mortgage"
    ],
    "wof:name":"Paragon Mortgage Services",
    "wof:placetype":"venue"
},
  "geometry": {"coordinates":[-119.776501,38.959067],"type":"Point"}
}