{
  "type": "Feature",
  "properties": {
    "iso:country":"US",
    "sg:address":"484 Cumberland Way",
    "sg:city":"Henderson",
    "sg:classifiers":[
        {
            "category":"Building & Trades",
            "subcategory":"Construction",
            "type":"Services"
        }
    ],
    "sg:phone":"+1 702 567 5909",
    "sg:postcode":"89015",
    "sg:province":"NV",
    "sg:tags":[
        "contractor"
    ],
    "wof:name":"Dale E Carstens Masonry",
    "wof:placetype":"venue"
},
  "geometry": {"coordinates":[-114.997277,36.02121],"type":"Point"}
}