{
  "type": "Feature",
  "properties": {
    "iso:country":"US",
    "sg:address":"3140 Polaris Ave",
    "sg:city":"Las Vegas",
    "sg:classifiers":[
        {
            "category":"Wholesale",
            "subcategory":"Home Furnishings",
            "type":"Manufacturing & Wholesale Goods"
        },
        {
            "category":"Home & Garden",
            "subcategory":"Carpets & Floor Coverings",
            "type":"Retail Goods"
        }
    ],
    "sg:phone":"+1 702 220 9115",
    "sg:postcode":"89102",
    "sg:province":"NV",
    "sg:tags":[
        "rug",
        "dealer"
    ],
    "wof:name":"Wholesale Carpet Distributors",
    "wof:placetype":"venue"
},
  "geometry": {"coordinates":[-115.185611,36.130788],"type":"Point"}
}