{
  "type": "Feature",
  "properties": {
    "iso:country":"US",
    "sg:address":"3885 S Decatur Blvd",
    "sg:city":"Las Vegas",
    "sg:classifiers":[
        {
            "category":"Professional",
            "subcategory":"Lawyer & Legal Services",
            "type":"Services"
        }
    ],
    "sg:phone":"+1 702 871 8535",
    "sg:postcode":"89103",
    "sg:province":"NV",
    "sg:tags":[
        "company",
        "incorporating"
    ],
    "sg:website":"www.bossoffice.com",
    "wof:name":"Acorn Corporate Svc",
    "wof:placetype":"venue"
},
  "geometry": {"coordinates":[-115.208173,36.118091],"type":"Point"}
}