{
  "type": "Feature",
  "properties": {
    "iso:country":"US",
    "sg:address":"2875 S Nellis Blvd",
    "sg:city":"Las Vegas",
    "sg:classifiers":[
        {
            "category":"Bars & Pubs",
            "type":"Food & Drink"
        }
    ],
    "sg:phone":"+1 702 641 1750",
    "sg:postcode":"89121",
    "sg:province":"NV",
    "sg:tags":[
        "drinking",
        "book"
    ],
    "wof:name":"Pts Pub",
    "wof:placetype":"venue"
},
  "geometry": {"coordinates":[-115.065533,36.14073],"type":"Point"}
}