{
  "type": "Feature",
  "properties": {
    "iso:country":"US",
    "sg:address":"2220 Sunrise Dr",
    "sg:city":"Reno",
    "sg:classifiers":[
        {
            "category":"Retail",
            "subcategory":"Laundry & Dry Cleaning",
            "type":"Services"
        }
    ],
    "sg:phone":"+1 775 323 1399",
    "sg:postcode":"89509",
    "sg:province":"NV",
    "sg:tags":[
        "cleaners",
        "rug",
        "carpet"
    ],
    "wof:name":"Brown's Pro-Clean",
    "wof:placetype":"venue"
},
  "geometry": {"coordinates":[-119.81120900000001,39.50068],"type":"Point"}
}