{
  "type": "Feature",
  "properties": {
    "iso:country":"US",
    "sg:address":"2227 Bellanca St",
    "sg:city":"Minden",
    "sg:classifiers":[
        {
            "category":"Airport",
            "type":"Transportation"
        }
    ],
    "sg:phone":"+1 775 782 7047",
    "sg:postcode":"89423",
    "sg:province":"NV",
    "wof:name":"Mansberger Aircraft Inc",
    "wof:placetype":"venue"
},
  "geometry": {"coordinates":[-119.757923,38.998449],"type":"Point"}
}