{
  "type": "Feature",
  "properties": {
    "iso:country":"US",
    "sg:address":"5030 Reno Hwy",
    "sg:city":"Fallon",
    "sg:classifiers":[
        {
            "category":"Autos & Motor Vehicles",
            "subcategory":"Recreational Vehicle Sales",
            "type":"Retail Goods"
        }
    ],
    "sg:phone":"+1 775 867 3388",
    "sg:postcode":"89406",
    "sg:province":"NV",
    "sg:tags":[
        "automobile",
        "used"
    ],
    "wof:name":"J & L Trailer Sales",
    "wof:placetype":"venue"
},
  "geometry": {"coordinates":[-118.860473,39.48549],"type":"Point"}
}