{
  "type": "Feature",
  "properties": {
    "iso:country":"US",
    "sg:address":"3059 N Nellis Blvd",
    "sg:city":"Las Vegas",
    "sg:classifiers":[
        {
            "category":"Shopping",
            "type":"Retail Goods"
        },
        {
            "category":"Wholesale",
            "subcategory":"Durable Goods & Equipment",
            "type":"Manufacturing & Wholesale Goods"
        }
    ],
    "sg:phone":"+1 702 263 9366",
    "sg:postcode":"89115",
    "sg:province":"NV",
    "sg:tags":[
        "fire",
        "extinguisher",
        "merchandise"
    ],
    "wof:name":"Silver State Fire & Security",
    "wof:placetype":"venue"
},
  "geometry": {"coordinates":[-115.06226,36.207921],"type":"Point"}
}