{
  "type": "Feature",
  "properties": {
    "iso:country":"US",
    "sg:address":"1828 Palisade Dr",
    "sg:city":"Reno",
    "sg:classifiers":[
        {
            "category":"Professional",
            "subcategory":"Secretarial Services",
            "type":"Services"
        }
    ],
    "sg:phone":"+1 775 329 6560",
    "sg:postcode":"89509",
    "sg:province":"NV",
    "sg:tags":[
        "convention",
        "court",
        "reporter"
    ],
    "wof:name":"Sierra Nevada Reporters",
    "wof:placetype":"venue"
},
  "geometry": {"coordinates":[-119.831878,39.505421],"type":"Point"}
}