{
  "type": "Feature",
  "properties": {
    "iso:country":"US",
    "sg:address":"2820 Winnemucca St",
    "sg:city":"Silver Springs",
    "sg:classifiers":[
        {
            "category":"Manufacturing",
            "subcategory":"Toys & Sporting Goods",
            "type":"Manufacturing & Wholesale Goods"
        }
    ],
    "sg:phone":"+1 775 577 2679",
    "sg:postcode":"89429",
    "sg:province":"NV",
    "sg:tags":[
        "mfg",
        "luggage"
    ],
    "wof:name":"Little Heffer",
    "wof:placetype":"venue"
},
  "geometry": {"coordinates":[-119.216802,39.407454],"type":"Point"}
}