{
  "type": "Feature",
  "properties": {
    "iso:country":"US",
    "sg:address":"5410 Cameron St",
    "sg:city":"Las Vegas",
    "sg:classifiers":[
        {
            "category":"Communications",
            "type":"Services"
        }
    ],
    "sg:phone":"+1 702 222 0238",
    "sg:postcode":"89118",
    "sg:province":"NV",
    "wof:name":"Kebord Communications",
    "wof:placetype":"venue"
},
  "geometry": {"coordinates":[-115.203781,36.092988],"type":"Point"}
}