{
  "type": "Feature",
  "properties": {
    "iso:country":"US",
    "sg:address":"9425 W Tropicana Ave",
    "sg:city":"Las Vegas",
    "sg:classifiers":[
        {
            "category":"Banks & Credit Unions",
            "subcategory":"Bank",
            "type":"Services"
        }
    ],
    "sg:phone":"+1 702 562 2200",
    "sg:postcode":"89147",
    "sg:province":"NV",
    "sg:tags":[
        "cashing",
        "check"
    ],
    "wof:name":"Check City",
    "wof:placetype":"venue"
},
  "geometry": {"coordinates":[-115.309919,36.10021],"type":"Point"}
}