{
  "type": "Feature",
  "properties": {
    "iso:country":"US",
    "sg:address":"685 W Williams Ave",
    "sg:city":"Fallon",
    "sg:classifiers":[
        {
            "category":"Real Estate",
            "subcategory":"Real Estate Agent",
            "type":"Services"
        }
    ],
    "sg:phone":"+1 775 423 5445",
    "sg:postcode":"89406",
    "sg:province":"NV",
    "sg:tags":[
        "management"
    ],
    "wof:name":"Eagle Realty",
    "wof:placetype":"venue"
},
  "geometry": {"coordinates":[-118.784974,39.474729],"type":"Point"}
}