{
  "type": "Feature",
  "properties": {
    "iso:country":"US",
    "sg:address":"3580 Barrymore Dr",
    "sg:city":"Reno",
    "sg:classifiers":[
        {
            "category":"Building & Trades",
            "subcategory":"Cleaning & Sanitation",
            "type":"Services"
        }
    ],
    "sg:phone":"+1 775 674 2753",
    "sg:postcode":"89512",
    "sg:province":"NV",
    "sg:tags":[
        "maintenance"
    ],
    "wof:name":"Gonzalez Janitorial Services",
    "wof:placetype":"venue"
},
  "geometry": {"coordinates":[-119.783188,39.562823],"type":"Point"}
}