{
  "type": "Feature",
  "properties": {
    "iso:country":"US",
    "sg:address":"1516 E Tropicana Ave",
    "sg:city":"Las Vegas",
    "sg:classifiers":[
        {
            "category":"Professional",
            "subcategory":"Business Services",
            "type":"Services"
        }
    ],
    "sg:phone":"+1 702 315 0768",
    "sg:postcode":"89119",
    "sg:province":"NV",
    "sg:tags":[
        "water",
        "treatment"
    ],
    "wof:name":"Towncraft Zeus",
    "wof:placetype":"venue"
},
  "geometry": {"coordinates":[-115.128171,36.101035],"type":"Point"}
}