{
  "type": "Feature",
  "properties": {
    "iso:country":"US",
    "sg:address":"318 Lander Dr",
    "sg:city":"Henderson",
    "sg:classifiers":[
        {
            "category":"Freight",
            "type":"Transportation"
        }
    ],
    "sg:phone":"+1 702 563 2925",
    "sg:postcode":"89074",
    "sg:province":"NV",
    "sg:tags":[
        "trucking"
    ],
    "wof:name":"Optimal Diversified Svc Inc",
    "wof:placetype":"venue"
},
  "geometry": {"coordinates":[-115.106128,36.051226],"type":"Point"}
}