{
  "type": "Feature",
  "properties": {
    "iso:country":"US",
    "sg:address":"7770 Duneville St Ste 12",
    "sg:city":"Las Vegas",
    "sg:classifiers":[
        {
            "category":"Shopping",
            "subcategory":"Pets & Pet Supplies",
            "type":"Retail Goods"
        }
    ],
    "sg:phone":"+1 702 609 9669",
    "sg:postcode":"89139",
    "sg:province":"NV",
    "sg:tags":[
        "groomers"
    ],
    "sg:website":"woofwoofdoggrooming.com",
    "wof:name":"Woof Woof Dog Grooming",
    "wof:placetype":"venue"
},
  "geometry": {"coordinates":[-115.220392,36.048061],"type":"Point"}
}