{
  "type": "Feature",
  "properties": {
    "iso:country":"US",
    "sg:address":"7429 W Gilmore Ave",
    "sg:city":"Las Vegas",
    "sg:classifiers":[
        {
            "category":"Building & Trades",
            "subcategory":"Cleaning & Sanitation",
            "type":"Services"
        }
    ],
    "sg:phone":"+1 702 645 8987",
    "sg:postcode":"89129",
    "sg:province":"NV",
    "sg:tags":[
        "maintenance"
    ],
    "wof:name":"Norris Janitorial",
    "wof:placetype":"venue"
},
  "geometry": {"coordinates":[-115.257929,36.229875],"type":"Point"}
}