{
  "type": "Feature",
  "properties": {
    "iso:country":"US",
    "sg:address":"3550 Barron Way",
    "sg:city":"Reno",
    "sg:classifiers":[
        {
            "category":"Real Estate",
            "subcategory":"Architect",
            "type":"Services"
        }
    ],
    "sg:phone":"+1 775 332 6640",
    "sg:postcode":"89511",
    "sg:province":"NV",
    "sg:tags":[
        "architectural"
    ],
    "wof:name":"Hershnow Klppnstein Architects",
    "wof:placetype":"venue"
},
  "geometry": {"coordinates":[-119.768633,39.472359],"type":"Point"}
}