{
  "type": "Feature",
  "properties": {
    "iso:country":"US",
    "sg:address":"6420 Spring Mountain Rd",
    "sg:city":"Las Vegas",
    "sg:classifiers":[
        {
            "category":"Banks & Credit Unions",
            "subcategory":"Bank",
            "type":"Services"
        }
    ],
    "sg:phone":"+1 702 248 4647",
    "sg:postcode":"89146",
    "sg:province":"NV",
    "sg:tags":[
        "banker",
        "mortgage"
    ],
    "wof:name":"Silver State Fincl Svcs Inc",
    "wof:placetype":"venue"
},
  "geometry": {"coordinates":[-115.23156,36.125608],"type":"Point"}
}