{
  "type": "Feature",
  "properties": {
    "iso:country":"US",
    "sg:address":"3789 Lorraine Ln",
    "sg:city":"Las Vegas",
    "sg:classifiers":[
        {
            "category":"Personal",
            "subcategory":"Barber",
            "type":"Services"
        }
    ],
    "sg:phone":"+1 702 456 3254",
    "sg:postcode":"89120",
    "sg:province":"NV",
    "sg:tags":[
        "shop"
    ],
    "wof:name":"Razor Communications LLC",
    "wof:placetype":"venue"
},
  "geometry": {"coordinates":[-115.093194,36.08868],"type":"Point"}
}