{
  "type": "Feature",
  "properties": {
    "iso:country":"US",
    "sg:address":"3570 Waterfall Dr",
    "sg:city":"Sparks",
    "sg:classifiers":[
        {
            "category":"Education",
            "subcategory":"School",
            "type":"Public Place"
        }
    ],
    "sg:phone":"+1 775 626 5200",
    "sg:postcode":"89434",
    "sg:province":"NV",
    "wof:name":"Whitehead Elementary School",
    "wof:placetype":"venue"
},
  "geometry": {"coordinates":[-119.711609,39.564152],"type":"Point"}
}