{
  "type": "Feature",
  "properties": {
    "iso:country":"US",
    "sg:address":"8811 W Sahara Avenue Suite 200",
    "sg:city":"Las Vegas",
    "sg:classifiers":[
        {
            "category":"Health Services",
            "subcategory":"Dentist",
            "type":"Services"
        }
    ],
    "sg:phone":"+1 702 401 9970",
    "sg:postcode":"89117",
    "sg:province":"NV",
    "sg:tags":[
        "orthodontist"
    ],
    "wof:name":"Sorbero Cheryl L DDS",
    "wof:placetype":"venue"
},
  "geometry": {"coordinates":[-115.288121,36.143996],"type":"Point"}
}