{
  "type": "Feature",
  "properties": {
    "iso:country":"US",
    "sg:address":"282 E Lake Mead Pkwy",
    "sg:city":"Henderson",
    "sg:classifiers":[
        {
            "category":"Professional",
            "subcategory":"Research",
            "type":"Services"
        }
    ],
    "sg:phone":"+1 702 565 2933",
    "sg:postcode":"89015",
    "sg:province":"NV",
    "wof:name":"Clinical Research Trial Inc",
    "wof:placetype":"venue"
},
  "geometry": {"coordinates":[-114.976823,36.043487],"type":"Point"}
}