{
  "type": "Feature",
  "properties": {
    "iso:country":"US",
    "sg:address":"695 Mile Circle Dr",
    "sg:city":"Reno",
    "sg:classifiers":[
        {
            "category":"Building & Trades",
            "subcategory":"Construction",
            "type":"Services"
        }
    ],
    "sg:phone":"+1 775 333 0817",
    "sg:postcode":"89511",
    "sg:province":"NV",
    "sg:tags":[
        "excavation",
        "general",
        "contractor"
    ],
    "wof:name":"Murphy Brian Cnstr & Dev",
    "wof:placetype":"venue"
},
  "geometry": {"coordinates":[-119.78763,39.447126],"type":"Point"}
}