{
  "type": "Feature",
  "properties": {
    "iso:country":"US",
    "sg:address":"6770 N Durango Dr",
    "sg:city":"Las Vegas",
    "sg:classifiers":[
        {
            "category":"Personal",
            "subcategory":"Tanning Parlor",
            "type":"Services"
        }
    ],
    "sg:phone":"+1 702 453 8267",
    "sg:postcode":"89149",
    "sg:province":"NV",
    "wof:name":"Hot Tan",
    "wof:placetype":"venue"
},
  "geometry": {"coordinates":[-115.287246,36.284018],"type":"Point"}
}