{
  "type": "Feature",
  "properties": {
    "iso:country":"US",
    "sg:address":"2850 Friar Rock Ct",
    "sg:city":"Sparks",
    "sg:classifiers":[
        {
            "category":"Food & Beverages",
            "subcategory":"Groceries & Convenience Stores",
            "type":"Retail Goods"
        }
    ],
    "sg:phone":"+1 775 626 1617",
    "sg:postcode":"89436",
    "sg:province":"NV",
    "wof:name":"Mindis Time Savers",
    "wof:placetype":"venue"
},
  "geometry": {"coordinates":[-119.689714,39.620726],"type":"Point"}
}