{
  "type": "Feature",
  "properties": {
    "iso:country":"US",
    "sg:address":"312 Stewart St",
    "sg:city":"Reno",
    "sg:classifiers":[
        {
            "category":"Professional",
            "subcategory":"Accounting & Tax Preparation",
            "type":"Services"
        }
    ],
    "sg:phone":"+1 775 324 5400",
    "sg:postcode":"89502",
    "sg:province":"NV",
    "sg:tags":[
        "return",
        "filing"
    ],
    "wof:name":"Susan Bergstrom Gaub Inc",
    "wof:placetype":"venue"
},
  "geometry": {"coordinates":[-119.805011,39.522152],"type":"Point"}
}