{
  "type": "Feature",
  "properties": {
    "iso:country":"US",
    "sg:address":"301 Orland St",
    "sg:city":"Las Vegas",
    "sg:classifiers":[
        {
            "category":"Real Estate",
            "subcategory":"Real Estate Operator",
            "type":"Services"
        }
    ],
    "sg:phone":"+1 702 878 8783",
    "sg:postcode":"89107",
    "sg:province":"NV",
    "sg:tags":[
        "apartment"
    ],
    "wof:name":"Almond Tree Apartments",
    "wof:placetype":"venue"
},
  "geometry": {"coordinates":[-115.220277,36.176106],"type":"Point"}
}