{
  "type": "Feature",
  "properties": {
    "iso:country":"US",
    "sg:address":"7541 Westcliff Dr",
    "sg:city":"Las Vegas",
    "sg:classifiers":[
        {
            "category":"Professional",
            "subcategory":"Accounting & Tax Preparation",
            "type":"Services"
        }
    ],
    "sg:phone":"+1 702 361 8789",
    "sg:postcode":"89145",
    "sg:province":"NV",
    "sg:tags":[
        "return"
    ],
    "wof:name":"Jfm Tax & Book Keeping",
    "wof:placetype":"venue"
},
  "geometry": {"coordinates":[-115.260278,36.173946],"type":"Point"}
}