{
  "type": "Feature",
  "properties": {
    "iso:country":"US",
    "sg:address":"2970 Traverse Creek Ln",
    "sg:city":"Las Vegas",
    "sg:classifiers":[
        {
            "category":"Real Estate",
            "subcategory":"Developer",
            "type":"Services"
        }
    ],
    "sg:phone":"+1 702 838 8653",
    "sg:postcode":"89135",
    "sg:province":"NV",
    "wof:name":"Butler Bros Scotia Inc",
    "wof:placetype":"venue"
},
  "geometry": {"coordinates":[-115.33171,36.136944],"type":"Point"}
}