{
  "type": "Feature",
  "properties": {
    "iso:country":"US",
    "sg:address":"2275 Renaissance Dr",
    "sg:city":"Las Vegas",
    "sg:classifiers":[
        {
            "category":"Travel",
            "subcategory":"Travel Agent",
            "type":"Entertainment"
        }
    ],
    "sg:phone":"+1 702 795 3999",
    "sg:postcode":"89119",
    "sg:province":"NV",
    "sg:tags":[
        "operator",
        "auto",
        "tour",
        "business"
    ],
    "wof:name":"Reservations Plus",
    "wof:placetype":"venue"
},
  "geometry": {"coordinates":[-115.122945,36.102571],"type":"Point"}
}