{
  "type": "Feature",
  "properties": {
    "iso:country":"US",
    "sg:address":"4342 Woodwell Street",
    "sg:city":"Las Vegas",
    "sg:classifiers":[
        {
            "category":"Real Estate",
            "subcategory":"Real Estate Operator",
            "type":"Services"
        }
    ],
    "sg:phone":"+1 702 396 6147",
    "sg:postcode":"89147",
    "sg:province":"NV",
    "sg:tags":[
        "apartment"
    ],
    "wof:name":"Shadow Ridge Townhomes",
    "wof:placetype":"venue"
},
  "geometry": {"coordinates":[-115.299886,36.110839],"type":"Point"}
}