{
  "type": "Feature",
  "properties": {
    "iso:country":"US",
    "sg:address":"8450 W Sahara Ave Ste 112",
    "sg:city":"Las Vegas",
    "sg:classifiers":[
        {
            "category":"Shopping",
            "subcategory":"Crafts & Fabrics",
            "type":"Retail Goods"
        }
    ],
    "sg:phone":"+1 702 838 7713",
    "sg:postcode":"89117",
    "sg:province":"NV",
    "sg:tags":[
        "art"
    ],
    "sg:website":"www.gailknits.com",
    "wof:name":"Gail Knits",
    "wof:placetype":"venue"
},
  "geometry": {"coordinates":[-115.275959,36.144105],"type":"Point"}
}