{
  "type": "Feature",
  "properties": {
    "iso:country":"US",
    "sg:address":"11028 Salford Dr",
    "sg:city":"Las Vegas",
    "sg:classifiers":[
        {
            "category":"Professional",
            "subcategory":"Lawyer & Legal Services",
            "type":"Services"
        }
    ],
    "sg:phone":"+1 702 254 4445",
    "sg:postcode":"89144",
    "sg:province":"NV",
    "sg:tags":[
        "attorney"
    ],
    "wof:name":"Eric Daly Law Office",
    "wof:placetype":"venue"
},
  "geometry": {"coordinates":[-115.335668,36.173143],"type":"Point"}
}