{
  "type": "Feature",
  "properties": {
    "iso:country":"US",
    "sg:address":"5185 Meadowood Mall Cir",
    "sg:city":"Reno",
    "sg:classifiers":[
        {
            "category":"Utilities",
            "subcategory":"Mobile Phone",
            "type":"Services"
        }
    ],
    "sg:phone":"+1 775 826 7007",
    "sg:postcode":"89502",
    "sg:province":"NV",
    "sg:tags":[
        "telephone",
        "cellular"
    ],
    "wof:name":"T Mobile",
    "wof:placetype":"venue"
},
  "geometry": {"coordinates":[-119.780429,39.475263],"type":"Point"}
}