{
  "type": "Feature",
  "properties": {
    "iso:country":"US",
    "sg:address":"2721 Tumble Brook Dr",
    "sg:city":"Las Vegas",
    "sg:classifiers":[
        {
            "category":"Professional",
            "subcategory":"Management & Consulting",
            "type":"Services"
        }
    ],
    "sg:phone":"+1 702 878 3073",
    "sg:postcode":"89134",
    "sg:province":"NV",
    "wof:name":"Hil Lurie & Associates",
    "wof:placetype":"venue"
},
  "geometry": {"coordinates":[-115.30674500000001,36.211927],"type":"Point"}
}