{
  "type": "Feature",
  "properties": {
    "iso:country":"US",
    "sg:address":"2300 Oddie Blvd",
    "sg:city":"Sparks",
    "sg:classifiers":[
        {
            "category":"Shopping",
            "subcategory":"Pharmacy",
            "type":"Retail Goods"
        }
    ],
    "sg:phone":"+1 775 331 4405",
    "sg:postcode":"89431",
    "sg:province":"NV",
    "wof:name":"Longs Drug",
    "wof:placetype":"venue"
},
  "geometry": {"coordinates":[-119.776222,39.545477],"type":"Point"}
}