{
  "type": "Feature",
  "properties": {
    "iso:country":"US",
    "sg:address":"3040 Clayton St",
    "sg:city":"North Las Vegas",
    "sg:classifiers":[
        {
            "category":"Manufacturing",
            "subcategory":"Tools & Machinery",
            "type":"Manufacturing & Wholesale Goods"
        }
    ],
    "sg:phone":"+1 702 851 7600",
    "sg:postcode":"89032",
    "sg:province":"NV",
    "sg:tags":[
        "equipment",
        "electric"
    ],
    "sg:website":"www.spacecraft.com",
    "wof:name":"Spacecraft Components Corp",
    "wof:placetype":"venue"
},
  "geometry": {"coordinates":[-115.170063,36.21468],"type":"Point"}
}