{
  "type": "Feature",
  "properties": {
    "iso:country":"US",
    "sg:address":"5390 S Decatur Boulevard",
    "sg:city":"Las Vegas",
    "sg:classifiers":[
        {
            "category":"Retail",
            "subcategory":"Auto Repair",
            "type":"Services"
        }
    ],
    "sg:phone":"+1 702 938 6310",
    "sg:postcode":"89118",
    "sg:province":"NV",
    "sg:website":"acclaimauto.mechanicnet.com/",
    "wof:name":"Acclaim Automotive & Fleet Repair",
    "wof:placetype":"venue"
},
  "geometry": {"coordinates":[-115.207888,36.090167],"type":"Point"}
}