{
  "type": "Feature",
  "properties": {
    "iso:country":"US",
    "sg:address":"4616 W Charleston Boulevard",
    "sg:city":"Las Vegas",
    "sg:classifiers":[
        {
            "category":"Shopping",
            "subcategory":"Shoes",
            "type":"Retail Goods"
        }
    ],
    "sg:phone":"+1 702 870 4244",
    "sg:postcode":"89102",
    "sg:province":"NV",
    "sg:tags":[
        "store"
    ],
    "wof:name":"Red Wing Shoe Store",
    "wof:placetype":"venue"
},
  "geometry": {"coordinates":[-115.20376,36.159264],"type":"Point"}
}