{
  "type": "Feature",
  "properties": {
    "iso:country":"US",
    "sg:address":"3663 Las Vegas Blvd S",
    "sg:city":"Las Vegas",
    "sg:classifiers":[
        {
            "category":"Shopping",
            "subcategory":"Gifts & Souvenirs",
            "type":"Retail Goods"
        }
    ],
    "sg:phone":"+1 702 733 9099",
    "sg:postcode":"89109",
    "sg:province":"NV",
    "sg:tags":[
        "shop"
    ],
    "wof:name":"Tresor",
    "wof:placetype":"venue"
},
  "geometry": {"coordinates":[-115.172838,36.114701],"type":"Point"}
}