{
  "type": "Feature",
  "properties": {
    "iso:country":"US",
    "sg:address":"1750 S Rainbow Boulevard",
    "sg:city":"Las Vegas",
    "sg:classifiers":[
        {
            "category":"Professional",
            "subcategory":"Accounting & Tax Preparation",
            "type":"Services"
        }
    ],
    "sg:phone":"+1 702 870 6115",
    "sg:postcode":"89146",
    "sg:province":"NV",
    "sg:tags":[
        "accountant"
    ],
    "wof:name":"Bailey George W CPA",
    "wof:placetype":"venue"
},
  "geometry": {"coordinates":[-115.24312500000001,36.152073],"type":"Point"}
}