{
  "type": "Feature",
  "properties": {
    "iso:country":"US",
    "sg:address":"933 Topsy Ln",
    "sg:city":"Carson City",
    "sg:classifiers":[
        {
            "category":"Restaurant",
            "type":"Food & Drink"
        }
    ],
    "sg:phone":"+1 775 267 9366",
    "sg:postcode":"89706",
    "sg:province":"NV",
    "sg:tags":[
        "mexican"
    ],
    "sg:website":"www.qdoba.com",
    "wof:name":"Qdoba Mexican Grill",
    "wof:placetype":"venue"
},
  "geometry": {"coordinates":[-119.772245,39.110358],"type":"Point"}
}