{
  "type": "Feature",
  "properties": {
    "iso:country":"US",
    "sg:address":"4860 S Eastern Avenue",
    "sg:city":"Las Vegas",
    "sg:classifiers":[
        {
            "category":"Food Court",
            "type":"Food & Drink"
        }
    ],
    "sg:phone":"+1 702 451 4976",
    "sg:postcode":"89119",
    "sg:province":"NV",
    "sg:tags":[
        "stand"
    ],
    "sg:website":"www.baskinrobbins.com",
    "wof:name":"Baskin Robbins",
    "wof:placetype":"venue"
},
  "geometry": {"coordinates":[-115.118887,36.100647],"type":"Point"}
}