{
  "type": "Feature",
  "properties": {
    "iso:country":"US",
    "sg:address":"1349 W Horizon Ridge Pkwy Box 123",
    "sg:city":"Henderson",
    "sg:classifiers":[
        {
            "category":"Personal",
            "subcategory":"Beauty Salon",
            "type":"Services"
        },
        {
            "category":"Personal",
            "subcategory":"Skin Care",
            "type":"Services"
        }
    ],
    "sg:phone":"+1 702 272 1985",
    "sg:postcode":"89012",
    "sg:province":"NV",
    "sg:tags":[
        "makeup",
        "artist"
    ],
    "sg:website":"www.mycolortheory.com",
    "wof:name":"My Color Theory Incorporated",
    "wof:placetype":"venue"
},
  "geometry": {"coordinates":[-115.045653,36.020772],"type":"Point"}
}