{
  "type": "Feature",
  "properties": {
    "iso:country":"US",
    "sg:address":"2550 E Desert Inn Rd",
    "sg:city":"Las Vegas",
    "sg:classifiers":[
        {
            "category":"Building & Trades",
            "subcategory":"Equipment Rental",
            "type":"Services"
        }
    ],
    "sg:phone":"+1 702 654 4763",
    "sg:postcode":"89121",
    "sg:province":"NV",
    "wof:name":"Banya Rentals",
    "wof:placetype":"venue"
},
  "geometry": {"coordinates":[-115.115855,36.129875],"type":"Point"}
}