{
  "type": "Feature",
  "properties": {
    "iso:country":"US",
    "sg:address":"939 Mica Dr Ste 20",
    "sg:city":"Carson City",
    "sg:classifiers":[
        {
            "category":"Restaurant",
            "type":"Food & Drink"
        }
    ],
    "sg:phone":"+1 775 783 0505",
    "sg:postcode":"89705",
    "sg:province":"NV",
    "sg:tags":[
        "traditional",
        "american"
    ],
    "sg:website":"www.mottcanyon.com/",
    "wof:name":"Mott Canyon Tavern & Grill - CLOSED",
    "wof:placetype":"venue"
},
  "geometry": {"coordinates":[-119.77815200000001,39.091253],"type":"Point"}
}