{
  "type": "Feature",
  "properties": {
    "iso:country":"US",
    "sg:address":"1201 S Jones Blvd",
    "sg:city":"Las Vegas",
    "sg:classifiers":[
        {
            "category":"Building & Trades",
            "subcategory":"Construction",
            "type":"Services"
        }
    ],
    "sg:phone":"+1 702 631 3222",
    "sg:postcode":"89146",
    "sg:province":"NV",
    "sg:tags":[
        "builder",
        "patio",
        "deck"
    ],
    "wof:name":"Patio Paradise",
    "wof:placetype":"venue"
},
  "geometry": {"coordinates":[-115.224122,36.158083],"type":"Point"}
}