{
  "type": "Feature",
  "properties": {
    "iso:country":"US",
    "sg:address":"7801 W Gilmore Ave",
    "sg:city":"Las Vegas",
    "sg:classifiers":[
        {
            "category":"Education",
            "subcategory":"School",
            "type":"Public Place"
        }
    ],
    "sg:phone":"+1 702 799 3400",
    "sg:postcode":"89129",
    "sg:province":"NV",
    "sg:tags":[
        "high",
        "middle",
        "elementary"
    ],
    "wof:name":"Schools Clark County Public",
    "wof:placetype":"venue"
},
  "geometry": {"coordinates":[-115.264999,36.2295],"type":"Point"}
}