{
  "type": "Feature",
  "properties": {
    "iso:country":"US",
    "sg:address":"5199 Jewel Canyon Dr",
    "sg:city":"Las Vegas",
    "sg:classifiers":[
        {
            "category":"Building & Trades",
            "subcategory":"Electrical",
            "type":"Services"
        }
    ],
    "sg:phone":"+1 702 431 6445",
    "sg:postcode":"89122",
    "sg:province":"NV",
    "sg:tags":[
        "electrical",
        "contractor"
    ],
    "wof:name":"Cash Only Electric",
    "wof:placetype":"venue"
},
  "geometry": {"coordinates":[-115.026974,36.094757],"type":"Point"}
}