{
  "type": "Feature",
  "properties": {
    "iso:country":"US",
    "sg:address":"1833 Cypress Greens Ave",
    "sg:city":"Henderson",
    "sg:classifiers":[
        {
            "category":"Real Estate",
            "subcategory":"Real Estate Agent",
            "type":"Services"
        }
    ],
    "sg:phone":"+1 702 260 9266",
    "sg:postcode":"89012",
    "sg:province":"NV",
    "wof:name":"Hennepin Lake Realty",
    "wof:placetype":"venue"
},
  "geometry": {"coordinates":[-115.06805199999999,35.999533],"type":"Point"}
}