{
  "type": "Feature",
  "properties": {
    "iso:country":"US",
    "sg:address":"5855 Valley Dr Unit 1104",
    "sg:city":"North Las Vegas",
    "sg:classifiers":[
        {
            "category":"Building & Trades",
            "subcategory":"Cleaning & Sanitation",
            "type":"Services"
        }
    ],
    "sg:phone":"+1 702 233 8800",
    "sg:postcode":"89031",
    "sg:province":"NV",
    "sg:tags":[
        "home"
    ],
    "sg:website":"www.thekleanteam.com",
    "wof:name":"The Klean Team Kleaning Service",
    "wof:placetype":"venue"
},
  "geometry": {"coordinates":[-115.19955400000001,36.267972],"type":"Point"}
}