{
  "type": "Feature",
  "properties": {
    "iso:country":"US",
    "sg:address":"95 Paradise Pkwy",
    "sg:city":"Henderson",
    "sg:classifiers":[
        {
            "category":"Building & Trades",
            "subcategory":"Construction",
            "type":"Services"
        }
    ],
    "sg:phone":"+1 702 361 2411",
    "sg:postcode":"89074",
    "sg:province":"NV",
    "sg:tags":[
        "painter"
    ],
    "wof:name":"Decor & More",
    "wof:placetype":"venue"
},
  "geometry": {"coordinates":[-115.097578,36.033699],"type":"Point"}
}