{
  "type": "Feature",
  "properties": {
    "iso:country":"US",
    "sg:address":"3068 E Sunset Rd Ste 13",
    "sg:city":"Las Vegas",
    "sg:classifiers":[
        {
            "category":"Professional",
            "subcategory":"Computer Services",
            "type":"Services"
        }
    ],
    "sg:phone":"+1 702 898 0022",
    "sg:postcode":"89120",
    "sg:province":"NV",
    "sg:tags":[
        "repair"
    ],
    "wof:name":"Technical Services Group",
    "wof:placetype":"venue"
},
  "geometry": {"coordinates":[-115.108189,36.071757],"type":"Point"}
}