{
  "type": "Feature",
  "properties": {
    "iso:country":"US",
    "sg:address":"221 N Rampart Blvd Rampart Casino",
    "sg:city":"Las Vegas",
    "sg:classifiers":[
        {
            "category":"Restaurant",
            "type":"Food & Drink"
        }
    ],
    "sg:phone":"+1 702 507 5900",
    "sg:postcode":"89145",
    "sg:province":"NV",
    "sg:tags":[
        "buffet"
    ],
    "sg:website":"www.rampartcasino.com/buffet.htm",
    "wof:name":"Rampart Buffet",
    "wof:placetype":"venue"
},
  "geometry": {"coordinates":[-115.290595,36.175699],"type":"Point"}
}