{
  "type": "Feature",
  "properties": {
    "iso:country":"US",
    "sg:address":"3634 Emerald Beach Ct",
    "sg:city":"Las Vegas",
    "sg:classifiers":[
        {
            "category":"Restaurant",
            "type":"Food & Drink"
        }
    ],
    "sg:phone":"+1 702 228 2123",
    "sg:postcode":"89147",
    "sg:province":"NV",
    "sg:tags":[
        "caterer"
    ],
    "wof:name":"Ambrosia Events",
    "wof:placetype":"venue"
},
  "geometry": {"coordinates":[-115.29030400000001,36.123108],"type":"Point"}
}