{
  "type": "Feature",
  "properties": {
    "iso:country":"US",
    "sg:address":"1290 W Warm Springs Rd",
    "sg:city":"Henderson",
    "sg:classifiers":[
        {
            "category":"Restaurant",
            "type":"Food & Drink"
        }
    ],
    "sg:menulink":"http://www.allmenus.com/nv/las-vegas/121580-fazolis/menu/",
    "sg:phone":"+1 702 454 1136",
    "sg:postcode":"89014",
    "sg:province":"NV",
    "sg:tags":[
        "italian"
    ],
    "wof:name":"Fazoli's",
    "wof:placetype":"venue"
},
  "geometry": {"coordinates":[-115.041527,36.056732],"type":"Point"}
}