{
  "type": "Feature",
  "properties": {
    "iso:country":"US",
    "sg:address":"4000 Boulder Hwy",
    "sg:city":"Las Vegas",
    "sg:classifiers":[
        {
            "category":"Personal",
            "subcategory":"Beauty Salon",
            "type":"Services"
        }
    ],
    "sg:phone":"+1 702 457 5250",
    "sg:postcode":"89121",
    "sg:province":"NV",
    "sg:tags":[
        "shop"
    ],
    "wof:name":"Shear Action Styling Center",
    "wof:placetype":"venue"
},
  "geometry": {"coordinates":[-115.085246,36.131299],"type":"Point"}
}