{
  "type": "Feature",
  "properties": {
    "iso:country":"US",
    "sg:address":"3665 S Fort Apache Rd",
    "sg:city":"Las Vegas",
    "sg:classifiers":[
        {
            "category":"Sports & Exercise",
            "subcategory":"Gym",
            "type":"Entertainment"
        }
    ],
    "sg:phone":"+1 702 804 2639",
    "sg:postcode":"89147",
    "sg:province":"NV",
    "sg:tags":[
        "club",
        "health",
        "studio",
        "gymnasium"
    ],
    "wof:name":"Beach Bodies Personal Fitness",
    "wof:placetype":"venue"
},
  "geometry": {"coordinates":[-115.296944,36.121442],"type":"Point"}
}