{
  "type": "Feature",
  "properties": {
    "iso:country":"US",
    "sg:address":"1315 Winter Solstice Ave",
    "sg:city":"Henderson",
    "sg:classifiers":[
        {
            "category":"Professional",
            "type":"Services"
        }
    ],
    "sg:phone":"+1 702 454 3164",
    "sg:postcode":"89014",
    "sg:province":"NV",
    "wof:name":"Dons Powerful Medicine Water",
    "wof:placetype":"venue"
},
  "geometry": {"coordinates":[-115.042444,36.049281],"type":"Point"}
}