{
  "type": "Feature",
  "properties": {
    "iso:country":"US",
    "sg:address":"1605 Stitzel Rd",
    "sg:city":"Elko",
    "sg:classifiers":[
        {
            "category":"Retail",
            "subcategory":"Veterinary Services",
            "type":"Services"
        }
    ],
    "sg:phone":"+1 775 753 7624",
    "sg:postcode":"89801",
    "sg:province":"NV",
    "sg:tags":[
        "hospital",
        "animal"
    ],
    "wof:name":"Hanks Veterinary Svc",
    "wof:placetype":"venue"
},
  "geometry": {"coordinates":[-115.728731,40.830259],"type":"Point"}
}