{
  "type": "Feature",
  "properties": {
    "iso:country":"US",
    "sg:address":"355 Sage St",
    "sg:city":"Reno",
    "sg:classifiers":[
        {
            "category":"Wholesale",
            "subcategory":"Motor Vehicles",
            "type":"Manufacturing & Wholesale Goods"
        }
    ],
    "sg:phone":"+1 775 786 6534",
    "sg:postcode":"89512",
    "sg:province":"NV",
    "sg:tags":[
        "body",
        "equipment",
        "truck"
    ],
    "wof:name":"Jordan's Thermo King Inc",
    "wof:placetype":"venue"
},
  "geometry": {"coordinates":[-119.79396,39.532551],"type":"Point"}
}