{
  "type": "Feature",
  "properties": {
    "iso:country":"US",
    "sg:address":"3732 Dorrington Dr",
    "sg:city":"Las Vegas",
    "sg:classifiers":[
        {
            "category":"Wholesale",
            "subcategory":"Medical Equipment & Supplies",
            "type":"Manufacturing & Wholesale Goods"
        }
    ],
    "sg:phone":"+1 702 254 6343",
    "sg:postcode":"89129",
    "sg:province":"NV",
    "sg:tags":[
        "physician",
        "surgeon"
    ],
    "wof:name":"Ethicon Inc",
    "wof:placetype":"venue"
},
  "geometry": {"coordinates":[-115.293672,36.228976],"type":"Point"}
}