{
  "type": "Feature",
  "properties": {
    "iso:country":"US",
    "sg:address":"83 Penrose Ln",
    "sg:city":"Yerington",
    "sg:classifiers":[
        {
            "category":"Building & Trades",
            "subcategory":"Construction",
            "type":"Services"
        }
    ],
    "sg:phone":"+1 775 463 2772",
    "sg:postcode":"89447",
    "sg:province":"NV",
    "sg:tags":[
        "contractor",
        "general"
    ],
    "wof:name":"Sierra Nevada Builders Inc",
    "wof:placetype":"venue"
},
  "geometry": {"coordinates":[-119.165971,39.098925],"type":"Point"}
}