{
  "type": "Feature",
  "properties": {
    "iso:country":"US",
    "sg:address":"2159 Lander St",
    "sg:city":"Reno",
    "sg:classifiers":[
        {
            "category":"Professional",
            "type":"Services"
        }
    ],
    "sg:phone":"+1 775 827 8646",
    "sg:postcode":"89509",
    "sg:province":"NV",
    "wof:name":"Mallorys Gallery",
    "wof:placetype":"venue"
},
  "geometry": {"coordinates":[-119.815588,39.502871],"type":"Point"}
}