{
  "type": "Feature",
  "properties": {
    "iso:country":"US",
    "sg:address":"5482 E Lake Mead Blvd Ste 110",
    "sg:city":"Las Vegas",
    "sg:classifiers":[
        {
            "category":"Food & Beverages",
            "subcategory":"Groceries & Convenience Stores",
            "type":"Retail Goods"
        }
    ],
    "sg:phone":"+1 702 437 5300",
    "sg:postcode":"89156",
    "sg:province":"NV",
    "wof:name":"Carniceria El Tapatio",
    "wof:placetype":"venue"
},
  "geometry": {"coordinates":[-115.053133,36.196401],"type":"Point"}
}