{
  "type": "Feature",
  "properties": {
    "iso:country":"US",
    "sg:address":"3325 W Sahara Ave",
    "sg:city":"Las Vegas",
    "sg:classifiers":[
        {
            "category":"Banks & Credit Unions",
            "subcategory":"Bank",
            "type":"Services"
        }
    ],
    "sg:phone":"+1 702 227 4888",
    "sg:postcode":"89102",
    "sg:province":"NV",
    "sg:tags":[
        "loan"
    ],
    "wof:name":"Koster's Cash Loans",
    "wof:placetype":"venue"
},
  "geometry": {"coordinates":[-115.18642199999999,36.144309],"type":"Point"}
}