{
  "type": "Feature",
  "properties": {
    "iso:country":"US",
    "sg:address":"953 E Sahara Avenue",
    "sg:city":"Las Vegas",
    "sg:classifiers":[
        {
            "category":"Shopping",
            "subcategory":"Adult",
            "type":"Retail Goods"
        }
    ],
    "sg:phone":"+1 702 732 4656",
    "sg:postcode":"89104",
    "sg:province":"NV",
    "sg:tags":[
        "entertainment"
    ],
    "sg:website":"www.greendoorlv.com",
    "wof:name":"The Green Door",
    "wof:placetype":"venue"
},
  "geometry": {"coordinates":[-115.141148,36.143676],"type":"Point"}
}