{
  "type": "Feature",
  "properties": {
    "iso:country":"US",
    "sg:address":"3010 S Highland Dr",
    "sg:city":"Las Vegas",
    "sg:classifiers":[
        {
            "category":"Wholesale",
            "subcategory":"Hardware",
            "type":"Manufacturing & Wholesale Goods"
        }
    ],
    "sg:phone":"+1 702 894 9100",
    "sg:postcode":"89109",
    "sg:province":"NV",
    "sg:tags":[
        "parts",
        "refrigerating"
    ],
    "wof:name":"United Refrigeration",
    "wof:placetype":"venue"
},
  "geometry": {"coordinates":[-115.17324499999999,36.136882],"type":"Point"}
}