{
  "type": "Feature",
  "properties": {
    "iso:country":"US",
    "sg:address":"1760 S Rainbow Boulevard",
    "sg:city":"Las Vegas",
    "sg:classifiers":[
        {
            "category":"Restaurant",
            "type":"Food & Drink"
        }
    ],
    "sg:phone":"+1 702 877 3314",
    "sg:postcode":"89146",
    "sg:province":"NV",
    "sg:website":"www.wienerschnitzel.com",
    "wof:name":"Wienerschnitzel",
    "wof:placetype":"venue"
},
  "geometry": {"coordinates":[-115.243292,36.152288],"type":"Point"}
}