{
  "type": "Feature",
  "properties": {
    "iso:country":"US",
    "sg:address":"124 S 11th St",
    "sg:city":"Las Vegas",
    "sg:classifiers":[
        {
            "category":"Bars & Pubs",
            "type":"Food & Drink"
        }
    ],
    "sg:phone":"+1 702 384 4536",
    "sg:postcode":"89101",
    "sg:province":"NV",
    "sg:tags":[
        "lounge",
        "cocktail"
    ],
    "wof:name":"Bunkhouse",
    "wof:placetype":"venue"
},
  "geometry": {"coordinates":[-115.134452,36.165448],"type":"Point"}
}