{
  "type": "Feature",
  "properties": {
    "iso:country":"US",
    "sg:address":"1111 Clubhouse Dr",
    "sg:city":"Reno",
    "sg:classifiers":[
        {
            "category":"Sports & Exercise",
            "subcategory":"Golf",
            "type":"Entertainment"
        }
    ],
    "sg:phone":"+1 775 747 7577",
    "sg:postcode":"89523",
    "sg:province":"NV",
    "sg:tags":[
        "course",
        "courses-private"
    ],
    "wof:name":"Northgate Golf Club",
    "wof:placetype":"venue"
},
  "geometry": {"coordinates":[-119.900375,39.533242],"type":"Point"}
}