{
  "type": "Feature",
  "properties": {
    "iso:country":"US",
    "sg:address":"220 W Country Club Dr",
    "sg:city":"Henderson",
    "sg:classifiers":[
        {
            "category":"Professional",
            "type":"Services"
        },
        {
            "category":"Shopping",
            "type":"Retail Goods"
        }
    ],
    "sg:phone":"+1 702 564 5510",
    "sg:postcode":"89015",
    "sg:province":"NV",
    "sg:tags":[
        "mural"
    ],
    "sg:website":"www.beckmannstudio.com",
    "wof:name":"Beckmann Robert Studio",
    "wof:placetype":"venue"
},
  "geometry": {"coordinates":[-114.99139700000001,36.019894],"type":"Point"}
}