{
  "type": "Feature",
  "properties": {
    "iso:country":"US",
    "sg:address":"2050 Villanova Dr",
    "sg:city":"Reno",
    "sg:phone":"+1 775 348 7433",
    "sg:postcode":"89502",
    "sg:province":"NV",
    "sg:website":"http://www.rtcwashoe.com",
    "wof:name":"RTC RIDE",
    "wof:placetype":"venue"
},
  "geometry": {"coordinates":[-119.78161299999999,39.509415],"type":"Point"}
}