{
  "type": "Feature",
  "properties": {
    "iso:country":"US",
    "sg:address":"5472 Burkshire Drive",
    "sg:city":"Las Vegas",
    "sg:classifiers":[
        {
            "category":"Building & Trades",
            "subcategory":"Construction",
            "type":"Services"
        }
    ],
    "sg:phone":"+1 702 432 2812",
    "sg:postcode":"89142",
    "sg:province":"NV",
    "sg:tags":[
        "contractor"
    ],
    "wof:name":"Nesco Construction",
    "wof:placetype":"venue"
},
  "geometry": {"coordinates":[-115.05492099999999,36.157323],"type":"Point"}
}