{
  "type": "Feature",
  "properties": {
    "iso:country":"US",
    "sg:address":"408 S Boulder Hwy",
    "sg:city":"Henderson",
    "sg:classifiers":[
        {
            "category":"Retail",
            "subcategory":"Auto Repair",
            "type":"Services"
        }
    ],
    "sg:phone":"+1 702 564 5566",
    "sg:postcode":"89015",
    "sg:province":"NV",
    "wof:name":"Pep Boys Automotive Supercenters",
    "wof:placetype":"venue"
},
  "geometry": {"coordinates":[-114.975258,36.03461],"type":"Point"}
}