{
  "type": "Feature",
  "properties": {
    "iso:country":"US",
    "sg:address":"9090 Alta Dr Suncoast Casino",
    "sg:city":"Las Vegas",
    "sg:classifiers":[
        {
            "category":"Bagels",
            "subcategory":"None",
            "type":"Food & Drink"
        }
    ],
    "sg:phone":"+1 702 636 7111",
    "sg:postcode":"89136",
    "sg:province":"NV",
    "wof:name":"Bagel Cafe Express",
    "wof:placetype":"venue"
},
  "geometry": {"coordinates":[-115.295043,36.168443],"type":"Point"}
}