{
  "type": "Feature",
  "properties": {
    "iso:country":"US",
    "sg:address":"2550 Prince Edward Dr",
    "sg:city":"Henderson",
    "sg:classifiers":[
        {
            "category":"Wholesale",
            "subcategory":"Durable Goods & Equipment",
            "type":"Manufacturing & Wholesale Goods"
        }
    ],
    "sg:phone":"+1 702 876 6438",
    "sg:postcode":"89052",
    "sg:province":"NV",
    "sg:tags":[
        "importer"
    ],
    "wof:name":"World Wide Import Group Inc",
    "wof:placetype":"venue"
},
  "geometry": {"coordinates":[-115.096069,35.998435],"type":"Point"}
}