{
  "type": "Feature",
  "properties": {
    "iso:country":"US",
    "sg:address":"1632 F St",
    "sg:city":"Sparks",
    "sg:classifiers":[
        {
            "category":"Professional",
            "subcategory":"Management & Consulting",
            "type":"Services"
        }
    ],
    "sg:phone":"+1 775 356 8899",
    "sg:postcode":"89431",
    "sg:province":"NV",
    "sg:tags":[
        "business"
    ],
    "wof:name":"Barbara Knutson",
    "wof:placetype":"venue"
},
  "geometry": {"coordinates":[-119.765,39.538951],"type":"Point"}
}