{
  "type": "Feature",
  "properties": {
    "iso:country":"US",
    "sg:address":"6001 S Decatur Blvd",
    "sg:city":"Las Vegas",
    "sg:classifiers":[
        {
            "category":"Wholesale",
            "subcategory":"Medical Equipment & Supplies",
            "type":"Manufacturing & Wholesale Goods"
        }
    ],
    "sg:phone":"+1 702 434 3030",
    "sg:postcode":"89118",
    "sg:province":"NV",
    "sg:tags":[
        "physician",
        "surgeon"
    ],
    "wof:name":"Ability Center",
    "wof:placetype":"venue"
},
  "geometry": {"coordinates":[-115.207978,36.08081],"type":"Point"}
}