{
  "type": "Feature",
  "properties": {
    "iso:country":"US",
    "sg:address":"6156 Bing Cherry Dr",
    "sg:city":"Las Vegas",
    "sg:classifiers":[
        {
            "category":"Social Services",
            "subcategory":"Adult Care",
            "type":"Services"
        }
    ],
    "sg:phone":"+1 702 457 2315",
    "sg:postcode":"89142",
    "sg:province":"NV",
    "sg:tags":[
        "home",
        "residential"
    ],
    "wof:name":"Quality Guest Home",
    "wof:placetype":"venue"
},
  "geometry": {"coordinates":[-115.03868300000001,36.15395],"type":"Point"}
}