{
  "type": "Feature",
  "properties": {
    "iso:country":"US",
    "sg:address":"3520 W Reno Ave",
    "sg:city":"Las Vegas",
    "sg:classifiers":[
        {
            "category":"Manufacturing",
            "subcategory":"Food",
            "type":"Manufacturing & Wholesale Goods"
        }
    ],
    "sg:phone":"+1 702 942 2000",
    "sg:postcode":"89118",
    "sg:province":"NV",
    "sg:tags":[
        "durable",
        "trade"
    ],
    "sg:website":"www.grappo.com",
    "wof:name":"Gig Inc",
    "wof:placetype":"venue"
},
  "geometry": {"coordinates":[-115.18723,36.097338],"type":"Point"}
}