{
  "type": "Feature",
  "properties": {
    "iso:country":"US",
    "sg:address":"3006 S Maryland Pkwy",
    "sg:city":"Las Vegas",
    "sg:classifiers":[
        {
            "category":"Health Services",
            "subcategory":"Doctor",
            "type":"Services"
        }
    ],
    "sg:phone":"+1 702 671 5140",
    "sg:postcode":"89109",
    "sg:province":"NV",
    "wof:name":"Chudacoff Richard MD",
    "wof:placetype":"venue"
},
  "geometry": {"coordinates":[-115.13666000000001,36.135801],"type":"Point"}
}