{
  "type": "Feature",
  "properties": {
    "iso:country":"US",
    "sg:address":"3131 High View Dr",
    "sg:city":"Henderson",
    "sg:classifiers":[
        {
            "category":"Freight",
            "type":"Transportation"
        }
    ],
    "sg:phone":"+1 702 434 5444",
    "sg:postcode":"89014",
    "sg:province":"NV",
    "sg:tags":[
        "delivery"
    ],
    "wof:name":"B B & D Courier & Delivery",
    "wof:placetype":"venue"
},
  "geometry": {"coordinates":[-115.086032,36.067142],"type":"Point"}
}