{
  "type": "Feature",
  "properties": {
    "iso:country":"US",
    "sg:address":"3360 W Sahara Avenue Suite 110",
    "sg:city":"Las Vegas",
    "sg:classifiers":[
        {
            "category":"Professional",
            "type":"Services"
        }
    ],
    "sg:phone":"+1 702 222 0594",
    "sg:postcode":"89102",
    "sg:province":"NV",
    "sg:tags":[
        "caterer"
    ],
    "wof:name":"Courtyard Deli",
    "wof:placetype":"venue"
},
  "geometry": {"coordinates":[-115.18615,36.144518],"type":"Point"}
}