{
  "type": "Feature",
  "properties": {
    "iso:country":"US",
    "sg:address":"3535 W Tropicana Ave",
    "sg:city":"Las Vegas",
    "sg:classifiers":[
        {
            "category":"Autos & Motor Vehicles",
            "subcategory":"Motorcycle Sales",
            "type":"Retail Goods"
        }
    ],
    "sg:phone":"+1 702 795 2000",
    "sg:postcode":"89103",
    "sg:province":"NV",
    "wof:name":"Carter Powersports",
    "wof:placetype":"venue"
},
  "geometry": {"coordinates":[-115.185997,36.1007],"type":"Point"}
}