{
  "type": "Feature",
  "properties": {
    "iso:country":"US",
    "sg:address":"2016 E Charleston Blvd",
    "sg:city":"Las Vegas",
    "sg:classifiers":[
        {
            "category":"Shopping",
            "subcategory":"Tobacco",
            "type":"Retail Goods"
        }
    ],
    "sg:phone":"+1 702 384 5799",
    "sg:postcode":"89104",
    "sg:province":"NV",
    "sg:tags":[
        "shop"
    ],
    "wof:name":"J & R Smoke Shop",
    "wof:placetype":"venue"
},
  "geometry": {"coordinates":[-115.120854,36.15871],"type":"Point"}
}