{
  "type": "Feature",
  "properties": {
    "iso:country":"US",
    "sg:address":"7900 Thorne Pine Ave",
    "sg:city":"Las Vegas",
    "sg:classifiers":[
        {
            "category":"Professional",
            "subcategory":"Management & Consulting",
            "type":"Services"
        }
    ],
    "sg:phone":"+1 702 656 8170",
    "sg:postcode":"89131",
    "sg:province":"NV",
    "wof:name":"Nevada Marketing Products",
    "wof:placetype":"venue"
},
  "geometry": {"coordinates":[-115.266838,36.29792],"type":"Point"}
}