{
  "type": "Feature",
  "properties": {
    "iso:country":"US",
    "sg:address":"4419 Sophia Way",
    "sg:city":"North Las Vegas",
    "sg:classifiers":[
        {
            "category":"Building & Trades",
            "subcategory":"Construction",
            "type":"Services"
        }
    ],
    "sg:phone":"+1 702 655 0167",
    "sg:postcode":"89032",
    "sg:province":"NV",
    "sg:tags":[
        "handyman"
    ],
    "wof:name":"Handyman Help",
    "wof:placetype":"venue"
},
  "geometry": {"coordinates":[-115.199912,36.225818],"type":"Point"}
}