{
  "type": "Feature",
  "properties": {
    "iso:country":"US",
    "sg:address":"3990 W Dewey Dr",
    "sg:city":"Las Vegas",
    "sg:classifiers":[
        {
            "category":"Freight",
            "type":"Transportation"
        },
        {
            "category":"Building & Trades",
            "subcategory":"Equipment Rental",
            "type":"Services"
        }
    ],
    "sg:phone":"+1 702 451 5553",
    "sg:postcode":"89118",
    "sg:province":"NV",
    "sg:tags":[
        "commercial",
        "storage",
        "general"
    ],
    "wof:name":"Miller's U-Rent-Um",
    "wof:placetype":"venue"
},
  "geometry": {"coordinates":[-115.191191,36.088214],"type":"Point"}
}