{
  "type": "Feature",
  "properties": {
    "iso:country":"US",
    "sg:address":"2090 Poppywood Ave",
    "sg:city":"Henderson",
    "sg:classifiers":[
        {
            "category":"Shopping",
            "subcategory":"Shoes",
            "type":"Retail Goods"
        }
    ],
    "sg:phone":"+1 702 837 0812",
    "sg:postcode":"89012",
    "sg:province":"NV",
    "wof:name":"Soldati",
    "wof:placetype":"venue"
},
  "geometry": {"coordinates":[-115.074197,36.009012],"type":"Point"}
}