{
  "type": "Feature",
  "properties": {
    "iso:country":"US",
    "sg:address":"1710 Sunrise Pass Rd",
    "sg:city":"Minden",
    "sg:classifiers":[
        {
            "category":"Professional",
            "subcategory":"Computer Services",
            "type":"Services"
        }
    ],
    "sg:phone":"+1 775 267 2782",
    "sg:postcode":"89423",
    "sg:province":"NV",
    "sg:tags":[
        "repair"
    ],
    "wof:name":"Computer Physician Unlimited",
    "wof:placetype":"venue"
},
  "geometry": {"coordinates":[-119.704598,39.012322],"type":"Point"}
}