{
  "type": "Feature",
  "properties": {
    "iso:country":"US",
    "sg:address":"2080 N Rainbow Blvd",
    "sg:city":"Las Vegas",
    "sg:classifiers":[
        {
            "category":"Restaurant",
            "type":"Food & Drink"
        }
    ],
    "sg:phone":"+1 702 648 1957",
    "sg:postcode":"89108",
    "sg:province":"NV",
    "sg:tags":[
        "traditional",
        "american",
        "buffet"
    ],
    "sg:website":"www.sweettomatoes.com",
    "wof:name":"Sweet Tomatoes",
    "wof:placetype":"venue"
},
  "geometry": {"coordinates":[-115.241997,36.198601],"type":"Point"}
}