{
  "type": "Feature",
  "properties": {
    "iso:country":"US",
    "sg:address":"4455 Paradise Rd",
    "sg:city":"Paradise",
    "sg:classifiers":[
        {
            "category":"Restaurant",
            "type":"Food & Drink"
        }
    ],
    "sg:postcode":"89169",
    "sg:province":"NV",
    "wof:name":"Espumoso Cafe",
    "wof:placetype":"venue"
},
  "geometry": {"coordinates":[-115.154455,36.109768],"type":"Point"}
}