{
  "type": "Feature",
  "properties": {
    "iso:country":"US",
    "sg:address":"3850 Las Vegas Blvd S",
    "sg:city":"Las Vegas",
    "sg:classifiers":[
        {
            "category":"Personal",
            "type":"Services"
        }
    ],
    "sg:phone":"+1 702 597 7278",
    "sg:postcode":"89109",
    "sg:province":"NV",
    "sg:tags":[
        "wedding",
        "chapel"
    ],
    "sg:website":"www.excaliburcasino.com",
    "wof:name":"Canterbury Wedding Chapels",
    "wof:placetype":"venue"
},
  "geometry": {"coordinates":[-115.172998,36.09923],"type":"Point"}
}