{
  "type": "Feature",
  "properties": {
    "iso:country":"US",
    "sg:address":"730 W Cheyenne Ave Ste 160",
    "sg:city":"North Las Vegas",
    "sg:classifiers":[
        {
            "category":"Professional",
            "subcategory":"Employment Agencies",
            "type":"Services"
        }
    ],
    "sg:phone":"+1 702 565 0032",
    "sg:postcode":"89030",
    "sg:province":"NV",
    "sg:website":"www.staffmark.com",
    "wof:name":"Staffmark",
    "wof:placetype":"venue"
},
  "geometry": {"coordinates":[-115.150989,36.217927],"type":"Point"}
}