{
  "type": "Feature",
  "properties": {
    "iso:country":"US",
    "sg:address":"5908 Losee Rd",
    "sg:city":"North Las Vegas",
    "sg:classifiers":[
        {
            "category":"Professional",
            "subcategory":"Business Services",
            "type":"Services"
        }
    ],
    "sg:phone":"+1 702 234 4905",
    "sg:postcode":"89030",
    "sg:province":"NV",
    "sg:tags":[
        "pool",
        "swimming"
    ],
    "wof:name":"Azure Blue Pool Svc",
    "wof:placetype":"venue"
},
  "geometry": {"coordinates":[-115.116853,36.266408],"type":"Point"}
}