{
  "type": "Feature",
  "properties": {
    "iso:country":"US",
    "sg:address":"1849 W Cheyenne Ave",
    "sg:city":"North Las Vegas",
    "sg:classifiers":[
        {
            "category":"Wholesale",
            "subcategory":"Wine & Distilled Alcoholic Beverages",
            "type":"Manufacturing & Wholesale Goods"
        }
    ],
    "sg:phone":"+1 702 735 9141",
    "sg:postcode":"89108",
    "sg:province":"NV",
    "sg:tags":[
        "liquor"
    ],
    "sg:website":"www.delucaliquor.com",
    "wof:name":"Deluca Liquor & Wine LTD",
    "wof:placetype":"venue"
},
  "geometry": {"coordinates":[-115.18789,36.188515],"type":"Point"}
}