{
  "type": "Feature",
  "properties": {
    "iso:country":"US",
    "sg:address":"2800 N Tenaya Way # 201",
    "sg:city":"Las Vegas",
    "sg:classifiers":[
        {
            "category":"Health Services",
            "subcategory":"Doctor",
            "type":"Services"
        }
    ],
    "sg:phone":"+1 702 242 4616",
    "sg:postcode":"89152",
    "sg:province":"NV",
    "sg:tags":[
        "surgeon",
        "cosmetic"
    ],
    "wof:name":"SW Institute of Plastic & Reconstructive Surgery",
    "wof:placetype":"venue"
},
  "geometry": {"coordinates":[-115.192001,36.172001],"type":"Point"}
}