{
  "type": "Feature",
  "properties": {
    "iso:country":"US",
    "sg:address":"3516 Coran Ln",
    "sg:city":"Las Vegas",
    "sg:classifiers":[
        {
            "category":"Professional",
            "type":"Services"
        }
    ],
    "sg:phone":"+1 702 646 1010",
    "sg:postcode":"89106",
    "sg:province":"NV",
    "sg:tags":[
        "establishment"
    ],
    "wof:name":"Ln Shadow Facts LA 3516 Coran",
    "wof:placetype":"venue"
},
  "geometry": {"coordinates":[-115.187693,36.195709],"type":"Point"}
}