{
  "type": "Feature",
  "properties": {
    "iso:country":"US",
    "sg:address":"3700 W Flamingo Rd",
    "sg:city":"Las Vegas",
    "sg:classifiers":[
        {
            "category":"Restaurant",
            "type":"Food & Drink"
        }
    ],
    "sg:menulink":"http://www.allmenus.com/nv/las-vegas/9811-bamboleo/menu/",
    "sg:phone":"+1 702 777 7923",
    "sg:postcode":"89103",
    "sg:province":"NV",
    "sg:tags":[
        "mexican"
    ],
    "wof:name":"Bamboleo",
    "wof:placetype":"venue"
},
  "geometry": {"coordinates":[-115.188534,36.115595],"type":"Point"}
}