{
  "type": "Feature",
  "properties": {
    "iso:country":"US",
    "sg:address":"2320 S Rancho Dr",
    "sg:city":"Las Vegas",
    "sg:classifiers":[
        {
            "category":"Education",
            "subcategory":"Junior College",
            "type":"Public Place"
        }
    ],
    "sg:phone":"+1 702 385 6700",
    "sg:postcode":"89102",
    "sg:province":"NV",
    "sg:tags":[
        "technical",
        "institute"
    ],
    "sg:website":"www.hightechschools.com",
    "wof:name":"High-Tech Institute Inc",
    "wof:placetype":"venue"
},
  "geometry": {"coordinates":[-115.17320100000001,36.144501],"type":"Point"}
}