{
  "type": "Feature",
  "properties": {
    "iso:country":"US",
    "sg:address":"3425 Dux Ave",
    "sg:city":"Elko",
    "sg:classifiers":[
        {
            "category":"Professional",
            "subcategory":"Management & Consulting",
            "type":"Services"
        }
    ],
    "sg:phone":"+1 775 753 6092",
    "sg:postcode":"89801",
    "sg:province":"NV",
    "sg:tags":[
        "consultant",
        "business"
    ],
    "wof:name":"Center For Advanced Management",
    "wof:placetype":"venue"
},
  "geometry": {"coordinates":[-115.79276900000001,40.846596],"type":"Point"}
}