{
  "type": "Feature",
  "properties": {
    "iso:country":"US",
    "sg:address":"8540 S Maryland Parkway",
    "sg:city":"Las Vegas",
    "sg:classifiers":[
        {
            "category":"Retail",
            "subcategory":"Laundry & Dry Cleaning",
            "type":"Services"
        }
    ],
    "sg:phone":"+1 702 458 1112",
    "sg:postcode":"89123",
    "sg:province":"NV",
    "wof:name":"Maple Cleaners",
    "wof:placetype":"venue"
},
  "geometry": {"coordinates":[-115.136202,36.034741],"type":"Point"}
}