{
  "type": "Feature",
  "properties": {
    "iso:country":"US",
    "sg:address":"840 King Richard Ave",
    "sg:city":"Las Vegas",
    "sg:classifiers":[
        {
            "category":"Retail",
            "subcategory":"Repair Shop",
            "type":"Services"
        }
    ],
    "sg:phone":"+1 702 217 7477",
    "sg:postcode":"89119",
    "sg:province":"NV",
    "wof:name":"Anytime Locksmith",
    "wof:placetype":"venue"
},
  "geometry": {"coordinates":[-115.145511,36.091129],"type":"Point"}
}