{
  "type": "Feature",
  "properties": {
    "iso:country":"US",
    "sg:address":"6970 Smoke Ranch Rd",
    "sg:city":"Las Vegas",
    "sg:classifiers":[
        {
            "category":"Health Services",
            "subcategory":"Dentist",
            "type":"Services"
        }
    ],
    "sg:phone":"+1 702 259 6725",
    "sg:postcode":"89128",
    "sg:province":"NV",
    "sg:website":"www.mountainvieworalsurgery.com",
    "wof:name":"Mountain View Oral Surgery",
    "wof:placetype":"venue"
},
  "geometry": {"coordinates":[-115.246269,36.203583],"type":"Point"}
}