{
  "type": "Feature",
  "properties": {
    "iso:country":"US",
    "sg:address":"900 W Moana Ln",
    "sg:city":"Reno",
    "sg:classifiers":[
        {
            "category":"Retail",
            "subcategory":"Laundry & Dry Cleaning",
            "type":"Services"
        }
    ],
    "sg:phone":"+1 775 827 1411",
    "sg:postcode":"89509",
    "sg:province":"NV",
    "sg:tags":[
        "drycleaning",
        "plant",
        "cleaners"
    ],
    "wof:name":"Fabric Care Specialist Inc",
    "wof:placetype":"venue"
},
  "geometry": {"coordinates":[-119.807898,39.491197],"type":"Point"}
}