{
  "type": "Feature",
  "properties": {
    "iso:country":"US",
    "sg:address":"3001 Ocean View Dr",
    "sg:city":"Las Vegas",
    "sg:classifiers":[
        {
            "category":"Professional",
            "subcategory":"Business Services",
            "type":"Services"
        }
    ],
    "sg:phone":"+1 702 254 7125",
    "sg:postcode":"89117",
    "sg:province":"NV",
    "wof:name":"If I Can Dream Interior Design",
    "wof:placetype":"venue"
},
  "geometry": {"coordinates":[-115.302366,36.13616],"type":"Point"}
}