{
  "type": "Feature",
  "properties": {
    "iso:country":"US",
    "sg:address":"280 N Jones Boulevard",
    "sg:city":"Las Vegas",
    "sg:classifiers":[
        {
            "category":"Restaurant",
            "type":"Food & Drink"
        }
    ],
    "sg:phone":"+1 702 870 0428",
    "sg:postcode":"89107",
    "sg:province":"NV",
    "sg:website":"www.deltaco.com",
    "wof:name":"Del Taco",
    "wof:placetype":"venue"
},
  "geometry": {"coordinates":[-115.223871,36.176349],"type":"Point"}
}