{
  "type": "Feature",
  "properties": {
    "iso:country":"US",
    "sg:address":"1816 Spring Summit Ln",
    "sg:city":"Las Vegas",
    "sg:classifiers":[
        {
            "category":"Professional",
            "subcategory":"Employment Agencies",
            "type":"Services"
        }
    ],
    "sg:phone":"+1 702 341 8153",
    "sg:postcode":"89134",
    "sg:province":"NV",
    "wof:name":"Alberg & Associates",
    "wof:placetype":"venue"
},
  "geometry": {"coordinates":[-115.315986,36.193377],"type":"Point"}
}