{
  "type": "Feature",
  "properties": {
    "iso:country":"US",
    "sg:address":"1051 Spoonbill Dr",
    "sg:city":"Sparks",
    "sg:classifiers":[
        {
            "category":"Recreation",
            "type":"Entertainment"
        }
    ],
    "sg:phone":"+1 775 424 4386",
    "sg:postcode":"89441",
    "sg:province":"NV",
    "wof:name":"Ultimate Bouncers",
    "wof:placetype":"venue"
},
  "geometry": {"coordinates":[-119.724104,39.657209],"type":"Point"}
}