{
  "type": "Feature",
  "properties": {
    "iso:country":"US",
    "sg:address":"575 College Drive",
    "sg:city":"Henderson",
    "sg:classifiers":[
        {
            "category":"Shopping",
            "subcategory":"Pharmacy",
            "type":"Retail Goods"
        }
    ],
    "sg:phone":"+1 702 568 0259",
    "sg:postcode":"89015",
    "sg:province":"NV",
    "sg:tags":[
        "drugstore"
    ],
    "wof:name":"Sav-On Pharmacy",
    "wof:placetype":"venue"
},
  "geometry": {"coordinates":[-114.963123,36.0138],"type":"Point"}
}