{
  "type": "Feature",
  "properties": {
    "iso:country":"US",
    "sg:address":"1205 S Maine St",
    "sg:city":"Fallon",
    "sg:classifiers":[
        {
            "category":"Building & Trades",
            "subcategory":"Cleaning & Sanitation",
            "type":"Services"
        }
    ],
    "sg:phone":"+1 775 423 5792",
    "sg:postcode":"89406",
    "sg:province":"NV",
    "wof:name":"D JS Cleaning",
    "wof:placetype":"venue"
},
  "geometry": {"coordinates":[-118.77712099999999,39.463898],"type":"Point"}
}