{
  "type": "Feature",
  "properties": {
    "iso:country":"US",
    "sg:address":"5724 Swimmer Dr",
    "sg:city":"Las Vegas",
    "sg:classifiers":[
        {
            "category":"Professional",
            "subcategory":"Business Services",
            "type":"Services"
        }
    ],
    "sg:phone":"+1 702 258 7446",
    "sg:postcode":"89110",
    "sg:province":"NV",
    "sg:tags":[
        "pool",
        "swimming"
    ],
    "wof:name":"Desert Island Pool & Spa",
    "wof:placetype":"venue"
},
  "geometry": {"coordinates":[-115.047416,36.172299],"type":"Point"}
}