{
  "type": "Feature",
  "properties": {
    "iso:country":"US",
    "sg:address":"3975 W Quail Ave",
    "sg:city":"Las Vegas",
    "sg:classifiers":[
        {
            "category":"Personal",
            "type":"Services"
        }
    ],
    "sg:phone":"+1 702 891 0655",
    "sg:postcode":"89118",
    "sg:province":"NV",
    "sg:tags":[
        "welcoming",
        "newcomer",
        "for"
    ],
    "wof:name":"Welcome Service",
    "wof:placetype":"venue"
},
  "geometry": {"coordinates":[-115.191915,36.084421],"type":"Point"}
}