{
  "type": "Feature",
  "properties": {
    "iso:country":"US",
    "sg:address":"2419 Morton Ave",
    "sg:city":"North Las Vegas",
    "sg:classifiers":[
        {
            "category":"Wholesale",
            "subcategory":"Electrical",
            "type":"Manufacturing & Wholesale Goods"
        }
    ],
    "sg:phone":"+1 702 646 2255",
    "sg:postcode":"89032",
    "sg:province":"NV",
    "sg:tags":[
        "control",
        "security",
        "system"
    ],
    "wof:name":"Action Security Svc",
    "wof:placetype":"venue"
},
  "geometry": {"coordinates":[-115.163141,36.203677],"type":"Point"}
}