{
  "type": "Feature",
  "properties": {
    "iso:country":"US",
    "sg:address":"590 Lakeshore Blvd Unit A",
    "sg:city":"Incline Village",
    "sg:classifiers":[
        {
            "category":"Professional",
            "subcategory":"Lawyer & Legal Services",
            "type":"Services"
        }
    ],
    "sg:phone":"+1 775 832 6800",
    "sg:postcode":"89451",
    "sg:province":"NV",
    "sg:website":"www.portersimonshadek.com",
    "wof:name":"Porter Simon & Shadek",
    "wof:placetype":"venue"
},
  "geometry": {"coordinates":[-119.99505,39.24834],"type":"Point"}
}