{
  "type": "Feature",
  "properties": {
    "iso:country":"US",
    "sg:address":"270 N Lake St",
    "sg:city":"Reno",
    "sg:classifiers":[
        {
            "category":"Restaurant",
            "type":"Food & Drink"
        }
    ],
    "sg:phone":"+1 775 786 7800",
    "sg:postcode":"89501",
    "sg:province":"NV",
    "sg:website":"www.mensclubofreno.com",
    "wof:name":"Men's Club Of Reno",
    "wof:placetype":"venue"
},
  "geometry": {"coordinates":[-119.810937,39.528496],"type":"Point"}
}