{
  "type": "Feature",
  "properties": {
    "iso:country":"US",
    "sg:address":"2963 Industrial Rd",
    "sg:city":"Las Vegas",
    "sg:classifiers":[
        {
            "category":"Retail",
            "subcategory":"Laundry & Dry Cleaning",
            "type":"Services"
        },
        {
            "category":"Shopping",
            "subcategory":"Clothing, Apparel, & Fashions",
            "type":"Retail Goods"
        }
    ],
    "sg:phone":"+1 702 732 0293",
    "sg:postcode":"89109",
    "sg:province":"NV",
    "sg:tags":[
        "dressmaker"
    ],
    "wof:name":"Annas Alterations",
    "wof:placetype":"venue"
},
  "geometry": {"coordinates":[-115.16502199999999,36.143798],"type":"Point"}
}