{
  "type": "Feature",
  "properties": {
    "iso:country":"US",
    "sg:address":"625 Sheehan St",
    "sg:city":"Winnemucca",
    "sg:classifiers":[
        {
            "category":"Wholesale",
            "subcategory":"Auto Parts",
            "type":"Manufacturing & Wholesale Goods"
        }
    ],
    "sg:phone":"+1 775 623 5200",
    "sg:postcode":"89445",
    "sg:province":"NV",
    "sg:tags":[
        "truck",
        "accessory"
    ],
    "wof:name":"Go Nuts Truck & Auto Acces",
    "wof:placetype":"venue"
},
  "geometry": {"coordinates":[-117.738699,40.965478],"type":"Point"}
}