{
  "type": "Feature",
  "properties": {
    "iso:country":"US",
    "sg:address":"333 N Rancho Dr",
    "sg:city":"Las Vegas",
    "sg:classifiers":[
        {
            "category":"Professional",
            "subcategory":"Employment Agencies",
            "type":"Services"
        }
    ],
    "sg:phone":"+1 702 638 1200",
    "sg:postcode":"89106",
    "sg:province":"NV",
    "sg:tags":[
        "personnel",
        "temporary"
    ],
    "wof:name":"Staffing Partners of Nevada",
    "wof:placetype":"venue"
},
  "geometry": {"coordinates":[-115.174905,36.176152],"type":"Point"}
}