{
  "type": "Feature",
  "properties": {
    "iso:country":"US",
    "sg:address":"213 Sage St",
    "sg:city":"Carson City",
    "sg:classifiers":[
        {
            "category":"Manufacturing",
            "subcategory":"Signs",
            "type":"Manufacturing & Wholesale Goods"
        }
    ],
    "sg:phone":"+1 775 283 0606",
    "sg:postcode":"89706",
    "sg:province":"NV",
    "wof:name":"Envision Signs",
    "wof:placetype":"venue"
},
  "geometry": {"coordinates":[-119.766712,39.181158],"type":"Point"}
}