{
  "type": "Feature",
  "properties": {
    "iso:country":"US",
    "sg:address":"350 Short St",
    "sg:city":"Gerlach",
    "sg:classifiers":[
        {
            "category":"Health Services",
            "subcategory":"Doctor",
            "type":"Services"
        }
    ],
    "sg:phone":"+1 775 557 2312",
    "sg:postcode":"89412",
    "sg:province":"NV",
    "sg:tags":[
        "clinic"
    ],
    "wof:name":"Gerlach Medical Clinic",
    "wof:placetype":"venue"
},
  "geometry": {"coordinates":[-119.355656,40.653315],"type":"Point"}
}