{
  "type": "Feature",
  "properties": {
    "iso:country":"US",
    "sg:address":"127 E Warm Springs Rd",
    "sg:city":"Las Vegas",
    "sg:classifiers":[
        {
            "category":"Banks & Credit Unions",
            "subcategory":"Bank",
            "type":"Services"
        }
    ],
    "sg:phone":"+1 702 851 3460",
    "sg:postcode":"89119",
    "sg:province":"NV",
    "sg:tags":[
        "escrow"
    ],
    "wof:name":"Sundance Escrow",
    "wof:placetype":"venue"
},
  "geometry": {"coordinates":[-115.166596,36.056854],"type":"Point"}
}