{
  "type": "Feature",
  "properties": {
    "iso:country":"US",
    "sg:address":"1406 Industrial Way",
    "sg:city":"Gardnerville",
    "sg:classifiers":[
        {
            "category":"Home & Garden",
            "subcategory":"Hardware",
            "type":"Retail Goods"
        }
    ],
    "sg:phone":"+1 775 782 5211",
    "sg:postcode":"89410",
    "sg:province":"NV",
    "wof:name":"Ace Hardware",
    "wof:placetype":"venue"
},
  "geometry": {"coordinates":[-119.73047200000001,38.930469],"type":"Point"}
}