{
  "type": "Feature",
  "properties": {
    "iso:country":"US",
    "sg:address":"2675 Spinnaker Dr",
    "sg:city":"Reno",
    "sg:classifiers":[
        {
            "category":"Professional",
            "subcategory":"Computer Services",
            "type":"Services"
        }
    ],
    "sg:phone":"+1 775 828 5085",
    "sg:postcode":"89519",
    "sg:province":"NV",
    "sg:tags":[
        "internet"
    ],
    "wof:name":"Big Planet",
    "wof:placetype":"venue"
},
  "geometry": {"coordinates":[-119.819937,39.472699],"type":"Point"}
}