{
  "type": "Feature",
  "properties": {
    "iso:country":"US",
    "sg:address":"7720 W Sahara Ave Ste 104",
    "sg:city":"Las Vegas",
    "sg:classifiers":[
        {
            "category":"Health Services",
            "subcategory":"Clinic",
            "type":"Services"
        }
    ],
    "sg:phone":"+1 702 514 0328",
    "sg:postcode":"89117",
    "sg:province":"NV",
    "sg:tags":[
        "loss",
        "weight"
    ],
    "sg:website":"www.shapewithin.com",
    "wof:name":"Shape Within",
    "wof:placetype":"venue"
},
  "geometry": {"coordinates":[-115.25971800000001,36.143788],"type":"Point"}
}