{
  "type": "Feature",
  "properties": {
    "iso:country":"US",
    "sg:address":"10504 Jeremy Ridge Ave",
    "sg:city":"Las Vegas",
    "sg:classifiers":[
        {
            "category":"Wholesale",
            "subcategory":"Non-durable Goods",
            "type":"Manufacturing & Wholesale Goods"
        }
    ],
    "sg:phone":"+1 702 765 9444",
    "sg:postcode":"89144",
    "sg:province":"NV",
    "sg:tags":[
        "jewelry"
    ],
    "wof:name":"Jem Services Inc",
    "wof:placetype":"venue"
},
  "geometry": {"coordinates":[-115.326887,36.189164],"type":"Point"}
}