{
  "type": "Feature",
  "properties": {
    "iso:country":"US",
    "sg:address":"123 Ocotillo St",
    "sg:city":"Henderson",
    "sg:classifiers":[
        {
            "category":"Shopping",
            "type":"Retail Goods"
        }
    ],
    "sg:phone":"+1 702 565 7841",
    "sg:postcode":"89015",
    "sg:province":"NV",
    "sg:tags":[
        "merchandise"
    ],
    "wof:name":"Mag Way",
    "wof:placetype":"venue"
},
  "geometry": {"coordinates":[-114.981145,36.043142],"type":"Point"}
}