{
  "type": "Feature",
  "properties": {
    "iso:country":"US",
    "sg:address":"2712 S Highland Dr",
    "sg:city":"Las Vegas",
    "sg:classifiers":[
        {
            "category":"Retail",
            "subcategory":"Auto Repair",
            "type":"Services"
        }
    ],
    "sg:phone":"+1 702 739 9818",
    "sg:postcode":"89109",
    "sg:province":"NV",
    "sg:tags":[
        "body",
        "automobile",
        "customizing",
        "automotive"
    ],
    "wof:name":"Musso Motor Sports",
    "wof:placetype":"venue"
},
  "geometry": {"coordinates":[-115.171767,36.139174],"type":"Point"}
}