{
  "type": "Feature",
  "properties": {
    "iso:country":"US",
    "sg:address":"4710 W Dewey Dr",
    "sg:city":"Las Vegas",
    "sg:classifiers":[
        {
            "category":"Building & Trades",
            "subcategory":"Construction",
            "type":"Services"
        }
    ],
    "sg:phone":"+1 702 480 2887",
    "sg:postcode":"89118",
    "sg:province":"NV",
    "sg:tags":[
        "woodworker"
    ],
    "wof:name":"Diamond Woodworks",
    "wof:placetype":"venue"
},
  "geometry": {"coordinates":[-115.206487,36.088092],"type":"Point"}
}