{
  "type": "Feature",
  "properties": {
    "iso:country":"US",
    "sg:address":"6325 N Commerce St",
    "sg:city":"North Las Vegas",
    "sg:classifiers":[
        {
            "category":"Retail",
            "subcategory":"Auto Repair",
            "type":"Services"
        }
    ],
    "sg:phone":"+1 702 633 7907",
    "sg:postcode":"89031",
    "sg:province":"NV",
    "sg:website":"www.honest-1nv.com",
    "wof:name":"Honest-1 Auto Care",
    "wof:placetype":"venue"
},
  "geometry": {"coordinates":[-115.144099,36.275092],"type":"Point"}
}