{
  "type": "Feature",
  "properties": {
    "iso:country":"US",
    "sg:address":"12693 Old Virginia Rd",
    "sg:city":"Reno",
    "sg:classifiers":[
        {
            "category":"Building & Trades",
            "subcategory":"Construction",
            "type":"Services"
        }
    ],
    "sg:phone":"+1 775 851 4289",
    "sg:postcode":"89521",
    "sg:province":"NV",
    "sg:tags":[
        "fabricator",
        "metal"
    ],
    "sg:website":"www.amf1.com",
    "wof:name":"Accurate Metal Fabricators",
    "wof:placetype":"venue"
},
  "geometry": {"coordinates":[-119.754274,39.421944],"type":"Point"}
}