{
  "type": "Feature",
  "properties": {
    "iso:country":"US",
    "sg:address":"8450 W Charleston Blvd",
    "sg:city":"Las Vegas",
    "sg:classifiers":[
        {
            "category":"Real Estate",
            "subcategory":"Real Estate Operator",
            "type":"Services"
        }
    ],
    "sg:phone":"+1 702 255 5222",
    "sg:postcode":"89117",
    "sg:province":"NV",
    "sg:tags":[
        "apartment"
    ],
    "wof:name":"Camden Apartment Homes",
    "wof:placetype":"venue"
},
  "geometry": {"coordinates":[-115.276224,36.161791],"type":"Point"}
}