{
  "type": "Feature",
  "properties": {
    "iso:country":"US",
    "sg:address":"3820 E Kolanut Ln",
    "sg:city":"Las Vegas",
    "sg:classifiers":[
        {
            "category":"Retail",
            "subcategory":"Repair Shop",
            "type":"Services"
        }
    ],
    "sg:phone":"+1 702 580 9096",
    "sg:postcode":"89115",
    "sg:province":"NV",
    "sg:tags":[
        "related"
    ],
    "wof:name":"Dennis R Paytas Design",
    "wof:placetype":"venue"
},
  "geometry": {"coordinates":[-115.091741,36.191663],"type":"Point"}
}