{
  "type": "Feature",
  "properties": {
    "iso:country":"US",
    "sg:address":"2373 Renaissance Dr",
    "sg:city":"Las Vegas",
    "sg:classifiers":[
        {
            "category":"Health Services",
            "subcategory":"Doctor",
            "type":"Services"
        }
    ],
    "sg:phone":"+1 702 736 1919",
    "sg:postcode":"89119",
    "sg:province":"NV",
    "sg:tags":[
        "medical"
    ],
    "wof:name":"Add Clinic",
    "wof:placetype":"venue"
},
  "geometry": {"coordinates":[-115.12,36.103594],"type":"Point"}
}