{
  "type": "Feature",
  "properties": {
    "iso:country":"US",
    "sg:address":"1009 S Main St",
    "sg:city":"Las Vegas",
    "sg:classifiers":[
        {
            "category":"Professional",
            "subcategory":"Business Services",
            "type":"Services"
        }
    ],
    "sg:phone":"+1 702 382 5900",
    "sg:postcode":"89101",
    "sg:province":"NV",
    "wof:name":"Certified Bail Bonds",
    "wof:placetype":"venue"
},
  "geometry": {"coordinates":[-115.153235,36.160059],"type":"Point"}
}