{
  "type": "Feature",
  "properties": {
    "iso:country":"US",
    "sg:address":"1301 W. Sunset Rd",
    "sg:city":"Henderson",
    "sg:classifiers":[
        {
            "category":"Restaurant",
            "type":"Food & Drink"
        }
    ],
    "sg:phone":"+1 702 547 7777",
    "sg:postcode":"89014",
    "sg:province":"NV",
    "sg:tags":[
        "seafood"
    ],
    "sg:website":"www.sunsetstation.com",
    "wof:name":"Oyster Bar at Sunset Station Casino",
    "wof:placetype":"venue"
},
  "geometry": {"coordinates":[-115.040954,36.060989],"type":"Point"}
}