{
  "type": "Feature",
  "properties": {
    "iso:country":"US",
    "sg:address":"6000 S Eastern Ave",
    "sg:city":"Las Vegas",
    "sg:classifiers":[
        {
            "category":"Manufacturing",
            "subcategory":"Metals",
            "type":"Manufacturing & Wholesale Goods"
        },
        {
            "category":"Manufacturing",
            "subcategory":"Tools & Machinery",
            "type":"Manufacturing & Wholesale Goods"
        }
    ],
    "sg:phone":"+1 702 262 3953",
    "sg:postcode":"89119",
    "sg:province":"NV",
    "sg:tags":[
        "fiber",
        "mfg",
        "process",
        "instr",
        "system",
        "an",
        "optics"
    ],
    "wof:name":"Fci Environmental Inc",
    "wof:placetype":"venue"
},
  "geometry": {"coordinates":[-115.118706,36.081757],"type":"Point"}
}