{
  "type": "Feature",
  "properties": {
    "iso:country":"US",
    "sg:address":"Grand Canal Shops 3377 Las Vegas Blvd S Ste 2600",
    "sg:city":"Las Vegas",
    "sg:classifiers":[
        {
            "category":"Shopping",
            "subcategory":"Department Store",
            "type":"Retail Goods"
        }
    ],
    "sg:phone":"+1 702 414 7463",
    "sg:postcode":"89109",
    "sg:province":"NV",
    "wof:name":"The Walking Company",
    "wof:placetype":"venue"
},
  "geometry": {"coordinates":[-115.17140000000001,36.12125],"type":"Point"}
}