{
  "type": "Feature",
  "properties": {
    "iso:country":"US",
    "sg:address":"955 Deming Way",
    "sg:city":"Sparks",
    "sg:classifiers":[
        {
            "category":"Wholesale",
            "subcategory":"Metals & Minerals",
            "type":"Manufacturing & Wholesale Goods"
        }
    ],
    "sg:phone":"+1 775 359 1200",
    "sg:postcode":"89431",
    "sg:province":"NV",
    "sg:tags":[
        "concrete",
        "reinforcement"
    ],
    "wof:name":"Farwest Steel Corp",
    "wof:placetype":"venue"
},
  "geometry": {"coordinates":[-119.722201,39.526455],"type":"Point"}
}