{
  "type": "Feature",
  "properties": {
    "iso:country":"US",
    "sg:address":"2301 Las Verdes Street",
    "sg:city":"Las Vegas",
    "sg:classifiers":[
        {
            "category":"Education",
            "subcategory":"Preschool",
            "type":"Public Place"
        },
        {
            "category":"Education",
            "subcategory":"School",
            "type":"Public Place"
        }
    ],
    "sg:phone":"+1 702 871 0600",
    "sg:postcode":"89102",
    "sg:province":"NV",
    "sg:tags":[
        "elementary"
    ],
    "wof:name":"Happy Days Child Care Pre-Schools",
    "wof:placetype":"venue"
},
  "geometry": {"coordinates":[-115.193981,36.146532],"type":"Point"}
}