{
  "type": "Feature",
  "properties": {
    "iso:country":"US",
    "sg:address":"19 Gamay Ln",
    "sg:city":"Reno",
    "sg:classifiers":[
        {
            "category":"Communications",
            "subcategory":"Film & Video Production",
            "type":"Services"
        }
    ],
    "sg:phone":"+1 775 337 8285",
    "sg:postcode":"89512",
    "sg:province":"NV",
    "sg:tags":[
        "taping"
    ],
    "wof:name":"Joseph J Staab General Bus",
    "wof:placetype":"venue"
},
  "geometry": {"coordinates":[-119.799894,39.561348],"type":"Point"}
}