{
  "type": "Feature",
  "properties": {
    "iso:country":"US",
    "sg:address":"4217 Terrapin Mountain Dr",
    "sg:city":"Las Vegas",
    "sg:classifiers":[
        {
            "category":"Building & Trades",
            "subcategory":"Landscaping Services",
            "type":"Services"
        }
    ],
    "sg:phone":"+1 702 870 1895",
    "sg:postcode":"89129",
    "sg:province":"NV",
    "sg:tags":[
        "lawn",
        "garden",
        "maintenance",
        "grounds"
    ],
    "wof:name":"Stucki Lawn Care",
    "wof:placetype":"venue"
},
  "geometry": {"coordinates":[-115.323188,36.237822],"type":"Point"}
}