{
  "type": "Feature",
  "properties": {
    "iso:country":"US",
    "sg:address":"197 Shady Ln",
    "sg:city":"Stateline",
    "sg:classifiers":[
        {
            "category":"Wholesale",
            "subcategory":"Apparel",
            "type":"Manufacturing & Wholesale Goods"
        }
    ],
    "sg:phone":"+1 775 588 3100",
    "sg:postcode":"89449",
    "sg:province":"NV",
    "sg:tags":[
        "sportswear"
    ],
    "wof:name":"Jos Designs",
    "wof:placetype":"venue"
},
  "geometry": {"coordinates":[-119.93097400000001,38.968863],"type":"Point"}
}