{
  "type": "Feature",
  "properties": {
    "iso:country":"US",
    "sg:address":"4385 S Carson St",
    "sg:city":"Carson City",
    "sg:classifiers":[
        {
            "category":"Restaurant",
            "type":"Food & Drink"
        }
    ],
    "sg:phone":"+1 775 883 0701",
    "sg:postcode":"89701",
    "sg:province":"NV",
    "wof:name":"Woody's",
    "wof:placetype":"venue"
},
  "geometry": {"coordinates":[-119.770704,39.127566],"type":"Point"}
}