{
  "type": "Feature",
  "properties": {
    "iso:country":"US",
    "sg:address":"4224 W Reno Ave",
    "sg:city":"Las Vegas",
    "sg:classifiers":[
        {
            "category":"Building & Trades",
            "subcategory":"Electrical",
            "type":"Services"
        }
    ],
    "sg:phone":"+1 702 873 6660",
    "sg:postcode":"89118",
    "sg:province":"NV",
    "sg:tags":[
        "electric",
        "contractor"
    ],
    "wof:name":"Energy Transfer Corp",
    "wof:placetype":"venue"
},
  "geometry": {"coordinates":[-115.196631,36.09734],"type":"Point"}
}