{
  "type": "Feature",
  "properties": {
    "iso:country":"US",
    "sg:address":"1211 S 10th St",
    "sg:city":"Las Vegas",
    "sg:classifiers":[
        {
            "category":"Building & Trades",
            "subcategory":"Construction",
            "type":"Services"
        }
    ],
    "sg:phone":"+1 702 382 4210",
    "sg:postcode":"89104",
    "sg:province":"NV",
    "sg:tags":[
        "contractor"
    ],
    "wof:name":"Pacer Pools",
    "wof:placetype":"venue"
},
  "geometry": {"coordinates":[-115.140938,36.156155],"type":"Point"}
}