{
  "type": "Feature",
  "properties": {
    "iso:country":"US",
    "sg:address":"3650 E Russell Rd",
    "sg:city":"Las Vegas",
    "sg:classifiers":[
        {
            "category":"Travel",
            "subcategory":"Travel Agent",
            "type":"Entertainment"
        }
    ],
    "sg:phone":"+1 702 434 8281",
    "sg:postcode":"89120",
    "sg:province":"NV",
    "sg:tags":[
        "agency",
        "bureau"
    ],
    "wof:name":"Leisure Life Travel",
    "wof:placetype":"venue"
},
  "geometry": {"coordinates":[-115.09539100000001,36.085992],"type":"Point"}
}