{
  "type": "Feature",
  "properties": {
    "iso:country":"US",
    "sg:address":"10410 Bermuda Rd",
    "sg:city":"Las Vegas",
    "sg:classifiers":[
        {
            "category":"Freight",
            "type":"Transportation"
        }
    ],
    "sg:phone":"+1 702 436 5050",
    "sg:postcode":"89183",
    "sg:province":"NV",
    "sg:tags":[
        "commercial",
        "storage"
    ],
    "wof:name":"Storage One",
    "wof:placetype":"venue"
},
  "geometry": {"coordinates":[-115.15485099999999,36.001917],"type":"Point"}
}