{
  "type": "Feature",
  "properties": {
    "iso:country":"US",
    "sg:address":"4556 Clay Peak Dr",
    "sg:city":"Las Vegas",
    "sg:classifiers":[
        {
            "category":"Professional",
            "type":"Services"
        }
    ],
    "sg:phone":"+1 702 645 0118",
    "sg:postcode":"89129",
    "sg:province":"NV",
    "sg:tags":[
        "establishment"
    ],
    "wof:name":"JRG Enterprises",
    "wof:placetype":"venue"
},
  "geometry": {"coordinates":[-115.286449,36.244276],"type":"Point"}
}