{
  "type": "Feature",
  "properties": {
    "iso:country":"US",
    "sg:address":"7400 Las Vegas Boulevard S Suite 56",
    "sg:city":"Las Vegas",
    "sg:classifiers":[
        {
            "category":"Shopping",
            "subcategory":"Jewelry",
            "type":"Retail Goods"
        }
    ],
    "sg:phone":"+1 702 837 8555",
    "sg:postcode":"89123",
    "sg:province":"NV",
    "wof:name":"Diamond Exchange",
    "wof:placetype":"venue"
},
  "geometry": {"coordinates":[-115.172185,36.055077],"type":"Point"}
}