{
  "type": "Feature",
  "properties": {
    "iso:country":"US",
    "sg:address":"Turnberry Town Square 6593 Las Vegas Blvd S",
    "sg:city":"Las Vegas",
    "sg:classifiers":[
        {
            "category":"Shopping",
            "subcategory":"Clothing, Apparel, & Fashions",
            "type":"Retail Goods"
        }
    ],
    "sg:phone":"+1 702 361 2447",
    "sg:postcode":"89119",
    "sg:province":"NV",
    "sg:website":"gap.com/",
    "wof:name":"Gap",
    "wof:placetype":"venue"
},
  "geometry": {"coordinates":[-115.172496,36.069372],"type":"Point"}
}