{
  "type": "Feature",
  "properties": {
    "iso:country":"US",
    "sg:address":"1448 Mountain Park Dr",
    "sg:city":"Carson City",
    "sg:classifiers":[
        {
            "category":"Wholesale",
            "subcategory":"Electrical",
            "type":"Manufacturing & Wholesale Goods"
        }
    ],
    "sg:phone":"+1 775 884 5900",
    "sg:postcode":"89706",
    "sg:province":"NV",
    "sg:tags":[
        "control",
        "security",
        "system"
    ],
    "wof:name":"Superior Security Video Inc",
    "wof:placetype":"venue"
},
  "geometry": {"coordinates":[-119.753424,39.179601],"type":"Point"}
}