{
  "type": "Feature",
  "properties": {
    "iso:country":"US",
    "sg:address":"7365 W Sahara Ave",
    "sg:city":"Las Vegas",
    "sg:classifiers":[
        {
            "category":"Professional",
            "subcategory":"Business Services",
            "type":"Services"
        }
    ],
    "sg:phone":"+1 702 737 7845",
    "sg:postcode":"89117",
    "sg:province":"NV",
    "sg:tags":[
        "auctioneer"
    ],
    "wof:name":"Quik Drop",
    "wof:placetype":"venue"
},
  "geometry": {"coordinates":[-115.252869,36.14381],"type":"Point"}
}