{
  "type": "Feature",
  "properties": {
    "iso:country":"US",
    "sg:address":"2441 Tech Center Ct",
    "sg:city":"Las Vegas",
    "sg:classifiers":[
        {
            "category":"Social Services",
            "type":"Services"
        }
    ],
    "sg:phone":"+1 702 318 8260",
    "sg:postcode":"89128",
    "sg:province":"NV",
    "sg:tags":[
        "counseling"
    ],
    "wof:name":"New Dimension Therapy Inc",
    "wof:placetype":"venue"
},
  "geometry": {"coordinates":[-115.253747,36.203929],"type":"Point"}
}