{
  "type": "Feature",
  "properties": {
    "iso:country":"US",
    "sg:address":"212 Woodley St",
    "sg:city":"Las Vegas",
    "sg:classifiers":[
        {
            "category":"Real Estate",
            "subcategory":"Architect",
            "type":"Services"
        }
    ],
    "sg:phone":"+1 702 386 2995",
    "sg:postcode":"89106",
    "sg:province":"NV",
    "sg:tags":[
        "building",
        "construction"
    ],
    "wof:name":"Suzanne A Thomas Consulting",
    "wof:placetype":"venue"
},
  "geometry": {"coordinates":[-115.170484,36.170405],"type":"Point"}
}