{
  "type": "Feature",
  "properties": {
    "iso:country":"US",
    "sg:address":"2543 Wigwam Parkway",
    "sg:city":"Henderson",
    "sg:classifiers":[
        {
            "category":"Personal",
            "subcategory":"Shoe Repair & Shine",
            "type":"Services"
        }
    ],
    "sg:phone":"+1 702 270 2337",
    "sg:postcode":"89074",
    "sg:province":"NV",
    "wof:name":"Green Valley Shoe Repair",
    "wof:placetype":"venue"
},
  "geometry": {"coordinates":[-115.09727,36.034555],"type":"Point"}
}