{
  "type": "Feature",
  "properties": {
    "iso:country":"US",
    "sg:address":"8551 W Lake Mead Blvd Ste 281",
    "sg:city":"Las Vegas",
    "sg:classifiers":[
        {
            "category":"Health Services",
            "subcategory":"Doctor",
            "type":"Services"
        }
    ],
    "sg:phone":"+1 702 360 7955",
    "sg:postcode":"89128",
    "sg:province":"NV",
    "sg:tags":[
        "dermatologist"
    ],
    "wof:name":"Wastek Greg MD PHD",
    "wof:placetype":"venue"
},
  "geometry": {"coordinates":[-115.280998,36.199001],"type":"Point"}
}