{
  "type": "Feature",
  "properties": {
    "iso:country":"US",
    "sg:address":"1861 Brian Rd",
    "sg:city":"Pahrump",
    "sg:classifiers":[
        {
            "category":"Organizations",
            "subcategory":"Religious Organization",
            "type":"Services"
        }
    ],
    "sg:phone":"+1 775 751 1223",
    "sg:postcode":"89048",
    "sg:province":"NV",
    "sg:tags":[
        "church"
    ],
    "wof:name":"H E A L Center",
    "wof:placetype":"venue"
},
  "geometry": {"coordinates":[-115.978883,36.14082],"type":"Point"}
}