{
  "type": "Feature",
  "properties": {
    "iso:country":"US",
    "sg:address":"9400 S Eastern Ave Ste 102",
    "sg:city":"Las Vegas",
    "sg:classifiers":[
        {
            "category":"Restaurant",
            "type":"Food & Drink"
        }
    ],
    "sg:phone":"+1 702 221 1600",
    "sg:postcode":"89123",
    "sg:province":"NV",
    "sg:tags":[
        "sushi",
        "bar",
        "hawaiian"
    ],
    "sg:website":"www.islandsushiandgrill.com",
    "wof:name":"Island Sushi",
    "wof:placetype":"venue"
},
  "geometry": {"coordinates":[-115.11808,36.018431],"type":"Point"}
}