{
  "type": "Feature",
  "properties": {
    "iso:country":"US",
    "sg:address":"4805 Sinelio Dr",
    "sg:city":"Reno",
    "sg:classifiers":[
        {
            "category":"Professional",
            "subcategory":"Business Services",
            "type":"Services"
        }
    ],
    "sg:phone":"+1 775 857 6473",
    "sg:postcode":"89502",
    "sg:province":"NV",
    "wof:name":"Lovelock Mercantile Company",
    "wof:placetype":"venue"
},
  "geometry": {"coordinates":[-119.746963,39.497479],"type":"Point"}
}