{
  "type": "Feature",
  "properties": {
    "iso:country":"US",
    "sg:address":"7661 Rolling View Dr",
    "sg:city":"Las Vegas",
    "sg:classifiers":[
        {
            "category":"Professional",
            "subcategory":"Advertising",
            "type":"Services"
        }
    ],
    "sg:phone":"+1 702 395 4567",
    "sg:postcode":"89149",
    "sg:province":"NV",
    "sg:tags":[
        "mail",
        "direct"
    ],
    "wof:name":"List Quest",
    "wof:placetype":"venue"
},
  "geometry": {"coordinates":[-115.262458,36.260106],"type":"Point"}
}