{
  "type": "Feature",
  "properties": {
    "iso:country":"US",
    "sg:address":"1605 Upper Valley Rd",
    "sg:city":"Lovelock",
    "sg:classifiers":[
        {
            "category":"Bars & Pubs",
            "type":"Food & Drink"
        }
    ],
    "sg:phone":"+1 775 273 2405",
    "sg:postcode":"89419",
    "sg:province":"NV",
    "wof:name":"Crazy Corners Saloon & Dance",
    "wof:placetype":"venue"
},
  "geometry": {"coordinates":[-118.439709,40.215742],"type":"Point"}
}