{
  "type": "Feature",
  "properties": {
    "iso:country":"US",
    "sg:address":"1485 S Wells Ave",
    "sg:city":"Reno",
    "sg:classifiers":[
        {
            "category":"Banks & Credit Unions",
            "subcategory":"Bank",
            "type":"Services"
        }
    ],
    "sg:phone":"+1 775 786 3699",
    "sg:postcode":"89502",
    "sg:province":"NV",
    "sg:tags":[
        "loan"
    ],
    "wof:name":"Family Finance",
    "wof:placetype":"venue"
},
  "geometry": {"coordinates":[-119.803217,39.511537],"type":"Point"}
}