{
  "type": "Feature",
  "properties": {
    "iso:country":"US",
    "sg:address":"10413 Turning Leaf Ave",
    "sg:city":"Las Vegas",
    "sg:classifiers":[
        {
            "category":"Professional",
            "subcategory":"Employment Agencies",
            "type":"Services"
        }
    ],
    "sg:phone":"+1 702 650 3900",
    "sg:postcode":"89129",
    "sg:province":"NV",
    "wof:name":"Construct-Temps",
    "wof:placetype":"venue"
},
  "geometry": {"coordinates":[-115.32306199999999,36.219423],"type":"Point"}
}