{
  "type": "Feature",
  "properties": {
    "iso:country":"US",
    "sg:address":"2690 Chandler Ave Ste 8",
    "sg:city":"Las Vegas",
    "sg:classifiers":[
        {
            "category":"Health Services",
            "subcategory":"Health Practitioner",
            "type":"Services"
        }
    ],
    "sg:phone":"+1 702 433 0404",
    "sg:postcode":"89120",
    "sg:province":"NV",
    "sg:tags":[
        "nutritionist"
    ],
    "sg:website":"www.sensoryresources.com",
    "wof:name":"Sensory Resources",
    "wof:placetype":"venue"
},
  "geometry": {"coordinates":[-115.113727,36.07399],"type":"Point"}
}