{
  "type": "Feature",
  "properties": {
    "iso:country":"US",
    "sg:address":"6740 W Flamingo Road",
    "sg:city":"Las Vegas",
    "sg:classifiers":[
        {
            "category":"Personal",
            "type":"Services"
        }
    ],
    "sg:phone":"+1 702 368 7500",
    "sg:postcode":"89103",
    "sg:province":"NV",
    "sg:tags":[
        "mover"
    ],
    "wof:name":"Self Storage City",
    "wof:placetype":"venue"
},
  "geometry": {"coordinates":[-115.239119,36.114724],"type":"Point"}
}