{
  "type": "Feature",
  "properties": {
    "iso:country":"US",
    "sg:address":"7500 W Lake Mead Blvd",
    "sg:city":"Las Vegas",
    "sg:classifiers":[
        {
            "category":"Recreation",
            "type":"Entertainment"
        }
    ],
    "sg:phone":"+1 702 393 4453",
    "sg:postcode":"89128",
    "sg:province":"NV",
    "sg:tags":[
        "hiking"
    ],
    "sg:website":"www.hikethislasvegas.com",
    "wof:name":"Hike This!",
    "wof:placetype":"venue"
},
  "geometry": {"coordinates":[-115.25841,36.197223],"type":"Point"}
}