{
  "type": "Feature",
  "properties": {
    "iso:country":"US",
    "sg:address":"1819 E Charleston Blvd",
    "sg:city":"Las Vegas",
    "sg:classifiers":[
        {
            "category":"Retail",
            "subcategory":"Photofinishing",
            "type":"Services"
        }
    ],
    "sg:phone":"+1 702 734 3111",
    "sg:postcode":"89104",
    "sg:province":"NV",
    "sg:tags":[
        "laboratory",
        "finishing",
        "photo"
    ],
    "wof:name":"Multicolor Photo Lab",
    "wof:placetype":"venue"
},
  "geometry": {"coordinates":[-115.12365699999999,36.15894],"type":"Point"}
}