{
  "type": "Feature",
  "properties": {
    "iso:country":"US",
    "sg:address":"10391 Tewa Ct",
    "sg:city":"Reno",
    "sg:classifiers":[
        {
            "category":"Organizations",
            "subcategory":"Community Association",
            "type":"Services"
        }
    ],
    "sg:phone":"+1 775 850 4450",
    "sg:postcode":"89511",
    "sg:province":"NV",
    "wof:name":"Arrowcreek Security Gate",
    "wof:placetype":"venue"
},
  "geometry": {"coordinates":[-119.8051,39.407025],"type":"Point"}
}