{
  "type": "Feature",
  "properties": {
    "iso:country":"US",
    "sg:address":"333 Las Vegas Blvd S",
    "sg:city":"Las Vegas",
    "sg:classifiers":[
        {
            "category":"Coffee & Tea",
            "type":"Food & Drink"
        }
    ],
    "sg:phone":"+1 702 750 1170",
    "sg:postcode":"89101",
    "sg:province":"NV",
    "wof:name":"Order in the Court",
    "wof:placetype":"venue"
},
  "geometry": {"coordinates":[-115.145903,36.158234],"type":"Point"}
}