{
  "type": "Feature",
  "properties": {
    "iso:country":"US",
    "sg:address":"948 Victorian Ave",
    "sg:city":"Sparks",
    "sg:classifiers":[
        {
            "category":"Shopping",
            "subcategory":"Clothing, Apparel, & Fashions",
            "type":"Retail Goods"
        }
    ],
    "sg:phone":"+1 775 626 2141",
    "sg:postcode":"89431",
    "sg:province":"NV",
    "sg:tags":[
        "shop",
        "bridal"
    ],
    "wof:name":"Blue Garter Bridal & Tux",
    "wof:placetype":"venue"
},
  "geometry": {"coordinates":[-119.754751,39.534776],"type":"Point"}
}