{
  "type": "Feature",
  "properties": {
    "iso:country":"US",
    "sg:address":"306 Ruby Ln",
    "sg:city":"Carson City",
    "sg:classifiers":[
        {
            "category":"Building & Trades",
            "subcategory":"Construction",
            "type":"Services"
        }
    ],
    "sg:phone":"+1 775 885 1537",
    "sg:postcode":"89706",
    "sg:province":"NV",
    "sg:tags":[
        "residential"
    ],
    "wof:name":"Gary W Hembree Construction",
    "wof:placetype":"venue"
},
  "geometry": {"coordinates":[-119.763851,39.19977],"type":"Point"}
}