{
  "type": "Feature",
  "properties": {
    "iso:country":"US",
    "sg:address":"112 Garces Ave",
    "sg:city":"Las Vegas",
    "sg:classifiers":[
        {
            "category":"Real Estate",
            "subcategory":"Real Estate Agent",
            "type":"Services"
        }
    ],
    "sg:phone":"+1 702 385 4988",
    "sg:postcode":"89101",
    "sg:province":"NV",
    "sg:website":"www.diversifiedgrp.com",
    "wof:name":"Diversified Real Estate Group",
    "wof:placetype":"venue"
},
  "geometry": {"coordinates":[-115.14878,36.163718],"type":"Point"}
}