{
  "type": "Feature",
  "properties": {
    "iso:country":"US",
    "sg:address":"10532 Riva Grande Ct",
    "sg:city":"Las Vegas",
    "sg:classifiers":[
        {
            "category":"Professional",
            "subcategory":"Management & Consulting",
            "type":"Services"
        }
    ],
    "sg:phone":"+1 702 228 7393",
    "sg:postcode":"89135",
    "sg:province":"NV",
    "sg:tags":[
        "consultant",
        "casino"
    ],
    "wof:name":"Amerine Gaming Enterprises Inc",
    "wof:placetype":"venue"
},
  "geometry": {"coordinates":[-115.324377,36.114046],"type":"Point"}
}