{
  "type": "Feature",
  "properties": {
    "iso:country":"US",
    "sg:address":"690 Keystone Ave",
    "sg:city":"Reno",
    "sg:classifiers":[
        {
            "category":"Utilities",
            "subcategory":"Mobile Phone",
            "type":"Services"
        },
        {
            "category":"Coffee & Tea",
            "type":"Food & Drink"
        }
    ],
    "sg:phone":"+1 775 747 7318",
    "sg:postcode":"89503",
    "sg:province":"NV",
    "sg:tags":[
        "shop",
        "wi-fi",
        "espresso",
        "hotspot",
        "restaurant"
    ],
    "sg:website":"http://www.starbuckscoffee.com",
    "wof:name":"Starbucks Coffee",
    "wof:placetype":"venue"
},
  "geometry": {"coordinates":[-119.83125699999999,39.530655],"type":"Point"}
}