{
  "type": "Feature",
  "properties": {
    "iso:country":"US",
    "sg:address":"1289 Park View Dr",
    "sg:city":"Elko",
    "sg:classifiers":[
        {
            "category":"Retail",
            "subcategory":"Repair Shop",
            "type":"Services"
        }
    ],
    "sg:phone":"+1 775 738 4772",
    "sg:postcode":"89801",
    "sg:province":"NV",
    "sg:tags":[
        "lock",
        "locksmith"
    ],
    "wof:name":"All Seasons Mobile Lock Svc",
    "wof:placetype":"venue"
},
  "geometry": {"coordinates":[-115.770566,40.849061],"type":"Point"}
}