{
  "type": "Feature",
  "properties": {
    "iso:country":"US",
    "sg:address":"3408 Mary Ann Ave",
    "sg:city":"Las Vegas",
    "sg:classifiers":[
        {
            "category":"Retail",
            "subcategory":"Repair Shop",
            "type":"Services"
        }
    ],
    "sg:phone":"+1 702 437 7270",
    "sg:postcode":"89101",
    "sg:province":"NV",
    "sg:tags":[
        "electrical",
        "apparatus"
    ],
    "wof:name":"Waymore Enterprises",
    "wof:placetype":"venue"
},
  "geometry": {"coordinates":[-115.098395,36.185472],"type":"Point"}
}