{
  "type": "Feature",
  "properties": {
    "iso:country":"US",
    "sg:address":"6861 Tamarus St",
    "sg:city":"Las Vegas",
    "sg:classifiers":[
        {
            "category":"Professional",
            "subcategory":"Computer Services",
            "type":"Services"
        }
    ],
    "sg:phone":"+1 702 897 9657",
    "sg:postcode":"89119",
    "sg:province":"NV",
    "sg:tags":[
        "repair"
    ],
    "wof:name":"2 U At Home Computer Repair",
    "wof:placetype":"venue"
},
  "geometry": {"coordinates":[-115.132198,36.064341],"type":"Point"}
}