{
  "type": "Feature",
  "properties": {
    "iso:country":"US",
    "sg:address":"3290 West Ann Rd",
    "sg:city":"North Las Vegas",
    "sg:classifiers":[
        {
            "category":"Bars & Pubs",
            "type":"Food & Drink"
        },
        {
            "category":"Restaurant",
            "type":"Food & Drink"
        }
    ],
    "sg:phone":"+1 702 395 0492",
    "sg:postcode":"89031",
    "sg:province":"NV",
    "sg:website":"www.irishpubslv.com",
    "wof:name":"Kavanaugh's Irish Pub and Grill",
    "wof:placetype":"venue"
},
  "geometry": {"coordinates":[-115.184258,36.261742],"type":"Point"}
}