{
  "type": "Feature",
  "properties": {
    "iso:country":"US",
    "sg:address":"321 Broadway Blvd",
    "sg:city":"Reno",
    "sg:classifiers":[
        {
            "category":"Restaurant",
            "type":"Food & Drink"
        }
    ],
    "sg:phone":"+1 775 323 0704",
    "sg:postcode":"89502",
    "sg:province":"NV",
    "sg:tags":[
        "eating"
    ],
    "wof:name":"McDonalds",
    "wof:placetype":"venue"
},
  "geometry": {"coordinates":[-119.800735,39.511742],"type":"Point"}
}