{
  "type": "Feature",
  "properties": {
    "iso:country":"US",
    "sg:address":"6621 W Cheyenne Ave",
    "sg:city":"Las Vegas",
    "sg:classifiers":[
        {
            "category":"Restaurant",
            "type":"Food & Drink"
        }
    ],
    "sg:menulink":"http://www.allmenus.com/nv/las-vegas/133920-subway/menu/",
    "sg:phone":"+1 702 656 2968",
    "sg:postcode":"89108",
    "sg:province":"NV",
    "sg:tags":[
        "american",
        "sandwich"
    ],
    "wof:name":"Subway",
    "wof:placetype":"venue"
},
  "geometry": {"coordinates":[-115.23857,36.217909],"type":"Point"}
}