{
  "type": "Feature",
  "properties": {
    "iso:country":"US",
    "sg:address":"420 N Nellis Blvd",
    "sg:city":"Las Vegas",
    "sg:classifiers":[
        {
            "category":"Shopping",
            "subcategory":"Mobile Phones",
            "type":"Retail Goods"
        }
    ],
    "sg:phone":"+1 702 459 7790",
    "sg:postcode":"89110",
    "sg:province":"NV",
    "sg:website":"www.bellsouth.com",
    "wof:name":"Cingular Wireless",
    "wof:placetype":"venue"
},
  "geometry": {"coordinates":[-115.06199599999999,36.166901],"type":"Point"}
}