{
  "type": "Feature",
  "properties": {
    "iso:country":"US",
    "sg:address":"625 Spice Islands Dr",
    "sg:city":"Sparks",
    "sg:phone":"+1 775 355 8818",
    "sg:postcode":"89431",
    "sg:province":"NV",
    "sg:website":"http://www.uniquedesigncabinetco.com",
    "wof:name":"Unique Design Cabinet Co.",
    "wof:placetype":"venue"
},
  "geometry": {"coordinates":[-119.734959,39.51669],"type":"Point"}
}