{
  "type": "Feature",
  "properties": {
    "iso:country":"US",
    "sg:address":"1781 Village Center Cir",
    "sg:city":"Las Vegas",
    "sg:classifiers":[
        {
            "category":"Health Services",
            "subcategory":"Dentist",
            "type":"Services"
        }
    ],
    "sg:phone":"+1 702 445 7075",
    "sg:postcode":"89134",
    "sg:province":"NV",
    "sg:website":"www.lasvegasbeautifulsmiles.com",
    "wof:name":"Las Vegas Beautiful Smiles",
    "wof:placetype":"venue"
},
  "geometry": {"coordinates":[-115.29930299999999,36.191372],"type":"Point"}
}