{
  "type": "Feature",
  "properties": {
    "iso:country":"US",
    "sg:address":"2015 W 6th St",
    "sg:city":"Reno",
    "sg:classifiers":[
        {
            "category":"Social Services",
            "subcategory":"Adult Care",
            "type":"Services"
        }
    ],
    "sg:phone":"+1 775 333 6696",
    "sg:postcode":"89503",
    "sg:province":"NV",
    "sg:tags":[
        "residential"
    ],
    "wof:name":"Heavenly Manor",
    "wof:placetype":"venue"
},
  "geometry": {"coordinates":[-119.842635,39.529683],"type":"Point"}
}