{
  "type": "Feature",
  "properties": {
    "iso:country":"US",
    "sg:address":"8551 W Lake Mead Blvd",
    "sg:city":"Las Vegas",
    "sg:classifiers":[
        {
            "category":"Health Services",
            "subcategory":"Doctor",
            "type":"Services"
        }
    ],
    "sg:phone":"+1 702 255 8786",
    "sg:postcode":"89128",
    "sg:province":"NV",
    "wof:name":"Family Health Center",
    "wof:placetype":"venue"
},
  "geometry": {"coordinates":[-115.264999,36.196301],"type":"Point"}
}