{
  "type": "Feature",
  "properties": {
    "iso:country":"US",
    "sg:address":"3500 Lakeside Ct",
    "sg:city":"Reno",
    "sg:classifiers":[
        {
            "category":"Social Services",
            "type":"Services"
        }
    ],
    "sg:phone":"+1 775 329 6002",
    "sg:postcode":"89509",
    "sg:province":"NV",
    "sg:tags":[
        "personal"
    ],
    "wof:name":"Ing Steven MA Mft",
    "wof:placetype":"venue"
},
  "geometry": {"coordinates":[-119.806651,39.493003],"type":"Point"}
}