{
  "type": "Feature",
  "properties": {
    "iso:country":"US",
    "sg:address":"2810 S Decatur Blvd",
    "sg:city":"Las Vegas",
    "sg:classifiers":[
        {
            "category":"Wholesale",
            "subcategory":"Non-durable Goods",
            "type":"Manufacturing & Wholesale Goods"
        }
    ],
    "sg:phone":"+1 702 248 5493",
    "sg:postcode":"89102",
    "sg:province":"NV",
    "wof:name":"Ztattoo Co",
    "wof:placetype":"venue"
},
  "geometry": {"coordinates":[-115.208023,36.139273],"type":"Point"}
}