{
  "type": "Feature",
  "properties": {
    "iso:country":"US",
    "sg:address":"7425 Indian Springs Dr",
    "sg:city":"Sparks",
    "sg:classifiers":[
        {
            "category":"Building & Trades",
            "subcategory":"Construction",
            "type":"Services"
        }
    ],
    "sg:phone":"+1 775 425 4875",
    "sg:postcode":"89436",
    "sg:province":"NV",
    "sg:tags":[
        "painter"
    ],
    "wof:name":"Painting By Erica",
    "wof:placetype":"venue"
},
  "geometry": {"coordinates":[-119.730703,39.63124],"type":"Point"}
}