{
  "type": "Feature",
  "properties": {
    "iso:country":"US",
    "sg:address":"8605 Canyon View Dr",
    "sg:city":"Las Vegas",
    "sg:classifiers":[
        {
            "category":"Banks & Credit Unions",
            "subcategory":"Financial Services",
            "type":"Services"
        }
    ],
    "sg:phone":"+1 702 363 9912",
    "sg:postcode":"89117",
    "sg:province":"NV",
    "sg:tags":[
        "fund",
        "investment"
    ],
    "wof:name":"Bahji Partners Ltd",
    "wof:placetype":"venue"
},
  "geometry": {"coordinates":[-115.280287,36.148933],"type":"Point"}
}