{
  "type": "Feature",
  "properties": {
    "iso:country":"US",
    "sg:address":"4055 W Sunset Rd",
    "sg:city":"Las Vegas",
    "sg:classifiers":[
        {
            "category":"Professional",
            "type":"Services"
        }
    ],
    "sg:phone":"+1 702 531 5858",
    "sg:postcode":"89118",
    "sg:province":"NV",
    "sg:tags":[
        "establishment"
    ],
    "wof:name":"Setus",
    "wof:placetype":"venue"
},
  "geometry": {"coordinates":[-115.196412,36.071624],"type":"Point"}
}