{
  "type": "Feature",
  "properties": {
    "iso:country":"US",
    "sg:address":"9542 Calico Garden Ave",
    "sg:city":"Las Vegas",
    "sg:classifiers":[
        {
            "category":"Real Estate",
            "subcategory":"Real Estate Agent",
            "type":"Services"
        }
    ],
    "sg:phone":"+1 702 324 3385",
    "sg:postcode":"89134",
    "sg:province":"NV",
    "sg:tags":[
        "consultant"
    ],
    "wof:name":"Las Vegas Real Estate Conslnts",
    "wof:placetype":"venue"
},
  "geometry": {"coordinates":[-115.303674,36.205719],"type":"Point"}
}