{
  "type": "Feature",
  "properties": {
    "iso:country":"US",
    "sg:address":"713 N Princeton St",
    "sg:city":"Las Vegas",
    "sg:classifiers":[
        {
            "category":"Building & Trades",
            "subcategory":"Construction",
            "type":"Services"
        }
    ],
    "sg:phone":"+1 702 258 9531",
    "sg:postcode":"89107",
    "sg:province":"NV",
    "sg:tags":[
        "hanging",
        "contractor"
    ],
    "wof:name":"Rockys Painting",
    "wof:placetype":"venue"
},
  "geometry": {"coordinates":[-115.208566,36.180259],"type":"Point"}
}