{
  "type": "Feature",
  "properties": {
    "iso:country":"US",
    "sg:address":"1800 Kings Row",
    "sg:city":"Reno",
    "sg:classifiers":[
        {
            "category":"Retail",
            "subcategory":"Laundry & Dry Cleaning",
            "type":"Services"
        }
    ],
    "sg:phone":"+1 775 787 0225",
    "sg:postcode":"89503",
    "sg:province":"NV",
    "wof:name":"A & R General Cleaning",
    "wof:placetype":"venue"
},
  "geometry": {"coordinates":[-119.841793,39.536679],"type":"Point"}
}