{
  "type": "Feature",
  "properties": {
    "iso:country":"US",
    "sg:address":"1111 N Saliman Rd",
    "sg:city":"Carson City",
    "sg:classifiers":[
        {
            "category":"Education",
            "subcategory":"School",
            "type":"Public Place"
        }
    ],
    "sg:phone":"+1 775 283 1600",
    "sg:postcode":"89701",
    "sg:province":"NV",
    "sg:tags":[
        "high",
        "middle",
        "elementary"
    ],
    "sg:website":"www.carsoncityschools.com",
    "wof:name":"Carson City School District",
    "wof:placetype":"venue"
},
  "geometry": {"coordinates":[-119.750797,39.170413],"type":"Point"}
}