{
  "type": "Feature",
  "properties": {
    "iso:country":"US",
    "sg:address":"513 Northstar St",
    "sg:city":"Las Vegas",
    "sg:classifiers":[
        {
            "category":"Building & Trades",
            "subcategory":"Electrical",
            "type":"Services"
        }
    ],
    "sg:phone":"+1 702 877 1788",
    "sg:postcode":"89107",
    "sg:province":"NV",
    "sg:tags":[
        "electrical",
        "installation",
        "contractor"
    ],
    "wof:name":"K Y Tile & Marble",
    "wof:placetype":"venue"
},
  "geometry": {"coordinates":[-115.193153,36.165159],"type":"Point"}
}