{
  "type": "Feature",
  "properties": {
    "iso:country":"US",
    "sg:address":"3145 Las Vegas Blvd S",
    "sg:city":"Las Vegas",
    "sg:classifiers":[
        {
            "category":"Communications",
            "subcategory":"Film & Video Production",
            "type":"Services"
        }
    ],
    "sg:phone":"+1 702 732 8089",
    "sg:postcode":"89109",
    "sg:province":"NV",
    "sg:tags":[
        "motion",
        "picture"
    ],
    "wof:name":"New Line Cinema",
    "wof:placetype":"venue"
},
  "geometry": {"coordinates":[-115.166571,36.129469],"type":"Point"}
}