{
  "type": "Feature",
  "properties": {
    "iso:country":"US",
    "sg:address":"4455 Smiley Rd",
    "sg:city":"Las Vegas",
    "sg:classifiers":[
        {
            "category":"Retail",
            "subcategory":"Auto Repair",
            "type":"Services"
        }
    ],
    "sg:phone":"+1 702 644 3290",
    "sg:postcode":"89115",
    "sg:province":"NV",
    "sg:tags":[
        "body",
        "automobile",
        "painting"
    ],
    "wof:name":"KAOS",
    "wof:placetype":"venue"
},
  "geometry": {"coordinates":[-115.078818,36.254587],"type":"Point"}
}