{
  "type": "Feature",
  "properties": {
    "iso:country":"US",
    "sg:address":"3700 N Carson St",
    "sg:city":"Carson City",
    "sg:classifiers":[
        {
            "category":"Restaurant",
            "type":"Food & Drink"
        }
    ],
    "sg:phone":"+1 775 884 4414",
    "sg:postcode":"89706",
    "sg:province":"NV",
    "sg:tags":[
        "eating"
    ],
    "wof:name":"Eagles Glen Restaurant",
    "wof:placetype":"venue"
},
  "geometry": {"coordinates":[-119.774002,39.192001],"type":"Point"}
}