{
  "type": "Feature",
  "properties": {
    "iso:country":"US",
    "sg:address":"2901 W Washington Ave",
    "sg:city":"Las Vegas",
    "sg:classifiers":[
        {
            "category":"Shopping",
            "type":"Retail Goods"
        }
    ],
    "sg:phone":"+1 702 646 5013",
    "sg:postcode":"89107",
    "sg:province":"NV",
    "sg:tags":[
        "plant",
        "flower",
        "tree",
        "artificial"
    ],
    "wof:name":"Delia's Home Decor",
    "wof:placetype":"venue"
},
  "geometry": {"coordinates":[-115.180388,36.181024],"type":"Point"}
}