{
  "type": "Feature",
  "properties": {
    "iso:country":"US",
    "sg:address":"1309 D St",
    "sg:city":"Las Vegas",
    "sg:classifiers":[
        {
            "category":"Personal",
            "subcategory":"Beauty Salon",
            "type":"Services"
        }
    ],
    "sg:phone":"+1 702 646 9822",
    "sg:postcode":"89106",
    "sg:province":"NV",
    "sg:tags":[
        "shop"
    ],
    "wof:name":"Fashionette Beauty Salon",
    "wof:placetype":"venue"
},
  "geometry": {"coordinates":[-115.147192,36.185891],"type":"Point"}
}