{
  "type": "Feature",
  "properties": {
    "iso:country":"US",
    "sg:address":"8112 Leger Dr",
    "sg:city":"Las Vegas",
    "sg:classifiers":[
        {
            "category":"Professional",
            "subcategory":"Business Services",
            "type":"Services"
        }
    ],
    "sg:phone":"+1 702 838 2670",
    "sg:postcode":"89145",
    "sg:province":"NV",
    "sg:tags":[
        "drafting"
    ],
    "wof:name":"Executive Drafting Svc",
    "wof:placetype":"venue"
},
  "geometry": {"coordinates":[-115.269144,36.169477],"type":"Point"}
}