{
  "type": "Feature",
  "properties": {
    "iso:country":"US",
    "sg:address":"3700 E Charleston Blvd",
    "sg:city":"Las Vegas",
    "sg:classifiers":[
        {
            "category":"Home & Garden",
            "subcategory":"Furniture",
            "type":"Retail Goods"
        }
    ],
    "sg:phone":"+1 702 459 0999",
    "sg:postcode":"89104",
    "sg:province":"NV",
    "wof:name":"All Design Furniture",
    "wof:placetype":"venue"
},
  "geometry": {"coordinates":[-115.095472,36.158766],"type":"Point"}
}