{
  "type": "Feature",
  "properties": {
    "iso:country":"US",
    "sg:address":"4255 E Charleston Blvd",
    "sg:city":"Las Vegas",
    "sg:classifiers":[
        {
            "category":"Shopping",
            "subcategory":"Gifts & Souvenirs",
            "type":"Retail Goods"
        }
    ],
    "sg:phone":"+1 702 457 0433",
    "sg:postcode":"89104",
    "sg:province":"NV",
    "sg:tags":[
        "balloon",
        "artist"
    ],
    "wof:name":"Party Favors Balloon Decor",
    "wof:placetype":"venue"
},
  "geometry": {"coordinates":[-115.080197,36.158958],"type":"Point"}
}