{
  "type": "Feature",
  "properties": {
    "iso:country":"US",
    "sg:address":"2100 W Warm Springs Road",
    "sg:city":"Henderson",
    "sg:classifiers":[
        {
            "category":"Sports & Exercise",
            "subcategory":"Golf",
            "type":"Entertainment"
        }
    ],
    "sg:phone":"+1 702 434 9000",
    "sg:postcode":"89014",
    "sg:province":"NV",
    "wof:name":"Wildhorse Golf Club",
    "wof:placetype":"venue"
},
  "geometry": {"coordinates":[-115.078305,36.056535],"type":"Point"}
}