{
  "type": "Feature",
  "properties": {
    "iso:country":"US",
    "sg:address":"7069 Ovation Way",
    "sg:city":"Las Vegas",
    "sg:classifiers":[
        {
            "category":"Banks & Credit Unions",
            "subcategory":"Investment Brokerage",
            "type":"Services"
        }
    ],
    "sg:phone":"+1 702 647 8880",
    "sg:postcode":"89119",
    "sg:province":"NV",
    "sg:tags":[
        "consultant",
        "financing"
    ],
    "wof:name":"Oritech",
    "wof:placetype":"venue"
},
  "geometry": {"coordinates":[-115.139703,36.060399],"type":"Point"}
}