{
  "type": "Feature",
  "properties": {
    "iso:country":"US",
    "sg:address":"788 Fairview Dr",
    "sg:city":"Carson City",
    "sg:classifiers":[
        {
            "category":"Government",
            "subcategory":"Office",
            "type":"Public Place"
        }
    ],
    "sg:phone":"+1 775 687 4280",
    "sg:postcode":"89701",
    "sg:province":"NV",
    "sg:tags":[
        "state"
    ],
    "sg:website":"www.red.state.nv.us",
    "wof:name":"Real Estate Div",
    "wof:placetype":"venue"
},
  "geometry": {"coordinates":[-119.760239,39.14999],"type":"Point"}
}