{
  "type": "Feature",
  "properties": {
    "iso:country":"US",
    "sg:address":"4380 E Bonanza Rd",
    "sg:city":"Las Vegas",
    "sg:classifiers":[
        {
            "category":"Food & Beverages",
            "subcategory":"Groceries & Convenience Stores",
            "type":"Retail Goods"
        }
    ],
    "sg:phone":"+1 702 453 4002",
    "sg:postcode":"89110",
    "sg:province":"NV",
    "sg:tags":[
        "station",
        "gasoline"
    ],
    "wof:name":"Circle K",
    "wof:placetype":"venue"
},
  "geometry": {"coordinates":[-115.081862,36.173386],"type":"Point"}
}