{
  "type": "Feature",
  "properties": {
    "iso:country":"US",
    "sg:address":"4493 Arville Street",
    "sg:city":"Las Vegas",
    "sg:classifiers":[
        {
            "category":"Education",
            "subcategory":"School",
            "type":"Public Place"
        }
    ],
    "sg:phone":"+1 702 799 8123",
    "sg:postcode":"89103",
    "sg:province":"NV",
    "wof:name":"Schools Clark County Public",
    "wof:placetype":"venue"
},
  "geometry": {"coordinates":[-115.19917,36.109393],"type":"Point"}
}