{
  "type": "Feature",
  "properties": {
    "iso:country":"US",
    "sg:address":"5000 W Charleston Boulevard",
    "sg:city":"Las Vegas",
    "sg:classifiers":[
        {
            "category":"Personal",
            "subcategory":"Shoe Repair & Shine",
            "type":"Services"
        }
    ],
    "sg:phone":"+1 702 877 0800",
    "sg:postcode":"89146",
    "sg:province":"NV",
    "wof:name":"A Cactus Boot & Shoe Repair",
    "wof:placetype":"venue"
},
  "geometry": {"coordinates":[-115.209159,36.159209],"type":"Point"}
}