{
  "type": "Feature",
  "properties": {
    "iso:country":"US",
    "sg:address":"5150 Mae Anne Ave",
    "sg:city":"Reno",
    "sg:classifiers":[
        {
            "category":"Utilities",
            "subcategory":"Mobile Phone",
            "type":"Services"
        }
    ],
    "sg:phone":"+1 775 284 5700",
    "sg:postcode":"89523",
    "sg:province":"NV",
    "sg:tags":[
        "telephone",
        "cellular"
    ],
    "wof:name":"T Mobile",
    "wof:placetype":"venue"
},
  "geometry": {"coordinates":[-119.86805699999999,39.533444],"type":"Point"}
}