{
  "type": "Feature",
  "properties": {
    "iso:country":"US",
    "sg:address":"3900 N Hualapai Way",
    "sg:city":"Las Vegas",
    "sg:classifiers":[
        {
            "category":"Real Estate",
            "subcategory":"Real Estate Agent",
            "type":"Services"
        }
    ],
    "sg:phone":"+1 702 933 2022",
    "sg:postcode":"89129",
    "sg:province":"NV",
    "wof:name":"Re Max Benchmark Realty",
    "wof:placetype":"venue"
},
  "geometry": {"coordinates":[-115.314702,36.230715],"type":"Point"}
}