{
  "type": "Feature",
  "properties": {
    "iso:country":"US",
    "sg:address":"5900 W Charleston Blvd",
    "sg:city":"Las Vegas",
    "sg:classifiers":[
        {
            "category":"Health Services",
            "subcategory":"Chiropractor",
            "type":"Services"
        }
    ],
    "sg:phone":"+1 702 259 6992",
    "sg:postcode":"89146",
    "sg:province":"NV",
    "sg:website":"drtlv.com",
    "wof:name":"Accelerated Chiropractic",
    "wof:placetype":"venue"
},
  "geometry": {"coordinates":[-115.222,36.159302],"type":"Point"}
}