{
  "type": "Feature",
  "properties": {
    "iso:country":"US",
    "sg:address":"835 E Eldorado Ln",
    "sg:city":"Las Vegas",
    "sg:classifiers":[
        {
            "category":"Autos & Motor Vehicles",
            "subcategory":"Automobile Sales",
            "type":"Retail Goods"
        }
    ],
    "sg:phone":"+1 702 361 6701",
    "sg:postcode":"89123",
    "sg:province":"NV",
    "sg:tags":[
        "car",
        "dealer"
    ],
    "wof:name":"Reliable Auto Sales",
    "wof:placetype":"venue"
},
  "geometry": {"coordinates":[-115.144678,36.053425],"type":"Point"}
}