{
  "type": "Feature",
  "properties": {
    "iso:country":"US",
    "sg:address":"8140 S Eastern Ave",
    "sg:city":"Las Vegas",
    "sg:classifiers":[
        {
            "category":"Shopping",
            "subcategory":"Department Store",
            "type":"Retail Goods"
        }
    ],
    "sg:phone":"+1 702 617 0830",
    "sg:postcode":"89123",
    "sg:province":"NV",
    "sg:website":"www.biglots.com",
    "wof:name":"Big Lots",
    "wof:placetype":"venue"
},
  "geometry": {"coordinates":[-115.118272,36.040071],"type":"Point"}
}