{
  "type": "Feature",
  "properties": {
    "iso:country":"US",
    "sg:address":"4555 Village Green Pkwy",
    "sg:city":"Reno",
    "sg:classifiers":[
        {
            "category":"Organizations",
            "subcategory":"Professional Association",
            "type":"Services"
        }
    ],
    "sg:phone":"+1 775 786 5506",
    "sg:postcode":"89519",
    "sg:province":"NV",
    "sg:tags":[
        "business"
    ],
    "wof:name":"Stegen & Associates",
    "wof:placetype":"venue"
},
  "geometry": {"coordinates":[-119.85353000000001,39.482118],"type":"Point"}
}