{
  "type": "Feature",
  "properties": {
    "iso:country":"US",
    "sg:address":"660 Hardy Way",
    "sg:city":"Mesquite",
    "sg:classifiers":[
        {
            "category":"Retail",
            "subcategory":"Veterinary Services",
            "type":"Services"
        }
    ],
    "sg:phone":"+1 702 346 4401",
    "sg:postcode":"89027",
    "sg:province":"NV",
    "sg:tags":[
        "veterinarian"
    ],
    "wof:name":"Virgin Valley Veterinary Hosp",
    "wof:placetype":"venue"
},
  "geometry": {"coordinates":[-114.086261,36.824131],"type":"Point"}
}