{
  "type": "Feature",
  "properties": {
    "iso:country":"US",
    "sg:address":"14 Sunset Way",
    "sg:city":"Henderson",
    "sg:classifiers":[
        {
            "category":"Communications",
            "type":"Services"
        }
    ],
    "sg:phone":"+1 702 318 6001",
    "sg:postcode":"89014",
    "sg:province":"NV",
    "sg:tags":[
        "recording",
        "rehearsal",
        "studio"
    ],
    "wof:name":"Odds On Recording Studios",
    "wof:placetype":"venue"
},
  "geometry": {"coordinates":[-115.066925,36.072709],"type":"Point"}
}