{
  "type": "Feature",
  "properties": {
    "iso:country":"US",
    "sg:address":"5475 Louie Ln",
    "sg:city":"Reno",
    "sg:classifiers":[
        {
            "category":"Arts & Performance",
            "subcategory":"Theater",
            "type":"Entertainment"
        }
    ],
    "sg:phone":"+1 775 323 3334",
    "sg:postcode":"89511",
    "sg:province":"NV",
    "sg:tags":[
        "live",
        "music"
    ],
    "wof:name":"Audio Impact Mobile DJ",
    "wof:placetype":"venue"
},
  "geometry": {"coordinates":[-119.769178,39.472931],"type":"Point"}
}