{
  "type": "Feature",
  "properties": {
    "iso:country":"US",
    "sg:address":"1100 E Colton Avenue",
    "sg:city":"North Las Vegas",
    "sg:classifiers":[
        {
            "category":"Autos & Motor Vehicles",
            "subcategory":"Auto Supplies",
            "type":"Retail Goods"
        }
    ],
    "sg:phone":"+1 702 642 8994",
    "sg:postcode":"89030",
    "sg:province":"NV",
    "sg:tags":[
        "tire"
    ],
    "wof:name":"Around the Clock Tire",
    "wof:placetype":"venue"
},
  "geometry": {"coordinates":[-115.127073,36.221236],"type":"Point"}
}