{
  "type": "Feature",
  "properties": {
    "iso:country":"US",
    "sg:address":"1881 N Decatur Blvd",
    "sg:city":"Las Vegas",
    "sg:classifiers":[
        {
            "category":"Freight",
            "type":"Transportation"
        }
    ],
    "sg:phone":"+1 702 647 4426",
    "sg:postcode":"89108",
    "sg:province":"NV",
    "sg:tags":[
        "general"
    ],
    "wof:name":"Public Storage Inc",
    "wof:placetype":"venue"
},
  "geometry": {"coordinates":[-115.206074,36.193917],"type":"Point"}
}