{
  "type": "Feature",
  "properties": {
    "iso:country":"US",
    "sg:address":"10001 Sailfish Cir",
    "sg:city":"Las Vegas",
    "sg:classifiers":[
        {
            "category":"Wholesale",
            "subcategory":"Groceries",
            "type":"Manufacturing & Wholesale Goods"
        }
    ],
    "sg:phone":"+1 702 562 0006",
    "sg:postcode":"89117",
    "sg:province":"NV",
    "wof:name":"Sweet Island Scents",
    "wof:placetype":"venue"
},
  "geometry": {"coordinates":[-115.314819,36.135408],"type":"Point"}
}