{
  "type": "Feature",
  "properties": {
    "iso:country":"US",
    "sg:address":"3111 S Valley View Blvd",
    "sg:city":"Las Vegas",
    "sg:classifiers":[
        {
            "category":"Building & Trades",
            "subcategory":"Cleaning & Sanitation",
            "type":"Services"
        }
    ],
    "sg:phone":"+1 702 220 9003",
    "sg:postcode":"89102",
    "sg:province":"NV",
    "sg:tags":[
        "carpet"
    ],
    "wof:name":"A Air Condtng Systm Clng",
    "wof:placetype":"venue"
},
  "geometry": {"coordinates":[-115.19000200000001,36.133598],"type":"Point"}
}