{
  "type": "Feature",
  "properties": {
    "iso:country":"US",
    "sg:address":"1909 Coyote Pass Way",
    "sg:city":"Henderson",
    "sg:classifiers":[
        {
            "category":"Insurance",
            "subcategory":"Insurance Agent",
            "type":"Services"
        }
    ],
    "sg:phone":"+1 702 616 8779",
    "sg:postcode":"89012",
    "sg:province":"NV",
    "wof:name":"Mike Seiffer & Assoc",
    "wof:placetype":"venue"
},
  "geometry": {"coordinates":[-115.067929,36.024498],"type":"Point"}
}