{
  "type": "Feature",
  "properties": {
    "iso:country":"US",
    "sg:address":"3450 Losee Rd",
    "sg:city":"North Las Vegas",
    "sg:classifiers":[
        {
            "category":"Building & Trades",
            "subcategory":"Construction",
            "type":"Services"
        }
    ],
    "sg:phone":"+1 702 642 9205",
    "sg:postcode":"89030",
    "sg:province":"NV",
    "sg:tags":[
        "general",
        "contractor"
    ],
    "wof:name":"Target Construction",
    "wof:placetype":"venue"
},
  "geometry": {"coordinates":[-115.123036,36.222973],"type":"Point"}
}