{
  "type": "Feature",
  "properties": {
    "iso:country":"US",
    "sg:address":"2965 S Jones Blvd",
    "sg:city":"Las Vegas",
    "sg:classifiers":[
        {
            "category":"Shopping",
            "type":"Retail Goods"
        }
    ],
    "sg:phone":"+1 702 249 8055",
    "sg:postcode":"89146",
    "sg:province":"NV",
    "sg:tags":[
        "miscellaneous",
        "store"
    ],
    "wof:name":"Your Maids To Order",
    "wof:placetype":"venue"
},
  "geometry": {"coordinates":[-115.225169,36.136024],"type":"Point"}
}