{
  "type": "Feature",
  "properties": {
    "iso:country":"US",
    "sg:address":"3201 W Sahara Avenue",
    "sg:city":"Las Vegas",
    "sg:classifiers":[
        {
            "category":"Building & Trades",
            "subcategory":"Locksmith",
            "type":"Services"
        }
    ],
    "sg:phone":"+1 702 227 5625",
    "sg:postcode":"89102",
    "sg:province":"NV",
    "sg:tags":[
        "key"
    ],
    "sg:website":"www.227lock.com",
    "wof:name":"A-Locks",
    "wof:placetype":"venue"
},
  "geometry": {"coordinates":[-115.184605,36.144307],"type":"Point"}
}