{
  "type": "Feature",
  "properties": {
    "iso:country":"US",
    "sg:address":"225 Telegraph St",
    "sg:city":"Reno",
    "sg:classifiers":[
        {
            "category":"Retail",
            "subcategory":"Auto Repair",
            "type":"Services"
        }
    ],
    "sg:phone":"+1 775 322 7223",
    "sg:postcode":"89502",
    "sg:province":"NV",
    "sg:tags":[
        "repairing",
        "automobile"
    ],
    "wof:name":"Compact Car Repair",
    "wof:placetype":"venue"
},
  "geometry": {"coordinates":[-119.773336,39.519482],"type":"Point"}
}