{
  "type": "Feature",
  "properties": {
    "iso:country":"US",
    "sg:address":"3301 Spring Mountain Rd",
    "sg:city":"Las Vegas",
    "sg:classifiers":[
        {
            "category":"Restaurant",
            "type":"Food & Drink"
        }
    ],
    "sg:phone":"+1 702 221 7037",
    "sg:postcode":"89102",
    "sg:province":"NV",
    "wof:name":"Coyote Cafe At The MGM Grand",
    "wof:placetype":"venue"
},
  "geometry": {"coordinates":[-115.18445699999999,36.126243],"type":"Point"}
}