{
  "type": "Feature",
  "properties": {
    "iso:country":"US",
    "sg:address":"2300 W Charleston Blvd",
    "sg:city":"Las Vegas",
    "sg:classifiers":[
        {
            "category":"Health Services",
            "subcategory":"Doctor",
            "type":"Services"
        }
    ],
    "sg:phone":"+1 702 877 8669",
    "sg:postcode":"89102",
    "sg:province":"NV",
    "sg:tags":[
        "medical"
    ],
    "wof:name":"Harry McKinnon MD",
    "wof:placetype":"venue"
},
  "geometry": {"coordinates":[-115.176215,36.158907],"type":"Point"}
}