{
  "type": "Feature",
  "properties": {
    "iso:country":"US",
    "sg:address":"204 Long Shadow Ter",
    "sg:city":"Henderson",
    "sg:classifiers":[
        {
            "category":"Retail",
            "subcategory":"Laundry & Dry Cleaning",
            "type":"Services"
        }
    ],
    "sg:phone":"+1 702 566 9556",
    "sg:postcode":"89015",
    "sg:province":"NV",
    "wof:name":"J P Ent Group",
    "wof:placetype":"venue"
},
  "geometry": {"coordinates":[-114.95268,36.046004],"type":"Point"}
}