{
  "type": "Feature",
  "properties": {
    "iso:country":"US",
    "sg:address":"1941 N Linda St",
    "sg:city":"Pahrump",
    "sg:classifiers":[
        {
            "category":"Freight",
            "type":"Transportation"
        }
    ],
    "sg:phone":"+1 775 727 8099",
    "sg:postcode":"89060",
    "sg:province":"NV",
    "sg:tags":[
        "general"
    ],
    "wof:name":"First Choice Self Storage",
    "wof:placetype":"venue"
},
  "geometry": {"coordinates":[-116.032577,36.243078],"type":"Point"}
}