{
  "type": "Feature",
  "properties": {
    "iso:country":"US",
    "sg:address":"2228 Barchetta Dr",
    "sg:city":"Las Vegas",
    "sg:classifiers":[
        {
            "category":"Professional",
            "subcategory":"Business Services",
            "type":"Services"
        }
    ],
    "sg:phone":"+1 702 242 9428",
    "sg:postcode":"89134",
    "sg:province":"NV",
    "wof:name":"Jasek Enterprises Inc",
    "wof:placetype":"venue"
},
  "geometry": {"coordinates":[-115.287659,36.201967],"type":"Point"}
}