{
  "type": "Feature",
  "properties": {
    "iso:country":"US",
    "sg:address":"3266 Las Vegas Boulevard N",
    "sg:city":"Las Vegas",
    "sg:classifiers":[
        {
            "category":"Cinema",
            "subcategory":"Movie Rental",
            "type":"Entertainment"
        }
    ],
    "sg:phone":"+1 702 651 0909",
    "sg:postcode":"89115",
    "sg:province":"NV",
    "sg:tags":[
        "game",
        "video"
    ],
    "wof:name":"Game Stop",
    "wof:placetype":"venue"
},
  "geometry": {"coordinates":[-115.09438900000001,36.216983],"type":"Point"}
}