{
  "type": "Feature",
  "properties": {
    "iso:country":"US",
    "sg:address":"5415 W Harmon Ave",
    "sg:city":"Las Vegas",
    "sg:classifiers":[
        {
            "category":"Professional",
            "subcategory":"Advertising",
            "type":"Services"
        }
    ],
    "sg:phone":"+1 702 247 6780",
    "sg:postcode":"89103",
    "sg:province":"NV",
    "wof:name":"Oasis America Co",
    "wof:placetype":"venue"
},
  "geometry": {"coordinates":[-115.21511099999999,36.107671],"type":"Point"}
}