{
  "type": "Feature",
  "properties": {
    "iso:country":"US",
    "sg:address":"361 S Frontage Rd",
    "sg:city":"Pahrump",
    "sg:classifiers":[
        {
            "category":"Retail",
            "subcategory":"Laundry & Dry Cleaning",
            "type":"Services"
        }
    ],
    "sg:phone":"+1 775 751 8712",
    "sg:postcode":"89048",
    "sg:province":"NV",
    "sg:tags":[
        "cleaners"
    ],
    "wof:name":"Courier Cleaners & Shoe Repair",
    "wof:placetype":"venue"
},
  "geometry": {"coordinates":[-115.99433500000001,36.220808],"type":"Point"}
}