{
  "type": "Feature",
  "properties": {
    "iso:country":"US",
    "sg:address":"1808 Fremont St",
    "sg:city":"Las Vegas",
    "sg:classifiers":[
        {
            "category":"Travel",
            "subcategory":"Hotels & Motels",
            "type":"Entertainment"
        }
    ],
    "sg:phone":"+1 702 382 3990",
    "sg:postcode":"89101",
    "sg:province":"NV",
    "wof:name":"Bonanza Lodge Motel",
    "wof:placetype":"venue"
},
  "geometry": {"coordinates":[-115.12074699999999,36.160608],"type":"Point"}
}