{
  "type": "Feature",
  "properties": {
    "iso:country":"US",
    "sg:address":"3600 Procyon St",
    "sg:city":"Las Vegas",
    "sg:classifiers":[
        {
            "category":"Retail",
            "subcategory":"Auto Repair",
            "type":"Services"
        }
    ],
    "sg:phone":"+1 702 368 7800",
    "sg:postcode":"89103",
    "sg:province":"NV",
    "sg:tags":[
        "wrecker"
    ],
    "wof:name":"Custom Towing",
    "wof:placetype":"venue"
},
  "geometry": {"coordinates":[-115.187763,36.124602],"type":"Point"}
}