{
  "type": "Feature",
  "properties": {
    "iso:country":"US",
    "sg:address":"4000 W Flamingo Rd",
    "sg:city":"Las Vegas",
    "sg:classifiers":[
        {
            "category":"Professional",
            "type":"Services"
        }
    ],
    "sg:phone":"+1 702 876 1904",
    "sg:postcode":"89103",
    "sg:province":"NV",
    "wof:name":"CMA Inc",
    "wof:placetype":"venue"
},
  "geometry": {"coordinates":[-115.194111,36.115612],"type":"Point"}
}