{
  "type": "Feature",
  "properties": {
    "iso:country":"US",
    "sg:address":"4800 S Maryland Pkwy",
    "sg:city":"Las Vegas",
    "sg:classifiers":[
        {
            "category":"Food & Beverages",
            "subcategory":"Bakery",
            "type":"Retail Goods"
        }
    ],
    "sg:phone":"+1 702 740 0305",
    "sg:postcode":"89119",
    "sg:province":"NV",
    "sg:tags":[
        "sandwich"
    ],
    "sg:website":"www.jimmyjohns.com",
    "wof:name":"Jimmy John's Gourmet Sandwiches",
    "wof:placetype":"venue"
},
  "geometry": {"coordinates":[-115.136937,36.103121],"type":"Point"}
}