{
  "type": "Feature",
  "properties": {
    "iso:country":"US",
    "sg:address":"4763 Procyon St",
    "sg:city":"Las Vegas",
    "sg:classifiers":[
        {
            "category":"Professional",
            "subcategory":"Computer Services",
            "type":"Services"
        }
    ],
    "sg:phone":"+1 702 736 3432",
    "sg:postcode":"89103",
    "sg:province":"NV",
    "sg:tags":[
        "stereo",
        "installation"
    ],
    "wof:name":"Mastermind Mobile Llc",
    "wof:placetype":"venue"
},
  "geometry": {"coordinates":[-115.187848,36.103476],"type":"Point"}
}