{
  "type": "Feature",
  "properties": {
    "iso:country":"US",
    "sg:address":"2600 S Town Center Dr",
    "sg:city":"Las Vegas",
    "sg:classifiers":[
        {
            "category":"Professional",
            "subcategory":"Management & Consulting",
            "type":"Services"
        }
    ],
    "sg:phone":"+1 702 454 9240",
    "sg:postcode":"89135",
    "sg:province":"NV",
    "sg:tags":[
        "fuel"
    ],
    "wof:name":"Pj B Management",
    "wof:placetype":"venue"
},
  "geometry": {"coordinates":[-115.32638300000001,36.142849],"type":"Point"}
}