{
  "type": "Feature",
  "properties": {
    "iso:country":"US",
    "sg:address":"1121 Palm St",
    "sg:city":"Las Vegas",
    "sg:classifiers":[
        {
            "category":"Professional",
            "subcategory":"Lawyer & Legal Services",
            "type":"Services"
        }
    ],
    "sg:phone":"+1 702 944 2254",
    "sg:postcode":"89104",
    "sg:province":"NV",
    "sg:tags":[
        "attorney"
    ],
    "wof:name":"Law Office of Ed Ewert Ltd",
    "wof:placetype":"venue"
},
  "geometry": {"coordinates":[-115.100998,36.1572],"type":"Point"}
}