{
  "type": "Feature",
  "properties": {
    "iso:country":"US",
    "sg:address":"4520 N Cimarron Rd",
    "sg:city":"Las Vegas",
    "sg:classifiers":[
        {
            "category":"Professional",
            "subcategory":"Business Services",
            "type":"Services"
        }
    ],
    "sg:phone":"+1 702 454 4460",
    "sg:postcode":"89129",
    "sg:province":"NV",
    "wof:name":"Herold Group Inc",
    "wof:placetype":"venue"
},
  "geometry": {"coordinates":[-115.269744,36.240966],"type":"Point"}
}