{
  "type": "Feature",
  "properties": {
    "iso:country":"US",
    "sg:address":"2191 E Tropicana Ave",
    "sg:city":"Las Vegas",
    "sg:classifiers":[
        {
            "category":"Food & Beverages",
            "subcategory":"Specialty",
            "type":"Retail Goods"
        }
    ],
    "sg:phone":"+1 702 214 0888",
    "sg:postcode":"89119",
    "sg:province":"NV",
    "sg:tags":[
        "tea",
        "coffee"
    ],
    "wof:name":"Jitters Gourmet Coffee",
    "wof:placetype":"venue"
},
  "geometry": {"coordinates":[-115.123063,36.100329],"type":"Point"}
}