{
  "type": "Feature",
  "properties": {
    "iso:country":"US",
    "sg:address":"680 Montello St",
    "sg:city":"Reno",
    "sg:classifiers":[
        {
            "category":"Retail",
            "subcategory":"Auto Repair",
            "type":"Services"
        }
    ],
    "sg:phone":"+1 775 348 0908",
    "sg:postcode":"89512",
    "sg:province":"NV",
    "sg:tags":[
        "body",
        "automobile",
        "painting"
    ],
    "wof:name":"A-1 Body Shop",
    "wof:placetype":"venue"
},
  "geometry": {"coordinates":[-119.795124,39.534839],"type":"Point"}
}