{
  "type": "Feature",
  "properties": {
    "iso:country":"US",
    "sg:address":"1506 Glendale Ave",
    "sg:city":"Sparks",
    "sg:classifiers":[
        {
            "category":"Wholesale",
            "subcategory":"Machinery & Supplies",
            "type":"Manufacturing & Wholesale Goods"
        }
    ],
    "sg:phone":"+1 775 352 1371",
    "sg:postcode":"89431",
    "sg:province":"NV",
    "sg:tags":[
        "equipment",
        "durable",
        "establishment"
    ],
    "wof:name":"Nls Lock Supply Inc",
    "wof:placetype":"venue"
},
  "geometry": {"coordinates":[-119.764974,39.527628],"type":"Point"}
}