{
  "type": "Feature",
  "properties": {
    "iso:country":"US",
    "sg:address":"9130 W Sahara Ave",
    "sg:city":"Las Vegas",
    "sg:classifiers":[
        {
            "category":"Insurance",
            "subcategory":"Insurance Agent",
            "type":"Services"
        }
    ],
    "sg:phone":"+1 702 233 0330",
    "sg:postcode":"89117",
    "sg:province":"NV",
    "wof:name":"Burford Roger Ins Agency",
    "wof:placetype":"venue"
},
  "geometry": {"coordinates":[-115.294673,36.144389],"type":"Point"}
}