{
  "type": "Feature",
  "properties": {
    "iso:country":"US",
    "sg:address":"416 N 8th St",
    "sg:city":"Las Vegas",
    "sg:classifiers":[
        {
            "category":"Communications",
            "subcategory":"Television Station",
            "type":"Services"
        }
    ],
    "sg:phone":"+1 702 366 1625",
    "sg:postcode":"89101",
    "sg:province":"NV",
    "sg:tags":[
        "broadcasting",
        "co"
    ],
    "wof:name":"KVVU TV 5",
    "wof:placetype":"venue"
},
  "geometry": {"coordinates":[-115.134748,36.171937],"type":"Point"}
}