{
  "type": "Feature",
  "properties": {
    "iso:country":"US",
    "sg:address":"14 Promontory Ridge Dr",
    "sg:city":"Las Vegas",
    "sg:classifiers":[
        {
            "category":"Building & Trades",
            "subcategory":"Construction",
            "type":"Services"
        }
    ],
    "sg:phone":"+1 702 363 2231",
    "sg:postcode":"89135",
    "sg:province":"NV",
    "sg:tags":[
        "contractor"
    ],
    "wof:name":"Downey Construction",
    "wof:placetype":"venue"
},
  "geometry": {"coordinates":[-115.344526,36.125776],"type":"Point"}
}