{
  "type": "Feature",
  "properties": {
    "iso:country":"US",
    "sg:address":"1785 E Sahara Ave",
    "sg:city":"Las Vegas",
    "sg:classifiers":[
        {
            "category":"Professional",
            "subcategory":"Computer Services",
            "type":"Services"
        }
    ],
    "sg:phone":"+1 702 731 6001",
    "sg:postcode":"89104",
    "sg:province":"NV",
    "sg:tags":[
        "consultant",
        "designer"
    ],
    "wof:name":"IBM",
    "wof:placetype":"venue"
},
  "geometry": {"coordinates":[-115.127881,36.144277],"type":"Point"}
}