{
  "type": "Feature",
  "properties": {
    "iso:country":"US",
    "sg:address":"1450 E Prater Way",
    "sg:city":"Sparks",
    "sg:classifiers":[
        {
            "category":"Shopping",
            "subcategory":"Bicycles & Sporting Goods",
            "type":"Retail Goods"
        }
    ],
    "sg:phone":"+1 775 331 2000",
    "sg:postcode":"89434",
    "sg:province":"NV",
    "wof:name":"Reno Cycling & Fitness",
    "wof:placetype":"venue"
},
  "geometry": {"coordinates":[-119.716267,39.542045],"type":"Point"}
}