{
  "type": "Feature",
  "properties": {
    "iso:country":"US",
    "sg:address":"408 S 7th St",
    "sg:city":"Las Vegas",
    "sg:classifiers":[
        {
            "category":"Real Estate",
            "subcategory":"Real Estate Agent",
            "type":"Services"
        }
    ],
    "sg:phone":"+1 702 798 4848",
    "sg:postcode":"89101",
    "sg:province":"NV",
    "wof:name":"Distinctive Real Estate",
    "wof:placetype":"venue"
},
  "geometry": {"coordinates":[-115.141443,36.163738],"type":"Point"}
}