{
  "type": "Feature",
  "properties": {
    "iso:country":"US",
    "sg:address":"1015 S Cimarron Rd",
    "sg:city":"Las Vegas",
    "sg:classifiers":[
        {
            "category":"Food & Beverages",
            "subcategory":"Specialty",
            "type":"Retail Goods"
        }
    ],
    "sg:phone":"+1 702 682 1525",
    "sg:postcode":"89145",
    "sg:province":"NV",
    "sg:tags":[
        "health",
        "diet"
    ],
    "wof:name":"Usana Health Sciences Distr",
    "wof:placetype":"venue"
},
  "geometry": {"coordinates":[-115.27111,36.160051],"type":"Point"}
}