{
  "type": "Feature",
  "properties": {
    "iso:country":"US",
    "sg:address":"1215 Stewart Avenue",
    "sg:city":"Las Vegas",
    "sg:classifiers":[
        {
            "category":"Food & Beverages",
            "subcategory":"Groceries & Convenience Stores",
            "type":"Retail Goods"
        }
    ],
    "sg:phone":"+1 702 386 0481",
    "sg:postcode":"89101",
    "sg:province":"NV",
    "sg:website":"www.7-eleven.com",
    "wof:name":"7-Eleven",
    "wof:placetype":"venue"
},
  "geometry": {"coordinates":[-115.13068199999999,36.168069],"type":"Point"}
}