{
  "type": "Feature",
  "properties": {
    "iso:country":"US",
    "sg:address":"3024 Fremont St",
    "sg:city":"Las Vegas",
    "sg:classifiers":[
        {
            "category":"Retail",
            "subcategory":"Auto Repair",
            "type":"Services"
        }
    ],
    "sg:phone":"+1 702 457 1021",
    "sg:postcode":"89104",
    "sg:province":"NV",
    "sg:tags":[
        "body",
        "shop"
    ],
    "wof:name":"Findlay Body Shop",
    "wof:placetype":"venue"
},
  "geometry": {"coordinates":[-115.10900100000001,36.1521],"type":"Point"}
}