{
  "type": "Feature",
  "properties": {
    "iso:country":"US",
    "sg:address":"110 N 15th St",
    "sg:city":"Las Vegas",
    "sg:classifiers":[
        {
            "category":"Building & Trades",
            "subcategory":"Pest Control",
            "type":"Services"
        }
    ],
    "sg:phone":"+1 702 452 0400",
    "sg:postcode":"89101",
    "sg:province":"NV",
    "wof:name":"Bigfoot Pest Control",
    "wof:placetype":"venue"
},
  "geometry": {"coordinates":[-115.12874600000001,36.164966],"type":"Point"}
}