{
  "type": "Feature",
  "properties": {
    "iso:country":"US",
    "sg:address":"4735 Madrigal Way",
    "sg:city":"Las Vegas",
    "sg:classifiers":[
        {
            "category":"Retail",
            "subcategory":"Auto Repair",
            "type":"Services"
        }
    ],
    "sg:phone":"+1 702 454 0665",
    "sg:postcode":"89122",
    "sg:province":"NV",
    "sg:tags":[
        "automotive"
    ],
    "wof:name":"Redline Auto Repair",
    "wof:placetype":"venue"
},
  "geometry": {"coordinates":[-115.043237,36.10326],"type":"Point"}
}