{
  "type": "Feature",
  "properties": {
    "iso:country":"US",
    "sg:address":"1417 Melissa St",
    "sg:city":"Las Vegas",
    "sg:classifiers":[
        {
            "category":"Personal",
            "type":"Services"
        },
        {
            "category":"Building & Trades",
            "subcategory":"Construction",
            "type":"Services"
        }
    ],
    "sg:phone":"+1 702 639 0423",
    "sg:postcode":"89101",
    "sg:province":"NV",
    "sg:tags":[
        "home",
        "improvement"
    ],
    "wof:name":"J & J & Little J",
    "wof:placetype":"venue"
},
  "geometry": {"coordinates":[-115.108275,36.186372],"type":"Point"}
}