{
  "type": "Feature",
  "properties": {
    "iso:country":"US",
    "sg:address":"94 Arthur Hills Ct",
    "sg:city":"Henderson",
    "sg:classifiers":[
        {
            "category":"Communications",
            "subcategory":"Film & Video Production",
            "type":"Services"
        }
    ],
    "sg:phone":"+1 702 617 8832",
    "sg:postcode":"89074",
    "sg:province":"NV",
    "sg:tags":[
        "educational",
        "program",
        "producer",
        "related",
        "entertainment"
    ],
    "wof:name":"Twin Faces East Entrmt Corp",
    "wof:placetype":"venue"
},
  "geometry": {"coordinates":[-115.07634,36.031131],"type":"Point"}
}