{
  "type": "Feature",
  "properties": {
    "iso:country":"US",
    "sg:address":"1812 Quail Point Ct",
    "sg:city":"Las Vegas",
    "sg:classifiers":[
        {
            "category":"Professional",
            "subcategory":"Management & Consulting",
            "type":"Services"
        }
    ],
    "sg:phone":"+1 702 360 5419",
    "sg:postcode":"89117",
    "sg:province":"NV",
    "sg:tags":[
        "business"
    ],
    "wof:name":"Eggman",
    "wof:placetype":"venue"
},
  "geometry": {"coordinates":[-115.278734,36.149928],"type":"Point"}
}