{
  "type": "Feature",
  "properties": {
    "iso:country":"US",
    "sg:address":"3937 Lost Miner Ct",
    "sg:city":"Las Vegas",
    "sg:classifiers":[
        {
            "category":"Real Estate",
            "subcategory":"Real Estate Agent",
            "type":"Services"
        }
    ],
    "sg:phone":"+1 702 254 7542",
    "sg:postcode":"89129",
    "sg:province":"NV",
    "wof:name":"Southwest Land Holding",
    "wof:placetype":"venue"
},
  "geometry": {"coordinates":[-115.28098300000001,36.233155],"type":"Point"}
}