{
  "type": "Feature",
  "properties": {
    "iso:country":"US",
    "sg:address":"3320 Wynn Road",
    "sg:city":"Las Vegas",
    "sg:classifiers":[
        {
            "category":"Education",
            "subcategory":"School",
            "type":"Public Place"
        }
    ],
    "sg:phone":"+1 702 247 1006",
    "sg:postcode":"89102",
    "sg:province":"NV",
    "wof:name":"Train 2 Excel",
    "wof:placetype":"venue"
},
  "geometry": {"coordinates":[-115.194588,36.129773],"type":"Point"}
}