{
  "type": "Feature",
  "properties": {
    "iso:country":"US",
    "sg:address":"500 Parkson Rd",
    "sg:city":"Henderson",
    "sg:classifiers":[
        {
            "category":"Professional",
            "type":"Services"
        }
    ],
    "sg:phone":"+1 702 737 0111",
    "sg:postcode":"89011",
    "sg:province":"NV",
    "sg:tags":[
        "establishment"
    ],
    "wof:name":"S A Sabraw & Co LLC",
    "wof:placetype":"venue"
},
  "geometry": {"coordinates":[-115.022388,36.063845],"type":"Point"}
}