{
  "type": "Feature",
  "properties": {
    "iso:country":"US",
    "sg:address":"4600 Kietzke Ln",
    "sg:city":"Reno",
    "sg:classifiers":[
        {
            "category":"Government",
            "subcategory":"Office",
            "type":"Public Place"
        }
    ],
    "sg:phone":"+1 775 688 1211",
    "sg:postcode":"89502",
    "sg:province":"NV",
    "sg:tags":[
        "commission",
        "dairy"
    ],
    "wof:name":"Nevada Dairy Commission",
    "wof:placetype":"venue"
},
  "geometry": {"coordinates":[-119.791048,39.482628],"type":"Point"}
}