{
  "type": "Feature",
  "properties": {
    "iso:country":"US",
    "sg:address":"8725 Robinson Ridge Drive",
    "sg:city":"Las Vegas",
    "sg:classifiers":[
        {
            "category":"Professional",
            "subcategory":"Lawyer & Legal Services",
            "type":"Services"
        }
    ],
    "sg:phone":"+1 702 368 1150",
    "sg:postcode":"89117",
    "sg:province":"NV",
    "wof:name":"Tavano Louis J Law Office",
    "wof:placetype":"venue"
},
  "geometry": {"coordinates":[-115.285386,36.152143],"type":"Point"}
}