{
  "type": "Feature",
  "properties": {
    "iso:country":"US",
    "sg:address":"7201 W Lake Mead Boulevard",
    "sg:city":"Las Vegas",
    "sg:classifiers":[
        {
            "category":"Professional",
            "subcategory":"Lawyer & Legal Services",
            "type":"Services"
        }
    ],
    "sg:phone":"+1 702 838 8600",
    "sg:postcode":"89128",
    "sg:province":"NV",
    "wof:name":"Parker Theodore Atty",
    "wof:placetype":"venue"
},
  "geometry": {"coordinates":[-115.249538,36.195968],"type":"Point"}
}