{
  "type": "Feature",
  "properties": {
    "iso:country":"US",
    "sg:address":"5836 S Pecos Rd",
    "sg:city":"Las Vegas",
    "sg:classifiers":[
        {
            "category":"Professional",
            "subcategory":"Lawyer & Legal Services",
            "type":"Services"
        }
    ],
    "sg:phone":"+1 702 315 0448",
    "sg:postcode":"89120",
    "sg:province":"NV",
    "wof:name":"The Groesbeck Group",
    "wof:placetype":"venue"
},
  "geometry": {"coordinates":[-115.100998,36.084],"type":"Point"}
}