{
  "type": "Feature",
  "properties": {
    "iso:country":"US",
    "sg:address":"220 S Rock Blvd",
    "sg:city":"Reno",
    "sg:classifiers":[
        {
            "category":"Professional",
            "type":"Services"
        }
    ],
    "sg:phone":"+1 775 352 3885",
    "sg:postcode":"89502",
    "sg:province":"NV",
    "sg:tags":[
        "establishment"
    ],
    "wof:name":"Wayne Stagner Steer America",
    "wof:placetype":"venue"
},
  "geometry": {"coordinates":[-119.76264500000001,39.511549],"type":"Point"}
}