{
  "type": "Feature",
  "properties": {
    "iso:country":"US",
    "sg:address":"3150 N Tenaya Way",
    "sg:city":"Las Vegas",
    "sg:classifiers":[
        {
            "category":"Health Services",
            "subcategory":"Doctor",
            "type":"Services"
        }
    ],
    "sg:phone":"+1 702 796 0300",
    "sg:postcode":"89128",
    "sg:province":"NV",
    "sg:tags":[
        "physician",
        "surgeon",
        "medical"
    ],
    "wof:name":"First Choice Family Care",
    "wof:placetype":"venue"
},
  "geometry": {"coordinates":[-115.250201,36.214129],"type":"Point"}
}