{
  "type": "Feature",
  "properties": {
    "iso:country":"US",
    "sg:address":"649 Caughlin Glen",
    "sg:city":"Reno",
    "sg:classifiers":[
        {
            "category":"Professional",
            "subcategory":"Business Services",
            "type":"Services"
        }
    ],
    "sg:phone":"+1 775 746 2422",
    "sg:postcode":"89509",
    "sg:province":"NV",
    "wof:name":"Holland & Associates",
    "wof:placetype":"venue"
},
  "geometry": {"coordinates":[-119.858988,39.503584],"type":"Point"}
}