{
  "type": "Feature",
  "properties": {
    "iso:country":"US",
    "sg:address":"10220 W Charleston Blvd",
    "sg:city":"Las Vegas",
    "sg:classifiers":[
        {
            "category":"Health Services",
            "subcategory":"Doctor",
            "type":"Services"
        }
    ],
    "sg:phone":"+1 702 947 6453",
    "sg:postcode":"89135",
    "sg:province":"NV",
    "sg:tags":[
        "dentist"
    ],
    "wof:name":"Comfort Dental Of Las Vegas",
    "wof:placetype":"venue"
},
  "geometry": {"coordinates":[-115.317187,36.159041],"type":"Point"}
}