{
  "type": "Feature",
  "properties": {
    "iso:country":"US",
    "sg:address":"8370 W Cheyenne Ave",
    "sg:city":"Las Vegas",
    "sg:classifiers":[
        {
            "category":"Building & Trades",
            "subcategory":"Construction",
            "type":"Services"
        }
    ],
    "sg:phone":"+1 702 328 5088",
    "sg:postcode":"89129",
    "sg:province":"NV",
    "sg:tags":[
        "coping",
        "plastering",
        "tiling",
        "pool",
        "swimming"
    ],
    "wof:name":"Pool Dude",
    "wof:placetype":"venue"
},
  "geometry": {"coordinates":[-115.275788,36.218645],"type":"Point"}
}