{
  "type": "Feature",
  "properties": {
    "iso:country":"US",
    "sg:address":"17650 S Reno Park Blvd",
    "sg:city":"Reno",
    "sg:classifiers":[
        {
            "category":"Real Estate",
            "subcategory":"Real Estate Operator",
            "type":"Services"
        }
    ],
    "sg:phone":"+1 775 972 6506",
    "sg:postcode":"89508",
    "sg:province":"NV",
    "sg:tags":[
        "mobile",
        "home",
        "community"
    ],
    "wof:name":"Lakeview 74",
    "wof:placetype":"venue"
},
  "geometry": {"coordinates":[-119.99720600000001,39.660466],"type":"Point"}
}