{
  "type": "Feature",
  "properties": {
    "iso:country":"US",
    "sg:address":"1925 Constellation Ct",
    "sg:city":"Reno",
    "sg:classifiers":[
        {
            "category":"Building & Trades",
            "subcategory":"Construction",
            "type":"Services"
        }
    ],
    "sg:phone":"+1 775 787 6820",
    "sg:postcode":"89523",
    "sg:province":"NV",
    "sg:tags":[
        "house"
    ],
    "wof:name":"Rathmann Construction & Dev",
    "wof:placetype":"venue"
},
  "geometry": {"coordinates":[-119.876067,39.534506],"type":"Point"}
}