{
  "type": "Feature",
  "properties": {
    "iso:country":"US",
    "sg:address":"1653 Lucerne St",
    "sg:city":"Minden",
    "sg:classifiers":[
        {
            "category":"Utilities",
            "subcategory":"Refuse",
            "type":"Services"
        }
    ],
    "sg:phone":"+1 775 782 5713",
    "sg:postcode":"89423",
    "sg:province":"NV",
    "sg:tags":[
        "garbage",
        "collection"
    ],
    "wof:name":"Douglas Disposal Inc",
    "wof:placetype":"venue"
},
  "geometry": {"coordinates":[-119.773551,38.954883],"type":"Point"}
}