{
  "type": "Feature",
  "properties": {
    "iso:country":"US",
    "sg:address":"1700 S Eastern Ave",
    "sg:city":"Las Vegas",
    "sg:classifiers":[
        {
            "category":"Health Services",
            "subcategory":"Doctor",
            "type":"Services"
        }
    ],
    "sg:phone":"+1 702 641 1775",
    "sg:postcode":"89104",
    "sg:province":"NV",
    "sg:tags":[
        "physician",
        "surgeon"
    ],
    "wof:name":"Najm Gharavi MD",
    "wof:placetype":"venue"
},
  "geometry": {"coordinates":[-115.118758,36.150946],"type":"Point"}
}