{
  "type": "Feature",
  "properties": {
    "iso:country":"US",
    "sg:address":"1308 Wyoming St",
    "sg:city":"Boulder City",
    "sg:classifiers":[
        {
            "category":"Social Services",
            "subcategory":"Child Care",
            "type":"Services"
        }
    ],
    "sg:phone":"+1 702 293 5188",
    "sg:postcode":"89005",
    "sg:province":"NV",
    "sg:tags":[
        "kindergarten",
        "academic",
        "school",
        "day"
    ],
    "wof:name":"Oaklane Preschool Academy",
    "wof:placetype":"venue"
},
  "geometry": {"coordinates":[-114.836583,35.976833],"type":"Point"}
}