{
  "type": "Feature",
  "properties": {
    "iso:country":"US",
    "sg:address":"241 S Sierra St",
    "sg:city":"Reno",
    "sg:classifiers":[
        {
            "category":"Arts & Performance",
            "subcategory":"Theater",
            "type":"Entertainment"
        }
    ],
    "sg:phone":"+1 775 762 7408",
    "sg:postcode":"89501",
    "sg:province":"NV",
    "sg:tags":[
        "design",
        "costume"
    ],
    "wof:name":"Ymi Wear",
    "wof:placetype":"venue"
},
  "geometry": {"coordinates":[-119.812883,39.522468],"type":"Point"}
}