{
  "type": "Feature",
  "properties": {
    "iso:country":"US",
    "sg:address":"3039 Woods Dr",
    "sg:city":"Las Vegas",
    "sg:classifiers":[
        {
            "category":"Building & Trades",
            "subcategory":"Construction",
            "type":"Services"
        }
    ],
    "sg:phone":"+1 702 561 3690",
    "sg:postcode":"89108",
    "sg:province":"NV",
    "sg:tags":[
        "handyman"
    ],
    "wof:name":"D & S Handyman",
    "wof:placetype":"venue"
},
  "geometry": {"coordinates":[-115.22269,36.214601],"type":"Point"}
}