{
  "type": "Feature",
  "properties": {
    "iso:country":"US",
    "sg:address":"1936 N Carson St",
    "sg:city":"Carson City",
    "sg:classifiers":[
        {
            "category":"Restaurant",
            "type":"Food & Drink"
        }
    ],
    "sg:phone":"+1 775 882 3050",
    "sg:postcode":"89701",
    "sg:province":"NV",
    "sg:tags":[
        "eating",
        "chinese"
    ],
    "wof:name":"China Kitchen",
    "wof:placetype":"venue"
},
  "geometry": {"coordinates":[-119.766998,39.178001],"type":"Point"}
}