{
  "type": "Feature",
  "properties": {
    "iso:country":"US",
    "sg:address":"11840 Camel Rock Dr",
    "sg:city":"Reno",
    "sg:classifiers":[
        {
            "category":"Building & Trades",
            "subcategory":"Construction",
            "type":"Services"
        }
    ],
    "sg:phone":"+1 775 771 7934",
    "sg:postcode":"89506",
    "sg:province":"NV",
    "sg:tags":[
        "house"
    ],
    "wof:name":"Home Repair Extraordinaire",
    "wof:placetype":"venue"
},
  "geometry": {"coordinates":[-119.870805,39.639865],"type":"Point"}
}