{
  "type": "Feature",
  "properties": {
    "iso:country":"US",
    "sg:address":"3421 E Tropicana Avenue Suite K",
    "sg:city":"Las Vegas",
    "sg:classifiers":[
        {
            "category":"Shopping",
            "subcategory":"Florist",
            "type":"Retail Goods"
        }
    ],
    "sg:phone":"+1 702 433 7330",
    "sg:postcode":"89121",
    "sg:province":"NV",
    "wof:name":"A Green Florist",
    "wof:placetype":"venue"
},
  "geometry": {"coordinates":[-115.10056,36.099972],"type":"Point"}
}