{
  "type": "Feature",
  "properties": {
    "iso:country":"US",
    "sg:address":"6540 Blue Diamond Rd",
    "sg:city":"Las Vegas",
    "sg:classifiers":[
        {
            "category":"Building & Trades",
            "subcategory":"Construction",
            "type":"Services"
        }
    ],
    "sg:phone":"+1 702 361 3400",
    "sg:postcode":"89139",
    "sg:province":"NV",
    "sg:tags":[
        "designer",
        "dealer",
        "pool",
        "swimming"
    ],
    "wof:name":"Renaissance Pools & Spas",
    "wof:placetype":"venue"
},
  "geometry": {"coordinates":[-115.23866099999999,36.023355],"type":"Point"}
}