{
  "type": "Feature",
  "properties": {
    "iso:country":"US",
    "sg:address":"2310 Pso del Prado",
    "sg:city":"Las Vegas",
    "sg:classifiers":[
        {
            "category":"Shopping",
            "subcategory":"Pharmacy",
            "type":"Retail Goods"
        }
    ],
    "sg:phone":"+1 702 876 8849",
    "sg:postcode":"89102",
    "sg:province":"NV",
    "sg:tags":[
        "pharmaceutical",
        "consultant"
    ],
    "wof:name":"Pharmadyne",
    "wof:placetype":"venue"
},
  "geometry": {"coordinates":[-115.177649,36.145147],"type":"Point"}
}