{
  "type": "Feature",
  "properties": {
    "iso:country":"US",
    "sg:address":"4975 Newportcove Dr",
    "sg:city":"Las Vegas",
    "sg:classifiers":[
        {
            "category":"Retail",
            "subcategory":"Repair Shop",
            "type":"Services"
        }
    ],
    "sg:phone":"+1 702 808 2729",
    "sg:postcode":"89119",
    "sg:province":"NV",
    "sg:tags":[
        "related"
    ],
    "wof:name":"Quality Plus Dental Handpiece",
    "wof:placetype":"venue"
},
  "geometry": {"coordinates":[-115.12621300000001,36.097624],"type":"Point"}
}