{
  "type": "Feature",
  "properties": {
    "iso:country":"US",
    "sg:address":"3172 N Rainbow Blvd",
    "sg:city":"Las Vegas",
    "sg:classifiers":[
        {
            "category":"Building & Trades",
            "subcategory":"Construction",
            "type":"Services"
        }
    ],
    "sg:phone":"+1 702 656 6200",
    "sg:postcode":"89108",
    "sg:province":"NV",
    "sg:tags":[
        "coping",
        "plastering",
        "tiling",
        "pool",
        "swimming"
    ],
    "sg:website":"www.poolspecialties.com",
    "wof:name":"Pool Specialties",
    "wof:placetype":"venue"
},
  "geometry": {"coordinates":[-115.24221199999999,36.215687],"type":"Point"}
}