{
  "type": "Feature",
  "properties": {
    "iso:country":"US",
    "sg:address":"50 E Azure Ave",
    "sg:city":"North Las Vegas",
    "sg:classifiers":[
        {
            "category":"Organizations",
            "subcategory":"Religious Organization",
            "type":"Services"
        }
    ],
    "sg:phone":"+1 702 633 0081",
    "sg:postcode":"89030",
    "sg:province":"NV",
    "sg:website":"www.lds.org",
    "wof:name":"Church of Jesus Christ of Latter-Day Saints",
    "wof:placetype":"venue"
},
  "geometry": {"coordinates":[-115.139031,36.272778],"type":"Point"}
}