{
  "type": "Feature",
  "properties": {
    "iso:country":"US",
    "sg:address":"1021 Court St",
    "sg:city":"Elko",
    "sg:classifiers":[
        {
            "category":"Professional",
            "subcategory":"Business Services",
            "type":"Services"
        }
    ],
    "sg:phone":"+1 775 753 8136",
    "sg:postcode":"89801",
    "sg:province":"NV",
    "wof:name":"Internet Sales",
    "wof:placetype":"venue"
},
  "geometry": {"coordinates":[-115.758657,40.837713],"type":"Point"}
}