{
  "type": "Feature",
  "properties": {
    "iso:country":"US",
    "sg:address":"1010 N Stephanie St",
    "sg:city":"Henderson",
    "sg:classifiers":[
        {
            "category":"Retail",
            "subcategory":"Auto Repair",
            "type":"Services"
        }
    ],
    "sg:phone":"+1 702 649 9722",
    "sg:postcode":"89014",
    "sg:province":"NV",
    "sg:tags":[
        "body",
        "automobile",
        "painting"
    ],
    "wof:name":"Tee's Auto Body & Paint",
    "wof:placetype":"venue"
},
  "geometry": {"coordinates":[-115.045008,36.079539],"type":"Point"}
}