{
  "type": "Feature",
  "properties": {
    "iso:country":"US",
    "sg:address":"915 Garces Ave",
    "sg:city":"Las Vegas",
    "sg:classifiers":[
        {
            "category":"Banks & Credit Unions",
            "subcategory":"Investment Brokerage",
            "type":"Services"
        },
        {
            "category":"Personal",
            "type":"Services"
        }
    ],
    "sg:phone":"+1 702 477 6477",
    "sg:postcode":"89101",
    "sg:province":"NV",
    "sg:tags":[
        "consultant",
        "planning",
        "financial"
    ],
    "wof:name":"Edwards Management Servic",
    "wof:placetype":"venue"
},
  "geometry": {"coordinates":[-115.139635,36.159938],"type":"Point"}
}