{
  "type": "Feature",
  "properties": {
    "iso:country":"US",
    "sg:address":"7 Promenade Way",
    "sg:city":"Henderson",
    "sg:classifiers":[
        {
            "category":"Professional",
            "subcategory":"Management & Consulting",
            "type":"Services"
        },
        {
            "category":"Professional",
            "subcategory":"Advertising",
            "type":"Services"
        }
    ],
    "sg:phone":"+1 702 564 2600",
    "sg:postcode":"89011",
    "sg:province":"NV",
    "sg:tags":[
        "marketing",
        "counselor",
        "consultant"
    ],
    "wof:name":"Schepps Communications Inc",
    "wof:placetype":"venue"
},
  "geometry": {"coordinates":[-114.920727,36.108277],"type":"Point"}
}