{
  "type": "Feature",
  "properties": {
    "iso:country":"US",
    "sg:address":"427 Paulson Dr",
    "sg:city":"Las Vegas",
    "sg:classifiers":[
        {
            "category":"Shopping",
            "subcategory":"Gifts & Souvenirs",
            "type":"Retail Goods"
        }
    ],
    "sg:phone":"+1 702 897 2348",
    "sg:postcode":"89123",
    "sg:province":"NV",
    "sg:tags":[
        "shop"
    ],
    "wof:name":"E Scential Gifts",
    "wof:placetype":"venue"
},
  "geometry": {"coordinates":[-115.150789,36.033909],"type":"Point"}
}