{
  "type": "Feature",
  "properties": {
    "iso:country":"US",
    "sg:address":"2365 Rocky Ridge Dr",
    "sg:city":"Henderson",
    "sg:classifiers":[
        {
            "category":"Real Estate",
            "subcategory":"Developer",
            "type":"Services"
        }
    ],
    "sg:phone":"+1 702 263 7666",
    "sg:postcode":"89052",
    "sg:province":"NV",
    "sg:tags":[
        "land"
    ],
    "wof:name":"Fait Enterprises Inc",
    "wof:placetype":"venue"
},
  "geometry": {"coordinates":[-115.091126,35.992235],"type":"Point"}
}