{
  "type": "Feature",
  "properties": {
    "iso:country":"US",
    "sg:address":"3624 E Russell Rd",
    "sg:city":"Las Vegas",
    "sg:classifiers":[
        {
            "category":"Building & Trades",
            "subcategory":"Construction",
            "type":"Services"
        }
    ],
    "sg:phone":"+1 702 458 2772",
    "sg:postcode":"89120",
    "sg:province":"NV",
    "sg:tags":[
        "contractor"
    ],
    "wof:name":"Rm General Contracting",
    "wof:placetype":"venue"
},
  "geometry": {"coordinates":[-115.095883,36.086173],"type":"Point"}
}