{
  "type": "Feature",
  "properties": {
    "iso:country":"US",
    "sg:address":"4079 Spring Mountain Road",
    "sg:city":"Las Vegas",
    "sg:classifiers":[
        {
            "category":"Shopping",
            "subcategory":"Pharmacy",
            "type":"Retail Goods"
        }
    ],
    "sg:phone":"+1 702 876 2273",
    "sg:postcode":"89102",
    "sg:province":"NV",
    "sg:tags":[
        "drugstore"
    ],
    "wof:name":"Rx Discount Pharmacy",
    "wof:placetype":"venue"
},
  "geometry": {"coordinates":[-115.194208,36.126313],"type":"Point"}
}