{
  "type": "Feature",
  "properties": {
    "iso:country":"US",
    "sg:address":"Four Queens 202 Fremont St",
    "sg:city":"Las Vegas",
    "sg:classifiers":[
        {
            "category":"Arts & Performance",
            "subcategory":"Comedy Club",
            "type":"Entertainment"
        }
    ],
    "sg:phone":"+1 702 275 3877",
    "sg:postcode":"89101",
    "sg:province":"NV",
    "sg:website":"www.lacomedyclub.com",
    "wof:name":"Four Queen's LA Comedy Club",
    "wof:placetype":"venue"
},
  "geometry": {"coordinates":[-115.144035,36.170345],"type":"Point"}
}