{
  "type": "Feature",
  "properties": {
    "iso:country":"US",
    "sg:address":"210 E Enterprise St",
    "sg:city":"Incline Village",
    "sg:classifiers":[
        {
            "category":"Building & Trades",
            "subcategory":"Construction",
            "type":"Services"
        }
    ],
    "sg:phone":"+1 775 831 9171",
    "sg:postcode":"89451",
    "sg:province":"NV",
    "sg:tags":[
        "roofing",
        "contractor"
    ],
    "wof:name":"Class A Roofing",
    "wof:placetype":"venue"
},
  "geometry": {"coordinates":[-119.953885,39.247738],"type":"Point"}
}