{
  "type": "Feature",
  "properties": {
    "iso:country":"US",
    "sg:address":"4425 Spring Mountain Road",
    "sg:city":"Las Vegas",
    "sg:classifiers":[
        {
            "category":"Banks & Credit Unions",
            "subcategory":"Bank",
            "type":"Services"
        }
    ],
    "sg:phone":"+1 702 952 6648",
    "sg:postcode":"89102",
    "sg:province":"NV",
    "wof:name":"First Security Bank of Nevada",
    "wof:placetype":"venue"
},
  "geometry": {"coordinates":[-115.199844,36.126344],"type":"Point"}
}