{
  "type": "Feature",
  "properties": {
    "iso:country":"US",
    "sg:address":"821 N Lamb Blvd",
    "sg:city":"Las Vegas",
    "sg:classifiers":[
        {
            "category":"Real Estate",
            "subcategory":"Real Estate Agent",
            "type":"Services"
        }
    ],
    "sg:phone":"+1 702 457 3394",
    "sg:postcode":"89110",
    "sg:province":"NV",
    "wof:name":"A Miracle Realty",
    "wof:placetype":"venue"
},
  "geometry": {"coordinates":[-115.080328,36.177516],"type":"Point"}
}