{
  "type": "Feature",
  "properties": {
    "iso:country":"US",
    "sg:address":"4375 W Desert Inn Rd",
    "sg:city":"Las Vegas",
    "sg:classifiers":[
        {
            "category":"Manufacturing",
            "subcategory":"Printing",
            "type":"Manufacturing & Wholesale Goods"
        }
    ],
    "sg:phone":"+1 702 870 9938",
    "sg:postcode":"89102",
    "sg:province":"NV",
    "sg:tags":[
        "news",
        "publication"
    ],
    "wof:name":"Next Weekly",
    "wof:placetype":"venue"
},
  "geometry": {"coordinates":[-115.197259,36.129981],"type":"Point"}
}