{
  "type": "Feature",
  "properties": {
    "iso:country":"US",
    "sg:address":"585 Pilot Rd",
    "sg:city":"Las Vegas",
    "sg:classifiers":[
        {
            "category":"Banks & Credit Unions",
            "subcategory":"Bank",
            "type":"Services"
        }
    ],
    "sg:phone":"+1 702 361 7485",
    "sg:postcode":"89119",
    "sg:province":"NV",
    "sg:website":"www.fnbmarin.com",
    "wof:name":"First National Bank Of Marin",
    "wof:placetype":"venue"
},
  "geometry": {"coordinates":[-115.152619,36.067756],"type":"Point"}
}