{
  "type": "Feature",
  "properties": {
    "iso:country":"US",
    "sg:address":"1600 E Desert Inn Rd Ste 225",
    "sg:city":"Las Vegas",
    "sg:classifiers":[
        {
            "category":"Health Services",
            "subcategory":"Health Practitioner",
            "type":"Services"
        }
    ],
    "sg:phone":"+1 702 252 3007",
    "sg:postcode":"89169",
    "sg:province":"NV",
    "sg:tags":[
        "therapy",
        "physical"
    ],
    "wof:name":"Nevada Rehabilitation Inc",
    "wof:placetype":"venue"
},
  "geometry": {"coordinates":[-115.130608,36.129967],"type":"Point"}
}