{
  "type": "Feature",
  "properties": {
    "iso:country":"US",
    "sg:address":"2380 E Flamingo Rd",
    "sg:city":"Las Vegas",
    "sg:classifiers":[
        {
            "category":"Autos & Motor Vehicles",
            "subcategory":"Fuel & Gas Station",
            "type":"Retail Goods"
        }
    ],
    "sg:phone":"+1 702 734 8711",
    "sg:postcode":"89119",
    "sg:province":"NV",
    "sg:tags":[
        "oil"
    ],
    "wof:name":"Rebel Oil Co",
    "wof:placetype":"venue"
},
  "geometry": {"coordinates":[-115.121191,36.114736],"type":"Point"}
}