{
  "type": "Feature",
  "properties": {
    "iso:country":"US",
    "sg:address":"612 W Plumb Ln",
    "sg:city":"Reno",
    "sg:classifiers":[
        {
            "category":"Shopping",
            "type":"Retail Goods"
        }
    ],
    "sg:phone":"+1 775 827 9992",
    "sg:postcode":"89509",
    "sg:province":"NV",
    "sg:tags":[
        "cosmetic",
        "perfume"
    ],
    "wof:name":"Hawaiian Bronze Inc",
    "wof:placetype":"venue"
},
  "geometry": {"coordinates":[-119.818251,39.505463],"type":"Point"}
}