{
  "type": "Feature",
  "properties": {
    "iso:country":"US",
    "sg:address":"102 W Center St",
    "sg:city":"Fallon",
    "sg:classifiers":[
        {
            "category":"Retail",
            "subcategory":"Auto Repair",
            "type":"Services"
        }
    ],
    "sg:phone":"+1 775 867 5050",
    "sg:postcode":"89406",
    "sg:province":"NV",
    "sg:tags":[
        "shop",
        "glass",
        "radiator"
    ],
    "wof:name":"Fallon Radiator & Glass",
    "wof:placetype":"venue"
},
  "geometry": {"coordinates":[-118.779135,39.473123],"type":"Point"}
}