{
  "type": "Feature",
  "properties": {
    "iso:country":"US",
    "sg:address":"480 Marks St",
    "sg:city":"Henderson",
    "sg:classifiers":[
        {
            "category":"Autos & Motor Vehicles",
            "subcategory":"Auto Supplies",
            "type":"Retail Goods"
        }
    ],
    "sg:phone":"+1 702 451 2610",
    "sg:postcode":"89014",
    "sg:province":"NV",
    "sg:tags":[
        "tire"
    ],
    "sg:website":"www.discounttire.com/makeappt",
    "wof:name":"Discount Tire",
    "wof:placetype":"venue"
},
  "geometry": {"coordinates":[-115.03656599999999,36.059142],"type":"Point"}
}