{
  "type": "Feature",
  "properties": {
    "iso:country":"US",
    "sg:address":"151 Comstock Cir W",
    "sg:city":"Pahrump",
    "sg:classifiers":[
        {
            "category":"Organizations",
            "subcategory":"Community Association",
            "type":"Services"
        }
    ],
    "sg:phone":"+1 775 727 6200",
    "sg:postcode":"89048",
    "sg:province":"NV",
    "sg:tags":[
        "club"
    ],
    "wof:name":"Comstock Homeowners Assoc",
    "wof:placetype":"venue"
},
  "geometry": {"coordinates":[-116.019797,36.204118],"type":"Point"}
}