{
  "type": "Feature",
  "properties": {
    "iso:country":"US",
    "sg:address":"4286 S Durango Dr",
    "sg:city":"Las Vegas",
    "sg:classifiers":[
        {
            "category":"Professional",
            "subcategory":"Engineering",
            "type":"Services"
        }
    ],
    "sg:phone":"+1 702 367 2800",
    "sg:postcode":"89147",
    "sg:province":"NV",
    "sg:tags":[
        "engineer"
    ],
    "wof:name":"Kubota & Associates Engineers",
    "wof:placetype":"venue"
},
  "geometry": {"coordinates":[-115.278977,36.112814],"type":"Point"}
}