{
  "type": "Feature",
  "properties": {
    "iso:country":"US",
    "sg:address":"3140 S Valley View Blvd",
    "sg:city":"Las Vegas",
    "sg:classifiers":[
        {
            "category":"Professional",
            "subcategory":"Accounting & Tax Preparation",
            "type":"Services"
        },
        {
            "category":"Banks & Credit Unions",
            "subcategory":"Bank",
            "type":"Services"
        }
    ],
    "sg:phone":"+1 702 251 8996",
    "sg:postcode":"89102",
    "sg:province":"NV",
    "sg:tags":[
        "return",
        "loan",
        "licensed",
        "small",
        "company",
        "filing"
    ],
    "sg:website":"www.securityfinancial.com",
    "wof:name":"Sunbelt Credit",
    "wof:placetype":"venue"
},
  "geometry": {"coordinates":[-115.190299,36.13362],"type":"Point"}
}