{
  "type": "Feature",
  "properties": {
    "iso:country":"US",
    "sg:address":"1018 S Main St",
    "sg:city":"Las Vegas",
    "sg:classifiers":[
        {
            "category":"Shopping",
            "subcategory":"Antiques",
            "type":"Retail Goods"
        },
        {
            "category":"Shopping",
            "subcategory":"Used Merchandise",
            "type":"Retail Goods"
        }
    ],
    "sg:phone":"+1 702 388 4088",
    "sg:postcode":"89101",
    "sg:province":"NV",
    "sg:tags":[
        "vintage",
        "consignment"
    ],
    "sg:website":"www.atticvintage.com",
    "wof:name":"The Attic",
    "wof:placetype":"venue"
},
  "geometry": {"coordinates":[-115.153,36.160599],"type":"Point"}
}