{
  "type": "Feature",
  "properties": {
    "iso:country":"US",
    "sg:address":"5109 Gilmore Ave",
    "sg:city":"Las Vegas",
    "sg:classifiers":[
        {
            "category":"Recreation",
            "type":"Entertainment"
        }
    ],
    "sg:phone":"+1 702 682 5778",
    "sg:postcode":"89130",
    "sg:province":"NV",
    "sg:tags":[
        "balloon"
    ],
    "wof:name":"Memory Makers Balloon Rides",
    "wof:placetype":"venue"
},
  "geometry": {"coordinates":[-115.216511,36.22807],"type":"Point"}
}