{
  "type": "Feature",
  "properties": {
    "iso:country":"US",
    "sg:address":"3625 S Rainbow Boulevard",
    "sg:city":"Las Vegas",
    "sg:classifiers":[
        {
            "category":"Shopping",
            "subcategory":"Department Store",
            "type":"Retail Goods"
        }
    ],
    "sg:phone":"+1 702 248 4248",
    "sg:postcode":"89103",
    "sg:province":"NV",
    "wof:name":"Dollar Plus USA",
    "wof:placetype":"venue"
},
  "geometry": {"coordinates":[-115.24303,36.121865],"type":"Point"}
}