{
  "type": "Feature",
  "properties": {
    "iso:country":"US",
    "sg:address":"995 S McCarran Blvd",
    "sg:city":"Sparks",
    "sg:classifiers":[
        {
            "category":"Manufacturing",
            "subcategory":"Chemicals & Compounds",
            "type":"Manufacturing & Wholesale Goods"
        }
    ],
    "sg:phone":"+1 775 355 7770",
    "sg:postcode":"89431",
    "sg:province":"NV",
    "sg:tags":[
        "inorganic",
        "industrial",
        "mfg"
    ],
    "wof:name":"Calgon Carbon Corporation Del",
    "wof:placetype":"venue"
},
  "geometry": {"coordinates":[-119.740202,39.521646],"type":"Point"}
}