{
  "type": "Feature",
  "properties": {
    "iso:country":"US",
    "sg:address":"3550 Barron Way",
    "sg:city":"Reno",
    "sg:classifiers":[
        {
            "category":"Real Estate",
            "subcategory":"Real Estate Agent",
            "type":"Services"
        }
    ],
    "sg:phone":"+1 775 829 7368",
    "sg:postcode":"89511",
    "sg:province":"NV",
    "sg:tags":[
        "finding",
        "apartment",
        "rental"
    ],
    "sg:website":"www.forrent.com",
    "wof:name":"Apartments For Rent Magazine",
    "wof:placetype":"venue"
},
  "geometry": {"coordinates":[-119.76863299999999,39.472359],"type":"Point"}
}