{
  "type": "Feature",
  "properties": {
    "iso:country":"US",
    "sg:address":"1101 Aultman St",
    "sg:city":"Ely",
    "sg:classifiers":[
        {
            "category":"Travel",
            "subcategory":"Hotels & Motels",
            "type":"Entertainment"
        }
    ],
    "sg:phone":"+1 775 289 4529",
    "sg:postcode":"89301",
    "sg:province":"NV",
    "wof:name":"Best Western-Main",
    "wof:placetype":"venue"
},
  "geometry": {"coordinates":[-114.885613,39.2491],"type":"Point"}
}