{
  "type": "Feature",
  "properties": {
    "iso:country":"US",
    "sg:address":"4815 W Russell Rd",
    "sg:city":"Las Vegas",
    "sg:classifiers":[
        {
            "category":"Recreation",
            "type":"Entertainment"
        }
    ],
    "sg:phone":"+1 702 365 1131",
    "sg:postcode":"89118",
    "sg:province":"NV",
    "wof:name":"Bushido Inc",
    "wof:placetype":"venue"
},
  "geometry": {"coordinates":[-115.207899,36.086348],"type":"Point"}
}