{
  "type": "Feature",
  "properties": {
    "iso:country":"US",
    "sg:address":"431 Canyon Way",
    "sg:city":"Sparks",
    "sg:classifiers":[
        {
            "category":"Government",
            "subcategory":"Fire Station",
            "type":"Public Place"
        }
    ],
    "sg:phone":"+1 775 342 0220",
    "sg:postcode":"89434",
    "sg:province":"NV",
    "sg:tags":[
        "protection"
    ],
    "wof:name":"Storey County Fire Department",
    "wof:placetype":"venue"
},
  "geometry": {"coordinates":[-119.644891,39.506682],"type":"Point"}
}