{
  "type": "Feature",
  "properties": {
    "iso:country":"US",
    "sg:address":"2861 S Highland Dr",
    "sg:city":"Las Vegas",
    "sg:classifiers":[
        {
            "category":"Shopping",
            "subcategory":"Gifts & Souvenirs",
            "type":"Retail Goods"
        },
        {
            "category":"Shopping",
            "subcategory":"Discount & Variety Stores",
            "type":"Retail Goods"
        }
    ],
    "sg:phone":"+1 702 222 0453",
    "sg:postcode":"89109",
    "sg:province":"NV",
    "sg:tags":[
        "wholesale",
        "flower"
    ],
    "sg:website":"www.fss.com",
    "wof:name":"Floral Supply Syndicate",
    "wof:placetype":"venue"
},
  "geometry": {"coordinates":[-115.172193,36.139409],"type":"Point"}
}