{
  "type": "Feature",
  "properties": {
    "iso:country":"US",
    "sg:address":"3140 S Durango Dr Ste 103",
    "sg:city":"Las Vegas",
    "sg:classifiers":[
        {
            "category":"Landmark",
            "subcategory":"Tourist Information",
            "type":"Public Place"
        }
    ],
    "sg:phone":"+1 702 798 6522",
    "sg:postcode":"89117",
    "sg:province":"NV",
    "sg:tags":[
        "tour"
    ],
    "wof:name":"See America",
    "wof:placetype":"venue"
},
  "geometry": {"coordinates":[-115.27877,36.133763],"type":"Point"}
}