{
  "type": "Feature",
  "properties": {
    "iso:country":"US",
    "sg:address":"5460 Meadowood Mall Cir",
    "sg:city":"Reno",
    "sg:classifiers":[
        {
            "category":"Shopping",
            "type":"Retail Goods"
        }
    ],
    "sg:phone":"+1 775 825 4888",
    "sg:postcode":"89502",
    "sg:province":"NV",
    "sg:tags":[
        "candle"
    ],
    "wof:name":"Mitchell's Candles",
    "wof:placetype":"venue"
},
  "geometry": {"coordinates":[-119.78458500000001,39.471439],"type":"Point"}
}