{
  "type": "Feature",
  "properties": {
    "iso:country":"US",
    "sg:address":"5075 W Diablo Dr",
    "sg:city":"Las Vegas",
    "sg:classifiers":[
        {
            "category":"Home & Garden",
            "subcategory":"Building Materials",
            "type":"Retail Goods"
        }
    ],
    "sg:phone":"+1 702 889 5844",
    "sg:postcode":"89118",
    "sg:province":"NV",
    "sg:tags":[
        "door",
        "gate",
        "operating",
        "devices"
    ],
    "sg:website":"www.garagedoorcenter.com",
    "wof:name":"Garage Door Ctr",
    "wof:placetype":"venue"
},
  "geometry": {"coordinates":[-115.209789,36.089789],"type":"Point"}
}