{
  "type": "Feature",
  "properties": {
    "iso:country":"US",
    "sg:address":"322 Fremont St",
    "sg:city":"Las Vegas",
    "sg:classifiers":[
        {
            "category":"Recreation",
            "type":"Entertainment"
        }
    ],
    "sg:phone":"+1 702 355 3145",
    "sg:postcode":"89101",
    "sg:province":"NV",
    "sg:tags":[
        "psychic",
        "medium"
    ],
    "wof:name":"Psychic Experience",
    "wof:placetype":"venue"
},
  "geometry": {"coordinates":[-115.141315,36.169498],"type":"Point"}
}