{
  "type": "Feature",
  "properties": {
    "iso:country":"US",
    "sg:address":"2910 S Highland Dr",
    "sg:city":"Las Vegas",
    "sg:classifiers":[
        {
            "category":"Retail",
            "subcategory":"Car Wash",
            "type":"Services"
        },
        {
            "category":"Retail",
            "subcategory":"Auto Repair",
            "type":"Services"
        }
    ],
    "sg:phone":"+1 702 614 9040",
    "sg:postcode":"89109",
    "sg:province":"NV",
    "sg:tags":[
        "body",
        "automobile",
        "rep",
        "customizing",
        "contractor",
        "hanging",
        "carwash"
    ],
    "wof:name":"Ten Ten Custom Paint Inc",
    "wof:placetype":"venue"
},
  "geometry": {"coordinates":[-115.172845,36.137509],"type":"Point"}
}