{
  "type": "Feature",
  "properties": {
    "iso:country":"US",
    "sg:address":"8954 Spanish Ridge Ave",
    "sg:city":"Las Vegas",
    "sg:classifiers":[
        {
            "category":"Health Services",
            "subcategory":"Doctor",
            "type":"Services"
        }
    ],
    "sg:phone":"+1 702 243 9555",
    "sg:postcode":"89148",
    "sg:province":"NV",
    "wof:name":"Stile Frank MD",
    "wof:placetype":"venue"
},
  "geometry": {"coordinates":[-115.287753,36.090981],"type":"Point"}
}