{
  "type": "Feature",
  "properties": {
    "iso:country":"US",
    "sg:address":"4277 E el Antonio Pl",
    "sg:city":"Las Vegas",
    "sg:classifiers":[
        {
            "category":"Building & Trades",
            "subcategory":"Landscaping Services",
            "type":"Services"
        }
    ],
    "sg:phone":"+1 702 647 3107",
    "sg:postcode":"89121",
    "sg:province":"NV",
    "sg:tags":[
        "designer",
        "landscape"
    ],
    "wof:name":"Mj Maintenance",
    "wof:placetype":"venue"
},
  "geometry": {"coordinates":[-115.07910800000001,36.104461],"type":"Point"}
}