{
  "type": "Feature",
  "properties": {
    "iso:country":"US",
    "sg:address":"4545 Spring Mountain Rd",
    "sg:city":"Las Vegas",
    "sg:classifiers":[
        {
            "category":"Home & Garden",
            "subcategory":"Carpets & Floor Coverings",
            "type":"Retail Goods"
        }
    ],
    "sg:phone":"+1 702 227 5688",
    "sg:postcode":"89102",
    "sg:province":"NV",
    "sg:tags":[
        "material"
    ],
    "wof:name":"A J Design Ctr",
    "wof:placetype":"venue"
},
  "geometry": {"coordinates":[-115.20449000000001,36.126215],"type":"Point"}
}