{
  "type": "Feature",
  "properties": {
    "iso:country":"US",
    "sg:address":"489 Tularosa Ct",
    "sg:city":"Reno",
    "sg:classifiers":[
        {
            "category":"Building & Trades",
            "subcategory":"Cleaning & Sanitation",
            "type":"Services"
        }
    ],
    "sg:phone":"+1 775 851 3355",
    "sg:postcode":"89511",
    "sg:province":"NV",
    "sg:tags":[
        "janitor"
    ],
    "wof:name":"Excel Building Svc Inc",
    "wof:placetype":"venue"
},
  "geometry": {"coordinates":[-119.816264,39.421732],"type":"Point"}
}