{
  "type": "Feature",
  "properties": {
    "iso:country":"US",
    "sg:address":"4092 Kings Canyon Rd",
    "sg:city":"Carson City",
    "sg:classifiers":[
        {
            "category":"Health Services",
            "subcategory":"Doctor",
            "type":"Services"
        }
    ],
    "sg:phone":"+1 775 883 7582",
    "sg:postcode":"89703",
    "sg:province":"NV",
    "wof:name":"Sonderegger C Brian MD",
    "wof:placetype":"venue"
},
  "geometry": {"coordinates":[-119.811089,39.155968],"type":"Point"}
}