{
  "type": "Feature",
  "properties": {
    "iso:country":"US",
    "sg:address":"1211 S Maryland Parkway",
    "sg:city":"Las Vegas",
    "sg:classifiers":[
        {
            "category":"Professional",
            "subcategory":"Lawyer & Legal Services",
            "type":"Services"
        }
    ],
    "sg:phone":"+1 702 214 4214",
    "sg:postcode":"89104",
    "sg:province":"NV",
    "sg:tags":[
        "divorce",
        "law",
        "family"
    ],
    "wof:name":"Tilman Christopher R ESQ",
    "wof:placetype":"venue"
},
  "geometry": {"coordinates":[-115.13633900000001,36.155827],"type":"Point"}
}