{
  "type": "Feature",
  "properties": {
    "iso:country":"US",
    "sg:address":"7026 Sawtooth Dr",
    "sg:city":"Las Vegas",
    "sg:classifiers":[
        {
            "category":"Building & Trades",
            "subcategory":"Construction",
            "type":"Services"
        }
    ],
    "sg:phone":"+1 702 210 0571",
    "sg:postcode":"89119",
    "sg:province":"NV",
    "sg:tags":[
        "maintenance",
        "contractor"
    ],
    "wof:name":"B & B Maintenance Co",
    "wof:placetype":"venue"
},
  "geometry": {"coordinates":[-115.134048,36.05991],"type":"Point"}
}