{
  "type": "Feature",
  "properties": {
    "iso:country":"US",
    "sg:address":"3620 S Maryland Pkwy",
    "sg:city":"Las Vegas",
    "sg:classifiers":[
        {
            "category":"Shopping",
            "subcategory":"Gifts & Souvenirs",
            "type":"Retail Goods"
        }
    ],
    "sg:phone":"+1 702 735 7745",
    "sg:postcode":"89169",
    "sg:province":"NV",
    "sg:tags":[
        "shop",
        "novelty"
    ],
    "sg:website":"www.thingsremembered.com",
    "wof:name":"Things Remembered",
    "wof:placetype":"venue"
},
  "geometry": {"coordinates":[-115.137182,36.125302],"type":"Point"}
}