{
  "type": "Feature",
  "properties": {
    "iso:country":"US",
    "sg:address":"529 W 2nd St",
    "sg:city":"Reno",
    "sg:classifiers":[
        {
            "category":"Real Estate",
            "subcategory":"Real Estate Agent",
            "type":"Services"
        }
    ],
    "sg:phone":"+1 775 323 6162",
    "sg:postcode":"89503",
    "sg:province":"NV",
    "wof:name":"Krause Vonn",
    "wof:placetype":"venue"
},
  "geometry": {"coordinates":[-119.820844,39.525573],"type":"Point"}
}