{
  "type": "Feature",
  "properties": {
    "iso:country":"US",
    "sg:address":"200 N Carson St",
    "sg:city":"Carson City",
    "sg:classifiers":[
        {
            "category":"Government",
            "subcategory":"Court House",
            "type":"Public Place"
        }
    ],
    "sg:phone":"+1 775 684 5708",
    "sg:postcode":"89701",
    "sg:province":"NV",
    "sg:tags":[
        "division",
        "state",
        "sec"
    ],
    "wof:name":"Secretary of State NV Office",
    "wof:placetype":"venue"
},
  "geometry": {"coordinates":[-119.766983,39.164577],"type":"Point"}
}