{
  "type": "Feature",
  "properties": {
    "iso:country":"US",
    "sg:address":"6333 W Washington Ave",
    "sg:city":"Las Vegas",
    "sg:classifiers":[
        {
            "category":"Real Estate",
            "subcategory":"Real Estate Agent",
            "type":"Services"
        }
    ],
    "sg:phone":"+1 702 734 3888",
    "sg:postcode":"89107",
    "sg:province":"NV",
    "wof:name":"Norman Kaye Real Estate",
    "wof:placetype":"venue"
},
  "geometry": {"coordinates":[-115.232022,36.180893],"type":"Point"}
}