{
  "type": "Feature",
  "properties": {
    "iso:country":"US",
    "sg:address":"985 White Dr",
    "sg:city":"Las Vegas",
    "sg:classifiers":[
        {
            "category":"Professional",
            "subcategory":"Lawyer & Legal Services",
            "type":"Services"
        }
    ],
    "sg:phone":"+1 702 796 9465",
    "sg:postcode":"89119",
    "sg:province":"NV",
    "sg:tags":[
        "attorney"
    ],
    "sg:website":"www.spadepotspas.com",
    "wof:name":"Darren J Welsh Chtd",
    "wof:placetype":"venue"
},
  "geometry": {"coordinates":[-115.142031,36.060802],"type":"Point"}
}