{
  "type": "Feature",
  "properties": {
    "iso:country":"US",
    "sg:address":"1916 Village Center Cir Ste 1",
    "sg:city":"Las Vegas",
    "sg:classifiers":[
        {
            "category":"Banks & Credit Unions",
            "subcategory":"Bank",
            "type":"Services"
        }
    ],
    "sg:phone":"+1 702 256 8253",
    "sg:postcode":"89134",
    "sg:province":"NV",
    "sg:website":"www.usbank.com",
    "wof:name":"US Bank",
    "wof:placetype":"venue"
},
  "geometry": {"coordinates":[-115.303782,36.193084],"type":"Point"}
}