{
  "type": "Feature",
  "properties": {
    "iso:country":"US",
    "sg:address":"2211 N Rampart Blvd",
    "sg:city":"Las Vegas",
    "sg:classifiers":[
        {
            "category":"Professional",
            "subcategory":"Computer Services",
            "type":"Services"
        }
    ],
    "sg:phone":"+1 702 869 0160",
    "sg:postcode":"89128",
    "sg:province":"NV",
    "sg:tags":[
        "consultant",
        "designer",
        "datum",
        "system"
    ],
    "wof:name":"Siniard Group",
    "wof:placetype":"venue"
},
  "geometry": {"coordinates":[-115.28223199999999,36.200071],"type":"Point"}
}