{
  "type": "Feature",
  "properties": {
    "iso:country":"US",
    "sg:address":"3175 Silver State Ave",
    "sg:city":"Fallon",
    "sg:classifiers":[
        {
            "category":"Shopping",
            "subcategory":"Bicycles & Sporting Goods",
            "type":"Retail Goods"
        }
    ],
    "sg:phone":"+1 775 423 4794",
    "sg:postcode":"89406",
    "sg:province":"NV",
    "wof:name":"Hargroves Saddlery",
    "wof:placetype":"venue"
},
  "geometry": {"coordinates":[-118.822844,39.48763],"type":"Point"}
}