{
  "type": "Feature",
  "properties": {
    "iso:country":"US",
    "sg:address":"3300 W Sirius Ave",
    "sg:city":"Las Vegas",
    "sg:classifiers":[
        {
            "category":"Wholesale",
            "subcategory":"Electrical",
            "type":"Manufacturing & Wholesale Goods"
        },
        {
            "category":"Building & Trades",
            "subcategory":"Plumbing",
            "type":"Services"
        }
    ],
    "sg:phone":"+1 702 257 2772",
    "sg:postcode":"89102",
    "sg:province":"NV",
    "sg:tags":[
        "control",
        "installation",
        "temperature",
        "contractor"
    ],
    "wof:name":"Hudson Controls Inc",
    "wof:placetype":"venue"
},
  "geometry": {"coordinates":[-115.18163800000001,36.133576],"type":"Point"}
}