{
  "type": "Feature",
  "properties": {
    "iso:country":"US",
    "sg:address":"1914 Hymer Ave",
    "sg:city":"Sparks",
    "sg:classifiers":[
        {
            "category":"Building & Trades",
            "subcategory":"Construction",
            "type":"Services"
        }
    ],
    "sg:phone":"+1 775 359 1468",
    "sg:postcode":"89431",
    "sg:province":"NV",
    "sg:tags":[
        "asbestos",
        "removal"
    ],
    "sg:website":"www.advanceinstallations.com",
    "wof:name":"Advance Installations Inc",
    "wof:placetype":"venue"
},
  "geometry": {"coordinates":[-119.771092,39.53132],"type":"Point"}
}