{
  "type": "Feature",
  "properties": {
    "iso:country":"US",
    "sg:address":"436 Chateau Dr",
    "sg:city":"Henderson",
    "sg:classifiers":[
        {
            "category":"Professional",
            "subcategory":"Accounting & Tax Preparation",
            "type":"Services"
        }
    ],
    "sg:phone":"+1 702 565 9916",
    "sg:postcode":"89002",
    "sg:province":"NV",
    "sg:tags":[
        "bookkeeping",
        "general"
    ],
    "wof:name":"Ester's Desktop",
    "wof:placetype":"venue"
},
  "geometry": {"coordinates":[-114.971408,36.010093],"type":"Point"}
}