{
  "type": "Feature",
  "properties": {
    "iso:country":"US",
    "sg:address":"4530 E Charleston Blvd",
    "sg:city":"Las Vegas",
    "sg:classifiers":[
        {
            "category":"Shopping",
            "subcategory":"Pharmacy",
            "type":"Retail Goods"
        }
    ],
    "sg:phone":"+1 702 452 3431",
    "sg:postcode":"89104",
    "sg:province":"NV",
    "wof:name":"Rite Aid Pharmacy",
    "wof:placetype":"venue"
},
  "geometry": {"coordinates":[-115.07773,36.159039],"type":"Point"}
}