{
  "type": "Feature",
  "properties": {
    "iso:country":"US",
    "sg:address":"234 Aerie Ln",
    "sg:city":"Elko",
    "sg:classifiers":[
        {
            "category":"Building & Trades",
            "subcategory":"Construction",
            "type":"Services"
        }
    ],
    "sg:phone":"+1 775 738 5105",
    "sg:postcode":"89801",
    "sg:province":"NV",
    "sg:tags":[
        "contractor"
    ],
    "wof:name":"TGMD Construction Inc",
    "wof:placetype":"venue"
},
  "geometry": {"coordinates":[-115.783086,40.841118],"type":"Point"}
}