{
  "type": "Feature",
  "properties": {
    "iso:country":"US",
    "sg:address":"4162 Jacqueline Way",
    "sg:city":"Las Vegas",
    "sg:classifiers":[
        {
            "category":"Building & Trades",
            "subcategory":"Electrical",
            "type":"Services"
        }
    ],
    "sg:phone":"+1 702 643 0119",
    "sg:postcode":"89115",
    "sg:province":"NV",
    "sg:tags":[
        "electric",
        "contractor"
    ],
    "wof:name":"Litchy Electric",
    "wof:placetype":"venue"
},
  "geometry": {"coordinates":[-115.085286,36.236139],"type":"Point"}
}