{
  "type": "Feature",
  "properties": {
    "iso:country":"US",
    "sg:address":"3120 Las Vegas Blvd S",
    "sg:city":"Las Vegas",
    "sg:classifiers":[
        {
            "category":"Restaurant",
            "type":"Food & Drink"
        }
    ],
    "sg:phone":"+1 702 651 3366",
    "sg:postcode":"89109",
    "sg:province":"NV",
    "wof:name":"Little Caesars Pizza",
    "wof:placetype":"venue"
},
  "geometry": {"coordinates":[-115.167601,36.128266],"type":"Point"}
}