{
  "type": "Feature",
  "properties": {
    "iso:country":"US",
    "sg:address":"2450 Pebble Rd",
    "sg:city":"Henderson",
    "sg:classifiers":[
        {
            "category":"Restaurant",
            "type":"Food & Drink"
        }
    ],
    "sg:menulink":"http://www.allmenus.com/nv/las-vegas/96756-ihop/menu/",
    "sg:phone":"+1 702 933 0420",
    "sg:postcode":"89074",
    "sg:province":"NV",
    "sg:tags":[
        "sandwich",
        "salad",
        "burger",
        "soup",
        "american",
        "steakhouse",
        "wrap"
    ],
    "wof:name":"IHOP",
    "wof:placetype":"venue"
},
  "geometry": {"coordinates":[-115.117295,36.028047],"type":"Point"}
}