{
  "type": "Feature",
  "properties": {
    "iso:country":"US",
    "sg:address":"3914 Seaton Pl",
    "sg:city":"Las Vegas",
    "sg:classifiers":[
        {
            "category":"Shopping",
            "subcategory":"Clothing, Apparel, & Fashions",
            "type":"Retail Goods"
        }
    ],
    "sg:postcode":"89121",
    "sg:province":"NV",
    "wof:name":"Marrick Ent",
    "wof:placetype":"venue"
},
  "geometry": {"coordinates":[-115.086715,36.11832],"type":"Point"}
}