{
  "type": "Feature",
  "properties": {
    "iso:country":"US",
    "sg:address":"8540 W Wigwam Ave",
    "sg:city":"Las Vegas",
    "sg:classifiers":[
        {
            "category":"Building & Trades",
            "subcategory":"Plumbing",
            "type":"Services"
        }
    ],
    "sg:phone":"+1 702 897 1134",
    "sg:postcode":"89113",
    "sg:province":"NV",
    "sg:tags":[
        "contractor"
    ],
    "wof:name":"M & S Pool Spa Plumbing Inc",
    "wof:placetype":"venue"
},
  "geometry": {"coordinates":[-115.277998,36.033592],"type":"Point"}
}