{
  "type": "Feature",
  "properties": {
    "iso:country":"US",
    "sg:address":"1150 Industrial Way",
    "sg:city":"Sparks",
    "sg:classifiers":[
        {
            "category":"Organizations",
            "subcategory":"Labor Organization",
            "type":"Services"
        }
    ],
    "sg:phone":"+1 775 356 9810",
    "sg:postcode":"89431",
    "sg:province":"NV",
    "sg:website":"www.plumbersunion.com",
    "wof:name":"Local 350 Apprentice Trust",
    "wof:placetype":"venue"
},
  "geometry": {"coordinates":[-119.758382,39.525132],"type":"Point"}
}