{
  "type": "Feature",
  "properties": {
    "iso:country":"US",
    "sg:address":"9530 S Eastern Ave",
    "sg:city":"Las Vegas",
    "sg:classifiers":[
        {
            "category":"Cinema",
            "subcategory":"Movie Rental",
            "type":"Entertainment"
        }
    ],
    "sg:phone":"+1 702 341 7529",
    "sg:postcode":"89123",
    "sg:province":"NV",
    "sg:tags":[
        "game",
        "video"
    ],
    "wof:name":"Playntrade",
    "wof:placetype":"venue"
},
  "geometry": {"coordinates":[-115.118883,36.015839],"type":"Point"}
}