{
  "type": "Feature",
  "properties": {
    "iso:country":"US",
    "sg:address":"58 Commercial Way",
    "sg:city":"Fallon",
    "sg:classifiers":[
        {
            "category":"Personal",
            "subcategory":"Beauty Salon",
            "type":"Services"
        }
    ],
    "sg:phone":"+1 775 423 3177",
    "sg:postcode":"89406",
    "sg:province":"NV",
    "wof:name":"Electric Chairs",
    "wof:placetype":"venue"
},
  "geometry": {"coordinates":[-118.793337,39.475714],"type":"Point"}
}