{
  "type": "Feature",
  "properties": {
    "iso:country":"US",
    "sg:address":"330 S 3rd Street",
    "sg:city":"Las Vegas",
    "sg:classifiers":[
        {
            "category":"Banks & Credit Unions",
            "subcategory":"Atm",
            "type":"Services"
        }
    ],
    "sg:phone":"+1 702 388 7185",
    "sg:postcode":"89101",
    "sg:province":"NV",
    "sg:tags":[
        "bankruptcy"
    ],
    "wof:name":"Law Offices of Richard McKnight PC",
    "wof:placetype":"venue"
},
  "geometry": {"coordinates":[-115.144704,36.167538],"type":"Point"}
}