{
  "type": "Feature",
  "properties": {
    "iso:country":"US",
    "sg:address":"629 Wedge Ln",
    "sg:city":"Fernley",
    "sg:classifiers":[
        {
            "category":"Professional",
            "subcategory":"Management & Consulting",
            "type":"Services"
        }
    ],
    "sg:phone":"+1 775 851 7761",
    "sg:postcode":"89408",
    "sg:province":"NV",
    "sg:tags":[
        "business"
    ],
    "wof:name":"Joe Muncy Enterprises",
    "wof:placetype":"venue"
},
  "geometry": {"coordinates":[-119.140349,39.590185],"type":"Point"}
}