{
  "type": "Feature",
  "properties": {
    "iso:country":"US",
    "sg:address":"534 S Boulder Hwy",
    "sg:city":"Henderson",
    "sg:classifiers":[
        {
            "category":"Retail",
            "subcategory":"Auto Rental",
            "type":"Services"
        }
    ],
    "sg:phone":"+1 702 567 8340",
    "sg:postcode":"89015",
    "sg:province":"NV",
    "sg:tags":[
        "car"
    ],
    "sg:website":"www.enterprise.com",
    "wof:name":"Enterprise Rent-A-Car",
    "wof:placetype":"venue"
},
  "geometry": {"coordinates":[-114.973021,36.03195],"type":"Point"}
}