{
  "type": "Feature",
  "properties": {
    "iso:country":"US",
    "sg:address":"420 Wellington Way",
    "sg:city":"Reno",
    "sg:classifiers":[
        {
            "category":"Manufacturing",
            "subcategory":"Glass & Minerals",
            "type":"Manufacturing & Wholesale Goods"
        }
    ],
    "sg:phone":"+1 775 378 1151",
    "sg:postcode":"89506",
    "sg:province":"NV",
    "sg:tags":[
        "cut",
        "mfg"
    ],
    "wof:name":"S & W Fabrication",
    "wof:placetype":"venue"
},
  "geometry": {"coordinates":[-119.840563,39.589286],"type":"Point"}
}