{
  "type": "Feature",
  "properties": {
    "iso:country":"US",
    "sg:address":"10829 Ickworth Ct",
    "sg:city":"Las Vegas",
    "sg:classifiers":[
        {
            "category":"Professional",
            "subcategory":"Management & Consulting",
            "type":"Services"
        }
    ],
    "sg:phone":"+1 702 459 3800",
    "sg:postcode":"89135",
    "sg:province":"NV",
    "sg:tags":[
        "construction"
    ],
    "wof:name":"KTB Construction",
    "wof:placetype":"venue"
},
  "geometry": {"coordinates":[-115.329317,36.133386],"type":"Point"}
}