{
  "type": "Feature",
  "properties": {
    "iso:country":"US",
    "sg:address":"1380 E 5th St",
    "sg:city":"Carson City",
    "sg:classifiers":[
        {
            "category":"Organizations",
            "subcategory":"Community Association",
            "type":"Services"
        }
    ],
    "sg:phone":"+1 775 883 1006",
    "sg:postcode":"89701",
    "sg:province":"NV",
    "sg:tags":[
        "fraternal"
    ],
    "wof:name":"Fraternal Order Of Eagles",
    "wof:placetype":"venue"
},
  "geometry": {"coordinates":[-119.755296,39.161386],"type":"Point"}
}