{
  "type": "Feature",
  "properties": {
    "iso:country":"US",
    "sg:address":"4855 S Pecos Rd",
    "sg:city":"Las Vegas",
    "sg:classifiers":[
        {
            "category":"Restaurant",
            "type":"Food & Drink"
        }
    ],
    "sg:phone":"+1 702 547 3777",
    "sg:postcode":"89121",
    "sg:province":"NV",
    "sg:tags":[
        "caterer"
    ],
    "wof:name":"Catering Referral Svc",
    "wof:placetype":"venue"
},
  "geometry": {"coordinates":[-115.101031,36.102033],"type":"Point"}
}