{
  "type": "Feature",
  "properties": {
    "iso:country":"US",
    "sg:address":"5501 Mayberry Dr",
    "sg:city":"Reno",
    "sg:classifiers":[
        {
            "category":"Wholesale",
            "subcategory":"Machinery & Supplies",
            "type":"Manufacturing & Wholesale Goods"
        }
    ],
    "sg:phone":"+1 775 747 7151",
    "sg:postcode":"89509",
    "sg:province":"NV",
    "sg:tags":[
        "packaging"
    ],
    "wof:name":"Mc Neil's Industrial Machine",
    "wof:placetype":"venue"
},
  "geometry": {"coordinates":[-119.876351,39.505984],"type":"Point"}
}