{
  "type": "Feature",
  "properties": {
    "iso:country":"US",
    "sg:address":"4736 Convair Dr",
    "sg:city":"Carson City",
    "sg:classifiers":[
        {
            "category":"Manufacturing",
            "subcategory":"Pottery",
            "type":"Manufacturing & Wholesale Goods"
        }
    ],
    "sg:phone":"+1 775 884 2777",
    "sg:postcode":"89706",
    "sg:province":"NV",
    "sg:tags":[
        "equipment",
        "ceramic",
        "supply"
    ],
    "sg:website":"www.cressmfg.com",
    "wof:name":"Cress Manufacturing Co",
    "wof:placetype":"venue"
},
  "geometry": {"coordinates":[-119.738241,39.201582],"type":"Point"}
}