{
  "type": "Feature",
  "properties": {
    "iso:country":"US",
    "sg:address":"3333 Bass Rd",
    "sg:city":"Fallon",
    "sg:classifiers":[
        {
            "category":"Farming",
            "subcategory":"Livestock Farm",
            "type":"Manufacturing & Wholesale Goods"
        }
    ],
    "sg:phone":"+1 775 423 4418",
    "sg:postcode":"89406",
    "sg:province":"NV",
    "sg:tags":[
        "beef",
        "feedlot",
        "cattle"
    ],
    "wof:name":"Delbert Bendickson",
    "wof:placetype":"venue"
},
  "geometry": {"coordinates":[-118.809122,39.433471],"type":"Point"}
}