{
  "type": "Feature",
  "properties": {
    "iso:country":"US",
    "sg:address":"1352 Sanden Ln",
    "sg:city":"Minden",
    "sg:classifiers":[
        {
            "category":"Professional",
            "subcategory":"Management & Consulting",
            "type":"Services"
        }
    ],
    "sg:phone":"+1 775 267 4531",
    "sg:postcode":"89423",
    "sg:province":"NV",
    "sg:tags":[
        "architectural"
    ],
    "wof:name":"Facilities Management Inc",
    "wof:placetype":"venue"
},
  "geometry": {"coordinates":[-119.73597,39.037665],"type":"Point"}
}