{
  "type": "Feature",
  "properties": {
    "iso:country":"US",
    "sg:address":"6280 S Valley View Blvd",
    "sg:city":"Las Vegas",
    "sg:classifiers":[
        {
            "category":"Building & Trades",
            "subcategory":"Construction",
            "type":"Services"
        }
    ],
    "sg:phone":"+1 702 895 7575",
    "sg:postcode":"89118",
    "sg:province":"NV",
    "sg:tags":[
        "contractor"
    ],
    "wof:name":"Pcl Construction Services",
    "wof:placetype":"venue"
},
  "geometry": {"coordinates":[-115.190002,36.0755],"type":"Point"}
}