{
  "type": "Feature",
  "properties": {
    "iso:country":"US",
    "sg:address":"673 N Stephanie St",
    "sg:city":"Henderson",
    "sg:classifiers":[
        {
            "category":"Shopping",
            "subcategory":"Hobbies, Toys, & Games",
            "type":"Retail Goods"
        }
    ],
    "sg:phone":"+1 702 456 5437",
    "sg:postcode":"89014",
    "sg:province":"NV",
    "sg:tags":[
        "toy",
        "store"
    ],
    "wof:name":"Learning Is Fun",
    "wof:placetype":"venue"
},
  "geometry": {"coordinates":[-115.045998,36.068001],"type":"Point"}
}