{
  "type": "Feature",
  "properties": {
    "iso:country":"US",
    "sg:address":"3097 Maple Ridge Ct",
    "sg:city":"Henderson",
    "sg:classifiers":[
        {
            "category":"Real Estate",
            "subcategory":"Real Estate Agent",
            "type":"Services"
        }
    ],
    "sg:phone":"+1 702 217 8817",
    "sg:postcode":"89052",
    "sg:province":"NV",
    "wof:name":"Vegas Life Inc",
    "wof:placetype":"venue"
},
  "geometry": {"coordinates":[-115.122753,35.987767],"type":"Point"}
}