{
  "type": "Feature",
  "properties": {
    "iso:country":"US",
    "sg:address":"10316 Back Plains Dr",
    "sg:city":"Las Vegas",
    "sg:classifiers":[
        {
            "category":"Retail",
            "subcategory":"Photofinishing",
            "type":"Services"
        }
    ],
    "sg:phone":"+1 702 838 3127",
    "sg:postcode":"89134",
    "sg:province":"NV",
    "sg:tags":[
        "laboratory"
    ],
    "wof:name":"Tour Photo Sculptures",
    "wof:placetype":"venue"
},
  "geometry": {"coordinates":[-115.321468,36.216248],"type":"Point"}
}