{
  "type": "Feature",
  "properties": {
    "iso:country":"US",
    "sg:address":"210 S Sierra St",
    "sg:city":"Reno",
    "sg:classifiers":[
        {
            "category":"Professional",
            "subcategory":"Accounting & Tax Preparation",
            "type":"Services"
        }
    ],
    "sg:phone":"+1 775 324 4041",
    "sg:postcode":"89501",
    "sg:province":"NV",
    "wof:name":"Diana Hurley",
    "wof:placetype":"venue"
},
  "geometry": {"coordinates":[-119.812946,39.523112],"type":"Point"}
}