{
  "type": "Feature",
  "properties": {
    "iso:country":"US",
    "sg:address":"46 Hardy Dr",
    "sg:city":"Sparks",
    "sg:classifiers":[
        {
            "category":"Autos & Motor Vehicles",
            "subcategory":"Automobile Sales",
            "type":"Retail Goods"
        }
    ],
    "sg:phone":"+1 775 826 8363",
    "sg:postcode":"89431",
    "sg:province":"NV",
    "sg:tags":[
        "used",
        "supply"
    ],
    "wof:name":"Cadillac Parts & Cars Ltd",
    "wof:placetype":"venue"
},
  "geometry": {"coordinates":[-119.741744,39.524569],"type":"Point"}
}