{
  "type": "Feature",
  "properties": {
    "iso:country":"US",
    "sg:address":"1028 E 16th St",
    "sg:city":"Ely",
    "sg:classifiers":[
        {
            "category":"Shopping",
            "subcategory":"Gifts & Souvenirs",
            "type":"Retail Goods"
        }
    ],
    "sg:phone":"+1 775 289 2581",
    "sg:postcode":"89301",
    "sg:province":"NV",
    "sg:tags":[
        "shop"
    ],
    "wof:name":"Carol's Country Corner",
    "wof:placetype":"venue"
},
  "geometry": {"coordinates":[-114.85562,39.253178],"type":"Point"}
}