{
  "type": "Feature",
  "properties": {
    "iso:country":"US",
    "sg:address":"Gold Coast Casino 4000 W Flamingo Rd",
    "sg:city":"Las Vegas",
    "sg:classifiers":[
        {
            "category":"Restaurant",
            "type":"Food & Drink"
        }
    ],
    "sg:phone":"+1 702 247 8136",
    "sg:postcode":"89103",
    "sg:province":"NV",
    "sg:tags":[
        "dim",
        "sum"
    ],
    "sg:website":"www.goldcoastcasino.com/restaura...",
    "wof:name":"Ping Pang Pong",
    "wof:placetype":"venue"
},
  "geometry": {"coordinates":[-115.192316,36.11565],"type":"Point"}
}