{
  "type": "Feature",
  "properties": {
    "iso:country":"US",
    "sg:address":"479 W Craig Rd",
    "sg:city":"North Las Vegas",
    "sg:classifiers":[
        {
            "category":"Sports & Exercise",
            "subcategory":"Gym",
            "type":"Entertainment"
        },
        {
            "category":"Arena",
            "subcategory":"Sports Club",
            "type":"Entertainment"
        }
    ],
    "sg:phone":"+1 702 685 5269",
    "sg:postcode":"89032",
    "sg:province":"NV",
    "sg:tags":[
        "martial art"
    ],
    "sg:website":"laboxing.com/northlasvegas/",
    "wof:name":"LA Boxing",
    "wof:placetype":"venue"
},
  "geometry": {"coordinates":[-115.147412,36.23937],"type":"Point"}
}