{
  "type": "Feature",
  "properties": {
    "iso:country":"US",
    "sg:address":"531 Canyon Rd",
    "sg:city":"Henderson",
    "sg:classifiers":[
        {
            "category":"Building & Trades",
            "subcategory":"Construction",
            "type":"Services"
        }
    ],
    "sg:phone":"+1 702 396 7286",
    "sg:postcode":"89015",
    "sg:province":"NV",
    "sg:tags":[
        "excavation",
        "contractor"
    ],
    "wof:name":"Andersen Hoeram & Excavation",
    "wof:placetype":"venue"
},
  "geometry": {"coordinates":[-114.983308,36.018947],"type":"Point"}
}