{
  "type": "Feature",
  "properties": {
    "iso:country":"US",
    "sg:address":"236 Fullerton Ave",
    "sg:city":"Henderson",
    "sg:classifiers":[
        {
            "category":"Building & Trades",
            "subcategory":"Cleaning & Sanitation",
            "type":"Services"
        }
    ],
    "sg:phone":"+1 702 498 9490",
    "sg:postcode":"89015",
    "sg:province":"NV",
    "sg:tags":[
        "maintenance"
    ],
    "wof:name":"Robert S Jasper",
    "wof:placetype":"venue"
},
  "geometry": {"coordinates":[-114.959414,36.0529],"type":"Point"}
}