{
  "type": "Feature",
  "properties": {
    "iso:country":"US",
    "sg:address":"7850 W Ann Road",
    "sg:city":"Las Vegas",
    "sg:classifiers":[
        {
            "category":"Shopping",
            "subcategory":"Pets & Pet Supplies",
            "type":"Retail Goods"
        }
    ],
    "sg:phone":"+1 702 385 7387",
    "sg:postcode":"89149",
    "sg:province":"NV",
    "sg:tags":[
        "groomers"
    ],
    "wof:name":"Royal Pet Salon",
    "wof:placetype":"venue"
},
  "geometry": {"coordinates":[-115.266414,36.262942],"type":"Point"}
}