{
  "type": "Feature",
  "properties": {
    "iso:country":"US",
    "sg:address":"6068 Attavilla Dr",
    "sg:city":"Las Vegas",
    "sg:classifiers":[
        {
            "category":"Shopping",
            "subcategory":"Gifts & Souvenirs",
            "type":"Retail Goods"
        }
    ],
    "sg:phone":"+1 702 361 0005",
    "sg:postcode":"89141",
    "sg:province":"NV",
    "sg:tags":[
        "basket",
        "parcel"
    ],
    "wof:name":"Whimsical Romance",
    "wof:placetype":"venue"
},
  "geometry": {"coordinates":[-115.224538,35.991063],"type":"Point"}
}