{
  "type": "Feature",
  "properties": {
    "iso:country":"US",
    "sg:address":"1801 Maison Way",
    "sg:city":"Carson City",
    "sg:classifiers":[
        {
            "category":"Professional",
            "subcategory":"Lawyer & Legal Services",
            "type":"Services"
        }
    ],
    "sg:phone":"+1 775 883 4126",
    "sg:postcode":"89703",
    "sg:province":"NV",
    "wof:name":"Nelson Bryan M Atty",
    "wof:placetype":"venue"
},
  "geometry": {"coordinates":[-119.78299699999999,39.1721],"type":"Point"}
}