{
  "type": "Feature",
  "properties": {
    "iso:country":"US",
    "sg:address":"8321 Corbett St",
    "sg:city":"Las Vegas",
    "sg:classifiers":[
        {
            "category":"Building & Trades",
            "subcategory":"Plumbing",
            "type":"Services"
        }
    ],
    "sg:phone":"+1 702 396 9600",
    "sg:postcode":"89149",
    "sg:province":"NV",
    "sg:website":"plumbingservicelasvegas.info/",
    "wof:name":"Water Heaters R Us",
    "wof:placetype":"venue"
},
  "geometry": {"coordinates":[-115.27695799999999,36.268092],"type":"Point"}
}