{
  "type": "Feature",
  "properties": {
    "iso:country":"US",
    "sg:address":"241 E Calvada Blvd",
    "sg:city":"Pahrump",
    "sg:classifiers":[
        {
            "category":"Building & Trades",
            "subcategory":"Construction",
            "type":"Services"
        }
    ],
    "sg:phone":"+1 775 727 4849",
    "sg:postcode":"89048",
    "sg:province":"NV",
    "sg:tags":[
        "contractor"
    ],
    "wof:name":"Mojave Homes & Pools",
    "wof:placetype":"venue"
},
  "geometry": {"coordinates":[-116.00995,36.188916],"type":"Point"}
}