{
  "type": "Feature",
  "properties": {
    "iso:country":"US",
    "sg:address":"949 W Moana Ln",
    "sg:city":"Reno",
    "sg:classifiers":[
        {
            "category":"Wholesale",
            "subcategory":"Machinery & Supplies",
            "type":"Manufacturing & Wholesale Goods"
        }
    ],
    "sg:phone":"+1 775 827 0466",
    "sg:postcode":"89509",
    "sg:province":"NV",
    "sg:tags":[
        "equipment",
        "establishment"
    ],
    "wof:name":"Malys of California",
    "wof:placetype":"venue"
},
  "geometry": {"coordinates":[-119.806984,39.491276],"type":"Point"}
}