{
  "type": "Feature",
  "properties": {
    "iso:country":"US",
    "sg:address":"13 Affonso Dr",
    "sg:city":"Carson City",
    "sg:classifiers":[
        {
            "category":"Autos & Motor Vehicles",
            "subcategory":"Recreational Vehicle Sales",
            "type":"Retail Goods"
        }
    ],
    "sg:phone":"+1 775 246 4141",
    "sg:postcode":"89706",
    "sg:province":"NV",
    "sg:tags":[
        "repair",
        "general"
    ],
    "wof:name":"DJS Rv Center Inc",
    "wof:placetype":"venue"
},
  "geometry": {"coordinates":[-119.652799,39.219454],"type":"Point"}
}