{
  "type": "Feature",
  "properties": {
    "iso:country":"US",
    "sg:address":"601 S 10th Street",
    "sg:city":"Las Vegas",
    "sg:classifiers":[
        {
            "category":"Professional",
            "subcategory":"Lawyer & Legal Services",
            "type":"Services"
        }
    ],
    "sg:phone":"+1 702 382 2222",
    "sg:postcode":"89101",
    "sg:province":"NV",
    "wof:name":"Posin & Posin Attorneys At Law",
    "wof:placetype":"venue"
},
  "geometry": {"coordinates":[-115.138897,36.160556],"type":"Point"}
}