{
  "type": "Feature",
  "properties": {
    "iso:country":"US",
    "sg:address":"2000 N Carson St",
    "sg:city":"Carson City",
    "sg:classifiers":[
        {
            "category":"Restaurant",
            "type":"Food & Drink"
        }
    ],
    "sg:phone":"+1 775 883 5600",
    "sg:postcode":"89706",
    "sg:province":"NV",
    "wof:name":"Juicy's Of Carson City",
    "wof:placetype":"venue"
},
  "geometry": {"coordinates":[-119.766907,39.179195],"type":"Point"}
}