{
  "type": "Feature",
  "properties": {
    "iso:country":"US",
    "sg:address":"4991 Longley Ln",
    "sg:city":"Reno",
    "sg:classifiers":[
        {
            "category":"Retail",
            "subcategory":"Car Wash",
            "type":"Services"
        }
    ],
    "sg:phone":"+1 775 828 9234",
    "sg:postcode":"89502",
    "sg:province":"NV",
    "sg:tags":[
        "polishing",
        "washing"
    ],
    "wof:name":"Metro Carwash",
    "wof:placetype":"venue"
},
  "geometry": {"coordinates":[-119.76397900000001,39.479349],"type":"Point"}
}