{
  "type": "Feature",
  "properties": {
    "iso:country":"US",
    "sg:address":"169 N Main St",
    "sg:city":"Alamo",
    "sg:classifiers":[
        {
            "category":"Banks & Credit Unions",
            "subcategory":"Bank",
            "type":"Services"
        }
    ],
    "sg:phone":"+1 775 725 3586",
    "sg:postcode":"89001",
    "sg:province":"NV",
    "sg:tags":[
        "federally",
        "chartered"
    ],
    "wof:name":"Pahranagat Valley Federal CU",
    "wof:placetype":"venue"
},
  "geometry": {"coordinates":[-115.165843,37.368211],"type":"Point"}
}