{
  "type": "Feature",
  "properties": {
    "iso:country":"US",
    "sg:address":"1205 W Sunset Rd",
    "sg:city":"Henderson",
    "sg:classifiers":[
        {
            "category":"Restaurant",
            "type":"Food & Drink"
        }
    ],
    "sg:phone":"+1 702 433 4824",
    "sg:postcode":"89014",
    "sg:province":"NV",
    "sg:tags":[
        "mexican"
    ],
    "sg:website":"www.rubios.com/",
    "wof:name":"Rubio's",
    "wof:placetype":"venue"
},
  "geometry": {"coordinates":[-115.038277,36.063151],"type":"Point"}
}