{
  "type": "Feature",
  "properties": {
    "iso:country":"US",
    "sg:address":"11570 Juniper St",
    "sg:city":"Reno",
    "sg:classifiers":[
        {
            "category":"Building & Trades",
            "subcategory":"Plumbing",
            "type":"Services"
        }
    ],
    "sg:phone":"+1 775 972 4165",
    "sg:postcode":"89506",
    "sg:province":"NV",
    "sg:tags":[
        "heating",
        "contractor"
    ],
    "wof:name":"D-Tech",
    "wof:placetype":"venue"
},
  "geometry": {"coordinates":[-119.830068,39.689462],"type":"Point"}
}