{
  "type": "Feature",
  "properties": {
    "iso:country":"US",
    "sg:address":"2232 S Nellis Blvd",
    "sg:city":"Las Vegas",
    "sg:classifiers":[
        {
            "category":"Freight",
            "type":"Transportation"
        }
    ],
    "sg:phone":"+1 702 837 6301",
    "sg:postcode":"89104",
    "sg:province":"NV",
    "sg:tags":[
        "operator",
        "local",
        "trucking"
    ],
    "wof:name":"Victor L Marlowe",
    "wof:placetype":"venue"
},
  "geometry": {"coordinates":[-115.065371,36.148202],"type":"Point"}
}