{
  "type": "Feature",
  "properties": {
    "iso:country":"US",
    "sg:address":"5160 S Valley View Blvd",
    "sg:city":"Las Vegas",
    "sg:classifiers":[
        {
            "category":"Professional",
            "subcategory":"Management & Consulting",
            "type":"Services"
        }
    ],
    "sg:phone":"+1 702 644 6789",
    "sg:postcode":"89118",
    "sg:province":"NV",
    "sg:tags":[
        "consultant",
        "business"
    ],
    "wof:name":"At Home Corporate Office",
    "wof:placetype":"venue"
},
  "geometry": {"coordinates":[-115.189766,36.096552],"type":"Point"}
}