{
  "type": "Feature",
  "properties": {
    "iso:country":"US",
    "sg:address":"8420 Willow Point Ct",
    "sg:city":"Las Vegas",
    "sg:classifiers":[
        {
            "category":"Professional",
            "subcategory":"Business Services",
            "type":"Services"
        }
    ],
    "sg:phone":"+1 702 251 0500",
    "sg:postcode":"89128",
    "sg:province":"NV",
    "wof:name":"Roth & Associates LLC",
    "wof:placetype":"venue"
},
  "geometry": {"coordinates":[-115.277897,36.189211],"type":"Point"}
}