{
  "type": "Feature",
  "properties": {
    "iso:country":"US",
    "sg:address":"3111 W Post Rd",
    "sg:city":"Las Vegas",
    "sg:classifiers":[
        {
            "category":"Building & Trades",
            "subcategory":"Electrical",
            "type":"Services"
        }
    ],
    "sg:phone":"+1 702 459 7732",
    "sg:postcode":"89118",
    "sg:province":"NV",
    "sg:tags":[
        "electric",
        "contractor"
    ],
    "wof:name":"Spec Electric LLC",
    "wof:placetype":"venue"
},
  "geometry": {"coordinates":[-115.18289300000001,36.074901],"type":"Point"}
}