{
  "type": "Feature",
  "properties": {
    "iso:country":"US",
    "sg:address":"3735 Spring Mountain Rd",
    "sg:city":"Las Vegas",
    "sg:classifiers":[
        {
            "category":"Restaurant",
            "type":"Food & Drink"
        }
    ],
    "sg:menulink":"http://www.allmenus.com/nv/las-vegas/122962-quiznos-sub/menu/",
    "sg:phone":"+1 702 252 8811",
    "sg:postcode":"89102",
    "sg:province":"NV",
    "sg:tags":[
        "wrap",
        "american",
        "sandwich"
    ],
    "wof:name":"Quiznos Sub",
    "wof:placetype":"venue"
},
  "geometry": {"coordinates":[-115.189329,36.126512],"type":"Point"}
}