{
  "type": "Feature",
  "properties": {
    "iso:country":"US",
    "sg:address":"3550 Kevin Street",
    "sg:city":"Las Vegas",
    "sg:classifiers":[
        {
            "category":"Education",
            "subcategory":"School",
            "type":"Public Place"
        }
    ],
    "sg:phone":"+1 702 799 4440",
    "sg:postcode":"89147",
    "sg:province":"NV",
    "wof:name":"Clark County School District",
    "wof:placetype":"venue"
},
  "geometry": {"coordinates":[-115.29006699999999,36.125386],"type":"Point"}
}