{
  "type": "Feature",
  "properties": {
    "iso:country":"US",
    "sg:address":"1825 N Carson St",
    "sg:city":"Carson City",
    "sg:classifiers":[
        {
            "category":"Coffee & Tea",
            "type":"Food & Drink"
        }
    ],
    "sg:phone":"+1 775 841 1818",
    "sg:postcode":"89701",
    "sg:province":"NV",
    "wof:name":"Barista Brothers Coffee",
    "wof:placetype":"venue"
},
  "geometry": {"coordinates":[-119.766998,39.176998],"type":"Point"}
}