{
  "type": "Feature",
  "properties": {
    "iso:country":"US",
    "sg:address":"5239 Caprice Ct",
    "sg:city":"Las Vegas",
    "sg:classifiers":[
        {
            "category":"Personal",
            "type":"Services"
        }
    ],
    "sg:phone":"+1 702 876 2283",
    "sg:postcode":"89118",
    "sg:province":"NV",
    "wof:name":"Healing From Within",
    "wof:placetype":"venue"
},
  "geometry": {"coordinates":[-115.227511,36.093247],"type":"Point"}
}