{
  "type": "Feature",
  "properties": {
    "iso:country":"US",
    "sg:address":"9901 Robin Oaks Dr",
    "sg:city":"Las Vegas",
    "sg:classifiers":[
        {
            "category":"Real Estate",
            "subcategory":"Real Estate Agent",
            "type":"Services"
        }
    ],
    "sg:phone":"+1 702 363 0800",
    "sg:postcode":"89117",
    "sg:province":"NV",
    "sg:tags":[
        "commercial",
        "leasing",
        "sales"
    ],
    "wof:name":"Paragon Commercial Real Estate",
    "wof:placetype":"venue"
},
  "geometry": {"coordinates":[-115.312874,36.133021],"type":"Point"}
}