{
  "type": "Feature",
  "properties": {
    "iso:country":"US",
    "sg:address":"1225 S Fort Apache Rd",
    "sg:city":"Las Vegas",
    "sg:classifiers":[
        {
            "category":"Restaurant",
            "type":"Food & Drink"
        }
    ],
    "sg:phone":"+1 702 804 1400",
    "sg:postcode":"89117",
    "sg:province":"NV",
    "sg:tags":[
        "steakhouse",
        "buffet",
        "brazilian"
    ],
    "sg:website":"viabrasilsteakhouse.com",
    "wof:name":"Via Brasil Steakhouse",
    "wof:placetype":"venue"
},
  "geometry": {"coordinates":[-115.291394,36.157534],"type":"Point"}
}