{
  "type": "Feature",
  "properties": {
    "iso:country":"US",
    "sg:address":"2116 Helen Ave",
    "sg:city":"Las Vegas",
    "sg:classifiers":[
        {
            "category":"Social Services",
            "subcategory":"Job Training",
            "type":"Services"
        }
    ],
    "sg:phone":"+1 702 647 6699",
    "sg:postcode":"89108",
    "sg:province":"NV",
    "sg:tags":[
        "rehabilitation"
    ],
    "wof:name":"Hope House Recovery For Women",
    "wof:placetype":"venue"
},
  "geometry": {"coordinates":[-115.216578,36.198173],"type":"Point"}
}