{
  "type": "Feature",
  "properties": {
    "iso:country":"US",
    "sg:address":"8080 W Sahara Ave",
    "sg:city":"Las Vegas",
    "sg:classifiers":[
        {
            "category":"Insurance",
            "subcategory":"Insurance Agent",
            "type":"Services"
        }
    ],
    "sg:phone":"+1 702 258 0300",
    "sg:postcode":"89117",
    "sg:province":"NV",
    "wof:name":"Insurance Services",
    "wof:placetype":"venue"
},
  "geometry": {"coordinates":[-115.266077,36.143873],"type":"Point"}
}