{
  "type": "Feature",
  "properties": {
    "iso:country":"US",
    "sg:address":"770 Smithridge Dr",
    "sg:city":"Reno",
    "sg:classifiers":[
        {
            "category":"Professional",
            "subcategory":"Research",
            "type":"Services"
        },
        {
            "category":"Professional",
            "subcategory":"Management & Consulting",
            "type":"Services"
        }
    ],
    "sg:phone":"+1 775 825 5800",
    "sg:postcode":"89502",
    "sg:province":"NV",
    "sg:tags":[
        "development",
        "geothermal",
        "exploration"
    ],
    "wof:name":"Geothermal Development Assoc",
    "wof:placetype":"venue"
},
  "geometry": {"coordinates":[-119.787857,39.479672],"type":"Point"}
}