{
  "type": "Feature",
  "properties": {
    "iso:country":"US",
    "sg:address":"801 S Rancho Dr Ste E3A",
    "sg:city":"Las Vegas",
    "sg:classifiers":[
        {
            "category":"Shopping",
            "subcategory":"Pharmacy",
            "type":"Retail Goods"
        }
    ],
    "sg:phone":"+1 702 463 7926",
    "sg:postcode":"89106",
    "sg:province":"NV",
    "sg:tags":[
        "drugstore"
    ],
    "wof:name":"Assured Pharmacy",
    "wof:placetype":"venue"
},
  "geometry": {"coordinates":[-115.17245,36.162276],"type":"Point"}
}