{
  "type": "Feature",
  "properties": {
    "iso:country":"US",
    "sg:address":"4374 E Alexander Rd",
    "sg:city":"Las Vegas",
    "sg:classifiers":[
        {
            "category":"Building & Trades",
            "subcategory":"Plumbing",
            "type":"Services"
        }
    ],
    "sg:phone":"+1 702 253 1022",
    "sg:postcode":"89115",
    "sg:province":"NV",
    "sg:tags":[
        "conditioning",
        "air",
        "system",
        "contractor"
    ],
    "wof:name":"Erich's Air Cond & Heating",
    "wof:placetype":"venue"
},
  "geometry": {"coordinates":[-115.079894,36.232772],"type":"Point"}
}