{
  "type": "Feature",
  "properties": {
    "iso:country":"US",
    "sg:address":"3135 Marco St",
    "sg:city":"Las Vegas",
    "sg:classifiers":[
        {
            "category":"Autos & Motor Vehicles",
            "subcategory":"Automobile Sales",
            "type":"Retail Goods"
        }
    ],
    "sg:phone":"+1 702 853 4813",
    "sg:postcode":"89115",
    "sg:province":"NV",
    "sg:tags":[
        "automotive"
    ],
    "sg:website":"www.aswf.com",
    "wof:name":"Erickson International",
    "wof:placetype":"venue"
},
  "geometry": {"coordinates":[-115.07054100000001,36.215747],"type":"Point"}
}