{
  "type": "Feature",
  "properties": {
    "iso:country":"US",
    "sg:address":"2683 Turtle Head Peak Dr",
    "sg:city":"Las Vegas",
    "sg:classifiers":[
        {
            "category":"Professional",
            "subcategory":"Computer Services",
            "type":"Services"
        }
    ],
    "sg:phone":"+1 702 256 1663",
    "sg:postcode":"89135",
    "sg:province":"NV",
    "sg:tags":[
        "software",
        "developer"
    ],
    "wof:name":"M M Z & Associates",
    "wof:placetype":"venue"
},
  "geometry": {"coordinates":[-115.342689,36.138944],"type":"Point"}
}