{
  "type": "Feature",
  "properties": {
    "iso:country":"US",
    "sg:address":"1009 Court St",
    "sg:city":"Elko",
    "sg:classifiers":[
        {
            "category":"Farming",
            "subcategory":"Livestock Farm",
            "type":"Manufacturing & Wholesale Goods"
        }
    ],
    "sg:phone":"+1 775 738 3886",
    "sg:postcode":"89801",
    "sg:province":"NV",
    "sg:tags":[
        "ranch"
    ],
    "wof:name":"Pattani Ranch Partnership",
    "wof:placetype":"venue"
},
  "geometry": {"coordinates":[-115.758577,40.837807],"type":"Point"}
}