{
  "type": "Feature",
  "properties": {
    "iso:country":"US",
    "sg:address":"100 N Green Valley Parkway",
    "sg:city":"Henderson",
    "sg:classifiers":[
        {
            "category":"Health Services",
            "subcategory":"Doctor",
            "type":"Services"
        }
    ],
    "sg:phone":"+1 702 933 1485",
    "sg:postcode":"89074",
    "sg:province":"NV",
    "sg:tags":[
        "practice",
        "family"
    ],
    "wof:name":"Nevada Family Care",
    "wof:placetype":"venue"
},
  "geometry": {"coordinates":[-115.08505700000001,36.025483],"type":"Point"}
}