{
  "type": "Feature",
  "properties": {
    "iso:country":"US",
    "sg:address":"240 Serpa Pl",
    "sg:city":"Fallon",
    "sg:classifiers":[
        {
            "category":"Real Estate",
            "subcategory":"Real Estate Operator",
            "type":"Services"
        }
    ],
    "sg:phone":"+1 775 423 3228",
    "sg:postcode":"89406",
    "sg:province":"NV",
    "sg:tags":[
        "building",
        "apartment"
    ],
    "wof:name":"Stillwater Apartments Home",
    "wof:placetype":"venue"
},
  "geometry": {"coordinates":[-118.773701,39.482096],"type":"Point"}
}