{
  "type": "Feature",
  "properties": {
    "iso:country":"US",
    "sg:address":"1009 Industrial Rd",
    "sg:city":"Boulder City",
    "sg:classifiers":[
        {
            "category":"Wholesale",
            "subcategory":"Electrical",
            "type":"Manufacturing & Wholesale Goods"
        }
    ],
    "sg:phone":"+1 702 294 8944",
    "sg:postcode":"89005",
    "sg:province":"NV",
    "sg:tags":[
        "distributor",
        "lighting",
        "fixture"
    ],
    "wof:name":"H & M Distributors Inc",
    "wof:placetype":"venue"
},
  "geometry": {"coordinates":[-114.845136,35.978838],"type":"Point"}
}