{
  "type": "Feature",
  "properties": {
    "iso:country":"US",
    "sg:address":"4425 Stewart St Ste107",
    "sg:city":"Las Vegas",
    "sg:classifiers":[
        {
            "category":"Fast Food",
            "type":"Food & Drink"
        }
    ],
    "sg:phone":"+1 702 434 1600",
    "sg:postcode":"89110",
    "sg:province":"NV",
    "sg:tags":[
        "burger"
    ],
    "wof:name":"Fat Boy",
    "wof:placetype":"venue"
},
  "geometry": {"coordinates":[-115.07918100000001,36.166844],"type":"Point"}
}