{
  "type": "Feature",
  "properties": {
    "iso:country":"US",
    "sg:address":"266 Spring Creek Pkwy",
    "sg:city":"Spring Creek",
    "sg:classifiers":[
        {
            "category":"Food & Beverages",
            "subcategory":"Groceries & Convenience Stores",
            "type":"Retail Goods"
        }
    ],
    "sg:phone":"+1 775 753 8984",
    "sg:postcode":"89815",
    "sg:province":"NV",
    "wof:name":"Shell",
    "wof:placetype":"venue"
},
  "geometry": {"coordinates":[-115.597227,40.748884],"type":"Point"}
}