{
  "type": "Feature",
  "properties": {
    "iso:country":"US",
    "sg:address":"467 Plumb Ln",
    "sg:city":"Reno",
    "sg:classifiers":[
        {
            "category":"Shopping",
            "subcategory":"Bicycles & Sporting Goods",
            "type":"Retail Goods"
        }
    ],
    "sg:phone":"+1 775 786 4447",
    "sg:postcode":"89502",
    "sg:province":"NV",
    "sg:tags":[
        "ammunition",
        "firearm"
    ],
    "wof:name":"Gun Trader The",
    "wof:placetype":"venue"
},
  "geometry": {"coordinates":[-119.797222,39.505881],"type":"Point"}
}