{
  "type": "Feature",
  "properties": {
    "iso:country":"US",
    "sg:address":"2972 Meade Ave",
    "sg:city":"Las Vegas",
    "sg:classifiers":[
        {
            "category":"Organizations",
            "subcategory":"Religious Organization",
            "type":"Services"
        }
    ],
    "sg:phone":"+1 702 631 3365",
    "sg:postcode":"89102",
    "sg:province":"NV",
    "sg:tags":[
        "church"
    ],
    "wof:name":"Las Vegas Christian Ctr Church",
    "wof:placetype":"venue"
},
  "geometry": {"coordinates":[-115.180387,36.136339],"type":"Point"}
}