{
  "type": "Feature",
  "properties": {
    "iso:country":"US",
    "sg:address":"4616 W. Sahara Ave., Ste # 372",
    "sg:city":"Las Vegas",
    "sg:classifiers":[
        {
            "category":"Arts & Performance",
            "subcategory":"Music",
            "type":"Entertainment"
        }
    ],
    "sg:phone":"+1 702 463 7336",
    "sg:postcode":"89102",
    "sg:province":"NV",
    "sg:tags":[
        "dj"
    ],
    "sg:website":"www.RockstarrDJz.com",
    "wof:name":"Rockstarr DJz",
    "wof:placetype":"venue"
},
  "geometry": {"coordinates":[-115.20334099999999,36.144617],"type":"Point"}
}