{
  "type": "Feature",
  "properties": {
    "iso:country":"US",
    "sg:address":"3620 N Rancho Drive Suite 109",
    "sg:city":"Las Vegas",
    "sg:classifiers":[
        {
            "category":"Real Estate",
            "subcategory":"Architect",
            "type":"Services"
        }
    ],
    "sg:phone":"+1 702 259 0011",
    "sg:postcode":"89130",
    "sg:province":"NV",
    "wof:name":"Pswc",
    "wof:placetype":"venue"
},
  "geometry": {"coordinates":[-115.219174,36.225098],"type":"Point"}
}