{
  "type": "Feature",
  "properties": {
    "iso:country":"US",
    "sg:address":"105 Montelago Blvd",
    "sg:city":"Henderson",
    "sg:classifiers":[
        {
            "category":"Building & Trades",
            "subcategory":"Construction",
            "type":"Services"
        }
    ],
    "sg:phone":"+1 702 567 8378",
    "sg:postcode":"89011",
    "sg:province":"NV",
    "sg:tags":[
        "home",
        "builder"
    ],
    "wof:name":"Marquis Homes",
    "wof:placetype":"venue"
},
  "geometry": {"coordinates":[-114.929284,36.108053],"type":"Point"}
}