{
  "type": "Feature",
  "properties": {
    "iso:country":"US",
    "sg:address":"1555 Balzar Ave",
    "sg:city":"Las Vegas",
    "sg:classifiers":[
        {
            "category":"Real Estate",
            "subcategory":"Real Estate Operator",
            "type":"Services"
        }
    ],
    "sg:phone":"+1 702 736 2002",
    "sg:postcode":"89106",
    "sg:province":"NV",
    "sg:tags":[
        "building",
        "apartment"
    ],
    "wof:name":"Sunset Park Appartments",
    "wof:placetype":"venue"
},
  "geometry": {"coordinates":[-115.161474,36.199281],"type":"Point"}
}