{
  "type": "Feature",
  "properties": {
    "iso:country":"US",
    "sg:address":"875 S Boulder Hwy",
    "sg:city":"Henderson",
    "sg:classifiers":[
        {
            "category":"Retail",
            "subcategory":"Repair Shop",
            "type":"Services"
        }
    ],
    "sg:phone":"+1 702 566 0777",
    "sg:postcode":"89015",
    "sg:province":"NV",
    "sg:tags":[
        "welding"
    ],
    "wof:name":"J & C Custom Welding",
    "wof:placetype":"venue"
},
  "geometry": {"coordinates":[-114.973554,36.032243],"type":"Point"}
}