{
  "type": "Feature",
  "properties": {
    "iso:country":"US",
    "sg:address":"522 N Lamb Blvd",
    "sg:city":"Las Vegas",
    "sg:classifiers":[
        {
            "category":"Real Estate",
            "subcategory":"Real Estate Operator",
            "type":"Services"
        }
    ],
    "sg:phone":"+1 702 452 4043",
    "sg:postcode":"89110",
    "sg:province":"NV",
    "sg:tags":[
        "apartment",
        "complex"
    ],
    "wof:name":"Saratoga Palms At Diamond Head",
    "wof:placetype":"venue"
},
  "geometry": {"coordinates":[-115.08000199999999,36.170799],"type":"Point"}
}