{
  "type": "Feature",
  "properties": {
    "iso:country":"US",
    "sg:address":"5450 Cameron St",
    "sg:city":"Las Vegas",
    "sg:classifiers":[
        {
            "category":"Wholesale",
            "subcategory":"Construction Materials",
            "type":"Manufacturing & Wholesale Goods"
        },
        {
            "category":"Wholesale",
            "subcategory":"Machinery & Supplies",
            "type":"Manufacturing & Wholesale Goods"
        }
    ],
    "sg:phone":"+1 702 889 2143",
    "sg:postcode":"89118",
    "sg:province":"NV",
    "sg:tags":[
        "granite",
        "industrial",
        "equipment"
    ],
    "wof:name":"Global Pneumatics",
    "wof:placetype":"venue"
},
  "geometry": {"coordinates":[-115.203767,36.090082],"type":"Point"}
}