{
  "type": "Feature",
  "properties": {
    "iso:country":"US",
    "sg:address":"3144 Morning Whisper Dr",
    "sg:city":"Henderson",
    "sg:classifiers":[
        {
            "category":"Professional",
            "subcategory":"Computer Services",
            "type":"Services"
        }
    ],
    "sg:phone":"+1 702 269 9952",
    "sg:postcode":"89052",
    "sg:province":"NV",
    "sg:tags":[
        "programing",
        "custom"
    ],
    "wof:name":"Data Specialties Company",
    "wof:placetype":"venue"
},
  "geometry": {"coordinates":[-115.126614,35.971625],"type":"Point"}
}