{
  "type": "Feature",
  "properties": {
    "iso:country":"US",
    "sg:address":"5216 Dana Springs Way",
    "sg:city":"Las Vegas",
    "sg:classifiers":[
        {
            "category":"Building & Trades",
            "subcategory":"Cleaning & Sanitation",
            "type":"Services"
        }
    ],
    "sg:phone":"+1 702 452 7600",
    "sg:postcode":"89130",
    "sg:province":"NV",
    "sg:tags":[
        "carpet"
    ],
    "wof:name":"Five Star Carpet Care",
    "wof:placetype":"venue"
},
  "geometry": {"coordinates":[-115.238826,36.256619],"type":"Point"}
}