{
  "type": "Feature",
  "properties": {
    "iso:country":"US",
    "sg:address":"4525 W Reno Ave",
    "sg:city":"Las Vegas",
    "sg:classifiers":[
        {
            "category":"Building & Trades",
            "subcategory":"Construction",
            "type":"Services"
        }
    ],
    "sg:phone":"+1 702 367 4810",
    "sg:postcode":"89118",
    "sg:province":"NV",
    "sg:tags":[
        "commercial",
        "renovation",
        "contractor"
    ],
    "wof:name":"Gkg Builders Inc",
    "wof:placetype":"venue"
},
  "geometry": {"coordinates":[-115.203337,36.097181],"type":"Point"}
}