{
  "type": "Feature",
  "properties": {
    "iso:country":"US",
    "sg:address":"615 Harrison Ave",
    "sg:city":"Las Vegas",
    "sg:classifiers":[
        {
            "category":"Shopping",
            "type":"Retail Goods"
        }
    ],
    "sg:phone":"+1 702 647 1777",
    "sg:postcode":"89106",
    "sg:province":"NV",
    "sg:tags":[
        "art",
        "gallery",
        "dealer"
    ],
    "wof:name":"Brainchild Art",
    "wof:placetype":"venue"
},
  "geometry": {"coordinates":[-115.150848,36.18788],"type":"Point"}
}