{
  "type": "Feature",
  "properties": {
    "iso:country":"US",
    "sg:address":"1825 Pinion Rd",
    "sg:city":"Elko",
    "sg:classifiers":[
        {
            "category":"Health Services",
            "subcategory":"Medical Lab",
            "type":"Services"
        }
    ],
    "sg:phone":"+1 775 753 6603",
    "sg:postcode":"89801",
    "sg:province":"NV",
    "sg:tags":[
        "laboratory"
    ],
    "wof:name":"Laboratory Corp Of America",
    "wof:placetype":"venue"
},
  "geometry": {"coordinates":[-115.733521,40.832312],"type":"Point"}
}