{
  "type": "Feature",
  "properties": {
    "iso:country":"US",
    "sg:address":"111 Lay St",
    "sg:city":"Winnemucca",
    "sg:classifiers":[
        {
            "category":"Social Services",
            "subcategory":"Child Care",
            "type":"Services"
        }
    ],
    "sg:phone":"+1 775 623 2661",
    "sg:postcode":"89445",
    "sg:province":"NV",
    "sg:tags":[
        "day"
    ],
    "wof:name":"Day Enterprises LLC",
    "wof:placetype":"venue"
},
  "geometry": {"coordinates":[-117.7387,40.9736],"type":"Point"}
}