{
  "type": "Feature",
  "properties": {
    "iso:country":"US",
    "sg:address":"3950 E Sunset Rd",
    "sg:city":"Las Vegas",
    "sg:classifiers":[
        {
            "category":"Retail",
            "subcategory":"Laundry & Dry Cleaning",
            "type":"Services"
        }
    ],
    "sg:phone":"+1 702 434 3687",
    "sg:postcode":"89120",
    "sg:province":"NV",
    "wof:name":"Four Seasons Cleaners",
    "wof:placetype":"venue"
},
  "geometry": {"coordinates":[-115.087997,36.071201],"type":"Point"}
}