{
  "type": "Feature",
  "properties": {
    "iso:country":"US",
    "sg:address":"285 Seal Ct",
    "sg:city":"Henderson",
    "sg:classifiers":[
        {
            "category":"Real Estate",
            "subcategory":"Real Estate Operator",
            "type":"Services"
        }
    ],
    "sg:phone":"+1 702 454 4985",
    "sg:postcode":"89074",
    "sg:province":"NV",
    "sg:tags":[
        "building",
        "nonresidential"
    ],
    "wof:name":"B & E Properties LLC",
    "wof:placetype":"venue"
},
  "geometry": {"coordinates":[-115.049668,36.048446],"type":"Point"}
}