{
  "type": "Feature",
  "properties": {
    "iso:country":"US",
    "sg:address":"1140 Cornell Ave",
    "sg:city":"Lovelock",
    "sg:classifiers":[
        {
            "category":"Health Services",
            "subcategory":"Chiropractor",
            "type":"Services"
        }
    ],
    "sg:phone":"+1 775 273 1140",
    "sg:postcode":"89419",
    "sg:province":"NV",
    "wof:name":"Classic Chiropractic",
    "wof:placetype":"venue"
},
  "geometry": {"coordinates":[-118.473618,40.181555],"type":"Point"}
}