{
  "type": "Feature",
  "properties": {
    "iso:country":"US",
    "sg:address":"9850 S Maryland Parkway",
    "sg:city":"Las Vegas",
    "sg:classifiers":[
        {
            "category":"Health Services",
            "subcategory":"Dentist",
            "type":"Services"
        }
    ],
    "sg:phone":"+1 702 914 9990",
    "sg:postcode":"89183",
    "sg:province":"NV",
    "sg:website":"www.choicedentallv.com",
    "wof:name":"Choice Dental",
    "wof:placetype":"venue"
},
  "geometry": {"coordinates":[-115.136716,36.010565],"type":"Point"}
}