{
  "type": "Feature",
  "properties": {
    "iso:country":"US",
    "sg:address":"3080 US Hwy 50",
    "sg:city":"Carson City",
    "sg:classifiers":[
        {
            "category":"Shopping",
            "subcategory":"Bicycles & Sporting Goods",
            "type":"Retail Goods"
        },
        {
            "category":"Shopping",
            "subcategory":"Clothing, Apparel, & Fashions",
            "type":"Retail Goods"
        }
    ],
    "sg:phone":"+1 775 883 3633",
    "sg:postcode":"89701",
    "sg:province":"NV",
    "sg:tags":[
        "equipment",
        "saddlery",
        "harness",
        "western"
    ],
    "wof:name":"Hitchin' Post",
    "wof:placetype":"venue"
},
  "geometry": {"coordinates":[-119.733509,39.176606],"type":"Point"}
}