{
  "type": "Feature",
  "properties": {
    "iso:country":"US",
    "sg:address":"7680 Las Vegas Blvd S",
    "sg:city":"Las Vegas",
    "sg:classifiers":[
        {
            "category":"Freight",
            "type":"Transportation"
        }
    ],
    "sg:phone":"+1 702 260 8144",
    "sg:postcode":"89123",
    "sg:province":"NV",
    "sg:tags":[
        "warehouse",
        "self",
        "storage"
    ],
    "wof:name":"Disney's Character Warehouse",
    "wof:placetype":"venue"
},
  "geometry": {"coordinates":[-115.172255,36.052954],"type":"Point"}
}