{
  "type": "Feature",
  "properties": {
    "iso:country":"US",
    "sg:address":"1120 Shadow Ln Ste C",
    "sg:city":"Las Vegas",
    "sg:classifiers":[
        {
            "category":"Banks & Credit Unions",
            "subcategory":"Financial Services",
            "type":"Services"
        }
    ],
    "sg:phone":"+1 702 474 7300",
    "sg:postcode":"89102",
    "sg:province":"NV",
    "sg:tags":[
        "broker",
        "mortgage"
    ],
    "wof:name":"Investors Mortgage Corp",
    "wof:placetype":"venue"
},
  "geometry": {"coordinates":[-115.165001,36.158501],"type":"Point"}
}