{
  "type": "Feature",
  "properties": {
    "iso:country":"US",
    "sg:address":"1271 Galleria Dr",
    "sg:city":"Henderson",
    "sg:classifiers":[
        {
            "category":"Shopping",
            "subcategory":"Clothing, Apparel, & Fashions",
            "type":"Retail Goods"
        }
    ],
    "sg:phone":"+1 702 458 8388",
    "sg:postcode":"89014",
    "sg:province":"NV",
    "sg:tags":[
        "shoes"
    ],
    "wof:name":"Footaction USA",
    "wof:placetype":"venue"
},
  "geometry": {"coordinates":[-115.0409,36.070817],"type":"Point"}
}