{
  "type": "Feature",
  "properties": {
    "iso:country":"US",
    "sg:address":"557 Washington St",
    "sg:city":"Reno",
    "sg:classifiers":[
        {
            "category":"Professional",
            "subcategory":"Lawyer & Legal Services",
            "type":"Services"
        }
    ],
    "sg:phone":"+1 775 677 7777",
    "sg:postcode":"89503",
    "sg:province":"NV",
    "sg:tags":[
        "attorney"
    ],
    "wof:name":"A Affordable Legal Clinic",
    "wof:placetype":"venue"
},
  "geometry": {"coordinates":[-119.824112,39.530047],"type":"Point"}
}