{
  "type": "Feature",
  "properties": {
    "iso:country":"US",
    "sg:address":"1135 Majestic Ct",
    "sg:city":"Reno",
    "sg:classifiers":[
        {
            "category":"Wholesale",
            "subcategory":"Hardware",
            "type":"Manufacturing & Wholesale Goods"
        }
    ],
    "sg:phone":"+1 775 746 4954",
    "sg:postcode":"89503",
    "sg:province":"NV",
    "sg:tags":[
        "prevention",
        "flow",
        "back",
        "devices"
    ],
    "wof:name":"Great Basin Back Flow",
    "wof:placetype":"venue"
},
  "geometry": {"coordinates":[-119.832461,39.535197],"type":"Point"}
}