{
  "type": "Feature",
  "properties": {
    "iso:country":"US",
    "sg:address":"4550 E Van Buren Ave",
    "sg:city":"Las Vegas",
    "sg:classifiers":[
        {
            "category":"Farming",
            "subcategory":"Farm & Veterinary Services",
            "type":"Manufacturing & Wholesale Goods"
        }
    ],
    "sg:phone":"+1 702 278 0332",
    "sg:postcode":"89110",
    "sg:province":"NV",
    "sg:tags":[
        "preparation",
        "crop",
        "for",
        "market"
    ],
    "wof:name":"Compton Cubes",
    "wof:placetype":"venue"
},
  "geometry": {"coordinates":[-115.079615,36.186547],"type":"Point"}
}