{
  "type": "Feature",
  "properties": {
    "iso:country":"US",
    "sg:address":"1530 Tyler Way",
    "sg:city":"Sparks",
    "sg:classifiers":[
        {
            "category":"Real Estate",
            "subcategory":"Real Estate Agent",
            "type":"Services"
        }
    ],
    "sg:phone":"+1 775 358 1131",
    "sg:postcode":"89431",
    "sg:province":"NV",
    "sg:tags":[
        "business"
    ],
    "wof:name":"Shakal Glenn T",
    "wof:placetype":"venue"
},
  "geometry": {"coordinates":[-119.762476,39.549605],"type":"Point"}
}