{
  "type": "Feature",
  "properties": {
    "iso:country":"US",
    "sg:address":"7200 N Rancho Dr",
    "sg:city":"Las Vegas",
    "sg:classifiers":[
        {
            "category":"Home & Garden",
            "subcategory":"Garden Supply",
            "type":"Retail Goods"
        }
    ],
    "sg:phone":"+1 702 735 8733",
    "sg:postcode":"89131",
    "sg:province":"NV",
    "sg:tags":[
        "nursery",
        "gardening"
    ],
    "wof:name":"Moon Valley Nurseries",
    "wof:placetype":"venue"
},
  "geometry": {"coordinates":[-115.25024000000001,36.260198],"type":"Point"}
}