{
  "type": "Feature",
  "properties": {
    "iso:country":"US",
    "sg:address":"25 State Rte 208",
    "sg:city":"Yerington",
    "sg:classifiers":[
        {
            "category":"Retail",
            "subcategory":"Funeral Services",
            "type":"Services"
        }
    ],
    "sg:phone":"+1 775 463 2911",
    "sg:postcode":"89447",
    "sg:province":"NV",
    "sg:tags":[
        "director"
    ],
    "wof:name":"Freitas Rupracht Funeral Home",
    "wof:placetype":"venue"
},
  "geometry": {"coordinates":[-119.163361,38.974813],"type":"Point"}
}