{
  "type": "Feature",
  "properties": {
    "iso:country":"US",
    "sg:address":"155 N Taylor St",
    "sg:city":"Fallon",
    "sg:classifiers":[
        {
            "category":"Government",
            "subcategory":"Office",
            "type":"Public Place"
        }
    ],
    "sg:phone":"+1 775 423 8423",
    "sg:postcode":"89406",
    "sg:province":"NV",
    "sg:tags":[
        "county",
        "resource"
    ],
    "wof:name":"Churchill County Child Support",
    "wof:placetype":"venue"
},
  "geometry": {"coordinates":[-118.781603,39.476758],"type":"Point"}
}