{
  "type": "Feature",
  "properties": {
    "iso:country":"US",
    "sg:address":"5575 Simmons Street Suite 10",
    "sg:city":"North Las Vegas",
    "sg:classifiers":[
        {
            "category":"Health Services",
            "subcategory":"Dentist",
            "type":"Services"
        }
    ],
    "sg:phone":"+1 702 317 7767",
    "sg:postcode":"89031",
    "sg:province":"NV",
    "wof:name":"A",
    "wof:placetype":"venue"
},
  "geometry": {"coordinates":[-115.18003899999999,36.261073],"type":"Point"}
}