{
  "type": "Feature",
  "properties": {
    "iso:country":"US",
    "sg:address":"2097 N Jones Blvd",
    "sg:city":"Las Vegas",
    "sg:classifiers":[
        {
            "category":"Shopping",
            "subcategory":"Tobacco",
            "type":"Retail Goods"
        }
    ],
    "sg:phone":"+1 702 631 9766",
    "sg:postcode":"89108",
    "sg:province":"NV",
    "sg:tags":[
        "shop"
    ],
    "wof:name":"Jr Smoke Shop Inc",
    "wof:placetype":"venue"
},
  "geometry": {"coordinates":[-115.223999,36.197201],"type":"Point"}
}