{
  "type": "Feature",
  "properties": {
    "iso:country":"US",
    "sg:address":"2816 Avanti Ln",
    "sg:city":"Henderson",
    "sg:classifiers":[
        {
            "category":"Manufacturing",
            "subcategory":"Printing",
            "type":"Manufacturing & Wholesale Goods"
        }
    ],
    "sg:phone":"+1 702 595 5145",
    "sg:postcode":"89074",
    "sg:province":"NV",
    "sg:tags":[
        "commercial"
    ],
    "wof:name":"Art Department Las Vegas",
    "wof:placetype":"venue"
},
  "geometry": {"coordinates":[-115.11600199999999,36.047614],"type":"Point"}
}