{
  "type": "Feature",
  "properties": {
    "iso:country":"US",
    "sg:address":"2987 Las Vegas Blvd N",
    "sg:city":"North Las Vegas",
    "sg:classifiers":[
        {
            "category":"Banks & Credit Unions",
            "subcategory":"Bank",
            "type":"Services"
        }
    ],
    "sg:phone":"+1 702 649 1921",
    "sg:postcode":"89030",
    "sg:province":"NV",
    "wof:name":"Wells Fargo Bank Na",
    "wof:placetype":"venue"
},
  "geometry": {"coordinates":[-115.10029,36.214549],"type":"Point"}
}