{
  "type": "Feature",
  "properties": {
    "iso:country":"US",
    "sg:address":"2300 S Casino Dr",
    "sg:city":"Laughlin",
    "sg:classifiers":[
        {
            "category":"Restaurant",
            "type":"Food & Drink"
        }
    ],
    "sg:menulink":"http://www.allmenus.com/nv/clark/235164-saltgrass-steak-house/menu/",
    "sg:phone":"+1 702 298 7153",
    "sg:postcode":"89029",
    "sg:province":"NV",
    "sg:tags":[
        "american",
        "steakhouse"
    ],
    "wof:name":"Saltgrass Steak House",
    "wof:placetype":"venue"
},
  "geometry": {"coordinates":[-114.57354599999999,35.154448],"type":"Point"}
}