{
  "type": "Feature",
  "properties": {
    "iso:country":"US",
    "sg:address":"875 S Grand Central Pkwy 1880",
    "sg:city":"Las Vegas",
    "sg:classifiers":[
        {
            "category":"Shopping",
            "subcategory":"Clothing, Apparel, & Fashions",
            "type":"Retail Goods"
        }
    ],
    "sg:phone":"+1 702 385 2219",
    "sg:postcode":"89106",
    "sg:province":"NV",
    "wof:name":"Hurley",
    "wof:placetype":"venue"
},
  "geometry": {"coordinates":[-115.156058,36.164625],"type":"Point"}
}