{
  "type": "Feature",
  "properties": {
    "iso:country":"US",
    "sg:address":"1615 E Sunset Road",
    "sg:city":"Las Vegas",
    "sg:classifiers":[
        {
            "category":"Insurance",
            "subcategory":"Health Insurance",
            "type":"Services"
        }
    ],
    "sg:phone":"+1 702 263 2391",
    "sg:postcode":"89119",
    "sg:province":"NV",
    "sg:tags":[
        "market"
    ],
    "wof:name":"Toe Corporation",
    "wof:placetype":"venue"
},
  "geometry": {"coordinates":[-115.130315,36.07183],"type":"Point"}
}