{
  "type": "Feature",
  "properties": {
    "iso:country":"US",
    "sg:address":"2550 W Sunset Rd",
    "sg:city":"Las Vegas",
    "sg:classifiers":[
        {
            "category":"Retail",
            "subcategory":"Auto Repair",
            "type":"Services"
        }
    ],
    "sg:phone":"+1 702 361 1112",
    "sg:postcode":"89119",
    "sg:province":"NV",
    "sg:tags":[
        "automotive"
    ],
    "wof:name":"Green Valley Towing",
    "wof:placetype":"venue"
},
  "geometry": {"coordinates":[-115.172518,36.071177],"type":"Point"}
}