{
  "type": "Feature",
  "properties": {
    "iso:country":"US",
    "sg:address":"4200 W Russell Rd",
    "sg:city":"Las Vegas",
    "sg:classifiers":[
        {
            "category":"Professional",
            "subcategory":"Advertising",
            "type":"Services"
        }
    ],
    "sg:phone":"+1 702 739 8135",
    "sg:postcode":"89118",
    "sg:province":"NV",
    "wof:name":"Resort Property Spec Corp",
    "wof:placetype":"venue"
},
  "geometry": {"coordinates":[-115.197179,36.086332],"type":"Point"}
}