{
  "type": "Feature",
  "properties": {
    "iso:country":"US",
    "sg:address":"1538 US Hwy 395 N",
    "sg:city":"Gardnerville",
    "sg:classifiers":[
        {
            "category":"Government",
            "subcategory":"Office",
            "type":"Public Place"
        }
    ],
    "sg:phone":"+1 775 782 3671",
    "sg:postcode":"89410",
    "sg:province":"NV",
    "sg:tags":[
        "state",
        "program",
        "health"
    ],
    "wof:name":"Douglas Mental Health Clinic",
    "wof:placetype":"venue"
},
  "geometry": {"coordinates":[-119.761956,38.952624],"type":"Point"}
}