{
  "type": "Feature",
  "properties": {
    "iso:country":"US",
    "sg:address":"4636 Olguin Ln",
    "sg:city":"Las Vegas",
    "sg:classifiers":[
        {
            "category":"Building & Trades",
            "subcategory":"Construction",
            "type":"Services"
        }
    ],
    "sg:phone":"+1 702 459 1581",
    "sg:postcode":"89110",
    "sg:province":"NV",
    "sg:tags":[
        "general",
        "contractor"
    ],
    "wof:name":"Antenes Construction",
    "wof:placetype":"venue"
},
  "geometry": {"coordinates":[-115.07161,36.165953],"type":"Point"}
}