{
  "type": "Feature",
  "properties": {
    "iso:country":"US",
    "sg:address":"530 S 7th Street",
    "sg:city":"Las Vegas",
    "sg:classifiers":[
        {
            "category":"Professional",
            "subcategory":"Lawyer & Legal Services",
            "type":"Services"
        }
    ],
    "sg:phone":"+1 702 385 0799",
    "sg:postcode":"89101",
    "sg:province":"NV",
    "wof:name":"Terry William B Chtd",
    "wof:placetype":"venue"
},
  "geometry": {"coordinates":[-115.142208,36.162663],"type":"Point"}
}