{
  "type": "Feature",
  "properties": {
    "iso:country":"US",
    "sg:address":"3735 Las Vegas Blvd S",
    "sg:city":"Las Vegas",
    "sg:classifiers":[
        {
            "category":"Retail",
            "subcategory":"Auto Rental",
            "type":"Services"
        }
    ],
    "sg:phone":"+1 702 736 2663",
    "sg:postcode":"89109",
    "sg:province":"NV",
    "sg:tags":[
        "renting",
        "automobile"
    ],
    "wof:name":"X-Press Car Rental",
    "wof:placetype":"venue"
},
  "geometry": {"coordinates":[-115.172903,36.104885],"type":"Point"}
}