{
  "type": "Feature",
  "properties": {
    "iso:country":"US",
    "sg:address":"329 Las Vegas Boulevard N",
    "sg:city":"Las Vegas",
    "sg:classifiers":[
        {
            "category":"Autos & Motor Vehicles",
            "subcategory":"Fuel & Gas Station",
            "type":"Retail Goods"
        }
    ],
    "sg:phone":"+1 702 366 1614",
    "sg:postcode":"89101",
    "sg:province":"NV",
    "wof:name":"Pump N Snack",
    "wof:placetype":"venue"
},
  "geometry": {"coordinates":[-115.13899000000001,36.172146],"type":"Point"}
}