{
  "type": "Feature",
  "properties": {
    "iso:country":"US",
    "sg:address":"2212 Fremont St",
    "sg:city":"Las Vegas",
    "sg:classifiers":[
        {
            "category":"Travel",
            "subcategory":"Hotels & Motels",
            "type":"Entertainment"
        }
    ],
    "sg:phone":"+1 702 383 7062",
    "sg:postcode":"89101",
    "sg:province":"NV",
    "sg:tags":[
        "operation"
    ],
    "wof:name":"Liberty Inn Motel",
    "wof:placetype":"venue"
},
  "geometry": {"coordinates":[-115.119563,36.160154],"type":"Point"}
}