{
  "type": "Feature",
  "properties": {
    "iso:country":"US",
    "sg:address":"395 Cliff View Dr",
    "sg:city":"Reno",
    "sg:classifiers":[
        {
            "category":"Building & Trades",
            "subcategory":"Construction",
            "type":"Services"
        }
    ],
    "sg:phone":"+1 775 345 1753",
    "sg:postcode":"89523",
    "sg:province":"NV",
    "sg:tags":[
        "hanging",
        "contractor"
    ],
    "wof:name":"Elite Custom Painting",
    "wof:placetype":"venue"
},
  "geometry": {"coordinates":[-119.924328,39.521033],"type":"Point"}
}