{
  "type": "Feature",
  "properties": {
    "iso:country":"US",
    "sg:address":"8987 Lillyhammer Ct",
    "sg:city":"Las Vegas",
    "sg:classifiers":[
        {
            "category":"Professional",
            "subcategory":"Business Services",
            "type":"Services"
        }
    ],
    "sg:phone":"+1 702 251 8283",
    "sg:postcode":"89147",
    "sg:province":"NV",
    "wof:name":"Center City Enterprises",
    "wof:placetype":"venue"
},
  "geometry": {"coordinates":[-115.287626,36.103919],"type":"Point"}
}