{
  "type": "Feature",
  "properties": {
    "iso:country":"US",
    "sg:address":"5108 Sparkling Dr",
    "sg:city":"Las Vegas",
    "sg:classifiers":[
        {
            "category":"Professional",
            "subcategory":"Business Services",
            "type":"Services"
        }
    ],
    "sg:phone":"+1 702 433 9934",
    "sg:postcode":"89130",
    "sg:province":"NV",
    "sg:tags":[
        "water",
        "conditioning",
        "treatment"
    ],
    "wof:name":"Bg Aquasoft Inc",
    "wof:placetype":"venue"
},
  "geometry": {"coordinates":[-115.208104,36.252271],"type":"Point"}
}