{
  "type": "Feature",
  "properties": {
    "iso:country":"US",
    "sg:address":"316 N 8th St",
    "sg:city":"Las Vegas",
    "sg:classifiers":[
        {
            "category":"Building & Trades",
            "subcategory":"Construction",
            "type":"Services"
        }
    ],
    "sg:phone":"+1 702 743 7080",
    "sg:postcode":"89101",
    "sg:province":"NV",
    "sg:tags":[
        "handyman"
    ],
    "wof:name":"Handy Magoos",
    "wof:placetype":"venue"
},
  "geometry": {"coordinates":[-115.135082,36.171081],"type":"Point"}
}