{
  "type": "Feature",
  "properties": {
    "iso:country":"US",
    "sg:address":"2511 Whippoorwill Ln",
    "sg:city":"Las Vegas",
    "sg:classifiers":[
        {
            "category":"Professional",
            "type":"Services"
        }
    ],
    "sg:phone":"+1 702 871 5242",
    "sg:postcode":"89121",
    "sg:province":"NV",
    "wof:name":"Textel Inc",
    "wof:placetype":"venue"
},
  "geometry": {"coordinates":[-115.11667199999999,36.112129],"type":"Point"}
}