{
  "type": "Feature",
  "properties": {
    "iso:country":"US",
    "sg:address":"3373 Pepper Ln",
    "sg:city":"Las Vegas",
    "sg:classifiers":[
        {
            "category":"Professional",
            "type":"Services"
        }
    ],
    "sg:phone":"+1 702 434 5506",
    "sg:postcode":"89120",
    "sg:province":"NV",
    "sg:tags":[
        "establishment"
    ],
    "wof:name":"V & G Enterprises Inc",
    "wof:placetype":"venue"
},
  "geometry": {"coordinates":[-115.101159,36.076185],"type":"Point"}
}