{
  "type": "Feature",
  "properties": {
    "iso:country":"US",
    "sg:address":"1771 E Flamingo Rd",
    "sg:city":"Las Vegas",
    "sg:classifiers":[
        {
            "category":"Banks & Credit Unions",
            "subcategory":"Bank",
            "type":"Services"
        }
    ],
    "sg:phone":"+1 702 796 5445",
    "sg:postcode":"89119",
    "sg:province":"NV",
    "sg:tags":[
        "lending",
        "consumer",
        "company"
    ],
    "wof:name":"Citifinancial Mortgage Company",
    "wof:placetype":"venue"
},
  "geometry": {"coordinates":[-115.130906,36.114523],"type":"Point"}
}