{
  "type": "Feature",
  "properties": {
    "iso:country":"US",
    "sg:address":"6901 E Lake Mead Blvd",
    "sg:city":"Las Vegas",
    "sg:classifiers":[
        {
            "category":"Utilities",
            "subcategory":"Telephone",
            "type":"Services"
        }
    ],
    "sg:phone":"+1 702 459 2031",
    "sg:postcode":"89156",
    "sg:province":"NV",
    "sg:tags":[
        "communications"
    ],
    "wof:name":"Inascent",
    "wof:placetype":"venue"
},
  "geometry": {"coordinates":[-115.017534,36.197939],"type":"Point"}
}