{
  "type": "Feature",
  "properties": {
    "iso:country":"US",
    "sg:address":"3894 Spring Mountain Rd",
    "sg:city":"Las Vegas",
    "sg:classifiers":[
        {
            "category":"Retail",
            "subcategory":"Repair Shop",
            "type":"Services"
        }
    ],
    "sg:phone":"+1 702 368 1848",
    "sg:postcode":"89102",
    "sg:province":"NV",
    "wof:name":"Great Basin Taxidermy",
    "wof:placetype":"venue"
},
  "geometry": {"coordinates":[-115.193314,36.126502],"type":"Point"}
}