{
  "type": "Feature",
  "properties": {
    "iso:country":"US",
    "sg:address":"2202 E Charleston Blvd",
    "sg:city":"Las Vegas",
    "sg:classifiers":[
        {
            "category":"Banks & Credit Unions",
            "subcategory":"Bank",
            "type":"Services"
        }
    ],
    "sg:phone":"+1 702 384 6622",
    "sg:postcode":"89104",
    "sg:province":"NV",
    "sg:tags":[
        "automobile",
        "loan",
        "title"
    ],
    "wof:name":"Cashworks",
    "wof:placetype":"venue"
},
  "geometry": {"coordinates":[-115.117115,36.158752],"type":"Point"}
}