{
  "type": "Feature",
  "properties": {
    "iso:country":"US",
    "sg:address":"6140 N Hollywood Blvd Ste 102",
    "sg:city":"Las Vegas",
    "sg:classifiers":[
        {
            "category":"Home & Garden",
            "subcategory":"Furniture",
            "type":"Retail Goods"
        }
    ],
    "sg:phone":"+1 702 643 2595",
    "sg:postcode":"89115",
    "sg:province":"NV",
    "sg:tags":[
        "store"
    ],
    "sg:website":"www.gistdecor.com",
    "wof:name":"Gist Decor",
    "wof:placetype":"venue"
},
  "geometry": {"coordinates":[-115.024821,36.272697],"type":"Point"}
}