{
  "type": "Feature",
  "properties": {
    "iso:country":"US",
    "sg:address":"500 W Owens Ave",
    "sg:city":"Las Vegas",
    "sg:classifiers":[
        {
            "category":"Social Services",
            "type":"Services"
        }
    ],
    "sg:phone":"+1 702 638 0570",
    "sg:postcode":"89106",
    "sg:province":"NV",
    "wof:name":"REM Service",
    "wof:placetype":"venue"
},
  "geometry": {"coordinates":[-115.14951499999999,36.18846],"type":"Point"}
}