{
  "type": "Feature",
  "properties": {
    "iso:country":"US",
    "sg:address":"1620 S Decatur Blvd",
    "sg:city":"Las Vegas",
    "sg:classifiers":[
        {
            "category":"Personal",
            "subcategory":"Beauty Salon",
            "type":"Services"
        }
    ],
    "sg:phone":"+1 702 336 1865",
    "sg:postcode":"89102",
    "sg:province":"NV",
    "wof:name":"Colorz By Linzi",
    "wof:placetype":"venue"
},
  "geometry": {"coordinates":[-115.208196,36.152118],"type":"Point"}
}