{
  "type": "Feature",
  "properties": {
    "iso:country":"US",
    "sg:address":"1631 N Decatur Blvd",
    "sg:city":"Las Vegas",
    "sg:classifiers":[
        {
            "category":"Bars & Pubs",
            "type":"Food & Drink"
        }
    ],
    "sg:phone":"+1 702 647 1178",
    "sg:postcode":"89108",
    "sg:province":"NV",
    "wof:name":"Andy Capz Pub",
    "wof:placetype":"venue"
},
  "geometry": {"coordinates":[-115.206108,36.19232],"type":"Point"}
}