{
  "type": "Feature",
  "properties": {
    "iso:country":"US",
    "sg:address":"808 Lacey Tree St",
    "sg:city":"Las Vegas",
    "sg:classifiers":[
        {
            "category":"Home & Garden",
            "subcategory":"Furniture",
            "type":"Retail Goods"
        }
    ],
    "sg:phone":"+1 702 270 3340",
    "sg:postcode":"89145",
    "sg:province":"NV",
    "wof:name":"Park Depot",
    "wof:placetype":"venue"
},
  "geometry": {"coordinates":[-115.305053,36.161821],"type":"Point"}
}