{
  "type": "Feature",
  "properties": {
    "iso:country":"US",
    "sg:address":"3720 W Tropicana Ave",
    "sg:city":"Las Vegas",
    "sg:classifiers":[
        {
            "category":"Manufacturing",
            "subcategory":"Food",
            "type":"Manufacturing & Wholesale Goods"
        }
    ],
    "sg:phone":"+1 702 362 9280",
    "sg:postcode":"89103",
    "sg:province":"NV",
    "sg:tags":[
        "bakery",
        "prod",
        "cookie"
    ],
    "sg:website":"www.saycheesecake.com",
    "wof:name":"Say Cheesecake Cafe & Bakery",
    "wof:placetype":"venue"
},
  "geometry": {"coordinates":[-115.188608,36.10084],"type":"Point"}
}