{
  "type": "Feature",
  "properties": {
    "iso:country":"US",
    "sg:address":"830 Lyman Ave",
    "sg:city":"Reno",
    "sg:classifiers":[
        {
            "category":"Professional",
            "subcategory":"Art Services",
            "type":"Services"
        }
    ],
    "sg:phone":"+1 775 322 7577",
    "sg:postcode":"89509",
    "sg:province":"NV",
    "sg:tags":[
        "commercial",
        "design"
    ],
    "wof:name":"Trakker Design Research",
    "wof:placetype":"venue"
},
  "geometry": {"coordinates":[-119.844303,39.512006],"type":"Point"}
}