{
  "type": "Feature",
  "properties": {
    "iso:country":"US",
    "sg:address":"1096 E Sahara Ave",
    "sg:city":"Las Vegas",
    "sg:classifiers":[
        {
            "category":"Personal",
            "subcategory":"Beauty Salon",
            "type":"Services"
        }
    ],
    "sg:phone":"+1 702 732 8500",
    "sg:postcode":"89104",
    "sg:province":"NV",
    "sg:tags":[
        "shop"
    ],
    "wof:name":"Champagnes Beauty Boutique",
    "wof:placetype":"venue"
},
  "geometry": {"coordinates":[-115.139712,36.144211],"type":"Point"}
}