{
  "type": "Feature",
  "properties": {
    "iso:country":"US",
    "sg:address":"7531 W Lake Mead Blvd",
    "sg:city":"Las Vegas",
    "sg:classifiers":[
        {
            "category":"Shopping",
            "subcategory":"Mobile Phones",
            "type":"Retail Goods"
        }
    ],
    "sg:phone":"+1 702 227 4000",
    "sg:postcode":"89128",
    "sg:province":"NV",
    "sg:website":"www.bellsouth.com",
    "wof:name":"AT&T",
    "wof:placetype":"venue"
},
  "geometry": {"coordinates":[-115.257794,36.195893],"type":"Point"}
}