{
  "type": "Feature",
  "properties": {
    "iso:country":"US",
    "sg:address":"1982 N Rainbow Blvd",
    "sg:city":"Las Vegas",
    "sg:classifiers":[
        {
            "category":"Building & Trades",
            "subcategory":"Landscaping Services",
            "type":"Services"
        }
    ],
    "sg:phone":"+1 702 658 3455",
    "sg:postcode":"89108",
    "sg:province":"NV",
    "sg:tags":[
        "landscape",
        "contractor"
    ],
    "wof:name":"Bridon Landscaping Inc",
    "wof:placetype":"venue"
},
  "geometry": {"coordinates":[-115.24220699999999,36.193213],"type":"Point"}
}