{
  "type": "Feature",
  "properties": {
    "iso:country":"US",
    "sg:address":"8636 Castle Hill Ave",
    "sg:city":"Las Vegas",
    "sg:classifiers":[
        {
            "category":"Shopping",
            "subcategory":"Clothing, Apparel, & Fashions",
            "type":"Retail Goods"
        }
    ],
    "sg:phone":"+1 702 804 8005",
    "sg:postcode":"89129",
    "sg:province":"NV",
    "sg:tags":[
        "t"
    ],
    "wof:name":"Morgan Specialties",
    "wof:placetype":"venue"
},
  "geometry": {"coordinates":[-115.287058,36.232482],"type":"Point"}
}