{
  "type": "Feature",
  "properties": {
    "iso:country":"US",
    "sg:address":"4116 W Craig Road Suite 104",
    "sg:city":"North Las Vegas",
    "sg:classifiers":[
        {
            "category":"Health Services",
            "subcategory":"Optometrist",
            "type":"Services"
        }
    ],
    "sg:phone":"+1 702 631 2015",
    "sg:postcode":"89032",
    "sg:province":"NV",
    "sg:website":"www.desertvisioneyecare.com/",
    "wof:name":"Desert Vision & Eye Care",
    "wof:placetype":"venue"
},
  "geometry": {"coordinates":[-115.19594,36.239293],"type":"Point"}
}