{
  "type": "Feature",
  "properties": {
    "iso:country":"US",
    "sg:address":"250 E 4th St",
    "sg:city":"Battle Mountain",
    "sg:classifiers":[
        {
            "category":"Sports & Exercise",
            "subcategory":"Gym",
            "type":"Entertainment"
        }
    ],
    "sg:phone":"+1 775 635 3162",
    "sg:postcode":"89820",
    "sg:province":"NV",
    "sg:tags":[
        "fitness"
    ],
    "wof:name":"No Mercy Fitness",
    "wof:placetype":"venue"
},
  "geometry": {"coordinates":[-116.935092,40.638282],"type":"Point"}
}