{
  "type": "Feature",
  "properties": {
    "iso:country":"US",
    "sg:address":"6555 Lucky Boy Dr",
    "sg:city":"Las Vegas",
    "sg:classifiers":[
        {
            "category":"Organizations",
            "subcategory":"Religious Organization",
            "type":"Services"
        }
    ],
    "sg:phone":"+1 702 456 2979",
    "sg:postcode":"89110",
    "sg:province":"NV",
    "wof:name":"New Shiloh Baptist Church",
    "wof:placetype":"venue"
},
  "geometry": {"coordinates":[-115.030117,36.181762],"type":"Point"}
}