{
  "type": "Feature",
  "properties": {
    "iso:country":"US",
    "sg:address":"204 Marsh Ave",
    "sg:city":"Reno",
    "sg:classifiers":[
        {
            "category":"Insurance",
            "subcategory":"Insurance Agent",
            "type":"Services"
        }
    ],
    "sg:phone":"+1 775 322 3203",
    "sg:postcode":"89509",
    "sg:province":"NV",
    "wof:name":"Luckadoo Insurance",
    "wof:placetype":"venue"
},
  "geometry": {"coordinates":[-119.813972,39.518974],"type":"Point"}
}