{
  "type": "Feature",
  "properties": {
    "iso:country":"US",
    "sg:address":"6475 S Rainbow Blvd Ste 100",
    "sg:city":"Las Vegas",
    "sg:classifiers":[
        {
            "category":"Juice Bar",
            "subcategory":"None",
            "type":"Food & Drink"
        }
    ],
    "sg:phone":"+1 702 222 9922",
    "sg:postcode":"89118",
    "sg:province":"NV",
    "sg:tags":[
        "smoothy"
    ],
    "sg:website":"www.melonslasvegas.com",
    "wof:name":"Melons Smoothies",
    "wof:placetype":"venue"
},
  "geometry": {"coordinates":[-115.242967,36.071212],"type":"Point"}
}