{
  "type": "Feature",
  "properties": {
    "iso:country":"US",
    "sg:address":"116 E 7th St",
    "sg:city":"Carson City",
    "sg:classifiers":[
        {
            "category":"Social Services",
            "type":"Services"
        }
    ],
    "sg:phone":"+1 775 883 2982",
    "sg:postcode":"89701",
    "sg:province":"NV",
    "wof:name":"Patricia H Elliott Lcsw Cdac",
    "wof:placetype":"venue"
},
  "geometry": {"coordinates":[-119.76625199999999,39.160061],"type":"Point"}
}