{
  "type": "Feature",
  "properties": {
    "iso:country":"US",
    "sg:address":"6431 Tina Ln",
    "sg:city":"Las Vegas",
    "sg:classifiers":[
        {
            "category":"Manufacturing",
            "subcategory":"Signs",
            "type":"Manufacturing & Wholesale Goods"
        }
    ],
    "sg:phone":"+1 702 645 7782",
    "sg:postcode":"89130",
    "sg:province":"NV",
    "sg:tags":[
        "specialty",
        "mfg"
    ],
    "wof:name":"Master Signs",
    "wof:placetype":"venue"
},
  "geometry": {"coordinates":[-115.235094,36.260457],"type":"Point"}
}