{
  "type": "Feature",
  "properties": {
    "iso:country":"US",
    "sg:address":"7176 Cressida Ct",
    "sg:city":"Las Vegas",
    "sg:classifiers":[
        {
            "category":"Manufacturing",
            "subcategory":"Retail Goods",
            "type":"Manufacturing & Wholesale Goods"
        }
    ],
    "sg:phone":"+1 702 227 9978",
    "sg:postcode":"89113",
    "sg:province":"NV",
    "sg:tags":[
        "beads",
        "jewelry",
        "mfg"
    ],
    "wof:name":"Jlm Beads & Jewelry",
    "wof:placetype":"venue"
},
  "geometry": {"coordinates":[-115.248214,36.078315],"type":"Point"}
}