{
  "type": "Feature",
  "properties": {
    "iso:country":"US",
    "sg:address":"2134 Dickerson Rd",
    "sg:city":"Reno",
    "sg:classifiers":[
        {
            "category":"Manufacturing",
            "subcategory":"Printing",
            "type":"Manufacturing & Wholesale Goods"
        }
    ],
    "sg:phone":"+1 775 786 5552",
    "sg:postcode":"89503",
    "sg:province":"NV",
    "sg:tags":[
        "commercial",
        "mfg"
    ],
    "wof:name":"Sierra Enterprises",
    "wof:placetype":"venue"
},
  "geometry": {"coordinates":[-119.836893,39.522532],"type":"Point"}
}