{
  "type": "Feature",
  "properties": {
    "iso:country":"US",
    "sg:address":"6220 S. Rainbow Blvd.",
    "sg:city":"Las Vegas",
    "sg:classifiers":[
        {
            "category":"Travel",
            "subcategory":"Hotels & Motels",
            "type":"Entertainment"
        },
        {
            "category":"Retail",
            "subcategory":"Event Space",
            "type":"Services"
        }
    ],
    "sg:phone":"+1 702 871 4453",
    "sg:postcode":"89118",
    "sg:province":"NV",
    "sg:tags":[
        "venue"
    ],
    "sg:website":"www.holidayinnexpress.com",
    "wof:name":"Holiday Inn Express Hotel Las Vegas I-215 S. Beltway",
    "wof:placetype":"venue"
},
  "geometry": {"coordinates":[-115.241787,36.075616],"type":"Point"}
}