{
  "type": "Feature",
  "properties": {
    "iso:country":"US",
    "sg:address":"McCarran International Airport",
    "sg:city":"Las Vegas",
    "sg:classifiers":[
        {
            "category":"Restaurant",
            "type":"Food & Drink"
        }
    ],
    "sg:postcode":"89119",
    "sg:province":"NV",
    "wof:name":"Burke in the Box",
    "wof:placetype":"venue"
},
  "geometry": {"coordinates":[-115.14594,36.08685],"type":"Point"}
}