{
  "type": "Feature",
  "properties": {
    "iso:country":"US",
    "sg:address":"1914 Victorian Ave",
    "sg:city":"Sparks",
    "sg:classifiers":[
        {
            "category":"Autos & Motor Vehicles",
            "subcategory":"Automobile Sales",
            "type":"Retail Goods"
        }
    ],
    "sg:phone":"+1 775 331 8477",
    "sg:postcode":"89431",
    "sg:province":"NV",
    "sg:tags":[
        "car",
        "dealer"
    ],
    "wof:name":"Churchill's Auto Sales",
    "wof:placetype":"venue"
},
  "geometry": {"coordinates":[-119.770261,39.535335],"type":"Point"}
}