{
  "type": "Feature",
  "properties": {
    "iso:country":"US",
    "sg:address":"27 Linwood Pl",
    "sg:city":"Reno",
    "sg:classifiers":[
        {
            "category":"Restaurant",
            "type":"Food & Drink"
        }
    ],
    "sg:phone":"+1 775 323 8080",
    "sg:postcode":"89509",
    "sg:province":"NV",
    "wof:name":"Domino's Pizza",
    "wof:placetype":"venue"
},
  "geometry": {"coordinates":[-119.82046699999999,39.509871],"type":"Point"}
}