{
  "type": "Feature",
  "properties": {
    "iso:country":"US",
    "sg:address":"1103 N Nevada St",
    "sg:city":"Carson City",
    "sg:classifiers":[
        {
            "category":"Professional",
            "subcategory":"Engineering",
            "type":"Services"
        }
    ],
    "sg:phone":"+1 775 882 5147",
    "sg:postcode":"89703",
    "sg:province":"NV",
    "wof:name":"Wayne H Reid",
    "wof:placetype":"venue"
},
  "geometry": {"coordinates":[-119.76853300000001,39.170468],"type":"Point"}
}