{
  "type": "Feature",
  "properties": {
    "iso:country":"US",
    "sg:address":"4444 W Russell Rd",
    "sg:city":"Las Vegas",
    "sg:classifiers":[
        {
            "category":"Building & Trades",
            "subcategory":"Construction",
            "type":"Services"
        }
    ],
    "sg:phone":"+1 702 253 1163",
    "sg:postcode":"89118",
    "sg:province":"NV",
    "sg:tags":[
        "builder",
        "stair"
    ],
    "wof:name":"Titan Stairs LTD",
    "wof:placetype":"venue"
},
  "geometry": {"coordinates":[-115.200588,36.086408],"type":"Point"}
}