{
  "type": "Feature",
  "properties": {
    "iso:country":"US",
    "sg:address":"3834 Vanessa Dr",
    "sg:city":"Las Vegas",
    "sg:classifiers":[
        {
            "category":"Manufacturing",
            "subcategory":"Metals",
            "type":"Manufacturing & Wholesale Goods"
        }
    ],
    "sg:phone":"+1 702 869 0755",
    "sg:postcode":"89103",
    "sg:province":"NV",
    "sg:tags":[
        "steel"
    ],
    "wof:name":"Cable Grippers Inc",
    "wof:placetype":"venue"
},
  "geometry": {"coordinates":[-115.194274,36.125291],"type":"Point"}
}