{
  "type": "Feature",
  "properties": {
    "iso:country":"US",
    "sg:address":"222 Ring Rd",
    "sg:city":"Dayton",
    "sg:classifiers":[
        {
            "category":"Professional",
            "subcategory":"Art Services",
            "type":"Services"
        }
    ],
    "sg:phone":"+1 775 246 7356",
    "sg:postcode":"89403",
    "sg:province":"NV",
    "sg:tags":[
        "graphic",
        "designer"
    ],
    "wof:name":"Martinez Custom Silk Screening",
    "wof:placetype":"venue"
},
  "geometry": {"coordinates":[-119.531681,39.301825],"type":"Point"}
}