{
  "type": "Feature",
  "properties": {
    "iso:country":"US",
    "sg:address":"2023 E Charleston Blvd",
    "sg:city":"Las Vegas",
    "sg:classifiers":[
        {
            "category":"Shopping",
            "subcategory":"Gifts & Souvenirs",
            "type":"Retail Goods"
        }
    ],
    "sg:phone":"+1 702 382 6074",
    "sg:postcode":"89104",
    "sg:province":"NV",
    "sg:tags":[
        "merchandise"
    ],
    "wof:name":"Azteca 2000",
    "wof:placetype":"venue"
},
  "geometry": {"coordinates":[-115.119386,36.158926],"type":"Point"}
}