{
  "type": "Feature",
  "properties": {
    "iso:country":"US",
    "sg:address":"3505 E Flamingo Road",
    "sg:city":"Las Vegas",
    "sg:classifiers":[
        {
            "category":"Education",
            "subcategory":"School",
            "type":"Public Place"
        }
    ],
    "sg:phone":"+1 702 794 2537",
    "sg:postcode":"89121",
    "sg:province":"NV",
    "wof:name":"Education Support Employees Association",
    "wof:placetype":"venue"
},
  "geometry": {"coordinates":[-115.098258,36.115156],"type":"Point"}
}