{
  "type": "Feature",
  "properties": {
    "iso:country":"US",
    "sg:address":"2713 Willoughby Ave",
    "sg:city":"Las Vegas",
    "sg:classifiers":[
        {
            "category":"Professional",
            "subcategory":"Business Services",
            "type":"Services"
        }
    ],
    "sg:phone":"+1 702 649 2431",
    "sg:postcode":"89101",
    "sg:province":"NV",
    "sg:tags":[
        "painter",
        "sign"
    ],
    "wof:name":"Southern Nevada Signs",
    "wof:placetype":"venue"
},
  "geometry": {"coordinates":[-115.114347,36.179776],"type":"Point"}
}