{
  "type": "Feature",
  "properties": {
    "iso:country":"US",
    "sg:address":"1279 Clover Ave",
    "sg:city":"Wells",
    "sg:classifiers":[
        {
            "category":"Government",
            "subcategory":"Office",
            "type":"Public Place"
        }
    ],
    "sg:phone":"+1 775 752 3120",
    "sg:postcode":"89835",
    "sg:province":"NV",
    "sg:tags":[
        "village"
    ],
    "wof:name":"Wells City Clerk's Office",
    "wof:placetype":"venue"
},
  "geometry": {"coordinates":[-114.96698600000001,41.108117],"type":"Point"}
}