{
  "type": "Feature",
  "properties": {
    "iso:country":"US",
    "sg:address":"8395 W Sunset Rd",
    "sg:city":"Las Vegas",
    "sg:classifiers":[
        {
            "category":"Banks & Credit Unions",
            "subcategory":"Bank",
            "type":"Services"
        }
    ],
    "sg:phone":"+1 702 791 4777",
    "sg:postcode":"89113",
    "sg:province":"NV",
    "wof:name":"Weststar Credit Union",
    "wof:placetype":"venue"
},
  "geometry": {"coordinates":[-115.26115799999999,36.070198],"type":"Point"}
}