{
  "type": "Feature",
  "properties": {
    "iso:country":"US",
    "sg:address":"1755 Plumb Ln",
    "sg:city":"Reno",
    "sg:classifiers":[
        {
            "category":"Professional",
            "subcategory":"Accounting & Tax Preparation",
            "type":"Services"
        }
    ],
    "sg:phone":"+1 775 746 1500",
    "sg:postcode":"89502",
    "sg:province":"NV",
    "sg:tags":[
        "billing"
    ],
    "wof:name":"Medical Billing Inc",
    "wof:placetype":"venue"
},
  "geometry": {"coordinates":[-119.778177,39.505941],"type":"Point"}
}