{
  "type": "Feature",
  "properties": {
    "iso:country":"US",
    "sg:address":"5222 Sawyer Ave",
    "sg:city":"Las Vegas",
    "sg:classifiers":[
        {
            "category":"Manufacturing",
            "subcategory":"Chemicals & Compounds",
            "type":"Manufacturing & Wholesale Goods"
        }
    ],
    "sg:phone":"+1 702 647 0189",
    "sg:postcode":"89108",
    "sg:province":"NV",
    "sg:tags":[
        "mfg",
        "printing",
        "ink"
    ],
    "wof:name":"Brookwood Ink",
    "wof:placetype":"venue"
},
  "geometry": {"coordinates":[-115.21384,36.196916],"type":"Point"}
}