{
  "type": "Feature",
  "properties": {
    "iso:country":"US",
    "sg:address":"7321 W Charleston Boulevard",
    "sg:city":"Las Vegas",
    "sg:classifiers":[
        {
            "category":"Professional",
            "subcategory":"Lawyer & Legal Services",
            "type":"Services"
        }
    ],
    "sg:phone":"+1 702 877 1846",
    "sg:postcode":"89117",
    "sg:province":"NV",
    "wof:name":"Light Erin Elizabeth ESQ",
    "wof:placetype":"venue"
},
  "geometry": {"coordinates":[-115.25255799999999,36.159025],"type":"Point"}
}