{
  "type": "Feature",
  "properties": {
    "iso:country":"US",
    "sg:address":"700 Reservoir Rd",
    "sg:city":"Lovelock",
    "sg:classifiers":[
        {
            "category":"Organizations",
            "subcategory":"Religious Organization",
            "type":"Services"
        }
    ],
    "sg:phone":"+1 775 273 7327",
    "sg:postcode":"89419",
    "sg:province":"NV",
    "sg:tags":[
        "church"
    ],
    "wof:name":"Big Meadow Bible Church",
    "wof:placetype":"venue"
},
  "geometry": {"coordinates":[-118.436712,40.19613],"type":"Point"}
}