{
  "type": "Feature",
  "properties": {
    "iso:country":"US",
    "sg:address":"8209 Cactus Canyon Ct",
    "sg:city":"Las Vegas",
    "sg:classifiers":[
        {
            "category":"Shopping",
            "subcategory":"Jewelry",
            "type":"Retail Goods"
        }
    ],
    "sg:phone":"+1 702 658 8400",
    "sg:postcode":"89128",
    "sg:province":"NV",
    "wof:name":"Aynv Fine Jewelry",
    "wof:placetype":"venue"
},
  "geometry": {"coordinates":[-115.273248,36.190272],"type":"Point"}
}