{
  "type": "Feature",
  "properties": {
    "iso:country":"US",
    "sg:address":"8848 Scenic Bay Dr",
    "sg:city":"Las Vegas",
    "sg:classifiers":[
        {
            "category":"Real Estate",
            "subcategory":"Real Estate Agent",
            "type":"Services"
        }
    ],
    "sg:phone":"+1 702 873 0440",
    "sg:postcode":"89117",
    "sg:province":"NV",
    "sg:tags":[
        "appraiser"
    ],
    "wof:name":"Scott D Vollmer",
    "wof:placetype":"venue"
},
  "geometry": {"coordinates":[-115.2848,36.127824],"type":"Point"}
}