{
  "type": "Feature",
  "properties": {
    "iso:country":"US",
    "sg:address":"3415 San Juan Dr",
    "sg:city":"Reno",
    "sg:classifiers":[
        {
            "category":"Professional",
            "subcategory":"Computer Services",
            "type":"Services"
        }
    ],
    "sg:phone":"+1 775 786 1366",
    "sg:postcode":"89509",
    "sg:province":"NV",
    "sg:tags":[
        "information",
        "retrieval"
    ],
    "wof:name":"Geospactial Reasoning Systems",
    "wof:placetype":"venue"
},
  "geometry": {"coordinates":[-119.842687,39.487765],"type":"Point"}
}