{
  "type": "Feature",
  "properties": {
    "iso:country":"US",
    "sg:address":"3525 W Craig Rd",
    "sg:city":"North Las Vegas",
    "sg:classifiers":[
        {
            "category":"Social Services",
            "subcategory":"Adult Care",
            "type":"Services"
        }
    ],
    "sg:phone":"+1 702 501 5144",
    "sg:postcode":"89032",
    "sg:province":"NV",
    "sg:tags":[
        "home",
        "residential"
    ],
    "wof:name":"Elder Care Referral Svc",
    "wof:placetype":"venue"
},
  "geometry": {"coordinates":[-115.189251,36.239336],"type":"Point"}
}