{
  "type": "Feature",
  "properties": {
    "iso:country":"US",
    "sg:address":"290 Gentry Way",
    "sg:city":"Reno",
    "sg:classifiers":[
        {
            "category":"Mining & Drilling",
            "type":"Manufacturing & Wholesale Goods"
        }
    ],
    "sg:phone":"+1 775 824 0707",
    "sg:postcode":"89502",
    "sg:province":"NV",
    "sg:tags":[
        "company",
        "metal"
    ],
    "wof:name":"Bonanza Explorations Inc",
    "wof:placetype":"venue"
},
  "geometry": {"coordinates":[-119.79485,39.494816],"type":"Point"}
}