{
  "type": "Feature",
  "properties": {
    "iso:country":"US",
    "sg:address":"701 Elm St",
    "sg:city":"Boulder City",
    "sg:classifiers":[
        {
            "category":"Real Estate",
            "subcategory":"Real Estate Operator",
            "type":"Services"
        }
    ],
    "sg:phone":"+1 702 293 2537",
    "sg:postcode":"89005",
    "sg:province":"NV",
    "sg:tags":[
        "mobile",
        "home",
        "community"
    ],
    "wof:name":"Moore's Mobile Home Park",
    "wof:placetype":"venue"
},
  "geometry": {"coordinates":[-114.843149,35.973111],"type":"Point"}
}