{
  "type": "Feature",
  "properties": {
    "iso:country":"US",
    "sg:address":"4180 S Pecos Rd",
    "sg:city":"Las Vegas",
    "sg:classifiers":[
        {
            "category":"Wholesale",
            "subcategory":"Durable Goods & Equipment",
            "type":"Manufacturing & Wholesale Goods"
        }
    ],
    "sg:phone":"+1 702 730 0001",
    "sg:postcode":"89121",
    "sg:province":"NV",
    "sg:tags":[
        "importer"
    ],
    "wof:name":"KBM Trading Intl Corp",
    "wof:placetype":"venue"
},
  "geometry": {"coordinates":[-115.100791,36.11426],"type":"Point"}
}