{
  "type": "Feature",
  "properties": {
    "iso:country":"US",
    "sg:address":"551 California Ave",
    "sg:city":"Reno",
    "sg:classifiers":[
        {
            "category":"Social Services",
            "subcategory":"Child Care",
            "type":"Services"
        }
    ],
    "sg:phone":"+1 775 786 1669",
    "sg:postcode":"89509",
    "sg:province":"NV",
    "sg:tags":[
        "day"
    ],
    "wof:name":"Little Learners",
    "wof:placetype":"venue"
},
  "geometry": {"coordinates":[-119.82004499999999,39.520033],"type":"Point"}
}