{
  "type": "Feature",
  "properties": {
    "iso:country":"US",
    "sg:address":"8935 S Pecos Rd",
    "sg:city":"Henderson",
    "sg:classifiers":[
        {
            "category":"Health Services",
            "subcategory":"Chiropractor",
            "type":"Services"
        }
    ],
    "sg:phone":"+1 702 948 2520",
    "sg:postcode":"89074",
    "sg:province":"NV",
    "sg:website":"www.lasvegaspainrelief.com",
    "wof:name":"Las Vegas Pain Relief Center",
    "wof:placetype":"venue"
},
  "geometry": {"coordinates":[-115.100723,36.026676],"type":"Point"}
}