{
  "type": "Feature",
  "properties": {
    "iso:country":"US",
    "sg:address":"205 N McCarran Blvd",
    "sg:city":"Sparks",
    "sg:classifiers":[
        {
            "category":"Banks & Credit Unions",
            "subcategory":"Bank",
            "type":"Services"
        }
    ],
    "sg:phone":"+1 775 358 1113",
    "sg:postcode":"89431",
    "sg:province":"NV",
    "sg:tags":[
        "cashing",
        "check"
    ],
    "wof:name":"All American Auto Title Loan",
    "wof:placetype":"venue"
},
  "geometry": {"coordinates":[-119.737368,39.535106],"type":"Point"}
}