{
  "type": "Feature",
  "properties": {
    "iso:country":"US",
    "sg:address":"2501 W 4th St",
    "sg:city":"Reno",
    "sg:classifiers":[
        {
            "category":"Restaurant",
            "type":"Food & Drink"
        }
    ],
    "sg:phone":"+1 775 323 3979",
    "sg:postcode":"89523",
    "sg:province":"NV",
    "wof:name":"Casale's Half Way Club",
    "wof:placetype":"venue"
},
  "geometry": {"coordinates":[-119.846033,39.520236],"type":"Point"}
}