{
  "type": "Feature",
  "properties": {
    "iso:country":"US",
    "sg:address":"9433 Teaberry Ct",
    "sg:city":"Las Vegas",
    "sg:classifiers":[
        {
            "category":"Shopping",
            "type":"Retail Goods"
        }
    ],
    "sg:phone":"+1 702 255 9994",
    "sg:postcode":"89129",
    "sg:province":"NV",
    "sg:tags":[
        "candle"
    ],
    "wof:name":"Unlimited Secents",
    "wof:placetype":"venue"
},
  "geometry": {"coordinates":[-115.301725,36.232971],"type":"Point"}
}