{
  "type": "Feature",
  "properties": {
    "iso:country":"US",
    "sg:address":"295 Gentry Way",
    "sg:city":"Reno",
    "sg:classifiers":[
        {
            "category":"Building & Trades",
            "subcategory":"Cleaning & Sanitation",
            "type":"Services"
        }
    ],
    "sg:phone":"+1 775 826 0899",
    "sg:postcode":"89502",
    "sg:province":"NV",
    "sg:tags":[
        "help",
        "maintenance",
        "supply"
    ],
    "wof:name":"Three Amigos",
    "wof:placetype":"venue"
},
  "geometry": {"coordinates":[-119.794909,39.494966],"type":"Point"}
}