{
  "type": "Feature",
  "properties": {
    "iso:country":"US",
    "sg:address":"4700 S Maryland Pkwy",
    "sg:city":"Las Vegas",
    "sg:classifiers":[
        {
            "category":"Professional",
            "type":"Services"
        }
    ],
    "sg:phone":"+1 702 256 4715",
    "sg:postcode":"89119",
    "sg:province":"NV",
    "wof:name":"Rosie Inc",
    "wof:placetype":"venue"
},
  "geometry": {"coordinates":[-115.13715,36.105659],"type":"Point"}
}