{
  "type": "Feature",
  "properties": {
    "iso:country":"US",
    "sg:address":"7400 Las Vegas Blvd S",
    "sg:city":"Las Vegas",
    "sg:classifiers":[
        {
            "category":"Shopping",
            "subcategory":"Tobacco",
            "type":"Retail Goods"
        }
    ],
    "sg:phone":"+1 702 361 9887",
    "sg:postcode":"89123",
    "sg:province":"NV",
    "sg:tags":[
        "cigarette",
        "cigar",
        "dealer"
    ],
    "wof:name":"Gift Corner",
    "wof:placetype":"venue"
},
  "geometry": {"coordinates":[-115.172273,36.05511],"type":"Point"}
}