{
  "type": "Feature",
  "properties": {
    "iso:country":"US",
    "sg:address":"300 E Lake Mead Pkwy",
    "sg:city":"Henderson",
    "sg:classifiers":[
        {
            "category":"Health Services",
            "subcategory":"Optometrist",
            "type":"Services"
        }
    ],
    "sg:phone":"+1 702 565 4425",
    "sg:postcode":"89015",
    "sg:province":"NV",
    "wof:name":"Keller James L OD",
    "wof:placetype":"venue"
},
  "geometry": {"coordinates":[-114.977678,36.042461],"type":"Point"}
}