{
  "type": "Feature",
  "properties": {
    "iso:country":"US",
    "sg:address":"7998 Security Cir",
    "sg:city":"Reno",
    "sg:classifiers":[
        {
            "category":"Building & Trades",
            "subcategory":"Construction",
            "type":"Services"
        }
    ],
    "sg:phone":"+1 775 972 0881",
    "sg:postcode":"89506",
    "sg:province":"NV",
    "sg:tags":[
        "except",
        "elevated",
        "contractor",
        "street",
        "paving",
        "highway"
    ],
    "wof:name":"Kustom Koatings Inc",
    "wof:placetype":"venue"
},
  "geometry": {"coordinates":[-119.835664,39.59202],"type":"Point"}
}