{
  "type": "Feature",
  "properties": {
    "iso:country":"US",
    "sg:address":"1123 Ladera Dr",
    "sg:city":"Carson City",
    "sg:classifiers":[
        {
            "category":"Retail",
            "subcategory":"Repair Shop",
            "type":"Services"
        }
    ],
    "sg:phone":"+1 775 883 3727",
    "sg:postcode":"89701",
    "sg:province":"NV",
    "wof:name":"Taz Clean Up",
    "wof:placetype":"venue"
},
  "geometry": {"coordinates":[-119.72621,39.170345],"type":"Point"}
}