{
  "type": "Feature",
  "properties": {
    "iso:country":"US",
    "sg:address":"124 N Main St",
    "sg:city":"Yerington",
    "sg:classifiers":[
        {
            "category":"Social Services",
            "type":"Services"
        }
    ],
    "sg:phone":"+1 775 463 2334",
    "sg:postcode":"89447",
    "sg:province":"NV",
    "sg:tags":[
        "youth",
        "organization",
        "center"
    ],
    "wof:name":"Boys & Girl Club",
    "wof:placetype":"venue"
},
  "geometry": {"coordinates":[-119.16311,38.987134],"type":"Point"}
}