{
  "type": "Feature",
  "properties": {
    "iso:country":"US",
    "sg:address":"3380 E Flamingo Road",
    "sg:city":"Las Vegas",
    "sg:classifiers":[
        {
            "category":"Autos & Motor Vehicles",
            "subcategory":"Fuel & Gas Station",
            "type":"Retail Goods"
        }
    ],
    "sg:phone":"+1 702 456 0096",
    "sg:postcode":"89121",
    "sg:province":"NV",
    "sg:website":"www.texaco.com",
    "wof:name":"Flamingo Pecos Texaco",
    "wof:placetype":"venue"
},
  "geometry": {"coordinates":[-115.10147600000001,36.115197],"type":"Point"}
}