{
  "type": "Feature",
  "properties": {
    "iso:country":"US",
    "sg:address":"6435 S Valley View Blvd",
    "sg:city":"Las Vegas",
    "sg:classifiers":[
        {
            "category":"Wholesale",
            "subcategory":"Stationery",
            "type":"Manufacturing & Wholesale Goods"
        }
    ],
    "sg:phone":"+1 702 837 5500",
    "sg:postcode":"89118",
    "sg:province":"NV",
    "sg:tags":[
        "product",
        "paper"
    ],
    "wof:name":"Xpedx",
    "wof:placetype":"venue"
},
  "geometry": {"coordinates":[-115.19009699999999,36.072377],"type":"Point"}
}