{
  "type": "Feature",
  "properties": {
    "iso:country":"US",
    "sg:address":"2466 Ping Dr",
    "sg:city":"Henderson",
    "sg:classifiers":[
        {
            "category":"Professional",
            "type":"Services"
        }
    ],
    "sg:phone":"+1 702 914 0889",
    "sg:postcode":"89074",
    "sg:province":"NV",
    "sg:tags":[
        "establishment"
    ],
    "wof:name":"Mcu",
    "wof:placetype":"venue"
},
  "geometry": {"coordinates":[-115.09330799999999,36.037422],"type":"Point"}
}