{
  "type": "Feature",
  "properties": {
    "iso:country":"US",
    "sg:address":"2701 N Decatur Blvd",
    "sg:city":"Las Vegas",
    "sg:classifiers":[
        {
            "category":"Real Estate",
            "subcategory":"Real Estate Operator",
            "type":"Services"
        }
    ],
    "sg:phone":"+1 702 631 4422",
    "sg:postcode":"89108",
    "sg:province":"NV",
    "sg:tags":[
        "apartment"
    ],
    "wof:name":"Rancho Del Rey Apartments",
    "wof:placetype":"venue"
},
  "geometry": {"coordinates":[-115.205392,36.209773],"type":"Point"}
}