{
  "type": "Feature",
  "properties": {
    "iso:country":"US",
    "sg:address":"2408 Chapman Dr",
    "sg:city":"Las Vegas",
    "sg:classifiers":[
        {
            "category":"Professional",
            "subcategory":"Business Services",
            "type":"Services"
        }
    ],
    "sg:phone":"+1 702 731 2449",
    "sg:postcode":"89104",
    "sg:province":"NV",
    "sg:tags":[
        "advertising",
        "representative"
    ],
    "wof:name":"Creative Endeavors",
    "wof:placetype":"venue"
},
  "geometry": {"coordinates":[-115.131871,36.144388],"type":"Point"}
}