{
  "type": "Feature",
  "properties": {
    "iso:country":"US",
    "sg:address":"210 Front St",
    "sg:city":"Caliente",
    "sg:classifiers":[
        {
            "category":"Banks & Credit Unions",
            "subcategory":"Bank",
            "type":"Services"
        }
    ],
    "sg:phone":"+1 775 726 3135",
    "sg:postcode":"89008",
    "sg:province":"NV",
    "sg:tags":[
        "loan"
    ],
    "sg:website":"www.nevadabankandtrust.com",
    "wof:name":"Nevada Bank & Trust Co",
    "wof:placetype":"venue"
},
  "geometry": {"coordinates":[-114.51175600000001,37.614855],"type":"Point"}
}