{
  "type": "Feature",
  "properties": {
    "iso:country":"US",
    "sg:address":"7737 Edna Ave",
    "sg:city":"Las Vegas",
    "sg:classifiers":[
        {
            "category":"Professional",
            "subcategory":"Business Services",
            "type":"Services"
        }
    ],
    "sg:phone":"+1 702 364 5872",
    "sg:postcode":"89117",
    "sg:province":"NV",
    "wof:name":"Savien Marketing",
    "wof:placetype":"venue"
},
  "geometry": {"coordinates":[-115.260853,36.136352],"type":"Point"}
}