{
  "type": "Feature",
  "properties": {
    "iso:country":"US",
    "sg:address":"5483 Club House Dr",
    "sg:city":"Las Vegas",
    "sg:classifiers":[
        {
            "category":"Sports & Exercise",
            "subcategory":"Golf",
            "type":"Entertainment"
        }
    ],
    "sg:phone":"+1 702 431 4653",
    "sg:postcode":"89142",
    "sg:province":"NV",
    "sg:tags":[
        "course",
        "public"
    ],
    "sg:website":"www.americangolf.com",
    "wof:name":"Desert Rose Golf Course",
    "wof:placetype":"venue"
},
  "geometry": {"coordinates":[-115.055878,36.143612],"type":"Point"}
}