{
  "type": "Feature",
  "properties": {
    "iso:country":"US",
    "sg:address":"20 Hillcrest Dr",
    "sg:city":"Reno",
    "sg:classifiers":[
        {
            "category":"Shopping",
            "subcategory":"Used Merchandise",
            "type":"Retail Goods"
        }
    ],
    "sg:phone":"+1 775 829 8767",
    "sg:postcode":"89509",
    "sg:province":"NV",
    "sg:tags":[
        "resale",
        "shop"
    ],
    "wof:name":"Reno Replays Consignment Boutique",
    "wof:placetype":"venue"
},
  "geometry": {"coordinates":[-119.80304599999999,39.504675],"type":"Point"}
}