{
  "type": "Feature",
  "properties": {
    "iso:country":"US",
    "sg:address":"506 E Glendale Ave",
    "sg:city":"Sparks",
    "sg:classifiers":[
        {
            "category":"Manufacturing",
            "subcategory":"Textiles",
            "type":"Manufacturing & Wholesale Goods"
        }
    ],
    "sg:phone":"+1 775 359 6111",
    "sg:postcode":"89431",
    "sg:province":"NV",
    "sg:tags":[
        "finishing",
        "plant",
        "cotton"
    ],
    "wof:name":"Fireblankets Inc",
    "wof:placetype":"venue"
},
  "geometry": {"coordinates":[-119.733955,39.527317],"type":"Point"}
}