{
  "type": "Feature",
  "properties": {
    "iso:country":"US",
    "sg:address":"2588 Fire Mesa St Ste 140",
    "sg:city":"Las Vegas",
    "sg:classifiers":[
        {
            "category":"Professional",
            "subcategory":"Detective & Security Services",
            "type":"Services"
        }
    ],
    "sg:phone":"+1 800 617 0900",
    "sg:postcode":"89128",
    "sg:province":"NV",
    "sg:tags":[
        "system"
    ],
    "sg:website":"www.adt.com",
    "wof:name":"ADT Security Services, Inc.",
    "wof:placetype":"venue"
},
  "geometry": {"coordinates":[-115.257002,36.207871],"type":"Point"}
}