{
  "type": "Feature",
  "properties": {
    "iso:country":"US",
    "sg:address":"1701 N Green Valley Parkway",
    "sg:city":"Henderson",
    "sg:classifiers":[
        {
            "category":"Health Services",
            "subcategory":"Doctor",
            "type":"Services"
        }
    ],
    "sg:phone":"+1 702 563 0698",
    "sg:postcode":"89074",
    "sg:province":"NV",
    "wof:name":"Urology Ltd",
    "wof:placetype":"venue"
},
  "geometry": {"coordinates":[-115.084652,36.034575],"type":"Point"}
}