{
  "type": "Feature",
  "properties": {
    "iso:country":"US",
    "sg:address":"4516 W Charleston Blvd",
    "sg:city":"Las Vegas",
    "sg:classifiers":[
        {
            "category":"Shopping",
            "subcategory":"Jewelry",
            "type":"Retail Goods"
        }
    ],
    "sg:phone":"+1 702 870 4516",
    "sg:postcode":"89102",
    "sg:province":"NV",
    "sg:tags":[
        "precious",
        "metal",
        "mfg"
    ],
    "wof:name":"Van Buren & Cox",
    "wof:placetype":"venue"
},
  "geometry": {"coordinates":[-115.205658,36.159158],"type":"Point"}
}