{
  "type": "Feature",
  "properties": {
    "iso:country":"US",
    "sg:address":"8311 W Sunset Road",
    "sg:city":"Las Vegas",
    "sg:classifiers":[
        {
            "category":"Banks & Credit Unions",
            "subcategory":"Financial Services",
            "type":"Services"
        }
    ],
    "sg:phone":"+1 702 731 1000",
    "sg:postcode":"89113",
    "sg:province":"NV",
    "sg:tags":[
        "broker",
        "mortgage"
    ],
    "wof:name":"The Mortgage Store",
    "wof:placetype":"venue"
},
  "geometry": {"coordinates":[-115.272633,36.070311],"type":"Point"}
}