{
  "type": "Feature",
  "properties": {
    "iso:country":"US",
    "sg:address":"5809 Westport Cir",
    "sg:city":"Las Vegas",
    "sg:classifiers":[
        {
            "category":"Arts & Performance",
            "subcategory":"Theater",
            "type":"Entertainment"
        }
    ],
    "sg:phone":"+1 702 645 1446",
    "sg:postcode":"89108",
    "sg:province":"NV",
    "sg:tags":[
        "live",
        "music"
    ],
    "wof:name":"Whitney Phoenix LTD",
    "wof:placetype":"venue"
},
  "geometry": {"coordinates":[-115.222394,36.223517],"type":"Point"}
}