{
  "type": "Feature",
  "properties": {
    "iso:country":"US",
    "sg:address":"2605 S Decatur Blvd 116",
    "sg:city":"Spring Valley",
    "sg:classifiers":[
        {
            "category":"Health Services",
            "subcategory":"Dentist",
            "type":"Services"
        }
    ],
    "sg:phone":"+1 702 876 2525",
    "sg:postcode":"89102",
    "sg:province":"NV",
    "wof:name":"identalFY.com",
    "wof:placetype":"venue"
},
  "geometry": {"coordinates":[-115.20906600000001,36.142762],"type":"Point"}
}