{
  "type": "Feature",
  "properties": {
    "iso:country":"US",
    "sg:address":"4155 W Teco Ave",
    "sg:city":"Las Vegas",
    "sg:classifiers":[
        {
            "category":"Building & Trades",
            "subcategory":"Plumbing",
            "type":"Services"
        }
    ],
    "sg:phone":"+1 702 914 8100",
    "sg:postcode":"89118",
    "sg:province":"NV",
    "sg:tags":[
        "contractor"
    ],
    "sg:website":"www.universalplumbing.net",
    "wof:name":"Universal Plumbing & Heating",
    "wof:placetype":"venue"
},
  "geometry": {"coordinates":[-115.190827,36.073583],"type":"Point"}
}