{
  "type": "Feature",
  "properties": {
    "iso:country":"US",
    "sg:address":"6145 S Valley View Blvd",
    "sg:city":"Las Vegas",
    "sg:classifiers":[
        {
            "category":"Professional",
            "subcategory":"Business Services",
            "type":"Services"
        }
    ],
    "sg:phone":"+1 702 938 0632",
    "sg:postcode":"89118",
    "sg:province":"NV",
    "sg:tags":[
        "trade",
        "fair",
        "show"
    ],
    "sg:website":"www.accesstca.com",
    "wof:name":"Access TCA",
    "wof:placetype":"venue"
},
  "geometry": {"coordinates":[-115.190046,36.075772],"type":"Point"}
}