{
  "type": "Feature",
  "properties": {
    "iso:country":"US",
    "sg:address":"4550 W Oakey Blvd",
    "sg:city":"Las Vegas",
    "sg:classifiers":[
        {
            "category":"Personal",
            "type":"Services"
        }
    ],
    "sg:phone":"+1 702 259 6710",
    "sg:postcode":"89102",
    "sg:province":"NV",
    "sg:tags":[
        "time",
        "sharing",
        "plan",
        "vacation"
    ],
    "wof:name":"Concord Servicing Corp",
    "wof:placetype":"venue"
},
  "geometry": {"coordinates":[-115.200237,36.151816],"type":"Point"}
}