{
  "type": "Feature",
  "properties": {
    "iso:country":"US",
    "sg:address":"4726 W Sahara Ave",
    "sg:city":"Las Vegas",
    "sg:classifiers":[
        {
            "category":"Shopping",
            "subcategory":"Jewelry",
            "type":"Retail Goods"
        }
    ],
    "sg:phone":"+1 702 251 0300",
    "sg:postcode":"89102",
    "sg:province":"NV",
    "wof:name":"Jewelry Express of Las Vegas",
    "wof:placetype":"venue"
},
  "geometry": {"coordinates":[-115.205862,36.144764],"type":"Point"}
}