{
  "type": "Feature",
  "properties": {
    "iso:country":"US",
    "sg:address":"9740 Powell Plateau Ct",
    "sg:city":"Las Vegas",
    "sg:classifiers":[
        {
            "category":"Building & Trades",
            "subcategory":"Cleaning & Sanitation",
            "type":"Services"
        }
    ],
    "sg:phone":"+1 702 523 2139",
    "sg:postcode":"89148",
    "sg:province":"NV",
    "sg:tags":[
        "janitor"
    ],
    "wof:name":"Personal Touch Cleaning Svc",
    "wof:placetype":"venue"
},
  "geometry": {"coordinates":[-115.304484,36.09317],"type":"Point"}
}