{
  "type": "Feature",
  "properties": {
    "iso:country":"US",
    "sg:address":"2540 Grandville Ave",
    "sg:city":"Henderson",
    "sg:classifiers":[
        {
            "category":"Professional",
            "subcategory":"Engineering",
            "type":"Services"
        }
    ],
    "sg:phone":"+1 702 242 1158",
    "sg:postcode":"89052",
    "sg:province":"NV",
    "wof:name":"C F Knutson Consult",
    "wof:placetype":"venue"
},
  "geometry": {"coordinates":[-115.097908,35.972277],"type":"Point"}
}