{
  "type": "Feature",
  "properties": {
    "iso:country":"US",
    "sg:address":"8337 W Sunset Rd Ste 300",
    "sg:city":"Las Vegas",
    "sg:classifiers":[
        {
            "category":"Banks & Credit Unions",
            "subcategory":"Bank",
            "type":"Services"
        }
    ],
    "sg:phone":"+1 702 889 2739",
    "sg:postcode":"89113",
    "sg:province":"NV",
    "sg:website":"www.mutualofomahabank.com",
    "wof:name":"Mutual of Omaha Bank",
    "wof:placetype":"venue"
},
  "geometry": {"coordinates":[-115.273246,36.070179],"type":"Point"}
}