{
  "type": "Feature",
  "properties": {
    "iso:country":"US",
    "sg:address":"5313 Yellow Sage Cir",
    "sg:city":"Las Vegas",
    "sg:classifiers":[
        {
            "category":"Personal",
            "type":"Services"
        }
    ],
    "sg:phone":"+1 702 656 8668",
    "sg:postcode":"89149",
    "sg:province":"NV",
    "wof:name":"A & S Vehicle Registration Svc",
    "wof:placetype":"venue"
},
  "geometry": {"coordinates":[-115.2706,36.257469],"type":"Point"}
}