{
  "type": "Feature",
  "properties": {
    "iso:country":"US",
    "sg:address":"3528 S Maryland Pkwy",
    "sg:city":"Las Vegas",
    "sg:classifiers":[
        {
            "category":"Retail",
            "subcategory":"Repair Shop",
            "type":"Services"
        }
    ],
    "sg:phone":"+1 702 369 8148",
    "sg:postcode":"89109",
    "sg:province":"NV",
    "sg:tags":[
        "jewelry"
    ],
    "wof:name":"Greg's Jewelry Repair",
    "wof:placetype":"venue"
},
  "geometry": {"coordinates":[-115.137074,36.126903],"type":"Point"}
}