{
  "type": "Feature",
  "properties": {
    "iso:country":"US",
    "sg:address":"3125 S Nellis Blvd",
    "sg:city":"Las Vegas",
    "sg:classifiers":[
        {
            "category":"Restaurant",
            "type":"Food & Drink"
        }
    ],
    "sg:phone":"+1 702 366 1312",
    "sg:postcode":"89121",
    "sg:province":"NV",
    "wof:name":"Sausoo Market & Talofo Cafe",
    "wof:placetype":"venue"
},
  "geometry": {"coordinates":[-115.065466,36.131878],"type":"Point"}
}