{
  "type": "Feature",
  "properties": {
    "iso:country":"US",
    "sg:address":"3900 W Charleston Blvd",
    "sg:city":"Las Vegas",
    "sg:classifiers":[
        {
            "category":"Professional",
            "subcategory":"Printing & Photocopies",
            "type":"Services"
        }
    ],
    "sg:phone":"+1 702 870 8870",
    "sg:postcode":"89102",
    "sg:province":"NV",
    "wof:name":"A Allcampbell Printing Company",
    "wof:placetype":"venue"
},
  "geometry": {"coordinates":[-115.192001,36.1591],"type":"Point"}
}