{
  "type": "Feature",
  "properties": {
    "iso:country":"US",
    "sg:address":"1910 E Serene Ave",
    "sg:city":"Las Vegas",
    "sg:classifiers":[
        {
            "category":"Shopping",
            "subcategory":"Department Store",
            "type":"Retail Goods"
        }
    ],
    "sg:phone":"+1 702 614 3995",
    "sg:postcode":"89123",
    "sg:province":"NV",
    "wof:name":"Sam's Optical",
    "wof:placetype":"venue"
},
  "geometry": {"coordinates":[-115.125999,36.020599],"type":"Point"}
}