{
  "type": "Feature",
  "properties": {
    "iso:country":"US",
    "sg:address":"1212 Park Cir",
    "sg:city":"Las Vegas",
    "sg:classifiers":[
        {
            "category":"Health Services",
            "subcategory":"Health Practitioner",
            "type":"Services"
        }
    ],
    "sg:phone":"+1 702 809 5151",
    "sg:postcode":"89102",
    "sg:province":"NV",
    "wof:name":"Rebecca Kerns",
    "wof:placetype":"venue"
},
  "geometry": {"coordinates":[-115.168506,36.156158],"type":"Point"}
}