{
  "type": "Feature",
  "properties": {
    "iso:country":"US",
    "sg:address":"10555 Stead Blvd",
    "sg:city":"Reno",
    "sg:classifiers":[
        {
            "category":"Restaurant",
            "type":"Food & Drink"
        }
    ],
    "sg:menulink":"http://www.allmenus.com/nv/north-valleys/162828-port-of-subs/menu/",
    "sg:phone":"+1 775 972 0100",
    "sg:postcode":"89506",
    "sg:province":"NV",
    "sg:tags":[
        "wrap",
        "american",
        "sandwich"
    ],
    "wof:name":"Port of Subs",
    "wof:placetype":"venue"
},
  "geometry": {"coordinates":[-119.882739,39.623576],"type":"Point"}
}