{
  "type": "Feature",
  "properties": {
    "iso:country":"US",
    "sg:address":"801 S Rancho Dr Ste B-2",
    "sg:city":"Las Vegas",
    "sg:classifiers":[
        {
            "category":"Professional",
            "subcategory":"Lawyer & Legal Services",
            "type":"Services"
        }
    ],
    "sg:phone":"+1 702 259 6789",
    "sg:postcode":"89106",
    "sg:province":"NV",
    "sg:tags":[
        "personal",
        "injury"
    ],
    "sg:website":"www.lasvegas-injurylawyer.com",
    "wof:name":"Wright & Weiner",
    "wof:placetype":"venue"
},
  "geometry": {"coordinates":[-115.171006,36.161342],"type":"Point"}
}