{
  "type": "Feature",
  "properties": {
    "iso:country":"US",
    "sg:address":"720 S 4th St",
    "sg:city":"Las Vegas",
    "sg:classifiers":[
        {
            "category":"Professional",
            "subcategory":"Engineering",
            "type":"Services"
        }
    ],
    "sg:phone":"+1 702 384 2525",
    "sg:postcode":"89101",
    "sg:province":"NV",
    "sg:tags":[
        "transportation",
        "engineer"
    ],
    "wof:name":"Meyer Mohaddes Assoc Inc",
    "wof:placetype":"venue"
},
  "geometry": {"coordinates":[-115.147032,36.161845],"type":"Point"}
}