{
  "type": "Feature",
  "properties": {
    "iso:country":"US",
    "sg:address":"5729 Ocean Beach Dr",
    "sg:city":"Las Vegas",
    "sg:classifiers":[
        {
            "category":"Banks & Credit Unions",
            "subcategory":"Bank",
            "type":"Services"
        }
    ],
    "sg:phone":"+1 702 655 7555",
    "sg:postcode":"89149",
    "sg:province":"NV",
    "wof:name":"First National Bankcard Svc",
    "wof:placetype":"venue"
},
  "geometry": {"coordinates":[-115.267008,36.26596],"type":"Point"}
}