{
  "type": "Feature",
  "properties": {
    "iso:country":"US",
    "sg:address":"4095 Pequeno Ave",
    "sg:city":"Las Vegas",
    "sg:classifiers":[
        {
            "category":"Building & Trades",
            "subcategory":"Construction",
            "type":"Services"
        }
    ],
    "sg:phone":"+1 702 526 2659",
    "sg:postcode":"89120",
    "sg:province":"NV",
    "sg:tags":[
        "house"
    ],
    "wof:name":"Procraft Home Improvement",
    "wof:placetype":"venue"
},
  "geometry": {"coordinates":[-115.08578,36.093434],"type":"Point"}
}