{
  "type": "Feature",
  "properties": {
    "iso:country":"US",
    "sg:address":"3201 Builders Ave Suite 100",
    "sg:city":"Las Vegas",
    "sg:classifiers":[
        {
            "category":"Shopping",
            "subcategory":"Stationery & Office Supplies",
            "type":"Retail Goods"
        }
    ],
    "sg:phone":"+1 702 457 6387",
    "sg:postcode":"89101",
    "sg:province":"NV",
    "sg:tags":[
        "equipment"
    ],
    "wof:name":"Office Furniture USA",
    "wof:placetype":"venue"
},
  "geometry": {"coordinates":[-115.102366,36.160832],"type":"Point"}
}