{
  "type": "Feature",
  "properties": {
    "iso:country":"US",
    "sg:address":"2900 E Patrick Ln",
    "sg:city":"Las Vegas",
    "sg:classifiers":[
        {
            "category":"Bars & Pubs",
            "type":"Food & Drink"
        }
    ],
    "sg:phone":"+1 702 795 0412",
    "sg:postcode":"89120",
    "sg:province":"NV",
    "sg:tags":[
        "club",
        "comedy"
    ],
    "wof:name":"Club Jester",
    "wof:placetype":"venue"
},
  "geometry": {"coordinates":[-115.111,36.078999],"type":"Point"}
}