{
  "type": "Feature",
  "properties": {
    "iso:country":"US",
    "sg:address":"7720 Rockfield Dr",
    "sg:city":"Las Vegas",
    "sg:classifiers":[
        {
            "category":"Shopping",
            "subcategory":"Jewelry",
            "type":"Retail Goods"
        }
    ],
    "sg:phone":"+1 702 255 9552",
    "sg:postcode":"89128",
    "sg:province":"NV",
    "sg:tags":[
        "jeweler"
    ],
    "wof:name":"Gemstoned",
    "wof:placetype":"venue"
},
  "geometry": {"coordinates":[-115.26213199999999,36.1893],"type":"Point"}
}