{
  "type": "Feature",
  "properties": {
    "iso:country":"US",
    "sg:address":"3501 Boyer Rd",
    "sg:city":"Fallon",
    "sg:classifiers":[
        {
            "category":"Retail",
            "subcategory":"Auto Repair",
            "type":"Services"
        }
    ],
    "sg:phone":"+1 775 867 3019",
    "sg:postcode":"89406",
    "sg:province":"NV",
    "sg:tags":[
        "repairing",
        "automobile"
    ],
    "wof:name":"Ed Bruflat Auto Repair",
    "wof:placetype":"venue"
},
  "geometry": {"coordinates":[-118.875255,39.437228],"type":"Point"}
}