{
  "type": "Feature",
  "properties": {
    "iso:country":"US",
    "sg:address":"4045 Industrial Rd",
    "sg:city":"Las Vegas",
    "sg:classifiers":[
        {
            "category":"Professional",
            "subcategory":"Business Services",
            "type":"Services"
        }
    ],
    "sg:phone":"+1 702 791 5606",
    "sg:postcode":"89103",
    "sg:province":"NV",
    "sg:tags":[
        "interior",
        "designer"
    ],
    "sg:website":"www.yates-silverman.com",
    "wof:name":"Yates-Silverman Inc",
    "wof:placetype":"venue"
},
  "geometry": {"coordinates":[-115.181341,36.11981],"type":"Point"}
}