{
  "type": "Feature",
  "properties": {
    "iso:country":"US",
    "sg:address":"3110 W Ann Rd",
    "sg:city":"North Las Vegas",
    "sg:classifiers":[
        {
            "category":"Retail",
            "subcategory":"Veterinary Services",
            "type":"Services"
        }
    ],
    "sg:phone":"+1 702 579 9111",
    "sg:postcode":"89031",
    "sg:province":"NV",
    "sg:tags":[
        "veterinarian"
    ],
    "sg:website":"www.annroadah.com",
    "wof:name":"Ann Road Animal Hospital",
    "wof:placetype":"venue"
},
  "geometry": {"coordinates":[-115.182571,36.261939],"type":"Point"}
}