{
  "type": "Feature",
  "properties": {
    "iso:country":"US",
    "sg:address":"4301 Tara Ave",
    "sg:city":"Las Vegas",
    "sg:classifiers":[
        {
            "category":"Building & Trades",
            "subcategory":"Cleaning & Sanitation",
            "type":"Services"
        }
    ],
    "sg:phone":"+1 702 365 7842",
    "sg:postcode":"89102",
    "sg:province":"NV",
    "sg:tags":[
        "janitor"
    ],
    "wof:name":"Mayis Cleanup Svc",
    "wof:placetype":"venue"
},
  "geometry": {"coordinates":[-115.198218,36.139024],"type":"Point"}
}