{
  "type": "Feature",
  "properties": {
    "iso:country":"US",
    "sg:address":"936 Serpentina",
    "sg:city":"Las Vegas",
    "sg:classifiers":[
        {
            "category":"Building & Trades",
            "subcategory":"Construction",
            "type":"Services"
        }
    ],
    "sg:phone":"+1 702 838 4025",
    "sg:postcode":"89123",
    "sg:province":"NV",
    "sg:tags":[
        "medical"
    ],
    "wof:name":"Elektra Oncology Systems",
    "wof:placetype":"venue"
},
  "geometry": {"coordinates":[-115.143428,36.045231],"type":"Point"}
}