{
  "type": "Feature",
  "properties": {
    "iso:country":"US",
    "sg:address":"3198 Rosa Vista Dr",
    "sg:city":"Reno",
    "sg:classifiers":[
        {
            "category":"Wholesale",
            "subcategory":"Durable Goods & Equipment",
            "type":"Manufacturing & Wholesale Goods"
        }
    ],
    "sg:phone":"+1 775 857 1705",
    "sg:postcode":"89502",
    "sg:province":"NV",
    "sg:tags":[
        "optical"
    ],
    "wof:name":"Diversified Optics Inc",
    "wof:placetype":"venue"
},
  "geometry": {"coordinates":[-119.743526,39.487792],"type":"Point"}
}