{
  "type": "Feature",
  "properties": {
    "iso:country":"US",
    "sg:address":"7997 W Sahara Ave",
    "sg:city":"Las Vegas",
    "sg:classifiers":[
        {
            "category":"Health Services",
            "subcategory":"Doctor",
            "type":"Services"
        }
    ],
    "sg:phone":"+1 702 476 5100",
    "sg:postcode":"89117",
    "sg:province":"NV",
    "wof:name":"Alan Greenberg Dr",
    "wof:placetype":"venue"
},
  "geometry": {"coordinates":[-115.265226,36.143528],"type":"Point"}
}