{
  "type": "Feature",
  "properties": {
    "iso:country":"US",
    "sg:address":"3335 W Craig Rd",
    "sg:city":"North Las Vegas",
    "sg:classifiers":[
        {
            "category":"Health Services",
            "subcategory":"Optometrist",
            "type":"Services"
        }
    ],
    "sg:phone":"+1 702 647 4798",
    "sg:postcode":"89032",
    "sg:province":"NV",
    "sg:website":"www.visionsource-drmorris.com",
    "wof:name":"Morris Dexter OD",
    "wof:placetype":"venue"
},
  "geometry": {"coordinates":[-115.18499799999999,36.239399],"type":"Point"}
}