{
  "type": "Feature",
  "properties": {
    "iso:country":"US",
    "sg:address":"7812 Leavorite Dr",
    "sg:city":"Las Vegas",
    "sg:classifiers":[
        {
            "category":"Building & Trades",
            "subcategory":"Construction",
            "type":"Services"
        }
    ],
    "sg:phone":"+1 702 228 3423",
    "sg:postcode":"89128",
    "sg:province":"NV",
    "sg:tags":[
        "hanging",
        "contractor"
    ],
    "wof:name":"Hollands Painting & Decorating",
    "wof:placetype":"venue"
},
  "geometry": {"coordinates":[-115.264487,36.183203],"type":"Point"}
}