{
  "type": "Feature",
  "properties": {
    "iso:country":"US",
    "sg:address":"2542 Las Vegas Blvd N",
    "sg:city":"North Las Vegas",
    "sg:classifiers":[
        {
            "category":"Casinos & Gambling",
            "type":"Entertainment"
        }
    ],
    "sg:phone":"+1 702 649 8801",
    "sg:postcode":"89030",
    "sg:province":"NV",
    "wof:name":"Opera House Saloon & Casino",
    "wof:placetype":"venue"
},
  "geometry": {"coordinates":[-115.113998,36.205601],"type":"Point"}
}