{
  "type": "Feature",
  "properties": {
    "iso:country":"US",
    "sg:address":"5055 W Patrick Ln",
    "sg:city":"Las Vegas",
    "sg:classifiers":[
        {
            "category":"Professional",
            "type":"Services"
        }
    ],
    "sg:phone":"+1 702 364 1822",
    "sg:postcode":"89118",
    "sg:province":"NV",
    "sg:tags":[
        "establishment"
    ],
    "wof:name":"Tuntland Land & Development",
    "wof:placetype":"venue"
},
  "geometry": {"coordinates":[-115.208115,36.078968],"type":"Point"}
}