{
  "type": "Feature",
  "properties": {
    "iso:country":"US",
    "sg:address":"5352 Carol Dr",
    "sg:city":"Sun Valley",
    "sg:classifiers":[
        {
            "category":"Building & Trades",
            "subcategory":"Landscaping Services",
            "type":"Services"
        }
    ],
    "sg:phone":"+1 775 673 6115",
    "sg:postcode":"89433",
    "sg:province":"NV",
    "sg:tags":[
        "lawn",
        "maintenance",
        "grounds"
    ],
    "wof:name":"L & P Yard Maintenance",
    "wof:placetype":"venue"
},
  "geometry": {"coordinates":[-119.778024,39.587173],"type":"Point"}
}