{
  "type": "Feature",
  "properties": {
    "iso:country":"US",
    "sg:address":"1383 Karen Ave",
    "sg:city":"Las Vegas",
    "sg:classifiers":[
        {
            "category":"Manufacturing",
            "subcategory":"Printing",
            "type":"Manufacturing & Wholesale Goods"
        }
    ],
    "sg:phone":"+1 702 734 6934",
    "sg:postcode":"89121",
    "sg:province":"NV",
    "sg:tags":[
        "publishing"
    ],
    "wof:name":"Watosh Publishing",
    "wof:placetype":"venue"
},
  "geometry": {"coordinates":[-115.133216,36.140743],"type":"Point"}
}