{
  "type": "Feature",
  "properties": {
    "iso:country":"US",
    "sg:address":"235 N Eastern Ave Ste 132",
    "sg:city":"Las Vegas",
    "sg:classifiers":[
        {
            "category":"Restaurant",
            "type":"Food & Drink"
        }
    ],
    "sg:phone":"+1 702 333 0110",
    "sg:postcode":"89101",
    "sg:province":"NV",
    "sg:tags":[
        "mexican"
    ],
    "wof:name":"El Tapatio",
    "wof:placetype":"venue"
},
  "geometry": {"coordinates":[-115.11605,36.165236],"type":"Point"}
}