{
  "type": "Feature",
  "properties": {
    "iso:country":"US",
    "sg:address":"5700 Spring Mountain Rd",
    "sg:city":"Las Vegas",
    "sg:classifiers":[
        {
            "category":"Restaurant",
            "type":"Food & Drink"
        }
    ],
    "sg:phone":"+1 702 365 0888",
    "sg:postcode":"89146",
    "sg:province":"NV",
    "wof:name":"A Taste Of Indonesia",
    "wof:placetype":"venue"
},
  "geometry": {"coordinates":[-115.220721,36.125642],"type":"Point"}
}