{
  "type": "Feature",
  "properties": {
    "iso:country":"US",
    "sg:address":"1421 Ingraham St",
    "sg:city":"Las Vegas",
    "sg:classifiers":[
        {
            "category":"Retail",
            "subcategory":"Laundry & Dry Cleaning",
            "type":"Services"
        }
    ],
    "sg:phone":"+1 702 644 3096",
    "sg:postcode":"89101",
    "sg:province":"NV",
    "sg:tags":[
        "cleaners",
        "rug",
        "carpet"
    ],
    "wof:name":"J & A Carpet Upholstery Clnng",
    "wof:placetype":"venue"
},
  "geometry": {"coordinates":[-115.105548,36.186609],"type":"Point"}
}