{
  "type": "Feature",
  "properties": {
    "iso:country":"US",
    "sg:address":"3900 Las Vegas Blvd",
    "sg:city":"Las Vegas",
    "sg:classifiers":[
        {
            "category":"Travel",
            "subcategory":"Hotels & Motels",
            "type":"Entertainment"
        }
    ],
    "sg:postcode":"89115",
    "sg:province":"NV",
    "wof:name":"Oasis Pool",
    "wof:placetype":"venue"
},
  "geometry": {"coordinates":[-115.072002,36.229804],"type":"Point"}
}