{
  "type": "Feature",
  "properties": {
    "iso:country":"US",
    "sg:address":"4300 Meadows Ln",
    "sg:city":"Las Vegas",
    "sg:classifiers":[
        {
            "category":"Shopping",
            "subcategory":"Mobile Phones",
            "type":"Retail Goods"
        }
    ],
    "sg:phone":"+1 702 880 1800",
    "sg:postcode":"89107",
    "sg:province":"NV",
    "wof:name":"Alert Cellular Llc",
    "wof:placetype":"venue"
},
  "geometry": {"coordinates":[-115.19899700000001,36.1702],"type":"Point"}
}