{
  "type": "Feature",
  "properties": {
    "iso:country":"US",
    "sg:address":"2881 Bus Park Ct",
    "sg:city":"Las Vegas",
    "sg:classifiers":[
        {
            "category":"Insurance",
            "subcategory":"Insurance Agent",
            "type":"Services"
        }
    ],
    "sg:phone":"+1 702 253 6350",
    "sg:postcode":"89128",
    "sg:province":"NV",
    "sg:website":"www.mutualofomaha.com",
    "wof:name":"Mutual Of Omaha Insurance Co",
    "wof:placetype":"venue"
},
  "geometry": {"coordinates":[-115.250064,36.213072],"type":"Point"}
}