{
  "type": "Feature",
  "properties": {
    "iso:country":"US",
    "sg:address":"1 Hastings Dr",
    "sg:city":"Reno",
    "sg:classifiers":[
        {
            "category":"Mining & Drilling",
            "type":"Manufacturing & Wholesale Goods"
        }
    ],
    "sg:phone":"+1 775 786 6697",
    "sg:postcode":"89503",
    "sg:province":"NV",
    "sg:tags":[
        "gold"
    ],
    "wof:name":"Aur Resources (usa) Inc",
    "wof:placetype":"venue"
},
  "geometry": {"coordinates":[-119.826536,39.53458],"type":"Point"}
}