{
  "type": "Feature",
  "properties": {
    "iso:country":"US",
    "sg:address":"4052 Laurel Hill Dr",
    "sg:city":"North Las Vegas",
    "sg:classifiers":[
        {
            "category":"Shopping",
            "type":"Retail Goods"
        }
    ],
    "sg:phone":"+1 702 646 9671",
    "sg:postcode":"89032",
    "sg:province":"NV",
    "sg:tags":[
        "product",
        "wood"
    ],
    "wof:name":"Beveled Edge Frame Shop",
    "wof:placetype":"venue"
},
  "geometry": {"coordinates":[-115.172878,36.234024],"type":"Point"}
}