{
  "type": "Feature",
  "properties": {
    "iso:country":"US",
    "sg:address":"1800 E Sahara Ave",
    "sg:city":"Las Vegas",
    "sg:classifiers":[
        {
            "category":"Professional",
            "subcategory":"Research",
            "type":"Services"
        }
    ],
    "sg:phone":"+1 702 693 5741",
    "sg:postcode":"89104",
    "sg:province":"NV",
    "sg:tags":[
        "market",
        "analysis"
    ],
    "wof:name":"Baron Marketing Group",
    "wof:placetype":"venue"
},
  "geometry": {"coordinates":[-115.123261,36.144325],"type":"Point"}
}