{
  "type": "Feature",
  "properties": {
    "iso:country":"US",
    "sg:address":"3434 el Camino Real",
    "sg:city":"Las Vegas",
    "sg:classifiers":[
        {
            "category":"Retail",
            "subcategory":"Repair Shop",
            "type":"Services"
        }
    ],
    "sg:phone":"+1 702 547 4443",
    "sg:postcode":"89121",
    "sg:province":"NV",
    "sg:tags":[
        "refrigerator"
    ],
    "wof:name":"Awan Mechanical Services",
    "wof:placetype":"venue"
},
  "geometry": {"coordinates":[-115.095578,36.126925],"type":"Point"}
}