{
  "type": "Feature",
  "properties": {
    "iso:country":"US",
    "sg:address":"5024 Schuster St",
    "sg:city":"Las Vegas",
    "sg:classifiers":[
        {
            "category":"Retail",
            "subcategory":"Auto Repair",
            "type":"Services"
        }
    ],
    "sg:phone":"+1 702 221 0752",
    "sg:postcode":"89118",
    "sg:province":"NV",
    "sg:tags":[
        "repairing",
        "automobile"
    ],
    "wof:name":"Silver State Motocar Corp",
    "wof:placetype":"venue"
},
  "geometry": {"coordinates":[-115.19210699999999,36.098417],"type":"Point"}
}