{
  "type": "Feature",
  "properties": {
    "iso:country":"US",
    "sg:address":"6316 Anaconda St",
    "sg:city":"Las Vegas",
    "sg:classifiers":[
        {
            "category":"Building & Trades",
            "subcategory":"Landscaping Services",
            "type":"Services"
        }
    ],
    "sg:phone":"+1 702 325 6186",
    "sg:postcode":"89108",
    "sg:province":"NV",
    "wof:name":"Water Smart Gardeners",
    "wof:placetype":"venue"
},
  "geometry": {"coordinates":[-115.230896,36.209083],"type":"Point"}
}