{
  "type": "Feature",
  "properties": {
    "iso:country":"US",
    "sg:address":"1570 Union Ct",
    "sg:city":"Sparks",
    "sg:classifiers":[
        {
            "category":"Food & Beverages",
            "subcategory":"Candy",
            "type":"Retail Goods"
        }
    ],
    "sg:phone":"+1 775 331 6626",
    "sg:postcode":"89434",
    "sg:province":"NV",
    "sg:tags":[
        "confectionery"
    ],
    "wof:name":"Sweet Tooth Candy Bouquets",
    "wof:placetype":"venue"
},
  "geometry": {"coordinates":[-119.716672,39.545222],"type":"Point"}
}