{
  "type": "Feature",
  "properties": {
    "iso:country":"US",
    "sg:address":"6301 Mountain Vista St Ste 100",
    "sg:city":"Henderson",
    "sg:classifiers":[
        {
            "category":"Health Services",
            "subcategory":"Doctor",
            "type":"Services"
        }
    ],
    "sg:phone":"+1 702 451 1844",
    "sg:postcode":"89014",
    "sg:province":"NV",
    "sg:tags":[
        "practice",
        "family"
    ],
    "wof:name":"Meli James DO Ltd",
    "wof:placetype":"venue"
},
  "geometry": {"coordinates":[-115.073328,36.074522],"type":"Point"}
}