{
  "type": "Feature",
  "properties": {
    "iso:country":"US",
    "sg:address":"736 Susanna Way",
    "sg:city":"Henderson",
    "sg:classifiers":[
        {
            "category":"Freight",
            "type":"Transportation"
        }
    ],
    "sg:phone":"+1 702 558 2200",
    "sg:postcode":"89011",
    "sg:province":"NV",
    "sg:tags":[
        "special"
    ],
    "wof:name":"Riverline USA Inc",
    "wof:placetype":"venue"
},
  "geometry": {"coordinates":[-115.023538,36.066671],"type":"Point"}
}