{
  "type": "Feature",
  "properties": {
    "iso:country":"US",
    "sg:address":"6014 Plumas St",
    "sg:city":"Reno",
    "sg:classifiers":[
        {
            "category":"Retail",
            "subcategory":"Repair Shop",
            "type":"Services"
        }
    ],
    "sg:phone":"+1 702 361 7146",
    "sg:postcode":"89519",
    "sg:province":"NV",
    "wof:name":"Tradewinds Studio",
    "wof:placetype":"venue"
},
  "geometry": {"coordinates":[-119.811715,39.476205],"type":"Point"}
}