{
  "type": "Feature",
  "properties": {
    "iso:country":"US",
    "sg:address":"2349 E Bonanza Rd",
    "sg:city":"Las Vegas",
    "sg:classifiers":[
        {
            "category":"Food & Beverages",
            "subcategory":"Candy",
            "type":"Retail Goods"
        }
    ],
    "sg:phone":"+1 702 388 4076",
    "sg:postcode":"89101",
    "sg:province":"NV",
    "wof:name":"La Tiendita Candies",
    "wof:placetype":"venue"
},
  "geometry": {"coordinates":[-115.116825,36.174023],"type":"Point"}
}