{
  "type": "Feature",
  "properties": {
    "iso:country":"US",
    "sg:address":"7007 Leter Rd",
    "sg:city":"Fallon",
    "sg:classifiers":[
        {
            "category":"Professional",
            "type":"Services"
        }
    ],
    "sg:phone":"+1 775 423 8853",
    "sg:postcode":"89406",
    "sg:province":"NV",
    "sg:tags":[
        "establishment"
    ],
    "wof:name":"High Desert Emporium",
    "wof:placetype":"venue"
},
  "geometry": {"coordinates":[-118.716301,39.580028],"type":"Point"}
}