{
  "type": "Feature",
  "properties": {
    "iso:country":"US",
    "sg:address":"7541 W Lake Mead Blvd",
    "sg:city":"Las Vegas",
    "sg:classifiers":[
        {
            "category":"Coffee & Tea",
            "type":"Food & Drink"
        }
    ],
    "sg:phone":"+1 702 240 4710",
    "sg:postcode":"89128",
    "sg:province":"NV",
    "sg:website":"www.starbucks.com",
    "wof:name":"Starbucks Coffee",
    "wof:placetype":"venue"
},
  "geometry": {"coordinates":[-115.25851400000001,36.19602],"type":"Point"}
}