{
  "type": "Feature",
  "properties": {
    "iso:country":"US",
    "sg:address":"7375 Peak Dr",
    "sg:city":"Las Vegas",
    "sg:classifiers":[
        {
            "category":"Professional",
            "subcategory":"Lawyer & Legal Services",
            "type":"Services"
        }
    ],
    "sg:phone":"+1 702 255 6161",
    "sg:postcode":"89128",
    "sg:province":"NV",
    "wof:name":"Graham & Wilde",
    "wof:placetype":"venue"
},
  "geometry": {"coordinates":[-115.252998,36.210098],"type":"Point"}
}