{
  "type": "Feature",
  "properties": {
    "iso:country":"US",
    "sg:address":"1058 Tiller Dr",
    "sg:city":"Incline Village",
    "sg:classifiers":[
        {
            "category":"Retail",
            "subcategory":"Repair Shop",
            "type":"Services"
        },
        {
            "category":"Shopping",
            "subcategory":"Bicycles & Sporting Goods",
            "type":"Retail Goods"
        }
    ],
    "sg:phone":"+1 775 831 2619",
    "sg:postcode":"89451",
    "sg:province":"NV",
    "wof:name":"Bob's Speed Shop",
    "wof:placetype":"venue"
},
  "geometry": {"coordinates":[-119.93383,39.237486],"type":"Point"}
}