{
  "type": "Feature",
  "properties": {
    "iso:country":"US",
    "sg:address":"1386 US Hwy 395 S",
    "sg:city":"Gardnerville",
    "sg:classifiers":[
        {
            "category":"Manufacturing",
            "subcategory":"Aerospace",
            "type":"Manufacturing & Wholesale Goods"
        }
    ],
    "sg:phone":"+1 775 266 4870",
    "sg:postcode":"89410",
    "sg:province":"NV",
    "sg:tags":[
        "machine",
        "shop"
    ],
    "wof:name":"Janll Engineering Company",
    "wof:placetype":"venue"
},
  "geometry": {"coordinates":[-119.744888,38.939379],"type":"Point"}
}