{
  "type": "Feature",
  "properties": {
    "iso:country":"US",
    "sg:address":"1397 Galleria Dr Ste 100",
    "sg:city":"Henderson",
    "sg:classifiers":[
        {
            "category":"Health Services",
            "subcategory":"Doctor",
            "type":"Services"
        }
    ],
    "sg:phone":"+1 702 436 5800",
    "sg:postcode":"89014",
    "sg:province":"NV",
    "wof:name":"Shurtleff Kristina",
    "wof:placetype":"venue"
},
  "geometry": {"coordinates":[-115.045432,36.070758],"type":"Point"}
}