{
  "type": "Feature",
  "properties": {
    "iso:country":"US",
    "sg:address":"2635 Cottonwillow St",
    "sg:city":"Las Vegas",
    "sg:classifiers":[
        {
            "category":"Wholesale",
            "subcategory":"Vending Machines",
            "type":"Manufacturing & Wholesale Goods"
        }
    ],
    "sg:phone":"+1 702 242 9921",
    "sg:postcode":"89135",
    "sg:province":"NV",
    "sg:tags":[
        "operator"
    ],
    "wof:name":"Vegas Vending Specialists",
    "wof:placetype":"venue"
},
  "geometry": {"coordinates":[-115.32713,36.141475],"type":"Point"}
}