{
  "type": "Feature",
  "properties": {
    "iso:country":"US",
    "sg:address":"6490 S Mccarran Blvd",
    "sg:city":"Reno",
    "sg:classifiers":[
        {
            "category":"Insurance",
            "subcategory":"Insurance Agent",
            "type":"Services"
        },
        {
            "category":"Insurance",
            "subcategory":"Hazard Insurance",
            "type":"Services"
        },
        {
            "category":"Insurance",
            "subcategory":"Title Insurance",
            "type":"Services"
        },
        {
            "category":"Insurance",
            "subcategory":"Life Insurance",
            "type":"Services"
        }
    ],
    "sg:phone":"+1 775 828 9747",
    "sg:postcode":"89509",
    "sg:province":"NV",
    "sg:tags":[
        "business",
        "auto",
        "commercial",
        "homeowner",
        "motorcycle",
        "renter"
    ],
    "wof:name":"Allstate Insurance Company - Gene L Gardella",
    "wof:placetype":"venue"
},
  "geometry": {"coordinates":[-119.796986,39.476738],"type":"Point"}
}