{
  "type": "Feature",
  "properties": {
    "iso:country":"US",
    "sg:address":"9890 S Maryland Parkway # 200",
    "sg:city":"Las Vegas",
    "sg:classifiers":[
        {
            "category":"Real Estate",
            "subcategory":"Real Estate Services",
            "type":"Services"
        },
        {
            "category":"Real Estate",
            "subcategory":"Real Estate Agent",
            "type":"Services"
        }
    ],
    "sg:phone":"+1 702 914 6567",
    "sg:postcode":"89183",
    "sg:province":"NV",
    "sg:tags":[
        "property",
        "management"
    ],
    "sg:website":"www.keypm.com",
    "wof:name":"Key Property Management",
    "wof:placetype":"venue"
},
  "geometry": {"coordinates":[-115.136715,36.009933],"type":"Point"}
}