{
  "type": "Feature",
  "properties": {
    "iso:country":"US",
    "sg:address":"1540 Little Dove Ct",
    "sg:city":"Henderson",
    "sg:classifiers":[
        {
            "category":"Education",
            "subcategory":"Special Training",
            "type":"Public Place"
        }
    ],
    "sg:phone":"+1 702 434 3151",
    "sg:postcode":"89014",
    "sg:province":"NV",
    "sg:tags":[
        "instruction",
        "music"
    ],
    "wof:name":"David Goldstein Music Studio",
    "wof:placetype":"venue"
},
  "geometry": {"coordinates":[-115.055143,36.072943],"type":"Point"}
}