{
  "type": "Feature",
  "properties": {
    "iso:country":"US",
    "sg:address":"1501 Prater Way",
    "sg:city":"Sparks",
    "sg:classifiers":[
        {
            "category":"Restaurant",
            "type":"Food & Drink"
        },
        {
            "category":"Ice Cream",
            "type":"Food & Drink"
        }
    ],
    "sg:menulink":"http://www.allmenus.com/nv/sparks/167562-dairy-queen/menu/",
    "sg:phone":"+1 702 359 5838",
    "sg:postcode":"89431",
    "sg:province":"NV",
    "sg:tags":[
        "burger",
        "american",
        "ice",
        "cream"
    ],
    "wof:name":"Dairy Queen",
    "wof:placetype":"venue"
},
  "geometry": {"coordinates":[-119.762381,39.538236],"type":"Point"}
}