{
  "type": "Feature",
  "properties": {
    "iso:country":"US",
    "sg:address":"1013 Slayton Dr",
    "sg:city":"Las Vegas",
    "sg:classifiers":[
        {
            "category":"Wholesale",
            "subcategory":"Home Furnishings",
            "type":"Manufacturing & Wholesale Goods"
        }
    ],
    "sg:phone":"+1 702 222 0511",
    "sg:postcode":"89107",
    "sg:province":"NV",
    "wof:name":"Menzildjian A Oriental Rugs",
    "wof:placetype":"venue"
},
  "geometry": {"coordinates":[-115.227155,36.162276],"type":"Point"}
}