{
  "type": "Feature",
  "properties": {
    "iso:country":"US",
    "sg:address":"5890 Shadow Park Dr",
    "sg:city":"Reno",
    "sg:classifiers":[
        {
            "category":"Building & Trades",
            "subcategory":"Construction",
            "type":"Services"
        }
    ],
    "sg:phone":"+1 775 825 6707",
    "sg:postcode":"89523",
    "sg:province":"NV",
    "sg:tags":[
        "contractor"
    ],
    "wof:name":"Mares Framing",
    "wof:placetype":"venue"
},
  "geometry": {"coordinates":[-119.877501,39.531026],"type":"Point"}
}