{
  "type": "Feature",
  "properties": {
    "iso:country":"US",
    "sg:address":"7548 W Sahara Ave",
    "sg:city":"Las Vegas",
    "sg:classifiers":[
        {
            "category":"Real Estate",
            "subcategory":"Real Estate Services",
            "type":"Services"
        }
    ],
    "sg:phone":"+1 702 932 0777",
    "sg:postcode":"89117",
    "sg:province":"NV",
    "sg:tags":[
        "company",
        "title"
    ],
    "wof:name":"Pioneer National Title",
    "wof:placetype":"venue"
},
  "geometry": {"coordinates":[-115.254381,36.143924],"type":"Point"}
}