{
  "type": "Feature",
  "properties": {
    "iso:country":"US",
    "sg:address":"9999 W Katie Ave",
    "sg:city":"Las Vegas",
    "sg:classifiers":[
        {
            "category":"Professional",
            "type":"Services"
        }
    ],
    "sg:phone":"+1 702 212 7151",
    "sg:postcode":"89147",
    "sg:province":"NV",
    "sg:tags":[
        "establishment"
    ],
    "wof:name":"Oakwood Corporate Housing",
    "wof:placetype":"venue"
},
  "geometry": {"coordinates":[-115.31133,36.120602],"type":"Point"}
}