{
  "type": "Feature",
  "properties": {
    "iso:country":"US",
    "sg:address":"10000 Covington Cross Dr",
    "sg:city":"Las Vegas",
    "sg:classifiers":[
        {
            "category":"Home & Garden",
            "subcategory":"Home Furnishings",
            "type":"Retail Goods"
        }
    ],
    "sg:phone":"+1 702 360 7000",
    "sg:postcode":"89144",
    "sg:province":"NV",
    "sg:tags":[
        "bath",
        "kitchen",
        "accessory"
    ],
    "sg:website":"www.williams-sonoma.com",
    "wof:name":"Williams-Sonoma",
    "wof:placetype":"venue"
},
  "geometry": {"coordinates":[-115.314003,36.186699],"type":"Point"}
}