{
  "type": "Feature",
  "properties": {
    "iso:country":"US",
    "sg:address":"4832 Stillwater Ave",
    "sg:city":"Las Vegas",
    "sg:classifiers":[
        {
            "category":"Building & Trades",
            "subcategory":"Landscaping Services",
            "type":"Services"
        }
    ],
    "sg:phone":"+1 702 591 1094",
    "sg:postcode":"89110",
    "sg:province":"NV",
    "sg:tags":[
        "landscape",
        "contractor"
    ],
    "wof:name":"J L Lawn Svc",
    "wof:placetype":"venue"
},
  "geometry": {"coordinates":[-115.067733,36.182816],"type":"Point"}
}