{
  "type": "Feature",
  "properties": {
    "iso:country":"US",
    "sg:address":"425 Cheney St",
    "sg:city":"Reno",
    "sg:classifiers":[
        {
            "category":"Building & Trades",
            "subcategory":"Construction",
            "type":"Services"
        }
    ],
    "sg:phone":"+1 775 786 7642",
    "sg:postcode":"89502",
    "sg:province":"NV",
    "sg:tags":[
        "home",
        "contractor",
        "general"
    ],
    "wof:name":"Daniels Construction Co",
    "wof:placetype":"venue"
},
  "geometry": {"coordinates":[-119.802085,39.518375],"type":"Point"}
}