{
  "type": "Feature",
  "properties": {
    "iso:country":"US",
    "sg:address":"608 Patricia Ct",
    "sg:city":"Gardnerville",
    "sg:classifiers":[
        {
            "category":"Marine",
            "type":"Transportation"
        }
    ],
    "sg:phone":"+1 775 265 4850",
    "sg:postcode":"89460",
    "sg:province":"NV",
    "sg:tags":[
        "water",
        "transport"
    ],
    "wof:name":"Tillack Trucking",
    "wof:placetype":"venue"
},
  "geometry": {"coordinates":[-119.730876,38.883037],"type":"Point"}
}