{
  "type": "Feature",
  "properties": {
    "iso:country":"US",
    "sg:address":"700 S 5th St",
    "sg:city":"Elko",
    "sg:classifiers":[
        {
            "category":"Retail",
            "subcategory":"Veterinary Services",
            "type":"Services"
        }
    ],
    "sg:phone":"+1 775 738 5010",
    "sg:postcode":"89801",
    "sg:province":"NV",
    "sg:tags":[
        "hospital",
        "animal"
    ],
    "wof:name":"Bergin Animal Clinic",
    "wof:placetype":"venue"
},
  "geometry": {"coordinates":[-115.75028399999999,40.826674],"type":"Point"}
}