{
  "type": "Feature",
  "properties": {
    "iso:country":"US",
    "sg:address":"7370 Bachelors Button Dr",
    "sg:city":"Las Vegas",
    "sg:classifiers":[
        {
            "category":"Health Services",
            "subcategory":"Doctor",
            "type":"Services"
        }
    ],
    "sg:phone":"+1 702 438 8122",
    "sg:postcode":"89131",
    "sg:province":"NV",
    "sg:tags":[
        "physician",
        "surgeon"
    ],
    "wof:name":"San Carlos Co Inc",
    "wof:placetype":"venue"
},
  "geometry": {"coordinates":[-115.253545,36.298455],"type":"Point"}
}