{
  "type": "Feature",
  "properties": {
    "iso:country":"US",
    "sg:address":"1235 N Nellis Blvd",
    "sg:city":"Las Vegas",
    "sg:classifiers":[
        {
            "category":"Manufacturing",
            "subcategory":"Metals",
            "type":"Manufacturing & Wholesale Goods"
        }
    ],
    "sg:phone":"+1 702 453 0046",
    "sg:postcode":"89110",
    "sg:province":"NV",
    "sg:tags":[
        "product",
        "fabricated",
        "mfg"
    ],
    "wof:name":"Southern Nev Met Fabricators",
    "wof:placetype":"venue"
},
  "geometry": {"coordinates":[-115.062254,36.184296],"type":"Point"}
}