{
  "type": "Feature",
  "properties": {
    "iso:country":"US",
    "sg:address":"277 Plumb Ln",
    "sg:city":"Reno",
    "sg:classifiers":[
        {
            "category":"Shopping",
            "subcategory":"Gifts & Souvenirs",
            "type":"Retail Goods"
        }
    ],
    "sg:phone":"+1 775 329 5998",
    "sg:postcode":"89502",
    "sg:province":"NV",
    "sg:tags":[
        "shop"
    ],
    "wof:name":"Hallmark The Card Place",
    "wof:placetype":"venue"
},
  "geometry": {"coordinates":[-119.803009,39.505814],"type":"Point"}
}