{
  "type": "Feature",
  "properties": {
    "iso:country":"US",
    "sg:address":"3064 Silver Sage Dr",
    "sg:city":"Carson City",
    "sg:classifiers":[
        {
            "category":"Professional",
            "subcategory":"Lawyer & Legal Services",
            "type":"Services"
        }
    ],
    "sg:phone":"+1 775 882 6450",
    "sg:postcode":"89701",
    "sg:province":"NV",
    "wof:name":"Rankl James J Attorney At Law",
    "wof:placetype":"venue"
},
  "geometry": {"coordinates":[-119.763608,39.141212],"type":"Point"}
}