{
  "type": "Feature",
  "properties": {
    "iso:country":"US",
    "sg:address":"Las Vegas Plastic Surgery 9280 W Sunset Rd Ste 236",
    "sg:city":"Las Vegas",
    "sg:classifiers":[
        {
            "category":"Health Services",
            "subcategory":"Doctor",
            "type":"Services"
        }
    ],
    "sg:phone":"+1 702 450 0777",
    "sg:postcode":"89148",
    "sg:province":"NV",
    "sg:tags":[
        "surgeon",
        "cosmetic"
    ],
    "sg:website":"www.jjrothmd.com",
    "wof:name":"Jeffrey J. Roth, MD, FACS",
    "wof:placetype":"venue"
},
  "geometry": {"coordinates":[-115.295313,36.070253],"type":"Point"}
}