{
  "type": "Feature",
  "properties": {
    "iso:country":"US",
    "sg:address":"247 Freeport Blvd",
    "sg:city":"Sparks",
    "sg:classifiers":[
        {
            "category":"Freight",
            "type":"Transportation"
        }
    ],
    "sg:phone":"+1 775 359 1439",
    "sg:postcode":"89431",
    "sg:province":"NV",
    "sg:tags":[
        "special"
    ],
    "wof:name":"Pennzoil - Quaker State Co",
    "wof:placetype":"venue"
},
  "geometry": {"coordinates":[-119.74577,39.525486],"type":"Point"}
}