{
  "type": "Feature",
  "properties": {
    "iso:country":"US",
    "sg:address":"255 N Sierra St",
    "sg:city":"Reno",
    "sg:classifiers":[
        {
            "category":"Travel",
            "subcategory":"Hotels & Motels",
            "type":"Entertainment"
        }
    ],
    "sg:phone":"+1 775 785 7100",
    "sg:postcode":"89501",
    "sg:province":"NV",
    "sg:tags":[
        "casino"
    ],
    "sg:website":"www.goldenphoenixreno.com",
    "wof:name":"Golden Phoenix Hotel & Casino",
    "wof:placetype":"venue"
},
  "geometry": {"coordinates":[-119.815088,39.527939],"type":"Point"}
}