{
  "type": "Feature",
  "properties": {
    "iso:country":"US",
    "sg:address":"7400 Las Vegas Blvd S Ofc",
    "sg:city":"Las Vegas",
    "sg:classifiers":[
        {
            "category":"Restaurant",
            "type":"Food & Drink"
        }
    ],
    "sg:phone":"+1 702 896 5105",
    "sg:postcode":"89123",
    "sg:province":"NV",
    "sg:tags":[
        "italian"
    ],
    "sg:website":"www.sbarro.com",
    "wof:name":"Sbarro the Italian Eatery",
    "wof:placetype":"venue"
},
  "geometry": {"coordinates":[-115.171997,36.055099],"type":"Point"}
}