{
  "type": "Feature",
  "properties": {
    "iso:country":"US",
    "sg:address":"10225 King Henry Ave",
    "sg:city":"Las Vegas",
    "sg:classifiers":[
        {
            "category":"Building & Trades",
            "subcategory":"Cleaning & Sanitation",
            "type":"Services"
        }
    ],
    "sg:phone":"+1 702 353 6559",
    "sg:postcode":"89144",
    "sg:province":"NV",
    "sg:tags":[
        "butler",
        "maid"
    ],
    "wof:name":"Four Seasons Cleaning Svc",
    "wof:placetype":"venue"
},
  "geometry": {"coordinates":[-115.31806400000001,36.191661],"type":"Point"}
}