{
  "type": "Feature",
  "properties": {
    "iso:country":"US",
    "sg:address":"102 Cedar St",
    "sg:city":"Beatty",
    "sg:classifiers":[
        {
            "category":"Professional",
            "subcategory":"Computer Services",
            "type":"Services"
        }
    ],
    "sg:phone":"+1 775 553 2525",
    "sg:postcode":"89003",
    "sg:province":"NV",
    "sg:tags":[
        "internet"
    ],
    "wof:name":"Bertram's Corner",
    "wof:placetype":"venue"
},
  "geometry": {"coordinates":[-116.754102,36.906275],"type":"Point"}
}