{
  "type": "Feature",
  "properties": {
    "iso:country":"US",
    "sg:address":"2649 W Horizon Ridge Pkwy",
    "sg:city":"Henderson",
    "sg:classifiers":[
        {
            "category":"Health Services",
            "subcategory":"Podiatrist",
            "type":"Services"
        }
    ],
    "sg:phone":"+1 702 565 6641",
    "sg:postcode":"89052",
    "sg:province":"NV",
    "wof:name":"Henderson Foot Care",
    "wof:placetype":"venue"
},
  "geometry": {"coordinates":[-115.102928,36.000763],"type":"Point"}
}