{
  "type": "Feature",
  "properties": {
    "iso:country":"US",
    "sg:address":"341 Baud St",
    "sg:city":"Winnemucca",
    "sg:classifiers":[
        {
            "category":"Retail",
            "subcategory":"Repair Shop",
            "type":"Services"
        }
    ],
    "sg:phone":"+1 775 625 1234",
    "sg:postcode":"89445",
    "sg:province":"NV",
    "wof:name":"Natural Game Taxidermy",
    "wof:placetype":"venue"
},
  "geometry": {"coordinates":[-117.733609,40.974016],"type":"Point"}
}