{
  "type": "Feature",
  "properties": {
    "iso:country":"US",
    "sg:address":"840 King Richard Ave",
    "sg:city":"Las Vegas",
    "sg:classifiers":[
        {
            "category":"Arts & Performance",
            "subcategory":"Theater",
            "type":"Entertainment"
        }
    ],
    "sg:phone":"+1 702 891 5452",
    "sg:postcode":"89119",
    "sg:province":"NV",
    "sg:tags":[
        "theatrical"
    ],
    "wof:name":"Variety Global Entertainment",
    "wof:placetype":"venue"
},
  "geometry": {"coordinates":[-115.145511,36.091129],"type":"Point"}
}