{
  "type": "Feature",
  "properties": {
    "iso:country":"US",
    "sg:address":"2909 Domino Way",
    "sg:city":"Las Vegas",
    "sg:classifiers":[
        {
            "category":"Arts & Performance",
            "subcategory":"Theater",
            "type":"Entertainment"
        }
    ],
    "sg:phone":"+1 702 254 1600",
    "sg:postcode":"89117",
    "sg:province":"NV",
    "sg:tags":[
        "live",
        "music"
    ],
    "wof:name":"Dynamic Sound Co",
    "wof:placetype":"venue"
},
  "geometry": {"coordinates":[-115.298046,36.138049],"type":"Point"}
}