{
  "type": "Feature",
  "properties": {
    "iso:country":"US",
    "sg:address":"4469 W Charleston Boulevard",
    "sg:city":"Las Vegas",
    "sg:classifiers":[
        {
            "category":"Shopping",
            "subcategory":"Shoes",
            "type":"Retail Goods"
        }
    ],
    "sg:phone":"+1 702 259 1200",
    "sg:postcode":"89102",
    "sg:province":"NV",
    "sg:tags":[
        "store"
    ],
    "sg:website":"www.payless.com",
    "wof:name":"Payless",
    "wof:placetype":"venue"
},
  "geometry": {"coordinates":[-115.200835,36.158903],"type":"Point"}
}