{
  "type": "Feature",
  "properties": {
    "iso:country":"US",
    "sg:address":"191 1st St",
    "sg:city":"Genoa",
    "sg:classifiers":[
        {
            "category":"Manufacturing",
            "subcategory":"Printing",
            "type":"Manufacturing & Wholesale Goods"
        }
    ],
    "sg:phone":"+1 775 782 2486",
    "sg:postcode":"89408",
    "sg:province":"NV",
    "sg:tags":[
        "book"
    ],
    "wof:name":"Dragon Enterprises",
    "wof:placetype":"venue"
},
  "geometry": {"coordinates":[-119.25314299999999,39.608676],"type":"Point"}
}