{
  "type": "Feature",
  "properties": {
    "iso:country":"US",
    "sg:address":"3455 E Flamingo Road",
    "sg:city":"Las Vegas",
    "sg:classifiers":[
        {
            "category":"Restaurant",
            "type":"Food & Drink"
        },
        {
            "category":"Bars & Pubs",
            "subcategory":"Nightclub",
            "type":"Food & Drink"
        },
        {
            "category":"Casinos & Gambling",
            "type":"Entertainment"
        }
    ],
    "sg:phone":"+1 702 436 2488",
    "sg:postcode":"89121",
    "sg:province":"NV",
    "sg:tags":[
        "nightlife"
    ],
    "wof:name":"Village Pub Bar & Grill",
    "wof:placetype":"venue"
},
  "geometry": {"coordinates":[-115.099177,36.115142],"type":"Point"}
}