{
  "type": "Feature",
  "properties": {
    "iso:country":"US",
    "sg:address":"2230 Corporate Cir",
    "sg:city":"Henderson",
    "sg:classifiers":[
        {
            "category":"Building & Trades",
            "subcategory":"Construction",
            "type":"Services"
        }
    ],
    "sg:phone":"+1 702 739 9916",
    "sg:postcode":"89074",
    "sg:province":"NV",
    "sg:tags":[
        "contractor"
    ],
    "wof:name":"O B Construction",
    "wof:placetype":"venue"
},
  "geometry": {"coordinates":[-115.087577,36.027841],"type":"Point"}
}