{
  "type": "Feature",
  "properties": {
    "iso:country":"US",
    "sg:address":"7415 S Durango Dr",
    "sg:city":"Las Vegas",
    "sg:classifiers":[
        {
            "category":"Insurance",
            "subcategory":"Insurance Agent",
            "type":"Services"
        }
    ],
    "sg:phone":"+1 702 870 9004",
    "sg:postcode":"89113",
    "sg:province":"NV",
    "wof:name":"State Farm Insurance",
    "wof:placetype":"venue"
},
  "geometry": {"coordinates":[-115.279202,36.051119],"type":"Point"}
}