{
  "type": "Feature",
  "properties": {
    "iso:country":"US",
    "sg:address":"401 E Basin Ave",
    "sg:city":"Pahrump",
    "sg:classifiers":[
        {
            "category":"Museum",
            "type":"Entertainment"
        }
    ],
    "sg:phone":"+1 775 751 1970",
    "sg:postcode":"89060",
    "sg:province":"NV",
    "wof:name":"Pahrump Valley Museum",
    "wof:placetype":"venue"
},
  "geometry": {"coordinates":[-116.007349,36.219547],"type":"Point"}
}