{
  "type": "Feature",
  "properties": {
    "iso:country":"US",
    "sg:address":"1549 Athol Ave",
    "sg:city":"Henderson",
    "sg:classifiers":[
        {
            "category":"Freight",
            "type":"Transportation"
        }
    ],
    "sg:phone":"+1 702 300 3064",
    "sg:postcode":"89011",
    "sg:province":"NV",
    "sg:tags":[
        "trucking"
    ],
    "wof:name":"Matkat Enterprises",
    "wof:placetype":"venue"
},
  "geometry": {"coordinates":[-115.005835,36.059065],"type":"Point"}
}