{
  "type": "Feature",
  "properties": {
    "iso:country":"US",
    "sg:address":"343 Fairview Dr Ste 104",
    "sg:city":"Carson City",
    "sg:classifiers":[
        {
            "category":"Health Services",
            "subcategory":"Doctor",
            "type":"Services"
        },
        {
            "category":"Health Services",
            "subcategory":"Clinic",
            "type":"Services"
        }
    ],
    "sg:phone":"+1 775 887 1817",
    "sg:postcode":"89701",
    "sg:province":"NV",
    "sg:tags":[
        "counseling",
        "mental",
        "psychiatrist"
    ],
    "wof:name":"Degraff Christopher PHD",
    "wof:placetype":"venue"
},
  "geometry": {"coordinates":[-119.764999,39.149899],"type":"Point"}
}