{
  "type": "Feature",
  "properties": {
    "iso:country":"US",
    "sg:address":"350 E Basic Rd",
    "sg:city":"Henderson",
    "sg:classifiers":[
        {
            "category":"Retail",
            "subcategory":"Repair Shop",
            "type":"Services"
        }
    ],
    "sg:phone":"+1 702 565 5037",
    "sg:postcode":"89015",
    "sg:province":"NV",
    "wof:name":"Mr Cleaning Services Inc",
    "wof:placetype":"venue"
},
  "geometry": {"coordinates":[-114.974767,36.033211],"type":"Point"}
}