{
  "type": "Feature",
  "properties": {
    "iso:country":"US",
    "sg:address":"916 Southwood Blvd",
    "sg:city":"Incline Village",
    "sg:classifiers":[
        {
            "category":"Personal",
            "subcategory":"Beauty Salon",
            "type":"Services"
        }
    ],
    "sg:phone":"+1 775 832 7984",
    "sg:postcode":"89451",
    "sg:province":"NV",
    "sg:tags":[
        "shop"
    ],
    "wof:name":"Beach Comber",
    "wof:placetype":"venue"
},
  "geometry": {"coordinates":[-119.949805,39.246421],"type":"Point"}
}