{
  "type": "Feature",
  "properties": {
    "iso:country":"US",
    "sg:address":"5435 Reno Hwy",
    "sg:city":"Fallon",
    "sg:classifiers":[
        {
            "category":"Real Estate",
            "subcategory":"Real Estate Agent",
            "type":"Services"
        }
    ],
    "sg:phone":"+1 775 423 2995",
    "sg:postcode":"89406",
    "sg:province":"NV",
    "wof:name":"L L Realty",
    "wof:placetype":"venue"
},
  "geometry": {"coordinates":[-118.864451,39.485446],"type":"Point"}
}