{
  "type": "Feature",
  "properties": {
    "iso:country":"US",
    "sg:address":"1085 Tiller Dr",
    "sg:city":"Incline Village",
    "sg:classifiers":[
        {
            "category":"Home & Garden",
            "subcategory":"Building Materials",
            "type":"Retail Goods"
        }
    ],
    "sg:phone":"+1 775 833 9772",
    "sg:postcode":"89451",
    "sg:province":"NV",
    "sg:tags":[
        "windows"
    ],
    "wof:name":"Nor Cal Window & Door",
    "wof:placetype":"venue"
},
  "geometry": {"coordinates":[-119.935799,39.238599],"type":"Point"}
}