{
  "type": "Feature",
  "properties": {
    "iso:country":"US",
    "sg:address":"1910 Industrial Rd",
    "sg:city":"Las Vegas",
    "sg:classifiers":[
        {
            "category":"Professional",
            "subcategory":"Advertising",
            "type":"Services"
        }
    ],
    "sg:phone":"+1 702 645 8517",
    "sg:postcode":"89102",
    "sg:province":"NV",
    "wof:name":"Trans Ad Inc",
    "wof:placetype":"venue"
},
  "geometry": {"coordinates":[-115.161141,36.149558],"type":"Point"}
}