{
  "type": "Feature",
  "properties": {
    "iso:country":"US",
    "sg:address":"3232 Meade Ave",
    "sg:city":"Las Vegas",
    "sg:classifiers":[
        {
            "category":"Building & Trades",
            "subcategory":"Plumbing",
            "type":"Services"
        }
    ],
    "sg:phone":"+1 702 362 4763",
    "sg:postcode":"89102",
    "sg:province":"NV",
    "sg:tags":[
        "sheet",
        "work",
        "metal",
        "contractor"
    ],
    "wof:name":"Tin Benders",
    "wof:placetype":"venue"
},
  "geometry": {"coordinates":[-115.179381,36.136321],"type":"Point"}
}