{
  "type": "Feature",
  "properties": {
    "iso:country":"US",
    "sg:address":"525 Marks Street",
    "sg:city":"Henderson",
    "sg:classifiers":[
        {
            "category":"Community Center",
            "type":"Public Place"
        }
    ],
    "sg:phone":"+1 702 383 6210",
    "sg:postcode":"89014",
    "sg:province":"NV",
    "sg:tags":[
        "medical"
    ],
    "sg:website":"www.umcsn.com",
    "wof:name":"University Medical Center",
    "wof:placetype":"venue"
},
  "geometry": {"coordinates":[-115.036736,36.060478],"type":"Point"}
}