{
  "type": "Feature",
  "properties": {
    "iso:country":"US",
    "sg:address":"1909 Weldon Pl",
    "sg:city":"Las Vegas",
    "sg:classifiers":[
        {
            "category":"Wholesale",
            "subcategory":"Electrical",
            "type":"Manufacturing & Wholesale Goods"
        }
    ],
    "sg:phone":"+1 702 731 9113",
    "sg:postcode":"89104",
    "sg:province":"NV",
    "sg:tags":[
        "alarm",
        "burglar",
        "system"
    ],
    "wof:name":"Sentinel Monitoring",
    "wof:placetype":"venue"
},
  "geometry": {"coordinates":[-115.151044,36.149877],"type":"Point"}
}