{
  "type": "Feature",
  "properties": {
    "iso:country":"US",
    "sg:address":"480 Greenway Rd",
    "sg:city":"Henderson",
    "sg:classifiers":[
        {
            "category":"Organizations",
            "subcategory":"Community Association",
            "type":"Services"
        }
    ],
    "sg:phone":"+1 702 564 2867",
    "sg:postcode":"89015",
    "sg:province":"NV",
    "sg:tags":[
        "fraternal"
    ],
    "wof:name":"Masonic Lodge Temple",
    "wof:placetype":"venue"
},
  "geometry": {"coordinates":[-114.971906,36.020839],"type":"Point"}
}