{
  "type": "Feature",
  "properties": {
    "iso:country":"US",
    "sg:address":"7775 S. Rainbow Blvd Ste 105",
    "sg:city":"Las Vegas",
    "sg:classifiers":[
        {
            "category":"Restaurant",
            "type":"Food & Drink"
        }
    ],
    "sg:phone":"+1 702 897 7696",
    "sg:postcode":"89139",
    "sg:province":"NV",
    "sg:tags":[
        "korean"
    ],
    "wof:name":"Soyo Korean Barstaurant",
    "wof:placetype":"venue"
},
  "geometry": {"coordinates":[-115.244147,36.047314],"type":"Point"}
}