{
  "type": "Feature",
  "properties": {
    "iso:country":"US",
    "sg:address":"220 US Hwy 395",
    "sg:city":"Washoe Valley",
    "sg:classifiers":[
        {
            "category":"Autos & Motor Vehicles",
            "subcategory":"Automobile Sales",
            "type":"Retail Goods"
        }
    ],
    "sg:phone":"+1 775 624 2277",
    "sg:postcode":"89704",
    "sg:province":"NV",
    "sg:tags":[
        "car",
        "dealer"
    ],
    "wof:name":"Washoe Valley Motors",
    "wof:placetype":"venue"
},
  "geometry": {"coordinates":[-119.803155,39.329047],"type":"Point"}
}