{
  "type": "Feature",
  "properties": {
    "iso:country":"US",
    "sg:address":"3515 Losee Rd",
    "sg:city":"North Las Vegas",
    "sg:classifiers":[
        {
            "category":"Autos & Motor Vehicles",
            "subcategory":"Automobile Sales",
            "type":"Retail Goods"
        }
    ],
    "sg:phone":"+1 702 474 1318",
    "sg:postcode":"89030",
    "sg:province":"NV",
    "sg:tags":[
        "used"
    ],
    "wof:name":"Auto World",
    "wof:placetype":"venue"
},
  "geometry": {"coordinates":[-115.116795,36.232079],"type":"Point"}
}