{
  "type": "Feature",
  "properties": {
    "iso:country":"US",
    "sg:address":"3290 N Roop St",
    "sg:city":"Carson City",
    "sg:classifiers":[
        {
            "category":"Building & Trades",
            "subcategory":"Landscaping Services",
            "type":"Services"
        }
    ],
    "sg:phone":"+1 775 883 7912",
    "sg:postcode":"89706",
    "sg:province":"NV",
    "sg:tags":[
        "landscape",
        "contractor"
    ],
    "wof:name":"Rock & Rose Landscpg & Lawn",
    "wof:placetype":"venue"
},
  "geometry": {"coordinates":[-119.760481,39.188364],"type":"Point"}
}