{
  "type": "Feature",
  "properties": {
    "iso:country":"US",
    "sg:address":"6820 W Sahara Ave",
    "sg:city":"Las Vegas",
    "sg:classifiers":[
        {
            "category":"Health Services",
            "subcategory":"Doctor",
            "type":"Services"
        }
    ],
    "sg:phone":"+1 702 247 7633",
    "sg:postcode":"89146",
    "sg:province":"NV",
    "sg:tags":[
        "clinic"
    ],
    "wof:name":"Us Med LLC",
    "wof:placetype":"venue"
},
  "geometry": {"coordinates":[-115.240525,36.144197],"type":"Point"}
}