{
  "type": "Feature",
  "properties": {
    "iso:country":"US",
    "sg:address":"6570 Tanana Ct",
    "sg:city":"Sun Valley",
    "sg:classifiers":[
        {
            "category":"Shopping",
            "type":"Retail Goods"
        }
    ],
    "sg:phone":"+1 775 674 1371",
    "sg:postcode":"89433",
    "sg:province":"NV",
    "sg:tags":[
        "merchandise"
    ],
    "wof:name":"Pampered Pets",
    "wof:placetype":"venue"
},
  "geometry": {"coordinates":[-119.76691599999999,39.613964],"type":"Point"}
}