{
  "type": "Feature",
  "properties": {
    "iso:country":"US",
    "sg:address":"2670 Graceful Ln",
    "sg:city":"Henderson",
    "sg:classifiers":[
        {
            "category":"Professional",
            "type":"Services"
        }
    ],
    "sg:phone":"+1 702 270 9522",
    "sg:postcode":"89052",
    "sg:province":"NV",
    "wof:name":"Ooh La La",
    "wof:placetype":"venue"
},
  "geometry": {"coordinates":[-115.10336,36.008638],"type":"Point"}
}