{
  "type": "Feature",
  "properties": {
    "iso:country":"US",
    "sg:address":"6 Bloomfield Hills Dr",
    "sg:city":"Henderson",
    "sg:classifiers":[
        {
            "category":"Education",
            "subcategory":"Special Training",
            "type":"Public Place"
        }
    ],
    "sg:phone":"+1 702 617 0090",
    "sg:postcode":"89052",
    "sg:province":"NV",
    "sg:tags":[
        "instruction",
        "driving"
    ],
    "wof:name":"A Driving Source Inc",
    "wof:placetype":"venue"
},
  "geometry": {"coordinates":[-115.094216,35.966714],"type":"Point"}
}