{
  "type": "Feature",
  "properties": {
    "iso:country":"US",
    "sg:address":"3310 S Jones Blvd",
    "sg:city":"Las Vegas",
    "sg:classifiers":[
        {
            "category":"Banks & Credit Unions",
            "subcategory":"Investment Brokerage",
            "type":"Services"
        }
    ],
    "sg:phone":"+1 702 227 8399",
    "sg:postcode":"89146",
    "sg:province":"NV",
    "sg:tags":[
        "advisory",
        "financial"
    ],
    "wof:name":"LA Financial",
    "wof:placetype":"venue"
},
  "geometry": {"coordinates":[-115.224844,36.125632],"type":"Point"}
}