{
  "type": "Feature",
  "properties": {
    "iso:country":"US",
    "sg:address":"1420 Reebok Ter",
    "sg:city":"Henderson",
    "sg:classifiers":[
        {
            "category":"Professional",
            "subcategory":"Detective & Security Services",
            "type":"Services"
        }
    ],
    "sg:phone":"+1 702 433 5517",
    "sg:postcode":"89014",
    "sg:province":"NV",
    "sg:tags":[
        "system"
    ],
    "wof:name":"M & E Fire Security Systems",
    "wof:placetype":"venue"
},
  "geometry": {"coordinates":[-115.048587,36.053315],"type":"Point"}
}