{
  "type": "Feature",
  "properties": {
    "iso:country":"US",
    "sg:address":"3025 Casey Rd",
    "sg:city":"Fallon",
    "sg:classifiers":[
        {
            "category":"Professional",
            "subcategory":"Business Services",
            "type":"Services"
        }
    ],
    "sg:phone":"+1 775 423 6654",
    "sg:postcode":"89406",
    "sg:province":"NV",
    "sg:tags":[
        "appraiser"
    ],
    "wof:name":"Jackson & Jackson",
    "wof:placetype":"venue"
},
  "geometry": {"coordinates":[-118.819511,39.472973],"type":"Point"}
}