{
  "type": "Feature",
  "properties": {
    "iso:country":"US",
    "sg:address":"3141 Westwood Drive",
    "sg:city":"Las Vegas",
    "sg:classifiers":[
        {
            "category":"Building & Trades",
            "subcategory":"Construction",
            "type":"Services"
        }
    ],
    "sg:phone":"+1 702 262 7847",
    "sg:postcode":"89109",
    "sg:province":"NV",
    "sg:tags":[
        "contractor"
    ],
    "wof:name":"First Quality Roofing",
    "wof:placetype":"venue"
},
  "geometry": {"coordinates":[-115.178698,36.131945],"type":"Point"}
}