{
  "type": "Feature",
  "properties": {
    "iso:country":"US",
    "sg:address":"711 Las Vegas Blvd S",
    "sg:city":"Las Vegas",
    "sg:classifiers":[
        {
            "category":"Retail",
            "subcategory":"Auto Repair",
            "type":"Services"
        }
    ],
    "sg:phone":"+1 702 384 3052",
    "sg:postcode":"89101",
    "sg:province":"NV",
    "sg:tags":[
        "transmission",
        "excavation",
        "general",
        "contractor"
    ],
    "wof:name":"Ted Tafras Transmission Exch",
    "wof:placetype":"venue"
},
  "geometry": {"coordinates":[-115.14586,36.16117],"type":"Point"}
}