{
  "type": "Feature",
  "properties": {
    "iso:country":"US",
    "sg:address":"9397 S Chateau St Jean Dr",
    "sg:city":"Las Vegas",
    "sg:classifiers":[
        {
            "category":"Shopping",
            "subcategory":"Luggage & Leather Goods",
            "type":"Retail Goods"
        }
    ],
    "sg:phone":"+1 702 737 4800",
    "sg:postcode":"89123",
    "sg:province":"NV",
    "sg:tags":[
        "travel",
        "accessory"
    ],
    "wof:name":"Travel Time",
    "wof:placetype":"venue"
},
  "geometry": {"coordinates":[-115.144834,36.019369],"type":"Point"}
}