{
  "type": "Feature",
  "properties": {
    "iso:country":"US",
    "sg:address":"4250 Reno Hwy",
    "sg:city":"Fallon",
    "sg:classifiers":[
        {
            "category":"Building & Trades",
            "subcategory":"Construction",
            "type":"Services"
        }
    ],
    "sg:phone":"+1 775 867 4869",
    "sg:postcode":"89406",
    "sg:province":"NV",
    "wof:name":"Future Home Intl Inc",
    "wof:placetype":"venue"
},
  "geometry": {"coordinates":[-118.843461,39.485489],"type":"Point"}
}