{
  "type": "Feature",
  "properties": {
    "iso:country":"US",
    "sg:address":"8490 S Eastern Avenue",
    "sg:city":"Las Vegas",
    "sg:classifiers":[
        {
            "category":"Health Services",
            "subcategory":"Dentist",
            "type":"Services"
        }
    ],
    "sg:phone":"+1 702 260 8241",
    "sg:postcode":"89123",
    "sg:province":"NV",
    "sg:tags":[
        "orthodontist"
    ],
    "sg:website":"www.vegascoolsmiles.com",
    "wof:name":"Reardon Timothy P DDS Ms",
    "wof:placetype":"venue"
},
  "geometry": {"coordinates":[-115.118324,36.034993],"type":"Point"}
}