{
  "type": "Feature",
  "properties": {
    "iso:country":"US",
    "sg:address":"2075 E Warm Springs Road",
    "sg:city":"Las Vegas",
    "sg:classifiers":[
        {
            "category":"Organizations",
            "subcategory":"Religious Organization",
            "type":"Services"
        }
    ],
    "sg:phone":"+1 702 361 7070",
    "sg:postcode":"89119",
    "sg:province":"NV",
    "wof:name":"Warm Springs Baptist Church",
    "wof:placetype":"venue"
},
  "geometry": {"coordinates":[-115.124111,36.05743],"type":"Point"}
}