{
  "type": "Feature",
  "properties": {
    "iso:country":"US",
    "sg:address":"467 E Silverado Ranch Blvd Ste 115",
    "sg:city":"Las Vegas",
    "sg:classifiers":[
        {
            "category":"Shopping",
            "subcategory":"Baby Store",
            "type":"Retail Goods"
        },
        {
            "category":"Shopping",
            "subcategory":"Clothing, Apparel, & Fashions",
            "type":"Retail Goods"
        }
    ],
    "sg:phone":"+1 702 260 1398",
    "sg:postcode":"89183",
    "sg:province":"NV",
    "sg:tags":[
        "children's",
        "clothing",
        "gear",
        "furniture"
    ],
    "wof:name":"The Children's Shop",
    "wof:placetype":"venue"
},
  "geometry": {"coordinates":[-115.153319,36.012155],"type":"Point"}
}