{
  "type": "Feature",
  "properties": {
    "iso:country":"US",
    "sg:address":"950 Seven Hills Dr",
    "sg:city":"Henderson",
    "sg:classifiers":[
        {
            "category":"Real Estate",
            "subcategory":"Real Estate Operator",
            "type":"Services"
        }
    ],
    "sg:phone":"+1 702 407 2424",
    "sg:postcode":"89052",
    "sg:province":"NV",
    "sg:tags":[
        "apartment"
    ],
    "wof:name":"Lontano Apartments",
    "wof:placetype":"venue"
},
  "geometry": {"coordinates":[-115.122089,35.995345],"type":"Point"}
}