{
  "type": "Feature",
  "properties": {
    "iso:country":"US",
    "sg:address":"2585 N Gateway Rd",
    "sg:city":"Las Vegas",
    "sg:classifiers":[
        {
            "category":"Building & Trades",
            "subcategory":"Landscaping Services",
            "type":"Services"
        }
    ],
    "sg:phone":"+1 702 438 6027",
    "sg:postcode":"89115",
    "sg:province":"NV",
    "sg:tags":[
        "landscape"
    ],
    "wof:name":"Stankosky & Sons Landscaping",
    "wof:placetype":"venue"
},
  "geometry": {"coordinates":[-115.087077,36.203379],"type":"Point"}
}