{
  "type": "Feature",
  "properties": {
    "iso:country":"US",
    "sg:address":"310 Spokane St",
    "sg:city":"Reno",
    "sg:classifiers":[
        {
            "category":"Arts & Performance",
            "subcategory":"Theater",
            "type":"Entertainment"
        }
    ],
    "sg:phone":"+1 775 786 1299",
    "sg:postcode":"89512",
    "sg:province":"NV",
    "sg:tags":[
        "entertainer"
    ],
    "sg:website":"www.spicehouse.com",
    "wof:name":"Spice House Adult Cabaret",
    "wof:placetype":"venue"
},
  "geometry": {"coordinates":[-119.800524,39.532391],"type":"Point"}
}