{
  "type": "Feature",
  "properties": {
    "iso:country":"US",
    "sg:address":"795 W 4th St",
    "sg:city":"Reno",
    "sg:classifiers":[
        {
            "category":"Restaurant",
            "type":"Food & Drink"
        }
    ],
    "sg:phone":"+1 775 324 5355",
    "sg:postcode":"89503",
    "sg:province":"NV",
    "wof:name":"El Herradero Mexican Food",
    "wof:placetype":"venue"
},
  "geometry": {"coordinates":[-119.82388899999999,39.528216],"type":"Point"}
}