{
  "type": "Feature",
  "properties": {
    "iso:country":"US",
    "sg:address":"1004 Dresslerville Rd",
    "sg:city":"Gardnerville",
    "sg:classifiers":[
        {
            "category":"Place Of Worship",
            "subcategory":"Church",
            "type":"Public Place"
        },
        {
            "category":"Place Of Worship",
            "type":"Public Place"
        }
    ],
    "sg:phone":"+1 775 265 3259",
    "sg:postcode":"89460",
    "sg:province":"NV",
    "sg:tags":[
        "churches-non-denominational",
        "denomination",
        "churches-various",
        "churches-christian"
    ],
    "wof:name":"Calvary Chapel Of Carson Valley",
    "wof:placetype":"venue"
},
  "geometry": {"coordinates":[-119.730476,38.9105],"type":"Point"}
}