{
  "type": "Feature",
  "properties": {
    "iso:country":"US",
    "sg:address":"8375 W Flamingo Rd",
    "sg:city":"Las Vegas",
    "sg:classifiers":[
        {
            "category":"Real Estate",
            "subcategory":"Real Estate Agent",
            "type":"Services"
        }
    ],
    "sg:phone":"+1 702 368 5800",
    "sg:postcode":"89147",
    "sg:province":"NV",
    "sg:tags":[
        "development",
        "general"
    ],
    "wof:name":"Sunset Greens",
    "wof:placetype":"venue"
},
  "geometry": {"coordinates":[-115.278007,36.114811],"type":"Point"}
}