{
  "type": "Feature",
  "properties": {
    "iso:country":"US",
    "sg:address":"276 N Whitmore St",
    "sg:city":"Overton",
    "sg:classifiers":[
        {
            "category":"Real Estate",
            "subcategory":"Real Estate Operator",
            "type":"Services"
        }
    ],
    "sg:phone":"+1 702 397 8339",
    "sg:postcode":"89040",
    "sg:province":"NV",
    "sg:tags":[
        "mobile",
        "home",
        "community"
    ],
    "wof:name":"Robinson's Trailer Park",
    "wof:placetype":"venue"
},
  "geometry": {"coordinates":[-114.451691,36.545007],"type":"Point"}
}