{
  "type": "Feature",
  "properties": {
    "iso:country":"US",
    "sg:address":"5069 S McCarran Blvd",
    "sg:city":"Reno",
    "sg:classifiers":[
        {
            "category":"Shopping",
            "subcategory":"Department Store",
            "type":"Retail Goods"
        }
    ],
    "sg:phone":"+1 775 826 7222",
    "sg:postcode":"89502",
    "sg:province":"NV",
    "wof:name":"Stein Mart",
    "wof:placetype":"venue"
},
  "geometry": {"coordinates":[-119.782507,39.477],"type":"Point"}
}