{
  "type": "Feature",
  "properties": {
    "iso:country":"US",
    "sg:address":"8320 W Sahara Ave Ste 140",
    "sg:city":"Las Vegas",
    "sg:classifiers":[
        {
            "category":"Bakery",
            "type":"Food & Drink"
        }
    ],
    "sg:phone":"+1 702 871 6301",
    "sg:postcode":"89117",
    "sg:province":"NV",
    "sg:website":"www.nothingbundtcakes.com",
    "wof:name":"Nothing Bundt Cakes",
    "wof:placetype":"venue"
},
  "geometry": {"coordinates":[-115.272823,36.14405],"type":"Point"}
}