{
  "type": "Feature",
  "properties": {
    "iso:country":"US",
    "sg:address":"1281 Kimmerling Rd",
    "sg:city":"Gardnerville",
    "sg:classifiers":[
        {
            "category":"Cinema",
            "subcategory":"Movie Rental",
            "type":"Entertainment"
        }
    ],
    "sg:phone":"+1 775 265 6111",
    "sg:postcode":"89460",
    "sg:province":"NV",
    "sg:tags":[
        "video",
        "game",
        "leasing"
    ],
    "wof:name":"Video Maniacs",
    "wof:placetype":"venue"
},
  "geometry": {"coordinates":[-119.743808,38.895491],"type":"Point"}
}