{
  "type": "Feature",
  "properties": {
    "iso:country":"US",
    "sg:address":"3281 Wisteria Tree St",
    "sg:city":"Las Vegas",
    "sg:classifiers":[
        {
            "category":"Utilities",
            "subcategory":"Cable",
            "type":"Services"
        }
    ],
    "sg:phone":"+1 702 254 1752",
    "sg:postcode":"89135",
    "sg:province":"NV",
    "sg:tags":[
        "television"
    ],
    "wof:name":"My TV",
    "wof:placetype":"venue"
},
  "geometry": {"coordinates":[-115.330253,36.131146],"type":"Point"}
}