{
  "type": "Feature",
  "properties": {
    "iso:country":"US",
    "sg:address":"6980 W Tropicana Ave",
    "sg:city":"Las Vegas",
    "sg:classifiers":[
        {
            "category":"Restaurant",
            "type":"Food & Drink"
        }
    ],
    "sg:phone":"+1 702 367 3134",
    "sg:postcode":"89147",
    "sg:province":"NV",
    "sg:tags":[
        "caterer"
    ],
    "wof:name":"F & B Catering",
    "wof:placetype":"venue"
},
  "geometry": {"coordinates":[-115.243513,36.099715],"type":"Point"}
}