{
  "type": "Feature",
  "properties": {
    "iso:country":"US",
    "sg:address":"271 Leisure Cir",
    "sg:city":"Henderson",
    "sg:classifiers":[
        {
            "category":"Education",
            "subcategory":"School",
            "type":"Public Place"
        }
    ],
    "sg:phone":"+1 702 799 8730",
    "sg:postcode":"89074",
    "sg:province":"NV",
    "sg:tags":[
        "high",
        "middle",
        "elementary"
    ],
    "wof:name":"Schools Clark County Public",
    "wof:placetype":"venue"
},
  "geometry": {"coordinates":[-115.072912,36.046842],"type":"Point"}
}