{
  "type": "Feature",
  "properties": {
    "iso:country":"US",
    "sg:address":"1333 N Buffalo Dr Ste 120",
    "sg:city":"Las Vegas",
    "sg:classifiers":[
        {
            "category":"Real Estate",
            "subcategory":"Real Estate Services",
            "type":"Services"
        }
    ],
    "sg:phone":"+1 702 787 1023",
    "sg:postcode":"89128",
    "sg:province":"NV",
    "sg:website":"www.virtusco.com/",
    "wof:name":"Virtus Commercial",
    "wof:placetype":"venue"
},
  "geometry": {"coordinates":[-115.26076399999999,36.185572],"type":"Point"}
}