{
  "type": "Feature",
  "properties": {
    "iso:country":"US",
    "sg:address":"1930 Village Center Cir",
    "sg:city":"Las Vegas",
    "sg:classifiers":[
        {
            "category":"Real Estate",
            "subcategory":"Real Estate Services",
            "type":"Services"
        }
    ],
    "sg:phone":"+1 702 645 1210",
    "sg:postcode":"89134",
    "sg:province":"NV",
    "sg:tags":[
        "management",
        "property"
    ],
    "wof:name":"Adept Management Services",
    "wof:placetype":"venue"
},
  "geometry": {"coordinates":[-115.304096,36.192919],"type":"Point"}
}