{
  "type": "Feature",
  "properties": {
    "iso:country":"US",
    "sg:address":"1825 E Warm Springs Road",
    "sg:city":"Las Vegas",
    "sg:classifiers":[
        {
            "category":"Shopping",
            "subcategory":"Pharmacy",
            "type":"Retail Goods"
        }
    ],
    "sg:phone":"+1 702 361 6581",
    "sg:postcode":"89119",
    "sg:province":"NV",
    "sg:tags":[
        "drugstore"
    ],
    "sg:website":"www.cvs.com",
    "wof:name":"Cvs Pharmacy",
    "wof:placetype":"venue"
},
  "geometry": {"coordinates":[-115.12733,36.057718],"type":"Point"}
}