{
  "type": "Feature",
  "properties": {
    "iso:country":"US",
    "sg:address":"6370 W Flamingo Rd",
    "sg:city":"Las Vegas",
    "sg:classifiers":[
        {
            "category":"Real Estate",
            "subcategory":"Real Estate Agent",
            "type":"Services"
        }
    ],
    "sg:phone":"+1 702 631 1100",
    "sg:postcode":"89103",
    "sg:province":"NV",
    "wof:name":"Home Finders Inc",
    "wof:placetype":"venue"
},
  "geometry": {"coordinates":[-115.232439,36.114598],"type":"Point"}
}