{
  "type": "Feature",
  "properties": {
    "iso:country":"US",
    "sg:address":"935 Topsy Ln Ste 430",
    "sg:city":"Carson City",
    "sg:classifiers":[
        {
            "category":"Shopping",
            "subcategory":"Computers & Home Electronics",
            "type":"Retail Goods"
        }
    ],
    "sg:phone":"+1 775 267 0770",
    "sg:postcode":"89705",
    "sg:province":"NV",
    "wof:name":"J & S Digital Satellite",
    "wof:placetype":"venue"
},
  "geometry": {"coordinates":[-119.777714,39.110092],"type":"Point"}
}