{
  "type": "Feature",
  "properties": {
    "iso:country":"US",
    "sg:address":"825 N Lamb Blvd",
    "sg:city":"Las Vegas",
    "sg:classifiers":[
        {
            "category":"Real Estate",
            "subcategory":"Real Estate Operator",
            "type":"Services"
        }
    ],
    "sg:phone":"+1 702 452 7002",
    "sg:postcode":"89110",
    "sg:province":"NV",
    "sg:tags":[
        "mobile",
        "home",
        "site"
    ],
    "wof:name":"El Adobe Estates",
    "wof:placetype":"venue"
},
  "geometry": {"coordinates":[-115.08032900000001,36.177377],"type":"Point"}
}