{
  "type": "Feature",
  "properties": {
    "iso:country":"US",
    "sg:address":"5175 W Diablo Dr",
    "sg:city":"Las Vegas",
    "sg:classifiers":[
        {
            "category":"Wholesale",
            "subcategory":"Groceries",
            "type":"Manufacturing & Wholesale Goods"
        }
    ],
    "sg:phone":"+1 702 312 3380",
    "sg:postcode":"89118",
    "sg:province":"NV",
    "sg:tags":[
        "beverage"
    ],
    "wof:name":"Boss Beverage",
    "wof:placetype":"venue"
},
  "geometry": {"coordinates":[-115.208364,36.089883],"type":"Point"}
}