{
  "type": "Feature",
  "properties": {
    "iso:country":"US",
    "sg:address":"290 S Decatur Blvd",
    "sg:city":"Las Vegas",
    "sg:classifiers":[
        {
            "category":"Shopping",
            "subcategory":"Hobbies, Toys, & Games",
            "type":"Retail Goods"
        }
    ],
    "sg:phone":"+1 702 451 7662",
    "sg:postcode":"89107",
    "sg:province":"NV",
    "sg:tags":[
        "craft",
        "supply"
    ],
    "sg:website":"www.dickblick.com",
    "wof:name":"Dick Blick Art Materials",
    "wof:placetype":"venue"
},
  "geometry": {"coordinates":[-115.206057,36.171588],"type":"Point"}
}