{
  "type": "Feature",
  "properties": {
    "iso:country":"US",
    "sg:address":"990 Rhode Island Dr",
    "sg:city":"Reno",
    "sg:classifiers":[
        {
            "category":"Home & Garden",
            "subcategory":"Carpets & Floor Coverings",
            "type":"Retail Goods"
        }
    ],
    "sg:phone":"+1 775 331 1949",
    "sg:postcode":"89503",
    "sg:province":"NV",
    "wof:name":"Carpet Repair",
    "wof:placetype":"venue"
},
  "geometry": {"coordinates":[-119.846436,39.530394],"type":"Point"}
}