{
  "type": "Feature",
  "properties": {
    "iso:country":"US",
    "sg:address":"2900 E Desert Inn Road",
    "sg:city":"Las Vegas",
    "sg:classifiers":[
        {
            "category":"Health Services",
            "subcategory":"Doctor",
            "type":"Services"
        }
    ],
    "sg:phone":"+1 702 731 0933",
    "sg:postcode":"89121",
    "sg:province":"NV",
    "sg:tags":[
        "dermatologist"
    ],
    "wof:name":"Social Diseases Institute",
    "wof:placetype":"venue"
},
  "geometry": {"coordinates":[-115.110885,36.129797],"type":"Point"}
}