{
  "type": "Feature",
  "properties": {
    "iso:country":"US",
    "sg:address":"905 S Grand Central Parkway",
    "sg:city":"Las Vegas",
    "sg:classifiers":[
        {
            "category":"Shopping",
            "subcategory":"Shoes",
            "type":"Retail Goods"
        }
    ],
    "sg:phone":"+1 702 383 4061",
    "sg:postcode":"89106",
    "sg:province":"NV",
    "sg:tags":[
        "store"
    ],
    "wof:name":"Skechers USA",
    "wof:placetype":"venue"
},
  "geometry": {"coordinates":[-115.158494,36.15981],"type":"Point"}
}