{
  "type": "Feature",
  "properties": {
    "iso:country":"US",
    "sg:address":"1221 Inca Ln",
    "sg:city":"Henderson",
    "sg:classifiers":[
        {
            "category":"Professional",
            "subcategory":"Business Services",
            "type":"Services"
        }
    ],
    "sg:phone":"+1 702 566 5575",
    "sg:postcode":"89015",
    "sg:province":"NV",
    "sg:tags":[
        "recording",
        "studio"
    ],
    "wof:name":"Las Vegas Audio Taping",
    "wof:placetype":"venue"
},
  "geometry": {"coordinates":[-114.959111,36.063509],"type":"Point"}
}