{
  "type": "Feature",
  "properties": {
    "iso:country":"US",
    "sg:address":"5608 Churchill St",
    "sg:city":"Las Vegas",
    "sg:classifiers":[
        {
            "category":"Professional",
            "subcategory":"Business Services",
            "type":"Services"
        }
    ],
    "sg:phone":"+1 702 399 3024",
    "sg:postcode":"89107",
    "sg:province":"NV",
    "wof:name":"Villanueva Group Inc",
    "wof:placetype":"venue"
},
  "geometry": {"coordinates":[-115.21856099999999,36.172686],"type":"Point"}
}