{
  "type": "Feature",
  "properties": {
    "iso:country":"US",
    "sg:address":"2015 Carroll St",
    "sg:city":"North Las Vegas",
    "sg:classifiers":[
        {
            "category":"Real Estate",
            "subcategory":"Real Estate Agent",
            "type":"Services"
        }
    ],
    "sg:phone":"+1 702 642 7700",
    "sg:postcode":"89030",
    "sg:province":"NV",
    "wof:name":"Shamrock Real Estate Services",
    "wof:placetype":"venue"
},
  "geometry": {"coordinates":[-115.115797,36.196046],"type":"Point"}
}