{
  "type": "Feature",
  "properties": {
    "iso:country":"US",
    "sg:address":"2410 E Gowan Rd",
    "sg:city":"North Las Vegas",
    "sg:classifiers":[
        {
            "category":"Building & Trades",
            "subcategory":"Construction",
            "type":"Services"
        }
    ],
    "sg:phone":"+1 702 365 1145",
    "sg:postcode":"89030",
    "sg:province":"NV",
    "sg:tags":[
        "contractor"
    ],
    "wof:name":"Rock Solutions Inc",
    "wof:placetype":"venue"
},
  "geometry": {"coordinates":[-115.112884,36.225065],"type":"Point"}
}