{
  "type": "Feature",
  "properties": {
    "iso:country":"US",
    "sg:address":"4041 Springhill Ave",
    "sg:city":"Las Vegas",
    "sg:classifiers":[
        {
            "category":"Shopping",
            "subcategory":"Hobbies, Toys, & Games",
            "type":"Retail Goods"
        }
    ],
    "sg:phone":"+1 702 456 8465",
    "sg:postcode":"89121",
    "sg:province":"NV",
    "sg:tags":[
        "equipment",
        "ceramic",
        "supply"
    ],
    "wof:name":"Juanita's Niche",
    "wof:placetype":"venue"
},
  "geometry": {"coordinates":[-115.084047,36.109751],"type":"Point"}
}