{
  "type": "Feature",
  "properties": {
    "iso:country":"US",
    "sg:address":"3200 Ferndale St",
    "sg:city":"Las Vegas",
    "sg:classifiers":[
        {
            "category":"Social Services",
            "subcategory":"Child Care",
            "type":"Services"
        },
        {
            "category":"Recreation",
            "type":"Entertainment"
        }
    ],
    "sg:phone":"+1 702 455 7517",
    "sg:postcode":"89121",
    "sg:province":"NV",
    "sg:tags":[
        "day",
        "hall",
        "auditorium"
    ],
    "sg:website":"www.co.clark.nv.us",
    "wof:name":"Parkdale Community Center",
    "wof:placetype":"venue"
},
  "geometry": {"coordinates":[-115.077448,36.130193],"type":"Point"}
}