{
  "type": "Feature",
  "properties": {
    "iso:country":"US",
    "sg:address":"850 E Cave Ave",
    "sg:city":"Overton",
    "sg:classifiers":[
        {
            "category":"Building & Trades",
            "subcategory":"Construction",
            "type":"Services"
        }
    ],
    "sg:phone":"+1 702 397 2294",
    "sg:postcode":"89040",
    "sg:province":"NV",
    "sg:tags":[
        "contractor"
    ],
    "wof:name":"DHR Construction",
    "wof:placetype":"venue"
},
  "geometry": {"coordinates":[-114.425406,36.557701],"type":"Point"}
}