{
  "type": "Feature",
  "properties": {
    "iso:country":"US",
    "sg:address":"9435 W Tropicana Ave",
    "sg:city":"Las Vegas",
    "sg:classifiers":[
        {
            "category":"Insurance",
            "subcategory":"Insurance Agent",
            "type":"Services"
        }
    ],
    "sg:phone":"+1 702 341 1500",
    "sg:postcode":"89147",
    "sg:province":"NV",
    "wof:name":"Allstate Insurance",
    "wof:placetype":"venue"
},
  "geometry": {"coordinates":[-115.309988,36.100211],"type":"Point"}
}