{
  "type": "Feature",
  "properties": {
    "iso:country":"US",
    "sg:address":"1700 S Main St",
    "sg:city":"Las Vegas",
    "sg:classifiers":[
        {
            "category":"Banks & Credit Unions",
            "subcategory":"Financial Services",
            "type":"Services"
        }
    ],
    "sg:phone":"+1 702 385 5363",
    "sg:postcode":"89104",
    "sg:province":"NV",
    "sg:tags":[
        "broker",
        "mortgage"
    ],
    "wof:name":"Nevada Credit & Lend Inc",
    "wof:placetype":"venue"
},
  "geometry": {"coordinates":[-115.153999,36.1511],"type":"Point"}
}