{
  "type": "Feature",
  "properties": {
    "iso:country":"US",
    "sg:address":"925 Riverside Dr",
    "sg:city":"Reno",
    "sg:classifiers":[
        {
            "category":"Arts & Performance",
            "subcategory":"Theater",
            "type":"Entertainment"
        }
    ],
    "sg:phone":"+1 775 323 6393",
    "sg:postcode":"89503",
    "sg:province":"NV",
    "sg:tags":[
        "band",
        "orchestra",
        "group"
    ],
    "sg:website":"www.renophil.com",
    "wof:name":"Reno Philharmonic",
    "wof:placetype":"venue"
},
  "geometry": {"coordinates":[-119.824138,39.520748],"type":"Point"}
}