{
  "type": "Feature",
  "properties": {
    "iso:country":"US",
    "sg:address":"7730 W Sahara Avenue",
    "sg:city":"Las Vegas",
    "sg:classifiers":[
        {
            "category":"Real Estate",
            "subcategory":"Architect",
            "type":"Services"
        }
    ],
    "sg:phone":"+1 702 365 9838",
    "sg:postcode":"89117",
    "sg:province":"NV",
    "wof:name":"Sherman Architecture",
    "wof:placetype":"venue"
},
  "geometry": {"coordinates":[-115.25937999999999,36.143816],"type":"Point"}
}