{
  "type": "Feature",
  "properties": {
    "iso:country":"US",
    "sg:address":"5485 Tolentino Dr",
    "sg:city":"Las Vegas",
    "sg:classifiers":[
        {
            "category":"Building & Trades",
            "subcategory":"Plumbing",
            "type":"Services"
        }
    ],
    "sg:phone":"+1 702 452 2931",
    "sg:postcode":"89156",
    "sg:province":"NV",
    "sg:tags":[
        "contractor"
    ],
    "wof:name":"Southern Nevada Plumbing Inc",
    "wof:placetype":"venue"
},
  "geometry": {"coordinates":[-115.0534,36.209349],"type":"Point"}
}