{
  "type": "Feature",
  "properties": {
    "iso:country":"US",
    "sg:address":"900 Deming Way",
    "sg:city":"Sparks",
    "sg:classifiers":[
        {
            "category":"Education",
            "subcategory":"Dance Studio",
            "type":"Public Place"
        }
    ],
    "sg:phone":"+1 775 358 0800",
    "sg:postcode":"89431",
    "sg:province":"NV",
    "sg:tags":[
        "instruction",
        "dancing"
    ],
    "wof:name":"Danceworks",
    "wof:placetype":"venue"
},
  "geometry": {"coordinates":[-119.722055,39.525373],"type":"Point"}
}