{
  "type": "Feature",
  "properties": {
    "iso:country":"US",
    "sg:address":"357 S Bridge St",
    "sg:city":"Winnemucca",
    "sg:classifiers":[
        {
            "category":"Personal",
            "subcategory":"Beauty Salon",
            "type":"Services"
        }
    ],
    "sg:phone":"+1 775 625 1800",
    "sg:postcode":"89445",
    "sg:province":"NV",
    "sg:tags":[
        "shop"
    ],
    "wof:name":"Elite Nails",
    "wof:placetype":"venue"
},
  "geometry": {"coordinates":[-117.734215,40.973212],"type":"Point"}
}