{
  "type": "Feature",
  "properties": {
    "iso:country":"US",
    "sg:address":"7008 W Charleston Blvd",
    "sg:city":"Las Vegas",
    "sg:classifiers":[
        {
            "category":"Building & Trades",
            "subcategory":"Construction",
            "type":"Services"
        }
    ],
    "sg:phone":"+1 702 228 6515",
    "sg:postcode":"89117",
    "sg:province":"NV",
    "sg:tags":[
        "builder",
        "custom",
        "contractor"
    ],
    "wof:name":"Custom Built Contractors Inc",
    "wof:placetype":"venue"
},
  "geometry": {"coordinates":[-115.25236,36.159181],"type":"Point"}
}