{
  "type": "Feature",
  "properties": {
    "iso:country":"US",
    "sg:address":"2885 Horseshoe Dr",
    "sg:city":"Las Vegas",
    "sg:classifiers":[
        {
            "category":"Food & Beverages",
            "subcategory":"Bakery",
            "type":"Retail Goods"
        }
    ],
    "sg:phone":"+1 702 378 2979",
    "sg:postcode":"89120",
    "sg:province":"NV",
    "wof:name":"Cookies By Joannie LLC",
    "wof:placetype":"venue"
},
  "geometry": {"coordinates":[-115.110351,36.088133],"type":"Point"}
}