{
  "type": "Feature",
  "properties": {
    "iso:country":"US",
    "sg:address":"3751 Mill St",
    "sg:city":"Reno",
    "sg:classifiers":[
        {
            "category":"Shopping",
            "type":"Retail Goods"
        },
        {
            "category":"Professional",
            "subcategory":"Business Services",
            "type":"Services"
        }
    ],
    "sg:phone":"+1 775 322 5001",
    "sg:postcode":"89502",
    "sg:province":"NV",
    "sg:tags":[
        "plant",
        "flower",
        "design",
        "maintenance",
        "artificial"
    ],
    "wof:name":"Plantworks - Reno",
    "wof:placetype":"venue"
},
  "geometry": {"coordinates":[-119.761955,39.516151],"type":"Point"}
}