{
  "type": "Feature",
  "properties": {
    "iso:country":"US",
    "sg:address":"3790 Las Vegas Blvd S",
    "sg:city":"Las Vegas",
    "sg:classifiers":[
        {
            "category":"Sports & Exercise",
            "subcategory":"Swimming Pool",
            "type":"Entertainment"
        }
    ],
    "sg:phone":"+1 866 815 4365",
    "sg:postcode":"89109",
    "sg:province":"NV",
    "sg:website":"www.nynyhotelcasino.com/amenitie...",
    "wof:name":"Pool at New York New York",
    "wof:placetype":"venue"
},
  "geometry": {"coordinates":[-115.174634,36.102099],"type":"Point"}
}