{
  "type": "Feature",
  "properties": {
    "iso:country":"US",
    "sg:address":"2665 Sorrel St",
    "sg:city":"Las Vegas",
    "sg:classifiers":[
        {
            "category":"Banks & Credit Unions",
            "subcategory":"Financial Services",
            "type":"Services"
        }
    ],
    "sg:phone":"+1 702 876 2124",
    "sg:postcode":"89146",
    "sg:province":"NV",
    "sg:tags":[
        "investor"
    ],
    "wof:name":"October 22nd Investors Lt",
    "wof:placetype":"venue"
},
  "geometry": {"coordinates":[-115.236223,36.141621],"type":"Point"}
}