{
  "type": "Feature",
  "properties": {
    "iso:country":"US",
    "sg:address":"372 Shadow Ln",
    "sg:city":"Fernley",
    "sg:classifiers":[
        {
            "category":"Shopping",
            "subcategory":"Bicycles & Sporting Goods",
            "type":"Retail Goods"
        }
    ],
    "sg:phone":"+1 775 575 3653",
    "sg:postcode":"89408",
    "sg:province":"NV",
    "wof:name":"H&H Gun Sales & Repair",
    "wof:placetype":"venue"
},
  "geometry": {"coordinates":[-119.244691,39.598815],"type":"Point"}
}