{
  "type": "Feature",
  "properties": {
    "iso:country":"US",
    "sg:address":"4021 S Decatur Blvd",
    "sg:city":"Las Vegas",
    "sg:classifiers":[
        {
            "category":"Home & Garden",
            "subcategory":"Home Furnishings",
            "type":"Retail Goods"
        }
    ],
    "sg:phone":"+1 702 876 2233",
    "sg:postcode":"89103",
    "sg:province":"NV",
    "wof:name":"Pier 1 Imports 857",
    "wof:placetype":"venue"
},
  "geometry": {"coordinates":[-115.208139,36.116554],"type":"Point"}
}