{
  "type": "Feature",
  "properties": {
    "iso:country":"US",
    "sg:address":"2877 Paradise Rd #706",
    "sg:city":"Las Vegas",
    "sg:classifiers":[
        {
            "category":"Professional",
            "subcategory":"Computer Services",
            "type":"Services"
        }
    ],
    "sg:phone":"+1 720 206 0660 ext. 501",
    "sg:postcode":"89109",
    "sg:province":"NV",
    "sg:tags":[
        "finfolio",
        "techfi",
        "advent",
        "portfolio-management",
        "axys",
        "advisor",
        "adviser-planner",
        "money",
        "finance",
        "financial",
        "accounting",
        "account",
        "fund",
        "stock",
        "bond",
        "microsoft",
        "silverlight",
        "open-source",
        "shared-source",
        "rebalance",
        "rebalancing"
    ],
    "sg:website":"http://www.finfolio.com",
    "wof:name":"FinFolio",
    "wof:placetype":"venue"
},
  "geometry": {"coordinates":[-115.15486,36.13977],"type":"Point"}
}