{
  "type": "Feature",
  "properties": {
    "iso:country":"US",
    "sg:address":"1880 Losee Rd",
    "sg:city":"North Las Vegas",
    "sg:classifiers":[
        {
            "category":"Retail",
            "subcategory":"Auto Repair",
            "type":"Services"
        }
    ],
    "sg:phone":"+1 702 382 0087",
    "sg:postcode":"89030",
    "sg:province":"NV",
    "sg:tags":[
        "repairing",
        "automobile"
    ],
    "wof:name":"Mr Auto Svc",
    "wof:placetype":"venue"
},
  "geometry": {"coordinates":[-115.142833,36.192074],"type":"Point"}
}