{
  "type": "Feature",
  "properties": {
    "iso:country":"US",
    "sg:address":"115 Tyrol Way",
    "sg:city":"Las Vegas",
    "sg:classifiers":[
        {
            "category":"Professional",
            "subcategory":"Management & Consulting",
            "type":"Services"
        }
    ],
    "sg:phone":"+1 702 244 8070",
    "sg:postcode":"89124",
    "sg:province":"NV",
    "sg:tags":[
        "business"
    ],
    "wof:name":"Woodencad Designs",
    "wof:placetype":"venue"
},
  "geometry": {"coordinates":[-115.634047,36.256329],"type":"Point"}
}