{
  "type": "Feature",
  "properties": {
    "iso:country":"US",
    "sg:address":"2195 Santa Paula Dr",
    "sg:city":"Las Vegas",
    "sg:classifiers":[
        {
            "category":"Retail",
            "subcategory":"Car Wash",
            "type":"Services"
        }
    ],
    "sg:phone":"+1 702 309 6299",
    "sg:postcode":"89104",
    "sg:province":"NV",
    "sg:tags":[
        "automobile",
        "detail",
        "clean"
    ],
    "wof:name":"Maxximum Detail",
    "wof:placetype":"venue"
},
  "geometry": {"coordinates":[-115.152075,36.145176],"type":"Point"}
}