{
  "type": "Feature",
  "properties": {
    "iso:country":"US",
    "sg:address":"1055 E Flamingo Rd",
    "sg:city":"Las Vegas",
    "sg:classifiers":[
        {
            "category":"Banks & Credit Unions",
            "subcategory":"Bank",
            "type":"Services"
        }
    ],
    "sg:phone":"+1 702 791 2900",
    "sg:postcode":"89119",
    "sg:province":"NV",
    "sg:tags":[
        "company",
        "trust"
    ],
    "wof:name":"Olson Family Trust",
    "wof:placetype":"venue"
},
  "geometry": {"coordinates":[-115.13899,36.114503],"type":"Point"}
}