{
  "type": "Feature",
  "properties": {
    "iso:country":"US",
    "sg:address":"1012 N Rancho Dr",
    "sg:city":"Las Vegas",
    "sg:classifiers":[
        {
            "category":"Personal",
            "subcategory":"Beauty Salon",
            "type":"Services"
        }
    ],
    "sg:phone":"+1 702 636 1442",
    "sg:postcode":"89106",
    "sg:province":"NV",
    "wof:name":"Braids By Sonia",
    "wof:placetype":"venue"
},
  "geometry": {"coordinates":[-115.180151,36.182193],"type":"Point"}
}