{
  "type": "Feature",
  "properties": {
    "iso:country":"US",
    "sg:address":"1516 E Tropicana Ave Ste 100",
    "sg:city":"Las Vegas",
    "sg:classifiers":[
        {
            "category":"Building & Trades",
            "subcategory":"Construction",
            "type":"Services"
        }
    ],
    "sg:phone":"+1 702 898 9777",
    "sg:postcode":"89119",
    "sg:province":"NV",
    "sg:tags":[
        "interior",
        "design"
    ],
    "wof:name":"New Wings",
    "wof:placetype":"venue"
},
  "geometry": {"coordinates":[-115.132091,36.101158],"type":"Point"}
}