{
  "type": "Feature",
  "properties": {
    "iso:country":"US",
    "sg:address":"3111 S Valley View Blvd",
    "sg:city":"Las Vegas",
    "sg:classifiers":[
        {
            "category":"Personal",
            "subcategory":"Beauty Salon",
            "type":"Services"
        }
    ],
    "sg:phone":"+1 702 355 9861",
    "sg:postcode":"89102",
    "sg:province":"NV",
    "wof:name":"Beautiful Image",
    "wof:placetype":"venue"
},
  "geometry": {"coordinates":[-115.19044,36.132927],"type":"Point"}
}