{
  "type": "Feature",
  "properties": {
    "iso:country":"US",
    "sg:address":"6804 Accent Ct",
    "sg:city":"Las Vegas",
    "sg:classifiers":[
        {
            "category":"Professional",
            "subcategory":"Computer Services",
            "type":"Services"
        }
    ],
    "sg:phone":"+1 702 870 9917",
    "sg:postcode":"89108",
    "sg:province":"NV",
    "sg:tags":[
        "programing",
        "custom"
    ],
    "wof:name":"Activant Solutions Inc",
    "wof:placetype":"venue"
},
  "geometry": {"coordinates":[-115.243151,36.239953],"type":"Point"}
}