{
  "type": "Feature",
  "properties": {
    "iso:country":"US",
    "sg:address":"3600 El Conlon Ave Ofc",
    "sg:city":"Las Vegas",
    "sg:classifiers":[
        {
            "category":"Real Estate",
            "subcategory":"Real Estate Operator",
            "type":"Services"
        }
    ],
    "sg:phone":"+1 702 873 7102",
    "sg:postcode":"89102",
    "sg:province":"NV",
    "sg:tags":[
        "apartment"
    ],
    "wof:name":"Sahara View Apts",
    "wof:placetype":"venue"
},
  "geometry": {"coordinates":[-115.189003,36.1427],"type":"Point"}
}