{
  "type": "Feature",
  "properties": {
    "iso:country":"US",
    "sg:address":"264 W Winnie Ln",
    "sg:city":"Carson City",
    "sg:classifiers":[
        {
            "category":"Organizations",
            "subcategory":"Religious Organization",
            "type":"Services"
        }
    ],
    "sg:phone":"+1 775 841 4544",
    "sg:postcode":"89703",
    "sg:province":"NV",
    "sg:tags":[
        "church"
    ],
    "wof:name":"Potters House",
    "wof:placetype":"venue"
},
  "geometry": {"coordinates":[-119.769595,39.179269],"type":"Point"}
}