{
  "type": "Feature",
  "properties": {
    "iso:country":"US",
    "sg:address":"195 E Glendale Ave",
    "sg:city":"Sparks",
    "sg:classifiers":[
        {
            "category":"Retail",
            "subcategory":"Repair Shop",
            "type":"Services"
        }
    ],
    "sg:phone":"+1 775 358 5431",
    "sg:postcode":"89431",
    "sg:province":"NV",
    "sg:tags":[
        "marine",
        "mo",
        "outboard",
        "boat",
        "supply"
    ],
    "wof:name":"Sierra Sport & Marine Inc",
    "wof:placetype":"venue"
},
  "geometry": {"coordinates":[-119.740549,39.52738],"type":"Point"}
}