{
  "type": "Feature",
  "properties": {
    "iso:country":"US",
    "sg:address":"4612 Bannister Ln",
    "sg:city":"Las Vegas",
    "sg:classifiers":[
        {
            "category":"Professional",
            "subcategory":"Lawyer & Legal Services",
            "type":"Services"
        }
    ],
    "sg:phone":"+1 702 313 4922",
    "sg:postcode":"89130",
    "sg:province":"NV",
    "sg:tags":[
        "plan"
    ],
    "wof:name":"Pre-Paid Legal Svc Inc",
    "wof:placetype":"venue"
},
  "geometry": {"coordinates":[-115.22776399999999,36.243775],"type":"Point"}
}