{
  "type": "Feature",
  "properties": {
    "iso:country":"US",
    "sg:address":"4496 E Dawley Ct",
    "sg:city":"Las Vegas",
    "sg:classifiers":[
        {
            "category":"Health Services",
            "subcategory":"Clinic",
            "type":"Services"
        }
    ],
    "sg:phone":"+1 702 431 0317",
    "sg:postcode":"89104",
    "sg:province":"NV",
    "sg:tags":[
        "home"
    ],
    "wof:name":"St Francis Homecare One",
    "wof:placetype":"venue"
},
  "geometry": {"coordinates":[-115.076387,36.154977],"type":"Point"}
}