{
  "type": "Feature",
  "properties": {
    "iso:country":"US",
    "sg:address":"10234 James Harbin Ave",
    "sg:city":"Las Vegas",
    "sg:classifiers":[
        {
            "category":"Personal",
            "type":"Services"
        }
    ],
    "sg:phone":"+1 702 240 9106",
    "sg:postcode":"89129",
    "sg:province":"NV",
    "sg:tags":[
        "therapist",
        "massage"
    ],
    "wof:name":"Kristi Black Massage Therapist",
    "wof:placetype":"venue"
},
  "geometry": {"coordinates":[-115.319226,36.228038],"type":"Point"}
}