{
  "type": "Feature",
  "properties": {
    "iso:country":"US",
    "sg:address":"2475 Chandler Ave",
    "sg:city":"Las Vegas",
    "sg:classifiers":[
        {
            "category":"Retail",
            "subcategory":"Repair Shop",
            "type":"Services"
        },
        {
            "category":"Building & Trades",
            "subcategory":"Plumbing",
            "type":"Services"
        }
    ],
    "sg:phone":"+1 702 433 5605",
    "sg:postcode":"89120",
    "sg:province":"NV",
    "sg:tags":[
        "water",
        "equipment",
        "plumbing",
        "softening",
        "contractor"
    ],
    "wof:name":"Colburn Enterprises Inc",
    "wof:placetype":"venue"
},
  "geometry": {"coordinates":[-115.113615,36.073884],"type":"Point"}
}