{
  "type": "Feature",
  "properties": {
    "iso:country":"US",
    "sg:address":"9480 W Lake Mead Blvd",
    "sg:city":"Las Vegas",
    "sg:classifiers":[
        {
            "category":"Fast Food",
            "type":"Food & Drink"
        }
    ],
    "sg:phone":"+1 702 360 8085",
    "sg:postcode":"89134",
    "sg:province":"NV",
    "sg:website":"www.tacobell.com",
    "wof:name":"Taco Bell",
    "wof:placetype":"venue"
},
  "geometry": {"coordinates":[-115.30305199999999,36.206663],"type":"Point"}
}