{
  "type": "Feature",
  "properties": {
    "iso:country":"US",
    "sg:address":"554 W Flamingo Rd",
    "sg:city":"Las Vegas",
    "sg:classifiers":[
        {
            "category":"Retail",
            "subcategory":"Auto Repair",
            "type":"Services"
        }
    ],
    "sg:phone":"+1 702 570 2213",
    "sg:postcode":"89109",
    "sg:province":"NV",
    "sg:website":"www.suvsandtrucksrus.com/",
    "wof:name":"Las Vegas - Suvs and Trucks r us",
    "wof:placetype":"venue"
},
  "geometry": {"coordinates":[-115.17482699999999,36.114837],"type":"Point"}
}