{
  "type": "Feature",
  "properties": {
    "iso:country":"US",
    "sg:address":"1652 State Hwy 88",
    "sg:city":"Minden",
    "sg:classifiers":[
        {
            "category":"Insurance",
            "subcategory":"Insurance Agent",
            "type":"Services"
        }
    ],
    "sg:phone":"+1 775 783 8707",
    "sg:postcode":"89423",
    "sg:province":"NV",
    "wof:name":"Lambin Insurance Services Inc",
    "wof:placetype":"venue"
},
  "geometry": {"coordinates":[-119.779405,38.952106],"type":"Point"}
}