{
  "type": "Feature",
  "properties": {
    "iso:country":"US",
    "sg:address":"110 W Arroyo St",
    "sg:city":"Reno",
    "sg:classifiers":[
        {
            "category":"Professional",
            "subcategory":"Computer Services",
            "type":"Services"
        }
    ],
    "sg:phone":"+1 775 324 7005",
    "sg:postcode":"89509",
    "sg:province":"NV",
    "sg:tags":[
        "consultant",
        "designer"
    ],
    "sg:website":"www.advlantech.com",
    "wof:name":"Advanced Lan Technologies Inc",
    "wof:placetype":"venue"
},
  "geometry": {"coordinates":[-119.809291,39.511475],"type":"Point"}
}