{
  "type": "Feature",
  "properties": {
    "iso:country":"US",
    "sg:address":"750 S Rampart Boulevard",
    "sg:city":"Las Vegas",
    "sg:classifiers":[
        {
            "category":"Shopping",
            "subcategory":"Jewelry",
            "type":"Retail Goods"
        }
    ],
    "sg:phone":"+1 702 932 9007",
    "sg:postcode":"89145",
    "sg:province":"NV",
    "wof:name":"Ultra Diamonds",
    "wof:placetype":"venue"
},
  "geometry": {"coordinates":[-115.2906,36.164035],"type":"Point"}
}