{
  "type": "Feature",
  "properties": {
    "iso:country":"US",
    "sg:address":"4030 W Winnemucca Blvd",
    "sg:city":"Winnemucca",
    "sg:classifiers":[
        {
            "category":"Manufacturing",
            "subcategory":"Glass & Minerals",
            "type":"Manufacturing & Wholesale Goods"
        }
    ],
    "sg:phone":"+1 775 623 5232",
    "sg:postcode":"89445",
    "sg:province":"NV",
    "sg:tags":[
        "ready",
        "concrete",
        "mfg"
    ],
    "wof:name":"Humboldt Ready Mix Inc",
    "wof:placetype":"venue"
},
  "geometry": {"coordinates":[-117.765902,40.94475],"type":"Point"}
}