{
  "type": "Feature",
  "properties": {
    "iso:country":"US",
    "sg:address":"101 S Rainbow Blvd",
    "sg:city":"Las Vegas",
    "sg:classifiers":[
        {
            "category":"Shopping",
            "subcategory":"Bicycles & Sporting Goods",
            "type":"Retail Goods"
        },
        {
            "category":"Shopping",
            "subcategory":"Clothing, Apparel, & Fashions",
            "type":"Retail Goods"
        }
    ],
    "sg:phone":"+1 702 878 2284",
    "sg:postcode":"89145",
    "sg:province":"NV",
    "wof:name":"Sportco Sporting Goods Inc",
    "wof:placetype":"venue"
},
  "geometry": {"coordinates":[-115.244328,36.170539],"type":"Point"}
}