{
  "type": "Feature",
  "properties": {
    "iso:country":"US",
    "sg:address":"1625 Sabatini Dr",
    "sg:city":"Henderson",
    "sg:classifiers":[
        {
            "category":"Home & Garden",
            "subcategory":"Home Furnishings",
            "type":"Retail Goods"
        }
    ],
    "sg:phone":"+1 702 227 1557",
    "sg:postcode":"89052",
    "sg:province":"NV",
    "wof:name":"Desert Dreams Enterprise",
    "wof:placetype":"venue"
},
  "geometry": {"coordinates":[-115.118463,35.97413],"type":"Point"}
}