{
  "type": "Feature",
  "properties": {
    "iso:country":"US",
    "sg:address":"2385 E Tropicana Avenue",
    "sg:city":"Las Vegas",
    "sg:classifiers":[
        {
            "category":"Retail",
            "subcategory":"Veterinary Services",
            "type":"Services"
        }
    ],
    "sg:phone":"+1 702 736 4944",
    "sg:postcode":"89119",
    "sg:province":"NV",
    "sg:tags":[
        "veterinarian"
    ],
    "wof:name":"Ezell Randall DVM",
    "wof:placetype":"venue"
},
  "geometry": {"coordinates":[-115.120068,36.100119],"type":"Point"}
}