{
  "type": "Feature",
  "properties": {
    "iso:country":"US",
    "sg:address":"9017 Little Horse Ave",
    "sg:city":"Las Vegas",
    "sg:classifiers":[
        {
            "category":"Personal",
            "type":"Services"
        }
    ],
    "sg:phone":"+1 702 378 5867",
    "sg:postcode":"89143",
    "sg:province":"NV",
    "sg:tags":[
        "party",
        "planning",
        "event"
    ],
    "sg:website":"www.affordablejumperslv.com",
    "wof:name":"Affordable Jumpers",
    "wof:placetype":"venue"
},
  "geometry": {"coordinates":[-115.29259,36.314941],"type":"Point"}
}