{
  "type": "Feature",
  "properties": {
    "iso:country":"US",
    "sg:address":"1005 Terminal Way",
    "sg:city":"Reno",
    "sg:classifiers":[
        {
            "category":"Professional",
            "subcategory":"Management & Consulting",
            "type":"Services"
        }
    ],
    "sg:phone":"+1 775 322 5901",
    "sg:postcode":"89502",
    "sg:province":"NV",
    "sg:tags":[
        "hydrologist"
    ],
    "wof:name":"Water Management Consultants",
    "wof:placetype":"venue"
},
  "geometry": {"coordinates":[-119.777355,39.514625],"type":"Point"}
}