{
  "type": "Feature",
  "properties": {
    "iso:country":"US",
    "sg:address":"1750 S Rainbow Blvd",
    "sg:city":"Las Vegas",
    "sg:classifiers":[
        {
            "category":"Shopping",
            "subcategory":"Clothing, Apparel, & Fashions",
            "type":"Retail Goods"
        }
    ],
    "sg:phone":"+1 702 870 0602",
    "sg:postcode":"89146",
    "sg:province":"NV",
    "sg:tags":[
        "navy",
        "army"
    ],
    "wof:name":"Army Navy Surplus",
    "wof:placetype":"venue"
},
  "geometry": {"coordinates":[-115.243172,36.150692],"type":"Point"}
}