{
  "type": "Feature",
  "properties": {
    "iso:country":"US",
    "sg:address":"201 Wonder St",
    "sg:city":"Reno",
    "sg:classifiers":[
        {
            "category":"Building & Trades",
            "subcategory":"Construction",
            "type":"Services"
        }
    ],
    "sg:phone":"+1 775 324 7974",
    "sg:postcode":"89502",
    "sg:province":"NV",
    "sg:tags":[
        "home",
        "improvement"
    ],
    "wof:name":"R Harding Maintenance",
    "wof:placetype":"venue"
},
  "geometry": {"coordinates":[-119.80316500000001,39.513822],"type":"Point"}
}