{
  "type": "Feature",
  "properties": {
    "iso:country":"US",
    "sg:address":"3027 E Sunset Rd",
    "sg:city":"Las Vegas",
    "sg:classifiers":[
        {
            "category":"Real Estate",
            "subcategory":"Real Estate Agent",
            "type":"Services"
        }
    ],
    "sg:phone":"+1 702 795 3770",
    "sg:postcode":"89120",
    "sg:province":"NV",
    "wof:name":"ARS Management",
    "wof:placetype":"venue"
},
  "geometry": {"coordinates":[-115.10938899999999,36.071473],"type":"Point"}
}