{
  "type": "Feature",
  "properties": {
    "iso:country":"US",
    "sg:address":"2372 Gabriel Dr",
    "sg:city":"Las Vegas",
    "sg:classifiers":[
        {
            "category":"Organizations",
            "subcategory":"Non-profit Organization",
            "type":"Services"
        }
    ],
    "sg:phone":"+1 702 798 5022",
    "sg:postcode":"89119",
    "sg:province":"NV",
    "sg:tags":[
        "information",
        "alcoholism",
        "treatment"
    ],
    "wof:name":"Vision House",
    "wof:placetype":"venue"
},
  "geometry": {"coordinates":[-115.119435,36.10578],"type":"Point"}
}