{
  "type": "Feature",
  "properties": {
    "iso:country":"US",
    "sg:address":"1110 Redwood St",
    "sg:city":"Las Vegas",
    "sg:classifiers":[
        {
            "category":"Professional",
            "subcategory":"Employment Agencies",
            "type":"Services"
        }
    ],
    "sg:phone":"+1 702 880 7029",
    "sg:postcode":"89146",
    "sg:province":"NV",
    "sg:tags":[
        "opportunity"
    ],
    "wof:name":"Fortune Nevada Alliance LLC",
    "wof:placetype":"venue"
},
  "geometry": {"coordinates":[-115.23908,36.15744],"type":"Point"}
}