{
  "type": "Feature",
  "properties": {
    "iso:country":"US",
    "sg:address":"2300 N Rainbow Blvd",
    "sg:city":"Las Vegas",
    "sg:classifiers":[
        {
            "category":"Home & Garden",
            "subcategory":"Household Appliances",
            "type":"Retail Goods"
        }
    ],
    "sg:phone":"+1 702 646 8787",
    "sg:postcode":"89108",
    "sg:province":"NV",
    "sg:tags":[
        "machine",
        "sewing"
    ],
    "wof:name":"Vegas Vacuum & Sewing",
    "wof:placetype":"venue"
},
  "geometry": {"coordinates":[-115.24218500000001,36.201327],"type":"Point"}
}