{
  "type": "Feature",
  "properties": {
    "iso:country":"US",
    "sg:address":"8490 S Eastern Ave",
    "sg:city":"Las Vegas",
    "sg:classifiers":[
        {
            "category":"Building & Trades",
            "subcategory":"Equipment Rental",
            "type":"Services"
        }
    ],
    "sg:phone":"+1 702 361 8065",
    "sg:postcode":"89123",
    "sg:province":"NV",
    "sg:tags":[
        "leasing"
    ],
    "wof:name":"Monarch Commercial",
    "wof:placetype":"venue"
},
  "geometry": {"coordinates":[-115.118246,36.036542],"type":"Point"}
}