{
  "type": "Feature",
  "properties": {
    "iso:country":"US",
    "sg:address":"9175 Moya Blvd",
    "sg:city":"Reno",
    "sg:classifiers":[
        {
            "category":"Shopping",
            "type":"Retail Goods"
        }
    ],
    "sg:phone":"+1 775 677 6080",
    "sg:postcode":"89506",
    "sg:province":"NV",
    "sg:tags":[
        "merchandise",
        "animal"
    ],
    "wof:name":"Petsmart",
    "wof:placetype":"venue"
},
  "geometry": {"coordinates":[-119.91493,39.632342],"type":"Point"}
}