{
  "type": "Feature",
  "properties": {
    "iso:country":"US",
    "sg:address":"2230 W. Bonanza Road",
    "sg:city":"Las Vegas",
    "sg:classifiers":[
        {
            "category":"Restaurant",
            "type":"Food & Drink"
        }
    ],
    "sg:phone":"+1 702 597 1616",
    "sg:postcode":"89106",
    "sg:province":"NV",
    "sg:tags":[
        "southern",
        "barbeque"
    ],
    "sg:website":"www.bigmamaslasvegas.com",
    "wof:name":"Big Mama's Soul Food Rib Shack",
    "wof:placetype":"venue"
},
  "geometry": {"coordinates":[-115.172279,36.177189],"type":"Point"}
}