{
  "type": "Feature",
  "properties": {
    "iso:country":"US",
    "sg:address":"1244 Wyoming St",
    "sg:city":"Boulder City",
    "sg:classifiers":[
        {
            "category":"Retail",
            "subcategory":"Animal Services",
            "type":"Services"
        }
    ],
    "sg:phone":"+1 702 293 6774",
    "sg:postcode":"89005",
    "sg:province":"NV",
    "sg:tags":[
        "pet",
        "grooming",
        "washing"
    ],
    "wof:name":"Hair Of The Dog",
    "wof:placetype":"venue"
},
  "geometry": {"coordinates":[-114.83587900000001,35.976873],"type":"Point"}
}