{
  "type": "Feature",
  "properties": {
    "iso:country":"US",
    "sg:address":"410 E St",
    "sg:city":"Hawthorne",
    "sg:phone":"+1 775 945 5094",
    "sg:postcode":"89415",
    "sg:province":"NV",
    "sg:tags":[
        "gas"
    ],
    "wof:name":"Valley Propane Svc",
    "wof:placetype":"venue"
},
  "geometry": {"coordinates":[-118.62469,38.524292],"type":"Point"}
}