{
  "type": "Feature",
  "properties": {
    "iso:country":"US",
    "sg:address":"3201 Avondale Ave",
    "sg:city":"Las Vegas",
    "sg:classifiers":[
        {
            "category":"Building & Trades",
            "subcategory":"Locksmith",
            "type":"Services"
        }
    ],
    "sg:phone":"+1 702 583 4246",
    "sg:postcode":"89121",
    "sg:province":"NV",
    "sg:tags":[
        "key"
    ],
    "wof:name":"Telcel Com",
    "wof:placetype":"venue"
},
  "geometry": {"coordinates":[-115.081745,36.131382],"type":"Point"}
}