{
  "type": "Feature",
  "properties": {
    "iso:country":"US",
    "sg:address":"300 S Decatur Boulevard",
    "sg:city":"Las Vegas",
    "sg:classifiers":[
        {
            "category":"Shopping",
            "subcategory":"Tobacco",
            "type":"Retail Goods"
        },
        {
            "category":"Personal",
            "subcategory":"Tattoo Parlor",
            "type":"Services"
        }
    ],
    "sg:phone":"+1 702 821 1584",
    "sg:postcode":"89107",
    "sg:province":"NV",
    "sg:tags":[
        "shop"
    ],
    "wof:name":"Diversity Mirked Tattoos",
    "wof:placetype":"venue"
},
  "geometry": {"coordinates":[-115.206205,36.169885],"type":"Point"}
}