{
  "type": "Feature",
  "properties": {
    "iso:country":"US",
    "sg:address":"10490 Blockade Dr",
    "sg:city":"Reno",
    "sg:classifiers":[
        {
            "category":"Professional",
            "subcategory":"Engineering",
            "type":"Services"
        }
    ],
    "sg:phone":"+1 702 461 8121",
    "sg:postcode":"89521",
    "sg:province":"NV",
    "sg:tags":[
        "engineer"
    ],
    "sg:website":"www.stablenets.com",
    "wof:name":"SNS Management",
    "wof:placetype":"venue"
},
  "geometry": {"coordinates":[-119.717567,39.426752],"type":"Point"}
}