{
  "type": "Feature",
  "properties": {
    "iso:country":"US",
    "sg:address":"1940 Idaho St",
    "sg:city":"Elko",
    "sg:classifiers":[
        {
            "category":"Retail",
            "subcategory":"Auto Repair",
            "type":"Services"
        }
    ],
    "sg:phone":"+1 775 753 5969",
    "sg:postcode":"89801",
    "sg:province":"NV",
    "sg:tags":[
        "repairing",
        "automobile"
    ],
    "wof:name":"Chucks Oil City & Auto Glass",
    "wof:placetype":"venue"
},
  "geometry": {"coordinates":[-115.74873599999999,40.846208],"type":"Point"}
}