{
  "type": "Feature",
  "properties": {
    "iso:country":"US",
    "sg:address":"2975 Industrial Rd",
    "sg:city":"Las Vegas",
    "sg:classifiers":[
        {
            "category":"Social Services",
            "subcategory":"Job Training",
            "type":"Services"
        }
    ],
    "sg:phone":"+1 702 791 0890",
    "sg:postcode":"89109",
    "sg:province":"NV",
    "sg:tags":[
        "rehabilitation"
    ],
    "wof:name":"Holgon Hart Care Ctr",
    "wof:placetype":"venue"
},
  "geometry": {"coordinates":[-115.16501599999999,36.14381],"type":"Point"}
}