{
  "type": "Feature",
  "properties": {
    "iso:country":"US",
    "sg:address":"1300 W Sunset Rd Space 2805",
    "sg:city":"Henderson",
    "sg:classifiers":[
        {
            "category":"Fast Food",
            "type":"Food & Drink"
        },
        {
            "category":"Food & Beverages",
            "subcategory":"Meat & Fish",
            "type":"Retail Goods"
        }
    ],
    "sg:postcode":"89014",
    "sg:province":"NV",
    "sg:tags":[
        "hot",
        "dog"
    ],
    "sg:website":"www.hotdogonastick.com",
    "wof:name":"Hot Dog on A Stick",
    "wof:placetype":"venue"
},
  "geometry": {"coordinates":[-115.040233,36.063823],"type":"Point"}
}