{
  "type": "Feature",
  "properties": {
    "iso:country":"US",
    "sg:address":"1470 S Virginia St",
    "sg:city":"Reno",
    "sg:classifiers":[
        {
            "category":"Bars & Pubs",
            "type":"Food & Drink"
        },
        {
            "category":"Restaurant",
            "type":"Food & Drink"
        },
        {
            "category":"Bars & Pubs",
            "subcategory":"Lounge",
            "type":"Food & Drink"
        }
    ],
    "sg:phone":"+1 775 329 9979",
    "sg:postcode":"89502",
    "sg:province":"NV",
    "sg:tags":[
        "american",
        "style",
        "family",
        "cocktail",
        "italian"
    ],
    "wof:name":"Lulou's Restaurant",
    "wof:placetype":"venue"
},
  "geometry": {"coordinates":[-119.805282,39.510031],"type":"Point"}
}