{
  "type": "Feature",
  "properties": {
    "iso:country":"US",
    "sg:address":"6065 Polaris Ave",
    "sg:city":"Las Vegas",
    "sg:classifiers":[
        {
            "category":"Freight",
            "type":"Transportation"
        }
    ],
    "sg:phone":"+1 702 798 1276",
    "sg:postcode":"89118",
    "sg:province":"NV",
    "sg:tags":[
        "trucking"
    ],
    "wof:name":"Western Refrigerated Freight",
    "wof:placetype":"venue"
},
  "geometry": {"coordinates":[-115.185684,36.080119],"type":"Point"}
}