{
  "type": "Feature",
  "properties": {
    "iso:country":"US",
    "sg:address":"4001 S Decatur Blvd Ste 39",
    "sg:city":"Las Vegas",
    "sg:classifiers":[
        {
            "category":"Professional",
            "type":"Services"
        },
        {
            "category":"Restaurant",
            "type":"Food & Drink"
        }
    ],
    "sg:phone":"+1 702 362 7896",
    "sg:postcode":"89103",
    "sg:province":"NV",
    "sg:tags":[
        "pizza",
        "caterer"
    ],
    "sg:website":"www.metropizza.com",
    "wof:name":"Metro Pizza",
    "wof:placetype":"venue"
},
  "geometry": {"coordinates":[-115.2093,36.117202],"type":"Point"}
}