{
  "type": "Feature",
  "properties": {
    "iso:country":"US",
    "sg:address":"2530 Losee Rd",
    "sg:city":"North Las Vegas",
    "sg:classifiers":[
        {
            "category":"Retail",
            "subcategory":"Auto Repair",
            "type":"Services"
        }
    ],
    "sg:phone":"+1 702 649 1637",
    "sg:postcode":"89030",
    "sg:province":"NV",
    "sg:tags":[
        "body",
        "shop"
    ],
    "wof:name":"C & S Body & Fender Shop",
    "wof:placetype":"venue"
},
  "geometry": {"coordinates":[-115.136002,36.2057],"type":"Point"}
}