{
  "type": "Feature",
  "properties": {
    "iso:country":"US",
    "sg:address":"5105 Paola Ct",
    "sg:city":"Las Vegas",
    "sg:classifiers":[
        {
            "category":"Education",
            "subcategory":"Special Training",
            "type":"Public Place"
        }
    ],
    "sg:phone":"+1 702 743 5215",
    "sg:postcode":"89130",
    "sg:province":"NV",
    "sg:tags":[
        "center",
        "learning"
    ],
    "wof:name":"LIFe",
    "wof:placetype":"venue"
},
  "geometry": {"coordinates":[-115.213801,36.265909],"type":"Point"}
}