{
  "type": "Feature",
  "properties": {
    "iso:country":"US",
    "sg:address":"8355 Rancho Destino Road",
    "sg:city":"Las Vegas",
    "sg:classifiers":[
        {
            "category":"Building & Trades",
            "subcategory":"Landscaping Services",
            "type":"Services"
        }
    ],
    "sg:phone":"+1 702 837 5757",
    "sg:postcode":"89123",
    "sg:province":"NV",
    "sg:website":"www.MauriLandscapes.com",
    "wof:name":"Mauri Landscapes",
    "wof:placetype":"venue"
},
  "geometry": {"coordinates":[-115.165465,36.037953],"type":"Point"}
}