{
  "type": "Feature",
  "properties": {
    "iso:country":"US",
    "sg:address":"1159 E Twain Avenue",
    "sg:city":"Las Vegas",
    "sg:classifiers":[
        {
            "category":"Shopping",
            "subcategory":"Clothing, Apparel, & Fashions",
            "type":"Retail Goods"
        }
    ],
    "sg:phone":"+1 702 369 6372",
    "sg:postcode":"89169",
    "sg:province":"NV",
    "sg:tags":[
        "accessory",
        "clothing",
        "women's"
    ],
    "sg:website":"www.susiesdeals.com",
    "wof:name":"Susie's Deals",
    "wof:placetype":"venue"
},
  "geometry": {"coordinates":[-115.138247,36.122151],"type":"Point"}
}