{
  "type": "Feature",
  "properties": {
    "iso:country":"US",
    "sg:address":"5301 Pioneer Avenue",
    "sg:city":"Las Vegas",
    "sg:classifiers":[
        {
            "category":"Real Estate",
            "subcategory":"Real Estate Operator",
            "type":"Services"
        }
    ],
    "sg:phone":"+1 702 871 8848",
    "sg:postcode":"89146",
    "sg:province":"NV",
    "sg:tags":[
        "apartment"
    ],
    "sg:website":"www.montereyparkapt.com",
    "wof:name":"Monterey Park Apartments",
    "wof:placetype":"venue"
},
  "geometry": {"coordinates":[-115.211962,36.127846],"type":"Point"}
}