{
  "type": "Feature",
  "properties": {
    "iso:country":"US",
    "sg:address":"7950 Sugar Pine Way",
    "sg:city":"Reno",
    "sg:classifiers":[
        {
            "category":"Manufacturing",
            "subcategory":"Metals",
            "type":"Manufacturing & Wholesale Goods"
        }
    ],
    "sg:phone":"+1 775 787 6700",
    "sg:postcode":"89523",
    "sg:province":"NV",
    "wof:name":"Sputtering Materials Inc",
    "wof:placetype":"venue"
},
  "geometry": {"coordinates":[-119.896915,39.504215],"type":"Point"}
}