{
  "type": "Feature",
  "properties": {
    "iso:country":"US",
    "sg:address":"1611 Foothill Dr",
    "sg:city":"Boulder City",
    "sg:classifiers":[
        {
            "category":"Retail",
            "subcategory":"Repair Shop",
            "type":"Services"
        }
    ],
    "sg:phone":"+1 702 293 6551",
    "sg:postcode":"89005",
    "sg:province":"NV",
    "sg:tags":[
        "upholsterer"
    ],
    "wof:name":"Jims Custom Upholstery",
    "wof:placetype":"venue"
},
  "geometry": {"coordinates":[-114.85623,35.971617],"type":"Point"}
}