{
  "type": "Feature",
  "properties": {
    "iso:country":"US",
    "sg:address":"4330 S Decatur Blvd",
    "sg:city":"Las Vegas",
    "sg:classifiers":[
        {
            "category":"Home & Garden",
            "subcategory":"Building Materials",
            "type":"Retail Goods"
        }
    ],
    "sg:phone":"+1 702 251 8498",
    "sg:postcode":"89103",
    "sg:province":"NV",
    "sg:tags":[
        "lumber"
    ],
    "sg:website":"www.84lumber.com",
    "wof:name":"84 Lumber Co",
    "wof:placetype":"venue"
},
  "geometry": {"coordinates":[-115.207956,36.110506],"type":"Point"}
}