{
  "type": "Feature",
  "properties": {
    "iso:country":"US",
    "sg:address":"8350 S Rainbow Blvd",
    "sg:city":"Las Vegas",
    "sg:classifiers":[
        {
            "category":"Bars & Pubs",
            "type":"Food & Drink"
        },
        {
            "category":"Restaurant",
            "type":"Food & Drink"
        }
    ],
    "sg:postcode":"89139",
    "sg:province":"NV",
    "sg:tags":[
        "traditional",
        "american"
    ],
    "wof:name":"The Lodge at Shelborne",
    "wof:placetype":"venue"
},
  "geometry": {"coordinates":[-115.243416,36.036693],"type":"Point"}
}