{
  "type": "Feature",
  "properties": {
    "iso:country":"US",
    "sg:address":"1501 S Martin Luther King Blvd",
    "sg:city":"Las Vegas",
    "sg:classifiers":[
        {
            "category":"Government",
            "subcategory":"City Hall",
            "type":"Public Place"
        }
    ],
    "sg:postcode":"89106",
    "sg:province":"NV",
    "sg:website":"www.lasvegasnevada.gov/Governmen...",
    "wof:name":"Las Vegas Fire Rescue Station 10",
    "wof:placetype":"venue"
},
  "geometry": {"coordinates":[-115.160818,36.179019],"type":"Point"}
}