{
  "type": "Feature",
  "properties": {
    "iso:country":"US",
    "sg:address":"1834 Quarley Pl",
    "sg:city":"Henderson",
    "sg:classifiers":[
        {
            "category":"Professional",
            "subcategory":"Computer Services",
            "type":"Services"
        }
    ],
    "sg:phone":"+1 702 547 0686",
    "sg:postcode":"89014",
    "sg:province":"NV",
    "sg:tags":[
        "design",
        "system"
    ],
    "wof:name":"Emerald Web Design",
    "wof:placetype":"venue"
},
  "geometry": {"coordinates":[-115.066428,36.06014],"type":"Point"}
}