{
  "type": "Feature",
  "properties": {
    "iso:country":"US",
    "sg:address":"2255 Renaissance Dr",
    "sg:city":"Las Vegas",
    "sg:classifiers":[
        {
            "category":"Professional",
            "subcategory":"Computer Services",
            "type":"Services"
        }
    ],
    "sg:phone":"+1 702 646 2830",
    "sg:postcode":"89119",
    "sg:province":"NV",
    "sg:tags":[
        "plotter",
        "retail",
        "printer"
    ],
    "wof:name":"Red Star Networks Inc",
    "wof:placetype":"venue"
},
  "geometry": {"coordinates":[-115.122968,36.101969],"type":"Point"}
}