{
  "type": "Feature",
  "properties": {
    "iso:country":"US",
    "sg:address":"3570 Las Vegas Blvd S",
    "sg:city":"Las Vegas",
    "sg:classifiers":[
        {
            "category":"Shopping",
            "subcategory":"Clothing, Apparel, & Fashions",
            "type":"Retail Goods"
        }
    ],
    "sg:phone":"+1 702 732 1331",
    "sg:postcode":"89109",
    "sg:province":"NV",
    "wof:name":"Cuzzens of Caesars Palace",
    "wof:placetype":"venue"
},
  "geometry": {"coordinates":[-115.169916,36.124748],"type":"Point"}
}