{
  "type": "Feature",
  "properties": {
    "iso:country":"US",
    "sg:address":"835 E Desert Inn Rd",
    "sg:city":"Las Vegas",
    "sg:classifiers":[
        {
            "category":"Personal",
            "subcategory":"Hair Removal",
            "type":"Services"
        }
    ],
    "sg:phone":"+1 702 732 2323",
    "sg:postcode":"89109",
    "sg:province":"NV",
    "wof:name":"Highley JD Co",
    "wof:placetype":"venue"
},
  "geometry": {"coordinates":[-115.142049,36.129691],"type":"Point"}
}