{
  "type": "Feature",
  "properties": {
    "iso:country":"US",
    "sg:address":"4355 Cameron St",
    "sg:city":"Las Vegas",
    "sg:classifiers":[
        {
            "category":"Professional",
            "subcategory":"Testing Lab",
            "type":"Services"
        }
    ],
    "sg:phone":"+1 702 251 0202",
    "sg:postcode":"89103",
    "sg:province":"NV",
    "sg:tags":[
        "laboratory"
    ],
    "wof:name":"Davis Laboritories",
    "wof:placetype":"venue"
},
  "geometry": {"coordinates":[-115.204083,36.11098],"type":"Point"}
}