{
  "type": "Feature",
  "properties": {
    "iso:country":"US",
    "sg:address":"868 Tahoe Blvd",
    "sg:city":"Incline Village",
    "sg:classifiers":[
        {
            "category":"Shopping",
            "subcategory":"Jewelry",
            "type":"Retail Goods"
        }
    ],
    "sg:phone":"+1 775 831 6602",
    "sg:postcode":"89451",
    "sg:province":"NV",
    "sg:tags":[
        "jeweler"
    ],
    "wof:name":"Incline Jewelry",
    "wof:placetype":"venue"
},
  "geometry": {"coordinates":[-119.953285,39.249785],"type":"Point"}
}