{
  "type": "Feature",
  "properties": {
    "iso:country":"US",
    "sg:address":"3638 N Rancho Dr",
    "sg:city":"Las Vegas",
    "sg:classifiers":[
        {
            "category":"Professional",
            "subcategory":"Management & Consulting",
            "type":"Services"
        }
    ],
    "sg:phone":"+1 949 306 3542",
    "sg:postcode":"89130",
    "sg:province":"NV",
    "sg:tags":[
        "marketing"
    ],
    "wof:name":"Lagestee Consulting",
    "wof:placetype":"venue"
},
  "geometry": {"coordinates":[-115.220967,36.226864],"type":"Point"}
}