{
  "type": "Feature",
  "properties": {
    "iso:country":"US",
    "sg:address":"1600 Pinto Ln",
    "sg:city":"Las Vegas",
    "sg:classifiers":[
        {
            "category":"Social Services",
            "type":"Services"
        }
    ],
    "sg:phone":"+1 702 455 3894",
    "sg:postcode":"89106",
    "sg:province":"NV",
    "sg:tags":[
        "counseling"
    ],
    "wof:name":"Sudden Infant Death Syndrome",
    "wof:placetype":"venue"
},
  "geometry": {"coordinates":[-115.164404,36.164403],"type":"Point"}
}