{
  "type": "Feature",
  "properties": {
    "iso:country":"US",
    "sg:address":"628 E John St",
    "sg:city":"Carson City",
    "sg:classifiers":[
        {
            "category":"Insurance",
            "subcategory":"Insurance Agent",
            "type":"Services"
        }
    ],
    "sg:phone":"+1 775 827 3700",
    "sg:postcode":"89706",
    "sg:province":"NV",
    "wof:name":"Mutual Of Omaha Insurance Co",
    "wof:placetype":"venue"
},
  "geometry": {"coordinates":[-119.761439,39.171157],"type":"Point"}
}