{
  "type": "Feature",
  "properties": {
    "iso:country":"US",
    "sg:address":"5650 W Charleston Blvd",
    "sg:city":"Las Vegas",
    "sg:classifiers":[
        {
            "category":"Organizations",
            "subcategory":"Labor Organization",
            "type":"Services"
        }
    ],
    "sg:phone":"+1 702 870 1908",
    "sg:postcode":"89146",
    "sg:province":"NV",
    "wof:name":"Internl Assn Fire Fighters",
    "wof:placetype":"venue"
},
  "geometry": {"coordinates":[-115.219379,36.15926],"type":"Point"}
}