{
  "type": "Feature",
  "properties": {
    "iso:country":"US",
    "sg:address":"7150 Haven St Ste 210",
    "sg:city":"Las Vegas",
    "sg:classifiers":[
        {
            "category":"Retail",
            "subcategory":"Auto Rental",
            "type":"Services"
        }
    ],
    "sg:phone":"+1 702 736 6147",
    "sg:postcode":"89119",
    "sg:province":"NV",
    "sg:tags":[
        "car"
    ],
    "sg:website":"www.paylesscarrental.com",
    "wof:name":"Payless Car Rental",
    "wof:placetype":"venue"
},
  "geometry": {"coordinates":[-115.16766,36.058649],"type":"Point"}
}