{
  "type": "Feature",
  "properties": {
    "iso:country":"US",
    "sg:address":"6375 W Charleston Blvd",
    "sg:city":"Las Vegas",
    "sg:classifiers":[
        {
            "category":"Health Services",
            "subcategory":"Doctor",
            "type":"Services"
        }
    ],
    "sg:phone":"+1 702 877 3999",
    "sg:postcode":"89146",
    "sg:province":"NV",
    "sg:tags":[
        "clinic"
    ],
    "wof:name":"Family Practice Ctr",
    "wof:placetype":"venue"
},
  "geometry": {"coordinates":[-115.231739,36.159092],"type":"Point"}
}