{
  "type": "Feature",
  "properties": {
    "iso:country":"US",
    "sg:address":"2442 Millcroft Dr",
    "sg:city":"Henderson",
    "sg:classifiers":[
        {
            "category":"Arts & Performance",
            "subcategory":"Theater",
            "type":"Entertainment"
        }
    ],
    "sg:phone":"+1 702 434 6166",
    "sg:postcode":"89074",
    "sg:province":"NV",
    "sg:tags":[
        "live",
        "music"
    ],
    "wof:name":"Sunset Music DJ",
    "wof:placetype":"venue"
},
  "geometry": {"coordinates":[-115.09643,36.053875],"type":"Point"}
}