{
  "type": "Feature",
  "properties": {
    "iso:country":"US",
    "sg:address":"8090 Blue Diamond Rd",
    "sg:city":"Las Vegas",
    "sg:classifiers":[
        {
            "category":"Restaurant",
            "type":"Food & Drink"
        }
    ],
    "sg:phone":"+1 702 270 0796",
    "sg:postcode":"89178",
    "sg:province":"NV",
    "sg:tags":[
        "pizza",
        "italian"
    ],
    "sg:website":"www.pizzahut.com",
    "wof:name":"Pizza Hut",
    "wof:placetype":"venue"
},
  "geometry": {"coordinates":[-115.26803200000001,36.020305],"type":"Point"}
}