{
  "type": "Feature",
  "properties": {
    "iso:country":"US",
    "sg:address":"2235 E Flamingo Rd",
    "sg:city":"Las Vegas",
    "sg:classifiers":[
        {
            "category":"Banks & Credit Unions",
            "subcategory":"Financial Services",
            "type":"Services"
        }
    ],
    "sg:phone":"+1 702 320 5430",
    "sg:postcode":"89119",
    "sg:province":"NV",
    "sg:tags":[
        "broker",
        "mortgage"
    ],
    "wof:name":"1st 2nd Mortgage Company",
    "wof:placetype":"venue"
},
  "geometry": {"coordinates":[-115.12200199999999,36.114601],"type":"Point"}
}