{
  "type": "Feature",
  "properties": {
    "iso:country":"US",
    "sg:address":"1750 US Hwy 395 N",
    "sg:city":"Minden",
    "sg:classifiers":[
        {
            "category":"Restaurant",
            "type":"Food & Drink"
        }
    ],
    "sg:phone":"+1 775 782 5014",
    "sg:postcode":"89423",
    "sg:province":"NV",
    "sg:tags":[
        "eating"
    ],
    "sg:website":"www.dairyqueen.com",
    "wof:name":"Dairy Queen",
    "wof:placetype":"venue"
},
  "geometry": {"coordinates":[-119.77916399999999,38.969539],"type":"Point"}
}