{
  "type": "Feature",
  "properties": {
    "iso:country":"US",
    "sg:address":"950 Seven Hills Dr",
    "sg:city":"Henderson",
    "sg:classifiers":[
        {
            "category":"Insurance",
            "subcategory":"Insurance Agent",
            "type":"Services"
        }
    ],
    "sg:phone":"+1 702 263 3475",
    "sg:postcode":"89052",
    "sg:province":"NV",
    "wof:name":"Independent Insurance Sales",
    "wof:placetype":"venue"
},
  "geometry": {"coordinates":[-115.122089,35.995345],"type":"Point"}
}