{
  "type": "Feature",
  "properties": {
    "iso:country":"US",
    "sg:address":"328 Fremont St",
    "sg:city":"Las Vegas",
    "sg:classifiers":[
        {
            "category":"Autos & Motor Vehicles",
            "subcategory":"Motorcycle Sales",
            "type":"Retail Goods"
        }
    ],
    "sg:phone":"+1 702 383 1010",
    "sg:postcode":"89101",
    "sg:province":"NV",
    "wof:name":"Trader Bill's",
    "wof:placetype":"venue"
},
  "geometry": {"coordinates":[-115.141998,36.169701],"type":"Point"}
}