{
  "type": "Feature",
  "properties": {
    "iso:country":"US",
    "sg:address":"1685 Sullivan Ln",
    "sg:city":"Sparks",
    "sg:classifiers":[
        {
            "category":"Personal",
            "subcategory":"Beauty Salon",
            "type":"Services"
        }
    ],
    "sg:phone":"+1 775 331 9223",
    "sg:postcode":"89431",
    "sg:province":"NV",
    "sg:tags":[
        "shop"
    ],
    "wof:name":"Yerania Beauty Salon",
    "wof:placetype":"venue"
},
  "geometry": {"coordinates":[-119.771389,39.548099],"type":"Point"}
}