{
  "type": "Feature",
  "properties": {
    "iso:country":"US",
    "sg:address":"924 S Valley View Blvd",
    "sg:city":"Las Vegas",
    "sg:classifiers":[
        {
            "category":"Wholesale",
            "subcategory":"Machinery & Supplies",
            "type":"Manufacturing & Wholesale Goods"
        }
    ],
    "sg:phone":"+1 702 310 4027",
    "sg:postcode":"89107",
    "sg:province":"NV",
    "sg:tags":[
        "equipment",
        "system",
        "vacuum"
    ],
    "wof:name":"AAA Enterpises",
    "wof:placetype":"venue"
},
  "geometry": {"coordinates":[-115.192598,36.16193],"type":"Point"}
}