{
  "type": "Feature",
  "properties": {
    "iso:country":"US",
    "sg:address":"160 Emery St",
    "sg:city":"Pahrump",
    "sg:classifiers":[
        {
            "category":"Professional",
            "subcategory":"Management & Consulting",
            "type":"Services"
        }
    ],
    "sg:phone":"+1 775 727 7472",
    "sg:postcode":"89048",
    "sg:province":"NV",
    "sg:tags":[
        "business"
    ],
    "wof:name":"Sunrise Childrens Foundation",
    "wof:placetype":"venue"
},
  "geometry": {"coordinates":[-115.991448,36.216213],"type":"Point"}
}