{
  "type": "Feature",
  "properties": {
    "iso:country":"US",
    "sg:address":"3100 E Sahara Avenue",
    "sg:city":"Las Vegas",
    "sg:classifiers":[
        {
            "category":"Retail",
            "subcategory":"Auto Rental",
            "type":"Services"
        }
    ],
    "sg:phone":"+1 702 641 7444",
    "sg:postcode":"89104",
    "sg:province":"NV",
    "sg:tags":[
        "car"
    ],
    "sg:website":"www.enterprise.com",
    "wof:name":"Enterprise Rent-A-Car",
    "wof:placetype":"venue"
},
  "geometry": {"coordinates":[-115.10729600000001,36.144309],"type":"Point"}
}