{
  "type": "Feature",
  "properties": {
    "iso:country":"US",
    "sg:address":"3720 W Oquendo Rd",
    "sg:city":"Las Vegas",
    "sg:classifiers":[
        {
            "category":"Professional",
            "type":"Services"
        }
    ],
    "sg:phone":"+1 702 597 2882",
    "sg:postcode":"89118",
    "sg:province":"NV",
    "sg:tags":[
        "caterer"
    ],
    "wof:name":"Mad Food Inc",
    "wof:placetype":"venue"
},
  "geometry": {"coordinates":[-115.189028,36.082771],"type":"Point"}
}