{
  "type": "Feature",
  "properties": {
    "iso:country":"US",
    "sg:address":"9408 del Webb Blvd",
    "sg:city":"Las Vegas",
    "sg:classifiers":[
        {
            "category":"Shopping",
            "subcategory":"Tobacco",
            "type":"Retail Goods"
        }
    ],
    "sg:phone":"+1 702 838 3839",
    "sg:postcode":"89134",
    "sg:province":"NV",
    "sg:tags":[
        "product"
    ],
    "wof:name":"Tobacco Factory",
    "wof:placetype":"venue"
},
  "geometry": {"coordinates":[-115.298319,36.210609],"type":"Point"}
}