{
  "type": "Feature",
  "properties": {
    "iso:country":"US",
    "sg:address":"1140 Corporate Blvd",
    "sg:city":"Reno",
    "sg:classifiers":[
        {
            "category":"Manufacturing",
            "subcategory":"Retail Goods",
            "type":"Manufacturing & Wholesale Goods"
        }
    ],
    "sg:phone":"+1 775 856 1800",
    "sg:postcode":"89502",
    "sg:province":"NV",
    "sg:tags":[
        "for",
        "mfg",
        "industry",
        "specialty",
        "pen",
        "graphics",
        "marker"
    ],
    "wof:name":"Griffin Products Inc",
    "wof:placetype":"venue"
},
  "geometry": {"coordinates":[-119.749888,39.511586],"type":"Point"}
}