{
  "type": "Feature",
  "properties": {
    "iso:country":"US",
    "sg:address":"9046 Hunting Arrow St",
    "sg:city":"Las Vegas",
    "sg:classifiers":[
        {
            "category":"Professional",
            "subcategory":"Accounting & Tax Preparation",
            "type":"Services"
        }
    ],
    "sg:phone":"+1 702 269 9963",
    "sg:postcode":"89123",
    "sg:province":"NV",
    "sg:tags":[
        "bookkeeping",
        "general"
    ],
    "wof:name":"William H Fordney Jr LLC",
    "wof:placetype":"venue"
},
  "geometry": {"coordinates":[-115.159448,36.025937],"type":"Point"}
}