{
  "type": "Feature",
  "properties": {
    "iso:country":"US",
    "sg:address":"4601 E Cheyenne Ave",
    "sg:city":"Las Vegas",
    "sg:classifiers":[
        {
            "category":"Organizations",
            "subcategory":"Labor Organization",
            "type":"Services"
        }
    ],
    "sg:phone":"+1 702 651 0344",
    "sg:postcode":"89115",
    "sg:province":"NV",
    "sg:website":"www.teamsters.org",
    "wof:name":"Southern Nevada Teamster",
    "wof:placetype":"venue"
},
  "geometry": {"coordinates":[-115.07170499999999,36.217654],"type":"Point"}
}