{
  "type": "Feature",
  "properties": {
    "iso:country":"US",
    "sg:address":"2510 Arville St",
    "sg:city":"Las Vegas",
    "sg:classifiers":[
        {
            "category":"Banks & Credit Unions",
            "subcategory":"Bank",
            "type":"Services"
        }
    ],
    "sg:phone":"+1 702 871 6161",
    "sg:postcode":"89102",
    "sg:province":"NV",
    "sg:tags":[
        "loan",
        "real estate"
    ],
    "wof:name":"Sourceone Mortgage",
    "wof:placetype":"venue"
},
  "geometry": {"coordinates":[-115.199867,36.14365],"type":"Point"}
}