{
  "type": "Feature",
  "properties": {
    "iso:country":"US",
    "sg:address":"325 Wildrose Dr",
    "sg:city":"Fernley",
    "sg:classifiers":[
        {
            "category":"Shopping",
            "subcategory":"Gifts & Souvenirs",
            "type":"Retail Goods"
        }
    ],
    "sg:phone":"+1 775 575 7994",
    "sg:postcode":"89408",
    "sg:province":"NV",
    "wof:name":"Old Ways",
    "wof:placetype":"venue"
},
  "geometry": {"coordinates":[-119.233081,39.599096],"type":"Point"}
}