{
  "type": "Feature",
  "properties": {
    "iso:country":"US",
    "sg:address":"1401 S Boulder Hwy",
    "sg:city":"Henderson",
    "sg:classifiers":[
        {
            "category":"Home & Garden",
            "subcategory":"Building Materials",
            "type":"Retail Goods"
        }
    ],
    "sg:phone":"+1 702 568 3494",
    "sg:postcode":"89015",
    "sg:province":"NV",
    "sg:tags":[
        "center"
    ],
    "wof:name":"Lowe's",
    "wof:placetype":"venue"
},
  "geometry": {"coordinates":[-114.971129,36.029916],"type":"Point"}
}