{
  "type": "Feature",
  "properties": {
    "iso:country":"US",
    "sg:address":"3200 Las Vegas Blvd S",
    "sg:city":"Las Vegas",
    "sg:classifiers":[
        {
            "category":"Travel",
            "subcategory":"Travel Agent",
            "type":"Entertainment"
        }
    ],
    "sg:phone":"+1 702 733 3828",
    "sg:postcode":"89109",
    "sg:province":"NV",
    "sg:tags":[
        "agency",
        "bureau"
    ],
    "wof:name":"American Express",
    "wof:placetype":"venue"
},
  "geometry": {"coordinates":[-115.168437,36.126749],"type":"Point"}
}