{
  "type": "Feature",
  "properties": {
    "iso:country":"US",
    "sg:address":"1501 US Hwy 395 N",
    "sg:city":"Gardnerville",
    "sg:classifiers":[
        {
            "category":"Travel",
            "subcategory":"Hotels & Motels",
            "type":"Entertainment"
        }
    ],
    "sg:phone":"+1 775 782 5145",
    "sg:postcode":"89423",
    "sg:province":"NV",
    "wof:name":"Sierra Motel",
    "wof:placetype":"venue"
},
  "geometry": {"coordinates":[-119.76080899999999,38.951156],"type":"Point"}
}