{
  "type": "Feature",
  "properties": {
    "iso:country":"US",
    "sg:address":"3511 Wingrove Ave",
    "sg:city":"Las Vegas",
    "sg:classifiers":[
        {
            "category":"Social Services",
            "subcategory":"Adult Care",
            "type":"Services"
        }
    ],
    "sg:phone":"+1 702 458 8223",
    "sg:postcode":"89121",
    "sg:province":"NV",
    "sg:tags":[
        "home",
        "residential"
    ],
    "wof:name":"Wingrove Family Home",
    "wof:placetype":"venue"
},
  "geometry": {"coordinates":[-115.098296,36.127804],"type":"Point"}
}