{
  "type": "Feature",
  "properties": {
    "iso:country":"US",
    "sg:address":"4242 Fidus",
    "sg:city":"Las Vegas",
    "sg:classifiers":[
        {
            "category":"Professional",
            "subcategory":"Business Services",
            "type":"Services"
        }
    ],
    "sg:phone":"+1 702 220 7379",
    "sg:postcode":"89103",
    "sg:province":"NV",
    "sg:tags":[
        "painter",
        "sign"
    ],
    "wof:name":"Graffiti Graphific",
    "wof:placetype":"venue"
},
  "geometry": {"coordinates":[-115.201041,36.112899],"type":"Point"}
}