{
  "type": "Feature",
  "properties": {
    "iso:country":"US",
    "sg:address":"100 W Liberty St",
    "sg:city":"Reno",
    "sg:classifiers":[
        {
            "category":"Professional",
            "subcategory":"Lawyer & Legal Services",
            "type":"Services"
        }
    ],
    "sg:phone":"+1 775 327 3000",
    "sg:postcode":"89501",
    "sg:province":"NV",
    "sg:tags":[
        "attorney"
    ],
    "wof:name":"Hale Lane Peek Dennison Howard",
    "wof:placetype":"venue"
},
  "geometry": {"coordinates":[-119.813885,39.521288],"type":"Point"}
}