{
  "type": "Feature",
  "properties": {
    "iso:country":"US",
    "sg:address":"4350 Arville St Ste 15",
    "sg:city":"Las Vegas",
    "sg:classifiers":[
        {
            "category":"Shopping",
            "subcategory":"Clothing, Apparel, & Fashions",
            "type":"Retail Goods"
        }
    ],
    "sg:phone":"+1 702 362 3000",
    "sg:postcode":"89103",
    "sg:province":"NV",
    "sg:tags":[
        "costume"
    ],
    "sg:website":"www.farringtonproductions.com",
    "wof:name":"Farrington Productions Inc",
    "wof:placetype":"venue"
},
  "geometry": {"coordinates":[-115.19809600000001,36.110882],"type":"Point"}
}