{
  "type": "Feature",
  "properties": {
    "iso:country":"US",
    "sg:address":"9480 W Tropical Parkway",
    "sg:city":"Las Vegas",
    "sg:classifiers":[
        {
            "category":"Education",
            "subcategory":"School",
            "type":"Public Place"
        }
    ],
    "sg:phone":"+1 702 799 6630",
    "sg:postcode":"89149",
    "sg:province":"NV",
    "wof:name":"Clark County School District",
    "wof:placetype":"venue"
},
  "geometry": {"coordinates":[-115.303421,36.270042],"type":"Point"}
}