{
  "type": "Feature",
  "properties": {
    "iso:country":"US",
    "sg:address":"330 Emery St",
    "sg:city":"Pahrump",
    "sg:classifiers":[
        {
            "category":"Arts & Performance",
            "subcategory":"Theater",
            "type":"Entertainment"
        }
    ],
    "sg:phone":"+1 775 751 3913",
    "sg:postcode":"89048",
    "sg:province":"NV",
    "sg:tags":[
        "group"
    ],
    "wof:name":"Dylans Dolls",
    "wof:placetype":"venue"
},
  "geometry": {"coordinates":[-115.993058,36.220724],"type":"Point"}
}