{
  "type": "Feature",
  "properties": {
    "iso:country":"US",
    "sg:address":"4780 W Ann Road Suite 5",
    "sg:city":"North Las Vegas",
    "sg:classifiers":[
        {
            "category":"Food & Beverages",
            "subcategory":"Bakery",
            "type":"Retail Goods"
        }
    ],
    "sg:phone":"+1 702 396 3003",
    "sg:postcode":"89031",
    "sg:province":"NV",
    "sg:tags":[
        "sandwich"
    ],
    "sg:website":"www.subway.com",
    "wof:name":"Subway",
    "wof:placetype":"venue"
},
  "geometry": {"coordinates":[-115.206903,36.261687],"type":"Point"}
}