{
  "type": "Feature",
  "properties": {
    "iso:country":"US",
    "sg:address":"2250 E Tropicana Ave",
    "sg:city":"Las Vegas",
    "sg:classifiers":[
        {
            "category":"Shopping",
            "type":"Retail Goods"
        }
    ],
    "sg:phone":"+1 702 383 6547",
    "sg:postcode":"89119",
    "sg:province":"NV",
    "sg:tags":[
        "merchandise"
    ],
    "wof:name":"Blowout Bargains Inc",
    "wof:placetype":"venue"
},
  "geometry": {"coordinates":[-115.123232,36.100502],"type":"Point"}
}