{
  "type": "Feature",
  "properties": {
    "iso:country":"US",
    "sg:address":"9545 W Russell Rd",
    "sg:city":"Las Vegas",
    "sg:classifiers":[
        {
            "category":"Building & Trades",
            "subcategory":"Construction",
            "type":"Services"
        }
    ],
    "sg:phone":"+1 702 562 0400",
    "sg:postcode":"89148",
    "sg:province":"NV",
    "sg:tags":[
        "shed",
        "utility"
    ],
    "wof:name":"Silverado Self Storage II LLC",
    "wof:placetype":"venue"
},
  "geometry": {"coordinates":[-115.30035700000001,36.08502],"type":"Point"}
}