{
  "type": "Feature",
  "properties": {
    "iso:country":"US",
    "sg:address":"300 S 4th St Ste 1201",
    "sg:city":"Las Vegas",
    "sg:classifiers":[
        {
            "category":"Professional",
            "subcategory":"Lawyer & Legal Services",
            "type":"Services"
        }
    ],
    "sg:phone":"+1 702 471 7000",
    "sg:postcode":"89101",
    "sg:province":"NV",
    "wof:name":"Curran & Parry",
    "wof:placetype":"venue"
},
  "geometry": {"coordinates":[-115.142998,36.1674],"type":"Point"}
}