{
  "type": "Feature",
  "properties": {
    "iso:country":"US",
    "sg:address":"755 N Roop St",
    "sg:city":"Carson City",
    "sg:classifiers":[
        {
            "category":"Banks & Credit Unions",
            "subcategory":"Bank",
            "type":"Services"
        }
    ],
    "sg:phone":"+1 775 841 8611",
    "sg:postcode":"89701",
    "sg:province":"NV",
    "sg:tags":[
        "mortgage",
        "loan",
        "broker",
        "real estate"
    ],
    "wof:name":"1st Premier Mortgage",
    "wof:placetype":"venue"
},
  "geometry": {"coordinates":[-119.761002,39.167801],"type":"Point"}
}