{
  "type": "Feature",
  "properties": {
    "iso:country":"US",
    "sg:address":"5834 Majestic Tide Ave",
    "sg:city":"Las Vegas",
    "sg:classifiers":[
        {
            "category":"Health Services",
            "subcategory":"Clinic",
            "type":"Services"
        }
    ],
    "sg:phone":"+1 702 656 4419",
    "sg:postcode":"89131",
    "sg:province":"NV",
    "wof:name":"Telewound Technologies",
    "wof:placetype":"venue"
},
  "geometry": {"coordinates":[-115.2223,36.297267],"type":"Point"}
}