{
  "type": "Feature",
  "properties": {
    "iso:country":"US",
    "sg:address":"2881 S Valley View Blvd",
    "sg:city":"Las Vegas",
    "sg:classifiers":[
        {
            "category":"Professional",
            "subcategory":"Management & Consulting",
            "type":"Services"
        }
    ],
    "sg:phone":"+1 702 222 0320",
    "sg:postcode":"89102",
    "sg:province":"NV",
    "sg:tags":[
        "relations",
        "public",
        "business"
    ],
    "wof:name":"Insight Communications",
    "wof:placetype":"venue"
},
  "geometry": {"coordinates":[-115.190599,36.1375],"type":"Point"}
}