{
  "type": "Feature",
  "properties": {
    "iso:country":"US",
    "sg:address":"3230 E Flamingo Rd",
    "sg:city":"Las Vegas",
    "sg:classifiers":[
        {
            "category":"Banks & Credit Unions",
            "subcategory":"Financial Services",
            "type":"Services"
        }
    ],
    "sg:phone":"+1 702 369 0700",
    "sg:postcode":"89121",
    "sg:province":"NV",
    "sg:tags":[
        "trust",
        "consulting",
        "management"
    ],
    "wof:name":"Independent Trust Consultants",
    "wof:placetype":"venue"
},
  "geometry": {"coordinates":[-115.103851,36.115222],"type":"Point"}
}