{
  "type": "Feature",
  "properties": {
    "iso:country":"US",
    "sg:address":"2207 Bellanca St",
    "sg:city":"Minden",
    "sg:classifiers":[
        {
            "category":"Airport",
            "type":"Transportation"
        }
    ],
    "sg:phone":"+1 775 782 4854",
    "sg:postcode":"89423",
    "sg:province":"NV",
    "sg:tags":[
        "aircraft",
        "maintenance"
    ],
    "wof:name":"Air Sierra Unlimited Inc",
    "wof:placetype":"venue"
},
  "geometry": {"coordinates":[-119.757496,38.99812],"type":"Point"}
}