{
  "type": "Feature",
  "properties": {
    "iso:country":"US",
    "sg:address":"7569 Rainbow Spray Dr",
    "sg:city":"Las Vegas",
    "sg:classifiers":[
        {
            "category":"Professional",
            "subcategory":"Management & Consulting",
            "type":"Services"
        }
    ],
    "sg:phone":"+1 702 395 2565",
    "sg:postcode":"89131",
    "sg:province":"NV",
    "sg:tags":[
        "consultant",
        "lighting"
    ],
    "wof:name":"Exteriorscapes",
    "wof:placetype":"venue"
},
  "geometry": {"coordinates":[-115.21759,36.29735],"type":"Point"}
}