{
  "type": "Feature",
  "properties": {
    "iso:country":"US",
    "sg:address":"5180 Cameron St",
    "sg:city":"Las Vegas",
    "sg:classifiers":[
        {
            "category":"Shopping",
            "subcategory":"Gifts & Souvenirs",
            "type":"Retail Goods"
        }
    ],
    "sg:phone":"+1 702 876 1517",
    "sg:postcode":"89118",
    "sg:province":"NV",
    "sg:tags":[
        "shop"
    ],
    "wof:name":"M & K Enterprises",
    "wof:placetype":"venue"
},
  "geometry": {"coordinates":[-115.203782,36.095081],"type":"Point"}
}