{
  "type": "Feature",
  "properties": {
    "iso:country":"US",
    "sg:address":"2186 Eastbrook Dr",
    "sg:city":"Sparks",
    "sg:classifiers":[
        {
            "category":"Sports & Exercise",
            "subcategory":"Gym",
            "type":"Entertainment"
        }
    ],
    "sg:phone":"+1 775 356 7445",
    "sg:postcode":"89434",
    "sg:province":"NV",
    "sg:tags":[
        "personal",
        "trainer"
    ],
    "wof:name":"Phillip E Zarrella Consultant",
    "wof:placetype":"venue"
},
  "geometry": {"coordinates":[-119.711207,39.550787],"type":"Point"}
}