{
  "type": "Feature",
  "properties": {
    "iso:country":"US",
    "sg:address":"9030 W Sahara Ave",
    "sg:city":"Las Vegas",
    "sg:classifiers":[
        {
            "category":"Building & Trades",
            "subcategory":"Construction",
            "type":"Services"
        }
    ],
    "sg:phone":"+1 702 363 2832",
    "sg:postcode":"89117",
    "sg:province":"NV",
    "sg:tags":[
        "concrete",
        "contractor"
    ],
    "wof:name":"K & E Contracting",
    "wof:placetype":"venue"
},
  "geometry": {"coordinates":[-115.28899,36.144208],"type":"Point"}
}