{
  "type": "Feature",
  "properties": {
    "iso:country":"US",
    "sg:address":"2028 Manhattan Dr",
    "sg:city":"Carson City",
    "sg:classifiers":[
        {
            "category":"Real Estate",
            "subcategory":"Real Estate Agent",
            "type":"Services"
        }
    ],
    "sg:phone":"+1 775 885 8825",
    "sg:postcode":"89703",
    "sg:province":"NV",
    "wof:name":"United Brokers",
    "wof:placetype":"venue"
},
  "geometry": {"coordinates":[-119.78727600000001,39.171274],"type":"Point"}
}