{
  "type": "Feature",
  "properties": {
    "iso:country":"US",
    "sg:address":"3838 Raymert Dr",
    "sg:city":"Las Vegas",
    "sg:classifiers":[
        {
            "category":"Restaurant",
            "type":"Food & Drink"
        }
    ],
    "sg:phone":"+1 702 796 9595",
    "sg:postcode":"89121",
    "sg:province":"NV",
    "wof:name":"Rock Lobster Inc",
    "wof:placetype":"venue"
},
  "geometry": {"coordinates":[-115.089406,36.128409],"type":"Point"}
}