{
  "type": "Feature",
  "properties": {
    "iso:country":"US",
    "sg:address":"3719 N Carson St",
    "sg:city":"Carson City",
    "sg:classifiers":[
        {
            "category":"Shopping",
            "type":"Retail Goods"
        }
    ],
    "sg:phone":"+1 775 841 9722",
    "sg:postcode":"89706",
    "sg:province":"NV",
    "sg:tags":[
        "pet",
        "shop"
    ],
    "wof:name":"Pet Pantry Intl Inc",
    "wof:placetype":"venue"
},
  "geometry": {"coordinates":[-119.773745,39.192173],"type":"Point"}
}