{
  "type": "Feature",
  "properties": {
    "iso:country":"US",
    "sg:address":"270 Dahlia St",
    "sg:city":"Pahrump",
    "sg:classifiers":[
        {
            "category":"Building & Trades",
            "subcategory":"Equipment Rental",
            "type":"Services"
        }
    ],
    "sg:phone":"+1 775 537 6099",
    "sg:postcode":"89048",
    "sg:province":"NV",
    "sg:tags":[
        "crane"
    ],
    "wof:name":"Leslie R Staples Crane Svc",
    "wof:placetype":"venue"
},
  "geometry": {"coordinates":[-115.996442,36.215258],"type":"Point"}
}