{
  "type": "Feature",
  "properties": {
    "iso:country":"US",
    "sg:address":"38 Heppner Dr",
    "sg:city":"Mound House",
    "sg:classifiers":[
        {
            "category":"Freight",
            "type":"Transportation"
        }
    ],
    "sg:phone":"+1 775 246 9930",
    "sg:postcode":"89706",
    "sg:province":"NV",
    "sg:tags":[
        "trucking"
    ],
    "wof:name":"Sheahan Transportation",
    "wof:placetype":"venue"
},
  "geometry": {"coordinates":[-119.65613,39.22742],"type":"Point"}
}