{
  "type": "Feature",
  "properties": {
    "iso:country":"US",
    "sg:address":"4350 S Arville St Bldg E Suite #40",
    "sg:city":"Las Vegas",
    "sg:classifiers":[
        {
            "category":"Sports & Exercise",
            "subcategory":"Bicycle Rental",
            "type":"Entertainment"
        }
    ],
    "sg:phone":"+1 702 610 4905",
    "sg:postcode":"89103",
    "sg:province":"NV",
    "sg:tags":[
        "bike"
    ],
    "sg:website":"www.702scooters.com",
    "wof:name":"Las Vegas Scooters",
    "wof:placetype":"venue"
},
  "geometry": {"coordinates":[-115.19931,36.110814],"type":"Point"}
}