{
  "type": "Feature",
  "properties": {
    "iso:country":"US",
    "sg:address":"4231 Dant Blvd",
    "sg:city":"Reno",
    "sg:classifiers":[
        {
            "category":"Professional",
            "subcategory":"Accounting & Tax Preparation",
            "type":"Services"
        }
    ],
    "sg:phone":"+1 775 829 0500",
    "sg:postcode":"89509",
    "sg:province":"NV",
    "sg:tags":[
        "return",
        "filing"
    ],
    "sg:website":"www.lindeken.com",
    "wof:name":"Lindeken & Assoc LTD",
    "wof:placetype":"venue"
},
  "geometry": {"coordinates":[-119.827189,39.483564],"type":"Point"}
}