{
  "type": "Feature",
  "properties": {
    "iso:country":"US",
    "sg:address":"1632 E Charleston Blvd",
    "sg:city":"Las Vegas",
    "sg:classifiers":[
        {
            "category":"Shopping",
            "subcategory":"Used Merchandise",
            "type":"Retail Goods"
        }
    ],
    "sg:phone":"+1 702 598 0860",
    "sg:postcode":"89104",
    "sg:province":"NV",
    "sg:tags":[
        "antique"
    ],
    "wof:name":"Glassman",
    "wof:placetype":"venue"
},
  "geometry": {"coordinates":[-115.130195,36.158797],"type":"Point"}
}