{
  "type": "Feature",
  "properties": {
    "iso:country":"US",
    "sg:address":"4644 Skybolt St",
    "sg:city":"Las Vegas",
    "sg:classifiers":[
        {
            "category":"Professional",
            "subcategory":"Advertising",
            "type":"Services"
        }
    ],
    "sg:phone":"+1 702 644 2873",
    "sg:postcode":"89115",
    "sg:province":"NV",
    "sg:tags":[
        "representative"
    ],
    "wof:name":"Digital Star Communicatio",
    "wof:placetype":"venue"
},
  "geometry": {"coordinates":[-115.057973,36.244047],"type":"Point"}
}