{
  "type": "Feature",
  "properties": {
    "iso:country":"US",
    "sg:address":"940 Opalite Dr",
    "sg:city":"Carson City",
    "sg:classifiers":[
        {
            "category":"Professional",
            "subcategory":"Business Services",
            "type":"Services"
        }
    ],
    "sg:phone":"+1 775 267 3967",
    "sg:postcode":"89705",
    "sg:province":"NV",
    "wof:name":"Tinas Goodies",
    "wof:placetype":"venue"
},
  "geometry": {"coordinates":[-119.776466,39.094678],"type":"Point"}
}