{
  "type": "Feature",
  "properties": {
    "iso:country":"US",
    "sg:address":"4780 W Harmon Ave Ste 12",
    "sg:city":"Las Vegas",
    "sg:classifiers":[
        {
            "category":"Retail",
            "subcategory":"Portrait Studio",
            "type":"Services"
        },
        {
            "category":"Professional",
            "subcategory":"Art Services",
            "type":"Services"
        }
    ],
    "sg:phone":"+1 702 227 0063",
    "sg:postcode":"89103",
    "sg:province":"NV",
    "sg:tags":[
        "photographer",
        "photography",
        "store"
    ],
    "wof:name":"Real Deal Media Arts Llc",
    "wof:placetype":"venue"
},
  "geometry": {"coordinates":[-115.20625699999999,36.10819],"type":"Point"}
}