{
  "type": "Feature",
  "properties": {
    "iso:country":"US",
    "sg:address":"5740 Kasandra Way",
    "sg:city":"Sun Valley",
    "sg:classifiers":[
        {
            "category":"Retail",
            "subcategory":"Repair Shop",
            "type":"Services"
        }
    ],
    "sg:phone":"+1 775 673 2201",
    "sg:postcode":"89433",
    "sg:province":"NV",
    "wof:name":"Reno Restaurant Equipment Repr",
    "wof:placetype":"venue"
},
  "geometry": {"coordinates":[-119.777614,39.601031],"type":"Point"}
}