{
  "type": "Feature",
  "properties": {
    "iso:country":"US",
    "sg:address":"1720 E Charleston Blvd",
    "sg:city":"Las Vegas",
    "sg:classifiers":[
        {
            "category":"Personal",
            "subcategory":"Nail Salon",
            "type":"Services"
        }
    ],
    "sg:phone":"+1 702 386 1988",
    "sg:postcode":"89104",
    "sg:province":"NV",
    "wof:name":"Viva Nail & Spa",
    "wof:placetype":"venue"
},
  "geometry": {"coordinates":[-115.12751799999999,36.15876],"type":"Point"}
}