{
  "type": "Feature",
  "properties": {
    "iso:country":"US",
    "sg:address":"10080 Alta Dr Ste 120",
    "sg:city":"Las Vegas",
    "sg:classifiers":[
        {
            "category":"Health Services",
            "subcategory":"Dentist",
            "type":"Services"
        }
    ],
    "sg:phone":"+1 702 313 2300",
    "sg:postcode":"89145",
    "sg:province":"NV",
    "sg:website":"farathomas.com",
    "wof:name":"Fara Thomas DDS",
    "wof:placetype":"venue"
},
  "geometry": {"coordinates":[-115.314424,36.168746],"type":"Point"}
}