{
  "type": "Feature",
  "properties": {
    "iso:country":"US",
    "sg:address":"1070 Mary Crest Rd",
    "sg:city":"Henderson",
    "sg:classifiers":[
        {
            "category":"Home & Garden",
            "subcategory":"Hardware",
            "type":"Retail Goods"
        }
    ],
    "sg:phone":"+1 702 990 5960",
    "sg:postcode":"89074",
    "sg:province":"NV",
    "sg:tags":[
        "store"
    ],
    "wof:name":"OTool Co",
    "wof:placetype":"venue"
},
  "geometry": {"coordinates":[-115.03215299999999,36.038179],"type":"Point"}
}