{
  "type": "Feature",
  "properties": {
    "iso:country":"US",
    "sg:address":"238 S Rainbow Blvd",
    "sg:city":"Las Vegas",
    "sg:classifiers":[
        {
            "category":"Restaurant",
            "type":"Food & Drink"
        }
    ],
    "sg:phone":"+1 702 363 2424",
    "sg:postcode":"89145",
    "sg:province":"NV",
    "sg:tags":[
        "bar"
    ],
    "wof:name":"Inn Zone Rainbow",
    "wof:placetype":"venue"
},
  "geometry": {"coordinates":[-115.244299,36.172809],"type":"Point"}
}