{
  "type": "Feature",
  "properties": {
    "iso:country":"US",
    "sg:address":"11 Cormorant Ct",
    "sg:city":"Sparks",
    "sg:classifiers":[
        {
            "category":"Shopping",
            "subcategory":"Gifts & Souvenirs",
            "type":"Retail Goods"
        }
    ],
    "sg:phone":"+1 775 424 1408",
    "sg:postcode":"89441",
    "sg:province":"NV",
    "wof:name":"Rileys Nic Nak Store",
    "wof:placetype":"venue"
},
  "geometry": {"coordinates":[-119.733181,39.6536],"type":"Point"}
}