{
  "type": "Feature",
  "properties": {
    "iso:country":"US",
    "sg:address":"54 N Pecos Rd",
    "sg:city":"Henderson",
    "sg:classifiers":[
        {
            "category":"Real Estate",
            "subcategory":"Real Estate Agent",
            "type":"Services"
        }
    ],
    "sg:phone":"+1 702 938 2277",
    "sg:postcode":"89074",
    "sg:province":"NV",
    "wof:name":"Galileo Group Inc",
    "wof:placetype":"venue"
},
  "geometry": {"coordinates":[-115.100202,36.032962],"type":"Point"}
}