{
  "type": "Feature",
  "properties": {
    "iso:country":"US",
    "sg:address":"1540 US Hwy 395 N",
    "sg:city":"Gardnerville",
    "sg:classifiers":[
        {
            "category":"Shopping",
            "type":"Retail Goods"
        }
    ],
    "sg:phone":"+1 775 782 7727",
    "sg:postcode":"89410",
    "sg:province":"NV",
    "sg:tags":[
        "spa",
        "hot",
        "tub"
    ],
    "wof:name":"Gardenville Spa & Pool",
    "wof:placetype":"venue"
},
  "geometry": {"coordinates":[-119.755796,38.946393],"type":"Point"}
}