{
  "type": "Feature",
  "properties": {
    "iso:country":"US",
    "sg:address":"1610 Montclair Ave",
    "sg:city":"Reno",
    "sg:classifiers":[
        {
            "category":"Real Estate",
            "subcategory":"Developer",
            "type":"Services"
        }
    ],
    "sg:phone":"+1 775 337 6555",
    "sg:postcode":"89509",
    "sg:province":"NV",
    "wof:name":"M M Baldwin Development",
    "wof:placetype":"venue"
},
  "geometry": {"coordinates":[-119.806035,39.508335],"type":"Point"}
}