{
  "type": "Feature",
  "properties": {
    "iso:country":"US",
    "sg:address":"1275 W Warm Springs Rd Ste 100",
    "sg:city":"Las Vegas",
    "sg:classifiers":[
        {
            "category":"Restaurant",
            "type":"Food & Drink"
        }
    ],
    "sg:phone":"+1 702 456 2050",
    "sg:postcode":"89014",
    "sg:province":"NV",
    "sg:tags":[
        "pizza"
    ],
    "wof:name":"Napoli Pizza",
    "wof:placetype":"venue"
},
  "geometry": {"coordinates":[-115.17300400000001,36.05684],"type":"Point"}
}