{
  "type": "Feature",
  "properties": {
    "iso:country":"US",
    "sg:address":"4441 Vicobello Ave",
    "sg:city":"Las Vegas",
    "sg:classifiers":[
        {
            "category":"Professional",
            "subcategory":"Business Services",
            "type":"Services"
        }
    ],
    "sg:phone":"+1 702 260 8069",
    "sg:postcode":"89141",
    "sg:province":"NV",
    "sg:tags":[
        "interior",
        "consultant",
        "design",
        "decorator"
    ],
    "wof:name":"R G Paul Interior Design",
    "wof:placetype":"venue"
},
  "geometry": {"coordinates":[-115.200858,35.992545],"type":"Point"}
}