{
  "type": "Feature",
  "properties": {
    "iso:country":"US",
    "sg:address":"Rainbow Promenade Shopping Center 2021 N Rainbow Blvd, #101",
    "sg:city":"Las Vegas",
    "sg:classifiers":[
        {
            "category":"Personal",
            "subcategory":"Beauty Salon",
            "type":"Services"
        }
    ],
    "sg:phone":"+1 702 405 0500",
    "sg:postcode":"89108",
    "sg:province":"NV",
    "sg:tags":[
        "hair"
    ],
    "sg:website":"www.americanmale.com/locations_s...",
    "wof:name":"American Male Salon",
    "wof:placetype":"venue"
},
  "geometry": {"coordinates":[-115.243255,36.20234],"type":"Point"}
}