{
  "type": "Feature",
  "properties": {
    "iso:country":"US",
    "sg:address":"5200 Los Altos Pkwy",
    "sg:city":"Sparks",
    "sg:classifiers":[
        {
            "category":"Real Estate",
            "subcategory":"Real Estate Operator",
            "type":"Services"
        }
    ],
    "sg:phone":"+1 775 626 7773",
    "sg:postcode":"89436",
    "sg:province":"NV",
    "sg:tags":[
        "apartment"
    ],
    "wof:name":"Canyon Vista",
    "wof:placetype":"venue"
},
  "geometry": {"coordinates":[-119.69441999999999,39.56837],"type":"Point"}
}