{
  "type": "Feature",
  "properties": {
    "iso:country":"US",
    "sg:address":"1016 S Rock Blvd",
    "sg:city":"Sparks",
    "sg:classifiers":[
        {
            "category":"Personal",
            "subcategory":"Beauty Salon",
            "type":"Services"
        }
    ],
    "sg:phone":"+1 775 329 7789",
    "sg:postcode":"89431",
    "sg:province":"NV",
    "wof:name":"Cinsational Nails",
    "wof:placetype":"venue"
},
  "geometry": {"coordinates":[-119.766692,39.524422],"type":"Point"}
}