{
  "type": "Feature",
  "properties": {
    "iso:country":"US",
    "sg:address":"7310 Smoke Ranch Rd",
    "sg:city":"Las Vegas",
    "sg:classifiers":[
        {
            "category":"Personal",
            "type":"Services"
        }
    ],
    "sg:phone":"+1 702 361 5678",
    "sg:postcode":"89128",
    "sg:province":"NV",
    "wof:name":"Brady C Nevius",
    "wof:placetype":"venue"
},
  "geometry": {"coordinates":[-115.256882,36.20355],"type":"Point"}
}