{
  "type": "Feature",
  "properties": {
    "iso:country":"US",
    "sg:address":"145 W 3rd St",
    "sg:city":"Battle Mountain",
    "sg:classifiers":[
        {
            "category":"Government",
            "subcategory":"Office",
            "type":"Public Place"
        }
    ],
    "sg:phone":"+1 775 635 2662",
    "sg:postcode":"89820",
    "sg:province":"NV",
    "sg:tags":[
        "county",
        "govt"
    ],
    "wof:name":"Water & Sewer Business Office",
    "wof:placetype":"venue"
},
  "geometry": {"coordinates":[-116.938011,40.642128],"type":"Point"}
}