{
  "type": "Feature",
  "properties": {
    "iso:country":"US",
    "sg:address":"6325 S Valley View Blvd",
    "sg:city":"Las Vegas",
    "sg:classifiers":[
        {
            "category":"Building & Trades",
            "subcategory":"Plumbing",
            "type":"Services"
        }
    ],
    "sg:phone":"+1 702 361 5111",
    "sg:postcode":"89118",
    "sg:province":"NV",
    "sg:tags":[
        "plumbing",
        "air",
        "heating",
        "conditioning",
        "contractor"
    ],
    "wof:name":"Hansen Mechanical Contractors",
    "wof:placetype":"venue"
},
  "geometry": {"coordinates":[-115.190064,36.074012],"type":"Point"}
}