{
  "type": "Feature",
  "properties": {
    "iso:country":"US",
    "sg:address":"1040 Skyline Blvd",
    "sg:city":"Reno",
    "sg:classifiers":[
        {
            "category":"Banks & Credit Unions",
            "subcategory":"Investment Brokerage",
            "type":"Services"
        }
    ],
    "sg:phone":"+1 775 825 8861",
    "sg:postcode":"89509",
    "sg:province":"NV",
    "sg:tags":[
        "management"
    ],
    "wof:name":"Meyer Investments",
    "wof:placetype":"venue"
},
  "geometry": {"coordinates":[-119.825723,39.498092],"type":"Point"}
}