{
  "type": "Feature",
  "properties": {
    "iso:country":"US",
    "sg:address":"12 State Rte 208",
    "sg:city":"Yerington",
    "sg:classifiers":[
        {
            "category":"Sports & Exercise",
            "subcategory":"Gym",
            "type":"Entertainment"
        }
    ],
    "sg:phone":"+1 775 463 7000",
    "sg:postcode":"89447",
    "sg:province":"NV",
    "sg:tags":[
        "club",
        "health",
        "studio",
        "gymnasium"
    ],
    "wof:name":"Curves For Women",
    "wof:placetype":"venue"
},
  "geometry": {"coordinates":[-119.163206,38.975855],"type":"Point"}
}