{
  "type": "Feature",
  "properties": {
    "iso:country":"US",
    "sg:address":"2950 E Flamingo Road",
    "sg:city":"Las Vegas",
    "sg:classifiers":[
        {
            "category":"Professional",
            "subcategory":"Accounting & Tax Preparation",
            "type":"Services"
        }
    ],
    "sg:phone":"+1 702 732 2775",
    "sg:postcode":"89121",
    "sg:province":"NV",
    "sg:tags":[
        "accountant"
    ],
    "wof:name":"Zerga & Tveter Ltd",
    "wof:placetype":"venue"
},
  "geometry": {"coordinates":[-115.110418,36.115098],"type":"Point"}
}