{
  "type": "Feature",
  "properties": {
    "iso:country":"US",
    "sg:address":"740 James Ct",
    "sg:city":"Reno",
    "sg:classifiers":[
        {
            "category":"Wholesale",
            "subcategory":"Medical Equipment & Supplies",
            "type":"Manufacturing & Wholesale Goods"
        }
    ],
    "sg:phone":"+1 775 747 0947",
    "sg:postcode":"89503",
    "sg:province":"NV",
    "sg:tags":[
        "microscope"
    ],
    "wof:name":"West Coast Microscopy",
    "wof:placetype":"venue"
},
  "geometry": {"coordinates":[-119.851875,39.53071],"type":"Point"}
}