{
  "type": "Feature",
  "properties": {
    "iso:country":"US",
    "sg:address":"27 S Main St",
    "sg:city":"Yerington",
    "sg:classifiers":[
        {
            "category":"Farming",
            "subcategory":"Farm & Veterinary Services",
            "type":"Manufacturing & Wholesale Goods"
        }
    ],
    "sg:phone":"+1 775 463 6566",
    "sg:postcode":"89447",
    "sg:province":"NV",
    "sg:tags":[
        "preparation",
        "soil"
    ],
    "wof:name":"Mason Valley Mosquito",
    "wof:placetype":"venue"
},
  "geometry": {"coordinates":[-119.163259,38.986706],"type":"Point"}
}