{
  "type": "Feature",
  "properties": {
    "iso:country":"US",
    "sg:address":"10638 Cliffords Tower Ct",
    "sg:city":"Las Vegas",
    "sg:classifiers":[
        {
            "category":"Manufacturing",
            "subcategory":"Textiles",
            "type":"Manufacturing & Wholesale Goods"
        }
    ],
    "sg:phone":"+1 702 254 9239",
    "sg:postcode":"89135",
    "sg:province":"NV",
    "sg:tags":[
        "mill",
        "narrow",
        "fabric"
    ],
    "wof:name":"Sun Blinds of Las Vegas",
    "wof:placetype":"venue"
},
  "geometry": {"coordinates":[-115.326441,36.131301],"type":"Point"}
}