{
  "type": "Feature",
  "properties": {
    "iso:country":"US",
    "sg:address":"2650 River Plate Dr",
    "sg:city":"Pahrump",
    "sg:classifiers":[
        {
            "category":"Building & Trades",
            "subcategory":"Construction",
            "type":"Services"
        }
    ],
    "sg:phone":"+1 775 751 8151",
    "sg:postcode":"89048",
    "sg:province":"NV",
    "sg:tags":[
        "excavation",
        "contractor"
    ],
    "wof:name":"Kenzevich Backhoe Service",
    "wof:placetype":"venue"
},
  "geometry": {"coordinates":[-116.034698,36.181351],"type":"Point"}
}