{
  "type": "Feature",
  "properties": {
    "iso:country":"US",
    "sg:address":"2924 Domino Way",
    "sg:city":"Las Vegas",
    "sg:classifiers":[
        {
            "category":"Building & Trades",
            "subcategory":"Cleaning & Sanitation",
            "type":"Services"
        }
    ],
    "sg:phone":"+1 702 307 6482",
    "sg:postcode":"89117",
    "sg:province":"NV",
    "sg:tags":[
        "janitor"
    ],
    "wof:name":"Regal Janitorial Svc",
    "wof:placetype":"venue"
},
  "geometry": {"coordinates":[-115.298046,36.138049],"type":"Point"}
}