{
  "type": "Feature",
  "properties": {
    "iso:country":"US",
    "sg:address":"8485 W Sahara Ave",
    "sg:city":"Las Vegas",
    "sg:classifiers":[
        {
            "category":"Cinema",
            "subcategory":"Movie Rental",
            "type":"Entertainment"
        }
    ],
    "sg:phone":"+1 702 363 1352",
    "sg:postcode":"89117",
    "sg:province":"NV",
    "sg:tags":[
        "video",
        "game",
        "leasing"
    ],
    "wof:name":"Game Crazy",
    "wof:placetype":"venue"
},
  "geometry": {"coordinates":[-115.277495,36.143994],"type":"Point"}
}