{
  "type": "Feature",
  "properties": {
    "iso:country":"US",
    "sg:address":"800 West St",
    "sg:city":"Pahrump",
    "sg:classifiers":[
        {
            "category":"Shopping",
            "subcategory":"Pets & Pet Supplies",
            "type":"Retail Goods"
        },
        {
            "category":"Retail",
            "subcategory":"Veterinary Services",
            "type":"Services"
        }
    ],
    "sg:phone":"+1 775 751 2263",
    "sg:postcode":"89048",
    "sg:province":"NV",
    "sg:tags":[
        "feed",
        "supplement",
        "specialty",
        "dog",
        "concentrate",
        "furnishing",
        "cat",
        "store"
    ],
    "sg:website":"http://www.acmegeneralstore.net",
    "wof:name":"Acme General Store",
    "wof:placetype":"venue"
},
  "geometry": {"coordinates":[-115.99617,36.207649],"type":"Point"}
}