{
  "type": "Feature",
  "properties": {
    "iso:country":"US",
    "sg:address":"Sam's Town 5111 Boulder Hwy",
    "sg:city":"Las Vegas",
    "sg:classifiers":[
        {
            "category":"Restaurant",
            "type":"Food & Drink"
        }
    ],
    "sg:phone":"+1 702 456 7777",
    "sg:postcode":"89122",
    "sg:province":"NV",
    "sg:tags":[
        "buffet"
    ],
    "sg:website":"www.samstownlv.com/dining/fireli...",
    "wof:name":"Firelight Buffet",
    "wof:placetype":"venue"
},
  "geometry": {"coordinates":[-115.061836,36.110775],"type":"Point"}
}