{
  "type": "Feature",
  "properties": {
    "iso:country":"US",
    "sg:address":"3755 Violet Rose Ct",
    "sg:city":"Las Vegas",
    "sg:classifiers":[
        {
            "category":"Professional",
            "subcategory":"Business Services",
            "type":"Services"
        }
    ],
    "sg:phone":"+1 702 498 2005",
    "sg:postcode":"89147",
    "sg:province":"NV",
    "wof:name":"Chiwahwah Group",
    "wof:placetype":"venue"
},
  "geometry": {"coordinates":[-115.268623,36.120999],"type":"Point"}
}