{
  "type": "Feature",
  "properties": {
    "iso:country":"US",
    "sg:address":"5243 W Charleston Blvd",
    "sg:city":"Las Vegas",
    "sg:classifiers":[
        {
            "category":"Building & Trades",
            "subcategory":"Construction",
            "type":"Services"
        }
    ],
    "sg:phone":"+1 702 258 1505",
    "sg:postcode":"89146",
    "sg:province":"NV",
    "sg:tags":[
        "floor",
        "laying",
        "contractor"
    ],
    "wof:name":"Quality Flooring",
    "wof:placetype":"venue"
},
  "geometry": {"coordinates":[-115.214758,36.159067],"type":"Point"}
}