{
  "type": "Feature",
  "properties": {
    "iso:country":"US",
    "sg:address":"1716 W Horizon Ridge Pkwy",
    "sg:city":"Henderson",
    "sg:classifiers":[
        {
            "category":"Restaurant",
            "type":"Food & Drink"
        }
    ],
    "sg:menulink":"http://www.allmenus.com/nv/las-vegas/122942-quiznos-sub/menu/",
    "sg:phone":"+1 702 360 2067",
    "sg:postcode":"89012",
    "sg:province":"NV",
    "sg:tags":[
        "wrap",
        "american",
        "sandwich"
    ],
    "wof:name":"Quiznos Sub",
    "wof:placetype":"venue"
},
  "geometry": {"coordinates":[-115.06304299999999,36.011801],"type":"Point"}
}