{
  "type": "Feature",
  "properties": {
    "iso:country":"US",
    "sg:address":"3210 E Patrick Ln",
    "sg:city":"Las Vegas",
    "sg:classifiers":[
        {
            "category":"Insurance",
            "subcategory":"Insurance Agent",
            "type":"Services"
        }
    ],
    "sg:phone":"+1 702 547 1300",
    "sg:postcode":"89120",
    "sg:province":"NV",
    "wof:name":"Farmers Insurance Group",
    "wof:placetype":"venue"
},
  "geometry": {"coordinates":[-115.10694700000001,36.079082],"type":"Point"}
}