{
  "type": "Feature",
  "properties": {
    "iso:country":"US",
    "sg:address":"2980 S Rainbow Blvd Ste 110-J",
    "sg:city":"Las Vegas",
    "sg:classifiers":[
        {
            "category":"Professional",
            "type":"Services"
        },
        {
            "category":"Professional",
            "subcategory":"Lawyer & Legal Services",
            "type":"Services"
        }
    ],
    "sg:phone":"+1 702 220 4002",
    "sg:postcode":"89146",
    "sg:province":"NV",
    "sg:tags":[
        "notary"
    ],
    "sg:website":"www.andrebhaynes.com",
    "wof:name":"Andre' B. Haynes & Associates",
    "wof:placetype":"venue"
},
  "geometry": {"coordinates":[-115.242276,36.135195],"type":"Point"}
}