{
  "type": "Feature",
  "properties": {
    "iso:country":"US",
    "sg:address":"7728 Thorne Pine Ave",
    "sg:city":"Las Vegas",
    "sg:classifiers":[
        {
            "category":"Professional",
            "subcategory":"Computer Services",
            "type":"Services"
        }
    ],
    "sg:phone":"+1 702 656 4450",
    "sg:postcode":"89131",
    "sg:province":"NV",
    "sg:tags":[
        "related"
    ],
    "wof:name":"Spirotek Inc",
    "wof:placetype":"venue"
},
  "geometry": {"coordinates":[-115.264637,36.297775],"type":"Point"}
}