{
  "type": "Feature",
  "properties": {
    "iso:country":"US",
    "sg:address":"1226 Kimmerling Rd",
    "sg:city":"Gardnerville",
    "sg:classifiers":[
        {
            "category":"Wholesale",
            "subcategory":"Construction Materials",
            "type":"Manufacturing & Wholesale Goods"
        }
    ],
    "sg:phone":"+1 775 265 3641",
    "sg:postcode":"89460",
    "sg:province":"NV",
    "sg:tags":[
        "aggregate",
        "concrete"
    ],
    "wof:name":"Bing Materials",
    "wof:placetype":"venue"
},
  "geometry": {"coordinates":[-119.754115,38.894905],"type":"Point"}
}