{
  "type": "Feature",
  "properties": {
    "iso:country":"US",
    "sg:address":"1008 E Charleston Boulevard",
    "sg:city":"Las Vegas",
    "sg:classifiers":[
        {
            "category":"Banks & Credit Unions",
            "subcategory":"Financial Services",
            "type":"Services"
        }
    ],
    "sg:phone":"+1 702 383 8188",
    "sg:postcode":"89104",
    "sg:province":"NV",
    "sg:tags":[
        "broker",
        "mortgage"
    ],
    "sg:website":"www.sunloan.com",
    "wof:name":"Sun Loan Company",
    "wof:placetype":"venue"
},
  "geometry": {"coordinates":[-115.140166,36.158858],"type":"Point"}
}