{
  "type": "Feature",
  "properties": {
    "iso:country":"US",
    "sg:address":"1111 N Michael Way",
    "sg:city":"Las Vegas",
    "sg:classifiers":[
        {
            "category":"Education",
            "subcategory":"School",
            "type":"Public Place"
        }
    ],
    "sg:phone":"+1 702 646 2266",
    "sg:postcode":"89108",
    "sg:province":"NV",
    "sg:tags":[
        "high",
        "middle",
        "elementary"
    ],
    "wof:name":"St Francis De Sales Religious Education",
    "wof:placetype":"venue"
},
  "geometry": {"coordinates":[-115.214996,36.182499],"type":"Point"}
}