{
  "type": "Feature",
  "properties": {
    "iso:country":"US",
    "sg:address":"924 S Main St",
    "sg:city":"Las Vegas",
    "sg:classifiers":[
        {
            "category":"Retail",
            "subcategory":"Auto Repair",
            "type":"Services"
        }
    ],
    "sg:phone":"+1 702 384 1230",
    "sg:postcode":"89101",
    "sg:province":"NV",
    "sg:tags":[
        "transmission"
    ],
    "wof:name":"Pro-Trans Inc",
    "wof:placetype":"venue"
},
  "geometry": {"coordinates":[-115.152605,36.16132],"type":"Point"}
}