{
  "type": "Feature",
  "properties": {
    "iso:country":"US",
    "sg:address":"1558 N Eastern Ave",
    "sg:city":"Las Vegas",
    "sg:classifiers":[
        {
            "category":"Restaurant",
            "type":"Food & Drink"
        }
    ],
    "sg:phone":"+1 702 639 9960",
    "sg:postcode":"89101",
    "sg:province":"NV",
    "wof:name":"LA Choza",
    "wof:placetype":"venue"
},
  "geometry": {"coordinates":[-115.116026,36.18742],"type":"Point"}
}