{
  "type": "Feature",
  "properties": {
    "iso:country":"US",
    "sg:address":"5464 Sun Valley Blvd",
    "sg:city":"Sun Valley",
    "sg:classifiers":[
        {
            "category":"Home & Garden",
            "subcategory":"Household Appliances",
            "type":"Retail Goods"
        }
    ],
    "sg:phone":"+1 775 673 5522",
    "sg:postcode":"89433",
    "sg:province":"NV",
    "wof:name":"Earls Appliance Center",
    "wof:placetype":"venue"
},
  "geometry": {"coordinates":[-119.780452,39.590352],"type":"Point"}
}