{
  "type": "Feature",
  "properties": {
    "iso:country":"US",
    "sg:address":"1932 Rock Springs Dr",
    "sg:city":"Las Vegas",
    "sg:classifiers":[
        {
            "category":"Personal",
            "subcategory":"Beauty Salon",
            "type":"Services"
        },
        {
            "category":"Personal",
            "subcategory":"Skin Care",
            "type":"Services"
        },
        {
            "category":"Personal",
            "subcategory":"Nail Salon",
            "type":"Services"
        }
    ],
    "sg:phone":"+1 702 240 3100",
    "sg:postcode":"89128",
    "sg:province":"NV",
    "sg:tags":[
        "hair"
    ],
    "wof:name":"Jagged Edge Salon",
    "wof:placetype":"venue"
},
  "geometry": {"coordinates":[-115.247007,36.194722],"type":"Point"}
}