{
  "type": "Feature",
  "properties": {
    "iso:country":"US",
    "sg:address":"7820 Leavorite Dr",
    "sg:city":"Las Vegas",
    "sg:classifiers":[
        {
            "category":"Professional",
            "subcategory":"Business Services",
            "type":"Services"
        }
    ],
    "sg:phone":"+1 702 494 9944",
    "sg:postcode":"89128",
    "sg:province":"NV",
    "wof:name":"White Nanella",
    "wof:placetype":"venue"
},
  "geometry": {"coordinates":[-115.26444,36.183292],"type":"Point"}
}