{
  "type": "Feature",
  "properties": {
    "iso:country":"US",
    "sg:address":"105 US Hwy 95 Alt",
    "sg:city":"Yerington",
    "sg:phone":"+1 775 463 2664",
    "sg:postcode":"89447",
    "sg:province":"NV",
    "sg:tags":[
        "farm",
        "field",
        "crop"
    ],
    "wof:name":"Guild Rolene",
    "wof:placetype":"venue"
},
  "geometry": {"coordinates":[-119.165494,38.993829],"type":"Point"}
}