{
  "type": "Feature",
  "properties": {
    "iso:country":"US",
    "sg:address":"4343 N Rancho Dr",
    "sg:city":"Las Vegas",
    "sg:classifiers":[
        {
            "category":"Wholesale",
            "subcategory":"Medical Equipment & Supplies",
            "type":"Manufacturing & Wholesale Goods"
        }
    ],
    "sg:phone":"+1 702 396 3590",
    "sg:postcode":"89130",
    "sg:province":"NV",
    "sg:tags":[
        "x",
        "apparatus"
    ],
    "wof:name":"Portable X Ray",
    "wof:placetype":"venue"
},
  "geometry": {"coordinates":[-115.227778,36.234194],"type":"Point"}
}