{
  "type": "Feature",
  "properties": {
    "iso:country":"US",
    "sg:address":"2325 Renaissance Dr",
    "sg:city":"Las Vegas",
    "sg:classifiers":[
        {
            "category":"Shopping",
            "subcategory":"Computers & Home Electronics",
            "type":"Retail Goods"
        }
    ],
    "sg:phone":"+1 702 968 5207",
    "sg:postcode":"89119",
    "sg:province":"NV",
    "sg:tags":[
        "software"
    ],
    "wof:name":"Intergraph Software Tech Co",
    "wof:placetype":"venue"
},
  "geometry": {"coordinates":[-115.121747,36.103645],"type":"Point"}
}