{
  "type": "Feature",
  "properties": {
    "iso:country":"US",
    "sg:address":"1000 Nevada Hwy",
    "sg:city":"Boulder City",
    "sg:classifiers":[
        {
            "category":"Banks & Credit Unions",
            "subcategory":"Bank",
            "type":"Services"
        }
    ],
    "sg:phone":"+1 702 765 2900",
    "sg:postcode":"89005",
    "sg:province":"NV",
    "sg:tags":[
        "federal",
        "savings",
        "institution"
    ],
    "wof:name":"Wells Fargo",
    "wof:placetype":"venue"
},
  "geometry": {"coordinates":[-114.844381,35.974564],"type":"Point"}
}