{
  "type": "Feature",
  "properties": {
    "iso:country":"US",
    "sg:address":"2755 Mohawk St",
    "sg:city":"Las Vegas",
    "sg:classifiers":[
        {
            "category":"Education",
            "subcategory":"School",
            "type":"Public Place"
        }
    ],
    "sg:phone":"+1 702 799 5890",
    "sg:postcode":"89146",
    "sg:province":"NV",
    "sg:tags":[
        "high",
        "middle",
        "elementary"
    ],
    "wof:name":"Schools Clark County Public",
    "wof:placetype":"venue"
},
  "geometry": {"coordinates":[-115.21464,36.139712],"type":"Point"}
}