{
  "type": "Feature",
  "properties": {
    "iso:country":"US",
    "sg:address":"1971 E Charleston Blvd",
    "sg:city":"Las Vegas",
    "sg:classifiers":[
        {
            "category":"Home & Garden",
            "subcategory":"Building Materials",
            "type":"Retail Goods"
        }
    ],
    "sg:phone":"+1 702 699 5634",
    "sg:postcode":"89104",
    "sg:province":"NV",
    "sg:tags":[
        "glass",
        "window",
        "plate"
    ],
    "wof:name":"Sin City Auto Glass",
    "wof:placetype":"venue"
},
  "geometry": {"coordinates":[-115.122807,36.158936],"type":"Point"}
}