{
  "type": "Feature",
  "properties": {
    "iso:country":"US",
    "sg:address":"9644 Bending River Ave",
    "sg:city":"Las Vegas",
    "sg:classifiers":[
        {
            "category":"Professional",
            "subcategory":"Accounting & Tax Preparation",
            "type":"Services"
        }
    ],
    "sg:phone":"+1 702 838 3889",
    "sg:postcode":"89129",
    "sg:province":"NV",
    "sg:tags":[
        "billing"
    ],
    "wof:name":"Comprehensive Practice Svc",
    "wof:placetype":"venue"
},
  "geometry": {"coordinates":[-115.305472,36.221176],"type":"Point"}
}