{
  "type": "Feature",
  "properties": {
    "iso:country":"US",
    "sg:address":"7761 W Tropical Parkway",
    "sg:city":"Las Vegas",
    "sg:classifiers":[
        {
            "category":"Shopping",
            "subcategory":"Stationery & Office Supplies",
            "type":"Retail Goods"
        }
    ],
    "sg:phone":"+1 702 243 3556",
    "sg:postcode":"89149",
    "sg:province":"NV",
    "sg:tags":[
        "equipment"
    ],
    "sg:website":"www.officemax.com",
    "wof:name":"Officemax",
    "wof:placetype":"venue"
},
  "geometry": {"coordinates":[-115.265547,36.271047],"type":"Point"}
}