{
  "type": "Feature",
  "properties": {
    "iso:country":"US",
    "sg:address":"9515 Hillwood Dr",
    "sg:city":"Las Vegas",
    "sg:classifiers":[
        {
            "category":"Insurance",
            "subcategory":"Insurance Agent",
            "type":"Services"
        }
    ],
    "sg:phone":"+1 702 647 2333",
    "sg:postcode":"89134",
    "sg:province":"NV",
    "sg:website":"www.aisins.com",
    "wof:name":"Aviation Insurance Svc-Nv Inc",
    "wof:placetype":"venue"
},
  "geometry": {"coordinates":[-115.303164,36.187369],"type":"Point"}
}