{
  "type": "Feature",
  "properties": {
    "iso:country":"US",
    "sg:address":"1380 E Sahara Ave",
    "sg:city":"Las Vegas",
    "sg:classifiers":[
        {
            "category":"Home & Garden",
            "subcategory":"Furniture",
            "type":"Retail Goods"
        }
    ],
    "sg:phone":"+1 702 463 7109",
    "sg:postcode":"89104",
    "sg:province":"NV",
    "sg:tags":[
        "store"
    ],
    "wof:name":"My Southwest Style Llc",
    "wof:placetype":"venue"
},
  "geometry": {"coordinates":[-115.133986,36.144517],"type":"Point"}
}