{
  "type": "Feature",
  "properties": {
    "iso:country":"US",
    "sg:address":"7408 W Sahara Ave",
    "sg:city":"Las Vegas",
    "sg:classifiers":[
        {
            "category":"Professional",
            "subcategory":"Lawyer & Legal Services",
            "type":"Services"
        }
    ],
    "sg:phone":"+1 702 382 5036",
    "sg:postcode":"89117",
    "sg:province":"NV",
    "wof:name":"Stark Thos M Atty",
    "wof:placetype":"venue"
},
  "geometry": {"coordinates":[-115.254997,36.1441],"type":"Point"}
}