{
  "type": "Feature",
  "properties": {
    "iso:country":"US",
    "sg:address":"1464 Mark Twain Ave",
    "sg:city":"Reno",
    "sg:classifiers":[
        {
            "category":"Food & Beverages",
            "subcategory":"Groceries & Convenience Stores",
            "type":"Retail Goods"
        }
    ],
    "sg:phone":"+1 775 329 2409",
    "sg:postcode":"89509",
    "sg:province":"NV",
    "wof:name":"Gabrielli Deli",
    "wof:placetype":"venue"
},
  "geometry": {"coordinates":[-119.821375,39.510602],"type":"Point"}
}