{
  "type": "Feature",
  "properties": {
    "iso:country":"US",
    "sg:address":"628 Belrose St",
    "sg:city":"Las Vegas",
    "sg:classifiers":[
        {
            "category":"Government",
            "subcategory":"Office",
            "type":"Public Place"
        }
    ],
    "sg:phone":"+1 702 486 7895",
    "sg:postcode":"89107",
    "sg:province":"NV",
    "wof:name":"State Of Nevada Vocational Ctr",
    "wof:placetype":"venue"
},
  "geometry": {"coordinates":[-115.178895,36.178611],"type":"Point"}
}