{
  "type": "Feature",
  "properties": {
    "iso:country":"US",
    "sg:address":"3330 E Tropicana Ave",
    "sg:city":"Las Vegas",
    "sg:classifiers":[
        {
            "category":"Shopping",
            "subcategory":"Comic Books",
            "type":"Retail Goods"
        }
    ],
    "sg:phone":"+1 702 451 6611",
    "sg:postcode":"89121",
    "sg:province":"NV",
    "wof:name":"Cosmic Comics",
    "wof:placetype":"venue"
},
  "geometry": {"coordinates":[-115.101997,36.100101],"type":"Point"}
}