{
  "type": "Feature",
  "properties": {
    "iso:country":"US",
    "sg:address":"5611 S Valley View Blvd",
    "sg:city":"Las Vegas",
    "sg:classifiers":[
        {
            "category":"Deli",
            "type":"Food & Drink"
        }
    ],
    "sg:phone":"+1 702 798 6070",
    "sg:postcode":"89118",
    "sg:province":"NV",
    "wof:name":"Anthony's Deli",
    "wof:placetype":"venue"
},
  "geometry": {"coordinates":[-115.189873,36.087907],"type":"Point"}
}