{
  "type": "Feature",
  "properties": {
    "iso:country":"US",
    "sg:address":"1510 Silver Point Ave",
    "sg:city":"Las Vegas",
    "sg:classifiers":[
        {
            "category":"Personal",
            "type":"Services"
        }
    ],
    "sg:phone":"+1 702 837 5677",
    "sg:postcode":"89123",
    "sg:province":"NV",
    "wof:name":"Longevity Massage & Wellness",
    "wof:placetype":"venue"
},
  "geometry": {"coordinates":[-115.13262899999999,36.014584],"type":"Point"}
}