{
  "type": "Feature",
  "properties": {
    "iso:country":"US",
    "sg:address":"7823 Harbour Towne Ave",
    "sg:city":"Las Vegas",
    "sg:classifiers":[
        {
            "category":"Shopping",
            "subcategory":"Bicycles & Sporting Goods",
            "type":"Retail Goods"
        }
    ],
    "sg:phone":"+1 702 286 7622",
    "sg:postcode":"89113",
    "sg:province":"NV",
    "sg:tags":[
        "golf"
    ],
    "wof:name":"Hohl In One Golf Corporation",
    "wof:placetype":"venue"
},
  "geometry": {"coordinates":[-115.262925,36.097481],"type":"Point"}
}