{
  "type": "Feature",
  "properties": {
    "iso:country":"US",
    "sg:address":"1135 Terminal Way",
    "sg:city":"Reno",
    "sg:classifiers":[
        {
            "category":"Organizations",
            "subcategory":"Religious Organization",
            "type":"Services"
        }
    ],
    "sg:phone":"+1 775 786 2888",
    "sg:postcode":"89502",
    "sg:province":"NV",
    "sg:tags":[
        "church"
    ],
    "wof:name":"Central Church Of Christ",
    "wof:placetype":"venue"
},
  "geometry": {"coordinates":[-119.777348,39.516605],"type":"Point"}
}