{
  "type": "Feature",
  "properties": {
    "iso:country":"US",
    "sg:address":"1800 E Sahara Ave Ste 110",
    "sg:city":"Las Vegas",
    "sg:classifiers":[
        {
            "category":"Health Services",
            "subcategory":"Clinic",
            "type":"Services"
        }
    ],
    "sg:phone":"+1 702 796 8857",
    "sg:postcode":"89104",
    "sg:province":"NV",
    "sg:tags":[
        "counseling",
        "mental"
    ],
    "wof:name":"Jan R. Flint, MA Mft",
    "wof:placetype":"venue"
},
  "geometry": {"coordinates":[-115.125067,36.1447],"type":"Point"}
}