{
  "type": "Feature",
  "properties": {
    "iso:country":"US",
    "sg:address":"5967 Harrison Drive",
    "sg:city":"Las Vegas",
    "sg:classifiers":[
        {
            "category":"Shopping",
            "subcategory":"Clothing, Apparel, & Fashions",
            "type":"Retail Goods"
        }
    ],
    "sg:phone":"+1 702 798 0999",
    "sg:postcode":"89120",
    "sg:province":"NV",
    "sg:tags":[
        "accessory",
        "clothing",
        "women's"
    ],
    "wof:name":"Tutu Tango",
    "wof:placetype":"venue"
},
  "geometry": {"coordinates":[-115.112069,36.081013],"type":"Point"}
}