{
  "type": "Feature",
  "properties": {
    "iso:country":"US",
    "sg:address":"4220 S Maryland Pkwy",
    "sg:city":"Las Vegas",
    "sg:classifiers":[
        {
            "category":"Building & Trades",
            "subcategory":"Construction",
            "type":"Services"
        }
    ],
    "sg:phone":"+1 702 696 1800",
    "sg:postcode":"89119",
    "sg:province":"NV",
    "sg:tags":[
        "home",
        "contractor",
        "improvement"
    ],
    "wof:name":"P H I",
    "wof:placetype":"venue"
},
  "geometry": {"coordinates":[-115.137617,36.11202],"type":"Point"}
}