{
  "type": "Feature",
  "properties": {
    "iso:country":"US",
    "sg:address":"1900 S Carson St",
    "sg:city":"Carson City",
    "sg:classifiers":[
        {
            "category":"Sports & Exercise",
            "subcategory":"Golf",
            "type":"Entertainment"
        }
    ],
    "sg:phone":"+1 877 697 4653",
    "sg:postcode":"89701",
    "sg:province":"NV",
    "sg:website":"www.divine9.com",
    "wof:name":"Divine Nine",
    "wof:placetype":"venue"
},
  "geometry": {"coordinates":[-119.767158,39.149912],"type":"Point"}
}