{
  "type": "Feature",
  "properties": {
    "iso:country":"US",
    "sg:address":"5915 S Eastern Ave Ste 102",
    "sg:city":"Las Vegas",
    "sg:classifiers":[
        {
            "category":"Shopping",
            "subcategory":"Stationery & Office Supplies",
            "type":"Retail Goods"
        }
    ],
    "sg:phone":"+1 702 736 1427",
    "sg:postcode":"89119",
    "sg:province":"NV",
    "sg:tags":[
        "equipment"
    ],
    "sg:website":"www.officedepot.com",
    "wof:name":"Office Depot",
    "wof:placetype":"venue"
},
  "geometry": {"coordinates":[-115.11900300000001,36.082311],"type":"Point"}
}