{
  "type": "Feature",
  "properties": {
    "iso:country":"US",
    "sg:address":"3663 Las Vegas Boulevard S",
    "sg:city":"Las Vegas",
    "sg:classifiers":[
        {
            "category":"Arts & Performance",
            "subcategory":"Art Gallery",
            "type":"Entertainment"
        },
        {
            "category":"Shopping",
            "subcategory":"Jewelry",
            "type":"Retail Goods"
        }
    ],
    "sg:phone":"+1 702 598 3929",
    "sg:postcode":"89109",
    "sg:province":"NV",
    "sg:website":"www.indianrivergallery.com",
    "wof:name":"Indian River Gallery",
    "wof:placetype":"venue"
},
  "geometry": {"coordinates":[-115.172826,36.111036],"type":"Point"}
}