{
  "type": "Feature",
  "properties": {
    "iso:country":"US",
    "sg:address":"6855 Bermuda Rd",
    "sg:city":"Las Vegas",
    "sg:classifiers":[
        {
            "category":"Restaurant",
            "type":"Food & Drink"
        }
    ],
    "sg:phone":"+1 702 263 7667",
    "sg:postcode":"89119",
    "sg:province":"NV",
    "sg:tags":[
        "eating"
    ],
    "wof:name":"To Snack & More",
    "wof:placetype":"venue"
},
  "geometry": {"coordinates":[-115.154579,36.06496],"type":"Point"}
}