{
  "type": "Feature",
  "properties": {
    "iso:country":"US",
    "sg:address":"11061 Zampino St",
    "sg:city":"Las Vegas",
    "sg:classifiers":[
        {
            "category":"Wholesale",
            "subcategory":"Stationery",
            "type":"Manufacturing & Wholesale Goods"
        }
    ],
    "sg:phone":"+1 702 434 8680",
    "sg:postcode":"89141",
    "sg:province":"NV",
    "sg:tags":[
        "decoration",
        "supply"
    ],
    "wof:name":"JLS Distributors",
    "wof:placetype":"venue"
},
  "geometry": {"coordinates":[-115.20722,35.988277],"type":"Point"}
}