{
  "type": "Feature",
  "properties": {
    "iso:country":"US",
    "sg:address":"4015 McLeod Dr",
    "sg:city":"Las Vegas",
    "sg:classifiers":[
        {
            "category":"Professional",
            "subcategory":"Management & Consulting",
            "type":"Services"
        }
    ],
    "sg:phone":"+1 702 433 2200",
    "sg:postcode":"89121",
    "sg:province":"NV",
    "sg:tags":[
        "hospital"
    ],
    "wof:name":"Progressive Hospital Las Vegas",
    "wof:placetype":"venue"
},
  "geometry": {"coordinates":[-115.10991199999999,36.117092],"type":"Point"}
}