{
  "type": "Feature",
  "properties": {
    "iso:country":"US",
    "sg:address":"8733 Villa Ridge Dr",
    "sg:city":"Las Vegas",
    "sg:classifiers":[
        {
            "category":"Manufacturing",
            "subcategory":"Soap",
            "type":"Manufacturing & Wholesale Goods"
        }
    ],
    "sg:phone":"+1 702 243 9453",
    "sg:postcode":"89134",
    "sg:province":"NV",
    "sg:tags":[
        "detergent",
        "mfg"
    ],
    "wof:name":"Soap Sachet of Nevada",
    "wof:placetype":"venue"
},
  "geometry": {"coordinates":[-115.284507,36.217188],"type":"Point"}
}