{
  "type": "Feature",
  "properties": {
    "iso:country":"US",
    "sg:address":"4211 N Production Ct",
    "sg:city":"Las Vegas",
    "sg:classifiers":[
        {
            "category":"Building & Trades",
            "subcategory":"Construction",
            "type":"Services"
        }
    ],
    "sg:phone":"+1 702 651 1700",
    "sg:postcode":"89115",
    "sg:province":"NV",
    "sg:tags":[
        "sub"
    ],
    "wof:name":"D & K Drywall Inc",
    "wof:placetype":"venue"
},
  "geometry": {"coordinates":[-115.09491800000001,36.240052],"type":"Point"}
}