{
  "type": "Feature",
  "properties": {
    "iso:country":"US",
    "sg:address":"4221 Stonebridge Ln",
    "sg:city":"Las Vegas",
    "sg:classifiers":[
        {
            "category":"Wholesale",
            "subcategory":"Durable Goods & Equipment",
            "type":"Manufacturing & Wholesale Goods"
        }
    ],
    "sg:phone":"+1 702 646 0014",
    "sg:postcode":"89108",
    "sg:province":"NV",
    "wof:name":"Allelacent Inc",
    "wof:placetype":"venue"
},
  "geometry": {"coordinates":[-115.197523,36.188883],"type":"Point"}
}