{
  "type": "Feature",
  "properties": {
    "iso:country":"US",
    "sg:address":"1701 W Charleston Blvd",
    "sg:city":"Las Vegas",
    "sg:classifiers":[
        {
            "category":"Professional",
            "subcategory":"Lawyer & Legal Services",
            "type":"Services"
        }
    ],
    "sg:phone":"+1 702 870 2400",
    "sg:postcode":"89102",
    "sg:province":"NV",
    "wof:name":"Linton Linda J Atty",
    "wof:placetype":"venue"
},
  "geometry": {"coordinates":[-115.164001,36.158699],"type":"Point"}
}