{
  "type": "Feature",
  "properties": {
    "iso:country":"US",
    "sg:address":"1591 N Decatur Blvd",
    "sg:city":"Las Vegas",
    "sg:classifiers":[
        {
            "category":"Food & Beverages",
            "subcategory":"Groceries & Convenience Stores",
            "type":"Retail Goods"
        }
    ],
    "sg:phone":"+1 702 631 3496",
    "sg:postcode":"89108",
    "sg:province":"NV",
    "wof:name":"Huey's Mart",
    "wof:placetype":"venue"
},
  "geometry": {"coordinates":[-115.206001,36.188099],"type":"Point"}
}