{
  "type": "Feature",
  "properties": {
    "iso:country":"US",
    "sg:address":"3528 S Maryland Pkwy",
    "sg:city":"Las Vegas",
    "sg:classifiers":[
        {
            "category":"Shopping",
            "subcategory":"Gifts & Souvenirs",
            "type":"Retail Goods"
        }
    ],
    "sg:phone":"+1 702 933 7223",
    "sg:postcode":"89109",
    "sg:province":"NV",
    "sg:tags":[
        "collectible"
    ],
    "wof:name":"Final Lap Racing Collection",
    "wof:placetype":"venue"
},
  "geometry": {"coordinates":[-115.137074,36.126903],"type":"Point"}
}