{
  "type": "Feature",
  "properties": {
    "iso:country":"US",
    "sg:address":"455 Karen Ave",
    "sg:city":"Las Vegas",
    "sg:classifiers":[
        {
            "category":"Organizations",
            "subcategory":"Membership Organization",
            "type":"Services"
        }
    ],
    "sg:phone":"+1 702 946 9200",
    "sg:postcode":"89109",
    "sg:province":"NV",
    "sg:tags":[
        "operation"
    ],
    "wof:name":"Michael Unger",
    "wof:placetype":"venue"
},
  "geometry": {"coordinates":[-115.15431700000001,36.140155],"type":"Point"}
}