{
  "type": "Feature",
  "properties": {
    "iso:country":"US",
    "sg:address":"505 S Arlington Ave",
    "sg:city":"Reno",
    "sg:classifiers":[
        {
            "category":"Professional",
            "subcategory":"Management & Consulting",
            "type":"Services"
        }
    ],
    "sg:phone":"+1 775 322 1391",
    "sg:postcode":"89509",
    "sg:province":"NV",
    "sg:tags":[
        "business"
    ],
    "wof:name":"Writing and Litercy Center",
    "wof:placetype":"venue"
},
  "geometry": {"coordinates":[-119.817219,39.519618],"type":"Point"}
}