{
  "type": "Feature",
  "properties": {
    "iso:country":"US",
    "sg:address":"2300 E Desert Inn Road Suite 11",
    "sg:city":"Las Vegas",
    "sg:classifiers":[
        {
            "category":"Donuts",
            "subcategory":"None",
            "type":"Food & Drink"
        }
    ],
    "sg:phone":"+1 702 796 1790",
    "sg:postcode":"89169",
    "sg:province":"NV",
    "wof:name":"Master Donuts",
    "wof:placetype":"venue"
},
  "geometry": {"coordinates":[-115.11990400000001,36.129829],"type":"Point"}
}