{
  "type": "Feature",
  "properties": {
    "iso:country":"US",
    "sg:address":"1241 W Newlands Dr",
    "sg:city":"Fernley",
    "sg:classifiers":[
        {
            "category":"Travel",
            "subcategory":"Hotels & Motels",
            "type":"Entertainment"
        }
    ],
    "sg:phone":"+1 775 575 6061",
    "sg:postcode":"89408",
    "sg:province":"NV",
    "sg:tags":[
        "operation"
    ],
    "wof:name":"Roger Rentals",
    "wof:placetype":"venue"
},
  "geometry": {"coordinates":[-119.2201,39.609588],"type":"Point"}
}