{
  "type": "Feature",
  "properties": {
    "iso:country":"US",
    "sg:address":"555 W Silver St",
    "sg:city":"Elko",
    "sg:classifiers":[
        {
            "category":"Real Estate",
            "subcategory":"Real Estate Agent",
            "type":"Services"
        }
    ],
    "sg:phone":"+1 775 738 2287",
    "sg:postcode":"89801",
    "sg:province":"NV",
    "wof:name":"Clark Co Real Estate",
    "wof:placetype":"venue"
},
  "geometry": {"coordinates":[-115.771642,40.825209],"type":"Point"}
}