{
  "type": "Feature",
  "properties": {
    "iso:country":"US",
    "sg:address":"4780 W Harmon Ave",
    "sg:city":"Las Vegas",
    "sg:classifiers":[
        {
            "category":"Wholesale",
            "subcategory":"Electrical",
            "type":"Manufacturing & Wholesale Goods"
        }
    ],
    "sg:phone":"+1 702 252 6921",
    "sg:postcode":"89103",
    "sg:province":"NV",
    "sg:tags":[
        "alarm",
        "burglar",
        "system"
    ],
    "wof:name":"Comspec",
    "wof:placetype":"venue"
},
  "geometry": {"coordinates":[-115.205738,36.108238],"type":"Point"}
}