{
  "type": "Feature",
  "properties": {
    "iso:country":"US",
    "sg:address":"1527 W Craig Rd",
    "sg:city":"North Las Vegas",
    "sg:classifiers":[
        {
            "category":"Personal",
            "subcategory":"Beauty Salon",
            "type":"Services"
        }
    ],
    "sg:phone":"+1 702 649 9949",
    "sg:postcode":"89032",
    "sg:province":"NV",
    "sg:tags":[
        "shop"
    ],
    "wof:name":"Classy Nails",
    "wof:placetype":"venue"
},
  "geometry": {"coordinates":[-115.166212,36.239346],"type":"Point"}
}