{
  "type": "Feature",
  "properties": {
    "iso:country":"US",
    "sg:address":"1196 Manhattan Way",
    "sg:city":"Gardnerville",
    "sg:classifiers":[
        {
            "category":"Building & Trades",
            "subcategory":"Landscaping Services",
            "type":"Services"
        }
    ],
    "sg:phone":"+1 775 265 5242",
    "sg:postcode":"89460",
    "sg:province":"NV",
    "sg:tags":[
        "tree"
    ],
    "wof:name":"J Kolesar Tree Svc",
    "wof:placetype":"venue"
},
  "geometry": {"coordinates":[-119.752,38.904856],"type":"Point"}
}