{
  "type": "Feature",
  "properties": {
    "iso:country":"US",
    "sg:address":"1301 Stanford Way",
    "sg:city":"Sparks",
    "sg:classifiers":[
        {
            "category":"Real Estate",
            "subcategory":"Real Estate Operator",
            "type":"Services"
        }
    ],
    "sg:phone":"+1 775 358 3478",
    "sg:postcode":"89431",
    "sg:province":"NV",
    "sg:tags":[
        "mobile",
        "home",
        "site"
    ],
    "wof:name":"Silver Crown Inc",
    "wof:placetype":"venue"
},
  "geometry": {"coordinates":[-119.743188,39.545857],"type":"Point"}
}