{
  "type": "Feature",
  "properties": {
    "iso:country":"US",
    "sg:address":"755 N Roop St Ste 108",
    "sg:city":"Carson City",
    "sg:classifiers":[
        {
            "category":"Health Services",
            "subcategory":"Clinic",
            "type":"Services"
        }
    ],
    "sg:phone":"+1 775 887 0303",
    "sg:postcode":"89701",
    "sg:province":"NV",
    "sg:tags":[
        "counseling",
        "mental"
    ],
    "wof:name":"Carson Mediation & Counseling Center",
    "wof:placetype":"venue"
},
  "geometry": {"coordinates":[-119.761002,39.168201],"type":"Point"}
}