{
  "type": "Feature",
  "properties": {
    "iso:country":"US",
    "sg:address":"8075 W Sahara Ave",
    "sg:city":"Las Vegas",
    "sg:classifiers":[
        {
            "category":"Retail",
            "subcategory":"Auto Repair",
            "type":"Services"
        }
    ],
    "sg:phone":"+1 702 838 1965",
    "sg:postcode":"89117",
    "sg:province":"NV",
    "sg:tags":[
        "automobile",
        "lubrication"
    ],
    "wof:name":"Texaco Xpress Lube",
    "wof:placetype":"venue"
},
  "geometry": {"coordinates":[-115.269739,36.143803],"type":"Point"}
}