{
  "type": "Feature",
  "properties": {
    "iso:country":"US",
    "sg:address":"6161 Candlewood Ct",
    "sg:city":"Las Vegas",
    "sg:classifiers":[
        {
            "category":"Shopping",
            "subcategory":"Computers & Home Electronics",
            "type":"Retail Goods"
        }
    ],
    "sg:phone":"+1 702 453 1995",
    "sg:postcode":"89108",
    "sg:province":"NV",
    "sg:tags":[
        "equipment",
        "electronic",
        "supply"
    ],
    "wof:name":"Conduit Bodies",
    "wof:placetype":"venue"
},
  "geometry": {"coordinates":[-115.227564,36.192497],"type":"Point"}
}