{
  "type": "Feature",
  "properties": {
    "iso:country":"US",
    "sg:address":"735 Spruce Tree Cir",
    "sg:city":"Henderson",
    "sg:classifiers":[
        {
            "category":"Home & Garden",
            "subcategory":"Home Furnishings",
            "type":"Retail Goods"
        }
    ],
    "sg:phone":"+1 702 898 1300",
    "sg:postcode":"89014",
    "sg:province":"NV",
    "sg:tags":[
        "curtain",
        "made",
        "drapery"
    ],
    "wof:name":"A All American Drapperies",
    "wof:placetype":"venue"
},
  "geometry": {"coordinates":[-115.052231,36.069437],"type":"Point"}
}