{
  "type": "Feature",
  "properties": {
    "iso:country":"US",
    "sg:address":"249 W Chicago Ave",
    "sg:city":"Las Vegas",
    "sg:classifiers":[
        {
            "category":"Building & Trades",
            "subcategory":"Plumbing",
            "type":"Services"
        }
    ],
    "sg:phone":"+1 702 382 7260",
    "sg:postcode":"89101",
    "sg:province":"NV",
    "wof:name":"Western Plumbing Wholesale",
    "wof:placetype":"venue"
},
  "geometry": {"coordinates":[-115.159879,36.150089],"type":"Point"}
}