{
  "type": "Feature",
  "properties": {
    "iso:country":"US",
    "sg:address":"8571 Heather Downs Dr",
    "sg:city":"Las Vegas",
    "sg:classifiers":[
        {
            "category":"Professional",
            "type":"Services"
        }
    ],
    "sg:phone":"+1 702 644 2891",
    "sg:postcode":"89113",
    "sg:province":"NV",
    "wof:name":"Ducharme Northwest LLC",
    "wof:placetype":"venue"
},
  "geometry": {"coordinates":[-115.277616,36.099563],"type":"Point"}
}