{
  "type": "Feature",
  "properties": {
    "iso:country":"US",
    "sg:address":"4375 W Reno Ave",
    "sg:city":"Las Vegas",
    "sg:classifiers":[
        {
            "category":"Shopping",
            "subcategory":"Tobacco",
            "type":"Retail Goods"
        }
    ],
    "sg:phone":"+1 702 222 9337",
    "sg:postcode":"89118",
    "sg:province":"NV",
    "sg:tags":[
        "shop"
    ],
    "wof:name":"Champs",
    "wof:placetype":"venue"
},
  "geometry": {"coordinates":[-115.19880000000001,36.097123],"type":"Point"}
}