{
  "type": "Feature",
  "properties": {
    "iso:country":"US",
    "sg:address":"1000 S Rampart Blvd",
    "sg:city":"Las Vegas",
    "sg:classifiers":[
        {
            "category":"Travel",
            "subcategory":"Travel Agent",
            "type":"Entertainment"
        }
    ],
    "sg:phone":"+1 702 968 1600",
    "sg:postcode":"89145",
    "sg:province":"NV",
    "sg:tags":[
        "agency"
    ],
    "sg:website":"www.deserttravellv.com",
    "wof:name":"Desert Travel",
    "wof:placetype":"venue"
},
  "geometry": {"coordinates":[-115.289212,36.165773],"type":"Point"}
}