{
  "type": "Feature",
  "properties": {
    "iso:country":"US",
    "sg:address":"3736 E Flamingo Rd",
    "sg:city":"Las Vegas",
    "sg:classifiers":[
        {
            "category":"Shopping",
            "subcategory":"Bicycles & Sporting Goods",
            "type":"Retail Goods"
        }
    ],
    "sg:phone":"+1 702 435 1978",
    "sg:postcode":"89121",
    "sg:province":"NV",
    "sg:tags":[
        "skating",
        "equipment",
        "skateboard",
        "accessory"
    ],
    "wof:name":"Sub Skates",
    "wof:placetype":"venue"
},
  "geometry": {"coordinates":[-115.092515,36.115347],"type":"Point"}
}