{
  "type": "Feature",
  "properties": {
    "iso:country":"US",
    "sg:address":"3870 E Leonesio Dr",
    "sg:city":"Reno",
    "sg:classifiers":[
        {
            "category":"Shopping",
            "subcategory":"Discount & Variety Stores",
            "type":"Retail Goods"
        }
    ],
    "sg:phone":"+1 775 673 9139",
    "sg:postcode":"89512",
    "sg:province":"NV",
    "sg:tags":[
        "merchandise",
        "general"
    ],
    "wof:name":"Jacks Artifacts",
    "wof:placetype":"venue"
},
  "geometry": {"coordinates":[-119.784204,39.565469],"type":"Point"}
}