{
  "type": "Feature",
  "properties": {
    "iso:country":"US",
    "sg:address":"7380 S Eastern Ave",
    "sg:city":"Las Vegas",
    "sg:classifiers":[
        {
            "category":"Shopping",
            "subcategory":"Music",
            "type":"Retail Goods"
        }
    ],
    "sg:phone":"+1 702 361 7469",
    "sg:postcode":"89123",
    "sg:province":"NV",
    "sg:tags":[
        "video",
        "disc",
        "tape",
        "cassette"
    ],
    "wof:name":"Movieland",
    "wof:placetype":"venue"
},
  "geometry": {"coordinates":[-115.118163,36.053443],"type":"Point"}
}