{
  "type": "Feature",
  "properties": {
    "iso:country":"US",
    "sg:address":"4401 E Sunset Rd",
    "sg:city":"Henderson",
    "sg:classifiers":[
        {
            "category":"Shopping",
            "subcategory":"Optician",
            "type":"Retail Goods"
        }
    ],
    "sg:phone":"+1 702 454 2020",
    "sg:postcode":"89014",
    "sg:province":"NV",
    "sg:tags":[
        "eyewear"
    ],
    "wof:name":"Pearle Vision",
    "wof:placetype":"venue"
},
  "geometry": {"coordinates":[-115.078003,36.0709],"type":"Point"}
}