{
  "type": "Feature",
  "properties": {
    "iso:country":"US",
    "sg:address":"2375 S Jones Blvd",
    "sg:city":"Las Vegas",
    "sg:classifiers":[
        {
            "category":"Utilities",
            "subcategory":"Mobile Phone",
            "type":"Services"
        }
    ],
    "sg:phone":"+1 702 433 2111",
    "sg:postcode":"89146",
    "sg:province":"NV",
    "sg:tags":[
        "telephone",
        "cellular"
    ],
    "wof:name":"Cellular 4 Sale",
    "wof:placetype":"venue"
},
  "geometry": {"coordinates":[-115.225423,36.145753],"type":"Point"}
}