{
  "type": "Feature",
  "properties": {
    "iso:country":"US",
    "sg:address":"206 N Carson S",
    "sg:city":"Carson City",
    "sg:classifiers":[
        {
            "category":"Shopping",
            "subcategory":"Clothing, Apparel, & Fashions",
            "type":"Retail Goods"
        }
    ],
    "sg:phone":"+1 775 883 3633",
    "sg:postcode":"89701",
    "sg:province":"NV",
    "sg:website":"www.facebook.com/pages/Carson-Ci...",
    "wof:name":"Sweet Mojo",
    "wof:placetype":"venue"
},
  "geometry": {"coordinates":[-119.767439,39.164941],"type":"Point"}
}