{
  "type": "Feature",
  "properties": {
    "iso:country":"US",
    "sg:address":"3200 Las Vegas Blvd S",
    "sg:city":"Las Vegas",
    "sg:classifiers":[
        {
            "category":"Shopping",
            "subcategory":"Mobile Phones",
            "type":"Retail Goods"
        }
    ],
    "sg:phone":"+1 702 650 2585",
    "sg:postcode":"89109",
    "sg:province":"NV",
    "wof:name":"Fones Gone Wild",
    "wof:placetype":"venue"
},
  "geometry": {"coordinates":[-115.168031,36.127746],"type":"Point"}
}