{
  "type": "Feature",
  "properties": {
    "iso:country":"US",
    "sg:address":"1451 College Pkwy",
    "sg:city":"Carson City",
    "sg:classifiers":[
        {
            "category":"Autos & Motor Vehicles",
            "subcategory":"Fuel & Gas Station",
            "type":"Retail Goods"
        }
    ],
    "sg:phone":"+1 800 789 4455",
    "sg:postcode":"89706",
    "sg:province":"NV",
    "sg:website":"www.maverik.com",
    "wof:name":"Maverik",
    "wof:placetype":"venue"
},
  "geometry": {"coordinates":[-119.751219,39.189001],"type":"Point"}
}