{
  "type": "Feature",
  "properties": {
    "iso:country":"US",
    "sg:address":"1635 Village Center Cir",
    "sg:city":"Las Vegas",
    "sg:classifiers":[
        {
            "category":"Professional",
            "subcategory":"Lawyer & Legal Services",
            "type":"Services"
        }
    ],
    "sg:phone":"+1 702 255 1300",
    "sg:postcode":"89134",
    "sg:province":"NV",
    "sg:tags":[
        "attorney"
    ],
    "wof:name":"Phillip A Kantor Law Office",
    "wof:placetype":"venue"
},
  "geometry": {"coordinates":[-115.302633,36.189202],"type":"Point"}
}