{
  "type": "Feature",
  "properties": {
    "iso:country":"US",
    "sg:address":"9430 W Lake Mead Blvd",
    "sg:city":"Las Vegas",
    "sg:classifiers":[
        {
            "category":"Shopping",
            "type":"Retail Goods"
        }
    ],
    "sg:phone":"+1 702 869 0006",
    "sg:postcode":"89134",
    "sg:province":"NV",
    "sg:tags":[
        "telephone",
        "cellular"
    ],
    "wof:name":"Nevada Bell PCS Store",
    "wof:placetype":"venue"
},
  "geometry": {"coordinates":[-115.302537,36.206336],"type":"Point"}
}