{
  "type": "Feature",
  "properties": {
    "iso:country":"US",
    "sg:address":"4240 E Craig Rd",
    "sg:city":"North Las Vegas",
    "sg:classifiers":[
        {
            "category":"Food & Beverages",
            "subcategory":"Groceries & Convenience Stores",
            "type":"Retail Goods"
        }
    ],
    "sg:phone":"+1 702 642 1224",
    "sg:postcode":"89030",
    "sg:province":"NV",
    "wof:name":"Rebel Oil Co",
    "wof:placetype":"venue"
},
  "geometry": {"coordinates":[-115.081117,36.240635],"type":"Point"}
}