{
  "type": "Feature",
  "properties": {
    "iso:country":"US",
    "sg:address":"309 W Lake Mead Parkway",
    "sg:city":"Henderson",
    "sg:classifiers":[
        {
            "category":"Professional",
            "subcategory":"Lawyer & Legal Services",
            "type":"Services"
        }
    ],
    "sg:phone":"+1 702 737 1122",
    "sg:postcode":"89015",
    "sg:province":"NV",
    "sg:tags":[
        "personal",
        "injury"
    ],
    "wof:name":"Rohay Ralph J Atty",
    "wof:placetype":"venue"
},
  "geometry": {"coordinates":[-114.968504,36.034689],"type":"Point"}
}