{
  "type": "Feature",
  "properties": {
    "iso:country":"US",
    "sg:address":"333 Sheckler Rd",
    "sg:city":"Fallon",
    "sg:classifiers":[
        {
            "category":"Recreation",
            "type":"Entertainment"
        }
    ],
    "sg:phone":"+1 775 423 7091",
    "sg:postcode":"89406",
    "sg:province":"NV",
    "sg:tags":[
        "pool",
        "swimming"
    ],
    "wof:name":"Churchill County Swimming Pool",
    "wof:placetype":"venue"
},
  "geometry": {"coordinates":[-118.787694,39.459778],"type":"Point"}
}