{
  "type": "Feature",
  "properties": {
    "iso:country":"US",
    "sg:address":"1465 W 4th St",
    "sg:city":"Reno",
    "sg:classifiers":[
        {
            "category":"Building & Trades",
            "subcategory":"Electrical",
            "type":"Services"
        }
    ],
    "sg:phone":"+1 775 329 0407",
    "sg:postcode":"89503",
    "sg:province":"NV",
    "sg:tags":[
        "electrical",
        "contractor"
    ],
    "sg:website":"www.parelectric.com",
    "wof:name":"PAR Electrical Contractors Inc",
    "wof:placetype":"venue"
},
  "geometry": {"coordinates":[-119.83143800000001,39.525435],"type":"Point"}
}