{
  "type": "Feature",
  "properties": {
    "iso:country":"US",
    "sg:address":"2400 S Cimarron Rd",
    "sg:city":"Las Vegas",
    "sg:classifiers":[
        {
            "category":"Health Services",
            "subcategory":"Health Practitioner",
            "type":"Services"
        }
    ],
    "sg:phone":"+1 702 375 6505",
    "sg:postcode":"89117",
    "sg:province":"NV",
    "sg:tags":[
        "psychologist"
    ],
    "wof:name":"Academic & Psychological Test",
    "wof:placetype":"venue"
},
  "geometry": {"coordinates":[-115.269929,36.143883],"type":"Point"}
}