{
  "type": "Feature",
  "properties": {
    "iso:country":"US",
    "sg:address":"3900 Paradise Rd",
    "sg:city":"Las Vegas",
    "sg:classifiers":[
        {
            "category":"Shopping",
            "subcategory":"Clothing, Apparel, & Fashions",
            "type":"Retail Goods"
        },
        {
            "category":"Personal",
            "type":"Services"
        }
    ],
    "sg:phone":"+1 702 796 6444",
    "sg:postcode":"89169",
    "sg:province":"NV",
    "sg:tags":[
        "planning",
        "men's",
        "clothing",
        "wedding"
    ],
    "sg:website":"www.tuxandgown.com",
    "wof:name":"Renta-Dress & Tux Shop",
    "wof:placetype":"venue"
},
  "geometry": {"coordinates":[-115.154359,36.118004],"type":"Point"}
}