{
  "type": "Feature",
  "properties": {
    "iso:country":"US",
    "sg:address":"737 Straight St",
    "sg:city":"Las Vegas",
    "sg:classifiers":[
        {
            "category":"Autos & Motor Vehicles",
            "subcategory":"Boat Sales",
            "type":"Retail Goods"
        }
    ],
    "sg:phone":"+1 702 453 8383",
    "sg:postcode":"89110",
    "sg:province":"NV",
    "sg:tags":[
        "supply"
    ],
    "wof:name":"Blazin Bell Tech",
    "wof:placetype":"venue"
},
  "geometry": {"coordinates":[-115.041684,36.174212],"type":"Point"}
}