{
  "type": "Feature",
  "properties": {
    "iso:country":"US",
    "sg:address":"4480 Spring Mountain Road",
    "sg:city":"Las Vegas",
    "sg:classifiers":[
        {
            "category":"Shopping",
            "subcategory":"Bridal",
            "type":"Retail Goods"
        }
    ],
    "sg:phone":"+1 702 893 9770",
    "sg:postcode":"89102",
    "sg:province":"NV",
    "wof:name":"Bridal & Etc",
    "wof:placetype":"venue"
},
  "geometry": {"coordinates":[-115.20130399999999,36.126374],"type":"Point"}
}