{
  "type": "Feature",
  "properties": {
    "iso:country":"US",
    "sg:address":"1276 Santa Fe Ct",
    "sg:city":"Minden",
    "sg:classifiers":[
        {
            "category":"Retail",
            "subcategory":"Repair Shop",
            "type":"Services"
        }
    ],
    "sg:phone":"+1 775 267 1445",
    "sg:postcode":"89423",
    "sg:province":"NV",
    "sg:tags":[
        "related"
    ],
    "wof:name":"Mattos Enterprises Inc",
    "wof:placetype":"venue"
},
  "geometry": {"coordinates":[-119.743663,39.051681],"type":"Point"}
}