{
  "type": "Feature",
  "properties": {
    "iso:country":"US",
    "sg:address":"4530 E Charleston Blvd",
    "sg:city":"Las Vegas",
    "sg:classifiers":[
        {
            "category":"Restaurant",
            "type":"Food & Drink"
        }
    ],
    "sg:phone":"+1 702 452 6780",
    "sg:postcode":"89104",
    "sg:province":"NV",
    "wof:name":"Dinero Envia",
    "wof:placetype":"venue"
},
  "geometry": {"coordinates":[-115.075996,36.158901],"type":"Point"}
}