{
  "type": "Feature",
  "properties": {
    "iso:country":"US",
    "sg:address":"8940 W Tropicana Ave",
    "sg:city":"Las Vegas",
    "sg:classifiers":[
        {
            "category":"Health Services",
            "subcategory":"Dentist",
            "type":"Services"
        }
    ],
    "sg:phone":"+1 702 365 6637",
    "sg:postcode":"89147",
    "sg:province":"NV",
    "sg:website":"www.drrandwaldron.com/",
    "wof:name":"Rand C Waldron DDS",
    "wof:placetype":"venue"
},
  "geometry": {"coordinates":[-115.286571,36.100504],"type":"Point"}
}