{
  "type": "Feature",
  "properties": {
    "iso:country":"US",
    "sg:address":"6396 W Sahara Ave",
    "sg:city":"Las Vegas",
    "sg:classifiers":[
        {
            "category":"Professional",
            "subcategory":"Computer Services",
            "type":"Services"
        }
    ],
    "sg:phone":"+1 702 871 9847",
    "sg:postcode":"89146",
    "sg:province":"NV",
    "wof:name":"1 Computer Pro",
    "wof:placetype":"venue"
},
  "geometry": {"coordinates":[-115.233375,36.144128],"type":"Point"}
}