{
  "type": "Feature",
  "properties": {
    "iso:country":"US",
    "sg:address":"341 Ski Way",
    "sg:city":"Incline Village",
    "sg:classifiers":[
        {
            "category":"Restaurant",
            "type":"Food & Drink"
        }
    ],
    "sg:phone":"+1 775 833 0606",
    "sg:postcode":"89451",
    "sg:province":"NV",
    "sg:tags":[
        "eating"
    ],
    "wof:name":"Dhy",
    "wof:placetype":"venue"
},
  "geometry": {"coordinates":[-119.93226199999999,39.248933],"type":"Point"}
}