{
  "type": "Feature",
  "properties": {
    "iso:country":"US",
    "sg:address":"6700 W Charleston Boulevard",
    "sg:city":"Las Vegas",
    "sg:classifiers":[
        {
            "category":"Restaurant",
            "type":"Food & Drink"
        }
    ],
    "sg:phone":"+1 702 877 2123",
    "sg:postcode":"89146",
    "sg:province":"NV",
    "sg:tags":[
        "hawaiian"
    ],
    "wof:name":"Maui Rose Hawaiian Bbq",
    "wof:placetype":"venue"
},
  "geometry": {"coordinates":[-115.241903,36.159271],"type":"Point"}
}