{
  "type": "Feature",
  "properties": {
    "iso:country":"US",
    "sg:address":"7260 S Rainbow Blvd Ste 104",
    "sg:city":"Las Vegas",
    "sg:classifiers":[
        {
            "category":"Health Services",
            "subcategory":"Dentist",
            "type":"Services"
        }
    ],
    "sg:phone":"+1 702 628 9104",
    "sg:postcode":"89118",
    "sg:province":"NV",
    "sg:website":"www.rainspringsdental.com/appoin...",
    "wof:name":"Rainsprings Dental Group & Orthodontics",
    "wof:placetype":"venue"
},
  "geometry": {"coordinates":[-115.242285,36.056699],"type":"Point"}
}