{
  "type": "Feature",
  "properties": {
    "iso:country":"US",
    "sg:address":"4648 Old Clear Creek Rd",
    "sg:city":"Carson City",
    "sg:classifiers":[
        {
            "category":"Building & Trades",
            "subcategory":"Construction",
            "type":"Services"
        }
    ],
    "sg:phone":"+1 775 883 2841",
    "sg:postcode":"89705",
    "sg:province":"NV",
    "wof:name":"Linwood Homes By Silverstate",
    "wof:placetype":"venue"
},
  "geometry": {"coordinates":[-119.808262,39.113793],"type":"Point"}
}