{
  "type": "Feature",
  "properties": {
    "iso:country":"US",
    "sg:address":"1755 Plumb Ln",
    "sg:city":"Reno",
    "sg:classifiers":[
        {
            "category":"Wholesale",
            "subcategory":"Medical Equipment & Supplies",
            "type":"Manufacturing & Wholesale Goods"
        }
    ],
    "sg:phone":"+1 775 786 2252",
    "sg:postcode":"89502",
    "sg:province":"NV",
    "sg:tags":[
        "hospital"
    ],
    "wof:name":"Medex Marketing Inc",
    "wof:placetype":"venue"
},
  "geometry": {"coordinates":[-119.778177,39.505941],"type":"Point"}
}