{
  "type": "Feature",
  "properties": {
    "iso:country":"US",
    "sg:address":"4988 San Rafael Cir",
    "sg:city":"Las Vegas",
    "sg:classifiers":[
        {
            "category":"Arts & Performance",
            "subcategory":"Theater",
            "type":"Entertainment"
        }
    ],
    "sg:phone":"+1 702 433 9008",
    "sg:postcode":"89122",
    "sg:province":"NV",
    "sg:tags":[
        "theatrical"
    ],
    "wof:name":"Adina & Friends",
    "wof:placetype":"venue"
},
  "geometry": {"coordinates":[-115.063235,36.099115],"type":"Point"}
}