{
  "type": "Feature",
  "properties": {
    "iso:country":"US",
    "sg:address":"2901 W Washington Ave",
    "sg:city":"Las Vegas",
    "sg:classifiers":[
        {
            "category":"Shopping",
            "subcategory":"Beauty & Cosmetics",
            "type":"Retail Goods"
        }
    ],
    "sg:phone":"+1 702 648 3122",
    "sg:postcode":"89107",
    "sg:province":"NV",
    "sg:tags":[
        "supply"
    ],
    "wof:name":"New Star Beauty Supplies",
    "wof:placetype":"venue"
},
  "geometry": {"coordinates":[-115.181,36.181],"type":"Point"}
}