{
  "type": "Feature",
  "properties": {
    "iso:country":"US",
    "sg:address":"8526 Del Webb Boulevard",
    "sg:city":"Las Vegas",
    "sg:classifiers":[
        {
            "category":"Health Services",
            "subcategory":"Doctor",
            "type":"Services"
        },
        {
            "category":"Community Center",
            "type":"Public Place"
        }
    ],
    "sg:phone":"+1 702 254 9192",
    "sg:postcode":"89134",
    "sg:province":"NV",
    "sg:tags":[
        "medical",
        "practice",
        "family"
    ],
    "wof:name":"Rainbow Medical Centers",
    "wof:placetype":"venue"
},
  "geometry": {"coordinates":[-115.280283,36.210245],"type":"Point"}
}