{
  "type": "Feature",
  "properties": {
    "iso:country":"US",
    "sg:address":"3056 Sheridan Street",
    "sg:city":"Las Vegas",
    "sg:classifiers":[
        {
            "category":"Retail",
            "subcategory":"Repair Shop",
            "type":"Services"
        }
    ],
    "sg:phone":"+1 702 878 7172",
    "sg:postcode":"89102",
    "sg:province":"NV",
    "sg:tags":[
        "reupholstery",
        "furniture"
    ],
    "wof:name":"Upholstery Cleaning Specialists",
    "wof:placetype":"venue"
},
  "geometry": {"coordinates":[-115.18854399999999,36.134967],"type":"Point"}
}