{
  "type": "Feature",
  "properties": {
    "iso:country":"US",
    "sg:address":"287 Bowsprit Ct",
    "sg:city":"Las Vegas",
    "sg:classifiers":[
        {
            "category":"Restaurant",
            "type":"Food & Drink"
        }
    ],
    "sg:phone":"+1 702 263 8367",
    "sg:postcode":"89183",
    "sg:province":"NV",
    "sg:tags":[
        "eating"
    ],
    "wof:name":"Robert Buist",
    "wof:placetype":"venue"
},
  "geometry": {"coordinates":[-115.16069299999999,36.009322],"type":"Point"}
}