{
  "type": "Feature",
  "properties": {
    "iso:country":"US",
    "sg:address":"210 Marsh Ave",
    "sg:city":"Reno",
    "sg:classifiers":[
        {
            "category":"Personal",
            "subcategory":"Beauty Salon",
            "type":"Services"
        }
    ],
    "sg:phone":"+1 775 323 0606",
    "sg:postcode":"89509",
    "sg:province":"NV",
    "wof:name":"Aloha Skin Care By Chin",
    "wof:placetype":"venue"
},
  "geometry": {"coordinates":[-119.813908,39.518974],"type":"Point"}
}