{
  "type": "Feature",
  "properties": {
    "iso:country":"US",
    "sg:address":"3985 Willowsprings Dr",
    "sg:city":"Reno",
    "sg:classifiers":[
        {
            "category":"Restaurant",
            "type":"Food & Drink"
        }
    ],
    "sg:phone":"+1 775 826 8188",
    "sg:postcode":"89519",
    "sg:province":"NV",
    "sg:tags":[
        "eating"
    ],
    "wof:name":"The Hilltop Grill",
    "wof:placetype":"venue"
},
  "geometry": {"coordinates":[-119.861378,39.50789],"type":"Point"}
}