{
  "type": "Feature",
  "properties": {
    "iso:country":"US",
    "sg:address":"4180 S Durango Dr",
    "sg:city":"Las Vegas",
    "sg:classifiers":[
        {
            "category":"Health Services",
            "subcategory":"Optometrist",
            "type":"Services"
        }
    ],
    "sg:phone":"+1 702 732 2020",
    "sg:postcode":"89147",
    "sg:province":"NV",
    "wof:name":"Adler Joel OD",
    "wof:placetype":"venue"
},
  "geometry": {"coordinates":[-115.278851,36.113361],"type":"Point"}
}