{
  "type": "Feature",
  "properties": {
    "iso:country":"US",
    "sg:address":"7245 S Durango Dr",
    "sg:city":"Las Vegas",
    "sg:classifiers":[
        {
            "category":"Fast Food",
            "type":"Food & Drink"
        },
        {
            "category":"Restaurant",
            "type":"Food & Drink"
        }
    ],
    "sg:phone":"+1 702 839 9600",
    "sg:postcode":"89113",
    "sg:province":"NV",
    "sg:tags":[
        "traditional",
        "american"
    ],
    "sg:website":"www.sonicdrivein.com",
    "wof:name":"Sonic Drive-In",
    "wof:placetype":"venue"
},
  "geometry": {"coordinates":[-115.279241,36.056529],"type":"Point"}
}