{
  "type": "Feature",
  "properties": {
    "iso:country":"US",
    "sg:address":"325 Convention Center Dr",
    "sg:city":"Las Vegas",
    "sg:classifiers":[
        {
            "category":"Travel",
            "subcategory":"Hotels & Motels",
            "type":"Entertainment"
        }
    ],
    "sg:phone":"+1 702 650 2000",
    "sg:postcode":"89109",
    "sg:province":"NV",
    "wof:name":"Marriott Hotels Resorts Suites",
    "wof:placetype":"venue"
},
  "geometry": {"coordinates":[-115.156998,36.132401],"type":"Point"}
}