{
  "type": "Feature",
  "properties": {
    "iso:country":"US",
    "sg:address":"2585 E Flamingo Rd",
    "sg:city":"Las Vegas",
    "sg:classifiers":[
        {
            "category":"Personal",
            "subcategory":"Beauty Salon",
            "type":"Services"
        }
    ],
    "sg:phone":"+1 702 792 4247",
    "sg:postcode":"89121",
    "sg:province":"NV",
    "wof:name":"Euphoria Salons & Day Spas",
    "wof:placetype":"venue"
},
  "geometry": {"coordinates":[-115.11523800000001,36.114738],"type":"Point"}
}