{
  "type": "Feature",
  "properties": {
    "iso:country":"US",
    "sg:address":"3081 Business Ln",
    "sg:city":"Las Vegas",
    "sg:classifiers":[
        {
            "category":"Building & Trades",
            "subcategory":"Plumbing",
            "type":"Services"
        }
    ],
    "sg:phone":"+1 702 730 3032",
    "sg:postcode":"89103",
    "sg:province":"NV",
    "sg:tags":[
        "conditioning",
        "air",
        "system",
        "contractor"
    ],
    "sg:website":"www.premierlv.com",
    "wof:name":"Premier Heating & Cooling LLC",
    "wof:placetype":"venue"
},
  "geometry": {"coordinates":[-115.181595,36.109329],"type":"Point"}
}