{
  "type": "Feature",
  "properties": {
    "iso:country":"US",
    "sg:address":"2835 S Jones Blvd",
    "sg:city":"Las Vegas",
    "sg:classifiers":[
        {
            "category":"Insurance",
            "subcategory":"Insurance Agent",
            "type":"Services"
        }
    ],
    "sg:phone":"+1 702 277 0793",
    "sg:postcode":"89146",
    "sg:province":"NV",
    "wof:name":"John Stewart & Co Inc",
    "wof:placetype":"venue"
},
  "geometry": {"coordinates":[-115.225196,36.137335],"type":"Point"}
}