{
  "type": "Feature",
  "properties": {
    "iso:country":"US",
    "sg:address":"8439 Placid St",
    "sg:city":"Las Vegas",
    "sg:classifiers":[
        {
            "category":"Personal",
            "type":"Services"
        }
    ],
    "sg:phone":"+1 702 361 1756",
    "sg:postcode":"89123",
    "sg:province":"NV",
    "wof:name":"J&K Rentals Inc",
    "wof:placetype":"venue"
},
  "geometry": {"coordinates":[-115.158956,36.035778],"type":"Point"}
}