{
  "type": "Feature",
  "properties": {
    "iso:country":"US",
    "sg:address":"9413 Salt Water Ct",
    "sg:city":"Las Vegas",
    "sg:classifiers":[
        {
            "category":"Personal",
            "type":"Services"
        }
    ],
    "sg:phone":"+1 702 360 3756",
    "sg:postcode":"89117",
    "sg:province":"NV",
    "sg:tags":[
        "party",
        "planning",
        "event"
    ],
    "wof:name":"Romantique Expressions",
    "wof:placetype":"venue"
},
  "geometry": {"coordinates":[-115.298783,36.134456],"type":"Point"}
}