{
  "type": "Feature",
  "properties": {
    "iso:country":"US",
    "sg:address":"9325 S Jones Blvd",
    "sg:city":"Las Vegas",
    "sg:classifiers":[
        {
            "category":"Mining & Drilling",
            "type":"Manufacturing & Wholesale Goods"
        }
    ],
    "sg:phone":"+1 702 263 2150",
    "sg:postcode":"89139",
    "sg:province":"NV",
    "sg:tags":[
        "construction"
    ],
    "wof:name":"Hanson Aggregates West Inc",
    "wof:placetype":"venue"
},
  "geometry": {"coordinates":[-115.225689,36.015581],"type":"Point"}
}