{
  "type": "Feature",
  "properties": {
    "iso:country":"US",
    "sg:address":"5373 San Milano Ave",
    "sg:city":"Las Vegas",
    "sg:classifiers":[
        {
            "category":"Professional",
            "subcategory":"Detective & Security Services",
            "type":"Services"
        }
    ],
    "sg:phone":"+1 702 353 2256",
    "sg:postcode":"89141",
    "sg:province":"NV",
    "sg:tags":[
        "car"
    ],
    "wof:name":"A Giggle & A Wiggle Bouncers",
    "wof:placetype":"venue"
},
  "geometry": {"coordinates":[-115.215761,35.996658],"type":"Point"}
}