{
  "type": "Feature",
  "properties": {
    "iso:country":"US",
    "sg:address":"6340 McLeod Dr",
    "sg:city":"Las Vegas",
    "sg:classifiers":[
        {
            "category":"Manufacturing",
            "subcategory":"Signs",
            "type":"Manufacturing & Wholesale Goods"
        }
    ],
    "sg:phone":"+1 702 798 6777",
    "sg:postcode":"89120",
    "sg:province":"NV",
    "sg:tags":[
        "mfg"
    ],
    "wof:name":"Sin City Signs & Lighting",
    "wof:placetype":"venue"
},
  "geometry": {"coordinates":[-115.112707,36.072442],"type":"Point"}
}