{
  "type": "Feature",
  "properties": {
    "iso:country":"US",
    "sg:address":"3920 Ponderosa Dr",
    "sg:city":"Carson City",
    "sg:classifiers":[
        {
            "category":"Manufacturing",
            "subcategory":"Jewelry",
            "type":"Manufacturing & Wholesale Goods"
        }
    ],
    "sg:phone":"+1 775 883 4120",
    "sg:postcode":"89701",
    "sg:province":"NV",
    "sg:tags":[
        "shop",
        "novelty",
        "gift",
        "souvenir"
    ],
    "wof:name":"Stoned Frog",
    "wof:placetype":"venue"
},
  "geometry": {"coordinates":[-119.758922,39.130413],"type":"Point"}
}