{
  "type": "Feature",
  "properties": {
    "iso:country":"US",
    "sg:address":"200 S Rainbow Blvd",
    "sg:city":"Las Vegas",
    "sg:classifiers":[
        {
            "category":"Retail",
            "subcategory":"Laundry & Dry Cleaning",
            "type":"Services"
        }
    ],
    "sg:phone":"+1 702 254 5050",
    "sg:postcode":"89145",
    "sg:province":"NV",
    "sg:tags":[
        "drycleaning",
        "plant"
    ],
    "wof:name":"Classic Cleaners Of Las Vegas",
    "wof:placetype":"venue"
},
  "geometry": {"coordinates":[-115.244287,36.172184],"type":"Point"}
}