{
  "type": "Feature",
  "properties": {
    "iso:country":"US",
    "sg:address":"475 Kirman Ave",
    "sg:city":"Reno",
    "sg:classifiers":[
        {
            "category":"Health Services",
            "subcategory":"Doctor",
            "type":"Services"
        }
    ],
    "sg:phone":"+1 775 786 3401",
    "sg:postcode":"89502",
    "sg:province":"NV",
    "wof:name":"David R Jarrett DDS",
    "wof:placetype":"venue"
},
  "geometry": {"coordinates":[-119.79851499999999,39.522075],"type":"Point"}
}