{
  "type": "Feature",
  "properties": {
    "iso:country":"US",
    "sg:address":"705 Aultman St",
    "sg:city":"Ely",
    "sg:classifiers":[
        {
            "category":"Health Services",
            "subcategory":"Clinic",
            "type":"Services"
        }
    ],
    "sg:phone":"+1 775 289 9933",
    "sg:postcode":"89301",
    "sg:province":"NV",
    "sg:tags":[
        "home"
    ],
    "wof:name":"Aerocare Inc",
    "wof:placetype":"venue"
},
  "geometry": {"coordinates":[-114.89020499999999,39.248388],"type":"Point"}
}