{
  "type": "Feature",
  "properties": {
    "iso:country":"US",
    "sg:address":"315 11th St",
    "sg:city":"Ely",
    "sg:classifiers":[
        {
            "category":"Government",
            "subcategory":"Post Office",
            "type":"Public Place"
        }
    ],
    "sg:phone":"+1 775 000 1111",
    "sg:postcode":"89301",
    "sg:province":"NV",
    "wof:name":"US Post Office",
    "wof:placetype":"venue"
},
  "geometry": {"coordinates":[-114.886831,39.249475],"type":"Point"}
}