{
  "type": "Feature",
  "properties": {
    "iso:country":"US",
    "sg:address":"2101 S Decatur Blvd",
    "sg:city":"Las Vegas",
    "sg:classifiers":[
        {
            "category":"Retail",
            "subcategory":"Laundry & Dry Cleaning",
            "type":"Services"
        },
        {
            "category":"Shopping",
            "subcategory":"Clothing, Apparel, & Fashions",
            "type":"Retail Goods"
        }
    ],
    "sg:phone":"+1 702 259 6066",
    "sg:postcode":"89102",
    "sg:province":"NV",
    "sg:tags":[
        "alteration"
    ],
    "wof:name":"Ella's Alterations",
    "wof:placetype":"venue"
},
  "geometry": {"coordinates":[-115.208222,36.14906],"type":"Point"}
}