{
  "type": "Feature",
  "properties": {
    "iso:country":"US",
    "sg:address":"50 E Greg St",
    "sg:city":"Sparks",
    "sg:classifiers":[
        {
            "category":"Wholesale",
            "subcategory":"Vending Machines",
            "type":"Manufacturing & Wholesale Goods"
        }
    ],
    "sg:phone":"+1 775 323 3224",
    "sg:postcode":"89431",
    "sg:province":"NV",
    "sg:tags":[
        "operates"
    ],
    "sg:website":"www.renosnaxsales.com",
    "wof:name":"Reno Toms Snax Sales",
    "wof:placetype":"venue"
},
  "geometry": {"coordinates":[-119.740893,39.521622],"type":"Point"}
}