{
  "type": "Feature",
  "properties": {
    "iso:country":"US",
    "sg:address":"510 S Boulder Hwy",
    "sg:city":"Henderson",
    "sg:classifiers":[
        {
            "category":"Ice Cream",
            "type":"Food & Drink"
        }
    ],
    "sg:phone":"+1 702 564 7482",
    "sg:postcode":"89015",
    "sg:province":"NV",
    "sg:tags":[
        "frozen",
        "yogurt"
    ],
    "sg:website":"www.baskinrobbins.com",
    "wof:name":"Baskin-Robbins",
    "wof:placetype":"venue"
},
  "geometry": {"coordinates":[-114.973722,36.032939],"type":"Point"}
}