{
  "type": "Feature",
  "properties": {
    "iso:country":"US",
    "sg:address":"10345 S Eastern Ave",
    "sg:city":"Henderson",
    "sg:classifiers":[
        {
            "category":"Building & Trades",
            "subcategory":"Construction",
            "type":"Services"
        }
    ],
    "sg:phone":"+1 702 655 2870",
    "sg:postcode":"89052",
    "sg:province":"NV",
    "sg:tags":[
        "designer",
        "business",
        "contractor",
        "dealer",
        "pool",
        "swimming"
    ],
    "wof:name":"Southern Nevada Pools",
    "wof:placetype":"venue"
},
  "geometry": {"coordinates":[-115.106182,36.000365],"type":"Point"}
}