{
  "type": "Feature",
  "properties": {
    "iso:country":"US",
    "sg:address":"445 W Craig Rd Ste 112",
    "sg:city":"North Las Vegas",
    "sg:classifiers":[
        {
            "category":"Insurance",
            "subcategory":"Health Insurance",
            "type":"Services"
        }
    ],
    "sg:phone":"+1 702 214 0896",
    "sg:postcode":"89032",
    "sg:province":"NV",
    "sg:tags":[
        "market"
    ],
    "wof:name":"The Natural Garden",
    "wof:placetype":"venue"
},
  "geometry": {"coordinates":[-115.146683,36.239287],"type":"Point"}
}