{
  "type": "Feature",
  "properties": {
    "iso:country":"US",
    "sg:address":"631 N Stephanie St",
    "sg:city":"Henderson",
    "sg:classifiers":[
        {
            "category":"Shopping",
            "type":"Retail Goods"
        }
    ],
    "sg:phone":"+1 702 567 8186",
    "sg:postcode":"89014",
    "sg:province":"NV",
    "sg:tags":[
        "art",
        "gallery",
        "dealer"
    ],
    "wof:name":"Qualtiy Artistt Group",
    "wof:placetype":"venue"
},
  "geometry": {"coordinates":[-115.046233,36.064622],"type":"Point"}
}