{
  "type": "Feature",
  "properties": {
    "iso:country":"US",
    "sg:address":"8471 W Sahara Avenue",
    "sg:city":"Las Vegas",
    "sg:classifiers":[
        {
            "category":"Restaurant",
            "type":"Food & Drink"
        }
    ],
    "sg:phone":"+1 702 240 8450",
    "sg:postcode":"89117",
    "sg:province":"NV",
    "sg:tags":[
        "mexican"
    ],
    "wof:name":"Del Taco",
    "wof:placetype":"venue"
},
  "geometry": {"coordinates":[-115.27631,36.143808],"type":"Point"}
}