{
  "type": "Feature",
  "properties": {
    "iso:country":"US",
    "sg:address":"3395 S.Jones #315",
    "sg:city":"Las Vegas",
    "sg:classifiers":[
        {
            "category":"Arts & Performance",
            "subcategory":"Arts Center",
            "type":"Entertainment"
        }
    ],
    "sg:phone":"+1 702 812 4604",
    "sg:postcode":"89146",
    "sg:province":"NV",
    "wof:name":"Vegas Star Bookings",
    "wof:placetype":"venue"
},
  "geometry": {"coordinates":[-115.224979,36.12766],"type":"Point"}
}