{
  "type": "Feature",
  "properties": {
    "iso:country":"US",
    "sg:address":"6424 Birchcrest Ct",
    "sg:city":"Las Vegas",
    "sg:classifiers":[
        {
            "category":"Arts & Performance",
            "subcategory":"Theater",
            "type":"Entertainment"
        }
    ],
    "sg:phone":"+1 702 325 3263",
    "sg:postcode":"89108",
    "sg:province":"NV",
    "sg:tags":[
        "live",
        "music"
    ],
    "wof:name":"Roxx Production DJ Svc",
    "wof:placetype":"venue"
},
  "geometry": {"coordinates":[-115.236485,36.231372],"type":"Point"}
}