{
  "type": "Feature",
  "properties": {
    "iso:country":"US",
    "sg:address":"7670 W Lake Mead Blvd",
    "sg:city":"Las Vegas",
    "sg:classifiers":[
        {
            "category":"Real Estate",
            "subcategory":"Real Estate Agent",
            "type":"Services"
        }
    ],
    "sg:phone":"+1 702 256 4900",
    "sg:postcode":"89128",
    "sg:province":"NV",
    "sg:tags":[
        "marketing",
        "property"
    ],
    "wof:name":"Kw Alliance LLC",
    "wof:placetype":"venue"
},
  "geometry": {"coordinates":[-115.261869,36.196315],"type":"Point"}
}