{
  "type": "Feature",
  "properties": {
    "iso:country":"US",
    "sg:address":"990 Equestrian Drive Apt 3320",
    "sg:city":"Henderson",
    "sg:classifiers":[
        {
            "category":"Real Estate",
            "subcategory":"Real Estate Operator",
            "type":"Services"
        }
    ],
    "sg:phone":"+1 702 568 9350",
    "sg:postcode":"89002",
    "sg:province":"NV",
    "sg:tags":[
        "apartment"
    ],
    "wof:name":"Horizon Senior Apartments",
    "wof:placetype":"venue"
},
  "geometry": {"coordinates":[-114.950963,36.009918],"type":"Point"}
}