{
  "type": "Feature",
  "properties": {
    "iso:country":"US",
    "sg:address":"610 West St",
    "sg:city":"Pahrump",
    "sg:classifiers":[
        {
            "category":"Retail",
            "subcategory":"Repair Shop",
            "type":"Services"
        }
    ],
    "sg:phone":"+1 775 727 5092",
    "sg:postcode":"89048",
    "sg:province":"NV",
    "sg:tags":[
        "lock",
        "locksmith"
    ],
    "wof:name":"H & R Locksmith",
    "wof:placetype":"venue"
},
  "geometry": {"coordinates":[-115.996262,36.210639],"type":"Point"}
}