{
  "type": "Feature",
  "properties": {
    "iso:country":"US",
    "sg:address":"206 N Virginia St",
    "sg:city":"Reno",
    "sg:classifiers":[
        {
            "category":"Professional",
            "type":"Services"
        },
        {
            "category":"Restaurant",
            "type":"Food & Drink"
        },
        {
            "category":"Food & Beverages",
            "subcategory":"Groceries & Convenience Stores",
            "type":"Retail Goods"
        }
    ],
    "sg:phone":"+1 775 323 5550",
    "sg:postcode":"89501",
    "sg:province":"NV",
    "sg:tags":[
        "bar",
        "house",
        "vegetarian",
        "sushi",
        "japanese",
        "asian",
        "caterer",
        "steak",
        "pan"
    ],
    "sg:website":"http://www.ichibanreno.com",
    "wof:name":"Ichiban Japanese Steak House & Sushi",
    "wof:placetype":"venue"
},
  "geometry": {"coordinates":[-119.81331,39.527059],"type":"Point"}
}