{
  "type": "Feature",
  "properties": {
    "iso:country":"US",
    "sg:address":"7501 W Washington Ave",
    "sg:city":"Las Vegas",
    "sg:classifiers":[
        {
            "category":"Shopping",
            "subcategory":"Pharmacy",
            "type":"Retail Goods"
        }
    ],
    "sg:phone":"+1 702 255 1421",
    "sg:postcode":"89128",
    "sg:province":"NV",
    "sg:tags":[
        "drugstore"
    ],
    "wof:name":"Kmart Stores",
    "wof:placetype":"venue"
},
  "geometry": {"coordinates":[-115.258003,36.181301],"type":"Point"}
}