{
  "type": "Feature",
  "properties": {
    "iso:country":"US",
    "sg:address":"10120 S Eastern Ave",
    "sg:city":"Henderson",
    "sg:classifiers":[
        {
            "category":"Professional",
            "subcategory":"Management & Consulting",
            "type":"Services"
        }
    ],
    "sg:phone":"+1 702 737 7555",
    "sg:postcode":"89052",
    "sg:province":"NV",
    "sg:tags":[
        "business"
    ],
    "wof:name":"North Shore A Pak Jack London",
    "wof:placetype":"venue"
},
  "geometry": {"coordinates":[-115.112787,36.006213],"type":"Point"}
}