{
  "type": "Feature",
  "properties": {
    "iso:country":"US",
    "sg:address":"6000 S Eastern Ave Ste 3B",
    "sg:city":"Las Vegas",
    "sg:classifiers":[
        {
            "category":"Arena",
            "subcategory":"Sports Club",
            "type":"Entertainment"
        }
    ],
    "sg:phone":"+1 702 798 5844",
    "sg:postcode":"89119",
    "sg:province":"NV",
    "sg:tags":[
        "martial art"
    ],
    "wof:name":"Legion Brazilian Jiu-Jitsu",
    "wof:placetype":"venue"
},
  "geometry": {"coordinates":[-115.11848000000001,36.081052],"type":"Point"}
}