{
  "type": "Feature",
  "properties": {
    "iso:country":"US",
    "sg:address":"180 N Nellis Blvd",
    "sg:city":"Las Vegas",
    "sg:classifiers":[
        {
            "category":"Retail",
            "subcategory":"Auto Repair",
            "type":"Services"
        }
    ],
    "sg:phone":"+1 702 437 0909",
    "sg:postcode":"89110",
    "sg:province":"NV",
    "wof:name":"Purrfect Auto Service",
    "wof:placetype":"venue"
},
  "geometry": {"coordinates":[-115.061996,36.161999],"type":"Point"}
}