{
  "type": "Feature",
  "properties": {
    "iso:country":"US",
    "sg:address":"8089 Kentshire Dr",
    "sg:city":"Las Vegas",
    "sg:classifiers":[
        {
            "category":"Organizations",
            "subcategory":"Community Association",
            "type":"Services"
        }
    ],
    "sg:phone":"+1 702 876 1704",
    "sg:postcode":"89117",
    "sg:province":"NV",
    "sg:tags":[
        "support",
        "business"
    ],
    "wof:name":"Express Processing Svc",
    "wof:placetype":"venue"
},
  "geometry": {"coordinates":[-115.266331,36.12876],"type":"Point"}
}