{
  "type": "Feature",
  "properties": {
    "iso:country":"US",
    "sg:address":"3048 Hills of Gold Ct",
    "sg:city":"Henderson",
    "sg:classifiers":[
        {
            "category":"Professional",
            "type":"Services"
        }
    ],
    "sg:phone":"+1 702 895 0181",
    "sg:postcode":"89052",
    "sg:province":"NV",
    "wof:name":"Brad Donohue Dr",
    "wof:placetype":"venue"
},
  "geometry": {"coordinates":[-115.122253,35.980809],"type":"Point"}
}