{
  "type": "Feature",
  "properties": {
    "iso:country":"US",
    "sg:address":"4355 S Pearl St",
    "sg:city":"Las Vegas",
    "sg:classifiers":[
        {
            "category":"Building & Trades",
            "subcategory":"Construction",
            "type":"Services"
        }
    ],
    "sg:phone":"+1 702 648 4242",
    "sg:postcode":"89121",
    "sg:province":"NV",
    "sg:tags":[
        "paving",
        "contractor"
    ],
    "wof:name":"R B Petersen Construction Co",
    "wof:placetype":"venue"
},
  "geometry": {"coordinates":[-115.096568,36.111412],"type":"Point"}
}