{
  "type": "Feature",
  "properties": {
    "iso:country":"US",
    "sg:address":"5450 Redwood Street",
    "sg:city":"Las Vegas",
    "sg:classifiers":[
        {
            "category":"Education",
            "subcategory":"School",
            "type":"Public Place"
        }
    ],
    "sg:phone":"+1 702 799 5980",
    "sg:postcode":"89118",
    "sg:province":"NV",
    "sg:tags":[
        "high",
        "middle",
        "elementary"
    ],
    "wof:name":"Schools Clark County Public",
    "wof:placetype":"venue"
},
  "geometry": {"coordinates":[-115.23855,36.09003],"type":"Point"}
}