{
  "type": "Feature",
  "properties": {
    "iso:country":"US",
    "sg:address":"5013 Glenarden Dr",
    "sg:city":"Las Vegas",
    "sg:classifiers":[
        {
            "category":"Professional",
            "subcategory":"Research",
            "type":"Services"
        }
    ],
    "sg:phone":"+1 702 496 2876",
    "sg:postcode":"89130",
    "sg:province":"NV",
    "sg:tags":[
        "detector",
        "business",
        "mfg"
    ],
    "wof:name":"Pentacore Measurement Tech",
    "wof:placetype":"venue"
},
  "geometry": {"coordinates":[-115.21145,36.260175],"type":"Point"}
}