{
  "type": "Feature",
  "properties": {
    "iso:country":"US",
    "sg:address":"3255 3rd St",
    "sg:city":"Silver Springs",
    "sg:classifiers":[
        {
            "category":"Real Estate",
            "subcategory":"Real Estate Services",
            "type":"Services"
        }
    ],
    "sg:phone":"+1 775 577 4295",
    "sg:postcode":"89429",
    "sg:province":"NV",
    "sg:tags":[
        "abstract",
        "title"
    ],
    "wof:name":"High Desert Title Svc",
    "wof:placetype":"venue"
},
  "geometry": {"coordinates":[-119.184424,39.353095],"type":"Point"}
}