{
  "type": "Feature",
  "properties": {
    "iso:country":"US",
    "sg:address":"1715 N Carson St.",
    "sg:city":"Carson City",
    "sg:classifiers":[
        {
            "category":"Retail",
            "subcategory":"Auto Repair",
            "type":"Services"
        }
    ],
    "sg:phone":"+1 775 885 0701",
    "sg:postcode":"89701",
    "sg:province":"NV",
    "sg:website":"www.carsonservicenter.com",
    "wof:name":"Carson Servicenter",
    "wof:placetype":"venue"
},
  "geometry": {"coordinates":[-119.766899,39.174857],"type":"Point"}
}