{
  "type": "Feature",
  "properties": {
    "iso:country":"US",
    "sg:address":"1155 W 4th St",
    "sg:city":"Reno",
    "sg:classifiers":[
        {
            "category":"Casinos & Gambling",
            "type":"Entertainment"
        }
    ],
    "sg:phone":"+1 775 332 4276",
    "sg:postcode":"89503",
    "sg:province":"NV",
    "wof:name":"International Casino Surveillance Network-ICSN",
    "wof:placetype":"venue"
},
  "geometry": {"coordinates":[-119.827896,39.526218],"type":"Point"}
}