{
  "type": "Feature",
  "properties": {
    "iso:country":"US",
    "sg:address":"3700 W Flamingo Rd",
    "sg:city":"Las Vegas",
    "sg:classifiers":[
        {
            "category":"Wholesale",
            "subcategory":"Chemicals & Plastics",
            "type":"Manufacturing & Wholesale Goods"
        }
    ],
    "sg:phone":"+1 702 220 9337",
    "sg:postcode":"89103",
    "sg:province":"NV",
    "sg:tags":[
        "oxygen"
    ],
    "wof:name":"Ozone Oxygen Bar",
    "wof:placetype":"venue"
},
  "geometry": {"coordinates":[-115.188318,36.115552],"type":"Point"}
}