{
  "type": "Feature",
  "properties": {
    "iso:country":"US",
    "sg:address":"3000 Mason Ave",
    "sg:city":"Las Vegas",
    "sg:classifiers":[
        {
            "category":"Banks & Credit Unions",
            "subcategory":"Investment Brokerage",
            "type":"Services"
        }
    ],
    "sg:phone":"+1 702 258 7771",
    "sg:postcode":"89102",
    "sg:province":"NV",
    "sg:tags":[
        "security"
    ],
    "wof:name":"Finance 500 Securities",
    "wof:placetype":"venue"
},
  "geometry": {"coordinates":[-115.180775,36.155819],"type":"Point"}
}