{
  "type": "Feature",
  "properties": {
    "iso:country":"US",
    "sg:address":"445 E Glendale Ave",
    "sg:city":"Sparks",
    "sg:classifiers":[
        {
            "category":"Professional",
            "subcategory":"Business Services",
            "type":"Services"
        }
    ],
    "sg:phone":"+1 775 356 6200",
    "sg:postcode":"89431",
    "sg:province":"NV",
    "sg:tags":[
        "trade",
        "show",
        "convention"
    ],
    "wof:name":"Freeman Decorating Co",
    "wof:placetype":"venue"
},
  "geometry": {"coordinates":[-119.73758599999999,39.527319],"type":"Point"}
}