{
  "type": "Feature",
  "properties": {
    "iso:country":"US",
    "sg:address":"2352 Oddie Blvd",
    "sg:city":"Sparks",
    "sg:classifiers":[
        {
            "category":"Restaurant",
            "type":"Food & Drink"
        },
        {
            "category":"Shopping",
            "subcategory":"Discount & Variety Stores",
            "type":"Retail Goods"
        },
        {
            "category":"Food & Beverages",
            "subcategory":"Ethnic Foods",
            "type":"Retail Goods"
        }
    ],
    "sg:phone":"+1 775 331 7999",
    "sg:postcode":"89431",
    "sg:province":"NV",
    "sg:tags":[
        "chinese",
        "oriental",
        "asian",
        "pan",
        "grocers-ethnic"
    ],
    "wof:name":"Manila Hongkong Kitchen",
    "wof:placetype":"venue"
},
  "geometry": {"coordinates":[-119.776608,39.545488],"type":"Point"}
}