{
  "type": "Feature",
  "properties": {
    "iso:country":"US",
    "sg:address":"150 State Hwy 160",
    "sg:city":"Pahrump",
    "sg:classifiers":[
        {
            "category":"Restaurant",
            "type":"Food & Drink"
        }
    ],
    "sg:phone":"+1 775 751 6000",
    "sg:postcode":"89048",
    "sg:province":"NV",
    "sg:tags":[
        "eating",
        "out"
    ],
    "wof:name":"Port of Subs",
    "wof:placetype":"venue"
},
  "geometry": {"coordinates":[-115.991332,36.213636],"type":"Point"}
}