{
  "type": "Feature",
  "properties": {
    "iso:country":"US",
    "sg:address":"2801 Fort Sumter Drive",
    "sg:city":"North Las Vegas",
    "sg:classifiers":[
        {
            "category":"Education",
            "subcategory":"School",
            "type":"Public Place"
        }
    ],
    "sg:phone":"+1 702 799 7103",
    "sg:postcode":"89030",
    "sg:province":"NV",
    "sg:tags":[
        "high",
        "middle",
        "elementary"
    ],
    "wof:name":"Schools Clark County Public",
    "wof:placetype":"venue"
},
  "geometry": {"coordinates":[-115.125343,36.210597],"type":"Point"}
}