{
  "type": "Feature",
  "properties": {
    "iso:country":"US",
    "sg:address":"3055 Camill Dr",
    "sg:city":"Reno",
    "sg:classifiers":[
        {
            "category":"Building & Trades",
            "subcategory":"Construction",
            "type":"Services"
        }
    ],
    "sg:phone":"+1 775 826 6838",
    "sg:postcode":"89509",
    "sg:province":"NV",
    "sg:tags":[
        "roofing",
        "contractor"
    ],
    "wof:name":"Horizon Roofing",
    "wof:placetype":"venue"
},
  "geometry": {"coordinates":[-119.829601,39.491377],"type":"Point"}
}