{
  "type": "Feature",
  "properties": {
    "iso:country":"US",
    "sg:address":"321 W Winnie Ln",
    "sg:city":"Carson City",
    "sg:classifiers":[
        {
            "category":"Banks & Credit Unions",
            "subcategory":"Bank",
            "type":"Services"
        }
    ],
    "sg:phone":"+1 775 887 1116",
    "sg:postcode":"89703",
    "sg:province":"NV",
    "sg:tags":[
        "loan",
        "mortgage",
        "real estate"
    ],
    "wof:name":"Mortgage Options Inc",
    "wof:placetype":"venue"
},
  "geometry": {"coordinates":[-119.769268,39.179119],"type":"Point"}
}