{
  "type": "Feature",
  "properties": {
    "iso:country":"US",
    "sg:address":"1801 Scimitar Dr",
    "sg:city":"Henderson",
    "sg:classifiers":[
        {
            "category":"Organizations",
            "subcategory":"Professional Association",
            "type":"Services"
        }
    ],
    "sg:phone":"+1 702 434 4297",
    "sg:postcode":"89014",
    "sg:province":"NV",
    "wof:name":"Ridgeview Homeowners Assn",
    "wof:placetype":"venue"
},
  "geometry": {"coordinates":[-115.065197,36.066041],"type":"Point"}
}