{
  "type": "Feature",
  "properties": {
    "iso:country":"US",
    "sg:address":"4965 S Virginia St",
    "sg:city":"Reno",
    "sg:classifiers":[
        {
            "category":"Restaurant",
            "type":"Food & Drink"
        }
    ],
    "sg:menulink":"http://www.allmenus.com/nv/reno-southwest/121812-keva-juice/menu/",
    "sg:phone":"+1 775 824 0616",
    "sg:postcode":"89502",
    "sg:province":"NV",
    "sg:tags":[
        "smoothy",
        "juice",
        "american"
    ],
    "wof:name":"Keva Juice",
    "wof:placetype":"venue"
},
  "geometry": {"coordinates":[-119.790982,39.480595],"type":"Point"}
}