{
  "type": "Feature",
  "properties": {
    "iso:country":"US",
    "sg:address":"460 5th St",
    "sg:city":"Wells",
    "sg:classifiers":[
        {
            "category":"Professional",
            "subcategory":"Management & Consulting",
            "type":"Services"
        }
    ],
    "sg:phone":"+1 775 752 3727",
    "sg:postcode":"89835",
    "sg:province":"NV",
    "sg:tags":[
        "consultant",
        "security",
        "system"
    ],
    "wof:name":"Security Consulting & Supply",
    "wof:placetype":"venue"
},
  "geometry": {"coordinates":[-114.965525,41.110357],"type":"Point"}
}