{
  "type": "Feature",
  "properties": {
    "iso:country":"US",
    "sg:address":"4472 S Eastern Ave",
    "sg:city":"Las Vegas",
    "sg:classifiers":[
        {
            "category":"Education",
            "subcategory":"Vocational School",
            "type":"Public Place"
        }
    ],
    "sg:phone":"+1 702 734 9900",
    "sg:postcode":"89119",
    "sg:province":"NV",
    "wof:name":"Institute-Professional Careers",
    "wof:placetype":"venue"
},
  "geometry": {"coordinates":[-115.11903700000001,36.109472],"type":"Point"}
}