{
  "type": "Feature",
  "properties": {
    "iso:country":"US",
    "sg:address":"1710 W Williams Ave",
    "sg:city":"Fallon",
    "sg:classifiers":[
        {
            "category":"Personal",
            "subcategory":"Barber",
            "type":"Services"
        }
    ],
    "sg:phone":"+1 775 423 2636",
    "sg:postcode":"89406",
    "sg:province":"NV",
    "sg:tags":[
        "shop"
    ],
    "wof:name":"Art's Red Neck Barber Shop",
    "wof:placetype":"venue"
},
  "geometry": {"coordinates":[-118.79429399999999,39.474958],"type":"Point"}
}