{
  "type": "Feature",
  "properties": {
    "iso:country":"US",
    "sg:address":"6020 W Levi Ave",
    "sg:city":"Las Vegas",
    "sg:classifiers":[
        {
            "category":"Wholesale",
            "subcategory":"Non-durable Goods",
            "type":"Manufacturing & Wholesale Goods"
        }
    ],
    "sg:phone":"+1 702 270 6314",
    "sg:postcode":"89141",
    "sg:province":"NV",
    "wof:name":"Glass Gaming & Gifts",
    "wof:placetype":"venue"
},
  "geometry": {"coordinates":[-115.22501699999999,35.994882],"type":"Point"}
}