{
  "type": "Feature",
  "properties": {
    "iso:country":"US",
    "sg:address":"9360 Villa Tuscany Ave",
    "sg:city":"Las Vegas",
    "sg:classifiers":[
        {
            "category":"Professional",
            "subcategory":"Business Services",
            "type":"Services"
        }
    ],
    "sg:phone":"+1 702 325 1907",
    "sg:postcode":"89129",
    "sg:province":"NV",
    "sg:tags":[
        "pool",
        "swimming"
    ],
    "wof:name":"Clear Waters",
    "wof:placetype":"venue"
},
  "geometry": {"coordinates":[-115.299441,36.231461],"type":"Point"}
}