{
  "type": "Feature",
  "properties": {
    "iso:country":"US",
    "sg:address":"9260 Las Vegas Blvd S",
    "sg:city":"Las Vegas",
    "sg:classifiers":[
        {
            "category":"Education",
            "subcategory":"Dance Studio",
            "type":"Public Place"
        }
    ],
    "sg:phone":"+1 702 407 7827",
    "sg:postcode":"89123",
    "sg:province":"NV",
    "sg:tags":[
        "instruction",
        "dancing"
    ],
    "wof:name":"Stars Elite Academy",
    "wof:placetype":"venue"
},
  "geometry": {"coordinates":[-115.172252,36.023994],"type":"Point"}
}