{
  "type": "Feature",
  "properties": {
    "iso:country":"US",
    "sg:address":"9340 Tall Wood Ln",
    "sg:city":"Las Vegas",
    "sg:classifiers":[
        {
            "category":"Building & Trades",
            "subcategory":"Construction",
            "type":"Services"
        }
    ],
    "sg:phone":"+1 702 242 3334",
    "sg:postcode":"89129",
    "sg:province":"NV",
    "sg:tags":[
        "general",
        "contractor"
    ],
    "wof:name":"Countrywide Construction LLC",
    "wof:placetype":"venue"
},
  "geometry": {"coordinates":[-115.300332,36.221923],"type":"Point"}
}