{
  "type": "Feature",
  "properties": {
    "iso:country":"US",
    "sg:address":"5762 Arbor Oak Cir",
    "sg:city":"Las Vegas",
    "sg:classifiers":[
        {
            "category":"Building & Trades",
            "subcategory":"Construction",
            "type":"Services"
        }
    ],
    "sg:phone":"+1 702 399 0190",
    "sg:postcode":"89142",
    "sg:province":"NV",
    "sg:tags":[
        "contractor"
    ],
    "sg:website":"windowcleaninginlasvegas.com#cid...",
    "wof:name":"Best Grade Services",
    "wof:placetype":"venue"
},
  "geometry": {"coordinates":[-115.048174,36.156999],"type":"Point"}
}