{
  "type": "Feature",
  "properties": {
    "iso:country":"US",
    "sg:address":"19 Via del Garda",
    "sg:city":"Henderson",
    "sg:classifiers":[
        {
            "category":"Shopping",
            "subcategory":"Clothing, Apparel, & Fashions",
            "type":"Retail Goods"
        }
    ],
    "sg:phone":"+1 702 567 0325",
    "sg:postcode":"89011",
    "sg:province":"NV",
    "wof:name":"Weekenders USA",
    "wof:placetype":"venue"
},
  "geometry": {"coordinates":[-114.908816,36.11427],"type":"Point"}
}