{
  "type": "Feature",
  "properties": {
    "iso:country":"US",
    "sg:address":"17996 Dalton Ln",
    "sg:city":"Cold Springs",
    "sg:classifiers":[
        {
            "category":"Building & Trades",
            "subcategory":"Construction",
            "type":"Services"
        }
    ],
    "sg:phone":"+1 775 677 7922",
    "sg:postcode":"89508",
    "sg:province":"NV",
    "sg:tags":[
        "plastering",
        "contractor"
    ],
    "wof:name":"D R Cowan Plastering",
    "wof:placetype":"venue"
},
  "geometry": {"coordinates":[-119.984701,39.677903],"type":"Point"}
}