{
  "type": "Feature",
  "properties": {
    "iso:country":"US",
    "sg:address":"4801 S Pecos Rd",
    "sg:city":"Las Vegas",
    "sg:classifiers":[
        {
            "category":"Retail",
            "subcategory":"Auto Repair",
            "type":"Services"
        }
    ],
    "sg:phone":"+1 702 456 3888",
    "sg:postcode":"89121",
    "sg:province":"NV",
    "sg:tags":[
        "automotive",
        "general"
    ],
    "wof:name":"Freds Autohouse",
    "wof:placetype":"venue"
},
  "geometry": {"coordinates":[-115.10107000000001,36.100997],"type":"Point"}
}