{
  "type": "Feature",
  "properties": {
    "iso:country":"US",
    "sg:address":"1190 Cornell Ave",
    "sg:city":"Lovelock",
    "sg:classifiers":[
        {
            "category":"Local Transit",
            "type":"Transportation"
        }
    ],
    "sg:phone":"+1 775 273 2641",
    "sg:postcode":"89419",
    "sg:province":"NV",
    "sg:tags":[
        "ambulance"
    ],
    "wof:name":"Pershing County Ambulance Svc",
    "wof:placetype":"venue"
},
  "geometry": {"coordinates":[-118.473875,40.181102],"type":"Point"}
}