{
  "type": "Feature",
  "properties": {
    "iso:country":"US",
    "sg:address":"3200 Bel Air Dr",
    "sg:city":"Las Vegas",
    "sg:classifiers":[
        {
            "category":"Retail",
            "subcategory":"Animal Services",
            "type":"Services"
        }
    ],
    "sg:phone":"+1 702 263 5757",
    "sg:postcode":"89109",
    "sg:province":"NV",
    "sg:tags":[
        "horse",
        "training"
    ],
    "wof:name":"Arnone Enterprises Inc",
    "wof:placetype":"venue"
},
  "geometry": {"coordinates":[-115.144784,36.132503],"type":"Point"}
}