{
  "type": "Feature",
  "properties": {
    "iso:country":"US",
    "sg:address":"4150 S Durango Drive",
    "sg:city":"Las Vegas",
    "sg:classifiers":[
        {
            "category":"Autos & Motor Vehicles",
            "subcategory":"Fuel & Gas Station",
            "type":"Retail Goods"
        }
    ],
    "sg:phone":"+1 702 871 7940",
    "sg:postcode":"89147",
    "sg:province":"NV",
    "sg:website":"www.terribleherbst.com",
    "wof:name":"Terrible Herbst #228",
    "wof:placetype":"venue"
},
  "geometry": {"coordinates":[-115.279162,36.113639],"type":"Point"}
}