{
  "type": "Feature",
  "properties": {
    "iso:country":"US",
    "sg:address":"769 Basque Way # 300",
    "sg:city":"Carson City",
    "sg:classifiers":[
        {
            "category":"Banks & Credit Unions",
            "subcategory":"Investment Brokerage",
            "type":"Services"
        }
    ],
    "sg:phone":"+1 775 315 2808",
    "sg:postcode":"89706",
    "sg:province":"NV",
    "sg:tags":[
        "investing"
    ],
    "wof:name":"Azimuth Consulting & Financial Planning",
    "wof:placetype":"venue"
},
  "geometry": {"coordinates":[-119.759688,39.18683],"type":"Point"}
}