{
  "type": "Feature",
  "properties": {
    "iso:country":"US",
    "sg:address":"13125 Gilespie St",
    "sg:city":"Henderson",
    "sg:classifiers":[
        {
            "category":"Food & Beverages",
            "subcategory":"Specialty",
            "type":"Retail Goods"
        }
    ],
    "sg:phone":"+1 702 385 3555",
    "sg:postcode":"89044",
    "sg:province":"NV",
    "sg:tags":[
        "health",
        "diet"
    ],
    "wof:name":"Sunrider",
    "wof:placetype":"venue"
},
  "geometry": {"coordinates":[-115.163496,35.952861],"type":"Point"}
}