{
  "type": "Feature",
  "properties": {
    "iso:country":"US",
    "sg:address":"1700 Zolezzi Ln",
    "sg:city":"Reno",
    "sg:classifiers":[
        {
            "category":"Organizations",
            "subcategory":"Religious Organization",
            "type":"Services"
        },
        {
            "category":"Social Services",
            "subcategory":"Child Care",
            "type":"Services"
        }
    ],
    "sg:phone":"+1 775 853 4234",
    "sg:postcode":"89511",
    "sg:province":"NV",
    "sg:tags":[
        "preschool",
        "church"
    ],
    "sg:website":"www.rcf.com",
    "wof:name":"Reno Christian Fellowship Pre",
    "wof:placetype":"venue"
},
  "geometry": {"coordinates":[-119.788756,39.418611],"type":"Point"}
}