{
  "type": "Feature",
  "properties": {
    "iso:country":"US",
    "sg:address":"6360 W Charleston Blvd",
    "sg:city":"Las Vegas",
    "sg:classifiers":[
        {
            "category":"Fast Food",
            "type":"Food & Drink"
        }
    ],
    "sg:phone":"+1 702 258 0298",
    "sg:postcode":"89146",
    "sg:province":"NV",
    "sg:website":"www.mcdonalds.com",
    "wof:name":"McDonald's",
    "wof:placetype":"venue"
},
  "geometry": {"coordinates":[-115.233002,36.159401],"type":"Point"}
}