{
  "type": "Feature",
  "properties": {
    "iso:country":"US",
    "sg:address":"6754 Spencer St",
    "sg:city":"Las Vegas",
    "sg:classifiers":[
        {
            "category":"Real Estate",
            "subcategory":"Developer",
            "type":"Services"
        }
    ],
    "sg:phone":"+1 702 795 0690",
    "sg:postcode":"89119",
    "sg:province":"NV",
    "wof:name":"Nevada Brokers Inc",
    "wof:placetype":"venue"
},
  "geometry": {"coordinates":[-115.127589,36.067398],"type":"Point"}
}