{
  "type": "Feature",
  "properties": {
    "iso:country":"US",
    "sg:address":"6510 N Buffalo Dr",
    "sg:city":"Las Vegas",
    "sg:classifiers":[
        {
            "category":"Insurance",
            "subcategory":"Insurance Agent",
            "type":"Services"
        }
    ],
    "sg:phone":"+1 702 515 2040",
    "sg:postcode":"89131",
    "sg:province":"NV",
    "wof:name":"AAA Insurance",
    "wof:placetype":"venue"
},
  "geometry": {"coordinates":[-115.260429,36.284081],"type":"Point"}
}