{
  "type": "Feature",
  "properties": {
    "iso:country":"US",
    "sg:address":"9525 W Maule Ave",
    "sg:city":"Las Vegas",
    "sg:classifiers":[
        {
            "category":"Education",
            "subcategory":"School",
            "type":"Public Place"
        }
    ],
    "sg:phone":"+1 702 799 6850",
    "sg:postcode":"89148",
    "sg:province":"NV",
    "sg:tags":[
        "high",
        "middle",
        "elementary"
    ],
    "wof:name":"Schools Clark County Public",
    "wof:placetype":"venue"
},
  "geometry": {"coordinates":[-115.30094,36.062743],"type":"Point"}
}