{
  "type": "Feature",
  "properties": {
    "iso:country":"US",
    "sg:address":"7913 Coral Point Ave",
    "sg:city":"Las Vegas",
    "sg:classifiers":[
        {
            "category":"Building & Trades",
            "subcategory":"Cleaning & Sanitation",
            "type":"Services"
        }
    ],
    "sg:phone":"+1 702 453 9400",
    "sg:postcode":"89128",
    "sg:province":"NV",
    "sg:tags":[
        "janitor"
    ],
    "wof:name":"ALF Maintenance",
    "wof:placetype":"venue"
},
  "geometry": {"coordinates":[-115.267655,36.202518],"type":"Point"}
}