{
  "type": "Feature",
  "properties": {
    "iso:country":"US",
    "sg:address":"3708 E Flamingo Rd",
    "sg:city":"Las Vegas",
    "sg:classifiers":[
        {
            "category":"Autos & Motor Vehicles",
            "subcategory":"Auto Supplies",
            "type":"Retail Goods"
        }
    ],
    "sg:phone":"+1 702 456 7055",
    "sg:postcode":"89121",
    "sg:province":"NV",
    "sg:tags":[
        "automobile",
        "parts"
    ],
    "sg:website":"www.csk.com",
    "wof:name":"Checker Auto Parts 1011",
    "wof:placetype":"venue"
},
  "geometry": {"coordinates":[-115.096465,36.115328],"type":"Point"}
}