{
  "type": "Feature",
  "properties": {
    "iso:country":"US",
    "sg:address":"8174 Las Vegas Blvd S Ste 107",
    "sg:city":"Las Vegas",
    "sg:classifiers":[
        {
            "category":"Shopping",
            "subcategory":"Discount & Variety Stores",
            "type":"Retail Goods"
        }
    ],
    "sg:phone":"+1 702 453 8004",
    "sg:postcode":"89123",
    "sg:province":"NV",
    "sg:tags":[
        "wholesale"
    ],
    "sg:website":"www.embroidme-lasvegassouth.com",
    "wof:name":"Embroidme",
    "wof:placetype":"venue"
},
  "geometry": {"coordinates":[-114.995964,36.274578],"type":"Point"}
}