{
  "type": "Feature",
  "properties": {
    "iso:country":"US",
    "sg:address":"9151 S Las Vegas Blvd",
    "sg:city":"Las Vegas",
    "sg:classifiers":[
        {
            "category":"Shopping",
            "subcategory":"Antiques",
            "type":"Retail Goods"
        }
    ],
    "sg:phone":"+1 818 497 6278",
    "sg:postcode":"89115",
    "sg:province":"NV",
    "wof:name":"Frank Antiques",
    "wof:placetype":"venue"
},
  "geometry": {"coordinates":[-114.99239,36.276716],"type":"Point"}
}