{
  "type": "Feature",
  "properties": {
    "iso:country":"US",
    "sg:address":"5018 E Monroe Ave",
    "sg:city":"Las Vegas",
    "sg:classifiers":[
        {
            "category":"Organizations",
            "subcategory":"Community Association",
            "type":"Services"
        }
    ],
    "sg:phone":"+1 702 452 5380",
    "sg:postcode":"89110",
    "sg:province":"NV",
    "wof:name":"Troop 561 Bsa",
    "wof:placetype":"venue"
},
  "geometry": {"coordinates":[-115.066638,36.185012],"type":"Point"}
}