{
  "type": "Feature",
  "properties": {
    "iso:country":"US",
    "sg:address":"3230 Wedekind Rd",
    "sg:city":"Sparks",
    "sg:classifiers":[
        {
            "category":"Personal",
            "subcategory":"Adult",
            "type":"Services"
        }
    ],
    "sg:phone":"+1 775 355 6789",
    "sg:postcode":"89431",
    "sg:province":"NV",
    "sg:tags":[
        "escort"
    ],
    "wof:name":"Body Language",
    "wof:placetype":"venue"
},
  "geometry": {"coordinates":[-119.77979,39.552895],"type":"Point"}
}