{
  "type": "Feature",
  "properties": {
    "iso:country":"US",
    "sg:address":"690 N Valle Verde Dr",
    "sg:city":"Henderson",
    "sg:classifiers":[
        {
            "category":"Personal",
            "subcategory":"Beauty Salon",
            "type":"Services"
        }
    ],
    "sg:phone":"+1 702 458 0898",
    "sg:postcode":"89014",
    "sg:province":"NV",
    "wof:name":"Deja Vu Full Svc Salon",
    "wof:placetype":"venue"
},
  "geometry": {"coordinates":[-115.068894,36.067532],"type":"Point"}
}