{
  "type": "Feature",
  "properties": {
    "iso:country":"US",
    "sg:address":"4534 W Diablo Drive",
    "sg:city":"Las Vegas",
    "sg:classifiers":[
        {
            "category":"Banks & Credit Unions",
            "subcategory":"Financial Services",
            "type":"Services"
        },
        {
            "category":"Communications",
            "type":"Services"
        }
    ],
    "sg:phone":"+1 702 309 5444",
    "sg:postcode":"89118",
    "sg:province":"NV",
    "sg:tags":[
        "web",
        "design",
        "broker",
        "mortgage"
    ],
    "wof:name":"Acropolis Ventures",
    "wof:placetype":"venue"
},
  "geometry": {"coordinates":[-115.201952,36.08992],"type":"Point"}
}