{
  "type": "Feature",
  "properties": {
    "iso:country":"US",
    "sg:address":"6845 Speedway Blvd",
    "sg:city":"Las Vegas",
    "sg:classifiers":[
        {
            "category":"Manufacturing",
            "subcategory":"Metals",
            "type":"Manufacturing & Wholesale Goods"
        }
    ],
    "sg:phone":"+1 702 651 3374",
    "sg:postcode":"89115",
    "sg:province":"NV",
    "sg:tags":[
        "steel"
    ],
    "wof:name":"Dittmeier Steel Svc",
    "wof:placetype":"venue"
},
  "geometry": {"coordinates":[-115.01978,36.279056],"type":"Point"}
}