{
  "type": "Feature",
  "properties": {
    "iso:country":"US",
    "sg:address":"4975 E Charleston Blvd",
    "sg:city":"Las Vegas",
    "sg:classifiers":[
        {
            "category":"Home & Garden",
            "subcategory":"Building Materials",
            "type":"Retail Goods"
        }
    ],
    "sg:phone":"+1 702 396 0136",
    "sg:postcode":"89104",
    "sg:province":"NV",
    "sg:tags":[
        "glass",
        "window",
        "plate"
    ],
    "wof:name":"AAA Quality Guaranteed Glass",
    "wof:placetype":"venue"
},
  "geometry": {"coordinates":[-115.06704000000001,36.158934],"type":"Point"}
}