{
  "type": "Feature",
  "properties": {
    "iso:country":"US",
    "sg:address":"8311 W Sunset Rd",
    "sg:city":"Las Vegas",
    "sg:classifiers":[
        {
            "category":"Banks & Credit Unions",
            "subcategory":"Bank",
            "type":"Services"
        }
    ],
    "sg:phone":"+1 702 207 7100",
    "sg:postcode":"89113",
    "sg:province":"NV",
    "sg:tags":[
        "loan",
        "real estate"
    ],
    "wof:name":"Mortgage Store",
    "wof:placetype":"venue"
},
  "geometry": {"coordinates":[-115.26631,36.07024],"type":"Point"}
}