{
  "type": "Feature",
  "properties": {
    "iso:country":"US",
    "sg:address":"355 W Mesquite Blvd",
    "sg:city":"Mesquite",
    "sg:classifiers":[
        {
            "category":"Real Estate",
            "subcategory":"Real Estate Agent",
            "type":"Services"
        }
    ],
    "sg:phone":"+1 702 346 7800",
    "sg:postcode":"89027",
    "sg:province":"NV",
    "sg:website":"www.ridgerealty.com",
    "wof:name":"Re/Max Ridge Realty",
    "wof:placetype":"venue"
},
  "geometry": {"coordinates":[-114.074326,36.804067],"type":"Point"}
}