{
  "type": "Feature",
  "properties": {
    "iso:country":"US",
    "sg:address":"5424 Holmby Ave",
    "sg:city":"Las Vegas",
    "sg:classifiers":[
        {
            "category":"Building & Trades",
            "subcategory":"Cleaning & Sanitation",
            "type":"Services"
        }
    ],
    "sg:phone":"+1 702 255 9249",
    "sg:postcode":"89146",
    "sg:province":"NV",
    "sg:tags":[
        "janitor"
    ],
    "wof:name":"Orange Clean",
    "wof:placetype":"venue"
},
  "geometry": {"coordinates":[-115.214142,36.157075],"type":"Point"}
}