{
  "type": "Feature",
  "properties": {
    "iso:country":"US",
    "sg:address":"821 N Center St",
    "sg:city":"Reno",
    "sg:classifiers":[
        {
            "category":"Professional",
            "subcategory":"Business Services",
            "type":"Services"
        }
    ],
    "sg:phone":"+1 775 784 7515",
    "sg:postcode":"89501",
    "sg:province":"NV",
    "wof:name":"Northern Navada Int Center",
    "wof:placetype":"venue"
},
  "geometry": {"coordinates":[-119.814927,39.536193],"type":"Point"}
}