{
  "type": "Feature",
  "properties": {
    "iso:country":"US",
    "sg:address":"3600 S Highland Dr",
    "sg:city":"Las Vegas",
    "sg:classifiers":[
        {
            "category":"Freight",
            "type":"Transportation"
        }
    ],
    "sg:phone":"+1 702 566 0002",
    "sg:postcode":"89103",
    "sg:province":"NV",
    "sg:tags":[
        "mover"
    ],
    "wof:name":"American Spirit Van Line",
    "wof:placetype":"venue"
},
  "geometry": {"coordinates":[-115.1812,36.125098],"type":"Point"}
}