{
  "type": "Feature",
  "properties": {
    "iso:country":"US",
    "sg:address":"8617 Estrelita Dr",
    "sg:city":"Las Vegas",
    "sg:classifiers":[
        {
            "category":"Professional",
            "subcategory":"Management & Consulting",
            "type":"Services"
        }
    ],
    "sg:phone":"+1 702 804 2827",
    "sg:postcode":"89128",
    "sg:province":"NV",
    "sg:tags":[
        "business"
    ],
    "wof:name":"Macguard Securities Systems",
    "wof:placetype":"venue"
},
  "geometry": {"coordinates":[-115.28278299999999,36.1926],"type":"Point"}
}