{
  "type": "Feature",
  "properties": {
    "iso:country":"US",
    "sg:address":"9506 Teton Diablo Ave",
    "sg:city":"Las Vegas",
    "sg:classifiers":[
        {
            "category":"Professional",
            "subcategory":"Management & Consulting",
            "type":"Services"
        }
    ],
    "sg:phone":"+1 702 648 1111",
    "sg:postcode":"89117",
    "sg:province":"NV",
    "sg:tags":[
        "consultant",
        "educational"
    ],
    "wof:name":"Nevadans For Quality Education",
    "wof:placetype":"venue"
},
  "geometry": {"coordinates":[-115.300396,36.126647],"type":"Point"}
}