{
  "type": "Feature",
  "properties": {
    "iso:country":"US",
    "sg:address":"2605 S Decatur Blvd",
    "sg:city":"Las Vegas",
    "sg:classifiers":[
        {
            "category":"Arts & Performance",
            "subcategory":"Arts Center",
            "type":"Entertainment"
        }
    ],
    "sg:phone":"+1 702 214 2777",
    "sg:postcode":"89102",
    "sg:province":"NV",
    "sg:tags":[
        "performing"
    ],
    "wof:name":"Westside Academy of Performing Arts",
    "wof:placetype":"venue"
},
  "geometry": {"coordinates":[-115.208,36.142502],"type":"Point"}
}