{
  "type": "Feature",
  "properties": {
    "iso:country":"US",
    "sg:address":"2820 W Charleston Blvd",
    "sg:city":"Las Vegas",
    "sg:classifiers":[
        {
            "category":"Real Estate",
            "subcategory":"Real Estate Agent",
            "type":"Services"
        }
    ],
    "sg:phone":"+1 702 870 5566",
    "sg:postcode":"89102",
    "sg:province":"NV",
    "wof:name":"Michael Plummer",
    "wof:placetype":"venue"
},
  "geometry": {"coordinates":[-115.183151,36.159026],"type":"Point"}
}