{
  "type": "Feature",
  "properties": {
    "iso:country":"US",
    "sg:address":"3315 W Craig Road",
    "sg:city":"North Las Vegas",
    "sg:classifiers":[
        {
            "category":"Shopping",
            "subcategory":"Beauty & Cosmetics",
            "type":"Retail Goods"
        }
    ],
    "sg:phone":"+1 702 207 0025",
    "sg:postcode":"89032",
    "sg:province":"NV",
    "sg:tags":[
        "supply"
    ],
    "wof:name":"Classique Beauty Supply",
    "wof:placetype":"venue"
},
  "geometry": {"coordinates":[-115.18481,36.239308],"type":"Point"}
}