{
  "type": "Feature",
  "properties": {
    "iso:country":"US",
    "sg:address":"75 Lewers Creek Rd",
    "sg:city":"Carson City",
    "sg:classifiers":[
        {
            "category":"Retail",
            "subcategory":"Animal Services",
            "type":"Services"
        }
    ],
    "sg:phone":"+1 775 883 1975",
    "sg:postcode":"89704",
    "sg:province":"NV",
    "sg:tags":[
        "breeder",
        "horse"
    ],
    "wof:name":"Remolino Ranch Inc",
    "wof:placetype":"venue"
},
  "geometry": {"coordinates":[-119.824932,39.251584],"type":"Point"}
}